Workbook

Sheet 2019-20 MASTER
D2: FOR THE YEAR 2019-20
D3: SL. NO. | F3: Apr | G3: May | H3: 2M | I3: June | J3: Q-I | K3: July | L3: 4M | M3: Aug | N3: 5M | O3: Sep | P3: Q-II | Q3: H-I | R3: Oct | S3: 7M | T3: Nov | U3: 8M | V3: Dec | W3: Q-III | X3: 9M | Y3: Jan | Z3: 10M | AA3: Feb | AB3: 11M | AC3: Mar | AD3: Q-IV | AE3: H-II | AF3: 12M
E4: I T E M S
E6: Days | F6: 30 | G6: 31 | H6: =+F6+G6 -> 61 | I6: 30 | J6: =+H6+I6 -> 91 | K6: 31 | L6: =+J6+K6 -> 122 | M6: 31 | N6: =+L6+M6 -> 153 | O6: 30 | P6: =+K6+M6+O6 -> 92 | Q6: =+J6+P6 -> 183 | R6: 31 | S6: =+Q6+R6 -> 214 | T6: 30 | U6: =+S6+T6 -> 244 | V6: 31 | W6: =+R6+T6+V6 -> 92 | X6: =+U6+V6 -> 275 | Y6: 31 | Z6: =+X6+Y6 -> 306 | AA6: 29 | AB6: =+Z6+AA6 -> 335 | AC6: 31 | AD6: =+Y6+AA6+AC6 -> 91 | AE6: =+W6+AD6 -> 183 | AF6: =+Q6+AE6 -> 366
D7: PRODUCTION
D8: 1 | E8: No.of Ovens Pushed (COB#10) | F8: 2336 | G8: 2647 | H8: =+F8+G8 -> 4983 | I8: 2766 | J8: =+H8+I8 -> 7749 | K8: 3009 | L8: =+J8+K8 -> 10758 | M8: 3024 | N8: =+L8+M8 -> 13782 | O8: 2780 | P8: =+K8+M8+O8 -> 8813 | Q8: =+N8+O8 -> 16562 | R8: 3008 | S8: =+Q8+R8 -> 19570 | T8: 2937 | U8: =+S8+T8 -> 22507 | V8: 3042 | W8: =+R8+T8+V8 -> 8987 | X8: =+U8+V8 -> 25549 | Y8: 3077 | Z8: =+X8+Y8 -> 28626 | AA8: 2882 | AB8: =+Z8+AA8 -> 31508 | AC8: 2920 | AD8: =+Y8+AA8+AC8 -> 8879 | AE8: =+W8+AD8 -> 17866 | AF8: =+AB8+AC8 -> 34428
E9: No.of Ovens Pushed/ Day (COB#10) | F9: =+F8/F6 -> 77.866667 | G9: =+G8/G6 -> 85.387097 | H9: =+H8/H6 -> 81.688525 | I9: =+I8/I6 -> 92.2 | J9: =+J8/J6 -> 85.153846 | K9: =+K8/K6 -> 97.064516 | L9: =+L8/L6 -> 88.180328 | M9: =+M8/M6 -> 97.548387 | ... O9: =+O8/O6 -> 92.666667 | P9: =+P8/$P$6 -> 95.793478 | Q9: =+Q8/$Q$6 -> 90.502732 | R9: =+R8/R6 -> 97.032258 | S9: =+S8/S6 -> 91.448598 | T9: =+T8/T6 -> 97.9 | U9: =+U8/U6 -> 92.241803 | V9: =+V8/V6 -> 98.129032 | W9: =+W8/W6 -> 97.684783 | X9: =+X8/X6 -> 92.905455 | Y9: =+Y8/Y6 -> 99.258065 | ... AF9: =+AF8/AF6 -> 94.065574
D10: 2 | E10: Nos.of Ovens Pushed (COB#11) | F10: 2333 | G10: 2329 | H10: =+F10+G10 -> 4662 | I10: 2595 | J10: =+H10+I10 -> 7257 | K10: 2816 | L10: =+J10+K10 -> 10073 | M10: 3052 | N10: =+L10+M10 -> 13125 | O10: 2775 | P10: =+K10+M10+O10 -> 8643 | Q10: =+N10+O10 -> 15900 | R10: 3008 | S10: =+Q10+R10 -> 18908 | T10: 2912 | U10: =+S10+T10 -> 21820 | V10: 3047 | W10: =+R10+T10+V10 -> 8967 | X10: =+U10+V10 -> 24867 | Y10: 2914 | Z10: =+X10+Y10 -> 27781 | AA10: 2811 | AB10: =+Z10+AA10 -> 30592 | AC10: 2858 | AD10: =+Y10+AA10+AC10 -> 8583 | AE10: =+W10+AD10 -> 17550 | AF10: =+AB10+AC10 -> 33450
E11: Nos.of Ovens Pushed/ Day (COB#11) | F11: =+F10/F6 -> 77.766667 | G11: =+G10/G6 -> 75.129032 | H11: =+H10/H6 -> 76.42623 | I11: =+I10/I6 -> 86.5 | J11: =+J10/J6 -> 79.747253 | K11: =+K10/K6 -> 90.83871 | L11: =+L10/L6 -> 82.565574 | M11: =+M10/M6 -> 98.451613 | ... O11: =+O10/O6 -> 92.5 | P11: =+P10/$P$6 -> 93.945652 | Q11: =+Q10/Q6 -> 86.885246 | R11: =+R10/R6 -> 97.032258 | S11: =+S10/S6 -> 88.35514 | T11: =+T10/T6 -> 97.066667 | U11: =+U10/U6 -> 89.42623 | V11: =+V10/V6 -> 98.290323 | W11: =+W10/W6 -> 97.467391 | X11: =+X10/X6 -> 90.425455 | ... AF11: =+AF10/AF6 -> 91.393443
E12: Total No.of Equiv. Ovens Pushed | F12: =F8+(F10*1.8343023255814) -> 6615.4273 | G12: =G8+(G10*1.8343023255814) -> 6919.0901 | H12: =+F12+G12 -> 13534.517 | I12: =I8+(I10*1.8343023255814) -> 7526.0145 | J12: =+H12+I12 -> 21060.532 | K12: =K8+(K10*1.8343023255814) -> 8174.3953 | L12: =+J12+K12 -> 29234.927 | M12: =M8+(M10*1.8343023255814) -> 8622.2907 | N12: =+L12+M12 -> 37857.218 | O12: =O8+(O10*1.8343023255814) -> 7870.189 | P12: =+K12+M12+O12 -> 24666.875 | Q12: =+N12+O12 -> 45727.407 | R12: =R8+(R10*1.8343023255814) -> 8525.5814 | S12: =+Q12+R12 -> 54252.988 | T12: =T8+(T10*1.8343023255814) -> 8278.4884 | U12: =+S12+T12 -> 62531.477 | V12: =V8+(V10*1.8343023255814) -> 8631.1192 | W12: =+R12+T12+V12 -> 25435.189 | X12: =+U12+V12 -> 71162.596 | Y12: =Y8+(Y10*1.8343023255814) -> 8422.157 | Z12: =+X12+Y12 -> 79584.753 | AA12: =AA8+(AA10*1.8343023255814) -> 8038.2238 | AB12: =+Z12+AA12 -> 87622.977 | AC12: =AC8+(AC10*1.8343023255814) -> 8162.436 | AD12: =+Y12+AA12+AC12 -> 24622.817 | AE12: =+W12+AD12 -> 50058.006 | AF12: =+AB12+AC12 -> 95785.413
E13: Overall Equiv. Ovens Pushed/ Day | F13: =+F12/F6 -> 220.51424 | G13: =+G12/G6 -> 223.19646 | H13: =+H12/H6 -> 221.87734 | I13: =+I12/I6 -> 250.86715 | J13: =+J12/J6 -> 231.43442 | K13: =+K12/K6 -> 263.69017 | L13: =+L12/L6 -> 239.63055 | M13: =+M12/M6 -> 278.13841 | ... O13: =+O12/O6 -> 262.33963 | P13: =+P12/$P$6 -> 268.11821 | Q13: =+Q12/$Q$6 -> 249.87654 | R13: =+R12/R6 -> 275.01875 | S13: =+S12/S6 -> 253.51864 | T13: =+T12/T6 -> 275.94961 | U13: =+U12/U6 -> 256.27654 | V13: =+V12/V6 -> 278.4232 | W13: =+W12/W6 -> 276.46945 | X13: =+X12/X6 -> 258.77308 | Y13: =+Y12/Y6 -> 271.68248 | ... AF13: =+AF12/AF6 -> 261.70878
E14: OVEN AVAILABILITY (COB #10) | F14: 77.43 | G14: 77.29 | H14: =+((F14*$F$6)+(G14*$G$6))/$H$6 -> 77.358852 | I14: 77.46 | J14: =+((H14*$H$6)+(I14*$I$6))/$J$6 -> 77.392198 | K14: 77.74 | L14: =+((J14*$J$6)+(K14*$K$6))/$L$6 -> 77.480574 | M14: 77.7 | N14: =+((L14*$L$6)+(M14*$M$6))/$N$6 -> 77.525033 | O14: 77.7 | P14: =+((K14*$K$6)+(M14*$M$6)+(O14*$O$6))/$P$6 -> 77.713478 | Q14: =+((N14*$N$6)+(O14*$O$6))/$Q$6 -> 77.553716 | R14: 77.6 | S14: =+((Q14*$Q$6)+(R14*$R$6))/$S$6 -> 77.560421 | T14: 77.73 | U14: =+((S14*$S$6)+(T14*$T$6))/$U$6 -> 77.58127 | V14: 76.71 | W14: =+((R14*$R$6)+(T14*$T$6)+(V14*$V$6))/$W$6 -> 77.3425 | X14: =+((U14*$U$6)+(V14*$V$6))/$X$6 -> 77.483055 | Y14: 77.77 | Z14: =+((X14*$X$6)+(Y14*$Y$6))/$Z$6 -> 77.512124 | AA14: 77.51 | AB14: =+((Z14*$Z$6)+(AA14*$AA$6))/$AB$6 -> 77.51194 | AC14: 77.58 | AD14: =+((Y14*$Y$6)+(AA14*$AA$6)+(AC14*$AC$6))/$AD$6 -> 77.622418 | AE14: =+((W14*$W$6)+(AD14*$AD$6))/$AE$6 -> 77.481694 | AF14: =+((AB14*$AB$6)+(AC14*$AC$6))/$AF$6 -> 77.517705
E15: OVEN AVAILABILITY (COB #11) | F15: 74 | G15: 74 | H15: =+((F15*$F$6)+(G15*$G$6))/$H$6 -> 74 | I15: 74 | J15: =+((H15*$H$6)+(I15*$I$6))/$J$6 -> 74 | K15: 73.9 | L15: =+((J15*$J$6)+(K15*$K$6))/$L$6 -> 73.97459 | M15: 74 | N15: =+((L15*$L$6)+(M15*$M$6))/$N$6 -> 73.979739 | O15: 73.9 | P15: =+((K15*$K$6)+(M15*$M$6)+(O15*$O$6))/$P$6 -> 73.933696 | Q15: =+((N15*$N$6)+(O15*$O$6))/$Q$6 -> 73.966667 | R15: 74 | S15: =+((Q15*$Q$6)+(R15*$R$6))/$S$6 -> 73.971495 | T15: 73.9 | U15: =+((S15*$S$6)+(T15*$T$6))/$U$6 -> 73.962705 | V15: 74 | W15: =+((R15*$R$6)+(T15*$T$6)+(V15*$V$6))/$W$6 -> 73.967391 | X15: =+((U15*$U$6)+(V15*$V$6))/$X$6 -> 73.966909 | Y15: 74 | Z15: =+((X15*$X$6)+(Y15*$Y$6))/$Z$6 -> 73.970261 | AA15: 74 | AB15: =+((Z15*$Z$6)+(AA15*$AA$6))/$AB$6 -> 73.972836 | AC15: 74 | AD15: =+((Y15*$Y$6)+(AA15*$AA$6)+(AC15*$AC$6))/$AD$6 -> 74 | AE15: =+((W15*$W$6)+(AD15*$AD$6))/$AE$6 -> 73.983607 | AF15: =+((AB15*$AB$6)+(AC15*$AC$6))/$AF$6 -> 73.975137
E16: PUSHING CO-EFFICIENT (BASED ON ACTUAL OVEN AVAILABILITY)
C17: =5575.09+47146.97 -> 52722.06 | E17: COB#10 | F17: =+F8/(F14*F6) -> 1.0056395 | G17: =+G8/(G14*G6) -> 1.1047625 | H17: =+H8/(H14*H6) -> 1.0559687 | I17: =+I8/(I14*I6) -> 1.1902918 | J17: =+J8/(J14*J6) -> 1.1002898 | K17: =+K8/(K14*K6) -> 1.2485788 | L17: =+L8/(L14*L6) -> 1.138096 | M17: =+M8/(M14*M6) -> 1.255449 | ... AF17: =+AF8/(AF14*AF6) -> 1.2134721
E18: COB#11 | F18: =+F10/(F15*F6) -> 1.0509009 | G18: =+G10/(G15*G6) -> 1.0152572 | H18: =+H10/(H15*H6) -> 1.0327869 | I18: =+I10/(I15*I6) -> 1.1689189 | J18: =+J10/(J15*J6) -> 1.0776656 | K18: =+K10/(K15*K6) -> 1.2292112 | L18: =+L10/(L15*L6) -> 1.1161343 | M18: =+M10/(M15*M6) -> 1.3304272 | ... AF18: =+AF10/(AF15*AF6) -> 1.2354616
E19: Dry Coal Charge (Old Batts) | F19: =+F8*17.2 -> 40179.2 | G19: =+G8*17.2 -> 45528.4 | H19: =+F19+G19 -> 85707.6 | I19: =+I8*17.2 -> 47575.2 | J19: =+H19+I19 -> 133282.8 | K19: =+K8*17.2 -> 51754.8 | L19: =SUM(J19:K19) -> 185037.6 | M19: =+M8*17.2 -> 52012.8 | N19: =SUM(L19:M19) -> 237050.4 | O19: =+O8*17.2 -> 47816 | P19: =+K19+M19+O19 -> 151583.6 | Q19: =+N19+O19 -> 284866.4 | R19: =+R8*17.2 -> 51737.6 | S19: =SUM(Q19:R19) -> 336604 | T19: =+T8*17.2 -> 50516.4 | U19: =SUM(S19:T19) -> 387120.4 | V19: =+V8*17.2 -> 52322.4 | W19: =+R19+T19+V19 -> 154576.4 | X19: =+U19+V19 -> 439442.8 | Y19: =+Y8*17.2 -> 52924.4 | Z19: =SUM(X19:Y19) -> 492367.2 | AA19: =+AA8*17.2 -> 49570.4 | AB19: =+Z19+AA19 -> 541937.6 | AC19: =+AC8*17.2 -> 50224 | AD19: =+Y19+AA19+AC19 -> 152718.8 | AE19: =+W19+AD19 -> 307295.2 | AF19: =+AB19+AC19 -> 592161.6
E20: Dry Coal Charge (New Batt) | F20: =+F10*31.55 -> 73606.15 | G20: =+G10*31.55 -> 73479.95 | H20: =SUM(F20:G20) -> 147086.1 | I20: =+I10*31.55 -> 81872.25 | J20: =+H20+I20 -> 228958.35 | K20: =+K10*31.55 -> 88844.8 | L20: =SUM(J20:K20) -> 317803.15 | M20: =+M10*31.55 -> 96290.6 | N20: =SUM(L20:M20) -> 414093.75 | O20: =+O10*31.55 -> 87551.25 | P20: =+K20+M20+O20 -> 272686.65 | Q20: =+N20+O20 -> 501645 | R20: =+R10*31.55 -> 94902.4 | S20: =SUM(Q20:R20) -> 596547.4 | T20: =+T10*31.55 -> 91873.6 | U20: =SUM(S20:T20) -> 688421 | V20: =+V10*31.55 -> 96132.85 | W20: =+R20+T20+V20 -> 282908.85 | X20: =+U20+V20 -> 784553.85 | Y20: =+Y10*31.55 -> 91936.7 | Z20: =SUM(X20:Y20) -> 876490.55 | AA20: =+AA10*31.55 -> 88687.05 | AB20: =+Z20+AA20 -> 965177.6 | AC20: =+AC10*31.55 -> 90169.9 | AD20: =+Y20+AA20+AC20 -> 270793.65 | AE20: =+W20+AD20 -> 553702.5 | AF20: =+AB20+AC20 -> 1055347.5
E21: Total Dry Coal Charge | F21: =SUM(F19:F20) -> 113785.35 | G21: =SUM(G19:G20) -> 119008.35 | H21: =SUM(H19:H20) -> 232793.7 | I21: =SUM(I19:I20) -> 129447.45 | J21: =SUM(J19:J20) -> 362241.15 | K21: =SUM(K19:K20) -> 140599.6 | L21: =SUM(L19:L20) -> 502840.75 | M21: =SUM(M19:M20) -> 148303.4 | ... AF21: =SUM(AF19:AF20) -> 1647509.1
D22: 5. | E22: B.F.Coke (Old Batts) | F22: 27936.6 | G22: 31876 | H22: =+F22+G22 -> 59812.6 | I22: 33669.6 | J22: =+H22+I22 -> 93482.2 | K22: 36675 | L22: =+J22+K22 -> 130157.2 | M22: 34692.54 | N22: =+L22+M22 -> 164849.74 | O22: 31931.5 | P22: =+K22+M22+O22 -> 103299.04 | Q22: =+N22+O22 -> 196781.24 | R22: 34545.2 | S22: =+Q22+R22 -> 231326.44 | T22: 34351.2 | U22: =+S22+T22 -> 265677.64 | V22: 35840.8 | W22: =+R22+T22+V22 -> 104737.2 | X22: =+U22+V22 -> 301518.44 | Y22: 36285 | Z22: =+X22+Y22 -> 337803.44 | AA22: 34074.7 | AB22: =+Z22+AA22 -> 371878.14 | AC22: 34659.6 | AD22: =+Y22+AA22+AC22 -> 105019.3 | AE22: =+W22+AD22 -> 209756.5 | AF22: =+AB22+AC22 -> 406537.74
E23: B.F Coke (New Batt) | F23: =+F626 -> 51175.3 | G23: =+G626 -> 51446 | H23: =SUM(F23:G23) -> 102621.3 | I23: =+I626 -> 57942.1 | J23: =+H23+I23 -> 160563.4 | K23: =+K626 -> 62959 | L23: =+J23+K23 -> 223522.4 | M23: =+M626 -> 64223.17 | N23: =+L23+M23 -> 287745.57 | O23: =+O626 -> 58471.09 | P23: =+K23+M23+O23 -> 185653.26 | Q23: =+N23+O23 -> 346216.66 | R23: =+R626 -> 63365.36 | S23: =+Q23+R23 -> 409582.02 | T23: =+T626 -> 62474 | U23: =SUM(S23:T23) -> 472056.02 | V23: =+V626 -> 65847 | W23: =+R23+T23+V23 -> 191686.36 | X23: =+U23+V23 -> 537903.02 | Y23: =+Y626 -> 63029 | Z23: =+X23+Y23 -> 600932.02 | AA23: =+AA626 -> 60966 | AB23: =+Z23+AA23 -> 661898.02 | AC23: =+AC626 -> 62225 | AD23: =+Y23+AA23+AC23 -> 186220 | AE23: =+W23+AD23 -> 377906.36 | AF23: =+AB23+AC23 -> 724123.02
E24: Total B.F.Coke | F24: =SUM(F22:F23) -> 79111.9 | G24: =SUM(G22:G23) -> 83322 | H24: =SUM(H22:H23) -> 162433.9 | I24: =SUM(I22:I23) -> 91611.7 | J24: =SUM(J22:J23) -> 254045.6 | K24: =SUM(K22:K23) -> 99634 | L24: =SUM(L22:L23) -> 353679.6 | M24: =SUM(M22:M23) -> 98915.71 | ... Y24: =SUM(Y22:Y23) -> 99314 | Z24: =+X24+Y24 -> 938735.46 | AA24: =SUM(AA22:AA23) -> 95040.7 | AB24: =+Z24+AA24 -> 1033776.2 | AC24: =SUM(AC22:AC23) -> 96884.6 | AD24: =SUM(AD22:AD23) -> 291239.3 | AE24: =SUM(AE22:AE23) -> 587662.86 | AF24: =SUM(AF22:AF23) -> 1130660.8
E25: Nut Coke (Old Batts) | F25: 317.4 | G25: 184 | H25: =+F25+G25 -> 501.4 | I25: 149.8 | J25: =+H25+I25 -> 651.2 | K25: 427 | L25: =+J25+K25 -> 1078.2 | M25: 1607.2 | N25: =+L25+M25 -> 2685.4 | O25: 1601.8 | P25: =+K25+M25+O25 -> 3636 | Q25: =+N25+O25 -> 4287.2 | R25: 1536.6 | S25: =+Q25+R25 -> 5823.8 | T25: 1262.9 | U25: =+S25+T25 -> 7086.7 | V25: 1339.5 | W25: =+R25+T25+V25 -> 4139 | X25: =+U25+V25 -> 8426.2 | Y25: 1122 | Z25: =+X25+Y25 -> 9548.2 | AA25: 931.9 | AB25: =+Z25+AA25 -> 10480.1 | AC25: 999.5 | AD25: =+Y25+AA25+AC25 -> 3053.4 | AE25: =+W25+AD25 -> 7192.4 | AF25: =+AB25+AC25 -> 11479.6
E26: Nut Coke (New Batt) | F26: =+F627 -> 582.6 | G26: =+G627 -> 297 | H26: =SUM(F26:G26) -> 879.6 | I26: =+I627 -> 257.8 | J26: =+H26+I26 -> 1137.4 | K26: =+K627 -> 733 | L26: =+J26+K26 -> 1870.4 | M26: =+M627 -> 2979.15 | N26: =+L26+M26 -> 4849.55 | O26: =+O627 -> 2932.95 | P26: =+K26+M26+O26 -> 6645.1 | Q26: =+N26+O26 -> 7782.5 | R26: =+R627 -> 2819.91 | S26: =+Q26+R26 -> 10602.41 | T26: =+T627 -> 2296.8 | U26: =SUM(S26:T26) -> 12899.21 | V26: =+V627 -> 2463 | W26: =+R26+T26+V26 -> 7579.71 | X26: =+U26+V26 -> 15362.21 | Y26: =+Y627 -> 1945 | Z26: =+X26+Y26 -> 17307.21 | AA26: =+AA627 -> 1670 | AB26: =+Z26+AA26 -> 18977.21 | AC26: =+AC627 -> 1795 | AD26: =+Y26+AA26+AC26 -> 5410 | AE26: =+W26+AD26 -> 12989.71 | AF26: =+AB26+AC26 -> 20772.21
E27: Total Nut Coke | F27: =SUM(F25:F26) -> 900 | G27: =SUM(G25:G26) -> 481 | H27: =SUM(H25:H26) -> 1381 | I27: =SUM(I25:I26) -> 407.6 | J27: =SUM(J25:J26) -> 1788.6 | K27: =SUM(K25:K26) -> 1160 | L27: =SUM(L25:L26) -> 2948.6 | M27: =SUM(M25:M26) -> 4586.35 | ... Y27: =SUM(Y25:Y26) -> 3067 | Z27: =+X27+Y27 -> 26855.41 | AA27: =SUM(AA25:AA26) -> 2601.9 | AB27: =+Z27+AA27 -> 29457.31 | AC27: =SUM(AC25:AC26) -> 2794.5 | AD27: =SUM(AD25:AD26) -> 8463.4 | AE27: =SUM(AE25:AE26) -> 20182.11 | AF27: =SUM(AF25:AF26) -> 32251.81
E28: Coke Breeze (Old Batts) | F28: 1884.4 | G28: 2091 | H28: =+F28+G28 -> 3975.4 | I28: 1871.5 | J28: =+H28+I28 -> 5846.9 | K28: 1715 | L28: =+J28+K28 -> 7561.9 | M28: 2735.87 | N28: =+L28+M28 -> 10297.77 | O28: 2390.8 | P28: =+K28+M28+O28 -> 6841.67 | Q28: =+N28+O28 -> 12688.57 | R28: 2773.1 | S28: =+Q28+R28 -> 15461.67 | T28: 2273.2 | U28: =+S28+T28 -> 17734.87 | V28: 2150.5 | W28: =+R28+T28+V28 -> 7196.8 | X28: =+U28+V28 -> 19885.37 | Y28: 2281 | Z28: =+X28+Y28 -> 22166.37 | AA28: 2171.2 | AB28: =+Z28+AA28 -> 24337.57 | AC28: 2009 | AD28: =+Y28+AA28+AC28 -> 6461.2 | AE28: =+W28+AD28 -> 13658 | AF28: =+AB28+AC28 -> 26346.57
E29: Coke Breeze (New Batt) | F29: =+F628 -> 3452.5 | G29: =+G628 -> 3374 | H29: =SUM(F29:G29) -> 6826.5 | I29: =+I628 -> 3220.7 | J29: =+H29+I29 -> 10047.2 | K29: =+K628 -> 2945 | L29: =+J29+K29 -> 12992.2 | M29: =+M628 -> 5068.85 | N29: =+L29+M29 -> 18061.05 | O29: =+O628 -> 4373.49 | P29: =+K29+M29+O29 -> 12387.34 | Q29: =+N29+O29 -> 22434.54 | R29: =+R628 -> 5085.66 | S29: =+Q29+R29 -> 27520.2 | T29: =+T628 -> 4134.3 | U29: =SUM(S29:T29) -> 31654.5 | V29: =+V628 -> 3947 | W29: =+R29+T29+V29 -> 13166.96 | X29: =+U29+V29 -> 35601.5 | Y29: =+Y628 -> 3965 | Z29: =+X29+Y29 -> 39566.5 | AA29: =+AA628 -> 3887 | AB29: =+Z29+AA29 -> 43453.5 | AC29: =+AC628 -> 3610 | AD29: =+Y29+AA29+AC29 -> 11462 | AE29: =+W29+AD29 -> 24628.96 | AF29: =+AB29+AC29 -> 47063.5
E30: Total Coke Breeze | F30: =SUM(F28:F29) -> 5336.9 | G30: =SUM(G28:G29) -> 5465 | H30: =SUM(H28:H29) -> 10801.9 | I30: =SUM(I28:I29) -> 5092.2 | J30: =SUM(J28:J29) -> 15894.1 | K30: =SUM(K28:K29) -> 4660 | L30: =SUM(L28:L29) -> 20554.1 | M30: =SUM(M28:M29) -> 7804.72 | ... Y30: =SUM(Y28:Y29) -> 6246 | Z30: =+X30+Y30 -> 61732.87 | AA30: =SUM(AA28:AA29) -> 6058.2 | AB30: =+Z30+AA30 -> 67791.07 | AC30: =SUM(AC28:AC29) -> 5619 | AD30: =SUM(AD28:AD29) -> 17923.2 | AE30: =SUM(AE28:AE29) -> 38286.96 | AF30: =SUM(AF28:AF29) -> 73410.07
E31: Coke Dust (Old Batts) | F31: 397.8 | G31: 451 | H31: =+F31+G31 -> 848.8 | I31: 466.2 | J31: =+H31+I31 -> 1315 | K31: 516 | L31: =+J31+K31 -> 1831 | M31: 488.92 | N31: =+L31+M31 -> 2319.92 | O31: 416 | P31: =+K31+M31+O31 -> 1420.92 | Q31: =+N31+O31 -> 2735.92 | R31: 465.6 | S31: =+Q31+R31 -> 3201.52 | T31: 505.2 | U31: =+S31+T31 -> 3706.72 | V31: 439.5 | W31: =+R31+T31+V31 -> 1410.3 | X31: =+U31+V31 -> 4146.22 | Y31: 539.8 | Z31: =+X31+Y31 -> 4686.02 | AA31: 490.7 | AB31: =+Z31+AA31 -> 5176.72 | AC31: 502.2 | AD31: =+Y31+AA31+AC31 -> 1532.7 | AE31: =+W31+AD31 -> 2943 | AF31: =+AB31+AC31 -> 5678.92
E32: Coke Dust (New Batt) | F32: =+F629 -> 730.3 | G32: =+G629 -> 728 | H32: =SUM(F32:G32) -> 1458.3 | I32: =+I629 -> 802.3 | J32: =+H32+I32 -> 2260.6 | K32: =+K629 -> 886 | L32: =+J32+K32 -> 3146.6 | M32: =+M629 -> 909.69 | N32: =+L32+M32 -> 4056.29 | O32: =+O629 -> 761.42 | P32: =+K32+M32+O32 -> 2557.11 | Q32: =+N32+O32 -> 4817.71 | R32: =+R629 -> 854.89 | S32: =+Q32+R32 -> 5672.6 | T32: =+T629 -> 918.7 | U32: =SUM(S32:T32) -> 6591.3 | V32: =+V629 -> 803 | W32: =+R32+T32+V32 -> 2576.59 | X32: =+U32+V32 -> 7394.3 | Y32: =+Y629 -> 933 | Z32: =+X32+Y32 -> 8327.3 | AA32: =+AA629 -> 879 | AB32: =+Z32+AA32 -> 9206.3 | AC32: =+AC629 -> 898 | AD32: =+Y32+AA32+AC32 -> 2710 | AE32: =+W32+AD32 -> 5286.59 | AF32: =+AB32+AC32 -> 10104.3
E33: Total Coke Dust | F33: =SUM(F31:F32) -> 1128.1 | G33: =SUM(G31:G32) -> 1179 | H33: =SUM(H31:H32) -> 2307.1 | I33: =SUM(I31:I32) -> 1268.5 | J33: =SUM(J31:J32) -> 3575.6 | K33: =SUM(K31:K32) -> 1402 | L33: =SUM(L31:L32) -> 4977.6 | M33: =SUM(M31:M32) -> 1398.61 | ... Y33: =SUM(Y31:Y32) -> 1472.8 | Z33: =+X33+Y33 -> 13013.32 | AA33: =SUM(AA31:AA32) -> 1369.7 | AB33: =+Z33+AA33 -> 14383.02 | AC33: =SUM(AC31:AC32) -> 1400.2 | AD33: =SUM(AD31:AD32) -> 4242.7 | AE33: =SUM(AE31:AE32) -> 8229.59 | AF33: =SUM(AF31:AF32) -> 15783.22
E34: Gross Coke (Old Batts) | F34: =+F22+F25+F28+F31 -> 30536.2 | G34: =+G22+G25+G28+G31 -> 34602 | H34: =+F34+G34 -> 65138.2 | I34: =+I22+I25+I28+I31 -> 36157.1 | J34: =+H34+I34 -> 101295.3 | K34: =+K22+K25+K28+K31 -> 39333 | L34: =+J34+K34 -> 140628.3 | M34: =+M22+M25+M28+M31 -> 39524.53 | N34: =+L34+M34 -> 180152.83 | O34: =+O22+O25+O28+O31 -> 36340.1 | P34: =+K34+M34+O34 -> 115197.63 | Q34: =+N34+O34 -> 216492.93 | R34: =+R22+R25+R28+R31 -> 39320.5 | S34: =+Q34+R34 -> 255813.43 | T34: =+T22+T25+T28+T31 -> 38392.5 | U34: =+S34+T34 -> 294205.93 | V34: =+V22+V25+V28+V31 -> 39770.3 | W34: =+R34+T34+V34 -> 117483.3 | X34: =+U34+V34 -> 333976.23 | Y34: =+Y22+Y25+Y28+Y31 -> 40227.8 | Z34: =+X34+Y34 -> 374204.03 | AA34: =+AA22+AA25+AA28+AA31 -> 37668.5 | AB34: =+Z34+AA34 -> 411872.53 | AC34: =+AC22+AC25+AC28+AC31 -> 38170.3 | AD34: =+Y34+AA34+AC34 -> 116066.6 | AE34: =+W34+AD34 -> 233549.9 | AF34: =+AB34+AC34 -> 450042.83
E35: Gross Coke (New Batt) | F35: =+F23+F26+F29+F32 -> 55940.7 | G35: =+G23+G26+G29+G32 -> 55845 | H35: =SUM(F35:G35) -> 111785.7 | I35: =+I23+I26+I29+I32 -> 62222.9 | J35: =+H35+I35 -> 174008.6 | K35: =+K23+K26+K29+K32 -> 67523 | L35: =+J35+K35 -> 241531.6 | M35: =+M23+M26+M29+M32 -> 73180.86 | N35: =+L35+M35 -> 314712.46 | O35: =+O23+O26+O29+O32 -> 66538.95 | P35: =+K35+M35+O35 -> 207242.81 | Q35: =+N35+O35 -> 381251.41 | R35: =+R23+R26+R29+R32 -> 72125.82 | S35: =+Q35+R35 -> 453377.23 | T35: =+T23+T26+T29+T32 -> 69823.8 | U35: =SUM(S35:T35) -> 523201.03 | V35: =+V23+V26+V29+V32 -> 73060 | W35: =+R35+T35+V35 -> 215009.62 | X35: =+U35+V35 -> 596261.03 | Y35: =+Y23+Y26+Y29+Y32 -> 69872 | Z35: =+X35+Y35 -> 666133.03 | AA35: =+AA23+AA26+AA29+AA32 -> 67402 | AB35: =+Z35+AA35 -> 733535.03 | AC35: =+AC23+AC26+AC29+AC32 -> 68528 | AD35: =+Y35+AA35+AC35 -> 205802 | AE35: =+W35+AD35 -> 420811.62 | AF35: =+AB35+AC35 -> 802063.03
E36: Total Gross Coke | F36: =SUM(F34:F35) -> 86476.9 | G36: =SUM(G34:G35) -> 90447 | H36: =SUM(H34:H35) -> 176923.9 | I36: =SUM(I34:I35) -> 98380 | J36: =SUM(J34:J35) -> 275303.9 | K36: =SUM(K34:K35) -> 106856 | L36: =SUM(L34:L35) -> 382159.9 | M36: =SUM(M34:M35) -> 112705.39 | ... Y36: =SUM(Y34:Y35) -> 110099.8 | Z36: =+X36+Y36 -> 1040337.1 | AA36: =SUM(AA34:AA35) -> 105070.5 | AB36: =+Z36+AA36 -> 1145407.6 | AC36: =SUM(AC34:AC35) -> 106698.3 | AD36: =SUM(AD34:AD35) -> 321868.6 | AE36: =SUM(AE34:AE35) -> 654361.52 | AF36: =SUM(AF34:AF35) -> 1252105.9
D37: 6. | E37: Sinter | F37: =+F717 -> 235289 | G37: =+G717 -> 239020 | H37: =+F37+G37 -> 474309 | I37: =+I717 -> 260541 | J37: =+H37+I37 -> 734850 | K37: =+K717 -> 0 | L37: =+J37+K37 -> 734850 | M37: =+M717 -> 335875 | N37: =+L37+M37 -> 1070725 | O37: =+O717 -> 248691 | P37: =+K37+M37+O37 -> 584566 | Q37: =+N37+O37 -> 1319416 | R37: =+R717 -> 276292 | S37: =+Q37+R37 -> 1595708 | T37: =+T717 -> 310927 | U37: =+S37+T37 -> 1906635 | V37: =+V717 -> 366651 | W37: =+R37+T37+V37 -> 953870 | X37: =+U37+V37 -> 2273286 | Y37: =+Y717 -> 347065 | Z37: =+X37+Y37 -> 2620351 | AA37: =+AA717 -> 341012 | AB37: =+Z37+AA37 -> 2961363 | AC37: =+AC717 -> 320002 | AD37: =+Y37+AA37+AC37 -> 1008079 | AE37: =+W37+AD37 -> 1961949 | AF37: =+AB37+AC37 -> 3281365
D38: 7. | E38: Hot Metal
E39: BF #5 | F39: 143766 | G39: 152132 | H39: =+F39+G39 -> 295898 | I39: 167381 | J39: =+H39+I39 -> 463279 | K39: 190559 | L39: =+J39+K39 -> 653838 | M39: 229309 | N39: =+L39+M39 -> 883147 | O39: 166018 | P39: =+K39+M39+O39 -> 585886 | Q39: =+N39+O39 -> 1049165 | R39: 195036 | S39: =+Q39+R39 -> 1244201 | T39: 211077 | U39: =+S39+T39 -> 1455278 | V39: 250305 | W39: =+R39+T39+V39 -> 656418 | X39: =+U39+V39 -> 1705583 | Y39: 240311 | Z39: =+X39+Y39 -> 1945894 | AA39: 234647 | AB39: =+Z39+AA39 -> 2180541 | AC39: 219210 | AD39: =+Y39+AA39+AC39 -> 694168 | AE39: =+W39+AD39 -> 1350586 | AF39: =+AB39+AC39 -> 2399751
E40: Total | F40: =SUM(F39:F39) -> 143766 | G40: =SUM(G39:G39) -> 152132 | H40: =SUM(H39:H39) -> 295898 | I40: =SUM(I39:I39) -> 167381 | J40: =SUM(J39:J39) -> 463279 | K40: =SUM(K39:K39) -> 190559 | L40: =SUM(L39:L39) -> 653838 | M40: =SUM(M39:M39) -> 229309 | ... AF40: =SUM(AF39:AF39) -> 2399751
C41: 26.52498 | D41: 8. | E41: Cold Pig & Pig Equivalent
C42: 15.8304 | E42: BF #5 (Pig ) Net | F42: 3047 | G42: 2899 | H42: =SUM(F42:G42) -> 5946 | I42: 2804 | J42: =+H42+I42 -> 8750 | K42: 8503 | L42: =+J42+K42 -> 17253 | M42: 5056 | N42: =+L42+M42 -> 22309 | O42: =3479+1178 -> 4657 | P42: =+K42+M42+O42 -> 18216 | Q42: =+N42+O42 -> 26966 | R42: 6703 | S42: =+Q42+R42 -> 33669 | T42: 13729 | U42: =+S42+T42 -> 47398 | V42: 12623 | W42: =+R42+T42+V42 -> 33055 | X42: =+U42+V42 -> 60021 | Y42: 8529 | Z42: =+X42+Y42 -> 68550 | AA42: 9429 | AB42: =+Z42+AA42 -> 77979 | AC42: 13226 | AD42: =+Y42+AA42+AC42 -> 31184 | AE42: =+W42+AD42 -> 64239 | AF42: =+AB42+AC42 -> 91205
E43: BF #5 (UPIS) Net | F43: 201 | G43: 191 | H43: =SUM(F43:G43) -> 392 | I43: 185 | J43: =+H43+I43 -> 577 | K43: 561 | L43: =+J43+K43 -> 1138 | M43: 341 | N43: =+L43+M43 -> 1479 | O43: 313 | P43: =+K43+M43+O43 -> 1215 | Q43: =+N43+O43 -> 1792 | R43: 518 | S43: =+Q43+R43 -> 2310 | T43: 905 | U43: =SUM(S43:T43) -> 3215 | V43: 832 | W43: =+R43+T43+V43 -> 2255 | X43: =+U43+V43 -> 4047 | Y43: 562 | Z43: =+X43+Y43 -> 4609 | AA43: 622 | AB43: =+Z43+AA43 -> 5231 | AC43: 872 | AD43: =+Y43+AA43+AC43 -> 2056 | AE43: =+W43+AD43 -> 4311 | AF43: =+AB43+AC43 -> 6103
E44: Processed CI Scrap (Sand Cast) produced from HM sent to Sand Pit | F44: 2418 | G44: 4190 | H44: =+F44+G44 -> 6608 | I44: 4452 | J44: =+H44+I44 -> 11060 | K44: 2813 | L44: =+J44+K44 -> 13873 | M44: 6142 | N44: =+L44+M44 -> 20015 | O44: 6105 | P44: =+K44+M44+O44 -> 15060 | Q44: =+N44+O44 -> 26120 | R44: 5596 | S44: =+Q44+R44 -> 31716 | T44: 5686.5 | U44: =+S44+T44 -> 37402.5 | V44: 2905.92 | W44: =+R44+T44+V44 -> 14188.42 | X44: =+U44+V44 -> 40308.42 | Y44: 7767.28 | Z44: =+X44+Y44 -> 48075.7 | AA44: 3268 | AB44: =+Z44+AA44 -> 51343.7 | AC44: 6946 | AD44: =+Y44+AA44+AC44 -> 17981.28 | AE44: =+W44+AD44 -> 32169.7 | AF44: =+AB44+AC44 -> 58289.7
E45: Total | F45: =SUM(F42:F44) -> 5666 | G45: =SUM(G42:G44) -> 7280 | H45: =SUM(H42:H44) -> 12946 | I45: =SUM(I42:I44) -> 7441 | J45: =SUM(J42:J44) -> 20387 | K45: =SUM(K42:K44) -> 11877 | L45: =SUM(L42:L44) -> 32264 | M45: =SUM(M42:M44) -> 11539 | ... V45: =SUM(V42:V44) -> 16360.92 | W45: =SUM(W42:W42) -> 33055 | X45: =SUM(X42:X44) -> 104376.42 | Y45: =SUM(Y42:Y44) -> 16858.28 | Z45: =SUM(Z42:Z44) -> 121234.7 | AA45: =SUM(AA42:AA44) -> 13319 | AB45: =SUM(AB42:AB44) -> 134553.7 | AC45: =SUM(AC42:AC44) -> 21044 | AD45: =SUM(AD42:AD44) -> 51221.28 | AE45: =SUM(AE42:AE44) -> 100719.7 | AF45: =SUM(AF42:AF44) -> 155597.7
A46: =86703-76333 -> 10370 | D46: 9. | E46: Gross Granulated Slag Generation (Incl recovery through segregation) - Mt | F46: 53267 | G46: 56520 | H46: =SUM(F46:G46) -> 109787 | I46: 62698 | J46: =SUM(H46:I46) -> 172485 | K46: 73739 | L46: =SUM(J46:K46) -> 246224 | M46: =74162+13000 -> 87162 | N46: =SUM(L46:M46) -> 333386 | O46: 52687 | P46: =+K46+M46+O46 -> 213588 | Q46: =+N46+O46 -> 386073 | R46: =57374+14000 -> 71374 | S46: =SUM(Q46:R46) -> 457447 | T46: =69190+20000 -> 89190 | U46: =SUM(S46:T46) -> 546637 | V46: 77243 | W46: =+R46+T46+V46 -> 237807 | X46: =+U46+V46 -> 623880 | Y46: 77620 | Z46: =+X46+Y46 -> 701500 | AA46: 82236 | AB46: =+Z46+AA46 -> 783736 | AC46: 76133 | AD46: =+Y46+AA46+AC46 -> 235989 | AE46: =+W46+AD46 -> 473796 | AF46: =+AB46+AC46 -> 859869
E47: Net Granulated Slag Production - Mt | F47: 55719 | G47: 52052 | H47: =+F47+G47 -> 107771 | I47: 61691 | J47: =+H47+I47 -> 169462 | K47: 63617 | L47: =+J47+K47 -> 233079 | M47: 72679 | N47: =+L47+M47 -> 305758 | O47: 52687 | P47: =+K47+M47+O47 -> 188983 | Q47: =+N47+O47 -> 358445 | R47: 57374 | S47: =+Q47+R47 -> 415819 | T47: 69190 | U47: =+S47+T47 -> 485009 | V47: 77243 | W47: =+R47+T47+V47 -> 203807 | X47: =+U47+V47 -> 562252 | Y47: 74753 | Z47: =+X47+Y47 -> 637005 | AA47: 81888 | AB47: =+Z47+AA47 -> 718893 | AC47: 88816 | AD47: =+Y47+AA47+AC47 -> 245457 | AE47: =+W47+AD47 -> 449264 | AF47: =+AB47+AC47 -> 807709
A48: =+A46/3 -> 3456.6667 | E48: Liquid Steel input in Turret - Mt | F48: 131608 | G48: 136603 | H48: =+F48+G48 -> 268211 | I48: 149590 | J48: =+H48+I48 -> 417801 | K48: 163478 | L48: =+J48+K48 -> 581279 | M48: 208900 | N48: =+L48+M48 -> 790179 | O48: 155000 | P48: =+K48+M48+O48 -> 527378 | Q48: =+N48+O48 -> 945179 | R48: 178280 | S48: =+Q48+R48 -> 1123459 | T48: 182777 | U48: =+S48+T48 -> 1306236 | V48: 213280 | W48: =+R48+T48+V48 -> 574337 | X48: =+U48+V48 -> 1519516 | Y48: 212375 | Z48: =+X48+Y48 -> 1731891 | AA48: 200520 | AB48: =+Z48+AA48 -> 1932411 | AC48: 187422 | AD48: =+Y48+AA48+AC48 -> 600317 | AE48: =+W48+AD48 -> 1174654 | AF48: =+AB48+AC48 -> 2119833
A49: =+A48/140 -> 24.690476 | D49: 11. | E49: Crude Steel (CCP) | F49: 129292 | G49: 134303 | H49: =+F49+G49 -> 263595 | I49: 147382 | J49: =+H49+I49 -> 410977 | K49: 160929 | L49: =+J49+K49 -> 571906 | M49: 202150 | N49: =+L49+M49 -> 774056 | O49: 150010 | P49: =+K49+M49+O49 -> 513089 | Q49: =+N49+O49 -> 924066 | R49: 173129 | S49: =+Q49+R49 -> 1097195 | T49: 176039 | U49: =+S49+T49 -> 1273234 | V49: 207005 | W49: =+R49+T49+V49 -> 556173 | X49: =+U49+V49 -> 1480239 | Y49: 208345 | Z49: =+X49+Y49 -> 1688584 | AA49: 197000 | AB49: =+Z49+AA49 -> 1885584 | AC49: 183944 | AD49: =+Y49+AA49+AC49 -> 589289 | AE49: =+W49+AD49 -> 1145462 | AF49: =+AB49+AC49 -> 2069528
D50: 13. | E50: Saleable Steel Production (Mill Wise)
A51: =241830/AB56 -> 0.13175439 | E51: a) Bloom Caster (Transfer) 200x280 mm | F51: 21768 | G51: 36077 | H51: =+F51+G51 -> 57845 | I51: 43155.668 | J51: =SUM(H51:I51) -> 101000.67 | K51: 59289.8 | L51: =+J51+K51 -> 160290.47 | M51: 38786 | N51: =+L51+M51 -> 199076.47 | O51: 20264 | P51: =+K51+M51+O51 -> 118339.8 | Q51: =+N51+O51 -> 219340.47 | R51: 2702 | S51: =+Q51+R51 -> 222042.47 | T51: 31761 | U51: =+S51+T51 -> 253803.47 | V51: 46722 | W51: =+R51+T51+V51 -> 81185 | X51: =+U51+V51 -> 300525.47 | Y51: 29641 | Z51: =+X51+Y51 -> 330166.47 | AA51: 19842 | AB51: =+Z51+AA51 -> 350008.47 | AC51: 8025 | AD51: =+Y51+AA51+AC51 -> 57508 | AE51: =+W51+AD51 -> 138693 | AF51: =+AB51+AC51 -> 358033.47
E52: b) Billet Caster (Transfer) 150x150 mm Bloom | F52: 73040 | G52: 29860 | H52: =+F52+G52 -> 102900 | I52: 28297 | J52: =+H52+I52 -> 131197 | K52: 63899.25 | L52: =+J52+K52 -> 195096.25 | M52: 40971.8 | N52: =+L52+M52 -> 236068.05 | O52: 54648 | P52: =+K52+M52+O52 -> 159519.05 | Q52: =+N52+O52 -> 290716.05 | R52: 51102 | S52: =+Q52+R52 -> 341818.05 | T52: 50426 | U52: =+S52+T52 -> 392244.05 | V52: 70891.929 | W52: =+R52+T52+V52 -> 172419.93 | X52: =+U52+V52 -> 463135.98 | Y52: 78377.962 | Z52: =+X52+Y52 -> 541513.94 | AA52: 53239.636 | AB52: =+Z52+AA52 -> 594753.58 | AC52: 58416.328 | AD52: =+Y52+AA52+AC52 -> 190033.93 | AE52: =+W52+AD52 -> 362453.86 | AF52: =+AB52+AC52 -> 653169.91
E53: c) US Mill | F53: 0 | G53: 0 | H53: =+F53+G53 -> 0 | I53: 0 | J53: =+H53+I53 -> 0 | K53: 0 | L53: =+J53+K53 -> 0 | M53: 12459.891 | N53: =+L53+M53 -> 12459.891 | O53: 2335.96 | P53: =+K53+M53+O53 -> 14795.851 | Q53: =+N53+O53 -> 14795.851 | R53: 11735.993 | S53: =+Q53+R53 -> 26531.844 | T53: 5543.1142 | U53: =+S53+T53 -> 32074.958 | V53: 0 | W53: =+R53+T53+V53 -> 17279.107 | X53: =+U53+V53 -> 32074.958 | Y53: 16592.986 | Z53: =+X53+Y53 -> 48667.944 | AA53: 18479.346 | AB53: =+Z53+AA53 -> 67147.291 | AC53: 16189.673 | AD53: =+Y53+AA53+AC53 -> 51262.006 | AE53: =+W53+AD53 -> 68541.113 | AF53: =+AB53+AC53 -> 83336.964
E54: d) Bar Mill | F54: 8073.14 | G54: 43712 | H54: =+F54+G54 -> 51785.14 | I54: 32149.445 | J54: =+H54+I54 -> 83934.585 | K54: 24173.96 | L54: =+J54+K54 -> 108108.54 | M54: 61631.08 | N54: =+L54+M54 -> 169739.62 | O54: 29247.88 | P54: =+K54+M54+O54 -> 115052.92 | Q54: =+N54+O54 -> 198987.51 | R54: 61701.12 | S54: =+Q54+R54 -> 260688.62 | T54: 50406.14 | U54: =+S54+T54 -> 311094.77 | V54: 57486.36 | W54: =+R54+T54+V54 -> 169593.62 | X54: =+U54+V54 -> 368581.12 | Y54: 49884.96 | Z54: =+X54+Y54 -> 418466.09 | AA54: 61851.5 | AB54: =+Z54+AA54 -> 480317.59 | AC54: 52820.46 | AD54: =+Y54+AA54+AC54 -> 164556.92 | AE54: =+W54+AD54 -> 334150.54 | AF54: =+AB54+AC54 -> 533138.05
E55: e) WR Mill | F55: 14366.4 | G55: 17668 | H55: =+F55+G55 -> 32034.4 | I55: 31338.144 | J55: =+H55+I55 -> 63372.544 | K55: 32647.336 | L55: =+J55+K55 -> 96019.88 | M55: 37622.25 | N55: =+L55+M55 -> 133642.13 | O55: 33300.09 | P55: =+K55+M55+O55 -> 103569.68 | Q55: =+N55+O55 -> 166942.22 | R55: 26479.44 | S55: =+Q55+R55 -> 193421.66 | T55: 41161.95 | U55: =+S55+T55 -> 234583.61 | V55: 35411.49 | W55: =+R55+T55+V55 -> 103052.88 | X55: =+U55+V55 -> 269995.1 | Y55: 35558.46 | Z55: =+X55+Y55 -> 305553.56 | AA55: 37680.21 | AB55: =+Z55+AA55 -> 343233.77 | AC55: 33527.79 | AD55: =+Y55+AA55+AC55 -> 106766.46 | AE55: =+W55+AD55 -> 209819.34 | AF55: =+AB55+AC55 -> 376761.56
E56: TOTAL | F56: =SUM(F51:F55) -> 117247.54 | G56: =SUM(G51:G55) -> 127317 | H56: =+F56+G56 -> 244564.54 | I56: =SUM(I51:I55) -> 134940.26 | J56: =+H56+I56 -> 379504.8 | K56: =SUM(K51:K55) -> 180010.35 | L56: =+J56+K56 -> 559515.14 | M56: =SUM(M51:M55) -> 191471.02 | N56: =+L56+M56 -> 750986.16 | O56: =SUM(O51:O55) -> 139795.93 | P56: =+Q56-J56 -> 511277.3 | Q56: =+N56+O56 -> 890782.09 | R56: =SUM(R51:R55) -> 153720.55 | S56: =+Q56+R56 -> 1044502.6 | T56: =SUM(T51:T55) -> 179298.2 | U56: =+S56+T56 -> 1223800.9 | V56: =SUM(V51:V55) -> 210511.78 | W56: =SUM(W51:W55) -> 543530.54 | X56: =SUM(X51:X55) -> 1434312.6 | Y56: =SUM(Y51:Y55) -> 210055.37 | Z56: =SUM(Z51:Z55) -> 1644368 | AA56: =SUM(AA51:AA55) -> 191092.69 | AB56: =SUM(AB51:AB55) -> 1835460.7 | AC56: =SUM(AC51:AC55) -> 168979.25 | AD56: =SUM(AD51:AD55) -> 570127.31 | AE56: =+W56+AD56 -> 1113657.8 | AF56: =SUM(AF51:AF55) -> 2004439.9
D57: FOR THE YEAR 2019-20
D58: SL. NO. | E58: I T E M S | F58: Apr | G58: May | H58: 2M | I58: Jun | J58: Q-I | K58: Jul | L58: 4M | M58: Aug | N58: 5M | O58: Sep | P58: Q-II | Q58: H-I | R58: Oct | S58: 7M | T58: Nov | U58: 8M | V58: Dec | W58: Q-III | X58: 9M | Y58: Jan | Z58: 10M | AA58: Feb | AB58: =+AB3 -> 11M | AC58: Mar | AD58: Q-IV | AE58: H-II | AF58: 12M
D59: 16. | E59: DESPATCH (As per CENVAT report from Finance) | H59: =38560+6105-6101 -> 38564
E60: a-i) Saleable Steel (Mill-wise sale type-wise)
E61: WR MILL
E62: CMO DIR | H62: =SUM(F62:G62) -> 0 | J62: =SUM(H62:I62) -> 0 | L62: =SUM(J62:K62) -> 0 | M62: 9662.56 | N62: =SUM(L62:M62) -> 9662.56 | O62: 13230.59 | P62: =+K62+M62+O62 -> 22893.15 | Q62: =+N62+O62 -> 22893.15 | R62: 12733.49 | S62: =SUM(Q62:R62) -> 35626.64 | T62: 22803.52 | U62: =SUM(S62:T62) -> 58430.16 | V62: =314.01+22799.721 -> 23113.731 | W62: =+R62+T62+V62 -> 58650.741 | X62: =+U62+V62 -> 81543.891 | Y62: =29104.208-61.84 -> 29042.368 | Z62: =SUM(X62:Y62) -> 110586.26 | AA62: 18917.775 | AB62: =SUM(Z62:AA62) -> 129504.03 | AC62: 11485.228 | AD62: =+Y62+AA62+AC62 -> 59445.371 | AE62: =+W62+AD62 -> 118096.11 | AF62: =+AB62+AC62 -> 140989.26
E63: MKTG DIR (DEF) | H63: =SUM(F63:G63) -> 0 | J63: =SUM(H63:I63) -> 0 | L63: =SUM(J63:K63) -> 0 | M63: 48.02 | N63: =SUM(L63:M63) -> 48.02 | O63: 0 | P63: =+K63+M63+O63 -> 48.02 | Q63: =+N63+O63 -> 48.02 | R63: 0 | S63: =SUM(Q63:R63) -> 48.02 | T63: 0 | U63: =SUM(S63:T63) -> 48.02 | V63: 0 | W63: =+R63+T63+V63 -> 0 | X63: =+U63+V63 -> 48.02 | Y63: 0 | Z63: =SUM(X63:Y63) -> 48.02 | AA63: 0 | AB63: =SUM(Z63:AA63) -> 48.02 | AC63: 0 | AD63: =+Y63+AA63+AC63 -> 0 | AE63: =+W63+AD63 -> 0 | AF63: =+AB63+AC63 -> 48.02
E64: CMO EXP | H64: =SUM(F64:G64) -> 0 | J64: =SUM(H64:I64) -> 0 | L64: =SUM(J64:K64) -> 0 | M64: 367.08 | N64: =SUM(L64:M64) -> 367.08 | O64: 7596.54 | P64: =+K64+M64+O64 -> 7963.62 | Q64: =+N64+O64 -> 7963.62 | R64: 6079.65 | S64: =SUM(Q64:R64) -> 14043.27 | T64: 6418.22 | U64: =SUM(S64:T64) -> 20461.49 | V64: =62.94+5279.59 -> 5342.53 | W64: =+R64+T64+V64 -> 17840.4 | X64: =+U64+V64 -> 25804.02 | Y64: 10368.701 | Z64: =SUM(X64:Y64) -> 36172.721 | AA64: 2650.032 | AB64: =SUM(Z64:AA64) -> 38822.753 | AC64: 11169.257 | AD64: =+Y64+AA64+AC64 -> 24187.99 | AE64: =+W64+AD64 -> 42028.39 | AF64: =+AB64+AC64 -> 49992.01
E65: CMO SYD | H65: =SUM(F65:G65) -> 0 | J65: =SUM(H65:I65) -> 0 | L65: =SUM(J65:K65) -> 0 | M65: 20975.07 | N65: =SUM(L65:M65) -> 20975.07 | O65: 12510.2 | P65: =+K65+M65+O65 -> 33485.27 | Q65: =+N65+O65 -> 33485.27 | R65: 10129.95 | S65: =SUM(Q65:R65) -> 43615.22 | T65: 10369.43 | U65: =SUM(S65:T65) -> 53984.65 | V65: =785.46+7194.92 -> 7980.38 | W65: =+R65+T65+V65 -> 28479.76 | X65: =+U65+V65 -> 61965.03 | Y65: 237.45 | Z65: =SUM(X65:Y65) -> 62202.48 | AA65: 10077.649 | AB65: =SUM(Z65:AA65) -> 72280.129 | AC65: 8329.093 | AD65: =+Y65+AA65+AC65 -> 18644.192 | AE65: =+W65+AD65 -> 47123.952 | AF65: =+AB65+AC65 -> 80609.222
E66: TOTAL | F66: =SUM(F62:F65) -> 0 | G66: =SUM(G62:G65) -> 0 | H66: =SUM(H62:H65) -> 0 | I66: =SUM(I62:I65) -> 0 | J66: =SUM(J62:J65) -> 0 | K66: =SUM(K62:K65) -> 0 | L66: =SUM(L62:L65) -> 0 | M66: =SUM(M62:M65) -> 31052.73 | ... AF66: =SUM(AF62:AF65) -> 271638.51
E67: BAR MILL
E68: CMO DIR | H68: =SUM(F68:G68) -> 0 | J68: =SUM(H68:I68) -> 0 | L68: =SUM(J68:K68) -> 0 | M68: 409.2 | N68: =SUM(L68:M68) -> 409.2 | O68: 2476.58 | P68: =+K68+M68+O68 -> 2885.78 | Q68: =+N68+O68 -> 2885.78 | R68: 3895.41 | S68: =SUM(Q68:R68) -> 6781.19 | T68: 3907.64 | U68: =SUM(S68:T68) -> 10688.83 | V68: =349.2+8325.53 -> 8674.73 | W68: =+R68+T68+V68 -> 16477.78 | X68: =+U68+V68 -> 19363.56 | Y68: 17277.715 | Z68: =SUM(X68:Y68) -> 36641.275 | AA68: 16984.76 | AB68: =SUM(Z68:AA68) -> 53626.035 | AC68: 5435.11 | AD68: =+Y68+AA68+AC68 -> 39697.585 | AE68: =+W68+AD68 -> 56175.365 | AF68: =+AB68+AC68 -> 59061.145
E69: MKTG DIR (DEF) | H69: =SUM(F69:G69) -> 0 | J69: =SUM(H69:I69) -> 0 | L69: =SUM(J69:K69) -> 0 | M69: 0 | N69: =SUM(L69:M69) -> 0 | O69: 0 | P69: =+K69+M69+O69 -> 0 | Q69: =+N69+O69 -> 0 | R69: 0 | S69: =SUM(Q69:R69) -> 0 | T69: 0 | U69: =SUM(S69:T69) -> 0 | V69: 0 | W69: =+R69+T69+V69 -> 0 | X69: =+U69+V69 -> 0 | Y69: 0 | Z69: =SUM(X69:Y69) -> 0 | AA69: 0 | AB69: =SUM(Z69:AA69) -> 0 | AC69: 0 | AD69: =+Y69+AA69+AC69 -> 0 | AE69: =+W69+AD69 -> 0 | AF69: =+AB69+AC69 -> 0
E70: CMO EXP | H70: =SUM(F70:G70) -> 0 | J70: =SUM(H70:I70) -> 0 | L70: =SUM(J70:K70) -> 0 | M70: 0 | N70: =SUM(L70:M70) -> 0 | O70: 0 | P70: =+K70+M70+O70 -> 0 | Q70: =+N70+O70 -> 0 | R70: 0 | S70: =SUM(Q70:R70) -> 0 | T70: 0 | U70: =SUM(S70:T70) -> 0 | V70: 0 | W70: =+R70+T70+V70 -> 0 | X70: =+U70+V70 -> 0 | Y70: 0 | Z70: =SUM(X70:Y70) -> 0 | AA70: 0 | AB70: =SUM(Z70:AA70) -> 0 | AC70: 0 | AD70: =+Y70+AA70+AC70 -> 0 | AE70: =+W70+AD70 -> 0 | AF70: =+AB70+AC70 -> 0
E71: CMO SYD | H71: =SUM(F71:G71) -> 0 | J71: =SUM(H71:I71) -> 0 | L71: =SUM(J71:K71) -> 0 | M71: 62529.34 | N71: =SUM(L71:M71) -> 62529.34 | O71: 29950.91 | P71: =+K71+M71+O71 -> 92480.25 | Q71: =+N71+O71 -> 92480.25 | R71: 51343.84 | S71: =SUM(Q71:R71) -> 143824.09 | T71: 47429.37 | U71: =SUM(S71:T71) -> 191253.46 | V71: =5827.25+39829.546 -> 45656.796 | W71: =+R71+T71+V71 -> 144430.01 | X71: =+U71+V71 -> 236910.26 | Y71: 35678.918 | Z71: =SUM(X71:Y71) -> 272589.17 | AA71: 41652.733 | AB71: =SUM(Z71:AA71) -> 314241.91 | AC71: 48684.705 | AD71: =+Y71+AA71+AC71 -> 126016.36 | AE71: =+W71+AD71 -> 270446.36 | AF71: =+AB71+AC71 -> 362926.61
E72: TOTAL | F72: =SUM(F68:F71) -> 0 | G72: =SUM(G68:G71) -> 0 | H72: =SUM(H68:H71) -> 0 | I72: =SUM(I68:I71) -> 0 | J72: =SUM(J68:J71) -> 0 | K72: =SUM(K68:K71) -> 0 | L72: =SUM(L68:L71) -> 0 | M72: =SUM(M68:M71) -> 62938.54 | ... AF72: =SUM(AF68:AF71) -> 421987.76
E73: US MILL
E74: CMO DIR | H74: =SUM(F74:G74) -> 0 | J74: =SUM(H74:I74) -> 0 | L74: =SUM(J74:K74) -> 0 | M74: 2958.22 | N74: =SUM(L74:M74) -> 2958.22 | O74: 4292.47 | P74: =+K74+M74+O74 -> 7250.69 | Q74: =+N74+O74 -> 7250.69 | R74: 5049.98 | S74: =SUM(Q74:R74) -> 12300.67 | T74: 5245.54 | U74: =SUM(S74:T74) -> 17546.21 | V74: =410.86+2509.4 -> 2920.26 | W74: =+R74+T74+V74 -> 13215.78 | X74: =+U74+V74 -> 20466.47 | Y74: 5324.778 | Z74: =SUM(X74:Y74) -> 25791.248 | AA74: 2842.179 | AB74: =SUM(Z74:AA74) -> 28633.427 | AC74: 3105.16 | AD74: =+Y74+AA74+AC74 -> 11272.117 | AE74: =+W74+AD74 -> 24487.897 | AF74: =+AB74+AC74 -> 31738.587
E75: MKTG DIR (DEF) | H75: =SUM(F75:G75) -> 0 | J75: =SUM(H75:I75) -> 0 | L75: =SUM(J75:K75) -> 0 | M75: 0 | N75: =SUM(L75:M75) -> 0 | O75: 0 | P75: =+K75+M75+O75 -> 0 | Q75: =+N75+O75 -> 0 | R75: 0 | S75: =SUM(Q75:R75) -> 0 | T75: 0 | U75: =SUM(S75:T75) -> 0 | V75: 0 | W75: =+R75+T75+V75 -> 0 | X75: =+U75+V75 -> 0 | Y75: 0 | Z75: =SUM(X75:Y75) -> 0 | AA75: 0 | AB75: =SUM(Z75:AA75) -> 0 | AC75: 0 | AD75: =+Y75+AA75+AC75 -> 0 | AE75: =+W75+AD75 -> 0 | AF75: =+AB75+AC75 -> 0
E76: CMO EXP | H76: =SUM(F76:G76) -> 0 | J76: =SUM(H76:I76) -> 0 | L76: =SUM(J76:K76) -> 0 | M76: 0 | N76: =SUM(L76:M76) -> 0 | O76: 0 | P76: =+K76+M76+O76 -> 0 | Q76: =+N76+O76 -> 0 | R76: 0 | S76: =SUM(Q76:R76) -> 0 | T76: 0 | U76: =SUM(S76:T76) -> 0 | V76: 24.41 | W76: =+R76+T76+V76 -> 24.41 | X76: =+U76+V76 -> 24.41 | Y76: 0 | Z76: =SUM(X76:Y76) -> 24.41 | AA76: 55.92 | AB76: =SUM(Z76:AA76) -> 80.33 | AC76: 0 | AD76: =+Y76+AA76+AC76 -> 55.92 | AE76: =+W76+AD76 -> 80.33 | AF76: =+AB76+AC76 -> 80.33
E77: CMO SYD | H77: =SUM(F77:G77) -> 0 | J77: =SUM(H77:I77) -> 0 | L77: =SUM(J77:K77) -> 0 | M77: 10350.16 | N77: =SUM(L77:M77) -> 10350.16 | O77: 4632.51 | P77: =+K77+M77+O77 -> 14982.67 | Q77: =+N77+O77 -> 14982.67 | R77: 3312.85 | S77: =SUM(Q77:R77) -> 18295.52 | T77: 5133.47 | U77: =SUM(S77:T77) -> 23428.99 | V77: 1928.39 | W77: =+R77+T77+V77 -> 10374.71 | X77: =+U77+V77 -> 25357.38 | Y77: 7005.001 | Z77: =SUM(X77:Y77) -> 32362.381 | AA77: 10789.968 | AB77: =SUM(Z77:AA77) -> 43152.349 | AC77: 13108.446 | AD77: =+Y77+AA77+AC77 -> 30903.415 | AE77: =+W77+AD77 -> 41278.125 | AF77: =+AB77+AC77 -> 56260.795
B78: =46227+13099 -> 59326 | E78: TOTAL | F78: =SUM(F74:F77) -> 0 | G78: =SUM(G74:G77) -> 0 | H78: =SUM(H74:H77) -> 0 | I78: =SUM(I74:I77) -> 0 | J78: =SUM(J74:J77) -> 0 | K78: =SUM(K74:K77) -> 0 | L78: =SUM(L74:L77) -> 0 | M78: =SUM(M74:M77) -> 13308.38 | ... AF78: =SUM(AF74:AF77) -> 88079.712
B79: 41574 | E79: SEMIS
B80: =SUM(B78:B79) -> 100900 | E80: CMO DIR | H80: =SUM(F80:G80) -> 0 | J80: =SUM(H80:I80) -> 0 | L80: =SUM(J80:K80) -> 0 | M80: 19328.31 | N80: =SUM(L80:M80) -> 19328.31 | O80: 27486.43 | P80: =+K80+M80+O80 -> 46814.74 | Q80: =+N80+O80 -> 46814.74 | R80: 29307.74 | S80: =SUM(Q80:R80) -> 76122.48 | T80: 28391.09 | U80: =SUM(S80:T80) -> 104513.57 | V80: =2139.14+26442.881 -> 28582.021 | W80: =+R80+T80+V80 -> 86280.851 | X80: =+U80+V80 -> 133095.59 | Y80: 43082.955 | Z80: =SUM(X80:Y80) -> 176178.55 | AA80: 23399.195 | AB80: =SUM(Z80:AA80) -> 199577.74 | AC80: 11134.412 | AD80: =+Y80+AA80+AC80 -> 77616.562 | AE80: =+W80+AD80 -> 163897.41 | AF80: =+AB80+AC80 -> 210712.15
E81: MKTG DIR (ASSORTED-DEF)+ Non rollable BB Scrap | H81: =SUM(F81:G81) -> 0 | J81: =SUM(H81:I81) -> 0 | L81: =SUM(J81:K81) -> 0 | M81: 1171.72 | N81: =SUM(L81:M81) -> 1171.72 | O81: 4125.85 | P81: =+K81+M81+O81 -> 5297.57 | Q81: =+N81+O81 -> 5297.57 | R81: =2017.82+1336.38 -> 3354.2 | S81: =SUM(Q81:R81) -> 8651.77 | T81: =2099.27+254.78 -> 2354.05 | U81: =SUM(S81:T81) -> 11005.82 | V81: 3697.62 | W81: =+R81+T81+V81 -> 9405.87 | X81: =+U81+V81 -> 14703.44 | Y81: =2164.93+1496.2 -> 3661.13 | Z81: =SUM(X81:Y81) -> 18364.57 | AA81: 298.61 | AB81: =SUM(Z81:AA81) -> 18663.18 | AC81: 999.3 | AD81: =+Y81+AA81+AC81 -> 4959.04 | AE81: =+W81+AD81 -> 14364.91 | AF81: =+AB81+AC81 -> 19662.48
E82: CMO SYD | H82: =SUM(F82:G82) -> 0 | J82: =SUM(H82:I82) -> 0 | L82: =SUM(J82:K82) -> 0 | M82: 1119.74 | N82: =SUM(L82:M82) -> 1119.74 | O82: 2955.32 | P82: =+K82+M82+O82 -> 4075.06 | Q82: =+N82+O82 -> 4075.06 | R82: 4628.89 | S82: =SUM(Q82:R82) -> 8703.95 | T82: 7369.99 | U82: =SUM(S82:T82) -> 16073.94 | V82: =595.31+6895.522 -> 7490.832 | W82: =+R82+T82+V82 -> 19489.712 | X82: =+U82+V82 -> 23564.772 | Y82: 6502.523 | Z82: =SUM(X82:Y82) -> 30067.295 | AA82: 27861.385 | AB82: =SUM(Z82:AA82) -> 57928.68 | AC82: 9231.865 | AD82: =+Y82+AA82+AC82 -> 43595.773 | AE82: =+W82+AD82 -> 63085.485 | AF82: =+AB82+AC82 -> 67160.545
E83: IPT | H83: =SUM(F83:G83) -> 0 | J83: =SUM(H83:I83) -> 0 | L83: =SUM(J83:K83) -> 0 | M83: 0 | N83: =SUM(L83:M83) -> 0 | O83: 0 | P83: =+K83+M83+O83 -> 0 | Q83: =+N83+O83 -> 0 | R83: 0 | S83: =SUM(Q83:R83) -> 0 | T83: 0 | U83: =SUM(S83:T83) -> 0 | V83: 0 | W83: =+R83+T83+V83 -> 0 | X83: =+U83+V83 -> 0 | Y83: 545.92 | Z83: =SUM(X83:Y83) -> 545.92 | AA83: 2180.354 | AB83: =SUM(Z83:AA83) -> 2726.274 | AC83: 2833.695 | AD83: =+Y83+AA83+AC83 -> 5559.969 | AE83: =+W83+AD83 -> 5559.969 | AF83: =+AB83+AC83 -> 5559.969
B84: =+B78/B80*100 -> 58.796829 | E84: CMO EXPORT | H84: =SUM(F84:G84) -> 0 | J84: =SUM(H84:I84) -> 0 | L84: =SUM(J84:K84) -> 0 | M84: 45590.26 | N84: =SUM(L84:M84) -> 45590.26 | O84: 45646.24 | P84: =+K84+M84+O84 -> 91236.5 | Q84: =+N84+O84 -> 91236.5 | R84: 39619.6 | S84: =SUM(Q84:R84) -> 130856.1 | T84: 48823.54 | U84: =SUM(S84:T84) -> 179679.64 | V84: =19255.9+50901.9729999999 -> 70157.873 | W84: =+R84+T84+V84 -> 158601.01 | X84: =+U84+V84 -> 249837.51 | Y84: 54434.999 | Z84: =SUM(X84:Y84) -> 304272.51 | AA84: 19341.119 | AB84: =SUM(Z84:AA84) -> 323613.63 | AC84: 21235.675 | AD84: =+Y84+AA84+AC84 -> 95011.793 | AE84: =+W84+AD84 -> 253612.81 | AF84: =+AB84+AC84 -> 344849.31
E85: TOTAL | F85: =SUM(F80:F84) -> 0 | G85: =SUM(G80:G84) -> 0 | H85: =SUM(H80:H84) -> 0 | I85: =SUM(I80:I84) -> 0 | J85: =SUM(J80:J84) -> 0 | K85: =SUM(K80:K84) -> 0 | L85: =SUM(L80:L84) -> 0 | M85: =SUM(M80:M84) -> 67210.03 | ... AF85: =SUM(AF80:AF84) -> 647944.45
E86: Saleable Steel (Total sale type-wise) | F86: =+F87+F88+F89+F90+F91 -> 0 | G86: =+G87+G88+G89+G90+G91 -> 0 | H86: =+F86+G86 -> 0 | I86: =+I87+I88+I89+I90+I91 -> 0 | J86: =+H86+I86 -> 0 | K86: =+K87+K88+K89+K90+K91 -> 0 | L86: =+J86+K86 -> 0 | M86: =+M87+M88+M89+M90+M91 -> 174509.68 | N86: =+L86+M86 -> 174509.68 | O86: =+O87+O88+O89+O90+O91 -> 154903.64 | P86: =+K86+M86+O86 -> 329413.32 | Q86: =+N86+O86 -> 329413.32 | R86: =+R87+R88+R89+R90+R91 -> 169455.6 | S86: =+Q86+R86 -> 498868.92 | T86: =+T87+T88+T89+T90+T91 -> 188245.86 | U86: =+S86+T86 -> 687114.78 | V86: =+V87+V88+V89+V90+V91 -> 205569.57 | W86: =+R86+T86+V86 -> 563271.03 | X86: =+U86+V86 -> 892684.35 | Y86: =+Y87+Y88+Y89+Y90+Y91 -> 213162.46 | Z86: =+X86+Y86 -> 1105846.8 | AA86: =+AA87+AA88+AA89+AA90+AA91 -> 177051.68 | AB86: =+Z86+AA86 -> 1282898.5 | AC86: =+AC87+AC88+AC89+AC90+AC91 -> 146751.95 | AD86: =+Y86+AA86+AC86 -> 536966.08 | AE86: =+W86+AD86 -> 1100237.1 | AF86: =+AB86+AC86 -> 1429650.4
E87: CMO DIR | F87: =+F62+F68+F74+F80 -> 0 | G87: =+G62+G68+G74+G80 -> 0 | H87: =SUM(F87:G87) -> 0 | I87: =+I62+I68+I74+I80 -> 0 | J87: =SUM(H87:I87) -> 0 | K87: =+K62+K68+K74+K80 -> 0 | L87: =SUM(J87:K87) -> 0 | M87: =+M62+M68+M74+M80 -> 32358.29 | N87: =SUM(L87:M87) -> 32358.29 | O87: =+O62+O68+O74+O80 -> 47486.07 | P87: =+K87+M87+O87 -> 79844.36 | Q87: =+N87+O87 -> 79844.36 | R87: =+R62+R68+R74+R80 -> 50986.62 | S87: =+Q87+R87 -> 130830.98 | T87: =+T62+T68+T74+T80 -> 60347.79 | U87: =+S87+T87 -> 191178.77 | V87: =+V62+V68+V74+V80 -> 63290.742 | W87: =+R87+T87+V87 -> 174625.15 | X87: =+U87+V87 -> 254469.51 | Y87: =+Y62+Y68+Y74+Y80 -> 94727.816 | Z87: =+X87+Y87 -> 349197.33 | AA87: =+AA62+AA68+AA74+AA80 -> 62143.909 | AB87: =+Z87+AA87 -> 411341.24 | AC87: =+AC62+AC68+AC74+AC80 -> 31159.91 | AD87: =+Y87+AA87+AC87 -> 188031.64 | AE87: =+W87+AD87 -> 362656.79 | AF87: =+AB87+AC87 -> 442501.15
E88: MKTG DIR (DEF) | F88: =+F63+F69+F75+F81 -> 0 | G88: =+G63+G69+G75+G81 -> 0 | H88: =SUM(F88:G88) -> 0 | I88: =+I63+I69+I75+I81 -> 0 | J88: =SUM(H88:I88) -> 0 | K88: =+K63+K69+K75+K81 -> 0 | L88: =SUM(J88:K88) -> 0 | M88: =+M63+M69+M75+M81 -> 1219.74 | N88: =SUM(L88:M88) -> 1219.74 | O88: =+O63+O69+O75+O81 -> 4125.85 | P88: =+K88+M88+O88 -> 5345.59 | Q88: =+N88+O88 -> 5345.59 | R88: =+R63+R69+R75+R81 -> 3354.2 | S88: =+Q88+R88 -> 8699.79 | T88: =+T63+T69+T75+T81 -> 2354.05 | U88: =+S88+T88 -> 11053.84 | V88: =+V63+V69+V75+V81 -> 3697.62 | W88: =+R88+T88+V88 -> 9405.87 | X88: =+U88+V88 -> 14751.46 | Y88: =+Y63+Y69+Y75+Y81 -> 3661.13 | Z88: =+X88+Y88 -> 18412.59 | AA88: =+AA63+AA69+AA75+AA81 -> 298.61 | AB88: =+Z88+AA88 -> 18711.2 | AC88: =+AC63+AC69+AC75+AC81 -> 999.3 | AD88: =+Y88+AA88+AC88 -> 4959.04 | AE88: =+W88+AD88 -> 14364.91 | AF88: =+AB88+AC88 -> 19710.5
E89: CMO SYD | F89: =+F65+F71+F77+F82 -> 0 | G89: =+G65+G71+G77+G82 -> 0 | H89: =SUM(F89:G89) -> 0 | I89: =+I65+I71+I77+I82 -> 0 | J89: =SUM(H89:I89) -> 0 | K89: =+K65+K71+K77+K82 -> 0 | L89: =SUM(J89:K89) -> 0 | M89: =+M65+M71+M77+M82 -> 94974.31 | N89: =SUM(L89:M89) -> 94974.31 | O89: =+O65+O71+O77+O82 -> 50048.94 | P89: =+K89+M89+O89 -> 145023.25 | Q89: =+N89+O89 -> 145023.25 | R89: =+R65+R71+R77+R82 -> 69415.53 | S89: =+Q89+R89 -> 214438.78 | T89: =+T65+T71+T77+T82 -> 70302.26 | U89: =+S89+T89 -> 284741.04 | V89: =+V65+V71+V77+V82 -> 63056.398 | W89: =+R89+T89+V89 -> 202774.19 | X89: =+U89+V89 -> 347797.44 | Y89: =+Y65+Y71+Y77+Y82 -> 49423.892 | Z89: =+X89+Y89 -> 397221.33 | AA89: =+AA65+AA71+AA77+AA82 -> 90381.735 | AB89: =+Z89+AA89 -> 487603.06 | AC89: =+AC65+AC71+AC77+AC82 -> 79354.109 | AD89: =+Y89+AA89+AC89 -> 219159.74 | AE89: =+W89+AD89 -> 421933.92 | AF89: =+AB89+AC89 -> 566957.17
E90: IPT | F90: =+F83 -> 0 | G90: =+G83 -> 0 | H90: =SUM(F90:G90) -> 0 | I90: =+I83 -> 0 | J90: =SUM(H90:I90) -> 0 | K90: =+K83 -> 0 | L90: =SUM(J90:K90) -> 0 | M90: =+M83 -> 0 | N90: =SUM(L90:M90) -> 0 | O90: =+O83 -> 0 | P90: =+K90+M90+O90 -> 0 | Q90: =+N90+O90 -> 0 | R90: =+R83 -> 0 | S90: =+Q90+R90 -> 0 | T90: =+T83 -> 0 | U90: =+S90+T90 -> 0 | V90: =+V83 -> 0 | W90: =+R90+T90+V90 -> 0 | X90: =+U90+V90 -> 0 | Y90: =+Y83 -> 545.92 | Z90: =+X90+Y90 -> 545.92 | AA90: =+AA83 -> 2180.354 | AB90: =+Z90+AA90 -> 2726.274 | AC90: =+AC83 -> 2833.695 | AD90: =+Y90+AA90+AC90 -> 5559.969 | AE90: =+W90+AD90 -> 5559.969 | AF90: =+AB90+AC90 -> 5559.969
E91: EXPORT DIR | F91: =+F64+F70+F76+F84 -> 0 | G91: =+G64+G70+G76+G84 -> 0 | H91: =SUM(F91:G91) -> 0 | I91: =+I64+I70+I76+I84 -> 0 | J91: =SUM(H91:I91) -> 0 | K91: =+K64+K70+K76+K84 -> 0 | L91: =SUM(J91:K91) -> 0 | M91: =+M64+M70+M76+M84 -> 45957.34 | N91: =SUM(L91:M91) -> 45957.34 | O91: =+O64+O70+O76+O84 -> 53242.78 | P91: =+K91+M91+O91 -> 99200.12 | Q91: =+N91+O91 -> 99200.12 | R91: =+R64+R70+R76+R84 -> 45699.25 | S91: =SUM(Q91:R91) -> 144899.37 | T91: =+T64+T70+T76+T84 -> 55241.76 | U91: =+S91+T91 -> 200141.13 | V91: =+V64+V70+V76+V84 -> 75524.813 | W91: =+R91+T91+V91 -> 176465.82 | X91: =+U91+V91 -> 275665.94 | Y91: =+Y64+Y70+Y76+Y84 -> 64803.7 | Z91: =+X91+Y91 -> 340469.64 | AA91: =+AA64+AA70+AA76+AA84 -> 22047.071 | AB91: =+Z91+AA91 -> 362516.71 | AC91: =+AC64+AC70+AC76+AC84 -> 32404.932 | AD91: =+Y91+AA91+AC91 -> 119255.7 | AE91: =+W91+AD91 -> 295721.53 | AF91: =+AB91+AC91 -> 394921.65
E92: % DIRECT OF TOTAL DESPATCH (INCL EXPORT) | F92: =+((F87+F88+F91)/F86)*100 -> #DIV/0! | G92: =+((G87+G88+G91)/G86)*100 -> #DIV/0! | H92: =+((H87+H88+H91)/H86)*100 -> #DIV/0! | I92: =+((I87+I88+I91)/I86)*100 -> #DIV/0! | J92: =+((J87+J88+J91)/J86)*100 -> #DIV/0! | K92: =+((K87+K88+K91)/K86)*100 -> #DIV/0! | L92: =+((L87+L88+L91)/L86)*100 -> #DIV/0! | M92: =+((M87+M88+M91)/M86)*100 -> 45.57648 | ... AF92: =+((AF87+AF88+AF91)/AF86)*100 -> 59.954047
E93: a-ii) Saleable Steel (mill-wise)
A94: =747517+135000 -> 882517 | E94: WR MILL | F94: =+F66 -> 0 | G94: =+G66 -> 0 | H94: =SUM(F94:G94) -> 0 | I94: =+I66 -> 0 | J94: =SUM(H94:I94) -> 0 | K94: =+K66 -> 0 | L94: =SUM(J94:K94) -> 0 | M94: =+M66 -> 31052.73 | N94: =SUM(L94:M94) -> 31052.73 | O94: =+O66 -> 33337.33 | P94: =+K94+M94+O94 -> 64390.06 | Q94: =+N94+O94 -> 64390.06 | R94: =+R66 -> 28943.09 | S94: =SUM(Q94:R94) -> 93333.15 | T94: =+T66 -> 39591.17 | U94: =SUM(S94:T94) -> 132924.32 | V94: =+V66 -> 36436.641 | W94: =+R94+T94+V94 -> 104970.9 | X94: =+U94+V94 -> 169360.96 | Y94: =+Y66 -> 39648.519 | Z94: =SUM(X94:Y94) -> 209009.48 | AA94: =+AA66 -> 31645.456 | AB94: =SUM(Z94:AA94) -> 240654.94 | AC94: =+AC66 -> 30983.578 | AD94: =+Y94+AA94+AC94 -> 102277.55 | AE94: =+W94+AD94 -> 207248.45 | AF94: =+AB94+AC94 -> 271638.51
E95: BAR MILL | F95: =+F72 -> 0 | G95: =+G72 -> 0 | H95: =SUM(F95:G95) -> 0 | I95: =+I72 -> 0 | J95: =SUM(H95:I95) -> 0 | K95: =+K72 -> 0 | L95: =SUM(J95:K95) -> 0 | M95: =+M72 -> 62938.54 | N95: =SUM(L95:M95) -> 62938.54 | O95: =+O72 -> 32427.49 | P95: =+K95+M95+O95 -> 95366.03 | Q95: =+N95+O95 -> 95366.03 | R95: =+R72 -> 55239.25 | S95: =SUM(Q95:R95) -> 150605.28 | T95: =+T72 -> 51337.01 | U95: =SUM(S95:T95) -> 201942.29 | V95: =+V72 -> 54331.526 | W95: =+R95+T95+V95 -> 160907.79 | X95: =+U95+V95 -> 256273.82 | Y95: =+Y72 -> 52956.633 | Z95: =SUM(X95:Y95) -> 309230.45 | AA95: =+AA72 -> 58637.493 | AB95: =SUM(Z95:AA95) -> 367867.94 | AC95: =+AC72 -> 54119.815 | AD95: =+Y95+AA95+AC95 -> 165713.94 | AE95: =+W95+AD95 -> 326621.73 | AF95: =+AB95+AC95 -> 421987.76
E96: US MILL | F96: =+F78 -> 0 | G96: =+G78 -> 0 | H96: =SUM(F96:G96) -> 0 | I96: =+I78 -> 0 | J96: =SUM(H96:I96) -> 0 | K96: =+K78 -> 0 | L96: =SUM(J96:K96) -> 0 | M96: =+M78 -> 13308.38 | N96: =SUM(L96:M96) -> 13308.38 | O96: =+O78 -> 8924.98 | P96: =+K96+M96+O96 -> 22233.36 | Q96: =+N96+O96 -> 22233.36 | R96: =+R78 -> 8362.83 | S96: =SUM(Q96:R96) -> 30596.19 | T96: =+T78 -> 10379.01 | U96: =SUM(S96:T96) -> 40975.2 | V96: =+V78 -> 4873.06 | W96: =+R96+T96+V96 -> 23614.9 | X96: =+U96+V96 -> 45848.26 | Y96: =+Y78 -> 12329.779 | Z96: =SUM(X96:Y96) -> 58178.039 | AA96: =+AA78 -> 13688.067 | AB96: =SUM(Z96:AA96) -> 71866.106 | AC96: =+AC78 -> 16213.606 | AD96: =+Y96+AA96+AC96 -> 42231.452 | AE96: =+W96+AD96 -> 65846.352 | AF96: =+AB96+AC96 -> 88079.712
E97: SEMIS | F97: =+F85 -> 0 | G97: =+G85 -> 0 | H97: =SUM(F97:G97) -> 0 | I97: =+I85 -> 0 | J97: =SUM(H97:I97) -> 0 | K97: =+K85 -> 0 | L97: =SUM(J97:K97) -> 0 | M97: =+M85 -> 67210.03 | N97: =SUM(L97:M97) -> 67210.03 | O97: =+O85 -> 80213.84 | P97: =+K97+M97+O97 -> 147423.87 | Q97: =+N97+O97 -> 147423.87 | R97: =+R85 -> 76910.43 | S97: =SUM(Q97:R97) -> 224334.3 | T97: =+T85 -> 86938.67 | U97: =SUM(S97:T97) -> 311272.97 | V97: =+V85 -> 109928.35 | W97: =+R97+T97+V97 -> 273777.45 | X97: =+U97+V97 -> 421201.32 | Y97: =+Y85 -> 108227.53 | Z97: =SUM(X97:Y97) -> 529428.84 | AA97: =+AA85 -> 73080.663 | AB97: =SUM(Z97:AA97) -> 602509.51 | AC97: =+AC85 -> 45434.947 | AD97: =+Y97+AA97+AC97 -> 226743.14 | AE97: =+W97+AD97 -> 500520.58 | AF97: =+AB97+AC97 -> 647944.45
E98: TOTAL | F98: =SUM(F94:F97) -> 0 | G98: =SUM(G94:G97) -> 0 | H98: =SUM(H94:H97) -> 0 | I98: =SUM(I94:I97) -> 0 | J98: =SUM(J94:J97) -> 0 | K98: =SUM(K94:K97) -> 0 | L98: =SUM(L94:L97) -> 0 | M98: =SUM(M94:M97) -> 174509.68 | ... AF98: =SUM(AF94:AF97) -> 1429650.4
E99: a-iii) Saleable Steel (CMO + Mktg - Mill-wise shipping mode-wise)
E100: WR MILL
E101: RAIL | H101: =SUM(F101:G101) -> 0 | J101: =SUM(H101:I101) -> 0 | L101: =SUM(J101:K101) -> 0 | M101: 27782.98 | N101: =SUM(L101:M101) -> 27782.98 | O101: 27477.01 | P101: =+K101+M101+O101 -> 55259.99 | Q101: =+N101+O101 -> 55259.99 | R101: 24123.54 | S101: =SUM(Q101:R101) -> 79383.53 | T101: 29640.27 | U101: =SUM(S101:T101) -> 109023.8 | V101: =785.46+25014.761 -> 25800.221 | W101: =+R101+T101+V101 -> 79564.031 | X101: =+U101+V101 -> 134824.02 | Y101: =33237.519-61.84 -> 33175.679 | Z101: =SUM(X101:Y101) -> 167999.7 | AA101: 23834.356 | AB101: =SUM(Z101:AA101) -> 191834.06 | AC101: 27384.358 | AD101: =+Y101+AA101+AC101 -> 84394.393 | AE101: =+W101+AD101 -> 163958.42 | AF101: =+AB101+AC101 -> 219218.41
E102: ROAD | H102: =SUM(F102:G102) -> 0 | J102: =SUM(H102:I102) -> 0 | L102: =SUM(J102:K102) -> 0 | M102: =3221.73+M63 -> 3269.75 | N102: =SUM(L102:M102) -> 3269.75 | O102: =5860.32+O63 -> 5860.32 | P102: =+K102+M102+O102 -> 9130.07 | Q102: =+N102+O102 -> 9130.07 | R102: =4819.55+R63 -> 4819.55 | S102: =SUM(Q102:R102) -> 13949.62 | T102: =9950.9+T63 -> 9950.9 | U102: =SUM(S102:T102) -> 23900.52 | V102: =376.95+10259.47 -> 10636.42 | W102: =+R102+T102+V102 -> 25406.87 | X102: =+U102+V102 -> 34536.94 | Y102: 6472.84 | Z102: =SUM(X102:Y102) -> 41009.78 | AA102: 7811.1 | AB102: =SUM(Z102:AA102) -> 48820.88 | AC102: 3599.22 | AD102: =+Y102+AA102+AC102 -> 17883.16 | AE102: =+W102+AD102 -> 43290.03 | AF102: =+AB102+AC102 -> 52420.1
...

Sheet Maj Prod Summ
B1: MAJOR PRODUCTION SUMMARY | D1: 30 | E1: 30 | F1: 31 | G1: 31 | H1: =+D1+F1 -> 61 | I1: =+E1+G1 -> 61 | J1: 30 | K1: 30 | L1: =+H1+J1 -> 91 | M1: =+I1+K1 -> 91 | N1: 31 | O1: 31 | P1: =+L1+N1 -> 122 | Q1: =+M1+O1 -> 122 | R1: 31 | S1: 31 | T1: =+P1+R1 -> 153 | U1: =+Q1+S1 -> 153 | V1: 30 | W1: 30 | X1: =+N1+R1+V1 -> 92 | Y1: =+O1+S1+W1 -> 92 | Z1: =+T1+V1 -> 183 | AA1: =+U1+W1 -> 183 | AB1: 31 | AC1: 31 | AD1: =+Z1+AB1 -> 214 | AE1: =+AA1+AC1 -> 214 | AF1: 30 | AG1: 30 | AH1: =+AD1+AF1 -> 244 | AI1: =+AE1+AG1 -> 244 | AJ1: 31 | AK1: 31 | AL1: =+AB1+AF1+AJ1 -> 92 | AM1: =+AC1+AG1+AK1 -> 92 | AN1: =+AH1+AJ1 -> 275 | AO1: =+AI1+AK1 -> 275 | AP1: 31 | AQ1: 31 | AR1: =+AN1+AP1 -> 306 | AS1: =+AO1+AQ1 -> 306 | AT1: 28 | AU1: 28 | AV1: =+AR1+AT1 -> 334 | AW1: =+AS1+AU1 -> 334 | AX1: 31 | AY1: 31 | AZ1: =+AP1+AT1+AX1 -> 90 | BA1: =+AQ1+AU1+AY1 -> 90 | BB1: =+AZ1+AL1 -> 182 | BC1: =+BA1+AM1 -> 182 | BD1: =+AV1+AX1 -> 365 | BE1: =+AW1+AY1 -> 365 | BF1: 366 | BG1: 366
D2: 30 | E2: 30 | F2: 31 | G2: 31 | H2: =+D2+F2 -> 61 | I2: =+E2+G2 -> 61 | J2: 30 | K2: 30 | L2: =+H2+J2 -> 91 | M2: =+I2+K2 -> 91 | N2: 31 | O2: 31 | P2: =+L2+N2 -> 122 | Q2: =+M2+O2 -> 122 | R2: 31 | S2: 31 | T2: =+P2+R2 -> 153 | U2: =+Q2+S2 -> 153 | V2: 30 | W2: 30 | X2: =+N2+R2+V2 -> 92 | Y2: =+O2+S2+W2 -> 92 | Z2: =+T2+V2 -> 183 | AA2: =+U2+W2 -> 183 | AB2: 31 | AC2: 31 | AD2: =+Z2+AB2 -> 214 | AE2: =+AA2+AC2 -> 214 | AF2: 30 | AG2: 30 | AH2: =+AD2+AF2 -> 244 | AI2: =+AE2+AG2 -> 244 | AJ2: 31 | AK2: 31 | AL2: =+AB2+AF2+AJ2 -> 92 | AM2: =+AC2+AG2+AK2 -> 92 | AN2: =+AH2+AJ2 -> 275 | AO2: =+AI2+AK2 -> 275 | AP2: 31 | AQ2: 31 | AR2: =+AN2+AP2 -> 306 | AS2: =+AO2+AQ2 -> 306 | AT2: 28 | AU2: 28 | AV2: =+AR2+AT2 -> 334 | AW2: =+AS2+AU2 -> 334 | AX2: 31 | AY2: 31 | AZ2: =+AP2+AT2+AX2 -> 90 | BA2: =+AQ2+AU2+AY2 -> 90 | BB2: =+AZ2+AL2 -> 182 | BC2: =+BA2+AM2 -> 182 | BD2: =+AV2+AX2 -> 365 | BE2: =+AW2+AY2 -> 365 | BF2: 366 | BG2: 366
B3: ITEM | C3: Unit | D3: Apr'20 | F3: May'20 | H3: 2M | J3: Jun'20 | L3: QRT-1 | N3: Jul'20 | P3: 4M | R3: Aug'20 | T3: 5M | V3: Sep'20 | X3: QTR 2 | Z3: H1 | AB3: Oct'20 | AD3: 7M | AF3: Nov'20 | AH3: 8M | AJ3: Dec'20 | AL3: QTR 3 | AN3: 9 M | AP3: Jan'21 | AR3: 10M | AT3: Feb'21 | AV3: 11M | AX3: Mar'21 | AZ3: QTR 4 | BB3: H2 | BD3: 2020-21 | BF3: 2019-20
D4: ABP | E4: ACT | F4: ABP | G4: ACT | H4: ABP | I4: ACT | J4: ABP | K4: ACT | L4: ABP | M4: ACT | N4: ABP | O4: ACT | P4: ABP | Q4: ACT | R4: ABP | S4: ACT | T4: ABP | U4: ACT | V4: ABP | W4: ACT | X4: ABP | Y4: ACT | Z4: ABP | AA4: ACT | AB4: ABP | AC4: ACT | AD4: ABP | AE4: ACT | AF4: ABP | AG4: ACT | AH4: ABP | AI4: ACT | AJ4: ABP | AK4: ACT | AL4: ABP | AM4: ACT | AN4: ABP | AO4: ACT | AP4: ABP | AQ4: ACT | AR4: ABP | AS4: ACT | AT4: ABP | AU4: ACT | AV4: ABP | AW4: ACT | AX4: ABP | AY4: ACT | AZ4: ABP | BA4: ACT | BB4: ABP | BC4: ACT | BD4: ABP | BE4: ACT | BF4: ABP | BG4: ACT
B5: COKE OVENS PUSHING
B6: (COB#10) | C6: Nos/ day | D6: 77.866667 | E6: =+E9/E2 -> 77.866667 | F6: 85.387097 | G6: =+G9/G2 -> 85.387097 | H6: =+((D6*$D$2)+(F6*$F$2))/$H$2 -> 81.688525 | I6: =+((E6*$E$2)+(G6*$G$2))/$I$2 -> 81.688525 | J6: 92.2 | K6: =+K9/K2 -> 92.2 | L6: =+((H6*$H$2)+(J6*$J$2))/$L$2 -> 85.153846 | M6: =+((I6*$I$2)+(K6*$K$2))/$M$2 -> 85.153846 | N6: 99 | O6: =+O9/O2 -> 97.064516 | P6: =+((L6*L$2)+(N6*N$2))/P$2 -> 88.672131 | Q6: =+((M6*M$2)+(O6*O$2))/Q$2 -> 88.180328 | R6: 99 | S6: =+S9/S2 -> 98.935484 | T6: =+((P6*P$2)+(R6*R$2))/T$2 -> 90.764706 | U6: =+((Q6*Q$2)+(S6*S$2))/U$2 -> 90.359477 | V6: 99 | W6: =+W9/W2 -> 97.833333 | X6: =+((N$6*N$1)+(R$6*R$1)+(V$6*V$1))/X$1 -> 99 | Y6: =+((O$6*O$1)+(S$6*S$1)+(W$6*W$1))/Y$1 -> 97.945652 | Z6: =+((T6*T$2)+(V6*V$2))/Z$2 -> 92.114754 | AA6: =+((U6*U$2)+(W6*W$2))/AA$2 -> 91.584699 | AB6: 99 | AC6: =+AC9/AC2 -> 98.677419 | AD6: =+((Z6*Z$2)+(AB6*AB$2))/AD$2 -> 93.11215 | AE6: =+((AA6*AA$2)+(AC6*AC$2))/AE$2 -> 92.61215 | AF6: 99 | AG6: =+AG9/AG2 -> 99.366667 | AH6: =+((AD6*AD$2)+(AF6*AF$2))/AH$2 -> 93.836066 | AI6: =+((AE6*AE$2)+(AG6*AG$2))/AI$2 -> 93.442623 | AJ6: 99 | AK6: =+AK9/AK2 -> 99.129032 | AL6: =+((AB$6*AB$1)+(AF$6*AF$1)+(AJ$6*AJ$1))/AL$1 -> 99 | AM6: =+((AC$6*AC$1)+(AG$6*AG$1)+(AK$6*AK$1))/AM$1 -> 99.054348 | AN6: =+((AH6*AH$2)+(AJ6*AJ$2))/AN$2 -> 94.418182 | AO6: =+((AI6*AI$2)+(AK6*AK$2))/AO$2 -> 94.083636 | AP6: 99 | AQ6: =+AQ9/AQ2 -> 99.129032 | AR6: =+((AN6*AN$2)+(AP6*AP$2))/AR$2 -> 94.882353 | AS6: =+((AO6*AO$2)+(AQ6*AQ$2))/AS$2 -> 94.594771 | AT6: 99 | AU6: =+AU9/AU2 -> 99.142857 | AV6: =+((AR6*AR$2)+(AT6*AT$2))/AV$2 -> 95.227545 | AW6: =+((AS6*AS$2)+(AU6*AU$2))/AW$2 -> 94.976048 | AX6: 99 | AY6: =+AY9/AY2 -> 99.290323 | AZ6: =+((AP$6*AP$1)+(AT$6*AT$1)+(AX$6*AX$1))/AZ$1 -> 99 | BA6: =+((AQ$6*AQ$1)+(AU$6*AU$1)+(AY$6*AY$1))/BA$1 -> 99.188889 | BB6: =+((AL6*AL$2)+(AZ6*AZ$2))/BB$2 -> 99 | BC6: =+((AM6*AM$2)+(BA6*BA$2))/BC$2 -> 99.120879 | BD6: =+((AV6*AV$2)+(AX6*AX$2))/BD$2 -> 95.547945 | BE6: =+((AW6*AW$2)+(AY6*AY$2))/BE$2 -> 95.342466 | BF6: 97 | BG6: 97.10959
B7: (COB#11) | C7: Nos/ day | D7: 77.766667 | E7: =+E10/E2 -> 77.766667 | F7: 75.129032 | G7: =+G10/G2 -> 75.129032 | H7: =+((D7*$D$2)+(F7*$F$2))/$H$2 -> 76.42623 | I7: =+((E7*$E$2)+(G7*$G$2))/$I$2 -> 76.42623 | J7: 86.5 | K7: =+K10/K2 -> 86.5 | L7: =+((H7*$H$2)+(J7*$J$2))/$L$2 -> 79.747253 | M7: =+((I7*$I$2)+(K7*$K$2))/$M$2 -> 79.747253 | N7: 99 | O7: =+O10/O2 -> 90.83871 | P7: =+((L7*L$2)+(N7*N$2))/P$2 -> 84.639344 | Q7: =+((M7*M$2)+(O7*O$2))/Q$2 -> 82.565574 | R7: 99 | S7: =+S10/S2 -> 98.935484 | T7: =+((P7*P$2)+(R7*R$2))/T$2 -> 87.54902 | U7: =+((Q7*Q$2)+(S7*S$2))/U$2 -> 85.882353 | V7: 99 | W7: =+W10/W2 -> 83.6 | X7: =+((N$7*N$1)+(R$7*R$1)+(V$7*V$1))/X$1 -> 99 | Y7: =+((O$7*O$1)+(S$7*S$1)+(W$7*W$1))/Y$1 -> 91.206522 | Z7: =+((T7*T$2)+(V7*V$2))/Z$2 -> 89.42623 | AA7: =+((U7*U$2)+(W7*W$2))/AA$2 -> 85.508197 | AB7: 99 | AC7: =+AC10/AC2 -> 92 | AD7: =+((Z7*Z$2)+(AB7*AB$2))/AD$2 -> 90.813084 | AE7: =+((AA7*AA$2)+(AC7*AC$2))/AE$2 -> 86.448598 | AF7: 99 | AG7: =+AG10/AG2 -> 88.633333 | AH7: =+((AD7*AD$2)+(AF7*AF$2))/AH$2 -> 91.819672 | AI7: =+((AE7*AE$2)+(AG7*AG$2))/AI$2 -> 86.717213 | AJ7: 99 | AK7: =+AK10/AK2 -> 98.83871 | AL7: =+((AB$7*AB$1)+(AF$7*AF$1)+(AJ$7*AJ$1))/AL$1 -> 99 | AM7: =+((AC$7*AC$1)+(AG$7*AG$1)+(AK$7*AK$1))/AM$1 -> 93.206522 | AN7: =+((AH7*AH$2)+(AJ7*AJ$2))/AN$2 -> 92.629091 | AO7: =+((AI7*AI$2)+(AK7*AK$2))/AO$2 -> 88.083636 | AP7: 99 | AQ7: =+AQ10/AQ2 -> 99 | AR7: =+((AN7*AN$2)+(AP7*AP$2))/AR$2 -> 93.27451 | AS7: =+((AO7*AO$2)+(AQ7*AQ$2))/AS$2 -> 89.189542 | AT7: 99 | AU7: =+AU10/AU2 -> 99 | AV7: =+((AR7*AR$2)+(AT7*AT$2))/AV$2 -> 93.754491 | AW7: =+((AS7*AS$2)+(AU7*AU$2))/AW$2 -> 90.011976 | AX7: 99 | AY7: =+AY10/AY2 -> 99.032258 | AZ7: =+((AP$7*AP$1)+(AT$7*AT$1)+(AX$7*AX$1))/AZ$1 -> 99 | BA7: =+((AQ$7*AQ$1)+(AU$7*AU$1)+(AY$7*AY$1))/BA$1 -> 99.011111 | BB7: =+((AL7*AL$2)+(AZ7*AZ$2))/BB$2 -> 99 | BC7: =+((AM7*AM$2)+(BA7*BA$2))/BC$2 -> 96.076923 | BD7: =+((AV7*AV$2)+(AX7*AX$2))/BD$2 -> 94.2 | BE7: =+((AW7*AW$2)+(AY7*AY$2))/BE$2 -> 90.778082 | BF7: 97 | BG7: 95.710246
B8: Overall Equiv. Ovens Pushed/ Day | C8: Nos/ day | D8: =D6+(D7*1.8343023255814) -> 220.51424 | E8: =E6+(E7*1.8343023255814) -> 220.51424 | F8: =F6+(F7*1.8343023255814) -> 223.19646 | G8: =G6+(G7*1.8343023255814) -> 223.19646 | H8: =H6+(H7*1.8343023255814) -> 221.87734 | I8: =I6+(I7*1.8343023255814) -> 221.87734 | J8: =J6+(J7*1.8343023255814) -> 250.86715 | K8: =K6+(K7*1.8343023255814) -> 250.86715 | ... BE8: =BE6+(BE7*1.8343023255814) -> 261.85691 | BF8: 274.92733 | BG8: 272.67112
B9: (COB#10) | C9: Nos | D9: =+D6*D2 -> 2336 | E9: 2336 | F9: =+F6*F2 -> 2647 | G9: 2647 | H9: =+H6*H2 -> 4983 | I9: =+E9+G9 -> 4983 | J9: =+J6*J2 -> 2766 | K9: 2766 | L9: =+H9+J9 -> 7749 | M9: =+I9+K9 -> 7749 | N9: =+N6*N2 -> 3069 | O9: 3009 | P9: =+L9+N9 -> 10818 | Q9: =+M9+O9 -> 10758 | R9: =+R6*R2 -> 3069 | S9: 3067 | T9: =+P9+R9 -> 13887 | U9: =+Q9+S9 -> 13825 | V9: =+V6*V2 -> 2970 | W9: 2935 | X9: =+N9+R9+V9 -> 9108 | Y9: =+O9+S9+W9 -> 9011 | Z9: =+T9+V9 -> 16857 | AA9: =+U9+W9 -> 16760 | AB9: =+AB6*AB2 -> 3069 | AC9: 3059 | AD9: =+Z9+AB9 -> 19926 | AE9: =+AA9+AC9 -> 19819 | AF9: =+AF6*AF2 -> 2970 | AG9: 2981 | AH9: =+AD9+AF9 -> 22896 | AI9: =+AE9+AG9 -> 22800 | AJ9: =+AJ6*AJ2 -> 3069 | AK9: 3073 | AL9: =+AB9+AF9+AJ9 -> 9108 | AM9: =+AC9+AG9+AK9 -> 9113 | AN9: =+AH9+AJ9 -> 25965 | AO9: =+AI9+AK9 -> 25873 | AP9: =+AP6*AP2 -> 3069 | AQ9: 3073 | AR9: =+AN9+AP9 -> 29034 | AS9: =+AO9+AQ9 -> 28946 | AT9: =+AT6*AT2 -> 2772 | AU9: 2776 | AV9: =+AR9+AT9 -> 31806 | AW9: =+AS9+AU9 -> 31722 | AX9: =+AX6*AX2 -> 3069 | AY9: 3078 | AZ9: =+AP9+AT9+AX9 -> 8910 | BA9: =+AQ9+AU9+AY9 -> 8927 | BB9: =+AL9+AZ9 -> 18018 | BC9: =+AM9+BA9 -> 18040 | BD9: =+AV9+AX9 -> 34875 | BE9: =+AW9+AY9 -> 34800 | BF9: 35502 | BG9: 35543
B10: (COB#11) | C10: Nos | D10: =+D7*D2 -> 2333 | E10: 2333 | F10: =+F7*F2 -> 2329 | G10: 2329 | H10: =+H7*H2 -> 4662 | I10: =+E10+G10 -> 4662 | J10: =+J7*J2 -> 2595 | K10: 2595 | L10: =+H10+J10 -> 7257 | M10: =+I10+K10 -> 7257 | N10: =+N7*N2 -> 3069 | O10: 2816 | P10: =+L10+N10 -> 10326 | Q10: =+M10+O10 -> 10073 | R10: =+R7*R2 -> 3069 | S10: 3067 | T10: =+P10+R10 -> 13395 | U10: =+Q10+S10 -> 13140 | V10: =+V7*V2 -> 2970 | W10: 2508 | X10: =+N10+R10+V10 -> 9108 | Y10: =+O10+S10+W10 -> 8391 | Z10: =+T10+V10 -> 16365 | AA10: =+U10+W10 -> 15648 | AB10: =+AB7*AB2 -> 3069 | AC10: 2852 | AD10: =+Z10+AB10 -> 19434 | AE10: =+AA10+AC10 -> 18500 | AF10: =+AF7*AF2 -> 2970 | AG10: 2659 | AH10: =+AD10+AF10 -> 22404 | AI10: =+AE10+AG10 -> 21159 | AJ10: =+AJ7*AJ2 -> 3069 | AK10: 3064 | AL10: =+AB10+AF10+AJ10 -> 9108 | AM10: =+AC10+AG10+AK10 -> 8575 | AN10: =+AH10+AJ10 -> 25473 | AO10: =+AI10+AK10 -> 24223 | AP10: =+AP7*AP2 -> 3069 | AQ10: =2871+198 -> 3069 | AR10: =+AN10+AP10 -> 28542 | AS10: =+AO10+AQ10 -> 27292 | AT10: =+AT7*AT2 -> 2772 | AU10: 2772 | AV10: =+AR10+AT10 -> 31314 | AW10: =+AS10+AU10 -> 30064 | AX10: =+AX7*AX2 -> 3069 | AY10: 3070 | AZ10: =+AP10+AT10+AX10 -> 8910 | BA10: =+AQ10+AU10+AY10 -> 8911 | BB10: =+AL10+AZ10 -> 18018 | BC10: =+AM10+BA10 -> 17486 | BD10: =+AV10+AX10 -> 34383 | BE10: =+AW10+AY10 -> 33134 | BF10: 35502 | BG10: 35030
B11: Overall Equiv. Ovens Pushed | C11: Nos | D11: =D9+(D10*1.8343023255814) -> 6615.4273 | E11: =E9+(E10*1.8343023255814) -> 6615.4273 | F11: =F9+(F10*1.8343023255814) -> 6919.0901 | G11: =G9+(G10*1.8343023255814) -> 6919.0901 | H11: =H9+(H10*1.8343023255814) -> 13534.517 | I11: =I9+(I10*1.8343023255814) -> 13534.517 | J11: =J9+(J10*1.8343023255814) -> 7526.0145 | K11: =K9+(K10*1.8343023255814) -> 7526.0145 | ... BA11: =BA9+(BA10*1.8343023255814) -> 25272.468 | BD11: =BD9+(BD10*1.8343023255814) -> 97943.817 | BE11: =BE9+(BE10*1.8343023255814) -> 95577.773 | BF11: 100623.4 | BG11: 99798.61
B12: BF COKE
B13: COB#10 | C13: Mt | D13: 28527 | E13: 27936.6 | F13: 31935 | G13: 31876 | H13: =+D13+F13 -> 60462 | I13: =+E13+G13 -> 59812.6 | J13: 33778 | K13: 33669.6 | L13: =+H13+J13 -> 94240 | M13: =+I13+K13 -> 93482.2 | N13: 37479 | O13: 36675 | P13: =+L13+N13 -> 131719 | Q13: =+M13+O13 -> 130157.2 | R13: 37479 | S13: 37836 | T13: =+P13+R13 -> 169198 | U13: =+Q13+S13 -> 167993.2 | V13: 36270 | W13: 36979 | X13: =+N13+R13+V13 -> 111228 | Y13: =+O13+S13+W13 -> 111490 | Z13: =+T13+V13 -> 205468 | AA13: =+U13+W13 -> 204972.2 | AB13: 37479 | AC13: 38591 | AD13: =+Z13+AB13 -> 242947 | AE13: =+AA13+AC13 -> 243563.2 | AF13: 36270 | AG13: 37324 | AH13: =+AD13+AF13 -> 279217 | AI13: =+AE13+AG13 -> 280887.2 | AJ13: 37479 | AK13: 38071 | AL13: =+AB13+AF13+AJ13 -> 111228 | AM13: =+AC13+AG13+AK13 -> 113986 | AN13: =+AH13+AJ13 -> 316696 | AO13: =+AI13+AK13 -> 318958.2 | AP13: 37479 | AQ13: 38030 | AR13: =+AN13+AP13 -> 354175 | AS13: =+AO13+AQ13 -> 356988.2 | AT13: 33852 | AU13: 34628 | AV13: =+AR13+AT13 -> 388027 | AW13: =+AS13+AU13 -> 391616.2 | AX13: 37479 | AY13: 39306 | AZ13: =+AP13+AT13+AX13 -> 108810 | BA13: =+AQ13+AU13+AY13 -> 111964 | BB13: =+AL13+AZ13 -> 220038 | BC13: =+AM13+BA13 -> 225950 | BD13: =+AV13+AX13 -> 425506 | BE13: =+AW13+AY13 -> 430922.2 | BF13: 406071.88 | BG13: 412610.14
B14: COB#11 | C14: Mt | D14: 52260 | E14: 51175.3 | F14: 52180 | G14: 51446 | H14: =+D14+F14 -> 104440 | I14: =+E14+G14 -> 102621.3 | J14: 58129 | K14: 57942.1 | L14: =+H14+J14 -> 162569 | M14: =+I14+K14 -> 160563.4 | N14: 68747 | O14: 62959 | P14: =+L14+N14 -> 231316 | Q14: =+M14+O14 -> 223522.4 | R14: 68747 | S14: 69404 | T14: =+P14+R14 -> 300063 | U14: =+Q14+S14 -> 292926.4 | V14: 66529 | W14: 57963 | X14: =+N14+R14+V14 -> 204023 | Y14: =+O14+S14+W14 -> 190326 | Z14: =+T14+V14 -> 366592 | AA14: =+U14+W14 -> 350889.4 | AB14: 68747 | AC14: 65998 | AD14: =+Z14+AB14 -> 435339 | AE14: =+AA14+AC14 -> 416887.4 | AF14: 66529 | AG14: 61068 | AH14: =+AD14+AF14 -> 501868 | AI14: =+AE14+AG14 -> 477955.4 | AJ14: 68747 | AK14: 69629 | AL14: =+AB14+AF14+AJ14 -> 204023 | AM14: =+AC14+AG14+AK14 -> 196695 | AN14: =+AH14+AJ14 -> 570615 | AO14: =+AI14+AK14 -> 547584.4 | AP14: 68747 | AQ14: 69668 | AR14: =+AN14+AP14 -> 639362 | AS14: =+AO14+AQ14 -> 617252.4 | AT14: 62094 | AU14: 63427 | AV14: =+AR14+AT14 -> 701456 | AW14: =+AS14+AU14 -> 680679.4 | AX14: 68747 | AY14: 71912 | AZ14: =+AP14+AT14+AX14 -> 199588 | BA14: =+AQ14+AU14+AY14 -> 205007 | BB14: =+AL14+AZ14 -> 403611 | BC14: =+AM14+BA14 -> 401702 | BD14: =+AV14+AX14 -> 770203 | BE14: =+AW14+AY14 -> 752591.4 | BF14: 744858.59 | BG14: 745859.84
B15: TOTAL | C15: Mt | D15: =SUM(D13:D14) -> 80787 | E15: =SUM(E13:E14) -> 79111.9 | F15: =SUM(F13:F14) -> 84115 | G15: =SUM(G13:G14) -> 83322 | H15: =SUM(H13:H14) -> 164902 | I15: =SUM(I13:I14) -> 162433.9 | J15: =SUM(J13:J14) -> 91907 | K15: =SUM(K13:K14) -> 91611.7 | ... BA15: =SUM(BA13:BA14) -> 316971 | BD15: =SUM(BD13:BD14) -> 1195709 | BE15: =SUM(BE13:BE14) -> 1183513.6 | BF15: 1150930.5 | BG15: 1158470
B16: SINTER | C16: Mt | D16: 235289 | E16: 235289 | F16: 239020 | G16: 239020 | H16: =+D16+F16 -> 474309 | I16: =+E16+G16 -> 474309 | J16: 261844 | K16: 260541 | L16: =+H16+J16 -> 736153 | M16: =+I16+K16 -> 734850 | N16: 348705.09 | O16: 297604 | P16: =+L16+N16 -> 1084858.1 | Q16: =+M16+O16 -> 1032454 | R16: 346672.77 | S16: 287210 | T16: =+P16+R16 -> 1431530.9 | U16: =+Q16+S16 -> 1319664 | V16: 342110.41 | W16: 217308 | X16: =+N16+R16+V16 -> 1037488.3 | Y16: =+O16+S16+W16 -> 802122 | Z16: =+T16+V16 -> 1773641.3 | AA16: =+U16+W16 -> 1536972 | AB16: 181250 | AC16: 294485 | AD16: =+Z16+AB16 -> 1954891.3 | AE16: =+AA16+AC16 -> 1831457 | AF16: =336.4*1000 -> 336400 | AG16: 320285 | AH16: =+AD16+AF16 -> 2291291.3 | AI16: =+AE16+AG16 -> 2151742 | AJ16: =353.8*1000 -> 353800 | AK16: 354168 | AL16: =+AB16+AF16+AJ16 -> 871450 | AM16: =+AC16+AG16+AK16 -> 968938 | AN16: =+AH16+AJ16 -> 2645091.3 | AO16: =+AI16+AK16 -> 2505910 | AP16: 348000 | AQ16: 377726 | AR16: =+AN16+AP16 -> 2993091.3 | AS16: =+AO16+AQ16 -> 2883636 | AT16: 319000 | AU16: =+SINTER!AU54 -> 345006 | AV16: =+AR16+AT16 -> 3312091.3 | AW16: =+AS16+AU16 -> 3228642 | AX16: 353800 | AY16: =+SINTER!AY54 -> 400935 | AZ16: =+AP16+AT16+AX16 -> 1020800 | BA16: =+AQ16+AU16+AY16 -> 1123667 | BB16: =+AL16+AZ16 -> 1892250 | BC16: =+AM16+BA16 -> 2092605 | BD16: =+AV16+AX16 -> 3665891.3 | BE16: =+AW16+AY16 -> 3629577 | BF16: 3903932.5 | BG16: 3709525 | BH16: 1008079 | BI16: =+AO16+BH16 -> 3513989 | BJ16: =+BI16/1000000 -> 3.513989
B17: HOT METAL | C17: Mt | D17: 143766 | E17: 143766 | F17: 152132 | G17: 152132 | H17: =+D17+F17 -> 295898 | I17: =+E17+G17 -> 295898 | J17: 180265 | K17: 167381 | L17: =+H17+J17 -> 476163 | M17: =+I17+K17 -> 463279 | N17: 240486.27 | O17: 190559 | P17: =+L17+N17 -> 716649.27 | Q17: =+M17+O17 -> 653838 | R17: 239084.67 | S17: 195518 | T17: =+P17+R17 -> 955733.94 | U17: =+Q17+S17 -> 849356 | V17: 235938.22 | W17: 107327 | X17: =+N17+R17+V17 -> 715509.15 | Y17: =+O17+S17+W17 -> 493404 | Z17: =+T17+V17 -> 1191672.2 | AA17: =+U17+W17 -> 956683 | AB17: 125000 | AC17: 125039 | AD17: =+Z17+AB17 -> 1316672.2 | AE17: =+AA17+AC17 -> 1081722 | AF17: =232*1000 -> 232000 | AG17: 154255 | AH17: =+AD17+AF17 -> 1548672.2 | AI17: =+AE17+AG17 -> 1235977 | AJ17: =244*1000 -> 244000 | AK17: 198815 | AL17: =+AB17+AF17+AJ17 -> 601000 | AM17: =+AC17+AG17+AK17 -> 478109 | AN17: =+AH17+AJ17 -> 1792672.2 | AO17: =+AI17+AK17 -> 1434792 | AP17: 240000 | AQ17: 221321 | AR17: =+AN17+AP17 -> 2032672.2 | AS17: =+AO17+AQ17 -> 1656113 | AT17: 220000 | AU17: 198514 | AV17: =+AR17+AT17 -> 2252672.2 | AW17: =+AS17+AU17 -> 1854627 | AX17: 244000 | AY17: 238171 | AZ17: =+AP17+AT17+AX17 -> 704000 | BA17: =+AQ17+AU17+AY17 -> 658006 | BB17: =+AL17+AZ17 -> 1305000 | BC17: =+AM17+BA17 -> 1136115 | BD17: =+AV17+AX17 -> 2496672.2 | BE17: =+AW17+AY17 -> 2092798 | BF17: 2700000 | BG17: 2505193 | BH17: 694168 | BI17: =+AO17+BH17 -> 2128960 | BJ17: =+BI17/1000000 -> 2.12896
B18: CRUDE STEEL | C18: Mt | D18: 129292 | E18: 129292 | F18: 134303 | G18: 134303 | H18: =+D18+F18 -> 263595 | I18: =+E18+G18 -> 263595 | J18: 161947 | K18: 147382 | L18: =+H18+J18 -> 425542 | M18: =+I18+K18 -> 410977 | N18: 221247 | O18: 160929 | P18: =+L18+N18 -> 646789 | Q18: =+M18+O18 -> 571906 | R18: 219958 | S18: 172012 | T18: =+P18+R18 -> 866747 | U18: =+Q18+S18 -> 743918 | V18: 217063 | W18: 83590 | X18: =+N18+R18+V18 -> 658268 | Y18: =+O18+S18+W18 -> 416531 | Z18: =+T18+V18 -> 1083810 | AA18: =+U18+W18 -> 827508 | AB18: 114155 | AC18: 98775 | AD18: =+Z18+AB18 -> 1197965 | AE18: =+AA18+AC18 -> 926283 | AF18: =215.955*1000 -> 215955 | AG18: 139620 | AH18: =+AD18+AF18 -> 1413920 | AI18: =+AE18+AG18 -> 1065903 | AJ18: =226.59*1000 -> 226590 | AK18: 167995 | AL18: =+AB18+AF18+AJ18 -> 556700 | AM18: =+AC18+AG18+AK18 -> 406390 | AN18: =+AH18+AJ18 -> 1640510 | AO18: =+AI18+AK18 -> 1233898 | AP18: 222957.5 | AQ18: 201367 | AR18: =+AN18+AP18 -> 1863467.5 | AS18: =+AO18+AQ18 -> 1435265 | AT18: 206078 | AU18: 189148 | AV18: =+AR18+AT18 -> 2069545.5 | AW18: =+AS18+AU18 -> 1624413 | AX18: 227618 | AY18: 223020 | AZ18: =+AP18+AT18+AX18 -> 656653.5 | BA18: =+AQ18+AU18+AY18 -> 613535 | BB18: =+AL18+AZ18 -> 1213353.5 | BC18: =+AM18+BA18 -> 1019925 | BD18: =+AV18+AX18 -> 2297163.5 | BE18: =+AW18+AY18 -> 1847433 | BF18: 2500000 | BG18: 2083412 | BH18: 589289 | BI18: =+AO18+BH18 -> 1823187 | BJ18: =+BI18/1000000 -> 1.823187
B19: Avg Heats Cast per Day | C19: Nos. / day | D19: =+D138/D1 -> 28.566667 | E19: =+E138/E1 -> 28.566667 | F19: =+F138/F1 -> 28.612903 | G19: =+G138/G1 -> 28.612903 | H19: =+H138/H1 -> 28.590164 | I19: =+I138/I1 -> 28.590164 | J19: =+J138/J1 -> 35.988222 | K19: =+K138/K1 -> 32.266667 | ... BE19: =+BE138/BE1 -> 33.309589 | BF19: 47.014645 | BG19: 38.663934
B20: Cold Pig & Pig Equivalent
A21: =+#REF!+#REF! -> #REF! | B21: MOG | C21: Mt | D21: 3047 | E21: 3047 | F21: 2899 | G21: 2899 | H21: =+D21+F21 -> 5946 | I21: =+E21+G21 -> 5946 | J21: 3951.4399 | K21: 2804 | L21: =+H21+J21 -> 9897.4399 | M21: =+I21+K21 -> 8750 | N21: 0.3735936 | O21: 8503 | P21: =+L21+N21 -> 9897.8135 | Q21: =+M21+O21 -> 17253 | R21: 0 | S21: 4172 | T21: =+P21+R21 -> 9897.8135 | U21: =+Q21+S21 -> 21425 | V21: 0 | W21: 7042 | X21: =+N21+R21+V21 -> 0.3735936 | Y21: =+O21+S21+W21 -> 19717 | Z21: =+T21+V21 -> 9897.8135 | AA21: =+U21+W21 -> 28467 | AB21: 2130.1605 | AC21: 9461 | AD21: =+Z21+AB21 -> 12027.974 | AE21: =+AA21+AC21 -> 37928 | AF21: 1873.1932 | AG21: 4903 | AH21: =+AD21+AF21 -> 13901.167 | AI21: =+AE21+AG21 -> 42831 | AJ21: 2501.7113 | AK21: 7314 | AL21: =+AB21+AF21+AJ21 -> 6505.0651 | AM21: =+AC21+AG21+AK21 -> 21678 | AN21: =+AH21+AJ21 -> 16402.879 | AO21: =+AI21+AK21 -> 50145 | AP21: 2379.1399 | AQ21: 4628 | AR21: =+AN21+AP21 -> 18782.018 | AS21: =+AO21+AQ21 -> 54773 | AT21: 492 | AU21: 643.3 | AV21: =+AR21+AT21 -> 19274.018 | AW21: =+AS21+AU21 -> 55416.3 | AX21: 1481 | AY21: 2804.4 | AZ21: =+AP21+AT21+AX21 -> 4352.1399 | BA21: =+AQ21+AU21+AY21 -> 8075.7 | BB21: =+AL21+AZ21 -> 10857.205 | BC21: =+AM21+BA21 -> 29753.7 | BD21: =+AV21+AX21 -> 20755.018 | BE21: =+AW21+AY21 -> 58220.7 | BF21: 29957.856 | BG21: 134629.18
A22: =+#REF!+#REF! -> #REF! | B22: UPIS | C22: Mt | D22: 201 | E22: 201 | F22: 191 | G22: 191 | H22: =+D22+F22 -> 392 | I22: =+E22+G22 -> 392 | J22: 0 | K22: 185 | L22: =+H22+J22 -> 392 | M22: =+I22+K22 -> 577 | N22: 0 | O22: 561 | P22: =+L22+N22 -> 392 | Q22: =+M22+O22 -> 1138 | R22: 0 | S22: 275 | T22: =+P22+R22 -> 392 | U22: =+Q22+S22 -> 1413 | V22: 0 | W22: 464 | X22: =+N22+R22+V22 -> 0 | Y22: =+O22+S22+W22 -> 1300 | Z22: =+T22+V22 -> 392 | AA22: =+U22+W22 -> 1877 | AB22: 0 | AC22: 638 | AD22: =+Z22+AB22 -> 392 | AE22: =+AA22+AC22 -> 2515 | AF22: 0 | AG22: 323 | AH22: =+AD22+AF22 -> 392 | AI22: =+AE22+AG22 -> 2838 | AJ22: 0 | AK22: 482 | AL22: =+AB22+AF22+AJ22 -> 0 | AM22: =+AC22+AG22+AK22 -> 1443 | AN22: =+AH22+AJ22 -> 392 | AO22: =+AI22+AK22 -> 3320 | AP22: 0 | AQ22: 305 | AR22: =+AN22+AP22 -> 392 | AS22: =+AO22+AQ22 -> 3625 | AT22: 0 | AU22: 42.4 | AV22: =+AR22+AT22 -> 392 | AW22: =+AS22+AU22 -> 3667.4 | AX22: 0 | AY22: 184.9 | AZ22: =+AP22+AT22+AX22 -> 0 | BA22: =+AQ22+AU22+AY22 -> 532.3 | BB22: =+AL22+AZ22 -> 0 | BC22: =+AM22+BA22 -> 1975.3 | BD22: =+AV22+AX22 -> 392 | BE22: =+AW22+AY22 -> 3852.3 | BF22: 1419.0563 | BG22: 8272.9783
B23: (Equiv. Pig Iron @ 80% of HM sent to Sand Pit. (Ref to Fax Msg from ED (O), vide SAIL/OPRNS/ PPMS/33 dt. 05.02.15) | C23: Mt | D23: 0 | E23: =0.8*0 -> 0 | F23: 0 | G23: =0.8*0 -> 0 | H23: =+D23+F23 -> 0 | I23: =+E23+G23 -> 0 | J23: 0 | K23: 0 | L23: =+H23+J23 -> 0 | M23: =+I23+K23 -> 0 | N23: 0 | O23: =0.8*0 -> 0 | P23: =+L23+N23 -> 0 | Q23: =+M23+O23 -> 0 | R23: 0 | S23: 0 | T23: =+P23+R23 -> 0 | U23: =+Q23+S23 -> 0 | V23: 0 | W23: 0 | X23: =+N23+R23+V23 -> 0 | Y23: =+O23+S23+W23 -> 0 | Z23: =+T23+V23 -> 0 | AA23: =+U23+W23 -> 0 | AB23: 0 | AC23: 0 | AD23: =+Z23+AB23 -> 0 | AE23: =+AA23+AC23 -> 0 | AF23: 0 | AG23: 0 | AH23: =+AD23+AF23 -> 0 | AI23: =+AE23+AG23 -> 0 | AJ23: 0 | AK23: 0 | AL23: =+AB23+AF23+AJ23 -> 0 | AM23: =+AC23+AG23+AK23 -> 0 | AN23: =+AH23+AJ23 -> 0 | AO23: =+AI23+AK23 -> 0 | AP23: 0 | AQ23: 0 | AR23: =+AN23+AP23 -> 0 | AS23: =+AO23+AQ23 -> 0 | AT23: 0 | AU23: 0 | AV23: =+AR23+AT23 -> 0 | AW23: =+AS23+AU23 -> 0 | AX23: 0 | AY23: 0 | AZ23: =+AP23+AT23+AX23 -> 0 | BA23: =+AQ23+AU23+AY23 -> 0 | BB23: =+AL23+AZ23 -> 0 | BC23: =+AM23+BA23 -> 0 | BD23: =+AV23+AX23 -> 0 | BE23: =+AW23+AY23 -> 0 | BF23: 0 | BG23: 26220.8
B24: TOTAL EQUIVALENT PIG IRON | C24: Mt | D24: =SUM(D21:D23) -> 3248 | E24: =SUM(E21:E23) -> 3248 | F24: =SUM(F21:F23) -> 3090 | G24: =SUM(G21:G23) -> 3090 | H24: =SUM(H21:H23) -> 6338 | I24: =SUM(I21:I23) -> 6338 | J24: =SUM(J21:J23) -> 3951.4399 | K24: =SUM(K21:K23) -> 2989 | ... BA24: =SUM(BA21:BA23) -> 8608 | BB24: =+AL24+AZ24 -> 10857.205 | BC24: =+AM24+BA24 -> 31729 | BD24: =SUM(BD21:BD23) -> 21147.018 | BE24: =SUM(BE21:BE23) -> 62073 | BF24: 31376.912 | BG24: 169122.96
B25: Net PCI Production | C25: Mt | D25: 1693 | E25: 1693 | F25: 4190 | G25: 4190 | H25: =+D25+F25 -> 5883 | I25: =+E25+G25 -> 5883 | J25: 807.0194 | K25: 4452 | L25: =+H25+J25 -> 6690.0194 | M25: =+I25+K25 -> 10335 | N25: 416.569 | O25: 2813 | P25: =+L25+N25 -> 7106.5884 | Q25: =+M25+O25 -> 13148 | R25: 414.19888 | S25: 2290 | T25: =+P25+R25 -> 7520.7873 | U25: =+Q25+S25 -> 15438 | V25: 408.66504 | W25: 1311 | X25: =+N25+R25+V25 -> 1239.4329 | Y25: =+O25+S25+W25 -> 6414 | Z25: =+T25+V25 -> 7929.4523 | AA25: =+U25+W25 -> 16749 | AB25: 484.30665 | AC25: 3244 | AD25: =+Z25+AB25 -> 8413.759 | AE25: =+AA25+AC25 -> 19993 | AF25: 640.09373 | AG25: 1716 | AH25: =+AD25+AF25 -> 9053.8527 | AI25: =+AE25+AG25 -> 21709 | AJ25: 739.76354 | AK25: 2856 | AL25: =+AB25+AF25+AJ25 -> 1864.1639 | AM25: =+AC25+AG25+AK25 -> 7816 | AN25: =+AH25+AJ25 -> 9793.6162 | AO25: =+AI25+AK25 -> 24565 | AP25: 717.42475 | AQ25: 4003 | AR25: =+AN25+AP25 -> 10511.041 | AS25: =+AO25+AQ25 -> 28568 | AT25: 446 | AU25: 5717.9 | AV25: =+AR25+AT25 -> 10957.041 | AW25: =+AS25+AU25 -> 34285.9 | AX25: 611.9487 | AY25: 6808 | AZ25: =+AP25+AT25+AX25 -> 1775.3734 | BA25: =+AQ25+AU25+AY25 -> 16528.9 | BB25: =+AL25+AZ25 -> 3639.5374 | BC25: =+AM25+BA25 -> 24344.9 | BD25: =+AV25+AX25 -> 11568.99 | BE25: =+AW25+AY25 -> 41093.9 | BF25: 0 | BG25: 44255.19
B26: Net Granulated Slag Production | C26: Mt | D26: 55719 | E26: 55719 | F26: 52052 | G26: 52052 | H26: =+D26+F26 -> 107771 | I26: =+E26+G26 -> 107771 | J26: 67868.386 | K26: 61691 | L26: =+H26+J26 -> 175639.39 | M26: =+I26+K26 -> 169462 | N26: 84144.296 | O26: 63617 | P26: =+L26+N26 -> 259783.68 | Q26: =+M26+O26 -> 233079 | R26: 83653.886 | S26: 75389 | T26: =+P26+R26 -> 343437.57 | U26: =+Q26+S26 -> 308468 | V26: 82552.967 | W26: 40763 | X26: =+N26+R26+V26 -> 250351.15 | Y26: =+O26+S26+W26 -> 179769 | Z26: =+T26+V26 -> 425990.53 | AA26: =+U26+W26 -> 349231 | AB26: 43736.538 | AC26: 47916 | AD26: =+Z26+AB26 -> 469727.07 | AE26: =+AA26+AC26 -> 397147 | AF26: 81175.015 | AG26: 57141 | AH26: =+AD26+AF26 -> 550902.09 | AI26: =+AE26+AG26 -> 454288 | AJ26: 85373.723 | AK26: 68072 | AL26: =+AB26+AF26+AJ26 -> 210285.28 | AM26: =+AC26+AG26+AK26 -> 173129 | AN26: =+AH26+AJ26 -> 636275.81 | AO26: =+AI26+AK26 -> 522360 | AP26: 83974.154 | AQ26: 81284 | AR26: =+AN26+AP26 -> 720249.97 | AS26: =+AO26+AQ26 -> 603644 | AT26: 76976 | AU26: 80505 | AV26: =+AR26+AT26 -> 797225.97 | AW26: =+AS26+AU26 -> 684149 | AX26: 85374 | AY26: 92550 | AZ26: =+AP26+AT26+AX26 -> 246324.15 | BA26: =+AQ26+AU26+AY26 -> 254339 | BB26: =+AL26+AZ26 -> 456609.43 | BC26: =+AM26+BA26 -> 427468 | BD26: =+AV26+AX26 -> 882599.97 | BE26: =+AW26+AY26 -> 776699 | BF26: 854658 | BG26: 809638.21
B27: Saleable Steel Production (Mill Wise)
B28: WR Mill | C28: Mt | D28: 14366.4 | E28: 14366.4 | F28: 17668 | G28: 17668 | H28: =+D28+F28 -> 32034.4 | I28: =+E28+G28 -> 32034.4 | J28: 35910 | K28: 31338.144 | L28: =+H28+J28 -> 67944.4 | M28: =+I28+K28 -> 63372.544 | N28: 35000 | O28: 32647.336 | P28: =+L28+N28 -> 102944.4 | Q28: =+M28+O28 -> 96019.88 | R28: 35000 | S28: 34032.42 | T28: =+P28+R28 -> 137944.4 | U28: =+Q28+S28 -> 130052.3 | V28: 32000 | W28: 27037.868 | X28: =+N28+R28+V28 -> 102000 | Y28: =+O28+S28+W28 -> 93717.624 | Z28: =+T28+V28 -> 169944.4 | AA28: =+U28+W28 -> 157090.17 | AB28: 40000 | AC28: 26925.816 | AD28: =+Z28+AB28 -> 209944.4 | AE28: =+AA28+AC28 -> 184015.98 | AF28: 45249.811 | AG28: 32756.97 | AH28: =+AD28+AF28 -> 255194.21 | AI28: =+AE28+AG28 -> 216772.95 | AJ28: 46294.038 | AK28: 34721.176 | AL28: =+AB28+AF28+AJ28 -> 131543.85 | AM28: =+AC28+AG28+AK28 -> 94403.962 | AN28: =+AH28+AJ28 -> 301488.25 | AO28: =+AI28+AK28 -> 251494.13 | AP28: 46294.038 | AQ28: 36021.128 | AR28: =+AN28+AP28 -> 347782.29 | AS28: =+AO28+AQ28 -> 287515.26 | AT28: 41769 | AU28: 31000.4 | AV28: =+AR28+AT28 -> 389551.29 | AW28: =+AS28+AU28 -> 318515.66 | AX28: 46414.675 | AY28: 38003 | AZ28: =+AP28+AT28+AX28 -> 134477.71 | BA28: =+AQ28+AU28+AY28 -> 105024.53 | BB28: =+AL28+AZ28 -> 266021.56 | BC28: =+AM28+BA28 -> 199428.49 | BD28: =+AV28+AX28 -> 435965.96 | BE28: =+AW28+AY28 -> 356518.66 | BF28: 500000 | BG28: 412025.22 | BH28: 106766.46 | BI28: =+AO28+BH28 -> 358260.59 | BJ28: =+BI28/1000000 -> 0.35826059
B29: Bar Mill | C29: Mt | D29: 8073.14 | E29: 8073.14 | F29: 43712 | G29: 43712 | H29: =+D29+F29 -> 51785.14 | I29: =+E29+G29 -> 51785.14 | J29: 41998 | K29: 32149.445 | L29: =+H29+J29 -> 93783.14 | M29: =+I29+K29 -> 83934.585 | N29: 59600 | O29: 24173.96 | P29: =+L29+N29 -> 153383.14 | Q29: =+M29+O29 -> 108108.54 | R29: 55000 | S29: 30791.565 | T29: =+P29+R29 -> 208383.14 | U29: =+Q29+S29 -> 138900.11 | V29: 58000 | W29: 31774.47 | X29: =+N29+R29+V29 -> 172600 | Y29: =+O29+S29+W29 -> 86739.995 | Z29: =+T29+V29 -> 266383.14 | AA29: =+U29+W29 -> 170674.58 | AB29: 50000 | AC29: 29425.245 | AD29: =+Z29+AB29 -> 316383.14 | AE29: =+AA29+AC29 -> 200099.82 | AF29: 72144 | AG29: 39377.085 | AH29: =+AD29+AF29 -> 388527.14 | AI29: =+AE29+AG29 -> 239476.91 | AJ29: 72945.6 | AK29: 55325.43 | AL29: =+AB29+AF29+AJ29 -> 195089.6 | AM29: =+AC29+AG29+AK29 -> 124127.76 | AN29: =+AH29+AJ29 -> 461472.74 | AO29: =+AI29+AK29 -> 294802.34 | AP29: 73480 | AQ29: 46008.41 | AR29: =+AN29+AP29 -> 534952.74 | AS29: =+AO29+AQ29 -> 340810.75 | AT29: 66800 | AU29: 48785.52 | AV29: =+AR29+AT29 -> 601752.74 | AW29: =+AS29+AU29 -> 389596.27 | AX29: 73122.4 | AY29: 50951 | AZ29: =+AP29+AT29+AX29 -> 213402.4 | BA29: =+AQ29+AU29+AY29 -> 145744.93 | BB29: =+AL29+AZ29 -> 408492 | BC29: =+AM29+BA29 -> 269872.69 | BD29: =+AV29+AX29 -> 674875.14 | BE29: =+AW29+AY29 -> 440547.27 | BF29: 800000 | BG29: 632220.18 | BH29: 164556.92 | BI29: =+AO29+BH29 -> 459359.26 | BJ29: =+BI29/1000000 -> 0.45935926
B30: US Mill | C30: Mt | D30: 0 | E30: 0 | F30: 0 | G30: 0 | H30: =+D30+F30 -> 0 | I30: =+E30+G30 -> 0 | J30: 0 | K30: 0 | L30: =+H30+J30 -> 0 | M30: =+I30+K30 -> 0 | N30: 7000 | O30: 0 | P30: =+L30+N30 -> 7000 | Q30: =+M30+O30 -> 0 | R30: 8000 | S30: 0 | T30: =+P30+R30 -> 15000 | U30: =+Q30+S30 -> 0 | V30: 10000 | W30: 0 | X30: =+N30+R30+V30 -> 25000 | Y30: =+O30+S30+W30 -> 0 | Z30: =+T30+V30 -> 25000 | AA30: =+U30+W30 -> 0 | AB30: 10000 | AC30: 16462.166 | AD30: =+Z30+AB30 -> 35000 | AE30: =+AA30+AC30 -> 16462.166 | AF30: 40000 | AG30: 18653.11 | AH30: =+AD30+AF30 -> 75000 | AI30: =+AE30+AG30 -> 35115.276 | AJ30: 30000 | AK30: 10177.08 | AL30: =+AB30+AF30+AJ30 -> 80000 | AM30: =+AC30+AG30+AK30 -> 45292.356 | AN30: =+AH30+AJ30 -> 105000 | AO30: =+AI30+AK30 -> 45292.356 | AP30: 35000 | AQ30: 13495.918 | AR30: =+AN30+AP30 -> 140000 | AS30: =+AO30+AQ30 -> 58788.274 | AT30: 35000 | AU30: 19064.62 | AV30: =+AR30+AT30 -> 175000 | AW30: =+AS30+AU30 -> 77852.894 | AX30: 45000 | AY30: 11091 | AZ30: =+AP30+AT30+AX30 -> 115000 | BA30: =+AQ30+AU30+AY30 -> 43651.538 | BB30: =+AL30+AZ30 -> 195000 | BC30: =+AM30+BA30 -> 88943.894 | BD30: =+AV30+AX30 -> 220000 | BE30: =+AW30+AY30 -> 88943.894 | BF30: 535000 | BG30: 171634.81 | BH30: 51262.006 | BI30: =+AO30+BH30 -> 96554.362 | BJ30: =+BI30/1000000 -> 0.096554362
B31: Finished Steel | C31: Mt | D31: =SUM(D28:D30) -> 22439.54 | E31: =SUM(E28:E30) -> 22439.54 | F31: =SUM(F28:F30) -> 61380 | G31: =SUM(G28:G30) -> 61380 | H31: =SUM(H28:H30) -> 83819.54 | I31: =SUM(I28:I30) -> 83819.54 | J31: =SUM(J28:J30) -> 77908 | K31: =SUM(K28:K30) -> 63487.589 | ... BA31: =SUM(BA28:BA30) -> 294421 | BB31: =+AL31+AZ31 -> 869513.56 | BC31: =+AM31+BA31 -> 558245.07 | BD31: =SUM(BD28:BD30) -> 1330841.1 | BE31: =SUM(BE28:BE30) -> 886009.82 | BF31: =SUM(BF28:BF30) -> 1835000 | BG31: =SUM(BG28:BG30) -> 1215880.2
B32: 150x150 mm | C32: Mt | D32: 73040 | E32: 73040 | F32: 29860 | G32: 29860 | H32: =+D32+F32 -> 102900 | I32: =+E32+G32 -> 102900 | J32: 33200 | K32: 28297 | L32: =+H32+J32 -> 136100 | M32: =+I32+K32 -> 131197 | N32: 70000 | O32: 63899.25 | P32: =+L32+N32 -> 206100 | Q32: =+M32+O32 -> 195096.25 | R32: 72000 | S32: =67757.59+2 -> 67759.59 | T32: =+P32+R32 -> 278100 | U32: =+Q32+S32 -> 262855.84 | V32: 75000 | W32: 25573.64 | X32: =+N32+R32+V32 -> 217000 | Y32: =+O32+S32+W32 -> 157232.48 | Z32: =+T32+V32 -> 353100 | AA32: =+U32+W32 -> 288429.48 | AB32: 0 | AC32: 7100 | AD32: =+Z32+AB32 -> 353100 | AE32: =+AA32+AC32 -> 295529.48 | AF32: 31910.882 | AG32: =33228.37+22 -> 33250.37 | AH32: =+AD32+AF32 -> 385010.88 | AI32: =+AE32+AG32 -> 328779.85 | AJ32: 38425.609 | AK32: 49987.88 | AL32: =+AB32+AF32+AJ32 -> 70336.491 | AM32: =+AC32+AG32+AK32 -> 90338.25 | AN32: =+AH32+AJ32 -> 423436.49 | AO32: =+AI32+AK32 -> 378767.73 | AP32: 38089.326 | AQ32: 71742 | AR32: =+AN32+AP32 -> 461525.82 | AS32: =+AO32+AQ32 -> 450509.73 | AT32: 34053 | AU32: 72217 | AV32: =+AR32+AT32 -> 495578.82 | AW32: =+AS32+AU32 -> 522726.73 | AX32: 37477 | AY32: 85769 | AZ32: =+AP32+AT32+AX32 -> 109619.33 | BA32: =+AQ32+AU32+AY32 -> 229728 | BB32: =+AL32+AZ32 -> 179955.82 | BC32: =+AM32+BA32 -> 320066.25 | BD32: =+AV32+AX32 -> 533055.82 | BE32: =+AW32+AY32 -> 608495.73 | BF32: 304999.74 | BG32: 629438.96
B33: 200x280 mm | C33: Mt | D33: 21768 | E33: 21768 | F33: 36077 | G33: 36077 | H33: =+D33+F33 -> 57845 | I33: =+E33+G33 -> 57845 | J33: 44642 | K33: 43155.668 | L33: =+H33+J33 -> 102487 | M33: =+I33+K33 -> 101000.67 | N33: 49500 | O33: 59289.8 | P33: =+L33+N33 -> 151987 | Q33: =+M33+O33 -> 160290.47 | R33: 50000 | S33: 40294.224 | T33: =+P33+R33 -> 201987 | U33: =+Q33+S33 -> 200584.69 | V33: 46000 | W33: 11235.674 | X33: =+N33+R33+V33 -> 145500 | Y33: =+O33+S33+W33 -> 110819.7 | Z33: =+T33+V33 -> 247987 | AA33: =+U33+W33 -> 211820.37 | AB33: 9175.3772 | AC33: 7360 | AD33: =+Z33+AB33 -> 257162.38 | AE33: =+AA33+AC33 -> 219180.37 | AF33: 20595.217 | AG33: 7790 | AH33: =+AD33+AF33 -> 277757.59 | AI33: =+AE33+AG33 -> 226970.37 | AJ33: 31252.038 | AK33: 19962.438 | AL33: =+AB33+AF33+AJ33 -> 61022.632 | AM33: =+AC33+AG33+AK33 -> 35112.438 | AN33: =+AH33+AJ33 -> 309009.63 | AO33: =+AI33+AK33 -> 246932.8 | AP33: 23177.377 | AQ33: 23925 | AR33: =+AN33+AP33 -> 332187.01 | AS33: =+AO33+AQ33 -> 270857.8 | AT33: 21445 | AU33: 19587 | AV33: =+AR33+AT33 -> 353632.01 | AW33: =+AS33+AU33 -> 290444.8 | AX33: 17746 | AY33: =+SMS!AY40+SMS!AY42 -> 38934 | AZ33: =+AP33+AT33+AX33 -> 62368.377 | BA33: =+AQ33+AU33+AY33 -> 82446 | BB33: =+AL33+AZ33 -> 123391.01 | BC33: =+AM33+BA33 -> 117558.44 | BD33: =+AV33+AX33 -> 371378.01 | BE33: =+AW33+AY33 -> 329378.8 | BF33: 267000 | BG33: 248401
B34: Saleable Semis | C34: Mt | D34: =SUM(D32:D33) -> 94808 | E34: =SUM(E32:E33) -> 94808 | F34: =SUM(F32:F33) -> 65937 | G34: =SUM(G32:G33) -> 65937 | H34: =SUM(H32:H33) -> 160745 | I34: =SUM(I32:I33) -> 160745 | J34: =SUM(J32:J33) -> 77842 | K34: =SUM(K32:K33) -> 71452.668 | ... BA34: =SUM(BA32:BA33) -> 312174 | BB34: =+AL34+AZ34 -> 303346.83 | BC34: =+AM34+BA34 -> 437624.69 | BD34: =SUM(BD32:BD33) -> 904433.83 | BE34: =SUM(BE32:BE33) -> 937874.53 | BF34: =SUM(BF32:BF33) -> 571999.74 | BG34: =SUM(BG32:BG33) -> 877839.96 | BH34: 247541.93 | BI34: =+AO34+BH34 -> 873242.46 | BJ34: =+BI34/1000000 -> 0.87324246
B35: TOTAL | C35: Mt | D35: =+D31+D34 -> 117247.54 | E35: =+E31+E34 -> 117247.54 | F35: =+F31+F34 -> 127317 | G35: =+G31+G34 -> 127317 | H35: =+H31+H34 -> 244564.54 | I35: =+I31+I34 -> 244564.54 | J35: =+J31+J34 -> 155750 | K35: =+K31+K34 -> 134940.26 | ... BA35: =+BA31+BA34 -> 606595 | BB35: =+AL35+AZ35 -> 1172860.4 | BC35: =+AM35+BA35 -> 995869.76 | BD35: =+BD31+BD34 -> 2235274.9 | BE35: =+BE31+BE34 -> 1823884.4 | BF35: =+BF31+BF34 -> 2406999.7 | BG35: =+BG31+BG34 -> 2093720.2 | BH35: =+BH28+BH29+BH30+BH34 -> 570127.31 | BI35: =+AO35+BH35 -> 1787416.7 | BJ35: =+BI35/1000000 -> 1.7874167
B36: SAL STEEL PRODN (CATEGORY WISE) | AJ36: =+AJ28+AJ29 -> 119239.64 | AK36: =+AK28+AK29 -> 90046.606
B37: Wire Rod Plain Coils | C37: Mt | D37: =+D28 -> 14366.4 | E37: 8786.3 | F37: =+F28 -> 17668 | G37: 16479.612 | H37: =+D37+F37 -> 32034.4 | I37: =+E37+G37 -> 25265.912 | J37: =+J28 -> 35910 | K37: 25935.228 | L37: =+H37+J37 -> 67944.4 | M37: =+I37+K37 -> 51201.14 | N37: =+N28 -> 35000 | O37: 32647.336 | P37: =+L37+N37 -> 102944.4 | Q37: =+M37+O37 -> 83848.476 | R37: =+R28 -> 35000 | S37: 34032.42 | T37: =+P37+R37 -> 137944.4 | U37: =+Q37+S37 -> 117880.9 | V37: =+V28 -> 32000 | W37: 27037.868 | X37: =+N37+R37+V37 -> 102000 | Y37: =+O37+S37+W37 -> 93717.624 | Z37: =+T37+V37 -> 169944.4 | AA37: =+U37+W37 -> 144918.76 | AB37: =+AB28 -> 40000 | AC37: 26925.816 | AD37: =+Z37+AB37 -> 209944.4 | AE37: =+AA37+AC37 -> 171844.58 | AF37: =+AF28 -> 45249.811 | AG37: 32756.97 | AH37: =+AD37+AF37 -> 255194.21 | AI37: =+AE37+AG37 -> 204601.55 | AJ37: =+AJ28 -> 46294.038 | AK37: 34721.176 | AL37: =+AB37+AF37+AJ37 -> 131543.85 | AM37: =+AC37+AG37+AK37 -> 94403.962 | AN37: =+AH37+AJ37 -> 301488.25 | AO37: =+AI37+AK37 -> 239322.73 | AP37: =+AP28 -> 46294.038 | AQ37: 36021.128 | AR37: =+AN37+AP37 -> 347782.29 | AS37: =+AO37+AQ37 -> 275343.85 | AT37: =+AT28 -> 41769 | AU37: =+AU28-AU38 -> 23689.71 | AV37: =+AR37+AT37 -> 389551.29 | AW37: =+AS37+AU37 -> 299033.56 | AX37: =+AX28 -> 46414.675 | AY37: =+AY28-AY38 -> 38003 | AZ37: =+AP37+AT37+AX37 -> 134477.71 | BA37: =+AQ37+AU37+AY37 -> 97713.838 | BB37: =+AL37+AZ37 -> 266021.56 | BC37: =+AM37+BA37 -> 192117.8 | BD37: =+AV37+AX37 -> 435965.96 | BE37: =+AW37+AY37 -> 337036.56 | BF37: =+BF28 -> 500000 | BG37: 270654.57
B38: TMT Coils | C38: Mt | E38: 5580.1 | G38: 1188.108 | I38: =+E38+G38 -> 6768.208 | K38: 5402.916 | M38: =+I38+K38 -> 12171.124 | O38: 0 | Q38: =+M38+O38 -> 12171.124 | S38: 0 | U38: =+Q38+S38 -> 12171.124 | W38: 0 | Y38: =+O38+S38+W38 -> 0 | AA38: =+U38+W38 -> 12171.124 | AC38: 0 | AE38: =+AA38+AC38 -> 12171.124 | AG38: 0 | AI38: =+AE38+AG38 -> 12171.124 | AK38: 0 | AM38: =+AC38+AG38+AK38 -> 0 | AO38: =+AI38+AK38 -> 12171.124 | AQ38: 0 | AS38: =+AO38+AQ38 -> 12171.124 | AU38: 7310.69 | AW38: =+AS38+AU38 -> 19481.814 | BA38: =+AQ38+AU38+AY38 -> 7310.69 | BB38: =+AL38+AZ38 -> 0 | BC38: =+AM38+BA38 -> 7310.69 | BE38: =+AW38+AY38 -> 19481.814 | BG38: 141370.65
B39: TMT Bars | C39: Mt | D39: =+D29 -> 8073.14 | E39: 8073.14 | F39: =+F29 -> 43712 | G39: 43711.875 | H39: =+D39+F39 -> 51785.14 | I39: =+E39+G39 -> 51785.015 | J39: =+J29 -> 41998 | K39: 32149.445 | L39: =+H39+J39 -> 93783.14 | M39: =+I39+K39 -> 83934.46 | N39: =+N29 -> 59600 | O39: 24173.96 | P39: =+L39+N39 -> 153383.14 | Q39: =+M39+O39 -> 108108.42 | R39: =+R29 -> 55000 | S39: 30791.565 | T39: =+P39+R39 -> 208383.14 | U39: =+Q39+S39 -> 138899.98 | V39: =+V29 -> 58000 | W39: 31774.47 | X39: =+N39+R39+V39 -> 172600 | Y39: =+O39+S39+W39 -> 86739.995 | Z39: =+T39+V39 -> 266383.14 | AA39: =+U39+W39 -> 170674.45 | AB39: =+AB29 -> 50000 | AC39: 29425.245 | AD39: =+Z39+AB39 -> 316383.14 | AE39: =+AA39+AC39 -> 200099.7 | AF39: =+AF29 -> 72144 | AG39: 39377.085 | AH39: =+AD39+AF39 -> 388527.14 | AI39: =+AE39+AG39 -> 239476.78 | AJ39: =+AJ29 -> 72945.6 | AK39: =+AK29 -> 55325.43 | AL39: =+AB39+AF39+AJ39 -> 195089.6 | AM39: =+AC39+AG39+AK39 -> 124127.76 | AN39: =+AH39+AJ39 -> 461472.74 | AO39: =+AI39+AK39 -> 294802.21 | AP39: =+AP29 -> 73480 | AQ39: =+AQ29 -> 46008.41 | AR39: =+AN39+AP39 -> 534952.74 | AS39: =+AO39+AQ39 -> 340810.62 | AT39: =+AT29 -> 66800 | AU39: =+AU29 -> 48785.52 | AV39: =+AR39+AT39 -> 601752.74 | AW39: =+AS39+AU39 -> 389596.14 | AX39: =+AX29 -> 73122.4 | AY39: =+AY29 -> 50951 | AZ39: =+AP39+AT39+AX39 -> 213402.4 | BA39: =+AQ39+AU39+AY39 -> 145744.93 | BB39: =+AL39+AZ39 -> 408492 | BC39: =+AM39+BA39 -> 269872.69 | BD39: =+AV39+AX39 -> 674875.14 | BE39: =+AW39+AY39 -> 440547.14 | BF39: =+BF29 -> 800000 | BG39: 632220.18
B40: NPB/IPE | C40: Mt | D40: =+D30 -> 0 | E40: 0 | F40: =+F30 -> 0 | G40: 0 | H40: =+D40+F40 -> 0 | I40: =+E40+G40 -> 0 | J40: =+J30 -> 0 | K40: 0 | L40: =+H40+J40 -> 0 | M40: =+I40+K40 -> 0 | N40: =+N30 -> 7000 | O40: 0 | P40: =+L40+N40 -> 7000 | Q40: =+M40+O40 -> 0 | R40: =+R30 -> 8000 | S40: 0 | T40: =+P40+R40 -> 15000 | U40: =+Q40+S40 -> 0 | V40: =+V30 -> 10000 | W40: 0 | X40: =+N40+R40+V40 -> 25000 | Y40: =+O40+S40+W40 -> 0 | Z40: =+T40+V40 -> 25000 | AA40: =+U40+W40 -> 0 | AB40: =+AB30 -> 10000 | AC40: 16462.166 | AD40: =+Z40+AB40 -> 35000 | AE40: =+AA40+AC40 -> 16462.166 | AF40: =+AF30 -> 40000 | AG40: 18653.11 | AH40: =+AD40+AF40 -> 75000 | AI40: =+AE40+AG40 -> 35115.276 | AJ40: =+AJ30 -> 30000 | AK40: 10177.08 | AL40: =+AB40+AF40+AJ40 -> 80000 | AM40: =+AC40+AG40+AK40 -> 45292.356 | AN40: =+AH40+AJ40 -> 105000 | AO40: =+AI40+AK40 -> 45292.356 | AP40: =+AP30 -> 35000 | AQ40: 11278.373 | AR40: =+AN40+AP40 -> 140000 | AS40: =+AO40+AQ40 -> 56570.729 | AT40: =+AT30 -> 35000 | AU40: 17295.42 | AV40: =+AR40+AT40 -> 175000 | AW40: =+AS40+AU40 -> 73866.149 | AX40: =+AX30 -> 45000 | AZ40: =+AP40+AT40+AX40 -> 115000 | BA40: =+AQ40+AU40+AY40 -> 28573.793 | BB40: =+AL40+AZ40 -> 195000 | BC40: =+AM40+BA40 -> 73866.149 | BD40: =+AV40+AX40 -> 220000 | BE40: =+AW40+AY40 -> 73866.149 | BF40: =+BF30 -> 535000 | BG40: 171635
B41: Channels | C41: Mt | E41: 0 | G41: 0 | H41: =+D41+F41 -> 0 | I41: =+E41+G41 -> 0 | K41: 0 | L41: =+H41+J41 -> 0 | M41: =+I41+K41 -> 0 | O41: 0 | P41: =+L41+N41 -> 0 | Q41: =+M41+O41 -> 0 | S41: 0 | T41: =+P41+R41 -> 0 | U41: =+Q41+S41 -> 0 | W41: 0 | X41: =+N41+R41+V41 -> 0 | Y41: =+O41+S41+W41 -> 0 | Z41: =+T41+V41 -> 0 | AA41: =+U41+W41 -> 0 | AC41: 0 | AD41: =+Z41+AB41 -> 0 | AE41: =+AA41+AC41 -> 0 | AG41: 0 | AH41: =+AD41+AF41 -> 0 | AI41: =+AE41+AG41 -> 0 | AK41: 0 | AL41: =+AB41+AF41+AJ41 -> 0 | AM41: =+AC41+AG41+AK41 -> 0 | AN41: =+AH41+AJ41 -> 0 | AO41: =+AI41+AK41 -> 0 | AQ41: 224.01905 | AR41: =+AN41+AP41 -> 0 | AS41: =+AO41+AQ41 -> 224.01905 | AU41: 1769.2 | AV41: =+AR41+AT41 -> 0 | AW41: =+AS41+AU41 -> 1993.219 | AZ41: =+AP41+AT41+AX41 -> 0 | BA41: =+AQ41+AU41+AY41 -> 1993.219 | BB41: =+AL41+AZ41 -> 0 | BC41: =+AM41+BA41 -> 1993.219 | BD41: =+AV41+AX41 -> 0 | BE41: =+AW41+AY41 -> 1993.219
B42: Angles | C42: Mt | E42: 0 | G42: 0 | H42: =+D42+F42 -> 0 | I42: =+E42+G42 -> 0 | K42: 0 | L42: =+H42+J42 -> 0 | M42: =+I42+K42 -> 0 | O42: 0 | P42: =+L42+N42 -> 0 | Q42: =+M42+O42 -> 0 | S42: 0 | T42: =+P42+R42 -> 0 | U42: =+Q42+S42 -> 0 | W42: 0 | X42: =+N42+R42+V42 -> 0 | Y42: =+O42+S42+W42 -> 0 | Z42: =+T42+V42 -> 0 | AA42: =+U42+W42 -> 0 | AC42: 0 | AD42: =+Z42+AB42 -> 0 | AE42: =+AA42+AC42 -> 0 | AG42: 0 | AH42: =+AD42+AF42 -> 0 | AI42: =+AE42+AG42 -> 0 | AK42: 0 | AL42: =+AB42+AF42+AJ42 -> 0 | AM42: =+AC42+AG42+AK42 -> 0 | AN42: =+AH42+AJ42 -> 0 | AO42: =+AI42+AK42 -> 0 | AQ42: 1993.5256 | AR42: =+AN42+AP42 -> 0 | AS42: =+AO42+AQ42 -> 1993.5256 | AU42: 0 | AV42: =+AR42+AT42 -> 0 | AW42: =+AS42+AU42 -> 1993.5256 | AY42: 0 | AZ42: =+AP42+AT42+AX42 -> 0 | BA42: =+AQ42+AU42+AY42 -> 1993.5256 | BB42: =+AL42+AZ42 -> 0 | BC42: =+AM42+BA42 -> 1993.5256 | BD42: =+AV42+AX42 -> 0 | BE42: =+AW42+AY42 -> 1993.5256
B43: Semis | C43: Mt | D43: =+D34 -> 94808 | E43: =+E34 -> 94808 | F43: =+F34 -> 65937 | G43: =+G34 -> 65937 | H43: =+H34 -> 160745 | I43: =+I34 -> 160745 | J43: =+J34 -> 77842 | K43: =+K34 -> 71452.668 | ... BA43: =+BA34 -> 312174 | BB43: =+AL43+AZ43 -> 303346.83 | BC43: =+AM43+BA43 -> 437624.69 | BD43: =+BD34 -> 904433.83 | BE43: =+BE34 -> 937874.53 | BF43: =+BF34 -> 571999.74 | BG43: =+BG34 -> 877839.96
B44: TOTAL | C44: Mt | D44: =SUM(D37:D43) -> 117247.54 | E44: =SUM(E37:E43) -> 117247.54 | F44: =SUM(F37:F43) -> 127317 | G44: =SUM(G37:G43) -> 127316.6 | H44: =SUM(H37:H43) -> 244564.54 | I44: =SUM(I37:I43) -> 244564.14 | J44: =SUM(J37:J43) -> 155750 | K44: =SUM(K37:K43) -> 134940.26 | ... BA44: =SUM(BA37:BA43) -> 595504 | BB44: =+AL44+AZ44 -> 1172860.4 | BC44: =+AM44+BA44 -> 984778.76 | BD44: =SUM(BD37:BD43) -> 2235274.9 | BE44: =SUM(BE37:BE43) -> 1812793 | BF44: =SUM(BF37:BF43) -> 2406999.7 | BG44: =SUM(BG37:BG43) -> 2093720.4
B45: COAL TAR | C45: Mt | D45: 3335.2 | E45: =1204+2131.2 -> 3335.2 | F45: 3568.2 | G45: =2204.4+1363.8 -> 3568.2 | H45: =+D45+F45 -> 6903.4 | I45: =+E45+G45 -> 6903.4 | J45: 3720.923 | K45: 1428.5 | L45: =+H45+J45 -> 10624.323 | M45: =+I45+K45 -> 8331.9 | N45: 4294.7586 | O45: =1554.8+2665.34 -> 4220.14 | P45: =+L45+N45 -> 14919.082 | Q45: =+M45+O45 -> 12552.04 | R45: 4294.7586 | S45: =1857.5+2902.92 -> 4760.42 | T45: =+P45+R45 -> 19213.84 | U45: =+Q45+S45 -> 17312.46 | V45: 4156.218 | W45: =1524.3+2373.82 -> 3898.12 | X45: =+N45+R45+V45 -> 12745.735 | Y45: =+O45+S45+W45 -> 12878.68 | Z45: =+T45+V45 -> 23370.058 | AA45: =+U45+W45 -> 21210.58 | AB45: 4294.7586 | AC45: =1591+2695.14 -> 4286.14 | AD45: =+Z45+AB45 -> 27664.817 | AE45: =+AA45+AC45 -> 25496.72 | AF45: 4156.218 | AG45: =1270.8+2516.74 -> 3787.54 | AH45: =+AD45+AF45 -> 31821.035 | AI45: =+AE45+AG45 -> 29284.26 | AJ45: 4294.7586 | AK45: =2900.08+1584.2 -> 4484.28 | AL45: =+AB45+AF45+AJ45 -> 12745.735 | AM45: =+AC45+AG45+AK45 -> 12557.96 | AN45: =+AH45+AJ45 -> 36115.793 | AO45: =+AI45+AK45 -> 33768.54 | AP45: 4294.7586 | AQ45: 4464.21 | AR45: =+AN45+AP45 -> 40410.552 | AS45: =+AO45+AQ45 -> 38232.75 | AT45: 3879 | AU45: =+'COKE OVENS'!AU41 -> 4004.74 | AV45: =+AR45+AT45 -> 44289.552 | AW45: =+AS45+AU45 -> 42237.49 | AX45: 4294.759 | AY45: =+'COKE OVENS'!AY41 -> 4441.46 | AZ45: =+AP45+AT45+AX45 -> 12468.518 | BA45: =+AQ45+AU45+AY45 -> 12910.41 | BB45: =+AL45+AZ45 -> 25214.253 | BC45: =+AM45+BA45 -> 25468.37 | BD45: =+AV45+AX45 -> 48584.311 | BE45: =+AW45+AY45 -> 46678.95 | BF45: 46118.873 | BG45: 49237.57
B46: AMMONIUM SULPHATE | C46: Mt | D46: 780.2 | E46: =375+405.2 -> 780.2 | F46: 694 | G46: =281.5+412.5 -> 694 | H46: =+D46+F46 -> 1474.2 | I46: =+E46+G46 -> 1474.2 | J46: 1056.9781 | K46: =345.3+318 -> 663.3 | L46: =+H46+J46 -> 2531.1781 | M46: =+I46+K46 -> 2137.5 | N46: 2170.4448 | O46: =324+499.2 -> 823.2 | P46: =+L46+N46 -> 4701.6229 | Q46: =+M46+O46 -> 2960.7 | R46: 2170.4448 | S46: =320.5+533.2 -> 853.7 | T46: =+P46+R46 -> 6872.0677 | U46: =+Q46+S46 -> 3814.4 | V46: 2099.225 | W46: =382+478 -> 860 | X46: =+N46+R46+V46 -> 6440.1146 | Y46: =+O46+S46+W46 -> 2536.9 | Z46: =+T46+V46 -> 8971.2927 | AA46: =+U46+W46 -> 4674.4 | AB46: 2170.4448 | AC46: =518.8+430 -> 948.8 | AD46: =+Z46+AB46 -> 11141.737 | AE46: =+AA46+AC46 -> 5623.2 | AF46: 2099.225 | AG46: =554.69+350 -> 904.69 | AH46: =+AD46+AF46 -> 13240.962 | AI46: =+AE46+AG46 -> 6527.89 | AJ46: 2170.4448 | AK46: =571.72+613 -> 1184.72 | AL46: =+AB46+AF46+AJ46 -> 6440.1146 | AM46: =+AC46+AG46+AK46 -> 3038.21 | AN46: =+AH46+AJ46 -> 15411.407 | AO46: =+AI46+AK46 -> 7712.61 | AP46: 2170.4448 | AQ46: 864.5 | AR46: =+AN46+AP46 -> 17581.852 | AS46: =+AO46+AQ46 -> 8577.11 | AT46: 1977 | AU46: =+'COKE OVENS'!AU44 -> 894.3 | AV46: =+AR46+AT46 -> 19558.852 | AW46: =+AS46+AU46 -> 9471.41 | AX46: 2170 | AY46: =+'COKE OVENS'!AY44 -> 1039.2 | AZ46: =+AP46+AT46+AX46 -> 6317.4448 | BA46: =+AQ46+AU46+AY46 -> 2798 | BB46: =+AL46+AZ46 -> 12757.559 | BC46: =+AM46+BA46 -> 5836.21 | BD46: =+AV46+AX46 -> 21728.852 | BE46: =+AW46+AY46 -> 10510.61 | BF46: 15654.415 | BG46: 12312.8
B48: MILL PRODUCTION (Arisings & Prime)
B49: WR MILL
B50: Gross | C50: Mt | D50: =+D28 -> 14366.4 | E50: =+E28 -> 14366.4 | F50: =+F28 -> 17668 | G50: =+G28 -> 17668 | H50: =+D50+F50 -> 32034.4 | I50: =+E50+G50 -> 32034.4 | J50: =+J28 -> 35910 | K50: =+K28 -> 31338.144 | L50: =+H50+J50 -> 67944.4 | M50: =+I50+K50 -> 63372.544 | N50: =+N28 -> 35000 | O50: =+O28 -> 32647.336 | P50: =+L50+N50 -> 102944.4 | Q50: =+M50+O50 -> 96019.88 | R50: =+R28 -> 35000 | S50: =+S28 -> 34032.42 | T50: =+P50+R50 -> 137944.4 | U50: =+Q50+S50 -> 130052.3 | V50: =+V28 -> 32000 | W50: =+W28 -> 27037.868 | X50: =+N50+R50+V50 -> 102000 | Y50: =+O50+S50+W50 -> 93717.624 | Z50: =+T50+V50 -> 169944.4 | AA50: =+U50+W50 -> 157090.17 | AB50: =+AB28 -> 40000 | AC50: =+AC28 -> 26925.816 | AD50: =+Z50+AB50 -> 209944.4 | AE50: =+AA50+AC50 -> 184015.98 | AF50: =+AF28 -> 45249.811 | AG50: =+AG28 -> 32756.97 | AH50: =+AD50+AF50 -> 255194.21 | AI50: =+AE50+AG50 -> 216772.95 | AJ50: =+AJ28 -> 46294.038 | AK50: =+AK28 -> 34721.176 | AL50: =+AB50+AF50+AJ50 -> 131543.85 | AM50: =+AC50+AG50+AK50 -> 94403.962 | AN50: =+AH50+AJ50 -> 301488.25 | AO50: =+AI50+AK50 -> 251494.13 | AP50: =+AP28 -> 46294.038 | AQ50: =+AQ28 -> 36021.128 | AR50: =+AN50+AP50 -> 347782.29 | AS50: =+AO50+AQ50 -> 287515.26 | AT50: =+AT28 -> 41769 | AU50: =+AU28 -> 31000.4 | AV50: =+AR50+AT50 -> 389551.29 | AW50: =+AS50+AU50 -> 318515.66 | AX50: =+AX28 -> 46414.675 | AY50: =+AY28 -> 38003 | AZ50: =+AP50+AT50+AX50 -> 134477.71 | BA50: =+AQ50+AU50+AY50 -> 105024.53 | BB50: =+AL50+AZ50 -> 266021.56 | BC50: =+AM50+BA50 -> 199428.49 | BD50: =+AV50+AX50 -> 435965.96 | BE50: =+AW50+AY50 -> 356518.66 | BF50: 500000 | BG50: 412025.22
B51: Rejections | C51: Mt | D51: =+D50-((D50-(D50*0))) -> 0 | E51: =+WRM!F96 -> 149.04 | F51: =+F50-((F50-(F50*0))) -> 0 | G51: =+WRM!H96 -> 336.93 | H51: =+D51+F51 -> 0 | I51: =+E51+G51 -> 485.97 | J51: =+J50-((J50-(J50*0))) -> 0 | K51: =+WRM!L96 -> 529.416 | L51: =+H51+J51 -> 0 | M51: =+I51+K51 -> 1015.386 | N51: =+N50-((N50-(N50*0))) -> 0 | O51: =+WRM!P96 -> 500.04 | P51: =+L51+N51 -> 0 | Q51: =+M51+O51 -> 1515.426 | R51: =+R50-((R50-(R50*0))) -> 0 | S51: =+WRM!T96 -> 728.46 | T51: =+P51+R51 -> 0 | U51: =+Q51+S51 -> 2243.886 | V51: =+V50-((V50-(V50*0))) -> 0 | W51: =+WRM!X96 -> 313.974 | X51: =+N51+R51+V51 -> 0 | Y51: =+O51+S51+W51 -> 1542.474 | Z51: =+T51+V51 -> 0 | AA51: =+U51+W51 -> 2557.86 | AB51: =+AB50-((AB50-(AB50*0))) -> 0 | AC51: =+WRM!AD96 -> 322.174 | AD51: =+Z51+AB51 -> 0 | AE51: =+AA51+AC51 -> 2880.034 | AF51: =+AF50-((AF50-(AF50*0))) -> 0 | AG51: =+WRM!AH96 -> 350.854 | AH51: =+AD51+AF51 -> 0 | AI51: =+AE51+AG51 -> 3230.888 | AJ51: =+AJ50-((AJ50-(AJ50*0))) -> 0 | AK51: =+WRM!AL96 -> 240.018 | AL51: =+AB51+AF51+AJ51 -> 0 | AM51: =+AC51+AG51+AK51 -> 913.046 | AN51: =+AH51+AJ51 -> 0 | AO51: =+AI51+AK51 -> 3470.906 | AP51: =+AP50-((AP50-(AP50*0))) -> 0 | AQ51: =+WRM!AR96 -> 370.442 | AR51: =+AN51+AP51 -> 0 | AS51: =+AO51+AQ51 -> 3841.348 | AT51: =+AT50-((AT50-(AT50*0))) -> 0 | AU51: =+WRM!AV96 -> 119.416 | AV51: =+AR51+AT51 -> 0 | AW51: =+AS51+AU51 -> 3960.764 | AX51: =+AX50-((AX50-(AX50*0))) -> 0 | AY51: =+WRM!AZ96 -> 419.742 | AZ51: =+AP51+AT51+AX51 -> 0 | BA51: =+AQ51+AU51+AY51 -> 909.6 | BB51: =+AL51+AZ51 -> 0 | BC51: =+AM51+BA51 -> 1822.646 | BD51: =+AV51+AX51 -> 0 | BE51: =+AW51+AY51 -> 4380.506 | BF51: 2200 | BG51: 4165.17
B52: Prime & Saleable Length | C52: Mt | D52: =+D50-D51 -> 14366.4 | E52: =+E50-E51 -> 14217.36 | F52: =+F50-F51 -> 17668 | G52: =+G50-G51 -> 17331.07 | H52: =+D52+F52 -> 32034.4 | I52: =+E52+G52 -> 31548.43 | J52: =+J50-J51 -> 35910 | K52: =+K50-K51 -> 30808.728 | L52: =+H52+J52 -> 67944.4 | M52: =+I52+K52 -> 62357.158 | N52: =+N50-N51 -> 35000 | O52: =+O50-O51 -> 32147.296 | P52: =+L52+N52 -> 102944.4 | Q52: =+M52+O52 -> 94504.454 | R52: =+R50-R51 -> 35000 | S52: =+S50-S51 -> 33303.96 | T52: =+P52+R52 -> 137944.4 | U52: =+Q52+S52 -> 127808.41 | V52: =+V50-V51 -> 32000 | W52: =+W50-W51 -> 26723.894 | X52: =+N52+R52+V52 -> 102000 | Y52: =+O52+S52+W52 -> 92175.15 | Z52: =+T52+V52 -> 169944.4 | AA52: =+U52+W52 -> 154532.31 | AB52: =+AB50-AB51 -> 40000 | AC52: =+AC50-AC51 -> 26603.642 | AD52: =+Z52+AB52 -> 209944.4 | AE52: =+AA52+AC52 -> 181135.95 | AF52: =+AF50-AF51 -> 45249.811 | AG52: =+AG50-AG51 -> 32406.116 | AH52: =+AD52+AF52 -> 255194.21 | AI52: =+AE52+AG52 -> 213542.07 | AJ52: =+AJ50-AJ51 -> 46294.038 | AK52: =+AK50-AK51 -> 34481.158 | AL52: =+AB52+AF52+AJ52 -> 131543.85 | AM52: =+AC52+AG52+AK52 -> 93490.916 | AN52: =+AH52+AJ52 -> 301488.25 | AO52: =+AI52+AK52 -> 248023.22 | AP52: =+AP50-AP51 -> 46294.038 | AQ52: =+AQ50-AQ51 -> 35650.686 | AR52: =+AN52+AP52 -> 347782.29 | AS52: =+AO52+AQ52 -> 283673.91 | AT52: =+AT50-AT51 -> 41769 | AU52: =+AU50-AU51 -> 30880.984 | AV52: =+AR52+AT52 -> 389551.29 | AW52: =+AS52+AU52 -> 314554.89 | AX52: =+AX50-AX51 -> 46414.675 | AY52: =+AY50-AY51 -> 37583.258 | AZ52: =+AP52+AT52+AX52 -> 134477.71 | BA52: =+AQ52+AU52+AY52 -> 104114.93 | BB52: =+AL52+AZ52 -> 266021.56 | BC52: =+AM52+BA52 -> 197605.84 | BD52: =+AV52+AX52 -> 435965.96 | BE52: =+AW52+AY52 -> 352138.15 | BF52: 497800 | BG52: 407860.05
B53: BAR MILL
B54: Gross | C54: Mt | D54: =+D29 -> 8073.14 | E54: =+E29 -> 8073.14 | F54: =+F29 -> 43712 | G54: =+G29 -> 43712 | H54: =+D54+F54 -> 51785.14 | I54: =+E54+G54 -> 51785.14 | J54: =+J29 -> 41998 | K54: =+K29 -> 32149.445 | L54: =+H54+J54 -> 93783.14 | M54: =+I54+K54 -> 83934.585 | N54: =+N29 -> 59600 | O54: =+O29 -> 24173.96 | P54: =+L54+N54 -> 153383.14 | Q54: =+M54+O54 -> 108108.54 | R54: =+R29 -> 55000 | S54: =+S29 -> 30791.565 | T54: =+P54+R54 -> 208383.14 | U54: =+Q54+S54 -> 138900.11 | V54: =+V29 -> 58000 | W54: =+W29 -> 31774.47 | X54: =+N54+R54+V54 -> 172600 | Y54: =+O54+S54+W54 -> 86739.995 | Z54: =+T54+V54 -> 266383.14 | AA54: =+U54+W54 -> 170674.58 | AB54: =+AB29 -> 50000 | AC54: =+AC29 -> 29425.245 | AD54: =+Z54+AB54 -> 316383.14 | AE54: =+AA54+AC54 -> 200099.82 | AF54: =+AF29 -> 72144 | AG54: =+AG29 -> 39377.085 | AH54: =+AD54+AF54 -> 388527.14 | AI54: =+AE54+AG54 -> 239476.91 | AJ54: =+AJ29 -> 72945.6 | AK54: =+AK29 -> 55325.43 | AL54: =+AB54+AF54+AJ54 -> 195089.6 | AM54: =+AC54+AG54+AK54 -> 124127.76 | AN54: =+AH54+AJ54 -> 461472.74 | AO54: =+AI54+AK54 -> 294802.34 | AP54: =+AP29 -> 73480 | AQ54: =+AQ29 -> 46008.41 | AR54: =+AN54+AP54 -> 534952.74 | AS54: =+AO54+AQ54 -> 340810.75 | AT54: =+AT29 -> 66800 | AU54: =+AU29 -> 48785.52 | AV54: =+AR54+AT54 -> 601752.74 | AW54: =+AS54+AU54 -> 389596.27 | AX54: =+AX29 -> 73122.4 | AY54: =+AY29 -> 50951 | AZ54: =+AP54+AT54+AX54 -> 213402.4 | BA54: =+AQ54+AU54+AY54 -> 145744.93 | BB54: =+AL54+AZ54 -> 408492 | BC54: =+AM54+BA54 -> 269872.69 | BD54: =+AV54+AX54 -> 674875.14 | BE54: =+AW54+AY54 -> 440547.27 | BF54: 800000 | BG54: 632220.18
B55: Rejections | C55: Mt | D55: =+D54-((D54-(D54*0))) -> 0 | E55: =+BM!F36 -> 111.56 | F55: =+F54-((F54-(F54*0))) -> 0 | G55: =+BM!H36 -> 497.08 | H55: =+D55+F55 -> 0 | I55: =+E55+G55 -> 608.64 | J55: =+J54-((J54-(J54*0))) -> 0 | K55: =+BM!L36 -> 300.368 | L55: =+H55+J55 -> 0 | M55: =+I55+K55 -> 909.008 | N55: =+N54-((N54-(N54*0))) -> 0 | O55: =+BM!P36 -> 347.5 | P55: =+L55+N55 -> 0 | Q55: =+M55+O55 -> 1256.508 | R55: =+R54-((R54-(R54*0))) -> 0 | S55: =+BM!T36 -> 96.28 | T55: =+P55+R55 -> 0 | U55: =+Q55+S55 -> 1352.788 | V55: =+V54-((V54-(V54*0))) -> 0 | W55: =+BM!X36 -> 170.035 | X55: =+N55+R55+V55 -> 0 | Y55: =+O55+S55+W55 -> 613.815 | Z55: =+T55+V55 -> 0 | AA55: =+U55+W55 -> 1522.823 | AB55: =+AB54-((AB54-(AB54*0))) -> 0 | AC55: =+BM!AD36 -> 49.92 | AD55: =+Z55+AB55 -> 0 | AE55: =+AA55+AC55 -> 1572.743 | AF55: =+AF54-((AF54-(AF54*0))) -> 0 | AG55: =+BM!AH36 -> 36.73 | AH55: =+AD55+AF55 -> 0 | AI55: =+AE55+AG55 -> 1609.473 | AJ55: =+AJ54-((AJ54-(AJ54*0))) -> 0 | AK55: =+BM!AL36 -> 62.818 | AL55: =+AB55+AF55+AJ55 -> 0 | AM55: =+AC55+AG55+AK55 -> 149.468 | AN55: =+AH55+AJ55 -> 0 | AO55: =+AI55+AK55 -> 1672.291 | AP55: =+AP54-((AP54-(AP54*0))) -> 0 | AQ55: =+BM!AR36 -> 12.96 | AR55: =+AN55+AP55 -> 0 | AS55: =+AO55+AQ55 -> 1685.251 | AT55: =+AT54-((AT54-(AT54*0))) -> 0 | AU55: =+BM!AV36 -> 38.582 | AV55: =+AR55+AT55 -> 0 | AW55: =+AS55+AU55 -> 1723.833 | AX55: =+AX54-((AX54-(AX54*0))) -> 0 | AY55: =+BM!AZ36 -> 37.66 | AZ55: =+AP55+AT55+AX55 -> 0 | BA55: =+AQ55+AU55+AY55 -> 89.202 | BB55: =+AL55+AZ55 -> 0 | BC55: =+AM55+BA55 -> 238.67 | BD55: =+AV55+AX55 -> 0 | BE55: =+AW55+AY55 -> 1761.493 | BF55: 2000 | BG55: 4798.5
B56: Prime & Saleable Length | C56: Mt | D56: =+D54-D55 -> 8073.14 | E56: =+E54-E55 -> 7961.58 | F56: =+F54-F55 -> 43712 | G56: =+G54-G55 -> 43214.92 | H56: =+D56+F56 -> 51785.14 | I56: =+E56+G56 -> 51176.5 | J56: =+J54-J55 -> 41998 | K56: =+K54-K55 -> 31849.077 | L56: =+H56+J56 -> 93783.14 | M56: =+I56+K56 -> 83025.577 | N56: =+N54-N55 -> 59600 | O56: =+O54-O55 -> 23826.46 | P56: =+L56+N56 -> 153383.14 | Q56: =+M56+O56 -> 106852.04 | R56: =+R54-R55 -> 55000 | S56: =+S54-S55 -> 30695.285 | T56: =+P56+R56 -> 208383.14 | U56: =+Q56+S56 -> 137547.32 | V56: =+V54-V55 -> 58000 | W56: =+W54-W55 -> 31604.435 | X56: =+N56+R56+V56 -> 172600 | Y56: =+O56+S56+W56 -> 86126.18 | Z56: =+T56+V56 -> 266383.14 | AA56: =+U56+W56 -> 169151.76 | AB56: =+AB54-AB55 -> 50000 | AC56: =+AC54-AC55 -> 29375.325 | AD56: =+Z56+AB56 -> 316383.14 | AE56: =+AA56+AC56 -> 198527.08 | AF56: =+AF54-AF55 -> 72144 | AG56: =+AG54-AG55 -> 39340.355 | AH56: =+AD56+AF56 -> 388527.14 | AI56: =+AE56+AG56 -> 237867.44 | AJ56: =+AJ54-AJ55 -> 72945.6 | AK56: =+AK54-AK55 -> 55262.612 | AL56: =+AB56+AF56+AJ56 -> 195089.6 | AM56: =+AC56+AG56+AK56 -> 123978.29 | AN56: =+AH56+AJ56 -> 461472.74 | AO56: =+AI56+AK56 -> 293130.05 | AP56: =+AP54-AP55 -> 73480 | AQ56: =+AQ54-AQ55 -> 45995.45 | AR56: =+AN56+AP56 -> 534952.74 | AS56: =+AO56+AQ56 -> 339125.5 | AT56: =+AT54-AT55 -> 66800 | AU56: =+AU54-AU55 -> 48746.938 | AV56: =+AR56+AT56 -> 601752.74 | AW56: =+AS56+AU56 -> 387872.44 | AX56: =+AX54-AX55 -> 73122.4 | AY56: =+AY54-AY55 -> 50913.34 | AZ56: =+AP56+AT56+AX56 -> 213402.4 | BA56: =+AQ56+AU56+AY56 -> 145655.73 | BB56: =+AL56+AZ56 -> 408492 | BC56: =+AM56+BA56 -> 269634.02 | BD56: =+AV56+AX56 -> 674875.14 | BE56: =+AW56+AY56 -> 438785.78 | BF56: 798000 | BG56: 627421.68
B57: US MILL
B58: Gross | C58: Mt | D58: =+D30 -> 0 | E58: =+E30 -> 0 | F58: =+F30 -> 0 | G58: =+G30 -> 0 | H58: =+D58+F58 -> 0 | I58: =+E58+G58 -> 0 | J58: =+J30 -> 0 | K58: =+K30 -> 0 | L58: =+H58+J58 -> 0 | M58: =+I58+K58 -> 0 | N58: =+N30 -> 7000 | O58: =+O30 -> 0 | P58: =+L58+N58 -> 7000 | Q58: =+M58+O58 -> 0 | R58: =+R30 -> 8000 | S58: =+S30 -> 0 | T58: =+P58+R58 -> 15000 | U58: =+Q58+S58 -> 0 | V58: =+V30 -> 10000 | W58: =+W30 -> 0 | X58: =+N58+R58+V58 -> 25000 | Y58: =+O58+S58+W58 -> 0 | Z58: =+T58+V58 -> 25000 | AA58: =+U58+W58 -> 0 | AB58: =+AB30 -> 10000 | AC58: =+AC30 -> 16462.166 | AD58: =+Z58+AB58 -> 35000 | AE58: =+AA58+AC58 -> 16462.166 | AF58: =+AF30 -> 40000 | AG58: =+AG30 -> 18653.11 | AH58: =+AD58+AF58 -> 75000 | AI58: =+AE58+AG58 -> 35115.276 | AJ58: =+AJ30 -> 30000 | AK58: =+AK30 -> 10177.08 | AL58: =+AB58+AF58+AJ58 -> 80000 | AM58: =+AC58+AG58+AK58 -> 45292.356 | AN58: =+AH58+AJ58 -> 105000 | AO58: =+AI58+AK58 -> 45292.356 | AP58: =+AP30 -> 35000 | AQ58: =+AQ30 -> 13495.918 | AR58: =+AN58+AP58 -> 140000 | AS58: =+AO58+AQ58 -> 58788.274 | AT58: =+AT30 -> 35000 | AU58: =+AU30 -> 19064.62 | AV58: =+AR58+AT58 -> 175000 | AW58: =+AS58+AU58 -> 77852.894 | AX58: =+AX30 -> 45000 | AY58: =+AY30 -> 11091 | AZ58: =+AP58+AT58+AX58 -> 115000 | BA58: =+AQ58+AU58+AY58 -> 43651.538 | BB58: =+AL58+AZ58 -> 195000 | BC58: =+AM58+BA58 -> 88943.894 | BD58: =+AV58+AX58 -> 220000 | BE58: =+AW58+AY58 -> 88943.894 | BF58: 535000 | BG58: 171634.81
B59: Rejections | C59: Mt | D59: =+D58-((D58-(D58*0))) -> 0 | E59: 0 | F59: =+F58-((F58-(F58*0))) -> 0 | G59: 0 | H59: =+D59+F59 -> 0 | I59: =+E59+G59 -> 0 | J59: =+J58-((J58-(J58*0))) -> 0 | K59: 0 | L59: =+H59+J59 -> 0 | M59: =+I59+K59 -> 0 | N59: =+N58-((N58-(N58*0))) -> 0 | O59: 0 | P59: =+L59+N59 -> 0 | Q59: =+M59+O59 -> 0 | R59: =+R58-((R58-(R58*0))) -> 0 | S59: 0 | T59: =+P59+R59 -> 0 | U59: =+Q59+S59 -> 0 | V59: =+V58-((V58-(V58*0))) -> 0 | W59: 0 | X59: =+N59+R59+V59 -> 0 | Y59: =+O59+S59+W59 -> 0 | Z59: =+T59+V59 -> 0 | AA59: =+U59+W59 -> 0 | AB59: =+AB58-((AB58-(AB58*0))) -> 0 | AC59: =+USM!AE48 -> 0 | AD59: =+Z59+AB59 -> 0 | AE59: =+AA59+AC59 -> 0 | AF59: =+AF58-((AF58-(AF58*0))) -> 0 | AG59: =+USM!AI48 -> 20.014 | AH59: =+AD59+AF59 -> 0 | AI59: =+AE59+AG59 -> 20.014 | AJ59: =+AJ58-((AJ58-(AJ58*0))) -> 0 | AK59: =+USM!AM48 -> 0 | AL59: =+AB59+AF59+AJ59 -> 0 | AM59: =+AC59+AG59+AK59 -> 20.014 | AN59: =+AH59+AJ59 -> 0 | AO59: =+AI59+AK59 -> 20.014 | AP59: =+AP58-((AP58-(AP58*0))) -> 0 | AQ59: =+USM!AS48 -> 32.278 | AR59: =+AN59+AP59 -> 0 | AS59: =+AO59+AQ59 -> 52.292 | AT59: =+AT58-((AT58-(AT58*0))) -> 0 | AU59: =+USM!AW48 -> 21.45 | AV59: =+AR59+AT59 -> 0 | AW59: =+AS59+AU59 -> 73.742 | AX59: =+AX58-((AX58-(AX58*0))) -> 0 | AY59: =+USM!BA48 -> 258.99 | AZ59: =+AP59+AT59+AX59 -> 0 | BA59: =+AQ59+AU59+AY59 -> 312.718 | BB59: =+AL59+AZ59 -> 0 | BC59: =+AM59+BA59 -> 332.732 | BD59: =+AV59+AX59 -> 0 | BE59: =+AW59+AY59 -> 332.732 | BF59: 3199.3 | BG59: 5316.8799
B60: Prime & Saleable Length | C60: Mt | D60: =+D58-D59 -> 0 | E60: =+E58-E59 -> 0 | F60: =+F58-F59 -> 0 | G60: =+G58-G59 -> 0 | H60: =+D60+F60 -> 0 | I60: =+E60+G60 -> 0 | J60: =+J58-J59 -> 0 | K60: =+K58-K59 -> 0 | L60: =+H60+J60 -> 0 | M60: =+I60+K60 -> 0 | N60: =+N58-N59 -> 7000 | O60: =+O58-O59 -> 0 | P60: =+L60+N60 -> 7000 | Q60: =+M60+O60 -> 0 | R60: =+R58-R59 -> 8000 | S60: =+S58-S59 -> 0 | T60: =+P60+R60 -> 15000 | U60: =+Q60+S60 -> 0 | V60: =+V58-V59 -> 10000 | W60: =+W58-W59 -> 0 | X60: =+N60+R60+V60 -> 25000 | Y60: =+O60+S60+W60 -> 0 | Z60: =+T60+V60 -> 25000 | AA60: =+U60+W60 -> 0 | AB60: =+AB58-AB59 -> 10000 | AC60: =+AC58-AC59 -> 16462.166 | AD60: =+Z60+AB60 -> 35000 | AE60: =+AA60+AC60 -> 16462.166 | AF60: =+AF58-AF59 -> 40000 | AG60: =+AG58-AG59 -> 18633.096 | AH60: =+AD60+AF60 -> 75000 | AI60: =+AE60+AG60 -> 35095.262 | AJ60: =+AJ58-AJ59 -> 30000 | AK60: =+AK58-AK59 -> 10177.08 | AL60: =+AB60+AF60+AJ60 -> 80000 | AM60: =+AC60+AG60+AK60 -> 45272.342 | AN60: =+AH60+AJ60 -> 105000 | AO60: =+AI60+AK60 -> 45272.342 | AP60: =+AP58-AP59 -> 35000 | AQ60: =+AQ58-AQ59 -> 13463.64 | AR60: =+AN60+AP60 -> 140000 | AS60: =+AO60+AQ60 -> 58735.982 | AT60: =+AT58-AT59 -> 35000 | AU60: =+AU58-AU59 -> 19043.17 | AV60: =+AR60+AT60 -> 175000 | AW60: =+AS60+AU60 -> 77779.152 | AX60: =+AX58-AX59 -> 45000 | AY60: =+AY58-AY59 -> 10832.01 | AZ60: =+AP60+AT60+AX60 -> 115000 | BA60: =+AQ60+AU60+AY60 -> 43338.82 | BB60: =+AL60+AZ60 -> 195000 | BC60: =+AM60+BA60 -> 88611.162 | BD60: =+AV60+AX60 -> 220000 | BE60: =+AW60+AY60 -> 88611.162 | BF60: 531800.7 | BG60: 166317.93
B61: TOTAL MILL
B62: Gross | C62: Mt | D62: =+D50+D54+D58 -> 22439.54 | E62: =+E50+E54+E58 -> 22439.54 | F62: =+F50+F54+F58 -> 61380 | G62: =+G50+G54+G58 -> 61380 | H62: =+H50+H54+H58 -> 83819.54 | I62: =+I50+I54+I58 -> 83819.54 | J62: =+J50+J54+J58 -> 77908 | K62: =+K50+K54+K58 -> 63487.589 | ... W62: =+W50+W54+W58 -> 58812.338 | X62: =+N62+R62+V62 -> 299600 | Y62: =+O62+S62+W62 -> 180457.62 | Z62: =+Z50+Z54+Z58 -> 461327.54 | AA62: =+AA50+AA54+AA58 -> 327764.75 | AB62: =+AB50+AB54+AB58 -> 100000 | AC62: =+AC50+AC54+AC58 -> 72813.227 | AD62: =+AD50+AD54+AD58 -> 561327.54 | AE62: =+AE50+AE54+AE58 -> 400577.97 | AF62: =+AF50+AF54+AF58 -> 157393.81 | AG62: =+AG50+AG54+AG58 -> 90787.165 | ... AK62: =+AK50+AK54+AK58 -> 100223.69 | AL62: =+AB62+AF62+AJ62 -> 406633.45 | AM62: =+AC62+AG62+AK62 -> 263824.08 | AN62: =+AN50+AN54+AN58 -> 867960.99 | AO62: =+AO50+AO54+AO58 -> 591588.83 | AP62: =+AP50+AP54+AP58 -> 154774.04 | AQ62: =+AQ50+AQ54+AQ58 -> 95525.456 | AR62: =+AR50+AR54+AR58 -> 1022735 | AS62: =+AS50+AS54+AS58 -> 687114.28 | AT62: =+AT50+AT54+AT58 -> 143569 | AU62: =+AU50+AU54+AU58 -> 98850.54 | ... AY62: =+AY50+AY54+AY58 -> 100045 | AZ62: =+AP62+AT62+AX62 -> 462880.11 | BA62: =+AQ62+AU62+AY62 -> 294421 | BB62: =+AL62+AZ62 -> 869513.56 | BC62: =+AM62+BA62 -> 558245.07 | BD62: =+AV62+AX62 -> 1330841.1 | BE62: =+AW62+AY62 -> 886009.82 | BF62: 1835000 | BG62: 1215880.2
B63: Rejections | C63: Mt | D63: =+D51+D55+D59 -> 0 | E63: =+E51+E55+E59 -> 260.6 | F63: =+F51+F55+F59 -> 0 | G63: =+G51+G55+G59 -> 834.01 | H63: =+H51+H55+H59 -> 0 | I63: =+I51+I55+I59 -> 1094.61 | J63: =+J51+J55+J59 -> 0 | K63: =+K51+K55+K59 -> 829.784 | ... W63: =+W51+W55+W59 -> 484.009 | X63: =+N63+R63+V63 -> 0 | Y63: =+O63+S63+W63 -> 2156.289 | Z63: =+Z51+Z55+Z59 -> 0 | AA63: =+AA51+AA55+AA59 -> 4080.683 | AB63: =+AB51+AB55+AB59 -> 0 | AC63: =+AC51+AC55+AC59 -> 372.094 | AD63: =+AD51+AD55+AD59 -> 0 | AE63: =+AE51+AE55+AE59 -> 4452.777 | AF63: =+AF51+AF55+AF59 -> 0 | AG63: =+AG51+AG55+AG59 -> 407.598 | ... AK63: =+AK51+AK55+AK59 -> 302.836 | AL63: =+AB63+AF63+AJ63 -> 0 | AM63: =+AC63+AG63+AK63 -> 1082.528 | AN63: =+AN51+AN55+AN59 -> 0 | AO63: =+AO51+AO55+AO59 -> 5163.211 | AP63: =+AP51+AP55+AP59 -> 0 | AQ63: =+AQ51+AQ55+AQ59 -> 415.68 | AR63: =+AR51+AR55+AR59 -> 0 | AS63: =+AS51+AS55+AS59 -> 5578.891 | AT63: =+AT51+AT55+AT59 -> 0 | AU63: =+AU51+AU55+AU59 -> 179.448 | ... AY63: =+AY51+AY55+AY59 -> 716.392 | AZ63: =+AP63+AT63+AX63 -> 0 | BA63: =+AQ63+AU63+AY63 -> 1311.52 | BB63: =+AL63+AZ63 -> 0 | BC63: =+AM63+BA63 -> 2394.048 | BD63: =+AV63+AX63 -> 0 | BE63: =+AW63+AY63 -> 6474.731 | BF63: 7399.3 | BG63: 14280.55
B64: Prime & Saleable Length | C64: Mt | D64: =+D52+D56+D60 -> 22439.54 | E64: =+E52+E56+E60 -> 22178.94 | F64: =+F52+F56+F60 -> 61380 | G64: =+G52+G56+G60 -> 60545.99 | H64: =+H52+H56+H60 -> 83819.54 | I64: =+I52+I56+I60 -> 82724.93 | J64: =+J52+J56+J60 -> 77908 | K64: =+K52+K56+K60 -> 62657.805 | ... W64: =+W52+W56+W60 -> 58328.329 | X64: =+N64+R64+V64 -> 299600 | Y64: =+O64+S64+W64 -> 178301.33 | Z64: =+Z52+Z56+Z60 -> 461327.54 | AA64: =+AA52+AA56+AA60 -> 323684.06 | AB64: =+AB52+AB56+AB60 -> 100000 | AC64: =+AC52+AC56+AC60 -> 72441.133 | AD64: =+AD52+AD56+AD60 -> 561327.54 | AE64: =+AE52+AE56+AE60 -> 396125.2 | AF64: =+AF52+AF56+AF60 -> 157393.81 | AG64: =+AG52+AG56+AG60 -> 90379.567 | ... AK64: =+AK52+AK56+AK60 -> 99920.85 | AL64: =+AB64+AF64+AJ64 -> 406633.45 | AM64: =+AC64+AG64+AK64 -> 262741.55 | AN64: =+AN52+AN56+AN60 -> 867960.99 | AO64: =+AO52+AO56+AO60 -> 586425.62 | AP64: =+AP52+AP56+AP60 -> 154774.04 | AQ64: =+AQ52+AQ56+AQ60 -> 95109.776 | AR64: =+AR52+AR56+AR60 -> 1022735 | AS64: =+AS52+AS56+AS60 -> 681535.39 | AT64: =+AT52+AT56+AT60 -> 143569 | AU64: =+AU52+AU56+AU60 -> 98671.092 | ... AY64: =+AY52+AY56+AY60 -> 99328.608 | AZ64: =+AP64+AT64+AX64 -> 462880.11 | BA64: =+AQ64+AU64+AY64 -> 293109.48 | BB64: =+AL64+AZ64 -> 869513.56 | BC64: =+AM64+BA64 -> 555851.03 | BD64: =+AV64+AX64 -> 1330841.1 | BE64: =+AW64+AY64 -> 879535.09 | BF64: 1827600.7 | BG64: 1201599.7
B65: % Arisings of Total Mill Production | C65: % | D65: =+D63/D62*100 -> 0 | E65: =+E63/E62*100 -> 1.1613429 | F65: =+F63/F62*100 -> 0 | G65: =+G63/G62*100 -> 1.3587651 | H65: =+H63/H62*100 -> 0 | I65: =+I63/I62*100 -> 1.3059127 | J65: =+J63/J62*100 -> 0 | K65: =+K63/K62*100 -> 1.3070019 | ... BA65: =+BA63/BA62*100 -> 0.44545736 | BB65: =+AL65+AZ65 -> 0 | BC65: =+AM65+BA65 -> 0.85577927 | BD65: =+AV65+AX65 -> 0 | BE65: =+AW65+AY65 -> 1.4487157 | BF65: 0.40323161 | BG65: 1.174503
B66: % Arisings of Total Sal Steel Production | C66: % | D66: =+D63/D35*100 -> 0 | E66: =+E63/E35*100 -> 0.22226479 | F66: =+F63/F35*100 -> 0 | G66: =+G63/G35*100 -> 0.6550657 | H66: =+H63/H35*100 -> 0 | I66: =+I63/I35*100 -> 0.44757511 | J66: =+J63/J35*100 -> 0 | K66: =+K63/K35*100 -> 0.61492695 | ... BA66: =+BA63/BA35*100 -> 0.21621016 | BB66: =+AL66+AZ66 -> 0 | BC66: =+AM66+BA66 -> 0.49429857 | BD66: =+AV66+AX66 -> 0 | BE66: =+AW66+AY66 -> 0.678844 | BF66: 0.30740759 | BG66: 0.68206583
B68: US MILL (ARISING BREAK-UP) | D68: =+D3 -> Apr'20 | F68: =+F3 -> May'20 | H68: 2M | J68: =+J3 -> Jun'20 | L68: QRT-1 | N68: =+N3 -> Jul'20 | P68: 4M | R68: =+R3 -> Aug'20 | T68: 4M | V68: =+V3 -> Sep'20 | X68: QRT-1 | Z68: 4M | AB68: =+AB3 -> Oct'20 | AD68: 4M | AF68: =+AF3 -> Nov'20 | AH68: 4M | AN68: 4M | AR68: 4M | AV68: 4M
B69: Short lengths (< 6.0 Mts) | C69: Mt | H69: =+D69+F69 -> 0 | L69: =+H69+J69 -> 0 | P69: =+L69+N69 -> 0 | T69: =+P69+R69 -> 0 | X69: =+T69+V69 -> 0 | Z69: =+T69+V69 -> 0 | AD69: =+Z69+AB69 -> 0 | AH69: =+AD69+AF69 -> 0 | AN69: =+AH69+AJ69 -> 0 | AR69: =+AN69+AP69 -> 0 | AV69: =+AR69+AT69 -> 0
B70: Defective | C70: Mt | H70: =+D70+F70 -> 0 | L70: =+H70+J70 -> 0 | P70: =+L70+N70 -> 0 | T70: =+P70+R70 -> 0 | X70: =+T70+V70 -> 0 | Z70: =+T70+V70 -> 0 | AD70: =+Z70+AB70 -> 0 | AH70: =+AD70+AF70 -> 0 | AN70: =+AH70+AJ70 -> 0 | AR70: =+AN70+AP70 -> 0 | AV70: =+AR70+AT70 -> 0
B71: TOTAL | C71: Mt | D71: =SUM(D69:D70) -> 0 | F71: =SUM(F69:F70) -> 0 | H71: =SUM(H69:H70) -> 0 | J71: =SUM(J69:J70) -> 0 | L71: =SUM(L69:L70) -> 0 | N71: =SUM(N69:N70) -> 0 | P71: =SUM(P69:P70) -> 0 | R71: =SUM(R69:R70) -> 0 | T71: =SUM(T69:T70) -> 0 | V71: =SUM(V69:V70) -> 0 | X71: =SUM(X69:X70) -> 0 | Z71: =SUM(Z69:Z70) -> 0 | AB71: =SUM(AB69:AB70) -> 0 | AD71: =SUM(AD69:AD70) -> 0 | AF71: =SUM(AF69:AF70) -> 0 | AH71: =SUM(AH69:AH70) -> 0 | AN71: =SUM(AN69:AN70) -> 0 | AR71: =SUM(AR69:AR70) -> 0 | AV71: =SUM(AV69:AV70) -> 0
P73: ` | T73: ` | Z73: ` | AD73: ` | AH73: ` | AN73: ` | AR73: ` | AV73: `
B74: USM Odd lengths | D74: =+D3 -> Apr'20 | F74: =+F3 -> May'20 | H74: 2M | J74: =+J3 -> Jun'20 | L74: QRT-1 | N74: =+N3 -> Jul'20 | P74: 4M | R74: =+R3 -> Aug'20 | T74: 4M | V74: =+V3 -> Sep'20 | X74: QRT-1 | Z74: 4M | AB74: =+AB3 -> Oct'20 | AD74: 4M | AF74: =+AF3 -> Nov'20 | AH74: 4M | AN74: 4M | AR74: 4M | AV74: 4M
B75: Shortlength Arisings below 6.0 mts | D75: =+D107 -> 0 | F75: =+F107 -> 0 | H75: =+H107 -> 0 | J75: =+J107 -> 0 | L75: =+L107 -> 0 | N75: =+N107 -> 0 | P75: =+P107 -> 0 | R75: =+R107 -> 0 | T75: =+T107 -> 0 | V75: =+V107 -> 0 | X75: =+X107 -> 0 | Z75: =+Z107 -> 0 | AB75: =+AB107 -> 0 | AD75: =+AD107 -> 0 | AF75: =+AF107 -> 0 | AH75: =+AH107 -> 0 | AN75: =+AN107 -> 0 | AR75: =+AR107 -> 0 | AV75: =+AV107 -> 0
B76: BREAK UP Shortlength Arisings below 6.0 mts
B77: EA150X12_E350 | C77: Mt | H77: =+D77+F77 -> 0 | L77: =+D77+F77+J77 -> 0 | P77: =+L77+N77 -> 0 | T77: =+P77+R77 -> 0 | X77: =+P77+R77+V77 -> 0 | Z77: =+T77+V77 -> 0 | AD77: =+Z77+AB77 -> 0 | AH77: =+AD77+AF77 -> 0 | AN77: =+AH77+AJ77 -> 0 | AR77: =+AN77+AP77 -> 0 | AV77: =+AR77+AT77 -> 0
B78: EA150X10_E350 | C78: Mt | H78: =+D78+F78 -> 0 | L78: =+D78+F78+J78 -> 0 | P78: =+L78+N78 -> 0 | T78: =+P78+R78 -> 0 | X78: =+P78+R78+V78 -> 0 | Z78: =+T78+V78 -> 0 | AD78: =+Z78+AB78 -> 0 | AH78: =+AD78+AF78 -> 0 | AN78: =+AH78+AJ78 -> 0 | AR78: =+AN78+AP78 -> 0 | AV78: =+AR78+AT78 -> 0
B79: IPE300_E250 | C79: Mt | H79: =+D79+F79 -> 0 | L79: =+D79+F79+J79 -> 0 | P79: =+L79+N79 -> 0 | T79: =+P79+R79 -> 0 | X79: =+P79+R79+V79 -> 0 | Z79: =+T79+V79 -> 0 | AD79: =+Z79+AB79 -> 0 | AH79: =+AD79+AF79 -> 0 | AN79: =+AH79+AJ79 -> 0 | AR79: =+AN79+AP79 -> 0 | AV79: =+AR79+AT79 -> 0
B80: IPE300_E350 | C80: Mt | H80: =+D80+F80 -> 0 | L80: =+D80+F80+J80 -> 0 | P80: =+L80+N80 -> 0 | T80: =+P80+R80 -> 0 | X80: =+P80+R80+V80 -> 0 | Z80: =+T80+V80 -> 0 | AD80: =+Z80+AB80 -> 0 | AH80: =+AD80+AF80 -> 0 | AN80: =+AH80+AJ80 -> 0 | AR80: =+AN80+AP80 -> 0 | AV80: =+AR80+AT80 -> 0
B81: IPE300O_E250 | C81: Mt | H81: =+D81+F81 -> 0 | L81: =+D81+F81+J81 -> 0 | P81: =+L81+N81 -> 0 | T81: =+P81+R81 -> 0 | X81: =+P81+R81+V81 -> 0 | Z81: =+T81+V81 -> 0 | AD81: =+Z81+AB81 -> 0 | AH81: =+AD81+AF81 -> 0 | AN81: =+AH81+AJ81 -> 0 | AR81: =+AN81+AP81 -> 0 | AV81: =+AR81+AT81 -> 0
B82: IPE300O_E350 | C82: Mt | H82: =+D82+F82 -> 0 | L82: =+D82+F82+J82 -> 0 | P82: =+L82+N82 -> 0 | T82: =+P82+R82 -> 0 | X82: =+P82+R82+V82 -> 0 | Z82: =+T82+V82 -> 0 | AD82: =+Z82+AB82 -> 0 | AH82: =+AD82+AF82 -> 0 | AN82: =+AH82+AJ82 -> 0 | AR82: =+AN82+AP82 -> 0 | AV82: =+AR82+AT82 -> 0
B83: IPE400_E250 | C83: Mt | H83: =+D83+F83 -> 0 | L83: =+D83+F83+J83 -> 0 | P83: =+L83+N83 -> 0 | T83: =+P83+R83 -> 0 | X83: =+P83+R83+V83 -> 0 | Z83: =+T83+V83 -> 0 | AD83: =+Z83+AB83 -> 0 | AH83: =+AD83+AF83 -> 0 | AN83: =+AH83+AJ83 -> 0 | AR83: =+AN83+AP83 -> 0 | AV83: =+AR83+AT83 -> 0
B84: IPE400_E350 | C84: Mt | H84: =+D84+F84 -> 0 | L84: =+D84+F84+J84 -> 0 | P84: =+L84+N84 -> 0 | T84: =+P84+R84 -> 0 | X84: =+P84+R84+V84 -> 0 | Z84: =+T84+V84 -> 0 | AD84: =+Z84+AB84 -> 0 | AH84: =+AD84+AF84 -> 0 | AN84: =+AH84+AJ84 -> 0 | AR84: =+AN84+AP84 -> 0 | AV84: =+AR84+AT84 -> 0
B85: IPE400 A_E350 | C85: Mt | H85: =+D85+F85 -> 0 | L85: =+D85+F85+J85 -> 0 | P85: =+L85+N85 -> 0 | T85: =+P85+R85 -> 0 | X85: =+P85+R85+V85 -> 0 | Z85: =+T85+V85 -> 0 | AD85: =+Z85+AB85 -> 0 | AH85: =+AD85+AF85 -> 0 | AN85: =+AH85+AJ85 -> 0 | AR85: =+AN85+AP85 -> 0 | AV85: =+AR85+AT85 -> 0
B86: IPE400 A_E250 | C86: Mt | H86: =+D86+F86 -> 0 | L86: =+D86+F86+J86 -> 0 | P86: =+L86+N86 -> 0 | T86: =+P86+R86 -> 0 | X86: =+P86+R86+V86 -> 0 | Z86: =+T86+V86 -> 0 | AD86: =+Z86+AB86 -> 0 | AH86: =+AD86+AF86 -> 0 | AN86: =+AH86+AJ86 -> 0 | AR86: =+AN86+AP86 -> 0 | AV86: =+AR86+AT86 -> 0
B87: IPE450_E250 | C87: Mt | H87: =+D87+F87 -> 0 | L87: =+D87+F87+J87 -> 0 | P87: =+L87+N87 -> 0 | T87: =+P87+R87 -> 0 | X87: =+P87+R87+V87 -> 0 | Z87: =+T87+V87 -> 0 | AD87: =+Z87+AB87 -> 0 | AH87: =+AD87+AF87 -> 0 | AN87: =+AH87+AJ87 -> 0 | AR87: =+AN87+AP87 -> 0 | AV87: =+AR87+AT87 -> 0
B88: IPE450_E350 | C88: Mt | H88: =+D88+F88 -> 0 | L88: =+D88+F88+J88 -> 0 | P88: =+L88+N88 -> 0 | T88: =+P88+R88 -> 0 | X88: =+P88+R88+V88 -> 0 | Z88: =+T88+V88 -> 0 | AD88: =+Z88+AB88 -> 0 | AH88: =+AD88+AF88 -> 0 | AN88: =+AH88+AJ88 -> 0 | AR88: =+AN88+AP88 -> 0 | AV88: =+AR88+AT88 -> 0
B89: IPE450 A_E350 | C89: Mt | H89: =+D89+F89 -> 0 | L89: =+D89+F89+J89 -> 0 | P89: =+L89+N89 -> 0 | T89: =+P89+R89 -> 0 | X89: =+P89+R89+V89 -> 0 | Z89: =+T89+V89 -> 0 | AD89: =+Z89+AB89 -> 0 | AH89: =+AD89+AF89 -> 0 | AN89: =+AH89+AJ89 -> 0 | AR89: =+AN89+AP89 -> 0 | AV89: =+AR89+AT89 -> 0
B90: IPE450 O_E350 | C90: Mt | H90: =+D90+F90 -> 0 | L90: =+D90+F90+J90 -> 0 | X90: =+P90+R90+V90 -> 0
B91: IPE500_E250 | C91: Mt | H91: =+D91+F91 -> 0 | L91: =+D91+F91+J91 -> 0 | P91: =+L91+N91 -> 0 | T91: =+P91+R91 -> 0 | X91: =+P91+R91+V91 -> 0 | Z91: =+T91+V91 -> 0 | AD91: =+Z91+AB91 -> 0 | AH91: =+AD91+AF91 -> 0 | AN91: =+AH91+AJ91 -> 0 | AR91: =+AN91+AP91 -> 0 | AV91: =+AR91+AT91 -> 0
B92: IPE500_E350 | C92: Mt | H92: =+D92+F92 -> 0 | L92: =+D92+F92+J92 -> 0 | P92: =+L92+N92 -> 0 | T92: =+P92+R92 -> 0 | X92: =+P92+R92+V92 -> 0 | Z92: =+T92+V92 -> 0 | AD92: =+Z92+AB92 -> 0 | AH92: =+AD92+AF92 -> 0 | AN92: =+AH92+AJ92 -> 0 | AR92: =+AN92+AP92 -> 0 | AV92: =+AR92+AT92 -> 0
B93: IPE500 A_E350 | C93: Mt | H93: =+D93+F93 -> 0 | L93: =+D93+F93+J93 -> 0 | P93: =+L93+N93 -> 0 | T93: =+P93+R93 -> 0 | X93: =+P93+R93+V93 -> 0 | Z93: =+T93+V93 -> 0 | AD93: =+Z93+AB93 -> 0 | AH93: =+AD93+AF93 -> 0 | AN93: =+AH93+AJ93 -> 0 | AR93: =+AN93+AP93 -> 0 | AV93: =+AR93+AT93 -> 0
B94: IPE500 O_E350 | C94: Mt | H94: =+D94+F94 -> 0 | L94: =+D94+F94+J94 -> 0 | P94: =+L94+N94 -> 0 | T94: =+P94+R94 -> 0 | X94: =+P94+R94+V94 -> 0 | Z94: =+T94+V94 -> 0 | AD94: =+Z94+AB94 -> 0 | AH94: =+AD94+AF94 -> 0 | AN94: =+AH94+AJ94 -> 0 | AR94: =+AN94+AP94 -> 0 | AV94: =+AR94+AT94 -> 0
B95: IPE600 O_E250 | C95: Mt | H95: =+D95+F95 -> 0 | L95: =+D95+F95+J95 -> 0 | P95: =+L95+N95 -> 0 | T95: =+P95+R95 -> 0 | X95: =+P95+R95+V95 -> 0 | Z95: =+T95+V95 -> 0 | AD95: =+Z95+AB95 -> 0 | AH95: =+AD95+AF95 -> 0 | AN95: =+AH95+AJ95 -> 0 | AR95: =+AN95+AP95 -> 0 | AV95: =+AR95+AT95 -> 0
B96: IPE600_E250 | C96: Mt | H96: =+D96+F96 -> 0 | L96: =+D96+F96+J96 -> 0 | P96: =+L96+N96 -> 0 | T96: =+P96+R96 -> 0 | X96: =+P96+R96+V96 -> 0 | Z96: =+T96+V96 -> 0 | AD96: =+Z96+AB96 -> 0 | AH96: =+AD96+AF96 -> 0 | AN96: =+AH96+AJ96 -> 0 | AR96: =+AN96+AP96 -> 0 | AV96: =+AR96+AT96 -> 0
B97: IPE600_E350 | C97: Mt | H97: =+D97+F97 -> 0 | L97: =+D97+F97+J97 -> 0 | P97: =+L97+N97 -> 0 | T97: =+P97+R97 -> 0 | X97: =+P97+R97+V97 -> 0 | Z97: =+T97+V97 -> 0 | AD97: =+Z97+AB97 -> 0 | AH97: =+AD97+AF97 -> 0 | AN97: =+AH97+AJ97 -> 0 | AR97: =+AN97+AP97 -> 0 | AV97: =+AR97+AT97 -> 0
B98: IPE600_E410 | C98: Mt | H98: =+D98+F98 -> 0 | L98: =+D98+F98+J98 -> 0 | P98: =+L98+N98 -> 0 | T98: =+P98+R98 -> 0 | X98: =+P98+R98+V98 -> 0 | Z98: =+T98+V98 -> 0 | AD98: =+Z98+AB98 -> 0 | AH98: =+AD98+AF98 -> 0 | AN98: =+AH98+AJ98 -> 0 | AR98: =+AN98+AP98 -> 0 | AV98: =+AR98+AT98 -> 0
B99: IPE600O_E350 | C99: Mt | H99: =+D99+F99 -> 0 | L99: =+D99+F99+J99 -> 0 | P99: =+L99+N99 -> 0 | T99: =+P99+R99 -> 0 | X99: =+P99+R99+V99 -> 0 | Z99: =+T99+V99 -> 0 | AD99: =+Z99+AB99 -> 0 | AH99: =+AD99+AF99 -> 0 | AN99: =+AH99+AJ99 -> 0 | AR99: =+AN99+AP99 -> 0 | AV99: =+AR99+AT99 -> 0
B100: EA200X20_E350 | C100: Mt | H100: =+D100+F100 -> 0 | L100: =+D100+F100+J100 -> 0 | P100: =+L100+N100 -> 0 | T100: =+P100+R100 -> 0 | X100: =+P100+R100+V100 -> 0 | Z100: =+T100+V100 -> 0 | AD100: =+Z100+AB100 -> 0 | AH100: =+AD100+AF100 -> 0 | AN100: =+AH100+AJ100 -> 0 | AR100: =+AN100+AP100 -> 0 | AV100: =+AR100+AT100 -> 0
B101: EA200X18_E350 | C101: Mt | H101: =+D101+F101 -> 0 | L101: =+D101+F101+J101 -> 0 | P101: =+L101+N101 -> 0 | T101: =+P101+R101 -> 0 | X101: =+P101+R101+V101 -> 0 | Z101: =+T101+V101 -> 0 | AD101: =+Z101+AB101 -> 0 | AH101: =+AD101+AF101 -> 0 | AN101: =+AH101+AJ101 -> 0 | AR101: =+AN101+AP101 -> 0 | AV101: =+AR101+AT101 -> 0
B102: EA200X16_E350 | C102: Mt | H102: =+D102+F102 -> 0 | L102: =+D102+F102+J102 -> 0 | P102: =+L102+N102 -> 0 | T102: =+P102+R102 -> 0 | X102: =+P102+R102+V102 -> 0 | Z102: =+T102+V102 -> 0 | AD102: =+Z102+AB102 -> 0 | AH102: =+AD102+AF102 -> 0 | AN102: =+AH102+AJ102 -> 0 | AR102: =+AN102+AP102 -> 0 | AV102: =+AR102+AT102 -> 0
B103: EA200X25_E350 | C103: Mt | H103: =+D103+F103 -> 0 | L103: =+D103+F103+J103 -> 0 | X103: =+P103+R103+V103 -> 0
...

Sheet Maj Desp Summ
B1: MAJOR DESPATCH SUMMARY 2020-21 (As per Finance CENVAT report)
D2: 30 | E2: 30 | F2: 31 | G2: 31 | H2: =+F2+D2 -> 61 | I2: =+G2+E2 -> 61 | J2: 30 | K2: 30 | L2: =+D2+F2+J2 -> 91 | M2: =+E2+G2+K2 -> 91 | N2: 31 | O2: 31 | P2: =+L2+N2 -> 122 | Q2: =+M2+O2 -> 122 | R2: 31 | S2: 31 | T2: =+P2+R2 -> 153 | U2: =+Q2+S2 -> 153 | V2: 30 | W2: 30 | X2: =+N2+R2+V2 -> 92 | Y2: =+O2+S2+W2 -> 92 | Z2: =+T2+V2 -> 183 | AA2: =+U2+W2 -> 183 | AB2: 31 | AC2: 31 | AD2: =+Z2+AB2 -> 214 | AE2: =+AA2+AC2 -> 214 | AF2: 30 | AG2: 30 | AH2: =+AD2+AF2 -> 244 | AI2: =+AE2+AG2 -> 244 | AJ2: 31 | AK2: 31 | AL2: =+AB2+AF2+AJ2 -> 92 | AM2: =+AC2+AG2+AK2 -> 92 | AN2: =+AH2+AJ2 -> 275 | AO2: =+AI2+AK2 -> 275 | AP2: 31 | AQ2: 31 | AR2: =+AN2+AP2 -> 306 | AS2: =+AO2+AQ2 -> 306 | AT2: 28 | AU2: 28 | AV2: =+AR2+AT2 -> 334 | AW2: =+AS2+AU2 -> 334 | AX2: 31 | AY2: 31 | AZ2: =+AP2+AT2+AX2 -> 90 | BA2: =+AQ2+AU2+AY2 -> 90 | BB2: =+AL2+AZ2 -> 182 | BC2: =+AM2+BA2 -> 182 | BD2: =+AV2+AX2 -> 365 | BE2: =+AW2+AY2 -> 365 | BF2: 366 | BG2: 366
B3: ITEM | C3: Unit | D3: Apr'20 | F3: May'20 | H3: 2M | J3: Jun'20 | L3: QTR-1 | N3: Jul'20 | P3: 4M | R3: Aug'20 | T3: 5M | V3: Sep'20 | X3: QTR-2 | Z3: H1 | AB3: Oct'20 | AD3: 7M | AF3: Nov'20 | AH3: 8M | AJ3: Dec'20 | AL3: QTR-3 | AN3: 9M | AP3: Jan'21 | AR3: 10M | AT3: Feb'21 | AV3: 11M | AX3: Mar'21 | AZ3: QTR-4 | BB3: H2 | BD3: 2020-21 | BF3: 2019-20
D4: ABP | E4: ACT | F4: ABP | G4: ACT | H4: ABP | I4: ACT | J4: ABP | K4: ACT | L4: ABP | M4: ACT | N4: ABP | O4: ACT | P4: ABP | Q4: ACT | R4: ABP | S4: ACT | T4: ABP | U4: ACT | V4: ABP | W4: ACT | X4: ABP | Y4: ACT | Z4: ABP | AA4: ACT | AB4: ABP | AC4: ACT | AD4: ABP | AE4: ACT | AF4: ABP | AG4: ACT | AH4: ABP | AI4: ACT | AJ4: ABP | AK4: ACT | AL4: ABP | AM4: ACT | AN4: ABP | AO4: ACT | AP4: ABP | AQ4: ACT | AR4: ABP | AS4: ACT | AT4: ABP | AU4: ACT | AV4: ABP | AW4: ACT | AX4: ABP | AY4: ACT | AZ4: ABP | BA4: ACT | BB4: ABP | BC4: ACT | BD4: ABP | BE4: ACT | BF4: ABP | BG4: ACT
B5: Saleable Steel (mill-wise)
B6: MKTG-MILL DEFECTIVES (ARISINGS) | C6: MT | D6: 0 | E6: 0 | F6: 0 | G6: 2126.39 | H6: =+D6+F6 -> 0 | I6: =+E6+G6 -> 2126.39 | J6: 0 | K6: 4977.56 | L6: =+H6+J6 -> 0 | M6: =+I6+K6 -> 7103.95 | N6: 0 | O6: 2063.21 | P6: =+L6+N6 -> 0 | Q6: =+M6+O6 -> 9167.16 | R6: 0 | S6: 3108.64 | T6: =+P6+R6 -> 0 | U6: =+Q6+S6 -> 12275.8 | V6: 0 | W6: 5547.54 | X6: =+N6+R6+V6 -> 0 | Y6: =+O6+S6+W6 -> 10719.39 | Z6: =+T6+V6 -> 0 | AA6: =+U6+W6 -> 17823.34 | AB6: 0 | AC6: 2544.15 | AD6: =+Z6+AB6 -> 0 | AE6: =+AA6+AC6 -> 20367.49 | AF6: 0 | AG6: 3032.45 | AH6: =+AD6+AF6 -> 0 | AI6: =+AE6+AG6 -> 23399.94 | AJ6: 0 | AK6: 2622.99 | AL6: =+AB6+AF6+AJ6 -> 0 | AM6: =+AC6+AG6+AK6 -> 8199.59 | AN6: =+AH6+AJ6 -> 0 | AO6: =+AI6+AK6 -> 26022.93 | AP6: 0 | AQ6: 3556.32 | AR6: =+AN6+AP6 -> 0 | AS6: =+AO6+AQ6 -> 29579.25 | AT6: 0 | AU6: 613.39 | AV6: =+AR6+AT6 -> 0 | AW6: =+AS6+AU6 -> 30192.64 | AX6: 0 | AY6: 5075.61 | AZ6: =+AP6+AT6+AX6 -> 0 | BA6: =+AQ6+AU6+AY6 -> 9245.32 | BB6: =+AL6+AZ6 -> 0 | BC6: =+AM6+BA6 -> 17444.91 | BD6: =+AV6+AX6 -> 0 | BE6: =+AW6+AY6 -> 35268.25 | BF6: 2000 | BG6: 28405.85
B7: IPT | C7: MT | D7: 0 | E7: 0 | F7: 0 | G7: 0 | H7: =+D7+F7 -> 0 | I7: =+E7+G7 -> 0 | J7: 0 | K7: 0 | L7: =+H7+J7 -> 0 | M7: =+I7+K7 -> 0 | N7: 0 | O7: 0 | P7: =+L7+N7 -> 0 | Q7: =+M7+O7 -> 0 | R7: 2700 | S7: 1092.39 | T7: =+P7+R7 -> 2700 | U7: =+Q7+S7 -> 1092.39 | V7: 2700 | W7: 190.24 | X7: =+N7+R7+V7 -> 5400 | Y7: =+O7+S7+W7 -> 1282.63 | Z7: =+T7+V7 -> 5400 | AA7: =+U7+W7 -> 1282.63 | AB7: 0 | AC7: 0 | AD7: =+Z7+AB7 -> 5400 | AE7: =+AA7+AC7 -> 1282.63 | AF7: 2700 | AG7: 0 | AH7: =+AD7+AF7 -> 8100 | AI7: =+AE7+AG7 -> 1282.63 | AJ7: 2700 | AK7: 0 | AL7: =+AB7+AF7+AJ7 -> 5400 | AM7: =+AC7+AG7+AK7 -> 0 | AN7: =+AH7+AJ7 -> 10800 | AO7: =+AI7+AK7 -> 1282.63 | AP7: 0 | AQ7: 8475.88 | AR7: =+AN7+AP7 -> 10800 | AS7: =+AO7+AQ7 -> 9758.51 | AT7: 0 | AU7: 0 | AV7: =+AR7+AT7 -> 10800 | AW7: =+AS7+AU7 -> 9758.51 | AX7: 0 | AY7: 0 | AZ7: =+AP7+AT7+AX7 -> 0 | BA7: =+AQ7+AU7+AY7 -> 8475.88 | BB7: =+AL7+AZ7 -> 5400 | BC7: =+AM7+BA7 -> 8475.88 | BD7: =+AV7+AX7 -> 10800 | BE7: =+AW7+AY7 -> 9758.51 | BF7: 24210 | BG7: 5928.095
B8: CMO-WR MILL | C8: MT | D8: 14366.4 | E8: 16375.711 | F8: 17668 | G8: 16536.607 | H8: =+D8+F8 -> 32034.4 | I8: =+E8+G8 -> 32912.318 | J8: 35910 | K8: 30920.368 | L8: =+H8+J8 -> 67944.4 | M8: =+I8+K8 -> 63832.686 | N8: 34800 | O8: 33185.978 | P8: =+L8+N8 -> 102744.4 | Q8: =+M8+O8 -> 97018.664 | R8: 34800 | S8: 35758.761 | T8: =+P8+R8 -> 137544.4 | U8: =+Q8+S8 -> 132777.42 | V8: 32000 | W8: 26492.411 | X8: =+N8+R8+V8 -> 101600 | Y8: =+O8+S8+W8 -> 95437.15 | Z8: =+T8+V8 -> 169544.4 | AA8: =+U8+W8 -> 159269.84 | AB8: 39800 | AC8: 24289.42 | AD8: =+Z8+AB8 -> 209344.4 | AE8: =+AA8+AC8 -> 183559.26 | AF8: 45249.811 | AG8: 32282.62 | AH8: =+AD8+AF8 -> 254594.21 | AI8: =+AE8+AG8 -> 215841.88 | AJ8: 46094.038 | AK8: 36641.61 | AL8: =+AB8+AF8+AJ8 -> 131143.85 | AM8: =+AC8+AG8+AK8 -> 93213.65 | AN8: =+AH8+AJ8 -> 300688.25 | AO8: =+AI8+AK8 -> 252483.49 | AP8: 46294.038 | AQ8: 30074.79 | AR8: =+AN8+AP8 -> 346982.29 | AS8: =+AO8+AQ8 -> 282558.28 | AT8: 41769 | AU8: =+'DETAIL DESP '!AU11 -> 31673.72 | AV8: =+AR8+AT8 -> 388751.29 | AW8: =+AS8+AU8 -> 314232 | AX8: 46415 | AY8: 37035.02 | AZ8: =+AP8+AT8+AX8 -> 134478.04 | BA8: =+AQ8+AU8+AY8 -> 98783.53 | BB8: =+AL8+AZ8 -> 265621.89 | BC8: =+AM8+BA8 -> 191997.18 | BD8: =+AV8+AX8 -> 435166.29 | BE8: =+AW8+AY8 -> 351267.02 | BF8: 498000 | BG8: 399090.26
B9: CMO-BAR MILL | C9: MT | D9: 8073.14 | E9: 11672.029 | F9: 43712 | G9: 31996.589 | H9: =+D9+F9 -> 51785.14 | I9: =+E9+G9 -> 43668.618 | J9: 41998 | K9: 34772.045 | L9: =+H9+J9 -> 93783.14 | M9: =+I9+K9 -> 78440.663 | N9: 59600 | O9: 28512.979 | P9: =+L9+N9 -> 153383.14 | Q9: =+M9+O9 -> 106953.64 | R9: 55000 | S9: 29750.625 | T9: =+P9+R9 -> 208383.14 | U9: =+Q9+S9 -> 136704.27 | V9: 58000 | W9: 35123.996 | X9: =+N9+R9+V9 -> 172600 | Y9: =+O9+S9+W9 -> 93387.6 | Z9: =+T9+V9 -> 266383.14 | AA9: =+U9+W9 -> 171828.26 | AB9: 50000 | AC9: 26097 | AD9: =+Z9+AB9 -> 316383.14 | AE9: =+AA9+AC9 -> 197925.26 | AF9: 72144 | AG9: 43636.79 | AH9: =+AD9+AF9 -> 388527.14 | AI9: =+AE9+AG9 -> 241562.05 | AJ9: 72945.6 | AK9: 50121.09 | AL9: =+AB9+AF9+AJ9 -> 195089.6 | AM9: =+AC9+AG9+AK9 -> 119854.88 | AN9: =+AH9+AJ9 -> 461472.74 | AO9: =+AI9+AK9 -> 291683.14 | AP9: 73480 | AQ9: 48805.76 | AR9: =+AN9+AP9 -> 534952.74 | AS9: =+AO9+AQ9 -> 340488.9 | AT9: 66800 | AU9: 49089.91 | AV9: =+AR9+AT9 -> 601752.74 | AW9: =+AS9+AU9 -> 389578.81 | AX9: 73122 | AY9: =48408.45-1028.8 -> 47379.65 | AZ9: =+AP9+AT9+AX9 -> 213402 | BA9: =+AQ9+AU9+AY9 -> 145275.32 | BB9: =+AL9+AZ9 -> 408491.6 | BC9: =+AM9+BA9 -> 265130.2 | BD9: =+AV9+AX9 -> 674874.74 | BE9: =+AW9+AY9 -> 436958.46 | BF9: 800000 | BG9: 612890.55
B10: CMO-US MILL | C10: MT | D10: 0 | E10: 985.8 | F10: 0 | G10: 3719.291 | H10: =+D10+F10 -> 0 | I10: =+E10+G10 -> 4705.091 | J10: 0 | K10: 4850.511 | L10: =+H10+J10 -> 0 | M10: =+I10+K10 -> 9555.602 | N10: 7000 | O10: 2379.7 | P10: =+L10+N10 -> 7000 | Q10: =+M10+O10 -> 11935.302 | R10: 8000 | S10: 461.73 | T10: =+P10+R10 -> 15000 | U10: =+Q10+S10 -> 12397.032 | V10: 10000 | W10: 359.27 | X10: =+N10+R10+V10 -> 25000 | Y10: =+O10+S10+W10 -> 3200.7 | Z10: =+T10+V10 -> 25000 | AA10: =+U10+W10 -> 12756.302 | AB10: 10000 | AC10: 12306.48 | AD10: =+Z10+AB10 -> 35000 | AE10: =+AA10+AC10 -> 25062.782 | AF10: 40000 | AG10: 18714.31 | AH10: =+AD10+AF10 -> 75000 | AI10: =+AE10+AG10 -> 43777.092 | AJ10: 30000 | AK10: 12687.54 | AL10: =+AB10+AF10+AJ10 -> 80000 | AM10: =+AC10+AG10+AK10 -> 43708.33 | AN10: =+AH10+AJ10 -> 105000 | AO10: =+AI10+AK10 -> 56464.632 | AP10: 35000 | AQ10: 13700.86 | AR10: =+AN10+AP10 -> 140000 | AS10: =+AO10+AQ10 -> 70165.492 | AT10: 35000 | AU10: 17221.01 | AV10: =+AR10+AT10 -> 175000 | AW10: =+AS10+AU10 -> 87386.502 | AX10: 45000 | AY10: =11212.68+1864.3-63.08 -> 13013.9 | AZ10: =+AP10+AT10+AX10 -> 115000 | BA10: =+AQ10+AU10+AY10 -> 43935.77 | BB10: =+AL10+AZ10 -> 195000 | BC10: =+AM10+BA10 -> 87644.1 | BD10: =+AV10+AX10 -> 220000 | BE10: =+AW10+AY10 -> 100400.4 | BF10: 535000 | BG10: 167166.99
B11: CMO-SEMIS | C11: MT | D11: 94808 | E11: 40972.333 | F11: 65936.95 | G11: 97680.588 | H11: =+D11+F11 -> 160744.95 | I11: =+E11+G11 -> 138652.92 | J11: 77842 | K11: 144748.36 | L11: =+H11+J11 -> 238586.95 | M11: =+I11+K11 -> 283401.28 | N11: 119500 | O11: 125532.51 | P11: =+L11+N11 -> 358086.95 | Q11: =+M11+O11 -> 408933.8 | R11: 119300 | S11: 103938.32 | T11: =+P11+R11 -> 477386.95 | U11: =+Q11+S11 -> 512872.12 | V11: 118300 | W11: 35832.576 | X11: =+N11+R11+V11 -> 357100 | Y11: =+O11+S11+W11 -> 265303.41 | Z11: =+T11+V11 -> 595686.95 | AA11: =+U11+W11 -> 548704.7 | AB11: 9175.3772 | AC11: 8843.88 | AD11: =+Z11+AB11 -> 604862.33 | AE11: =+AA11+AC11 -> 557548.58 | AF11: 49806.099 | AG11: 41046.29 | AH11: =+AD11+AF11 -> 654668.43 | AI11: =+AE11+AG11 -> 598594.87 | AJ11: 66977.646 | AK11: 69541.31 | AL11: =+AB11+AF11+AJ11 -> 125959.12 | AM11: =+AC11+AG11+AK11 -> 119431.48 | AN11: =+AH11+AJ11 -> 721646.07 | AO11: =+AI11+AK11 -> 668136.18 | AP11: 61266.703 | AQ11: 76352.02 | AR11: =+AN11+AP11 -> 782912.78 | AS11: =+AO11+AQ11 -> 744488.2 | AT11: 55498 | AU11: 81687.71 | AV11: =+AR11+AT11 -> 838410.78 | AW11: =+AS11+AU11 -> 826175.91 | AX11: 55223 | AY11: 117826.3 | AZ11: =+AP11+AT11+AX11 -> 171987.7 | BA11: =+AQ11+AU11+AY11 -> 275866.03 | BB11: =+AL11+AZ11 -> 297946.83 | BC11: =+AM11+BA11 -> 395297.51 | BD11: =+AV11+AX11 -> 893633.78 | BE11: =+AW11+AY11 -> 944002.21 | BF11: 547789.74 | BG11: 836451
B12: TOTAL | C12: MT | D12: =SUM(D6:D11) -> 117247.54 | E12: =SUM(E6:E11) -> 70005.873 | F12: =SUM(F6:F11) -> 127316.95 | G12: =SUM(G6:G11) -> 152059.46 | H12: =SUM(H6:H11) -> 244564.49 | I12: =SUM(I6:I11) -> 222065.34 | J12: =SUM(J6:J11) -> 155750 | K12: =SUM(K6:K11) -> 220268.85 | ... BA12: =SUM(BA6:BA11) -> 581581.85 | BB12: =+AL12+AZ12 -> 1172460.3 | BC12: =+AM12+BA12 -> 965989.78 | BD12: =SUM(BD6:BD11) -> 2234474.8 | BE12: =SUM(BE6:BE11) -> 1877654.8 | BF12: 2406999.7 | BG12: 2049932.7
B13: Saleable Steel (Sale type-wise) | BC13: =+AM13+BA13 -> 0
B14: IPT | C14: MT | D14: =+D12 -> 117247.54 | E14: 0 | F14: =+F12 -> 127316.95 | G14: 0 | H14: =+D14+F14 -> 244564.49 | I14: =+E14+G14 -> 0 | J14: =+J12 -> 155750 | K14: 0 | L14: =+H14+J14 -> 400314.49 | M14: =+I14+K14 -> 0 | N14: =+N12 -> 220900 | O14: 0 | P14: =+L14+N14 -> 621214.49 | Q14: =+M14+O14 -> 0 | R14: =+R12 -> 219800 | S14: =+S7 -> 1092.39 | T14: =+P14+R14 -> 841014.49 | U14: =+Q14+S14 -> 1092.39 | V14: =+V12 -> 221000 | W14: 190.24 | X14: =+N14+R14+V14 -> 661700 | Y14: =+O14+S14+W14 -> 1282.63 | Z14: =+T14+V14 -> 1062014.5 | AA14: =+U14+W14 -> 1282.63 | AB14: =+AB12 -> 108975.38 | AC14: =+AC7 -> 0 | AD14: =+Z14+AB14 -> 1170989.9 | AE14: =+AA14+AC14 -> 1282.63 | AF14: =+AF12 -> 209899.91 | AG14: =+AG7 -> 0 | AH14: =+AD14+AF14 -> 1380889.8 | AI14: =+AE14+AG14 -> 1282.63 | AJ14: =+AJ12 -> 218717.28 | AK14: =+AK7 -> 0 | AL14: =+AB14+AF14+AJ14 -> 537592.57 | AM14: =+AC14+AG14+AK14 -> 0 | AN14: =+AH14+AJ14 -> 1599607.1 | AO14: =+AI14+AK14 -> 1282.63 | AP14: =+AP12 -> 216040.74 | AQ14: =+AQ7 -> 8475.88 | AR14: =+AN14+AP14 -> 1815647.8 | AS14: =+AO14+AQ14 -> 9758.51 | AT14: =+AT12 -> 199067 | AU14: 0 | AV14: =+AR14+AT14 -> 2014714.8 | AW14: =+AS14+AU14 -> 9758.51 | AX14: =+AX12 -> 219760 | AZ14: =+AP14+AT14+AX14 -> 634867.74 | BA14: =+AQ14+AU14+AY14 -> 8475.88 | BB14: =+BB12 -> 1172460.3 | BC14: =+AM14+BA14 -> 8475.88 | BD14: =+AV14+AX14 -> 2234474.8 | BE14: =+AW14+AY14 -> 9758.51 | BF14: =+BF12 -> 2406999.7 | BG14: 5928.249
B15: CMO DIR | C15: MT | E15: 122.16 | G15: 34820.794 | I15: =+E15+G15 -> 34942.954 | K15: 58512.051 | M15: =+I15+K15 -> 93455.005 | O15: 63472.621 | Q15: =+M15+O15 -> 156927.63 | S15: 62729.821 | U15: =+Q15+S15 -> 219657.45 | W15: 35304.871 | Y15: =+O15+S15+W15 -> 161507.31 | AA15: =+U15+W15 -> 254962.32 | AC15: 53651.13 | AE15: =+AA15+AC15 -> 308613.45 | AG15: 83158.94 | AI15: =+AE15+AG15 -> 391772.39 | AK15: 102972.69 | AM15: =+AC15+AG15+AK15 -> 239782.76 | AO15: =+AI15+AK15 -> 494745.08 | AQ15: 54335.57 | AS15: =+AO15+AQ15 -> 549080.65 | AU15: 58789.76 | AW15: =+AS15+AU15 -> 607870.41 | AY15: 83456.11 | BA15: =+AQ15+AU15+AY15 -> 196581.44 | BC15: =+AM15+BA15 -> 436364.2 | BE15: =+AW15+AY15 -> 691326.52 | BG15: 569419.83
B16: CMO SYD | C16: MT | E16: 21003.339 | G16: 43245.988 | I16: =+E16+G16 -> 64249.327 | K16: 52184.348 | M16: =+I16+K16 -> 116433.68 | O16: 36302.984 | Q16: =+M16+O16 -> 152736.66 | S16: 29096.228 | U16: =+Q16+S16 -> 181832.89 | W16: 30382.416 | Y16: =+O16+S16+W16 -> 95781.628 | AA16: =+U16+W16 -> 212215.3 | AC16: 17823.58 | AE16: =+AA16+AC16 -> 230038.88 | AG16: 36285.45 | AI16: =+AE16+AG16 -> 266324.33 | AK16: 37228.55 | AM16: =+AC16+AG16+AK16 -> 91337.58 | AO16: =+AI16+AK16 -> 303552.88 | AQ16: 74738.85 | AS16: =+AO16+AQ16 -> 378291.73 | AU16: 69720.89 | AW16: =+AS16+AU16 -> 448012.62 | AY16: 31192.53 | BA16: =+AQ16+AU16+AY16 -> 175652.27 | BC16: =+AM16+BA16 -> 266989.85 | BE16: =+AW16+AY16 -> 479205.15 | BG16: 909567
B17: MKTG DIR (DEF) | C17: MT | E17: 0 | G17: 2126.39 | I17: =+E17+G17 -> 2126.39 | K17: 4977.56 | M17: =+I17+K17 -> 7103.95 | O17: 2063.21 | Q17: =+M17+O17 -> 9167.16 | S17: =+S6 -> 3108.64 | U17: =+Q17+S17 -> 12275.8 | W17: 5547.54 | Y17: =+O17+S17+W17 -> 10719.39 | AA17: =+U17+W17 -> 17823.34 | AC17: =+AC6 -> 2544.15 | AE17: =+AA17+AC17 -> 20367.49 | AG17: =+AG6 -> 3032.45 | AI17: =+AE17+AG17 -> 23399.94 | AK17: =+AK6 -> 2622.99 | AM17: =+AC17+AG17+AK17 -> 8199.59 | AO17: =+AI17+AK17 -> 26022.93 | AQ17: =+AQ6 -> 3556.32 | AS17: =+AO17+AQ17 -> 29579.25 | AU17: =+AU6 -> 613.39 | AW17: =+AS17+AU17 -> 30192.64 | AY17: =+AY6 -> 5075.61 | BA17: =+AQ17+AU17+AY17 -> 9245.32 | BC17: =+AM17+BA17 -> 17444.91 | BE17: =+AW17+AY17 -> 35268.25 | BG17: 28405.85
B18: EXPORT DIR | C18: MT | E18: 48880.374 | G18: 71866.293 | I18: =+E18+G18 -> 120746.67 | K18: 104594.89 | M18: =+I18+K18 -> 225341.55 | O18: 89835.567 | Q18: =+M18+O18 -> 315177.12 | S18: 78083.391 | U18: =+Q18+S18 -> 393260.51 | W18: 32120.966 | Y18: =+O18+S18+W18 -> 200039.92 | AA18: =+U18+W18 -> 425381.48 | AC18: 62.07 | AE18: =+AA18+AC18 -> 425443.55 | AG18: 16235.62 | AI18: =+AE18+AG18 -> 441679.17 | AK18: 28790.31 | AM18: =+AC18+AG18+AK18 -> 45088 | AO18: =+AI18+AK18 -> 470469.48 | AQ18: 39859.01 | AS18: =+AO18+AQ18 -> 510328.49 | AU18: 51161.7 | AW18: =+AS18+AU18 -> 561490.19 | AY18: 100606.79 | BA18: =+AQ18+AU18+AY18 -> 191627.5 | BC18: =+AM18+BA18 -> 236715.5 | BE18: =+AW18+AY18 -> 662096.98 | BG18: 536611.98
B19: % DIRECT I/C EXPORT OF TOTAL DESPATCH | C19: % | E19: =+((E15+E17+E18)/E12)*100 -> 69.997747 | G19: =+((G15+G17+G18)/G12)*100 -> 71.559818 | I19: =+((I15+I17+I18)/I12)*100 -> 71.067377 | K19: =+((K15+K17+K18)/K12)*100 -> 76.308793 | M19: =+((M15+M17+M18)/M12)*100 -> 73.677441 | O19: =+((O15+O17+O18)/O12)*100 -> 81.060075 | Q19: =+((Q15+Q17+Q18)/Q12)*100 -> 75.90937 | S19: =+((S15+S17+S18)/S12)*100 -> 82.661228 | U19: =+((U15+U17+U18)/U12)*100 -> 77.364068 | W19: =+((W15+W17+W18)/W12)*100 -> 70.474334 | Y19: =+((Y15+Y17+Y18)/Y12)*100 -> 79.318587 | AA19: =+((AA15+AA17+AA18)/AA12)*100 -> 76.581539 | AC19: =+((AC15+AC17+AC18)/AC12)*100 -> 75.940394 | AE19: =+((AE15+AE17+AE18)/AE12)*100 -> 76.533355 | AG19: =+((AG15+AG17+AG18)/AG12)*100 -> 73.841247 | AI19: =+((AI15+AI17+AI18)/AI12)*100 -> 76.201258 | AK19: =+((AK15+AK17+AK18)/AK12)*100 -> 78.306879 | AM19: =+((AM15+AM17+AM18)/AM12)*100 -> 76.239413 | AO19: =+((AO15+AO17+AO18)/AO12)*100 -> 76.480066 | AQ19: =+((AQ15+AQ17+AQ18)/AQ12)*100 -> 54.016279 | AS19: =+((AS15+AS17+AS18)/AS12)*100 -> 73.72782 | AU19: =+((AU15+AU17+AU18)/AU12)*100 -> 61.327563 | AW19: =+((AW15+AW17+AW18)/AW12)*100 -> 72.378905 | AY19: =+((AY15+AY17+AY18)/AY12)*100 -> 85.843098 | BA19: =+((BA15+BA17+BA18)/BA12)*100 -> 68.34021 | BC19: =+((BC15+BC17+BC18)/BC12)*100 -> 71.483635 | BE19: =+((BE15+BE17+BE18)/BE12)*100 -> 73.95884 | BG19: =+((BG15+BG17+BG18)/BG12)*100 -> 55.340238
B20: Saleable Steel (Shipping Mode-wise)
B21: RAIL | C21: MT | D21: =+D12 -> 117247.54 | E21: 68765.633 | F21: =+F12 -> 127316.95 | G21: 124775.23 | H21: =+H12 -> 244564.49 | I21: =+E21+G21 -> 193540.87 | J21: =+J12 -> 155750 | K21: 193311.76 | L21: =+L12 -> 400314.49 | M21: =+I21+K21 -> 386852.62 | N21: =+N12 -> 220900 | O21: 157731.73 | P21: =+P12 -> 621214.49 | Q21: =+M21+O21 -> 544584.36 | R21: =+R12 -> 219800 | S21: 136841.41 | T21: =+T12 -> 841014.49 | U21: =+Q21+S21 -> 681425.77 | V21: =+V12 -> 221000 | W21: 77711.063 | X21: =+X12 -> 661700 | Y21: =+O21+S21+W21 -> 372284.2 | Z21: =+Z12 -> 1062014.5 | AA21: =+U21+W21 -> 759136.83 | AB21: =+AB12 -> 108975.38 | AC21: 49715.88 | AD21: =+AD12 -> 1170989.9 | AE21: =+AA21+AC21 -> 808852.71 | AF21: =+AF12 -> 209899.91 | AG21: 97538.36 | AH21: =+AH12 -> 1380889.8 | AI21: =+AE21+AG21 -> 906391.07 | AJ21: =+AJ12 -> 218717.28 | AK21: 138016.78 | AL21: =+AL12 -> 537592.57 | AM21: =+AC21+AG21+AK21 -> 285271.02 | AN21: =+AN12 -> 1599607.1 | AO21: =+AI21+AK21 -> 1044407.8 | AP21: =+AP12 -> 216040.74 | AQ21: =151753.48+11741.26 -> 163494.74 | AR21: =+AR12 -> 1815647.8 | AS21: =+AO21+AQ21 -> 1207902.6 | AT21: =+AT12 -> 199067 | AU21: 159781.49 | AV21: =+AV12 -> 2014714.8 | AW21: =+AS21+AU21 -> 1367684.1 | AX21: =+AX12 -> 219760 | AY21: 189497.87 | AZ21: =+AZ12 -> 634867.74 | BA21: =+AQ21+AU21+AY21 -> 512774.1 | BB21: =+BB12 -> 1172460.3 | BC21: =+AM21+BA21 -> 798045.12 | BD21: =+BD12 -> 2234474.8 | BE21: =+AW21+AY21 -> 1557181.9 | BF21: =+BF12 -> 2406999.7 | BG21: 1655527.4
B22: ROAD | C22: MT | E22: 1240.24 | G22: 27284.23 | I22: =+E22+G22 -> 28524.47 | K22: 26957.09 | M22: =+I22+K22 -> 55481.56 | O22: 33942.65 | Q22: =+M22+O22 -> 89424.21 | S22: 37269.06 | U22: =+Q22+S22 -> 126693.27 | W22: =20097.19+5737.78 -> 25834.97 | Y22: =+O22+S22+W22 -> 97046.68 | AA22: =+U22+W22 -> 152528.24 | AC22: =21820.9+2544.15 -> 24365.05 | AE22: =+AA22+AC22 -> 176893.29 | AG22: 41174.1 | AI22: =+AE22+AG22 -> 218067.39 | AK22: 33597.76 | AM22: =+AC22+AG22+AK22 -> 99136.91 | AO22: =+AI22+AK22 -> 251665.15 | AQ22: =17179.95+290.94 -> 17470.89 | AS22: =+AO22+AQ22 -> 269136.04 | AU22: =+AU12-AU21 -> 20504.25 | AW22: =+AS22+AU22 -> 289640.29 | AY22: =+AY12-AY21 -> 30832.61 | BA22: =+AQ22+AU22+AY22 -> 68807.75 | BC22: =+BC12-BC21 -> 167944.66 | BE22: =+AW22+AY22 -> 320472.9 | BG22: 394405.54
B23: TOTAL | C23: MT | E23: =SUM(E21:E22) -> 70005.873 | G23: =SUM(G21:G22) -> 152059.46 | I23: =SUM(I21:I22) -> 222065.34 | K23: =SUM(K21:K22) -> 220268.85 | M23: =SUM(M21:M22) -> 442334.18 | O23: =SUM(O21:O22) -> 191674.38 | Q23: =SUM(Q21:Q22) -> 634008.57 | S23: =SUM(S21:S22) -> 174110.47 | U23: =SUM(U21:U22) -> 808119.04 | W23: =SUM(W21:W22) -> 103546.03 | Y23: =SUM(Y21:Y22) -> 469330.88 | AA23: =SUM(AA21:AA22) -> 911665.07 | AC23: =SUM(AC21:AC22) -> 74080.93 | AE23: =SUM(AE21:AE22) -> 985746 | AG23: =SUM(AG21:AG22) -> 138712.46 | AI23: =SUM(AI21:AI22) -> 1124458.5 | AK23: =SUM(AK21:AK22) -> 171614.54 | AM23: =SUM(AM21:AM22) -> 384407.93 | AO23: =SUM(AO21:AO22) -> 1296073 | AQ23: =SUM(AQ21:AQ22) -> 180965.63 | AS23: =SUM(AS21:AS22) -> 1477038.6 | AU23: =SUM(AU21:AU22) -> 180285.74 | AW23: =SUM(AW21:AW22) -> 1657324.4 | AY23: =SUM(AY21:AY22) -> 220330.48 | BA23: =SUM(BA21:BA22) -> 581581.85 | BC23: =SUM(BC21:BC22) -> 965989.78 | BE23: =SUM(BE21:BE22) -> 1877654.8 | BG23: =SUM(BG21:BG22) -> 2049932.9
B24: ROAD CO-EFFICIENT (%) | C24: % | E24: =+E22/E23*100 -> 1.7716228 | G24: =+G22/G23*100 -> 17.943132 | I24: =+I22/I23*100 -> 12.84508 | K24: =+K22/K23*100 -> 12.238267 | M24: =+M22/M23*100 -> 12.542906 | O24: =+O22/O23*100 -> 17.708496 | Q24: =+Q22/Q23*100 -> 14.104574 | S24: =+S22/S23*100 -> 21.40541 | U24: =+U22/U23*100 -> 15.677551 | W24: =+W22/W23*100 -> 24.950227 | Y24: =+Y22/Y23*100 -> 20.677668 | AA24: =+AA22/AA23*100 -> 16.730732 | AC24: =+AC22/AC23*100 -> 32.889773 | AE24: =+AE22/AE23*100 -> 17.945119 | AG24: =+AG22/AG23*100 -> 29.683058 | AI24: =+AI22/AI23*100 -> 19.393103 | AK24: =+AK22/AK23*100 -> 19.577455 | AM24: =+AM22/AM23*100 -> 25.789507 | AO24: =+AO22/AO23*100 -> 19.417514 | AQ24: =+AQ22/AQ23*100 -> 9.6542587 | AS24: =+AS22/AS23*100 -> 18.221327 | AU24: =+AU22/AU23*100 -> 11.373196 | AW24: =+AW22/AW23*100 -> 17.476379 | AY24: =+AY22/AY23*100 -> 13.993801 | BA24: =+BA22/BA23*100 -> 11.831138 | BC24: =+BC22/BC23*100 -> 17.38576 | BE24: =+BE22/BE23*100 -> 17.067721 | BG24: =+BG22/BG23*100 -> 19.239924
B25: Pig Iron (CMO/Secondary sales)+Export+IPT | C25: MT | D25: 3047 | E25: 0 | F25: 2899 | G25: 20776.96 | H25: =+D25+F25 -> 5946 | I25: =+E25+G25 -> 20776.96 | J25: 3951.4399 | K25: 7691 | L25: =+H25+J25 -> 9897.4399 | M25: =+I25+K25 -> 28467.96 | N25: 0 | O25: 6302.39 | P25: =+L25+N25 -> 9897.4399 | Q25: =+M25+O25 -> 34770.35 | R25: 0 | S25: 7754.69 | T25: =+P25+R25 -> 9897.4399 | U25: =+Q25+S25 -> 42525.04 | V25: 0 | W25: 5957.69 | X25: =+N25+R25+V25 -> 0 | Y25: =+O25+S25+W25 -> 20014.77 | Z25: =+T25+V25 -> 9897.4399 | AA25: =+U25+W25 -> 48482.73 | AB25: 2130.1605 | AC25: 4510.62 | AD25: =+Z25+AB25 -> 12027.6 | AE25: =+AA25+AC25 -> 52993.35 | AF25: 1873.1932 | AG25: 9056.14 | AH25: =+AD25+AF25 -> 13900.794 | AI25: =+AE25+AG25 -> 62049.49 | AJ25: 2501.7113 | AK25: 8811.57 | AL25: =+AB25+AF25+AJ25 -> 6505.0651 | AM25: =+AC25+AG25+AK25 -> 22378.33 | AN25: =+AH25+AJ25 -> 16402.505 | AO25: =+AI25+AK25 -> 70861.06 | AP25: 2379.1399 | AQ25: 2182.92 | AR25: =+AN25+AP25 -> 18781.645 | AS25: =+AO25+AQ25 -> 73043.98 | AT25: 492 | AU25: 4417.97 | AV25: =+AR25+AT25 -> 19273.645 | AW25: =+AS25+AU25 -> 77461.95 | AX25: 1481 | AY25: 2540.23 | AZ25: =+AP25+AT25+AX25 -> 4352.1399 | BA25: =+AQ25+AU25+AY25 -> 9141.12 | BC25: =+AM25+BA25 -> 31519.45 | BD25: =+AV25+AX25 -> 20754.645 | BE25: =+AW25+AY25 -> 80002.18 | BF25: 29958.272 | BG25: 124050.8
B26: PCIS (Sand Casts)-Plant Sales | C26: MT | D26: 647.4919 | E26: 0 | F26: 640.17735 | G26: 4059.45 | H26: =+D26+F26 -> 1287.6692 | I26: =+E26+G26 -> 4059.45 | J26: 807.0194 | K26: 3123.71 | L26: =+H26+J26 -> 2094.6886 | M26: =+I26+K26 -> 7183.16 | N26: 416.569 | O26: 2966.55 | P26: =+L26+N26 -> 2511.2576 | Q26: =+M26+O26 -> 10149.71 | R26: 414.19888 | S26: 1521.07 | T26: =+P26+R26 -> 2925.4565 | U26: =+Q26+S26 -> 11670.78 | V26: 408.66504 | W26: 3132.99 | X26: =+N26+R26+V26 -> 1239.4329 | Y26: =+O26+S26+W26 -> 7620.61 | Z26: =+T26+V26 -> 3334.1216 | AA26: =+U26+W26 -> 14803.77 | AB26: 484.30665 | AC26: 2455.95 | AD26: =+Z26+AB26 -> 3818.4282 | AE26: =+AA26+AC26 -> 17259.72 | AF26: 640.09373 | AG26: 1774.55 | AH26: =+AD26+AF26 -> 4458.5219 | AI26: =+AE26+AG26 -> 19034.27 | AJ26: 739.76354 | AK26: 3257.06 | AL26: =+AB26+AF26+AJ26 -> 1864.1639 | AM26: =+AC26+AG26+AK26 -> 7487.56 | AN26: =+AH26+AJ26 -> 5198.2855 | AO26: =+AI26+AK26 -> 22291.33 | AP26: 717.42475 | AQ26: 1615.15 | AR26: =+AN26+AP26 -> 5915.7102 | AS26: =+AO26+AQ26 -> 23906.48 | AT26: 446 | AU26: 2379.75 | AV26: =+AR26+AT26 -> 6361.7102 | AW26: =+AS26+AU26 -> 26286.23 | AX26: 612 | AY26: 3197.55 | AZ26: =+AP26+AT26+AX26 -> 1775.4247 | BA26: =+AQ26+AU26+AY26 -> 7192.45 | BC26: =+AM26+BA26 -> 14680.01 | BD26: =+AV26+AX26 -> 6973.7102 | BE26: =+AW26+AY26 -> 29483.78 | BF26: 8472.5251 | BG26: 59555.1
B27: UPIS-Plant Sales | C27: MT | D27: 0 | E27: 0 | F27: 0 | G27: 0 | H27: =+D27+F27 -> 0 | I27: =+E27+G27 -> 0 | J27: 0 | K27: 0 | L27: =+H27+J27 -> 0 | M27: =+I27+K27 -> 0 | N27: 0 | O27: 0 | P27: =+L27+N27 -> 0 | Q27: =+M27+O27 -> 0 | R27: 0 | S27: 0 | T27: =+P27+R27 -> 0 | U27: =+Q27+S27 -> 0 | V27: 0 | W27: 0 | X27: =+N27+R27+V27 -> 0 | Y27: =+O27+S27+W27 -> 0 | Z27: =+T27+V27 -> 0 | AA27: =+U27+W27 -> 0 | AB27: 0 | AC27: 0 | AD27: =+Z27+AB27 -> 0 | AE27: =+AA27+AC27 -> 0 | AF27: 0 | AG27: 0 | AH27: =+AD27+AF27 -> 0 | AI27: =+AE27+AG27 -> 0 | AJ27: 0 | AK27: 0 | AL27: =+AB27+AF27+AJ27 -> 0 | AM27: =+AC27+AG27+AK27 -> 0 | AN27: =+AH27+AJ27 -> 0 | AO27: =+AI27+AK27 -> 0 | AP27: 0 | AQ27: 0 | AR27: =+AN27+AP27 -> 0 | AS27: =+AO27+AQ27 -> 0 | AT27: 0 | AU27: 0 | AV27: =+AR27+AT27 -> 0 | AW27: =+AS27+AU27 -> 0 | AX27: 0 | AY27: 0 | AZ27: =+AP27+AT27+AX27 -> 0 | BA27: =+AQ27+AU27+AY27 -> 0 | BC27: =+AM27+BA27 -> 0 | BD27: =+AV27+AX27 -> 0 | BE27: =+AW27+AY27 -> 0 | BF27: 4268.5371 | BG27: 0
B28: Total Pig & Pig Equiv | C28: MT | D28: =SUM(D25:D27) -> 3694.4919 | E28: =SUM(E25:E27) -> 0 | F28: =SUM(F25:F27) -> 3539.1773 | G28: =SUM(G25:G27) -> 24836.41 | H28: =SUM(H25:H27) -> 7233.6692 | I28: =SUM(I25:I27) -> 24836.41 | J28: =SUM(J25:J27) -> 4758.4593 | K28: =SUM(K25:K27) -> 10814.71 | ... BG28: =SUM(BG25:BG27) -> 183605.9
B29: Gran Slag (Shipping mode-wise)
B30: RAIL | C30: MT | E30: 19751.66 | G30: 69551.36 | I30: =+E30+G30 -> 89303.02 | K30: 77900.91 | M30: =+I30+K30 -> 167203.93 | O30: 73503.63 | Q30: =+M30+O30 -> 240707.56 | S30: 77428.87 | U30: =+Q30+S30 -> 318136.43 | W30: 46883.22 | Y30: =+O30+S30+W30 -> 197815.72 | AA30: =+U30+W30 -> 365019.65 | AC30: 28974.93 | AE30: =+AA30+AC30 -> 393994.58 | AG30: 70613.84 | AI30: =+AE30+AG30 -> 464608.42 | AK30: 70626.11 | AM30: =+AC30+AG30+AK30 -> 170214.88 | AO30: =+AI30+AK30 -> 535234.53 | AQ30: 74386.92 | AS30: =+AO30+AQ30 -> 609621.45 | AU30: =85015-AU31 -> 84766.96 | AW30: =+AS30+AU30 -> 694388.41 | AY30: 104578.25 | BA30: =+AQ30+AU30+AY30 -> 263732.13 | BC30: =+AM30+BA30 -> 433947.01 | BE30: =+AW30+AY30 -> 798966.66 | BG30: 895368.17
B31: ROAD | C31: MT | E31: 0 | G31: 0 | I31: =+E31+G31 -> 0 | K31: 0 | M31: =+I31+K31 -> 0 | O31: 0 | Q31: =+M31+O31 -> 0 | S31: 0 | U31: =+Q31+S31 -> 0 | W31: 0 | Y31: =+O31+S31+W31 -> 0 | AA31: =+U31+W31 -> 0 | AC31: 0 | AE31: =+AA31+AC31 -> 0 | AG31: 0 | AI31: =+AE31+AG31 -> 0 | AK31: 0 | AM31: =+AC31+AG31+AK31 -> 0 | AO31: =+AI31+AK31 -> 0 | AQ31: 0 | AS31: =+AO31+AQ31 -> 0 | AU31: 248.04 | AW31: =+AS31+AU31 -> 248.04 | AY31: 0 | BA31: =+AQ31+AU31+AY31 -> 248.04 | BC31: =+AM31+BA31 -> 248.04 | BE31: =+AW31+AY31 -> 248.04 | BG31: 0
B32: TOTAL | C32: MT | D32: 55704.059 | E32: =SUM(E30:E31) -> 19751.66 | F32: 59123.73 | G32: =SUM(G30:G31) -> 69551.36 | H32: =+D32+F32 -> 114827.79 | I32: =SUM(I30:I31) -> 89303.02 | J32: 67868.386 | K32: =SUM(K30:K31) -> 77900.91 | L32: =+H32+J32 -> 182696.18 | M32: =SUM(M30:M31) -> 167203.93 | N32: 84144 | O32: =SUM(O30:O31) -> 73503.63 | P32: =+L32+N32 -> 266840.18 | Q32: =SUM(Q30:Q31) -> 240707.56 | R32: 83654 | S32: =SUM(S30:S31) -> 77428.87 | T32: =+P32+R32 -> 350494.18 | U32: =SUM(U30:U31) -> 318136.43 | V32: 82552.967 | W32: =SUM(W30:W31) -> 46883.22 | X32: =+N32+R32+V32 -> 250350.97 | Y32: =SUM(Y30:Y31) -> 197815.72 | Z32: =+T32+V32 -> 433047.14 | AA32: =SUM(AA30:AA31) -> 365019.65 | AB32: 43737 | AC32: =SUM(AC30:AC31) -> 28974.93 | AD32: =+Z32+AB32 -> 476784.14 | AE32: =SUM(AE30:AE31) -> 393994.58 | AF32: 81175.015 | AG32: =SUM(AG30:AG31) -> 70613.84 | AH32: =+AD32+AF32 -> 557959.16 | AI32: =SUM(AI30:AI31) -> 464608.42 | AJ32: 85373.723 | AK32: =SUM(AK30:AK31) -> 70626.11 | AL32: =+AB32+AF32+AJ32 -> 210285.74 | AM32: =SUM(AM30:AM31) -> 170214.88 | AN32: =+AH32+AJ32 -> 643332.88 | AO32: =SUM(AO30:AO31) -> 535234.53 | AP32: 85373.723 | AQ32: =SUM(AQ30:AQ31) -> 74386.92 | AR32: =+AN32+AP32 -> 728706.6 | AS32: =SUM(AS30:AS31) -> 609621.45 | AT32: 76976 | AU32: =SUM(AU30:AU31) -> 85015 | AV32: =+AR32+AT32 -> 805682.6 | AW32: =SUM(AW30:AW31) -> 694636.45 | AX32: 85374 | AY32: =SUM(AY30:AY31) -> 104578.25 | AZ32: =+AP32+AT32+AX32 -> 247723.72 | BA32: =SUM(BA30:BA31) -> 263980.17 | BC32: =SUM(BC30:BC31) -> 434195.05 | BD32: =+AV32+AX32 -> 891056.6 | BE32: =SUM(BE30:BE31) -> 799214.7 | BF32: 850423 | BG32: =SUM(BG30:BG31) -> 895368.17
B33: Gran Slag (Sale Type-wise)
B34: DOMESTIC | C34: MT | D34: =+D32 -> 55704.059 | E34: 19751.66 | F34: =+F32 -> 59123.73 | G34: 62282.52 | H34: =+D34+F34 -> 114827.79 | I34: =+E34+G34 -> 82034.18 | J34: =+J32 -> 67868.386 | K34: 70484.41 | L34: =+H34+J34 -> 182696.18 | M34: =+I34+K34 -> 152518.59 | N34: =+N32 -> 84144 | O34: 69714.63 | P34: =+L34+N34 -> 266840.18 | Q34: =+M34+O34 -> 222233.22 | R34: =+R32 -> 83654 | S34: 66353.35 | T34: =+P34+R34 -> 350494.18 | U34: =+Q34+S34 -> 288586.57 | V34: =+V32 -> 82552.967 | W34: 43119.8 | X34: =+N34+R34+V34 -> 250350.97 | Y34: =+O34+S34+W34 -> 179187.78 | Z34: =+T34+V34 -> 433047.14 | AA34: =+U34+W34 -> 331706.37 | AB34: =+AB32 -> 43737 | AC34: 28974.93 | AD34: =+Z34+AB34 -> 476784.14 | AE34: =+AA34+AC34 -> 360681.3 | AF34: =+AF32 -> 81175.015 | AG34: 70613.84 | AH34: =+AD34+AF34 -> 557959.16 | AI34: =+AE34+AG34 -> 431295.14 | AJ34: =+AJ32 -> 85373.723 | AK34: 66811.11 | AL34: =+AB34+AF34+AJ34 -> 210285.74 | AM34: =+AC34+AG34+AK34 -> 166399.88 | AN34: =+AH34+AJ34 -> 643332.88 | AO34: =+AI34+AK34 -> 498106.25 | AP34: =+AP32 -> 85373.723 | AQ34: 66878.09 | AR34: =+AN34+AP34 -> 728706.6 | AS34: =+AO34+AQ34 -> 564984.34 | AT34: =+AT32 -> 76976 | AU34: 77506.15 | AV34: =+AR34+AT34 -> 805682.6 | AW34: =+AS34+AU34 -> 642490.49 | AX34: =+AX32 -> 85374 | AY34: 104578.25 | AZ34: =+AP34+AT34+AX34 -> 247723.72 | BA34: =+AQ34+AU34+AY34 -> 248962.49 | BB34: =+BB32 -> 0 | BC34: =+AM34+BA34 -> 415362.37 | BD34: =+AV34+AX34 -> 891056.6 | BE34: =+AW34+AY34 -> 747068.74 | BF34: =+BF32 -> 850423 | BG34: 843210.72
B35: EXPORT | C35: MT | E35: 0 | G35: 7268.84 | I35: =+E35+G35 -> 7268.84 | K35: 7416.5 | M35: =+I35+K35 -> 14685.34 | O35: 3789 | Q35: =+M35+O35 -> 18474.34 | S35: 11075.52 | U35: =+Q35+S35 -> 29549.86 | W35: 3763.42 | Y35: =+O35+S35+W35 -> 18627.94 | AA35: =+U35+W35 -> 33313.28 | AC35: 0 | AE35: =+AA35+AC35 -> 33313.28 | AG35: 0 | AI35: =+AE35+AG35 -> 33313.28 | AK35: 3815 | AM35: =+AC35+AG35+AK35 -> 3815 | AO35: =+AI35+AK35 -> 37128.28 | AQ35: 7508.83 | AS35: =+AO35+AQ35 -> 44637.11 | AU35: 7508.4 | AW35: =+AS35+AU35 -> 52145.51 | AY35: 0 | BA35: =+AQ35+AU35+AY35 -> 15017.23 | BC35: =+AM35+BA35 -> 18832.23 | BE35: =+AW35+AY35 -> 52145.51 | BG35: 52157.45
B36: TOTAL | C36: MT | E36: =SUM(E34:E35) -> 19751.66 | G36: =SUM(G34:G35) -> 69551.36 | I36: =SUM(I34:I35) -> 89303.02 | K36: =SUM(K34:K35) -> 77900.91 | M36: =SUM(M34:M35) -> 167203.93 | O36: =SUM(O34:O35) -> 73503.63 | Q36: =SUM(Q34:Q35) -> 240707.56 | S36: =SUM(S34:S35) -> 77428.87 | U36: =SUM(U34:U35) -> 318136.43 | W36: =SUM(W34:W35) -> 46883.22 | Y36: =SUM(Y34:Y35) -> 197815.72 | AA36: =SUM(AA34:AA35) -> 365019.65 | AC36: =SUM(AC34:AC35) -> 28974.93 | AE36: =SUM(AE34:AE35) -> 393994.58 | AG36: =SUM(AG34:AG35) -> 70613.84 | AI36: =SUM(AI34:AI35) -> 464608.42 | AK36: =SUM(AK34:AK35) -> 70626.11 | AM36: =SUM(AM34:AM35) -> 170214.88 | AO36: =SUM(AO34:AO35) -> 535234.53 | AQ36: =SUM(AQ34:AQ35) -> 74386.92 | AS36: =SUM(AS34:AS35) -> 609621.45 | AU36: =SUM(AU34:AU35) -> 85014.55 | AW36: =SUM(AW34:AW35) -> 694636 | AY36: =SUM(AY34:AY35) -> 104578.25 | BA36: =SUM(BA34:BA35) -> 263979.72 | BC36: =SUM(BC34:BC35) -> 434194.6 | BE36: =SUM(BE34:BE35) -> 799214.25 | BG36: =SUM(BG34:BG35) -> 895368.17
B37: Coal Tar | C37: MT | D37: 3035.59 | E37: 2951.91 | F37: 3735.89 | G37: 4722.03 | H37: =+D37+F37 -> 6771.48 | I37: =+E37+G37 -> 7673.94 | J37: 4000.063 | K37: 4246.22 | L37: =+H37+J37 -> 10771.543 | M37: =+I37+K37 -> 11920.16 | N37: 4294.7586 | O37: 4469.45 | P37: =+L37+N37 -> 15066.302 | Q37: =+M37+O37 -> 16389.61 | R37: 4295 | S37: 2964.31 | T37: =+P37+R37 -> 19361.302 | U37: =+Q37+S37 -> 19353.92 | V37: 4156.218 | W37: 5277.03 | X37: =+N37+R37+V37 -> 12745.977 | Y37: =+O37+S37+W37 -> 12710.79 | Z37: =+T37+V37 -> 23517.52 | AA37: =+U37+W37 -> 24630.95 | AB37: 4295 | AC37: 4013.56 | AD37: =+Z37+AB37 -> 27812.52 | AE37: =+AA37+AC37 -> 28644.51 | AF37: 4156.218 | AG37: 3334.99 | AH37: =+AD37+AF37 -> 31968.738 | AI37: =+AE37+AG37 -> 31979.5 | AJ37: 4294.7586 | AK37: 4865.01 | AL37: =+AB37+AF37+AJ37 -> 12745.977 | AM37: =+AC37+AG37+AK37 -> 12213.56 | AN37: =+AH37+AJ37 -> 36263.496 | AO37: =+AI37+AK37 -> 36844.51 | AP37: 4294.7586 | AQ37: 4114.56 | AR37: =+AN37+AP37 -> 40558.255 | AS37: =+AO37+AQ37 -> 40959.07 | AT37: 3879 | AU37: 4072.9 | AV37: =+AR37+AT37 -> 44437.255 | AW37: =+AS37+AU37 -> 45031.97 | AX37: =+'Maj Prod Summ'!AX45 -> 4294.759 | AY37: 4389.55 | AZ37: =+AP37+AT37+AX37 -> 12468.518 | BA37: =+AQ37+AU37+AY37 -> 12577.01 | BC37: =+AM37+BA37 -> 24790.57 | BD37: =+AV37+AX37 -> 48732.014 | BE37: =+AW37+AY37 -> 49421.52 | BF37: 46118.873 | BG37: 46910.34
B38: Ammonium Sulphate | C38: MT | D38: 611.23 | E38: 298.44 | F38: 805.56486 | G38: 1229.23 | H38: =+D38+F38 -> 1416.7949 | I38: =+E38+G38 -> 1527.67 | J38: 1326.0581 | K38: 1109.12 | L38: =+H38+J38 -> 2742.8529 | M38: =+I38+K38 -> 2636.79 | N38: 2170.4448 | O38: 706.71 | P38: =+L38+N38 -> 4913.2978 | Q38: =+M38+O38 -> 3343.5 | R38: 2170 | S38: 573.68 | T38: =+P38+R38 -> 7083.2978 | U38: =+Q38+S38 -> 3917.18 | V38: 2099.225 | W38: 734.28 | X38: =+N38+R38+V38 -> 6439.6698 | Y38: =+O38+S38+W38 -> 2014.67 | Z38: =+T38+V38 -> 9182.5227 | AA38: =+U38+W38 -> 4651.46 | AB38: 2170 | AC38: 912.15 | AD38: =+Z38+AB38 -> 11352.523 | AE38: =+AA38+AC38 -> 5563.61 | AF38: 2099.225 | AG38: 1106.24 | AH38: =+AD38+AF38 -> 13451.748 | AI38: =+AE38+AG38 -> 6669.85 | AJ38: 2170.4448 | AK38: 1490.84 | AL38: =+AB38+AF38+AJ38 -> 6439.6698 | AM38: =+AC38+AG38+AK38 -> 3509.23 | AN38: =+AH38+AJ38 -> 15622.192 | AO38: =+AI38+AK38 -> 8160.69 | AP38: 2170.4448 | AQ38: 988.96 | AR38: =+AN38+AP38 -> 17792.637 | AS38: =+AO38+AQ38 -> 9149.65 | AT38: 1977 | AU38: 690.26 | AV38: =+AR38+AT38 -> 19769.637 | AW38: =+AS38+AU38 -> 9839.91 | AX38: =+'Maj Prod Summ'!AX46 -> 2170 | AY38: 674.57 | AZ38: =+AP38+AT38+AX38 -> 6317.4448 | BA38: =+AQ38+AU38+AY38 -> 2353.79 | BC38: =+AM38+BA38 -> 5863.02 | BD38: =+AV38+AX38 -> 21939.637 | BE38: =+AW38+AY38 -> 10514.48 | BF38: 15654.415 | BG38: 12285.02

Sheet Maj Techno Summ
B1: MAJOR TECHNO PARAMETERS 2020-21
D2: 30 | E2: 30 | F2: 31 | G2: 31 | H2: =+D2+F2 -> 61 | I2: =+E2+G2 -> 61 | J2: 30 | K2: 30 | L2: =+H2+J2 -> 91 | M2: =+I2+K2 -> 91 | N2: 31 | O2: 31 | P2: =+L2+N2 -> 122 | Q2: =+M2+O2 -> 122 | R2: 31 | S2: 31 | T2: =+P2+R2 -> 153 | U2: =+Q2+S2 -> 153 | V2: 30 | W2: 30 | X2: =+N2+R2+V2 -> 92 | Y2: =+O2+S2+W2 -> 92 | Z2: =+T2+V2 -> 183 | AA2: =+U2+W2 -> 183 | AB2: 31 | AC2: 31 | AD2: =+Z2+AB2 -> 214 | AE2: =+AA2+AC2 -> 214 | AF2: 30 | AG2: 30 | AH2: =+AD2+AF2 -> 244 | AI2: =+AE2+AG2 -> 244 | AJ2: 31 | AK2: 31 | AL2: =+AB2+AF2+AJ2 -> 92 | AM2: =+AC2+AG2+AK2 -> 92 | AN2: =+AH2+AJ2 -> 275 | AO2: =+AI2+AK2 -> 275 | AP2: 31 | AQ2: 31 | AR2: =+AN2+AP2 -> 306 | AS2: =+AO2+AQ2 -> 306 | AT2: 28 | AU2: 28 | AV2: =+AR2+AT2 -> 334 | AW2: =+AS2+AU2 -> 334 | AX2: 31 | AY2: 31 | AZ2: =+AP2+AT2+AX2 -> 90 | BA2: =+AQ2+AU2+AY2 -> 90 | BB2: =+AZ2+AL2 -> 182 | BC2: =+AM2+BA2 -> 182 | BD2: =+AV2+AX2 -> 365 | BE2: =+AW2+AY2 -> 365 | BF2: 366 | BG2: 366 | BH2: 365
B3: ITEM | C3: Unit | D3: Apr'20 | F3: May'20 | H3: 2M | J3: Jun'20 | L3: QTR-1 | N3: Jul'20 | P3: 4M | R3: Aug'20 | T3: 5M | V3: Sep'20 | X3: QTR-2 | Z3: H1 | AB3: Oct'20 | AD3: 7M | AF3: Nov'20 | AH3: 8M | AJ3: Dec'20 | AL3: QTR-3 | AN3: 9 M | AP3: Jan'21 | AR3: 10M | AT3: Feb'21 | AV3: 11M | AX3: Mar'21 | AZ3: QTR-4 | BB3: H2 | BD3: 2020-21 | BF3: 2019-20 | BH3: 2018-19
D4: ABP | E4: ACT | F4: ABP | G4: ACT | H4: ABP | I4: ACT | J4: ABP | K4: ACT | L4: ABP | M4: ACT | N4: ABP | O4: ACT | P4: ABP | Q4: ACT | R4: ABP | S4: ACT | T4: ABP | U4: ACT | V4: ABP | W4: ACT | X4: ABP | Y4: ACT | Z4: ABP | AA4: ACT | AB4: ABP | AC4: ACT | AD4: ABP | AE4: ACT | AF4: ABP | AG4: ACT | AH4: ABP | AI4: ACT | AJ4: ABP | AK4: ACT | AL4: ABP | AM4: ACT | AN4: ABP | AO4: ACT | AP4: ABP | AQ4: ACT | AR4: ABP | AS4: ACT | AT4: ABP | AU4: ACT | AV4: ABP | AW4: ACT | AX4: ABP | AY4: ACT | AZ4: ABP | BA4: ACT | BB4: ABP | BC4: ACT | BD4: ABP | BE4: ACT | BF4: ABP | BG4: ACT | BH4: ACT
B5: B.F.Coke Yield | C5: % | D5: =('Maj Prod Summ'!D14*100)/('Maj Prod Summ'!D10*31.55) -> 70.999502 | E5: =('Maj Prod Summ'!E14*100)/('Maj Prod Summ'!E10*31.55) -> 69.525848 | F5: =('Maj Prod Summ'!F14*100)/('Maj Prod Summ'!F10*31.55) -> 71.012569 | G5: =('Maj Prod Summ'!G14*100)/('Maj Prod Summ'!G10*31.55) -> 70.013657 | H5: =('Maj Prod Summ'!H14*100)/('Maj Prod Summ'!H10*31.55) -> 71.00603 | I5: =('Maj Prod Summ'!I14*100)/('Maj Prod Summ'!I10*31.55) -> 69.769543 | J5: =('Maj Prod Summ'!J14*100)/('Maj Prod Summ'!J10*31.55) -> 70.999637 | K5: =('Maj Prod Summ'!K14*100)/('Maj Prod Summ'!K10*31.55) -> 70.771354 | ... BC5: =('Maj Prod Summ'!BC14*100)/('Maj Prod Summ'!BC10*31.55) -> 72.813877 | BD5: =('Maj Prod Summ'!BB14*100)/('Maj Prod Summ'!BB10*31.55) -> 70.999787 | BE5: =('Maj Prod Summ'!BC14*100)/('Maj Prod Summ'!BC10*31.55) -> 72.813877 | BF5: 66.5 | BG5: 67.48567 | BH5: 67.015011
B6: ICC in Coal Blend
B7: (COB#10) | C7: % | D7: ='COKE OVENS'!D137 -> 90.113581 | E7: ='COKE OVENS'!E137 -> 89.559691 | F7: ='COKE OVENS'!F137 -> 90.139697 | G7: ='COKE OVENS'!G137 -> 89.98997 | H7: ='COKE OVENS'!H137 -> 90.127408 | I7: ='COKE OVENS'!I137 -> 89.788095 | J7: ='COKE OVENS'!J137 -> 95.078915 | K7: ='COKE OVENS'!K137 -> 91.997697 | ... BE7: ='COKE OVENS'!BE137 -> 95.478511 | BF7: 90 | BG7: 91.425995 | BH7: 91.808306
B8: (COB#11) | C8: % | D8: ='COKE OVENS'!D162 -> 92.951251 | E8: ='COKE OVENS'!E162 -> 92.851579 | F8: ='COKE OVENS'!F162 -> 93.632607 | G8: ='COKE OVENS'!G162 -> 93.531728 | H8: ='COKE OVENS'!H162 -> 93.291666 | I8: ='COKE OVENS'!I162 -> 93.191366 | J8: ='COKE OVENS'!J162 -> 95.078915 | K8: ='COKE OVENS'!K162 -> 96.075315 | ... BE8: ='COKE OVENS'!BE162 -> 95.080613 | BF8: 90 | BG8: 96.370935 | BH8: 94.117213
B9: Overall ICC in Blend | C9: % | D9: ='COKE OVENS'!D261 -> 91.952862 | E9: ='COKE OVENS'!E261 -> 91.690744 | F9: ='COKE OVENS'!F261 -> 92.306968 | G9: ='COKE OVENS'!G261 -> 92.179819 | H9: ='COKE OVENS'!H261 -> 92.133642 | I9: ='COKE OVENS'!I261 -> 91.940691 | J9: ='COKE OVENS'!J261 -> 95.078915 | K9: ='COKE OVENS'!K261 -> 94.579776 | ... BE9: ='COKE OVENS'!BE261 -> 94.71202 | BF9: 90 | BG9: 94.617133 | BH9: 93.297278
B10: BF Coke Rate | C10: Kg/ THM | D10: 428.04279 | E10: =+('B-FCE'!E23/'Maj Prod Summ'!E$17)*1000 -> 428.04279 | F10: 430.79694 | G10: =+('B-FCE'!G23/'Maj Prod Summ'!G$17)*1000 -> 430.79694 | H10: =+('B-FCE'!H23/'Maj Prod Summ'!H$17)*1000 -> 429.4588 | I10: =+('B-FCE'!I23/'Maj Prod Summ'!I$17)*1000 -> 429.4588 | J10: 408 | K10: =+('B-FCE'!K23/'Maj Prod Summ'!K$17)*1000 -> 420.24483 | L10: =+('B-FCE'!L23/'Maj Prod Summ'!L$17)*1000 -> 421.33496 | M10: =+('B-FCE'!M23/'Maj Prod Summ'!M$17)*1000 -> 426.12983 | N10: 360 | O10: =+('B-FCE'!O23/'Maj Prod Summ'!O$17)*1000 -> 426.53981 | P10: =+('B-FCE'!P23/'Maj Prod Summ'!P$17)*1000 -> 400.75277 | Q10: =+('B-FCE'!Q23/'Maj Prod Summ'!Q$17)*1000 -> 426.24932 | R10: 360 | S10: =+('B-FCE'!S23/'Maj Prod Summ'!S$17)*1000 -> 408.54039 | T10: =+('B-FCE'!T23/'Maj Prod Summ'!T$17)*1000 -> 390.55813 | U10: =+('B-FCE'!U23/'Maj Prod Summ'!U$17)*1000 -> 422.1728 | V10: 360 | W10: =+('B-FCE'!W23/'Maj Prod Summ'!W$17)*1000 -> 492.9235 | X10: =+('B-FCE'!X23/'Maj Prod Summ'!X$17)*1000 -> 360 | Y10: =+('B-FCE'!Y23/'Maj Prod Summ'!Y$17)*1000 -> 433.84731 | Z10: =+('B-FCE'!Z23/'Maj Prod Summ'!Z$17)*1000 -> 384.50795 | AA10: =+('B-FCE'!AA23/'Maj Prod Summ'!AA$17)*1000 -> 430.11008 | AB10: 385 | AC10: =+('B-FCE'!AC23/'Maj Prod Summ'!AC$17)*1000 -> 585.76924 | AD10: =+('B-FCE'!AD23/'Maj Prod Summ'!AD$17)*1000 -> 384.55466 | AE10: =+('B-FCE'!AE23/'Maj Prod Summ'!AE$17)*1000 -> 448.10312 | AF10: 370 | AG10: =+('B-FCE'!AG23/'Maj Prod Summ'!AG$17)*1000 -> 455.86205 | AH10: =+('B-FCE'!AH23/'Maj Prod Summ'!AH$17)*1000 -> 382.37429 | AI10: =+('B-FCE'!AI23/'Maj Prod Summ'!AI$17)*1000 -> 449.07146 | AJ10: 360 | AK10: =+('B-FCE'!AK23/'Maj Prod Summ'!AK$17)*1000 -> 399.7133 | AL10: =+('B-FCE'!AL23/'Maj Prod Summ'!AL$17)*1000 -> 369.0599 | AM10: =+('B-FCE'!AM23/'Maj Prod Summ'!AM$17)*1000 -> 466.48777 | AN10: =+('B-FCE'!AN23/'Maj Prod Summ'!AN$17)*1000 -> 379.32893 | AO10: =+('B-FCE'!AO23/'Maj Prod Summ'!AO$17)*1000 -> 442.23204 | AP10: 360 | AQ10: =+('B-FCE'!AQ23/'Maj Prod Summ'!AQ$17)*1000 -> 382.62975 | AR10: =+('B-FCE'!AR23/'Maj Prod Summ'!AR$17)*1000 -> 377.04674 | AS10: =+('B-FCE'!AS23/'Maj Prod Summ'!AS$17)*1000 -> 434.26686 | AT10: 360 | AU10: =+('B-FCE'!AU23/'Maj Prod Summ'!AU$17)*1000 -> 383.5397 | AV10: =+('B-FCE'!AV23/'Maj Prod Summ'!AV$17)*1000 -> 375.38193 | AW10: =+('B-FCE'!AW23/'Maj Prod Summ'!AW$17)*1000 -> 428.83717 | AX10: 360 | AY10: =+('B-FCE'!AY23/'Maj Prod Summ'!AY$17)*1000 -> 383.35482 | AZ10: =+('B-FCE'!AZ23/'Maj Prod Summ'!AZ$17)*1000 -> 360 | BA10: =+('B-FCE'!BA23/'Maj Prod Summ'!BA$17)*1000 -> 383.16672 | BB10: =+('B-FCE'!BB23/'Maj Prod Summ'!BB$17)*1000 -> 364.17241 | BC10: =+('B-FCE'!BC23/'Maj Prod Summ'!BC$17)*1000 -> 418.23055 | BD10: =+('B-FCE'!BD23/'Maj Prod Summ'!BD$17)*1000 -> 373.87865 | BE10: =+('B-FCE'!BE23/'Maj Prod Summ'!BE$17)*1000 -> 423.66105 | BF10: 370.47898 | BG10: 381.58771 | BH10: 388.39311
B11: Nut Coke rate | C11: Kg/ THM | D11: 50.310922 | E11: =+('B-FCE'!E24/'Maj Prod Summ'!E$17)*1000 -> 50.310922 | F11: 53.907133 | G11: =+('B-FCE'!G24/'Maj Prod Summ'!G$17)*1000 -> 53.907133 | H11: =+('B-FCE'!H24/'Maj Prod Summ'!H$17)*1000 -> 52.159866 | I11: =+('B-FCE'!I24/'Maj Prod Summ'!I$17)*1000 -> 52.159866 | J11: 51 | K11: =+('B-FCE'!K24/'Maj Prod Summ'!K$17)*1000 -> 49.438108 | L11: =+('B-FCE'!L24/'Maj Prod Summ'!L$17)*1000 -> 51.720766 | M11: =+('B-FCE'!M24/'Maj Prod Summ'!M$17)*1000 -> 51.176505 | N11: 30 | O11: =+('B-FCE'!O24/'Maj Prod Summ'!O$17)*1000 -> 53.411279 | P11: =+('B-FCE'!P24/'Maj Prod Summ'!P$17)*1000 -> 44.43192 | Q11: =+('B-FCE'!Q24/'Maj Prod Summ'!Q$17)*1000 -> 51.827823 | R11: 30 | S11: =+('B-FCE'!S24/'Maj Prod Summ'!S$17)*1000 -> 45.213228 | T11: =+('B-FCE'!T24/'Maj Prod Summ'!T$17)*1000 -> 40.821657 | U11: =+('B-FCE'!U24/'Maj Prod Summ'!U$17)*1000 -> 50.305172 | V11: 30 | W11: =+('B-FCE'!W24/'Maj Prod Summ'!W$17)*1000 -> 31.371416 | X11: =+('B-FCE'!X24/'Maj Prod Summ'!X$17)*1000 -> 30 | Y11: =+('B-FCE'!Y24/'Maj Prod Summ'!Y$17)*1000 -> 45.368501 | Z11: =+('B-FCE'!Z24/'Maj Prod Summ'!Z$17)*1000 -> 38.679086 | AA11: =+('B-FCE'!AA24/'Maj Prod Summ'!AA$17)*1000 -> 48.181059 | AB11: 35 | AC11: =+('B-FCE'!AC24/'Maj Prod Summ'!AC$17)*1000 -> 6.7818841 | AD11: =+('B-FCE'!AD24/'Maj Prod Summ'!AD$17)*1000 -> 38.329807 | AE11: =+('B-FCE'!AE24/'Maj Prod Summ'!AE$17)*1000 -> 43.395623 | AF11: 35 | AG11: =+('B-FCE'!AG24/'Maj Prod Summ'!AG$17)*1000 -> 19.928041 | AH11: =+('B-FCE'!AH24/'Maj Prod Summ'!AH$17)*1000 -> 37.830983 | AI11: =+('B-FCE'!AI24/'Maj Prod Summ'!AI$17)*1000 -> 40.466772 | AJ11: 30 | AK11: =+('B-FCE'!AK24/'Maj Prod Summ'!AK$17)*1000 -> 33.910922 | AL11: =+('B-FCE'!AL24/'Maj Prod Summ'!AL$17)*1000 -> 32.97005 | AM11: =+('B-FCE'!AM24/'Maj Prod Summ'!AM$17)*1000 -> 22.304537 | AN11: =+('B-FCE'!AN24/'Maj Prod Summ'!AN$17)*1000 -> 36.76511 | AO11: =+('B-FCE'!AO24/'Maj Prod Summ'!AO$17)*1000 -> 39.558347 | AP11: 30 | AQ11: =+('B-FCE'!AQ24/'Maj Prod Summ'!AQ$17)*1000 -> 46.010094 | AR11: =+('B-FCE'!AR24/'Maj Prod Summ'!AR$17)*1000 -> 35.966346 | AS11: =+('B-FCE'!AS24/'Maj Prod Summ'!AS$17)*1000 -> 40.420551 | AT11: 30 | AU11: =+('B-FCE'!AU24/'Maj Prod Summ'!AU$17)*1000 -> 45.503088 | AV11: =+('B-FCE'!AV24/'Maj Prod Summ'!AV$17)*1000 -> 35.383662 | AW11: =+('B-FCE'!AW24/'Maj Prod Summ'!AW$17)*1000 -> 40.964571 | AX11: 30 | AY11: =+('B-FCE'!AY24/'Maj Prod Summ'!AY$17)*1000 -> 43.111882 | AZ11: =+('B-FCE'!AZ24/'Maj Prod Summ'!AZ$17)*1000 -> 30 | BA11: =+('B-FCE'!BA24/'Maj Prod Summ'!BA$17)*1000 -> 44.808102 | BB11: =+('B-FCE'!BB24/'Maj Prod Summ'!BB$17)*1000 -> 31.367816 | BC11: =+('B-FCE'!BC24/'Maj Prod Summ'!BC$17)*1000 -> 35.337972 | BD11: =+('B-FCE'!BD24/'Maj Prod Summ'!BD$17)*1000 -> 34.857516 | BE11: =+('B-FCE'!BE24/'Maj Prod Summ'!BE$17)*1000 -> 41.208946 | BF11: 25 | BG11: 44.993877 | BH11: 29.180384
B12: CDI rate | C12: Kg/ THM | D12: 67 | E12: =+('B-FCE'!E25/'Maj Prod Summ'!E$17)*1000 -> 67.429017 | F12: 68.99929 | G12: =+('B-FCE'!G25/'Maj Prod Summ'!G$17)*1000 -> 68.99929 | H12: =+('B-FCE'!H25/'Maj Prod Summ'!H$17)*1000 -> 68.027908 | I12: =+('B-FCE'!I25/'Maj Prod Summ'!I$17)*1000 -> 68.236352 | J12: 84 | K12: =+('B-FCE'!K25/'Maj Prod Summ'!K$17)*1000 -> 74.703819 | L12: =+('B-FCE'!L25/'Maj Prod Summ'!L$17)*1000 -> 74.074596 | M12: =+('B-FCE'!M25/'Maj Prod Summ'!M$17)*1000 -> 70.573024 | N12: 145 | O12: =+('B-FCE'!O25/'Maj Prod Summ'!O$17)*1000 -> 91.798341 | P12: =+('B-FCE'!P25/'Maj Prod Summ'!P$17)*1000 -> 97.875061 | Q12: =+('B-FCE'!Q25/'Maj Prod Summ'!Q$17)*1000 -> 76.759075 | R12: 145 | S12: =+('B-FCE'!S25/'Maj Prod Summ'!S$17)*1000 -> 94.359599 | T12: =+('B-FCE'!T25/'Maj Prod Summ'!T$17)*1000 -> 109.66375 | U12: =+('B-FCE'!U25/'Maj Prod Summ'!U$17)*1000 -> 80.810638 | V12: 145 | W12: =+('B-FCE'!W25/'Maj Prod Summ'!W$17)*1000 -> 75.5821 | X12: =+('B-FCE'!X25/'Maj Prod Summ'!X$17)*1000 -> 145 | Y12: =+('B-FCE'!Y25/'Maj Prod Summ'!Y$17)*1000 -> 89.285859 | Z12: =+('B-FCE'!Z25/'Maj Prod Summ'!Z$17)*1000 -> 116.65995 | AA12: =+('B-FCE'!AA25/'Maj Prod Summ'!AA$17)*1000 -> 80.224066 | AB12: 115 | AC12: =+('B-FCE'!AC25/'Maj Prod Summ'!AC$17)*1000 -> 5.4383032 | AD12: =+('B-FCE'!AD25/'Maj Prod Summ'!AD$17)*1000 -> 116.50236 | AE12: =+('B-FCE'!AE25/'Maj Prod Summ'!AE$17)*1000 -> 71.579389 | AF12: 130 | AG12: =+('B-FCE'!AG25/'Maj Prod Summ'!AG$17)*1000 -> 86.486662 | AH12: =+('B-FCE'!AH25/'Maj Prod Summ'!AH$17)*1000 -> 118.52438 | AI12: =+('B-FCE'!AI25/'Maj Prod Summ'!AI$17)*1000 -> 73.439878 | AJ12: 145 | AK12: =+('B-FCE'!AK25/'Maj Prod Summ'!AK$17)*1000 -> 110.28846 | AL12: =+('B-FCE'!AL25/'Maj Prod Summ'!AL$17)*1000 -> 132.97005 | AM12: =+('B-FCE'!AM25/'Maj Prod Summ'!AM$17)*1000 -> 75.187876 | AN12: =+('B-FCE'!AN25/'Maj Prod Summ'!AN$17)*1000 -> 122.12797 | AO12: =+('B-FCE'!AO25/'Maj Prod Summ'!AO$17)*1000 -> 78.54588 | AP12: 145 | AQ12: =+('B-FCE'!AQ25/'Maj Prod Summ'!AQ$17)*1000 -> 108.73347 | AR12: =+('B-FCE'!AR25/'Maj Prod Summ'!AR$17)*1000 -> 124.8285 | AS12: =+('B-FCE'!AS25/'Maj Prod Summ'!AS$17)*1000 -> 82.580114 | AT12: 145 | AU12: =+('B-FCE'!AU25/'Maj Prod Summ'!AU$17)*1000 -> 111.68986 | AV12: =+('B-FCE'!AV25/'Maj Prod Summ'!AV$17)*1000 -> 126.79848 | AW12: =+('B-FCE'!AW25/'Maj Prod Summ'!AW$17)*1000 -> 85.695938 | AX12: 145 | AY12: =+('B-FCE'!AY25/'Maj Prod Summ'!AY$17)*1000 -> 116.2694 | AZ12: =+('B-FCE'!AZ25/'Maj Prod Summ'!AZ$17)*1000 -> 145 | BA12: =+('B-FCE'!BA25/'Maj Prod Summ'!BA$17)*1000 -> 112.35308 | BB12: =+('B-FCE'!BB25/'Maj Prod Summ'!BB$17)*1000 -> 139.45977 | BC12: =+('B-FCE'!BC25/'Maj Prod Summ'!BC$17)*1000 -> 96.712921 | BD12: =+('B-FCE'!BD25/'Maj Prod Summ'!BD$17)*1000 -> 128.57732 | BE12: =+('B-FCE'!BE25/'Maj Prod Summ'!BE$17)*1000 -> 89.175353 | BF12: 139.85352 | BG12: 118.98027 | BH12: 123.03826
B13: Total Fuel | C13: Kg/ THM | D13: =SUM(D10:D12) -> 545.35371 | E13: =SUM(E10:E12) -> 545.78273 | F13: =SUM(F10:F12) -> 553.70336 | G13: =SUM(G10:G12) -> 553.70336 | H13: =SUM(H10:H12) -> 549.64657 | I13: =SUM(I10:I12) -> 549.85502 | J13: =SUM(J10:J12) -> 543 | K13: =SUM(K10:K12) -> 544.38676 | ... BE13: =SUM(BE10:BE12) -> 554.04535 | BF13: 535.3325 | BG13: 545.56186 | BH13: 540.61176
B14: BF PRODUCTIVITY | C14: T/M³/Day | D14: 1.4568572 | E14: 1.457 | F14: 1.448 | G14: 1.448 | H14: =+('Maj Prod Summ'!H17/3551)/('B-FCE'!D47+'B-FCE'!F47) -> 1.4522899 | I14: =+('Maj Prod Summ'!I17/3551)/('B-FCE'!E47+'B-FCE'!G47) -> 1.4523588 | J14: 1.8459845 | K14: 1.7 | L14: =+('Maj Prod Summ'!L17/3551)/('B-FCE'!H47+'B-FCE'!J47) -> 1.5798462 | M14: =+('Maj Prod Summ'!M17/3551)/('B-FCE'!I47+'B-FCE'!K47) -> 1.5330437 | N14: 2.2574511 | O14: 1.774 | P14: =+('Maj Prod Summ'!P17/3551)/('B-FCE'!L47+'B-FCE'!N47) -> 1.7568019 | Q14: =+('Maj Prod Summ'!Q17/3551)/('B-FCE'!M47+'B-FCE'!O47) -> 1.5962325 | R14: 2.2442943 | S14: 1.845 | T14: =+('Maj Prod Summ'!T17/3551)/('B-FCE'!P47+'B-FCE'!R47) -> 1.857748 | U14: =+('Maj Prod Summ'!U17/3551)/('B-FCE'!Q47+'B-FCE'!S47) -> 1.6473634 | V14: 2.2522967 | W14: 1.599 | X14: =+('Maj Prod Summ'!X17/3551)/('B-FCE'!N47+'B-FCE'!R47+'B-FCE'!V47) -> 2.2513421 | Y14: =+('Maj Prod Summ'!Y17/3551)/('B-FCE'!O47+'B-FCE'!S47+'B-FCE'!W47) -> 1.7589481 | Z14: =+('Maj Prod Summ'!Z17/3551)/('B-FCE'!V47+'B-FCE'!T47) -> 1.9244953 | AA14: =+('Maj Prod Summ'!AA17/3551)/('B-FCE'!W47+'B-FCE'!U47) -> 1.6417925 | AB14: 1.7600676 | AC14: 1.182 | AD14: =+('Maj Prod Summ'!AD17/3551)/('B-FCE'!Z47+'B-FCE'!AB47) -> 1.9075768 | AE14: =+('Maj Prod Summ'!AE17/3551)/('B-FCE'!AA47+'B-FCE'!AC47) -> 1.571146 | AF14: 2.2528865 | AG14: 1.65 | AH14: =+('Maj Prod Summ'!AH17/3551)/('B-FCE'!AD47+'B-FCE'!AF47) -> 1.9524068 | AI14: =+('Maj Prod Summ'!AI17/3551)/('B-FCE'!AE47+'B-FCE'!AG47) -> 1.5805732 | AJ14: 2.2528865 | AK14: 1.928 | AL14: =+('Maj Prod Summ'!AL17/3551)/('B-FCE'!AB47+'B-FCE'!AF47+'B-FCE'!AJ47) -> 2.1289069 | AM14: =+('Maj Prod Summ'!AM17/3551)/('B-FCE'!AC47+'B-FCE'!AG47+'B-FCE'!AK47) -> 1.5810815 | AN14: =+('Maj Prod Summ'!AN17/3551)/('B-FCE'!AJ47+'B-FCE'!AH47) -> 1.9885055 | AO14: =+('Maj Prod Summ'!AO17/3551)/('B-FCE'!AK47+'B-FCE'!AI47) -> 1.6210506 | AP14: 2.2528865 | AQ14: 2.059 | AR14: =+('Maj Prod Summ'!AR17/3551)/('B-FCE'!AN47+'B-FCE'!AP47) -> 2.0164452 | AS14: =+('Maj Prod Summ'!AS17/3551)/('B-FCE'!AO47+'B-FCE'!AQ47) -> 1.6684771 | AT14: 2.253 | AU14: 2.03 | AV14: =+('Maj Prod Summ'!AV17/3551)/('B-FCE'!AR47+'B-FCE'!AT47) -> 2.0373361 | AW14: =+('Maj Prod Summ'!AW17/3551)/('B-FCE'!AS47+'B-FCE'!AU47) -> 1.7009001 | AX14: 2.253 | AY14: 2.187 | AZ14: =+('Maj Prod Summ'!AZ17/3551)/('B-FCE'!AP47+'B-FCE'!AT47+'B-FCE'!AX47) -> 2.2529613 | BA14: =+('Maj Prod Summ'!BA17/3551)/('B-FCE'!AQ47+'B-FCE'!AU47+'B-FCE'!AY47) -> 2.0943415 | BB14: =+('Maj Prod Summ'!BB17/3551)/('B-FCE'!AL47+'B-FCE'!AZ47) -> 2.1940807 | BC14: =+('Maj Prod Summ'!BC17/3551)/('B-FCE'!AM47+'B-FCE'!BA47) -> 1.8426183 | BD14: =+('Maj Prod Summ'!BD17/3551)/('B-FCE'!AX47+'B-FCE'!AV47) -> 2.0565754 | BE14: =+('Maj Prod Summ'!BE17/3551)/('B-FCE'!AY47+'B-FCE'!AW47) -> 1.7450413 | BF14: 2.1585499 | BG14: 2.0057992 | BH14: 1.7419242
B15: Gross Coal to Hot Metal Ratio | C15: Kg/ THM | D15: 991.89383 | E15: 991.57268 | F15: 1001.3622 | G15: 1001.2956 | H15: =+((D15*'Maj Prod Summ'!D$17)+('Maj Prod Summ'!F$17*F15))/('Maj Prod Summ'!H$17) -> 996.76185 | I15: 996.89047 | J15: 958.6769 | K15: 986.78215 | L15: =+((H15*'Maj Prod Summ'!H$17)+('Maj Prod Summ'!J$17*J15))/('Maj Prod Summ'!L$17) -> 982.34371 | M15: 992.97434 | N15: 881 | O15: 1026.6954 | P15: =+((L15*'Maj Prod Summ'!L$17)+('Maj Prod Summ'!N$17*N15))/('Maj Prod Summ'!P$17) -> 948.33576 | Q15: 1002.0323 | R15: 881 | S15: 981.69055 | T15: =+((P15*'Maj Prod Summ'!P$17)+('Maj Prod Summ'!R$17*R15))/('Maj Prod Summ'!T$17) -> 931.49117 | U15: 997.4904 | V15: 881 | W15: 1170.2716 | X15: =+((N15*'Maj Prod Summ'!N$17)+('Maj Prod Summ'!V$17*V15)+(R15*'Maj Prod Summ'!R$17))/('Maj Prod Summ'!X$17) -> 881 | Y15: 1038.2667 | Z15: =+((V15*'Maj Prod Summ'!V$17)+(T15*'Maj Prod Summ'!T$17))/('Maj Prod Summ'!Z$17) -> 921.49446 | AA15: 1015.9172 | AB15: 1000 | AC15: 1254.4862 | AD15: =+((Z15*'Maj Prod Summ'!Z$17)+('Maj Prod Summ'!AB$17*AB15))/('Maj Prod Summ'!AD$17) -> 928.94749 | AE15: 1043.3321 | AF15: 882 | AG15: 1045.5776 | AH15: =+((AD15*'Maj Prod Summ'!AD$17)+('Maj Prod Summ'!AF$17*AF15))/('Maj Prod Summ'!AH$17) -> 921.91449 | AI15: 1043.5757 | AJ15: 883 | AK15: 966.73827 | AL15: =+((AB15*'Maj Prod Summ'!AB$17)+('Maj Prod Summ'!AJ$17*AJ15)+(AF15*'Maj Prod Summ'!AF$17))/('Maj Prod Summ'!AL$17) -> 906.94842 | AM15: 1067.5942 | AN15: =+((AJ15*'Maj Prod Summ'!AJ$17)+(AH15*'Maj Prod Summ'!AH$17))/('Maj Prod Summ'!AN$17) -> 916.61785 | AO15: 1032.9764 | AP15: 884 | AQ15: 896.07875 | AR15: =+((AN15*'Maj Prod Summ'!AN$17)+('Maj Prod Summ'!AP$17*AP15))/('Maj Prod Summ'!AR$17) -> 912.76662 | AS15: 1014.8133 | AT15: 885 | AU15: 918 | AV15: =+((AR15*'Maj Prod Summ'!AR$17)+('Maj Prod Summ'!AT$17*AT15))/('Maj Prod Summ'!AV$17) -> 910.05488 | AW15: 1005 | AX15: 884 | AY15: =+((('B-FCE'!AY33*100/'Maj Techno Summ'!AY5)*100/(100-(('COKE OVENS'!AY140*1+'COKE OVENS'!AY166*31.55/17.2)/(1+31.55/17.2))))*100/(100-((3*AY9+4*(100-AY9))/100))+(('B-FCE'!AY25/0.91/0.97)))*1000/'Maj Prod Summ'!AY17 -> 885.90487 | AZ15: =+((AP15*'Maj Prod Summ'!AP$17)+('Maj Prod Summ'!AX$17*AX15)+(AT15*'Maj Prod Summ'!AT$17))/('Maj Prod Summ'!AZ$17) -> 884.3125 | BA15: =+((AQ15*'Maj Prod Summ'!AQ$17)+('Maj Prod Summ'!AY$17*AY15)+(AU15*'Maj Prod Summ'!AU$17))/('Maj Prod Summ'!BA$17) -> 899.00965 | BB15: =+((AL15*'Maj Prod Summ'!AL$17)+('Maj Prod Summ'!AZ$17*AZ15))/('Maj Prod Summ'!BB$17) -> 894.73716 | BC15: =+((AM15*'Maj Prod Summ'!AM$17)+('Maj Prod Summ'!BA$17*BA15))/('Maj Prod Summ'!BC$17) -> 969.95476 | BD15: =+((AX15*'Maj Prod Summ'!AX$17)+(AV15*'Maj Prod Summ'!AV$17))/('Maj Prod Summ'!BD$17) -> 907.50854 | BE15: =+(AW15*'Maj Prod Summ'!AW17+'Maj Prod Summ'!AY17*'Maj Techno Summ'!AY15)/'Maj Prod Summ'!BE17 -> 991.44637 | BF15: 886.42712 | BG15: 931.68363 | BH15: 905.6097
B16: Hot Metal to Crude Steel | C16: Kg/ TCS | D16: =+(D43/'Maj Prod Summ'!D18)*1000 -> 1085.5737 | E16: =+(E43/'Maj Prod Summ'!E18)*1000 -> 1060.5761 | F16: =+(F43/'Maj Prod Summ'!F18)*1000 -> 1108.5977 | G16: =+(G43/'Maj Prod Summ'!G18)*1000 -> 1090.3405 | H16: =+(H43/'Maj Prod Summ'!H18)*1000 -> 1097.3046 | I16: =+(I43/'Maj Prod Summ'!I18)*1000 -> 1075.7412 | J16: =+(J43/'Maj Prod Summ'!J18)*1000 -> 1086.9565 | K16: =+(K43/'Maj Prod Summ'!K18)*1000 -> 1100.9078 | ... AS16: =+(AS43/'Maj Prod Summ'!AS18)*1000 -> 1080.3259 | AT16: 1065 | AU16: =+(AU43/'Maj Prod Summ'!AU18)*1000 -> 1037.579 | AV16: =+(AV43/'Maj Prod Summ'!AV18)*1000 -> 1078.3681 | AW16: =+(AW43/'Maj Prod Summ'!AW18)*1000 -> 1075.3484 | AX16: 1065 | AY16: =+(AY43/'Maj Prod Summ'!AY18)*1000 -> 1040.7856 | AZ16: =+(AZ43/'Maj Prod Summ'!AZ18)*1000 -> 1064.9996 | BA16: =+(BA43/'Maj Prod Summ'!BA18)*1000 -> 1045.9925 | BB16: =+(BB43/BB33)*1000 -> 1065.9406 | BC16: =+(BC43/BC33)*1000 -> 1054.8805 | BD16: =+(BD43/BD33)*1000 -> 1077.0434 | BE16: =+(BE43/'Maj Prod Summ'!BE18)*1000 -> 1071.1761 | BF16: 1065 | BG16: 1093.6626 | BH16: 1078.33
B17: Scrap consumption at SMS | C17: Kg/ TCS | D17: =+(D44/'Maj Prod Summ'!D18)*1000 -> 54.501748 | E17: =+(E44/'Maj Prod Summ'!E18)*1000 -> 54.501748 | F17: =+(F44/'Maj Prod Summ'!F18)*1000 -> 25.435024 | G17: =+(G44/'Maj Prod Summ'!G18)*1000 -> 25.435024 | H17: =+(H44/'Maj Prod Summ'!H18)*1000 -> 39.692103 | I17: =+(I44/'Maj Prod Summ'!I18)*1000 -> 39.692103 | J17: =+(J44/'Maj Prod Summ'!J18)*1000 -> 28 | K17: =+(K44/'Maj Prod Summ'!K18)*1000 -> 21.146409 | ... AS17: =+(AS44/'Maj Prod Summ'!AS18)*1000 -> 35.771262 | AT17: 50 | AU17: =+(AU44/'Maj Prod Summ'!AU18)*1000 -> 62.552604 | AV17: =+(AV44/'Maj Prod Summ'!AV18)*1000 -> 39.416328 | AW17: =+(AW44/'Maj Prod Summ'!AW18)*1000 -> 38.889704 | AX17: 50 | AY17: =+(AY44/'Maj Prod Summ'!AY18)*1000 -> 57.384988 | AZ17: =+(AZ44/'Maj Prod Summ'!AZ18)*1000 -> 50 | BA17: =+(BA44/'Maj Prod Summ'!BA18)*1000 -> 55.77954 | BB17: =+(BB44/BB33)*1000 -> 49.059178 | BC17: =+(BC44/BC33)*1000 -> 51.699586 | BD17: =+(BD44/BD33)*1000 -> 40.465028 | BE17: =+(BE44/'Maj Prod Summ'!BE18)*1000 -> 41.122433 | BF17: 50 | BG17: 25.532166 | BH17: 41.130412
B18: TMI | C18: Kg/ TCS | D18: =SUM(D16:D17) -> 1140.0755 | E18: =SUM(E16:E17) -> 1115.0778 | F18: =SUM(F16:F17) -> 1134.0327 | G18: =SUM(G16:G17) -> 1115.7755 | H18: =SUM(H16:H17) -> 1136.9967 | I18: =SUM(I16:I17) -> 1115.4333 | J18: =SUM(J16:J17) -> 1114.9565 | K18: =SUM(K16:K17) -> 1122.0543 | ... BE18: =SUM(BE16:BE17) -> 1112.2985 | BF18: 1115 | BG18: 1119.1948 | BH18: 1119.4604
B19: Total Ferro Alloys (FeMn+FeSi+SiMn) | C19: Kg/ TCS | D19: =D53+D54+D55 -> 20.592129 | E19: =E53+E54+E55 -> 20.612258 | F19: =F53+F54+F55 -> 20.342062 | G19: =G53+G54+G55 -> 20.342062 | H19: =H53+H54+H55 -> 20.464719 | I19: =I53+I54+I55 -> 20.474592 | J19: =J53+J54+J55 -> 21 | K19: =K53+K54+K55 -> 20.354996 | ... BE19: =BE53+BE54+BE55 -> 20.212673 | BF19: 21 | BG19: 21.832464 | BH19: 23.120676
B20: Mill yield
B21: WR Mill | C21: % | D21: =+('Maj Prod Summ'!D28/WRM!E5)*100 -> 95.037181 | E21: =+('Maj Prod Summ'!E28/WRM!F5)*100 -> 95.037181 | F21: =+('Maj Prod Summ'!F28/WRM!G5)*100 -> 95.693367 | G21: =+('Maj Prod Summ'!G28/WRM!H5)*100 -> 95.694884 | H21: =+('Maj Prod Summ'!H28/WRM!I5)*100 -> 95.397971 | I21: =+('Maj Prod Summ'!I28/WRM!J5)*100 -> 95.398803 | J21: =+('Maj Prod Summ'!J28/WRM!K5)*100 -> 95 | K21: =+('Maj Prod Summ'!K28/WRM!L5)*100 -> 95.952244 | ... BE21: =+('Maj Prod Summ'!BE28/WRM!BF5)*100 -> 94.958654 | BF21: 96.5 | BG21: 96.195271 | BH21: 96.032659
B22: Bar Mill | C22: % | D22: =+('Maj Prod Summ'!D29/BM!E5)*100 -> 92.39899 | E22: =+('Maj Prod Summ'!E29/BM!F5)*100 -> 92.39899 | F22: =+('Maj Prod Summ'!F29/BM!G5)*100 -> 95.46271 | G22: =+('Maj Prod Summ'!G29/BM!H5)*100 -> 95.462994 | H22: =+('Maj Prod Summ'!H29/BM!I5)*100 -> 94.971787 | I22: =+('Maj Prod Summ'!I29/BM!J5)*100 -> 94.972024 | J22: =+('Maj Prod Summ'!J29/BM!K5)*100 -> 95 | K22: =+('Maj Prod Summ'!K29/BM!L5)*100 -> 94.819006 | ... BE22: =+('Maj Prod Summ'!BE29/BM!BF5)*100 -> 95.175924 | BF22: 96.5 | BG22: 96.065593 | BH22: 96.05494
B23: US Mill | C23: % | D23: =+('Maj Prod Summ'!D30/USM!F5)*100 -> #DIV/0! | E23: =+('Maj Prod Summ'!E30/USM!G5)*100 -> #DIV/0! | F23: =+('Maj Prod Summ'!F30/USM!H5)*100 -> #DIV/0! | G23: =+('Maj Prod Summ'!G30/USM!I5)*100 -> #DIV/0! | H23: =+('Maj Prod Summ'!H30/USM!J5)*100 -> #DIV/0! | I23: =+('Maj Prod Summ'!I30/USM!K5)*100 -> #DIV/0! | J23: =+('Maj Prod Summ'!J30/USM!L5)*100 -> #DIV/0! | K23: =+('Maj Prod Summ'!K30/USM!M5)*100 -> #DIV/0! | ... BA23: =+('Maj Prod Summ'!BA30/USM!BC5)*100 -> 95.178255 | BB23: =+BD23 -> 95.699819 | BC23: =+('Maj Prod Summ'!BC30/USM!BE5)*100 -> 95.266762 | BD23: =+('Maj Prod Summ'!BD30/USM!BD5)*100 -> 95.699819 | BE23: =+('Maj Prod Summ'!BE30/USM!BE5)*100 -> 95.266762 | BF23: 95.7 | BG23: 95.476013 | BH23: 95.486333
B24: Overall Sp Energy Consumpt | C24: G.cal/TCS | D24: 6.5341824 | E24: 6.5338425 | F24: 6.647 | G24: 6.6638049 | H24: =+((D33*D24)+(F33*F24))/H33 -> 6.5916635 | I24: =+((E33*E24)+(G33*G24))/I33 -> 6.600059 | J24: 6.27 | K24: 6.3708623 | L24: =+((H33*H24)+(J33*J24))/L33 -> 6.4692492 | M24: =+((I33*I24)+(K33*K24))/M33 -> 6.5178659 | N24: 6.2 | O24: 6.575813 | P24: =+((L33*L24)+(N33*N24))/P33 -> 6.3771472 | Q24: =+((M33*M24)+(O33*O24))/Q33 -> 6.5341717 | R24: 5.95 | S24: 6.3597118 | T24: =+((P33*P24)+(R33*R24))/T33 -> 6.2687482 | U24: =+((Q33*Q24)+(S33*S24))/U33 -> 6.4938323 | V24: 5.95 | W24: 8.1269049 | X24: =+((N24*N33)+(R24*R33)+(V24*V33))/X33 -> 6.0340262 | Y24: =+((O24*O33)+(S24*S33)+(W24*W33))/Y33 -> 6.7978463 | Z24: =+((T33*T24)+(V33*V24))/Z33 -> 6.2049101 | AA24: =+((U33*U24)+(W33*W24))/AA33 -> 6.6587957 | AB24: 8.5 | AC24: 7.9370955 | AD24: =+((Z33*Z24)+(AB33*AB24))/AD33 -> 6.4236109 | AE24: =+((AA33*AA24)+(AC33*AC24))/AE33 -> 6.7951083 | AF24: 5.95 | AG24: 6.6548428 | AH24: =+((AD33*AD24)+(AF33*AF24))/AH33 -> 6.351274 | AI24: =+((AE33*AE24)+(AG33*AG24))/AI33 -> 6.7767353 | AJ24: 5.95 | AK24: 6.5098715 | AL24: =+((AB24*AB33)+(AF24*AF33)+(AJ24*AJ33))/AL33 -> 6.4728943 | AM24: =+((AC24*AC33)+(AG24*AG33)+(AK24*AK33))/AM33 -> 6.9065716 | AN24: =+((AH33*AH24)+(AJ33*AJ24))/AN33 -> 6.2958494 | AO24: =+((AI33*AI24)+(AK33*AK24))/AO33 -> 6.7404018 | AP24: 5.95 | AQ24: 6.0224855 | AR24: =+((AN33*AN24)+(AP33*AP24))/AR33 -> 6.2544697 | AS24: =+((AO33*AO24)+(AQ33*AQ24))/AS33 -> 6.6396785 | AT24: 5.95 | AU24: 5.8971714 | AV24: =+((AR33*AR24)+(AT33*AT24))/AV33 -> 6.2241517 | AW24: =+((AS33*AS24)+(AU33*AU24))/AW33 -> 6.5532204 | AX24: 5.95 | AY24: 5.8653442 | AZ24: =+((AP24*AP33)+(AT24*AT33)+(AX24*AX33))/AZ33 -> 5.95 | BA24: =+((AQ24*AQ33)+(AU24*AU33)+(AY24*AY33))/BA33 -> 5.9267312 | BB24: =+((AL24*AL33)+(AZ24*AZ33))/BB33 -> 6.1899097 | BC24: =+((AM24*AM33)+(BA24*BA33))/BC33 -> 6.3171495 | BD24: =+((AV33*AV24)+(AX33*AX24))/BD33 -> 6.1969869 | BE24: 6.4827566 | BF24: 5.95 | BG24: 6.1800191 | BH24: 6.3116941
B25: Overall Specific Power Consumption(Kwh) | C25: KwH/TSS | D25: 672.88078 | E25: 672.30305 | F25: 659.15639 | G25: 658.84 | H25: =+((D25*'Maj Prod Summ'!D35)+('Maj Prod Summ'!F35*F25))/'Maj Prod Summ'!H35 -> 665.73605 | I25: =+((E25*'Maj Prod Summ'!E35)+('Maj Prod Summ'!G35*G25))/'Maj Prod Summ'!I35 -> 665.29437 | J25: 550.11683 | K25: 634.42 | L25: =+((D25*'Maj Prod Summ'!D35)+(F25*'Maj Prod Summ'!F35)+(J25*'Maj Prod Summ'!J35))/('Maj Prod Summ'!D35+'Maj Prod Summ'!F35+'Maj Prod Summ'!J35) -> 620.75219 | M25: =+((E25*'Maj Prod Summ'!E35)+(G25*'Maj Prod Summ'!G35)+(K25*'Maj Prod Summ'!K35))/('Maj Prod Summ'!E35+'Maj Prod Summ'!G35+'Maj Prod Summ'!K35) -> 654.31639 | N25: 438.86154 | O25: 500.29 | P25: =+((L25*'Maj Prod Summ'!L35)+('Maj Prod Summ'!N35*N25))/'Maj Prod Summ'!P35 -> 556.03529 | Q25: =+((M25*'Maj Prod Summ'!M35)+('Maj Prod Summ'!O35*O25))/'Maj Prod Summ'!Q35 -> 604.76216 | R25: 438.70206 | S25: 540.22 | T25: =+((P25*'Maj Prod Summ'!P35)+('Maj Prod Summ'!R35*R25))/'Maj Prod Summ'!T35 -> 525.35682 | U25: =+((Q25*'Maj Prod Summ'!Q35)+('Maj Prod Summ'!S35*S25))/'Maj Prod Summ'!U35 -> 589.52729 | V25: 427.93062 | W25: 823.15 | X25: =+((N25*'Maj Prod Summ'!N35)+('Maj Prod Summ'!R35*R25)+(V25*'Maj Prod Summ'!V35))/'Maj Prod Summ'!X35 -> 435.15996 | Y25: =+((O25*'Maj Prod Summ'!O35)+('Maj Prod Summ'!S35*S25)+(W25*'Maj Prod Summ'!W35))/'Maj Prod Summ'!Y35 -> 584.51428 | Z25: =+((T25*'Maj Prod Summ'!T35)+('Maj Prod Summ'!V35*V25))/'Maj Prod Summ'!Z35 -> 505.09054 | AA25: =+((U25*'Maj Prod Summ'!U35)+('Maj Prod Summ'!W35*W25))/'Maj Prod Summ'!AA35 -> 616.50676 | AB25: 698.53593 | AC25: 960.92 | AD25: =+((Z25*'Maj Prod Summ'!Z35)+('Maj Prod Summ'!AB35*AB25))/'Maj Prod Summ'!AD35 -> 523.11688 | AE25: =+((AA25*'Maj Prod Summ'!AA35)+('Maj Prod Summ'!AC35*AC25))/'Maj Prod Summ'!AE35 -> 649.34676 | AF25: 477.80723 | AG25: 671.71 | AH25: =+((AD25*'Maj Prod Summ'!AD35)+('Maj Prod Summ'!AF35*AF25))/'Maj Prod Summ'!AH35 -> 516.23265 | AI25: =+((AE25*'Maj Prod Summ'!AE35)+('Maj Prod Summ'!AG35*AG25))/'Maj Prod Summ'!AI35 -> 652.1622 | AJ25: 469.77836 | AK25: 540.23 | AL25: =+((AB25*'Maj Prod Summ'!AB35)+('Maj Prod Summ'!AF35*AF25)+(AJ25*'Maj Prod Summ'!AJ35))/'Maj Prod Summ'!AL35 -> 519.33286 | AM25: =+((AC25*'Maj Prod Summ'!AC35)+('Maj Prod Summ'!AG35*AG25)+(AK25*'Maj Prod Summ'!AK35))/'Maj Prod Summ'!AM35 -> 679.07193 | AN25: =+((AH25*'Maj Prod Summ'!AH35)+('Maj Prod Summ'!AJ35*AJ25))/'Maj Prod Summ'!AN35 -> 509.87824 | AO25: =+((AI25*'Maj Prod Summ'!AI35)+('Maj Prod Summ'!AK35*AK25))/'Maj Prod Summ'!AO35 -> 636.51436 | AP25: 475.54667 | AQ25: 497.94 | AR25: =+((AN25*'Maj Prod Summ'!AN35)+('Maj Prod Summ'!AP35*AP25))/'Maj Prod Summ'!AR35 -> 505.79498 | AS25: =+((AO25*'Maj Prod Summ'!AO35)+('Maj Prod Summ'!AQ35*AQ25))/'Maj Prod Summ'!AS35 -> 617.70377 | AT25: 473 | AU25: =+'POWER DISTRIBUTION'!AZ17/('Maj Prod Summ'!AU35+0.25*'Maj Prod Summ'!AU24) -> 465.19781 | AV25: =+((AR25*'Maj Prod Summ'!AR35)+('Maj Prod Summ'!AT35*AT25))/'Maj Prod Summ'!AV35 -> 502.55591 | AW25: =+((AS25*'Maj Prod Summ'!AS35)+('Maj Prod Summ'!AU35*AU25))/'Maj Prod Summ'!AW35 -> 599.52148 | AX25: 477 | AY25: =+'POWER DISTRIBUTION'!BD17/('Maj Prod Summ'!AY35+0.25*'Maj Prod Summ'!AY24) -> 439.52012 | AZ25: =+((AP25*'Maj Prod Summ'!AP35)+('Maj Prod Summ'!AT35*AT25)+(AX25*'Maj Prod Summ'!AX35))/'Maj Prod Summ'!AZ35 -> 475.25122 | BA25: =+((AQ25*'Maj Prod Summ'!AQ35)+('Maj Prod Summ'!AU35*AU25)+(AY25*'Maj Prod Summ'!AY35))/'Maj Prod Summ'!BA35 -> 466.00403 | BB25: =+((AL25*'Maj Prod Summ'!AL35)+(AZ25*'Maj Prod Summ'!AZ35))/'Maj Prod Summ'!BB35 -> 495.47152 | BC25: =+((AM25*'Maj Prod Summ'!AM35)+(BA25*'Maj Prod Summ'!BA35))/'Maj Prod Summ'!BC35 -> 549.28998 | BD25: =+((AV25*'Maj Prod Summ'!AV35)+('Maj Prod Summ'!AX35*AX25))/'Maj Prod Summ'!BD35 -> 500.04339 | BE25: =+((AW25*'Maj Prod Summ'!AW35)+('Maj Prod Summ'!AY35*AY25))/'Maj Prod Summ'!BE35 -> 579.80533 | BF25: 483.423 | BG25: 525.26173 | BH25: 552.03691
C26: KwH/TCS | D26: 614.16162 | E26: 613.97359 | F26: 628.42606 | G26: 628.43 | H26: =+((D26*D33)+(F33*F26))/H33 -> 621.42942 | I26: =+((E26*E33)+(G33*G26))/(I33) -> 621.3392 | J26: 531.6046 | K26: 584.14 | L26: =+((H26*H33)+(J33*J26))/L33 -> 587.24511 | M26: =+((I26*I33)+(K33*K26))/(M33) -> 607.99906 | N26: 438.57014 | O26: 566.85 | P26: =+((L26*L33)+(N33*N26))/P33 -> 536.38789 | Q26: =+((M26*M33)+(O33*O26))/(Q33) -> 596.4201 | R26: 438.78624 | S26: 546.49 | T26: =+((P26*P33)+(R33*R26))/T33 -> 511.61911 | U26: =+((Q26*Q33)+(S33*S26))/(U33) -> 584.87504 | V26: 435.69233 | W26: 982.33 | X26: =+((N26*N33)+(R26*R33)+(V26*V33))/X33 -> 437.69339 | Y26: =+((O26*O33)+(S26*S33)+(W26*W33))/Y33 -> 641.82115 | Z26: =+((T26*T33)+(V33*V26))/Z33 -> 496.41267 | AA26: =+((U26*U33)+(W33*W26))/(AA33) -> 625.02361 | AB26: 671.3234 | AC26: 889.91 | AD26: =+((Z26*Z33)+(AB33*AB26))/AD33 -> 513.08005 | AE26: =+((AA26*AA33)+(AC33*AC26))/(AE33) -> 653.27 | AF26: 465.44628 | AG26: 640.62 | AH26: =+((AD26*AD33)+(AF33*AF26))/AH33 -> 505.8047 | AI26: =+((AE26*AE33)+(AG33*AG26))/(AI33) -> 651.61301 | AJ26: 455.16755 | AK26: 557.12 | AL26: =+((AB26*AB33)+(AF26*AF33)+(AJ26*AJ33))/AL33 -> 503.47905 | AM26: =+((AC26*AC33)+(AG26*AG33)+(AK26*AK33))/AM33 -> 666.69357 | AN26: =+((AH26*AH33)+(AJ33*AJ26))/AN33 -> 498.81062 | AO26: =+((AI26*AI33)+(AK33*AK26))/(AO33) -> 638.7478 | AP26: 462.06252 | AQ26: 476.02 | AR26: =+((AN26*AN33)+(AP33*AP26))/AR33 -> 494.41383 | AS26: =+((AO26*AO33)+(AQ33*AQ26))/(AS33) -> 615.91717 | AT26: 457 | AU26: =+'POWER DISTRIBUTION'!AZ17/'Maj Prod Summ'!AU18 -> 469.32466 | AV26: =+((AR26*AR33)+(AT33*AT26))/AV33 -> 490.68829 | AW26: =+((AS26*AS33)+(AU33*AU26))/(AW33) -> 598.84781 | AX26: 461 | AY26: =+'POWER DISTRIBUTION'!BD17/'Maj Prod Summ'!AY18 -> 444.39841 | AZ26: =+((AP26*AP33)+(AT26*AT33)+(AX26*AX33))/AZ33 -> 460.10544 | BA26: =+((AQ26*AQ33)+(AU26*AU33)+(AY26*AY33))/BA33 -> 462.46143 | BB26: =+((AL26*AL33)+(AZ26*AZ33))/BB33 -> 480.00573 | BC26: =+((AM26*AM33)+(BA26*BA33))/BC33 -> 543.8379 | BD26: =+((AV26*AV33)+(AX33*AX26))/BD33 -> 487.74658 | BE26: =+((AW26*AW33)+(AY33*AY26))/(BE33) -> 580.20286 | BF26: 448.29125 | BG26: 538.52024 | BH26: 565.51994
B27: Overall Sp Water Consumption | C27: M³/TCS | D27: 4.3 | E27: 5.83 | F27: 4.3 | G27: 5.81 | H27: =+((D27*D33)+(F27*F33))/H33 -> 4.3 | I27: =+((E27*E33)+(G27*G33))/I33 -> 5.8198099 | J27: 4.3 | K27: 5.23 | L27: =+((H27*H33)+(J27*J33))/L33 -> 4.3 | M27: =+((I27*I33)+(K27*K33))/M33 -> 5.608296 | N27: 4.3 | O27: 5.32 | P27: =+((L27*L33)+(N27*N33))/P33 -> 4.3 | Q27: =+((M27*M33)+(O27*O33))/Q33 -> 5.5271722 | R27: 4.3 | S27: 4.8 | T27: =+((P27*P33)+(R27*R33))/T33 -> 4.3 | U27: =+((Q27*Q33)+(S27*S33))/U33 -> 5.3590322 | V27: 4.3 | W27: 7.49 | X27: =+((N27*N33)+(R27*R33)+(V27*V33))/X33 -> 4.3 | Y27: =+((O27*O33)+(S27*S33)+(W27*W33))/Y33 -> 5.5407376 | Z27: =+((T27*T33)+(V27*V33))/Z33 -> 4.3 | AA27: =+((U27*U33)+(W27*W33))/AA33 -> 5.5742901 | AB27: 4.3 | AC27: 7.72 | AD27: =+((Z27*Z33)+(AB27*AB33))/AD33 -> 4.3 | AE27: =+((AA27*AA33)+(AC27*AC33))/AE33 -> 5.8030997 | AF27: 4.3 | AG27: 5.43 | AH27: =+((AD27*AD33)+(AF27*AF33))/AH33 -> 4.3 | AI27: =+((AE27*AE33)+(AG27*AG33))/AI33 -> 5.7542283 | AJ27: 4.3 | AK27: 4.84 | AL27: =+((AB27*AB33)+(AF27*AF33)+(AJ27*AJ33))/AL33 -> 4.3 | AM27: =+((AC27*AC33)+(AG27*AG33)+(AK27*AK33))/AM33 -> 5.7426989 | AN27: =+((AH27*AH33)+(AJ27*AJ33))/AN33 -> 4.3 | AO27: =+((AI27*AI33)+(AK27*AK33))/AO33 -> 5.6297563 | AP27: 4.3 | AQ27: 3.9 | AR27: =+((AN27*AN33)+(AP27*AP33))/AR33 -> 4.3 | AS27: =+((AO27*AO33)+(AQ27*AQ33))/AS33 -> 5.3870723 | AT27: 4.3 | AU27: 3.97 | AV27: =+((AR27*AR33)+(AT27*AT33))/AV33 -> 4.3 | AW27: =+((AS27*AS33)+(AU27*AU33))/AW33 -> 5.2220672 | AX27: 4.3 | AY27: 3.72 | AZ27: =+((AP27*AP33)+(AT27*AT33)+(AX27*AX33))/AZ33 -> 4.3 | BA27: =+((AQ27*AQ33)+(AU27*AU33)+(AY27*AY33))/BA33 -> 3.8561504 | BB27: =+((AL27*AL33)+(AZ27*AZ33))/BB33 -> 4.3 | BC27: =+((AM27*AM33)+(BA27*BA33))/BC33 -> 4.6078473 | BD27: =+((AV27*AV33)+(AX27*AX33))/BD33 -> 4.3 | BE27: =+((AW27*AW33)+(AY27*AY33))/BE33 -> 5.0407394 | BF27: 4.6 | BG27: 5.0056729 | BH27: 5.0192042
B28: Sp. CO2 emission | C28: T/TCS | D28: 2.45 | E28: 2.82 | F28: 2.45 | G28: 2.56 | H28: =+((D28*D33)+(F28*F33))/H33 -> 2.45 | I28: =+((E28*E33)+(G28*G33))/I33 -> 2.6875287 | J28: 2.45 | K28: 2.5 | L28: =+((H28*H33)+(J28*J33))/L33 -> 2.45 | M28: =+((I28*I33)+(K28*K33))/M33 -> 2.6202783 | N28: 2.45 | O28: 2.66 | P28: =+((L28*L33)+(N28*N33))/P33 -> 2.45 | Q28: =+((M28*M33)+(O28*O33))/Q33 -> 2.6314556 | R28: 2.45 | S28: 2.7 | T28: =+((P28*P33)+(R28*R33))/T33 -> 2.45 | U28: =+((Q28*Q33)+(S28*S33))/U33 -> 2.6473048 | V28: 2.45 | W28: 3.47 | X28: =+((N28*N33)+(R28*R33)+(V28*V33))/X33 -> 2.45 | Y28: =+((O28*O33)+(S28*S33)+(W28*W33))/Y33 -> 2.8390704 | Z28: =+((T28*T33)+(V28*V33))/Z33 -> 2.45 | AA28: =+((U28*U33)+(W28*W33))/AA33 -> 2.7304086 | AB28: 2.45 | AC28: 3.62 | AD28: =+((Z28*Z33)+(AB28*AB33))/AD33 -> 2.45 | AE28: =+((AA28*AA33)+(AC28*AC33))/AE33 -> 2.825271 | AF28: 2.45 | AG28: 2.58 | AH28: =+((AD28*AD33)+(AF28*AF33))/AH33 -> 2.45 | AI28: =+((AE28*AE33)+(AG28*AG33))/AI33 -> 2.7931435 | AJ28: 2.45 | AK28: 2.39 | AL28: =+((AB28*AB33)+(AF28*AF33)+(AJ28*AJ33))/AL33 -> 2.45 | AM28: =+((AC28*AC33)+(AG28*AG33)+(AK28*AK33))/AM33 -> 2.754234 | AN28: =+((AH28*AH33)+(AJ28*AJ33))/AN33 -> 2.45 | AO28: =+((AI28*AI33)+(AK28*AK33))/AO33 -> 2.7382556 | AP28: 2.45 | AQ28: 2.43 | AR28: =+((AN28*AN33)+(AP28*AP33))/AR33 -> 2.45 | AS28: =+((AO28*AO33)+(AQ28*AQ33))/AS33 -> 2.6950075 | AT28: 2.45 | AU28: 2.38 | AV28: =+((AR28*AR33)+(AT28*AT33))/AV33 -> 2.45 | AW28: =+((AS28*AS33)+(AU28*AU33))/AW33 -> 2.6583278 | AX28: 2.45 | AY28: 2.35 | AZ28: =+((AP28*AP33)+(AT28*AT33)+(AX28*AX33))/AZ33 -> 2.45 | BA28: =+((AQ28*AQ33)+(AU28*AU33)+(AY28*AY33))/BA33 -> 2.3855054 | BB28: =+((AL28*AL33)+(AZ28*AZ33))/BB33 -> 2.45 | BC28: =+((AM28*AM33)+(BA28*BA33))/BC33 -> 2.5324256 | BD28: =+((AV28*AV33)+(AX28*AX33))/BD33 -> 2.45 | BE28: =+((AW28*AW33)+(AY28*AY33))/BE33 -> 2.6211068 | BF28: 2.456658 | BG28: 2.4355942 | BH28: 2.609953
B29: Sp. PM emissions | C29: kg/TCS | D29: 0.55 | E29: 0.76 | F29: 0.55 | G29: 0.66 | H29: =+((D29*D33)+(F29*F33))/H33 -> 0.55 | I29: =+((E29*E33)+(G29*G33))/I33 -> 0.70904949 | J29: 0.55 | K29: 0.63 | L29: =+((H29*H33)+(J29*J33))/L33 -> 0.55 | M29: =+((I29*I33)+(K29*K33))/M33 -> 0.68070126 | N29: 0.55 | O29: 0.6 | P29: =+((L29*L33)+(N29*N33))/P33 -> 0.55 | Q29: =+((M29*M33)+(O29*O33))/Q33 -> 0.65799268 | R29: 0.55 | S29: 0.58 | T29: =+((P29*P33)+(R29*R33))/T33 -> 0.55 | U29: =+((Q29*Q33)+(S29*S33))/U33 -> 0.63995887 | V29: 0.55 | W29: 0.94 | X29: =+((N29*N33)+(R29*R33)+(V29*V33))/X33 -> 0.55 | Y29: =+((O29*O33)+(S29*S33)+(W29*W33))/Y33 -> 0.65997239 | Z29: =+((T29*T33)+(V29*V33))/Z33 -> 0.55 | AA29: =+((U29*U33)+(W29*W33))/AA33 -> 0.67026726 | AB29: 0.55 | AC29: 0.9 | AD29: =+((Z29*Z33)+(AB29*AB33))/AD33 -> 0.55 | AE29: =+((AA29*AA33)+(AC29*AC33))/AE33 -> 0.69476501 | AF29: 0.55 | AG29: 0.63 | AH29: =+((AD29*AD33)+(AF29*AF33))/AH33 -> 0.55 | AI29: =+((AE29*AE33)+(AG29*AG33))/AI33 -> 0.6862816 | AJ29: 0.55 | AK29: 0.61 | AL29: =+((AB29*AB33)+(AF29*AF33)+(AJ29*AJ33))/AL33 -> 0.55 | AM29: =+((AC29*AC33)+(AG29*AG33)+(AK29*AK33))/AM33 -> 0.6873571 | AN29: =+((AH29*AH33)+(AJ29*AJ33))/AN33 -> 0.55 | AO29: =+((AI29*AI33)+(AK29*AK33))/AO33 -> 0.67589588 | AP29: 0.55 | AQ29: 0.52 | AR29: =+((AN29*AN33)+(AP29*AP33))/AR33 -> 0.55 | AS29: =+((AO29*AO33)+(AQ29*AQ33))/AS33 -> 0.65402376 | AT29: 0.55 | AU29: 0.5 | AV29: =+((AR29*AR33)+(AT29*AT33))/AV33 -> 0.55 | AW29: =+((AS29*AS33)+(AU29*AU33))/AW33 -> 0.6360891 | AX29: 0.55 | AY29: 0.53 | AZ29: =+((AP29*AP33)+(AT29*AT33)+(AX29*AX33))/AZ33 -> 0.55 | BA29: =+((AQ29*AQ33)+(AU29*AU33)+(AY29*AY33))/BA33 -> 0.51746916 | BB29: =+((AL29*AL33)+(AZ29*AZ33))/BB33 -> 0.55 | BC29: =+((AS29*AS33)+(AW29*AW33)+(BA29*BA33))/BC33 -> 2.2447281 | BD29: =+((AV29*AV33)+(AX29*AX33))/BD33 -> 0.55 | BE29: =+((AW29*AW33)+(AY29*AY33))/BE33 -> 0.62328215 | BF29: 0.551124 | BG29: 0.57147495 | BH29: 0.55061804
B30: Labour Productivity | C30: TCS/Man/Year | D30: =+D39 -> 368.28008 | E30: =+E39 -> 368.28008 | F30: =+F39 -> 371.45858 | G30: =+G39 -> 373.10489 | H30: =+H39 -> 369.87854 | I30: =+I39 -> 370.69457 | J30: =+J39 -> 465.43596 | K30: =+K39 -> 426.59697 | ... BE30: =+BE39 -> 459.2495 | BF30: 562.64319 | BG30: 490.34382 | BH30: 421.02863
