Workbook
Name _1: #REF!
Name _1: #REF!
Name _1: #REF!
Name _1: #REF!
Name _1: #REF!
Name _1: #REF!
Name _1: #REF!
Name _1: #REF!
Name _1: #REF!
Name _2: #REF!
Name _2: #REF!
Name _2: #REF!
Name _2: #REF!
Name _2: #REF!
Name _2: #REF!
Name _2: #REF!
Name _2: #REF!
Name _2: #REF!
Name _3: #REF!
Name _3: #REF!
Name _3: #REF!
Name _3: #REF!
Name _3: #REF!
Name _3: #REF!
Name _3: #REF!
Name _3: #REF!
Name _4: #REF!
Name _4: #REF!
Name a: #REF!
Name a: #REF!
Name a: #REF!
Name a: #REF!
Name AA: #REF!
Name AA: #REF!
Name AA: #REF!
Name AB: #REF!
Name AB: #REF!
Name AB: #REF!
Name AC: #REF!
Name AC: #REF!
Name AD: #REF!
Name AD: #REF!
Name AE: #REF!
Name AE: #REF!
Name AF: #REF!
Name AF: #REF!
Name AG: #REF!
Name AG: #REF!
Name AH: #REF!
Name AH: #REF!
Name AI: #REF!
Name AI: #REF!
Name AK: #REF!
Name AK: #REF!
Name AL: #REF!
Name AL: #REF!
Name AM: #REF!
Name AM: #REF!
Name AN: #REF!
Name AN: #REF!

Sheet Maj Production Summ
B1: MAJOR PRODUCTION SUMMARY | D1: 340 | E1: 26 | F1: =F2-'B-FCE'!F3 -> 29.538194 | G1: 20 | H1: =H2-'B-FCE'!H3-3 -> 14.055556 | I1: =E1+G1 -> 46 | J1: =F1+H1 -> 43.59375 | K1: 29 | L1: =L2-'B-FCE'!L3 -> 29.61125 | M1: =+E1+G1+K1 -> 75 | N1: =+F1+H1+L1 -> 73.205 | O1: 30 | P1: =P2-'B-FCE'!P3 -> 31 | Q1: =+M1+O1 -> 105 | R1: =+N1+P1 -> 104.205 | S1: 30 | T1: =T2-'B-FCE'!T3 -> 30.024306 | U1: =+Q1+S1 -> 135 | V1: =+R1+T1 -> 134.22931 | W1: 17.016867 | X1: =X2-'B-FCE'!X3 -> 29.67375 | Y1: =+O1+S1+W1 -> 77.016867 | Z1: =+P1+T1+X1 -> 90.698056 | AA1: =+U1+W1 -> 152.01687 | AB1: =+V1+X1 -> 163.90306 | AC1: 30 | AD1: =AD2-'B-FCE'!AD3-2 -> 24.930556 | AE1: =AA1+AC1 -> 182.01687 | AF1: =AB1+AD1 -> 188.83361 | AG1: 29 | AH1: =AH2-'B-FCE'!AH3 -> 29.1075 | AI1: =AE1+AG1 -> 211.01687 | AJ1: =AF1+AH1 -> 217.94111 | AK1: 30 | AL1: =31-'B-FCE'!AL3 -> 30.697917 | AM1: =+AC1+AG1+AK1 -> 89 | AN1: =+AD1+AH1+AL1 -> 84.735972 | AO1: =AI1+AK1 -> 241.01687 | AP1: =AJ1+AL1 -> 248.63903 | AQ1: 30 | AR1: =31-'B-FCE'!AR3 -> 30.413194 | AS1: =AO1+AQ1 -> 271.01687 | AT1: =AP1+AR1 -> 279.05222 | AU1: 27 | AV1: =28-'B-FCE'!AV3 -> 27.57625 | AW1: =AS1+AU1 -> 298.01687 | AX1: =AT1+AV1 -> 306.62847 | AY1: 30 | AZ1: =31-'B-FCE'!AZ3 -> 29.972222 | BA1: =+AQ1+AU1+AY1 -> 87 | BB1: =+AR1+AV1+AZ1 -> 87.961667 | BC1: =+AM1+BA1 -> 176 | BD1: =+AN1+BB1 -> 172.69764 | BE1: =AW1+AY1 -> 328.01687 | BF1: =AX1+AZ1 -> 336.60069
A2: 1000 | D2: 365 | E2: 30 | F2: 30 | G2: 31 | H2: 31 | I2: =+E2+G2 -> 61 | J2: =+F2+H2 -> 61 | K2: 30 | L2: 30 | M2: =+I2+K2 -> 91 | N2: =+J2+L2 -> 91 | O2: 31 | P2: 31 | Q2: =+M2+O2 -> 122 | R2: =+N2+P2 -> 122 | S2: 31 | T2: 31 | U2: =+Q2+S2 -> 153 | V2: =+R2+T2 -> 153 | W2: 30 | X2: 30 | Y2: =+O2+S2+W2 -> 92 | Z2: =+P2+T2+X2 -> 92 | AA2: =+U2+W2 -> 183 | AB2: =+V2+X2 -> 183 | AC2: 31 | AD2: 31 | AE2: =AA2+AC2 -> 214 | AF2: =AB2+AD2 -> 214 | AG2: 30 | AH2: 30 | AI2: =AE2+AG2 -> 244 | AJ2: =AF2+AH2 -> 244 | AK2: 31 | AL2: 31 | AM2: =+AC2+AG2+AK2 -> 92 | AN2: =+AD2+AH2+AL2 -> 92 | AO2: =AI2+AK2 -> 275 | AP2: =AJ2+AL2 -> 275 | AQ2: 31 | AR2: 31 | AS2: =AO2+AQ2 -> 306 | AT2: =AP2+AR2 -> 306 | AU2: 28 | AV2: 28 | AW2: =AS2+AU2 -> 334 | AX2: =AT2+AV2 -> 334 | AY2: 31 | AZ2: 31 | BA2: =+AQ2+AU2+AY2 -> 90 | BB2: =+AR2+AV2+AZ2 -> 90 | BC2: =+AM2+BA2 -> 182 | BD2: =+AN2+BB2 -> 182 | BE2: =AW2+AY2 -> 365 | BF2: =AX2+AZ2 -> 365 | BQ2: 365 | BR2: 365 | BS2: 366 | BT2: 366
A3: 1000 | B3: ITEM | C3: Unit | D3: 2026-27 ABP | E3: Apr'26 | G3: May'26 | I3: 2M | K3: Jun'25 | M3: QTR-1 | O3: Jul'25 | Q3: 4M | S3: Aug'25 | U3: 5M | W3: Sep'25 | Y3: QTR 2 | AA3: H1 | AC3: Oct'25 | AE3: 7M | AG3: Nov'25 | AI3: 8M | AK3: Dec'25 | AM3: QTR 3 | AO3: 9M | AQ3: Jan'26 | AS3: 10M | AU3: Feb'26 | AW3: 11M | AY3: Mar'26 | BA3: QTR 4 | BC3: H2 | BE3: 2026-27 | BH3: 2025-26 | BJ3: 2024-25 | BL3: 2023-24 | BN3: 2022-23 | BO3: 2021-22 | BQ3: 2020-21 | BS3: 2019-20
E4: ABP | F4: ACT | G4: ABP | H4: ACT | I4: ABP | J4: ACT | K4: ABP | L4: ACT | M4: ABP | N4: ACT | O4: ABP | P4: ACT | Q4: ABP | R4: ACT | S4: ABP | T4: ACT | U4: ABP | V4: ACT | W4: ABP | X4: ACT | Y4: ABP | Z4: ACT | AA4: ABP | AB4: ACT | AC4: ABP | AD4: ACT | AE4: ABP | AF4: ACT | AG4: ABP | AH4: ACT | AI4: ABP | AJ4: ACT | AK4: ABP | AL4: ACT | AM4: ABP | AN4: ACT | AO4: ABP | AP4: ACT | AQ4: ABP | AR4: ACT | AS4: ABP | AT4: ACT | AU4: ABP | AV4: ACT | AW4: ABP | AX4: ACT | AY4: ABP | AZ4: ACT | BA4: ABP | BB4: ACT | BC4: ABP | BD4: ACT | BE4: ABP | BF4: ACT | BH4: ABP | BI4: ACT | BJ4: ABP | BK4: ACT | BL4: ABP | BM4: ACT | BN4: ACT | BO4: ABP | BP4: ACT | BQ4: ABP | BR4: ACT | BS4: ABP | BT4: ACT
B5: COKE OVENS PUSHING
B6: (COB#10) | C6: Nos/ day | D6: 96.509589 | E6: 98 | F6: =+F9/F2 -> 98 | G6: 98 | H6: =+H9/H2 -> 97.064516 | I6: =+((E6*$E$2)+(G6*$G$2))/$I$2 -> 98 | J6: =+((F6*$F$2)+(H6*$H$2))/$J$2 -> 97.52459 | K6: 94 | L6: =+L9/L2 -> 96.066667 | M6: =+((E6*$E$2)+(G6*$G$2)+(K6*$K$2))/$M$2 -> 96.681319 | N6: =+((F6*$F$2)+(H6*$H$2)+(L6*$L$2))/$N$2 -> 97.043956 | O6: 94 | P6: =+P9/P2 -> 95.419355 | Q6: =+((M6*M$2)+(O6*O$2))/Q$2 -> 96 | R6: =+((N6*N$2)+(P6*P$2))/R$2 -> 96.631148 | S6: 94 | T6: =+T9/T2 -> 98 | U6: =+((Q6*Q$2)+(S6*S$2))/U$2 -> 95.594771 | V6: =+((R6*R$2)+(T6*T$2))/V$2 -> 96.908497 | W6: 92.1 | X6: =+X9/X2 -> 98 | Y6: =+((O$6*O$2)+(S$6*S$2)+(W$6*W$2))/Y$2 -> 93.380435 | Z6: =+((P$6*P$2)+(T$6*T$2)+(X$6*X$2))/Z$2 -> 97.130435 | AA6: =+((M6*M$2)+(Y6*Y$2))/AA$2 -> 95.021858 | AB6: =+((N6*N$2)+(Z6*Z$2))/AB$2 -> 97.087432 | AC6: 94 | AD6: =+AD9/AD2 -> 96.548387 | AE6: =+((AA6*$AA$2)+(AC6*$AC$2))/$AE$2 -> 94.873832 | AF6: =+((AB6*$AB$2)+(AD6*$AD$2))/$AF$2 -> 97.009346 | AG6: 94 | AH6: =+AH9/AH2 -> 94.233333 | AI6: =+((AE6*$AE$2)+(AG6*$AG$2))/$AI$2 -> 94.766393 | AJ6: =+((AF6*$AF$2)+(AH6*$AH$2))/$AJ$2 -> 96.668033 | AK6: 94 | AL6: =+AL9/AL2 -> 94.096774 | AM6: =+((AC$6*AC$2)+(AG$6*AG$2)+(AK$6*AK$2))/AM$2 -> 94 | AN6: =+((AD$6*AD$2)+(AH$6*AH$2)+(AL$6*AL$2))/AN$2 -> 94.967391 | AO6: =+((AK6*$AK$2)+(AI6*$AI$2))/$AO$2 -> 94.68 | AP6: =+((AL6*$AL$2)+(AJ6*$AJ$2))/$AP$2 -> 96.378182 | AQ6: 94 | AR6: =+AR9/AR2 -> 94.83871 | AS6: =+((AO6*$AO$2)+(AQ6*$AQ$2))/$AS$2 -> 94.611111 | AT6: =+((AP6*$AP$2)+(AR6*$AR$2))/$AT$2 -> 96.222222 | AU6: 94 | AV6: =+AV9/AV2 -> 94.428571 | AW6: =+((AS6*$AS$2)+(AU6*$AU$2))/$AW$2 -> 94.55988 | AX6: =+((AT6*$AT$2)+(AV6*$AV$2))/$AX$2 -> 96.071856 | AY6: 94 | AZ6: =+AZ9/AZ2 -> 98 | BA6: =+((AQ$6*AQ$2)+(AU$6*AU$2)+(AY$6*AY$2))/BA$2 -> 94 | BB6: =+((AR$6*AR$2)+(AV$6*AV$2)+(AZ$6*AZ$2))/BB$2 -> 95.8 | BC6: =+((AM6*AM$2)+(BA6*BA$2))/BC$2 -> 94 | BD6: =+((AN6*AN$2)+(BB6*BB$2))/BD$2 -> 95.379121 | BE6: =+((AW6*$AW$2)+(AY6*$AY$2))/$BE$2 -> 94.512329 | BF6: =+((AZ6*$AZ$2)+(AX6*$AX$2))/$BF$2 -> 96.235616 | BH6: 94.512329 | BI6: 96.216438 | BJ6: 96.420548 | BK6: 97.709589 | BL6: 99 | BM6: 98.976067 | BN6: 98.783562 | BO6: 99 | BP6: 97.824658 | BQ6: 95.547945 | BR6: 95.342466 | BS6: 97 | BT6: 97.10959
B7: (COB#11) | C7: Nos/ day | D7: 97.717616 | E7: 96.6 | F7: =+F10/F2 -> 98.433333 | G7: 96.03 | H7: =+H10/H2 -> 93.677419 | I7: =+((E7*$E$2)+(G7*$G$2))/$I$2 -> 96.310328 | J7: =+((F7*$F$2)+(H7*$H$2))/$J$2 -> 96.016393 | K7: 98 | L7: =+L10/L2 -> 98.466667 | M7: =+((E7*$E$2)+(G7*$G$2)+(K7*$K$2))/$M$2 -> 96.867363 | N7: =+((F7*$F$2)+(H7*$H$2)+(L7*$L$2))/$N$2 -> 96.824176 | O7: 98 | P7: =+P10/P2 -> 99 | Q7: =+((M7*M$2)+(O7*O$2))/Q$2 -> 97.155164 | R7: =+((N7*N$2)+(P7*P$2))/R$2 -> 97.377049 | S7: 98 | T7: =+T10/T2 -> 98.516129 | U7: =+((Q7*Q$2)+(S7*S$2))/U$2 -> 97.32634 | V7: =+((R7*R$2)+(T7*T$2))/V$2 -> 97.607843 | W7: 93.5 | X7: =+X10/X2 -> 98.766667 | Y7: =((O7*O2)+(S7*S2)+(W7*W2))/Y2 -> 96.532609 | Z7: =+((P$7*P$2)+(T$7*T$2)+(X$7*X$2))/Z$2 -> 98.76087 | AA7: =+((M7*M$2)+(Y7*Y$2))/AA$2 -> 96.699071 | AB7: =+((N7*N$2)+(Z7*Z$2))/AB$2 -> 97.797814 | AC7: 98 | AD7: =+AD10/AD2 -> 97.193548 | AE7: =+((AA7*$AA$2)+(AC7*$AC$2))/$AE$2 -> 96.887523 | AF7: =+((AB7*$AB$2)+(AD7*$AD$2))/$AF$2 -> 97.71028 | AG7: 98 | AH7: =+AH10/AH2 -> 98.666667 | AI7: =+((AE7*$AE$2)+(AG7*$AG$2))/$AI$2 -> 97.024303 | AJ7: =+((AF7*$AF$2)+(AH7*$AH$2))/$AJ$2 -> 97.827869 | AK7: 98 | AL7: =+AL10/AL2 -> 98.741935 | AM7: =+((AC$7*AC$2)+(AG$7*AG$2)+(AK$7*AK$2))/AM$2 -> 98 | AN7: =+((AD$7*AD$2)+(AH$7*AH$2)+(AL$7*AL$2))/AN$2 -> 98.195652 | AO7: =+((AK7*$AK$2)+(AI7*$AI$2))/$AO$2 -> 97.134291 | AP7: =+((AL7*$AL$2)+(AJ7*$AJ$2))/$AP$2 -> 97.930909 | AQ7: 98 | AR7: =+AR10/AR2 -> 97.870968 | AS7: =+((AO7*$AO$2)+(AQ7*$AQ$2))/$AS$2 -> 97.221993 | AT7: =+((AP7*$AP$2)+(AR7*$AR$2))/$AT$2 -> 97.924837 | AU7: 98 | AV7: =+AV10/AV2 -> 98.035714 | AW7: =+((AS7*$AS$2)+(AU7*$AU$2))/$AW$2 -> 97.287216 | AX7: =+((AT7*$AT$2)+(AV7*$AV$2))/$AX$2 -> 97.934132 | AY7: 98 | AZ7: =+AZ10/AZ2 -> 98.677419 | BA7: =+((AQ$7*AQ$2)+(AU$7*AU$2)+(AY$7*AY$2))/BA$2 -> 98 | BB7: =+((AR$7*AR$2)+(AV$7*AV$2)+(AZ$7*AZ$2))/BB$2 -> 98.2 | BC7: =+((AM7*AM$2)+(BA7*BA$2))/BC$2 -> 98 | BD7: =+((AN7*AN$2)+(BB7*BB$2))/BD$2 -> 98.197802 | BE7: =+((AW7*$AW$2)+(AY7*$AY$2))/$BE$2 -> 97.347753 | BF7: =+((AZ7*$AZ$2)+(AX7*$AX$2))/$BF$2 -> 97.99726 | BH7: 97.630137 | BI7: 98.210959 | BJ7: 98.167671 | BK7: 97.991781 | BL7: 98.000061 | BM7: 96.670251 | BN7: 92.210959 | BO7: 99 | BP7: 96.816438 | BQ7: 94.2 | BR7: 90.778082 | BS7: 97 | BT7: 95.710246
B8: Overall Equiv. Ovens Pushed/ Day | C8: Nos/ day | D8: =+D6+(D7*(31.55/17.2)) -> 275.75324 | E8: =+E6+(E7*(31.55/17.2)) -> 275.1936 | F8: =+F6+(F7*(31.55/17.2)) -> 278.55649 | G8: =+G6+(G7*(31.55/17.2)) -> 274.14805 | H8: =+H6+(H7*(31.55/17.2)) -> 268.89722 | I8: =+I6+(I7*(31.55/17.2)) -> 274.66226 | J8: =+J6+(J7*(31.55/17.2)) -> 273.64768 | K8: =+K6+(K7*(31.55/17.2)) -> 273.76163 | ... X8: =+X6+(X7*(31.55/17.2)) -> 279.16793 | Y8: =Y6+(Y7*31.55/17.2) -> 270.45042 | Z8: =Z6+(Z7*31.55/17.2) -> 278.28773 | AA8: =AA6+(AA7*31.55/17.2) -> 272.39719 | AB8: =AB6+(AB7*31.55/17.2) -> 276.47819 | AC8: =+AC6+(AC7*(31.55/17.2)) -> 273.76163 | AD8: =+AD6+(AD7*(31.55/17.2)) -> 274.83074 | AE8: =+AE6+(AE7*(31.55/17.2)) -> 272.59484 | AF8: =+AF6+(AF7*(31.55/17.2)) -> 276.23954 | AG8: =+AG6+(AG7*(31.55/17.2)) -> 273.76163 | AH8: =+AH6+(AH7*(31.55/17.2)) -> 275.21783 | AI8: =+AI6+(AI7*(31.55/17.2)) -> 272.7383 | AJ8: =+AJ6+(AJ7*(31.55/17.2)) -> 276.11392 | ... AL8: =+AL6+(AL7*(31.55/17.2)) -> 275.21934 | AM8: =AM6+(AM7*31.55/17.2) -> 273.76163 | AN8: =AN6+(AN7*31.55/17.2) -> 275.0879 | AO8: =+AO6+(AO7*(31.55/17.2)) -> 272.85366 | AP8: =+AP6+(AP7*(31.55/17.2)) -> 276.01308 | AQ8: =+AQ6+(AQ7*(31.55/17.2)) -> 273.76163 | AR8: =+AR6+(AR7*(31.55/17.2)) -> 274.36365 | AS8: =+AS6+(AS7*(31.55/17.2)) -> 272.94564 | AT8: =+AT6+(AT7*(31.55/17.2)) -> 275.84598 | AU8: =+AU6+(AU7*(31.55/17.2)) -> 273.76163 | AV8: =+AV6+(AV7*(31.55/17.2)) -> 274.25571 | ... AZ8: =+AZ6+(AZ7*(31.55/17.2)) -> 279.00422 | BA8: =BA6+(BA7*31.55/17.2) -> 273.76163 | BB8: =BB6+(BB7*31.55/17.2) -> 275.92849 | BC8: =BC6+(BC7*31.55/17.2) -> 273.76163 | BD8: =BD6+(BD7*31.55/17.2) -> 275.50358 | BE8: =+BE6+(BE7*(31.55/17.2)) -> 273.07754 | BF8: =+BF6+(BF7*(31.55/17.2)) -> 275.99222 | BH8: 273.59552 | BI8: 276.36503 | BJ8: 276.48974 | BK8: 277.45614 | BL8: 278.76174 | BM8: 276.29853 | BN8: 267.92634 | BO8: 280.59593 | BP8: 275.41528 | BQ8: 268.33922 | BR8: 261.85691 | BS8: 274.92733 | BT8: 272.67112
B9: (COB#10) | C9: Nos | D9: =+D6*D2 -> 35226 | E9: =+E6*E2 -> 2940 | F9: 2940 | G9: =+G6*G2 -> 3038 | H9: 3009 | I9: =+I6*I2 -> 5978 | J9: =+F9+H9 -> 5949 | K9: =+K6*K2 -> 2820 | L9: 2882 | M9: =+E9+G9+K9 -> 8798 | N9: =+F9+H9+L9 -> 8831 | O9: =+O6*O2 -> 2914 | P9: 2958 | Q9: =+M9+O9 -> 11712 | R9: =+N9+P9 -> 11789 | S9: =+S6*S2 -> 2914 | T9: 3038 | U9: =+Q9+S9 -> 14626 | V9: =+R9+T9 -> 14827 | W9: =+W6*W2 -> 2763 | X9: 2940 | Y9: =+O9+S9+W9 -> 8591 | Z9: =+P9+T9+X9 -> 8936 | AA9: =M9+Y9 -> 17389 | AB9: =+N9+Z9 -> 17767 | AC9: =+AC6*AC2 -> 2914 | AD9: 2993 | AE9: =+AE6*AE2 -> 20303 | AF9: =+AB9+AD9 -> 20760 | AG9: =+AG6*AG2 -> 2820 | AH9: 2827 | AI9: =+AI6*AI2 -> 23123 | AJ9: =+AF9+AH9 -> 23587 | AK9: =+AK6*AK2 -> 2914 | AL9: 2917 | AM9: =+AC9+AG9+AK9 -> 8648 | AN9: =+AD9+AH9+AL9 -> 8737 | AO9: =AI9+AK9 -> 26037 | AP9: =AJ9+AL9 -> 26504 | AQ9: =+AQ6*AQ2 -> 2914 | AR9: 2940 | AS9: =+AS6*AS2 -> 28951 | AT9: =+AP9+AR9 -> 29444 | AU9: =+AU6*AU2 -> 2632 | AV9: 2644 | AW9: =+AW6*AW2 -> 31583 | AX9: =+AT9+AV9 -> 32088 | AY9: =+AY6*AY2 -> 2914 | AZ9: 3038 | BA9: =+AQ9+AU9+AY9 -> 8460 | BB9: =+AR9+AV9+AZ9 -> 8622 | BC9: =AM9+BA9 -> 17108 | BD9: =AN9+BB9 -> 17359 | BE9: =AW9+AY9 -> 34497 | BF9: =AX9+AZ9 -> 35126 | BH9: 34497 | BI9: 35119 | BJ9: 35193.5 | BK9: 35664 | BL9: 36234 | BM9: 36225 | BN9: 36056 | BO9: 36135 | BP9: 35706 | BQ9: 34875 | BR9: 34800 | BS9: 35502 | BT9: 35543
B10: (COB#11) | C10: Nos | D10: =+D7*D2 -> 35666.93 | E10: =+E7*E2 -> 2898 | F10: 2953 | G10: =+G7*G2 -> 2976.93 | H10: 2904 | I10: =+I7*I2 -> 5874.93 | J10: =+F10+H10 -> 5857 | K10: =+K7*K2 -> 2940 | L10: 2954 | M10: =+E10+G10+K10 -> 8814.93 | N10: =+F10+H10+L10 -> 8811 | O10: =+O7*O2 -> 3038 | P10: 3069 | Q10: =+M10+O10 -> 11852.93 | R10: =+N10+P10 -> 11880 | S10: =+S7*S2 -> 3038 | T10: 3054 | U10: =+Q10+S10 -> 14890.93 | V10: =+R10+T10 -> 14934 | W10: =+W7*W2 -> 2805 | X10: 2963 | Y10: =+O10+S10+W10 -> 8881 | Z10: =+P10+T10+X10 -> 9086 | AA10: =+M10+Y10 -> 17695.93 | AB10: =+N10+Z10 -> 17897 | AC10: =+AC7*AC2 -> 3038 | AD10: 3013 | AE10: =+AE7*AE2 -> 20733.93 | AF10: =+AB10+AD10 -> 20910 | AG10: =+AG7*AG2 -> 2940 | AH10: 2960 | AI10: =+AI7*AI2 -> 23673.93 | AJ10: =+AF10+AH10 -> 23870 | AK10: =+AK7*AK2 -> 3038 | AL10: 3061 | AM10: =+AC10+AG10+AK10 -> 9016 | AN10: =+AD10+AH10+AL10 -> 9034 | AO10: =AI10+AK10 -> 26711.93 | AP10: =AJ10+AL10 -> 26931 | AQ10: =+AQ7*AQ2 -> 3038 | AR10: 3034 | AS10: =+AS7*AS2 -> 29749.93 | AT10: =+AP10+AR10 -> 29965 | AU10: =+AU7*AU2 -> 2744 | AV10: 2745 | AW10: =+AW7*AW2 -> 32493.93 | AX10: =+AT10+AV10 -> 32710 | AY10: =+AY7*AY2 -> 3038 | AZ10: 3059 | BA10: =+AQ10+AU10+AY10 -> 8820 | BB10: =+AR10+AV10+AZ10 -> 8838 | BC10: =AM10+BA10 -> 17836 | BD10: =AN10+BB10 -> 17872 | BE10: =AW10+AY10 -> 35531.93 | BF10: =AX10+AZ10 -> 35769 | BH10: 35635 | BI10: 35847 | BJ10: 35831.2 | BK10: 35767 | BL10: 35868.022 | BM10: 35382 | BN10: 33657 | BO10: 36135 | BP10: 35338 | BQ10: 34383 | BR10: 33134 | BS10: 35502 | BT10: 35030
B11: Overall Equiv. Ovens Pushed | C11: Nos | D11: =+D9+(D10*(31.55/17.2)) -> 100649.93 | E11: =+E9+(E10*(31.55/17.2)) -> 8255.8081 | F11: =+F9+(F10*(31.55/17.2)) -> 8356.6948 | G11: =+G9+(G10*(31.55/17.2)) -> 8498.5896 | H11: =+H9+(H10*(31.55/17.2)) -> 8335.814 | I11: =+I9+(I10*(31.55/17.2)) -> 16754.398 | J11: =+J9+(J10*(31.55/17.2)) -> 16692.509 | K11: =+K9+(K10*(31.55/17.2)) -> 8212.8488 | ... X11: =+X9+(X10*(31.55/17.2)) -> 8375.0378 | Y11: =Y9+(Y10*31.55/17.2) -> 24881.439 | Z11: =Z9+(Z10*31.55/17.2) -> 25602.471 | AA11: =AA9+(AA10*31.55/17.2) -> 49848.686 | AB11: =AB9+(AB10*31.55/17.2) -> 50595.509 | AC11: =+AC9+(AC10*(31.55/17.2)) -> 8486.6105 | AD11: =+AD9+(AD10*(31.55/17.2)) -> 8519.7529 | AE11: =+AE9+(AE10*(31.55/17.2)) -> 58335.296 | AF11: =+AF9+(AF10*(31.55/17.2)) -> 59115.262 | AG11: =+AG9+(AG10*(31.55/17.2)) -> 8212.8488 | AH11: =+AH9+(AH10*(31.55/17.2)) -> 8256.5349 | AI11: =+AI9+(AI10*(31.55/17.2)) -> 66548.145 | AJ11: =+AJ9+(AJ10*(31.55/17.2)) -> 67371.797 | ... AL11: =+AL9+(AL10*(31.55/17.2)) -> 8531.7994 | AM11: =AM9+(AM10*31.55/17.2) -> 25186.07 | AN11: =AN9+(AN10*31.55/17.2) -> 25308.087 | AO11: =+AO9+(AO10*(31.55/17.2)) -> 75034.755 | AP11: =+AP9+(AP10*(31.55/17.2)) -> 75903.596 | AQ11: =+AQ9+(AQ10*(31.55/17.2)) -> 8486.6105 | AR11: =+AR9+(AR10*(31.55/17.2)) -> 8505.2733 | AS11: =+AS9+(AS10*(31.55/17.2)) -> 83521.366 | AT11: =+AT9+(AT10*(31.55/17.2)) -> 84408.869 | AU11: =+AU9+(AU10*(31.55/17.2)) -> 7665.3256 | AV11: =+AV9+(AV10*(31.55/17.2)) -> 7679.1599 | ... AZ11: =+AZ9+(AZ10*(31.55/17.2)) -> 8649.1308 | BA11: =BA9+(BA10*31.55/17.2) -> 24638.547 | BB11: =BB9+(BB10*31.55/17.2) -> 24833.564 | BC11: =BC9+(BC10*31.55/17.2) -> 49824.616 | BD11: =BD9+(BD10*31.55/17.2) -> 50141.651 | BE11: =+BE9+(BE10*(31.55/17.2)) -> 99673.302 | BF11: =+BF9+(BF10*(31.55/17.2)) -> 100737.16 | BH11: 99862.363 | BI11: 100873.24 | BJ11: 100918.75 | BK11: 101271.49 | BL11: 102026.8 | BM11: 101126.28 | BN11: 97793.113 | BO11: 102417.51 | BP11: 100526.58 | BQ11: 97943.817 | BR11: 95577.773 | BS11: 100623.4 | BT11: 99798.61
B12: BF COKE
B13: COB#10 | C13: Mt | D13: =+D9*0.7*17.2 -> 424121.04 | E13: =+E9*0.7*17.2 -> 35397.6 | F13: ='COKE OVENS'!F21 -> 35144.76 | G13: =+G9*0.7*17.2 -> 36577.52 | H13: ='COKE OVENS'!H21 -> 35969.586 | I13: =+E13+G13 -> 71975.12 | J13: =+F13+H13 -> 71114.346 | K13: =+K9*0.7*17.2 -> 33952.8 | L13: ='COKE OVENS'!L21 -> 34699.28 | M13: =+E13+G13+K13 -> 105927.92 | N13: =+F13+H13+L13 -> 105813.63 | O13: =+O9*0.7*17.2 -> 35084.56 | P13: ='COKE OVENS'!P21 -> 35614.32 | Q13: =+M13+O13 -> 141012.48 | R13: =+N13+P13 -> 141427.95 | S13: =+S9*0.7*17.2 -> 35084.56 | T13: ='COKE OVENS'!T21 -> 36577.52 | U13: =+Q13+S13 -> 176097.04 | V13: =+R13+T13 -> 178005.47 | W13: =+W9*0.7*17.2 -> 33266.52 | X13: ='COKE OVENS'!X21 -> 35397.6 | Y13: =+O13+S13+W13 -> 103435.64 | Z13: =+P13+T13+X13 -> 107589.44 | AA13: =+M13+Y13 -> 209363.56 | AB13: =+N13+Z13 -> 213403.07 | AC13: =+AC9*0.7*17.2 -> 35084.56 | AD13: ='COKE OVENS'!AD21 -> 35881.281 | AE13: =+AA13+AC13 -> 244448.12 | AF13: =+AB13+AD13 -> 249284.35 | AG13: =+AG9*0.7*17.2 -> 33952.8 | AH13: ='COKE OVENS'!AH21 -> 33793.958 | AI13: =+AE13+AG13 -> 278400.92 | AJ13: =+AF13+AH13 -> 283078.31 | AK13: =+AK9*0.7*17.2 -> 35084.56 | AL13: ='COKE OVENS'!AL21 -> 34869.818 | AM13: =+AC13+AG13+AK13 -> 104121.92 | AN13: =+AD13+AH13+AL13 -> 104545.06 | AO13: =AI13+AK13 -> 313485.48 | AP13: =AJ13+AL13 -> 317948.12 | AQ13: =+AQ9*0.7*17.2 -> 35084.56 | AR13: ='COKE OVENS'!AR21 -> 35144.76 | AS13: =+AO13+AQ13 -> 348570.04 | AT13: =+AP13+AR13 -> 353092.88 | AU13: =+AU9*0.7*17.2 -> 31689.28 | AV13: ='COKE OVENS'!AV21 -> 31606.376 | AW13: =+AS13+AU13 -> 380259.32 | AX13: =+AT13+AV13 -> 384699.26 | AY13: =+AY9*0.7*17.2 -> 35084.56 | AZ13: ='COKE OVENS'!AZ21 -> 36316.252 | BA13: =+AQ13+AU13+AY13 -> 101858.4 | BB13: =+AR13+AV13+AZ13 -> 103067.39 | BC13: =AM13+BA13 -> 205980.32 | BD13: =AN13+BB13 -> 207612.45 | BE13: =AW13+AY13 -> 415343.88 | BF13: =AX13+AZ13 -> 421015.51 | BH13: 415343.88 | BI13: 421442.85 | BJ13: 423729.74 | BK13: 431508.84 | BL13: 433141.24 | BM13: 432382.85 | BN13: 430769.03 | BO13: 438172.79 | BP13: 428806 | BQ13: 425506 | BR13: 430922.2 | BS13: 406071.88 | BT13: 412610.14
B14: COB#11 | C14: Mt | D14: =+D10*0.7*31.55 -> 787704.15 | E14: =+E10*31.55*0.7 -> 64002.33 | F14: ='COKE OVENS'!F22 -> 64751.169 | G14: =+G10*31.55*0.7 -> 65745.499 | H14: ='COKE OVENS'!H22 -> 63676.734 | I14: =+E14+G14 -> 129747.83 | J14: =+F14+H14 -> 128427.9 | K14: =+K10*31.55*0.7 -> 64929.9 | L14: ='COKE OVENS'!L22 -> 65239.09 | M14: =+E14+G14+K14 -> 194677.73 | N14: =+F14+H14+L14 -> 193666.99 | O14: =+O10*31.55*0.7 -> 67094.23 | P14: ='COKE OVENS'!P22 -> 67778.865 | Q14: =+M14+O14 -> 261771.96 | R14: =+N14+P14 -> 261445.86 | S14: =+S10*31.55*0.7 -> 67094.23 | T14: ='COKE OVENS'!T22 -> 67447.59 | U14: =+Q14+S14 -> 328866.19 | V14: =+R14+T14 -> 328893.45 | W14: =+W10*31.55*0.7 -> 61948.425 | X14: ='COKE OVENS'!X22 -> 64963.855 | Y14: =+O14+S14+W14 -> 196136.88 | Z14: =+P14+T14+X14 -> 200190.31 | AA14: =+M14+Y14 -> 390814.61 | AB14: =+N14+Z14 -> 393857.3 | AC14: =+AC10*31.55*0.7 -> 67094.23 | AD14: ='COKE OVENS'!AD22 -> 66256.925 | AE14: =+AA14+AC14 -> 457908.84 | AF14: =+AB14+AD14 -> 460114.23 | AG14: =+AG10*31.55*0.7 -> 64929.9 | AH14: ='COKE OVENS'!AH22 -> 64904.66 | AI14: =+AE14+AG14 -> 522838.74 | AJ14: =+AF14+AH14 -> 525018.89 | AK14: =+AK10*31.55*0.7 -> 67094.23 | AL14: ='COKE OVENS'!AL22 -> 67119.312 | AM14: =+AC14+AG14+AK14 -> 199118.36 | AN14: =+AD14+AH14+AL14 -> 198280.9 | AO14: =AI14+AK14 -> 589932.97 | AP14: =AJ14+AL14 -> 592138.2 | AQ14: =+AQ10*31.55*0.7 -> 67094.23 | AR14: ='COKE OVENS'!AR22 -> 66527.276 | AS14: =+AO14+AQ14 -> 657027.2 | AT14: =+AP14+AR14 -> 658665.48 | AU14: =+AU10*31.55*0.7 -> 60601.24 | AV14: ='COKE OVENS'!AV22 -> 60190.301 | AW14: =+AS14+AU14 -> 717628.44 | AX14: =+AT14+AV14 -> 718855.78 | AY14: =+AY10*31.55*0.7 -> 67094.23 | AZ14: ='COKE OVENS'!AZ22 -> 67075.458 | BA14: =+AQ14+AU14+AY14 -> 194789.7 | BB14: =+AR14+AV14+AZ14 -> 193793.04 | BC14: =AM14+BA14 -> 393908.06 | BD14: =AN14+BB14 -> 392073.93 | BE14: =AW14+AY14 -> 784722.67 | BF14: =AX14+AZ14 -> 785931.24 | BH14: 786998.97 | BI14: 788577.81 | BJ14: 791332.05 | BK14: 793765.31 | BL14: 786486.6 | BM14: 774691.65 | BN14: 737579.38 | BO14: 803741.8 | BP14: 778192 | BQ14: 770203 | BR14: 752591.4 | BS14: 744858.59 | BT14: 745859.84
B15: Total BF COKE | C15: Mt | D15: =SUM(D13:D14) -> 1211825.2 | E15: =SUM(E13:E14) -> 99399.93 | F15: =SUM(F13:F14) -> 99895.929 | G15: =SUM(G13:G14) -> 102323.02 | H15: =SUM(H13:H14) -> 99646.32 | I15: =SUM(I13:I14) -> 201722.95 | J15: =SUM(J13:J14) -> 199542.25 | K15: =SUM(K13:K14) -> 98882.7 | ... BF15: =SUM(BF13:BF14) -> 1206946.7 | BH15: 1202342.9 | BI15: 1210020.7 | BJ15: 1215061.8 | BK15: 1225274.2 | BL15: 1219627.8 | BM15: 1207074.5 | BN15: 1168348.4 | BO15: 1241914.6 | BP15: 1206998 | BQ15: 1195709 | BR15: 1183513.6 | BS15: 1150930.5 | BT15: 1158470
B16: SINTER | C16: Mt | D16: 4206886.4 | E16: 291677.45 | F16: 353508 | G16: 262229.25 | H16: 154593 | I16: =+E16+G16 -> 553906.71 | J16: =+F16+H16 -> 508101 | K16: =372.191438188584*1000 -> 372191.44 | L16: 376274 | M16: =+E16+G16+K16 -> 926098.14 | N16: =+F16+H16+L16 -> 884375 | O16: =376.384193405115*1000 -> 376384.19 | P16: 397960 | Q16: =+M16+O16 -> 1302482.3 | R16: =+N16+P16 -> 1282335 | S16: =376.384193405115*1000 -> 376384.19 | T16: 383179 | U16: =+Q16+S16 -> 1678866.5 | V16: =+R16+T16 -> 1665514 | W16: =207.661910104769*1000 -> 207661.91 | X16: 374784 | Y16: =+O16+S16+W16 -> 960430.3 | Z16: =+P16+T16+X16 -> 1155923 | AA16: =+M16+Y16 -> 1886528.4 | AB16: =+N16+Z16 -> 2040298 | AC16: =383.372118766*1000 -> 383372.12 | AD16: 301448 | AE16: =+AA16+AC16 -> 2269900.6 | AF16: =+AB16+AD16 -> 2341746 | AG16: =376.191438188584*1000 -> 376191.44 | AH16: 366206 | AI16: =+AE16+AG16 -> 2646092 | AJ16: =+AF16+AH16 -> 2707952 | AK16: =387.372118766*1000 -> 387372.12 | AL16: 360713 | AM16: =+AC16+AG16+AK16 -> 1146935.7 | AN16: =+AD16+AH16+AL16 -> 1028367 | AO16: =AI16+AK16 -> 3033464.1 | AP16: =AJ16+AL16 -> 3068665 | AQ16: 388962.46 | AR16: 366580 | AS16: =+AO16+AQ16 -> 3422426.6 | AT16: =+AP16+AR16 -> 3435245 | AU16: 349830.08 | AV16: 314846 | AW16: =+AS16+AU16 -> 3772256.7 | AX16: =+AT16+AV16 -> 3750091 | AY16: 388962.46 | AZ16: 379828 | BA16: =+AQ16+AU16+AY16 -> 1127755 | BB16: =+AR16+AV16+AZ16 -> 1061254 | BC16: =AM16+BA16 -> 2274690.7 | BD16: =AN16+BB16 -> 2089621 | BE16: =AW16+AY16 -> 4161219.1 | BF16: =AX16+AZ16 -> 4129919 | BH16: 4362876 | BI16: 4298954 | BJ16: 4387544.5 | BK16: 3980714 | BL16: 4499999.9 | BM16: 4398445 | BN16: 4395665 | BO16: 4183927.8 | BP16: 4277831 | BQ16: 3665891.3 | BR16: 3629577 | BS16: 3903932.5 | BT16: 3709525
B17: HOT METAL | C17: Mt | D17: 3000000 | E17: 208000 | F17: 237076.8 | G17: 187000 | H17: 110658.1 | I17: =+E17+G17 -> 395000 | J17: =+F17+H17 -> 347734.9 | K17: =252*1000 -> 252000 | L17: 261489.9 | M17: =+E17+G17+K17 -> 647000 | N17: =+F17+H17+L17 -> 609224.8 | O17: 255000 | P17: 268142.3 | Q17: =+M17+O17 -> 902000 | R17: =+N17+P17 -> 877367.1 | S17: 255000 | T17: 253263.6 | U17: =+Q17+S17 -> 1157000 | V17: =+R17+T17 -> 1130630.7 | W17: 140000 | X17: 243297.4 | Y17: =+O17+S17+W17 -> 650000 | Z17: =+P17+T17+X17 -> 764703.3 | AA17: =+M17+Y17 -> 1297000 | AB17: =+N17+Z17 -> 1373928.1 | AC17: 260000 | AD17: 202962.1 | AE17: =+AA17+AC17 -> 1557000 | AF17: =+AB17+AD17 -> 1576890.2 | AG17: 252000 | AH17: 244148.2 | AI17: =+AE17+AG17 -> 1809000 | AJ17: =+AF17+AH17 -> 1821038.4 | AK17: 260000 | AL17: 251561 | AM17: =+AC17+AG17+AK17 -> 772000 | AN17: =+AD17+AH17+AL17 -> 698671.3 | AO17: =AI17+AK17 -> 2069000 | AP17: =AJ17+AL17 -> 2072599.4 | AQ17: 264000 | AR17: 244851.4 | AS17: =+AO17+AQ17 -> 2333000 | AT17: =+AP17+AR17 -> 2317450.8 | AU17: 236000 | AV17: 196575.3 | AW17: =+AS17+AU17 -> 2569000 | AX17: =+AT17+AV17 -> 2514026.1 | AY17: 264000 | AZ17: 251871.7 | BA17: =+AQ17+AU17+AY17 -> 764000 | BB17: =+AR17+AV17+AZ17 -> 693298.4 | BC17: =AM17+BA17 -> 1536000 | BD17: =AN17+BB17 -> 1391969.7 | BE17: =AW17+AY17 -> 2833000 | BF17: =AX17+AZ17 -> 2765897.8 | BH17: 2950000 | BI17: 2900019.4 | BJ17: 2650000 | BK17: 2622585.7 | BL17: 2800000 | BM17: 2721268.1 | BN17: 2592119.6 | BO17: 2650001 | BP17: 2406785.7 | BQ17: 2496672.2 | BR17: 2092798 | BS17: 2700000 | BT17: 2505193
B18: CRUDE STEEL | C18: Mt | D18: 2817514.1 | E18: 193691.15 | F18: 223226 | G18: 170903.95 | H18: 97961 | I18: =+E18+G18 -> 364595.1 | J18: =+F18+H18 -> 321187 | K18: =237.110481586402*1000 -> 237110.48 | L18: 243453 | M18: =+E18+G18+K18 -> 601705.59 | N18: =+F18+H18+L18 -> 564640 | O18: =239.943342776204*1000 -> 239943.34 | P18: 253662 | Q18: =+M18+O18 -> 841648.93 | R18: =+N18+P18 -> 818302 | S18: =239.943342776204*1000 -> 239943.34 | T18: 237622 | U18: =+Q18+S18 -> 1081592.3 | V18: =+R18+T18 -> 1055924 | W18: =125.920679886686*1000 -> 125920.68 | X18: 226847 | Y18: =+O18+S18+W18 -> 605807.37 | Z18: =+P18+T18+X18 -> 718131 | AA18: =+M18+Y18 -> 1207513 | AB18: =+N18+Z18 -> 1282771 | AC18: =244.66477809254*1000 -> 244664.78 | AD18: 179201 | AE18: =+AA18+AC18 -> 1452177.7 | AF18: =+AB18+AD18 -> 1461972 | AG18: =237.110481586402*1000 -> 237110.48 | AH18: 229502 | AI18: =+AE18+AG18 -> 1689288.2 | AJ18: =+AF18+AH18 -> 1691474 | AK18: =244.66477809254*1000 -> 244664.78 | AL18: 234365 | AM18: =+AC18+AG18+AK18 -> 726440.04 | AN18: =+AD18+AH18+AL18 -> 643068 | AO18: =AI18+AK18 -> 1933953 | AP18: =AJ18+AL18 -> 1925839 | AQ18: 248441.93 | AR18: 228047 | AS18: =+AO18+AQ18 -> 2182394.9 | AT18: =+AP18+AR18 -> 2153886 | AU18: 222001.89 | AV18: 185016 | AW18: =+AS18+AU18 -> 2404396.8 | AX18: =+AT18+AV18 -> 2338902 | AY18: 248441.93 | AZ18: 241240 | BA18: =+AQ18+AU18+AY18 -> 718885.74 | BB18: =+AR18+AV18+AZ18 -> 654303 | BC18: =AM18+BA18 -> 1445325.8 | BD18: =AN18+BB18 -> 1297371 | BE18: =AW18+AY18 -> 2652838.7 | BF18: =AX18+AZ18 -> 2580142 | BH18: 2770018.9 | BI18: 2702613 | BJ18: 2489528.3 | BK18: 2436959 | BL18: 2620075.5 | BM18: 2528925 | BN18: 2422324.3 | BO18: 2451737.7 | BP18: 2227867 | BQ18: 2297163.5 | BR18: 1847433 | BS18: 2500000 | BT18: 2083412
B19: Caster #(1+2 ) | C19: Mt | D19: 1920416.1 | E19: =SMS!E29 -> 134587.97 | F19: =SMS!F37 -> 166745.17 | G19: =SMS!G29 -> 108106.99 | H19: =SMS!H37 -> 76500.33 | I19: =+E19+G19 -> 242694.96 | J19: =SMS!J37 -> 243245.5 | K19: =SMS!K29 -> 171147.42 | L19: =SMS!L37 -> 182735 | M19: =+E19+G19+K19 -> 413842.38 | N19: =+F19+H19+L19 -> 425980.5 | O19: =SMS!O29 -> 171341.76 | P19: =SMS!P37 -> 189077 | Q19: =+M19+O19 -> 585184.14 | R19: =+N19+P19 -> 615057.5 | S19: =SMS!S29 -> 171341.76 | T19: =SMS!T37 -> 179543 | U19: =+Q19+S19 -> 756525.9 | V19: =+R19+T19 -> 794600.5 | W19: =SMS!W29 -> 90564.479 | X19: =SMS!X37 -> 172339.6 | Y19: =+O19+S19+W19 -> 433248 | Z19: =+P19+T19+X19 -> 540959.6 | AA19: =+M19+Y19 -> 847090.38 | AB19: =+N19+Z19 -> 966940.1 | AC19: =SMS!AC29 -> 173952.38 | AD19: =SMS!AD37 -> 135241 | AE19: =+AA19+AC19 -> 1021042.8 | AF19: =+AB19+AD19 -> 1102181.1 | AG19: =SMS!AG29 -> 168508.9 | AH19: =SMS!AH37 -> 178010.44 | AI19: =SMS!AI29 -> 1189551.7 | AJ19: =SMS!AJ37 -> 1280191.5 | AK19: =SMS!AK29 -> 173424.67 | AL19: =SMS!AL37 -> 168781 | AM19: =SMS!AM29 -> 515885.95 | AN19: =SMS!AN37 -> 482032.44 | AO19: =SMS!AO29 -> 1362976.3 | AP19: =SMS!AP37 -> 1448972.5 | AQ19: =SMS!AQ29 -> 176674.12 | AR19: =SMS!AR37 -> 164934.28 | AS19: =+AO19+AQ19 -> 1539650.4 | AT19: =+AP19+AR19 -> 1613906.8 | AU19: =SMS!AU29 -> 157621.94 | AV19: =SMS!AV37 -> 135607.79 | AW19: =+AS19+AU19 -> 1697272.4 | AX19: =+AT19+AV19 -> 1749514.6 | AY19: =SMS!AY29 -> 176146.41 | AZ19: =SMS!AZ37 -> 176644.91 | BA19: =+AQ19+AU19+AY19 -> 510442.47 | BB19: =+AR19+AV19+AZ19 -> 477186.98 | BC19: =AM19+BA19 -> 1026328.4 | BD19: =AN19+BB19 -> 959219.42 | BE19: =AW19+AY19 -> 1873418.8 | BF19: =AX19+AZ19 -> 1926159.5 | BH19: 1978462.2 | BI19: 2007374.6 | BJ19: 1880445.4 | BK19: 1818588.7 | BM19: 1922629.6 | BN19: 1903696 | BP19: 1777963.7
B20: Caster #3 | C20: Mt | D20: 897098.03 | E20: =SMS!E38 -> 59103.176 | F20: =SMS!F46 -> 56481.07 | G20: =SMS!G38 -> 62796.968 | H20: =SMS!H46 -> 21460.42 | I20: =+E20+G20 -> 121900.14 | J20: =SMS!J46 -> 77941.49 | K20: =SMS!K38 -> 65963.061 | L20: =SMS!L46 -> 60718.3 | M20: =+E20+G20+K20 -> 187863.2 | N20: =+F20+H20+L20 -> 138659.79 | O20: =SMS!O38 -> 68601.583 | P20: =SMS!P46 -> 64584.79 | Q20: =+M20+O20 -> 256464.79 | R20: =+N20+P20 -> 203244.58 | S20: =SMS!S38 -> 68601.583 | T20: =SMS!T46 -> 58078.79 | U20: =+Q20+S20 -> 325066.37 | V20: =+R20+T20 -> 261323.37 | W20: =SMS!W38 -> 35356.201 | X20: =SMS!X46 -> 54507 | Y20: =+O20+S20+W20 -> 172559.37 | Z20: =+P20+T20+X20 -> 177170.58 | AA20: =+M20+Y20 -> 360422.57 | AB20: =+N20+Z20 -> 315830.37 | AC20: =SMS!AC38 -> 70712.4 | AD20: =SMS!AD46 -> 43960.31 | AE20: =+AA20+AC20 -> 431134.97 | AF20: =+AB20+AD20 -> 359790.68 | AG20: =SMS!AG38 -> 68601.583 | AH20: =SMS!AH46 -> 51491.21 | AI20: =SMS!AI38 -> 499736.55 | AJ20: =SMS!AJ46 -> 411281.89 | AK20: =SMS!AK38 -> 71240.106 | AL20: =SMS!AL46 -> 65584.38 | AM20: =SMS!AM38 -> 210554.09 | AN20: =SMS!AN46 -> 161035.9 | AO20: =SMS!AO38 -> 570976.66 | AP20: =SMS!AP46 -> 476866.27 | AQ20: =SMS!AQ38 -> 71767.81 | AR20: =SMS!AR46 -> 63113.1 | AS20: =+AO20+AQ20 -> 642744.47 | AT20: =+AP20+AR20 -> 539979.37 | AU20: =SMS!AU38 -> 64379.947 | AV20: =SMS!AV46 -> 49408.38 | AW20: =+AS20+AU20 -> 707124.42 | AX20: =+AT20+AV20 -> 589387.75 | AY20: =SMS!AY38 -> 72295.515 | AZ20: =SMS!AZ46 -> 64595.04 | BA20: =+AQ20+AU20+AY20 -> 208443.27 | BB20: =+AR20+AV20+AZ20 -> 177116.52 | BC20: =AM20+BA20 -> 418997.36 | BD20: =AN20+BB20 -> 338152.42 | BE20: =AW20+AY20 -> 779419.93 | BF20: =AX20+AZ20 -> 653982.79 | BH20: 791556.73 | BI20: 695238.43 | BJ20: 609083.07 | BK20: 618370.32 | BM20: 606294.79 | BN20: 518629.33 | BP20: 449903.88
B21: Avg Heats Cast per Day | C21: Nos. / day | D21: =D53/D1 -> 53.120553 | E21: =+E53/E1 -> 47.754228 | F21: =+F53/F1 -> 48.005642 | G21: =+G53/G1 -> 54.776909 | H21: =+H53/H1 -> 44.679842 | I21: =+I53/I1 -> 50.807567 | J21: =+J53/J1 -> 46.933333 | K21: =+K53/K1 -> 54.508157 | L21: =+L53/L1 -> 52.547596 | ... BF21: =+BF53/BF1 -> 48.879875 | BH21: 54.152138 | BI21: 49.349681 | BJ21: 51.463117 | BK21: 49.270546 | BL21: 50.337665 | BM21: 48.130368 | BN21: 45.269663 | BO21: 44.780041 | BP21: 40.065753 | BQ21: 41.920046 | BR21: 33.309589 | BS21: 47.014645 | BT21: 38.663934
B22: Cold Pig & Pig Equivalent
B23: MOG | C23: Mt | D23: 3420 | E23: 1620 | F23: 246.31997 | G23: 1800 | H23: 1995.0165 | I23: =+E23+G23 -> 3420 | J23: =+F23+H23 -> 2241.3364 | K23: =0.81*1000 -> 810 | L23: 902.97846 | M23: =+E23+G23+K23 -> 4230 | N23: =+F23+H23+L23 -> 3144.3149 | O23: 810 | P23: 0 | Q23: =+M23+O23 -> 5040 | R23: =+N23+P23 -> 3144.3149 | S23: =0.81*1000 -> 810 | T23: 144.06922 | U23: =+Q23+S23 -> 5850 | V23: =+R23+T23 -> 3288.3841 | W23: =5360-1625 -> 3735 | X23: 256.58678 | Y23: =+O23+S23+W23 -> 5355 | Z23: =+P23+T23+X23 -> 400.656 | AA23: =+M23+Y23 -> 9585 | AB23: =+N23+Z23 -> 3544.9709 | AC23: 810 | AD23: 3014.2686 | AE23: =+AA23+AC23 -> 10395 | AF23: =+AB23+AD23 -> 6559.2395 | AG23: 810 | AH23: 135.13793 | AI23: =+AE23+AG23 -> 11205 | AJ23: =+AF23+AH23 -> 6694.3775 | AK23: 810 | AL23: 35.72516 | AM23: =+AC23+AG23+AK23 -> 2430 | AN23: =+AD23+AH23+AL23 -> 3185.1317 | AO23: =AI23+AK23 -> 12015 | AP23: =AJ23+AL23 -> 6730.1026 | AQ23: 810 | AR23: 662.91874 | AS23: =+AO23+AQ23 -> 12825 | AT23: =+AP23+AR23 -> 7393.0214 | AU23: 810 | AV23: 0 | AW23: =+AS23+AU23 -> 13635 | AX23: =+AT23+AV23 -> 7393.0214 | AY23: 810 | AZ23: 80.29814 | BA23: =+AQ23+AU23+AY23 -> 2430 | BB23: =+AR23+AV23+AZ23 -> 743.21688 | BC23: =AM23+BA23 -> 4860 | BD23: =AN23+BB23 -> 3928.3486 | BE23: =AW23+AY23 -> 14445 | BF23: =AX23+AZ23 -> 7473.3195 | BH23: 12645 | BI23: 11530.128 | BJ23: 7740 | BK23: 12917.886 | BL23: 19561.1 | BM23: 7548.2756 | BN23: 9129.3344 | BO23: 19735.515 | BP23: 22361.072 | BQ23: 20755.018 | BR23: 58220.7 | BS23: 29957.856 | BT23: 134629.18
B24: UPIS | C24: Mt | D24: 0 | E24: 0 | F24: 34.774584 | G24: 0 | H24: 281.64938 | I24: =+E24+G24 -> 0 | J24: =+F24+H24 -> 316.42397 | K24: 0 | L24: 127.47931 | M24: =+E24+G24+K24 -> 0 | N24: =+F24+H24+L24 -> 443.90328 | O24: 0 | P24: 0 | Q24: =+M24+O24 -> 0 | R24: =+N24+P24 -> 443.90328 | S24: 0 | T24: 20.339184 | U24: =+Q24+S24 -> 0 | V24: =+R24+T24 -> 464.24246 | W24: 0 | X24: 36.224016 | Y24: =+O24+S24+W24 -> 0 | Z24: =+P24+T24+X24 -> 56.5632 | AA24: =+M24+Y24 -> 0 | AB24: =+N24+Z24 -> 500.46648 | AC24: 0 | AD24: 426 | AE24: =+AA24+AC24 -> 0 | AF24: =+AB24+AD24 -> 926.46648 | AG24: 0 | AH24: 19.078296 | AI24: =+AE24+AG24 -> 0 | AJ24: =+AF24+AH24 -> 945.54478 | AK24: 0 | AL24: 5 | AM24: =+AC24+AG24+AK24 -> 0 | AN24: =+AD24+AH24+AL24 -> 450.0783 | AO24: =AI24+AK24 -> 0 | AP24: =AJ24+AL24 -> 950.54478 | AQ24: 0 | AR24: 93.588528 | AS24: =+AO24+AQ24 -> 0 | AT24: =+AP24+AR24 -> 1044.1333 | AU24: 0 | AV24: 0 | AW24: =+AS24+AU24 -> 0 | AX24: =+AT24+AV24 -> 1044.1333 | AY24: 0 | AZ24: 11.336208 | BA24: =+AQ24+AU24+AY24 -> 0 | BB24: =+AR24+AV24+AZ24 -> 104.92474 | BC24: =AM24+BA24 -> 0 | BD24: =AN24+BB24 -> 555.00303 | BE24: =AW24+AY24 -> 0 | BF24: =AX24+AZ24 -> 1055.4695 | BH24: 0 | BI24: 1628.1955 | BJ24: 0 | BK24: 1823.7656 | BL24: 0 | BM24: 1026.6221 | BN24: 2541.6495 | BO24: 0 | BP24: 2774.7649 | BQ24: 392 | BR24: 3852.3 | BS24: 1419.0563 | BT24: 8272.9783
B25: Equiv. Pig Iron @ 65% of HM sent to Sand Pit | C25: Mt | D25: 2600 | E25: 325 | F25: 190 | G25: 2275 | H25: 4005 | I25: =+E25+G25 -> 2600 | J25: =+F25+H25 -> 4195 | K25: 0 | L25: 0 | M25: =+E25+G25+K25 -> 2600 | N25: =+F25+H25+L25 -> 4195 | O25: 0 | P25: 0 | Q25: =+M25+O25 -> 2600 | R25: =+N25+P25 -> 4195 | S25: 0 | T25: 0 | U25: =+Q25+S25 -> 2600 | V25: =+R25+T25 -> 4195 | W25: =2500*0.65 -> 1625 | X25: 0 | Y25: =+O25+S25+W25 -> 1625 | Z25: =+P25+T25+X25 -> 0 | AA25: =+M25+Y25 -> 4225 | AB25: =+N25+Z25 -> 4195 | AC25: 0 | AD25: 5603 | AE25: =+AA25+AC25 -> 4225 | AF25: =+AB25+AD25 -> 9798 | AG25: 0 | AH25: 0 | AI25: =+AE25+AG25 -> 4225 | AJ25: =+AF25+AH25 -> 9798 | AK25: 0 | AL25: 0 | AM25: =+AC25+AG25+AK25 -> 0 | AN25: =+AD25+AH25+AL25 -> 5603 | AO25: =AI25+AK25 -> 4225 | AP25: =AJ25+AL25 -> 9798 | AQ25: 0 | AR25: 800.6 | AS25: =+AO25+AQ25 -> 4225 | AT25: =+AP25+AR25 -> 10598.6 | AU25: 0 | AV25: 920 | AW25: =+AS25+AU25 -> 4225 | AX25: =+AT25+AV25 -> 11518.6 | AY25: 0 | AZ25: 310 | BA25: =+AQ25+AU25+AY25 -> 0 | BB25: =+AR25+AV25+AZ25 -> 2030.6 | BC25: =AM25+BA25 -> 0 | BD25: =AN25+BB25 -> 7633.6 | BE25: =AW25+AY25 -> 4225 | BF25: =AX25+AZ25 -> 11828.6 | BH25: 1625 | BI25: 8058.2 | BJ25: 1625 | BK25: 11114.8 | BL25: 2000 | BM25: 5022 | BN25: 4664.8 | BO25: 14800 | BP25: 9214.4 | BQ25: 0 | BR25: 0 | BS25: 0 | BT25: 26220.8
B26: TOTAL EQUIVALENT PIG IRON | C26: Mt | D26: =SUM(D23:D25) -> 6020 | E26: =SUM(E23:E25) -> 1945 | F26: =SUM(F23:F25) -> 471.09455 | G26: =SUM(G23:G25) -> 4075 | H26: =SUM(H23:H25) -> 6281.6659 | I26: =SUM(I23:I25) -> 6020 | J26: =SUM(J23:J25) -> 6752.7604 | K26: =SUM(K23:K25) -> 810 | ... BF26: =SUM(BF23:BF25) -> 20357.389 | BH26: 14270 | BI26: 21216.524 | BJ26: 9365 | BK26: 25856.451 | BL26: 21561.1 | BM26: 13596.898 | BN26: 16335.784 | BO26: 34535.515 | BP26: 34350.237 | BQ26: 21147.018 | BR26: 62073 | BS26: 31376.912 | BT26: 169122.96
B27: Net PCI Production | C27: Mt | D27: 5103 | E27: 644.512 | F27: 160.65 | G27: 2598.518 | H27: 162.365 | I27: =+E27+G27 -> 3243.03 | J27: =+F27+H27 -> 323.015 | K27: 273.996 | L27: 0 | M27: =+E27+G27+K27 -> 3517.026 | N27: =+F27+H27+L27 -> 323.015 | O27: 276.24 | P27: 0 | Q27: =+M27+O27 -> 3793.266 | R27: =+N27+P27 -> 323.015 | S27: 276.24 | T27: 0 | U27: =+Q27+S27 -> 4069.506 | V27: =+R27+T27 -> 323.015 | W27: 498.97 | X27: 0 | Y27: =+O27+S27+W27 -> 1051.45 | Z27: =+P27+T27+X27 -> 0 | AA27: =+M27+Y27 -> 4568.476 | AB27: =+N27+Z27 -> 323.015 | AC27: 279.98 | AD27: 549.087 | AE27: =+AA27+AC27 -> 4848.456 | AF27: =+AB27+AD27 -> 872.102 | AG27: 273.996 | AH27: 833.469 | AI27: =+AE27+AG27 -> 5122.452 | AJ27: =+AF27+AH27 -> 1705.571 | AK27: 279.98 | AL27: 1510.747 | AM27: =+AC27+AG27+AK27 -> 833.956 | AN27: =+AD27+AH27+AL27 -> 2893.303 | AO27: =AI27+AK27 -> 5402.432 | AP27: =AJ27+AL27 -> 3216.318 | AQ27: 282.972 | AR27: 1549.45 | AS27: =+AO27+AQ27 -> 5685.404 | AT27: =+AP27+AR27 -> 4765.768 | AU27: 262.028 | AV27: 755.405 | AW27: =+AS27+AU27 -> 5947.432 | AX27: =+AT27+AV27 -> 5521.173 | AY27: 282.972 | AZ27: 209.86 | BA27: =+AQ27+AU27+AY27 -> 827.972 | BB27: =+AR27+AV27+AZ27 -> 2514.715 | BC27: =AM27+BA27 -> 1661.928 | BD27: =AN27+BB27 -> 5408.018 | BE27: =AW27+AY27 -> 6230.404 | BF27: =AX27+AZ27 -> 5731.033 | BH27: 3541.35 | BI27: 6386.38 | BJ27: 2831.5 | BK27: 7991.486 | BL27: 2377.872 | BM27: 6141.395 | BN27: 5885.734 | BO27: 2398.56 | BP27: 13377.679 | BQ27: 11568.99 | BR27: 41093.9 | BS27: 0 | BT27: 44255.19
B28: Net Granulated Slag Production | C28: Mt | D28: 1049580 | E28: 72770.88 | F28: 73016.796 | G28: 63421.05 | H28: 34000.934 | I28: =+E28+G28 -> 136191.93 | J28: =+F28+H28 -> 107017.73 | K28: 92363.04 | L28: 72846.055 | M28: =+E28+G28+K28 -> 228554.97 | N28: =+F28+H28+L28 -> 179863.79 | O28: 93462.6 | P28: 75682.97 | Q28: =+M28+O28 -> 322017.57 | R28: =+N28+P28 -> 255546.76 | S28: 93462.6 | T28: 80832.023 | U28: =+Q28+S28 -> 415480.17 | V28: =+R28+T28 -> 336378.78 | W28: 51312.8 | X28: 79584.049 | Y28: =+O28+S28+W28 -> 238238 | Z28: =+P28+T28+X28 -> 236099.04 | AA28: =+M28+Y28 -> 466792.97 | AB28: =+N28+Z28 -> 415962.83 | AC28: 95295.2 | AD28: 63840.922 | AE28: =+AA28+AC28 -> 562088.17 | AF28: =+AB28+AD28 -> 479803.75 | AG28: 92363.04 | AH28: 88321.763 | AI28: =+AE28+AG28 -> 654451.21 | AJ28: =+AF28+AH28 -> 568125.51 | AK28: 95295.2 | AL28: 84104.855 | AM28: =+AC28+AG28+AK28 -> 282953.44 | AN28: =+AD28+AH28+AL28 -> 236267.54 | AO28: =AI28+AK28 -> 749746.41 | AP28: =AJ28+AL28 -> 652230.37 | AQ28: 96761.28 | AR28: 81040.671 | AS28: =+AO28+AQ28 -> 846507.69 | AT28: =+AP28+AR28 -> 733271.04 | AU28: 86498.72 | AV28: 67236.848 | AW28: =+AS28+AU28 -> 933006.41 | AX28: =+AT28+AV28 -> 800507.89 | AY28: 96761.28 | AZ28: 71373.052 | BA28: =+AQ28+AU28+AY28 -> 280021.28 | BB28: =+AR28+AV28+AZ28 -> 219650.57 | BC28: =AM28+BA28 -> 562974.72 | BD28: =AN28+BB28 -> 455918.11 | BE28: =AW28+AY28 -> 1029767.7 | BF28: =AX28+AZ28 -> 871880.94 | BH28: 1081234 | BI28: 911237.59 | BJ28: 987899.89 | BK28: 899258.76 | BL28: 1063047 | BM28: 1075244.6 | BN28: 1065593 | BO28: 157305.12 | BP28: 920129.3 | BQ28: 882599.97 | BR28: 776699 | BS28: 854658 | BT28: 809638.21
B29: Saleable Steel Production (Mill Wise)
B30: WR Mill | C30: Mt | D30: 520000 | E30: 36500 | F30: =+WRM!F159 -> 41533 | G30: 37500 | H30: =+WRM!H159 -> 21522.95 | I30: =+E30+G30 -> 74000 | J30: =+F30+H30 -> 63055.95 | K30: 42500 | L30: =+WRM!L159 -> 38291.35 | M30: =+E30+G30+K30 -> 116500 | N30: =+F30+H30+L30 -> 101347.3 | O30: 44000 | P30: =+WRM!P159 -> 47063.9 | Q30: =+M30+O30 -> 160500 | R30: =+N30+P30 -> 148411.2 | S30: 44000 | T30: =+WRM!T159 -> 38718.35 | U30: =+Q30+S30 -> 204500 | V30: =+R30+T30 -> 187129.55 | W30: 25000 | X30: =+WRM!X159 -> 41006.15 | Y30: =+O30+S30+W30 -> 113000 | Z30: =+P30+T30+X30 -> 126788.4 | AA30: =+M30+Y30 -> 229500 | AB30: =+N30+Z30 -> 228135.7 | AC30: 42500 | AD30: =+WRM!AD159 -> 30034.55 | AE30: =+AA30+AC30 -> 272000 | AF30: =+AB30+AD30 -> 258170.25 | AG30: 42500 | AH30: =+WRM!AH159 -> 34614.25 | AI30: =+AE30+AG30 -> 314500 | AJ30: =+AF30+AH30 -> 292784.5 | AK30: 44000 | AL30: =+WRM!AL159 -> 44007.35 | AM30: =+AC30+AG30+AK30 -> 129000 | AN30: =+AD30+AH30+AL30 -> 108656.15 | AO30: =AI30+AK30 -> 358500 | AP30: =AJ30+AL30 -> 336791.85 | AQ30: 44500 | AR30: =+WRM!AR159 -> 44589.55 | AS30: =+AO30+AQ30 -> 403000 | AT30: =+AP30+AR30 -> 381381.4 | AU30: 40000 | AV30: =+WRM!AV159 -> 37420.7 | AW30: =+AS30+AU30 -> 443000 | AX30: =+AT30+AV30 -> 418802.1 | AY30: 44500 | AZ30: =+WRM!AZ159 -> 46692.85 | BA30: =+AQ30+AU30+AY30 -> 129000 | BB30: =+AR30+AV30+AZ30 -> 128703.1 | BC30: =AM30+BA30 -> 258000 | BD30: =AN30+BB30 -> 237359.25 | BE30: =AW30+AY30 -> 487500 | BF30: =AX30+AZ30 -> 465494.95 | BH30: 500000 | BI30: 478532.93 | BJ30: 500000 | BK30: 459030.64 | BL30: 500000 | BM30: 478528.39 | BN30: 466114.65 | BO30: 500000 | BP30: 465343.77 | BQ30: 435965.96 | BR30: 356518.66 | BS30: 500000 | BT30: 412025.22
B31: Bar Mill | C31: Mt | D31: 990000 | E31: 68500 | F31: =+BM!F56 -> 74661.04 | G31: 71000 | H31: =+BM!H56 -> 33192.92 | I31: =+E31+G31 -> 139500 | J31: =+F31+H31 -> 107853.96 | K31: 76000 | L31: =+BM!L56 -> 73644.015 | M31: =+E31+G31+K31 -> 215500 | N31: =+F31+H31+L31 -> 181497.98 | O31: 79000 | P31: =+BM!P56 -> 88056.49 | Q31: =+M31+O31 -> 294500 | R31: =+N31+P31 -> 269554.47 | S31: 79000 | T31: =+BM!T56 -> 75853.695 | U31: =+Q31+S31 -> 373500 | V31: =+R31+T31 -> 345408.16 | W31: =47.5*1000 -> 47500 | X31: =+BM!X56 -> 76319.035 | Y31: =+O31+S31+W31 -> 205500 | Z31: =+P31+T31+X31 -> 240229.22 | AA31: =+M31+Y31 -> 421000 | AB31: =+N31+Z31 -> 421727.2 | AC31: 78000 | AD31: =+BM!AD56 -> 50950.275 | AE31: =+AA31+AC31 -> 499000 | AF31: =+AB31+AD31 -> 472677.47 | AG31: 76000 | AH31: =+BM!AH56 -> 69720.765 | AI31: =+AE31+AG31 -> 575000 | AJ31: =+AF31+AH31 -> 542398.24 | AK31: 79000 | AL31: =+BM!AL56 -> 81616.765 | AM31: =+AC31+AG31+AK31 -> 233000 | AN31: =+AD31+AH31+AL31 -> 202287.81 | AO31: =AI31+AK31 -> 654000 | AP31: =AJ31+AL31 -> 624015 | AQ31: 79000 | AR31: =+BM!AR56 -> 85804.6 | AS31: =+AO31+AQ31 -> 733000 | AT31: =+AP31+AR31 -> 709819.6 | AU31: 71500 | AV31: =+BM!AV56 -> 74058.32 | AW31: =+AS31+AU31 -> 804500 | AX31: =+AT31+AV31 -> 783877.92 | AY31: 80000 | AZ31: =+BM!AZ56 -> 81200 | BA31: =+AQ31+AU31+AY31 -> 230500 | BB31: =+AR31+AV31+AZ31 -> 241062.92 | BC31: =AM31+BA31 -> 463500 | BD31: =AN31+BB31 -> 443350.73 | BE31: =AW31+AY31 -> 884500 | BF31: =AX31+AZ31 -> 865077.92 | BH31: 900000 | BI31: 900295.05 | BJ31: 870000 | BK31: 750867.85 | BL31: 850000 | BM31: 795322.27 | BN31: 775906.63 | BO31: 750000 | BP31: 649840.96 | BQ31: 674875.14 | BR31: 440547.27 | BS31: 800000 | BT31: 632220.18
B32: US Mill | C32: Mt | D32: 850000 | E32: 56000 | F32: =+USM!G121 -> 52520.054 | G32: 59500 | H32: =+USM!I121 -> 10535.918 | I32: =+E32+G32 -> 115500 | J32: =+F32+H32 -> 63055.972 | K32: 62500 | L32: =+USM!M121 -> 58674.633 | M32: =+E32+G32+K32 -> 178000 | N32: =+F32+H32+L32 -> 121730.61 | O32: 65000 | P32: =+USM!Q121 -> 57327.387 | Q32: =+M32+O32 -> 243000 | R32: =+N32+P32 -> 179057.99 | S32: 65000 | T32: =+USM!U121 -> 44406.293 | U32: =+Q32+S32 -> 308000 | V32: =+R32+T32 -> 223464.29 | W32: 33500 | X32: =+USM!Y121 -> 49996.716 | Y32: =+O32+S32+W32 -> 163500 | Z32: =+P32+T32+X32 -> 151730.4 | AA32: =+M32+Y32 -> 341500 | AB32: =+N32+Z32 -> 273461 | AC32: 67000 | AD32: =+USM!AE121 -> 29659.897 | AE32: =+AA32+AC32 -> 408500 | AF32: =+AB32+AD32 -> 303120.9 | AG32: 65000 | AH32: =+USM!AI121 -> 49060.044 | AI32: =+AE32+AG32 -> 473500 | AJ32: =+AF32+AH32 -> 352180.94 | AK32: =67.5*1000 -> 67500 | AL32: =+USM!AM121 -> 52987.18 | AM32: =+AC32+AG32+AK32 -> 199500 | AN32: =+AD32+AH32+AL32 -> 131707.12 | AO32: =AI32+AK32 -> 541000 | AP32: =AJ32+AL32 -> 405168.12 | AQ32: 68000 | AR32: =+USM!AS121 -> 56169.978 | AS32: =+AO32+AQ32 -> 609000 | AT32: =+AP32+AR32 -> 461338.1 | AU32: 61000 | AV32: =+USM!AW121 -> 54279.398 | AW32: =+AS32+AU32 -> 670000 | AX32: =+AT32+AV32 -> 515617.5 | AY32: 68500 | AZ32: =+USM!BA121 -> 63120.146 | BA32: =+AQ32+AU32+AY32 -> 197500 | BB32: =+AR32+AV32+AZ32 -> 173569.52 | BC32: =AM32+BA32 -> 397000 | BD32: =AN32+BB32 -> 305276.64 | BE32: =AW32+AY32 -> 738500 | BF32: =AX32+AZ32 -> 578737.64 | BH32: 750000 | BI32: 622444.59 | BJ32: 560000 | BK32: 499887.23 | BL32: 525000 | BM32: 459141.95 | BN32: 361987.56 | BO32: 450000 | BP32: 213226.16 | BQ32: 220000 | BR32: 88943.894 | BS32: 535000 | BT32: 171634.81
B33: Finished Steel | C33: Mt | D33: =SUM(D30:D32) -> 2360000 | E33: =SUM(E30:E32) -> 161000 | F33: =SUM(F30:F32) -> 168714.09 | G33: =SUM(G30:G32) -> 168000 | H33: =SUM(H30:H32) -> 65251.788 | I33: =SUM(I30:I32) -> 329000 | J33: =SUM(J30:J32) -> 233965.88 | K33: =SUM(K30:K32) -> 181000 | ... BF33: =SUM(BF30:BF32) -> 1909310.5 | BH33: 2150000 | BI33: 2001272.6 | BJ33: 1930000 | BK33: 1709785.7 | BL33: 1875000 | BM33: 1732992.6 | BN33: 1604008.8 | BO33: 1700000 | BP33: 1328410.9 | BQ33: 1330841.1 | BR33: 886009.82 | BS33: =SUM(BS30:BS32) -> 1835000 | BT33: =SUM(BT30:BT32) -> 1215880.2
B34: 150x150 mm | C34: Mt | D34: 349999.99 | E34: 20999.684 | F34: =38395.02-12 -> 38383.02 | G34: 0.3568633 | H34: =19481.02-67 -> 19414.02 | I34: =+E34+G34 -> 21000.041 | J34: =+F34+H34 -> 57797.04 | K34: =48.0001108831152*1000 -> 48000.111 | L34: 56218 | M34: =+E34+G34+K34 -> 69000.151 | N34: =+F34+H34+L34 -> 114015.04 | O34: =43.5001413553209*1000 -> 43500.141 | P34: 50303 | Q34: =+M34+O34 -> 112500.29 | R34: =+N34+P34 -> 164318.04 | S34: =43.5001413553209*1000 -> 43500.141 | T34: 51235.42 | U34: =+Q34+S34 -> 156000.43 | V34: =+R34+T34 -> 215553.46 | W34: =15.3000147648532*1000 -> 15300.015 | X34: 54076 | Y34: =+O34+S34+W34 -> 102300.3 | Z34: =+P34+T34+X34 -> 155614.42 | AA34: =+M34+Y34 -> 171300.45 | AB34: =+N34+Z34 -> 269629.46 | AC34: =48.9995281597563*1000 -> 48999.528 | AD34: 54595 | AE34: =+AA34+AC34 -> 220299.98 | AF34: =+AB34+AD34 -> 324224.46 | AG34: =45.4995884556746*1000 -> 45499.588 | AH34: 61080 | AI34: =+AE34+AG34 -> 265799.57 | AJ34: =+AF34+AH34 -> 385304.46 | AK34: =46.0000542442164*1000 -> 46000.054 | AL34: 52347.66 | AM34: =+AC34+AG34+AK34 -> 140499.17 | AN34: =+AD34+AH34+AL34 -> 168022.66 | AO34: =AI34+AK34 -> 311799.62 | AP34: =AJ34+AL34 -> 437652.12 | AQ34: 48499.665 | AR34: 30958 | AS34: =+AO34+AQ34 -> 360299.28 | AT34: =+AP34+AR34 -> 468610.12 | AU34: 41500.01 | AV34: 16550 | AW34: =+AS34+AU34 -> 401799.29 | AX34: =+AT34+AV34 -> 485160.12 | AY34: 46999.691 | AZ34: =38139.639-111 -> 38028.639 | BA34: =+AQ34+AU34+AY34 -> 136999.37 | BB34: =+AR34+AV34+AZ34 -> 85536.639 | BC34: =AM34+BA34 -> 277498.54 | BD34: =AN34+BB34 -> 253559.3 | BE34: =AW34+AY34 -> 448798.99 | BF34: =AX34+AZ34 -> 523188.76 | BH34: 524798.34 | BI34: 563564.31 | BJ34: 461999.56 | BK34: 558374.45 | BL34: 592000 | BM34: 574823.37 | BN34: 595119.91 | BO34: 516406.77 | BP34: 627684.57 | BQ34: 533055.82 | BR34: 608495.73 | BS34: 304999.74 | BT34: 629438.96
B35: 200x280 mm | C35: Mt | D35: 0.40803377 | E35: 0.27340158 | F35: 1625.08 | G35: 0.13463219 | H35: =3617.44+67 -> 3684.44 | I35: =+E35+G35 -> 0.40803377 | J35: =+F35+H35 -> 5309.52 | K35: 0 | L35: 1066 | M35: =+E35+G35+K35 -> 0.40803377 | N35: =+F35+H35+L35 -> 6375.52 | O35: 0 | P35: 463 | Q35: =+M35+O35 -> 0.40803377 | R35: =+N35+P35 -> 6838.52 | S35: 0 | T35: 8811.77 | U35: =+Q35+S35 -> 0.40803377 | V35: =+R35+T35 -> 15650.29 | W35: 0 | X35: 1414 | Y35: =+O35+S35+W35 -> 0 | Z35: =+P35+T35+X35 -> 10688.77 | AA35: =+M35+Y35 -> 0.40803377 | AB35: =+N35+Z35 -> 17064.29 | AC35: 0 | AD35: =11175+37 -> 11212 | AE35: =+AA35+AC35 -> 0.40803377 | AF35: =+AB35+AD35 -> 28276.29 | AG35: 0 | AH35: 0 | AI35: =+AE35+AG35 -> 0.40803377 | AJ35: =+AF35+AH35 -> 28276.29 | AK35: 0 | AL35: 703.34 | AM35: =+AC35+AG35+AK35 -> 0 | AN35: =+AD35+AH35+AL35 -> 11915.34 | AO35: =AI35+AK35 -> 0.40803377 | AP35: =AJ35+AL35 -> 28979.63 | AQ35: 0 | AR35: 7040 | AS35: =+AO35+AQ35 -> 0.40803377 | AT35: =+AP35+AR35 -> 36019.63 | AU35: 0 | AV35: 1892 | AW35: =+AS35+AU35 -> 0.40803377 | AX35: =+AT35+AV35 -> 37911.63 | AY35: 0 | AZ35: =4180.26+111 -> 4291.26 | BA35: =+AQ35+AU35+AY35 -> 0 | BB35: =+AR35+AV35+AZ35 -> 13223.26 | BC35: =AM35+BA35 -> 0 | BD35: =AN35+BB35 -> 25138.6 | BE35: =AW35+AY35 -> 0.40803377 | BF35: =AX35+AZ35 -> 42202.89 | BH35: 0 | BI35: 39893.37 | BJ35: 17999.996 | BK35: 63663.849 | BL35: 57999.916 | BM35: 101828.14 | BN35: 116079.05 | BO35: 153592.34 | BP35: 204330.35 | BQ35: 371378.01 | BR35: 329378.8 | BS35: 267000 | BT35: 248401
B36: Saleable Semis | C36: Mt | D36: =SUM(D34:D35) -> 350000.4 | E36: =SUM(E34:E35) -> 20999.957 | F36: =SUM(F34:F35) -> 40008.1 | G36: =SUM(G34:G35) -> 0.49149549 | H36: =SUM(H34:H35) -> 23098.46 | I36: =SUM(I34:I35) -> 21000.449 | J36: =SUM(J34:J35) -> 63106.56 | K36: =SUM(K34:K35) -> 48000.111 | ... BF36: =SUM(BF34:BF35) -> 565391.65 | BH36: 524798.34 | BI36: 603457.68 | BJ36: 479999.56 | BK36: 622038.3 | BL36: 649999.92 | BM36: 676651.51 | BN36: 711198.96 | BO36: 669999.11 | BP36: 832014.92 | BQ36: 904433.83 | BR36: 937874.53 | BS36: =SUM(BS34:BS35) -> 571999.74 | BT36: =SUM(BT34:BT35) -> 877839.96
B37: TOTAL SALEABLE STEEL | C37: Mt | D37: =+D33+D36 -> 2710000.4 | E37: =+E33+E36 -> 181999.96 | F37: =+F33+F36 -> 208722.19 | G37: =+G33+G36 -> 168000.49 | H37: =+H33+H36 -> 88350.248 | I37: =+I33+I36 -> 350000.45 | J37: =+J33+J36 -> 297072.44 | K37: =+K33+K36 -> 229000.11 | ... BF37: =+BF33+BF36 -> 2474702.2 | BH37: 2674798.3 | BI37: 2604730.3 | BJ37: 2409999.6 | BK37: 2331824 | BL37: 2524999.9 | BM37: 2409644.1 | BN37: 2315207.8 | BO37: 2369999.1 | BP37: 2160425.8 | BQ37: 2235274.9 | BR37: 1823884.4 | BS37: =+BS33+BS36 -> 2406999.7 | BT37: =+BT33+BT36 -> 2093720.2
B38: SAL STEEL PRODN (CATEGORY WISE)
B39: Wire Rod Plain Coils | C39: Mt | D39: =+D30 -> 520000 | E39: =+E30 -> 36500 | F39: =+WRM!F199 -> 41533 | G39: =+G30 -> 37500 | H39: =+WRM!H199 -> 21522.95 | I39: =+E39+G39 -> 74000 | J39: =+F39+H39 -> 63055.95 | K39: =+K30 -> 42500 | L39: =+WRM!L199 -> 28929.6 | M39: =+E39+G39+K39 -> 116500 | N39: =+F39+H39+L39 -> 91985.55 | O39: =+O30 -> 44000 | P39: =+WRM!P199 -> 35815.55 | Q39: =+M39+O39 -> 160500 | R39: =+N39+P39 -> 127801.1 | S39: =+S30 -> 44000 | T39: =+WRM!T199 -> 38718.35 | U39: =+Q39+S39 -> 204500 | V39: =+R39+T39 -> 166519.45 | W39: =+W30 -> 25000 | X39: =+WRM!X199 -> 41006.15 | Y39: =+O39+S39+W39 -> 113000 | Z39: =+P39+T39+X39 -> 115540.05 | AA39: =+M39+Y39 -> 229500 | AB39: =+N39+Z39 -> 207525.6 | AC39: =+AC30 -> 42500 | AD39: =+WRM!AD199 -> 30034.55 | AE39: =+AA39+AC39 -> 272000 | AF39: =+AB39+AD39 -> 237560.15 | AG39: =+AG30 -> 42500 | AH39: =+WRM!AH199 -> 34614.25 | AI39: =+AE39+AG39 -> 314500 | AJ39: =+AF39+AH39 -> 272174.4 | AK39: =+AK30 -> 44000 | AL39: =+WRM!AL199 -> 44007.35 | AM39: =+AC39+AG39+AK39 -> 129000 | AN39: =+AD39+AH39+AL39 -> 108656.15 | AO39: =AI39+AK39 -> 358500 | AP39: =AJ39+AL39 -> 316181.75 | AQ39: =+AQ30 -> 44500 | AR39: =+WRM!AR199 -> 44589.55 | AS39: =+AO39+AQ39 -> 403000 | AT39: =+AP39+AR39 -> 360771.3 | AU39: =+AU30 -> 40000 | AV39: =+WRM!AV199 -> 37420.7 | AW39: =+AS39+AU39 -> 443000 | AX39: =+AT39+AV39 -> 398192 | AY39: =+AY30 -> 44500 | AZ39: =+WRM!AZ199 -> 46692.85 | BA39: =+AQ39+AU39+AY39 -> 129000 | BB39: =+AR39+AV39+AZ39 -> 128703.1 | BC39: =AM39+BA39 -> 258000 | BD39: =AN39+BB39 -> 237359.25 | BE39: =AW39+AY39 -> 487500 | BF39: =AX39+AZ39 -> 444884.85 | BH39: 500000 | BI39: 457922.83 | BJ39: 500000 | BK39: 459030.64 | BL39: 500000 | BM39: 471802.34 | BN39: 410762.6 | BO39: =+BO30 -> 500000 | BP39: 456374.84 | BQ39: =+BQ30 -> 435965.96 | BR39: 333534.61 | BS39: 500000 | BT39: 270654.57
B40: TMT Coils | C40: Mt | F40: =+WRM!F200 -> 0 | H40: =+WRM!H200 -> 0 | J40: =+F40+H40 -> 0 | L40: =+WRM!L200 -> 9361.75 | N40: =+F40+H40+L40 -> 9361.75 | P40: =+WRM!P200 -> 11248.35 | R40: =+N40+P40 -> 20610.1 | T40: =+WRM!T200 -> 0 | V40: =+R40+T40 -> 20610.1 | X40: =+WRM!X200 -> 0 | Z40: =+P40+T40+X40 -> 11248.35 | AB40: =+N40+Z40 -> 20610.1 | AD40: =+WRM!AD200 -> 0 | AF40: =+AB40+AD40 -> 20610.1 | AH40: =+WRM!AH200 -> 0 | AJ40: =+AF40+AH40 -> 20610.1 | AL40: =+WRM!AL200 -> 0 | AN40: =+AD40+AH40+AL40 -> 0 | AP40: =AJ40+AL40 -> 20610.1 | AR40: =+WRM!AR200 -> 0 | AT40: =+AP40+AR40 -> 20610.1 | AV40: =+WRM!AV200 -> 0 | AX40: =+AT40+AV40 -> 20610.1 | AZ40: =+WRM!AZ200 -> 0 | BA40: =+AQ40+AU40+AY40 -> 0 | BB40: =+AR40+AV40+AZ40 -> 0 | BC40: =AM40+BA40 -> 0 | BD40: =AN40+BB40 -> 0 | BF40: =AX40+AZ40 -> 20610.1 | BI40: 20610.1 | BK40: 0 | BM40: 6726.05 | BN40: 55352.05 | BP40: 8968.93 | BR40: 22983.766 | BT40: 141370.65
B41: TMT Bars | C41: Mt | D41: =+D31 -> 990000 | E41: =+E31 -> 68500 | F41: =+F31 -> 74661.04 | G41: =+G31 -> 71000 | H41: =+H31 -> 33192.92 | I41: =+E41+G41 -> 139500 | J41: =+F41+H41 -> 107853.96 | K41: =+K31 -> 76000 | L41: =+L31 -> 73644.015 | M41: =+E41+G41+K41 -> 215500 | N41: =+F41+H41+L41 -> 181497.98 | O41: =+O31 -> 79000 | P41: =+P31 -> 88056.49 | Q41: =+M41+O41 -> 294500 | R41: =+N41+P41 -> 269554.47 | S41: =+S31 -> 79000 | T41: =+T31 -> 75853.695 | U41: =+Q41+S41 -> 373500 | V41: =+R41+T41 -> 345408.16 | W41: =+W31 -> 47500 | X41: =+X31 -> 76319.035 | Y41: =+O41+S41+W41 -> 205500 | Z41: =+P41+T41+X41 -> 240229.22 | AA41: =+M41+Y41 -> 421000 | AB41: =+N41+Z41 -> 421727.2 | AC41: =+AC31 -> 78000 | AD41: =+AD31 -> 50950.275 | AE41: =+AA41+AC41 -> 499000 | AF41: =+AB41+AD41 -> 472677.47 | AG41: =+AG31 -> 76000 | AH41: =+AH31 -> 69720.765 | AI41: =+AE41+AG41 -> 575000 | AJ41: =+AF41+AH41 -> 542398.24 | AK41: =+AK31 -> 79000 | AL41: =+AL31 -> 81616.765 | AM41: =+AC41+AG41+AK41 -> 233000 | AN41: =+AD41+AH41+AL41 -> 202287.81 | AO41: =AI41+AK41 -> 654000 | AP41: =AJ41+AL41 -> 624015 | AQ41: =+AQ31 -> 79000 | AR41: =+AR31 -> 85804.6 | AS41: =+AO41+AQ41 -> 733000 | AT41: =+AP41+AR41 -> 709819.6 | AU41: =+AU31 -> 71500 | AV41: =+AV31 -> 74058.32 | AW41: =+AS41+AU41 -> 804500 | AX41: =+AT41+AV41 -> 783877.92 | AY41: =+AY31 -> 80000 | AZ41: =+AZ31 -> 81200 | BA41: =+AQ41+AU41+AY41 -> 230500 | BB41: =+AR41+AV41+AZ41 -> 241062.92 | BC41: =AM41+BA41 -> 463500 | BD41: =AN41+BB41 -> 443350.73 | BE41: =AW41+AY41 -> 884500 | BF41: =AX41+AZ41 -> 865077.92 | BH41: 900000 | BI41: 900295.05 | BJ41: 870000 | BK41: 750867.85 | BL41: 850000 | BM41: 795322.27 | BN41: 775906.63 | BO41: 750000 | BP41: 649840.96 | BQ41: =+BQ31 -> 674875.14 | BR41: 440547.14 | BS41: 800000 | BT41: 632220.18
B42: NPB | C42: Mt | D42: =+D32 -> 850000 | E42: =+E32 -> 56000 | F42: =+USM!G162 -> 35837.255 | G42: =+G32 -> 59500 | H42: =+USM!I162 -> 3259.244 | I42: =+G42+E42 -> 115500 | J42: =+F42+H42 -> 39096.499 | K42: =+K32 -> 62500 | L42: =+USM!M162 -> 41676.831 | M42: =+K42+G42+E42 -> 178000 | N42: =+F42+H42+L42 -> 80773.33 | O42: =+O32 -> 65000 | P42: =+USM!Q162 -> 39505.728 | Q42: =+M42+O42 -> 243000 | R42: =+N42+P42 -> 120279.06 | S42: =+S32 -> 65000 | T42: =+USM!U162 -> 30061.678 | U42: =+Q42+S42 -> 308000 | V42: =+R42+T42 -> 150340.74 | W42: =+W32 -> 33500 | X42: =+USM!Y162 -> 32261.594 | Y42: =+W42+S42+O42 -> 163500 | Z42: =+P42+T42+X42 -> 101829 | AA42: =+M42+Y42 -> 341500 | AB42: =+N42+Z42 -> 182602.33 | AC42: =+AC32 -> 67000 | AD42: =+USM!AE162 -> 26347.059 | AE42: =+AC42+AA42 -> 408500 | AF42: =+AB42+AD42 -> 208949.39 | AG42: =+AG32 -> 65000 | AH42: =+USM!AI162 -> 33174.987 | AI42: =+AG42+AE42 -> 473500 | AJ42: =+AF42+AH42 -> 242124.38 | AK42: =+AK32 -> 67500 | AL42: =+USM!AM162 -> 34992.378 | AM42: =+AK42+AG42+AC42 -> 199500 | AN42: =+AD42+AH42+AL42 -> 94514.424 | AO42: =AI42+AK42 -> 541000 | AP42: =AJ42+AL42 -> 277116.75 | AQ42: =+AQ32 -> 68000 | AR42: =+USM!AS162 -> 35829.667 | AS42: =+AQ42+AO42 -> 609000 | AT42: =+AP42+AR42 -> 312946.42 | AU42: =+AU32 -> 61000 | AV42: =+USM!AW162 -> 43359.471 | AW42: =+AU42+AS42 -> 670000 | AX42: =+AT42+AV42 -> 356305.89 | AY42: =+AY32 -> 68500 | AZ42: =+USM!BA162 -> 50048.393 | BA42: =+AQ42+AU42+AY42 -> 197500 | BB42: =+AR42+AV42+AZ42 -> 129237.53 | BC42: =AM42+BA42 -> 397000 | BD42: =AN42+BB42 -> 223751.95 | BE42: =AW42+AY42 -> 738500 | BF42: =AX42+AZ42 -> 406354.29 | BH42: 750000 | BI42: 448592.32 | BJ42: 560000 | BK42: 369513.93 | BL42: 525000 | BM42: 322948.42 | BN42: 273627.65 | BO42: =+BO32 -> 450000 | BP42: 168119.5 | BQ42: =+BQ32 -> 220000 | BR42: 78790 | BS42: 535000 | BT42: =+BT32 -> 171634.81
B43: WPB | C43: Mt | F43: =+USM!G163 -> 8136.526 | H43: =+USM!I163 -> 2879.526 | I43: =+E43+G43 -> 0 | J43: =+F43+H43 -> 11016.052 | L43: =+USM!M163 -> 5963.765 | N43: =+F43+H43+L43 -> 16979.817 | P43: =+USM!Q163 -> 6848.383 | Q43: =+M43+O43 -> 0 | R43: =+N43+P43 -> 23828.2 | T43: =+USM!U163 -> 1438.253 | U43: =+Q43+S43 -> 0 | V43: =+R43+T43 -> 25266.453 | X43: =+USM!Y163 -> 5720.883 | Z43: =+P43+T43+X43 -> 14007.519 | AB43: =+N43+Z43 -> 30987.336 | AD43: =+USM!AE163 -> 0 | AE43: =+AA43+AC43 -> 0 | AF43: =+AB43+AD43 -> 30987.336 | AH43: =+USM!AI163 -> 6170.536 | AI43: =+AE43+AG43 -> 0 | AJ43: =+AF43+AH43 -> 37157.872 | AL43: =+USM!AM163 -> 4072.823 | AN43: =+AD43+AH43+AL43 -> 10243.359 | AO43: =+AK43+AM43 -> 0 | AP43: =AJ43+AL43 -> 41230.695 | AR43: =+USM!AS163 -> 5596.393 | AS43: =+AO43+AQ43 -> 0 | AT43: =+AP43+AR43 -> 46827.088 | AV43: =+USM!AW163 -> 3073.86 | AW43: =+AS43+AU43 -> 0 | AX43: =+AT43+AV43 -> 49900.948 | AZ43: =+USM!BA163 -> 4775.869 | BA43: =+AQ43+AU43+AY43 -> 0 | BB43: =+AR43+AV43+AZ43 -> 13446.122 | BC43: =AM43+BA43 -> 0 | BD43: =AN43+BB43 -> 23689.481 | BE43: =+AY43+BA43 -> 0 | BF43: =AX43+AZ43 -> 54676.817 | BH43: 0 | BI43: 56928.032 | BJ43: 0 | BK43: 47628.758 | BL43: 0 | BM43: 47288.061 | BN43: 21791.11
B44: Channels | C44: Mt | F44: =+USM!G164 -> 3735.17 | H44: =+USM!I164 -> 4397.148 | I44: =+E44+G44 -> 0 | J44: =+F44+H44 -> 8132.318 | L44: =+USM!M164 -> 6391.514 | N44: =+F44+H44+L44 -> 14523.832 | P44: =+USM!Q164 -> 8126.569 | Q44: =+M44+O44 -> 0 | R44: =+N44+P44 -> 22650.401 | T44: =+USM!U164 -> 9825.494 | U44: =+Q44+S44 -> 0 | V44: =+R44+T44 -> 32475.895 | X44: =+USM!Y164 -> 9271.39 | Z44: =+P44+T44+X44 -> 27223.453 | AB44: =+N44+Z44 -> 41747.285 | AD44: =+USM!AE164 -> 2320.602 | AE44: =+AA44+AC44 -> 0 | AF44: =+AB44+AD44 -> 44067.887 | AH44: =+USM!AI164 -> 6989.325 | AI44: =+AE44+AG44 -> 0 | AJ44: =+AF44+AH44 -> 51057.212 | AL44: =+USM!AM164 -> 10163.959 | AN44: =+AD44+AH44+AL44 -> 19473.886 | AO44: =+AK44+AM44 -> 0 | AP44: =AJ44+AL44 -> 61221.171 | AR44: =+USM!AS164 -> 7822.952 | AS44: =+AO44+AQ44 -> 0 | AT44: =+AP44+AR44 -> 69044.123 | AV44: =+USM!AW164 -> 7846.067 | AW44: =+AS44+AU44 -> 0 | AX44: =+AT44+AV44 -> 76890.19 | AZ44: =+USM!BA164 -> 4314.13 | BA44: =+AQ44+AU44+AY44 -> 0 | BB44: =+AR44+AV44+AZ44 -> 19983.149 | BC44: =AM44+BA44 -> 0 | BD44: =AN44+BB44 -> 39457.035 | BE44: =+AY44+BA44 -> 0 | BF44: =AX44+AZ44 -> 81204.32 | BH44: 0 | BI44: 85233.119 | BJ44: 0 | BK44: 81214.697 | BL44: 0 | BM44: 86018.164 | BN44: 62409.791 | BP44: 44187.11 | BR44: 4414.219
B45: Angles | C45: Mt | F45: =+USM!G165 -> 2238.924 | H45: =+USM!I165 -> 0 | I45: =+E45+G45 -> 0 | J45: =+F45+H45 -> 2238.924 | L45: =+USM!M165 -> 1992.848 | N45: =+F45+H45+L45 -> 4231.772 | P45: =+USM!Q165 -> 0 | Q45: =+M45+O45 -> 0 | R45: =+N45+P45 -> 4231.772 | T45: =+USM!U165 -> 468.21 | U45: =+Q45+S45 -> 0 | V45: =+R45+T45 -> 4699.982 | X45: =+USM!Y165 -> 0 | Z45: =+P45+T45+X45 -> 468.21 | AB45: =+N45+Z45 -> 4699.982 | AD45: =+USM!AE165 -> 0 | AE45: =+AA45+AC45 -> 0 | AF45: =+AB45+AD45 -> 4699.982 | AH45: =+USM!AI165 -> 0 | AI45: =+AE45+AG45 -> 0 | AJ45: =+AF45+AH45 -> 4699.982 | AL45: =+USM!AM165 -> 0 | AN45: =+AD45+AH45+AL45 -> 0 | AO45: =+AK45+AM45 -> 0 | AP45: =AJ45+AL45 -> 4699.982 | AR45: =+USM!AS165 -> 0 | AS45: =+AO45+AQ45 -> 0 | AT45: =+AP45+AR45 -> 4699.982 | AV45: =+USM!AW165 -> 0 | AW45: =+AS45+AU45 -> 0 | AX45: =+AT45+AV45 -> 4699.982 | AZ45: =+USM!BA165 -> 0 | BA45: =+AQ45+AU45+AY45 -> 0 | BB45: =+AR45+AV45+AZ45 -> 0 | BC45: =AM45+BA45 -> 0 | BD45: =AN45+BB45 -> 0 | BE45: =+AY45+BA45 -> 0 | BF45: =AX45+AZ45 -> 4699.982 | BH45: 0 | BI45: 2461.058 | BJ45: 0 | BK45: 1529.844 | BL45: 0 | BM45: 2887.321 | BN45: 4159.184 | BP45: 919.55454 | BR45: 5739.5256
B46: Beam | C46: Mt | F46: =+USM!G166 -> 1617.461 | H46: =+USM!I166 -> 0 | J46: =+F46+H46 -> 1617.461 | L46: =+USM!M166 -> 0 | N46: =+F46+H46+L46 -> 1617.461 | P46: =+USM!Q166 -> 15.713 | R46: =+N46+P46 -> 1633.174 | T46: =+USM!U166 -> 0 | V46: =+R46+T46 -> 1633.174 | X46: =+USM!Y166 -> 1199.047 | Z46: =+P46+T46+X46 -> 1214.76 | AB46: =+N46+Z46 -> 2832.221 | AD46: =+USM!AE166 -> 992.236 | AF46: =+AB46+AD46 -> 3824.457 | AH46: =+USM!AI166 -> 1383.221 | AJ46: =+AF46+AH46 -> 5207.678 | AL46: =+USM!AM166 -> 3758.02 | AN46: =+AD46+AH46+AL46 -> 6133.477 | AP46: =AJ46+AL46 -> 8965.698 | AR46: =+USM!AS166 -> 2622.34 | AT46: =+AP46+AR46 -> 11588.038 | AV46: =+USM!AW166 -> 0 | AX46: =+AT46+AV46 -> 11588.038 | AZ46: =+USM!BA166 -> 1750.001 | BA46: =+AQ46+AU46+AY46 -> 0 | BB46: =+AR46+AV46+AZ46 -> 4372.341 | BC46: =AM46+BA46 -> 0 | BD46: =AN46+BB46 -> 10505.818 | BE46: =AW46+AY46 -> 0 | BF46: =AX46+AZ46 -> 13338.039 | BH46: 0 | BI46: 11720.578
B47: Column | C47: Mt | F47: =+USM!G167 -> 954.718 | H47: =+USM!I167 -> 0 | J47: =+USM!K167 -> 954.718 | L47: =+USM!M167 -> 2649.675 | N47: =+USM!O167 -> 3604.393 | P47: =+USM!Q167 -> 2830.994 | R47: =+N47+P47 -> 6435.387 | T47: =+USM!U167 -> 2612.658 | V47: =+R47+T47 -> 9048.045 | X47: =+USM!Y167 -> 1543.802 | Z47: =+P47+T47+X47 -> 6987.454 | AB47: =+N47+Z47 -> 10591.847 | AD47: =+USM!AE167 -> 0 | AF47: =+AB47+AD47 -> 10591.847 | AH47: =+USM!AI167 -> 1341.975 | AJ47: =+AF47+AH47 -> 11933.822 | AL47: =+USM!AM167 -> 0 | AN47: =+AD47+AH47+AL47 -> 1341.975 | AP47: =AJ47+AL47 -> 11933.822 | AR47: =+USM!AS167 -> 4298.626 | AT47: =+AP47+AR47 -> 16232.448 | AV47: =+USM!AW167 -> 0 | AX47: =+AT47+AV47 -> 16232.448 | AZ47: =+USM!BA167 -> 2231.753 | BA47: =+AQ47+AU47+AY47 -> 0 | BB47: =+AR47+AV47+AZ47 -> 6530.379 | BC47: =AM47+BA47 -> 0 | BD47: =AN47+BB47 -> 7872.354 | BE47: =AW47+AY47 -> 0 | BF47: =AX47+AZ47 -> 18464.201 | BH47: 0 | BI47: 17509.483
B48: Semis | C48: Mt | D48: =+D36 -> 350000.4 | E48: =+E36 -> 20999.957 | F48: =+F36 -> 40008.1 | G48: =+G36 -> 0.49149549 | H48: =+H36 -> 23098.46 | I48: =+I36 -> 21000.449 | J48: =+J36 -> 63106.56 | K48: =+K36 -> 48000.111 | L48: =+L36 -> 57284 | M48: =+E48+G48+K48 -> 69000.559 | N48: =+F48+H48+L48 -> 120390.56 | O48: =+O36 -> 43500.141 | P48: =+P36 -> 50766 | Q48: =+Q36 -> 112500.7 | R48: =+R36 -> 171156.56 | S48: =+S36 -> 43500.141 | T48: =+T36 -> 60047.19 | U48: =+U36 -> 156000.84 | V48: =+V36 -> 231203.75 | ... AA48: =+AA36 -> 171300.86 | AB48: =+N48+Z48 -> 286693.75 | AC48: =+AC36 -> 48999.528 | AD48: =+AD36 -> 65807 | AE48: =+AE36 -> 220300.39 | AF48: =+AF36 -> 352500.75 | AG48: =+AG36 -> 45499.588 | AH48: =+AH36 -> 61080 | AI48: =+AI36 -> 265799.97 | AJ48: =+AJ36 -> 413580.75 | ... AN48: =+AN36 -> 179938 | AO48: =AI48+AK48 -> 311800.03 | AP48: =AJ48+AL48 -> 466631.75 | AQ48: =+AQ36 -> 48499.665 | AR48: =+AR36 -> 37998 | AS48: =+AS36 -> 360299.69 | AT48: =+AT36 -> 504629.75 | AU48: =+AU36 -> 41500.01 | AV48: =+AV36 -> 18442 | AW48: =+AW36 -> 401799.7 | AX48: =+AX36 -> 523071.75 | ... AZ48: =+AZ36 -> 42319.899 | BA48: =+AQ48+AU48+AY48 -> 136999.37 | BB48: =+AR48+AV48+AZ48 -> 98759.899 | BC48: =AM48+BA48 -> 277498.54 | BD48: =AN48+BB48 -> 278697.9 | BE48: =AW48+AY48 -> 448799.39 | BF48: =AX48+AZ48 -> 565391.65 | BH48: 524798.34 | BI48: 603457.68 | BJ48: 479999.56 | BK48: 622038.3 | BL48: 649999.92 | BM48: 676651.51 | BN48: 711198.96 | BO48: 669999.11 | BP48: 832014.92 | BQ48: =+BQ36 -> 904433.83 | BR48: 937874.53 | BS48: 571999.74 | BT48: =+BT36 -> 877839.96
B49: TOTAL SALEABLE STEEL | C49: Mt | D49: =SUM(D39:D48) -> 2710000.4 | E49: =SUM(E39:E48) -> 181999.96 | F49: =SUM(F39:F48) -> 208722.19 | G49: =SUM(G39:G48) -> 168000.49 | H49: =SUM(H39:H48) -> 88350.248 | I49: =SUM(I39:I48) -> 350000.45 | J49: =SUM(J39:J48) -> 297072.44 | K49: =SUM(K39:K48) -> 229000.11 | ... BF49: =SUM(BF39:BF48) -> 2474702.2 | BH49: 2674798.3 | BI49: 2604730.3 | BJ49: 2409999.6 | BK49: 2331824 | BL49: 2524999.9 | BM49: 2409644.1 | BN49: 2315208 | BO49: =SUM(BO39:BO48) -> 2369999.1 | BP49: =SUM(BP39:BP48) -> 2160425.8 | BQ49: =SUM(BQ39:BQ48) -> 2235274.9 | BR49: =SUM(BR39:BR48) -> 1823883.8 | BS49: =SUM(BS39:BS48) -> 2406999.7 | BT49: =SUM(BT39:BT48) -> 2093720.2
B50: COAL TAR | C50: Mt | D50: 42110.938 | E50: 3555.1789 | F50: 3446.42 | G50: 3555.1789 | H50: 3428.96 | I50: =+E50+G50 -> 7110.3577 | J50: =+F50+H50 -> 6875.38 | K50: 3531.525 | L50: 3463.07 | M50: =+E50+G50+K50 -> 10641.883 | N50: =+F50+H50+L50 -> 10338.45 | O50: 3649.2425 | P50: 3586.12 | Q50: =+M50+O50 -> 14291.125 | R50: =+N50+P50 -> 13924.57 | S50: 3649.2425 | T50: 3608.69 | U50: =+Q50+S50 -> 17940.368 | V50: =+R50+T50 -> 17533.26 | W50: 3400.5337 | X50: 3497.87 | Y50: =+O50+S50+W50 -> 10699.019 | Z50: =+P50+T50+X50 -> 10692.68 | AA50: =+M50+Y50 -> 21340.901 | AB50: =+N50+Z50 -> 21031.13 | AC50: 3649.2425 | AD50: 3405.82 | AE50: =+AA50+AC50 -> 24990.144 | AF50: =+AB50+AD50 -> 24436.95 | AG50: 3531.525 | AH50: 3215 | AI50: =+AE50+AG50 -> 28521.669 | AJ50: =+AF50+AH50 -> 27651.95 | AK50: 3649.2425 | AL50: 3251.75 | AM50: =+AC50+AG50+AK50 -> 10830.01 | AN50: =+AD50+AH50+AL50 -> 9872.57 | AO50: =AI50+AK50 -> 32170.911 | AP50: =AJ50+AL50 -> 30903.7 | AQ50: 3649.2425 | AR50: 3434.68 | AS50: =+AO50+AQ50 -> 35820.154 | AT50: =+AP50+AR50 -> 34338.38 | AU50: 3296.09 | AV50: 3170.67 | AW50: =+AS50+AU50 -> 39116.244 | AX50: =+AT50+AV50 -> 37509.05 | AY50: 3649.2425 | AZ50: 3562.08 | BA50: =+AQ50+AU50+AY50 -> 10594.575 | BB50: =+AR50+AV50+AZ50 -> 10167.43 | BC50: =AM50+BA50 -> 21424.585 | BD50: =AN50+BB50 -> 20040 | BE50: =AW50+AY50 -> 42765.486 | BF50: =AX50+AZ50 -> 41071.13 | BH50: 42940.816 | BI50: 41221.32 | BJ50: 46866.669 | BK50: 43164.837 | BL50: 50890.946 | BM50: 44869.641 | BN50: 48878.17 | BO50: 51086.383 | BP50: 49592.55 | BQ50: 48584.311 | BR50: 46678.95 | BS50: 46118.873 | BT50: 49237.57
B51: AMMONIUM SULPHATE | C51: Mt | D51: 10785.097 | E51: 917.00899 | F51: 553 | G51: 917.00899 | H51: 667.8 | I51: =+E51+G51 -> 1834.018 | J51: =+F51+H51 -> 1220.8 | K51: 816.31144 | L51: 494.65 | M51: =+E51+G51+K51 -> 2650.3294 | N51: =+F51+H51+L51 -> 1715.45 | O51: 845.46542 | P51: 717.5 | Q51: =+M51+O51 -> 3495.7948 | R51: =+N51+P51 -> 2432.95 | S51: 845.46542 | T51: 586.55 | U51: =+Q51+S51 -> 4341.2603 | V51: =+R51+T51 -> 3019.5 | W51: 790.46478 | X51: 519.6 | Y51: =+O51+S51+W51 -> 2481.3956 | Z51: =+P51+T51+X51 -> 1823.65 | AA51: =+M51+Y51 -> 5131.725 | AB51: =+N51+Z51 -> 3539.1 | AC51: 376.59342 | AD51: 502.5 | AE51: =+AA51+AC51 -> 5508.3185 | AF51: =+AB51+AD51 -> 4041.6 | AG51: 452.704 | AH51: 384 | AI51: =+AE51+AG51 -> 5961.0225 | AJ51: =+AF51+AH51 -> 4425.6 | AK51: 845.46542 | AL51: 573.8 | AM51: =+AC51+AG51+AK51 -> 1674.7628 | AN51: =+AD51+AH51+AL51 -> 1460.3 | AO51: =AI51+AK51 -> 6806.4879 | AP51: =AJ51+AL51 -> 4999.4 | AQ51: 845.46542 | AR51: 682.35 | AS51: =+AO51+AQ51 -> 7651.9533 | AT51: =+AP51+AR51 -> 5681.75 | AU51: 758.00348 | AV51: 478.4 | AW51: =+AS51+AU51 -> 8409.9568 | AX51: =+AT51+AV51 -> 6160.15 | AY51: 845.46542 | AZ51: 412.2 | BA51: =+AQ51+AU51+AY51 -> 2448.9343 | BB51: =+AR51+AV51+AZ51 -> 1572.95 | BC51: =AM51+BA51 -> 4123.6972 | BD51: =AN51+BB51 -> 3033.25 | BE51: =AW51+AY51 -> 9255.4222 | BF51: =AX51+AZ51 -> 6572.35 | BH51: 9122.3971 | BI51: 6514.05 | BJ51: 9348.2026 | BK51: 4897.75 | BL51: 8145.2 | BM51: 16578.809 | BN51: 8876.9 | BO51: 21728.852 | BP51: 10510.61 | BQ51: 15654.415 | BR51: 12312.8
B53: Total casts | C53: No | D53: 18060.988 | E53: 1241.6099 | F53: 1418 | G53: 1095.5382 | H53: 628 | I53: =+E53+G53 -> 2337.1481 | J53: =+F53+H53 -> 2046 | K53: 1580.7365 | L53: 1556 | M53: =+E53+G53+K53 -> 3917.8846 | N53: =+F53+H53+L53 -> 3602 | O53: 1599.6223 | P53: 1610 | Q53: =+M53+O53 -> 5517.5069 | R53: =+N53+P53 -> 5212 | S53: 1599.6223 | T53: 1515 | U53: =+Q53+S53 -> 7117.1292 | V53: =+R53+T53 -> 6727 | W53: 839.4712 | X53: 1448 | Y53: =+O53+S53+W53 -> 4038.7158 | Z53: =+P53+T53+X53 -> 4573 | AA53: =+M53+Y53 -> 7956.6004 | AB53: =+N53+Z53 -> 8175 | AC53: 1631.0985 | AD53: 1145 | AE53: =+AA53+AC53 -> 9587.6989 | AF53: =+AB53+AD53 -> 9320 | AG53: 1580.7365 | AH53: 1457 | AI53: =+AE53+AG53 -> 11168.435 | AJ53: =+AF53+AH53 -> 10777 | AK53: 1631.0985 | AL53: 1504 | AM53: =+AC53+AG53+AK53 -> 4842.9336 | AN53: =+AD53+AH53+AL53 -> 4106 | AO53: =AI53+AK53 -> 12799.534 | AP53: =AJ53+AL53 -> 12281 | AQ53: 1656.2795 | AR53: 1461 | AS53: =+AO53+AQ53 -> 14455.814 | AT53: =+AP53+AR53 -> 13742 | AU53: 1480.0126 | AV53: 1185 | AW53: =+AS53+AU53 -> 15935.826 | AX53: =+AT53+AV53 -> 14927 | AY53: 1656.2795 | AZ53: 1526 | BA53: =+AQ53+AU53+AY53 -> 4792.5716 | BB53: =+AR53+AV53+AZ53 -> 4172 | BC53: =AM53+BA53 -> 9635.5052 | BD53: =AN53+BB53 -> 8278 | BE53: =AW53+AY53 -> 17592.106 | BF53: =AX53+AZ53 -> 16453 | BH53: 18466.793 | BI53: 17246 | BJ53: 16596.855 | BK53: 15925 | BL53: 16116 | BM53: 16344.715 | BN53: 14624 | BO53: 15300.817 | BP53: 12158 | BQ53: 16891.892 | BR53: 14151
E55: =+E37-E49 -> 0 | F55: =+F37-F49 -> 0 | G55: =+G37-G49 -> 0 | H55: =+H37-H49 -> 0 | I55: =+I37-I49 -> 0 | J55: =+J37-J49 -> 0 | K55: =+K37-K49 -> 0 | L55: =+L37-L49 -> 0 | ... BF55: =+BF37-BF49 -> 0 | BH55: 0 | BI55: 0 | BJ55: 0 | BK55: 0 | BL55: -0.01296 | BM55: =+BO37-BO49 -> 0 | BN55: =+BP37-BP49 -> -0.00039024325 | BO55: =+BQ37-BQ49 -> 0 | BP55: =+BR37-BR49 -> 0.55446018 | BQ55: =+BS37-BS49 -> 0 | BR55: =+BT37-BT49 -> 0

Sheet Maj Despatch Summ
B1: MAJOR DESPATCH SUMMARY 2025-26 (As per Finance CENVAT report)
E2: 30 | F2: 30 | G2: 31 | H2: 31 | I2: =+G2+E2 -> 61 | J2: =+H2+F2 -> 61 | K2: 30 | L2: 30 | M2: =+E2+G2+K2 -> 91 | N2: =+F2+H2+L2 -> 91 | O2: 31 | P2: 31 | Q2: =+M2+O2 -> 122 | R2: =+N2+P2 -> 122 | S2: 31 | T2: 31 | U2: =+Q2+S2 -> 153 | V2: =+R2+T2 -> 153 | W2: 30 | X2: 30 | Y2: =+O2+S2+W2 -> 92 | Z2: =+P2+T2+X2 -> 92 | AA2: =+M2+Y2 -> 183 | AB2: =+N2+Z2 -> 183 | AC2: 31 | AD2: 31 | AE2: =AA2+AC2 -> 214 | AF2: =AB2+AD2 -> 214 | AG2: 30 | AH2: 30 | AI2: =AE2+AG2 -> 244 | AJ2: =AF2+AH2 -> 244 | AK2: 31 | AL2: 31 | AM2: =+AC2+AG2+AK2 -> 92 | AN2: =+AD2+AH2+AL2 -> 92 | AO2: =AI2+AK2 -> 275 | AP2: =AJ2+AL2 -> 275 | AQ2: 31 | AR2: 31 | AS2: =AO2+AQ2 -> 306 | AT2: =AP2+AR2 -> 306 | AU2: 28 | AV2: 28 | AW2: =AS2+AU2 -> 334 | AX2: =AT2+AV2 -> 334 | AY2: 31 | AZ2: 31 | BA2: =+AQ2+AU2+AY2 -> 90 | BB2: =+AR2+AV2+AZ2 -> 90 | BC2: =AM2+BA2 -> 182 | BD2: =AN2+BB2 -> 182 | BE2: =AW2+AY2 -> 365 | BF2: =AX2+AZ2 -> 365 | BR2: 365 | BS2: 365 | BT2: 366 | BU2: 366
B3: ITEM | C3: Unit | D3: 2026-27 ABP | E3: Apr'26 | G3: May'26 | I3: 2M | K3: Jun'25 | M3: QTR-1 | O3: Jul'25 | Q3: 4M | S3: Aug'25 | U3: 5M | W3: Sep'25 | Y3: QTR-2 | AA3: H1 | AC3: Oct'25 | AE3: 7M | AG3: Nov'25 | AI3: 8M | AK3: Dec'25 | AM3: QTR-3 | AO3: 9M | AQ3: Jan'26 | AS3: 10M | AU3: Feb'26 | AW3: 11M | AY3: Mar'26 | BA3: QTR-4 | BC3: H2 | BE3: 2026-27 | BH3: 2025-26 | BJ3: 2024-25 | BL3: 2023-24 | BN3: 2022-23 | BP3: 2021-22 | BR3: 2020-21 | BT3: 2019-20
E4: ABP | F4: ACT | G4: ABP | H4: ACT | I4: ABP | J4: ACT | K4: ABP | L4: ACT | M4: ABP | N4: ACT | O4: ABP | P4: ACT | Q4: ABP | R4: ACT | S4: ABP | T4: ACT | U4: ABP | V4: ACT | W4: ABP | X4: ACT | Y4: ABP | Z4: ACT | AA4: ABP | AB4: ACT | AC4: ABP | AD4: ACT | AE4: ABP | AF4: ACT | AG4: ABP | AH4: ACT | AI4: ABP | AJ4: ACT | AK4: ABP | AL4: ACT | AM4: ABP | AN4: ACT | AO4: ABP | AP4: ACT | AQ4: ABP | AR4: ACT | AS4: ABP | AT4: ACT | AU4: ABP | AV4: ACT | AW4: ABP | AX4: ACT | AY4: ABP | AZ4: ACT | BA4: ABP | BB4: ACT | BC4: ABP | BD4: ACT | BE4: ABP | BF4: ACT | BH4: ABP | BI4: ACT | BJ4: ABP | BK4: ACT | BL4: ABP | BM4: ACT | BN4: ABP | BO4: ACT | BP4: ABP | BQ4: ACT | BR4: ABP | BS4: ACT | BT4: ABP | BU4: ACT
B5: Saleable Steel (mill-wise)
B6: MKTG-Plant sales | C6: MT | D6: 16000 | E6: 83 | F6: 5965.35 | G6: 83 | H6: 1783.23 | I6: =+E6+G6 -> 166 | J6: =+F6+H6 -> 7748.58 | K6: 2083.3333 | L6: 6803.81 | M6: =+E6+G6+K6 -> 2249.3333 | N6: =+F6+H6+L6 -> 14552.39 | O6: 2083.3333 | P6: 3865.36 | Q6: =+M6+O6 -> 4332.6667 | R6: =+N6+P6 -> 18417.75 | S6: 2083.3333 | T6: 6257.93 | U6: =+Q6+S6 -> 6416 | V6: =+R6+T6 -> 24675.68 | W6: 2083 | X6: 5182.59 | Y6: =+O6+S6+W6 -> 6249.6667 | Z6: =+P6+T6+X6 -> 15305.88 | AA6: =+M6+Y6 -> 8499 | AB6: =+N6+Z6 -> 29858.27 | AC6: =83.3333333333333+2000 -> 2083.3333 | AD6: 5221.92 | AE6: =+AA6+AC6 -> 10582.333 | AF6: =+AB6+AD6 -> 35080.19 | AG6: 2083.3333 | AH6: 0 | AI6: =+AE6+AG6 -> 12665.667 | AJ6: =+AF6+AH6 -> 35080.19 | AK6: 2083.3333 | AL6: 2960.73 | AM6: =+AC6+AG6+AK6 -> 6250 | AN6: =+AD6+AH6+AL6 -> 8182.65 | AO6: =AI6+AK6 -> 14749 | AP6: =AJ6+AL6 -> 38040.92 | AQ6: 2083.3333 | AR6: 6204.61 | AS6: =+AO6+AQ6 -> 16832.333 | AT6: =+AP6+AR6 -> 44245.53 | AU6: 2083.3333 | AV6: 3912.15 | AW6: =+AS6+AU6 -> 18915.667 | AX6: =+AT6+AV6 -> 48157.68 | AY6: 2083.3333 | AZ6: 3740.4 | BA6: =+AQ6+AU6+AY6 -> 6250 | BB6: =+AR6+AV6+AZ6 -> 13857.16 | BC6: =AM6+BA6 -> 12500 | BD6: =AN6+BB6 -> 22039.81 | BE6: =+AW6+AY6 -> 20999 | BF6: =+AX6+AZ6 -> 51898.08 | BH6: 24999.667 | BI6: 47950.34 | BJ6: 21500 | BK6: 53987.54 | BL6: 21500 | BM6: 30649.84 | BN6: 25500 | BO6: 34807.22 | BP6: 16050 | BQ6: 33201.15 | BR6: 0 | BS6: 35268.25 | BT6: 2000 | BU6: 28405.85
B7: IPT | C7: MT | D7: 0 | E7: 0 | F7: 0 | G7: 0 | H7: 3857.66 | I7: =+E7+G7 -> 0 | J7: =+F7+H7 -> 3857.66 | K7: 0 | L7: 0 | M7: =+E7+G7+K7 -> 0 | N7: =+F7+H7+L7 -> 3857.66 | O7: 0 | P7: 64.1 | Q7: =+M7+O7 -> 0 | R7: =+N7+P7 -> 3921.76 | S7: 0 | T7: 1485.16 | U7: =+Q7+S7 -> 0 | V7: =+R7+T7 -> 5406.92 | W7: 0 | X7: 694 | Y7: =+O7+S7+W7 -> 0 | Z7: =+P7+T7+X7 -> 2243.26 | AA7: =+M7+Y7 -> 0 | AB7: =+N7+Z7 -> 6100.92 | AC7: 0 | AD7: 747.82 | AE7: =+AA7+AC7 -> 0 | AF7: =+AB7+AD7 -> 6848.74 | AG7: 0 | AH7: 0 | AI7: =+AE7+AG7 -> 0 | AJ7: =+AF7+AH7 -> 6848.74 | AK7: 0 | AL7: 244.1 | AM7: =+AC7+AG7+AK7 -> 0 | AN7: =+AD7+AH7+AL7 -> 991.92 | AO7: =AI7+AK7 -> 0 | AP7: =AJ7+AL7 -> 7092.84 | AQ7: 0 | AR7: 0 | AS7: =+AO7+AQ7 -> 0 | AT7: =+AP7+AR7 -> 7092.84 | AU7: 0 | AV7: 2333.64 | AW7: =+AS7+AU7 -> 0 | AX7: =+AT7+AV7 -> 9426.48 | AY7: 0 | AZ7: 2066.9 | BA7: =+AQ7+AU7+AY7 -> 0 | BB7: =+AR7+AV7+AZ7 -> 4400.54 | BC7: =AM7+BA7 -> 0 | BD7: =AN7+BB7 -> 5392.46 | BE7: =+AW7+AY7 -> 0 | BF7: =+AX7+AZ7 -> 11493.38 | BH7: 0 | BI7: 7635.72 | BJ7: 0 | BK7: 322.72 | BL7: 0 | BM7: 3076.2 | BN7: 123000 | BO7: 42263.08 | BP7: 0 | BQ7: 71707.42 | BR7: 10800 | BS7: 9758.51 | BT7: 24210 | BU7: 5928.095
B8: CMO-WR MILL | C8: MT | D8: 519000 | E8: 36417 | F8: 41076.23 | G8: 37417 | H8: 28878.062 | I8: =+E8+G8 -> 73834 | J8: =+F8+H8 -> 69954.292 | K8: 42416.667 | L8: 37508.06 | M8: =+E8+G8+K8 -> 116250.67 | N8: =+F8+H8+L8 -> 107462.35 | O8: 43916.667 | P8: 44133.19 | Q8: =+M8+O8 -> 160167.33 | R8: =+N8+P8 -> 151595.54 | S8: 43916.667 | T8: 40726.54 | U8: =+Q8+S8 -> 204084 | V8: =+R8+T8 -> 192322.08 | W8: 24916.667 | X8: 36332.97 | Y8: =+O8+S8+W8 -> 112750 | Z8: =+P8+T8+X8 -> 121192.7 | AA8: =+M8+Y8 -> 229000.67 | AB8: =+N8+Z8 -> 228655.05 | AC8: 42416.667 | AD8: 31032.3 | AE8: =+AA8+AC8 -> 271417.33 | AF8: =+AB8+AD8 -> 259687.35 | AG8: 42416.667 | AH8: 38334.736 | AI8: =+AE8+AG8 -> 313834 | AJ8: =+AF8+AH8 -> 298022.09 | AK8: 43916.667 | AL8: 41187.81 | AM8: =+AC8+AG8+AK8 -> 128750 | AN8: =+AD8+AH8+AL8 -> 110554.85 | AO8: =AI8+AK8 -> 357750.67 | AP8: =AJ8+AL8 -> 339209.9 | AQ8: 44416.667 | AR8: 39752.561 | AS8: =+AO8+AQ8 -> 402167.33 | AT8: =+AP8+AR8 -> 378962.46 | AU8: 39916.667 | AV8: 41871.84 | AW8: =+AS8+AU8 -> 442084 | AX8: =+AT8+AV8 -> 420834.3 | AY8: 44416.667 | AZ8: 48073.32 | BA8: =+AQ8+AU8+AY8 -> 128750 | BB8: =+AR8+AV8+AZ8 -> 129697.72 | BC8: =AM8+BA8 -> 257500 | BD8: =AN8+BB8 -> 240252.57 | BE8: =+AW8+AY8 -> 486500.67 | BF8: =+AX8+AZ8 -> 468907.62 | BH8: 499000 | BI8: 471653.15 | BJ8: 498500 | BK8: 459216.41 | BL8: 498500 | BM8: 473494.21 | BN8: 498500 | BO8: 453432.75 | BP8: 498500 | BQ8: 467953.64 | BR8: 435166.29 | BS8: 351267.02 | BT8: 498000 | BU8: 399090.26
B9: CMO-BAR MILL | C9: MT | D9: 990000 | E9: 68500 | F9: 78698.73 | G9: 71000 | H9: 35387.67 | I9: =+E9+G9 -> 139500 | J9: =+F9+H9 -> 114086.4 | K9: 76000 | L9: 73175.63 | M9: =+E9+G9+K9 -> 215500 | N9: =+F9+H9+L9 -> 187262.03 | O9: 79000 | P9: 84102.5 | Q9: =+M9+O9 -> 294500 | R9: =+N9+P9 -> 271364.53 | S9: 79000 | T9: 86905.93 | U9: =+Q9+S9 -> 373500 | V9: =+R9+T9 -> 358270.46 | W9: 47500 | X9: 68689.99 | Y9: =+O9+S9+W9 -> 205500 | Z9: =+P9+T9+X9 -> 239698.42 | AA9: =+M9+Y9 -> 421000 | AB9: =+N9+Z9 -> 426960.45 | AC9: 78000 | AD9: 52260.41 | AE9: =+AA9+AC9 -> 499000 | AF9: =+AB9+AD9 -> 479220.86 | AG9: 76000 | AH9: 70091.169 | AI9: =+AE9+AG9 -> 575000 | AJ9: =+AF9+AH9 -> 549312.03 | AK9: 79000 | AL9: 83237.28 | AM9: =+AC9+AG9+AK9 -> 233000 | AN9: =+AD9+AH9+AL9 -> 205588.86 | AO9: =AI9+AK9 -> 654000 | AP9: =AJ9+AL9 -> 632549.31 | AQ9: 79000 | AR9: 79536.07 | AS9: =+AO9+AQ9 -> 733000 | AT9: =+AP9+AR9 -> 712085.38 | AU9: 71500 | AV9: 77559.29 | AW9: =+AS9+AU9 -> 804500 | AX9: =+AT9+AV9 -> 789644.67 | AY9: 80000 | AZ9: 81642.31 | BA9: =+AQ9+AU9+AY9 -> 230500 | BB9: =+AR9+AV9+AZ9 -> 238737.67 | BC9: =AM9+BA9 -> 463500 | BD9: =AN9+BB9 -> 444326.53 | BE9: =+AW9+AY9 -> 884500 | BF9: =+AX9+AZ9 -> 871286.98 | BH9: 900000 | BI9: 884559.69 | BJ9: 870000 | BK9: 750184.19 | BL9: 850000 | BM9: 781402.45 | BN9: 780000 | BO9: 768402.31 | BP9: 750000 | BQ9: 648761.89 | BR9: 674874.74 | BS9: 436958.46 | BT9: 800000 | BU9: 612890.55
B10: CMO-US MILL | C10: MT | D10: 850000 | E10: 56000 | F10: 50540.923 | G10: 59500 | H10: 28795.449 | I10: =+E10+G10 -> 115500 | J10: =+F10+H10 -> 79336.372 | K10: 62500 | L10: 56720.68 | M10: =+E10+G10+K10 -> 178000 | N10: =+F10+H10+L10 -> 136057.05 | O10: 65000 | P10: 57264.83 | Q10: =+M10+O10 -> 243000 | R10: =+N10+P10 -> 193321.88 | S10: 65000 | T10: 47224.14 | U10: =+Q10+S10 -> 308000 | V10: =+R10+T10 -> 240546.02 | W10: 33500 | X10: 45948.12 | Y10: =+O10+S10+W10 -> 163500 | Z10: =+P10+T10+X10 -> 150437.09 | AA10: =+M10+Y10 -> 341500 | AB10: =+N10+Z10 -> 286494.14 | AC10: 67000 | AD10: 30215.88 | AE10: =+AA10+AC10 -> 408500 | AF10: =+AB10+AD10 -> 316710.02 | AG10: 65000 | AH10: 49444.75 | AI10: =+AE10+AG10 -> 473500 | AJ10: =+AF10+AH10 -> 366154.77 | AK10: 67500 | AL10: 51538.881 | AM10: =+AC10+AG10+AK10 -> 199500 | AN10: =+AD10+AH10+AL10 -> 131199.51 | AO10: =AI10+AK10 -> 541000 | AP10: =AJ10+AL10 -> 417693.65 | AQ10: 68000 | AR10: 55396.94 | AS10: =+AO10+AQ10 -> 609000 | AT10: =+AP10+AR10 -> 473090.59 | AU10: 61000 | AV10: 53071.49 | AW10: =+AS10+AU10 -> 670000 | AX10: =+AT10+AV10 -> 526162.08 | AY10: 68500 | AZ10: 58800.212 | BA10: =+AQ10+AU10+AY10 -> 197500 | BB10: =+AR10+AV10+AZ10 -> 167268.64 | BC10: =AM10+BA10 -> 397000 | BD10: =AN10+BB10 -> 298468.15 | BE10: =+AW10+AY10 -> 738500 | BF10: =+AX10+AZ10 -> 584962.29 | BH10: 750000 | BI10: 607464.62 | BJ10: 560000 | BK10: 502052.01 | BL10: 525000 | BM10: 452802.59 | BN10: 470000 | BO10: 357334.79 | BP10: 445000 | BQ10: 214319.65 | BR10: 220000 | BS10: 100400.4 | BT10: 535000 | BU10: 167166.99
B11: CMO-SEMIS | C11: MT | D11: 334999.99 | E11: 20999.684 | F11: 26141.36 | G11: 0 | H11: 20761.05 | I11: =+E11+G11 -> 20999.684 | J11: =+F11+H11 -> 46902.41 | K11: 46000.111 | L11: 44296.21 | M11: =+E11+G11+K11 -> 66999.795 | N11: =+F11+H11+L11 -> 91198.62 | O11: 41500.141 | P11: 54193.85 | Q11: =+M11+O11 -> 108499.94 | R11: =+N11+P11 -> 145392.47 | S11: 41500.141 | T11: 63719.03 | U11: =+Q11+S11 -> 150000.08 | V11: =+R11+T11 -> 209111.5 | W11: 13300.015 | X11: 50417.94 | Y11: =+O11+S11+W11 -> 96300.297 | Z11: =+P11+T11+X11 -> 168330.82 | AA11: =+M11+Y11 -> 163300.09 | AB11: =+N11+Z11 -> 259529.44 | AC11: 46999.528 | AD11: 54079.36 | AE11: =+AA11+AC11 -> 210299.62 | AF11: =+AB11+AD11 -> 313608.8 | AG11: 43499.588 | AH11: 63043.03 | AI11: =+AE11+AG11 -> 253799.21 | AJ11: =+AF11+AH11 -> 376651.83 | AK11: 44000.054 | AL11: 51546.68 | AM11: =+AC11+AG11+AK11 -> 134499.17 | AN11: =+AD11+AH11+AL11 -> 168669.07 | AO11: =AI11+AK11 -> 297799.26 | AP11: =AJ11+AL11 -> 428198.51 | AQ11: 46499.665 | AR11: 35800.43 | AS11: =+AO11+AQ11 -> 344298.93 | AT11: =+AP11+AR11 -> 463998.94 | AU11: 39500.01 | AV11: 12710.87 | AW11: =+AS11+AU11 -> 383798.94 | AX11: =+AT11+AV11 -> 476709.81 | AY11: 45000 | AZ11: 37056.46 | BA11: =+AQ11+AU11+AY11 -> 130999.68 | BB11: =+AR11+AV11+AZ11 -> 85567.76 | BC11: =AM11+BA11 -> 265498.85 | BD11: =AN11+BB11 -> 254236.83 | BE11: =+AW11+AY11 -> 428798.94 | BF11: =+AX11+AZ11 -> 513766.27 | BH11: 500798.65 | BI11: 554522.42 | BJ11: 459999.54 | BK11: 584980.47 | BL11: 630000.01 | BM11: 623466.17 | BN11: 513000.01 | BO11: 641816.63 | BP11: 659950.15 | BQ11: 742311.77 | BR11: 893633.78 | BS11: 944002.21 | BT11: 547789.74 | BU11: 836451
B12: TOTAL | C12: MT | D12: =SUM(D6:D11) -> 2710000 | E12: =SUM(E6:E11) -> 181999.68 | F12: =SUM(F6:F11) -> 202422.59 | G12: =SUM(G6:G11) -> 168000 | H12: =SUM(H6:H11) -> 119463.12 | I12: =SUM(I6:I11) -> 349999.68 | J12: =SUM(J6:J11) -> 321885.71 | K12: =SUM(K6:K11) -> 229000.11 | ... BF12: =SUM(BF6:BF11) -> 2502314.6 | BH12: 2674798.3 | BI12: 2573785.9 | BJ12: 2409999.5 | BK12: 2350743.3 | BL12: 2525000 | BM12: 2364891.5 | BN12: 2410000 | BO12: 2298056.8 | BP12: 2369500.2 | BQ12: 2178255.5 | BR12: 2234474.8 | BS12: 1877654.8 | BT12: 2406999.7 | BU12: 2049932.7
B13: Consideration in internal consumption | D13: Saleable production Plan: 2410000 (1500 T has been kept in plan for Internal consumption) | E13: Saleable production Plan: 201135 (200 T has been kept in plan for Internal consumption) | G13: Saleable production Plan: 201135 (200 T has been kept in plan for Internal consumption) | K13: Saleable production Plan: 201135 (200 T has been kept in plan for Internal consumption) | O13: Saleable production Plan: 201135 (200 T has been kept in plan for Internal consumption) | S13: Saleable production Plan: 201135 (200 T has been kept in plan for Internal consumption) | W13: Saleable production Plan: 201135 (200 T has been kept in plan for Internal consumption) | AC13: Saleable production Plan: 201135 (200 T has been kept in plan for Internal consumption) | AG13: Saleable production Plan: 201135 (200 T has been kept in plan for Internal consumption) | AK13: Saleable production Plan: 201135 (200 T has been kept in plan for Internal consumption) | AQ13: Saleable production Plan: 201135 (200 T has been kept in plan for Internal consumption) | AU13: Saleable production Plan: 201135 (200 T has been kept in plan for Internal consumption) | AY13: Saleable production Plan: 201135 (200 T has been kept in plan for Internal consumption)
B14: Saleable Steel (Sale type-wise)
B15: IPT | C15: MT | D15: =+D12 -> 2710000 | E15: =+E12 -> 181999.68 | F15: =+F7 -> 0 | G15: =+G12 -> 168000 | H15: =+H7 -> 3857.66 | I15: =+E15+G15 -> 349999.68 | J15: =+F15+H15 -> 3857.66 | K15: =+K12 -> 229000.11 | L15: =+L7 -> 0 | M15: =+E15+G15+K15 -> 578999.79 | N15: =+F15+H15+L15 -> 3857.66 | O15: =+O12 -> 231500.14 | P15: =+P7 -> 64.1 | Q15: =+M15+O15 -> 810499.94 | R15: =+N15+P15 -> 3921.76 | S15: =+S12 -> 231500.14 | T15: =+T7 -> 1485.16 | U15: =+Q15+S15 -> 1042000.1 | V15: =+R15+T15 -> 5406.92 | W15: =+W12 -> 121299.68 | X15: =+X7 -> 694 | Y15: =+O15+S15+W15 -> 584299.96 | Z15: =+P15+T15+X15 -> 2243.26 | AA15: =+M15+Y15 -> 1163299.8 | AB15: =+N15+Z15 -> 6100.92 | AC15: =+AC12 -> 236499.53 | AD15: =+AD7 -> 747.82 | AE15: =+AA15+AC15 -> 1399799.3 | AF15: =+AB15+AD15 -> 6848.74 | AG15: =+AG12 -> 228999.59 | AH15: =+AH7 -> 0 | AI15: =+AE15+AG15 -> 1628798.9 | AJ15: =+AF15+AH15 -> 6848.74 | AK15: =+AK12 -> 236500.05 | AL15: =+AL7 -> 244.1 | AM15: =+AC15+AG15+AK15 -> 701999.17 | AN15: =+AD15+AH15+AL15 -> 991.92 | AO15: =AI15+AK15 -> 1865298.9 | AP15: =AJ15+AL15 -> 7092.84 | AQ15: =+AQ12 -> 239999.66 | AR15: =+AR7 -> 0 | AS15: =+AO15+AQ15 -> 2105298.6 | AT15: =+AP15+AR15 -> 7092.84 | AU15: =+AU12 -> 214000.01 | AV15: =+AV7 -> 2333.64 | AW15: =+AS15+AU15 -> 2319298.6 | AX15: =+AT15+AV15 -> 9426.48 | AY15: =+AY12 -> 240000 | AZ15: =+AZ7 -> 2066.9 | BA15: =+AQ15+AU15+AY15 -> 693999.68 | BB15: =+AR15+AV15+AZ15 -> 4400.54 | BC15: =+AM15+BA15 -> 1395998.8 | BD15: =AN15+BB15 -> 5392.46 | BE15: =+AW15+AY15 -> 2559298.6 | BF15: =+AX15+AZ15 -> 11493.38 | BH15: 2674798.3 | BI15: 7635.72 | BJ15: 2409999.5 | BK15: 322.72 | BL15: 2525000 | BM15: 3076.2 | BN15: 2410000 | BO15: 42263.08 | BP15: 2369500.2 | BQ15: 71707.42 | BR15: 2234474.8 | BS15: 9758.51 | BT15: =+BT12 -> 2406999.7 | BU15: 5928.249
B16: CMO DIR | C16: MT | F16: 118626.72 | H16: 56864.99 | J16: =+F16+H16 -> 175491.71 | L16: 120386.74 | N16: =+F16+H16+L16 -> 295878.45 | P16: 136780.81 | R16: =+N16+P16 -> 432659.26 | T16: 149407.49 | V16: =+R16+T16 -> 582066.75 | X16: 118171.66 | Z16: =+P16+T16+X16 -> 404359.96 | AB16: =+N16+Z16 -> 700238.41 | AD16: 102074.34 | AF16: =+AB16+AD16 -> 802312.75 | AH16: 144101.09 | AJ16: =+AF16+AH16 -> 946413.84 | AL16: 155324.23 | AN16: =+AD16+AH16+AL16 -> 401499.66 | AP16: =AJ16+AL16 -> 1101738.1 | AR16: 154023.1 | AT16: =+AP16+AR16 -> 1255761.2 | AV16: 143472.91 | AX16: =+AT16+AV16 -> 1399234.1 | AZ16: 163014.04 | BB16: =+AR16+AV16+AZ16 -> 460510.05 | BD16: =AN16+BB16 -> 862009.71 | BF16: =+AX16+AZ16 -> 1562248.1 | BI16: 1647383.2 | BK16: 1620104.9 | BM16: 1443296 | BO16: 1325226.7 | BQ16: 1097093.1 | BS16: 691326.52 | BU16: 569419.83
B17: CMO SYD | C17: MT | F17: 74831.493 | H17: 53166.081 | J17: =+F17+H17 -> 127997.57 | L17: 91277.94 | N17: =+F17+H17+L17 -> 219275.51 | P17: 102874.62 | R17: =+N17+P17 -> 322150.13 | T17: 89009.36 | V17: =+R17+T17 -> 411159.49 | X17: 83127.57 | Z17: =+P17+T17+X17 -> 275011.55 | AB17: =+N17+Z17 -> 494287.06 | AD17: 62676.91 | AF17: =+AB17+AD17 -> 556963.97 | AH17: 73868.745 | AJ17: =+AF17+AH17 -> 630832.72 | AL17: 69474.281 | AN17: =+AD17+AH17+AL17 -> 206019.94 | AP17: =AJ17+AL17 -> 700307 | AR17: 53620.361 | AT17: =+AP17+AR17 -> 753927.36 | AV17: 41740.58 | AX17: =+AT17+AV17 -> 795667.94 | AZ17: 59773.862 | BB17: =+AR17+AV17+AZ17 -> 155134.8 | BD17: =AN17+BB17 -> 361154.74 | BF17: =+AX17+AZ17 -> 855441.8 | BI17: 849060.92 | BK17: 662107.03 | BM17: 829404.4 | BO17: 809005.31 | BQ17: 567271.22 | BS17: 479205.15 | BU17: 909567
B18: MKTG DIR | C18: MT | F18: =+F6 -> 5965.35 | H18: =+H6 -> 1783.23 | J18: =+F18+H18 -> 7748.58 | L18: =+L6 -> 6803.81 | N18: =+F18+H18+L18 -> 14552.39 | P18: =+P6 -> 3865.36 | R18: =+N18+P18 -> 18417.75 | T18: =+T6 -> 6257.93 | V18: =+R18+T18 -> 24675.68 | X18: =+X6 -> 5182.59 | Z18: =+P18+T18+X18 -> 15305.88 | AB18: =+N18+Z18 -> 29858.27 | AD18: =+AD6 -> 5221.92 | AF18: =+AB18+AD18 -> 35080.19 | AH18: =+AH6 -> 0 | AJ18: =+AF18+AH18 -> 35080.19 | AL18: =+AL6 -> 2960.73 | AN18: =+AD18+AH18+AL18 -> 8182.65 | AP18: =AJ18+AL18 -> 38040.92 | AR18: =+AR6 -> 6204.61 | AT18: =+AP18+AR18 -> 44245.53 | AV18: =+AV6 -> 3912.15 | AX18: =+AT18+AV18 -> 48157.68 | AZ18: =+AZ6 -> 3740.4 | BB18: =+AR18+AV18+AZ18 -> 13857.16 | BD18: =AN18+BB18 -> 22039.81 | BF18: =+AX18+AZ18 -> 51898.08 | BI18: 47950.34 | BK18: 53987.54 | BM18: 30649.84 | BO18: 34807.22 | BQ18: 33201.15 | BS18: 35268.25 | BU18: 28405.85
B19: EXPORT | C19: MT | F19: 2999.03 | H19: 3791.16 | J19: =+F19+H19 -> 6790.19 | L19: 35.9 | N19: =+F19+H19+L19 -> 6826.09 | P19: 38.94 | R19: =+N19+P19 -> 6865.03 | T19: 158.79 | V19: =+R19+T19 -> 7023.82 | X19: 89.79 | Z19: =+P19+T19+X19 -> 287.52 | AB19: =+N19+Z19 -> 7113.61 | AD19: 2836.7 | AF19: =+AB19+AD19 -> 9950.31 | AH19: 2943.85 | AJ19: =+AF19+AH19 -> 12894.16 | AL19: 2712.14 | AN19: =+AD19+AH19+AL19 -> 8492.69 | AP19: =AJ19+AL19 -> 15606.3 | AR19: 2842.54 | AT19: =+AP19+AR19 -> 18448.84 | AV19: 0 | AX19: =+AT19+AV19 -> 18448.84 | AZ19: 2784.4 | BB19: =+AR19+AV19+AZ19 -> 5626.94 | BD19: =AN19+BB19 -> 14119.63 | BF19: =+AX19+AZ19 -> 21233.24 | BI19: 21755.74 | BK19: 14221 | BM19: 58464.99 | BO19: 86754.52 | BQ19: 408982.58 | BS19: 662096.98 | BU19: 536611.98
B20: % DIRECT (IPT+CMO DIR+ EXPORT+ PLANT SALES) | C20: % | F20: =+((F16+F18+F15+F19)/F12)*100 -> 63.032045 | H20: =+((H16+H18+H15+H19)/H12)*100 -> 55.495821 | J20: =+((+J15+J16+J18+J19)/J12)*100 -> 60.235087 | L20: =+((L16+L18+L15+L19)/L12)*100 -> 58.226038 | N20: =+((+N15+N16+N18+N19)/N12)*100 -> 59.422737 | P20: =+((P16+P18+P15+P19)/P12)*100 -> 57.77317 | R20: =+((+R15+R16+R18+R19)/R12)*100 -> 58.910152 | T20: =+((T16+T18+T15+T19)/T12)*100 -> 63.864153 | V20: =+((+V15+V16+V18+V19)/V12)*100 -> 60.094491 | X20: =+((X16+X18+X15+X19)/X12)*100 -> 59.893216 | Z20: =+((Z16+Z18+Z15+Z19)/Z12)*100 -> 60.555317 | AB20: =+((AB16+AB18+AB15+AB19)/AB12)*100 -> 60.060783 | AD20: =+((AD16+AD18+AD15+AD19)/AD12)*100 -> 63.886988 | AF20: =+((+AF15+AF16+AF18+AF19)/AF12)*100 -> 60.531367 | AH20: =+((AH16+AH18+AH15+AH19)/AH12)*100 -> 66.562169 | AJ20: =+((+AJ15+AJ16+AJ18+AJ19)/AJ12)*100 -> 61.347684 | AL20: =+((AL16+AL18+AL15+AL19)/AL12)*100 -> 69.887465 | AN20: =+((AN16+AN18+AN15+AN19)/AN12)*100 -> 67.046662 | AP20: =+((+AP15+AP16+AP18+AP19)/AP12)*100 -> 62.40538 | AR20: =+((AR16+AR18+AR15+AR19)/AR12)*100 -> 75.254876 | AT20: =+((+AT15+AT16+AT18+AT19)/AT12)*100 -> 63.744354 | AV20: =+((AV16+AV18+AV15+AV19)/AV12)*100 -> 78.198717 | AX20: =+((+AX15+AX16+AX18+AX19)/AX12)*100 -> 64.962981 | AZ20: =+((AZ16+AZ18+AZ15+AZ19)/AZ12)*100 -> 74.166322 | BB20: =+((BB16+BB18+BB15+BB19)/BB12)*100 -> 75.742354 | BD20: =+((BD16+BD18+BD15+BD19)/BD12)*100 -> 71.443815 | BF20: =+((+BF15+BF16+BF18+BF19)/BF12)*100 -> 65.813979 | BI20: 67.011207 | BK20: 71.834135 | BM20: 64.928437 | BO20: 64.796113 | BQ20: 70.665579 | BS20: =+((BS16+BS18+BS15+BS19)/BS12)*100 -> 74.478558 | BU20: =+((BU16+BU18+BU15+BU19)/BU12)*100 -> 55.62943
B21: Saleable Steel (Shipping Mode-wise)
B22: RAIL | C22: MT | D22: =+D12 -> 2710000 | E22: =+E12 -> 181999.68 | F22: 164894.72 | G22: =+G12 -> 168000 | H22: 97343.181 | I22: =+I12 -> 349999.68 | J22: =+F22+H22 -> 262237.9 | K22: =+K12 -> 229000.11 | L22: 185082.04 | M22: =+M12 -> 578999.79 | N22: =+F22+H22+L22 -> 447319.94 | O22: =+O12 -> 231500.14 | P22: 192470.12 | Q22: =+Q12 -> 810499.94 | R22: =+N22+P22 -> 639790.06 | S22: =+S12 -> 231500.14 | T22: 199128.92 | U22: =+U12 -> 1042000.1 | V22: =+R22+T22 -> 838918.98 | W22: =+W12 -> 121299.68 | X22: 164143.06 | Y22: =+Y12 -> 584299.96 | Z22: =+P22+T22+X22 -> 555742.1 | AA22: =+AA12 -> 1163299.8 | AB22: =+N22+Z22 -> 1003062 | AC22: =+AC12 -> 236499.53 | AD22: 145794.66 | AE22: =+AE12 -> 1399799.3 | AF22: =+AB22+AD22 -> 1148856.7 | AG22: =+AG12 -> 228999.59 | AH22: 168162.39 | AI22: =+AI12 -> 1628798.9 | AJ22: =+AF22+AH22 -> 1317019.1 | AK22: =+AK12 -> 236500.05 | AL22: 173711.4 | AM22: =+AM12 -> 701999.17 | AN22: =+AD22+AH22+AL22 -> 487668.45 | AO22: =AI22+AK22 -> 1865298.9 | AP22: =AJ22+AL22 -> 1490730.5 | AQ22: =+AQ12 -> 239999.66 | AR22: 175869.74 | AS22: =+AS12 -> 2105298.6 | AT22: =+AP22+AR22 -> 1666600.2 | AU22: =+AU12 -> 214000.01 | AV22: 153661.52 | AW22: =+AW12 -> 2319298.6 | AX22: =+AT22+AV22 -> 1820261.8 | AY22: =+AY12 -> 240000 | AZ22: 193134.93 | BA22: =+BA12 -> 693999.68 | BB22: =+AR22+AV22+AZ22 -> 522666.19 | BC22: =+BC12 -> 1395998.8 | BD22: =AN22+BB22 -> 1010334.6 | BE22: =+BE12 -> 2559298.6 | BF22: =+AX22+AZ22 -> 2013396.7 | BH22: =+BH15 -> 2674798.3 | BI22: 2068091.4 | BJ22: 2409999.5 | BK22: 1898391 | BL22: 2525000 | BM22: 1848504.3 | BN22: 2410000 | BO22: 1959110.7 | BP22: 2369500.2 | BQ22: 1882591.4 | BR22: 2234474.8 | BS22: 1557181.9 | BT22: =+BT12 -> 2406999.7 | BU22: 1655527.4
B23: ROAD | C23: MT | F23: 37527.87 | H23: 22119.88 | J23: =+F23+H23 -> 59647.75 | L23: 33422.35 | N23: =+F23+H23+L23 -> 93070.1 | P23: 51153.71 | R23: =+N23+P23 -> 144223.81 | T23: 47189.73 | V23: =+R23+T23 -> 191413.54 | X23: 43122.55 | Z23: =+P23+T23+X23 -> 141465.99 | AB23: =+N23+Z23 -> 234536.09 | AD23: 27763.03 | AF23: =+AB23+AD23 -> 262299.12 | AH23: 52751.3 | AJ23: =+AF23+AH23 -> 315050.42 | AL23: 57004.08 | AN23: =+AD23+AH23+AL23 -> 137518.41 | AP23: =AJ23+AL23 -> 372054.5 | AR23: 40820.87 | AT23: =+AP23+AR23 -> 412875.37 | AV23: 37797.76 | AX23: =+AT23+AV23 -> 450673.13 | AZ23: 38244.77 | BB23: =+AR23+AV23+AZ23 -> 116863.4 | BD23: =AN23+BB23 -> 254381.81 | BF23: =+AX23+AZ23 -> 488917.9 | BI23: 505694.56 | BK23: 452352.24 | BM23: 516386.89 | BO23: 338946.25 | BQ23: 295664.13 | BS23: 320472.9 | BU23: 394405.54
B24: TOTAL | C24: MT | F24: =SUM(F22:F23) -> 202422.59 | H24: =SUM(H22:H23) -> 119463.06 | J24: =SUM(J22:J23) -> 321885.65 | L24: =SUM(L22:L23) -> 218504.39 | N24: =SUM(N22:N23) -> 540390.04 | P24: =SUM(P22:P23) -> 243623.83 | R24: =SUM(R22:R23) -> 784013.87 | T24: =SUM(T22:T23) -> 246318.65 | V24: =SUM(V22:V23) -> 1030332.5 | X24: =SUM(X22:X23) -> 207265.61 | Z24: =SUM(Z22:Z23) -> 697208.09 | AB24: =SUM(AB22:AB23) -> 1237598.1 | AD24: =SUM(AD22:AD23) -> 173557.69 | AF24: =SUM(AF22:AF23) -> 1411155.8 | AH24: =SUM(AH22:AH23) -> 220913.69 | AJ24: =SUM(AJ22:AJ23) -> 1632069.5 | AL24: =SUM(AL22:AL23) -> 230715.48 | AN24: =SUM(AN22:AN23) -> 625186.86 | AP24: =SUM(AP22:AP23) -> 1862785 | AR24: =SUM(AR22:AR23) -> 216690.61 | AT24: =SUM(AT22:AT23) -> 2079475.6 | AV24: =SUM(AV22:AV23) -> 191459.28 | AX24: =SUM(AX22:AX23) -> 2270934.9 | AZ24: =SUM(AZ22:AZ23) -> 231379.7 | BB24: =SUM(BB22:BB23) -> 639529.59 | BD24: =SUM(BD22:BD23) -> 1264716.4 | BF24: =SUM(BF22:BF23) -> 2502314.6 | BI24: 2573786 | BK24: 2350743.2 | BM24: 2364891.2 | BO24: 2298057 | BQ24: =SUM(BQ22:BQ23) -> 2178255.5 | BS24: 1877654.8 | BU24: =SUM(BU22:BU23) -> 2049932.9
B25: ROAD CO-EFFICIENT (%) | C25: % | F25: =+F23/F24*100 -> 18.539368 | H25: =+H23/H24*100 -> 18.516083 | J25: =+J23/J24*100 -> 18.530726 | L25: =+L23/L24*100 -> 15.295963 | N25: =+N23/N24*100 -> 17.222764 | P25: =+P23/P24*100 -> 20.997006 | R25: =+R23/R24*100 -> 18.395569 | T25: =+T23/T24*100 -> 19.158001 | V25: =+V23/V24*100 -> 18.577841 | X25: =+X23/X24*100 -> 20.805453 | Z25: =+Z23/Z24*100 -> 20.290354 | AB25: =+AB23/AB24*100 -> 18.950909 | AD25: =+AD23/AD24*100 -> 15.996427 | AF25: =+AF23/AF24*100 -> 18.587538 | AH25: =+AH23/AH24*100 -> 23.878693 | AJ25: =+AJ23/AJ24*100 -> 19.303738 | AL25: =+AL23/AL24*100 -> 24.707523 | AN25: =+AN23/AN24*100 -> 21.996369 | AP25: =+AP23/AP24*100 -> 19.973024 | AR25: =+AR23/AR24*100 -> 18.83832 | AT25: =+AT23/AT24*100 -> 19.854783 | AV25: =+AV23/AV24*100 -> 19.741932 | AX25: =+AX23/AX24*100 -> 19.845269 | AZ25: =+AZ23/AZ24*100 -> 16.529008 | BB25: =+BB23/BB24*100 -> 18.273337 | BD25: =+BD23/BD24*100 -> 20.113743 | BF25: =+BF23/BF24*100 -> 19.538626 | BI25: 19.647887 | BK25: 19.242946 | BM25: 21.835546 | BO25: 14.749254 | BQ25: 13.573438 | BS25: =+BS23/BS24*100 -> 17.067721 | BU25: =+BU23/BU24*100 -> 19.239924
B26: Pig Iron | C26: MT | D26: =+'Maj Production Summ'!D26 -> 6020 | E26: =+'Maj Production Summ'!E26 -> 1945 | F26: ='Direct sales IPT details'!E102 -> 296.7 | G26: =+'Maj Production Summ'!G26 -> 4075 | H26: ='Direct sales IPT details'!G102 -> 0 | I26: =+E26+G26 -> 6020 | J26: =+F26+H26 -> 296.7 | K26: =+'Maj Production Summ'!K26 -> 810 | L26: 996.79 | M26: =+E26+G26+K26 -> 6830 | N26: =+F26+H26+L26 -> 1293.49 | O26: =+'Maj Production Summ'!O26 -> 810 | P26: 900.29 | Q26: =+M26+O26 -> 7640 | R26: =+N26+P26 -> 2193.78 | S26: =+'Maj Production Summ'!S26 -> 810 | T26: 98.82 | U26: =+Q26+S26 -> 8450 | V26: =+R26+T26 -> 2292.6 | W26: =+'Maj Production Summ'!W26 -> 5360 | X26: 199.97 | Y26: =+O26+S26+W26 -> 6980 | Z26: =+P26+T26+X26 -> 1199.08 | AA26: =+M26+Y26 -> 13810 | AB26: =+N26+Z26 -> 2492.57 | AC26: =+'Maj Production Summ'!AC26 -> 810 | AD26: 696.92 | AE26: =+AA26+AC26 -> 14620 | AF26: =+AB26+AD26 -> 3189.49 | AG26: =+'Maj Production Summ'!AG26 -> 810 | AH26: 1596.1 | AI26: =+AE26+AG26 -> 15430 | AJ26: =+AF26+AH26 -> 4785.59 | AK26: =+'Maj Production Summ'!AK26 -> 810 | AL26: 298.72 | AM26: =+AC26+AG26+AK26 -> 2430 | AN26: =+AD26+AH26+AL26 -> 2591.74 | AO26: =AI26+AK26 -> 16240 | AP26: =AJ26+AL26 -> 5084.31 | AQ26: =+'Maj Production Summ'!AQ26 -> 810 | AR26: 99.25 | AS26: =+AO26+AQ26 -> 17050 | AT26: =+AP26+AR26 -> 5183.56 | AU26: =+'Maj Production Summ'!AU26 -> 810 | AV26: 647.95 | AW26: =+AS26+AU26 -> 17860 | AX26: =+AT26+AV26 -> 5831.51 | AY26: =+'Maj Production Summ'!AY26 -> 810 | AZ26: 99.5 | BA26: =+AQ26+AU26+AY26 -> 2430 | BB26: =+AR26+AV26+AZ26 -> 846.7 | BC26: =AM26+BA26 -> 4860 | BD26: =AN26+BB26 -> 3438.44 | BE26: =+AW26+AY26 -> 18670 | BF26: =+AX26+AZ26 -> 5931.01 | BH26: 14270 | BI26: 11725.78 | BJ26: 9365 | BK26: 8679.79 | BL26: 20742.204 | BM26: 7537.1 | BN26: 16929.735 | BO26: 8801.74 | BP26: 19251.635 | BQ26: 20488.86 | BR26: 20754.645 | BS26: 80002.18 | BT26: 29958.272 | BU26: 124050.8
B27: PCIS Plant Sales | C27: MT | D27: =+'Maj Production Summ'!D27 -> 5103 | E27: =+'Maj Production Summ'!E27 -> 644.512 | F27: ='Direct sales IPT details'!E50 -> 499.25 | G27: =+'Maj Production Summ'!G27 -> 2598.518 | H27: ='Direct sales IPT details'!G50 -> 0 | I27: =+E27+G27 -> 3243.03 | J27: =+F27+H27 -> 499.25 | K27: =+'Maj Production Summ'!K27 -> 273.996 | L27: 0 | M27: =+E27+G27+K27 -> 3517.026 | N27: =+F27+H27+L27 -> 499.25 | O27: =+'Maj Production Summ'!O27 -> 276.24 | P27: 996.4 | Q27: =+M27+O27 -> 3793.266 | R27: =+N27+P27 -> 1495.65 | S27: =+'Maj Production Summ'!S27 -> 276.24 | T27: 496.32 | U27: =+Q27+S27 -> 4069.506 | V27: =+R27+T27 -> 1991.97 | W27: =+'Maj Production Summ'!W27 -> 498.97 | X27: 335.17 | Y27: =+O27+S27+W27 -> 1051.45 | Z27: =+P27+T27+X27 -> 1827.89 | AA27: =+M27+Y27 -> 4568.476 | AB27: =+N27+Z27 -> 2327.14 | AC27: =+'Maj Production Summ'!AC27 -> 279.98 | AD27: 162.11 | AE27: =+AA27+AC27 -> 4848.456 | AF27: =+AB27+AD27 -> 2489.25 | AG27: =+'Maj Production Summ'!AG27 -> 273.996 | AH27: 498.65 | AI27: =+AE27+AG27 -> 5122.452 | AJ27: =+AF27+AH27 -> 2987.9 | AK27: =+'Maj Production Summ'!AK27 -> 279.98 | AL27: 1493.55 | AM27: =+AC27+AG27+AK27 -> 833.956 | AN27: =+AD27+AH27+AL27 -> 2154.31 | AO27: =AI27+AK27 -> 5402.432 | AP27: =AJ27+AL27 -> 4481.45 | AQ27: =+'Maj Production Summ'!AQ27 -> 282.972 | AR27: 1497.07 | AS27: =+AO27+AQ27 -> 5685.404 | AT27: =+AP27+AR27 -> 5978.52 | AU27: =+'Maj Production Summ'!AU27 -> 262.028 | AV27: 499.07 | AW27: =+AS27+AU27 -> 5947.432 | AX27: =+AT27+AV27 -> 6477.59 | AY27: =+'Maj Production Summ'!AY27 -> 282.972 | AZ27: 499.56 | BA27: =+AQ27+AU27+AY27 -> 827.972 | BB27: =+AR27+AV27+AZ27 -> 2495.7 | BC27: =AM27+BA27 -> 1661.928 | BD27: =AN27+BB27 -> 4650.01 | BE27: =+AW27+AY27 -> 6230.404 | BF27: =+AX27+AZ27 -> 6977.15 | BH27: 3541.35 | BI27: 7477.21 | BJ27: 2831.5 | BK27: 5762.52 | BL27: 2236.752 | BM27: 5991.84 | BN27: 2057.6 | BO27: 5429.83 | BP27: 2163.56 | BQ27: 17862.58 | BR27: 6973.7102 | BS27: 29483.78 | BT27: 8472.5251 | BU27: 59555.1
B28: Total Pig & Pig Equiv | C28: MT | D28: =SUM(D26:D27) -> 11123 | E28: =SUM(E26:E27) -> 2589.512 | F28: =SUM(F26:F27) -> 795.95 | G28: =SUM(G26:G27) -> 6673.518 | H28: =SUM(H26:H27) -> 0 | I28: =SUM(I26:I27) -> 9263.03 | J28: =SUM(J26:J27) -> 795.95 | K28: =SUM(K26:K27) -> 1083.996 | ... AO28: =SUM(AO26:AO27) -> 21642.432 | AP28: =AJ28+AL28 -> 9565.76 | AQ28: =SUM(AQ26:AQ27) -> 1092.972 | AR28: =SUM(AR26:AR27) -> 1596.32 | AS28: =SUM(AS26:AS27) -> 22735.404 | AT28: =SUM(AT26:AT27) -> 11162.08 | AU28: =SUM(AU26:AU27) -> 1072.028 | AV28: =SUM(AV26:AV27) -> 1147.02 | AW28: =SUM(AW26:AW27) -> 23807.432 | AX28: =SUM(AX26:AX27) -> 12309.1 | ... BB28: =SUM(BB26:BB27) -> 3342.4 | BC28: =AM28+BA28 -> 6521.928 | BD28: =AN28+BB28 -> 8088.45 | BE28: =SUM(BE26:BE27) -> 24900.404 | BF28: =SUM(BF26:BF27) -> 12908.16 | BH28: 17811.35 | BI28: 19202.99 | BJ28: 12196.5 | BK28: 14442.31 | BL28: 22978.956 | BM28: 13528.94 | BN28: 18987.335 | BO28: 14231.57 | BP28: 21415.195 | BQ28: 38351.44 | BR28: 27728.355 | BS28: 109485.96 | BT28: =SUM(BT26:BT27) -> 38430.797 | BU28: =SUM(BU26:BU27) -> 183605.9

Sheet Maj Techno Summ
B1: MAJOR TECHNO PARAMETERS 2025-2026
D2: 365 | E2: 30 | F2: 30 | G2: 31 | H2: 31 | I2: =+E2+G2 -> 61 | J2: =+F2+H2 -> 61 | K2: 30 | L2: 30 | M2: =+I2+K2 -> 91 | N2: =+J2+L2 -> 91 | O2: 31 | P2: 31 | Q2: =+M2+O2 -> 122 | R2: =+N2+P2 -> 122 | S2: 31 | T2: 31 | U2: =+Q2+S2 -> 153 | V2: =+R2+T2 -> 153 | W2: 30 | X2: 30 | Y2: =+O2+S2+W2 -> 92 | Z2: =+P2+T2+X2 -> 92 | AA2: =+U2+W2 -> 183 | AB2: =+V2+X2 -> 183 | AC2: 31 | AD2: 31 | AE2: =+AA2+AC2 -> 214 | AF2: =+AB2+AD2 -> 214 | AG2: 30 | AH2: 30 | AI2: =+AE2+AG2 -> 244 | AJ2: =+AF2+AH2 -> 244 | AK2: 31 | AL2: 31 | AM2: =+AC2+AG2+AK2 -> 92 | AN2: =+AD2+AH2+AL2 -> 92 | AO2: =+AI2+AK2 -> 275 | AP2: =+AJ2+AL2 -> 275 | AQ2: 31 | AR2: 31 | AS2: =+AO2+AQ2 -> 306 | AT2: =+AP2+AR2 -> 306 | AU2: 28 | AV2: 28 | AW2: =+AS2+AU2 -> 334 | AX2: =+AT2+AV2 -> 334 | AY2: 31 | AZ2: 31 | BA2: =+AQ2+AU2+AY2 -> 90 | BB2: =+AR2+AV2+AZ2 -> 90 | BC2: =+AM2+BA2 -> 182 | BD2: =+AN2+BB2 -> 182 | BE2: =+AW2+AY2 -> 365 | BF2: =+AX2+AZ2 -> 365 | BR2: 365 | BS2: 365 | BT2: 366 | BU2: 366 | BV2: 365
B3: ITEM | C3: Unit | D3: 2026-27 Norm | E3: Apr'26 | G3: May'26 | I3: 2M | K3: Jun'25 | M3: QTR-1 | O3: Jul'25 | Q3: 4M | S3: Aug'25 | U3: 5M | W3: Sep'25 | Y3: QTR-2 | AA3: H1 | AC3: Oct'25 | AE3: 7M | AG3: Nov'25 | AI3: 8M | AK3: Dec'25 | AM3: QTR-3 | AO3: 9 M | AQ3: Jan'26 | AS3: 10M | AU3: Feb'26 | AW3: 11M | AY3: Mar'26 | BA3: QTR-4 | BC3: H2 | BE3: 2026-27 | BH3: 2025-26 | BJ3: 2024-25 | BL3: 2023-24 | BN3: 2022-23 | BP3: 2021-22 | BR3: 2020-21 | BT3: 2019-20 | BV3: 2018-19
E4: ABP | F4: ACT | G4: ABP | H4: ACT | I4: ABP | J4: ACT | K4: ABP | L4: ACT | M4: ABP | N4: ACT | O4: ABP | P4: ACT | Q4: ABP | R4: ACT | S4: ABP | T4: ACT | U4: ABP | V4: ACT | W4: ABP | X4: ACT | Y4: ABP | Z4: ACT | AA4: ABP | AB4: ACT | AC4: ABP | AD4: ACT | AE4: ABP | AF4: ACT | AG4: ABP | AH4: ACT | AI4: ABP | AJ4: ACT | AK4: ABP | AL4: ACT | AM4: ABP | AN4: ACT | AO4: ABP | AP4: ACT | AQ4: ABP | AR4: ACT | AS4: ABP | AT4: ACT | AU4: ABP | AV4: ACT | AW4: ABP | AX4: ACT | AY4: ABP | AZ4: ACT | BA4: ABP | BB4: ACT | BC4: ABP | BD4: ACT | BE4: ABP | BF4: ACT | BH4: ABP | BI4: ACT | BJ4: ABP | BK4: ACT | BL4: ABP | BM4: ACT | BN4: ABP | BO4: ACT | BP4: ABP | BQ4: ACT | BR4: ABP | BS4: ACT | BT4: ABP | BU4: ACT | BV4: ACT
B5: B.F.Coke Yield | C5: % | D5: 69.5 | E5: =+$D$5 -> 69.5 | F5: =('Maj Production Summ'!F14*100)/('Maj Production Summ'!F10*31.55) -> 69.5 | G5: =+$D$5 -> 69.5 | H5: =('Maj Production Summ'!H14*100)/('Maj Production Summ'!H10*31.55) -> 69.5 | I5: =+$D$5 -> 69.5 | J5: =('Maj Production Summ'!J14*100)/('Maj Production Summ'!J10*31.55) -> 69.5 | K5: =+$D$5 -> 69.5 | L5: =('Maj Production Summ'!L14*100)/('Maj Production Summ'!L10*31.55) -> 70 | M5: =+$D$5 -> 69.5 | N5: =('Maj Production Summ'!N14*100)/('Maj Production Summ'!N10*31.55) -> 69.667631 | O5: =+$D$5 -> 69.5 | P5: =('Maj Production Summ'!P14*100)/('Maj Production Summ'!P10*31.55) -> 70 | Q5: =+$D$5 -> 69.5 | R5: =('Maj Production Summ'!R14*100)/('Maj Production Summ'!R10*31.55) -> 69.753493 | S5: =+$D$5 -> 69.5 | T5: =('Maj Production Summ'!T14*100)/('Maj Production Summ'!T10*31.55) -> 70 | U5: =+$D$5 -> 69.5 | V5: =('Maj Production Summ'!V14*100)/('Maj Production Summ'!V10*31.55) -> 69.803904 | W5: =+$D$5 -> 69.5 | X5: =('Maj Production Summ'!X14*100)/('Maj Production Summ'!X10*31.55) -> 69.492954 | Y5: =+$D$5 -> 69.5 | Z5: =('Maj Production Summ'!Z14*100)/('Maj Production Summ'!Z10*31.55) -> 69.834649 | AA5: =+$D$5 -> 69.5 | AB5: =('Maj Production Summ'!AB14*100)/('Maj Production Summ'!AB10*31.55) -> 69.752423 | AC5: =+$D$5 -> 69.5 | AD5: =('Maj Production Summ'!AD14*100)/('Maj Production Summ'!AD10*31.55) -> 69.7 | AE5: =+$D$5 -> 69.5 | AF5: =('Maj Production Summ'!AF14*100)/('Maj Production Summ'!AF10*31.55) -> 69.74487 | AG5: =+$D$5 -> 69.5 | AH5: =('Maj Production Summ'!AH14*100)/('Maj Production Summ'!AH10*31.55) -> 69.5 | AI5: =+$D$5 -> 69.5 | AJ5: =('Maj Production Summ'!AJ14*100)/('Maj Production Summ'!AJ10*31.55) -> 69.714505 | AK5: =+$D$5 -> 69.5 | AL5: =('Maj Production Summ'!AL14*100)/('Maj Production Summ'!AL10*31.55) -> 69.5 | AM5: =+$D$5 -> 69.5 | AN5: =('Maj Production Summ'!AN14*100)/('Maj Production Summ'!AN10*31.55) -> 69.566704 | AO5: =+$D$5 -> 69.5 | AP5: =('Maj Production Summ'!AP14*100)/('Maj Production Summ'!AP10*31.55) -> 69.690124 | AQ5: =+$D$5 -> 69.5 | AR5: =('Maj Production Summ'!AR14*100)/('Maj Production Summ'!AR10*31.55) -> 69.5 | AS5: =+$D$5 -> 69.5 | AT5: =('Maj Production Summ'!AT14*100)/('Maj Production Summ'!AT10*31.55) -> 69.670873 | AU5: =+$D$5 -> 69.5 | AV5: =('Maj Production Summ'!AV14*100)/('Maj Production Summ'!AV10*31.55) -> 69.5 | AW5: =+$D$5 -> 69.5 | AX5: =('Maj Production Summ'!AX14*100)/('Maj Production Summ'!AX10*31.55) -> 69.656534 | AY5: =+$D$5 -> 69.5 | AZ5: =('Maj Production Summ'!AZ14*100)/('Maj Production Summ'!AZ10*31.55) -> 69.5 | BA5: =+$D$5 -> 69.5 | BB5: =('Maj Production Summ'!BB14*100)/('Maj Production Summ'!BB10*31.55) -> 69.5 | BC5: =+$D$5 -> 69.5 | BD5: =('Maj Production Summ'!BD14*100)/('Maj Production Summ'!BD10*31.55) -> 69.533718 | BE5: =+$D$5 -> 69.5 | BF5: =('Maj Production Summ'!BF14*100)/('Maj Production Summ'!BF10*31.55) -> 69.643147 | BH5: 70 | BI5: 69.725618 | BJ5: 70 | BK5: 70.341275 | BL5: 69.5 | BM5: 69.398029 | BN5: 69.5 | BO5: 69.459875 | BP5: 70.500003 | BQ5: 69.798394 | BR5: 70.999787 | BS5: 72.813877 | BT5: 66.5 | BU5: 67.48567 | BV5: 67.015011
B6: ICC in Coal Blend
B7: (COB#10) | C7: % | D7: 89 | E7: =+$D$7 -> 89 | F7: ='COKE OVENS'!F146 -> 89 | G7: =+$D$7 -> 89 | H7: ='COKE OVENS'!H146 -> 89 | I7: =+$D$7 -> 89 | J7: ='COKE OVENS'!J146 -> 89 | K7: =+$D$7 -> 89 | L7: ='COKE OVENS'!L146 -> #REF! | M7: =+$D$7 -> 89 | N7: ='COKE OVENS'!N146 -> #REF! | O7: =+$D$7 -> 89 | P7: ='COKE OVENS'!P146 -> #REF! | Q7: =+$D$7 -> 89 | R7: ='COKE OVENS'!R146 -> #REF! | S7: =+$D$7 -> 89 | T7: ='COKE OVENS'!T146 -> #REF! | U7: =+$D$7 -> 89 | V7: ='COKE OVENS'!V146 -> #REF! | W7: =+$D$7 -> 89 | X7: ='COKE OVENS'!X146 -> #REF! | Y7: =+$D$7 -> 89 | Z7: ='COKE OVENS'!Z146 -> #REF! | AA7: =+$D$7 -> 89 | AB7: ='COKE OVENS'!AB146 -> #REF! | AC7: =+$D$7 -> 89 | AD7: ='COKE OVENS'!AD146 -> #REF! | AE7: =+$D$7 -> 89 | AF7: ='COKE OVENS'!AF146 -> #REF! | AG7: =+$D$7 -> 89 | AH7: ='COKE OVENS'!AH146 -> #REF! | AI7: =+$D$7 -> 89 | AJ7: ='COKE OVENS'!AJ146 -> #REF! | AK7: =+$D$7 -> 89 | AL7: ='COKE OVENS'!AL146 -> #REF! | AM7: =+$D$7 -> 89 | AN7: ='COKE OVENS'!AN146 -> #REF! | AO7: =+$D$7 -> 89 | AP7: ='COKE OVENS'!AP146 -> #REF! | AQ7: =+$D$7 -> 89 | AR7: ='COKE OVENS'!AR146 -> #REF! | AS7: =+$D$7 -> 89 | AT7: ='COKE OVENS'!AT146 -> #REF! | AU7: =+$D$7 -> 89 | AV7: ='COKE OVENS'!AV146 -> #REF! | AW7: =+$D$7 -> 89 | AX7: ='COKE OVENS'!AX146 -> #REF! | AY7: =+$D$7 -> 89 | AZ7: ='COKE OVENS'!AZ146 -> #REF! | BA7: =+$D$7 -> 89 | BB7: ='COKE OVENS'!BB146 -> #REF! | BC7: =+$D$7 -> 89 | BD7: ='COKE OVENS'!BD146 -> #REF! | BE7: =+$D$7 -> 89 | BF7: ='COKE OVENS'!BF146 -> #REF! | BH7: 92 | BI7: 89.787075 | BJ7: 95 | BK7: 92.468484 | BL7: 92 | BM7: 90.939873 | BN7: 92 | BO7: 89.651306 | BP7: 95 | BQ7: 93.865972 | BR7: 94.377235 | BS7: 94.02333 | BT7: 90 | BU7: 91.425995 | BV7: 91.808306
B8: (COB#11) | C8: % | D8: 95 | E8: =+$D$8 -> 95 | F8: ='COKE OVENS'!F174 -> 95 | G8: =+$D$8 -> 95 | H8: ='COKE OVENS'!H174 -> 95 | I8: =+$D$8 -> 95 | J8: ='COKE OVENS'!J174 -> 94.97637 | K8: =+$D$8 -> 95 | L8: ='COKE OVENS'!L174 -> 95 | M8: =+$D$8 -> 95 | N8: ='COKE OVENS'!N174 -> 94.984317 | O8: =+$D$8 -> 95 | P8: ='COKE OVENS'!P174 -> 95.000001 | Q8: =+$D$8 -> 95 | R8: ='COKE OVENS'!R174 -> 94.988378 | S8: =+$D$8 -> 95 | T8: ='COKE OVENS'!T174 -> 95 | U8: =+$D$8 -> 95 | V8: ='COKE OVENS'!V174 -> 94.990759 | W8: =+$D$8 -> 95 | X8: ='COKE OVENS'!X174 -> 95 | Y8: =+$D$8 -> 95 | Z8: ='COKE OVENS'!Z174 -> 95 | AA8: =+$D$8 -> 95 | AB8: ='COKE OVENS'!AB174 -> 94.992291 | AC8: =+$D$8 -> 95 | AD8: ='COKE OVENS'!AD174 -> 95 | AE8: =+$D$8 -> 95 | AF8: ='COKE OVENS'!AF174 -> 94.993404 | AG8: =+$D$8 -> 95 | AH8: ='COKE OVENS'!AH174 -> 95 | AI8: =+$D$8 -> 95 | AJ8: ='COKE OVENS'!AJ174 -> 94.994222 | AK8: =+$D$8 -> 95 | AL8: ='COKE OVENS'!AL174 -> 95 | AM8: =+$D$8 -> 95 | AN8: ='COKE OVENS'!AN174 -> 95 | AO8: =+$D$8 -> 95 | AP8: ='COKE OVENS'!AP174 -> 94.99488 | AQ8: =+$D$8 -> 95 | AR8: ='COKE OVENS'!AR174 -> 95 | AS8: =+$D$8 -> 95 | AT8: ='COKE OVENS'!AT174 -> 94.995399 | AU8: =+$D$8 -> 95 | AV8: ='COKE OVENS'!AV174 -> 95 | AW8: =+$D$8 -> 95 | AX8: ='COKE OVENS'!AX174 -> 94.995785 | AY8: =+$D$8 -> 95 | AZ8: ='COKE OVENS'!AZ174 -> 95 | BA8: =+$D$8 -> 95 | BB8: ='COKE OVENS'!BB174 -> 95 | BC8: =+$D$8 -> 95 | BD8: ='COKE OVENS'!BD174 -> 95 | BE8: =+$D$8 -> 95 | BF8: ='COKE OVENS'!BF174 -> 94.996146 | BH8: 97 | BI8: 94.966859 | BJ8: 100 | BK8: 97.818139 | BL8: 94 | BM8: 93.889004 | BN8: 94 | BO8: 92.198587 | BP8: 95 | BQ8: 94.753433 | BR8: 94.836589 | BS8: 95.080613 | BT8: 90 | BU8: 96.370935 | BV8: 94.117213
B9: Overall ICC in Blend | C9: % | D9: 92.972626 | E9: =+$D$9 -> 92.972626 | F9: ='COKE OVENS'!F216 -> 92.889184 | G9: =+$D$9 -> 92.972626 | H9: ='COKE OVENS'!H216 -> 92.834232 | I9: =+$D$9 -> 92.972626 | J9: ='COKE OVENS'!J216 -> 92.861742 | K9: =+$D$9 -> 92.972626 | L9: ='COKE OVENS'!L216 -> 93.437619 | M9: =+$D$9 -> 92.972626 | N9: ='COKE OVENS'!N216 -> 92.549763 | O9: =+$D$9 -> 92.972626 | P9: ='COKE OVENS'!P216 -> 104.58173 | Q9: =+$D$9 -> 92.972626 | R9: ='COKE OVENS'!R216 -> 95.789546 | S9: =+$D$9 -> 92.972626 | T9: ='COKE OVENS'!T216 -> 100.75072 | U9: =+$D$9 -> 92.972626 | V9: ='COKE OVENS'!V216 -> 96.847082 | W9: =+$D$9 -> 92.972626 | X9: ='COKE OVENS'!X216 -> 105.92804 | Y9: =+$D$9 -> 92.972626 | Z9: ='COKE OVENS'!Z216 -> 103.72929 | AA9: =+$D$9 -> 92.972626 | AB9: ='COKE OVENS'!AB216 -> 98.40213 | AC9: =+$D$9 -> 92.972626 | AD9: ='COKE OVENS'!AD216 -> 102.81574 | AE9: =+$D$9 -> 92.972626 | AF9: ='COKE OVENS'!AF216 -> 99.056922 | AG9: =+$D$9 -> 92.972626 | AH9: ='COKE OVENS'!AH216 -> 99.873119 | AI9: =+$D$9 -> 92.972626 | AJ9: ='COKE OVENS'!AJ216 -> 99.15952 | AK9: =+$D$9 -> 92.972626 | AL9: ='COKE OVENS'!AL216 -> 92.364182 | AM9: =+$D$9 -> 92.972626 | AN9: ='COKE OVENS'!AN216 -> 98.332317 | AO9: =+$D$9 -> 92.972626 | AP9: ='COKE OVENS'!AP216 -> 98.378323 | AQ9: =+$D$9 -> 92.972626 | AR9: ='COKE OVENS'!AR216 -> 99.186871 | AS9: =+$D$9 -> 92.972626 | AT9: ='COKE OVENS'!AT216 -> 98.461457 | AU9: =+$D$9 -> 92.972626 | AV9: ='COKE OVENS'!AV216 -> 99.901433 | AW9: =+$D$9 -> 92.972626 | AX9: ='COKE OVENS'!AX216 -> 98.583778 | AY9: =+$D$9 -> 92.972626 | AZ9: ='COKE OVENS'!AZ216 -> 93.243821 | BA9: =+$D$9 -> 92.972626 | BB9: ='COKE OVENS'!BB216 -> 97.337963 | BC9: =+$D$9 -> 92.972626 | BD9: ='COKE OVENS'!BD216 -> 97.839846 | BE9: =+$D$9 -> 92.972626 | BF9: ='COKE OVENS'!BF216 -> 98.117484 | BH9: 95.32229 | BI9: 93.163577 | BJ9: 98.275343 | BK9: 95.930698 | BL9: 93.289716 | BM9: 92.83339 | BN9: 93.294359 | BO9: 91.262624 | BP9: 95 | BQ9: 94.439237 | BR9: 94.673168 | BS9: 94.71202 | BT9: 90 | BU9: 94.617133 | BV9: 93.297278
B10: BF Coke Rate | C10: Kg/ THM | D10: 348.374 | E10: 375 | F10: =+('B-FCE'!F23/'Maj Production Summ'!F$17)*1000 -> 383.57168 | G10: 356 | H10: =+('B-FCE'!H23/'Maj Production Summ'!H$17)*1000 -> 415.31471 | I10: =+('B-FCE'!I23/'Maj Production Summ'!I$17)*1000 -> 366.00506 | J10: =+('B-FCE'!J23/'Maj Production Summ'!J$17)*1000 -> 393.67312 | K10: 356 | L10: =+('B-FCE'!L23/'Maj Production Summ'!L$17)*1000 -> 348.40699 | M10: =+('B-FCE'!M23/'Maj Production Summ'!M$17)*1000 -> 362.10819 | N10: =+('B-FCE'!N23/'Maj Production Summ'!N$17)*1000 -> 374.24411 | O10: 356 | P10: =+('B-FCE'!P23/'Maj Production Summ'!P$17)*1000 -> 362.56962 | Q10: =+('B-FCE'!Q23/'Maj Production Summ'!Q$17)*1000 -> 360.38137 | R10: =+('B-FCE'!R23/'Maj Production Summ'!R$17)*1000 -> 370.67613 | S10: 356 | T10: =+('B-FCE'!T23/'Maj Production Summ'!T$17)*1000 -> 365.93798 | U10: =+('B-FCE'!U23/'Maj Production Summ'!U$17)*1000 -> 359.41573 | V10: =+('B-FCE'!V23/'Maj Production Summ'!V$17)*1000 -> 369.61478 | W10: 383 | X10: =+('B-FCE'!X23/'Maj Production Summ'!X$17)*1000 -> 390.38903 | Y10: =+('B-FCE'!Y23/'Maj Production Summ'!Y$17)*1000 -> 361.81538 | Z10: =+('B-FCE'!Z23/'Maj Production Summ'!Z$17)*1000 -> 372.5362 | AA10: =+('B-FCE'!AA23/'Maj Production Summ'!AA$17)*1000 -> 361.96145 | AB10: =+('B-FCE'!AB23/'Maj Production Summ'!AB$17)*1000 -> 373.29352 | AC10: 354 | AD10: =+('B-FCE'!AD23/'Maj Production Summ'!AD$17)*1000 -> 407.03377 | AE10: =+('B-FCE'!AE23/'Maj Production Summ'!AE$17)*1000 -> 360.63198 | AF10: =+('B-FCE'!AF23/'Maj Production Summ'!AF$17)*1000 -> 377.63624 | AG10: 354 | AH10: =+('B-FCE'!AH23/'Maj Production Summ'!AH$17)*1000 -> 366.29801 | AI10: =+('B-FCE'!AI23/'Maj Production Summ'!AI$17)*1000 -> 359.70813 | AJ10: =+('B-FCE'!AJ23/'Maj Production Summ'!AJ$17)*1000 -> 376.11611 | AK10: 354 | AL10: =+('B-FCE'!AL23/'Maj Production Summ'!AL$17)*1000 -> 379.38955 | AM10: =+('B-FCE'!AM23/'Maj Production Summ'!AM$17)*1000 -> 354 | AN10: =+('B-FCE'!AN23/'Maj Production Summ'!AN$17)*1000 -> 382.84533 | AO10: =+('B-FCE'!AO23/'Maj Production Summ'!AO$17)*1000 -> 358.99082 | AP10: =+('B-FCE'!AP23/'Maj Production Summ'!AP$17)*1000 -> 376.51342 | AQ10: 354 | AR10: =+('B-FCE'!AR23/'Maj Production Summ'!AR$17)*1000 -> 385.39817 | AS10: =+('B-FCE'!AS23/'Maj Production Summ'!AS$17)*1000 -> 358.42606 | AT10: =+('B-FCE'!AT23/'Maj Production Summ'!AT$17)*1000 -> 377.45214 | AU10: 354 | AV10: =+('B-FCE'!AV23/'Maj Production Summ'!AV$17)*1000 -> 429.82864 | AW10: =+('B-FCE'!AW23/'Maj Production Summ'!AW$17)*1000 -> 358.01946 | AX10: =+('B-FCE'!AX23/'Maj Production Summ'!AX$17)*1000 -> 381.54754 | AY10: 354 | AZ10: =+('B-FCE'!AZ23/'Maj Production Summ'!AZ$17)*1000 -> 367.13629 | BA10: =+('B-FCE'!BA23/'Maj Production Summ'!BA$17)*1000 -> 354 | BB10: =+('B-FCE'!BB23/'Maj Production Summ'!BB$17)*1000 -> 391.36138 | BC10: =+('B-FCE'!BC23/'Maj Production Summ'!BC$17)*1000 -> 354 | BD10: =+('B-FCE'!BD23/'Maj Production Summ'!BD$17)*1000 -> 387.08692 | BE10: =+('B-FCE'!BE23/'Maj Production Summ'!BE$17)*1000 -> 357.6449 | BF10: =+('B-FCE'!BF23/'Maj Production Summ'!BF$17)*1000 -> 380.2352 | BH10: 356.24 | BI10: 373.08643 | BJ10: 360.04562 | BK10: 371.74357 | BL10: 380.42 | BM10: 390.51224 | BN10: 389.92559 | BO10: 400.04041 | BP10: 377.88521 | BQ10: 396.71459 | BR10: 373.87865 | BS10: 423.66105 | BT10: 370.47898 | BU10: 381.58771 | BV10: 388.39311
B11: Nut Coke rate | C11: Kg/ THM | D11: 27.055333 | E11: 26 | F11: =+('B-FCE'!F24/'Maj Production Summ'!F$17)*1000 -> 31.725019 | G11: 29 | H11: =+('B-FCE'!H24/'Maj Production Summ'!H$17)*1000 -> 33.469193 | I11: =+('B-FCE'!I24/'Maj Production Summ'!I$17)*1000 -> 27.420253 | J11: =+('B-FCE'!J24/'Maj Production Summ'!J$17)*1000 -> 32.28006 | K11: 29 | L11: =+('B-FCE'!L24/'Maj Production Summ'!L$17)*1000 -> 31.876011 | M11: =+('B-FCE'!M24/'Maj Production Summ'!M$17)*1000 -> 28.035549 | N11: =+('B-FCE'!N24/'Maj Production Summ'!N$17)*1000 -> 32.106635 | O11: 29 | P11: =+('B-FCE'!P24/'Maj Production Summ'!P$17)*1000 -> 40.769373 | Q11: =+('B-FCE'!Q24/'Maj Production Summ'!Q$17)*1000 -> 28.308204 | R11: =+('B-FCE'!R24/'Maj Production Summ'!R$17)*1000 -> 34.754154 | S11: 29 | T11: =+('B-FCE'!T24/'Maj Production Summ'!T$17)*1000 -> 37.253344 | U11: =+('B-FCE'!U24/'Maj Production Summ'!U$17)*1000 -> 28.460674 | V11: =+('B-FCE'!V24/'Maj Production Summ'!V$17)*1000 -> 35.313978 | W11: 28 | X11: =+('B-FCE'!X24/'Maj Production Summ'!X$17)*1000 -> 36.73382 | Y11: =+('B-FCE'!Y24/'Maj Production Summ'!Y$17)*1000 -> 28.784615 | Z11: =+('B-FCE'!Z24/'Maj Production Summ'!Z$17)*1000 -> 38.320944 | AA11: =+('B-FCE'!AA24/'Maj Production Summ'!AA$17)*1000 -> 28.410948 | AB11: =+('B-FCE'!AB24/'Maj Production Summ'!AB$17)*1000 -> 35.565406 | AC11: 29 | AD11: =+('B-FCE'!AD24/'Maj Production Summ'!AD$17)*1000 -> 30.284128 | AE11: =+('B-FCE'!AE24/'Maj Production Summ'!AE$17)*1000 -> 28.509313 | AF11: =+('B-FCE'!AF24/'Maj Production Summ'!AF$17)*1000 -> 34.885651 | AG11: 29 | AH11: =+('B-FCE'!AH24/'Maj Production Summ'!AH$17)*1000 -> 37.743469 | AI11: =+('B-FCE'!AI24/'Maj Production Summ'!AI$17)*1000 -> 28.577667 | AJ11: =+('B-FCE'!AJ24/'Maj Production Summ'!AJ$17)*1000 -> 35.268801 | AK11: 29 | AL11: =+('B-FCE'!AL24/'Maj Production Summ'!AL$17)*1000 -> 35.629725 | AM11: =+('B-FCE'!AM24/'Maj Production Summ'!AM$17)*1000 -> 29 | AN11: =+('B-FCE'!AN24/'Maj Production Summ'!AN$17)*1000 -> 34.815484 | AO11: =+('B-FCE'!AO24/'Maj Production Summ'!AO$17)*1000 -> 28.630739 | AP11: =+('B-FCE'!AP24/'Maj Production Summ'!AP$17)*1000 -> 35.312608 | AQ11: 29 | AR11: =+('B-FCE'!AR24/'Maj Production Summ'!AR$17)*1000 -> 31.827294 | AS11: =+('B-FCE'!AS24/'Maj Production Summ'!AS$17)*1000 -> 28.672525 | AT11: =+('B-FCE'!AT24/'Maj Production Summ'!AT$17)*1000 -> 34.944365 | AU11: 29 | AV11: =+('B-FCE'!AV24/'Maj Production Summ'!AV$17)*1000 -> 29.819622 | AW11: =+('B-FCE'!AW24/'Maj Production Summ'!AW$17)*1000 -> 28.702608 | AX11: =+('B-FCE'!AX24/'Maj Production Summ'!AX$17)*1000 -> 34.543654 | AY11: 29 | AZ11: =+('B-FCE'!AZ24/'Maj Production Summ'!AZ$17)*1000 -> 32.889139 | BA11: =+('B-FCE'!BA24/'Maj Production Summ'!BA$17)*1000 -> 29 | BB11: =+('B-FCE'!BB24/'Maj Production Summ'!BB$17)*1000 -> 31.643809 | BC11: =+('B-FCE'!BC24/'Maj Production Summ'!BC$17)*1000 -> 29 | BD11: =+('B-FCE'!BD24/'Maj Production Summ'!BD$17)*1000 -> 33.235768 | BE11: =+('B-FCE'!BE24/'Maj Production Summ'!BE$17)*1000 -> 28.730321 | BF11: =+('B-FCE'!BF24/'Maj Production Summ'!BF$17)*1000 -> 34.392989 | BH11: 28.952542 | BI11: 33.75022 | BJ11: 38.916226 | BK11: 40.499376 | BL11: 32.204286 | BM11: 47.260949 | BN11: 30 | BO11: 36.610035 | BP11: 23.751425 | BQ11: 37.043769 | BR11: 34.857516 | BS11: 41.208946 | BT11: 25 | BU11: 44.993877 | BV11: 29.180384
B12: CDI rate | C12: Kg/ THM | D12: 149.57067 | E12: 124 | F12: =+('B-FCE'!F25/'Maj Production Summ'!F$17)*1000 -> 125.12614 | G12: 140 | H12: =+('B-FCE'!H25/'Maj Production Summ'!H$17)*1000 -> 93.14978 | I12: =+('B-FCE'!I25/'Maj Production Summ'!I$17)*1000 -> 131.57468 | J12: =+('B-FCE'!J25/'Maj Production Summ'!J$17)*1000 -> 114.95045 | K12: 150 | L12: =+('B-FCE'!L25/'Maj Production Summ'!L$17)*1000 -> 155.24561 | M12: =+('B-FCE'!M25/'Maj Production Summ'!M$17)*1000 -> 138.75116 | N12: =+('B-FCE'!N25/'Maj Production Summ'!N$17)*1000 -> 132.24584 | O12: 150 | P12: =+('B-FCE'!P25/'Maj Production Summ'!P$17)*1000 -> 142.77674 | Q12: =+('B-FCE'!Q25/'Maj Production Summ'!Q$17)*1000 -> 141.93126 | R12: =+('B-FCE'!R25/'Maj Production Summ'!R$17)*1000 -> 135.46431 | S12: 150 | T12: =+('B-FCE'!T25/'Maj Production Summ'!T$17)*1000 -> 141.84997 | U12: =+('B-FCE'!U25/'Maj Production Summ'!U$17)*1000 -> 143.70959 | V12: =+('B-FCE'!V25/'Maj Production Summ'!V$17)*1000 -> 136.89471 | W12: 121 | X12: =+('B-FCE'!X25/'Maj Production Summ'!X$17)*1000 -> 128.55199 | Y12: =+('B-FCE'!Y25/'Maj Production Summ'!Y$17)*1000 -> 143.75385 | Z12: =+('B-FCE'!Z25/'Maj Production Summ'!Z$17)*1000 -> 137.94406 | AA12: =+('B-FCE'!AA25/'Maj Production Summ'!AA$17)*1000 -> 141.25829 | AB12: =+('B-FCE'!AB25/'Maj Production Summ'!AB$17)*1000 -> 135.41737 | AC12: 152 | AD12: =+('B-FCE'!AD25/'Maj Production Summ'!AD$17)*1000 -> 125.46642 | AE12: =+('B-FCE'!AE25/'Maj Production Summ'!AE$17)*1000 -> 143.05202 | AF12: =+('B-FCE'!AF25/'Maj Production Summ'!AF$17)*1000 -> 134.13658 | AG12: 152 | AH12: =+('B-FCE'!AH25/'Maj Production Summ'!AH$17)*1000 -> 136.65061 | AI12: =+('B-FCE'!AI25/'Maj Production Summ'!AI$17)*1000 -> 144.29851 | AJ12: =+('B-FCE'!AJ25/'Maj Production Summ'!AJ$17)*1000 -> 134.47363 | AK12: 152 | AL12: =+('B-FCE'!AL25/'Maj Production Summ'!AL$17)*1000 -> 130.86443 | AM12: =+('B-FCE'!AM25/'Maj Production Summ'!AM$17)*1000 -> 152 | AN12: =+('B-FCE'!AN25/'Maj Production Summ'!AN$17)*1000 -> 131.31828 | AO12: =+('B-FCE'!AO25/'Maj Production Summ'!AO$17)*1000 -> 145.26631 | AP12: =+('B-FCE'!AP25/'Maj Production Summ'!AP$17)*1000 -> 134.03557 | AQ12: 152 | AR12: =+('B-FCE'!AR25/'Maj Production Summ'!AR$17)*1000 -> 129.82366 | AS12: =+('B-FCE'!AS25/'Maj Production Summ'!AS$17)*1000 -> 146.02829 | AT12: =+('B-FCE'!AT25/'Maj Production Summ'!AT$17)*1000 -> 133.59056 | AU12: 152 | AV12: =+('B-FCE'!AV25/'Maj Production Summ'!AV$17)*1000 -> 89.192169 | AW12: =+('B-FCE'!AW25/'Maj Production Summ'!AW$17)*1000 -> 146.57688 | AX12: =+('B-FCE'!AX25/'Maj Production Summ'!AX$17)*1000 -> 130.11898 | AY12: 152 | AZ12: =+('B-FCE'!AZ25/'Maj Production Summ'!AZ$17)*1000 -> 135.42125 | BA12: =+('B-FCE'!BA25/'Maj Production Summ'!BA$17)*1000 -> 152 | BB12: =+('B-FCE'!BB25/'Maj Production Summ'!BB$17)*1000 -> 120.33673 | BC12: =+('B-FCE'!BC25/'Maj Production Summ'!BC$17)*1000 -> 152 | BD12: =+('B-FCE'!BD25/'Maj Production Summ'!BD$17)*1000 -> 125.8487 | BE12: =+('B-FCE'!BE25/'Maj Production Summ'!BE$17)*1000 -> 147.08224 | BF12: =+('B-FCE'!BF25/'Maj Production Summ'!BF$17)*1000 -> 130.60183 | BH12: 149.66508 | BI12: 136.29498 | BJ12: 140.90981 | BK12: 134.06434 | BL12: 139.6475 | BM12: 125.94309 | BN12: 129.64578 | BO12: 122.58808 | BP12: 133.64292 | BQ12: 118.07599 | BR12: 128.57732 | BS12: 89.175353 | BT12: 139.85352 | BU12: 118.98027 | BV12: 123.03826
B13: Total Fuel | C13: Kg/ THM | D13: =SUM(D10:D12) -> 525 | E13: =SUM(E10:E12) -> 525 | F13: =SUM(F10:F12) -> 540.42285 | G13: =SUM(G10:G12) -> 525 | H13: =SUM(H10:H12) -> 541.93368 | I13: =SUM(I10:I12) -> 525 | J13: =SUM(J10:J12) -> 540.90363 | K13: =SUM(K10:K12) -> 535 | ... BF13: =SUM(BF10:BF12) -> 545.23002 | BH13: 534.85763 | BI13: 543.13163 | BJ13: 539.87166 | BK13: 546.30729 | BL13: 552.27179 | BM13: 563.71628 | BN13: 549.57137 | BO13: 559.23852 | BP13: 535.27955 | BQ13: 551.83435 | BR13: 537.31348 | BS13: 554.04535 | BT13: 535.3325 | BU13: 545.56186 | BV13: 540.61176
B14: BF Productivity | C14: T/M³/Day | D14: 2.4702703 | E14: 2.2528865 | F14: 2.2602394 | G14: 2.3936919 | H14: 1.8271183 | I14: =+('Maj Production Summ'!I17/3551)/('B-FCE'!E50+'B-FCE'!G50) -> 2.3174223 | J14: =+('Maj Production Summ'!J17/3551)/('B-FCE'!F50+'B-FCE'!H50) -> 2.10169 | K14: 2.4471009 | L14: 2.4868497 | M14: =+('Maj Production Summ'!M17/3551)/('B-FCE'!E50+'B-FCE'!G50+'B-FCE'!K50) -> 2.3662623 | N14: =+('Maj Production Summ'!N17/3551)/('B-FCE'!F50+'B-FCE'!H50+'B-FCE'!L50) -> 2.2513522 | O14: 2.3936919 | P14: 2.4358636 | Q14: =+('Maj Production Summ'!Q17/3551)/('B-FCE'!M50+'B-FCE'!O50) -> 2.3739528 | R14: =+('Maj Production Summ'!R17/3551)/('B-FCE'!N50+'B-FCE'!P50) -> 2.3047065 | S14: 2.3936919 | T14: 2.3754677 | U14: =+('Maj Production Summ'!U17/3551)/('B-FCE'!Q50+'B-FCE'!S50) -> 2.3782753 | V14: =+('Maj Production Summ'!V17/3551)/('B-FCE'!R50+'B-FCE'!T50) -> 2.3201883 | W14: 2.3168491 | X14: 2.3089599 | Y14: =+('Maj Production Summ'!Y17/3551)/('B-FCE'!P50+'B-FCE'!T50+'B-FCE'!X50) -> 2.0182054 | Z14: =+('Maj Production Summ'!Z17/3551)/('B-FCE'!P50+'B-FCE'!T50+'B-FCE'!X50) -> 2.3743513 | AA14: =+('Maj Production Summ'!AA17/3551)/('B-FCE'!M50+'B-FCE'!Y50) -> 2.3714885 | AB14: =+('Maj Production Summ'!AB17/3551)/('B-FCE'!N50+'B-FCE'!Z50) -> 2.318192 | AC14: 2.4406271 | AD14: 2.1223596 | AE14: =+('Maj Production Summ'!AE17/3551)/('B-FCE'!AA50+'B-FCE'!AC50) -> 2.38276 | AF14: =+('Maj Production Summ'!AF17/3551)/('B-FCE'!AB50+'B-FCE'!AD50) -> 2.2909837 | AG14: 2.4471009 | AH14: 2.3620869 | AI14: =+('Maj Production Summ'!AI17/3551)/('B-FCE'!AE50+'B-FCE'!AG50) -> 2.3915194 | AJ14: =+('Maj Production Summ'!AJ17/3551)/('B-FCE'!AF50+'B-FCE'!AH50) -> 2.3002671 | AK14: 2.4406271 | AL14: 2.3077233 | AM14: =+('Maj Production Summ'!AM17/3551)/('B-FCE'!AC50+'B-FCE'!AG50+'B-FCE'!AK50) -> 2.4427365 | AN14: =+('Maj Production Summ'!AN17/3551)/('B-FCE'!AD50+'B-FCE'!AH50+'B-FCE'!AL50) -> 2.2684138 | AO14: =+('Maj Production Summ'!AO17/3551)/('B-FCE'!AK50+'B-FCE'!AI50) -> 2.3975816 | AP14: =+('Maj Production Summ'!AP17/3551)/('B-FCE'!AL50+'B-FCE'!AJ50) -> 2.3011695 | AQ14: 2.4781752 | AR14: 2.2672002 | AS14: =+('Maj Production Summ'!AS17/3551)/('B-FCE'!AO50+'B-FCE'!AQ50) -> 2.4064375 | AT14: =+('Maj Production Summ'!AT17/3551)/('B-FCE'!AP50+'B-FCE'!AR50) -> 2.2975325 | AU14: 2.4614871 | AV14: 2.0074322 | AW14: =+('Maj Production Summ'!AW17/3551)/('B-FCE'!AS50+'B-FCE'!AU50) -> 2.4113917 | AX14: =+('Maj Production Summ'!AX17/3551)/('B-FCE'!AT50+'B-FCE'!AV50) -> 2.2718612 | AY14: 2.4781752 | AZ14: 2.3665177 | BA14: =+('Maj Production Summ'!BA17/3551)/('B-FCE'!AQ50+'B-FCE'!AU50+'B-FCE'!AY50) -> 2.4729961 | BB14: =+('Maj Production Summ'!BB17/3551)/('B-FCE'!AR50+'B-FCE'!AV50+'B-FCE'!AZ50) -> 2.2196034 | BC14: =+('Maj Production Summ'!BC17/3551)/('B-FCE'!AM50+'B-FCE'!BA50) -> 2.4576944 | BD14: =+('Maj Production Summ'!BD17/3551)/('B-FCE'!AN50+'B-FCE'!BB50) -> 2.2438374 | BE14: =+('Maj Production Summ'!BE17/3551)/('B-FCE'!AW50+'B-FCE'!AY50) -> 2.4174626 | BF14: =+('Maj Production Summ'!BF17/3551)/('B-FCE'!AX50+'B-FCE'!AZ50) -> 2.2801664 | BH14: 2.4361021 | BI14: 2.3236344 | BJ14: 2.3140113 | BK14: 2.2734567 | BL14: 2.2723639 | BM14: 2.1810142 | BN14: 2.2132463 | BO14: 2.0862545 | BP14: 2.2066158 | BQ14: 2.0192263 | BR14: 2.0565754 | BS14: 1.7450413 | BT14: 2.1585499 | BU14: 2.0057992 | BV14: 1.7419242
B15: Gross Coal to Hot Metal Ratio | C15: Kg/ THM | D15: 859.24202 | E15: 871.2139 | F15: =+'Coal to Hot Metal'!F20 -> 881.94094 | G15: 947.92239 | H15: =+'Coal to Hot Metal'!H20 -> 1000.1443 | I15: =+'Coal to Hot Metal'!I20 -> 907.53182 | J15: =+'Coal to Hot Metal'!J20 -> 919.55625 | K15: 866.91252 | L15: =+'Coal to Hot Metal'!L20 -> #REF! | M15: =+'Coal to Hot Metal'!M20 -> 893.57387 | N15: =+'Coal to Hot Metal'!N20 -> #REF! | O15: 866.91252 | P15: =+'Coal to Hot Metal'!P20 -> #REF! | Q15: =+((M15*'Maj Production Summ'!M$17)+('Maj Production Summ'!O$17*O15))/('Maj Production Summ'!Q$17) -> 886.03657 | R15: =+'Coal to Hot Metal'!R20 -> #REF! | S15: 866.91252 | T15: =+'Coal to Hot Metal'!T20 -> #REF! | U15: =+((Q15*'Maj Production Summ'!Q$17)+('Maj Production Summ'!S$17*S15))/('Maj Production Summ'!U$17) -> 881.82168 | V15: =+'Coal to Hot Metal'!V20 -> #REF! | W15: 973.86832 | X15: =+'Coal to Hot Metal'!X20 -> #REF! | Y15: =+'Coal to Hot Metal'!Y20 -> 894.94289 | Z15: =+'Coal to Hot Metal'!Z20 -> #REF! | AA15: =+((M15*'Maj Production Summ'!M$17)+('Maj Production Summ'!Y$17*Y15))/('Maj Production Summ'!AA$17) -> 894.25997 | AB15: =+'Coal to Hot Metal'!AB20 -> #REF! | AC15: 865.57463 | AD15: =+'Coal to Hot Metal'!AD20 -> #REF! | AE15: =+((AA15*'Maj Production Summ'!AA$17)+('Maj Production Summ'!AC$17*AC15))/('Maj Production Summ'!AE$17) -> 889.46987 | AF15: =+'Coal to Hot Metal'!AF20 -> #REF! | AG15: 865.57463 | AH15: =+'Coal to Hot Metal'!AH20 -> #REF! | AI15: =+((AE15*'Maj Production Summ'!AE$17)+('Maj Production Summ'!AG$17*AG15))/('Maj Production Summ'!AI$17) -> 886.14118 | AJ15: =+'Coal to Hot Metal'!AJ20 -> #REF! | AK15: 865.57463 | AL15: =+'Coal to Hot Metal'!AL20 -> #REF! | AM15: =+'Coal to Hot Metal'!AM20 -> 870.3318 | AN15: =+'Coal to Hot Metal'!AN20 -> #REF! | AO15: =+'Coal to Hot Metal'!AO20 -> 885.33172 | AP15: =+'Coal to Hot Metal'!AP20 -> #REF! | AQ15: 865.57463 | AR15: =+'Coal to Hot Metal'!AR20 -> #REF! | AS15: =+((AO15*'Maj Production Summ'!AO$17)+('Maj Production Summ'!AQ$17*AQ15))/('Maj Production Summ'!AS$17) -> 883.09602 | AT15: =+'Coal to Hot Metal'!AT20 -> #REF! | AU15: 865.57463 | AV15: =+'Coal to Hot Metal'!AV20 -> #REF! | AW15: =+((AS15*'Maj Production Summ'!AS$17)+('Maj Production Summ'!AU$17*AU15))/('Maj Production Summ'!AW$17) -> 881.48643 | AX15: =+'Coal to Hot Metal'!AX20 -> #REF! | AY15: 865.57463 | AZ15: =+'Coal to Hot Metal'!AZ20 -> #REF! | BA15: =+'Coal to Hot Metal'!BA20 -> 870.3318 | BB15: =+'Coal to Hot Metal'!BB20 -> #REF! | BC15: =+'Coal to Hot Metal'!BC20 -> 870.3318 | BD15: =+'Coal to Hot Metal'!BD20 -> #REF! | BE15: =+'Coal to Hot Metal'!BE20 -> 881.28656 | BF15: =+'Coal to Hot Metal'!BF20 -> #REF! | BH15: 871.29178 | BI15: 896.49806 | BJ15: 879.87436 | BK15: 887.52975 | BL15: 900.75554 | BM15: 932.03785 | BN15: 910.43802 | BO15: 930.86111 | BP15: 908.3767 | BQ15: 935.21205 | BR15: 907.50854 | BS15: 991.44637 | BT15: 886.42712 | BU15: 931.68363 | BV15: 905.6097
B16: Hot Metal to Crude Steel | C16: Kg/ TCS | D16: 1062 | E16: =+$D$16 -> 1062 | F16: =+(F56/'Maj Production Summ'!F18)*1000 -> 1055.9173 | G16: =+$D$16 -> 1062 | H16: =+(H56/'Maj Production Summ'!H18)*1000 -> 1046.1686 | I16: =+$D$16 -> 1062 | J16: =+(J56/'Maj Production Summ'!J18)*1000 -> 1052.944 | K16: =+$D$16 -> 1062 | L16: =+(L56/'Maj Production Summ'!L18)*1000 -> 1061.9197 | M16: =+$D$16 -> 1062 | N16: =+(N56/'Maj Production Summ'!N18)*1000 -> 1056.814 | O16: =+$D$16 -> 1062 | P16: =+(P56/'Maj Production Summ'!P18)*1000 -> 1051.7069 | Q16: =+$D$16 -> 1062 | R16: =+(R56/'Maj Production Summ'!R18)*1000 -> 1055.2309 | S16: =+$D$16 -> 1062 | T16: =+(T56/'Maj Production Summ'!T18)*1000 -> 1060.1658 | U16: =+$D$16 -> 1062 | V16: =+(V56/'Maj Production Summ'!V18)*1000 -> 1056.3414 | W16: =+$D$16 -> 1062 | X16: =+(X56/'Maj Production Summ'!X18)*1000 -> 1063.8153 | Y16: =+$D$16 -> 1062 | Z16: =+(Z56/'Maj Production Summ'!Z18)*1000 -> 1058.3307 | AA16: =+$D$16 -> 1062 | AB16: =+(AB56/'Maj Production Summ'!AB18)*1000 -> 1057.6631 | AC16: =+$D$16 -> 1062 | AD16: =+(AD56/'Maj Production Summ'!AD18)*1000 -> 1064.5745 | AE16: =+$D$16 -> 1062 | AF16: =+(AF56/'Maj Production Summ'!AF18)*1000 -> 1058.5103 | AG16: =+$D$16 -> 1062 | AH16: =+(AH56/'Maj Production Summ'!AH18)*1000 -> 1059.8754 | AI16: =+$D$16 -> 1062 | AJ16: =+(AJ56/'Maj Production Summ'!AJ18)*1000 -> 1058.6955 | AK16: =+$D$16 -> 1062 | AL16: =+(AL56/'Maj Production Summ'!AL18)*1000 -> 1068.1895 | AM16: =+$D$16 -> 1062 | AN16: =+(AN56/'Maj Production Summ'!AN18)*1000 -> 1064.215 | AO16: =+$D$16 -> 1062 | AP16: =+(AP56/'Maj Production Summ'!AP18)*1000 -> 1059.8509 | AQ16: =+$D$16 -> 1062 | AR16: =+(AR56/'Maj Production Summ'!AR18)*1000 -> 1062.1673 | AS16: =+$D$16 -> 1062 | AT16: =+(AT56/'Maj Production Summ'!AT18)*1000 -> 1060.0961 | AU16: =+$D$16 -> 1062 | AV16: =+(AV56/'Maj Production Summ'!AV18)*1000 -> 1052.2391 | AW16: =+$D$16 -> 1062 | AX16: =+(AX56/'Maj Production Summ'!AX18)*1000 -> 1059.4746 | AY16: =+$D$16 -> 1062 | AZ16: =+(AZ56/'Maj Production Summ'!AZ18)*1000 -> 1038.4428 | BA16: =+$D$16 -> 1062 | BB16: =+(BB56/'Maj Production Summ'!BB18)*1000 -> 1050.6128 | BC16: =+$D$16 -> 1062 | BD16: =+(BD56/'Maj Production Summ'!BD18)*1000 -> 1057.355 | BE16: =+$D$16 -> 1062 | BF16: =+(BF56/'Maj Production Summ'!BF18)*1000 -> 1057.5082 | BH16: 1059 | BI16: 1059.1268 | BJ16: 1060 | BK16: 1059.546 | BL16: 1060 | BM16: 1066.0114 | BN16: 1062 | BO16: 1062.9741 | BP16: 1064.9999 | BQ16: 1062.0577 | BR16: 1077.0434 | BS16: 1071.1761 | BT16: 1065 | BU16: 1093.6626 | BV16: 1078.33
B17: Scrap consumption | C17: Kg/ TCS | D17: 34 | E17: =+$D$17 -> 34 | F17: =+(F57/'Maj Production Summ'!F18)*1000 -> 40.079113 | G17: =+$D$17 -> 34 | H17: =+(H57/'Maj Production Summ'!H18)*1000 -> 49.211421 | I17: =+$D$17 -> 34 | J17: =+(J57/'Maj Production Summ'!J18)*1000 -> 42.864437 | K17: =+$D$17 -> 34 | L17: =+(L57/'Maj Production Summ'!L18)*1000 -> 34.520832 | M17: =+$D$17 -> 34 | N17: =+(N57/'Maj Production Summ'!N18)*1000 -> 39.266967 | O17: =+$D$17 -> 34 | P17: =+(P57/'Maj Production Summ'!P18)*1000 -> 44.526181 | Q17: =+$D$17 -> 34 | R17: =+(R57/'Maj Production Summ'!R18)*1000 -> 40.897248 | S17: =+$D$17 -> 34 | T17: =+(T57/'Maj Production Summ'!T18)*1000 -> 36.183939 | U17: =+$D$17 -> 34 | V17: =+(V57/'Maj Production Summ'!V18)*1000 -> 39.836579 | W17: =+$D$17 -> 34 | X17: =+(X57/'Maj Production Summ'!X18)*1000 -> 34.040565 | Y17: =+$D$17 -> 34 | Z17: =+(Z57/'Maj Production Summ'!Z18)*1000 -> 38.453569 | AA17: =+$D$17 -> 34 | AB17: =+(AB57/'Maj Production Summ'!AB18)*1000 -> 38.811604 | AC17: =+$D$17 -> 34 | AD17: =+(AD57/'Maj Production Summ'!AD18)*1000 -> 30.862551 | AE17: =+$D$17 -> 34 | AF17: =+(AF57/'Maj Production Summ'!AF18)*1000 -> 37.83725 | AG17: =+$D$17 -> 34 | AH17: =+(AH57/'Maj Production Summ'!AH18)*1000 -> 36.486828 | AI17: =+$D$17 -> 34 | AJ17: =+(AJ57/'Maj Production Summ'!AJ18)*1000 -> 37.654022 | AK17: =+$D$17 -> 34 | AL17: =+(AL57/'Maj Production Summ'!AL18)*1000 -> 27.934205 | AM17: =+$D$17 -> 34 | AN17: =+(AN57/'Maj Production Summ'!AN18)*1000 -> 31.802547 | AO17: =+$D$17 -> 34 | AP17: =+(AP57/'Maj Production Summ'!AP18)*1000 -> 36.471169 | AQ17: =+$D$17 -> 34 | AR17: =+(AR57/'Maj Production Summ'!AR18)*1000 -> 33.233062 | AS17: =+$D$17 -> 34 | AT17: =+(AT57/'Maj Production Summ'!AT18)*1000 -> 36.128328 | AU17: =+$D$17 -> 34 | AV17: =+(AV57/'Maj Production Summ'!AV18)*1000 -> 43.482726 | AW17: =+$D$17 -> 34 | AX17: =+(AX57/'Maj Production Summ'!AX18)*1000 -> 36.710089 | AY17: =+$D$17 -> 34 | AZ17: =+(AZ57/'Maj Production Summ'!AZ18)*1000 -> 54.990466 | BA17: =+(BA57/'Maj Production Summ'!BA18)*1000 -> 34 | BB17: =+(BB57/'Maj Production Summ'!BB18)*1000 -> 44.153244 | BC17: =+(BC57/'Maj Production Summ'!BC18)*1000 -> 34 | BD17: =+(BD57/'Maj Production Summ'!BD18)*1000 -> 38.031373 | BE17: =+(BE57/'Maj Production Summ'!BE18)*1000 -> 34 | BF17: =+(BF57/'Maj Production Summ'!BF18)*1000 -> 38.419281 | BH17: 38 | BI17: 36.899993 | BJ17: 40 | BK17: 37.680158 | BL17: 40 | BM17: 34.431041 | BN17: 46 | BO17: 38.506405 | BP17: 50 | BQ17: 45.611233 | BR17: 40.465028 | BS17: 41.122433 | BT17: 50 | BU17: 25.532166 | BV17: 41.130412
B18: TMI | C18: Kg/ TCS | D18: =SUM(D16:D17) -> 1096 | E18: =+$D$18 -> 1096 | F18: =SUM(F16:F17) -> 1095.9964 | G18: =+$D$18 -> 1096 | H18: =SUM(H16:H17) -> 1095.38 | I18: =+$D$18 -> 1096 | J18: =SUM(J16:J17) -> 1095.8084 | K18: =+$D$18 -> 1096 | L18: =SUM(L16:L17) -> 1096.4405 | M18: =+$D$18 -> 1096 | N18: =SUM(N16:N17) -> 1096.0809 | O18: =+$D$18 -> 1096 | P18: =SUM(P16:P17) -> 1096.2331 | Q18: =+$D$18 -> 1096 | R18: =SUM(R16:R17) -> 1096.1281 | S18: =+$D$18 -> 1096 | T18: =SUM(T16:T17) -> 1096.3497 | U18: =+$D$18 -> 1096 | V18: =SUM(V16:V17) -> 1096.178 | W18: =+$D$18 -> 1096 | X18: =SUM(X16:X17) -> 1097.8558 | Y18: =+$D$18 -> 1096 | Z18: =SUM(Z16:Z17) -> 1096.7843 | AA18: =+$D$18 -> 1096 | AB18: =SUM(AB16:AB17) -> 1096.4747 | AC18: =+$D$18 -> 1096 | AD18: =SUM(AD16:AD17) -> 1095.4371 | AE18: =+$D$18 -> 1096 | AF18: =SUM(AF16:AF17) -> 1096.3475 | AG18: =+$D$18 -> 1096 | AH18: =SUM(AH16:AH17) -> 1096.3623 | AI18: =+$D$18 -> 1096 | AJ18: =SUM(AJ16:AJ17) -> 1096.3495 | AK18: =+$D$18 -> 1096 | AL18: =SUM(AL16:AL17) -> 1096.1237 | AM18: =+$D$18 -> 1096 | AN18: =SUM(AN16:AN17) -> 1096.0175 | AO18: =+$D$18 -> 1096 | AP18: =SUM(AP16:AP17) -> 1096.322 | AQ18: =+$D$18 -> 1096 | AR18: =SUM(AR16:AR17) -> 1095.4004 | AS18: =+$D$18 -> 1096 | AT18: =SUM(AT16:AT17) -> 1096.2245 | AU18: =+$D$18 -> 1096 | AV18: =SUM(AV16:AV17) -> 1095.7219 | AW18: =+$D$18 -> 1096 | AX18: =SUM(AX16:AX17) -> 1096.1847 | AY18: =+$D$18 -> 1096 | AZ18: =SUM(AZ16:AZ17) -> 1093.4333 | BA18: =+$D$18 -> 1096 | BB18: =SUM(BB16:BB17) -> 1094.766 | BC18: =+$D$18 -> 1096 | BD18: =SUM(BD16:BD17) -> 1095.3863 | BE18: =+$D$18 -> 1096 | BF18: =SUM(BF16:BF17) -> 1095.9274 | BH18: 1097 | BI18: 1096.0268 | BJ18: 1100 | BK18: 1097.2261 | BL18: 1100 | BM18: 1100.4424 | BN18: 1108 | BO18: 1101.4805 | BP18: 1114.9999 | BQ18: 1107.6689 | BR18: 1117.5084 | BS18: 1112.2985 | BT18: 1115 | BU18: 1119.1948 | BV18: 1119.4604
B19: Ferro Alloys (FeMn+LCFeMn+SiMn+FeSi) | C19: Kg/ TCS | D19: =+D68+D69+D72 -> 18.044118 | E19: =+$D$19 -> 18.044118 | F19: =F68+F71+F72 -> 17.484522 | G19: =+$D$19 -> 18.044118 | H19: =H68+H71+H72 -> 17.037392 | I19: =+$D$19 -> 18.044118 | J19: =J68+J71+J72 -> 17.348149 | K19: =+$D$19 -> 18.044118 | L19: =L68+L71+L72 -> 19.733624 | M19: =+$D$19 -> 18.044118 | N19: =N68+N71+N72 -> 18.376682 | O19: =+$D$19 -> 18.044118 | P19: =P68+P71+P72 -> 20.120846 | Q19: =+$D$19 -> 18.044118 | R19: =R68+R71+R72 -> 18.917348 | S19: =+$D$19 -> 18.044118 | T19: =T68+T71+T72 -> 19.080809 | U19: =+$D$19 -> 18.044118 | V19: =V68+V71+V72 -> 18.954133 | W19: =+$D$19 -> 18.044118 | X19: =X68+X71+X72 -> 17.254405 | Y19: =+$D$19 -> 18.044118 | Z19: =Z68+Z71+Z72 -> 18.871242 | AA19: =+$D$19 -> 18.044118 | AB19: =AB68+AB71+AB72 -> 18.653551 | AC19: =+$D$19 -> 18.044118 | AD19: =AD68+AD71+AD72 -> 17.868204 | AE19: =+$D$19 -> 18.044118 | AF19: =AF68+AF71+AF72 -> 18.557287 | AG19: =+$D$19 -> 18.044118 | AH19: =AH68+AH71+AH72 -> 16.204652 | AI19: =+$D$19 -> 18.044118 | AJ19: =AJ68+AJ71+AJ72 -> 18.238078 | AK19: =+$D$19 -> 18.044118 | AL19: =AL68+AL71+AL72 -> 17.496341 | AM19: =+$D$19 -> 18.044118 | AN19: =AN68+AN71+AN72 -> 17.138981 | AO19: =+$D$19 -> 18.044118 | AP19: =AP68+AP71+AP72 -> 18.147812 | AQ19: =+$D$19 -> 18.044118 | AR19: =AR68+AR71+AR72 -> 17.201717 | AS19: =+$D$19 -> 18.044118 | AT19: =AT68+AT71+AT72 -> 18.047642 | AU19: =+$D$19 -> 18.044118 | AV19: =AV68+AV71+AV72 -> 16.786191 | AW19: =+$D$19 -> 18.044118 | AX19: =AX68+AX71+AX72 -> 17.947857 | AY19: =+$D$19 -> 18.044118 | AZ19: =AZ68+AZ71+AZ72 -> 17.903333 | BA19: =+$D$19 -> 18.044118 | BB19: =BB68+BB71+BB72 -> 17.342904 | BC19: =+$D$19 -> 18.044118 | BD19: =BD68+BD71+BD72 -> 17.241825 | BE19: =+$D$19 -> 18.044118 | BF19: =BF68+BF71+BF72 -> 17.943694 | BH19: 22.017292 | BI19: 18.349012 | BJ19: 23 | BK19: 20.403235 | BL19: 21.173677 | BM19: 22.701786 | BN19: 21 | BO19: 22.930617 | BP19: 21.95779 | BQ19: 20.936322 | BR19: 20.938578 | BS19: 20.212673 | BT19: 21 | BU19: 21.832464 | BV19: 23.120676
B20: Mill yield
B21: WR Mill | C21: % | D21: 96 | E21: =+$D$21 -> 96 | F21: =+WRM!F161 -> 95.64166 | G21: =+$D$21 -> 96 | H21: =+WRM!H161 -> 95.154918 | I21: =+$D$21 -> 96 | J21: =+WRM!J161 -> 95.474961 | K21: =+$D$21 -> 96 | L21: =+WRM!L161 -> 95.257541 | M21: =+$D$21 -> 96 | N21: =+WRM!N161 -> 95.143786 | O21: =+$D$21 -> 96 | P21: =+WRM!P161 -> 95.750554 | Q21: =+$D$21 -> 96 | R21: =+WRM!R161 -> 95.335711 | S21: =+$D$21 -> 96 | T21: =+WRM!T161 -> 95.876083 | U21: =+$D$21 -> 96 | V21: =+WRM!V161 -> 95.447175 | W21: =+$D$21 -> 96 | X21: =+WRM!X161 -> 95.610321 | Y21: =+$D$21 -> 96 | Z21: =+WRM!Z161 -> 95.743417 | AA21: =+$D$21 -> 96 | AB21: =+WRM!AB161 -> 95.476493 | AC21: =+$D$21 -> 96 | AD21: =+WRM!AD161 -> 95.95434 | AE21: =+$D$21 -> 96 | AF21: =+WRM!AF161 -> 95.531896 | AG21: =+$D$21 -> 96 | AH21: =+WRM!AH161 -> 95.766381 | AI21: =+$D$21 -> 96 | AJ21: =+WRM!AJ161 -> 95.559583 | AK21: =+$D$21 -> 96 | AL21: =+WRM!AL161 -> 95.336202 | AM21: =+$D$21 -> 96 | AN21: =+WRM!AN161 -> 95.643378 | AO21: =+$D$21 -> 96 | AP21: =+WRM!AP161 -> 95.530312 | AQ21: =+$D$21 -> 96 | AR21: =+WRM!AR161 -> 95.804245 | AS21: =+$D$21 -> 96 | AT21: =+WRM!AT161 -> 95.56228 | AU21: =+$D$21 -> 96 | AV21: =+WRM!AV161 -> 95.614821 | AW21: =+$D$21 -> 96 | AX21: =+WRM!AX161 -> 95.566976 | AY21: =+$D$21 -> 96 | AZ21: =+WRM!AZ161 -> 95.474823 | BA21: =+$D$21 -> 96 | BB21: =+WRM!BB161 -> 95.629455 | BC21: =+$D$21 -> 96 | BD21: =+WRM!BD161 -> 95.635828 | BE21: =+$D$21 -> 96 | BF21: =+WRM!BF161 -> 95.557719 | BH21: 96 | BI21: 95.645148 | BJ21: 96 | BK21: 95.818831 | BL21: 96 | BM21: 95.881785 | BN21: 96 | BO21: 95.450038 | BP21: 96 | BQ21: 95.505336 | BR21: 96.222984 | BS21: 94.958654 | BT21: 96.5 | BU21: 96.195271 | BV21: 96.032659
B22: Bar Mill | C22: % | D22: 96.5 | E22: =+$D$22 -> 96.5 | F22: =+BM!F58 -> 95.918611 | G22: =+$D$22 -> 96.5 | H22: =+BM!H58 -> 95.96124 | I22: =+$D$22 -> 96.5 | J22: =+BM!J58 -> 95.931726 | K22: =+$D$22 -> 96.5 | L22: =+BM!L58 -> 96.41942 | M22: =+$D$22 -> 96.5 | N22: =+BM!N58 -> 96.129015 | O22: =+$D$22 -> 96.5 | P22: =+BM!P58 -> 96.454668 | Q22: =+$D$22 -> 96.5 | R22: =+BM!R58 -> 96.235155 | S22: =+$D$22 -> 96.5 | T22: =+BM!T58 -> 96.32902 | U22: =+$D$22 -> 96.5 | V22: =+BM!V58 -> 96.255753 | W22: =+$D$22 -> 96.5 | X22: =+BM!X58 -> 96.394637 | Y22: =+$D$22 -> 96.5 | Z22: =+BM!Z58 -> 96.395895 | AA22: =+$D$22 -> 96.5 | AB22: =+BM!AB58 -> 96.280857 | AC22: =+$D$22 -> 96.5 | AD22: =+BM!AD58 -> 96.409969 | AE22: =+$D$22 -> 96.5 | AF22: =+BM!AF58 -> 96.294757 | AG22: =+$D$22 -> 96.5 | AH22: =+BM!AH58 -> 96.083718 | AI22: =+$D$22 -> 96.5 | AJ22: =+BM!AJ58 -> 96.267578 | AK22: =+$D$22 -> 96.5 | AL22: =+BM!AL58 -> 95.865818 | AM22: =+$D$22 -> 96.5 | AN22: =+BM!AN58 -> 96.077498 | AO22: =+$D$22 -> 96.5 | AP22: =+BM!AP58 -> 96.214839 | AQ22: =+$D$22 -> 96.5 | AR22: =+BM!AR58 -> 95.990775 | AS22: =+$D$22 -> 96.5 | AT22: =+BM!AT58 -> 96.187698 | AU22: =+$D$22 -> 96.5 | AV22: =+BM!AV58 -> 95.960644 | AW22: =+$D$22 -> 96.5 | AX22: =+BM!AX58 -> 96.166201 | AY22: =+$D$22 -> 96.5 | AZ22: =+BM!AZ58 -> 93.352458 | BA22: =+$D$22 -> 96.5 | BB22: =+BM!BB58 -> 95.076496 | BC22: =+$D$22 -> 96.5 | BD22: =+BM!BD58 -> 95.530624 | BE22: =+$D$22 -> 96.5 | BF22: =+BM!BF58 -> 95.894898 | BH22: 96.5 | BI22: 95.975857 | BJ22: 96.5 | BK22: 96.286951 | BL22: 96.5 | BM22: 96.088708 | BN22: 96.5 | BO22: 95.450022 | BP22: 96.499982 | BQ22: 95.423966 | BR22: 96.209843 | BS22: 95.175924 | BT22: 96.5 | BU22: 96.065593 | BV22: 96.05494
B23: US Mill | C23: % | D23: 94.75 | E23: =+$D$23 -> 94.75 | F23: =+USM!G123 -> 93.988403 | G23: =+$D$23 -> 94.75 | H23: =+USM!I123 -> 92.538149 | I23: =+$D$23 -> 94.75 | J23: =+USM!K123 -> 93.742927 | K23: =+$D$23 -> 94.75 | L23: =+USM!M123 -> 94.300658 | M23: =+$D$23 -> 94.75 | N23: =+USM!O123 -> 92.597989 | O23: =+$D$23 -> 94.75 | P23: =+USM!Q123 -> 94.039737 | Q23: =+$D$23 -> 94.75 | R23: =+USM!S123 -> 90.479723 | S23: =+$D$23 -> 94.75 | T23: =+USM!U123 -> 93.446166 | U23: =+$D$23 -> 94.75 | V23: =+USM!W123 -> 91.072106 | W23: =+$D$23 -> 94.75 | X23: =+USM!Y123 -> 93.97245 | Y23: =+$D$23 -> 94.75 | Z23: =+USM!AA123 -> 93.84314 | AA23: =+$D$23 -> 94.75 | AB23: =+USM!AC123 -> 93.289413 | AC23: =+$D$23 -> 94.75 | AD23: =+USM!AE123 -> 93.165856 | AE23: =+$D$23 -> 94.75 | AF23: =+USM!AG123 -> 93.277235 | AG23: =+$D$23 -> 94.75 | AH23: =+USM!AI123 -> 93.342594 | AI23: =+$D$23 -> 94.75 | AJ23: =+USM!AK123 -> 93.286382 | AK23: =+$D$23 -> 94.75 | AL23: =+USM!AM123 -> 93.351849 | AM23: =+$D$23 -> 94.75 | AN23: =+USM!AO123 -> 93.306455 | AO23: =+$D$23 -> 94.75 | AP23: =+USM!AQ123 -> 93.294977 | AQ23: =+$D$23 -> 94.75 | AR23: =+USM!AS123 -> 93.241261 | AS23: =+$D$23 -> 94.75 | AT23: =+USM!AU123 -> 93.288408 | AU23: =+$D$23 -> 94.75 | AV23: =+USM!AW123 -> 94.339918 | AW23: =+$D$23 -> 94.75 | AX23: =+USM!AY123 -> 93.398386 | AY23: =+$D$23 -> 94.75 | AZ23: =+USM!BA123 -> 94.146465 | BA23: =+$D$23 -> 94.75 | BB23: =+USM!BC123 -> 93.911642 | BC23: =+$D$23 -> 94.75 | BD23: =+USM!BE123 -> 93.649583 | BE23: =+$D$23 -> 94.75 | BF23: =+USM!BG123 -> 93.479655 | BH23: 94.75 | BI23: 93.784865 | BJ23: 94.75 | BK23: 93.736035 | BL23: 94.5 | BM23: 94.168642 | BN23: 94.5 | BO23: 93.371871 | BP23: 95.700065 | BQ23: 93.445481 | BR23: 95.699819 | BS23: 95.266762 | BT23: 95.7 | BU23: 95.476013 | BV23: 95.486333
B24: Sp Energy Consumption | C24: G.cal/TCS | D24: 5.886278 | E24: 6.0987917 | F24: =EMD!E128 -> 6.1129634 | G24: 6.2451991 | H24: =EMD!G128 -> 7.3224223 | I24: =EMD!H128 -> 6.1674202 | J24: =EMD!I128 -> 6.4818445 | K24: 5.8881875 | L24: =EMD!K128 -> 5.9510025 | M24: =EMD!L128 -> 5.9135486 | N24: =EMD!M128 -> 6.0018291 | O24: 5.9044904 | P24: =EMD!O128 -> 5.923191 | Q24: =+EMD!P128 -> 5.9112818 | R24: =+EMD!Q128 -> 5.9807715 | S24: 5.9110636 | T24: =EMD!S128 -> 6.0281542 | U24: =+EMD!T128 -> 5.9112381 | V24: =+EMD!U128 -> 5.9902738 | W24: 6.4404862 | X24: =EMD!W128 -> 6.2161034 | Y24: =+EMD!X128 -> 6.0185038 | Z24: =+EMD!Y128 -> 6.0504489 | AA24: =+EMD!Z128 -> 5.9615466 | AB24: =+EMD!AA128 -> 6.0267097 | AC24: 5.897773 | AD24: =EMD!AC128 -> 6.5564134 | AE24: =+EMD!AD128 -> 5.9515643 | AF24: =+EMD!AE128 -> 6.0869784 | AG24: 5.9674105 | AH24: =EMD!AG128 -> 6.0353483 | AI24: =+EMD!AH128 -> 5.9533717 | AJ24: =+EMD!AI128 -> 6.0801532 | AK24: 5.961908 | AL24: =EMD!AK128 -> 6.1355366 | AM24: =+EMD!AL128 -> 5.9413396 | AN24: =+EMD!AM128 -> 6.2170648 | AO24: =+EMD!AN128 -> 5.9544517 | AP24: =+EMD!AO128 -> 6.0868931 | AQ24: 5.95667 | AR24: 6.1463269 | AS24: =+EMD!AR128 -> 5.9547042 | AT24: =+EMD!AS128 -> 6.0931858 | AU24: 5.9639133 | AV24: 6.1805508 | AW24: =+EMD!AV128 -> 5.9555545 | AX24: =+EMD!AW128 -> 6.0935992 | AY24: 5.8906678 | AZ24: 5.9116956 | BA24: =+EMD!AZ128 -> 5.9360969 | BB24: =+EMD!BA128 -> 6.0462703 | BC24: =+EMD!BB128 -> 5.938732 | BD24: =+EMD!BC128 -> 6.130928 | BE24: =+EMD!BD128 -> 5.9494778 | BF24: =+EMD!BE128 -> 6.0765915 | BH24: 5.9496425 | BI24: 6.0875484 | BJ24: 5.950002 | BK24: 6.1600133 | BL24: 5.9498029 | BM24: 6.1924446 | BN24: 5.9892031 | BO24: 6.2012038 | BP24: 5.9854778 | BQ24: 6.300637 | BR24: 6.1969869 | BS24: 6.4827566 | BT24: 5.95 | BU24: 6.1800191 | BV24: 6.3116941
B25: Sp Power Consumption with oxygen plant | C25: KwH/TSS | D25: 458.20337 | E25: 494.08443 | F25: =+'POWER DISTRIBUTION'!J17/('Maj Production Summ'!F37+0.25*'Maj Production Summ'!F26) -> 492.29361 | G25: 516.21138 | H25: =+'POWER DISTRIBUTION'!L17/('Maj Production Summ'!H37+0.25*'Maj Production Summ'!H26) -> 777.28876 | I25: =+'POWER DISTRIBUTION'!M17/('Maj Production Summ'!I37+0.25*'Maj Production Summ'!I26) -> 504.72404 | J25: =+'POWER DISTRIBUTION'!N17/('Maj Production Summ'!J37+0.25*'Maj Production Summ'!J26) -> 578.07116 | K25: 461.3094 | L25: =+'POWER DISTRIBUTION'!P17/('Maj Production Summ'!L37+0.25*'Maj Production Summ'!L26) -> 452.70789 | M25: =+'POWER DISTRIBUTION'!Q17/('Maj Production Summ'!M37+0.25*'Maj Production Summ'!M26) -> 487.5885 | N25: =+'POWER DISTRIBUTION'!R17/('Maj Production Summ'!N37+0.25*'Maj Production Summ'!N26) -> 523.78919 | O25: 467.74394 | P25: =+'POWER DISTRIBUTION'!T17/('Maj Production Summ'!P37+0.25*'Maj Production Summ'!P26) -> 442.75385 | Q25: =+'POWER DISTRIBUTION'!U17/('Maj Production Summ'!Q37+0.25*'Maj Production Summ'!Q26) -> 481.92875 | R25: =+'POWER DISTRIBUTION'!V17/('Maj Production Summ'!R37+0.25*'Maj Production Summ'!R26) -> 498.19739 | S25: 467.74394 | T25: =+'POWER DISTRIBUTION'!X17/('Maj Production Summ'!T37+0.25*'Maj Production Summ'!T26) -> 478.6447 | U25: =+'POWER DISTRIBUTION'!Y17/('Maj Production Summ'!U37+0.25*'Maj Production Summ'!U26) -> 478.78096 | V25: =+'POWER DISTRIBUTION'!Z17/('Maj Production Summ'!V37+0.25*'Maj Production Summ'!V26) -> 493.86725 | W25: 583.45256 | X25: =+'POWER DISTRIBUTION'!AB17/('Maj Production Summ'!X37+0.25*'Maj Production Summ'!X26) -> 460.52955 | Y25: =+'POWER DISTRIBUTION'!AC17/('Maj Production Summ'!Y37+0.25*'Maj Production Summ'!Y26) -> 491.95795 | Z25: =+'POWER DISTRIBUTION'!AD17/('Maj Production Summ'!Z37+0.25*'Maj Production Summ'!Z26) -> 460.01162 | AA25: =+'POWER DISTRIBUTION'!AE17/('Maj Production Summ'!AA37+0.25*'Maj Production Summ'!AA26) -> 489.78322 | AB25: =+'POWER DISTRIBUTION'!AF17/('Maj Production Summ'!AB37+0.25*'Maj Production Summ'!AB26) -> 487.73689 | AC25: 460.88039 | AD25: =+'POWER DISTRIBUTION'!AH17/('Maj Production Summ'!AD37+0.25*'Maj Production Summ'!AD26) -> 521.9908 | AE25: =+'POWER DISTRIBUTION'!AI17/('Maj Production Summ'!AE37+0.25*'Maj Production Summ'!AE26) -> 484.90857 | AF25: =+'POWER DISTRIBUTION'!AJ17/('Maj Production Summ'!AF37+0.25*'Maj Production Summ'!AF26) -> 492.13842 | AG25: 462.80371 | AH25: =+'POWER DISTRIBUTION'!AL17/('Maj Production Summ'!AH37+0.25*'Maj Production Summ'!AH26) -> 473.49811 | AI25: =+'POWER DISTRIBUTION'!AM17/('Maj Production Summ'!AI37+0.25*'Maj Production Summ'!AI26) -> 481.80536 | AJ25: =+'POWER DISTRIBUTION'!AN17/('Maj Production Summ'!AJ37+0.25*'Maj Production Summ'!AJ26) -> 489.64755 | AK25: 463.03105 | AL25: =+'POWER DISTRIBUTION'!AP17/('Maj Production Summ'!AL37+0.25*'Maj Production Summ'!AL26) -> 443.87204 | AM25: =+'POWER DISTRIBUTION'!AQ17/('Maj Production Summ'!AM37+0.25*'Maj Production Summ'!AM26) -> 462.23235 | AN25: =+'POWER DISTRIBUTION'!AR17/('Maj Production Summ'!AN37+0.25*'Maj Production Summ'!AN26) -> 476.38291 | AO25: =+'POWER DISTRIBUTION'!AS17/('Maj Production Summ'!AO37+0.25*'Maj Production Summ'!AO26) -> 479.42811 | AP25: =+'POWER DISTRIBUTION'!AT17/('Maj Production Summ'!AP37+0.25*'Maj Production Summ'!AP26) -> 483.87451 | AQ25: 459.24603 | AR25: =+'POWER DISTRIBUTION'!AV17/('Maj Production Summ'!AR37+0.25*'Maj Production Summ'!AR26) -> 461.48647 | AS25: =+'POWER DISTRIBUTION'!AW17/('Maj Production Summ'!AS37+0.25*'Maj Production Summ'!AS26) -> 477.13011 | AT25: =+'POWER DISTRIBUTION'!AX17/('Maj Production Summ'!AT37+0.25*'Maj Production Summ'!AT26) -> 481.43203 | AU25: 463.10735 | AV25: =+'POWER DISTRIBUTION'!AZ17/('Maj Production Summ'!AV37+0.25*'Maj Production Summ'!AV26) -> 502.65661 | AW25: =+'POWER DISTRIBUTION'!BA17/('Maj Production Summ'!AW37+0.25*'Maj Production Summ'!AW26) -> 475.83751 | AX25: =+'POWER DISTRIBUTION'!BB17/('Maj Production Summ'!AX37+0.25*'Maj Production Summ'!AX26) -> 483.17461 | AY25: 459.76937 | AZ25: =+'POWER DISTRIBUTION'!BD17/('Maj Production Summ'!AZ37+0.25*'Maj Production Summ'!AZ26) -> 450.62512 | BA25: =+'POWER DISTRIBUTION'!BE17/('Maj Production Summ'!BA37+0.25*'Maj Production Summ'!BA26) -> 460.61776 | BB25: =+'POWER DISTRIBUTION'!BF17/('Maj Production Summ'!BB37+0.25*'Maj Production Summ'!BB26) -> 469.3544 | BC25: =+'POWER DISTRIBUTION'!BG17/('Maj Production Summ'!BC37+0.25*'Maj Production Summ'!BC26) -> 461.42968 | BD25: =+'POWER DISTRIBUTION'!BH17/('Maj Production Summ'!BD37+0.25*'Maj Production Summ'!BD26) -> 472.81899 | BE25: =+'POWER DISTRIBUTION'!BI17/('Maj Production Summ'!BE37+0.25*'Maj Production Summ'!BE26) -> 474.33218 | BF25: =+'POWER DISTRIBUTION'!BJ17/('Maj Production Summ'!BF37+0.25*'Maj Production Summ'!BF26) -> 480.11059 | BH25: 468.12374 | BI25: 466.61606 | BJ25: 498.86963 | BK25: 491.52958 | BL25: 491.86598 | BM25: 499.12041 | BN25: 499.14523 | BO25: 516.74946 | BP25: 501.08848 | BQ25: 528.34198 | BR25: 500.04339 | BS25: 579.80533 | BT25: 483.423 | BU25: 525.26173 | BV25: 552.03691
C26: KwH/TCS | D26: 440.96351 | E26: 465.50188 | F26: =+'POWER DISTRIBUTION'!J17/'Maj Production Summ'!F18 -> 460.56724 | G26: 510.51865 | H26: =+'POWER DISTRIBUTION'!L17/'Maj Production Summ'!H18 -> 713.49131 | I26: =+'POWER DISTRIBUTION'!M17/'Maj Production Summ'!I18 -> 486.60349 | J26: =+'POWER DISTRIBUTION'!N17/'Maj Production Summ'!J18 -> 537.70826 | K26: 445.92427 | L26: =+'POWER DISTRIBUTION'!P17/'Maj Production Summ'!L18 -> 424.25451 | M26: =+'POWER DISTRIBUTION'!Q17/'Maj Production Summ'!M18 -> 470.57328 | N26: =+'POWER DISTRIBUTION'!R17/'Maj Production Summ'!N18 -> 488.79098 | O26: 451.67958 | P26: =+'POWER DISTRIBUTION'!T17/'Maj Production Summ'!P18 -> 424.51702 | Q26: =+'POWER DISTRIBUTION'!U17/'Maj Production Summ'!Q18 -> 465.18692 | R26: =+'POWER DISTRIBUTION'!V17/'Maj Production Summ'!R18 -> 468.86696 | S26: 451.67958 | T26: =+'POWER DISTRIBUTION'!X17/'Maj Production Summ'!T18 -> 441.26841 | U26: =+'POWER DISTRIBUTION'!Y17/'Maj Production Summ'!U18 -> 462.19042 | V26: =+'POWER DISTRIBUTION'!Z17/'Maj Production Summ'!V18 -> 462.65627 | W26: 568.25163 | X26: =+'POWER DISTRIBUTION'!AB17/'Maj Production Summ'!X18 -> 452.48637 | Y26: =+'POWER DISTRIBUTION'!AC17/'Maj Production Summ'!Y18 -> 475.90977 | Z26: =+'POWER DISTRIBUTION'!AD17/'Maj Production Summ'!Z18 -> 438.89498 | AA26: =+'POWER DISTRIBUTION'!AE17/'Maj Production Summ'!AA18 -> 473.25059 | AB26: =+'POWER DISTRIBUTION'!AF17/'Maj Production Summ'!AB18 -> 460.85781 | AC26: 445.88079 | AD26: =+'POWER DISTRIBUTION'!AH17/'Maj Production Summ'!AD18 -> 520.56797 | AE26: =+'POWER DISTRIBUTION'!AI17/'Maj Production Summ'!AE18 -> 468.63929 | AF26: =+'POWER DISTRIBUTION'!AJ17/'Maj Production Summ'!AF18 -> 468.17677 | AG26: 447.36773 | AH26: =+'POWER DISTRIBUTION'!AL17/'Maj Production Summ'!AH18 -> 442.57475 | AI26: =+'POWER DISTRIBUTION'!AM17/'Maj Production Summ'!AI18 -> 465.65359 | AJ26: =+'POWER DISTRIBUTION'!AN17/'Maj Production Summ'!AJ18 -> 464.70305 | AK26: 447.96245 | AL26: =+'POWER DISTRIBUTION'!AP17/'Maj Production Summ'!AL18 -> 438.77258 | AM26: =+'POWER DISTRIBUTION'!AQ17/'Maj Production Summ'!AM18 -> 447.06723 | AN26: =+'POWER DISTRIBUTION'!AR17/'Maj Production Summ'!AN18 -> 462.92309 | AO26: =+'POWER DISTRIBUTION'!AS17/'Maj Production Summ'!AO18 -> 463.41548 | AP26: =+'POWER DISTRIBUTION'!AT17/'Maj Production Summ'!AP18 -> 461.54744 | AQ26: 444.0148 | AR26: =+'POWER DISTRIBUTION'!AV17/'Maj Production Summ'!AR18 -> 455.22208 | AS26: =+'POWER DISTRIBUTION'!AW17/'Maj Production Summ'!AS18 -> 461.20692 | AT26: =+'POWER DISTRIBUTION'!AX17/'Maj Production Summ'!AT18 -> 460.87773 | AU26: 446.83745 | AV26: =+'POWER DISTRIBUTION'!AZ17/'Maj Production Summ'!AV18 -> 501.06568 | AW26: =+'POWER DISTRIBUTION'!BA17/'Maj Production Summ'!AW18 -> 459.88017 | AX26: =+'POWER DISTRIBUTION'!BB17/'Maj Production Summ'!AX18 -> 464.05675 | AY26: 444.52083 | AZ26: =+'POWER DISTRIBUTION'!BD17/'Maj Production Summ'!AZ18 -> 436.04258 | BA26: =+'POWER DISTRIBUTION'!BE17/'Maj Production Summ'!BA18 -> 445.06135 | BB26: =+'POWER DISTRIBUTION'!BF17/'Maj Production Summ'!BB18 -> 461.11375 | BC26: =+'POWER DISTRIBUTION'!BG17/'Maj Production Summ'!BC18 -> 446.06953 | BD26: =+'POWER DISTRIBUTION'!BH17/'Maj Production Summ'!BD18 -> 462.01058 | BE26: =+'POWER DISTRIBUTION'!BI17/'Maj Production Summ'!BE18 -> 458.44174 | BF26: =+'POWER DISTRIBUTION'!BJ17/'Maj Production Summ'!BF18 -> 461.43746 | BH26: 452.63469 | BI26: 450.63202 | BJ26: 483.40224 | BK26: 471.62787 | BL26: 475.02939 | BM26: 476.24946 | BN26: 482.32053 | BO26: 494.76974 | BP26: 486.14726 | BQ26: 514.38476 | BR26: 487.74658 | BS26: 580.20286 | BT26: 448.29125 | BU26: 538.52024 | BV26: 565.51994
B27: Sp Water Consumption | C27: M³/TCS | D27: 2.8 | E27: =+$D$27 -> 2.8 | F27: 2.82 | G27: =+$D$27 -> 2.8 | H27: 2.82 | I27: =+$D$27 -> 2.8 | J27: =+((F27*F33)+(H27*H33))/J33 -> 2.82 | K27: =+$D$27 -> 2.8 | L27: 2.96 | M27: =+$D$27 -> 2.8 | N27: =+((F33*F27)+(H33*H27)+(L33*L27))/N33 -> 2.8803631 | O27: =+$D$27 -> 2.8 | P27: 2.9 | Q27: =+$D$27 -> 2.8 | R27: =+(((N27*N33)+(P27*P33))/R33) -> 2.8864503 | S27: =+$D$27 -> 2.8 | T27: 2.9 | U27: =+$D$27 -> 2.8 | V27: =+(((R27*R33)+(T27*T33))/V33) -> 2.8894995 | W27: =+$D$27 -> 2.8 | X27: 2.905 | Y27: =+$D$27 -> 2.8 | Z27: =+((P33*P27)+(T33*T27)+(X33*X27))/Z33 -> 2.9015794 | AA27: =+$D$27 -> 2.8 | AB27: =+((N27*N33)+(Z27*Z33))/AB33 -> 2.8922406 | AC27: =+$D$27 -> 2.8 | AD27: 2.94 | AE27: =+$D$27 -> 2.8 | AF27: =+(((AB27*AB33)+(AD27*AD33))/AF33) -> 2.8980947 | AG27: =+$D$27 -> 2.8 | AH27: 2.86 | AI27: =+$D$27 -> 2.8 | AJ27: =+(((AF27*AF33)+(AH27*AH33))/AJ33) -> 2.8929259 | AK27: =+$D$27 -> 2.8 | AL27: 2.87 | AM27: =+$D$27 -> 2.8 | AN27: =+((AD33*AD27)+(AH33*AH27)+(AL33*AL27))/AN33 -> 2.8859377 | AO27: =+$D$27 -> 2.8 | AP27: =+(((AL27*AL33)+(AJ27*AJ33))/AP33) -> 2.890136 | AQ27: 2.85 | AR27: 2.88 | AS27: =+$D$27 -> 2.8 | AT27: =+(((AP27*AP33)+(AR27*AR33))/AT33) -> 2.8890628 | AU27: 2.85 | AV27: 2.86 | AW27: =+$D$27 -> 2.8 | AX27: =+(((AT27*AT33)+(AV27*AV33))/AX33) -> 2.8867638 | AY27: 2.85 | AZ27: 2.87 | BA27: =+$D$27 -> 2.8 | BB27: =+((AR27*AR33)+(AV27*AV33)+(AZ27*AZ33))/BB33 -> 2.8706577 | BC27: =+$D$27 -> 2.8 | BD27: =+((AN27*AN33)+(BB27*BB33))/BD33 -> 2.8782315 | BE27: =+$D$27 -> 2.8 | BF27: =+((AX27*AX33)+(AZ27*AZ33))/BF33 -> 2.8851964 | BH27: 2.85 | BI27: 2.9076318 | BJ27: 2.85 | BK27: 2.9919746 | BL27: 2.85 | BM27: 3.0828892 | BN27: 3.3 | BO27: 3.0186532 | BP27: 4.3 | BQ27: 3.3197104 | BR27: 4.3 | BS27: 5.0407394 | BT27: 4.6 | BU27: 5.0056729 | BV27: 5.0192042
B28: Sp. CO2 emission (New WSA methodolgy) | C28: T/TCS | D28: 2.51 | E28: =+$D$28 -> 2.51 | F28: 2.68 | G28: =+$D$28 -> 2.51 | H28: 3.08 | I28: =+$D$28 -> 2.51 | J28: =+((F28*F33)+(H28*H33))/J33 -> 2.8019987 | K28: =+$D$28 -> 2.51 | L28: 2.34 | M28: =+$D$28 -> 2.51 | N28: =+((F33*F28)+(H33*H28)+(L33*L28))/N33 -> 2.602801 | O28: =+$D$28 -> 2.51 | P28: 2.35 | Q28: =+$D$28 -> 2.51 | R28: =+((N28*N33)+(P28*P33))/R33 -> 2.5244363 | S28: =+$D$28 -> 2.51 | T28: 2.4 | U28: =+$D$28 -> 2.51 | V28: =+((R28*R33)+(T28*T33))/V33 -> 2.4964335 | W28: =+$D$28 -> 2.51 | X28: 2.45 | Y28: =+$D$28 -> 2.51 | Z28: =+((P33*P28)+(T33*T28)+(X33*X28))/Z33 -> 2.398133 | AA28: =+$D$28 -> 2.51 | AB28: =+((N28*N33)+(Z28*Z33))/AB33+0.01 -> 2.4982222 | AC28: =+$D$28 -> 2.51 | AD28: 2.78 | AE28: =+$D$28 -> 2.51 | AF28: =+((AB28*AB33)+(AD28*AD33))/AF33 -> 2.532761 | AG28: =+$D$28 -> 2.51 | AH28: 2.41 | AI28: =+$D$28 -> 2.51 | AJ28: =+(((AF28*AF33)+(AH28*AH33))/AJ33)-0.01 -> 2.5061046 | AK28: =+$D$28 -> 2.51 | AL28: 2.4 | AM28: =+$D$28 -> 2.51 | AN28: =+((AD33*AD28)+(AH33*AH28)+(AL33*AL28))/AN33 -> 2.5094618 | AO28: =+$D$28 -> 2.51 | AP28: =+((AL28*AL33)+(AJ28*AJ33))/AP33 -> 2.4931922 | AQ28: =+$D$28 -> 2.51 | AR28: 2.4 | AS28: =+$D$28 -> 2.51 | AT28: =+((AP28*AP33)+(AR28*AR33))/AT33 -> 2.4833253 | AU28: =+$D$28 -> 2.51 | AV28: 2.48 | AW28: =+$D$28 -> 2.51 | AX28: =+((AT28*AT33)+(AV28*AV33))/AX33 -> 2.4830623 | AY28: =+$D$28 -> 2.51 | AZ28: 2.37 | BA28: =+$D$28 -> 2.51 | BB28: =+((AR28*AR33)+(AV28*AV33)+(AZ28*AZ33))/BB33 -> 2.4115605 | BC28: =+$D$28 -> 2.51 | BD28: =+((AN28*AN33)+(BB28*BB33))/BD33 -> 2.4600873 | BE28: =+$D$28 -> 2.51 | BF28: =+((AX28*AX33)+(AZ28*AZ33))/BF33 -> 2.4724911 | BH28: 2.2695882 | BI28: 2.4090646 | BJ28: 2.32 | BK28: 2.3695074 | BL28: 2.375 | BM28: 2.4275692 | BN28: 2.35 | BO28: 2.4470555 | BP28: 2.45 | BQ28: 2.4734992 | BR28: 2.45 | BS28: 2.6211068 | BT28: 2.456658 | BU28: 2.4355942 | BV28: 2.609953
B29: Sp. PM emissions | C29: kg/TCS | D29: 0.5 | E29: =+$D$29 -> 0.5 | F29: 0.52 | G29: =+$D$29 -> 0.5 | H29: 0.56 | I29: =+$D$29 -> 0.5 | J29: =+((F29*F33)+(H29*H33))/J33 -> 0.53219987 | K29: =+$D$29 -> 0.5 | L29: 0.5 | M29: =+$D$29 -> 0.5 | N29: =+((F33*F29)+(H33*H29)+(L33*L29))/N33 -> 0.51831641 | O29: =+$D$29 -> 0.5 | P29: 0.5 | Q29: =+$D$29 -> 0.5 | R29: =+((N29*N33)+(P29*P33))/R33 -> 0.51263859 | S29: =+$D$29 -> 0.5 | T29: 0.5 | U29: =+$D$29 -> 0.5 | V29: =+((R29*R33)+(T29*T33))/V33 -> 0.50979444 | W29: =+$D$29 -> 0.5 | X29: 0.5 | Y29: =+$D$29 -> 0.5 | Z29: =+((P33*P29)+(T33*T29)+(X33*X29))/Z33 -> 0.5 | AA29: =+$D$29 -> 0.5 | AB29: =+((N29*N33)+(Z29*Z33))/AB33 -> 0.50806237 | AC29: =+$D$29 -> 0.5 | AD29: 0.5 | AE29: =+$D$29 -> 0.5 | AF29: =+((AB29*AB33)+(AD29*AD33))/AF33 -> 0.50707413 | AG29: =+$D$29 -> 0.5 | AH29: 0.46 | AI29: =+$D$29 -> 0.5 | AJ29: =+((AF29*AF33)+(AH29*AH33))/AJ33 -> 0.50068703 | AK29: =+$D$29 -> 0.5 | AL29: 0.49 | AM29: =+$D$29 -> 0.5 | AN29: =+((AD33*AD29)+(AH33*AH29)+(AL33*AL29))/AN33 -> 0.48208008 | AO29: =+$D$29 -> 0.5 | AP29: =+((AL29*AL33)+(AJ29*AJ33))/AP33 -> 0.49938648 | AQ29: =+$D$29 -> 0.5 | AR29: 0.5 | AS29: =+$D$29 -> 0.5 | AT29: =+((AP29*AP33)+(AR29*AR33))/AT33 -> 0.49945143 | AU29: =+$D$29 -> 0.5 | AV29: 0.52 | AW29: =+$D$29 -> 0.5 | AX29: =+((AT29*AT33)+(AV29*AV33))/AX33 -> 0.5010769 | AY29: =+$D$29 -> 0.5 | AZ29: 0.5 | BA29: =+$D$29 -> 0.5 | BB29: =+((AR29*AR33)+(AV29*AV33)+(AZ29*AZ33))/BB33 -> 0.50565536 | BC29: =+$D$29 -> 0.5 | BD29: =+((AN29*AN33)+(BB29*BB33))/BD33 -> 0.4939698 | BE29: =+$D$29 -> 0.5 | BF29: =+((AX29*AX33)+(AZ29*AZ33))/BF33 -> 0.50097621 | BH29: 0.5 | BI29: 0.49640477 | BJ29: 0.5 | BK29: 0.49588309 | BL29: 0.53 | BM29: 0.53450495 | BN29: 0.53 | BO29: 0.5280682 | BP29: 0.55 | BQ29: 0.53916083 | BR29: 0.55 | BS29: 0.62328215 | BT29: 0.551124 | BU29: 0.57147495 | BV29: 0.55061804
B30: Labour Productivity (Pre-existing) | C30: TCS/Man/Year | D30: 832.79094 | E30: =+E38 -> 694.95532 | F30: =+F38 -> 802.23728 | G30: =+G38 -> 598.01649 | H30: =+H38 -> 351.97887 | I30: =+I38 -> 645.708 | J30: =+J38 -> 573.6404 | K30: =+K38 -> 817.70563 | L30: =+L38 -> 850.75383 | ... BF30: =+BF38 -> 754.62718 | BH30: 789.97408 | BI30: 785.58705 | BJ30: 712.17383 | BK30: 691.16367 | BL30: 729.20664 | BM30: 695.16315 | BN30: 656.40621 | BO30: 639.11266 | BP30: 615.77607 | BQ30: 561.88094 | BR30: 549.90658 | BS30: 459.2495 | BT30: 562.64319 | BU30: 490.34382 | BV30: 421.02863
B31: Labour Productivity (MoU) | C31: TCS/Man/Year | D31: =D43 -> 308.34707 | E31: =E43 -> 258.6936 | F31: =F43 -> 296.57273 | G31: =G43 -> 224.03611 | H31: =H43 -> 135.48662 | I31: =I43 -> 241.08441 | J31: =J43 -> 215.20756 | AD31: =+AD43 -> 210.92734 | AH31: =+AH43 -> 268.17839 | AL31: =+AL43 -> 268.16346 | AR31: =+AR43 -> 274.37361 | AV31: =+AV43 -> 256.65063 | AZ31: =+AZ43 -> 308.14853
B33: Labor productivity calculation (Pre existing) | C33: Crude Steel | D33: ='Maj Production Summ'!D18 -> 2817514.1 | E33: ='Maj Production Summ'!E18 -> 193691.15 | F33: ='Maj Production Summ'!F18 -> 223226 | G33: ='Maj Production Summ'!G18 -> 170903.95 | H33: ='Maj Production Summ'!H18 -> 97961 | I33: =+E33+G33 -> 364595.1 | J33: =+F33+H33 -> 321187 | K33: ='Maj Production Summ'!K18 -> 237110.48 | L33: ='Maj Production Summ'!L18 -> 243453 | M33: =+E33+G33+K33 -> 601705.59 | N33: =+F33+H33+L33 -> 564640 | O33: ='Maj Production Summ'!O18 -> 239943.34 | P33: ='Maj Production Summ'!P18 -> 253662 | Q33: =+M33+O33 -> 841648.93 | R33: =+N33+P33 -> 818302 | S33: ='Maj Production Summ'!S18 -> 239943.34 | T33: ='Maj Production Summ'!T18 -> 237622 | U33: =+Q33+S33 -> 1081592.3 | V33: =+R33+T33 -> 1055924 | W33: ='Maj Production Summ'!W18 -> 125920.68 | X33: ='Maj Production Summ'!X18 -> 226847 | Y33: =+O33+S33+W33 -> 605807.37 | Z33: =+P33+T33+X33 -> 718131 | AA33: =+M33+Y33 -> 1207513 | AB33: =+N33+Z33 -> 1282771 | AC33: ='Maj Production Summ'!AC18 -> 244664.78 | AD33: ='Maj Production Summ'!AD18 -> 179201 | AE33: =+AA33+AC33 -> 1452177.7 | AF33: =+AB33+AD33 -> 1461972 | AG33: ='Maj Production Summ'!AG18 -> 237110.48 | AH33: ='Maj Production Summ'!AH18 -> 229502 | AI33: =+AE33+AG33 -> 1689288.2 | AJ33: =+AF33+AH33 -> 1691474 | AK33: ='Maj Production Summ'!AK18 -> 244664.78 | AL33: ='Maj Production Summ'!AL18 -> 234365 | AM33: =+AC33+AG33+AK33 -> 726440.04 | AN33: =+AD33+AH33+AL33 -> 643068 | AO33: =AI33+AK33 -> 1933953 | AP33: =AJ33+AL33 -> 1925839 | AQ33: ='Maj Production Summ'!AQ18 -> 248441.93 | AR33: ='Maj Production Summ'!AR18 -> 228047 | AS33: =+AO33+AQ33 -> 2182394.9 | AT33: =+AP33+AR33 -> 2153886 | AU33: ='Maj Production Summ'!AU18 -> 222001.89 | AV33: ='Maj Production Summ'!AV18 -> 185016 | AW33: =+AS33+AU33 -> 2404396.8 | AX33: =+AT33+AV33 -> 2338902 | AY33: ='Maj Production Summ'!AY18 -> 248441.93 | AZ33: ='Maj Production Summ'!AZ18 -> 241240 | BA33: =+AQ33+AU33+AY33 -> 718885.74 | BB33: =+AR33+AV33+AZ33 -> 654303 | BC33: =+AM33+BA33 -> 1445325.8 | BD33: =+AN33+BB33 -> 1297371 | BE33: =+AW33+AY33 -> 2652838.7 | BF33: =+AX33+AZ33 -> 2580142 | BH33: 2770018.9 | BI33: 2702613 | BJ33: 2489528.3 | BK33: 2436959 | BL33: 2620075.5 | BM33: 2528925 | BN33: 2500000 | BO33: 2422324.3 | BP33: 2573000.8 | BQ33: 2322716
C34: Pig+Eq | D34: ='Maj Production Summ'!D26 -> 6020 | E34: ='Maj Production Summ'!E26 -> 1945 | F34: ='Maj Production Summ'!F26 -> 471.09455 | G34: ='Maj Production Summ'!G26 -> 4075 | H34: ='Maj Production Summ'!H26 -> 6281.6659 | I34: =+E34+G34 -> 6020 | J34: =+F34+H34 -> 6752.7604 | K34: ='Maj Production Summ'!K26 -> 810 | L34: ='Maj Production Summ'!L26 -> 1030.4578 | M34: =+E34+G34+K34 -> 6830 | N34: =+F34+H34+L34 -> 7783.2182 | O34: ='Maj Production Summ'!O26 -> 810 | P34: ='Maj Production Summ'!P26 -> 0 | Q34: =+M34+O34 -> 7640 | R34: =+N34+P34 -> 7783.2182 | S34: ='Maj Production Summ'!S26 -> 810 | T34: ='Maj Production Summ'!T26 -> 164.4084 | U34: =+Q34+S34 -> 8450 | V34: =+R34+T34 -> 7947.6266 | W34: ='Maj Production Summ'!W26 -> 5360 | X34: ='Maj Production Summ'!X26 -> 292.8108 | Y34: =+O34+S34+W34 -> 6980 | Z34: =+P34+T34+X34 -> 457.2192 | AA34: =+M34+Y34 -> 13810 | AB34: =+N34+Z34 -> 8240.4374 | AC34: ='Maj Production Summ'!AC26 -> 810 | AD34: ='Maj Production Summ'!AD26 -> 9043.2686 | AE34: =+AA34+AC34 -> 14620 | AF34: =+AB34+AD34 -> 17283.706 | AG34: ='Maj Production Summ'!AG26 -> 810 | AH34: ='Maj Production Summ'!AH26 -> 154.21623 | AI34: =+AE34+AG34 -> 15430 | AJ34: =+AF34+AH34 -> 17437.922 | AK34: ='Maj Production Summ'!AK26 -> 810 | AL34: ='Maj Production Summ'!AL26 -> 40.72516 | AM34: =+AC34+AG34+AK34 -> 2430 | AN34: =+AD34+AH34+AL34 -> 9238.21 | AO34: =AI34+AK34 -> 16240 | AP34: =AJ34+AL34 -> 17478.647 | AQ34: ='Maj Production Summ'!AQ26 -> 810 | AR34: ='Maj Production Summ'!AR26 -> 1557.1073 | AS34: =+AO34+AQ34 -> 17050 | AT34: =+AP34+AR34 -> 19035.755 | AU34: ='Maj Production Summ'!AU26 -> 810 | AV34: ='Maj Production Summ'!AV26 -> 920 | AW34: =+AS34+AU34 -> 17860 | AX34: =+AT34+AV34 -> 19955.755 | AY34: ='Maj Production Summ'!AY26 -> 810 | AZ34: ='Maj Production Summ'!AZ26 -> 401.63435 | BA34: =+AQ34+AU34+AY34 -> 2430 | BB34: =+AR34+AV34+AZ34 -> 2878.7416 | BC34: =+AM34+BA34 -> 4860 | BD34: =+AN34+BB34 -> 12116.952 | BE34: =+AW34+AY34 -> 18670 | BF34: =+AX34+AZ34 -> 20357.389 | BH34: 14270 | BI34: 21216.524 | BJ34: 9365 | BK34: 25856.451 | BL34: 21561.1 | BM34: 13596.898 | BN34: 22929.735 | BO34: 16335.784 | BP34: 34051.635 | BQ34: 32547.079
C35: 50% of Pig Eq | D35: =+D34/2 -> 3010 | E35: =+E34/2 -> 972.5 | F35: =+F34/2 -> 235.54728 | G35: =+G34/2 -> 2037.5 | H35: =+H34/2 -> 3140.8329 | I35: =+E35+G35 -> 3010 | J35: =+F35+H35 -> 3376.3802 | K35: =+K34/2 -> 405 | L35: =+L34/2 -> 515.22889 | M35: =+E35+G35+K35 -> 3415 | N35: =+F35+H35+L35 -> 3891.6091 | O35: =+O34/2 -> 405 | P35: =+P34/2 -> 0 | Q35: =+M35+O35 -> 3820 | R35: =+N35+P35 -> 3891.6091 | S35: =+S34/2 -> 405 | T35: =+T34/2 -> 82.204202 | U35: =+Q35+S35 -> 4225 | V35: =+R35+T35 -> 3973.8133 | W35: =+W34/2 -> 2680 | X35: =+X34/2 -> 146.4054 | Y35: =+O35+S35+W35 -> 3490 | Z35: =+P35+T35+X35 -> 228.6096 | AA35: =+M35+Y35 -> 6905 | AB35: =+N35+Z35 -> 4120.2187 | AC35: =+AC34/2 -> 405 | AD35: =+AD34/2 -> 4521.6343 | AE35: =+AA35+AC35 -> 7310 | AF35: =+AB35+AD35 -> 8641.853 | AG35: =+AG34/2 -> 405 | AH35: =+AH34/2 -> 77.108113 | AI35: =+AE35+AG35 -> 7715 | AJ35: =+AF35+AH35 -> 8718.9611 | AK35: =+AK34/2 -> 405 | AL35: =+AL34/2 -> 20.36258 | AM35: =+AC35+AG35+AK35 -> 1215 | AN35: =+AD35+AH35+AL35 -> 4619.105 | AO35: =AI35+AK35 -> 8120 | AP35: =AJ35+AL35 -> 8739.3237 | AQ35: =+AQ34/2 -> 405 | AR35: =+AR34/2 -> 778.55363 | AS35: =+AO35+AQ35 -> 8525 | AT35: =+AP35+AR35 -> 9517.8773 | AU35: =+AU34/2 -> 405 | AV35: =+AV34/2 -> 460 | AW35: =+AS35+AU35 -> 8930 | AX35: =+AT35+AV35 -> 9977.8773 | AY35: =+AY34/2 -> 405 | AZ35: =+AZ34/2 -> 200.81717 | BA35: =+AQ35+AU35+AY35 -> 1215 | BB35: =+AR35+AV35+AZ35 -> 1439.3708 | BC35: =+AM35+BA35 -> 2430 | BD35: =+AN35+BB35 -> 6058.4758 | BE35: =+AW35+AY35 -> 9335 | BF35: =+AX35+AZ35 -> 10178.695 | BH35: 7135 | BI35: 10608.262 | BJ35: 4682.5 | BK35: 12928.226 | BL35: 10780.55 | BM35: 6798.4488 | BN35: 11464.868 | BO35: 8167.892 | BP35: 17025.818 | BQ35: 16273.54
C36: CS+50%Pig Eq | D36: =+D33+D35 -> 2820524.1 | E36: =+E33+E35 -> 194663.65 | F36: =+F33+F35 -> 223461.55 | G36: =+G33+G35 -> 172941.45 | H36: =+H33+H35 -> 101101.83 | I36: =+E36+G36 -> 367605.1 | J36: =+F36+H36 -> 324563.38 | K36: =+K33+K35 -> 237515.48 | L36: =+L33+L35 -> 243968.23 | M36: =+E36+G36+K36 -> 605120.59 | N36: =+F36+H36+L36 -> 568531.61 | O36: =+O33+O35 -> 240348.34 | P36: =+P33+P35 -> 253662 | Q36: =+M36+O36 -> 845468.93 | R36: =+N36+P36 -> 822193.61 | S36: =+S33+S35 -> 240348.34 | T36: =+T33+T35 -> 237704.2 | U36: =+Q36+S36 -> 1085817.3 | V36: =+R36+T36 -> 1059897.8 | W36: =+W33+W35 -> 128600.68 | X36: =+X33+X35 -> 226993.41 | Y36: =+O36+S36+W36 -> 609297.37 | Z36: =+P36+T36+X36 -> 718359.61 | AA36: =+M36+Y36 -> 1214418 | AB36: =+N36+Z36 -> 1286891.2 | AC36: =+AC33+AC35 -> 245069.78 | AD36: =+AD33+AD35 -> 183722.63 | AE36: =+AA36+AC36 -> 1459487.7 | AF36: =+AB36+AD36 -> 1470613.9 | AG36: =+AG33+AG35 -> 237515.48 | AH36: =+AH33+AH35 -> 229579.11 | AI36: =+AE36+AG36 -> 1697003.2 | AJ36: =+AF36+AH36 -> 1700193 | AK36: =+AK33+AK35 -> 245069.78 | AL36: =+AL33+AL35 -> 234385.36 | AM36: =+AC36+AG36+AK36 -> 727655.04 | AN36: =+AD36+AH36+AL36 -> 647687.11 | AO36: =AI36+AK36 -> 1942073 | AP36: =AJ36+AL36 -> 1934578.3 | AQ36: =+AQ33+AQ35 -> 248846.93 | AR36: =+AR33+AR35 -> 228825.55 | AS36: =+AO36+AQ36 -> 2190919.9 | AT36: =+AP36+AR36 -> 2163403.9 | AU36: =+AU33+AU35 -> 222406.89 | AV36: =+AV33+AV35 -> 185476 | AW36: =+AS36+AU36 -> 2413326.8 | AX36: =+AT36+AV36 -> 2348879.9 | AY36: =+AY33+AY35 -> 248846.93 | AZ36: =+AZ33+AZ35 -> 241440.82 | BA36: =+AQ36+AU36+AY36 -> 720100.74 | BB36: =+AR36+AV36+AZ36 -> 655742.37 | BC36: =+AM36+BA36 -> 1447755.8 | BD36: =+AN36+BB36 -> 1303429.5 | BE36: =+AW36+AY36 -> 2662173.7 | BF36: =+AX36+AZ36 -> 2590320.7 | BH36: 2777153.9 | BI36: 2713221.3 | BJ36: 2494210.8 | BK36: 2449887.2 | BL36: 2630856 | BM36: 2535723.4 | BN36: 2511464.9 | BO36: 2430492.2 | BP36: 2590026.6 | BQ36: 2338989.5
C37: Average Manpower (Works) | D37: 3387 | E37: 3408 | F37: 3389 | G37: 3405 | H37: 3382 | I37: =+AVERAGE(E37,G37) -> 3406.5 | J37: =+AVERAGE(F37,H37) -> 3385.5 | K37: 3534 | L37: 3489 | M37: =+AVERAGE(E37,G37,K37) -> 3449 | N37: =+AVERAGE(F37,H37,L37) -> 3420 | O37: 3527 | P37: 3478 | Q37: =+AVERAGE(E37,G37,K37,O37) -> 3468.5 | R37: =+AVERAGE(F37,H37,L37,P37) -> 3434.5 | S37: 3524 | T37: 3465 | U37: =+AVERAGE(E37,G37,K37,O37,S37) -> 3479.6 | V37: =+AVERAGE(F37,H37,L37,P37,T37) -> 3440.6 | W37: 3517 | X37: 3450 | Y37: =+AVERAGE(Q37,S37,W37) -> 3503.1667 | Z37: =+AVERAGE(P37,T37,X37) -> 3464.3333 | AA37: =+AVERAGE(E37,G37,K37,O37,S37,W37) -> 3485.8333 | AB37: =+AVERAGE(X37,P37,L37,H37,T37,F37) -> 3442.1667 | AC37: 3512 | AD37: 3449 | AE37: =+AVERAGE(E37,G37,K37,O37,S37,W37,AC37) -> 3489.5714 | AF37: =+AVERAGE(F37,H37,L37,P37,T37,X37,AD37) -> 3443.1429 | AG37: 3502 | AH37: 3439 | AI37: =AVERAGE(E37,G37,K37,O37,S37,W37,AC37,AG37) -> 3491.125 | AJ37: =AVERAGE(AH37,AD37,X37,T37,L37,P37,H37,F37) -> 3442.625 | AK37: 3500 | AL37: 3428 | AM37: =+AVERAGE(AC37,AG37,AK37) -> 3504.6667 | AN37: =+AVERAGE(AD37,AH37,AL37) -> 3438.6667 | AO37: =+AVERAGE(E37,G37,K37,O37,S37,W37,AC37,AG37,AK37) -> 3492.1111 | AP37: =+AVERAGE(F37,H37,L37,P37,T37,X37,AD37,AH37,AL37) -> 3441 | AQ37: 3493 | AR37: 3412 | AS37: =+AVERAGE(E37,G37,K37,O37,S37,W37,AC37,AG37,AK37,AQ37) -> 3492.2 | AT37: =+AVERAGE(F37,H37,L37,P37,T37,X37,AD37,AH37,AL37,AR37) -> 3438.1 | AU37: 3491 | AV37: 3415 | AW37: =+AVERAGE(E37,G37,K37,O37,S37,W37,AC37,AG37,AK37,AQ37,AU37) -> 3492.0909 | AX37: =+AVERAGE(F37,H37,L37,P37,T37,X37,AD37,AH37,AL37,AR37,AV37) -> 3436 | AY37: 3489 | AZ37: 3395 | BA37: =+AVERAGE(AQ37,AU37,AY37) -> 3491 | BB37: =+AVERAGE(AR37,AV37,AZ37) -> 3407.3333 | BC37: =+AVERAGE(AC37,AG37,AK37,AQ37,AU37,AY37) -> 3497.8333 | BD37: =+AVERAGE(AD37,AH37,AL37,AR37,AV37,AZ37) -> 3423 | BE37: =+AVERAGE(E37,G37,K37,O37,S37,W37,AC37,AG37,AK37,AQ37,AU37,AY37) -> 3491.8333 | BF37: =+AVERAGE(F37,H37,L37,P37,T37,X37,AD37,AH37,AL37,AR37,AV37,AZ37) -> 3432.5833 | BH37: 3515.5 | BI37: 3453.75 | BJ37: 3502.25 | BK37: 3544.5833 | BL37: 3607.8333 | BM37: 3647.6667 | BN37: 3826.0833 | BO37: 3802.9167
C38: LP | D38: =+D36/(D37/365*D2) -> 832.74996 | E38: =+E36/(E37/365*E2) -> 694.95532 | F38: =+F36/(F37/365*F2) -> 802.23728 | G38: =+G36/(G37/365*G2) -> 598.01649 | H38: =+H36/(H37/365*H2) -> 351.97887 | I38: =+I36/(I37/365*I2) -> 645.708 | J38: =+J36/(J37/365*J2) -> 573.6404 | K38: =+K36/(K37/365*K2) -> 817.70563 | ... BF38: =+BF36/(BF37/365*BF2) -> 754.62718 | BH38: 789.97408 | BI38: 785.58705 | BJ38: 712.17383 | BK38: 691.16367 | BL38: 729.20664 | BM38: 695.16315 | BN38: 656.40621 | BO38: 639.11266 | BP38: 645.95904 | BQ38: 585.39376
B40: Labor productivity calculation (MoU) | C40: Crude Steel | D40: =+D33 -> 2817514.1 | E40: =+E33 -> 193691.15 | F40: =+F33 -> 223226 | G40: =+G33 -> 170903.95 | H40: =+H33 -> 97961 | I40: =+I33 -> 364595.1 | J40: =+J33 -> 321187 | L40: =+L33 -> 243453 | N40: =+N33 -> 564640 | P40: =+P33 -> 253662 | R40: =+R33 -> 818302 | T40: =+T33 -> 237622 | V40: =+V33 -> 1055924 | X40: =+X33 -> 226847 | Z40: =+Z33 -> 718131 | AB40: =+AB33 -> 1282771 | AD40: =+AD33 -> 179201 | AF40: =+AF33 -> 1461972 | AH40: =+AH33 -> 229502 | AJ40: =+AJ33 -> 1691474 | AL40: =+AL33 -> 234365 | AN40: =+AN33 -> 643068 | AR40: =+AR33 -> 228047 | AV40: =+AV33 -> 185016 | AZ40: =+AZ33 -> 241240 | BB40: =+BB33 -> 654303 | BD40: =+BD33 -> 1297371
C41: Pig+Eq | D41: =+D34 -> 6020 | E41: =+E34 -> 1945 | F41: =+F34 -> 471.09455 | G41: =+G34 -> 4075 | H41: =+H34 -> 6281.6659 | I41: =+I34 -> 6020 | J41: =+J34 -> 6752.7604 | L41: =+L34 -> 1030.4578 | N41: =+N34 -> 7783.2182 | P41: =+P34 -> 0 | R41: =+R34 -> 7783.2182 | T41: =+T34 -> 164.4084 | V41: =+V34 -> 7947.6266 | X41: =+X34 -> 292.8108 | Z41: =+Z34 -> 457.2192 | AB41: =+AB34 -> 8240.4374 | AD41: =+AD34 -> 9043.2686 | AF41: =+AF34 -> 17283.706 | AH41: =+AH34 -> 154.21623 | AJ41: =+AJ34 -> 17437.922 | AL41: =+AL34 -> 40.72516 | AN41: =+AN34 -> 9238.21 | AR41: =+AR34 -> 1557.1073 | AV41: =+AV34 -> 920 | AZ41: =+AZ34 -> 401.63435 | BB41: =+BB34 -> 2878.7416 | BD41: =+BD34 -> 12116.952
C42: Average MP = all regular employees + Contract workers deployed in the Works & NW areas of the Plant except workforce deployed in Projects. | D42: 9157 | E42: 9201 | F42: 9177 | G42: 9196 | H42: 9059 | I42: =+AVERAGE(E42,G42) -> 9198.5 | J42: =+AVERAGE(F42,H42) -> 9118 | AD42: 10508 | AH42: 10419 | AL42: 10292 | AN42: =+AVERAGE(AD42,AH42,AL42) -> 10406.333 | AR42: 9853 | AV42: 9444 | AZ42: 9233 | BB42: =+AVERAGE(AR42,AV42,AZ42) -> 9510 | BD42: =+AVERAGE(AN42,BB42) -> 9958.1667
C43: LP | D43: =(D40+D41)/(D42/$D$2*D2) -> 308.34707 | E43: =(E40+E41)/(E42/$D$2*E2) -> 258.6936 | F43: =(F40+F41)/(F42/$D$2*F2) -> 296.57273 | G43: =(G40+G41)/(G42/$D$2*G2) -> 224.03611 | H43: =(H40+H41)/(H42/$D$2*H2) -> 135.48662 | I43: =(I40+I41)/(I42/$D$2*I2) -> 241.08441 | J43: =(J40+J41)/(J42/$D$2*J2) -> 215.20756 | AD43: =+(AD41+AD40)/(AD42/365*AD2) -> 210.92734 | AH43: =+(AH41+AH40)/(AH42/365*AH2) -> 268.17839 | AL43: =+(AL41+AL40)/(AL42/365*AL2) -> 268.16346 | AN43: =+(AN41+AN40)/(AN42/365*AN2) -> 248.69028 | AR43: =+(AR41+AR40)/(AR42/365*AR2) -> 274.37361 | AV43: =+(AV41+AV40)/(AV42/365*AV2) -> 256.65063 | AZ43: =+(AZ41+AZ40)/(AZ42/365*AZ2) -> 308.14853 | BB43: =+(BB41+BB40)/(BB42/365*BB2) -> 280.25626 | BD43: =+(BD41+BD40)/(BD42/365*BD2) -> 263.72032
B56: Hot metal consumed in BOF | C56: MT | D56: =+(D16*D33)/1000 -> 2992200 | E56: =+(E16*E33)/1000 -> 205700 | F56: =+SMS!F15 -> 235708.2 | G56: =+(G16*G33)/1000 -> 181500 | H56: =+SMS!H15 -> 102483.72 | I56: =+(I16*I33)/1000 -> 387200 | J56: =+SMS!J15 -> 338191.92 | K56: =+(K16*K33)/1000 -> 251811.33 | L56: =+SMS!L15 -> 258527.52 | M56: =+(M16*M33)/1000 -> 639011.33 | N56: =+SMS!N15 -> 596719.45 | O56: =+(O16*O33)/1000 -> 254819.83 | P56: =+SMS!P15 -> 266778.08 | Q56: =+(Q16*Q33)/1000 -> 893831.16 | R56: =+SMS!R15 -> 863497.52 | S56: =+(S16*S33)/1000 -> 254819.83 | T56: =+SMS!T15 -> 251918.72 | U56: =+(U16*U33)/1000 -> 1148651 | V56: =+SMS!V15 -> 1115416.2 | W56: =+(W16*W33)/1000 -> 133727.76 | X56: =+SMS!X15 -> 241323.3 | Y56: =+O56+S56+W56 -> 643367.42 | Z56: =+P56+T56+X56 -> 760020.09 | AA56: =+M56+Y56 -> 1282378.8 | AB56: =+N56+Z56 -> 1356739.5 | AC56: =+(AC16*AC33)/1000 -> 259833.99 | AD56: =+SMS!AD15 -> 190772.82 | AE56: =+(AE16*AE33)/1000 -> 1542212.7 | AF56: =+SMS!AF15 -> 1547512.4 | AG56: =+(AG16*AG33)/1000 -> 251811.33 | AH56: =+SMS!AH15 -> 243243.53 | AI56: =+(AI16*AI33)/1000 -> 1794024.1 | AJ56: =+SMS!AJ15 -> 1790755.9 | AK56: =+(AK16*AK33)/1000 -> 259833.99 | AL56: =+SMS!AL15 -> 250346.24 | AM56: =+AC56+AG56+AK56 -> 771479.32 | AN56: =+AD56+AH56+AL56 -> 684362.59 | AO56: =+(AO16*AO33)/1000 -> 2053858.1 | AP56: =+SMS!AP15 -> 2041102.1 | AQ56: =+(AQ16*AQ33)/1000 -> 263845.33 | AR56: =+SMS!AR15 -> 242224.07 | AS56: =+(AS16*AS33)/1000 -> 2317703.4 | AT56: =+SMS!AT15 -> 2283326.2 | AU56: =+(AU16*AU33)/1000 -> 235766.01 | AV56: =+SMS!AV15 -> 194681.08 | AW56: =+(AW16*AW33)/1000 -> 2553469.4 | AX56: =+SMS!AX15 -> 2478007.3 | AY56: =+(AY16*AY33)/1000 -> 263845.33 | AZ56: =+SMS!AZ15 -> 250513.95 | BA56: =+AQ56+AU56+AY56 -> 763456.66 | BB56: =+AR56+AV56+AZ56 -> 687419.09 | BC56: =+AM56+BA56 -> 1534936 | BD56: =+AN56+BB56 -> 1371781.7 | BE56: =+AW56+AY56 -> 2817314.7 | BF56: =+AX56+AZ56 -> 2728521.2 | BH56: 2933450 | BI56: 2862409.8 | BJ56: 2638900 | BK56: 2582070.1 | BL56: 2777280 | BM56: 2695862.8 | BN56: 2655000 | BO56: 2574868 | BP56: 2611100.5 | BQ56: 2366123.2
B57: Total Scrap Charged | C57: MT | D57: =+(D17*D33)/1000 -> 95795.48 | E57: =+(E17*E33)/1000 -> 6585.4991 | F57: =+SMS!F19 -> 8946.7 | G57: =+(G17*G33)/1000 -> 5810.7345 | H57: =+SMS!H19 -> 4820.8 | I57: =+(I17*I33)/1000 -> 12396.234 | J57: =+SMS!J19 -> 13767.5 | K57: =+(K17*K33)/1000 -> 8061.7564 | L57: =+SMS!L19 -> 8404.2 | M57: =+(M17*M33)/1000 -> 20457.99 | N57: =+SMS!N19 -> 22171.7 | O57: =+(O17*O33)/1000 -> 8158.0737 | P57: =+SMS!P19 -> 11294.6 | Q57: =+(Q17*Q33)/1000 -> 28616.064 | R57: =+SMS!R19 -> 33466.3 | S57: =+(S17*S33)/1000 -> 8158.0737 | T57: =+SMS!T19 -> 8598.1 | U57: =+(U17*U33)/1000 -> 36774.137 | V57: =+SMS!V19 -> 42064.4 | W57: =+(W17*W33)/1000 -> 4281.3031 | X57: =+SMS!X19 -> 7722 | Y57: =+O57+S57+W57 -> 20597.45 | Z57: =+P57+T57+X57 -> 27614.7 | AA57: =+M57+Y57 -> 41055.44 | AB57: =+N57+Z57 -> 49786.4 | AC57: =+(AC17*AC33)/1000 -> 8318.6025 | AD57: =+SMS!AD19 -> 5530.6 | AE57: =+(AE17*AE33)/1000 -> 49374.043 | AF57: =+SMS!AF19 -> 55317 | AG57: =+(AG17*AG33)/1000 -> 8061.7564 | AH57: =+SMS!AH19 -> 8373.8 | AI57: =+(AI17*AI33)/1000 -> 57435.799 | AJ57: =+SMS!AJ19 -> 63690.8 | AK57: =+(AK17*AK33)/1000 -> 8318.6025 | AL57: =+SMS!AL19 -> 6546.8 | AM57: =+AC57+AG57+AK57 -> 24698.961 | AN57: =+AD57+AH57+AL57 -> 20451.2 | AO57: =+(AO17*AO33)/1000 -> 65754.402 | AP57: =+SMS!AP19 -> 70237.6 | AQ57: =+(AQ17*AQ33)/1000 -> 8447.0255 | AR57: =+SMS!AR19 -> 7578.7 | AS57: =+(AS17*AS33)/1000 -> 74201.427 | AT57: =+SMS!AT19 -> 77816.3 | AU57: =+(AU17*AU33)/1000 -> 7548.0642 | AV57: =+SMS!AV19 -> 8045 | AW57: =+(AW17*AW33)/1000 -> 81749.491 | AX57: =+SMS!AX19 -> 85861.3 | AY57: =+(AY17*AY33)/1000 -> 8447.0255 | AZ57: =+SMS!AZ19 -> 13265.9 | BA57: =+AQ57+AU57+AY57 -> 24442.115 | BB57: =+AR57+AV57+AZ57 -> 28889.6 | BC57: =+AM57+BA57 -> 49141.076 | BD57: =+AN57+BB57 -> 49340.8 | BE57: =+AW57+AY57 -> 90196.517 | BF57: =+AX57+AZ57 -> 99127.2 | BH57: 105260.72 | BI57: 99726.4 | BJ57: 99581.132 | BK57: 91825 | BL57: 104803.02 | BM57: 87073.52 | BN57: 121081.64 | BO57: 93275 | BP57: 128650.04 | BQ57: 101615.76
B58: Fe-Mn | C58: MT | D58: =+(D66*'Maj Production Summ'!D$18)/1000 -> 3512.0014 | E58: =+(E66*'Maj Production Summ'!E$18)/1000 -> 241.43396 | F58: =+SMS!F55 -> 409 | G58: =+(G66*'Maj Production Summ'!G$18)/1000 -> 213.02996 | H58: =+SMS!H55 -> 147 | I58: =+(I66*'Maj Production Summ'!I$18)/1000 -> 454.46392 | J58: =+SMS!J55 -> 556 | K58: =+(K66*'Maj Production Summ'!K$18)/1000 -> 295.55569 | L58: =+SMS!L55 -> 405 | M58: =+(M66*'Maj Production Summ'!M$18)/1000 -> 750.01961 | N58: =+SMS!N55 -> 961 | O58: =+(O66*'Maj Production Summ'!O$18)/1000 -> 299.08683 | P58: =+SMS!P55 -> 383 | Q58: =+(Q66*'Maj Production Summ'!Q$18)/1000 -> 1049.1064 | R58: =+SMS!R55 -> 1344 | S58: =+(S66*'Maj Production Summ'!S$18)/1000 -> 299.08683 | T58: =+SMS!T55 -> 300 | U58: =+(U66*'Maj Production Summ'!U$18)/1000 -> 1348.1933 | V58: =+SMS!V55 -> 1644 | W58: =+(W66*'Maj Production Summ'!W$18)/1000 -> 156.95879 | X58: =+SMS!X55 -> 293 | Y58: =+O58+S58+W58 -> 755.13244 | Z58: =+P58+T58+X58 -> 976 | AA58: =+M58+Y58 -> 1505.1521 | AB58: =+N58+Z58 -> 1937 | AC58: =+(AC66*'Maj Production Summ'!AC$18)/1000 -> 304.97204 | AD58: =+SMS!AD55 -> 251 | AE58: =+(AE66*'Maj Production Summ'!AE$18)/1000 -> 1810.1241 | AF58: =+SMS!AF55 -> 2188 | AG58: =+(AG66*'Maj Production Summ'!AG$18)/1000 -> 295.55569 | AH58: =+SMS!AH55 -> 290 | AI58: =+(AI66*'Maj Production Summ'!AI$18)/1000 -> 2105.6798 | AJ58: =+SMS!AJ55 -> 2478 | AK58: =+(AK66*'Maj Production Summ'!AK$18)/1000 -> 304.97204 | AL58: =+SMS!AL55 -> 401.53 | AM58: =+AC58+AG58+AK58 -> 905.49978 | AN58: =+AD58+AH58+AL58 -> 942.53 | AO58: =+(AO66*'Maj Production Summ'!AO$18)/1000 -> 2410.6518 | AP58: =+SMS!AP55 -> 2879.53 | AQ58: =+(AQ66*'Maj Production Summ'!AQ$18)/1000 -> 309.68022 | AR58: =+SMS!AR55 -> 267.8 | AS58: =+(AS66*'Maj Production Summ'!AS$18)/1000 -> 2720.3321 | AT58: =+SMS!AT55 -> 3147.33 | AU58: =+(AU66*'Maj Production Summ'!AU$18)/1000 -> 276.72299 | AV58: =+SMS!AV55 -> 135 | AW58: =+(AW66*'Maj Production Summ'!AW$18)/1000 -> 2997.055 | AX58: =+SMS!AX55 -> 3282.33 | AY58: =+(AY66*'Maj Production Summ'!AY$18)/1000 -> 309.68022 | AZ58: =+SMS!AZ55 -> 421 | BA58: =+AQ58+AU58+AY58 -> 896.08343 | BB58: =+AR58+AV58+AZ58 -> 823.8 | BC58: =+AM58+BA58 -> 1801.5832 | BD58: =+AN58+BB58 -> 1766.33 | BE58: =+AW58+AY58 -> 3306.7353 | BF58: =+AX58+AZ58 -> 3703.33 | BH58: 4535.1642 | BI58: 3809.33 | BJ58: 4107.7217 | BK58: 3222 | BL58: 3385.0943 | BM58: 4727 | BN58: 4500 | BO58: 4569.84 | BP58: 6693.3528 | BQ58: 4136
B59: LCFeMn | C59: MT | D59: =+(D67*'Maj Production Summ'!D$18)/1000 -> 2201.7356 | E59: =+(E67*'Maj Production Summ'!E$18)/1000 -> 151.35921 | F59: =+SMS!F56 -> 140 | G59: =+(G67*'Maj Production Summ'!G$18)/1000 -> 133.55224 | H59: =+SMS!H56 -> 56 | I59: 0 | J59: =+SMS!J56 -> 196 | K59: =+(K67*'Maj Production Summ'!K$18)/1000 -> 185.28908 | L59: =+SMS!L56 -> 105 | M59: 0 | N59: =+SMS!N56 -> 301 | O59: =+(O67*'Maj Production Summ'!O$18)/1000 -> 187.50281 | P59: =+SMS!P56 -> 137 | Q59: 0 | R59: =+SMS!R56 -> 438 | S59: =+(S67*'Maj Production Summ'!S$18)/1000 -> 187.50281 | T59: =+SMS!T56 -> 131 | U59: 0 | V59: =+SMS!V56 -> 569 | W59: =+(W67*'Maj Production Summ'!W$18)/1000 -> 98.400233 | X59: =+SMS!X56 -> 129 | Y59: =+O59+S59+W59 -> 473.40584 | Z59: =+P59+T59+X59 -> 397 | AA59: =+M59+Y59 -> 473.40584 | AB59: =+N59+Z59 -> 698 | AC59: =+(AC67*'Maj Production Summ'!AC$18)/1000 -> 191.19235 | AD59: =+SMS!AD56 -> 94 | AE59: 0 | AF59: =+SMS!AF56 -> 792 | AG59: =+(AG67*'Maj Production Summ'!AG$18)/1000 -> 185.28908 | AH59: =+SMS!AH56 -> 112 | AI59: 0 | AJ59: =+SMS!AJ56 -> 904 | AK59: =+(AK67*'Maj Production Summ'!AK$18)/1000 -> 191.19235 | AL59: =+SMS!AL56 -> 70 | AM59: =+AC59+AG59+AK59 -> 567.67378 | AN59: =+AD59+AH59+AL59 -> 276 | AO59: 0 | AP59: =+SMS!AP56 -> 974 | AQ59: =+(AQ67*'Maj Production Summ'!AQ$18)/1000 -> 194.14399 | AR59: =+SMS!AR56 -> 88 | AS59: 0 | AT59: =+SMS!AT56 -> 1062 | AU59: =+(AU67*'Maj Production Summ'!AU$18)/1000 -> 173.48253 | AV59: =+SMS!AV56 -> 143.714 | AW59: 0 | AX59: =+SMS!AX56 -> 1205.714 | AY59: =+(AY67*'Maj Production Summ'!AY$18)/1000 -> 194.14399 | AZ59: =+SMS!AZ56 -> 122 | BA59: =+AQ59+AU59+AY59 -> 561.77051 | BB59: =+AR59+AV59+AZ59 -> 353.714 | BC59: =+AM59+BA59 -> 1129.4443 | BD59: =+AN59+BB59 -> 629.714 | BE59: =+AW59+AY59 -> 194.14399 | BF59: =+AX59+AZ59 -> 1327.714 | BH59: 208.72246 | BI59: 1414.714 | BJ59: 0 | BK59: 1433 | BL59: 0 | BM59: 1668.305 | BN59: 0 | BO59: 1122.042 | BP59: 0 | BQ59: 968.34
B60: Total Fe-Mn | C60: MT | D60: =SUM(D58:D59) -> 5713.737 | E60: =SUM(E58:E59) -> 392.79316 | F60: =SUM(F58:F59) -> 549 | G60: =SUM(G58:G59) -> 346.5822 | H60: =SUM(H58:H59) -> 203 | I60: =SUM(I58:I59) -> 454.46392 | J60: =SUM(J58:J59) -> 752 | K60: =SUM(K58:K59) -> 480.84477 | ... BF60: =SUM(BF58:BF59) -> 5031.044 | BH60: 4743.8866 | BI60: 5224.044 | BJ60: 4107.7217 | BK60: 4655 | BL60: 3385.0943 | BM60: 6395.305 | BN60: 4500 | BO60: 5691.882 | BP60: 6693.3528 | BQ60: 5104.34
B61: Si-Mn | C61: MT | D61: =+(D69*'Maj Production Summ'!D$18)/1000 -> 39108.929 | E61: =+(E69*'Maj Production Summ'!E$18)/1000 -> 2688.5592 | F61: =+SMS!F58 -> 2872 | G61: =+(G69*'Maj Production Summ'!G$18)/1000 -> 2372.2581 | H61: =+SMS!H58 -> 1223 | I61: =+(I69*'Maj Production Summ'!I$18)/1000 -> 5060.8173 | J61: =+SMS!J58 -> 4095 | K61: =+(K69*'Maj Production Summ'!K$18)/1000 -> 3291.2478 | L61: =+SMS!L58 -> 3768 | M61: =+(M69*'Maj Production Summ'!M$18)/1000 -> 8352.065 | N61: =+SMS!N58 -> 7863 | O61: =+(O69*'Maj Production Summ'!O$18)/1000 -> 3330.5697 | P61: =+SMS!P58 -> 4098 | Q61: =+(Q69*'Maj Production Summ'!Q$18)/1000 -> 11682.635 | R61: =+SMS!R58 -> 11961 | S61: =+(S69*'Maj Production Summ'!S$18)/1000 -> 3330.5697 | T61: =+SMS!T58 -> 3587.02 | U61: =+(U69*'Maj Production Summ'!U$18)/1000 -> 15013.204 | V61: =+SMS!V58 -> 15548.02 | W61: =+(W69*'Maj Production Summ'!W$18)/1000 -> 1747.861 | X61: =+SMS!X58 -> 3011.11 | Y61: =+O61+S61+W61 -> 8409.0004 | Z61: =+P61+T61+X61 -> 10696.13 | AA61: =+M61+Y61 -> 16761.065 | AB61: =+N61+Z61 -> 18559.13 | AC61: =+(AC69*'Maj Production Summ'!AC$18)/1000 -> 3396.1063 | AD61: =+SMS!AD58 -> 2470 | AE61: =+(AE69*'Maj Production Summ'!AE$18)/1000 -> 20157.172 | AF61: =+SMS!AF58 -> 21029.13 | AG61: =+(AG69*'Maj Production Summ'!AG$18)/1000 -> 3291.2478 | AH61: =+SMS!AH58 -> 2814 | AI61: =+(AI69*'Maj Production Summ'!AI$18)/1000 -> 23448.419 | AJ61: =+SMS!AJ58 -> 23843.13 | AK61: =+(AK69*'Maj Production Summ'!AK$18)/1000 -> 3396.1063 | AL61: =+SMS!AL58 -> 3092 | AM61: =+AC61+AG61+AK61 -> 10083.46 | AN61: =+AD61+AH61+AL61 -> 8376 | AO61: =+(AO69*'Maj Production Summ'!AO$18)/1000 -> 26844.526 | AP61: =+SMS!AP58 -> 26935.13 | AQ61: =+(AQ69*'Maj Production Summ'!AQ$18)/1000 -> 3448.5356 | AR61: =+SMS!AR58 -> 3008 | AS61: =+(AS69*'Maj Production Summ'!AS$18)/1000 -> 30293.061 | AT61: =+SMS!AT58 -> 29943.13 | AU61: =+(AU69*'Maj Production Summ'!AU$18)/1000 -> 3081.5307 | AV61: =+SMS!AV58 -> 2409 | AW61: =+(AW69*'Maj Production Summ'!AW$18)/1000 -> 33374.592 | AX61: =+SMS!AX58 -> 32352.13 | AY61: =+(AY69*'Maj Production Summ'!AY$18)/1000 -> 3448.5356 | AZ61: =+SMS!AZ58 -> 3289 | BA61: =+AQ61+AU61+AY61 -> 9978.6018 | BB61: =+AR61+AV61+AZ61 -> 8706 | BC61: =+AM61+BA61 -> 20062.062 | BD61: =+AN61+BB61 -> 17082 | BE61: =+AW61+AY61 -> 36823.128 | BF61: =+AX61+AZ61 -> 35641.13 | BH61: 48123.449 | BI61: 38448.13 | BJ61: 45682.844 | BK61: 39439.44 | BL61: 44076.08 | BM61: 45680 | BN61: 40000 | BO61: 44647.62 | BP61: 42007.866 | BQ61: 36347
B62: LP Si-Mn | C62: MT | F62: =+SMS!F59 -> 0 | H62: =+SMS!H59 -> 0 | J62: =+SMS!J59 -> 0 | L62: =+SMS!L59 -> 0 | N62: =+SMS!N59 -> 0 | P62: =+SMS!P59 -> 0 | R62: =+SMS!R59 -> 0 | T62: =+SMS!T59 -> 0 | V62: =+SMS!V59 -> 0 | X62: =+SMS!X59 -> 0 | Z62: =P62+T62+X62 -> 0 | AB62: =+N62+Z62 -> 0 | AD62: =+SMS!AD59 -> 0 | AF62: =+SMS!AF59 -> 0 | AH62: =+SMS!AH59 -> 0 | AJ62: =+SMS!AJ59 -> 0 | AL62: =+SMS!AL59 -> 0 | AN62: =AD62+AH62+AL62 -> 0 | AP62: =+SMS!AP59 -> 0 | AR62: =+SMS!AR59 -> 0 | AT62: =+SMS!AT59 -> 0 | AV62: =+SMS!AV59 -> 0 | AX62: =+SMS!AX59 -> 0 | AZ62: =+SMS!AZ59 -> 0 | BB62: =+SMS!BB59 -> 0 | BD62: =+SMS!BD59 -> 0 | BF62: =+SMS!BF59 -> 0 | BI62: 0 | BK62: 0 | BM62: 25.81
B63: Total Si-Mn | C63: MT | D63: =SUM(D61:D62) -> 39108.929 | E63: =SUM(E61:E62) -> 2688.5592 | F63: =SUM(F61:F62) -> 2872 | G63: =SUM(G61:G62) -> 2372.2581 | H63: =SUM(H61:H62) -> 1223 | I63: =SUM(I61:I62) -> 5060.8173 | J63: =SUM(J61:J62) -> 4095 | K63: =SUM(K61:K62) -> 3291.2478 | ... BF63: =SUM(BF61:BF62) -> 35641.13 | BH63: 48123.449 | BI63: 38448.13 | BJ63: 45682.844 | BK63: 39439.44 | BL63: 44076.08 | BM63: 45705.81
B64: Fe-Si | C64: MT | D64: =+(D72*'Maj Production Summ'!D$18)/1000 -> 6016.8906 | E64: =+(E72*'Maj Production Summ'!E$18)/1000 -> 413.63358 | F64: =+SMS!F61 -> 482 | G64: =+(G72*'Maj Production Summ'!G$18)/1000 -> 364.97081 | H64: =+SMS!H61 -> 243 | I64: =+(I72*'Maj Production Summ'!I$18)/1000 -> 778.60439 | J64: =+SMS!J61 -> 725 | K64: =+(K72*'Maj Production Summ'!K$18)/1000 -> 506.35694 | L64: =+SMS!L61 -> 526.21 | M64: =+(M72*'Maj Production Summ'!M$18)/1000 -> 1284.9613 | N64: =+SMS!N61 -> 1251.21 | O64: =+(O72*'Maj Production Summ'!O$18)/1000 -> 512.40661 | P64: =+SMS!P61 -> 485.894 | Q64: =+(Q72*'Maj Production Summ'!Q$18)/1000 -> 1797.3679 | R64: =+SMS!R61 -> 1737.104 | S64: =+(S72*'Maj Production Summ'!S$18)/1000 -> 512.40661 | T64: =+SMS!T61 -> 516 | U64: =+(U72*'Maj Production Summ'!U$18)/1000 -> 2309.7745 | V64: =+SMS!V61 -> 2253.104 | W64: =+(W72*'Maj Production Summ'!W$18)/1000 -> 268.9076 | X64: =+SMS!X61 -> 481 | Y64: =+O64+S64+W64 -> 1293.7208 | Z64: =+P64+T64+X64 -> 1482.894 | AA64: =+M64+Y64 -> 2578.6821 | AB64: =+N64+Z64 -> 2734.104 | AC64: =+(AC72*'Maj Production Summ'!AC$18)/1000 -> 522.48938 | AD64: =+SMS!AD61 -> 387 | AE64: =+(AE72*'Maj Production Summ'!AE$18)/1000 -> 3101.1715 | AF64: =+SMS!AF61 -> 3121.104 | AG64: =+(AG72*'Maj Production Summ'!AG$18)/1000 -> 506.35694 | AH64: =+SMS!AH61 -> 503 | AI64: =+(AI72*'Maj Production Summ'!AI$18)/1000 -> 3607.5285 | AJ64: =+SMS!AJ61 -> 3624.104 | AK64: =+(AK72*'Maj Production Summ'!AK$18)/1000 -> 522.48938 | AL64: =+SMS!AL61 -> 537 | AM64: =+AC64+AG64+AK64 -> 1551.3357 | AN64: =+AD64+AH64+AL64 -> 1427 | AO64: =+(AO72*'Maj Production Summ'!AO$18)/1000 -> 4130.0178 | AP64: =+SMS!AP61 -> 4161.104 | AQ64: =+(AQ72*'Maj Production Summ'!AQ$18)/1000 -> 530.5556 | AR64: =+SMS!AR61 -> 559 | AS64: =+(AS72*'Maj Production Summ'!AS$18)/1000 -> 4660.5734 | AT64: =+SMS!AT61 -> 4720.104 | AU64: =+(AU72*'Maj Production Summ'!AU$18)/1000 -> 474.09206 | AV64: =+SMS!AV61 -> 418 | AW64: =+(AW72*'Maj Production Summ'!AW$18)/1000 -> 5134.6655 | AX64: =+SMS!AX61 -> 5138.104 | AY64: =+(AY72*'Maj Production Summ'!AY$18)/1000 -> 530.5556 | AZ64: =+SMS!AZ61 -> 487 | BA64: =+AQ64+AU64+AY64 -> 1535.2033 | BB64: =+AR64+AV64+AZ64 -> 1464 | BC64: =+AM64+BA64 -> 3086.539 | BD64: =+AN64+BB64 -> 2891 | BE64: =+AW64+AY64 -> 5665.2211 | BF64: =+AX64+AZ64 -> 5625.104 | BH64: 6002.5359 | BI64: 5918.104 | BJ64: 5352.4858 | BK64: 5627.407 | BL64: 7386.6389 | BM64: 5310 | BN64: 8000 | BO64: 5205.89 | BP64: 7796.1924 | BQ64: 5192
B65: Ferro Alloys Break-up
B66: Fe-Mn | C66: Kg/TCS | D66: 1.2464894 | E66: =+$D$66 -> 1.2464894 | F66: =+(F58/'Maj Production Summ'!F$18)*1000 -> 1.8322238 | G66: =+$D$66 -> 1.2464894 | H66: =+(H58/'Maj Production Summ'!H$18)*1000 -> 1.5005972 | I66: =+$D$66 -> 1.2464894 | J66: =+(J58/'Maj Production Summ'!J$18)*1000 -> 1.7310788 | K66: =+$D$66 -> 1.2464894 | L66: =+(L58/'Maj Production Summ'!L$18)*1000 -> 1.6635655 | M66: =+$D$66 -> 1.2464894 | N66: =+(N58/'Maj Production Summ'!N$18)*1000 -> 1.7019694 | O66: =+$D$66 -> 1.2464894 | P66: =+(P58/'Maj Production Summ'!P$18)*1000 -> 1.5098832 | Q66: =+$D$66 -> 1.2464894 | R66: =+(R58/'Maj Production Summ'!R$18)*1000 -> 1.6424254 | S66: =+$D$66 -> 1.2464894 | T66: =+(T58/'Maj Production Summ'!T$18)*1000 -> 1.2625094 | U66: =+$D$66 -> 1.2464894 | V66: =+(V58/'Maj Production Summ'!V$18)*1000 -> 1.5569302 | W66: =+$D$66 -> 1.2464894 | X66: =+(X58/'Maj Production Summ'!X$18)*1000 -> 1.2916195 | Y66: =+$D$66 -> 1.2464894 | Z66: =+(Z58/'Maj Production Summ'!Z$18)*1000 -> 1.3590835 | AA66: =+$D$66 -> 1.2464894 | AB66: =+(AB58/'Maj Production Summ'!AB$18)*1000 -> 1.5100123 | AC66: =+$D$66 -> 1.2464894 | AD66: =+(AD58/'Maj Production Summ'!AD$18)*1000 -> 1.4006618 | AE66: =+$D$66 -> 1.2464894 | AF66: =+(AF58/'Maj Production Summ'!AF$18)*1000 -> 1.4966087 | AG66: =+$D$66 -> 1.2464894 | AH66: =+(AH58/'Maj Production Summ'!AH$18)*1000 -> 1.2636055 | AI66: =+$D$66 -> 1.2464894 | AJ66: =+(AJ58/'Maj Production Summ'!AJ$18)*1000 -> 1.4649944 | AK66: =+$D$66 -> 1.2464894 | AL66: =+(AL58/'Maj Production Summ'!AL$18)*1000 -> 1.7132678 | AM66: =+$D$66 -> 1.2464894 | AN66: =+(AN58/'Maj Production Summ'!AN$18)*1000 -> 1.465677 | AO66: =+$D$66 -> 1.2464894 | AP66: =+(AP58/'Maj Production Summ'!AP$18)*1000 -> 1.4952081 | AQ66: =+$D$66 -> 1.2464894 | AR66: =+(AR58/'Maj Production Summ'!AR$18)*1000 -> 1.1743193 | AS66: =+$D$66 -> 1.2464894 | AT66: =+(AT58/'Maj Production Summ'!AT$18)*1000 -> 1.4612333 | AU66: =+$D$66 -> 1.2464894 | AV66: =+(AV58/'Maj Production Summ'!AV$18)*1000 -> 0.72966662 | AW66: =+$D$66 -> 1.2464894 | AX66: =+(AX58/'Maj Production Summ'!AX$18)*1000 -> 1.4033636 | AY66: =+$D$66 -> 1.2464894 | AZ66: =+(AZ58/'Maj Production Summ'!AZ$18)*1000 -> 1.7451501 | BA66: =+$D$66 -> 1.2464894 | BB66: =+(BB58/'Maj Production Summ'!BB$18)*1000 -> 1.2590497 | BC66: =+$D$66 -> 1.2464894 | BD66: =+(BD58/'Maj Production Summ'!BD$18)*1000 -> 1.3614687 | BE66: =+$D$66 -> 1.2464894 | BF66: =+(BF58/'Maj Production Summ'!BF$18)*1000 -> 1.4353202 | BH66: 1.6372322 | BI66: 1.4094989 | BJ66: 1.65 | BK66: 1.3221396 | BL66: 1.2919835 | BM66: 1.8691737 | BN66: 1.8 | BO66: 1.8865517 | BP66: 2.60138 | BQ66: 1.780674
B67: LCFeMn | C67: Kg/TCS | D67: 0.78144617 | E67: =+$D$67 -> 0.78144617 | F67: =+(F59/'Maj Production Summ'!F$18)*1000 -> 0.62716709 | G67: =+$D$67 -> 0.78144617 | H67: =+(H59/'Maj Production Summ'!H$18)*1000 -> 0.57165607 | I67: =+$D$67 -> 0.78144617 | J67: =+(J59/'Maj Production Summ'!J$18)*1000 -> 0.6102364 | K67: =+$D$67 -> 0.78144617 | L67: =+(L59/'Maj Production Summ'!L$18)*1000 -> 0.43129475 | M67: =+$D$67 -> 0.78144617 | N67: =+(N59/'Maj Production Summ'!N$18)*1000 -> 0.53308303 | O67: =+$D$67 -> 0.78144617 | P67: =+(P59/'Maj Production Summ'!P$18)*1000 -> 0.54008878 | Q67: =+$D$67 -> 0.78144617 | R67: =+(R59/'Maj Production Summ'!R$18)*1000 -> 0.53525471 | S67: =+$D$67 -> 0.78144617 | T67: =+(T59/'Maj Production Summ'!T$18)*1000 -> 0.55129576 | U67: =+$D$67 -> 0.78144617 | V67: =+(V59/'Maj Production Summ'!V$18)*1000 -> 0.53886454 | W67: =+$D$67 -> 0.78144617 | X67: =+(X59/'Maj Production Summ'!X$18)*1000 -> 0.56866522 | Y67: =+$D$67 -> 0.78144617 | Z67: =+(Z59/'Maj Production Summ'!Z$18)*1000 -> 0.55282393 | AA67: =+$D$67 -> 0.78144617 | AB67: =+(AB59/'Maj Production Summ'!AB$18)*1000 -> 0.54413453 | AC67: =+$D$67 -> 0.78144617 | AD67: =+(AD59/'Maj Production Summ'!AD$18)*1000 -> 0.52455064 | AE67: =+$D$67 -> 0.78144617 | AF67: =+(AF59/'Maj Production Summ'!AF$18)*1000 -> 0.54173404 | AG67: =+$D$67 -> 0.78144617 | AH67: =+(AH59/'Maj Production Summ'!AH$18)*1000 -> 0.48801318 | AI67: =+$D$67 -> 0.78144617 | AJ67: =+(AJ59/'Maj Production Summ'!AJ$18)*1000 -> 0.53444511 | AK67: =+$D$67 -> 0.78144617 | AL67: =+(AL59/'Maj Production Summ'!AL$18)*1000 -> 0.29867941 | AM67: =+$D$67 -> 0.78144617 | AN67: =+(AN59/'Maj Production Summ'!AN$18)*1000 -> 0.42919256 | AO67: =+$D$67 -> 0.78144617 | AP67: =+(AP59/'Maj Production Summ'!AP$18)*1000 -> 0.5057536 | AQ67: =+$D$67 -> 0.78144617 | AR67: =+(AR59/'Maj Production Summ'!AR$18)*1000 -> 0.38588537 | AS67: =+$D$67 -> 0.78144617 | AT67: =+(AT59/'Maj Production Summ'!AT$18)*1000 -> 0.49306231 | AU67: =+$D$67 -> 0.78144617 | AV67: =+(AV59/'Maj Production Summ'!AV$18)*1000 -> 0.77676525 | AW67: =+$D$67 -> 0.78144617 | AX67: =+(AX59/'Maj Production Summ'!AX$18)*1000 -> 0.51550428 | AY67: =+$D$67 -> 0.78144617 | AZ67: =+(AZ59/'Maj Production Summ'!AZ$18)*1000 -> 0.50572044 | BA67: =+$D$67 -> 0.78144617 | BB67: =+(BB59/'Maj Production Summ'!BB$18)*1000 -> 0.54059663 | BC67: =+$D$67 -> 0.78144617 | BD67: =+(BD59/'Maj Production Summ'!BD$18)*1000 -> 0.48537697 | BE67: =+$D$67 -> 0.78144617 | BF67: =+(BF59/'Maj Production Summ'!BF$18)*1000 -> 0.51458951 | BH67: 0.84012576 | BI67: 0.52346155 | BJ67: 0.85 | BK67: 0.58802795 | BL67: 0.24 | BM67: 0.65968939 | BN67: 0 | BO67: 0.46320883 | BP67: 0 | BQ67: 0.41689987
B68: Total Fe-Mn | C68: Kg/TCS | D68: =SUM(D66:D67) -> 2.0279355 | E68: =SUM(E66:E67) -> 2.0279355 | F68: =SUM(F66:F67) -> 2.4593909 | G68: =SUM(G66:G67) -> 2.0279355 | H68: =SUM(H66:H67) -> 2.0722532 | I68: =SUM(I66:I67) -> 2.0279355 | J68: =SUM(J66:J67) -> 2.3413152 | K68: =SUM(K66:K67) -> 2.0279355 | ... BF68: =SUM(BF66:BF67) -> 1.9499097 | BH68: 2.477358 | BI68: 1.9329604 | BJ68: 2.5 | BK68: 1.9101675 | BL68: 1.5319835 | BM68: 2.5288631 | BN68: 1.8 | BO68: 2.3497605 | BP68: 2.60138 | BQ68: 2.1975739
B69: Si-Mn | C69: Kg/TCS | D69: 13.880651 | E69: =+$D$69 -> 13.880651 | F69: =+(F61/'Maj Production Summ'!F$18)*1000 -> 12.865885 | G69: =+$D$69 -> 13.880651 | H69: =+(H61/'Maj Production Summ'!H$18)*1000 -> 12.48456 | I69: =+$D$69 -> 13.880651 | J69: =+(J61/'Maj Production Summ'!J$18)*1000 -> 12.749582 | K69: =+$D$69 -> 13.880651 | L69: =+(L61/'Maj Production Summ'!L$18)*1000 -> 15.47732 | M69: =+$D$69 -> 13.880651 | N69: =+(N61/'Maj Production Summ'!N$18)*1000 -> 13.925687 | O69: =+$D$69 -> 13.880651 | P69: =+(P61/'Maj Production Summ'!P$18)*1000 -> 16.155356 | Q69: =+$D$69 -> 13.880651 | R69: =+(R61/'Maj Production Summ'!R$18)*1000 -> 14.616853 | S69: =+$D$69 -> 13.880651 | T69: =+(T61/'Maj Production Summ'!T$18)*1000 -> 15.095488 | U69: =+$D$69 -> 13.880651 | V69: =+(V61/'Maj Production Summ'!V$18)*1000 -> 14.724564 | W69: =+$D$69 -> 13.880651 | X69: =+(X61/'Maj Production Summ'!X$18)*1000 -> 13.273748 | Y69: =+$D$69 -> 13.880651 | Z69: =+(Z61/'Maj Production Summ'!Z$18)*1000 -> 14.894399 | AA69: =+$D$69 -> 13.880651 | AB69: =+(AB61/'Maj Production Summ'!AB$18)*1000 -> 14.467999 | AC69: =+$D$69 -> 13.880651 | AD69: =+(AD61/'Maj Production Summ'!AD$18)*1000 -> 13.783405 | AE69: =+$D$69 -> 13.880651 | AF69: =+(AF61/'Maj Production Summ'!AF$18)*1000 -> 14.384085 | AG69: =+$D$69 -> 13.880651 | AH69: =+(AH61/'Maj Production Summ'!AH$18)*1000 -> 12.261331 | AI69: =+$D$69 -> 13.880651 | AJ69: =+(AJ61/'Maj Production Summ'!AJ$18)*1000 -> 14.096067 | AK69: =+$D$69 -> 13.880651 | AL69: =+(AL61/'Maj Production Summ'!AL$18)*1000 -> 13.193096 | AM69: =+$D$69 -> 13.880651 | AN69: =+(AN61/'Maj Production Summ'!AN$18)*1000 -> 13.025061 | AO69: =+$D$69 -> 13.880651 | AP69: =+(AP61/'Maj Production Summ'!AP$18)*1000 -> 13.98618 | AQ69: =+$D$69 -> 13.880651 | AR69: =+(AR61/'Maj Production Summ'!AR$18)*1000 -> 13.190263 | AS69: =+$D$69 -> 13.880651 | AT69: =+(AT61/'Maj Production Summ'!AT$18)*1000 -> 13.90191 | AU69: =+$D$69 -> 13.880651 | AV69: =+(AV61/'Maj Production Summ'!AV$18)*1000 -> 13.020496 | AW69: =+$D$69 -> 13.880651 | AX69: =+(AX61/'Maj Production Summ'!AX$18)*1000 -> 13.832187 | AY69: =+$D$69 -> 13.880651 | AZ69: =+(AZ61/'Maj Production Summ'!AZ$18)*1000 -> 13.633726 | BA69: =+$D$69 -> 13.880651 | BB69: =+(BB61/'Maj Production Summ'!BB$18)*1000 -> 13.305762 | BC69: =+$D$69 -> 13.880651 | BD69: =+(BD61/'Maj Production Summ'!BD$18)*1000 -> 13.166627 | BE69: =+$D$69 -> 13.880651 | BF69: =+(BF61/'Maj Production Summ'!BF$18)*1000 -> 13.813631 | BH69: 17.372968 | BI69: 14.22628 | BJ69: 18.35 | BK69: 16.183875 | BL69: 16.822447 | BM69: 18.063011 | BN69: 16 | BO69: 18.431727 | BP69: 16.32641 | BQ69: 15.648491
B70: LP Si-Mn | C70: Kg/TCS | D70: 0 | E70: =D70 -> 0 | F70: =+(F62/'Maj Production Summ'!F$18)*1000 -> 0 | G70: =F70 -> 0 | H70: =+(H62/'Maj Production Summ'!H$18)*1000 -> 0 | J70: =+(J62/'Maj Production Summ'!J$18)*1000 -> 0 | K70: =J70 -> 0 | L70: =+(L62/'Maj Production Summ'!L$18)*1000 -> 0 | M70: =D70 -> 0 | N70: =+(N62/'Maj Production Summ'!N$18)*1000 -> 0 | O70: =N70 -> 0 | P70: =+(P62/'Maj Production Summ'!P$18)*1000 -> 0 | R70: =+(R62/'Maj Production Summ'!R$18)*1000 -> 0 | S70: =R70 -> 0 | T70: =+(T62/'Maj Production Summ'!T$18)*1000 -> 0 | V70: =+(V62/'Maj Production Summ'!V$18)*1000 -> 0 | W70: =V70 -> 0 | X70: =+(X62/'Maj Production Summ'!X$18)*1000 -> 0 | Y70: =D70 -> 0 | Z70: =+(Z62/'Maj Production Summ'!Z$18)*1000 -> 0 | AA70: =D70 -> 0 | AB70: =+(AB62/'Maj Production Summ'!AB$18)*1000 -> 0 | AC70: =AB70 -> 0 | AD70: =+(AD62/'Maj Production Summ'!AD$18)*1000 -> 0 | AF70: =+(AF62/'Maj Production Summ'!AF$18)*1000 -> 0 | AG70: =AF70 -> 0 | AH70: =+(AH62/'Maj Production Summ'!AH$18)*1000 -> 0 | AJ70: =+(AJ62/'Maj Production Summ'!AJ$18)*1000 -> 0 | AK70: =AJ70 -> 0 | AL70: =+(AL62/'Maj Production Summ'!AL$18)*1000 -> 0 | AM70: 0 | AN70: =+(AN62/'Maj Production Summ'!AN$18)*1000 -> 0 | AO70: =D70 -> 0 | AP70: =+(AP62/'Maj Production Summ'!AP$18)*1000 -> 0 | AQ70: =AP70 -> 0 | AR70: =+(AR62/'Maj Production Summ'!AR$18)*1000 -> 0 | AS70: =D70 -> 0 | AT70: =+(AT62/'Maj Production Summ'!AT$18)*1000 -> 0 | AU70: =AT70 -> 0 | AV70: =+(AV62/'Maj Production Summ'!AV$18)*1000 -> 0 | AW70: =H70 -> 0 | AX70: =+(AX62/'Maj Production Summ'!AX$18)*1000 -> 0 | AY70: =AX70 -> 0 | AZ70: =+(AZ62/'Maj Production Summ'!AZ$18)*1000 -> 0 | BA70: =L70 -> 0 | BB70: =+(BB62/'Maj Production Summ'!BB$18)*1000 -> 0 | BC70: =N70 -> 0 | BD70: =+(BD62/'Maj Production Summ'!BD$18)*1000 -> 0 | BE70: =P70 -> 0 | BF70: =+(BF62/'Maj Production Summ'!BF$18)*1000 -> 0 | BH70: 0 | BI70: 0 | BJ70: 0 | BK70: 0 | BL70: 0 | BM70: 0.010205918
B71: Total Si-Mn | C71: Kg/TCS | D71: =SUM(D69:D70) -> 13.880651 | E71: =+$D$69 -> 13.880651 | F71: =SUM(F69:F70) -> 12.865885 | G71: =+$D$69 -> 13.880651 | H71: =SUM(H69:H70) -> 12.48456 | I71: =+$D$69 -> 13.880651 | J71: =SUM(J69:J70) -> 12.749582 | K71: =+$D$69 -> 13.880651 | L71: =SUM(L69:L70) -> 15.47732 | M71: =+$D$69 -> 13.880651 | N71: =SUM(N69:N70) -> 13.925687 | O71: =+$D$69 -> 13.880651 | P71: =SUM(P69:P70) -> 16.155356 | Q71: =+$D$69 -> 13.880651 | R71: =SUM(R69:R70) -> 14.616853 | S71: =+$D$69 -> 13.880651 | T71: =SUM(T69:T70) -> 15.095488 | U71: =+$D$69 -> 13.880651 | V71: =SUM(V69:V70) -> 14.724564 | W71: =+$D$69 -> 13.880651 | X71: =SUM(X69:X70) -> 13.273748 | Y71: =SUM(Y69:Y70) -> 13.880651 | Z71: =SUM(Z69:Z70) -> 14.894399 | AA71: =SUM(AA69:AA70) -> 13.880651 | AB71: =SUM(AB69:AB70) -> 14.467999 | AC71: =+$D$69 -> 13.880651 | AD71: =SUM(AD69:AD70) -> 13.783405 | AE71: =+$D$69 -> 13.880651 | AF71: =SUM(AF69:AF70) -> 14.384085 | AG71: =+$D$69 -> 13.880651 | AH71: =SUM(AH69:AH70) -> 12.261331 | AI71: =+$D$69 -> 13.880651 | AJ71: =SUM(AJ69:AJ70) -> 14.096067 | AK71: =+$D$69 -> 13.880651 | AL71: =SUM(AL69:AL70) -> 13.193096 | AM71: =SUM(AM69:AM70) -> 13.880651 | AN71: =SUM(AN69:AN70) -> 13.025061 | AO71: =+$D$69 -> 13.880651 | AP71: =SUM(AP69:AP70) -> 13.98618 | AQ71: =+$D$69 -> 13.880651 | AR71: =SUM(AR69:AR70) -> 13.190263 | AS71: =+$D$69 -> 13.880651 | AT71: =SUM(AT69:AT70) -> 13.90191 | AU71: =+$D$69 -> 13.880651 | AV71: =SUM(AV69:AV70) -> 13.020496 | AW71: =+$D$69 -> 13.880651 | AX71: =SUM(AX69:AX70) -> 13.832187 | AY71: =+$D$69 -> 13.880651 | AZ71: =SUM(AZ69:AZ70) -> 13.633726 | BA71: =+$D$69 -> 13.880651 | BB71: =SUM(BB69:BB70) -> 13.305762 | BC71: =+$D$69 -> 13.880651 | BD71: =SUM(BD69:BD70) -> 13.166627 | BE71: =+$D$69 -> 13.880651 | BF71: =SUM(BF69:BF70) -> 13.813631 | BH71: 17.372968 | BI71: 14.22628 | BJ71: 18.35 | BK71: 16.183875 | BL71: 16.822447 | BM71: 18.073217 | BN71: =SUM(BN69:BN70) -> 16 | BO71: =SUM(BO69:BO70) -> 18.431727 | BQ71: =SUM(BQ69:BQ70) -> 15.648491
