Workbook
Name _1: #REF!
Name _1: #REF!
Name _1: #REF!
Name _1: #REF!
Name _1: #REF!
Name _1: #REF!
Name _1: #REF!
Name _1: #REF!
Name _1: #REF!
Name _2: #REF!
Name _2: #REF!
Name _2: #REF!
Name _2: #REF!
Name _2: #REF!
Name _2: #REF!
Name _2: #REF!
Name _2: #REF!
Name _2: #REF!
Name _3: #REF!
Name _3: #REF!
Name _3: #REF!
Name _3: #REF!
Name _3: #REF!
Name _3: #REF!
Name _3: #REF!
Name _3: #REF!
Name _4: #REF!
Name _4: #REF!
Name _4: #REF!
Name a: #REF!
Name a: #REF!
Name a: #REF!
Name a: #REF!
Name a: #REF!
Name AA: #REF!
Name AA: #REF!
Name AA: #REF!
Name AA: #REF!
Name AB: #REF!
Name AB: #REF!
Name AB: #REF!
Name AB: #REF!
Name AC: #REF!
Name AC: #REF!
Name AC: #REF!
Name AD: #REF!
Name AD: #REF!
Name AD: #REF!
Name AE: #REF!
Name AE: #REF!
Name AE: #REF!
Name AF: #REF!
Name AF: #REF!
Name AF: #REF!
Name AG: #REF!
Name AG: #REF!
Name AG: #REF!
Name AH: #REF!
Name AH: #REF!
Name AH: #REF!

Sheet Maj Production Summ
B1: MAJOR PRODUCTION SUMMARY | D1: 341.01687 | E1: 29 | F1: =F2-'B-FCE'!F3 -> 26.666667 | G1: 30 | H1: =H2-'B-FCE'!H3 -> 29.791667 | I1: =E1+G1 -> 59 | J1: =F1+H1 -> 56.458333 | K1: 29 | L1: =L2-'B-FCE'!L3 -> 29.61125 | M1: =+E1+G1+K1 -> 88 | N1: =+F1+H1+L1 -> 86.069583 | O1: 30 | P1: =P2-'B-FCE'!P3 -> 31 | Q1: =+M1+O1 -> 118 | R1: =+N1+P1 -> 117.06958 | S1: 30 | T1: =T2-'B-FCE'!T3 -> 30.024306 | U1: =+Q1+S1 -> 148 | V1: =+R1+T1 -> 147.09389 | W1: 17.016867 | X1: =X2-'B-FCE'!X3 -> 29.67375 | Y1: =+O1+S1+W1 -> 77.016867 | Z1: =+P1+T1+X1 -> 90.698056 | AA1: =+U1+W1 -> 165.01687 | AB1: =+V1+X1 -> 176.76764 | AC1: 30 | AD1: =AD2-'B-FCE'!AD3 -> 29.965417 | AE1: =AA1+AC1 -> 195.01687 | AF1: =AB1+AD1 -> 206.73306 | AG1: 29 | AH1: 1 | AI1: =AE1+AG1 -> 224.01687 | AJ1: =AF1+AH1 -> 207.73306 | AK1: 30 | AL1: =31-'B-FCE'!AL3 -> 30.75 | AM1: =+AC1+AG1+AK1 -> 89 | AN1: =+AD1+AH1+AL1 -> 61.715417 | AO1: =AI1+AK1 -> 254.01687 | AP1: =AJ1+AL1 -> 238.48306 | AQ1: 30 | AR1: =31-'B-FCE'!AR3 -> 29.875 | AS1: =AO1+AQ1 -> 284.01687 | AT1: =AP1+AR1 -> 268.35806 | AU1: 27 | AV1: =28-'B-FCE'!AV3 -> 27.1875 | AW1: =AS1+AU1 -> 311.01687 | AX1: =AT1+AV1 -> 295.54556 | AY1: 30 | AZ1: =31-'B-FCE'!AZ3 -> 30.229167 | BA1: =+AQ1+AU1+AY1 -> 87 | BB1: =+AR1+AV1+AZ1 -> 87.291667 | BC1: =+AM1+BA1 -> 176 | BD1: =+AN1+BB1 -> 149.00708 | BE1: =AW1+AY1 -> 341.01687 | BF1: =AX1+AZ1 -> 325.77472
D2: 365 | E2: 30 | F2: 30 | G2: 31 | H2: 31 | I2: =+E2+G2 -> 61 | J2: =+F2+H2 -> 61 | K2: 30 | L2: 30 | M2: =+I2+K2 -> 91 | N2: =+J2+L2 -> 91 | O2: 31 | P2: 31 | Q2: =+M2+O2 -> 122 | R2: =+N2+P2 -> 122 | S2: 31 | T2: 31 | U2: =+Q2+S2 -> 153 | V2: =+R2+T2 -> 153 | W2: 30 | X2: 30 | Y2: =+O2+S2+W2 -> 92 | Z2: =+P2+T2+X2 -> 92 | AA2: =+U2+W2 -> 183 | AB2: =+V2+X2 -> 183 | AC2: 31 | AD2: 31 | AE2: =AA2+AC2 -> 214 | AF2: =AB2+AD2 -> 214 | AG2: 30 | AH2: 30 | AI2: =AE2+AG2 -> 244 | AJ2: =AF2+AH2 -> 244 | AK2: 31 | AL2: 31 | AM2: =+AC2+AG2+AK2 -> 92 | AN2: =+AD2+AH2+AL2 -> 92 | AO2: =AI2+AK2 -> 275 | AP2: =AJ2+AL2 -> 275 | AQ2: 31 | AR2: 31 | AS2: =AO2+AQ2 -> 306 | AT2: =AP2+AR2 -> 306 | AU2: 28 | AV2: 28 | AW2: =AS2+AU2 -> 334 | AX2: =AT2+AV2 -> 334 | AY2: 31 | AZ2: 31 | BA2: =+AQ2+AU2+AY2 -> 90 | BB2: =+AR2+AV2+AZ2 -> 90 | BC2: =+AM2+BA2 -> 182 | BD2: =+AN2+BB2 -> 182 | BE2: =AW2+AY2 -> 365 | BF2: =AX2+AZ2 -> 365 | BN2: 365 | BO2: 365 | BP2: 366 | BQ2: 366
B3: ITEM | C3: Unit | D3: 2025-26 ABP | E3: Apr'25 | G3: May'25 | I3: 2M | K3: Jun'25 | M3: QTR-1 | O3: Jul'25 | Q3: 4M | S3: Aug'25 | U3: 5M | W3: Sep'25 | Y3: QTR 2 | AA3: H1 | AC3: Oct'24 | AE3: 7M | AG3: Nov'24 | AI3: 8M | AK3: Dec'24 | AM3: QTR 3 | AO3: 9M | AQ3: Jan'25 | AS3: 10M | AU3: Feb'25 | AW3: 11M | AY3: Mar'25 | BA3: QTR 4 | BC3: H2 | BE3: 2024-25 | BG3: 2024-25 | BI3: 2023-24 | BK3: 2022-23 | BL3: 2021-22 | BN3: 2020-21 | BP3: 2019-20
E4: ABP | F4: ACT | G4: ABP | H4: ACT | I4: ABP | J4: ACT | K4: ABP | L4: ACT | M4: ABP | N4: ACT | O4: ABP | P4: ACT | Q4: ABP | R4: ACT | S4: ABP | T4: ACT | U4: ABP | V4: ACT | W4: ABP | X4: ACT | Y4: ABP | Z4: ACT | AA4: ABP | AB4: ACT | AC4: ABP | AD4: ACT | AE4: ABP | AF4: ACT | AG4: ABP | AH4: ACT | AI4: ABP | AJ4: ACT | AK4: ABP | AL4: ACT | AM4: ABP | AN4: ACT | AO4: ABP | AP4: ACT | AQ4: ABP | AR4: ACT | AS4: ABP | AT4: ACT | AU4: ABP | AV4: ACT | AW4: ABP | AX4: ACT | AY4: ABP | AZ4: ACT | BA4: ABP | BB4: ACT | BC4: ABP | BD4: ACT | BE4: ABP | BF4: ACT | BG4: ABP | BH4: ACT | BI4: ABP | BJ4: ACT | BK4: ACT | BL4: ABP | BM4: ACT | BN4: ABP | BO4: ACT | BP4: ABP | BQ4: ACT
B5: COKE OVENS PUSHING
B6: (COB#10) | C6: Nos/ day | D6: 94.512329 | E6: 98 | F6: =+F9/F2 -> 97.2 | G6: 98 | H6: =+H9/H2 -> 97.612903 | I6: =+((E6*$E$2)+(G6*$G$2))/$I$2 -> 98 | J6: =+((F6*$F$2)+(H6*$H$2))/$J$2 -> 97.409836 | K6: 94 | L6: =+L9/L2 -> 96.066667 | M6: =+((E6*$E$2)+(G6*$G$2)+(K6*$K$2))/$M$2 -> 96.681319 | N6: =+((F6*$F$2)+(H6*$H$2)+(L6*$L$2))/$N$2 -> 96.967033 | O6: 94 | P6: =+P9/P2 -> 95.419355 | Q6: =+((M6*M$2)+(O6*O$2))/Q$2 -> 96 | R6: =+((N6*N$2)+(P6*P$2))/R$2 -> 96.57377 | S6: 94 | T6: =+T9/T2 -> 98 | U6: =+((Q6*Q$2)+(S6*S$2))/U$2 -> 95.594771 | V6: =+((R6*R$2)+(T6*T$2))/V$2 -> 96.862745 | W6: 92.1 | X6: =+X9/X2 -> 98 | Y6: =+((O$6*O$2)+(S$6*S$2)+(W$6*W$2))/Y$2 -> 93.380435 | Z6: =+((P$6*P$2)+(T$6*T$2)+(X$6*X$2))/Z$2 -> 97.130435 | AA6: =+((M6*M$2)+(Y6*Y$2))/AA$2 -> 95.021858 | AB6: =+((N6*N$2)+(Z6*Z$2))/AB$2 -> 97.04918 | AC6: 96 | AD6: =+AD9/AD2 -> 98 | AE6: =+((AA6*$AA$2)+(AC6*$AC$2))/$AE$2 -> 95.163551 | AF6: =+((AB6*$AB$2)+(AD6*$AD$2))/$AF$2 -> 97.186916 | AG6: 96 | AH6: =+AH9/AH2 -> 94.3 | AI6: =+((AE6*$AE$2)+(AG6*$AG$2))/$AI$2 -> 95.266393 | AJ6: =+((AF6*$AF$2)+(AH6*$AH$2))/$AJ$2 -> 96.831967 | AK6: 96 | AL6: =+AL9/AL2 -> 98 | AM6: =+((AC$6*AC$2)+(AG$6*AG$2)+(AK$6*AK$2))/AM$2 -> 96 | AN6: =+((AD$6*AD$2)+(AH$6*AH$2)+(AL$6*AL$2))/AN$2 -> 96.793478 | AO6: =+((AK6*$AK$2)+(AI6*$AI$2))/$AO$2 -> 95.349091 | AP6: =+((AL6*$AL$2)+(AJ6*$AJ$2))/$AP$2 -> 96.963636 | AQ6: 96 | AR6: =+AR9/AR2 -> 98 | AS6: =+((AO6*$AO$2)+(AQ6*$AQ$2))/$AS$2 -> 95.415033 | AT6: =+((AP6*$AP$2)+(AR6*$AR$2))/$AT$2 -> 97.068627 | AU6: 96 | AV6: =+AV9/AV2 -> 97.678571 | AW6: =+((AS6*$AS$2)+(AU6*$AU$2))/$AW$2 -> 95.464072 | AX6: =+((AT6*$AT$2)+(AV6*$AV$2))/$AX$2 -> 97.11976 | AY6: 96 | AZ6: =+AZ9/AZ2 -> 98 | BA6: =+((AQ$6*AQ$2)+(AU$6*AU$2)+(AY$6*AY$2))/BA$2 -> 96 | BB6: =+((AR$6*AR$2)+(AV$6*AV$2)+(AZ$6*AZ$2))/BB$2 -> 97.9 | BC6: =+((AM6*AM$2)+(BA6*BA$2))/BC$2 -> 96 | BD6: =+((AN6*AN$2)+(BB6*BB$2))/BD$2 -> 97.340659 | BE6: =+((AW6*$AW$2)+(AY6*$AY$2))/$BE$2 -> 95.509589 | BF6: =+((AZ6*$AZ$2)+(AX6*$AX$2))/$BF$2 -> 97.194521 | BG6: 96.420548 | BH6: 97.709589 | BI6: 99 | BJ6: 98.976067 | BK6: 98.783562 | BL6: 99 | BM6: 97.824658 | BN6: 95.547945 | BO6: 95.342466 | BP6: 97 | BQ6: 97.10959
B7: (COB#11) | C7: Nos/ day | D7: 97.630137 | E7: 98 | F7: =+F10/F2 -> 97.1 | G7: 98 | H7: =+H10/H2 -> 97.483871 | I7: =+((E7*$E$2)+(G7*$G$2))/$I$2 -> 98 | J7: =+((F7*$F$2)+(H7*$H$2))/$J$2 -> 97.295082 | K7: 98 | L7: =+L10/L2 -> 98.466667 | M7: =+((E7*$E$2)+(G7*$G$2)+(K7*$K$2))/$M$2 -> 98 | N7: =+((F7*$F$2)+(H7*$H$2)+(L7*$L$2))/$N$2 -> 97.681319 | O7: 98 | P7: =+P10/P2 -> 99 | Q7: =+((M7*M$2)+(O7*O$2))/Q$2 -> 98 | R7: =+((N7*N$2)+(P7*P$2))/R$2 -> 98.016393 | S7: 98 | T7: =+T10/T2 -> 98.516129 | U7: =+((Q7*Q$2)+(S7*S$2))/U$2 -> 98 | V7: =+((R7*R$2)+(T7*T$2))/V$2 -> 98.117647 | W7: 93.5 | X7: =+X10/X2 -> 98.766667 | Y7: =((O7*O2)+(S7*S2)+(W7*W2))/Y2 -> 96.532609 | Z7: =+((P$7*P$2)+(T$7*T$2)+(X$7*X$2))/Z$2 -> 98.76087 | AA7: =+((M7*M$2)+(Y7*Y$2))/AA$2 -> 97.262295 | AB7: =+((N7*N$2)+(Z7*Z$2))/AB$2 -> 98.224044 | AC7: 99 | AD7: =+AD10/AD2 -> 97.83871 | AE7: =+((AA7*$AA$2)+(AC7*$AC$2))/$AE$2 -> 97.514019 | AF7: =+((AB7*$AB$2)+(AD7*$AD$2))/$AF$2 -> 98.168224 | AG7: 99 | AH7: =+AH10/AH2 -> 94 | AI7: =+((AE7*$AE$2)+(AG7*$AG$2))/$AI$2 -> 97.696721 | AJ7: =+((AF7*$AF$2)+(AH7*$AH$2))/$AJ$2 -> 97.655738 | AK7: 99 | AL7: =+AL10/AL2 -> 98.483871 | AM7: =+((AC$7*AC$2)+(AG$7*AG$2)+(AK$7*AK$2))/AM$2 -> 99 | AN7: =+((AD$7*AD$2)+(AH$7*AH$2)+(AL$7*AL$2))/AN$2 -> 96.804348 | AO7: =+((AK7*$AK$2)+(AI7*$AI$2))/$AO$2 -> 97.843636 | AP7: =+((AL7*$AL$2)+(AJ7*$AJ$2))/$AP$2 -> 97.749091 | AQ7: 99 | AR7: =+AR10/AR2 -> 98.483871 | AS7: =+((AO7*$AO$2)+(AQ7*$AQ$2))/$AS$2 -> 97.960784 | AT7: =+((AP7*$AP$2)+(AR7*$AR$2))/$AT$2 -> 97.823529 | AU7: 99 | AV7: =+AV10/AV2 -> 98.392857 | AW7: =+((AS7*$AS$2)+(AU7*$AU$2))/$AW$2 -> 98.047904 | AX7: =+((AT7*$AT$2)+(AV7*$AV$2))/$AX$2 -> 97.871257 | AY7: 99 | AZ7: =+AZ10/AZ2 -> 98.645161 | BA7: =+((AQ$7*AQ$2)+(AU$7*AU$2)+(AY$7*AY$2))/BA$2 -> 99 | BB7: =+((AR$7*AR$2)+(AV$7*AV$2)+(AZ$7*AZ$2))/BB$2 -> 98.511111 | BC7: =+((AM7*AM$2)+(BA7*BA$2))/BC$2 -> 99 | BD7: =+((AN7*AN$2)+(BB7*BB$2))/BD$2 -> 97.648352 | BE7: =+((AW7*$AW$2)+(AY7*$AY$2))/$BE$2 -> 98.128767 | BF7: =+((AZ7*$AZ$2)+(AX7*$AX$2))/$BF$2 -> 97.936986 | BG7: 98.167671 | BH7: 97.991781 | BI7: 98.000061 | BJ7: 96.670251 | BK7: 92.210959 | BL7: 99 | BM7: 96.816438 | BN7: 94.2 | BO7: 90.778082 | BP7: 97 | BQ7: 95.710246
B8: Overall Equiv. Ovens Pushed/ Day | C8: Nos/ day | D8: =+D6+(D7*(31.55/17.2)) -> 273.59552 | E8: =+E6+(E7*(31.55/17.2)) -> 277.76163 | F8: =+F6+(F7*(31.55/17.2)) -> 275.31076 | G8: =+G6+(G7*(31.55/17.2)) -> 277.76163 | H8: =+H6+(H7*(31.55/17.2)) -> 276.42779 | I8: =+I6+(I7*(31.55/17.2)) -> 277.76163 | J8: =+J6+(J7*(31.55/17.2)) -> 275.87843 | K8: =+K6+(K7*(31.55/17.2)) -> 273.76163 | ... X8: =+X6+(X7*(31.55/17.2)) -> 279.16793 | Y8: =Y6+(Y7*31.55/17.2) -> 270.45042 | Z8: =Z6+(Z7*31.55/17.2) -> 278.28773 | AA8: =AA6+(AA7*31.55/17.2) -> 273.43031 | AB8: =AB6+(AB7*31.55/17.2) -> 277.22177 | AC8: =+AC6+(AC7*(31.55/17.2)) -> 277.59593 | AD8: =+AD6+(AD7*(31.55/17.2)) -> 277.46577 | AE8: =+AE6+(AE7*(31.55/17.2)) -> 274.03374 | AF8: =+AF6+(AF7*(31.55/17.2)) -> 277.25712 | AG8: =+AG6+(AG7*(31.55/17.2)) -> 277.59593 | AH8: =+AH6+(AH7*(31.55/17.2)) -> 266.72442 | AI8: =+AI6+(AI7*(31.55/17.2)) -> 274.47172 | AJ8: =+AJ6+(AJ7*(31.55/17.2)) -> 275.96211 | ... AL8: =+AL6+(AL7*(31.55/17.2)) -> 278.64919 | AM8: =AM6+(AM7*31.55/17.2) -> 277.59593 | AN8: =AN6+(AN7*31.55/17.2) -> 274.36192 | AO8: =+AO6+(AO7*(31.55/17.2)) -> 274.8239 | AP8: =+AP6+(AP7*(31.55/17.2)) -> 276.26502 | AQ8: =+AQ6+(AQ7*(31.55/17.2)) -> 277.59593 | AR8: =+AR6+(AR7*(31.55/17.2)) -> 278.64919 | AS8: =+AS6+(AS7*(31.55/17.2)) -> 275.10473 | AT8: =+AT6+(AT7*(31.55/17.2)) -> 276.50655 | AU8: =+AU6+(AU7*(31.55/17.2)) -> 277.59593 | AV8: =+AV6+(AV7*(31.55/17.2)) -> 278.16082 | ... AZ8: =+AZ6+(AZ7*(31.55/17.2)) -> 278.94505 | BA8: =BA6+(BA7*31.55/17.2) -> 277.59593 | BB8: =BB6+(BB7*31.55/17.2) -> 278.59916 | BC8: =BC6+(BC7*31.55/17.2) -> 277.59593 | BD8: =BD6+(BD7*31.55/17.2) -> 276.45726 | BE8: =+BE6+(BE7*(31.55/17.2)) -> 275.50741 | BF8: =+BF6+(BF7*(31.55/17.2)) -> 276.84056 | BG8: 276.48974 | BH8: 277.45614 | BI8: 278.76174 | BJ8: 276.29853 | BK8: 267.92634 | BL8: 280.59593 | BM8: 275.41528 | BN8: 268.33922 | BO8: 261.85691 | BP8: 274.92733 | BQ8: 272.67112
B9: (COB#10) | C9: Nos | D9: =+D6*D2 -> 34497 | E9: =+E6*E2 -> 2940 | F9: 2916 | G9: =+G6*G2 -> 3038 | H9: 3026 | I9: =+I6*I2 -> 5978 | J9: =+F9+H9 -> 5942 | K9: =+K6*K2 -> 2820 | L9: 2882 | M9: =+E9+G9+K9 -> 8798 | N9: =+F9+H9+L9 -> 8824 | O9: =+O6*O2 -> 2914 | P9: 2958 | Q9: =+M9+O9 -> 11712 | R9: =+N9+P9 -> 11782 | S9: =+S6*S2 -> 2914 | T9: 3038 | U9: =+Q9+S9 -> 14626 | V9: =+R9+T9 -> 14820 | W9: =+W6*W2 -> 2763 | X9: 2940 | Y9: =+O9+S9+W9 -> 8591 | Z9: =+P9+T9+X9 -> 8936 | AA9: =M9+Y9 -> 17389 | AB9: =+N9+Z9 -> 17760 | AC9: =+AC6*AC2 -> 2976 | AD9: 3038 | AE9: =+AE6*AE2 -> 20365 | AF9: =+AB9+AD9 -> 20798 | AG9: =+AG6*AG2 -> 2880 | AH9: 2829 | AI9: =+AI6*AI2 -> 23245 | AJ9: =+AF9+AH9 -> 23627 | AK9: =+AK6*AK2 -> 2976 | AL9: 3038 | AM9: =+AC9+AG9+AK9 -> 8832 | AN9: =+AD9+AH9+AL9 -> 8905 | AO9: =AI9+AK9 -> 26221 | AP9: =AJ9+AL9 -> 26665 | AQ9: =+AQ6*AQ2 -> 2976 | AR9: 3038 | AS9: =+AS6*AS2 -> 29197 | AT9: =+AP9+AR9 -> 29703 | AU9: =+AU6*AU2 -> 2688 | AV9: 2735 | AW9: =+AW6*AW2 -> 31885 | AX9: =+AT9+AV9 -> 32438 | AY9: =+AY6*AY2 -> 2976 | AZ9: 3038 | BA9: =+AQ9+AU9+AY9 -> 8640 | BB9: =+AR9+AV9+AZ9 -> 8811 | BC9: =AM9+BA9 -> 17472 | BD9: =AN9+BB9 -> 17716 | BE9: =AW9+AY9 -> 34861 | BF9: =AX9+AZ9 -> 35476 | BG9: 35193.5 | BH9: 35664 | BI9: 36234 | BJ9: 36225 | BK9: 36056 | BL9: 36135 | BM9: 35706 | BN9: 34875 | BO9: 34800 | BP9: 35502 | BQ9: 35543
B10: (COB#11) | C10: Nos | D10: =+D7*D2 -> 35635 | E10: =+E7*E2 -> 2940 | F10: 2913 | G10: =+G7*G2 -> 3038 | H10: 3022 | I10: =+I7*I2 -> 5978 | J10: =+F10+H10 -> 5935 | K10: =+K7*K2 -> 2940 | L10: 2954 | M10: =+E10+G10+K10 -> 8918 | N10: =+F10+H10+L10 -> 8889 | O10: =+O7*O2 -> 3038 | P10: 3069 | Q10: =+M10+O10 -> 11956 | R10: =+N10+P10 -> 11958 | S10: =+S7*S2 -> 3038 | T10: 3054 | U10: =+Q10+S10 -> 14994 | V10: =+R10+T10 -> 15012 | W10: =+W7*W2 -> 2805 | X10: 2963 | Y10: =+O10+S10+W10 -> 8881 | Z10: =+P10+T10+X10 -> 9086 | AA10: =+M10+Y10 -> 17799 | AB10: =+N10+Z10 -> 17975 | AC10: =+AC7*AC2 -> 3069 | AD10: 3033 | AE10: =+AE7*AE2 -> 20868 | AF10: =+AB10+AD10 -> 21008 | AG10: =+AG7*AG2 -> 2970 | AH10: 2820 | AI10: =+AI7*AI2 -> 23838 | AJ10: =+AF10+AH10 -> 23828 | AK10: =+AK7*AK2 -> 3069 | AL10: 3053 | AM10: =+AC10+AG10+AK10 -> 9108 | AN10: =+AD10+AH10+AL10 -> 8906 | AO10: =AI10+AK10 -> 26907 | AP10: =AJ10+AL10 -> 26881 | AQ10: =+AQ7*AQ2 -> 3069 | AR10: 3053 | AS10: =+AS7*AS2 -> 29976 | AT10: =+AP10+AR10 -> 29934 | AU10: =+AU7*AU2 -> 2772 | AV10: 2755 | AW10: =+AW7*AW2 -> 32748 | AX10: =+AT10+AV10 -> 32689 | AY10: =+AY7*AY2 -> 3069 | AZ10: 3058 | BA10: =+AQ10+AU10+AY10 -> 8910 | BB10: =+AR10+AV10+AZ10 -> 8866 | BC10: =AM10+BA10 -> 18018 | BD10: =AN10+BB10 -> 17772 | BE10: =AW10+AY10 -> 35817 | BF10: =AX10+AZ10 -> 35747 | BG10: 35831.2 | BH10: 35767 | BI10: 35868.022 | BJ10: 35382 | BK10: 33657 | BL10: 36135 | BM10: 35338 | BN10: 34383 | BO10: 33134 | BP10: 35502 | BQ10: 35030
B11: Overall Equiv. Ovens Pushed | C11: Nos | D11: =+D9+(D10*(31.55/17.2)) -> 99862.363 | E11: =+E9+(E10*(31.55/17.2)) -> 8332.8488 | F11: =+F9+(F10*(31.55/17.2)) -> 8259.3227 | G11: =+G9+(G10*(31.55/17.2)) -> 8610.6105 | H11: =+H9+(H10*(31.55/17.2)) -> 8569.2616 | I11: =+I9+(I10*(31.55/17.2)) -> 16943.459 | J11: =+J9+(J10*(31.55/17.2)) -> 16828.584 | K11: =+K9+(K10*(31.55/17.2)) -> 8212.8488 | ... X11: =+X9+(X10*(31.55/17.2)) -> 8375.0378 | Y11: =Y9+(Y10*31.55/17.2) -> 24881.439 | Z11: =Z9+(Z10*31.55/17.2) -> 25602.471 | AA11: =AA9+(AA10*31.55/17.2) -> 50037.747 | AB11: =AB9+(AB10*31.55/17.2) -> 50731.584 | AC11: =+AC9+(AC10*(31.55/17.2)) -> 8605.4738 | AD11: =+AD9+(AD10*(31.55/17.2)) -> 8601.439 | AE11: =+AE9+(AE10*(31.55/17.2)) -> 58643.221 | AF11: =+AF9+(AF10*(31.55/17.2)) -> 59333.023 | AG11: =+AG9+(AG10*(31.55/17.2)) -> 8327.8779 | AH11: =+AH9+(AH10*(31.55/17.2)) -> 8001.7326 | AI11: =+AI9+(AI10*(31.55/17.2)) -> 66971.099 | AJ11: =+AJ9+(AJ10*(31.55/17.2)) -> 67334.756 | ... AL11: =+AL9+(AL10*(31.55/17.2)) -> 8638.125 | AM11: =AM9+(AM10*31.55/17.2) -> 25538.826 | AN11: =AN9+(AN10*31.55/17.2) -> 25241.297 | AO11: =+AO9+(AO10*(31.55/17.2)) -> 75576.573 | AP11: =+AP9+(AP10*(31.55/17.2)) -> 75972.881 | AQ11: =+AQ9+(AQ10*(31.55/17.2)) -> 8605.4738 | AR11: =+AR9+(AR10*(31.55/17.2)) -> 8638.125 | AS11: =+AS9+(AS10*(31.55/17.2)) -> 84182.047 | AT11: =+AT9+(AT10*(31.55/17.2)) -> 84611.006 | AU11: =+AU9+(AU10*(31.55/17.2)) -> 7772.686 | AV11: =+AV9+(AV10*(31.55/17.2)) -> 7788.5029 | ... AZ11: =+AZ9+(AZ10*(31.55/17.2)) -> 8647.2965 | BA11: =BA9+(BA10*31.55/17.2) -> 24983.634 | BB11: =BB9+(BB10*31.55/17.2) -> 25073.924 | BC11: =BC9+(BC10*31.55/17.2) -> 50522.459 | BD11: =BD9+(BD10*31.55/17.2) -> 50315.221 | BE11: =+BE9+(BE10*(31.55/17.2)) -> 100560.21 | BF11: =+BF9+(BF10*(31.55/17.2)) -> 101046.81 | BG11: 100918.75 | BH11: 101271.49 | BI11: 102026.8 | BJ11: 101126.28 | BK11: 97793.113 | BL11: 102417.51 | BM11: 100526.58 | BN11: 97943.817 | BO11: 95577.773 | BP11: 100623.4 | BQ11: 99798.61
B12: BF COKE
B13: COB#10 | C13: Mt | D13: =+D9*0.7*17.2 -> 415343.88 | E13: =+E9*0.7*17.2 -> 35397.6 | F13: ='COKE OVENS'!F21 -> 35108.64 | G13: =+G9*0.7*17.2 -> 36577.52 | H13: ='COKE OVENS'!H21 -> 36433.04 | I13: =+E13+G13 -> 71975.12 | J13: =+F13+H13 -> 71541.68 | K13: =+K9*0.7*17.2 -> 33952.8 | L13: ='COKE OVENS'!L21 -> 34699.28 | M13: =+E13+G13+K13 -> 105927.92 | N13: =+F13+H13+L13 -> 106240.96 | O13: =+O9*0.7*17.2 -> 35084.56 | P13: ='COKE OVENS'!P21 -> 35614.32 | Q13: =+M13+O13 -> 141012.48 | R13: =+N13+P13 -> 141855.28 | S13: =+S9*0.7*17.2 -> 35084.56 | T13: ='COKE OVENS'!T21 -> 36577.52 | U13: =+Q13+S13 -> 176097.04 | V13: =+R13+T13 -> 178432.8 | W13: =+W9*0.7*17.2 -> 33266.52 | X13: ='COKE OVENS'!X21 -> 35397.6 | Y13: =+O13+S13+W13 -> 103435.64 | Z13: =+P13+T13+X13 -> 107589.44 | AA13: =+M13+Y13 -> 209363.56 | AB13: =+N13+Z13 -> 213830.4 | AC13: =+AC9*0.7*17.2 -> 35831.04 | AD13: ='COKE OVENS'!AD21 -> 36839 | AE13: =+AA13+AC13 -> 245194.6 | AF13: =+AB13+AD13 -> 250669.4 | AG13: =+AG9*0.7*17.2 -> 34675.2 | AH13: ='COKE OVENS'!AH21 -> 34299.588 | AI13: =+AE13+AG13 -> 279869.8 | AJ13: =+AF13+AH13 -> 284968.99 | AK13: =+AK9*0.7*17.2 -> 35831.04 | AL13: ='COKE OVENS'!AL21 -> 36582.745 | AM13: =+AC13+AG13+AK13 -> 106337.28 | AN13: =+AD13+AH13+AL13 -> 107721.33 | AO13: =AI13+AK13 -> 315700.84 | AP13: =AJ13+AL13 -> 321551.73 | AQ13: =+AQ9*0.7*17.2 -> 35831.04 | AR13: ='COKE OVENS'!AR21 -> 36888.429 | AS13: =+AO13+AQ13 -> 351531.88 | AT13: =+AP13+AR13 -> 358440.16 | AU13: =+AU9*0.7*17.2 -> 32363.52 | AV13: ='COKE OVENS'!AV21 -> 33164.61 | AW13: =+AS13+AU13 -> 383895.4 | AX13: =+AT13+AV13 -> 391604.77 | AY13: =+AY9*0.7*17.2 -> 35831.04 | AZ13: ='COKE OVENS'!AZ21 -> 36838.788 | BA13: =+AQ13+AU13+AY13 -> 104025.6 | BB13: =+AR13+AV13+AZ13 -> 106891.83 | BC13: =AM13+BA13 -> 210362.88 | BD13: =AN13+BB13 -> 214613.16 | BE13: =AW13+AY13 -> 419726.44 | BF13: =AX13+AZ13 -> 428443.56 | BG13: 423729.74 | BH13: 431508.84 | BI13: 433141.24 | BJ13: 432382.85 | BK13: 430769.03 | BL13: 438172.79 | BM13: 428806 | BN13: 425506 | BO13: 430922.2 | BP13: 406071.88 | BQ13: 412610.14
B14: COB#11 | C14: Mt | D14: =+D10*0.7*31.55 -> 786998.97 | E14: =+E10*31.55*0.7 -> 64929.9 | F14: ='COKE OVENS'!F22 -> 64333.605 | G14: =+G10*31.55*0.7 -> 67094.23 | H14: ='COKE OVENS'!H22 -> 66740.87 | I14: =+E14+G14 -> 132024.13 | J14: =+F14+H14 -> 131074.48 | K14: =+K10*31.55*0.7 -> 64929.9 | L14: ='COKE OVENS'!L22 -> 65239.09 | M14: =+E14+G14+K14 -> 196954.03 | N14: =+F14+H14+L14 -> 196313.57 | O14: =+O10*31.55*0.7 -> 67094.23 | P14: ='COKE OVENS'!P22 -> 67778.865 | Q14: =+M14+O14 -> 264048.26 | R14: =+N14+P14 -> 264092.43 | S14: =+S10*31.55*0.7 -> 67094.23 | T14: ='COKE OVENS'!T22 -> 67447.59 | U14: =+Q14+S14 -> 331142.49 | V14: =+R14+T14 -> 331540.02 | W14: =+W10*31.55*0.7 -> 61948.425 | X14: ='COKE OVENS'!X22 -> 64963.855 | Y14: =+O14+S14+W14 -> 196136.88 | Z14: =+P14+T14+X14 -> 200190.31 | AA14: =+M14+Y14 -> 393090.91 | AB14: =+N14+Z14 -> 396503.88 | AC14: =+AC10*31.55*0.7 -> 67778.865 | AD14: ='COKE OVENS'!AD22 -> 67418 | AE14: =+AA14+AC14 -> 460869.78 | AF14: =+AB14+AD14 -> 463921.88 | AG14: =+AG10*31.55*0.7 -> 65592.45 | AH14: ='COKE OVENS'!AH22 -> 62715.658 | AI14: =+AE14+AG14 -> 526462.23 | AJ14: =+AF14+AH14 -> 526637.53 | AK14: =+AK10*31.55*0.7 -> 67778.865 | AL14: ='COKE OVENS'!AL22 -> 67435.137 | AM14: =+AC14+AG14+AK14 -> 201150.18 | AN14: =+AD14+AH14+AL14 -> 197568.8 | AO14: =AI14+AK14 -> 594241.09 | AP14: =AJ14+AL14 -> 594072.67 | AQ14: =+AQ10*31.55*0.7 -> 67778.865 | AR14: ='COKE OVENS'!AR22 -> 67998.622 | AS14: =+AO14+AQ14 -> 662019.96 | AT14: =+AP14+AR14 -> 662071.29 | AU14: =+AU10*31.55*0.7 -> 61219.62 | AV14: ='COKE OVENS'!AV22 -> 61278.776 | AW14: =+AS14+AU14 -> 723239.58 | AX14: =+AT14+AV14 -> 723350.07 | AY14: =+AY10*31.55*0.7 -> 67778.865 | AZ14: ='COKE OVENS'!AZ22 -> 68018.33 | BA14: =+AQ14+AU14+AY14 -> 196777.35 | BB14: =+AR14+AV14+AZ14 -> 197295.73 | BC14: =AM14+BA14 -> 397927.53 | BD14: =AN14+BB14 -> 394864.52 | BE14: =AW14+AY14 -> 791018.44 | BF14: =AX14+AZ14 -> 791368.4 | BG14: 791332.05 | BH14: 793765.31 | BI14: 786486.6 | BJ14: 774691.65 | BK14: 737579.38 | BL14: 803741.8 | BM14: 778192 | BN14: 770203 | BO14: 752591.4 | BP14: 744858.59 | BQ14: 745859.84
B15: Total BF COKE | C15: Mt | D15: =SUM(D13:D14) -> 1202342.9 | E15: =SUM(E13:E14) -> 100327.5 | F15: =SUM(F13:F14) -> 99442.245 | G15: =SUM(G13:G14) -> 103671.75 | H15: =SUM(H13:H14) -> 103173.91 | I15: =SUM(I13:I14) -> 203999.25 | J15: =SUM(J13:J14) -> 202616.15 | K15: =SUM(K13:K14) -> 98882.7 | ... BF15: =SUM(BF13:BF14) -> 1219812 | BG15: 1215061.8 | BH15: 1225274.2 | BI15: 1219627.8 | BJ15: 1207074.5 | BK15: 1168348.4 | BL15: 1241914.6 | BM15: 1206998 | BN15: 1195709 | BO15: 1183513.6 | BP15: 1150930.5 | BQ15: 1158470
B16: SINTER | C16: Mt | D16: =4362.87596292192*1000+124 -> 4363000 | E16: =372.191438188584*1000 -> 372191.44 | F16: 321830 | G16: =383.372118766*1000 -> 383372.12 | H16: 355306 | I16: =+E16+G16 -> 755563.56 | J16: =+F16+H16 -> 677136 | K16: =372.191438188584*1000 -> 372191.44 | L16: 376274 | M16: =+E16+G16+K16 -> 1127755 | N16: =+F16+H16+L16 -> 1053410 | O16: =376.384193405115*1000 -> 376384.19 | P16: 397960 | Q16: =+M16+O16 -> 1504139.2 | R16: =+N16+P16 -> 1451370 | S16: =376.384193405115*1000 -> 376384.19 | T16: 383179 | U16: =+Q16+S16 -> 1880523.4 | V16: =+R16+T16 -> 1834549 | W16: =207.661910104769*1000 -> 207661.91 | X16: 374784 | Y16: =+O16+S16+W16 -> 960430.3 | Z16: =+P16+T16+X16 -> 1155923 | AA16: =+M16+Y16 -> 2088185.3 | AB16: =+N16+Z16 -> 2209333 | AC16: 403051.36 | AD16: 372857 | AE16: =+AA16+AC16 -> 2491236.7 | AF16: =+AB16+AD16 -> 2582190 | AG16: =392.409719810871*1000 -> 392409.72 | AH16: 24407 | AI16: =+AE16+AG16 -> 2883646.4 | AJ16: =+AF16+AH16 -> 2606597 | AK16: =403.051363440982*1000 -> 403051.36 | AL16: 361604 | AM16: =+AC16+AG16+AK16 -> 1198512.4 | AN16: =+AD16+AH16+AL16 -> 758868 | AO16: =AI16+AK16 -> 3286697.7 | AP16: =AJ16+AL16 -> 2968201 | AQ16: =403.051363440982*1000 -> 403051.36 | AR16: 369250 | AS16: =+AO16+AQ16 -> 3689749.1 | AT16: =+AP16+AR16 -> 3337451 | AU16: =365.546227096884*1000 -> 365546.23 | AV16: 342499 | AW16: =+AS16+AU16 -> 4055295.3 | AX16: =+AT16+AV16 -> 3679950 | AY16: =403.051363440982*1000 -> 403051.36 | AZ16: 410020 | BA16: =+AQ16+AU16+AY16 -> 1171649 | BB16: =+AR16+AV16+AZ16 -> 1121769 | BC16: =AM16+BA16 -> 2370161.4 | BD16: =AN16+BB16 -> 1880637 | BE16: =AW16+AY16 -> 4458346.7 | BF16: =AX16+AZ16 -> 4089970 | BG16: 4387544.5 | BH16: 3980714 | BI16: 4499999.9 | BJ16: 4398445 | BK16: 4395665 | BL16: 4183927.8 | BM16: 4277831 | BN16: 3665891.3 | BO16: 3629577 | BP16: 3903932.5 | BQ16: 3709525
B17: HOT METAL | C17: Mt | D17: 2950000 | E17: 252000 | F17: 226125.6 | G17: 260000 | H17: 255730.9 | I17: =+E17+G17 -> 512000 | J17: =+F17+H17 -> 481856.5 | K17: =252*1000 -> 252000 | L17: 261489.9 | M17: =+E17+G17+K17 -> 764000 | N17: =+F17+H17+L17 -> 743346.4 | O17: 255000 | P17: 268142.3 | Q17: =+M17+O17 -> 1019000 | R17: =+N17+P17 -> 1011488.7 | S17: 255000 | T17: 253263.6 | U17: =+Q17+S17 -> 1274000 | V17: =+R17+T17 -> 1264752.3 | W17: 140000 | X17: 243297.4 | Y17: =+O17+S17+W17 -> 650000 | Z17: =+P17+T17+X17 -> 764703.3 | AA17: =+M17+Y17 -> 1414000 | AB17: =+N17+Z17 -> 1508049.7 | AC17: 250000 | AD17: 237886.3 | AE17: =+AA17+AC17 -> 1664000 | AF17: =+AB17+AD17 -> 1745936 | AG17: 242000 | AH17: 8246.5 | AI17: =+AE17+AG17 -> 1906000 | AJ17: =+AF17+AH17 -> 1754182.5 | AK17: 250000 | AL17: 257290.9 | AM17: =+AC17+AG17+AK17 -> 742000 | AN17: =+AD17+AH17+AL17 -> 503423.7 | AO17: =AI17+AK17 -> 2156000 | AP17: =AJ17+AL17 -> 2011473.4 | AQ17: =250*1000 -> 250000 | AR17: 261845.4 | AS17: =+AO17+AQ17 -> 2406000 | AT17: =+AP17+AR17 -> 2273318.8 | AU17: =225*1000 -> 225000 | AV17: 239624 | AW17: =+AS17+AU17 -> 2631000 | AX17: =+AT17+AV17 -> 2512942.8 | AY17: 250000 | AZ17: 263830 | BA17: =+AQ17+AU17+AY17 -> 725000 | BB17: =+AR17+AV17+AZ17 -> 765299.4 | BC17: =AM17+BA17 -> 1467000 | BD17: =AN17+BB17 -> 1268723.1 | BE17: =AW17+AY17 -> 2881000 | BF17: =AX17+AZ17 -> 2776772.8 | BG17: 2650000 | BH17: 2622585.7 | BI17: 2800000 | BJ17: 2721268.1 | BK17: 2592119.6 | BL17: 2650001 | BM17: 2406785.7 | BN17: 2496672.2 | BO17: 2092798 | BP17: 2700000 | BQ17: 2505193
B18: CRUDE STEEL | C18: Mt | D18: =2770.01888574126*1000-19 -> 2769999.9 | E18: =237.110481586402*1000 -> 237110.48 | F18: 207020 | G18: =244.66477809254*1000 -> 244664.78 | H18: 236638 | I18: =+E18+G18 -> 481775.26 | J18: =+F18+H18 -> 443658 | K18: =237.110481586402*1000 -> 237110.48 | L18: 243453 | M18: =+E18+G18+K18 -> 718885.74 | N18: =+F18+H18+L18 -> 687111 | O18: =239.943342776204*1000 -> 239943.34 | P18: 253662 | Q18: =+M18+O18 -> 958829.08 | R18: =+N18+P18 -> 940773 | S18: =239.943342776204*1000 -> 239943.34 | T18: 237622 | U18: =+Q18+S18 -> 1198772.4 | V18: =+R18+T18 -> 1178395 | W18: =125.920679886686*1000 -> 125920.68 | X18: 226847 | Y18: =+O18+S18+W18 -> 605807.37 | Z18: =+P18+T18+X18 -> 718131 | AA18: =+M18+Y18 -> 1324693.1 | AB18: =+N18+Z18 -> 1405242 | AC18: 235490.57 | AD18: 222138 | AE18: =+AA18+AC18 -> 1560183.7 | AF18: =+AB18+AD18 -> 1627380 | AG18: =227.943396226415*1000 -> 227943.4 | AH18: 7935 | AI18: =+AE18+AG18 -> 1788127.1 | AJ18: =+AF18+AH18 -> 1635315 | AK18: =235.490566037736*1000 -> 235490.57 | AL18: 234930 | AM18: =+AC18+AG18+AK18 -> 698924.53 | AN18: =+AD18+AH18+AL18 -> 465003 | AO18: =AI18+AK18 -> 2023617.6 | AP18: =AJ18+AL18 -> 1870245 | AQ18: =235.490566037736*1000 -> 235490.57 | AR18: 246040 | AS18: =+AO18+AQ18 -> 2259108.2 | AT18: =+AP18+AR18 -> 2116285 | AU18: =211.905660377358*1000 -> 211905.66 | AV18: 222895 | AW18: =+AS18+AU18 -> 2471013.9 | AX18: =+AT18+AV18 -> 2339180 | AY18: =235.490566037736*1000 -> 235490.57 | AZ18: 243552 | BA18: =+AQ18+AU18+AY18 -> 682886.79 | BB18: =+AR18+AV18+AZ18 -> 712487 | BC18: =AM18+BA18 -> 1381811.3 | BD18: =AN18+BB18 -> 1177490 | BE18: =AW18+AY18 -> 2706504.4 | BF18: =AX18+AZ18 -> 2582732 | BG18: 2489528.3 | BH18: 2436959 | BI18: 2620075.5 | BJ18: 2528925 | BK18: 2422324.3 | BL18: 2451737.7 | BM18: 2227867 | BN18: 2297163.5 | BO18: 1847433 | BP18: 2500000 | BQ18: 2083412
B19: Caster #(1+2 ) | C19: Mt | D19: =1978.46215750908*1000-2 -> 1978460.2 | E19: =SMS!E29 -> 171675.13 | F19: =SMS!F37 -> 149261 | G19: =SMS!G29 -> 176063.19 | H19: =SMS!H37 -> 175199.54 | I19: =+E19+G19 -> 347738.32 | J19: =SMS!J37 -> 324460.54 | K19: =SMS!K29 -> 171147.42 | L19: =SMS!L37 -> 182735 | M19: =+E19+G19+K19 -> 518885.74 | N19: =+F19+H19+L19 -> 507195.54 | O19: =SMS!O29 -> 171341.76 | P19: =SMS!P37 -> 189077 | Q19: =+M19+O19 -> 690227.5 | R19: =+N19+P19 -> 696272.54 | S19: =SMS!S29 -> 171341.76 | T19: =SMS!T37 -> 179543 | U19: =+Q19+S19 -> 861569.26 | V19: =+R19+T19 -> 875815.54 | W19: =SMS!W29 -> 90564.479 | X19: =SMS!X37 -> 172339.6 | Y19: =+O19+S19+W19 -> 433248 | Z19: =+P19+T19+X19 -> 540959.6 | AA19: =+M19+Y19 -> 952133.74 | AB19: =+N19+Z19 -> 1048155.1 | AC19: =SMS!AC29 -> 177750 | AD19: =SMS!AD37 -> 168140 | AE19: =+AA19+AC19 -> 1129883.7 | AF19: =+AB19+AD19 -> 1216295.1 | AG19: =SMS!AG29 -> 171825 | AH19: =SMS!AH37 -> 7935 | AI19: =SMS!AI29 -> 1301708.7 | AJ19: =SMS!AJ37 -> 1224230.1 | AK19: =SMS!AK29 -> 177840.45 | AL19: =SMS!AL37 -> 176215.37 | AM19: =SMS!AM29 -> 527415.45 | AN19: =SMS!AN37 -> 352290.37 | AO19: =SMS!AO29 -> 1479549.2 | AP19: =SMS!AP37 -> 1400445.5 | AQ19: =SMS!AQ29 -> 177750 | AR19: =SMS!AR37 -> 183526 | AS19: =+AO19+AQ19 -> 1657299.2 | AT19: =+AP19+AR19 -> 1583971.5 | AU19: =SMS!AU29 -> 159975 | AV19: =SMS!AV37 -> 163924 | AW19: =+AS19+AU19 -> 1817274.2 | AX19: =+AT19+AV19 -> 1747895.5 | AY19: =SMS!AY29 -> 177750 | AZ19: =SMS!AZ37 -> 171866 | BA19: =+AQ19+AU19+AY19 -> 515475 | BB19: =+AR19+AV19+AZ19 -> 519316 | BC19: =AM19+BA19 -> 1042890.4 | BD19: =AN19+BB19 -> 871606.37 | BE19: =AW19+AY19 -> 1995024.2 | BF19: =AX19+AZ19 -> 1919761.5 | BG19: 1880445.4 | BH19: 1818588.7 | BJ19: 1922629.6 | BK19: 1903696 | BM19: 1777963.7
B20: Caster #3 | C20: Mt | D20: =791.55672823219*1000-17 -> 791539.73 | E20: =SMS!E38 -> 65435.356 | F20: =SMS!F46 -> 57758.57 | G20: =SMS!G38 -> 68601.583 | H20: =SMS!H46 -> 61438.56 | I20: =+E20+G20 -> 134036.94 | J20: =SMS!J46 -> 119197.13 | K20: =SMS!K38 -> 65963.061 | L20: =SMS!L46 -> 60718.3 | M20: =+E20+G20+K20 -> 200000 | N20: =+F20+H20+L20 -> 179915.43 | O20: =SMS!O38 -> 68601.583 | P20: =SMS!P46 -> 64584.79 | Q20: =+M20+O20 -> 268601.58 | R20: =+N20+P20 -> 244500.22 | S20: =SMS!S38 -> 68601.583 | T20: =SMS!T46 -> 58078.79 | U20: =+Q20+S20 -> 337203.17 | V20: =+R20+T20 -> 302579.01 | W20: =SMS!W38 -> 35356.201 | X20: =SMS!X46 -> 54507 | Y20: =+O20+S20+W20 -> 172559.37 | Z20: =+P20+T20+X20 -> 177170.58 | AA20: =+M20+Y20 -> 372559.37 | AB20: =+N20+Z20 -> 357086.01 | AC20: =SMS!AC38 -> 57740.566 | AD20: =SMS!AD46 -> 53997.96 | AE20: =+AA20+AC20 -> 430299.93 | AF20: =+AB20+AD20 -> 411083.97 | AG20: =SMS!AG38 -> 56118.396 | AH20: =SMS!AH46 -> 0 | AI20: =SMS!AI38 -> 486418.33 | AJ20: =SMS!AJ46 -> 411083.97 | AK20: =SMS!AK38 -> 57650.116 | AL20: =SMS!AL46 -> 58714.36 | AM20: =SMS!AM38 -> 171509.08 | AN20: =SMS!AN46 -> 112712.32 | AO20: =SMS!AO38 -> 544068.45 | AP20: =SMS!AP46 -> 469798.33 | AQ20: =SMS!AQ38 -> 57740.566 | AR20: =SMS!AR46 -> 62514.11 | AS20: =+AO20+AQ20 -> 601809.01 | AT20: =+AP20+AR20 -> 532312.44 | AU20: =SMS!AU38 -> 51930.66 | AV20: =SMS!AV46 -> 58971.81 | AW20: =+AS20+AU20 -> 653739.67 | AX20: =+AT20+AV20 -> 591284.25 | AY20: =SMS!AY38 -> 57740.566 | AZ20: =SMS!AZ46 -> 71685.7 | BA20: =+AQ20+AU20+AY20 -> 167411.79 | BB20: =+AR20+AV20+AZ20 -> 193171.62 | BC20: =AM20+BA20 -> 338920.87 | BD20: =AN20+BB20 -> 305883.94 | BE20: =AW20+AY20 -> 711480.24 | BF20: =AX20+AZ20 -> 662969.95 | BG20: 609083.07 | BH20: 618370.32 | BJ20: 606294.79 | BK20: 518629.33 | BM20: 449903.88
B21: Avg Heats Cast per Day | C21: Nos. / day | D21: =D53/D1 -> 54.152138 | E21: =+E53/E1 -> 54.508157 | F21: =+F53/F1 -> 49.6125 | G21: =+G53/G1 -> 54.369951 | H21: =+H53/H1 -> 50.886713 | I21: =+I53/I1 -> 54.437882 | J21: =+J53/J1 -> 50.284871 | K21: =+K53/K1 -> 54.508157 | L21: =+L53/L1 -> 52.547596 | ... BF21: =+BF53/BF1 -> 51.004571 | BG21: 51.463117 | BH21: 49.270546 | BI21: 50.337665 | BJ21: 48.130368 | BK21: 45.269663 | BL21: 44.780041 | BM21: 40.065753 | BN21: 41.920046 | BO21: 33.309589 | BP21: 47.014645 | BQ21: 38.663934
B22: Cold Pig & Pig Equivalent
B23: MOG | C23: Mt | D23: 12645 | E23: =0.81*1000 -> 810 | F23: 3914.4926 | G23: 810 | H23: 2383.6528 | I23: =+E23+G23 -> 1620 | J23: =+F23+H23 -> 6298.1454 | K23: =0.81*1000 -> 810 | L23: 902.97846 | M23: =+E23+G23+K23 -> 2430 | N23: =+F23+H23+L23 -> 7201.1238 | O23: 810 | P23: 0 | Q23: =+M23+O23 -> 3240 | R23: =+N23+P23 -> 7201.1238 | S23: =0.81*1000 -> 810 | T23: 144.06922 | U23: =+Q23+S23 -> 4050 | V23: =+R23+T23 -> 7345.1931 | W23: =5360-1625 -> 3735 | X23: 256.58678 | Y23: =+O23+S23+W23 -> 5355 | Z23: =+P23+T23+X23 -> 400.656 | AA23: =+M23+Y23 -> 7785 | AB23: =+N23+Z23 -> 7601.7798 | AC23: 342 | AD23: 264.68337 | AE23: =+AA23+AC23 -> 8127 | AF23: =+AB23+AD23 -> 7866.4632 | AG23: 342 | AH23: 25.041 | AI23: =+AE23+AG23 -> 8469 | AJ23: =+AF23+AH23 -> 7891.5042 | AK23: 342 | AL23: 2134.9957 | AM23: =+AC23+AG23+AK23 -> 1026 | AN23: =+AD23+AH23+AL23 -> 2424.72 | AO23: =AI23+AK23 -> 8811 | AP23: =AJ23+AL23 -> 10026.5 | AQ23: 342 | AR23: 495.31098 | AS23: =+AO23+AQ23 -> 9153 | AT23: =+AP23+AR23 -> 10521.811 | AU23: =0.342*1000 -> 342 | AV23: 324.53136 | AW23: =+AS23+AU23 -> 9495 | AX23: =+AT23+AV23 -> 10846.342 | AY23: =0.342*1000 -> 342 | AZ23: 4393.36 | BA23: =+AQ23+AU23+AY23 -> 1026 | BB23: =+AR23+AV23+AZ23 -> 5213.2023 | BC23: =AM23+BA23 -> 2052 | BD23: =AN23+BB23 -> 7637.9223 | BE23: =AW23+AY23 -> 9837 | BF23: =AX23+AZ23 -> 15239.702 | BG23: 7740 | BH23: 12917.886 | BI23: 19561.1 | BJ23: 7548.2756 | BK23: 9129.3344 | BL23: 19735.515 | BM23: 22361.072 | BN23: 20755.018 | BO23: 58220.7 | BP23: 29957.856 | BQ23: 134629.18
B24: UPIS | C24: Mt | D24: 0 | E24: 0 | F24: 194.6 | G24: 0 | H24: 230 | I24: =+E24+G24 -> 0 | J24: =+F24+H24 -> 424.6 | K24: 0 | L24: 127.47931 | M24: =+E24+G24+K24 -> 0 | N24: =+F24+H24+L24 -> 552.07931 | O24: 0 | P24: 0 | Q24: =+M24+O24 -> 0 | R24: =+N24+P24 -> 552.07931 | S24: 0 | T24: 20.339184 | U24: =+Q24+S24 -> 0 | V24: =+R24+T24 -> 572.4185 | W24: 0 | X24: 36.224016 | Y24: =+O24+S24+W24 -> 0 | Z24: =+P24+T24+X24 -> 56.5632 | AA24: =+M24+Y24 -> 0 | AB24: =+N24+Z24 -> 608.64251 | AC24: 0 | AD24: 37.367064 | AE24: =+AA24+AC24 -> 0 | AF24: =+AB24+AD24 -> 646.00958 | AG24: 0 | AH24: 3.5352 | AI24: =+AE24+AG24 -> 0 | AJ24: =+AF24+AH24 -> 649.54478 | AK24: 0 | AL24: 301.41115 | AM24: =+AC24+AG24+AK24 -> 0 | AN24: =+AD24+AH24+AL24 -> 342.31342 | AO24: =AI24+AK24 -> 0 | AP24: =AJ24+AL24 -> 950.95593 | AQ24: 0 | AR24: 70 | AS24: =+AO24+AQ24 -> 0 | AT24: =+AP24+AR24 -> 1020.9559 | AU24: 0 | AV24: 45.816192 | AW24: =+AS24+AU24 -> 0 | AX24: =+AT24+AV24 -> 1066.7721 | AY24: 0 | AZ24: 620.23906 | BA24: =+AQ24+AU24+AY24 -> 0 | BB24: =+AR24+AV24+AZ24 -> 736.05525 | BC24: =AM24+BA24 -> 0 | BD24: =AN24+BB24 -> 1078.3687 | BE24: =AW24+AY24 -> 0 | BF24: =AX24+AZ24 -> 1687.0112 | BG24: 0 | BH24: 1823.7656 | BI24: 0 | BJ24: 1026.6221 | BK24: 2541.6495 | BL24: 0 | BM24: 2774.7649 | BN24: 392 | BO24: 3852.3 | BP24: 1419.0563 | BQ24: 8272.9783
B25: Equiv. Pig Iron @ 65% of HM sent to Sand Pit | C25: Mt | D25: =2500*0.65 -> 1625 | E25: 0 | F25: 552.63425 | G25: 0 | H25: 336.51569 | I25: =+E25+G25 -> 0 | J25: =+F25+H25 -> 889.14994 | K25: 0 | L25: 0 | M25: =+E25+G25+K25 -> 0 | N25: =+F25+H25+L25 -> 889.14994 | O25: 0 | P25: 0 | Q25: =+M25+O25 -> 0 | R25: =+N25+P25 -> 889.14994 | S25: 0 | T25: 0 | U25: =+Q25+S25 -> 0 | V25: =+R25+T25 -> 889.14994 | W25: =2500*0.65 -> 1625 | X25: 0 | Y25: =+O25+S25+W25 -> 1625 | Z25: =+P25+T25+X25 -> 0 | AA25: =+M25+Y25 -> 1625 | AB25: =+N25+Z25 -> 889.14994 | AC25: 0 | AD25: 0 | AE25: =+AA25+AC25 -> 1625 | AF25: =+AB25+AD25 -> 889.14994 | AG25: 0 | AH25: 1512.9 | AI25: =+AE25+AG25 -> 1625 | AJ25: =+AF25+AH25 -> 2402.0499 | AK25: 0 | AL25: 2513.5 | AM25: =+AC25+AG25+AK25 -> 0 | AN25: =+AD25+AH25+AL25 -> 4026.4 | AO25: =AI25+AK25 -> 1625 | AP25: =AJ25+AL25 -> 4915.5499 | AQ25: 0 | AR25: 0 | AS25: =+AO25+AQ25 -> 1625 | AT25: =+AP25+AR25 -> 4915.5499 | AU25: 0 | AV25: 630 | AW25: =+AS25+AU25 -> 1625 | AX25: =+AT25+AV25 -> 5545.5499 | AY25: 0 | AZ25: 480 | BA25: =+AQ25+AU25+AY25 -> 0 | BB25: =+AR25+AV25+AZ25 -> 1110 | BC25: =AM25+BA25 -> 0 | BD25: =AN25+BB25 -> 5136.4 | BE25: =AW25+AY25 -> 1625 | BF25: =AX25+AZ25 -> 6025.5499 | BG25: 1625 | BH25: 11114.8 | BI25: 2000 | BJ25: 5022 | BK25: 4664.8 | BL25: 14800 | BM25: 9214.4 | BN25: 0 | BO25: 0 | BP25: 0 | BQ25: 26220.8
B26: TOTAL EQUIVALENT PIG IRON | C26: Mt | D26: =SUM(D23:D25) -> 14270 | E26: =SUM(E23:E25) -> 810 | F26: =SUM(F23:F25) -> 4661.7268 | G26: =SUM(G23:G25) -> 810 | H26: =SUM(H23:H25) -> 2950.1685 | I26: =SUM(I23:I25) -> 1620 | J26: =SUM(J23:J25) -> 7611.8953 | K26: =SUM(K23:K25) -> 810 | ... BF26: =SUM(BF23:BF25) -> 22952.263 | BG26: 9365 | BH26: 25856.451 | BI26: 21561.1 | BJ26: 13596.898 | BK26: 16335.784 | BL26: 34535.515 | BM26: 34350.237 | BN26: 21147.018 | BO26: 62073 | BP26: 31376.912 | BQ26: 169122.96
B27: Net PCI Production | C27: Mt | D27: 3541.35 | E27: 273.996 | F27: 374.5 | G27: 279.98 | H27: 603.862 | I27: =+E27+G27 -> 553.976 | J27: =+F27+H27 -> 978.362 | K27: 273.996 | L27: 0 | M27: =+E27+G27+K27 -> 827.972 | N27: =+F27+H27+L27 -> 978.362 | O27: 276.24 | P27: 0 | Q27: =+M27+O27 -> 1104.212 | R27: =+N27+P27 -> 978.362 | S27: 276.24 | T27: 0 | U27: =+Q27+S27 -> 1380.452 | V27: =+R27+T27 -> 978.362 | W27: 498.97 | X27: 0 | Y27: =+O27+S27+W27 -> 1051.45 | Z27: =+P27+T27+X27 -> 0 | AA27: =+M27+Y27 -> 1879.422 | AB27: =+N27+Z27 -> 978.362 | AC27: 226.1 | AD27: 0 | AE27: =+AA27+AC27 -> 2105.522 | AF27: =+AB27+AD27 -> 978.362 | AG27: 220.02 | AH27: 1174.369 | AI27: =+AE27+AG27 -> 2325.542 | AJ27: =+AF27+AH27 -> 2152.731 | AK27: 226.1 | AL27: 1177.785 | AM27: =+AC27+AG27+AK27 -> 672.22 | AN27: =+AD27+AH27+AL27 -> 2352.154 | AO27: =AI27+AK27 -> 2551.642 | AP27: =AJ27+AL27 -> 3330.516 | AQ27: 226.1 | AR27: 766.241 | AS27: =+AO27+AQ27 -> 2777.742 | AT27: =+AP27+AR27 -> 4096.757 | AU27: 207.1 | AV27: 658.147 | AW27: =+AS27+AU27 -> 2984.842 | AX27: =+AT27+AV27 -> 4754.904 | AY27: 226.1 | AZ27: 554.33 | BA27: =+AQ27+AU27+AY27 -> 659.3 | BB27: =+AR27+AV27+AZ27 -> 1978.718 | BC27: =AM27+BA27 -> 1331.52 | BD27: =AN27+BB27 -> 4330.872 | BE27: =AW27+AY27 -> 3210.942 | BF27: =AX27+AZ27 -> 5309.234 | BG27: 2831.5 | BH27: 7991.486 | BI27: 2377.872 | BJ27: 6141.395 | BK27: 5885.734 | BL27: 2398.56 | BM27: 13377.679 | BN27: 11568.99 | BO27: 41093.9 | BP27: 0 | BQ27: 44255.19
B28: Net Granulated Slag Production | C28: Mt | D28: 1081234 | E28: 92363.04 | F28: 70955.831 | G28: 95295.2 | H28: 75418.546 | I28: =+E28+G28 -> 187658.24 | J28: =+F28+H28 -> 146374.38 | K28: 92363.04 | L28: 72846.055 | M28: =+E28+G28+K28 -> 280021.28 | N28: =+F28+H28+L28 -> 219220.43 | O28: 93462.6 | P28: 75682.97 | Q28: =+M28+O28 -> 373483.88 | R28: =+N28+P28 -> 294903.4 | S28: 93462.6 | T28: 80832.023 | U28: =+Q28+S28 -> 466946.48 | V28: =+R28+T28 -> 375735.43 | W28: 51312.8 | X28: 79584.049 | Y28: =+O28+S28+W28 -> 238238 | Z28: =+P28+T28+X28 -> 236099.04 | AA28: =+M28+Y28 -> 518259.28 | AB28: =+N28+Z28 -> 455319.47 | AC28: 93198.103 | AD28: 81673.877 | AE28: =+AA28+AC28 -> 611457.38 | AF28: =+AB28+AD28 -> 536993.35 | AG28: 90215.764 | AH28: 2328.2551 | AI28: =+AE28+AG28 -> 701673.15 | AJ28: =+AF28+AH28 -> 539321.61 | AK28: 93198.103 | AL28: 92452.296 | AM28: =+AC28+AG28+AK28 -> 276611.97 | AN28: =+AD28+AH28+AL28 -> 176454.43 | AO28: =AI28+AK28 -> 794871.25 | AP28: =AJ28+AL28 -> 631773.9 | AQ28: 93198.103 | AR28: 94062.296 | AS28: =+AO28+AQ28 -> 888069.35 | AT28: =+AP28+AR28 -> 725836.2 | AU28: 83878.293 | AV28: 80273.363 | AW28: =+AS28+AU28 -> 971947.65 | AX28: =+AT28+AV28 -> 806109.56 | AY28: 93198.103 | AZ28: 90266.534 | BA28: =+AQ28+AU28+AY28 -> 270274.5 | BB28: =+AR28+AV28+AZ28 -> 264602.19 | BC28: =AM28+BA28 -> 546886.47 | BD28: =AN28+BB28 -> 441056.62 | BE28: =AW28+AY28 -> 1065145.7 | BF28: =AX28+AZ28 -> 896376.09 | BG28: 987899.89 | BH28: 899258.76 | BI28: 1063047 | BJ28: 1075244.6 | BK28: 1065593 | BL28: 157305.12 | BM28: 920129.3 | BN28: 882599.97 | BO28: 776699 | BP28: 854658 | BQ28: 809638.21
B29: Saleable Steel Production (Mill Wise)
B30: WR Mill | C30: Mt | D30: 500000 | E30: 42500 | F30: =+WRM!F154 -> 36744.18 | G30: 44000 | H30: =+WRM!H154 -> 39374.35 | I30: =+E30+G30 -> 86500 | J30: =+F30+H30 -> 76118.53 | K30: 42500 | L30: =+WRM!L154 -> 38297.5 | M30: =+E30+G30+K30 -> 129000 | N30: =+F30+H30+L30 -> 114416.03 | O30: 44000 | P30: =+WRM!P154 -> 47070.05 | Q30: =+M30+O30 -> 173000 | R30: =+N30+P30 -> 161486.08 | S30: 44000 | T30: =+WRM!T154 -> 38734.75 | U30: =+Q30+S30 -> 217000 | V30: =+R30+T30 -> 200220.83 | W30: 25000 | X30: =+WRM!X154 -> 41006.15 | Y30: =+O30+S30+W30 -> 113000 | Z30: =+P30+T30+X30 -> 126810.95 | AA30: =+M30+Y30 -> 242000 | AB30: =+N30+Z30 -> 241226.98 | AC30: 45500 | AD30: =+WRM!AD154 -> 42384.76 | AE30: =+AA30+AC30 -> 287500 | AF30: =+AB30+AD30 -> 283611.74 | AG30: 44000 | AH30: =+WRM!AH154 -> 19981.35 | AI30: =+AE30+AG30 -> 331500 | AJ30: =+AF30+AH30 -> 303593.09 | AK30: 45500 | AL30: =+WRM!AL154 -> 39200.1 | AM30: =+AC30+AG30+AK30 -> 135000 | AN30: =+AD30+AH30+AL30 -> 101566.21 | AO30: =AI30+AK30 -> 377000 | AP30: =AJ30+AL30 -> 342793.19 | AQ30: =45.5*1000 -> 45500 | AR30: =+WRM!AR154 -> 40296.85 | AS30: =+AO30+AQ30 -> 422500 | AT30: =+AP30+AR30 -> 383090.04 | AU30: =40.5*1000 -> 40500 | AV30: =+WRM!AV154 -> 34335.35 | AW30: =+AS30+AU30 -> 463000 | AX30: =+AT30+AV30 -> 417425.39 | AY30: =45.5*1000 -> 45500 | AZ30: =+WRM!AZ154 -> 43072.55 | BA30: =+AQ30+AU30+AY30 -> 131500 | BB30: =+AR30+AV30+AZ30 -> 117704.75 | BC30: =AM30+BA30 -> 266500 | BD30: =AN30+BB30 -> 219270.96 | BE30: =AW30+AY30 -> 508500 | BF30: =AX30+AZ30 -> 460497.94 | BG30: 500000 | BH30: 459030.64 | BI30: 500000 | BJ30: 478528.39 | BK30: 466114.65 | BL30: 500000 | BM30: 465343.77 | BN30: 435965.96 | BO30: 356518.66 | BP30: 500000 | BQ30: 412025.22
B31: Bar Mill | C31: Mt | D31: 900000 | E31: 76000 | F31: =+BM!F56 -> 66895.455 | G31: 79000 | H31: =+BM!H56 -> 76175.635 | I31: =+E31+G31 -> 155000 | J31: =+F31+H31 -> 143071.09 | K31: 76000 | L31: =+BM!L56 -> 73644.015 | M31: =+E31+G31+K31 -> 231000 | N31: =+F31+H31+L31 -> 216715.11 | O31: 79000 | P31: =+BM!P56 -> 88056.49 | Q31: =+M31+O31 -> 310000 | R31: =+N31+P31 -> 304771.6 | S31: 79000 | T31: =+BM!T56 -> 75853.695 | U31: =+Q31+S31 -> 389000 | V31: =+R31+T31 -> 380625.29 | W31: =47.5*1000 -> 47500 | X31: =+BM!X56 -> 76319.035 | Y31: =+O31+S31+W31 -> 205500 | Z31: =+P31+T31+X31 -> 240229.22 | AA31: =+M31+Y31 -> 436500 | AB31: =+N31+Z31 -> 456944.33 | AC31: 80000 | AD31: =+BM!AD56 -> 66747.8 | AE31: =+AA31+AC31 -> 516500 | AF31: =+AB31+AD31 -> 523692.13 | AG31: 77500 | AH31: =+BM!AH56 -> 3169.72 | AI31: =+AE31+AG31 -> 594000 | AJ31: =+AF31+AH31 -> 526861.85 | AK31: 80000 | AL31: =+BM!AL56 -> 70630.63 | AM31: =+AC31+AG31+AK31 -> 237500 | AN31: =+AD31+AH31+AL31 -> 140548.15 | AO31: =AI31+AK31 -> 674000 | AP31: =AJ31+AL31 -> 597492.48 | AQ31: 80000 | AR31: =+BM!AR56 -> 70085.115 | AS31: =+AO31+AQ31 -> 754000 | AT31: =+AP31+AR31 -> 667577.59 | AU31: =72.5*1000 -> 72500 | AV31: =+BM!AV56 -> 65990 | AW31: =+AS31+AU31 -> 826500 | AX31: =+AT31+AV31 -> 733567.59 | AY31: 80000 | AZ31: =+BM!AZ56 -> 78010.61 | BA31: =+AQ31+AU31+AY31 -> 232500 | BB31: =+AR31+AV31+AZ31 -> 214085.73 | BC31: =AM31+BA31 -> 470000 | BD31: =AN31+BB31 -> 354633.88 | BE31: =AW31+AY31 -> 906500 | BF31: =AX31+AZ31 -> 811578.2 | BG31: 870000 | BH31: 750867.85 | BI31: 850000 | BJ31: 795322.27 | BK31: 775906.63 | BL31: 750000 | BM31: 649840.96 | BN31: 674875.14 | BO31: 440547.27 | BP31: 800000 | BQ31: 632220.18
B32: US Mill | C32: Mt | D32: 750000 | E32: 62000 | F32: =+USM!G108 -> 49543.777 | G32: 65000 | H32: =+USM!I108 -> 57219.144 | I32: =+E32+G32 -> 127000 | J32: =+F32+H32 -> 106762.92 | K32: 62500 | L32: =+USM!M108 -> 58674.633 | M32: =+E32+G32+K32 -> 189500 | N32: =+F32+H32+L32 -> 165437.55 | O32: 65000 | P32: =+USM!Q108 -> 57327.387 | Q32: =+M32+O32 -> 254500 | R32: =+N32+P32 -> 222764.94 | S32: 65000 | T32: =+USM!U108 -> 44406.293 | U32: =+Q32+S32 -> 319500 | V32: =+R32+T32 -> 267171.23 | W32: 33500 | X32: =+USM!Y108 -> 50010.386 | Y32: =+O32+S32+W32 -> 163500 | Z32: =+P32+T32+X32 -> 151744.07 | AA32: =+M32+Y32 -> 353000 | AB32: =+N32+Z32 -> 317181.62 | AC32: 54000 | AD32: =+USM!AE108 -> 44900.301 | AE32: =+AA32+AC32 -> 407000 | AF32: =+AB32+AD32 -> 362081.92 | AG32: 52000 | AH32: =+USM!AI108 -> 8584.984 | AI32: =+AE32+AG32 -> 459000 | AJ32: =+AF32+AH32 -> 370666.9 | AK32: 54000 | AL32: =+USM!AM108 -> 40066.768 | AM32: =+AC32+AG32+AK32 -> 160000 | AN32: =+AD32+AH32+AL32 -> 93552.053 | AO32: =AI32+AK32 -> 513000 | AP32: =AJ32+AL32 -> 410733.67 | AQ32: 54000 | AR32: =+USM!AS108 -> 51039.179 | AS32: =+AO32+AQ32 -> 567000 | AT32: =+AP32+AR32 -> 461772.85 | AU32: 48000 | AV32: =+USM!AW108 -> 51009.48 | AW32: =+AS32+AU32 -> 615000 | AX32: =+AT32+AV32 -> 512782.33 | AY32: 60000 | AZ32: =+USM!BA108 -> 62071.89 | BA32: =+AQ32+AU32+AY32 -> 162000 | BB32: =+AR32+AV32+AZ32 -> 164120.55 | BC32: =AM32+BA32 -> 322000 | BD32: =AN32+BB32 -> 257672.6 | BE32: =AW32+AY32 -> 675000 | BF32: =AX32+AZ32 -> 574854.22 | BG32: 560000 | BH32: 499887.23 | BI32: 525000 | BJ32: 459141.95 | BK32: 361987.56 | BL32: 450000 | BM32: 213226.16 | BN32: 220000 | BO32: 88943.894 | BP32: 535000 | BQ32: 171634.81
B33: Finished Steel | C33: Mt | D33: =SUM(D30:D32) -> 2150000 | E33: =SUM(E30:E32) -> 180500 | F33: =SUM(F30:F32) -> 153183.41 | G33: =SUM(G30:G32) -> 188000 | H33: =SUM(H30:H32) -> 172769.13 | I33: =SUM(I30:I32) -> 368500 | J33: =SUM(J30:J32) -> 325952.54 | K33: =SUM(K30:K32) -> 181000 | ... BF33: =SUM(BF30:BF32) -> 1846930.4 | BG33: 1930000 | BH33: 1709785.7 | BI33: 1875000 | BJ33: 1732992.6 | BK33: 1604008.8 | BL33: 1700000 | BM33: 1328410.9 | BN33: 1330841.1 | BO33: 886009.82 | BP33: =SUM(BP30:BP32) -> 1835000 | BQ33: =SUM(BQ30:BQ32) -> 1215880.2
B34: 150x150 mm | C34: Mt | D34: =524.79833712911*1000+202 -> 525000.34 | E34: =48.4998153686034*1000 -> 48499.815 | F34: 45616.588 | G34: 48499.577 | H34: 52556 | I34: =+E34+G34 -> 96999.392 | J34: =+F34+H34 -> 98172.588 | K34: =48.0001108831152*1000 -> 48000.111 | L34: 56218 | M34: =+E34+G34+K34 -> 144999.5 | N34: =+F34+H34+L34 -> 154390.59 | O34: =43.5001413553209*1000 -> 43500.141 | P34: 50303 | Q34: =+M34+O34 -> 188499.64 | R34: =+N34+P34 -> 204693.59 | S34: =43.5001413553209*1000 -> 43500.141 | T34: 51235.42 | U34: =+Q34+S34 -> 231999.79 | V34: =+R34+T34 -> 255929.01 | W34: =15.3000147648532*1000 -> 15300.015 | X34: 54076 | Y34: =+O34+S34+W34 -> 102300.3 | Z34: =+P34+T34+X34 -> 155614.42 | AA34: =+M34+Y34 -> 247299.8 | AB34: =+N34+Z34 -> 310005.01 | AC34: 47340.612 | AD34: 25418 | AE34: =+AA34+AC34 -> 294640.41 | AF34: =+AB34+AD34 -> 335423.01 | AG34: =45.6807858376511*1000 -> 45680.786 | AH34: 7935 | AI34: =+AE34+AG34 -> 340321.2 | AJ34: =+AF34+AH34 -> 343358.01 | AK34: =45.7100622625216*1000 -> 45710.062 | AL34: 64493 | AM34: =+AC34+AG34+AK34 -> 138731.46 | AN34: =+AD34+AH34+AL34 -> 97846 | AO34: =AI34+AK34 -> 386031.26 | AP34: =AJ34+AL34 -> 407851.01 | AQ34: =47.3396122625216*1000 -> 47339.612 | AR34: 63074.18 | AS34: =+AO34+AQ34 -> 433370.87 | AT34: =+AP34+AR34 -> 470925.19 | AU34: =42.6579663212435*1000 -> 42657.966 | AV34: 57481.27 | AW34: =+AS34+AU34 -> 476028.84 | AX34: =+AT34+AV34 -> 528406.46 | AY34: =45.4526122625216*1000 -> 45452.612 | AZ34: 57620 | BA34: =+AQ34+AU34+AY34 -> 135450.19 | BB34: =+AR34+AV34+AZ34 -> 178175.45 | BC34: =AM34+BA34 -> 274181.65 | BD34: =AN34+BB34 -> 276021.45 | BE34: =AW34+AY34 -> 521481.45 | BF34: =AX34+AZ34 -> 586026.46 | BG34: 461999.56 | BH34: 558374.45 | BI34: 592000 | BJ34: 574823.37 | BK34: 595119.91 | BL34: 516406.77 | BM34: 627684.57 | BN34: 533055.82 | BO34: 608495.73 | BP34: 304999.74 | BQ34: 629438.96
B35: 200x280 mm | C35: Mt | D35: 0 | E35: 0 | F35: 0 | G35: 0 | H35: 3000 | I35: =+E35+G35 -> 0 | J35: =+F35+H35 -> 3000 | K35: 0 | L35: 1066 | M35: =+E35+G35+K35 -> 0 | N35: =+F35+H35+L35 -> 4066 | O35: 0 | P35: 463 | Q35: =+M35+O35 -> 0 | R35: =+N35+P35 -> 4529 | S35: 0 | T35: 8811.77 | U35: =+Q35+S35 -> 0 | V35: =+R35+T35 -> 13340.77 | W35: 0 | X35: 1414 | Y35: =+O35+S35+W35 -> 0 | Z35: =+P35+T35+X35 -> 10688.77 | AA35: =+M35+Y35 -> 0 | AB35: =+N35+Z35 -> 14754.77 | AC35: 0.48160502 | AD35: 7379.5262 | AE35: =+AA35+AC35 -> 0.48160502 | AF35: =+AB35+AD35 -> 22134.296 | AG35: =4.00012973564992*1000 -> 4000.1297 | AH35: 637 | AI35: =+AE35+AG35 -> 4000.6113 | AJ35: =+AF35+AH35 -> 22771.296 | AK35: 0 | AL35: 12910 | AM35: =+AC35+AG35+AK35 -> 4000.6113 | AN35: =+AD35+AH35+AL35 -> 20926.526 | AO35: =AI35+AK35 -> 4000.6113 | AP35: =AJ35+AL35 -> 35681.296 | AQ35: 0 | AR35: 10907.843 | AS35: =+AO35+AQ35 -> 4000.6113 | AT35: =+AP35+AR35 -> 46589.139 | AU35: =4.00002977049834*1000 -> 4000.0298 | AV35: 0 | AW35: =+AS35+AU35 -> 8000.6411 | AX35: =+AT35+AV35 -> 46589.139 | AY35: 0 | AZ35: 0 | BA35: =+AQ35+AU35+AY35 -> 4000.0298 | BB35: =+AR35+AV35+AZ35 -> 10907.843 | BC35: =AM35+BA35 -> 8000.6411 | BD35: =AN35+BB35 -> 31834.369 | BE35: =AW35+AY35 -> 8000.6411 | BF35: =AX35+AZ35 -> 46589.139 | BG35: 17999.996 | BH35: 63663.849 | BI35: 57999.916 | BJ35: 101828.14 | BK35: 116079.05 | BL35: 153592.34 | BM35: 204330.35 | BN35: 371378.01 | BO35: 329378.8 | BP35: 267000 | BQ35: 248401
B36: Saleable Semis | C36: Mt | D36: =SUM(D34:D35) -> 525000.34 | E36: =SUM(E34:E35) -> 48499.815 | F36: =SUM(F34:F35) -> 45616.588 | G36: =SUM(G34:G35) -> 48499.577 | H36: =SUM(H34:H35) -> 55556 | I36: =SUM(I34:I35) -> 96999.392 | J36: =SUM(J34:J35) -> 101172.59 | K36: =SUM(K34:K35) -> 48000.111 | ... BF36: =SUM(BF34:BF35) -> 632615.6 | BG36: 479999.56 | BH36: 622038.3 | BI36: 649999.92 | BJ36: 676651.51 | BK36: 711198.96 | BL36: 669999.11 | BM36: 832014.92 | BN36: 904433.83 | BO36: 937874.53 | BP36: =SUM(BP34:BP35) -> 571999.74 | BQ36: =SUM(BQ34:BQ35) -> 877839.96
B37: TOTAL SALEABLE STEEL | C37: Mt | D37: =+D33+D36 -> 2675000.3 | E37: =+E33+E36 -> 228999.82 | F37: =+F33+F36 -> 198800 | G37: =+G33+G36 -> 236499.58 | H37: =+H33+H36 -> 228325.13 | I37: =+I33+I36 -> 465499.39 | J37: =+J33+J36 -> 427125.13 | K37: =+K33+K36 -> 229000.11 | ... BF37: =+BF33+BF36 -> 2479546 | BG37: 2409999.6 | BH37: 2331824 | BI37: 2524999.9 | BJ37: 2409644.1 | BK37: 2315207.8 | BL37: 2369999.1 | BM37: 2160425.8 | BN37: 2235274.9 | BO37: 1823884.4 | BP37: =+BP33+BP36 -> 2406999.7 | BQ37: =+BQ33+BQ36 -> 2093720.2
B38: SAL STEEL PRODN (CATEGORY WISE)
B39: Wire Rod Plain Coils | C39: Mt | D39: =+D30 -> 500000 | E39: =+E30 -> 42500 | F39: =+WRM!F200 -> 36744.18 | G39: =+G30 -> 44000 | H39: =+WRM!H200 -> 39374.35 | I39: =+E39+G39 -> 86500 | J39: =+F39+H39 -> 76118.53 | K39: =+K30 -> 42500 | L39: =+WRM!L200 -> 28933.7 | M39: =+E39+G39+K39 -> 129000 | N39: =+F39+H39+L39 -> 105052.23 | O39: =+O30 -> 44000 | P39: =+WRM!P200 -> 35819.65 | Q39: =+M39+O39 -> 173000 | R39: =+N39+P39 -> 140871.88 | S39: =+S30 -> 44000 | T39: =+WRM!T200 -> 38734.75 | U39: =+Q39+S39 -> 217000 | V39: =+R39+T39 -> 179606.63 | W39: =+W30 -> 25000 | X39: =+WRM!X200 -> 41006.15 | Y39: =+O39+S39+W39 -> 113000 | Z39: =+P39+T39+X39 -> 115560.55 | AA39: =+M39+Y39 -> 242000 | AB39: =+N39+Z39 -> 220612.78 | AC39: =+AC30 -> 45500 | AD39: =+WRM!AD200 -> 42384.76 | AE39: =+AA39+AC39 -> 287500 | AF39: =+AB39+AD39 -> 262997.54 | AG39: =+AG30 -> 44000 | AH39: =+WRM!AH200 -> 19981.35 | AI39: =+AE39+AG39 -> 331500 | AJ39: =+AF39+AH39 -> 282978.89 | AK39: =+AK30 -> 45500 | AL39: =+WRM!AL200 -> 39200.1 | AM39: =+AC39+AG39+AK39 -> 135000 | AN39: =+AD39+AH39+AL39 -> 101566.21 | AO39: =AI39+AK39 -> 377000 | AP39: =AJ39+AL39 -> 322178.99 | AQ39: =+AQ30 -> 45500 | AR39: =+WRM!AR200 -> 40296.85 | AS39: =+AO39+AQ39 -> 422500 | AT39: =+AP39+AR39 -> 362475.84 | AU39: =+AU30 -> 40500 | AV39: =+WRM!AV200 -> 34335.35 | AW39: =+AS39+AU39 -> 463000 | AX39: =+AT39+AV39 -> 396811.19 | AY39: =+AY30 -> 45500 | AZ39: =+WRM!AZ200 -> 43072.55 | BA39: =+AQ39+AU39+AY39 -> 131500 | BB39: =+AR39+AV39+AZ39 -> 117704.75 | BC39: =AM39+BA39 -> 266500 | BD39: =AN39+BB39 -> 219270.96 | BE39: =AW39+AY39 -> 508500 | BF39: =AX39+AZ39 -> 439883.74 | BG39: 500000 | BH39: 459030.64 | BI39: 500000 | BJ39: 471802.34 | BK39: 410762.6 | BL39: =+BL30 -> 500000 | BM39: 456374.84 | BN39: =+BN30 -> 435965.96 | BO39: 333534.61 | BP39: 500000 | BQ39: 270654.57
B40: TMT Coils | C40: Mt | F40: =+WRM!F201 -> 0 | H40: =+WRM!H201 -> 0 | J40: =+F40+H40 -> 0 | L40: =+WRM!L201 -> 9363.8 | N40: =+F40+H40+L40 -> 9363.8 | P40: =+WRM!P201 -> 11250.4 | R40: =+N40+P40 -> 20614.2 | T40: =+WRM!T201 -> 0 | V40: =+R40+T40 -> 20614.2 | X40: =+WRM!X201 -> 0 | Z40: =+P40+T40+X40 -> 11250.4 | AB40: =+N40+Z40 -> 20614.2 | AD40: =+WRM!AD201 -> 0 | AF40: =+AB40+AD40 -> 20614.2 | AH40: =+WRM!AH201 -> 0 | AJ40: =+AF40+AH40 -> 20614.2 | AL40: =+WRM!AL201 -> 0 | AN40: =+AD40+AH40+AL40 -> 0 | AP40: =AJ40+AL40 -> 20614.2 | AR40: =+WRM!AR201 -> 0 | AT40: =+AP40+AR40 -> 20614.2 | AV40: =+WRM!AV201 -> 0 | AX40: =+AT40+AV40 -> 20614.2 | AZ40: =+WRM!AZ201 -> 0 | BB40: =+AR40+AV40+AZ40 -> 0 | BD40: =AN40+BB40 -> 0 | BF40: =AX40+AZ40 -> 20614.2 | BH40: 0 | BJ40: 6726.05 | BK40: 55352.05 | BM40: 8968.93 | BO40: 22983.766 | BQ40: 141370.65
B41: TMT Bars | C41: Mt | D41: =+D31 -> 900000 | E41: =+E31 -> 76000 | F41: =+F31 -> 66895.455 | G41: =+G31 -> 79000 | H41: =+H31 -> 76175.635 | I41: =+E41+G41 -> 155000 | J41: =+F41+H41 -> 143071.09 | K41: =+K31 -> 76000 | L41: =+L31 -> 73644.015 | M41: =+E41+G41+K41 -> 231000 | N41: =+F41+H41+L41 -> 216715.11 | O41: =+O31 -> 79000 | P41: =+P31 -> 88056.49 | Q41: =+M41+O41 -> 310000 | R41: =+N41+P41 -> 304771.6 | S41: =+S31 -> 79000 | T41: =+T31 -> 75853.695 | U41: =+Q41+S41 -> 389000 | V41: =+R41+T41 -> 380625.29 | W41: =+W31 -> 47500 | X41: =+X31 -> 76319.035 | Y41: =+O41+S41+W41 -> 205500 | Z41: =+P41+T41+X41 -> 240229.22 | AA41: =+M41+Y41 -> 436500 | AB41: =+N41+Z41 -> 456944.33 | AC41: =+AC31 -> 80000 | AD41: =+AD31 -> 66747.8 | AE41: =+AA41+AC41 -> 516500 | AF41: =+AB41+AD41 -> 523692.13 | AG41: =+AG31 -> 77500 | AH41: =+AH31 -> 3169.72 | AI41: =+AE41+AG41 -> 594000 | AJ41: =+AF41+AH41 -> 526861.85 | AK41: =+AK31 -> 80000 | AL41: =+AL31 -> 70630.63 | AM41: =+AC41+AG41+AK41 -> 237500 | AN41: =+AD41+AH41+AL41 -> 140548.15 | AO41: =AI41+AK41 -> 674000 | AP41: =AJ41+AL41 -> 597492.48 | AQ41: =+AQ31 -> 80000 | AR41: =+AR31 -> 70085.115 | AS41: =+AO41+AQ41 -> 754000 | AT41: =+AP41+AR41 -> 667577.59 | AU41: =+AU31 -> 72500 | AV41: =+AV31 -> 65990 | AW41: =+AS41+AU41 -> 826500 | AX41: =+AT41+AV41 -> 733567.59 | AY41: =+AY31 -> 80000 | AZ41: =+AZ31 -> 78010.61 | BA41: =+AQ41+AU41+AY41 -> 232500 | BB41: =+AR41+AV41+AZ41 -> 214085.73 | BC41: =AM41+BA41 -> 470000 | BD41: =AN41+BB41 -> 354633.88 | BE41: =AW41+AY41 -> 906500 | BF41: =AX41+AZ41 -> 811578.2 | BG41: 870000 | BH41: 750867.85 | BI41: 850000 | BJ41: 795322.27 | BK41: 775906.63 | BL41: 750000 | BM41: 649840.96 | BN41: =+BN31 -> 674875.14 | BO41: 440547.14 | BP41: 800000 | BQ41: 632220.18
B42: NPB | C42: Mt | D42: =+D32 -> 750000 | E42: =+E32 -> 62000 | F42: =+USM!G171 -> 36340.903 | G42: =+G32 -> 65000 | H42: =+USM!I171 -> 44993.634 | I42: =+G42+E42 -> 127000 | J42: =+F42+H42 -> 81334.537 | K42: =+K32 -> 62500 | L42: =+USM!M171 -> 41676.831 | M42: =+K42+G42+E42 -> 189500 | N42: =+F42+H42+L42 -> 123011.37 | O42: =+O32 -> 65000 | P42: =+USM!Q171 -> 39505.728 | Q42: =+M42+O42 -> 254500 | R42: =+N42+P42 -> 162517.1 | S42: =+S32 -> 65000 | T42: =+USM!U171 -> 30061.678 | U42: =+Q42+S42 -> 319500 | V42: =+R42+T42 -> 192578.77 | W42: =+W32 -> 33500 | X42: =+USM!Y171 -> 32261.594 | Y42: =+W42+S42+O42 -> 163500 | Z42: =+P42+T42+X42 -> 101829 | AA42: =+M42+Y42 -> 353000 | AB42: =+N42+Z42 -> 224840.37 | AC42: =+AC32 -> 54000 | AD42: =+USM!AE171 -> 34793.765 | AE42: =+AC42+AA42 -> 407000 | AF42: =+AB42+AD42 -> 259634.13 | AG42: =+AG32 -> 52000 | AH42: =+USM!AI171 -> 2029.933 | AI42: =+AG42+AE42 -> 459000 | AJ42: =+AF42+AH42 -> 261664.07 | AK42: =+AK32 -> 54000 | AL42: =+USM!AM171 -> 29630.324 | AM42: =+AK42+AG42+AC42 -> 160000 | AN42: =+AD42+AH42+AL42 -> 66454.022 | AO42: =AI42+AK42 -> 513000 | AP42: =AJ42+AL42 -> 291294.39 | AQ42: =+AQ32 -> 54000 | AR42: =+USM!AS171 -> 38310.493 | AS42: =+AQ42+AO42 -> 567000 | AT42: =+AP42+AR42 -> 329604.88 | AU42: =+AU32 -> 48000 | AV42: =+USM!AW171 -> 36772.828 | AW42: =+AU42+AS42 -> 615000 | AX42: =+AT42+AV42 -> 366377.71 | AY42: =+AY32 -> 60000 | AZ42: =+USM!BA171 -> 48620.817 | BA42: =+AY42+AU42+AQ42 -> 162000 | BB42: =+AR42+AV42+AZ42 -> 123704.14 | BC42: =AM42+BA42 -> 322000 | BD42: =AN42+BB42 -> 190158.16 | BE42: =AW42+AY42 -> 675000 | BF42: =AX42+AZ42 -> 414998.53 | BG42: 560000 | BH42: 369513.93 | BI42: 525000 | BJ42: 322948.42 | BK42: 273627.65 | BL42: =+BL32 -> 450000 | BM42: 168119.5 | BN42: =+BN32 -> 220000 | BO42: 78790 | BP42: 535000 | BQ42: =+BQ32 -> 171634.81
B43: WPB | C43: Mt | F43: =+USM!G172 -> 8108.238 | H43: =+USM!I172 -> 5159.029 | I43: =+E43+G43 -> 0 | J43: =+F43+H43 -> 13267.267 | L43: =+USM!M172 -> 5963.765 | N43: =+F43+H43+L43 -> 19231.032 | P43: =+USM!Q172 -> 6848.383 | Q43: =+M43+O43 -> 0 | R43: =+N43+P43 -> 26079.415 | T43: =+USM!U172 -> 1438.253 | U43: =+Q43+S43 -> 0 | V43: =+R43+T43 -> 27517.668 | X43: =+USM!Y172 -> 5720.883 | Z43: =+P43+T43+X43 -> 14007.519 | AB43: =+N43+Z43 -> 33238.551 | AD43: =+USM!AE172 -> 2513.328 | AE43: =+AA43+AC43 -> 0 | AF43: =+AB43+AD43 -> 35751.879 | AH43: =+USM!AI172 -> 0 | AI43: =+AE43+AG43 -> 0 | AJ43: =+AF43+AH43 -> 35751.879 | AL43: =+USM!AM172 -> 4923.02 | AN43: =+AD43+AH43+AL43 -> 7436.348 | AO43: =+AK43+AM43 -> 0 | AP43: =AJ43+AL43 -> 40674.899 | AR43: =+USM!AS172 -> 5654.599 | AS43: =+AO43+AQ43 -> 0 | AT43: =+AP43+AR43 -> 46329.498 | AV43: =+USM!AW172 -> 7646.882 | AW43: =+AS43+AU43 -> 0 | AX43: =+AT43+AV43 -> 53976.38 | AZ43: =+USM!BA172 -> 7746.718 | BB43: =+AR43+AV43+AZ43 -> 21048.199 | BD43: =AN43+BB43 -> 28484.547 | BE43: =+AY43+BA43 -> 0 | BF43: =AX43+AZ43 -> 61723.098 | BG43: 0 | BH43: 47628.758 | BI43: 0 | BJ43: 47288.061 | BK43: 21791.11
B44: Channels | C44: Mt | F44: =+USM!G173 -> 5094.636 | H44: =+USM!I173 -> 7066.481 | I44: =+E44+G44 -> 0 | J44: =+F44+H44 -> 12161.117 | L44: =+USM!M173 -> 6391.514 | N44: =+F44+H44+L44 -> 18552.631 | P44: =+USM!Q173 -> 8126.569 | Q44: =+M44+O44 -> 0 | R44: =+N44+P44 -> 26679.2 | T44: =+USM!U173 -> 9825.494 | U44: =+Q44+S44 -> 0 | V44: =+R44+T44 -> 36504.694 | X44: =+USM!Y173 -> 9271.39 | Z44: =+P44+T44+X44 -> 27223.453 | AB44: =+N44+Z44 -> 45776.084 | AD44: =+USM!AE173 -> 6063.364 | AE44: =+AA44+AC44 -> 0 | AF44: =+AB44+AD44 -> 51839.448 | AH44: =+USM!AI173 -> 6555.051 | AI44: =+AE44+AG44 -> 0 | AJ44: =+AF44+AH44 -> 58394.499 | AL44: =+USM!AM173 -> 5513.424 | AN44: =+AD44+AH44+AL44 -> 18131.839 | AO44: =+AK44+AM44 -> 0 | AP44: =AJ44+AL44 -> 63907.923 | AR44: =+USM!AS173 -> 7074.087 | AS44: =+AO44+AQ44 -> 0 | AT44: =+AP44+AR44 -> 70982.01 | AV44: =+USM!AW173 -> 6589.77 | AW44: =+AS44+AU44 -> 0 | AX44: =+AT44+AV44 -> 77571.78 | AZ44: =+USM!BA173 -> 5704.355 | BB44: =+AR44+AV44+AZ44 -> 19368.212 | BD44: =AN44+BB44 -> 37500.051 | BE44: =+AY44+BA44 -> 0 | BF44: =AX44+AZ44 -> 83276.135 | BG44: 0 | BH44: 81214.697 | BI44: 0 | BJ44: 86018.164 | BK44: 62409.791 | BM44: 44187.11 | BO44: 4414.219
B45: Angles | C45: Mt | F45: =+USM!G174 -> 0 | H45: =+USM!I174 -> 0 | I45: =+E45+G45 -> 0 | J45: =+F45+H45 -> 0 | L45: =+USM!M174 -> 1992.848 | N45: =+F45+H45+L45 -> 1992.848 | P45: =+USM!Q174 -> 0 | Q45: =+M45+O45 -> 0 | R45: =+N45+P45 -> 1992.848 | T45: =+USM!U174 -> 468.21 | U45: =+Q45+S45 -> 0 | V45: =+R45+T45 -> 2461.058 | X45: =+USM!Y174 -> 0 | Z45: =+P45+T45+X45 -> 468.21 | AB45: =+N45+Z45 -> 2461.058 | AD45: =+USM!AE174 -> 1529.844 | AE45: =+AA45+AC45 -> 0 | AF45: =+AB45+AD45 -> 3990.902 | AH45: =+USM!AI174 -> 0 | AI45: =+AE45+AG45 -> 0 | AJ45: =+AF45+AH45 -> 3990.902 | AL45: =+USM!AM174 -> 0 | AN45: =+AD45+AH45+AL45 -> 1529.844 | AO45: =+AK45+AM45 -> 0 | AP45: =AJ45+AL45 -> 3990.902 | AR45: =+USM!AS174 -> 0 | AS45: =+AO45+AQ45 -> 0 | AT45: =+AP45+AR45 -> 3990.902 | AV45: =+USM!AW174 -> 0 | AW45: =+AS45+AU45 -> 0 | AX45: =+AT45+AV45 -> 3990.902 | AZ45: =+USM!BA174 -> 0 | BB45: =+AR45+AV45+AZ45 -> 0 | BD45: =AN45+BB45 -> 1529.844 | BE45: =+AY45+BA45 -> 0 | BF45: =AX45+AZ45 -> 3990.902 | BG45: 0 | BH45: 1529.844 | BI45: 0 | BJ45: 2887.321 | BK45: 4159.184 | BM45: 919.55454 | BO45: 5739.5256
B46: Beam | L46: =+USM!M175 -> 0 | N46: =+F46+H46+L46 -> 0 | P46: =+USM!Q175 -> 15.713 | R46: =+N46+P46 -> 15.713 | T46: =+USM!U175 -> 0 | V46: =+R46+T46 -> 15.713 | X46: =+USM!Y175 -> 1212.717 | Z46: =+P46+T46+X46 -> 1228.43 | AB46: =+N46+Z46 -> 1228.43
B47: Column | F47: =+USM!G176 -> 0 | H47: =+USM!I176 -> 0 | J47: =+USM!K176 -> 0 | L47: =+USM!M176 -> 2649.675 | N47: =+USM!O176 -> 2649.675 | P47: =+USM!Q176 -> 2830.994 | R47: =+N47+P47 -> 5480.669 | T47: =+USM!U176 -> 2612.658 | V47: =+R47+T47 -> 8093.327 | X47: =+USM!Y176 -> 1543.802 | Z47: =+P47+T47+X47 -> 6987.454 | AB47: =+N47+Z47 -> 9637.129
B48: Semis | C48: Mt | D48: =+D36 -> 525000.34 | E48: =+E36 -> 48499.815 | F48: =+F36 -> 45616.588 | G48: =+G36 -> 48499.577 | H48: =+H36 -> 55556 | I48: =+I36 -> 96999.392 | J48: =+J36 -> 101172.59 | K48: =+K36 -> 48000.111 | L48: =+L36 -> 57284 | M48: =+E48+G48+K48 -> 144999.5 | N48: =+F48+H48+L48 -> 158456.59 | O48: =+O36 -> 43500.141 | P48: =+P36 -> 50766 | Q48: =+Q36 -> 188499.64 | R48: =+R36 -> 209222.59 | S48: =+S36 -> 43500.141 | T48: =+T36 -> 60047.19 | U48: =+U36 -> 231999.79 | V48: =+V36 -> 269269.78 | ... AA48: =+AA36 -> 247299.8 | AB48: =+N48+Z48 -> 324759.78 | AC48: =+AC36 -> 47341.094 | AD48: =+AD36 -> 32797.526 | AE48: =+AE36 -> 294640.89 | AF48: =+AF36 -> 357557.3 | AG48: =+AG36 -> 49680.916 | AH48: =+AH36 -> 8572 | AI48: =+AI36 -> 344321.81 | AJ48: =+AJ36 -> 366129.3 | ... AN48: =+AN36 -> 118772.53 | AO48: =AI48+AK48 -> 390031.87 | AP48: =AJ48+AL48 -> 443532.3 | AQ48: =+AQ36 -> 47339.612 | AR48: =+AR36 -> 73982.023 | AS48: =+AS36 -> 437371.48 | AT48: =+AT36 -> 517514.33 | AU48: =+AU36 -> 46657.996 | AV48: =+AV36 -> 57481.27 | AW48: =+AW36 -> 484029.48 | AX48: =+AX36 -> 574995.6 | ... BC48: =+BC36 -> 282182.29 | BD48: =AN48+BB48 -> 307855.82 | BE48: =AW48+AY48 -> 529482.09 | BF48: =AX48+AZ48 -> 632615.6 | BG48: 479999.56 | BH48: 622038.3 | BI48: 649999.92 | BJ48: 676651.51 | BK48: 711198.96 | BL48: 669999.11 | BM48: 832014.92 | BN48: =+BN36 -> 904433.83 | BO48: 937874.53 | BP48: 571999.74 | BQ48: =+BQ36 -> 877839.96
B49: TOTAL SALEABLE STEEL | C49: Mt | D49: =SUM(D39:D48) -> 2675000.3 | E49: =SUM(E39:E48) -> 228999.82 | F49: =SUM(F39:F48) -> 198800 | G49: =SUM(G39:G48) -> 236499.58 | H49: =SUM(H39:H48) -> 228325.13 | I49: =SUM(I39:I48) -> 465499.39 | J49: =SUM(J39:J48) -> 427125.13 | K49: =SUM(K39:K48) -> 229000.11 | ... BF49: =SUM(BF39:BF48) -> 2468680.4 | BG49: 2409999.6 | BH49: 2331824 | BI49: 2524999.9 | BJ49: 2409644.1 | BK49: 2315208 | BL49: =SUM(BL39:BL48) -> 2369999.1 | BM49: =SUM(BM39:BM48) -> 2160425.8 | BN49: =SUM(BN39:BN48) -> 2235274.9 | BO49: =SUM(BO39:BO48) -> 1823883.8 | BP49: =SUM(BP39:BP48) -> 2406999.7 | BQ49: =SUM(BQ39:BQ48) -> 2093720.2
B50: COAL TAR | C50: Mt | D50: 42940.816 | E50: 3583.125 | F50: 3447.44 | G50: 3702.5625 | H50: 3578.13 | I50: =+E50+G50 -> 7285.6875 | J50: =+F50+H50 -> 7025.57 | K50: 3531.525 | L50: 3463.07 | M50: =+E50+G50+K50 -> 10817.212 | N50: =+F50+H50+L50 -> 10488.64 | O50: 3649.2425 | P50: 3586.12 | Q50: =+M50+O50 -> 14466.455 | R50: =+N50+P50 -> 14074.76 | S50: 3649.2425 | T50: 3608.69 | U50: =+Q50+S50 -> 18115.697 | V50: =+R50+T50 -> 17683.45 | W50: 3400.5337 | X50: 3497.87 | Y50: =+O50+S50+W50 -> 10699.019 | Z50: =+P50+T50+X50 -> 10692.68 | AA50: =+M50+Y50 -> 21516.231 | AB50: =+N50+Z50 -> 21181.32 | AC50: 3996.382 | AD50: 3647.77 | AE50: =+AA50+AC50 -> 25512.613 | AF50: =+AB50+AD50 -> 24829.09 | AG50: 3867.4665 | AH50: 3383.76 | AI50: =+AE50+AG50 -> 29380.08 | AJ50: =+AF50+AH50 -> 28212.85 | AK50: 3996.382 | AL50: 3673.95 | AM50: =+AC50+AG50+AK50 -> 11860.231 | AN50: =+AD50+AH50+AL50 -> 10705.48 | AO50: =AI50+AK50 -> 33376.462 | AP50: =AJ50+AL50 -> 31886.8 | AQ50: 3996.382 | AR50: 3683.34 | AS50: =+AO50+AQ50 -> 37372.844 | AT50: =+AP50+AR50 -> 35570.14 | AU50: 3609.6354 | AV50: 3305.7 | AW50: =+AS50+AU50 -> 40982.479 | AX50: =+AT50+AV50 -> 38875.84 | AY50: 3996.382 | AZ50: 3667.4975 | BA50: =+AQ50+AU50+AY50 -> 11602.399 | BB50: =+AR50+AV50+AZ50 -> 10656.538 | BC50: =AM50+BA50 -> 23462.63 | BD50: =AN50+BB50 -> 21362.018 | BE50: =AW50+AY50 -> 44978.861 | BF50: =AX50+AZ50 -> 42543.337 | BG50: 46866.669 | BH50: 43164.837 | BI50: 50890.946 | BJ50: 44869.641 | BK50: 48878.17 | BL50: 51086.383 | BM50: 49592.55 | BN50: 48584.311 | BO50: 46678.95 | BP50: 46118.873 | BQ50: 49237.57
B51: AMMONIUM SULPHATE | C51: Mt | D51: 9122.3971 | E51: 835.57544 | F51: 674 | G51: 865.41742 | H51: 488.5 | I51: =+E51+G51 -> 1700.9929 | J51: =+F51+H51 -> 1162.5 | K51: 816.31144 | L51: 494.65 | M51: =+E51+G51+K51 -> 2517.3043 | N51: =+F51+H51+L51 -> 1657.15 | O51: 845.46542 | P51: 717.5 | Q51: =+M51+O51 -> 3362.7697 | R51: =+N51+P51 -> 2374.65 | S51: 845.46542 | T51: 586.55 | U51: =+Q51+S51 -> 4208.2351 | V51: =+R51+T51 -> 2961.2 | W51: 790.46478 | X51: 519.6 | Y51: =+O51+S51+W51 -> 2481.3956 | Z51: =+P51+T51+X51 -> 1823.65 | AA51: =+M51+Y51 -> 4998.6999 | AB51: =+N51+Z51 -> 3480.8 | AC51: 902.03319 | AD51: 376 | AE51: =+AA51+AC51 -> 5900.7331 | AF51: =+AB51+AD51 -> 3856.8 | AG51: 0 | AH51: 317 | AI51: =+AE51+AG51 -> 5900.7331 | AJ51: =+AF51+AH51 -> 4173.8 | AK51: 902.03319 | AL51: 455 | AM51: =+AC51+AG51+AK51 -> 1804.0664 | AN51: =+AD51+AH51+AL51 -> 1148 | AO51: =AI51+AK51 -> 6802.7663 | AP51: =AJ51+AL51 -> 4628.8 | AQ51: 902.03319 | AR51: 479 | AS51: =+AO51+AQ51 -> 7704.7995 | AT51: =+AP51+AR51 -> 5107.8 | AU51: 813.14172 | AV51: 501 | AW51: =+AS51+AU51 -> 8517.9412 | AX51: =+AT51+AV51 -> 5608.8 | AY51: 902.03319 | AZ51: 572 | BA51: =+AQ51+AU51+AY51 -> 2617.2081 | BB51: =+AR51+AV51+AZ51 -> 1552 | BC51: =AM51+BA51 -> 4421.2745 | BD51: =AN51+BB51 -> 2700 | BE51: =AW51+AY51 -> 9419.9744 | BF51: =AX51+AZ51 -> 6180.8 | BG51: 9348.2026 | BH51: 4897.75 | BI51: 8145.2 | BJ51: 16578.809 | BK51: 8876.9 | BL51: 21728.852 | BM51: 10510.61 | BN51: 15654.415 | BO51: 12312.8
B53: Total casts | C53: No | D53: 18466.793 | E53: 1580.7365 | F53: 1323 | G53: 1631.0985 | H53: 1516 | I53: =+E53+G53 -> 3211.8351 | J53: =+F53+H53 -> 2839 | K53: 1580.7365 | L53: 1556 | M53: =+E53+G53+K53 -> 4792.5716 | N53: =+F53+H53+L53 -> 4395 | O53: 1599.6223 | P53: 1610 | Q53: =+M53+O53 -> 6392.1939 | R53: =+N53+P53 -> 6005 | S53: 1599.6223 | T53: 1515 | U53: =+Q53+S53 -> 7991.8162 | V53: =+R53+T53 -> 7520 | W53: 839.4712 | X53: 1448 | Y53: =+O53+S53+W53 -> 4038.7158 | Z53: =+P53+T53+X53 -> 4573 | AA53: =+M53+Y53 -> 8831.2874 | AB53: =+N53+Z53 -> 8968 | AC53: 1569.9371 | AD53: 1451 | AE53: =+AA53+AC53 -> 10401.224 | AF53: =+AB53+AD53 -> 10419 | AG53: 1519.6226 | AH53: 52 | AI53: =+AE53+AG53 -> 11920.847 | AJ53: =+AF53+AH53 -> 10471 | AK53: 1569.9371 | AL53: 1531 | AM53: =+AC53+AG53+AK53 -> 4659.4969 | AN53: =+AD53+AH53+AL53 -> 3034 | AO53: =AI53+AK53 -> 13490.784 | AP53: =AJ53+AL53 -> 12002 | AQ53: 1569.9371 | AR53: 1599 | AS53: =+AO53+AQ53 -> 15060.721 | AT53: =+AP53+AR53 -> 13601 | AU53: 1412.7044 | AV53: 1443 | AW53: =+AS53+AU53 -> 16473.426 | AX53: =+AT53+AV53 -> 15044 | AY53: 1569.9371 | AZ53: 1572 | BA53: =+AQ53+AU53+AY53 -> 4552.5786 | BB53: =+AR53+AV53+AZ53 -> 4614 | BC53: =AM53+BA53 -> 9212.0755 | BD53: =AN53+BB53 -> 7648 | BE53: =AW53+AY53 -> 18043.363 | BF53: =AX53+AZ53 -> 16616 | BG53: 16596.855 | BH53: 15925 | BI53: 16116 | BJ53: 16344.715 | BK53: 14624 | BL53: 15300.817 | BM53: 12158 | BN53: 16891.892 | BO53: 14151
E55: =+E37-E49 -> 0 | F55: =+F37-F49 -> 0 | G55: =+G37-G49 -> 0 | H55: =+H37-H49 -> 0 | I55: =+I37-I49 -> 0 | J55: =+J37-J49 -> 0 | K55: =+K37-K49 -> 0 | L55: =+L37-L49 -> 0 | ... BF55: =+BF37-BF49 -> 10865.559 | BG55: 0 | BH55: 0 | BI55: -0.01296 | BJ55: =+BL37-BL49 -> 0 | BK55: =+BM37-BM49 -> -0.00039024325 | BL55: =+BN37-BN49 -> 0 | BM55: =+BO37-BO49 -> 0.55446018 | BN55: =+BP37-BP49 -> 0 | BO55: =+BQ37-BQ49 -> 0
E58: 237.077 | F58: 110.658 | G58: 257.623
E59: 223.226 | F59: 97.961 | G59: 240.806
E62: hm | G62: 384 | K62: =+($E$63*G62+$E$64*G63+$E$65*G64)/SUM($E$63:$E$65) -> 376.89959
E63: 237.077 | G63: 415
E64: 110.658 | G64: 354
E65: 257.623
G66: 32 | K66: =+($E$63*G66+$E$64*G67+$E$65*G68)/SUM($E$63:$E$65) -> 33.03394
E67: 223.226 | G67: 33
E68: 97.961 | G68: 34
E69: 240.806
G70: 125 | K70: =+($E$63*G70+$E$64*G71+$E$65*G72)/SUM($E$63:$E$65) -> 126.38519
G71: 93
G72: 142
G74: =+G62+G66+G70 -> 541 | K74: =+($E$63*G74+$E$64*G75+$E$65*G76)/SUM($E$63:$E$65) -> 536.31872
G75: =+G63+G67+G71 -> 541
G76: =+G64+G68+G72 -> 530
G78: 71 | K78: =+($E$63*G78+$E$64*G79+$E$65*G80)/SUM($E$63:$E$65) -> 68.93212
G79: 69
G80: 67
G82: 15 | K82: =+($E$63*G82+$E$64*G83+$E$65*G84)/SUM($E$63:$E$65) -> 15.973964
G83: 18
G84: 16
G87: 6.11 | K87: =+($E$67*G87+$E$68*G88+$E$69*G89)/SUM($E$67:$E$69) -> 6.2823514
G88: 7.32
G89: 6.02
G94: 2.26 | K94: 2.2
G95: 1.83
G96: 2.47

Sheet Maj Despatch Summ
B1: MAJOR DESPATCH SUMMARY 2025-26 (As per Finance CENVAT report)
E2: 30 | F2: 30 | G2: 31 | H2: 31 | I2: =+G2+E2 -> 61 | J2: =+H2+F2 -> 61 | K2: 30 | L2: 30 | M2: =+E2+G2+K2 -> 91 | N2: =+F2+H2+L2 -> 91 | O2: 31 | P2: 31 | Q2: =+M2+O2 -> 122 | R2: =+N2+P2 -> 122 | S2: 31 | T2: 31 | U2: =+Q2+S2 -> 153 | V2: =+R2+T2 -> 153 | W2: 30 | X2: 30 | Y2: =+O2+S2+W2 -> 92 | Z2: =+P2+T2+X2 -> 92 | AA2: =+M2+Y2 -> 183 | AB2: =+N2+Z2 -> 183 | AC2: 31 | AD2: 31 | AE2: =AA2+AC2 -> 214 | AF2: =AB2+AD2 -> 214 | AG2: 30 | AH2: 30 | AI2: =AE2+AG2 -> 244 | AJ2: =AF2+AH2 -> 244 | AK2: 31 | AL2: 31 | AM2: =+AC2+AG2+AK2 -> 92 | AN2: =+AD2+AH2+AL2 -> 92 | AO2: =AI2+AK2 -> 275 | AP2: =AJ2+AL2 -> 275 | AQ2: 31 | AR2: 31 | AS2: =AO2+AQ2 -> 306 | AT2: =AP2+AR2 -> 306 | AU2: 28 | AV2: 28 | AW2: =AS2+AU2 -> 334 | AX2: =AT2+AV2 -> 334 | AY2: 31 | AZ2: 31 | BA2: =+AQ2+AU2+AY2 -> 90 | BB2: =+AR2+AV2+AZ2 -> 90 | BC2: =AM2+BA2 -> 182 | BD2: =AN2+BB2 -> 182 | BE2: =AW2+AY2 -> 365 | BF2: =AX2+AZ2 -> 365 | BO2: 365 | BP2: 365 | BQ2: 366 | BR2: 366
B3: ITEM | C3: Unit | D3: 2025-26 ABP | E3: Apr'25 | G3: May'25 | I3: 2M | K3: Jun'25 | M3: QTR-1 | O3: Jul'25 | Q3: 4M | S3: Aug'25 | U3: 5M | W3: Sep'25 | Y3: QTR-2 | AA3: H1 | AC3: Oct'24 | AE3: 7M | AG3: Nov'24 | AI3: 8M | AK3: Dec'24 | AM3: QTR-3 | AO3: 9M | AQ3: Jan'25 | AS3: 10M | AU3: Feb'25 | AW3: 11M | AY3: Mar'25 | BA3: QTR-4 | BC3: H2 | BE3: 2024-25 | BG3: 2024-25 | BI3: 2023-24 | BK3: 2022-23 | BM3: 2021-22 | BO3: 2020-21 | BQ3: 2019-20
E4: ABP | F4: ACT | G4: ABP | H4: ACT | I4: ABP | J4: ACT | K4: ABP | L4: ACT | M4: ABP | N4: ACT | O4: ABP | P4: ACT | Q4: ABP | R4: ACT | S4: ABP | T4: ACT | U4: ABP | V4: ACT | W4: ABP | X4: ACT | Y4: ABP | Z4: ACT | AA4: ABP | AB4: ACT | AC4: ABP | AD4: ACT | AE4: ABP | AF4: ACT | AG4: ABP | AH4: ACT | AI4: ABP | AJ4: ACT | AK4: ABP | AL4: ACT | AM4: ABP | AN4: ACT | AO4: ABP | AP4: ACT | AQ4: ABP | AR4: ACT | AS4: ABP | AT4: ACT | AU4: ABP | AV4: ACT | AW4: ABP | AX4: ACT | AY4: ABP | AZ4: ACT | BA4: ABP | BB4: ACT | BC4: ABP | BD4: ACT | BE4: ABP | BF4: ACT | BG4: ABP | BH4: ACT | BI4: ABP | BJ4: ACT | BK4: ABP | BL4: ACT | BM4: ABP | BN4: ACT | BO4: ABP | BP4: ACT | BQ4: ABP | BR4: ACT
B5: Saleable Steel (mill-wise)
B6: MKTG-Plant sales | C6: MT | D6: 25000 | E6: 2083.3333 | F6: 1095.89 | G6: 2083.3333 | H6: 2704.95 | I6: =+E6+G6 -> 4166.6667 | J6: =+F6+H6 -> 3800.84 | K6: 2083.3333 | L6: 6803.81 | M6: =+E6+G6+K6 -> 6250 | N6: =+F6+H6+L6 -> 10604.65 | O6: 2083.3333 | P6: 3865.36 | Q6: =+M6+O6 -> 8333.3333 | R6: =+N6+P6 -> 14470.01 | S6: 2083.3333 | T6: 6257.93 | U6: =+Q6+S6 -> 10416.667 | V6: =+R6+T6 -> 20727.94 | W6: 2083 | X6: 5182.59 | Y6: =+O6+S6+W6 -> 6249.6667 | Z6: =+P6+T6+X6 -> 15305.88 | AA6: =+M6+Y6 -> 12499.667 | AB6: =+N6+Z6 -> 25910.53 | AC6: 2100 | AD6: 4044.21 | AE6: =+AA6+AC6 -> 14599.667 | AF6: =+AB6+AD6 -> 29954.74 | AG6: 2100 | AH6: 5778.35 | AI6: =+AE6+AG6 -> 16699.667 | AJ6: =+AF6+AH6 -> 35733.09 | AK6: 2100 | AL6: 3912 | AM6: =+AC6+AG6+AK6 -> 6300 | AN6: =+AD6+AH6+AL6 -> 13734.56 | AO6: =AI6+AK6 -> 18799.667 | AP6: =AJ6+AL6 -> 39645.09 | AQ6: 2200 | AR6: 3486.44 | AS6: =+AO6+AQ6 -> 20999.667 | AT6: =+AP6+AR6 -> 43131.53 | AU6: 2100 | AV6: 1080.89 | AW6: =+AS6+AU6 -> 23099.667 | AX6: =+AT6+AV6 -> 44212.42 | AY6: 2100 | AZ6: 6965.79 | BA6: =+AQ6+AU6+AY6 -> 6400 | BB6: =+AR6+AV6+AZ6 -> 11533.12 | BC6: =AM6+BA6 -> 12700 | BD6: =AN6+BB6 -> 25267.68 | BE6: =+AW6+AY6 -> 25199.667 | BF6: =+AX6+AZ6 -> 51178.21 | BG6: 21500 | BH6: 53987.54 | BI6: 21500 | BJ6: 30649.84 | BK6: 25500 | BL6: 34807.22 | BM6: 16050 | BN6: 33201.15 | BO6: 0 | BP6: 35268.25 | BQ6: 2000 | BR6: 28405.85
B7: IPT | C7: MT | D7: 0 | E7: 0 | F7: 0 | G7: 0 | H7: 0 | I7: =+E7+G7 -> 0 | J7: =+F7+H7 -> 0 | K7: 0 | L7: 0 | M7: =+E7+G7+K7 -> 0 | N7: =+F7+H7+L7 -> 0 | O7: 0 | P7: 64.1 | Q7: =+M7+O7 -> 0 | R7: =+N7+P7 -> 64.1 | S7: 0 | T7: 1485.16 | U7: =+Q7+S7 -> 0 | V7: =+R7+T7 -> 1549.26 | W7: 0 | X7: 694 | Y7: =+O7+S7+W7 -> 0 | Z7: =+P7+T7+X7 -> 2243.26 | AA7: =+M7+Y7 -> 0 | AB7: =+N7+Z7 -> 2243.26 | AC7: 0 | AD7: 0 | AE7: =+AA7+AC7 -> 0 | AF7: =+AB7+AD7 -> 2243.26 | AG7: 0 | AH7: 0 | AI7: =+AE7+AG7 -> 0 | AJ7: =+AF7+AH7 -> 2243.26 | AK7: 0 | AL7: 0 | AM7: =+AC7+AG7+AK7 -> 0 | AN7: =+AD7+AH7+AL7 -> 0 | AO7: =AI7+AK7 -> 0 | AP7: =AJ7+AL7 -> 2243.26 | AQ7: 0 | AR7: 0 | AS7: =+AO7+AQ7 -> 0 | AT7: =+AP7+AR7 -> 2243.26 | AU7: 0 | AV7: 0 | AW7: =+AS7+AU7 -> 0 | AX7: =+AT7+AV7 -> 2243.26 | AY7: 0 | AZ7: 0 | BA7: =+AQ7+AU7+AY7 -> 0 | BB7: =+AR7+AV7+AZ7 -> 0 | BC7: =AM7+BA7 -> 0 | BD7: =AN7+BB7 -> 0 | BE7: =+AW7+AY7 -> 0 | BF7: =+AX7+AZ7 -> 2243.26 | BG7: 0 | BH7: 322.72 | BI7: 0 | BJ7: 3076.2 | BK7: 123000 | BL7: 42263.08 | BM7: 0 | BN7: 71707.42 | BO7: 10800 | BP7: 9758.51 | BQ7: 24210 | BR7: 5928.095
B8: CMO-WR MILL | C8: MT | D8: 499000 | E8: 42416.667 | F8: 33332.8 | G8: 43916.667 | H8: 39367.02 | I8: =+E8+G8 -> 86333.333 | J8: =+F8+H8 -> 72699.82 | K8: 42416.667 | L8: 37508.06 | M8: =+E8+G8+K8 -> 128750 | N8: =+F8+H8+L8 -> 110207.88 | O8: 43916.667 | P8: 44133.19 | Q8: =+M8+O8 -> 172666.67 | R8: =+N8+P8 -> 154341.07 | S8: 43916.667 | T8: 40726.54 | U8: =+Q8+S8 -> 216583.33 | V8: =+R8+T8 -> 195067.61 | W8: 24916.667 | X8: 36332.97 | Y8: =+O8+S8+W8 -> 112750 | Z8: =+P8+T8+X8 -> 121192.7 | AA8: =+M8+Y8 -> 241500 | AB8: =+N8+Z8 -> 231400.58 | AC8: 45400 | AD8: 37048.14 | AE8: =+AA8+AC8 -> 286900 | AF8: =+AB8+AD8 -> 268448.72 | AG8: 43900 | AH8: 30159.91 | AI8: =+AE8+AG8 -> 330800 | AJ8: =+AF8+AH8 -> 298608.63 | AK8: 45400 | AL8: 37390 | AM8: =+AC8+AG8+AK8 -> 134700 | AN8: =+AD8+AH8+AL8 -> 104598.05 | AO8: =AI8+AK8 -> 376200 | AP8: =AJ8+AL8 -> 335998.63 | AQ8: 45300 | AR8: 37025.61 | AS8: =+AO8+AQ8 -> 421500 | AT8: =+AP8+AR8 -> 373024.24 | AU8: 40400 | AV8: 32967.39 | AW8: =+AS8+AU8 -> 461900 | AX8: =+AT8+AV8 -> 405991.63 | AY8: 45400 | AZ8: 44837.42 | BA8: =+AQ8+AU8+AY8 -> 131100 | BB8: =+AR8+AV8+AZ8 -> 114830.42 | BC8: =AM8+BA8 -> 265800 | BD8: =AN8+BB8 -> 219428.47 | BE8: =+AW8+AY8 -> 507300 | BF8: =+AX8+AZ8 -> 450829.05 | BG8: 498500 | BH8: 459216.41 | BI8: 498500 | BJ8: 473494.21 | BK8: 498500 | BL8: 453432.75 | BM8: 498500 | BN8: 467953.64 | BO8: 435166.29 | BP8: 351267.02 | BQ8: 498000 | BR8: 399090.26
B9: CMO-BAR MILL | C9: MT | D9: 900000 | E9: 76000 | F9: 60011.21 | G9: 79000 | H9: 67347.9 | I9: =+E9+G9 -> 155000 | J9: =+F9+H9 -> 127359.11 | K9: 76000 | L9: 73175.63 | M9: =+E9+G9+K9 -> 231000 | N9: =+F9+H9+L9 -> 200534.74 | O9: 79000 | P9: 84102.5 | Q9: =+M9+O9 -> 310000 | R9: =+N9+P9 -> 284637.24 | S9: 79000 | T9: 86905.93 | U9: =+Q9+S9 -> 389000 | V9: =+R9+T9 -> 371543.17 | W9: 47500 | X9: 68689.99 | Y9: =+O9+S9+W9 -> 205500 | Z9: =+P9+T9+X9 -> 239698.42 | AA9: =+M9+Y9 -> 436500 | AB9: =+N9+Z9 -> 440233.16 | AC9: 80000 | AD9: 64076.47 | AE9: =+AA9+AC9 -> 516500 | AF9: =+AB9+AD9 -> 504309.63 | AG9: 77500 | AH9: 10813.23 | AI9: =+AE9+AG9 -> 594000 | AJ9: =+AF9+AH9 -> 515122.86 | AK9: 80000 | AL9: 67253 | AM9: =+AC9+AG9+AK9 -> 237500 | AN9: =+AD9+AH9+AL9 -> 142142.7 | AO9: =AI9+AK9 -> 674000 | AP9: =AJ9+AL9 -> 582375.86 | AQ9: 80000 | AR9: 70877.68 | AS9: =+AO9+AQ9 -> 754000 | AT9: =+AP9+AR9 -> 653253.54 | AU9: 72500 | AV9: 58216.86 | AW9: =+AS9+AU9 -> 826500 | AX9: =+AT9+AV9 -> 711470.4 | AY9: 80000 | AZ9: 84208.42 | BA9: =+AQ9+AU9+AY9 -> 232500 | BB9: =+AR9+AV9+AZ9 -> 213302.96 | BC9: =AM9+BA9 -> 470000 | BD9: =AN9+BB9 -> 355445.66 | BE9: =+AW9+AY9 -> 906500 | BF9: =+AX9+AZ9 -> 795678.82 | BG9: 870000 | BH9: 750184.19 | BI9: 850000 | BJ9: 781402.45 | BK9: 780000 | BL9: 768402.31 | BM9: 750000 | BN9: 648761.89 | BO9: 674874.74 | BP9: 436958.46 | BQ9: 800000 | BR9: 612890.55
B10: CMO-US MILL | C10: MT | D10: 750000 | E10: 62000 | F10: 44122.7 | G10: 65000 | H10: 57716 | I10: =+E10+G10 -> 127000 | J10: =+F10+H10 -> 101838.7 | K10: 62500 | L10: 56720.68 | M10: =+E10+G10+K10 -> 189500 | N10: =+F10+H10+L10 -> 158559.38 | O10: 65000 | P10: 57264.83 | Q10: =+M10+O10 -> 254500 | R10: =+N10+P10 -> 215824.21 | S10: 65000 | T10: 47224.14 | U10: =+Q10+S10 -> 319500 | V10: =+R10+T10 -> 263048.35 | W10: 33500 | X10: 45948.12 | Y10: =+O10+S10+W10 -> 163500 | Z10: =+P10+T10+X10 -> 150437.09 | AA10: =+M10+Y10 -> 353000 | AB10: =+N10+Z10 -> 308996.47 | AC10: 54000 | AD10: 43303.75 | AE10: =+AA10+AC10 -> 407000 | AF10: =+AB10+AD10 -> 352300.22 | AG10: 52000 | AH10: 15465.42 | AI10: =+AE10+AG10 -> 459000 | AJ10: =+AF10+AH10 -> 367765.64 | AK10: 54000 | AL10: 33463 | AM10: =+AC10+AG10+AK10 -> 160000 | AN10: =+AD10+AH10+AL10 -> 92232.17 | AO10: =AI10+AK10 -> 513000 | AP10: =AJ10+AL10 -> 401228.64 | AQ10: 54000 | AR10: 44656.88 | AS10: =+AO10+AQ10 -> 567000 | AT10: =+AP10+AR10 -> 445885.52 | AU10: 48000 | AV10: 47339.01 | AW10: =+AS10+AU10 -> 615000 | AX10: =+AT10+AV10 -> 493224.53 | AY10: 60000 | AZ10: 68418.51 | BA10: =+AQ10+AU10+AY10 -> 162000 | BB10: =+AR10+AV10+AZ10 -> 160414.4 | BC10: =AM10+BA10 -> 322000 | BD10: =AN10+BB10 -> 252646.57 | BE10: =+AW10+AY10 -> 675000 | BF10: =+AX10+AZ10 -> 561643.04 | BG10: 560000 | BH10: 502052.01 | BI10: 525000 | BJ10: 452802.59 | BK10: 470000 | BL10: 357334.79 | BM10: 445000 | BN10: 214319.65 | BO10: 220000 | BP10: 100400.4 | BQ10: 535000 | BR10: 167166.99
B11: CMO-SEMIS | C11: MT | D11: 500798.34 | E11: 46499.815 | F11: 37328.4 | G11: 46499.577 | H11: 50330.16 | I11: =+E11+G11 -> 92999.392 | J11: =+F11+H11 -> 87658.56 | K11: 46000.111 | L11: 44296.21 | M11: =+E11+G11+K11 -> 138999.5 | N11: =+F11+H11+L11 -> 131954.77 | O11: 41500.141 | P11: 54193.85 | Q11: =+M11+O11 -> 180499.64 | R11: =+N11+P11 -> 186148.62 | S11: 41500.141 | T11: 63719.03 | U11: =+Q11+S11 -> 221999.79 | V11: =+R11+T11 -> 249867.65 | W11: 13300.015 | X11: 50417.94 | Y11: =+O11+S11+W11 -> 96300.297 | Z11: =+P11+T11+X11 -> 168330.82 | AA11: =+M11+Y11 -> 235299.8 | AB11: =+N11+Z11 -> 300285.59 | AC11: 45341.094 | AD11: 31038.07 | AE11: =+AA11+AC11 -> 280640.89 | AF11: =+AB11+AD11 -> 331323.66 | AG11: 47680.916 | AH11: 11905.3 | AI11: =+AE11+AG11 -> 328321.81 | AJ11: =+AF11+AH11 -> 343228.96 | AK11: 43710.094 | AL11: 56100 | AM11: =+AC11+AG11+AK11 -> 136732.1 | AN11: =+AD11+AH11+AL11 -> 99043.37 | AO11: =AI11+AK11 -> 372031.9 | AP11: =AJ11+AL11 -> 399328.96 | AQ11: 45340.094 | AR11: 82929.73 | AS11: =+AO11+AQ11 -> 417372 | AT11: =+AP11+AR11 -> 482258.69 | AU11: 44657.996 | AV11: 49136.17 | AW11: =+AS11+AU11 -> 462029.99 | AX11: =+AT11+AV11 -> 531394.86 | AY11: 43452.64 | AZ11: 61705.96 | BA11: =+AQ11+AU11+AY11 -> 133450.73 | BB11: =+AR11+AV11+AZ11 -> 193771.86 | BC11: =AM11+BA11 -> 270182.83 | BD11: =AN11+BB11 -> 292815.23 | BE11: =+AW11+AY11 -> 505482.63 | BF11: =+AX11+AZ11 -> 593100.82 | BG11: 459999.54 | BH11: 584980.47 | BI11: 630000.01 | BJ11: 623466.17 | BK11: 513000.01 | BL11: 641816.63 | BM11: 659950.15 | BN11: 742311.77 | BO11: 893633.78 | BP11: 944002.21 | BQ11: 547789.74 | BR11: 836451
B12: TOTAL | C12: MT | D12: =SUM(D6:D11) -> 2674798.3 | E12: =SUM(E6:E11) -> 228999.82 | F12: =SUM(F6:F11) -> 175891 | G12: =SUM(G6:G11) -> 236499.58 | H12: =SUM(H6:H11) -> 217466.03 | I12: =SUM(I6:I11) -> 465499.39 | J12: =SUM(J6:J11) -> 393357.03 | K12: =SUM(K6:K11) -> 229000.11 | ... BF12: =SUM(BF6:BF11) -> 2454673.2 | BG12: 2409999.5 | BH12: 2350743.3 | BI12: 2525000 | BJ12: 2364891.5 | BK12: 2410000 | BL12: 2298056.8 | BM12: 2369500.2 | BN12: 2178255.5 | BO12: 2234474.8 | BP12: 1877654.8 | BQ12: 2406999.7 | BR12: 2049932.7
B13: Consideration in internal consumption | D13: Saleable production Plan: 2410000 (1500 T has been kept in plan for Internal consumption) | E13: Saleable production Plan: 201135 (200 T has been kept in plan for Internal consumption) | G13: Saleable production Plan: 201135 (200 T has been kept in plan for Internal consumption) | K13: Saleable production Plan: 201135 (200 T has been kept in plan for Internal consumption) | O13: Saleable production Plan: 201135 (200 T has been kept in plan for Internal consumption) | S13: Saleable production Plan: 201135 (200 T has been kept in plan for Internal consumption) | W13: Saleable production Plan: 201135 (200 T has been kept in plan for Internal consumption) | AC13: Saleable production Plan: 201135 (200 T has been kept in plan for Internal consumption) | AG13: Saleable production Plan: 201135 (200 T has been kept in plan for Internal consumption) | AK13: Saleable production Plan: 201135 (200 T has been kept in plan for Internal consumption) | AQ13: Saleable production Plan: 201135 (200 T has been kept in plan for Internal consumption) | AU13: Saleable production Plan: 201135 (200 T has been kept in plan for Internal consumption) | AY13: Saleable production Plan: 201135 (200 T has been kept in plan for Internal consumption)
B14: Saleable Steel (Sale type-wise)
B15: IPT | C15: MT | D15: =+D12 -> 2674798.3 | E15: =+E12 -> 228999.82 | F15: =+F7 -> 0 | G15: =+G12 -> 236499.58 | H15: =+H7 -> 0 | I15: =+E15+G15 -> 465499.39 | J15: =+F15+H15 -> 0 | K15: =+K12 -> 229000.11 | L15: =+L7 -> 0 | M15: =+E15+G15+K15 -> 694499.5 | N15: =+F15+H15+L15 -> 0 | O15: =+O12 -> 231500.14 | P15: =+P7 -> 64.1 | Q15: =+M15+O15 -> 925999.64 | R15: =+N15+P15 -> 64.1 | S15: =+S12 -> 231500.14 | T15: =+T7 -> 1485.16 | U15: =+Q15+S15 -> 1157499.8 | V15: =+R15+T15 -> 1549.26 | W15: =+W12 -> 121299.68 | X15: =+X7 -> 694 | Y15: =+O15+S15+W15 -> 584299.96 | Z15: =+P15+T15+X15 -> 2243.26 | AA15: =+M15+Y15 -> 1278799.5 | AB15: =+N15+Z15 -> 2243.26 | AC15: =+AC12 -> 226841.09 | AD15: =+AD7 -> 0 | AE15: =+AA15+AC15 -> 1505640.6 | AF15: =+AB15+AD15 -> 2243.26 | AG15: =+AG12 -> 223180.92 | AH15: =+AH7 -> 0 | AI15: =+AE15+AG15 -> 1728821.5 | AJ15: =+AF15+AH15 -> 2243.26 | AK15: =+AK12 -> 225210.09 | AL15: =+AL7 -> 0 | AM15: =+AC15+AG15+AK15 -> 675232.1 | AN15: =+AD15+AH15+AL15 -> 0 | AO15: =AI15+AK15 -> 1954031.6 | AP15: =AJ15+AL15 -> 2243.26 | AQ15: =+AQ12 -> 226840.09 | AR15: =+AR7 -> 0 | AS15: =+AO15+AQ15 -> 2180871.7 | AT15: =+AP15+AR15 -> 2243.26 | AU15: =+AU12 -> 207658 | AV15: =+AV7 -> 0 | AW15: =+AS15+AU15 -> 2388529.7 | AX15: =+AT15+AV15 -> 2243.26 | AY15: =+AY12 -> 230952.64 | AZ15: =+AZ7 -> 0 | BA15: =+AQ15+AU15+AY15 -> 665450.73 | BB15: =+AR15+AV15+AZ15 -> 0 | BC15: =+AM15+BA15 -> 1340682.8 | BD15: =AN15+BB15 -> 0 | BE15: =+AW15+AY15 -> 2619482.3 | BF15: =+AX15+AZ15 -> 2243.26 | BG15: 2409999.5 | BH15: 322.72 | BI15: 2525000 | BJ15: 3076.2 | BK15: 2410000 | BL15: 42263.08 | BM15: 2369500.2 | BN15: 71707.42 | BO15: 2234474.8 | BP15: 9758.51 | BQ15: =+BQ12 -> 2406999.7 | BR15: 5928.249
B16: CMO DIR | C16: MT | F16: 121879.8 | H16: 138747.01 | J16: =+F16+H16 -> 260626.81 | L16: 120386.74 | N16: =+F16+H16+L16 -> 381013.55 | P16: 136780.81 | R16: =+N16+P16 -> 517794.36 | T16: 149407.49 | V16: =+R16+T16 -> 667201.85 | X16: 118171.66 | Z16: =+P16+T16+X16 -> 404359.96 | AB16: =+N16+Z16 -> 785373.51 | AD16: 116531.94 | AF16: =+AB16+AD16 -> 901905.45 | AH16: 55204.14 | AJ16: =+AF16+AH16 -> 957109.59 | AL16: 139405.21 | AN16: =+AD16+AH16+AL16 -> 311141.29 | AP16: =AJ16+AL16 -> 1096514.8 | AR16: 171765.58 | AT16: =+AP16+AR16 -> 1268280.4 | AV16: 136540.59 | AX16: =+AT16+AV16 -> 1404821 | AZ16: 189752.74 | BB16: =+AR16+AV16+AZ16 -> 498058.91 | BD16: =AN16+BB16 -> 809200.2 | BF16: =+AX16+AZ16 -> 1594573.7 | BH16: 1620104.9 | BJ16: 1443296 | BL16: 1325226.7 | BN16: 1097093.1 | BP16: 691326.52 | BR16: 569419.83
B17: CMO SYD | C17: MT | F17: 48531.65 | H17: 73085.04 | J17: =+F17+H17 -> 121616.69 | L17: 91277.94 | N17: =+F17+H17+L17 -> 212894.63 | P17: 102874.62 | R17: =+N17+P17 -> 315769.25 | T17: 89009.36 | V17: =+R17+T17 -> 404778.61 | X17: 83127.57 | Z17: =+P17+T17+X17 -> 275011.55 | AB17: =+N17+Z17 -> 487906.18 | AD17: 56105 | AF17: =+AB17+AD17 -> 544011.18 | AH17: 12954.53 | AJ17: =+AF17+AH17 -> 556965.71 | AL17: 54572.32 | AN17: =+AD17+AH17+AL17 -> 123631.85 | AP17: =AJ17+AL17 -> 611538.03 | AR17: 60538.11 | AT17: =+AP17+AR17 -> 672076.14 | AV17: 51118.84 | AX17: =+AT17+AV17 -> 723194.98 | AZ17: 68622.95 | BB17: =+AR17+AV17+AZ17 -> 180279.9 | BD17: =AN17+BB17 -> 303911.75 | BF17: =+AX17+AZ17 -> 791817.93 | BH17: 662107.03 | BJ17: 829404.4 | BL17: 809005.31 | BN17: 567271.22 | BP17: 479205.15 | BR17: 909567
B18: MKTG DIR | C18: MT | F18: =+F6 -> 1095.89 | H18: =+H6 -> 2704.95 | J18: =+F18+H18 -> 3800.84 | L18: =+L6 -> 6803.81 | N18: =+F18+H18+L18 -> 10604.65 | P18: =+P6 -> 3865.36 | R18: =+N18+P18 -> 14470.01 | T18: =+T6 -> 6257.93 | V18: =+R18+T18 -> 20727.94 | X18: =+X6 -> 5182.59 | Z18: =+P18+T18+X18 -> 15305.88 | AB18: =+N18+Z18 -> 25910.53 | AD18: =+AD6 -> 4044.21 | AF18: =+AB18+AD18 -> 29954.74 | AH18: =+AH6 -> 5778.35 | AJ18: =+AF18+AH18 -> 35733.09 | AL18: =+AL6 -> 3912 | AN18: =+AD18+AH18+AL18 -> 13734.56 | AP18: =AJ18+AL18 -> 39645.09 | AR18: =+AR6 -> 3486.44 | AT18: =+AP18+AR18 -> 43131.53 | AV18: =+AV6 -> 1080.89 | AX18: =+AT18+AV18 -> 44212.42 | AZ18: =+AZ6 -> 6965.79 | BB18: =+AR18+AV18+AZ18 -> 11533.12 | BD18: =AN18+BB18 -> 25267.68 | BF18: =+AX18+AZ18 -> 51178.21 | BH18: 53987.54 | BJ18: 30649.84 | BL18: 34807.22 | BN18: 33201.15 | BP18: 35268.25 | BR18: 28405.85
B19: EXPORT | C19: MT | F19: 4383.66 | H19: 2929.03 | J19: =+F19+H19 -> 7312.69 | L19: 35.9 | N19: =+F19+H19+L19 -> 7348.59 | P19: 38.94 | R19: =+N19+P19 -> 7387.53 | T19: 158.79 | V19: =+R19+T19 -> 7546.32 | X19: 89.79 | Z19: =+P19+T19+X19 -> 287.52 | AB19: =+N19+Z19 -> 7636.11 | AD19: 2829.49 | AF19: =+AB19+AD19 -> 10465.6 | AH19: 185.19 | AJ19: =+AF19+AH19 -> 10650.79 | AL19: 228.3 | AN19: =+AD19+AH19+AL19 -> 3242.98 | AP19: =AJ19+AL19 -> 10879.09 | AR19: 3186.21 | AT19: =+AP19+AR19 -> 14065.3 | AV19: 0 | AX19: =+AT19+AV19 -> 14065.3 | AZ19: 794.62 | BB19: =+AR19+AV19+AZ19 -> 3980.83 | BD19: =AN19+BB19 -> 7223.81 | BF19: =+AX19+AZ19 -> 14859.92 | BH19: 14221 | BJ19: 58464.99 | BL19: 86754.52 | BN19: 408982.58 | BP19: 662096.98 | BR19: 536611.98
B20: % DIRECT (IPT+CMO DIR+ EXPORT+ PLANT SALES) | C20: % | F20: =+((F16+F18+F15+F19)/F12)*100 -> 72.408111 | H20: =+((H16+H18+H15+H19)/H12)*100 -> 66.392434 | J20: =+((+J15+J16+J18+J19)/J12)*100 -> 69.082365 | L20: =+((L16+L18+L15+L19)/L12)*100 -> 58.226038 | N20: =+((+N15+N16+N18+N19)/N12)*100 -> 65.205417 | P20: =+((P16+P18+P15+P19)/P12)*100 -> 57.77317 | R20: =+((+R15+R16+R18+R19)/R12)*100 -> 63.088873 | T20: =+((T16+T18+T15+T19)/T12)*100 -> 63.864153 | V20: =+((+V15+V16+V18+V19)/V12)*100 -> 63.262194 | X20: =+((X16+X18+X15+X19)/X12)*100 -> 59.893216 | Z20: =+((Z16+Z18+Z15+Z19)/Z12)*100 -> 60.555317 | AB20: =+((AB16+AB18+AB15+AB19)/AB12)*100 -> 62.728782 | AD20: =+((AD16+AD18+AD15+AD19)/AD12)*100 -> 68.745585 | AF20: =+((+AF15+AF16+AF18+AF19)/AF12)*100 -> 63.454359 | AH20: =+((AH16+AH18+AH15+AH19)/AH12)*100 -> 82.522742 | AJ20: =+((+AJ15+AJ16+AJ18+AJ19)/AJ12)*100 -> 64.358812 | AL20: =+((AL16+AL18+AL15+AL19)/AL12)*100 -> 72.454552 | AN20: =+((AN16+AN18+AN15+AN19)/AN12)*100 -> 72.632698 | AP20: =+((+AP15+AP16+AP18+AP19)/AP12)*100 -> 65.269701 | AR20: =+((AR16+AR18+AR15+AR19)/AR12)*100 -> 74.667739 | AT20: =+((+AT15+AT16+AT18+AT19)/AT12)*100 -> 66.39277 | AV20: =+((AV16+AV18+AV15+AV19)/AV12)*100 -> 72.915782 | AX20: =+((+AX15+AX16+AX18+AX19)/AX12)*100 -> 66.955317 | AZ20: =+((AZ16+AZ18+AZ15+AZ19)/AZ12)*100 -> 74.215091 | BB20: =+((BB16+BB18+BB15+BB19)/BB12)*100 -> 74.017557 | BD20: =+((BD16+BD18+BD15+BD19)/BD12)*100 -> 73.471459 | BF20: =+((+BF15+BF16+BF18+BF19)/BF12)*100 -> 67.742423 | BH20: 71.834135 | BJ20: 64.928437 | BL20: 64.796113 | BN20: 70.665579 | BP20: =+((BP16+BP18+BP15+BP19)/BP12)*100 -> 74.478558 | BR20: =+((BR16+BR18+BR15+BR19)/BR12)*100 -> 55.62943
B21: Saleable Steel (Shipping Mode-wise)
B22: RAIL | C22: MT | D22: =+D12 -> 2674798.3 | E22: =+E12 -> 228999.82 | F22: 141481.1 | G22: =+G12 -> 236499.58 | H22: 175451.52 | I22: =+I12 -> 465499.39 | J22: =+F22+H22 -> 316932.62 | K22: =+K12 -> 229000.11 | L22: 185082.04 | M22: =+M12 -> 694499.5 | N22: =+F22+H22+L22 -> 502014.66 | O22: =+O12 -> 231500.14 | P22: 192470.12 | Q22: =+Q12 -> 925999.64 | R22: =+N22+P22 -> 694484.78 | S22: =+S12 -> 231500.14 | T22: 199128.92 | U22: =+U12 -> 1157499.8 | V22: =+R22+T22 -> 893613.7 | W22: =+W12 -> 121299.68 | X22: 164143.06 | Y22: =+Y12 -> 584299.96 | Z22: =+P22+T22+X22 -> 555742.1 | AA22: =+AA12 -> 1278799.5 | AB22: =+N22+Z22 -> 1057756.8 | AC22: =+AC12 -> 226841.09 | AD22: 148158.06 | AE22: =+AE12 -> 1505640.6 | AF22: =+AB22+AD22 -> 1205914.8 | AG22: =+AG12 -> 223180.92 | AH22: 62803.84 | AI22: =+AI12 -> 1728821.5 | AJ22: =+AF22+AH22 -> 1268718.7 | AK22: =+AK12 -> 225210.09 | AL22: 157996.8 | AM22: =+AM12 -> 675232.1 | AN22: =+AD22+AH22+AL22 -> 368958.7 | AO22: =AI22+AK22 -> 1954031.6 | AP22: =AJ22+AL22 -> 1426715.5 | AQ22: =+AQ12 -> 226840.09 | AR22: 197810 | AS22: =+AS12 -> 2180871.7 | AT22: =+AP22+AR22 -> 1624525.5 | AU22: =+AU12 -> 207658 | AV22: 141082.9 | AW22: =+AW12 -> 2388529.7 | AX22: =+AT22+AV22 -> 1765608.4 | AY22: =+AY12 -> 230952.64 | AZ22: 218617.3 | BA22: =+BA12 -> 665450.73 | BB22: =+AR22+AV22+AZ22 -> 557510.2 | BC22: =+BC12 -> 1340682.8 | BD22: =AN22+BB22 -> 926468.9 | BE22: =+BE12 -> 2619482.3 | BF22: =+AX22+AZ22 -> 1984225.7 | BG22: 2409999.5 | BH22: 1898391 | BI22: 2525000 | BJ22: 1848504.3 | BK22: 2410000 | BL22: 1959110.7 | BM22: 2369500.2 | BN22: 1882591.4 | BO22: 2234474.8 | BP22: 1557181.9 | BQ22: =+BQ12 -> 2406999.7 | BR22: 1655527.4
B23: ROAD | C23: MT | F23: 34409.9 | H23: 42014.51 | J23: =+F23+H23 -> 76424.41 | L23: 33422.35 | N23: =+F23+H23+L23 -> 109846.76 | P23: 51153.71 | R23: =+N23+P23 -> 161000.47 | T23: 47189.73 | V23: =+R23+T23 -> 208190.2 | X23: 43122.55 | Z23: =+P23+T23+X23 -> 141465.99 | AB23: =+N23+Z23 -> 251312.75 | AD23: 31352.58 | AF23: =+AB23+AD23 -> 282665.33 | AH23: 11318.37 | AJ23: =+AF23+AH23 -> 293983.7 | AL23: 40121.52 | AN23: =+AD23+AH23+AL23 -> 82792.47 | AP23: =AJ23+AL23 -> 334105.22 | AR23: 41165.9 | AT23: =+AP23+AR23 -> 375271.12 | AV23: 47657.42 | AX23: =+AT23+AV23 -> 422928.54 | AZ23: 47518.8 | BB23: =+AR23+AV23+AZ23 -> 136342.12 | BD23: =AN23+BB23 -> 219134.59 | BF23: =+AX23+AZ23 -> 470447.34 | BH23: 452352.24 | BJ23: 516386.89 | BL23: 338946.25 | BN23: 295664.13 | BP23: 320472.9 | BR23: 394405.54
B24: TOTAL | C24: MT | F24: =SUM(F22:F23) -> 175891 | H24: =SUM(H22:H23) -> 217466.03 | J24: =SUM(J22:J23) -> 393357.03 | L24: =SUM(L22:L23) -> 218504.39 | N24: =SUM(N22:N23) -> 611861.42 | P24: =SUM(P22:P23) -> 243623.83 | R24: =SUM(R22:R23) -> 855485.25 | T24: =SUM(T22:T23) -> 246318.65 | V24: =SUM(V22:V23) -> 1101803.9 | X24: =SUM(X22:X23) -> 207265.61 | Z24: =SUM(Z22:Z23) -> 697208.09 | AB24: =SUM(AB22:AB23) -> 1309069.5 | AD24: =SUM(AD22:AD23) -> 179510.64 | AF24: =SUM(AF22:AF23) -> 1488580.2 | AH24: =SUM(AH22:AH23) -> 74122.21 | AJ24: =SUM(AJ22:AJ23) -> 1562702.4 | AL24: =SUM(AL22:AL23) -> 198118.32 | AN24: =SUM(AN22:AN23) -> 451751.17 | AP24: =SUM(AP22:AP23) -> 1760820.7 | AR24: =SUM(AR22:AR23) -> 238975.9 | AT24: =SUM(AT22:AT23) -> 1999796.6 | AV24: =SUM(AV22:AV23) -> 188740.32 | AX24: =SUM(AX22:AX23) -> 2188536.9 | AZ24: =SUM(AZ22:AZ23) -> 266136.1 | BB24: =SUM(BB22:BB23) -> 693852.32 | BD24: =SUM(BD22:BD23) -> 1145603.5 | BF24: =SUM(BF22:BF23) -> 2454673 | BH24: 2350743.2 | BJ24: 2364891.2 | BL24: 2298057 | BN24: =SUM(BN22:BN23) -> 2178255.5 | BP24: 1877654.8 | BR24: =SUM(BR22:BR23) -> 2049932.9
B25: ROAD CO-EFFICIENT (%) | C25: % | F25: =+F23/F24*100 -> 19.563195 | H25: =+H23/H24*100 -> 19.320034 | J25: =+J23/J24*100 -> 19.428764 | L25: =+L23/L24*100 -> 15.295963 | N25: =+N23/N24*100 -> 17.952882 | P25: =+P23/P24*100 -> 20.997006 | R25: =+R23/R24*100 -> 18.819783 | T25: =+T23/T24*100 -> 19.158001 | V25: =+V23/V24*100 -> 18.895395 | X25: =+X23/X24*100 -> 20.805453 | Z25: =+Z23/Z24*100 -> 20.290354 | AB25: =+AB23/AB24*100 -> 19.197816 | AD25: =+AD23/AD24*100 -> 17.465583 | AF25: =+AF23/AF24*100 -> 18.988922 | AH25: =+AH23/AH24*100 -> 15.269877 | AJ25: =+AJ23/AJ24*100 -> 18.81252 | AL25: =+AL23/AL24*100 -> 20.251292 | AN25: =+AN23/AN24*100 -> 18.327007 | AP25: =+AP23/AP24*100 -> 18.974403 | AR25: =+AR23/AR24*100 -> 17.225963 | AT25: =+AT23/AT24*100 -> 18.765465 | AV25: =+AV23/AV24*100 -> 25.250259 | AX25: =+AX23/AX24*100 -> 19.324716 | AZ25: =+AZ23/AZ24*100 -> 17.855075 | BB25: =+BB23/BB24*100 -> 19.65002 | BD25: =+BD23/BD24*100 -> 19.12831 | BF25: =+BF23/BF24*100 -> 19.165377 | BH25: 19.242946 | BJ25: 21.835546 | BL25: 14.749254 | BN25: 13.573438 | BP25: =+BP23/BP24*100 -> 17.067721 | BR25: =+BR23/BR24*100 -> 19.239924
B26: Pig Iron | C26: MT | D26: 14270 | E26: =+'Maj Production Summ'!E26 -> 810 | F26: 3593.88 | G26: =+'Maj Production Summ'!G26 -> 810 | H26: 2497.59 | I26: =+E26+G26 -> 1620 | J26: =+F26+H26 -> 6091.47 | K26: =+'Maj Production Summ'!K26 -> 810 | L26: 996.79 | M26: =+E26+G26+K26 -> 2430 | N26: =+F26+H26+L26 -> 7088.26 | O26: =+'Maj Production Summ'!O26 -> 810 | P26: 900.29 | Q26: =+M26+O26 -> 3240 | R26: =+N26+P26 -> 7988.55 | S26: =+'Maj Production Summ'!S26 -> 810 | T26: 98.82 | U26: =+Q26+S26 -> 4050 | V26: =+R26+T26 -> 8087.37 | W26: =+'Maj Production Summ'!W26 -> 5360 | X26: 199.97 | Y26: =+O26+S26+W26 -> 6980 | Z26: =+P26+T26+X26 -> 1199.08 | AA26: =+M26+Y26 -> 9410 | AB26: =+N26+Z26 -> 8287.34 | AC26: =+'Maj Production Summ'!AC26 -> 342 | AD26: 748.03 | AE26: =+AA26+AC26 -> 9752 | AF26: =+AB26+AD26 -> 9035.37 | AG26: =+'Maj Production Summ'!AG26 -> 342 | AH26: 298.97 | AI26: =+AE26+AG26 -> 10094 | AJ26: =+AF26+AH26 -> 9334.34 | AK26: =+'Maj Production Summ'!AK26 -> 342 | AL26: 499.24 | AM26: =+AC26+AG26+AK26 -> 1026 | AN26: =+AD26+AH26+AL26 -> 1546.24 | AO26: =AI26+AK26 -> 10436 | AP26: =AJ26+AL26 -> 9833.58 | AQ26: =+'Maj Production Summ'!AQ26 -> 342 | AR26: 1595.84 | AS26: =+AO26+AQ26 -> 10778 | AT26: =+AP26+AR26 -> 11429.42 | AU26: =+'Maj Production Summ'!AU26 -> 342 | AV26: 249.07 | AW26: =+AS26+AU26 -> 11120 | AX26: =+AT26+AV26 -> 11678.49 | AY26: =+'Maj Production Summ'!AY26 -> 342 | AZ26: 1297.13 | BA26: =+AQ26+AU26+AY26 -> 1026 | BB26: =+AR26+AV26+AZ26 -> 3142.04 | BC26: =AM26+BA26 -> 2052 | BD26: =AN26+BB26 -> 4688.28 | BE26: =+AW26+AY26 -> 11462 | BF26: =+AX26+AZ26 -> 12975.62 | BG26: 9365 | BH26: 8679.79 | BI26: 20742.204 | BJ26: 7537.1 | BK26: 16929.735 | BL26: 8801.74 | BM26: 19251.635 | BN26: 20488.86 | BO26: 20754.645 | BP26: 80002.18 | BQ26: 29958.272 | BR26: 124050.8
B27: PCIS Plant Sales | C27: MT | D27: =+'Maj Production Summ'!D27 -> 3541.35 | E27: =+'Maj Production Summ'!E27 -> 273.996 | F27: 999.31 | G27: =+'Maj Production Summ'!G27 -> 279.98 | H27: 0 | I27: =+E27+G27 -> 553.976 | J27: =+F27+H27 -> 999.31 | K27: =+'Maj Production Summ'!K27 -> 273.996 | L27: 0 | M27: =+E27+G27+K27 -> 827.972 | N27: =+F27+H27+L27 -> 999.31 | O27: =+'Maj Production Summ'!O27 -> 276.24 | P27: 996.4 | Q27: =+M27+O27 -> 1104.212 | R27: =+N27+P27 -> 1995.71 | S27: =+'Maj Production Summ'!S27 -> 276.24 | T27: 496.32 | U27: =+Q27+S27 -> 1380.452 | V27: =+R27+T27 -> 2492.03 | W27: =+'Maj Production Summ'!W27 -> 498.97 | X27: 335.17 | Y27: =+O27+S27+W27 -> 1051.45 | Z27: =+P27+T27+X27 -> 1827.89 | AA27: =+M27+Y27 -> 1879.422 | AB27: =+N27+Z27 -> 2827.2 | AC27: =+'Maj Production Summ'!AC27 -> 226.1 | AD27: 0 | AE27: =+AA27+AC27 -> 2105.522 | AF27: =+AB27+AD27 -> 2827.2 | AG27: =+'Maj Production Summ'!AG27 -> 220.02 | AH27: 198.57 | AI27: =+AE27+AG27 -> 2325.542 | AJ27: =+AF27+AH27 -> 3025.77 | AK27: =+'Maj Production Summ'!AK27 -> 226.1 | AL27: 298.71 | AM27: =+AC27+AG27+AK27 -> 672.22 | AN27: =+AD27+AH27+AL27 -> 497.28 | AO27: =AI27+AK27 -> 2551.642 | AP27: =AJ27+AL27 -> 3324.48 | AQ27: =+'Maj Production Summ'!AQ27 -> 226.1 | AR27: 499.09 | AS27: =+AO27+AQ27 -> 2777.742 | AT27: =+AP27+AR27 -> 3823.57 | AU27: =+'Maj Production Summ'!AU27 -> 207.1 | AV27: 0 | AW27: =+AS27+AU27 -> 2984.842 | AX27: =+AT27+AV27 -> 3823.57 | AY27: =+'Maj Production Summ'!AY27 -> 226.1 | AZ27: 998.41 | BA27: =+AQ27+AU27+AY27 -> 659.3 | BB27: =+AR27+AV27+AZ27 -> 1497.5 | BC27: =AM27+BA27 -> 1331.52 | BD27: =AN27+BB27 -> 1994.78 | BE27: =+AW27+AY27 -> 3210.942 | BF27: =+AX27+AZ27 -> 4821.98 | BG27: 2831.5 | BH27: 5762.52 | BI27: 2236.752 | BJ27: 5991.84 | BK27: 2057.6 | BL27: 5429.83 | BM27: 2163.56 | BN27: 17862.58 | BO27: 6973.7102 | BP27: 29483.78 | BQ27: 8472.5251 | BR27: 59555.1
B28: Total Pig & Pig Equiv | C28: MT | D28: =SUM(D26:D27) -> 17811.35 | E28: =SUM(E26:E27) -> 1083.996 | F28: =SUM(F26:F27) -> 4593.19 | G28: =SUM(G26:G27) -> 1089.98 | H28: =SUM(H26:H27) -> 2497.59 | I28: =SUM(I26:I27) -> 2173.976 | J28: =SUM(J26:J27) -> 7090.78 | K28: =SUM(K26:K27) -> 1083.996 | ... AO28: =SUM(AO26:AO27) -> 12987.642 | AP28: =AJ28+AL28 -> 13158.06 | AQ28: =SUM(AQ26:AQ27) -> 568.1 | AR28: =SUM(AR26:AR27) -> 2094.93 | AS28: =SUM(AS26:AS27) -> 13555.742 | AT28: =SUM(AT26:AT27) -> 15252.99 | AU28: =SUM(AU26:AU27) -> 549.1 | AV28: =SUM(AV26:AV27) -> 249.07 | AW28: =SUM(AW26:AW27) -> 14104.842 | AX28: =SUM(AX26:AX27) -> 15502.06 | ... BB28: =SUM(BB26:BB27) -> 4639.54 | BC28: =AM28+BA28 -> 3383.52 | BD28: =AN28+BB28 -> 6683.06 | BE28: =SUM(BE26:BE27) -> 14672.942 | BF28: =SUM(BF26:BF27) -> 17797.6 | BG28: 12196.5 | BH28: 14442.31 | BI28: 22978.956 | BJ28: 13528.94 | BK28: 18987.335 | BL28: 14231.57 | BM28: 21415.195 | BN28: 38351.44 | BO28: 27728.355 | BP28: 109485.96 | BQ28: =SUM(BQ26:BQ27) -> 38430.797 | BR28: =SUM(BR26:BR27) -> 183605.9

Sheet Maj Techno Summ
B1: MAJOR TECHNO PARAMETERS 2025-2026
D2: 365 | E2: 30 | F2: 30 | G2: 31 | H2: 31 | I2: =+E2+G2 -> 61 | J2: =+F2+H2 -> 61 | K2: 30 | L2: 30 | M2: =+I2+K2 -> 91 | N2: =+J2+L2 -> 91 | O2: 31 | P2: 31 | Q2: =+M2+O2 -> 122 | R2: =+N2+P2 -> 122 | S2: 31 | T2: 31 | U2: =+Q2+S2 -> 153 | V2: =+R2+T2 -> 153 | W2: 30 | X2: 30 | Y2: =+O2+S2+W2 -> 92 | Z2: =+P2+T2+X2 -> 92 | AA2: =+U2+W2 -> 183 | AB2: =+V2+X2 -> 183 | AC2: 31 | AD2: 31 | AE2: =+AA2+AC2 -> 214 | AF2: =+AB2+AD2 -> 214 | AG2: 30 | AH2: 30 | AI2: =+AE2+AG2 -> 244 | AJ2: =+AF2+AH2 -> 244 | AK2: 31 | AL2: 31 | AM2: =+AC2+AG2+AK2 -> 92 | AN2: =+AD2+AH2+AL2 -> 92 | AO2: =+AI2+AK2 -> 275 | AP2: =+AJ2+AL2 -> 275 | AQ2: 31 | AR2: 31 | AS2: =+AO2+AQ2 -> 306 | AT2: =+AP2+AR2 -> 306 | AU2: 28 | AV2: 28 | AW2: =+AS2+AU2 -> 334 | AX2: =+AT2+AV2 -> 334 | AY2: 31 | AZ2: 31 | BA2: =+AQ2+AU2+AY2 -> 90 | BB2: =+AR2+AV2+AZ2 -> 90 | BC2: =+AM2+BA2 -> 182 | BD2: =+AN2+BB2 -> 182 | BE2: =+AW2+AY2 -> 365 | BF2: =+AX2+AZ2 -> 365 | BO2: 365 | BP2: 365 | BQ2: 366 | BR2: 366 | BS2: 365
B3: ITEM | C3: Unit | D3: 2025-26 Norm | E3: Apr'25 | G3: May'25 | I3: 2M | K3: Jun'25 | M3: QTR-1 | O3: Jul'25 | Q3: 4M | S3: Aug'25 | U3: 5M | W3: Sep'25 | Y3: QTR-2 | AA3: H1 | AC3: Oct'24 | AE3: 7M | AG3: Nov'24 | AI3: 8M | AK3: Dec'24 | AM3: QTR-3 | AO3: 9 M | AQ3: Jan'25 | AS3: 10M | AU3: Feb'25 | AW3: 11M | AY3: Mar'25 | BA3: QTR-4 | BC3: H2 | BE3: 2024-25 | BG3: 2024-25 | BI3: 2023-24 | BK3: 2022-23 | BM3: 2021-22 | BO3: 2020-21 | BQ3: 2019-20 | BS3: 2018-19
E4: ABP | F4: ACT | G4: ABP | H4: ACT | I4: ABP | J4: ACT | K4: ABP | L4: ACT | M4: ABP | N4: ACT | O4: ABP | P4: ACT | Q4: ABP | R4: ACT | S4: ABP | T4: ACT | U4: ABP | V4: ACT | W4: ABP | X4: ACT | Y4: ABP | Z4: ACT | AA4: ABP | AB4: ACT | AC4: ABP | AD4: ACT | AE4: ABP | AF4: ACT | AG4: ABP | AH4: ACT | AI4: ABP | AJ4: ACT | AK4: ABP | AL4: ACT | AM4: ABP | AN4: ACT | AO4: ABP | AP4: ACT | AQ4: ABP | AR4: ACT | AS4: ABP | AT4: ACT | AU4: ABP | AV4: ACT | AW4: ABP | AX4: ACT | AY4: ABP | AZ4: ACT | BA4: ABP | BB4: ACT | BC4: ABP | BD4: ACT | BE4: ABP | BF4: ACT | BG4: ABP | BH4: ACT | BI4: ABP | BJ4: ACT | BK4: ABP | BL4: ACT | BM4: ABP | BN4: ACT | BO4: ABP | BP4: ACT | BQ4: ABP | BR4: ACT | BS4: ACT
B5: B.F.Coke Yield | C5: % | D5: 70 | E5: =+$D$5 -> 70 | F5: =('Maj Production Summ'!F14*100)/('Maj Production Summ'!F10*31.55) -> 70 | G5: =+$D$5 -> 70 | H5: =('Maj Production Summ'!H14*100)/('Maj Production Summ'!H10*31.55) -> 70 | I5: =+$D$5 -> 70 | J5: =('Maj Production Summ'!J14*100)/('Maj Production Summ'!J10*31.55) -> 70 | K5: =+$D$5 -> 70 | L5: =('Maj Production Summ'!L14*100)/('Maj Production Summ'!L10*31.55) -> 70 | M5: =+$D$5 -> 70 | N5: =('Maj Production Summ'!N14*100)/('Maj Production Summ'!N10*31.55) -> 70 | O5: =+$D$5 -> 70 | P5: =('Maj Production Summ'!P14*100)/('Maj Production Summ'!P10*31.55) -> 70 | Q5: =+$D$5 -> 70 | R5: =('Maj Production Summ'!R14*100)/('Maj Production Summ'!R10*31.55) -> 70 | S5: =+$D$5 -> 70 | T5: =('Maj Production Summ'!T14*100)/('Maj Production Summ'!T10*31.55) -> 70 | U5: =+$D$5 -> 70 | V5: =('Maj Production Summ'!V14*100)/('Maj Production Summ'!V10*31.55) -> 70 | W5: =+$D$5 -> 70 | X5: =('Maj Production Summ'!X14*100)/('Maj Production Summ'!X10*31.55) -> 69.492954 | Y5: =+$D$5 -> 70 | Z5: =('Maj Production Summ'!Z14*100)/('Maj Production Summ'!Z10*31.55) -> 69.834649 | AA5: =+$D$5 -> 70 | AB5: =('Maj Production Summ'!AB14*100)/('Maj Production Summ'!AB10*31.55) -> 69.916419 | AC5: =+$D$5 -> 70 | AD5: =('Maj Production Summ'!AD14*100)/('Maj Production Summ'!AD10*31.55) -> 70.453746 | AE5: =+$D$5 -> 70 | AF5: =('Maj Production Summ'!AF14*100)/('Maj Production Summ'!AF10*31.55) -> 69.993994 | AG5: =+$D$5 -> 70 | AH5: =('Maj Production Summ'!AH14*100)/('Maj Production Summ'!AH10*31.55) -> 70.49 | AI5: =+$D$5 -> 70 | AJ5: =('Maj Production Summ'!AJ14*100)/('Maj Production Summ'!AJ10*31.55) -> 70.052696 | AK5: =+$D$5 -> 70 | AL5: =('Maj Production Summ'!AL14*100)/('Maj Production Summ'!AL10*31.55) -> 70.01 | AM5: =+$D$5 -> 70 | AN5: =('Maj Production Summ'!AN14*100)/('Maj Production Summ'!AN10*31.55) -> 70.313108 | AO5: =+$D$5 -> 70 | AP5: =('Maj Production Summ'!AP14*100)/('Maj Production Summ'!AP10*31.55) -> 70.047847 | AQ5: =+$D$5 -> 70 | AR5: =('Maj Production Summ'!AR14*100)/('Maj Production Summ'!AR10*31.55) -> 70.595 | AS5: =+$D$5 -> 70 | AT5: =('Maj Production Summ'!AT14*100)/('Maj Production Summ'!AT10*31.55) -> 70.103651 | AU5: =+$D$5 -> 70 | AV5: =('Maj Production Summ'!AV14*100)/('Maj Production Summ'!AV10*31.55) -> 70.5 | AW5: =+$D$5 -> 70 | AX5: =('Maj Production Summ'!AX14*100)/('Maj Production Summ'!AX10*31.55) -> 70.137055 | AY5: =+$D$5 -> 70 | AZ5: =('Maj Production Summ'!AZ14*100)/('Maj Production Summ'!AZ10*31.55) -> 70.5 | BA5: =+$D$5 -> 70 | BB5: =('Maj Production Summ'!BB14*100)/('Maj Production Summ'!BB10*31.55) -> 70.532713 | BC5: =+$D$5 -> 70 | BD5: =('Maj Production Summ'!BD14*100)/('Maj Production Summ'!BD10*31.55) -> 70.422664 | BE5: =+$D$5 -> 70 | BF5: =('Maj Production Summ'!BF14*100)/('Maj Production Summ'!BF10*31.55) -> 70.168104 | BG5: 70 | BH5: 70.341275 | BI5: 69.5 | BJ5: 69.398029 | BK5: 69.5 | BL5: 69.459875 | BM5: 70.500003 | BN5: 69.798394 | BO5: 70.999787 | BP5: 72.813877 | BQ5: 66.5 | BR5: 67.48567 | BS5: 67.015011
B6: ICC in Coal Blend
B7: (COB#10) | C7: % | D7: 92 | E7: =+$D$7 -> 92 | F7: ='COKE OVENS'!F149 -> 89.466617 | G7: =+$D$7 -> 92 | H7: ='COKE OVENS'!H149 -> 91.225794 | I7: =+$D$7 -> 92 | J7: ='COKE OVENS'!J149 -> 90.36249 | K7: =+$D$7 -> 92 | L7: ='COKE OVENS'!L149 -> 90.5 | M7: =+$D$7 -> 92 | N7: ='COKE OVENS'!N149 -> 90.407402 | O7: =+$D$7 -> 92 | P7: ='COKE OVENS'!P149 -> 92 | Q7: =+$D$7 -> 92 | R7: ='COKE OVENS'!R149 -> 90.807241 | S7: =+$D$7 -> 92 | T7: ='COKE OVENS'!T149 -> 90 | U7: =+$D$7 -> 92 | V7: ='COKE OVENS'!V149 -> 90.641762 | W7: =+$D$7 -> 92 | X7: ='COKE OVENS'!X149 -> 89.999963 | Y7: =+$D$7 -> 92 | Z7: ='COKE OVENS'!Z149 -> 90.66203 | AA7: =+$D$7 -> 92 | AB7: ='COKE OVENS'!AB149 -> 90.535518 | AC7: =+$D$7 -> 92 | AD7: ='COKE OVENS'!AD149 -> 92.000348 | AE7: =+$D$7 -> 92 | AF7: ='COKE OVENS'!AF149 -> 90.749876 | AG7: =+$D$7 -> 92 | AH7: ='COKE OVENS'!AH149 -> 90.270086 | AI7: =+$D$7 -> 92 | AJ7: ='COKE OVENS'!AJ149 -> 90.692444 | AK7: =+$D$7 -> 92 | AL7: ='COKE OVENS'!AL149 -> 91.999923 | AM7: =+$D$7 -> 92 | AN7: ='COKE OVENS'!AN149 -> 91.450919 | AO7: =+$D$7 -> 92 | AP7: ='COKE OVENS'!AP149 -> 90.841372 | AQ7: =+$D$7 -> 92 | AR7: ='COKE OVENS'!AR149 -> 91.999923 | AS7: =+$D$7 -> 92 | AT7: ='COKE OVENS'!AT149 -> 90.959842 | AU7: =+$D$7 -> 92 | AV7: ='COKE OVENS'!AV149 -> 89.850746 | AW7: =+$D$7 -> 92 | AX7: ='COKE OVENS'!AX149 -> 90.87003 | AY7: =+$D$7 -> 92 | AZ7: ='COKE OVENS'!AZ149 -> 88.356132 | BA7: =+$D$7 -> 92 | BB7: ='COKE OVENS'!BB149 -> 90.115171 | BC7: =+$D$7 -> 92 | BD7: ='COKE OVENS'!BD149 -> 90.798146 | BE7: =+$D$7 -> 92 | BF7: ='COKE OVENS'!BF149 -> 90.665596 | BG7: 95 | BH7: 92.468484 | BI7: 92 | BJ7: 90.939873 | BK7: 92 | BL7: 89.651306 | BM7: 95 | BN7: 93.865972 | BO7: 94.377235 | BP7: 94.02333 | BQ7: 90 | BR7: 91.425995 | BS7: 91.808306
B8: (COB#11) | C8: % | D8: 97 | E8: =+$D$8 -> 97 | F8: ='COKE OVENS'!F174 -> 94.592173 | G8: =+$D$8 -> 97 | H8: ='COKE OVENS'!H174 -> 94.999998 | I8: =+$D$8 -> 97 | J8: ='COKE OVENS'!J174 -> 94.79983 | K8: =+$D$8 -> 97 | L8: ='COKE OVENS'!L174 -> 95 | M8: =+$D$8 -> 97 | N8: ='COKE OVENS'!N174 -> 94.866351 | O8: =+$D$8 -> 97 | P8: ='COKE OVENS'!P174 -> 95.000001 | Q8: =+$D$8 -> 97 | R8: ='COKE OVENS'!R174 -> 94.900652 | S8: =+$D$8 -> 97 | T8: ='COKE OVENS'!T174 -> 95 | U8: =+$D$8 -> 97 | V8: ='COKE OVENS'!V174 -> 94.920863 | W8: =+$D$8 -> 97 | X8: ='COKE OVENS'!X174 -> 95 | Y8: =+$D$8 -> 97 | Z8: ='COKE OVENS'!Z174 -> 95 | AA8: =+$D$8 -> 97 | AB8: ='COKE OVENS'!AB174 -> 94.933908 | AC8: =+$D$8 -> 97 | AD8: ='COKE OVENS'!AD174 -> 97.142521 | AE8: =+$D$8 -> 97 | AF8: ='COKE OVENS'!AF174 -> 95.266138 | AG8: =+$D$8 -> 97 | AH8: ='COKE OVENS'!AH174 -> 95.492104 | AI8: =+$D$8 -> 97 | AJ8: ='COKE OVENS'!AJ174 -> 95.29388 | AK8: =+$D$8 -> 97 | AL8: ='COKE OVENS'!AL174 -> 97.075494 | AM8: =+$D$8 -> 97 | AN8: ='COKE OVENS'!AN174 -> 96.593022 | AO8: =+$D$8 -> 97 | AP8: ='COKE OVENS'!AP174 -> 95.498637 | AQ8: =+$D$8 -> 97 | AR8: ='COKE OVENS'!AR174 -> 96.999996 | AS8: =+$D$8 -> 97 | AT8: ='COKE OVENS'!AT174 -> 95.649896 | AU8: =+$D$8 -> 97 | AV8: ='COKE OVENS'!AV174 -> 97.000003 | AW8: =+$D$8 -> 97 | AX8: ='COKE OVENS'!AX174 -> 95.762411 | AY8: =+$D$8 -> 97 | AZ8: ='COKE OVENS'!AZ174 -> 95.11945 | BA8: =+$D$8 -> 97 | BB8: ='COKE OVENS'!BB174 -> 96.375124 | BC8: =+$D$8 -> 97 | BD8: ='COKE OVENS'!BD174 -> 96.487571 | BE8: =+$D$8 -> 97 | BF8: ='COKE OVENS'!BF174 -> 95.710716 | BG8: 100 | BH8: 97.818139 | BI8: 94 | BJ8: 93.889004 | BK8: 94 | BL8: 92.198587 | BM8: 95 | BN8: 94.753433 | BO8: 94.836589 | BP8: 95.080613 | BQ8: 90 | BR8: 96.370935 | BS8: 94.117213
B9: Overall ICC in Blend | C9: % | D9: 95.32229 | E9: =+$D$9 -> 95.32229 | F9: ='COKE OVENS'!F215 -> 92.782624 | G9: =+$D$9 -> 95.32229 | H9: ='COKE OVENS'!H215 -> 93.667282 | I9: =+$D$9 -> 95.32229 | J9: ='COKE OVENS'!J215 -> 93.233099 | K9: =+$D$9 -> 95.32229 | L9: ='COKE OVENS'!L215 -> 93.437619 | M9: =+$D$9 -> 95.32229 | N9: ='COKE OVENS'!N215 -> 93.300655 | O9: =+$D$9 -> 95.32229 | P9: ='COKE OVENS'!P215 -> 93.966668 | Q9: =+$D$9 -> 95.32229 | R9: ='COKE OVENS'!R215 -> 93.470286 | S9: =+$D$9 -> 95.32229 | T9: ='COKE OVENS'!T215 -> 93.241945 | U9: =+$D$9 -> 95.32229 | V9: ='COKE OVENS'!V215 -> 93.423709 | W9: =+$D$9 -> 95.32229 | X9: ='COKE OVENS'!X215 -> 93.24483 | Y9: =+$D$9 -> 95.32229 | Z9: ='COKE OVENS'!Z215 -> 93.485973 | AA9: =+$D$9 -> 95.32229 | AB9: ='COKE OVENS'!AB215 -> 93.394179 | AC9: =+$D$9 -> 95.32229 | AD9: ='COKE OVENS'!AD215 -> 95.380088 | AE9: =+$D$9 -> 95.32229 | AF9: ='COKE OVENS'!AF215 -> 93.690075 | AG9: =+$D$9 -> 95.32229 | AH9: ='COKE OVENS'!AH215 -> 93.703754 | AI9: =+$D$9 -> 95.32229 | AJ9: ='COKE OVENS'!AJ215 -> 93.69174 | AK9: =+$D$9 -> 95.32229 | AL9: ='COKE OVENS'!AL215 -> 95.319884 | AM9: =+$D$9 -> 95.32229 | AN9: ='COKE OVENS'!AN215 -> 94.825575 | AO9: =+$D$9 -> 95.32229 | AP9: ='COKE OVENS'!AP215 -> 93.87828 | AQ9: =+$D$9 -> 95.32229 | AR9: ='COKE OVENS'!AR215 -> 95.241553 | AS9: =+$D$9 -> 95.32229 | AT9: ='COKE OVENS'!AT215 -> 94.016343 | AU9: =+$D$9 -> 95.32229 | AV9: ='COKE OVENS'!AV215 -> 94.560451 | AW9: =+$D$9 -> 95.32229 | AX9: ='COKE OVENS'!AX215 -> 94.061242 | AY9: =+$D$9 -> 95.32229 | AZ9: ='COKE OVENS'!AZ215 -> 92.748692 | BA9: =+$D$9 -> 95.32229 | BB9: ='COKE OVENS'!BB215 -> 94.196516 | BC9: =+$D$9 -> 95.32229 | BD9: ='COKE OVENS'!BD215 -> 94.520112 | BE9: =+$D$9 -> 95.32229 | BF9: ='COKE OVENS'!BF215 -> 93.955291 | BG9: 98.275343 | BH9: 95.930698 | BI9: 93.289716 | BJ9: 92.83339 | BK9: 93.294359 | BL9: 91.262624 | BM9: 95 | BN9: 94.439237 | BO9: 94.673168 | BP9: 94.71202 | BQ9: 90 | BR9: 94.617133 | BS9: 93.297278
B10: BF Coke Rate | C10: Kg/ THM | D10: 356.24 | E10: 356 | F10: =+('B-FCE'!F23/'Maj Production Summ'!F$17)*1000 -> 347.96952 | G10: 356 | H10: =+('B-FCE'!H23/'Maj Production Summ'!H$17)*1000 -> 345.97012 | I10: =+('B-FCE'!I23/'Maj Production Summ'!I$17)*1000 -> 356 | J10: =+('B-FCE'!J23/'Maj Production Summ'!J$17)*1000 -> 346.9084 | K10: 356 | L10: =+('B-FCE'!L23/'Maj Production Summ'!L$17)*1000 -> 348.40699 | M10: =+('B-FCE'!M23/'Maj Production Summ'!M$17)*1000 -> 356 | N10: =+('B-FCE'!N23/'Maj Production Summ'!N$17)*1000 -> 347.43557 | O10: 356 | P10: =+('B-FCE'!P23/'Maj Production Summ'!P$17)*1000 -> 362.56962 | Q10: =+('B-FCE'!Q23/'Maj Production Summ'!Q$17)*1000 -> 356 | R10: =+('B-FCE'!R23/'Maj Production Summ'!R$17)*1000 -> 351.44755 | S10: 356 | T10: =+('B-FCE'!T23/'Maj Production Summ'!T$17)*1000 -> 365.93798 | U10: =+('B-FCE'!U23/'Maj Production Summ'!U$17)*1000 -> 356 | V10: =+('B-FCE'!V23/'Maj Production Summ'!V$17)*1000 -> 354.34923 | W10: 383 | X10: =+('B-FCE'!X23/'Maj Production Summ'!X$17)*1000 -> 390.38903 | Y10: =+('B-FCE'!Y23/'Maj Production Summ'!Y$17)*1000 -> 361.81538 | Z10: =+('B-FCE'!Z23/'Maj Production Summ'!Z$17)*1000 -> 372.5362 | AA10: =+('B-FCE'!AA23/'Maj Production Summ'!AA$17)*1000 -> 358.67327 | AB10: =+('B-FCE'!AB23/'Maj Production Summ'!AB$17)*1000 -> 360.16362 | AC10: 362.4 | AD10: =+('B-FCE'!AD23/'Maj Production Summ'!AD$17)*1000 -> 380.55652 | AE10: =+('B-FCE'!AE23/'Maj Production Summ'!AE$17)*1000 -> 359.23317 | AF10: =+('B-FCE'!AF23/'Maj Production Summ'!AF$17)*1000 -> 362.94218 | AG10: 355.3 | AH10: =+('B-FCE'!AH23/'Maj Production Summ'!AH$17)*1000 -> 624.51898 | AI10: =+('B-FCE'!AI23/'Maj Production Summ'!AI$17)*1000 -> 358.73379 | AJ10: =+('B-FCE'!AJ23/'Maj Production Summ'!AJ$17)*1000 -> 364.17187 | AK10: 355.3 | AL10: =+('B-FCE'!AL23/'Maj Production Summ'!AL$17)*1000 -> 366.34425 | AM10: =+('B-FCE'!AM23/'Maj Production Summ'!AM$17)*1000 -> 357.69218 | AN10: =+('B-FCE'!AN23/'Maj Production Summ'!AN$17)*1000 -> 377.28919 | AO10: =+('B-FCE'!AO23/'Maj Production Summ'!AO$17)*1000 -> 358.33562 | AP10: =+('B-FCE'!AP23/'Maj Production Summ'!AP$17)*1000 -> 364.44974 | AQ10: 355.3 | AR10: =+('B-FCE'!AR23/'Maj Production Summ'!AR$17)*1000 -> 348.01919 | AS10: =+('B-FCE'!AS23/'Maj Production Summ'!AS$17)*1000 -> 358.0202 | AT10: =+('B-FCE'!AT23/'Maj Production Summ'!AT$17)*1000 -> 362.55724 | AU10: 355.3 | AV10: =+('B-FCE'!AV23/'Maj Production Summ'!AV$17)*1000 -> 342.24192 | AW10: =+('B-FCE'!AW23/'Maj Production Summ'!AW$17)*1000 -> 357.78757 | AX10: =+('B-FCE'!AX23/'Maj Production Summ'!AX$17)*1000 -> 360.62005 | AY10: 355.3 | AZ10: =+('B-FCE'!AZ23/'Maj Production Summ'!AZ$17)*1000 -> 339.29314 | BA10: =+('B-FCE'!BA23/'Maj Production Summ'!BA$17)*1000 -> 355.3 | BB10: =+('B-FCE'!BB23/'Maj Production Summ'!BB$17)*1000 -> 343.20204 | BC10: =+('B-FCE'!BC23/'Maj Production Summ'!BC$17)*1000 -> 356.50995 | BD10: =+('B-FCE'!BD23/'Maj Production Summ'!BD$17)*1000 -> 356.72767 | BE10: =+('B-FCE'!BE23/'Maj Production Summ'!BE$17)*1000 -> 357.57171 | BF10: =+('B-FCE'!BF23/'Maj Production Summ'!BF$17)*1000 -> 358.59371 | BG10: 360.04562 | BH10: 371.74357 | BI10: 380.42 | BJ10: 390.51224 | BK10: 389.92559 | BL10: 400.04041 | BM10: 377.88521 | BN10: 396.71459 | BO10: 373.87865 | BP10: 423.66105 | BQ10: 370.47898 | BR10: 381.58771 | BS10: 388.39311
B11: Nut Coke rate | C11: Kg/ THM | D11: 28.952542 | E11: 29 | F11: =+('B-FCE'!F24/'Maj Production Summ'!F$17)*1000 -> 28.720759 | G11: 29 | H11: =+('B-FCE'!H24/'Maj Production Summ'!H$17)*1000 -> 29.246391 | I11: =+('B-FCE'!I24/'Maj Production Summ'!I$17)*1000 -> 29 | J11: =+('B-FCE'!J24/'Maj Production Summ'!J$17)*1000 -> 28.999723 | K11: 29 | L11: =+('B-FCE'!L24/'Maj Production Summ'!L$17)*1000 -> 31.876011 | M11: =+('B-FCE'!M24/'Maj Production Summ'!M$17)*1000 -> 29 | N11: =+('B-FCE'!N24/'Maj Production Summ'!N$17)*1000 -> 30.011526 | O11: 29 | P11: =+('B-FCE'!P24/'Maj Production Summ'!P$17)*1000 -> 40.769373 | Q11: =+('B-FCE'!Q24/'Maj Production Summ'!Q$17)*1000 -> 29 | R11: =+('B-FCE'!R24/'Maj Production Summ'!R$17)*1000 -> 32.863395 | S11: 29 | T11: =+('B-FCE'!T24/'Maj Production Summ'!T$17)*1000 -> 37.253344 | U11: =+('B-FCE'!U24/'Maj Production Summ'!U$17)*1000 -> 29 | V11: =+('B-FCE'!V24/'Maj Production Summ'!V$17)*1000 -> 33.742472 | W11: 28 | X11: =+('B-FCE'!X24/'Maj Production Summ'!X$17)*1000 -> 36.73382 | Y11: =+('B-FCE'!Y24/'Maj Production Summ'!Y$17)*1000 -> 28.784615 | Z11: =+('B-FCE'!Z24/'Maj Production Summ'!Z$17)*1000 -> 38.320944 | AA11: =+('B-FCE'!AA24/'Maj Production Summ'!AA$17)*1000 -> 28.90099 | AB11: =+('B-FCE'!AB24/'Maj Production Summ'!AB$17)*1000 -> 34.225074 | AC11: 39 | AD11: =+('B-FCE'!AD24/'Maj Production Summ'!AD$17)*1000 -> 39.767759 | AE11: =+('B-FCE'!AE24/'Maj Production Summ'!AE$17)*1000 -> 30.418269 | AF11: =+('B-FCE'!AF24/'Maj Production Summ'!AF$17)*1000 -> 34.980273 | AG11: 39 | AH11: =+('B-FCE'!AH24/'Maj Production Summ'!AH$17)*1000 -> 14.079452 | AI11: =+('B-FCE'!AI24/'Maj Production Summ'!AI$17)*1000 -> 31.50787 | AJ11: =+('B-FCE'!AJ24/'Maj Production Summ'!AJ$17)*1000 -> 34.882017 | AK11: 39 | AL11: =+('B-FCE'!AL24/'Maj Production Summ'!AL$17)*1000 -> 33.196782 | AM11: =+('B-FCE'!AM24/'Maj Production Summ'!AM$17)*1000 -> 39 | AN11: =+('B-FCE'!AN24/'Maj Production Summ'!AN$17)*1000 -> 35.988654 | AO11: =+('B-FCE'!AO24/'Maj Production Summ'!AO$17)*1000 -> 32.376623 | AP11: =+('B-FCE'!AP24/'Maj Production Summ'!AP$17)*1000 -> 34.666456 | AQ11: 39 | AR11: =+('B-FCE'!AR24/'Maj Production Summ'!AR$17)*1000 -> 30.413521 | AS11: =+('B-FCE'!AS24/'Maj Production Summ'!AS$17)*1000 -> 33.064838 | AT11: =+('B-FCE'!AT24/'Maj Production Summ'!AT$17)*1000 -> 34.176594 | AU11: 39 | AV11: =+('B-FCE'!AV24/'Maj Production Summ'!AV$17)*1000 -> 29.174869 | AW11: =+('B-FCE'!AW24/'Maj Production Summ'!AW$17)*1000 -> 33.572406 | AX11: =+('B-FCE'!AX24/'Maj Production Summ'!AX$17)*1000 -> 33.69965 | AY11: 39 | AZ11: =+('B-FCE'!AZ24/'Maj Production Summ'!AZ$17)*1000 -> 28.136016 | BA11: =+('B-FCE'!BA24/'Maj Production Summ'!BA$17)*1000 -> 39 | BB11: =+('B-FCE'!BB24/'Maj Production Summ'!BB$17)*1000 -> 29.240536 | BC11: =+('B-FCE'!BC24/'Maj Production Summ'!BC$17)*1000 -> 39 | BD11: =+('B-FCE'!BD24/'Maj Production Summ'!BD$17)*1000 -> 31.918159 | BE11: =+('B-FCE'!BE24/'Maj Production Summ'!BE$17)*1000 -> 34.043388 | BF11: =+('B-FCE'!BF24/'Maj Production Summ'!BF$17)*1000 -> 33.171031 | BG11: 38.916226 | BH11: 40.499376 | BI11: 32.204286 | BJ11: 47.260949 | BK11: 30 | BL11: 36.610035 | BM11: 23.751425 | BN11: 37.043769 | BO11: 34.857516 | BP11: 41.208946 | BQ11: 25 | BR11: 44.993877 | BS11: 29.180384
B12: CDI rate | C12: Kg/ THM | D12: 149.66508 | E12: 150 | F12: =+('B-FCE'!F25/'Maj Production Summ'!F$17)*1000 -> 150.90022 | G12: 150 | H12: =+('B-FCE'!H25/'Maj Production Summ'!H$17)*1000 -> 155.93209 | I12: =+('B-FCE'!I25/'Maj Production Summ'!I$17)*1000 -> 150 | J12: =+('B-FCE'!J25/'Maj Production Summ'!J$17)*1000 -> 153.57074 | K12: 150 | L12: =+('B-FCE'!L25/'Maj Production Summ'!L$17)*1000 -> 155.24561 | M12: =+('B-FCE'!M25/'Maj Production Summ'!M$17)*1000 -> 150 | N12: =+('B-FCE'!N25/'Maj Production Summ'!N$17)*1000 -> 154.15991 | O12: 150 | P12: =+('B-FCE'!P25/'Maj Production Summ'!P$17)*1000 -> 142.77674 | Q12: =+('B-FCE'!Q25/'Maj Production Summ'!Q$17)*1000 -> 150 | R12: =+('B-FCE'!R25/'Maj Production Summ'!R$17)*1000 -> 151.14227 | S12: 150 | T12: =+('B-FCE'!T25/'Maj Production Summ'!T$17)*1000 -> 141.84997 | U12: =+('B-FCE'!U25/'Maj Production Summ'!U$17)*1000 -> 150 | V12: =+('B-FCE'!V25/'Maj Production Summ'!V$17)*1000 -> 149.28151 | W12: 121 | X12: =+('B-FCE'!X25/'Maj Production Summ'!X$17)*1000 -> 128.55199 | Y12: =+('B-FCE'!Y25/'Maj Production Summ'!Y$17)*1000 -> 143.75385 | Z12: =+('B-FCE'!Z25/'Maj Production Summ'!Z$17)*1000 -> 137.94406 | AA12: =+('B-FCE'!AA25/'Maj Production Summ'!AA$17)*1000 -> 147.12871 | AB12: =+('B-FCE'!AB25/'Maj Production Summ'!AB$17)*1000 -> 145.93717 | AC12: 146 | AD12: =+('B-FCE'!AD25/'Maj Production Summ'!AD$17)*1000 -> 126.07256 | AE12: =+('B-FCE'!AE25/'Maj Production Summ'!AE$17)*1000 -> 146.95913 | AF12: =+('B-FCE'!AF25/'Maj Production Summ'!AF$17)*1000 -> 143.23058 | AG12: 146 | AH12: =+('B-FCE'!AH25/'Maj Production Summ'!AH$17)*1000 -> 0 | AI12: =+('B-FCE'!AI25/'Maj Production Summ'!AI$17)*1000 -> 146.83736 | AJ12: =+('B-FCE'!AJ25/'Maj Production Summ'!AJ$17)*1000 -> 142.55725 | AK12: 146 | AL12: =+('B-FCE'!AL25/'Maj Production Summ'!AL$17)*1000 -> 138.96212 | AM12: =+('B-FCE'!AM25/'Maj Production Summ'!AM$17)*1000 -> 146 | AN12: =+('B-FCE'!AN25/'Maj Production Summ'!AN$17)*1000 -> 130.59501 | AO12: =+('B-FCE'!AO25/'Maj Production Summ'!AO$17)*1000 -> 146.74026 | AP12: =+('B-FCE'!AP25/'Maj Production Summ'!AP$17)*1000 -> 142.09739 | AQ12: 146 | AR12: =+('B-FCE'!AR25/'Maj Production Summ'!AR$17)*1000 -> 153.6184 | AS12: =+('B-FCE'!AS25/'Maj Production Summ'!AS$17)*1000 -> 146.66334 | AT12: =+('B-FCE'!AT25/'Maj Production Summ'!AT$17)*1000 -> 143.4244 | AU12: 146 | AV12: =+('B-FCE'!AV25/'Maj Production Summ'!AV$17)*1000 -> 156.32761 | AW12: =+('B-FCE'!AW25/'Maj Production Summ'!AW$17)*1000 -> 146.60661 | AX12: =+('B-FCE'!AX25/'Maj Production Summ'!AX$17)*1000 -> 144.6548 | AY12: 146 | AZ12: =+('B-FCE'!AZ25/'Maj Production Summ'!AZ$17)*1000 -> 158.53603 | BA12: =+('B-FCE'!BA25/'Maj Production Summ'!BA$17)*1000 -> 146 | BB12: =+('B-FCE'!BB25/'Maj Production Summ'!BB$17)*1000 -> 156.16199 | BC12: =+('B-FCE'!BC25/'Maj Production Summ'!BC$17)*1000 -> 146 | BD12: =+('B-FCE'!BD25/'Maj Production Summ'!BD$17)*1000 -> 146.01713 | BE12: =+('B-FCE'!BE25/'Maj Production Summ'!BE$17)*1000 -> 146.55397 | BF12: =+('B-FCE'!BF25/'Maj Production Summ'!BF$17)*1000 -> 145.9737 | BG12: 140.90981 | BH12: 134.06434 | BI12: 139.6475 | BJ12: 125.94309 | BK12: 129.64578 | BL12: 122.58808 | BM12: 133.64292 | BN12: 118.07599 | BO12: 128.57732 | BP12: 89.175353 | BQ12: 139.85352 | BR12: 118.98027 | BS12: 123.03826
B13: Total Fuel | C13: Kg/ THM | D13: =SUM(D10:D12) -> 534.85763 | E13: =SUM(E10:E12) -> 535 | F13: =SUM(F10:F12) -> 527.59051 | G13: =SUM(G10:G12) -> 535 | H13: =SUM(H10:H12) -> 531.14861 | I13: =SUM(I10:I12) -> 535 | J13: =SUM(J10:J12) -> 529.47886 | K13: =SUM(K10:K12) -> 535 | ... BF13: =SUM(BF10:BF12) -> 537.73844 | BG13: 539.87166 | BH13: 546.30729 | BI13: 552.27179 | BJ13: 563.71628 | BK13: 549.57137 | BL13: 559.23852 | BM13: 535.27955 | BN13: 551.83435 | BO13: 537.31348 | BP13: 554.04535 | BQ13: 535.3325 | BR13: 545.56186 | BS13: 540.61176
B14: BF Productivity | C14: T/M³/Day | D14: 2.4361021 | E14: 2.4471009 | F14: 2.387978 | G14: 2.4406271 | H14: 2.41734 | I14: =+('Maj Production Summ'!I17/3551)/('B-FCE'!E50+'B-FCE'!G50) -> 2.4438091 | J14: =+('Maj Production Summ'!J17/3551)/('B-FCE'!F50+'B-FCE'!H50) -> 2.4034716 | K14: 2.4471009 | L14: 2.4868497 | M14: =+('Maj Production Summ'!M17/3551)/('B-FCE'!E50+'B-FCE'!G50+'B-FCE'!K50) -> 2.4448939 | N14: =+('Maj Production Summ'!N17/3551)/('B-FCE'!F50+'B-FCE'!H50+'B-FCE'!L50) -> 2.4321568 | O14: 2.3936919 | P14: 2.4358636 | Q14: =+('Maj Production Summ'!Q17/3551)/('B-FCE'!M50+'B-FCE'!O50) -> 2.4318764 | R14: =+('Maj Production Summ'!R17/3551)/('B-FCE'!N50+'B-FCE'!P50) -> 2.4331384 | S14: 2.3936919 | T14: 2.3754677 | U14: =+('Maj Production Summ'!U17/3551)/('B-FCE'!Q50+'B-FCE'!S50) -> 2.4241363 | V14: =+('Maj Production Summ'!V17/3551)/('B-FCE'!R50+'B-FCE'!T50) -> 2.4213668 | W14: 2.3168491 | X14: 2.3089599 | Y14: =+('Maj Production Summ'!Y17/3551)/('B-FCE'!P50+'B-FCE'!T50+'B-FCE'!X50) -> 2.0182054 | Z14: =+('Maj Production Summ'!Z17/3551)/('B-FCE'!P50+'B-FCE'!T50+'B-FCE'!X50) -> 2.3743513 | AA14: =+('Maj Production Summ'!AA17/3551)/('B-FCE'!M50+'B-FCE'!Y50) -> 2.4130727 | AB14: =+('Maj Production Summ'!AB17/3551)/('B-FCE'!N50+'B-FCE'!Z50) -> 2.4024973 | AC14: 2.3467568 | AD14: 2.2356327 | AE14: =+('Maj Production Summ'!AE17/3551)/('B-FCE'!AA50+'B-FCE'!AC50) -> 2.4028711 | AF14: =+('Maj Production Summ'!AF17/3551)/('B-FCE'!AB50+'B-FCE'!AD50) -> 2.3783108 | AG14: 2.3499937 | AH14: 0.80694656 | AI14: =+('Maj Production Summ'!AI17/3551)/('B-FCE'!AE50+'B-FCE'!AG50) -> 2.3960259 | AJ14: =+('Maj Production Summ'!AJ17/3551)/('B-FCE'!AF50+'B-FCE'!AH50) -> 2.3567364 | AK14: 2.3467568 | AL14: 2.3560234 | AM14: =+('Maj Production Summ'!AM17/3551)/('B-FCE'!AC50+'B-FCE'!AG50+'B-FCE'!AK50) -> 2.3478115 | AN14: =+('Maj Production Summ'!AN17/3551)/('B-FCE'!AD50+'B-FCE'!AH50+'B-FCE'!AL50) -> 2.2291989 | AO14: =+('Maj Production Summ'!AO17/3551)/('B-FCE'!AK50+'B-FCE'!AI50) -> 2.3902071 | AP14: =+('Maj Production Summ'!AP17/3551)/('B-FCE'!AL50+'B-FCE'!AJ50) -> 2.3566452 | AQ14: 2.3467568 | AR14: 2.4887715 | AS14: =+('Maj Production Summ'!AS17/3551)/('B-FCE'!AO50+'B-FCE'!AQ50) -> 2.3856175 | AT14: =+('Maj Production Summ'!AT17/3551)/('B-FCE'!AP50+'B-FCE'!AR50) -> 2.3711445 | AU14: 2.3467568 | AV14: 2.4820491 | AW14: =+('Maj Production Summ'!AW17/3551)/('B-FCE'!AS50+'B-FCE'!AU50) -> 2.382244 | AX14: =+('Maj Production Summ'!AX17/3551)/('B-FCE'!AT50+'B-FCE'!AV50) -> 2.3812906 | AY14: 2.3467568 | AZ14: 2.4580868 | BA14: =+('Maj Production Summ'!BA17/3551)/('B-FCE'!AQ50+'B-FCE'!AU50+'B-FCE'!AY50) -> 2.3467568 | BB14: =+('Maj Production Summ'!BB17/3551)/('B-FCE'!AR50+'B-FCE'!AV50+'B-FCE'!AZ50) -> 2.4760163 | BC14: =+('Maj Production Summ'!BC17/3551)/('B-FCE'!AM50+'B-FCE'!BA50) -> 2.3472901 | BD14: =+('Maj Production Summ'!BD17/3551)/('B-FCE'!AN50+'B-FCE'!BB50) -> 2.3718147 | BE14: =+('Maj Production Summ'!BE17/3551)/('B-FCE'!AW50+'B-FCE'!AY50) -> 2.3791221 | BF14: =+('Maj Production Summ'!BF17/3551)/('B-FCE'!AX50+'B-FCE'!AZ50) -> 2.3883803 | BG14: 2.3140113 | BH14: 2.2734567 | BI14: 2.2723639 | BJ14: 2.1810142 | BK14: 2.2132463 | BL14: 2.0862545 | BM14: 2.2066158 | BN14: 2.0192263 | BO14: 2.0565754 | BP14: 1.7450413 | BQ14: 2.1585499 | BR14: 2.0057992 | BS14: 1.7419242
B15: Gross Coal to Hot Metal Ratio | C15: Kg/ THM | D15: 871.29178 | E15: 866.91252 | F15: =+'Coal to Hot Metal'!F20 -> 846.11005 | G15: 866.91252 | H15: =+'Coal to Hot Metal'!H20 -> 849.3419 | I15: =+'Coal to Hot Metal'!I20 -> 866.91252 | J15: =+'Coal to Hot Metal'!J20 -> 847.82526 | K15: 866.91252 | L15: =+'Coal to Hot Metal'!L20 -> 861.73356 | M15: =+'Coal to Hot Metal'!M20 -> 866.91252 | N15: =+'Coal to Hot Metal'!N20 -> 852.71784 | O15: 866.91252 | P15: =+'Coal to Hot Metal'!P20 -> 901.89702 | Q15: =+((M15*'Maj Production Summ'!M$17)+('Maj Production Summ'!O$17*O15))/('Maj Production Summ'!Q$17) -> 866.91252 | R15: =+'Coal to Hot Metal'!R20 -> 865.75508 | S15: 866.91252 | T15: =+'Coal to Hot Metal'!T20 -> 901.57952 | U15: =+((Q15*'Maj Production Summ'!Q$17)+('Maj Production Summ'!S$17*S15))/('Maj Production Summ'!U$17) -> 866.91252 | V15: =+'Coal to Hot Metal'!V20 -> 872.92884 | W15: 973.86832 | X15: =+'Coal to Hot Metal'!X20 -> 935.33175 | Y15: =+'Coal to Hot Metal'!Y20 -> 889.94915 | Z15: =+'Coal to Hot Metal'!Z20 -> 912.42944 | AA15: =+((M15*'Maj Production Summ'!M$17)+('Maj Production Summ'!Y$17*Y15))/('Maj Production Summ'!AA$17) -> 877.5022 | AB15: =+'Coal to Hot Metal'!AB20 -> 882.99645 | AC15: 882.68649 | AD15: =+'Coal to Hot Metal'!AD20 -> 891.42548 | AE15: =+((AA15*'Maj Production Summ'!AA$17)+('Maj Production Summ'!AC$17*AC15))/('Maj Production Summ'!AE$17) -> 878.28109 | AF15: =+'Coal to Hot Metal'!AF20 -> 884.14492 | AG15: 869.98416 | AH15: =+'Coal to Hot Metal'!AH20 -> 1821.6844 | AI15: =+((AE15*'Maj Production Summ'!AE$17)+('Maj Production Summ'!AG$17*AG15))/('Maj Production Summ'!AI$17) -> 877.22765 | AJ15: =+'Coal to Hot Metal'!AJ20 -> 888.55234 | AK15: 869.98416 | AL15: =+'Coal to Hot Metal'!AL20 -> 880.90991 | AM15: =+'Coal to Hot Metal'!AM20 -> 883.49537 | AN15: =+'Coal to Hot Metal'!AN20 -> 901.28957 | AO15: =+'Coal to Hot Metal'!AO20 -> 879.56479 | AP15: =+'Coal to Hot Metal'!AP20 -> 887.57478 | AQ15: 869.98416 | AR15: =+'Coal to Hot Metal'!AR20 -> 839.50234 | AS15: =+((AO15*'Maj Production Summ'!AO$17)+('Maj Production Summ'!AQ$17*AQ15))/('Maj Production Summ'!AS$17) -> 878.56929 | AT15: =+'Coal to Hot Metal'!AT20 -> 882.0377 | AU15: 869.98416 | AV15: =+'Coal to Hot Metal'!AV20 -> 833.07785 | AW15: =+((AS15*'Maj Production Summ'!AS$17)+('Maj Production Summ'!AU$17*AU15))/('Maj Production Summ'!AW$17) -> 877.8351 | AX15: =+'Coal to Hot Metal'!AX20 -> 877.36909 | AY15: 869.98416 | AZ15: =+'Coal to Hot Metal'!AZ20 -> 821.74982 | BA15: =+'Coal to Hot Metal'!BA20 -> 879.17042 | BB15: =+'Coal to Hot Metal'!BB20 -> 831.37074 | BC15: =+'Coal to Hot Metal'!BC20 -> 881.35796 | BD15: =+'Coal to Hot Metal'!BD20 -> 859.11422 | BE15: =+'Coal to Hot Metal'!BE20 -> 879.46554 | BF15: =+'Coal to Hot Metal'!BF20 -> 872.08453 | BG15: 879.87436 | BH15: 887.52975 | BI15: 900.75554 | BJ15: 932.03785 | BK15: 910.43802 | BL15: 930.86111 | BM15: 908.3767 | BN15: 935.21205 | BO15: 907.50854 | BP15: 991.44637 | BQ15: 886.42712 | BR15: 931.68363 | BS15: 905.6097
B16: Hot Metal to Crude Steel | C16: Kg/ TCS | D16: 1059 | E16: =+$D$16 -> 1059 | F16: =+(F38/'Maj Production Summ'!F18)*1000 -> 1059.7699 | G16: =+$D$16 -> 1059 | H16: =+(H38/'Maj Production Summ'!H18)*1000 -> 1067.8205 | I16: =+$D$16 -> 1059 | J16: =+(J38/'Maj Production Summ'!J18)*1000 -> 1064.0639 | K16: =+$D$16 -> 1059 | L16: =+(L38/'Maj Production Summ'!L18)*1000 -> 1061.9197 | M16: =+$D$16 -> 1059 | N16: =+(N38/'Maj Production Summ'!N18)*1000 -> 1063.3042 | O16: =+$D$16 -> 1059 | P16: =+(P38/'Maj Production Summ'!P18)*1000 -> 1051.7069 | Q16: =+$D$16 -> 1059 | R16: =+(R38/'Maj Production Summ'!R18)*1000 -> 1060.1772 | S16: =+$D$16 -> 1059 | T16: =+(T38/'Maj Production Summ'!T18)*1000 -> 1060.1658 | U16: =+$D$16 -> 1059 | V16: =+(V38/'Maj Production Summ'!V18)*1000 -> 1060.1749 | W16: =+$D$16 -> 1059 | X16: =+(X38/'Maj Production Summ'!X18)*1000 -> 1063.8153 | Y16: =+$D$16 -> 1059 | Z16: =+(Z38/'Maj Production Summ'!Z18)*1000 -> 1058.3307 | AA16: =+$D$16 -> 1059 | AB16: =+(AB38/'Maj Production Summ'!AB18)*1000 -> 1060.7625 | AC16: =+$D$16 -> 1059 | AD16: =+(AD38/'Maj Production Summ'!AD18)*1000 -> 1061.2178 | AE16: =+$D$16 -> 1059 | AF16: =+(AF38/'Maj Production Summ'!AF18)*1000 -> 1060.8247 | AG16: =$D$16 -> 1059 | AH16: =+(AH38/'Maj Production Summ'!AH18)*1000 -> 1058.3743 | AI16: =+$D$16 -> 1059 | AJ16: =+(AJ38/'Maj Production Summ'!AJ18)*1000 -> 1060.8128 | AK16: =$D$16 -> 1059 | AL16: =+(AL38/'Maj Production Summ'!AL18)*1000 -> 1061.5577 | AM16: =+$D$16 -> 1059 | AN16: =+(AN38/'Maj Production Summ'!AN18)*1000 -> 1061.341 | AO16: =+$D$16 -> 1059 | AP16: =+(AP38/'Maj Production Summ'!AP18)*1000 -> 1060.9064 | AQ16: =$D$16 -> 1059 | AR16: =+(AR38/'Maj Production Summ'!AR18)*1000 -> 1062.3569 | AS16: =+$D$16 -> 1059 | AT16: =+(AT38/'Maj Production Summ'!AT18)*1000 -> 1061.075 | AU16: =$D$16 -> 1059 | AV16: =+(AV38/'Maj Production Summ'!AV18)*1000 -> 1061.4914 | AW16: =+$D$16 -> 1059 | AX16: =+(AX38/'Maj Production Summ'!AX18)*1000 -> 1061.1147 | AY16: =$D$16 -> 1059 | AZ16: =+(AZ38/'Maj Production Summ'!AZ18)*1000 -> 1057.0891 | BA16: =+$D$16 -> 1059 | BB16: =+(BB38/'Maj Production Summ'!BB18)*1000 -> 1060.2854 | BC16: =+$D$16 -> 1059 | BD16: =+(BD38/'Maj Production Summ'!BD18)*1000 -> 1060.7023 | BE16: =+$D$16 -> 1059 | BF16: =+(BF38/'Maj Production Summ'!BF18)*1000 -> 1060.7351 | BG16: 1060 | BH16: 1059.546 | BI16: 1060 | BJ16: 1066.0114 | BK16: 1062 | BL16: 1062.9741 | BM16: 1064.9999 | BN16: 1062.0577 | BO16: 1077.0434 | BP16: 1071.1761 | BQ16: 1065 | BR16: 1093.6626 | BS16: 1078.33
B17: Scrap consumption | C17: Kg/ TCS | D17: 38 | E17: =+$D$17 -> 38 | F17: =+(F39/'Maj Production Summ'!F18)*1000 -> 37.174669 | G17: =+$D$17 -> 38 | H17: =+(H39/'Maj Production Summ'!H18)*1000 -> 28.189893 | I17: =+$D$17 -> 38 | J17: =+(J39/'Maj Production Summ'!J18)*1000 -> 32.382376 | K17: =+$D$17 -> 38 | L17: =+(L39/'Maj Production Summ'!L18)*1000 -> 34.520832 | M17: =+$D$17 -> 38 | N17: =+(N39/'Maj Production Summ'!N18)*1000 -> 33.14006 | O17: =+$D$17 -> 38 | P17: =+(P39/'Maj Production Summ'!P18)*1000 -> 44.526181 | Q17: =+$D$17 -> 38 | R17: =+(R39/'Maj Production Summ'!R18)*1000 -> 36.210117 | S17: =+$D$17 -> 38 | T17: =+(T39/'Maj Production Summ'!T18)*1000 -> 36.183939 | U17: =+$D$17 -> 38 | V17: =+(V39/'Maj Production Summ'!V18)*1000 -> 36.204838 | W17: =+$D$17 -> 38 | X17: =+(X39/'Maj Production Summ'!X18)*1000 -> 34.040565 | Y17: =+$D$17 -> 38 | Z17: =+(Z39/'Maj Production Summ'!Z18)*1000 -> 38.453569 | AA17: =+$D$17 -> 38 | AB17: =+(AB39/'Maj Production Summ'!AB18)*1000 -> 35.855461 | AC17: =+$D$17 -> 38 | AD17: =+(AD39/'Maj Production Summ'!AD18)*1000 -> 34.008139 | AE17: =+$D$17 -> 38 | AF17: =+(AF39/'Maj Production Summ'!AF18)*1000 -> 35.603301 | AG17: =$D$17 -> 38 | AH17: =+(AH39/'Maj Production Summ'!AH18)*1000 -> 41.109011 | AI17: =+$D$17 -> 38 | AJ17: =+(AJ39/'Maj Production Summ'!AJ18)*1000 -> 35.630016 | AK17: =$D$17 -> 38 | AL17: =+(AL39/'Maj Production Summ'!AL18)*1000 -> 37.654621 | AM17: =+$D$17 -> 38 | AN17: =+(AN39/'Maj Production Summ'!AN18)*1000 -> 35.971596 | AO17: =+$D$17 -> 38 | AP17: =+(AP39/'Maj Production Summ'!AP18)*1000 -> 35.884336 | AQ17: =$D$17 -> 38 | AR17: =+(AR39/'Maj Production Summ'!AR18)*1000 -> 37.524386 | AS17: =+$D$17 -> 38 | AT17: =+(AT39/'Maj Production Summ'!AT18)*1000 -> 36.075009 | AU17: =$D$17 -> 38 | AV17: =+(AV39/'Maj Production Summ'!AV18)*1000 -> 35.703807 | AW17: =+$D$17 -> 38 | AX17: =+(AX39/'Maj Production Summ'!AX18)*1000 -> 36.039638 | AY17: =$D$17 -> 38 | AZ17: =+(AZ39/'Maj Production Summ'!AZ18)*1000 -> 38.362239 | BA17: =+(BA39/'Maj Production Summ'!BA18)*1000 -> 38 | BB17: =+(BB39/'Maj Production Summ'!BB18)*1000 -> 37.241241 | BC17: =+(BC39/'Maj Production Summ'!BC18)*1000 -> 38 | BD17: =+(BD39/'Maj Production Summ'!BD18)*1000 -> 36.739845 | BE17: =+(BE39/'Maj Production Summ'!BE18)*1000 -> 38 | BF17: =+(BF39/'Maj Production Summ'!BF18)*1000 -> 36.258659 | BG17: 40 | BH17: 37.680158 | BI17: 40 | BJ17: 34.431041 | BK17: 46 | BL17: 38.506405 | BM17: 50 | BN17: 45.611233 | BO17: 40.465028 | BP17: 41.122433 | BQ17: 50 | BR17: 25.532166 | BS17: 41.130412
B18: TMI | C18: Kg/ TCS | D18: =SUM(D16:D17) -> 1097 | E18: =+$D$18 -> 1097 | F18: =SUM(F16:F17) -> 1096.9446 | G18: =+$D$18 -> 1097 | H18: =SUM(H16:H17) -> 1096.0104 | I18: =+$D$18 -> 1097 | J18: =SUM(J16:J17) -> 1096.4463 | K18: =+$D$18 -> 1097 | L18: =SUM(L16:L17) -> 1096.4405 | M18: =+$D$18 -> 1097 | N18: =SUM(N16:N17) -> 1096.4442 | O18: =+$D$18 -> 1097 | P18: =SUM(P16:P17) -> 1096.2331 | Q18: =+$D$18 -> 1097 | R18: =SUM(R16:R17) -> 1096.3873 | S18: =+$D$18 -> 1097 | T18: =SUM(T16:T17) -> 1096.3497 | U18: =+$D$18 -> 1097 | V18: =SUM(V16:V17) -> 1096.3797 | W18: =+$D$18 -> 1097 | X18: =SUM(X16:X17) -> 1097.8558 | Y18: =+$D$18 -> 1097 | Z18: =SUM(Z16:Z17) -> 1096.7843 | AA18: =+$D$18 -> 1097 | AB18: =SUM(AB16:AB17) -> 1096.618 | AC18: =+$D$18 -> 1097 | AD18: =SUM(AD16:AD17) -> 1095.2259 | AE18: =+$D$18 -> 1097 | AF18: =SUM(AF16:AF17) -> 1096.428 | AG18: =+$D$18 -> 1097 | AH18: =SUM(AH16:AH17) -> 1099.4833 | AI18: =+$D$18 -> 1097 | AJ18: =SUM(AJ16:AJ17) -> 1096.4428 | AK18: =+$D$18 -> 1097 | AL18: =SUM(AL16:AL17) -> 1099.2123 | AM18: =+$D$18 -> 1097 | AN18: =SUM(AN16:AN17) -> 1097.3126 | AO18: =+$D$18 -> 1097 | AP18: =SUM(AP16:AP17) -> 1096.7907 | AQ18: =+$D$18 -> 1097 | AR18: =SUM(AR16:AR17) -> 1099.8813 | AS18: =+$D$18 -> 1097 | AT18: =SUM(AT16:AT17) -> 1097.15 | AU18: =+$D$18 -> 1097 | AV18: =SUM(AV16:AV17) -> 1097.1952 | AW18: =+$D$18 -> 1097 | AX18: =SUM(AX16:AX17) -> 1097.1543 | AY18: =+$D$18 -> 1097 | AZ18: =SUM(AZ16:AZ17) -> 1095.4514 | BA18: =+$D$18 -> 1097 | BB18: =SUM(BB16:BB17) -> 1097.5267 | BC18: =+$D$18 -> 1097 | BD18: =SUM(BD16:BD17) -> 1097.4421 | BE18: =+$D$18 -> 1097 | BF18: =SUM(BF16:BF17) -> 1096.9937 | BG18: 1100 | BH18: 1097.2261 | BI18: 1100 | BJ18: 1100.4424 | BK18: 1108 | BL18: 1101.4805 | BM18: 1114.9999 | BN18: 1107.6689 | BO18: 1117.5084 | BP18: 1112.2985 | BQ18: 1115 | BR18: 1119.1948 | BS18: 1119.4604
B19: Ferro Alloys (FeMn+LCFeMn+SiMn+FeSi) | C19: Kg/ TCS | D19: =+D50+D51+D54 -> 22.017292 | E19: =+$D$19 -> 22.017292 | F19: =F50+F53+F54 -> 20.621196 | G19: =+$D$19 -> 22.017292 | H19: =H50+H53+H54 -> 19.422071 | I19: =+$D$19 -> 22.017292 | J19: =J50+J53+J54 -> 19.981607 | K19: =+$D$19 -> 22.017292 | L19: =L50+L53+L54 -> 19.733624 | M19: =+$D$19 -> 22.017292 | N19: =N50+N53+N54 -> 19.893744 | O19: =+$D$19 -> 22.017292 | P19: =P50+P53+P54 -> 20.120846 | Q19: =+$D$19 -> 22.017292 | R19: =R50+R53+R54 -> 19.954977 | S19: =+$D$19 -> 22.017292 | T19: =T50+T53+T54 -> 19.080809 | U19: =+$D$19 -> 22.017292 | V19: =V50+V53+V54 -> 19.778702 | W19: =+$D$19 -> 22.017292 | X19: =X50+X53+X54 -> 17.254405 | Y19: =+$D$19 -> 22.017292 | Z19: =Z50+Z53+Z54 -> 18.871242 | AA19: =+$D$19 -> 22.017292 | AB19: =AB50+AB53+AB54 -> 19.371207 | AC19: =+$D$19 -> 22.017292 | AD19: =AD50+AD53+AD54 -> 19.519398 | AE19: =+$D$19 -> 22.017292 | AF19: =AF50+AF53+AF54 -> 19.391435 | AG19: =+$D$19 -> 22.017292 | AH19: =AH50+AH53+AH54 -> 17.643352 | AI19: =+$D$19 -> 22.017292 | AJ19: =AJ50+AJ53+AJ54 -> 19.382953 | AK19: =+$D$19 -> 22.017292 | AL19: =AL50+AL53+AL54 -> 21.325501 | AM19: =+$D$19 -> 22.017292 | AN19: =AN50+AN53+AN54 -> 20.399868 | AO19: =+$D$19 -> 22.017292 | AP19: =AP50+AP53+AP54 -> 19.626965 | AQ19: =+$D$19 -> 22.017292 | AR19: =AR50+AR53+AR54 -> 20.886848 | AS19: =+$D$19 -> 22.017292 | AT19: =AT50+AT53+AT54 -> 19.77344 | AU19: =+$D$19 -> 22.017292 | AV19: =AV50+AV53+AV54 -> 20.63752 | AW19: =+$D$19 -> 22.017292 | AX19: =AX50+AX53+AX54 -> 19.855776 | AY19: =+$D$19 -> 22.017292 | AZ19: =AZ50+AZ53+AZ54 -> 20.430955 | BA19: =+$D$19 -> 22.017292 | BB19: =BB50+BB53+BB54 -> 20.653008 | BC19: =+$D$19 -> 22.017292 | BD19: =BD50+BD53+BD54 -> 20.553041 | BE19: =+$D$19 -> 22.017292 | BF19: =BF50+BF53+BF54 -> 19.910015 | BG19: 23 | BH19: 20.403235 | BI19: 21.173677 | BJ19: 22.701786 | BK19: 21 | BL19: 22.930617 | BM19: 21.95779 | BN19: 20.936322 | BO19: 20.938578 | BP19: 20.212673 | BQ19: 21 | BR19: 21.832464 | BS19: 23.120676
B20: Mill yield
B21: WR Mill | C21: % | D21: 96 | E21: =+$D$21 -> 96 | F21: =+WRM!F161 -> 95.81254 | G21: =+$D$21 -> 96 | H21: =+WRM!H161 -> 95.667534 | I21: =+$D$21 -> 96 | J21: =+WRM!J161 -> 95.737477 | K21: =+$D$21 -> 96 | L21: =+WRM!L161 -> 95.27284 | M21: =+$D$21 -> 96 | N21: =+WRM!N161 -> 95.581449 | O21: =+$D$21 -> 96 | P21: =+WRM!P161 -> 95.763066 | Q21: =+$D$21 -> 96 | R21: =+WRM!R161 -> 95.634316 | S21: =+$D$21 -> 96 | T21: =+WRM!T161 -> 95.916693 | U21: =+$D$21 -> 96 | V21: =+WRM!V161 -> 95.688815 | W21: =+$D$21 -> 96 | X21: =+WRM!X161 -> 95.610321 | Y21: =+$D$21 -> 96 | Z21: =+WRM!Z161 -> 95.760446 | AA21: =+$D$21 -> 96 | AB21: =+WRM!AB161 -> 95.675463 | AC21: =+$D$21 -> 96 | AD21: =+WRM!AD161 -> 95.917021 | AE21: =+$D$21 -> 96 | AF21: =+WRM!AF161 -> 89.211338 | AG21: =+$D$21 -> 96 | AH21: =+WRM!AH161 -> 95.589763 | AI21: =+$D$21 -> 96 | AJ21: =+WRM!AJ161 -> 89.631641 | AK21: =+$D$21 -> 96 | AL21: =+WRM!AL161 -> 95.504191 | AM21: =+$D$21 -> 96 | AN21: =+WRM!AN161 -> 95.69292 | AO21: =+$D$21 -> 96 | AP21: =+WRM!AP161 -> 90.304437 | AQ21: =+$D$21 -> 96 | AR21: =+WRM!AR161 -> 96.131408 | AS21: =+$D$21 -> 96 | AT21: =+WRM!AT161 -> 90.914797 | AU21: =+$D$21 -> 96 | AV21: =+WRM!AV161 -> 95.760199 | AW21: =+$D$21 -> 96 | AX21: =+WRM!AX161 -> 91.313232 | AY21: =+$D$21 -> 96 | AZ21: =+WRM!AZ161 -> 95.419404 | BA21: =+$D$21 -> 96 | BB21: =+WRM!BB161 -> 95.761639 | BC21: =+$D$21 -> 96 | BD21: =+WRM!BD161 -> 95.729796 | BE21: =+$D$21 -> 96 | BF21: =+WRM!BF161 -> 91.698437 | BG21: 96 | BH21: 95.818831 | BI21: 96 | BJ21: 95.881785 | BK21: 96 | BL21: 95.450038 | BM21: 96 | BN21: 95.505336 | BO21: 96.222984 | BP21: 94.958654 | BQ21: 96.5 | BR21: 96.195271 | BS21: 96.032659
B22: Bar Mill | C22: % | D22: 96.5 | E22: =+$D$22 -> 96.5 | F22: =+BM!F58 -> 96.340554 | G22: =+$D$22 -> 96.5 | H22: =+BM!H58 -> 96.517504 | I22: =+$D$22 -> 96.5 | J22: =+BM!J58 -> 96.434687 | K22: =+$D$22 -> 96.5 | L22: =+BM!L58 -> 96.41942 | M22: =+$D$22 -> 96.5 | N22: =+BM!N58 -> 96.429498 | O22: =+$D$22 -> 96.5 | P22: =+BM!P58 -> 96.454668 | Q22: =+$D$22 -> 96.5 | R22: =+BM!R58 -> 96.436769 | S22: =+$D$22 -> 96.5 | T22: =+BM!T58 -> 96.32902 | U22: =+$D$22 -> 96.5 | V22: =+BM!V58 -> 96.415277 | W22: =+$D$22 -> 96.5 | X22: =+BM!X58 -> 96.394637 | Y22: =+$D$22 -> 96.5 | Z22: =+BM!Z58 -> 96.395895 | AA22: =+$D$22 -> 96.5 | AB22: =+BM!AB58 -> 96.411829 | AC22: =+$D$22 -> 96.5 | AD22: =+BM!AD58 -> 96.204059 | AE22: =+$D$22 -> 96.5 | AF22: =+BM!AF58 -> 95.549715 | AG22: =+$D$22 -> 96.5 | AH22: =+BM!AH58 -> 94.958487 | AI22: =+$D$22 -> 96.5 | AJ22: =+BM!AJ58 -> 95.546105 | AK22: =+$D$22 -> 96.5 | AL22: =+BM!AL58 -> 96.296098 | AM22: =+$D$22 -> 96.5 | AN22: =+BM!AN58 -> 96.221812 | AO22: =+$D$22 -> 96.5 | AP22: =+BM!AP58 -> 95.634828 | AQ22: =+$D$22 -> 96.5 | AR22: =+BM!AR58 -> 96.148155 | AS22: =+$D$22 -> 96.5 | AT22: =+BM!AT58 -> 95.688829 | AU22: =+$D$22 -> 96.5 | AV22: =+BM!AV58 -> 96.184461 | AW22: =+$D$22 -> 96.5 | AX22: =+BM!AX58 -> 95.733483 | AY22: =+$D$22 -> 96.5 | AZ22: =+BM!AZ58 -> 96.379798 | BA22: =+$D$22 -> 96.5 | BB22: =+BM!BB58 -> 96.243642 | BC22: =+$D$22 -> 96.5 | BD22: =+BM!BD58 -> 96.234989 | BE22: =+$D$22 -> 96.5 | BF22: =+BM!BF58 -> 95.795579 | BG22: 96.5 | BH22: 96.286951 | BI22: 96.5 | BJ22: 96.088708 | BK22: 96.5 | BL22: 95.450022 | BM22: 96.499982 | BN22: 95.423966 | BO22: 96.209843 | BP22: 95.175924 | BQ22: 96.5 | BR22: 96.065593 | BS22: 96.05494
B23: US Mill | C23: % | D23: 94.75 | E23: =+$D$23 -> 94.75 | F23: =+USM!G123 -> 93.760477 | G23: =+$D$23 -> 94.75 | H23: =+USM!I123 -> 93.848373 | I23: =+$D$23 -> 94.75 | J23: =+USM!K123 -> 93.807564 | K23: =+$D$23 -> 94.75 | L23: =+USM!M123 -> 94.300658 | M23: =+$D$23 -> 94.75 | N23: =+USM!O123 -> 93.981855 | O23: =+$D$23 -> 94.75 | P23: =+USM!Q123 -> 94.039737 | Q23: =+$D$23 -> 94.75 | R23: =+USM!S123 -> 93.996744 | S23: =+$D$23 -> 94.75 | T23: =+USM!U123 -> 93.446166 | U23: =+$D$23 -> 94.75 | V23: =+USM!W123 -> 93.904784 | W23: =+$D$23 -> 94.75 | X23: =+USM!Y123 -> 93.998144 | Y23: =+$D$23 -> 94.75 | Z23: =+USM!AA123 -> 93.851594 | AA23: =+$D$23 -> 94.75 | AB23: =+USM!AC123 -> 93.919492 | AC23: =+$D$23 -> 94.75 | AD23: =+USM!AE123 -> 94.095026 | AE23: =+$D$23 -> 94.75 | AF23: =+USM!AG123 -> 88.973342 | AG23: =+$D$23 -> 94.75 | AH23: =+USM!AI123 -> 93.695979 | AI23: =+$D$23 -> 94.75 | AJ23: =+USM!AK123 -> 89.083002 | AK23: =+$D$23 -> 94.75 | AL23: =+USM!AM123 -> 91.062906 | AM23: =+$D$23 -> 94.75 | AN23: =+USM!AO123 -> 92.736312 | AO23: =+$D$23 -> 94.75 | AP23: =+USM!AQ123 -> 89.281621 | AQ23: =+$D$23 -> 94.75 | AR23: =+USM!AS123 -> 93.529416 | AS23: =+$D$23 -> 94.75 | AT23: =+USM!AU123 -> 89.751651 | AU23: =+$D$23 -> 94.75 | AV23: =+USM!AW123 -> 94.085079 | AW23: =+$D$23 -> 94.75 | AX23: =+USM!AY123 -> 90.180862 | AY23: =+$D$23 -> 94.75 | AZ23: =+USM!BA123 -> 94.093152 | BA23: =+$D$23 -> 94.75 | BB23: =+USM!BC123 -> 93.914612 | BC23: =+$D$23 -> 94.75 | BD23: =+USM!BE123 -> 93.483365 | BE23: =+$D$23 -> 94.75 | BF23: =+USM!BG123 -> 90.601646 | BG23: 94.75 | BH23: 93.736035 | BI23: 94.5 | BJ23: 94.168642 | BK23: 94.5 | BL23: 93.371871 | BM23: 95.700065 | BN23: 93.445481 | BO23: 95.699819 | BP23: 95.266762 | BQ23: 95.7 | BR23: 95.476013 | BS23: 95.486333
B24: Sp Energy Consumption | C24: G.cal/TCS | D24: 5.9499751 | E24: 5.9579646 | F24: =EMD!E130 -> 6.0846477 | G24: 5.8950819 | H24: =EMD!G130 -> 5.9791618 | I24: =EMD!H130 -> 5.9260303 | J24: =EMD!I130 -> 6.0300559 | K24: 5.8881875 | L24: =EMD!K130 -> 5.9510025 | M24: =EMD!L130 -> 5.9135486 | N24: =EMD!M130 -> 6.0018291 | O24: 5.9044904 | P24: =EMD!O130 -> 5.923191 | Q24: =+EMD!P130 -> 5.9112818 | R24: =+EMD!Q130 -> 5.9807715 | S24: 5.9110636 | T24: =EMD!S130 -> 6.0281542 | U24: =+EMD!T130 -> 5.9112381 | V24: =+EMD!U130 -> 5.9903261 | W24: 6.4404862 | X24: =EMD!W130 -> 6.2161034 | Y24: =+EMD!X130 -> 6.0185038 | Z24: =+EMD!Y130 -> 6.0504489 | AA24: =+EMD!Z130 -> 5.9615466 | AB24: =+EMD!AA130 -> 6.0267097 | AC24: =EMD!AB130 -> 5.9185019 | AD24: =EMD!AC130 -> 6.0970124 | AE24: =+EMD!AD130 -> 6.0094385 | AF24: =+EMD!AE130 -> 6.1913024 | AG24: =+EMD!AF130 -> 5.8679361 | AH24: =+EMD!AG130 -> 29.436172 | AI24: =+EMD!AH130 -> 5.9889093 | AJ24: =+EMD!AI130 -> 6.3410739 | AK24: =+EMD!AJ130 -> 5.860739 | AL24: =+EMD!AK130 -> 5.9578574 | ... BF24: =+EMD!BE130 -> 6.1600133 | BG24: 5.950002 | BH24: 6.1600133 | BI24: 5.9498029 | BJ24: 6.1924446 | BK24: 5.9892031 | BL24: 6.2012038 | BM24: 5.9854778 | BN24: 6.300637 | BO24: 6.1969869 | BP24: 6.4827566 | BQ24: 5.95 | BR24: 6.1800191 | BS24: 6.3116941
B25: Sp Power Consumption | C25: KwH/TSS | D25: 467.95995 | E25: 461.33365 | F25: =+'POWER DISTRIBUTION'!J18/('Maj Production Summ'!F37+0.25*'Maj Production Summ'!F26) -> 479.82229 | G25: 461.80049 | H25: =+'POWER DISTRIBUTION'!L18/('Maj Production Summ'!H37+0.25*'Maj Production Summ'!H26) -> 454.07152 | I25: =+'POWER DISTRIBUTION'!M18/('Maj Production Summ'!I37+0.25*'Maj Production Summ'!I26) -> 461.57083 | J25: =+'POWER DISTRIBUTION'!N18/('Maj Production Summ'!J37+0.25*'Maj Production Summ'!J26) -> 466.07368 | K25: 461.3094 | L25: =+'POWER DISTRIBUTION'!P18/('Maj Production Summ'!L37+0.25*'Maj Production Summ'!L26) -> 452.69568 | M25: =+'POWER DISTRIBUTION'!Q18/('Maj Production Summ'!M37+0.25*'Maj Production Summ'!M26) -> 461.48463 | N25: =+'POWER DISTRIBUTION'!R18/('Maj Production Summ'!N37+0.25*'Maj Production Summ'!N26) -> 461.42919 | O25: 467.74394 | P25: =+'POWER DISTRIBUTION'!T18/('Maj Production Summ'!P37+0.25*'Maj Production Summ'!P26) -> 442.74265 | Q25: =+'POWER DISTRIBUTION'!U18/('Maj Production Summ'!Q37+0.25*'Maj Production Summ'!Q26) -> 463.04946 | R25: =+'POWER DISTRIBUTION'!V18/('Maj Production Summ'!R37+0.25*'Maj Production Summ'!R26) -> 456.38153 | S25: 467.74394 | T25: =+'POWER DISTRIBUTION'!X18/('Maj Production Summ'!T37+0.25*'Maj Production Summ'!T26) -> 478.60887 | U25: =+'POWER DISTRIBUTION'!Y18/('Maj Production Summ'!U37+0.25*'Maj Production Summ'!U26) -> 463.98836 | V25: =+'POWER DISTRIBUTION'!Z18/('Maj Production Summ'!V37+0.25*'Maj Production Summ'!V26) -> 460.73141 | W25: 583.45256 | X25: =+'POWER DISTRIBUTION'!AB18/('Maj Production Summ'!X37+0.25*'Maj Production Summ'!X26) -> 460.5013 | Y25: =+'POWER DISTRIBUTION'!AC18/('Maj Production Summ'!Y37+0.25*'Maj Production Summ'!Y26) -> 491.95795 | Z25: =+'POWER DISTRIBUTION'!AD18/('Maj Production Summ'!Z37+0.25*'Maj Production Summ'!Z26) -> 459.9873 | AA25: =+'POWER DISTRIBUTION'!AE18/('Maj Production Summ'!AA37+0.25*'Maj Production Summ'!AA26) -> 475.42423 | AB25: =+'POWER DISTRIBUTION'!AF18/('Maj Production Summ'!AB37+0.25*'Maj Production Summ'!AB26) -> 460.6932 | AC25: 473.75976 | AD25: =+'POWER DISTRIBUTION'!AH18/('Maj Production Summ'!AD37+0.25*'Maj Production Summ'!AD26) -> 548.71956 | AE25: =+'POWER DISTRIBUTION'!AI18/('Maj Production Summ'!AE37+0.25*'Maj Production Summ'!AE26) -> 475.17377 | AF25: =+'POWER DISTRIBUTION'!AJ18/('Maj Production Summ'!AF37+0.25*'Maj Production Summ'!AF26) -> 471.45153 | AG25: 466.25573 | AH25: =+'POWER DISTRIBUTION'!AL18/('Maj Production Summ'!AH37+0.25*'Maj Production Summ'!AH26) -> 1065.6856 | AI25: =+'POWER DISTRIBUTION'!AM18/('Maj Production Summ'!AI37+0.25*'Maj Production Summ'!AI26) -> 474.02374 | AJ25: =+'POWER DISTRIBUTION'!AN18/('Maj Production Summ'!AJ37+0.25*'Maj Production Summ'!AJ26) -> 486.85383 | AK25: 477.18949 | AL25: =+'POWER DISTRIBUTION'!AP18/('Maj Production Summ'!AL37+0.25*'Maj Production Summ'!AL26) -> 440.38863 | AM25: =+'POWER DISTRIBUTION'!AQ18/('Maj Production Summ'!AM37+0.25*'Maj Production Summ'!AM26) -> 472.42342 | AN25: =+'POWER DISTRIBUTION'!AR18/('Maj Production Summ'!AN37+0.25*'Maj Production Summ'!AN26) -> 540.56277 | AO25: =+'POWER DISTRIBUTION'!AS18/('Maj Production Summ'!AO37+0.25*'Maj Production Summ'!AO26) -> 474.38826 | AP25: =+'POWER DISTRIBUTION'!AT18/('Maj Production Summ'!AP37+0.25*'Maj Production Summ'!AP26) -> 480.94952 | AQ25: 473.76185 | AR25: =+'POWER DISTRIBUTION'!AV18/('Maj Production Summ'!AR37+0.25*'Maj Production Summ'!AR26) -> 429.41761 | AS25: =+'POWER DISTRIBUTION'!AW18/('Maj Production Summ'!AS37+0.25*'Maj Production Summ'!AS26) -> 474.32327 | AT25: =+'POWER DISTRIBUTION'!AX18/('Maj Production Summ'!AT37+0.25*'Maj Production Summ'!AT26) -> 474.98214 | AU25: 466.39505 | AV25: =+'POWER DISTRIBUTION'!AZ18/('Maj Production Summ'!AV37+0.25*'Maj Production Summ'!AV26) -> 447.46906 | AW25: =+'POWER DISTRIBUTION'!BA18/('Maj Production Summ'!AW37+0.25*'Maj Production Summ'!AW26) -> 473.63451 | AX25: =+'POWER DISTRIBUTION'!BB18/('Maj Production Summ'!AX37+0.25*'Maj Production Summ'!AX26) -> 472.41785 | AY25: 467.63958 | AZ25: =+'POWER DISTRIBUTION'!BD18/('Maj Production Summ'!AZ37+0.25*'Maj Production Summ'!AZ26) -> 432.53356 | BA25: =+'POWER DISTRIBUTION'!BE18/('Maj Production Summ'!BA37+0.25*'Maj Production Summ'!BA26) -> 469.33852 | BB25: =+'POWER DISTRIBUTION'!BF18/('Maj Production Summ'!BB37+0.25*'Maj Production Summ'!BB26) -> 436.01158 | BC25: =+'POWER DISTRIBUTION'!BG18/('Maj Production Summ'!BC37+0.25*'Maj Production Summ'!BC26) -> 470.89222 | BD25: =+'POWER DISTRIBUTION'!BH18/('Maj Production Summ'!BD37+0.25*'Maj Production Summ'!BD26) -> 477.73863 | BE25: =+'POWER DISTRIBUTION'!BI18/('Maj Production Summ'!BE37+0.25*'Maj Production Summ'!BE26) -> 473.10634 | BF25: =+'POWER DISTRIBUTION'!BJ18/('Maj Production Summ'!BF37+0.25*'Maj Production Summ'!BF26) -> 468.53181 | BG25: 498.86963 | BH25: 491.52958 | BI25: 491.86598 | BJ25: 499.12041 | BK25: 499.14523 | BL25: 516.74946 | BM25: 501.08848 | BN25: 528.34198 | BO25: 500.04339 | BP25: 579.80533 | BQ25: 483.423 | BR25: 525.26173 | BS25: 552.03691
C26: KwH/TCS | D26: 452.47632 | E26: 445.94714 | F26: =+'POWER DISTRIBUTION'!J18/'Maj Production Summ'!F18 -> 463.4715 | G26: 446.77103 | H26: =+'POWER DISTRIBUTION'!L18/'Maj Production Summ'!H18 -> 439.53564 | I26: =+'POWER DISTRIBUTION'!M18/'Maj Production Summ'!I18 -> 446.36554 | J26: =+'POWER DISTRIBUTION'!N18/'Maj Production Summ'!J18 -> 450.70461 | K26: 445.92427 | L26: =+'POWER DISTRIBUTION'!P18/'Maj Production Summ'!L18 -> 424.25451 | M26: =+'POWER DISTRIBUTION'!Q18/'Maj Production Summ'!M18 -> 446.22 | N26: =+'POWER DISTRIBUTION'!R18/'Maj Production Summ'!N18 -> 441.33297 | O26: 451.67958 | P26: =+'POWER DISTRIBUTION'!T18/'Maj Production Summ'!P18 -> 424.51702 | Q26: =+'POWER DISTRIBUTION'!U18/'Maj Production Summ'!Q18 -> 447.58624 | R26: =+'POWER DISTRIBUTION'!V18/'Maj Production Summ'!R18 -> 436.79886 | S26: 451.67958 | T26: =+'POWER DISTRIBUTION'!X18/'Maj Production Summ'!T18 -> 441.26841 | U26: =+'POWER DISTRIBUTION'!Y18/'Maj Production Summ'!U18 -> 448.40555 | V26: =+'POWER DISTRIBUTION'!Z18/'Maj Production Summ'!V18 -> 437.70014 | W26: 568.25163 | X26: =+'POWER DISTRIBUTION'!AB18/'Maj Production Summ'!X18 -> 452.48637 | Y26: =+'POWER DISTRIBUTION'!AC18/'Maj Production Summ'!Y18 -> 475.90977 | Z26: =+'POWER DISTRIBUTION'!AD18/'Maj Production Summ'!Z18 -> 438.89498 | AA26: =+'POWER DISTRIBUTION'!AE18/'Maj Production Summ'!AA18 -> 459.7977 | AB26: =+'POWER DISTRIBUTION'!AF18/'Maj Production Summ'!AB18 -> 440.08707 | AC26: 456.53077 | AD26: =+'POWER DISTRIBUTION'!AH18/'Maj Production Summ'!AD18 -> 461.69014 | AE26: =+'POWER DISTRIBUTION'!AI18/'Maj Production Summ'!AE18 -> 459.30459 | AF26: =+'POWER DISTRIBUTION'!AJ18/'Maj Production Summ'!AF18 -> 443.0359 | AG26: 456.68902 | AH26: =+'POWER DISTRIBUTION'!AL18/'Maj Production Summ'!AH18 -> 5465.2041 | AI26: =+'POWER DISTRIBUTION'!AM18/'Maj Production Summ'!AI18 -> 458.97117 | AJ26: =+'POWER DISTRIBUTION'!AN18/'Maj Production Summ'!AJ18 -> 467.40484 | AK26: 456.53077 | AL26: =+'POWER DISTRIBUTION'!AP18/'Maj Production Summ'!AL18 -> 428.40644 | AM26: =+'POWER DISTRIBUTION'!AQ18/'Maj Production Summ'!AM18 -> 456.58238 | AN26: =+'POWER DISTRIBUTION'!AR18/'Maj Production Summ'!AN18 -> 530.25646 | AO26: =+'POWER DISTRIBUTION'!AS18/'Maj Production Summ'!AO18 -> 458.68718 | AP26: =+'POWER DISTRIBUTION'!AT18/'Maj Production Summ'!AP18 -> 462.50608 | AQ26: 456.53077 | AR26: =+'POWER DISTRIBUTION'!AV18/'Maj Production Summ'!AR18 -> 411.09963 | AS26: =+'POWER DISTRIBUTION'!AW18/'Maj Production Summ'!AS18 -> 458.46239 | AT26: =+'POWER DISTRIBUTION'!AX18/'Maj Production Summ'!AT18 -> 456.52955 | AU26: 457.23431 | AV26: =+'POWER DISTRIBUTION'!AZ18/'Maj Production Summ'!AV18 -> 419.70726 | AW26: =+'POWER DISTRIBUTION'!BA18/'Maj Production Summ'!AW18 -> 458.35708 | AX26: =+'POWER DISTRIBUTION'!BB18/'Maj Production Summ'!AX18 -> 453.02084 | AY26: 458.7979 | AZ26: =+'POWER DISTRIBUTION'!BD18/'Maj Production Summ'!AZ18 -> 430.04094 | BA26: =+'POWER DISTRIBUTION'!BE18/'Maj Production Summ'!BA18 -> 457.53089 | BB26: =+'POWER DISTRIBUTION'!BF18/'Maj Production Summ'!BB18 -> 420.26723 | BC26: =+'POWER DISTRIBUTION'!BG18/'Maj Production Summ'!BC18 -> 457.05113 | BD26: =+'POWER DISTRIBUTION'!BH18/'Maj Production Summ'!BD18 -> 463.70311 | BE26: =+'POWER DISTRIBUTION'!BI18/'Maj Production Summ'!BE18 -> 458.39543 | BF26: =+'POWER DISTRIBUTION'!BJ18/'Maj Production Summ'!BF18 -> 450.85383 | BG26: 483.40224 | BH26: 471.62787 | BI26: 475.02939 | BJ26: 476.24946 | BK26: 482.32053 | BL26: 494.76974 | BM26: 486.14726 | BN26: 514.38476 | BO26: 487.74658 | BP26: 580.20286 | BQ26: 448.29125 | BR26: 538.52024 | BS26: 565.51994
B27: Sp Water Consumption | C27: M³/TCS | D27: 2.85 | E27: =+$D$27 -> 2.85 | F27: 2.98 | G27: =+$D$27 -> 2.85 | H27: 2.97 | I27: =+$D$27 -> 2.85 | J27: =+((F27*F32)+(H27*H32))/J32 -> 2.9746662 | K27: =+$D$27 -> 2.85 | L27: 2.96 | M27: =+$D$27 -> 2.85 | N27: =+((F32*F27)+(H32*H27)+(L32*L27))/N32 -> 2.9694698 | O27: =+$D$27 -> 2.85 | P27: 2.9 | Q27: =+$D$27 -> 2.85 | R27: =+(((N27*N32)+(P27*P32))/R32) -> 2.9507385 | S27: =+$D$27 -> 2.85 | T27: 2.9 | U27: =+$D$27 -> 2.85 | V27: =+(((R27*R32)+(T27*T32))/V32) -> 2.9405072 | W27: =+$D$27 -> 2.85 | X27: 2.905 | Y27: =+$D$27 -> 2.85 | Z27: =+((P32*P27)+(T32*T27)+(X32*X27))/Z32 -> 2.9015794 | AA27: =+$D$27 -> 2.85 | AB27: =+((N27*N32)+(Z27*Z32))/AB32 -> 2.9347753 | AC27: =+$D$27 -> 2.85 | AD27: 2.99 | AE27: =+$D$27 -> 2.85 | AF27: =+(((AB27*AB32)+(AD27*AD32))/AF32) -> 2.9423135 | AG27: =+$D$27 -> 2.85 | AH27: 3.19 | AI27: =+$D$27 -> 2.85 | AJ27: =+(((AF27*AF32)+(AH27*AH32))/AJ32) -> 2.9435153 | AK27: =+$D$27 -> 2.85 | AL27: 2.87 | AM27: =+$D$27 -> 2.85 | AN27: =+((AD32*AD27)+(AH32*AH27)+(AL32*AL27))/AN32 -> 2.9327862 | AO27: =+$D$27 -> 2.85 | AP27: =+(((AL27*AL32)+(AJ27*AJ32))/AP32) -> 2.9342807 | AQ27: =+$D$27 -> 2.85 | AR27: 2.87 | AS27: =+$D$27 -> 2.85 | AT27: =+(((AP27*AP32)+(AR27*AR32))/AT32) -> 2.9268074 | AU27: =+$D$27 -> 2.85 | AV27: 2.86 | AW27: =+$D$27 -> 2.85 | AX27: =+(((AT27*AT32)+(AV27*AV32))/AX32) -> 2.9204415 | AY27: =+$D$27 -> 2.85 | AZ27: 2.88 | BA27: =+$D$27 -> 2.85 | BB27: =+((AR27*AR32)+(AV27*AV32)+(AZ27*AZ32))/BB32 -> 2.8702899 | BC27: =+$D$27 -> 2.85 | BD27: =+((AN27*AN32)+(BB27*BB32))/BD32 -> 2.8949703 | BE27: =+$D$27 -> 2.85 | BF27: =+((AX27*AX32)+(AZ27*AZ32))/BF32 -> 2.9166279 | BG27: 2.85 | BH27: 2.9919746 | BI27: 2.85 | BJ27: 3.0828892 | BK27: 3.3 | BL27: 3.0186532 | BM27: 4.3 | BN27: 3.3197104 | BO27: 4.3 | BP27: 5.0407394 | BQ27: 4.6 | BR27: 5.0056729 | BS27: 5.0192042
B28: Sp. CO2 emission | C28: T/TCS | D28: 2.2695882 | E28: =+$D$28 -> 2.2695882 | F28: 2.3 | G28: =+$D$28 -> 2.2695882 | H28: 2.291 | I28: =+$D$28 -> 2.2695882 | J28: =+((F28*F32)+(H28*H32))/J32 -> 2.2951996 | K28: =+$D$28 -> 2.2695882 | L28: 2.31 | M28: =+$D$28 -> 2.2695882 | N28: =+((F32*F28)+(H32*H28)+(L32*L28))/N32 -> 2.3004436 | O28: =+$D$28 -> 2.2695882 | P28: 2.32 | Q28: =+$D$28 -> 2.2695882 | R28: =+((N28*N32)+(P28*P32))/R32 -> 2.3057166 | S28: =+$D$28 -> 2.2695882 | T28: 2.36 | U28: =+$D$28 -> 2.2695882 | V28: =+((R28*R32)+(T28*T32))/V32 -> 2.3166628 | W28: =+$D$28 -> 2.2695882 | X28: 2.42 | Y28: =+$D$28 -> 2.2695882 | Z28: =+((P32*P28)+(T32*T28)+(X32*X28))/Z32 -> 2.3648241 | AA28: =+$D$28 -> 2.2695882 | AB28: =+((N28*N32)+(Z28*Z32))/AB32+0.01 -> 2.3433444 | AC28: =+$D$28 -> 2.2695882 | AD28: 2.36 | AE28: =+$D$28 -> 2.2695882 | AF28: =+((AB28*AB32)+(AD28*AD32))/AF32 -> 2.3456179 | AG28: =+$D$28 -> 2.2695882 | AI28: =+$D$28 -> 2.2695882 | AJ28: 2.45 | AK28: =+$D$28 -> 2.2695882 | AL28: 2.33 | AM28: =+$D$28 -> 2.2695882 | AN28: =+((AD32*AD28)+(AH32*AH28)+(AL32*AL28))/AN32 -> 2.3045713 | AO28: =+$D$28 -> 2.2695882 | AP28: =+((AL28*AL32)+(AJ28*AJ32))/AP32-0.034 -> 2.4009263 | AQ28: =+$D$28 -> 2.2695882 | AR28: 2.29 | AS28: =+$D$28 -> 2.2695882 | AT28: =+((AP28*AP32)+(AR28*AR32))/AT32-0.01 -> 2.3780299 | AU28: =+$D$28 -> 2.2695882 | AV28: 2.29 | AW28: =+$D$28 -> 2.2695882 | AX28: =+((AT28*AT32)+(AV28*AV32))/AX32 -> 2.3696418 | AY28: =+$D$28 -> 2.2695882 | AZ28: 2.29 | BA28: =+$D$28 -> 2.2695882 | BB28: =+((AR28*AR32)+(AV28*AV32)+(AZ28*AZ32))/BB32 -> 2.29 | BC28: =+$D$28 -> 2.2695882 | BD28: =+((AN28*AN32)+(BB28*BB32))/BD32 -> 2.2957544 | BE28: =+$D$28 -> 2.2695882 | BF28: =+((AX28*AX32)+(AZ28*AZ32))/BF32+0.01 -> 2.3721315 | BG28: 2.32 | BH28: 2.3695074 | BI28: 2.375 | BJ28: 2.4275692 | BK28: 2.35 | BL28: 2.4470555 | BM28: 2.45 | BN28: 2.4734992 | BO28: 2.45 | BP28: 2.6211068 | BQ28: 2.456658 | BR28: 2.4355942 | BS28: 2.609953
B29: Sp. PM emissions | C29: kg/TCS | D29: 0.5 | E29: =+$D$29 -> 0.5 | F29: 0.5 | G29: =+$D$29 -> 0.5 | H29: 0.492 | I29: =+$D$29 -> 0.5 | J29: =+((F29*F32)+(H29*H32))/J32 -> 0.49573297 | K29: =+$D$29 -> 0.5 | L29: 0.5 | M29: =+$D$29 -> 0.5 | N29: =+((F32*F29)+(H32*H29)+(L32*L29))/N32 -> 0.49724484 | O29: =+$D$29 -> 0.5 | P29: 0.5 | Q29: =+$D$29 -> 0.5 | R29: =+((N29*N32)+(P29*P32))/R32 -> 0.49798771 | S29: =+$D$29 -> 0.5 | T29: 0.5 | U29: =+$D$29 -> 0.5 | V29: =+((R29*R32)+(T29*T32))/V32 -> 0.49839349 | W29: =+$D$29 -> 0.5 | X29: 0.5 | Y29: =+$D$29 -> 0.5 | Z29: =+((P32*P29)+(T32*T29)+(X32*X29))/Z32 -> 0.5 | AA29: =+$D$29 -> 0.5 | AB29: =+((N29*N32)+(Z29*Z32))/AB32 -> 0.49865283 | AC29: =+$D$29 -> 0.5 | AD29: 0.5 | AE29: =+$D$29 -> 0.5 | AF29: =+((AB29*AB32)+(AD29*AD32))/AF32 -> 0.49883672 | AG29: =+$D$29 -> 0.5 | AI29: =+$D$29 -> 0.5 | AJ29: 0.54 | AK29: =+$D$29 -> 0.5 | AL29: 0.49 | AM29: =+$D$29 -> 0.5 | AN29: =+((AD32*AD29)+(AH32*AH29)+(AL32*AL29))/AN32 -> 0.48641557 | AO29: =+$D$29 -> 0.5 | AP29: =+((AL29*AL32)+(AJ29*AJ32))/AP32-0.01 -> 0.52371927 | AQ29: =+$D$29 -> 0.5 | AR29: 0.46 | AS29: =+$D$29 -> 0.5 | AT29: =+((AP29*AP32)+(AR29*AR32))/AT32 -> 0.51631125 | AU29: =+$D$29 -> 0.5 | AV29: 0.44 | AW29: =+$D$29 -> 0.5 | AX29: =+((AT29*AT32)+(AV29*AV32))/AX32 -> 0.50903973 | AY29: =+$D$29 -> 0.5 | AZ29: 0.49 | BA29: =+$D$29 -> 0.5 | BB29: =+((AR29*AR32)+(AV29*AV32)+(AZ29*AZ32))/BB32 -> 0.46399819 | BC29: =+$D$29 -> 0.5 | BD29: =+((AN29*AN32)+(BB29*BB32))/BD32 -> 0.47285105 | BE29: =+$D$29 -> 0.5 | BF29: =+((AX29*AX32)+(AZ29*AZ32))/BF32-0.01 -> 0.49724428 | BG29: 0.5 | BH29: 0.49588309 | BI29: 0.53 | BJ29: 0.53450495 | BK29: 0.53 | BL29: 0.5280682 | BM29: 0.55 | BN29: 0.53916083 | BO29: 0.55 | BP29: 0.62328215 | BQ29: 0.551124 | BR29: 0.57147495 | BS29: 0.55061804
B30: Labour Productivity | C30: TCS/Man/Year | D30: 789.97408 | E30: =+E36 -> 812.64671 | F30: =+F36 -> 724.01995 | G30: =+G36 -> 814.88252 | H30: =+H36 -> 799.42673 | I30: =+I36 -> 813.75238 | J30: =+J36 -> 762.26284 | K30: =+K36 -> 817.70563 | L30: =+L36 -> 850.75383 | ... AG30: =+AG36 -> 797.75563 | AH30: 30 * | AI30: =+AI36 -> 761.91359 | AJ30: 632* | AK30: =+AK36 -> 799.40216 | AL30: =+AL36 -> 783.42261 | AM30: =+AM36 -> 797.62644 | AN30: =+AN36 -> 523.0789 | AO30: =+AO36 -> 766.06916 | AP30: =+AP36 -> 710.78255 | AQ30: =+AQ36 -> 801.24889 | AR30: =+AR36 -> 812.39513 | ... BF30: =+BF36 -> 737.49728 | BG30: 712.17383 | BH30: 691.16367 | BI30: 729.20664 | BJ30: 695.16315 | BK30: 656.40621 | BL30: 639.11266 | BM30: 615.77607 | BN30: 561.88094 | BO30: 549.90658 | BP30: 459.2495 | BQ30: 562.64319 | BR30: 490.34382 | BS30: 421.02863
B31: Average Manpower (Works) | C31: Nos. | D31: 3515.5 | E31: 3556 | F31: 3518 | G31: 3541 | H31: 3507 | I31: =+AVERAGE(E31,G31) -> 3548.5 | J31: =+AVERAGE(F31,H31) -> 3512.5 | K31: 3534 | L31: 3489 | M31: =+AVERAGE(E31,G31,K31) -> 3543.6667 | N31: =+AVERAGE(F31,H31,L31) -> 3504.6667 | O31: 3527 | P31: 3478 | Q31: =+AVERAGE(E31,G31,K31,O31) -> 3539.5 | R31: =+AVERAGE(F31,H31,L31,P31) -> 3498 | S31: 3524 | T31: 3465 | U31: =+AVERAGE(E31,G31,K31,O31,S31) -> 3536.4 | V31: =+AVERAGE(F31,H31,L31,P31,T31) -> 3491.4 | W31: 3517 | X31: 3450 | Y31: =+AVERAGE(Q31,S31,W31) -> 3526.8333 | Z31: =+AVERAGE(P31,T31,X31) -> 3464.3333 | AA31: =+AVERAGE(E31,G31,K31,O31,S31,W31) -> 3533.1667 | AB31: =+AVERAGE(X31,P31,L31,H31,T31,F31) -> 3484.5 | AC31: 3487 | AD31: 3539 | AE31: =+AVERAGE(E31,G31,K31,O31,S31,W31,AC31) -> 3526.5714 | AF31: =+AVERAGE(F31,H31,L31,P31,T31,X31,AD31) -> 3492.2857 | AG31: 3479 | AH31: 3551 | AI31: =+AVERAGE(E31,G31,K31,O31,S31,W31,AC31,AG31) -> 3520.625 | AJ31: =+AVERAGE(F31,H31,L31,P31,T31,X31,AD31,AH31) -> 3499.625 | AK31: 3471 | AL31: 3568 | AM31: =+AVERAGE(AC31,AG31,AK31) -> 3479 | AN31: =+AVERAGE(AD31,AH31,AL31) -> 3552.6667 | AO31: =+AVERAGE(E31,G31,K31,O31,S31,W31,AC31,AG31,AK31) -> 3515.1111 | AP31: =+AVERAGE(F31,H31,L31,P31,T31,X31,AD31,AH31,AL31) -> 3507.2222 | AQ31: 3463 | AR31: 3570 | AS31: =+AVERAGE(E31,G31,K31,O31,S31,W31,AC31,AG31,AK31,AQ31) -> 3509.9 | AT31: =+AVERAGE(F31,H31,L31,P31,T31,X31,AD31,AH31,AL31,AR31) -> 3513.5 | AU31: 3452 | AV31: 3545 | AW31: =+AVERAGE(E31,G31,K31,O31,S31,W31,AC31,AG31,AK31,AQ31,AU31) -> 3504.6364 | AX31: =+AVERAGE(F31,H31,L31,P31,T31,X31,AD31,AH31,AL31,AR31,AV31) -> 3516.3636 | AY31: 3449 | AZ31: 3531 | BA31: =+AVERAGE(AQ31,AU31,AY31) -> 3454.6667 | BB31: =+AVERAGE(AR31,AV31,AZ31) -> 3548.6667 | BC31: =+AVERAGE(AC31,AG31,AK31,AQ31,AU31,AY31) -> 3466.8333 | BD31: =+AVERAGE(AD31,AH31,AL31,AR31,AV31,AZ31) -> 3550.6667 | BE31: =+AVERAGE(E31,G31,K31,O31,S31,W31,AC31,AG31,AK31,AQ31,AU31,AY31) -> 3500 | BF31: =+AVERAGE(F31,H31,L31,P31,T31,X31,AD31,AH31,AL31,AR31,AV31,AZ31) -> 3517.5833 | BG31: 3502.25 | BH31: 3544.5833 | BI31: 3607.8333 | BJ31: 3647.6667 | BK31: 3826.0833 | BL31: 3802.9167 | BM31: 4009.5833 | BN31: 3995.5833 | BO31: 4196.5983 | BP31: 4090.3027 | BQ31: 4470.8033 | BR31: 4421.3333 | BS31: 4614.4192
B32: Labor productivity calculation | C32: Crude Steel | D32: ='Maj Production Summ'!D18 -> 2769999.9 | E32: ='Maj Production Summ'!E18 -> 237110.48 | F32: ='Maj Production Summ'!F18 -> 207020 | G32: ='Maj Production Summ'!G18 -> 244664.78 | H32: ='Maj Production Summ'!H18 -> 236638 | I32: =+E32+G32 -> 481775.26 | J32: =+F32+H32 -> 443658 | K32: ='Maj Production Summ'!K18 -> 237110.48 | L32: ='Maj Production Summ'!L18 -> 243453 | M32: =+E32+G32+K32 -> 718885.74 | N32: =+F32+H32+L32 -> 687111 | O32: ='Maj Production Summ'!O18 -> 239943.34 | P32: ='Maj Production Summ'!P18 -> 253662 | Q32: =+M32+O32 -> 958829.08 | R32: =+N32+P32 -> 940773 | S32: ='Maj Production Summ'!S18 -> 239943.34 | T32: ='Maj Production Summ'!T18 -> 237622 | U32: =+Q32+S32 -> 1198772.4 | V32: =+R32+T32 -> 1178395 | W32: ='Maj Production Summ'!W18 -> 125920.68 | X32: ='Maj Production Summ'!X18 -> 226847 | Y32: =+O32+S32+W32 -> 605807.37 | Z32: =+P32+T32+X32 -> 718131 | AA32: =+M32+Y32 -> 1324693.1 | AB32: =+N32+Z32 -> 1405242 | AC32: ='Maj Production Summ'!AC18 -> 235490.57 | AD32: ='Maj Production Summ'!AD18 -> 222138 | AE32: =+AA32+AC32 -> 1560183.7 | AF32: =+AB32+AD32 -> 1627380 | AG32: ='Maj Production Summ'!AG18 -> 227943.4 | AH32: ='Maj Production Summ'!AH18 -> 7935 | AI32: =+AE32+AG32 -> 1788127.1 | AJ32: =+AF32+AH32 -> 1635315 | AK32: ='Maj Production Summ'!AK18 -> 235490.57 | AL32: ='Maj Production Summ'!AL18 -> 234930 | AM32: =+AC32+AG32+AK32 -> 698924.53 | AN32: =+AD32+AH32+AL32 -> 465003 | AO32: =AI32+AK32 -> 2023617.6 | AP32: =AJ32+AL32 -> 1870245 | AQ32: ='Maj Production Summ'!AQ18 -> 235490.57 | AR32: ='Maj Production Summ'!AR18 -> 246040 | AS32: =+AO32+AQ32 -> 2259108.2 | AT32: =+AP32+AR32 -> 2116285 | AU32: ='Maj Production Summ'!AU18 -> 211905.66 | AV32: ='Maj Production Summ'!AV18 -> 222895 | AW32: =+AS32+AU32 -> 2471013.9 | AX32: =+AT32+AV32 -> 2339180 | AY32: ='Maj Production Summ'!AY18 -> 235490.57 | AZ32: ='Maj Production Summ'!AZ18 -> 243552 | BA32: =+AQ32+AU32+AY32 -> 682886.79 | BB32: =+AR32+AV32+AZ32 -> 712487 | BC32: =+AM32+BA32 -> 1381811.3 | BD32: =+AN32+BB32 -> 1177490 | BE32: =+AW32+AY32 -> 2706504.4 | BF32: =+AX32+AZ32 -> 2582732 | BG32: 2489528.3 | BH32: 2436959 | BI32: 2620075.5 | BJ32: 2528925 | BK32: 2500000 | BL32: 2422324.3 | BM32: 2573000.8 | BN32: 2322716
C33: Pig+Eq | D33: ='Maj Production Summ'!D26 -> 14270 | E33: ='Maj Production Summ'!E26 -> 810 | F33: ='Maj Production Summ'!F26 -> 4661.7268 | G33: ='Maj Production Summ'!G26 -> 810 | H33: ='Maj Production Summ'!H26 -> 2950.1685 | I33: =+E33+G33 -> 1620 | J33: =+F33+H33 -> 7611.8953 | K33: ='Maj Production Summ'!K26 -> 810 | L33: ='Maj Production Summ'!L26 -> 1030.4578 | M33: =+E33+G33+K33 -> 2430 | N33: =+F33+H33+L33 -> 8642.3531 | O33: ='Maj Production Summ'!O26 -> 810 | P33: ='Maj Production Summ'!P26 -> 0 | Q33: =+M33+O33 -> 3240 | R33: =+N33+P33 -> 8642.3531 | S33: ='Maj Production Summ'!S26 -> 810 | T33: ='Maj Production Summ'!T26 -> 164.4084 | U33: =+Q33+S33 -> 4050 | V33: =+R33+T33 -> 8806.7615 | W33: ='Maj Production Summ'!W26 -> 5360 | X33: ='Maj Production Summ'!X26 -> 292.8108 | Y33: =+O33+S33+W33 -> 6980 | Z33: =+P33+T33+X33 -> 457.2192 | AA33: =+M33+Y33 -> 9410 | AB33: =+N33+Z33 -> 9099.5723 | AC33: ='Maj Production Summ'!AC26 -> 342 | AD33: ='Maj Production Summ'!AD26 -> 302.05043 | AE33: =+AA33+AC33 -> 9752 | AF33: =+AB33+AD33 -> 9401.6227 | AG33: ='Maj Production Summ'!AG26 -> 342 | AH33: ='Maj Production Summ'!AH26 -> 1541.4762 | AI33: =+AE33+AG33 -> 10094 | AJ33: =+AF33+AH33 -> 10943.099 | AK33: ='Maj Production Summ'!AK26 -> 342 | AL33: ='Maj Production Summ'!AL26 -> 4949.9068 | AM33: =+AC33+AG33+AK33 -> 1026 | AN33: =+AD33+AH33+AL33 -> 6793.4334 | AO33: =AI33+AK33 -> 10436 | AP33: =AJ33+AL33 -> 15893.006 | AQ33: ='Maj Production Summ'!AQ26 -> 342 | AR33: ='Maj Production Summ'!AR26 -> 565.31098 | AS33: =+AO33+AQ33 -> 10778 | AT33: =+AP33+AR33 -> 16458.317 | AU33: ='Maj Production Summ'!AU26 -> 342 | AV33: ='Maj Production Summ'!AV26 -> 1000.3476 | AW33: =+AS33+AU33 -> 11120 | AX33: =+AT33+AV33 -> 17458.664 | AY33: ='Maj Production Summ'!AY26 -> 342 | AZ33: ='Maj Production Summ'!AZ26 -> 5493.599 | BA33: =+AQ33+AU33+AY33 -> 1026 | BB33: =+AR33+AV33+AZ33 -> 7059.2576 | BC33: =+AM33+BA33 -> 2052 | BD33: =+AN33+BB33 -> 13852.691 | BE33: =+AW33+AY33 -> 11462 | BF33: =+AX33+AZ33 -> 22952.263 | BG33: 9365 | BH33: 25856.451 | BI33: 21561.1 | BJ33: 13596.898 | BK33: 22929.735 | BL33: 16335.784 | BM33: 34051.635 | BN33: 32547.079
C34: 50% of Pig Eq | D34: =+D33/2 -> 7135 | E34: =+E33/2 -> 405 | F34: =+F33/2 -> 2330.8634 | G34: =+G33/2 -> 405 | H34: =+H33/2 -> 1475.0842 | I34: =+E34+G34 -> 810 | J34: =+F34+H34 -> 3805.9477 | K34: =+K33/2 -> 405 | L34: =+L33/2 -> 515.22889 | M34: =+E34+G34+K34 -> 1215 | N34: =+F34+H34+L34 -> 4321.1765 | O34: =+O33/2 -> 405 | P34: =+P33/2 -> 0 | Q34: =+M34+O34 -> 1620 | R34: =+N34+P34 -> 4321.1765 | S34: =+S33/2 -> 405 | T34: =+T33/2 -> 82.204202 | U34: =+Q34+S34 -> 2025 | V34: =+R34+T34 -> 4403.3807 | W34: =+W33/2 -> 2680 | X34: =+X33/2 -> 146.4054 | Y34: =+O34+S34+W34 -> 3490 | Z34: =+P34+T34+X34 -> 228.6096 | AA34: =+M34+Y34 -> 4705 | AB34: =+N34+Z34 -> 4549.7861 | AC34: =+AC33/2 -> 171 | AD34: =+AD33/2 -> 151.02522 | AE34: =+AA34+AC34 -> 4876 | AF34: =+AB34+AD34 -> 4700.8114 | AG34: =+AG33/2 -> 171 | AH34: =+AH33/2 -> 770.7381 | AI34: =+AE34+AG34 -> 5047 | AJ34: =+AF34+AH34 -> 5471.5495 | AK34: =+AK33/2 -> 171 | AL34: =+AL33/2 -> 2474.9534 | AM34: =+AC34+AG34+AK34 -> 513 | AN34: =+AD34+AH34+AL34 -> 3396.7167 | AO34: =AI34+AK34 -> 5218 | AP34: =AJ34+AL34 -> 7946.5029 | AQ34: =+AQ33/2 -> 171 | AR34: =+AR33/2 -> 282.65549 | AS34: =+AO34+AQ34 -> 5389 | AT34: =+AP34+AR34 -> 8229.1584 | AU34: =+AU33/2 -> 171 | AV34: =+AV33/2 -> 500.17378 | AW34: =+AS34+AU34 -> 5560 | AX34: =+AT34+AV34 -> 8729.3321 | AY34: =+AY33/2 -> 171 | AZ34: =+AZ33/2 -> 2746.7995 | BA34: =+AQ34+AU34+AY34 -> 513 | BB34: =+AR34+AV34+AZ34 -> 3529.6288 | BC34: =+AM34+BA34 -> 1026 | BD34: =+AN34+BB34 -> 6926.3455 | BE34: =+AW34+AY34 -> 5731 | BF34: =+AX34+AZ34 -> 11476.132 | BG34: 4682.5 | BH34: 12928.226 | BI34: 10780.55 | BJ34: 6798.4488 | BK34: 11464.868 | BL34: 8167.892 | BM34: 17025.818 | BN34: 16273.54
C35: CS+50%Pig Eq | D35: =+D32+D34 -> 2777134.9 | E35: =+E32+E34 -> 237515.48 | F35: =+F32+F34 -> 209350.86 | G35: =+G32+G34 -> 245069.78 | H35: =+H32+H34 -> 238113.08 | I35: =+E35+G35 -> 482585.26 | J35: =+F35+H35 -> 447463.95 | K35: =+K32+K34 -> 237515.48 | L35: =+L32+L34 -> 243968.23 | M35: =+E35+G35+K35 -> 720100.74 | N35: =+F35+H35+L35 -> 691432.18 | O35: =+O32+O34 -> 240348.34 | P35: =+P32+P34 -> 253662 | Q35: =+M35+O35 -> 960449.08 | R35: =+N35+P35 -> 945094.18 | S35: =+S32+S34 -> 240348.34 | T35: =+T32+T34 -> 237704.2 | U35: =+Q35+S35 -> 1200797.4 | V35: =+R35+T35 -> 1182798.4 | W35: =+W32+W34 -> 128600.68 | X35: =+X32+X34 -> 226993.41 | Y35: =+O35+S35+W35 -> 609297.37 | Z35: =+P35+T35+X35 -> 718359.61 | AA35: =+M35+Y35 -> 1329398.1 | AB35: =+N35+Z35 -> 1409791.8 | AC35: =+AC32+AC34 -> 235661.57 | AD35: =+AD32+AD34 -> 222289.03 | AE35: =+AA35+AC35 -> 1565059.7 | AF35: =+AB35+AD35 -> 1632080.8 | AG35: =+AG32+AG34 -> 228114.4 | AH35: =+AH32+AH34 -> 8705.7381 | AI35: =+AE35+AG35 -> 1793174.1 | AJ35: =+AF35+AH35 -> 1640786.5 | AK35: =+AK32+AK34 -> 235661.57 | AL35: =+AL32+AL34 -> 237404.95 | AM35: =+AC35+AG35+AK35 -> 699437.53 | AN35: =+AD35+AH35+AL35 -> 468399.72 | AO35: =AI35+AK35 -> 2028835.6 | AP35: =AJ35+AL35 -> 1878191.5 | AQ35: =+AQ32+AQ34 -> 235661.57 | AR35: =+AR32+AR34 -> 246322.66 | AS35: =+AO35+AQ35 -> 2264497.2 | AT35: =+AP35+AR35 -> 2124514.2 | AU35: =+AU32+AU34 -> 212076.66 | AV35: =+AV32+AV34 -> 223395.17 | AW35: =+AS35+AU35 -> 2476573.9 | AX35: =+AT35+AV35 -> 2347909.3 | AY35: =+AY32+AY34 -> 235661.57 | AZ35: =+AZ32+AZ34 -> 246298.8 | BA35: =+AQ35+AU35+AY35 -> 683399.79 | BB35: =+AR35+AV35+AZ35 -> 716016.63 | BC35: =+AM35+BA35 -> 1382837.3 | BD35: =+AN35+BB35 -> 1184416.3 | BE35: =+AW35+AY35 -> 2712235.4 | BF35: =+AX35+AZ35 -> 2594208.1 | BG35: 2494210.8 | BH35: 2449887.2 | BI35: 2630856 | BJ35: 2535723.4 | BK35: 2511464.9 | BL35: 2430492.2 | BM35: 2590026.6 | BN35: 2338989.5
D36: =+D35/(D31/365*D2) -> 789.96868 | E36: =+E35/(E31/365*E2) -> 812.64671 | F36: =+F35/(F31/365*F2) -> 724.01995 | G36: =+G35/(G31/365*G2) -> 814.88252 | H36: =+H35/(H31/365*H2) -> 799.42673 | I36: =+I35/(I31/365*I2) -> 813.75238 | J36: =+J35/(J31/365*J2) -> 762.26284 | K36: =+K35/(K31/365*K2) -> 817.70563 | ... BF36: =+BF35/(BF31/365*BF2) -> 737.49728 | BG36: 712.17383 | BH36: 691.16367 | BI36: 729.20664 | BJ36: 695.16315 | BK36: 656.40621 | BL36: 639.11266 | BM36: 645.95904 | BN36: 585.39376
B38: Hot metal consumed in BOF | C38: MT | D38: =+(D16*D32)/1000 -> 2933429.9 | E38: =+(E16*E32)/1000 -> 251100 | F38: =+SMS!F15 -> 219393.57 | G38: =+(G16*G32)/1000 -> 259100 | H38: =+SMS!H15 -> 252686.9 | I38: =+(I16*I32)/1000 -> 510200 | J38: =+SMS!J15 -> 472080.46 | K38: =+(K16*K32)/1000 -> 251100 | L38: =+SMS!L15 -> 258527.52 | M38: =+(M16*M32)/1000 -> 761300 | N38: =+SMS!N15 -> 730607.99 | O38: =+(O16*O32)/1000 -> 254100 | P38: =+SMS!P15 -> 266778.08 | Q38: =+(Q16*Q32)/1000 -> 1015400 | R38: =+SMS!R15 -> 997386.06 | S38: =+(S16*S32)/1000 -> 254100 | T38: =+SMS!T15 -> 251918.72 | U38: =+(U16*U32)/1000 -> 1269500 | V38: =+SMS!V15 -> 1249304.8 | W38: =+(W16*W32)/1000 -> 133350 | X38: =+SMS!X15 -> 241323.3 | Y38: =+O38+S38+W38 -> 641550 | Z38: =+P38+T38+X38 -> 760020.09 | AA38: =+M38+Y38 -> 1402850 | AB38: =+N38+Z38 -> 1490628.1 | AC38: =+(AC16*AC32)/1000 -> 249384.51 | AD38: =+SMS!AD15 -> 235736.8 | AE38: =+(AE16*AE32)/1000 -> 1652234.5 | AF38: =+SMS!AF15 -> 1726364.9 | AG38: =+(AG16*AG32)/1000 -> 241392.06 | AH38: =+SMS!AH15 -> 8398.2 | AI38: =+(AI16*AI32)/1000 -> 1893626.6 | AJ38: =+SMS!AJ15 -> 1734763.1 | AK38: =+(AK16*AK32)/1000 -> 249384.51 | AL38: =+SMS!AL15 -> 249391.75 | AM38: =+AC38+AG38+AK38 -> 740161.08 | AN38: =+AD38+AH38+AL38 -> 493526.75 | AO38: =+(AO16*AO32)/1000 -> 2143011.1 | AP38: =+SMS!AP15 -> 1984154.8 | AQ38: =+(AQ16*AQ32)/1000 -> 249384.51 | AR38: =+SMS!AR15 -> 261382.3 | AS38: =+(AS16*AS32)/1000 -> 2392395.6 | AT38: =+SMS!AT15 -> 2245537.1 | AU38: =+(AU16*AU32)/1000 -> 224408.09 | AV38: =+SMS!AV15 -> 236601.12 | AW38: =+(AW16*AW32)/1000 -> 2616803.7 | AX38: =+SMS!AX15 -> 2482138.3 | AY38: =+(AY16*AY32)/1000 -> 249384.51 | AZ38: =+SMS!AZ15 -> 257456.17 | BA38: =+AQ38+AU38+AY38 -> 723177.11 | BB38: =+AR38+AV38+AZ38 -> 755439.59 | BC38: =+AM38+BA38 -> 1463338.2 | BD38: =+AN38+BB38 -> 1248966.3 | BE38: =+AW38+AY38 -> 2866188.2 | BF38: =+AX38+AZ38 -> 2739594.4 | BG38: 2638900 | BH38: 2582070.1 | BI38: 2777280 | BJ38: 2695862.8 | BK38: 2655000 | BL38: 2574868 | BM38: 2611100.5 | BN38: 2366123.2
B39: Total Scrap Charged | C39: MT | D39: =+(D17*D32)/1000 -> 105260 | E39: =+(E17*E32)/1000 -> 9010.1983 | F39: =+SMS!F19 -> 7695.9 | G39: =+(G17*G32)/1000 -> 9297.2616 | H39: =+SMS!H19 -> 6670.8 | I39: =+(I17*I32)/1000 -> 18307.46 | J39: =+SMS!J19 -> 14366.7 | K39: =+(K17*K32)/1000 -> 9010.1983 | L39: =+SMS!L19 -> 8404.2 | M39: =+(M17*M32)/1000 -> 27317.658 | N39: =+SMS!N19 -> 22770.9 | O39: =+(O17*O32)/1000 -> 9117.847 | P39: =+SMS!P19 -> 11294.6 | Q39: =+(Q17*Q32)/1000 -> 36435.505 | R39: =+SMS!R19 -> 34065.5 | S39: =+(S17*S32)/1000 -> 9117.847 | T39: =+SMS!T19 -> 8598.1 | U39: =+(U17*U32)/1000 -> 45553.352 | V39: =+SMS!V19 -> 42663.6 | W39: =+(W17*W32)/1000 -> 4784.9858 | X39: =+SMS!X19 -> 7722 | Y39: =+O39+S39+W39 -> 23020.68 | Z39: =+P39+T39+X39 -> 27614.7 | AA39: =+M39+Y39 -> 50338.338 | AB39: =+N39+Z39 -> 50385.6 | AC39: =+(AC17*AC32)/1000 -> 8948.6415 | AD39: =+SMS!AD19 -> 7554.5 | AE39: =+(AE17*AE32)/1000 -> 59286.98 | AF39: =+SMS!AF19 -> 57940.1 | AG39: =+(AG17*AG32)/1000 -> 8661.8491 | AH39: =+SMS!AH19 -> 326.2 | AI39: =+(AI17*AI32)/1000 -> 67948.829 | AJ39: =+SMS!AJ19 -> 58266.3 | AK39: =+(AK17*AK32)/1000 -> 8948.6415 | AL39: =+SMS!AL19 -> 8846.2 | AM39: =+AC39+AG39+AK39 -> 26559.132 | AN39: =+AD39+AH39+AL39 -> 16726.9 | AO39: =+(AO17*AO32)/1000 -> 76897.47 | AP39: =+SMS!AP19 -> 67112.5 | AQ39: =+(AQ17*AQ32)/1000 -> 8948.6415 | AR39: =+SMS!AR19 -> 9232.5 | AS39: =+(AS17*AS32)/1000 -> 85846.112 | AT39: =+SMS!AT19 -> 76345 | AU39: =+(AU17*AU32)/1000 -> 8052.4151 | AV39: =+SMS!AV19 -> 7958.2 | AW39: =+(AW17*AW32)/1000 -> 93898.527 | AX39: =+SMS!AX19 -> 84303.2 | AY39: =+(AY17*AY32)/1000 -> 8948.6415 | AZ39: =+SMS!AZ19 -> 9343.2 | BA39: =+AQ39+AU39+AY39 -> 25949.698 | BB39: =+AR39+AV39+AZ39 -> 26533.9 | BC39: =+AM39+BA39 -> 52508.83 | BD39: =+AN39+BB39 -> 43260.8 | BE39: =+AW39+AY39 -> 102847.17 | BF39: =+AX39+AZ39 -> 93646.4 | BG39: 99581.132 | BH39: 91825 | BI39: 104803.02 | BJ39: 87073.52 | BK39: 121081.64 | BL39: 93275 | BM39: 128650.04 | BN39: 101615.76
B40: Fe-Mn | C40: MT | D40: =+(D48*'Maj Production Summ'!D$18)/1000 -> 4535.1331 | E40: =+(E48*'Maj Production Summ'!E$18)/1000 -> 388.20492 | F40: =+SMS!F55 -> 365 | G40: =+(G48*'Maj Production Summ'!G$18)/1000 -> 400.57306 | H40: =+SMS!H55 -> 297 | I40: =+(I48*'Maj Production Summ'!I$18)/1000 -> 788.77798 | J40: =+SMS!J55 -> 662 | K40: =+(K48*'Maj Production Summ'!K$18)/1000 -> 388.20492 | L40: =+SMS!L55 -> 405 | M40: =+(M48*'Maj Production Summ'!M$18)/1000 -> 1176.9829 | N40: =+SMS!N55 -> 1067 | O40: =+(O48*'Maj Production Summ'!O$18)/1000 -> 392.84297 | P40: =+SMS!P55 -> 383 | Q40: =+(Q48*'Maj Production Summ'!Q$18)/1000 -> 1569.8259 | R40: =+SMS!R55 -> 1450 | S40: =+(S48*'Maj Production Summ'!S$18)/1000 -> 392.84297 | T40: =+SMS!T55 -> 300 | U40: =+(U48*'Maj Production Summ'!U$18)/1000 -> 1962.6688 | V40: =+SMS!V55 -> 1750 | W40: =+(W48*'Maj Production Summ'!W$18)/1000 -> 206.16139 | X40: =+SMS!X55 -> 293 | Y40: =+O40+S40+W40 -> 991.84734 | Z40: =+P40+T40+X40 -> 976 | AA40: =+M40+Y40 -> 2168.8302 | AB40: =+N40+Z40 -> 2043 | AC40: =+(AC48*'Maj Production Summ'!AC$18)/1000 -> 385.55274 | AD40: =+SMS!AD55 -> 291 | AE40: =+(AE48*'Maj Production Summ'!AE$18)/1000 -> 2554.383 | AF40: =+SMS!AF55 -> 2334 | AG40: =+(AG48*'Maj Production Summ'!AG$18)/1000 -> 373.19627 | AH40: =+SMS!AH55 -> 2 | AI40: =+(AI48*'Maj Production Summ'!AI$18)/1000 -> 2927.5793 | AJ40: =+SMS!AJ55 -> 2336 | AK40: =+(AK48*'Maj Production Summ'!AK$18)/1000 -> 385.55274 | AL40: =+SMS!AL55 -> 421 | AM40: =+AC40+AG40+AK40 -> 1144.3018 | AN40: =+AD40+AH40+AL40 -> 714 | AO40: =+(AO48*'Maj Production Summ'!AO$18)/1000 -> 3313.132 | AP40: =+SMS!AP55 -> 2757 | AQ40: =+(AQ48*'Maj Production Summ'!AQ$18)/1000 -> 385.55274 | AR40: =+SMS!AR55 -> 443 | AS40: =+(AS48*'Maj Production Summ'!AS$18)/1000 -> 3698.6847 | AT40: =+SMS!AT55 -> 3200 | AU40: =+(AU48*'Maj Production Summ'!AU$18)/1000 -> 346.93878 | AV40: =+SMS!AV55 -> 330 | AW40: =+(AW48*'Maj Production Summ'!AW$18)/1000 -> 4045.6235 | AX40: =+SMS!AX55 -> 3530 | AY40: =+(AY48*'Maj Production Summ'!AY$18)/1000 -> 385.55274 | AZ40: =+SMS!AZ55 -> 328 | BA40: =+AQ40+AU40+AY40 -> 1118.0443 | BB40: =+AR40+AV40+AZ40 -> 1101 | BC40: =+AM40+BA40 -> 2262.346 | BD40: =+AN40+BB40 -> 1815 | BE40: =+AW40+AY40 -> 4431.1763 | BF40: =+AX40+AZ40 -> 3858 | BG40: 4107.7217 | BH40: 3222 | BI40: 3385.0943 | BJ40: 4727 | BK40: 4500 | BL40: 4569.84 | BM40: 6693.3528 | BN40: 4136
B41: LCFeMn | C41: MT | D41: =+(D49*'Maj Production Summ'!D$18)/1000 -> 2327.1483 | E41: =+(E49*'Maj Production Summ'!E$18)/1000 -> 199.20262 | F41: =+SMS!F56 -> 105 | G41: =+(G49*'Maj Production Summ'!G$18)/1000 -> 205.54918 | H41: =+SMS!H56 -> 178 | I41: 0 | J41: =+SMS!J56 -> 283 | K41: =+(K49*'Maj Production Summ'!K$18)/1000 -> 199.20262 | L41: =+SMS!L56 -> 105 | M41: 0 | N41: =+SMS!N56 -> 388 | O41: =+(O49*'Maj Production Summ'!O$18)/1000 -> 201.58258 | P41: =+SMS!P56 -> 137 | Q41: 0 | R41: =+SMS!R56 -> 525 | S41: =+(S49*'Maj Production Summ'!S$18)/1000 -> 201.58258 | T41: =+SMS!T56 -> 131 | U41: 0 | V41: =+SMS!V56 -> 656 | W41: =+(W49*'Maj Production Summ'!W$18)/1000 -> 105.78921 | X41: =+SMS!X56 -> 129 | Y41: =+O41+S41+W41 -> 508.95437 | Z41: =+P41+T41+X41 -> 397 | AA41: =+M41+Y41 -> 508.95437 | AB41: =+N41+Z41 -> 785 | AC41: =+(AC49*'Maj Production Summ'!AC$18)/1000 -> 197.84169 | AD41: =+SMS!AD56 -> 155 | AE41: 0 | AF41: =+SMS!AF56 -> 940 | AH41: =+SMS!AH56 -> 9 | AI41: 0 | AJ41: =+SMS!AJ56 -> 949 | AL41: =+SMS!AL56 -> 123 | AM41: =+AC41+AG41+AK41 -> 197.84169 | AN41: =+AD41+AH41+AL41 -> 287 | AO41: 0 | AP41: =+SMS!AP56 -> 1072 | AR41: =+SMS!AR56 -> 116 | AS41: 0 | AT41: =+SMS!AT56 -> 1188 | AV41: =+SMS!AV56 -> 149 | AW41: 0 | AX41: =+SMS!AX56 -> 1337 | AZ41: =+SMS!AZ56 -> 78 | BA41: =+AQ41+AU41+AY41 -> 0 | BB41: =+AR41+AV41+AZ41 -> 343 | BC41: =+AM41+BA41 -> 197.84169 | BD41: =+AN41+BB41 -> 630 | BE41: =+AW41+AY41 -> 0 | BF41: =+AX41+AZ41 -> 1415 | BG41: 0 | BH41: 1433 | BI41: 0 | BJ41: 1668.305 | BK41: 0 | BL41: 1122.042 | BM41: 0 | BN41: 968.34
B42: Total Fe-Mn | C42: MT | D42: =SUM(D40:D41) -> 6862.2813 | E42: =SUM(E40:E41) -> 587.40755 | F42: =SUM(F40:F41) -> 470 | G42: =SUM(G40:G41) -> 606.12224 | H42: =SUM(H40:H41) -> 475 | I42: =SUM(I40:I41) -> 788.77798 | J42: =SUM(J40:J41) -> 945 | K42: =SUM(K40:K41) -> 587.40755 | ... BF42: =SUM(BF40:BF41) -> 5273 | BG42: 4107.7217 | BH42: 4655 | BI42: 3385.0943 | BJ42: 6395.305 | BK42: 4500 | BL42: 5691.882 | BM42: 6693.3528 | BN42: 5104.34
B43: Si-Mn | C43: MT | D43: =+(D51*'Maj Production Summ'!D$18)/1000 -> 48123.119 | E43: =+(E51*'Maj Production Summ'!E$18)/1000 -> 4119.3128 | F43: =+SMS!F58 -> 3332 | G43: =+(G51*'Maj Production Summ'!G$18)/1000 -> 4250.5534 | H43: =+SMS!H58 -> 3570 | I43: =+(I51*'Maj Production Summ'!I$18)/1000 -> 8369.8662 | J43: =+SMS!J58 -> 6902 | K43: =+(K51*'Maj Production Summ'!K$18)/1000 -> 4119.3128 | L43: =+SMS!L58 -> 3768 | M43: =+(M51*'Maj Production Summ'!M$18)/1000 -> 12489.179 | N43: =+SMS!N58 -> 10670 | O43: =+(O51*'Maj Production Summ'!O$18)/1000 -> 4168.528 | P43: =+SMS!P58 -> 4098 | Q43: =+(Q51*'Maj Production Summ'!Q$18)/1000 -> 16657.707 | R43: =+SMS!R58 -> 14768 | S43: =+(S51*'Maj Production Summ'!S$18)/1000 -> 4168.528 | T43: =+SMS!T58 -> 3587.02 | U43: =+(U51*'Maj Production Summ'!U$18)/1000 -> 20826.235 | V43: =+SMS!V58 -> 18355.02 | W43: =+(W51*'Maj Production Summ'!W$18)/1000 -> 2187.6159 | X43: =+SMS!X58 -> 3011.11 | Y43: =+O43+S43+W43 -> 10524.672 | Z43: =+P43+T43+X43 -> 10696.13 | AA43: =+M43+Y43 -> 23013.851 | AB43: =+N43+Z43 -> 21366.13 | AC43: =+(AC51*'Maj Production Summ'!AC$18)/1000 -> 4091.1701 | AD43: =+SMS!AD58 -> 3276 | AE43: =+(AE51*'Maj Production Summ'!AE$18)/1000 -> 27105.021 | AF43: =+SMS!AF58 -> 24642.13 | AG43: =+(AG51*'Maj Production Summ'!AG$18)/1000 -> 3960.0533 | AH43: =+SMS!AH58 -> 110 | AI43: =+(AI51*'Maj Production Summ'!AI$18)/1000 -> 31065.074 | AJ43: =+SMS!AJ58 -> 24752.13 | AK43: =+(AK51*'Maj Production Summ'!AK$18)/1000 -> 4091.1701 | AL43: =+SMS!AL58 -> 3928 | AM43: =+AC43+AG43+AK43 -> 12142.393 | AN43: =+AD43+AH43+AL43 -> 7314 | AO43: =+(AO51*'Maj Production Summ'!AO$18)/1000 -> 35156.244 | AP43: =+SMS!AP58 -> 28680.13 | AQ43: =+(AQ51*'Maj Production Summ'!AQ$18)/1000 -> 4091.1701 | AR43: =+SMS!AR58 -> 4040 | AS43: =+(AS51*'Maj Production Summ'!AS$18)/1000 -> 39247.414 | AT43: =+SMS!AT58 -> 32720.13 | AU43: =+(AU51*'Maj Production Summ'!AU$18)/1000 -> 3681.4303 | AV43: =+SMS!AV58 -> 3626 | AW43: =+(AW51*'Maj Production Summ'!AW$18)/1000 -> 42928.845 | AX43: =+SMS!AX58 -> 36346.13 | AY43: =+(AY51*'Maj Production Summ'!AY$18)/1000 -> 4091.1701 | AZ43: =+SMS!AZ58 -> 4060 | BA43: =+AQ43+AU43+AY43 -> 11863.77 | BB43: =+AR43+AV43+AZ43 -> 11726 | BC43: =+AM43+BA43 -> 24006.164 | BD43: =+AN43+BB43 -> 19040 | BE43: =+AW43+AY43 -> 47020.015 | BF43: =+AX43+AZ43 -> 40406.13 | BG43: 45682.844 | BH43: 39439.44 | BI43: 44076.08 | BJ43: 45680 | BK43: 40000 | BL43: 44647.62 | BM43: 42007.866 | BN43: 36347
B44: LP Si-Mn | C44: MT | F44: =+SMS!F59 -> 0 | H44: =+SMS!H59 -> 0 | J44: =+SMS!J59 -> 0 | L44: =+SMS!L59 -> 0 | N44: =+SMS!N59 -> 0 | P44: =+SMS!P59 -> 0 | R44: =+SMS!R59 -> 0 | T44: =+SMS!T59 -> 0 | V44: =+SMS!V59 -> 0 | X44: =+SMS!X59 -> 0 | Z44: =P44+T44+X44 -> 0 | AB44: =+N44+Z44 -> 0 | AD44: =+SMS!AD59 -> 0 | AF44: =+SMS!AF59 -> 0 | AH44: =+SMS!AH59 -> 0 | AJ44: =+SMS!AJ59 -> 0 | AL44: =+SMS!AL59 -> 0 | AN44: =AD44+AH44+AL44 -> 0 | AP44: =+SMS!AP59 -> 0 | AR44: =+SMS!AR59 -> 0 | AT44: =+SMS!AT59 -> 0 | AV44: =+SMS!AV59 -> 0 | AX44: =+SMS!AX59 -> 0 | AZ44: =+SMS!AZ59 -> 0 | BB44: =+SMS!BB59 -> 0 | BD44: =+SMS!BD59 -> 0 | BF44: =+SMS!BF59 -> 0 | BH44: 0 | BJ44: 25.81
B45: Total Si-Mn | C45: MT | D45: =SUM(D43:D44) -> 48123.119 | E45: =SUM(E43:E44) -> 4119.3128 | F45: =SUM(F43:F44) -> 3332 | G45: =SUM(G43:G44) -> 4250.5534 | H45: =SUM(H43:H44) -> 3570 | I45: =SUM(I43:I44) -> 8369.8662 | J45: =SUM(J43:J44) -> 6902 | K45: =SUM(K43:K44) -> 4119.3128 | ... BF45: =SUM(BF43:BF44) -> 40406.13 | BG45: 45682.844 | BH45: 39439.44 | BI45: 44076.08 | BJ45: 45705.81
B46: Fe-Si | C46: MT | D46: =+(D54*'Maj Production Summ'!D$18)/1000 -> 6002.4947 | E46: =+(E54*'Maj Production Summ'!E$18)/1000 -> 513.81028 | F46: =+SMS!F61 -> 467 | G46: =+(G54*'Maj Production Summ'!G$18)/1000 -> 530.18018 | H46: =+SMS!H61 -> 551 | I46: =+(I54*'Maj Production Summ'!I$18)/1000 -> 1043.9905 | J46: =+SMS!J61 -> 1018 | K46: =+(K54*'Maj Production Summ'!K$18)/1000 -> 513.81028 | L46: =+SMS!L61 -> 526.21 | M46: =+(M54*'Maj Production Summ'!M$18)/1000 -> 1557.8007 | N46: =+SMS!N61 -> 1544.21 | O46: =+(O54*'Maj Production Summ'!O$18)/1000 -> 519.94899 | P46: =+SMS!P61 -> 485.894 | Q46: =+(Q54*'Maj Production Summ'!Q$18)/1000 -> 2077.7497 | R46: =+SMS!R61 -> 2030.104 | S46: =+(S54*'Maj Production Summ'!S$18)/1000 -> 519.94899 | T46: =+SMS!T61 -> 516 | U46: =+(U54*'Maj Production Summ'!U$18)/1000 -> 2597.6987 | V46: =+SMS!V61 -> 2546.104 | W46: =+(W54*'Maj Production Summ'!W$18)/1000 -> 272.86579 | X46: =+SMS!X61 -> 481 | Y46: =+O46+S46+W46 -> 1312.7638 | Z46: =+P46+T46+X46 -> 1482.894 | AA46: =+M46+Y46 -> 2870.5645 | AB46: =+N46+Z46 -> 3027.104 | AC46: =+(AC54*'Maj Production Summ'!AC$18)/1000 -> 510.29997 | AD46: =+SMS!AD61 -> 614 | AE46: =+(AE54*'Maj Production Summ'!AE$18)/1000 -> 3380.8645 | AF46: =+SMS!AF61 -> 3641.104 | AG46: =+(AG54*'Maj Production Summ'!AG$18)/1000 -> 493.94552 | AH46: =+SMS!AH61 -> 19 | AI46: =+(AI54*'Maj Production Summ'!AI$18)/1000 -> 3874.81 | AJ46: =+SMS!AJ61 -> 3660.104 | AK46: =+(AK54*'Maj Production Summ'!AK$18)/1000 -> 510.29997 | AL46: =+SMS!AL61 -> 538 | AM46: =+AC46+AG46+AK46 -> 1514.5455 | AN46: =+AD46+AH46+AL46 -> 1171 | AO46: =+(AO54*'Maj Production Summ'!AO$18)/1000 -> 4385.11 | AP46: =+SMS!AP61 -> 4198.104 | AQ46: =+(AQ54*'Maj Production Summ'!AQ$18)/1000 -> 510.29997 | AR46: =+SMS!AR61 -> 540 | AS46: =+(AS54*'Maj Production Summ'!AS$18)/1000 -> 4895.4099 | AT46: =+SMS!AT61 -> 4738.104 | AU46: =+(AU54*'Maj Production Summ'!AU$18)/1000 -> 459.19229 | AV46: =+SMS!AV61 -> 495 | AW46: =+(AW54*'Maj Production Summ'!AW$18)/1000 -> 5354.6022 | AX46: =+SMS!AX61 -> 5233.104 | AY46: =+(AY54*'Maj Production Summ'!AY$18)/1000 -> 510.29997 | AZ46: =+SMS!AZ61 -> 510 | BA46: =+AQ46+AU46+AY46 -> 1479.7922 | BB46: =+AR46+AV46+AZ46 -> 1545 | BC46: =+AM46+BA46 -> 2994.3377 | BD46: =+AN46+BB46 -> 2716 | BE46: =+AW46+AY46 -> 5864.9022 | BF46: =+AX46+AZ46 -> 5743.104 | BG46: 5352.4858 | BH46: 5627.407 | BI46: 7386.6389 | BJ46: 5310 | BK46: 8000 | BL46: 5205.89 | BM46: 7796.1924 | BN46: 5192
B47: Ferro Alloys Break-up
B48: Fe-Mn | C48: Kg/TCS | D48: 1.6372322 | E48: =+$D$48 -> 1.6372322 | F48: =+(F40/'Maj Production Summ'!F$18)*1000 -> 1.7631147 | G48: =+$D$48 -> 1.6372322 | H48: =+(H40/'Maj Production Summ'!H$18)*1000 -> 1.2550816 | I48: =+$D$48 -> 1.6372322 | J48: =+(J40/'Maj Production Summ'!J$18)*1000 -> 1.4921403 | K48: =+$D$48 -> 1.6372322 | L48: =+(L40/'Maj Production Summ'!L$18)*1000 -> 1.6635655 | M48: =+$D$48 -> 1.6372322 | N48: =+(N40/'Maj Production Summ'!N$18)*1000 -> 1.5528786 | O48: =+$D$48 -> 1.6372322 | P48: =+(P40/'Maj Production Summ'!P$18)*1000 -> 1.5098832 | Q48: =+$D$48 -> 1.6372322 | R48: =+(R40/'Maj Production Summ'!R$18)*1000 -> 1.5412857 | S48: =+$D$48 -> 1.6372322 | T48: =+(T40/'Maj Production Summ'!T$18)*1000 -> 1.2625094 | U48: =+$D$48 -> 1.6372322 | V48: =+(V40/'Maj Production Summ'!V$18)*1000 -> 1.4850708 | W48: =+$D$48 -> 1.6372322 | X48: =+(X40/'Maj Production Summ'!X$18)*1000 -> 1.2916195 | Y48: =+$D$48 -> 1.6372322 | Z48: =+(Z40/'Maj Production Summ'!Z$18)*1000 -> 1.3590835 | AA48: =+$D$48 -> 1.6372322 | AB48: =+(AB40/'Maj Production Summ'!AB$18)*1000 -> 1.4538421 | AC48: =+$D$48 -> 1.6372322 | AD48: =+(AD40/'Maj Production Summ'!AD$18)*1000 -> 1.3099965 | AE48: =+$D$48 -> 1.6372322 | AF48: =+(AF40/'Maj Production Summ'!AF$18)*1000 -> 1.4342071 | AG48: =+$D$48 -> 1.6372322 | AH48: =+(AH40/'Maj Production Summ'!AH$18)*1000 -> 0.25204789 | AI48: =+$D$48 -> 1.6372322 | AJ48: =+(AJ40/'Maj Production Summ'!AJ$18)*1000 -> 1.428471 | AK48: =+$D$48 -> 1.6372322 | AL48: =+(AL40/'Maj Production Summ'!AL$18)*1000 -> 1.7920232 | AM48: =+$D$48 -> 1.6372322 | AN48: =+(AN40/'Maj Production Summ'!AN$18)*1000 -> 1.535474 | AO48: =+$D$48 -> 1.6372322 | AP48: =+(AP40/'Maj Production Summ'!AP$18)*1000 -> 1.4741384 | AQ48: =+$D$48 -> 1.6372322 | AR48: =+(AR40/'Maj Production Summ'!AR$18)*1000 -> 1.8005202 | AS48: =+$D$48 -> 1.6372322 | AT48: =+(AT40/'Maj Production Summ'!AT$18)*1000 -> 1.5120837 | AU48: =+$D$48 -> 1.6372322 | AV48: =+(AV40/'Maj Production Summ'!AV$18)*1000 -> 1.4805177 | AW48: =+$D$48 -> 1.6372322 | AX48: =+(AX40/'Maj Production Summ'!AX$18)*1000 -> 1.5090758 | AY48: =+$D$48 -> 1.6372322 | AZ48: =+(AZ40/'Maj Production Summ'!AZ$18)*1000 -> 1.346735 | BA48: =+$D$48 -> 1.6372322 | BB48: =+(BB40/'Maj Production Summ'!BB$18)*1000 -> 1.5452914 | BC48: =+$D$48 -> 1.6372322 | BD48: =+(BD40/'Maj Production Summ'!BD$18)*1000 -> 1.5414144 | BE48: =+$D$48 -> 1.6372322 | BF48: =+(BF40/'Maj Production Summ'!BF$18)*1000 -> 1.4937671 | BG48: 1.65 | BH48: 1.3221396 | BI48: 1.2919835 | BJ48: 1.8691737 | BK48: 1.8 | BL48: 1.8865517 | BM48: 2.60138 | BN48: 1.780674
B49: LCFeMn | C49: Kg/TCS | D49: 0.84012576 | E49: =+$D$49 -> 0.84012576 | F49: =+(F41/'Maj Production Summ'!F$18)*1000 -> 0.50719737 | G49: =+$D$49 -> 0.84012576 | H49: =+(H41/'Maj Production Summ'!H$18)*1000 -> 0.75220379 | I49: =+$D$49 -> 0.84012576 | J49: =+(J41/'Maj Production Summ'!J$18)*1000 -> 0.63787873 | K49: =+$D$49 -> 0.84012576 | L49: =+(L41/'Maj Production Summ'!L$18)*1000 -> 0.43129475 | M49: =+$D$49 -> 0.84012576 | N49: =+(N41/'Maj Production Summ'!N$18)*1000 -> 0.56468314 | O49: =+$D$49 -> 0.84012576 | P49: =+(P41/'Maj Production Summ'!P$18)*1000 -> 0.54008878 | Q49: =+$D$49 -> 0.84012576 | R49: =+(R41/'Maj Production Summ'!R$18)*1000 -> 0.55805173 | S49: =+$D$49 -> 0.84012576 | T49: =+(T41/'Maj Production Summ'!T$18)*1000 -> 0.55129576 | U49: =+$D$49 -> 0.84012576 | V49: =+(V41/'Maj Production Summ'!V$18)*1000 -> 0.5566894 | W49: =+$D$49 -> 0.84012576 | X49: =+(X41/'Maj Production Summ'!X$18)*1000 -> 0.56866522 | Y49: =+$D$49 -> 0.84012576 | Z49: =+(Z41/'Maj Production Summ'!Z$18)*1000 -> 0.55282393 | AA49: =+$D$49 -> 0.84012576 | AB49: =+(AB41/'Maj Production Summ'!AB$18)*1000 -> 0.55862264 | AC49: =+$D$49 -> 0.84012576 | AD49: =+(AD41/'Maj Production Summ'!AD$18)*1000 -> 0.69776445 | AE49: =+$D$49 -> 0.84012576 | AF49: =+(AF41/'Maj Production Summ'!AF$18)*1000 -> 0.57761555 | AG49: =+$D$49 -> 0.84012576 | AH49: =+(AH41/'Maj Production Summ'!AH$18)*1000 -> 1.1342155 | AI49: =+$D$49 -> 0.84012576 | AJ49: =+(AJ41/'Maj Production Summ'!AJ$18)*1000 -> 0.58031633 | AK49: =+$D$49 -> 0.84012576 | AL49: =+(AL41/'Maj Production Summ'!AL$18)*1000 -> 0.52356021 | AM49: =+$D$49 -> 0.84012576 | AN49: =+(AN41/'Maj Production Summ'!AN$18)*1000 -> 0.61720032 | AO49: =+$D$49 -> 0.84012576 | AP49: =+(AP41/'Maj Production Summ'!AP$18)*1000 -> 0.57318694 | AQ49: =+$D$49 -> 0.84012576 | AR49: =+(AR41/'Maj Production Summ'!AR$18)*1000 -> 0.47146805 | AS49: =+$D$49 -> 0.84012576 | AT49: =+(AT41/'Maj Production Summ'!AT$18)*1000 -> 0.56136106 | AU49: =+$D$49 -> 0.84012576 | AV49: =+(AV41/'Maj Production Summ'!AV$18)*1000 -> 0.66847619 | AW49: =+$D$49 -> 0.84012576 | AX49: =+(AX41/'Maj Production Summ'!AX$18)*1000 -> 0.57156781 | AY49: =+$D$49 -> 0.84012576 | AZ49: =+(AZ41/'Maj Production Summ'!AZ$18)*1000 -> 0.32026015 | BA49: =+$D$49 -> 0.84012576 | BB49: =+(BB41/'Maj Production Summ'!BB$18)*1000 -> 0.48141229 | BC49: =+$D$49 -> 0.84012576 | BD49: =+(BD41/'Maj Production Summ'!BD$18)*1000 -> 0.53503639 | BE49: =+$D$49 -> 0.84012576 | BF49: =+(BF41/'Maj Production Summ'!BF$18)*1000 -> 0.54786947 | BG49: 0.85 | BH49: 0.58802795 | BI49: 0.24 | BJ49: 0.65968939 | BK49: 0 | BL49: 0.46320883 | BM49: 0 | BN49: 0.41689987
B50: Total Fe-Mn | C50: Kg/TCS | D50: =SUM(D48:D49) -> 2.477358 | E50: =SUM(E48:E49) -> 2.477358 | F50: =SUM(F48:F49) -> 2.270312 | G50: =SUM(G48:G49) -> 2.477358 | H50: =SUM(H48:H49) -> 2.0072854 | I50: =SUM(I48:I49) -> 2.477358 | J50: =SUM(J48:J49) -> 2.1300191 | K50: =SUM(K48:K49) -> 2.477358 | ... BF50: =SUM(BF48:BF49) -> 2.0416365 | BG50: 2.5 | BH50: 1.9101675 | BI50: 1.5319835 | BJ50: 2.5288631 | BK50: 1.8 | BL50: 2.3497605 | BM50: 2.60138 | BN50: 2.1975739
B51: Si-Mn | C51: Kg/TCS | D51: 17.372968 | E51: =+$D$51 -> 17.372968 | F51: =+(F43/'Maj Production Summ'!F$18)*1000 -> 16.095063 | G51: =+$D$51 -> 17.372968 | H51: =+(H43/'Maj Production Summ'!H$18)*1000 -> 15.086334 | I51: =+$D$51 -> 17.372968 | J51: =+(J43/'Maj Production Summ'!J$18)*1000 -> 15.557028 | K51: =+$D$51 -> 17.372968 | L51: =+(L43/'Maj Production Summ'!L$18)*1000 -> 15.47732 | M51: =+$D$51 -> 17.372968 | N51: =+(N43/'Maj Production Summ'!N$18)*1000 -> 15.528786 | O51: =+$D$51 -> 17.372968 | P51: =+(P43/'Maj Production Summ'!P$18)*1000 -> 16.155356 | Q51: =+$D$51 -> 17.372968 | R51: =+(R43/'Maj Production Summ'!R$18)*1000 -> 15.697729 | S51: =+$D$51 -> 17.372968 | T51: =+(T43/'Maj Production Summ'!T$18)*1000 -> 15.095488 | U51: =+$D$51 -> 17.372968 | V51: =+(V43/'Maj Production Summ'!V$18)*1000 -> 15.576288 | W51: =+$D$51 -> 17.372968 | X51: =+(X43/'Maj Production Summ'!X$18)*1000 -> 13.273748 | Y51: =+$D$51 -> 17.372968 | Z51: =+(Z43/'Maj Production Summ'!Z$18)*1000 -> 14.894399 | AA51: =+$D$51 -> 17.372968 | AB51: =+(AB43/'Maj Production Summ'!AB$18)*1000 -> 15.204591 | AC51: =+$D$51 -> 17.372968 | AD51: =+(AD43/'Maj Production Summ'!AD$18)*1000 -> 14.747589 | AE51: =+$D$51 -> 17.372968 | AF51: =+(AF43/'Maj Production Summ'!AF$18)*1000 -> 15.14221 | AG51: =+$D$51 -> 17.372968 | AH51: =+(AH43/'Maj Production Summ'!AH$18)*1000 -> 13.862634 | AI51: =+$D$51 -> 17.372968 | AJ51: =+(AJ43/'Maj Production Summ'!AJ$18)*1000 -> 15.136001 | AK51: =+$D$51 -> 17.372968 | AL51: =+(AL43/'Maj Production Summ'!AL$18)*1000 -> 16.719874 | AM51: =+$D$51 -> 17.372968 | AN51: =+(AN43/'Maj Production Summ'!AN$18)*1000 -> 15.728931 | AO51: =+$D$51 -> 17.372968 | AP51: =+(AP43/'Maj Production Summ'!AP$18)*1000 -> 15.334959 | AQ51: =+$D$51 -> 17.372968 | AR51: =+(AR43/'Maj Production Summ'!AR$18)*1000 -> 16.420094 | AS51: =+$D$51 -> 17.372968 | AT51: =+(AT43/'Maj Production Summ'!AT$18)*1000 -> 15.461117 | AU51: =+$D$51 -> 17.372968 | AV51: =+(AV43/'Maj Production Summ'!AV$18)*1000 -> 16.267749 | AW51: =+$D$51 -> 17.372968 | AX51: =+(AX43/'Maj Production Summ'!AX$18)*1000 -> 15.537979 | AY51: =+$D$51 -> 17.372968 | AZ51: =+(AZ43/'Maj Production Summ'!AZ$18)*1000 -> 16.669951 | BA51: =+$D$51 -> 17.372968 | BB51: =+(BB43/'Maj Production Summ'!BB$18)*1000 -> 16.457844 | BC51: =+$D$51 -> 17.372968 | BD51: =+(BD43/'Maj Production Summ'!BD$18)*1000 -> 16.169989 | BE51: =+$D$51 -> 17.372968 | BF51: =+(BF43/'Maj Production Summ'!BF$18)*1000 -> 15.644724 | BG51: 18.35 | BH51: 16.183875 | BI51: 16.822447 | BJ51: 18.063011 | BK51: 16 | BL51: 18.431727 | BM51: 16.32641 | BN51: 15.648491
B52: LP Si-Mn | C52: Kg/TCS | D52: 0 | E52: =D52 -> 0 | F52: =+(F44/'Maj Production Summ'!F$18)*1000 -> 0 | G52: =F52 -> 0 | H52: =+(H44/'Maj Production Summ'!H$18)*1000 -> 0 | J52: =+(J44/'Maj Production Summ'!J$18)*1000 -> 0 | K52: =J52 -> 0 | L52: =+(L44/'Maj Production Summ'!L$18)*1000 -> 0 | M52: =D52 -> 0 | N52: =+(N44/'Maj Production Summ'!N$18)*1000 -> 0 | O52: =N52 -> 0 | P52: =+(P44/'Maj Production Summ'!P$18)*1000 -> 0 | R52: =+(R44/'Maj Production Summ'!R$18)*1000 -> 0 | S52: =R52 -> 0 | T52: =+(T44/'Maj Production Summ'!T$18)*1000 -> 0 | V52: =+(V44/'Maj Production Summ'!V$18)*1000 -> 0 | W52: =V52 -> 0 | X52: =+(X44/'Maj Production Summ'!X$18)*1000 -> 0 | Y52: =D52 -> 0 | Z52: =+(Z44/'Maj Production Summ'!Z$18)*1000 -> 0 | AA52: =D52 -> 0 | AB52: =+(AB44/'Maj Production Summ'!AB$18)*1000 -> 0 | AC52: =AB52 -> 0 | AD52: =+(AD44/'Maj Production Summ'!AD$18)*1000 -> 0 | AF52: =+(AF44/'Maj Production Summ'!AF$18)*1000 -> 0 | AG52: =D52 -> 0 | AH52: =+(AH44/'Maj Production Summ'!AH$18)*1000 -> 0 | AI52: =D52 -> 0 | AJ52: =+(AJ44/'Maj Production Summ'!AJ$18)*1000 -> 0 | AK52: =H52 -> 0 | AL52: =+(AL44/'Maj Production Summ'!AL$18)*1000 -> 0 | AM52: 0 | AN52: =+(AN44/'Maj Production Summ'!AN$18)*1000 -> 0 | AO52: =D52 -> 0 | AP52: =+(AP44/'Maj Production Summ'!AP$18)*1000 -> 0 | AQ52: =N52 -> 0 | AR52: =+(AR44/'Maj Production Summ'!AR$18)*1000 -> 0 | AS52: =D52 -> 0 | AT52: =+(AT44/'Maj Production Summ'!AT$18)*1000 -> 0 | AU52: =R52 -> 0 | AV52: =+(AV44/'Maj Production Summ'!AV$18)*1000 -> 0 | AW52: =H52 -> 0 | AX52: =+(AX44/'Maj Production Summ'!AX$18)*1000 -> 0 | AY52: =V52 -> 0 | AZ52: =+(AZ44/'Maj Production Summ'!AZ$18)*1000 -> 0 | BA52: =L52 -> 0 | BB52: =+(BB44/'Maj Production Summ'!BB$18)*1000 -> 0 | BC52: =N52 -> 0 | BD52: =+(BD44/'Maj Production Summ'!BD$18)*1000 -> 0 | BE52: =P52 -> 0 | BF52: =+(BF44/'Maj Production Summ'!BF$18)*1000 -> 0 | BG52: 0 | BH52: 0 | BI52: 0 | BJ52: 0.010205918
B53: Total Si-Mn | C53: Kg/TCS | D53: =SUM(D51:D52) -> 17.372968 | E53: =+$D$51 -> 17.372968 | F53: =SUM(F51:F52) -> 16.095063 | G53: =+$D$51 -> 17.372968 | H53: =SUM(H51:H52) -> 15.086334 | I53: =+$D$51 -> 17.372968 | J53: =SUM(J51:J52) -> 15.557028 | K53: =+$D$51 -> 17.372968 | L53: =SUM(L51:L52) -> 15.47732 | M53: =+$D$51 -> 17.372968 | N53: =SUM(N51:N52) -> 15.528786 | O53: =+$D$51 -> 17.372968 | P53: =SUM(P51:P52) -> 16.155356 | Q53: =+$D$51 -> 17.372968 | R53: =SUM(R51:R52) -> 15.697729 | S53: =+$D$51 -> 17.372968 | T53: =SUM(T51:T52) -> 15.095488 | U53: =+$D$51 -> 17.372968 | V53: =SUM(V51:V52) -> 15.576288 | W53: =+$D$51 -> 17.372968 | X53: =SUM(X51:X52) -> 13.273748 | Y53: =SUM(Y51:Y52) -> 17.372968 | Z53: =SUM(Z51:Z52) -> 14.894399 | AA53: =SUM(AA51:AA52) -> 17.372968 | AB53: =SUM(AB51:AB52) -> 15.204591 | AC53: =+$D$51 -> 17.372968 | AD53: =SUM(AD51:AD52) -> 14.747589 | AE53: =+$D$51 -> 17.372968 | AF53: =SUM(AF51:AF52) -> 15.14221 | AG53: =+$D$51 -> 17.372968 | AH53: =SUM(AH51:AH52) -> 13.862634 | AI53: =+$D$51 -> 17.372968 | AJ53: =SUM(AJ51:AJ52) -> 15.136001 | AK53: =+$D$51 -> 17.372968 | AL53: =SUM(AL51:AL52) -> 16.719874 | AM53: =SUM(AM51:AM52) -> 17.372968 | AN53: =SUM(AN51:AN52) -> 15.728931 | AO53: =+$D$51 -> 17.372968 | AP53: =SUM(AP51:AP52) -> 15.334959 | AQ53: =+$D$51 -> 17.372968 | AR53: =SUM(AR51:AR52) -> 16.420094 | AS53: =+$D$51 -> 17.372968 | AT53: =SUM(AT51:AT52) -> 15.461117 | AU53: =+$D$51 -> 17.372968 | AV53: =SUM(AV51:AV52) -> 16.267749 | AW53: =+$D$51 -> 17.372968 | AX53: =SUM(AX51:AX52) -> 15.537979 | AY53: =+$D$51 -> 17.372968 | AZ53: =SUM(AZ51:AZ52) -> 16.669951 | BA53: =+$D$51 -> 17.372968 | BB53: =SUM(BB51:BB52) -> 16.457844 | BC53: =+$D$51 -> 17.372968 | BD53: =SUM(BD51:BD52) -> 16.169989 | BE53: =+$D$51 -> 17.372968 | BF53: =SUM(BF51:BF52) -> 15.644724 | BG53: 18.35 | BH53: 16.183875 | BI53: 16.822447 | BJ53: 18.073217 | BK53: =SUM(BK51:BK52) -> 16 | BL53: =SUM(BL51:BL52) -> 18.431727 | BN53: =SUM(BN51:BN52) -> 15.648491
B54: Fe-Si | C54: Kg/TCS | D54: 2.1669657 | E54: =+$D$54 -> 2.1669657 | F54: =+(F46/'Maj Production Summ'!F$18)*1000 -> 2.2558207 | G54: =+$D$54 -> 2.1669657 | H54: =+(H46/'Maj Production Summ'!H$18)*1000 -> 2.3284511 | I54: =+$D$54 -> 2.1669657 | J54: =+(J46/'Maj Production Summ'!J$18)*1000 -> 2.2945602 | K54: =+$D$54 -> 2.1669657 | L54: =+(L46/'Maj Production Summ'!L$18)*1000 -> 2.1614439 | M54: =+$D$54 -> 2.1669657 | N54: =+(N46/'Maj Production Summ'!N$18)*1000 -> 2.2473953 | O54: =+$D$54 -> 2.1669657 | P54: =+(P46/'Maj Production Summ'!P$18)*1000 -> 1.9155175 | Q54: =+$D$54 -> 2.1669657 | R54: =+(R46/'Maj Production Summ'!R$18)*1000 -> 2.1579106 | S54: =+$D$54 -> 2.1669657 | T54: =+(T46/'Maj Production Summ'!T$18)*1000 -> 2.1715161 | U54: =+$D$54 -> 2.1669657 | V54: =+(V46/'Maj Production Summ'!V$18)*1000 -> 2.1606541 | W54: =+$D$54 -> 2.1669657 | X54: =+(X46/'Maj Production Summ'!X$18)*1000 -> 2.1203719 | Y54: =+$D$54 -> 2.1669657 | Z54: =+(Z46/'Maj Production Summ'!Z$18)*1000 -> 2.0649352 | AA54: =+$D$54 -> 2.1669657 | AB54: =+(AB46/'Maj Production Summ'!AB$18)*1000 -> 2.1541514 | AC54: =+$D$54 -> 2.1669657 | AD54: =+(AD46/'Maj Production Summ'!AD$18)*1000 -> 2.7640476 | AE54: =+$D$54 -> 2.1669657 | AF54: =+(AF46/'Maj Production Summ'!AF$18)*1000 -> 2.2374025 | AG54: =+$D$54 -> 2.1669657 | AH54: =+(AH46/'Maj Production Summ'!AH$18)*1000 -> 2.3944549 | AI54: =+$D$54 -> 2.1669657 | AJ54: =+(AJ46/'Maj Production Summ'!AJ$18)*1000 -> 2.2381645 | AK54: =+$D$54 -> 2.1669657 | AL54: =+(AL46/'Maj Production Summ'!AL$18)*1000 -> 2.2900438 | AM54: =+$D$54 -> 2.1669657 | AN54: =+(AN46/'Maj Production Summ'!AN$18)*1000 -> 2.5182633 | AO54: =+$D$54 -> 2.1669657 | AP54: =+(AP46/'Maj Production Summ'!AP$18)*1000 -> 2.2446813 | AQ54: =+$D$54 -> 2.1669657 | AR54: =+(AR46/'Maj Production Summ'!AR$18)*1000 -> 2.1947651 | AS54: =+$D$54 -> 2.1669657 | AT54: =+(AT46/'Maj Production Summ'!AT$18)*1000 -> 2.238878 | AU54: =+$D$54 -> 2.1669657 | AV54: =+(AV46/'Maj Production Summ'!AV$18)*1000 -> 2.2207766 | AW54: =+$D$54 -> 2.1669657 | AX54: =+(AX46/'Maj Production Summ'!AX$18)*1000 -> 2.2371532 | AY54: =+$D$54 -> 2.1669657 | AZ54: =+(AZ46/'Maj Production Summ'!AZ$18)*1000 -> 2.0940087 | BA54: =+$D$54 -> 2.1669657 | BB54: =+(BB46/'Maj Production Summ'!BB$18)*1000 -> 2.1684606 | BC54: =+$D$54 -> 2.1669657 | BD54: =+(BD46/'Maj Production Summ'!BD$18)*1000 -> 2.3066013 | BE54: =+$D$54 -> 2.1669657 | BF54: =+(BF46/'Maj Production Summ'!BF$18)*1000 -> 2.2236546 | BG54: 2.15 | BH54: 2.3091923 | BI54: 2.8192466 | BJ54: 2.0997064 | BK54: 3.2 | BL54: 2.1491301 | BM54: 3.03 | BN54: 2.2353142

Sheet Major techno all dept
C3: MAJOR TECHNO PARAMETERS 2025-26
C4: DEPARTMENTS | D4: ITEM | E4: Unit | F4: 2022-23 Actual | G4: ABP 2025-26 | H4: Apr'25 | J4: May'25 | L4: 2M | N4: Jun'25 | P4: QTR-1 | R4: Jul'25 | T4: 4M | V4: Aug'25 | X4: 5M | Z4: Sep'25 | AB4: QTR-2 | AD4: H1 | AF4: Oct'24 | AH4: 7M | AJ4: Nov'24 | AL4: 8M | AN4: Dec'24 | AP4: QTR-3 | AR4: 9M | AT4: Jan'25 | AV4: 10M | AX4: Feb'25 | AZ4: 11M | BB4: Mar'25 | BD4: QTR-4 | BF4: H2 | BH4: 2024-25
H5: ABP | I5: ACT | J5: ABP | K5: ACT | L5: ABP | M5: ACT | N5: ABP | O5: ACT | P5: ABP | Q5: ACT | R5: ABP | S5: ACT | T5: ABP | U5: ACT | V5: ABP | W5: ACT | X5: ABP | Y5: ACT | Z5: ABP | AA5: ACT | AB5: ABP | AC5: ACT | AD5: ABP | AE5: ACT | AF5: ABP | AG5: ACT | AH5: ABP | AI5: ACT | AJ5: ABP | AK5: ACT | AL5: ABP | AM5: ACT | AN5: ABP | AO5: ACT | AP5: ABP | AQ5: ACT | AR5: ABP | AS5: ACT | AT5: ABP | AU5: ACT | AV5: ABP | AW5: ACT | AX5: ABP | AY5: ACT | AZ5: ABP | BA5: ACT | BB5: ABP | BC5: ACT | BD5: ABP | BE5: ACT | BF5: ABP | BG5: ACT | BH5: ABP | BI5: ACT
C6: COKE OVENS | D6: B.F.Coke Yield | E6: % | F6: 69.459875 | G6: 70 | H6: =+'Maj Techno Summ'!E5 -> 70 | I6: =+'Maj Techno Summ'!F5 -> 70 | J6: =+'Maj Techno Summ'!G5 -> 70 | K6: =+'Maj Techno Summ'!H5 -> 70 | L6: =+'Maj Techno Summ'!I5 -> 70 | M6: =+'Maj Techno Summ'!J5 -> 70 | N6: =+'Maj Techno Summ'!K5 -> 70 | O6: =+'Maj Techno Summ'!L5 -> 70 | ... BI6: =+'Maj Techno Summ'!BF5 -> 70.168104
D7: ICC in Coal Blend
D8: (COB#10) | E8: % | F8: 89.651306 | G8: 92 | H8: =+'Maj Techno Summ'!E7 -> 92 | I8: =+'Maj Techno Summ'!F7 -> 89.466617 | J8: =+'Maj Techno Summ'!G7 -> 92 | K8: =+'Maj Techno Summ'!H7 -> 91.225794 | L8: =+'Maj Techno Summ'!I7 -> 92 | M8: =+'Maj Techno Summ'!J7 -> 90.36249 | N8: =+'Maj Techno Summ'!K7 -> 92 | O8: =+'Maj Techno Summ'!L7 -> 90.5 | ... BI8: =+'Maj Techno Summ'!BF7 -> 90.665596
D9: (COB#11) | E9: % | F9: 92.198587 | G9: 97 | H9: =+'Maj Techno Summ'!E8 -> 97 | I9: =+'Maj Techno Summ'!F8 -> 94.592173 | J9: =+'Maj Techno Summ'!G8 -> 97 | K9: =+'Maj Techno Summ'!H8 -> 94.999998 | L9: =+'Maj Techno Summ'!I8 -> 97 | M9: =+'Maj Techno Summ'!J8 -> 94.79983 | N9: =+'Maj Techno Summ'!K8 -> 97 | O9: =+'Maj Techno Summ'!L8 -> 95 | ... BI9: =+'Maj Techno Summ'!BF8 -> 95.710716
D10: Overall ICC in Blend | E10: % | F10: 91.262624 | G10: 95.32229 | H10: =+'Maj Techno Summ'!E9 -> 95.32229 | I10: =+'Maj Techno Summ'!F9 -> 92.782624 | J10: =+'Maj Techno Summ'!G9 -> 95.32229 | K10: =+'Maj Techno Summ'!H9 -> 93.667282 | L10: =+'Maj Techno Summ'!I9 -> 95.32229 | M10: =+'Maj Techno Summ'!J9 -> 93.233099 | N10: =+'Maj Techno Summ'!K9 -> 95.32229 | O10: =+'Maj Techno Summ'!L9 -> 93.437619 | ... BI10: =+'Maj Techno Summ'!BF9 -> 93.955291
D11: Soft Coal in Blend | E11: % | F11: 23.372863 | G11: 25 | H11: =+$G$11 -> 25 | I11: =+'COKE OVENS'!F214 -> 24.618125 | J11: =+$G$11 -> 25 | K11: =+'COKE OVENS'!H214 -> 24.70623 | L11: =+$G$11 -> 25 | M11: =+'COKE OVENS'!J214 -> 24.662989 | N11: =+$G$11 -> 25 | O11: =+'COKE OVENS'!L214 -> 24.694394 | P11: =+$G$11 -> 25 | Q11: =+'COKE OVENS'!N214 -> 24.673362 | R11: =+$G$11 -> 25 | S11: =+'COKE OVENS'!P214 -> 24.688884 | T11: =+$G$11 -> 25 | U11: =+'COKE OVENS'!R214 -> 24.677316 | V11: =+$G$11 -> 25 | W11: =+'COKE OVENS'!T214 -> 24.351611 | X11: =+$G$11 -> 25 | Y11: =+'COKE OVENS'!V214 -> 24.610878 | Z11: =+$G$11 -> 25 | AA11: =+'COKE OVENS'!X214 -> 24.350934 | AB11: =+$G$11 -> 25 | AC11: =+'COKE OVENS'!Z214 -> 24.464516 | AD11: =+$G$11 -> 25 | AE11: =+'COKE OVENS'!AB214 -> 24.567965 | AF11: =+$G$11 -> 25 | AG11: =+'COKE OVENS'!AD214 -> 24.560108 | AH11: =+$G$11 -> 25 | AI11: =+'COKE OVENS'!AF214 -> 24.566794 | AJ11: =+$G$11 -> 25 | AK11: =+'COKE OVENS'!AH214 -> 23.967065 | AL11: =+$G$11 -> 25 | AM11: =+'COKE OVENS'!AJ214 -> 24.493806 | AN11: =+$G$11 -> 25 | AO11: =+'COKE OVENS'!AL214 -> 24.934342 | AP11: =+$G$11 -> 25 | AQ11: =+'COKE OVENS'!AN214 -> 24.497929 | AR11: =+$G$11 -> 25 | AS11: =+'COKE OVENS'!AP214 -> 24.544279 | AT11: =+$G$11 -> 25 | AU11: =+'COKE OVENS'!AR214 -> 22.433433 | AV11: =+$G$11 -> 25 | AW11: =+'COKE OVENS'!AT214 -> 24.330506 | AX11: =+$G$11 -> 25 | AY11: =+'COKE OVENS'!AV214 -> 22.181135 | AZ11: =+$G$11 -> 25 | BA11: =+'COKE OVENS'!AX214 -> 24.153146 | BB11: =+$G$11 -> 25 | BC11: =+'COKE OVENS'!AZ214 -> 26.158141 | BD11: =+'COKE OVENS'!BA214 -> 25.350686 | BE11: =+'COKE OVENS'!BB214 -> 23.596787 | BF11: =+'COKE OVENS'!BC214 -> 25.350686 | BG11: =+'COKE OVENS'!BD214 -> 24.060346 | BH11: =+'COKE OVENS'!BE214 -> 25.181782 | BI11: =+'COKE OVENS'!BF214 -> 24.314991
D12: Average Coking Time | E12: Hrs | G12: 18.469687 | H12: =+'COKE OVENS'!E62 -> 0 | I12: =+'COKE OVENS'!F62 -> 0 | J12: =+'COKE OVENS'!G62 -> 0 | K12: =+'COKE OVENS'!H62 -> 0 | L12: =+'COKE OVENS'!I62 -> 0 | M12: =+'COKE OVENS'!J62 -> 0 | N12: =+'COKE OVENS'!K62 -> 0 | O12: =+'COKE OVENS'!L62 -> 0 | ... BI12: =+'COKE OVENS'!BF62 -> 0
D14: COB#10
