Workbook
Name _1: #REF!
Name _1: #REF!
Name _1: #REF!
Name _1: #REF!
Name _1: #REF!
Name _1: #REF!
Name _1: #REF!
Name _1: #REF!
Name _1: #REF!
Name _2: #REF!
Name _2: #REF!
Name _2: #REF!
Name _2: #REF!
Name _2: #REF!
Name _2: #REF!
Name _2: #REF!
Name _2: #REF!
Name _2: #REF!
Name _3: #REF!
Name _3: #REF!
Name _3: #REF!
Name _3: #REF!
Name _3: #REF!
Name _3: #REF!
Name _3: #REF!
Name _3: #REF!
Name _4: #REF!
Name _4: #REF!
Name _4: #REF!
Name a: #REF!
Name a: #REF!
Name a: #REF!
Name a: #REF!
Name a: #REF!
Name AA: #REF!
Name AA: #REF!
Name AA: #REF!
Name AA: #REF!
Name AB: #REF!
Name AB: #REF!
Name AB: #REF!
Name AB: #REF!
Name AC: #REF!
Name AC: #REF!
Name AC: #REF!
Name AD: #REF!
Name AD: #REF!
Name AD: #REF!
Name AE: #REF!
Name AE: #REF!
Name AE: #REF!
Name AF: #REF!
Name AF: #REF!
Name AF: #REF!
Name AG: #REF!
Name AG: #REF!
Name AG: #REF!
Name AH: #REF!
Name AH: #REF!
Name AH: #REF!

Sheet Maj Production Summ
B1: MAJOR PRODUCTION SUMMARY | D1: 322.5 | E1: 29 | F1: 30 | G1: 30 | H1: 29.375 | I1: 59 | J1: 59.375 | K1: 19 | L1: 25.083333 | M1: 78 | N1: 84.458333 | O1: 9.5 | P1: 30.25 | Q1: 87.5 | R1: 114.70833 | S1: 30 | T1: 29.583333 | U1: 117.5 | V1: 144.29167 | W1: 29 | X1: 29.916667 | Y1: 68.5 | Z1: 89.75 | AA1: 146.5 | AB1: 174.20833 | AC1: 30 | AD1: 29.965417 | AE1: 176.5 | AF1: 204.17375 | AG1: 29 | AH1: 1 | AI1: 205.5 | AJ1: 205.17375 | AK1: 30 | AL1: 30.75 | AM1: 89 | AN1: 61.715417 | AO1: 235.5 | AP1: 235.92375 | AQ1: 30 | AR1: 29.875 | AS1: 265.5 | AT1: 265.79875 | AU1: 27 | AV1: 27.1875 | AW1: 292.5 | AX1: 292.98625 | AY1: 30 | AZ1: 30.229167 | BA1: 87 | BB1: 87.291667 | BC1: 176 | BD1: 149.00708 | BE1: 322.5 | BF1: 323.21542
D2: 365 | E2: 30 | F2: 30 | G2: 31 | H2: 31 | I2: 61 | J2: 61 | K2: 30 | L2: 30 | M2: 91 | N2: 91 | O2: 31 | P2: 31 | Q2: 122 | R2: 122 | S2: 31 | T2: 31 | U2: 153 | V2: 153 | W2: 30 | X2: 30 | Y2: 92 | Z2: 92 | AA2: 183 | AB2: 183 | AC2: 31 | AD2: 31 | AE2: 214 | AF2: 214 | AG2: 30 | AH2: 30 | AI2: 244 | AJ2: 244 | AK2: 31 | AL2: 31 | AM2: 92 | AN2: 92 | AO2: 275 | AP2: 275 | AQ2: 31 | AR2: 31 | AS2: 306 | AT2: 306 | AU2: 28 | AV2: 28 | AW2: 334 | AX2: 334 | AY2: 31 | AZ2: 31 | BA2: 90 | BB2: 90 | BC2: 182 | BD2: 182 | BE2: 365 | BF2: 365 | BL2: 365 | BM2: 365 | BN2: 366 | BO2: 366
B3: ITEM | C3: Unit | D3: 2024-25 ABP | E3: Apr'24 | G3: May'24 | I3: 2M | K3: Jun'24 | M3: QTR-1 | O3: Jul'24 | Q3: 4M | S3: Aug'24 | U3: 5M | W3: Sep'24 | Y3: QTR 2 | AA3: H1 | AC3: Oct'24 | AE3: 7M | AG3: Nov'24 | AI3: 8M | AK3: Dec'24 | AM3: QTR 3 | AO3: 9M | AQ3: Jan'25 | AS3: 10M | AU3: Feb'25 | AW3: 11M | AY3: Mar'25 | BA3: QTR 4 | BC3: H2 | BE3: 2024-25 | BG3: 2023-24 | BI3: 2022-23 | BJ3: 2021-22 | BL3: 2020-21 | BN3: 2019-20
E4: ABP | F4: ACT | G4: ABP | H4: ACT | I4: ABP | J4: ACT | K4: ABP | L4: ACT | M4: ABP | N4: ACT | O4: ABP | P4: ACT | Q4: ABP | R4: ACT | S4: ABP | T4: ACT | U4: ABP | V4: ACT | W4: ABP | X4: ACT | Y4: ABP | Z4: ACT | AA4: ABP | AB4: ACT | AC4: ABP | AD4: ACT | AE4: ABP | AF4: ACT | AG4: ABP | AH4: ACT | AI4: ABP | AJ4: ACT | AK4: ABP | AL4: ACT | AM4: ABP | AN4: ACT | AO4: ABP | AP4: ACT | AQ4: ABP | AR4: ACT | AS4: ABP | AT4: ACT | AU4: ABP | AV4: ACT | AW4: ABP | AX4: ACT | AY4: ABP | AZ4: ACT | BA4: ABP | BB4: ACT | BC4: ABP | BD4: ACT | BE4: ABP | BF4: ACT | BG4: ABP | BH4: ACT | BI4: ACT | BJ4: ABP | BK4: ACT | BL4: ABP | BM4: ACT | BN4: ABP | BO4: ACT
B5: COKE OVENS PUSHING
B6: (COB#10) | C6: Nos/ day | D6: 96.420548 | E6: 97.8 | F6: 98.766667 | G6: 97.8 | H6: 98.709677 | I6: 97.8 | J6: 98.737705 | K6: 97.456667 | L6: 97.4 | M6: 97.686813 | N6: 98.296703 | O6: 96 | P6: 97.580645 | Q6: 97.258197 | R6: 98.114754 | S6: 96 | T6: 98 | U6: 97.003268 | V6: 98.091503 | W6: 96 | X6: 98 | Y6: 96 | Z6: 97.858696 | AA6: 96.838798 | AB6: 98.076503 | AC6: 96 | AD6: 98 | AE6: 96.71729 | AF6: 98.065421 | AG6: 96 | AH6: 94.3 | AI6: 96.629098 | AJ6: 97.602459 | AK6: 96 | AL6: 98 | AM6: 96 | AN6: 96.793478 | AO6: 96.558182 | AP6: 97.647273 | AQ6: 96 | AR6: 98 | AS6: 96.501634 | AT6: 97.683007 | AU6: 96 | AV6: 97.678571 | AW6: 96.459581 | AX6: 97.682635 | AY6: 96 | AZ6: 98 | BA6: 96 | BB6: 97.9 | BC6: 96 | BD6: 97.340659 | BE6: 96.420548 | BF6: 97.709589 | BG6: 99 | BH6: 98.976067 | BI6: 98.783562 | BJ6: 99 | BK6: 97.824658 | BL6: 95.547945 | BM6: 95.342466 | BN6: 97 | BO6: 97.10959
B7: (COB#11) | C7: Nos/ day | D7: 98.167671 | E7: 98 | F7: 99 | G7: 98 | H7: 98.516129 | I7: 98 | J7: 98.754098 | K7: 96.006667 | L7: 96.7 | M7: 97.342857 | N7: 98.076923 | O7: 94.064516 | P7: 98.806452 | Q7: 96.509836 | R7: 98.262295 | S7: 99 | T7: 98.645161 | U7: 97.014379 | V7: 98.339869 | W7: 99 | X7: 98.3 | Y7: 97.336957 | Z7: 98.586957 | AA7: 97.339891 | AB7: 98.333333 | AC7: 99 | AD7: 97.83871 | AE7: 97.580374 | AF7: 98.261682 | AG7: 99 | AH7: 94 | AI7: 97.754918 | AJ7: 97.737705 | AK7: 99 | AL7: 98.483871 | AM7: 99 | AN7: 96.804348 | AO7: 97.895273 | AP7: 97.821818 | AQ7: 99 | AR7: 98.483871 | AS7: 98.00719 | AT7: 97.888889 | AU7: 99 | AV7: 98.392857 | AW7: 98.090419 | AX7: 97.931138 | AY7: 99 | AZ7: 98.645161 | BA7: 99 | BB7: 98.511111 | BC7: 99 | BD7: 97.648352 | BE7: 98.167671 | BF7: 97.991781 | BG7: 98.000061 | BH7: 96.670251 | BI7: 92.210959 | BJ7: 99 | BK7: 96.816438 | BL7: 94.2 | BM7: 90.778082 | BN7: 97 | BO7: 95.710246
B8: Overall Equiv. Ovens Pushed/ Day | C8: Nos/ day | D8: 276.48974 | E8: 277.56163 | F8: 280.3626 | G8: 277.56163 | H8: 279.41804 | I8: 277.56163 | J8: 279.88258 | K8: 273.56192 | L8: 274.77703 | M8: 276.24304 | N8: 278.19943 | O8: 268.54276 | P8: 278.82155 | Q8: 274.28641 | R8: 278.35751 | S8: 277.59593 | T8: 278.94505 | U8: 274.95697 | V8: 278.47655 | W8: 277.59593 | X8: 278.31192 | Y8: 274.54541 | Z8: 278.69698 | AA8: 275.38959 | AB8: 278.44956 | AC8: 277.59593 | AD8: 277.46577 | AE8: 275.7092 | AF8: 278.30705 | AG8: 277.59593 | AH8: 266.72442 | AI8: 275.94117 | AJ8: 276.88296 | AK8: 277.59593 | AL8: 278.64919 | AM8: 277.59593 | AN8: 274.36192 | AO8: 276.12771 | AP8: 277.08206 | AQ8: 277.59593 | AR8: 278.64919 | AS8: 276.27645 | AT8: 277.24082 | AU8: 277.59593 | AV8: 278.16082 | AW8: 276.38706 | AX8: 277.31795 | AY8: 277.59593 | AZ8: 278.94505 | BA8: 277.59593 | BB8: 278.59916 | BC8: 277.59593 | BD8: 276.45726 | BE8: 276.48974 | BF8: 277.45614 | BG8: 278.76174 | BH8: 276.29853 | BI8: 267.92634 | BJ8: 280.59593 | BK8: 275.41528 | BL8: 268.33922 | BM8: 261.85691 | BN8: 274.92733 | BO8: 272.67112
B9: (COB#10) | C9: Nos | D9: 35193.5 | E9: 2934 | F9: 2963 | G9: 3031.8 | H9: 3060 | I9: 5965.8 | J9: 6023 | K9: 2923.7 | L9: 2922 | M9: 8889.5 | N9: 8945 | O9: 2976 | P9: 3025 | Q9: 11865.5 | R9: 11970 | S9: 2976 | T9: 3038 | U9: 14841.5 | V9: 15008 | W9: 2880 | X9: 2940 | Y9: 8832 | Z9: 9003 | AA9: 17721.5 | AB9: 17948 | AC9: 2976 | AD9: 3038 | AE9: 20697.5 | AF9: 20986 | AG9: 2880 | AH9: 2829 | AI9: 23577.5 | AJ9: 23815 | AK9: 2976 | AL9: 3038 | AM9: 8832 | AN9: 8905 | AO9: 26553.5 | AP9: 26853 | AQ9: 2976 | AR9: 3038 | AS9: 29529.5 | AT9: 29891 | AU9: 2688 | AV9: 2735 | AW9: 32217.5 | AX9: 32626 | AY9: 2976 | AZ9: 3038 | BA9: 8640 | BB9: 8811 | BC9: 17472 | BD9: 17716 | BE9: 35193.5 | BF9: 35664 | BG9: 36234 | BH9: 36225 | BI9: 36056 | BJ9: 36135 | BK9: 35706 | BL9: 34875 | BM9: 34800 | BN9: 35502 | BO9: 35543
B10: (COB#11) | C10: Nos | D10: 35831.2 | E10: 2940 | F10: 2970 | G10: 3038 | H10: 3054 | I10: 5978 | J10: 6024 | K10: 2880.2 | L10: 2901 | M10: 8858.2 | N10: 8925 | O10: 2916 | P10: 3063 | Q10: 11774.2 | R10: 11988 | S10: 3069 | T10: 3058 | U10: 14843.2 | V10: 15046 | W10: 2970 | X10: 2949 | Y10: 8955 | Z10: 9070 | AA10: 17813.2 | AB10: 17995 | AC10: 3069 | AD10: 3033 | AE10: 20882.2 | AF10: 21028 | AG10: 2970 | AH10: 2820 | AI10: 23852.2 | AJ10: 23848 | AK10: 3069 | AL10: 3053 | AM10: 9108 | AN10: 8906 | AO10: 26921.2 | AP10: 26901 | AQ10: 3069 | AR10: 3053 | AS10: 29990.2 | AT10: 29954 | AU10: 2772 | AV10: 2755 | AW10: 32762.2 | AX10: 32709 | AY10: 3069 | AZ10: 3058 | BA10: 8910 | BB10: 8866 | BC10: 18018 | BD10: 17772 | BE10: 35831.2 | BF10: 35767 | BG10: 35868.022 | BH10: 35382 | BI10: 33657 | BJ10: 36135 | BK10: 35338 | BL10: 34383 | BM10: 33134 | BN10: 35502 | BO10: 35030
B11: Overall Equiv. Ovens Pushed | C11: Nos | D11: 100918.75 | E11: 8326.8488 | F11: 8410.8779 | G11: 8604.4105 | H11: 8661.9593 | I11: 16931.259 | J11: 17072.837 | K11: 8206.8576 | L11: 8243.311 | M11: 25138.117 | N11: 25316.148 | O11: 8324.8256 | P11: 8643.468 | Q11: 33462.942 | R11: 33959.616 | S11: 8605.4738 | T11: 8647.2965 | U11: 42068.416 | V11: 42606.913 | W11: 8327.8779 | X11: 8349.3576 | Y11: 25258.177 | Z11: 25640.122 | AA11: 50396.294 | AB11: 50956.27 | AC11: 8605.4738 | AD11: 8601.439 | AE11: 59001.768 | AF11: 59557.709 | AG11: 8327.8779 | AH11: 8001.7326 | AI11: 67329.646 | AJ11: 67559.442 | AK11: 8605.4738 | AL11: 8638.125 | AM11: 25538.826 | AN11: 25241.297 | AO11: 75935.12 | AP11: 76197.567 | AQ11: 8605.4738 | AR11: 8638.125 | AS11: 84540.594 | AT11: 84835.692 | AU11: 7772.686 | AV11: 7788.5029 | AW11: 92313.28 | AX11: 92624.195 | AY11: 8605.4738 | AZ11: 8647.2965 | BA11: 24983.634 | BB11: 25073.924 | BC11: 50522.459 | BD11: 50315.221 | BE11: 100918.75 | BF11: 101271.49 | BG11: 102026.8 | BH11: 101126.28 | BI11: 97793.113 | BJ11: 102417.51 | BK11: 100526.58 | BL11: 97943.817 | BM11: 95577.773 | BN11: 100623.4 | BO11: 99798.61
B12: BF COKE
B13: COB#10 | C13: Mt | D13: 423729.74 | E13: 35325.36 | F13: 35684.713 | G13: 36502.872 | H13: 36852.926 | I13: 71828.232 | J13: 72537.639 | K13: 35201.348 | L13: 35185.906 | M13: 107029.58 | N13: 107723.54 | O13: 35831.04 | P13: 36682.905 | Q13: 142860.62 | R13: 144406.45 | S13: 35831.04 | T13: 36838.788 | U13: 178691.66 | V13: 181245.24 | W13: 34675.2 | X13: 35650.44 | Y13: 106337.28 | Z13: 109172.13 | AA13: 213366.86 | AB13: 216895.68 | AC13: 35831.04 | AD13: 36839 | AE13: 249197.9 | AF13: 253734.68 | AG13: 34675.2 | AH13: 34299.588 | AI13: 283873.1 | AJ13: 288034.27 | AK13: 35831.04 | AL13: 36582.745 | AM13: 106337.28 | AN13: 107721.33 | AO13: 319704.14 | AP13: 324617.01 | AQ13: 35831.04 | AR13: 36888.429 | AS13: 355535.18 | AT13: 361505.44 | AU13: 32363.52 | AV13: 33164.61 | AW13: 387898.7 | AX13: 394670.05 | AY13: 35831.04 | AZ13: 36838.788 | BA13: 104025.6 | BB13: 106891.83 | BC13: 210362.88 | BD13: 214613.16 | BE13: 423729.74 | BF13: 431508.84 | BG13: 433141.24 | BH13: 432382.85 | BI13: 430769.03 | BJ13: 438172.79 | BK13: 428806 | BL13: 425506 | BM13: 430922.2 | BN13: 406071.88 | BO13: 412610.14
B14: COB#11 | C14: Mt | D14: 791332.05 | E14: 64929.9 | F14: 65611.191 | G14: 67094.23 | H14: 67466.861 | I14: 132024.13 | J14: 133078.05 | K14: 63609.217 | L14: 64077.738 | M14: 195633.35 | N14: 197155.79 | O14: 64399.86 | P14: 68132.803 | Q14: 260033.21 | R14: 265288.59 | S14: 67778.865 | T14: 68018.33 | U14: 327812.07 | V14: 333306.92 | W14: 65592.45 | X14: 65593.87 | Y14: 197771.17 | Z14: 201745 | AA14: 393404.52 | AB14: 398900.79 | AC14: 67778.865 | AD14: 67418 | AE14: 461183.39 | AF14: 466318.79 | AG14: 65592.45 | AH14: 62715.658 | AI14: 526775.84 | AJ14: 529034.45 | AK14: 67778.865 | AL14: 67435.137 | AM14: 201150.18 | AN14: 197568.8 | AO14: 594554.7 | AP14: 596469.59 | AQ14: 67778.865 | AR14: 67998.622 | AS14: 662333.57 | AT14: 664468.21 | AU14: 61219.62 | AV14: 61278.776 | AW14: 723553.19 | AX14: 725746.98 | AY14: 67778.865 | AZ14: 68018.33 | BA14: 196777.35 | BB14: 197295.73 | BC14: 397927.53 | BD14: 394864.52 | BE14: 791332.05 | BF14: 793765.31 | BG14: 786486.6 | BH14: 774691.65 | BI14: 737579.38 | BJ14: 803741.8 | BK14: 778192 | BL14: 770203 | BM14: 752591.4 | BN14: 744858.59 | BO14: 745859.84
B15: Total BF COKE | C15: Mt | D15: 1215061.8 | E15: 100255.26 | F15: 101295.9 | G15: 103597.1 | H15: 104319.79 | I15: 203852.36 | J15: 205615.69 | K15: 98810.565 | L15: 99263.643 | M15: 302662.93 | N15: 304879.33 | O15: 100230.9 | P15: 104815.71 | Q15: 402893.83 | R15: 409695.04 | S15: 103609.9 | T15: 104857.12 | U15: 506503.73 | V15: 514552.16 | W15: 100267.65 | X15: 101244.31 | Y15: 304108.45 | Z15: 310917.14 | AA15: 606771.38 | AB15: 615796.47 | AC15: 103609.9 | AD15: 104257 | AE15: 710381.29 | AF15: 720053.47 | AG15: 100267.65 | AH15: 97015.246 | AI15: 810648.94 | AJ15: 817068.72 | AK15: 103609.9 | AL15: 104017.88 | AM15: 307487.46 | AN15: 305290.13 | AO15: 914258.84 | AP15: 921086.6 | AQ15: 103609.9 | AR15: 104887.05 | AS15: 1017868.7 | AT15: 1025973.6 | AU15: 93583.14 | AV15: 94443.386 | AW15: 1111451.9 | AX15: 1120417 | AY15: 103609.9 | AZ15: 104857.12 | BA15: 300802.95 | BB15: 304187.55 | BC15: 608290.41 | BD15: 609477.68 | BE15: 1215061.8 | BF15: 1225274.2 | BG15: 1219627.8 | BH15: 1207074.5 | BI15: 1168348.4 | BJ15: 1241914.6 | BK15: 1206998 | BL15: 1195709 | BM15: 1183513.6 | BN15: 1150930.5 | BO15: 1158470
B16: SINTER | C16: Mt | D16: 4387544.5 | E16: 387249.31 | F16: 364112 | G16: 403890.95 | H16: 343877 | I16: 791140.26 | J16: 707989 | K16: 287450.61 | L16: 260737 | M16: 1078590.9 | N16: 968726 | O16: 172935.2 | P16: 393033 | Q16: 1251526.1 | R16: 1361759 | S16: 391249.31 | T16: 367891 | U16: 1642775.4 | V16: 1729650 | W16: 374607.67 | X16: 370427 | Y16: 938792.18 | Z16: 1131351 | AA16: 2017383.1 | AB16: 2100077 | AC16: 403051.36 | AD16: 372857 | AE16: 2420434.4 | AF16: 2472934 | AG16: 392409.72 | AH16: 24407 | AI16: 2812844.1 | AJ16: 2497341 | AK16: 403051.36 | AL16: 361604 | AM16: 1198512.4 | AN16: 758868 | AO16: 3215895.5 | AP16: 2858945 | AQ16: 403051.36 | AR16: 369250 | AS16: 3618946.9 | AT16: 3228195 | AU16: 365546.23 | AV16: 342499 | AW16: 3984493.1 | AX16: 3570694 | AY16: 403051.36 | AZ16: 410020 | BA16: 1171649 | BB16: 1121769 | BC16: 2370161.4 | BD16: 1880637 | BE16: 4387544.5 | BF16: 3980714 | BG16: 4499999.9 | BH16: 4398445 | BI16: 4395665 | BJ16: 4183927.8 | BK16: 4277831 | BL16: 3665891.3 | BM16: 3629577 | BN16: 3903932.5 | BO16: 3709525
B17: HOT METAL | C17: Mt | D17: 2650000 | E17: 240000 | F17: 236134 | G17: 248000 | H17: 209171.6 | I17: 488000 | J17: 445305.6 | K17: 149000 | L17: 167351.5 | M17: 637000 | N17: 612657.1 | O17: 74000 | P17: 250033.8 | Q17: 711000 | R17: 862690.9 | S17: 240000 | T17: 245401.9 | U17: 951000 | V17: 1108092.8 | W17: 232000 | X17: 245769.8 | Y17: 546000 | Z17: 741205.5 | AA17: 1183000 | AB17: 1353862.6 | AC17: 250000 | AD17: 237886.3 | AE17: 1433000 | AF17: 1591748.9 | AG17: 242000 | AH17: 8246.5 | AI17: 1675000 | AJ17: 1599995.4 | AK17: 250000 | AL17: 257290.9 | AM17: 742000 | AN17: 503423.7 | AO17: 1925000 | AP17: 1857286.3 | AQ17: 250000 | AR17: 261845.4 | AS17: 2175000 | AT17: 2119131.7 | AU17: 225000 | AV17: 239624 | AW17: 2400000 | AX17: 2358755.7 | AY17: 250000 | AZ17: 263830 | BA17: 725000 | BB17: 765299.4 | BC17: 1467000 | BD17: 1268723.1 | BE17: 2650000 | BF17: 2622585.7 | BG17: 2800000 | BH17: 2721268.1 | BI17: 2592119.6 | BJ17: 2650001 | BK17: 2406785.7 | BL17: 2496672.2 | BM17: 2092798 | BN17: 2700000 | BO17: 2505193
B18: CRUDE STEEL | C18: Mt | D18: 2489528.3 | E18: 226056.6 | F18: 220127 | G18: 233603.77 | H18: 197854 | I18: 459660.38 | J18: 417981 | K18: 139811.32 | L18: 144189 | M18: 599471.7 | N18: 562170 | O18: 63679.245 | P18: 234513 | Q18: 663150.94 | R18: 796683 | S18: 226056.6 | T18: 231517 | U18: 889207.55 | V18: 1028200 | W18: 218509.43 | X18: 231269 | Y18: 508245.28 | Z18: 697299 | AA18: 1107717 | AB18: 1259469 | AC18: 235490.57 | AD18: 222138 | AE18: 1343207.5 | AF18: 1481607 | AG18: 227943.4 | AH18: 7935 | AI18: 1571150.9 | AJ18: 1489542 | AK18: 235490.57 | AL18: 234930 | AM18: 698924.53 | AN18: 465003 | AO18: 1806641.5 | AP18: 1724472 | AQ18: 235490.57 | AR18: 246040 | AS18: 2042132.1 | AT18: 1970512 | AU18: 211905.66 | AV18: 222895 | AW18: 2254037.7 | AX18: 2193407 | AY18: 235490.57 | AZ18: 243552 | BA18: 682886.79 | BB18: 712487 | BC18: 1381811.3 | BD18: 1177490 | BE18: 2489528.3 | BF18: 2436959 | BG18: 2620075.5 | BH18: 2528925 | BI18: 2422324.3 | BJ18: 2451737.7 | BK18: 2227867 | BL18: 2297163.5 | BM18: 1847433 | BN18: 2500000 | BO18: 2083412
B19: Caster #(1+2 ) | C19: Mt | D19: 1880445.4 | E19: 171825 | F19: 167017 | G19: 177750 | H19: 142026 | I19: 349575 | J19: 309043 | K19: 106020 | L19: 113537 | M19: 455595 | N19: 422580 | O19: 50085 | P19: 175693.36 | Q19: 505680 | R19: 598273.36 | S19: 168750 | T19: 173992 | U19: 674430 | V19: 772265.36 | W19: 163125 | X19: 174717 | Y19: 381960 | Z19: 524402.36 | AA19: 837555 | AB19: 946982.36 | AC19: 177750 | AD19: 168140 | AE19: 1015305 | AF19: 1115122.4 | AG19: 171825 | AH19: 7935 | AI19: 1187130 | AJ19: 1123057.4 | AK19: 177840.45 | AL19: 176215.37 | AM19: 527415.45 | AN19: 352290.37 | AO19: 1364970.4 | AP19: 1299272.7 | AQ19: 177750 | AR19: 183526 | AS19: 1542720.4 | AT19: 1482798.7 | AU19: 159975 | AV19: 163924 | AW19: 1702695.4 | AX19: 1646722.7 | AY19: 177750 | AZ19: 171866 | BA19: 515475 | BB19: 519316 | BC19: 1042890.4 | BD19: 871606.37 | BE19: 1880445.4 | BF19: 1818588.7 | BH19: 1922629.6 | BI19: 1903696 | BK19: 1777963.7
B20: Caster #3 | C20: Mt | D20: 609082.85 | E20: 54231.604 | F20: 53110 | G20: 55854 | H20: 55827.86 | I20: 110085.6 | J20: 108937.86 | K20: 33791.32 | L20: 30651.96 | M20: 143876.92 | N20: 139589.82 | O20: 13594.245 | P20: 58819.91 | Q20: 157471.17 | R20: 198409.73 | S20: 57306.6 | T20: 57524.85 | U20: 214777.77 | V20: 255934.58 | W20: 55384.43 | X20: 56551.8 | Y20: 126285.28 | Z20: 172896.56 | AA20: 270162.2 | AB20: 312486.38 | AC20: 57740.566 | AD20: 53997.96 | AE20: 327902.77 | AF20: 366484.34 | AG20: 56118.396 | AH20: 0 | AI20: 384021.16 | AJ20: 366484.34 | AK20: 57650.116 | AL20: 58714.36 | AM20: 171509.08 | AN20: 112712.32 | AO20: 441671.28 | AP20: 425198.7 | AQ20: 57740.566 | AR20: 62514.11 | AS20: 499411.84 | AT20: 487712.81 | AU20: 51930.66 | AV20: 58971.81 | AW20: 551342.5 | AX20: 546684.62 | AY20: 57740.566 | AZ20: 71685.7 | BA20: 167411.79 | BB20: 193171.62 | BC20: 338920.87 | BD20: 305883.94 | BE20: 609083.07 | BF20: 618370.32 | BH20: 606294.79 | BI20: 518629.33 | BK20: 449903.88
B21: Avg Heats Cast per Day | C21: Nos. / day | D21: 51.463117 | E21: 51.967035 | F21: 48.6 | G21: 51.91195 | H21: 44.187234 | I21: 51.939026 | J21: 46.416842 | K21: 49.056604 | L21: 37.79402 | M21: 51.236897 | N21: 43.855945 | O21: 44.68719 | P21: 51.041322 | Q21: 50.525786 | R21: 45.750817 | S21: 50.234801 | T21: 51.346479 | U21: 50.451492 | V21: 46.898065 | W21: 50.232053 | X21: 50.473538 | Y21: 49.464261 | Z21: 50.952646 | AA21: 50.408054 | AB21: 47.512078 | AC21: 52.331237 | AD21: 48.422487 | AE21: 50.73494 | AF21: 47.645694 | AG21: 52.400781 | AH21: 52 | AI21: 50.970022 | AJ21: 47.666916 | AK21: 52.331237 | AL21: 49.788618 | AM21: 52.353897 | AN21: 49.161136 | AO21: 51.143425 | AP21: 47.943456 | AQ21: 52.331237 | AR21: 53.523013 | AS21: 51.277641 | AT21: 48.570582 | AU21: 52.322385 | AV21: 53.075862 | AW21: 51.374079 | AX21: 48.988647 | AY21: 52.331237 | AZ21: 52.002757 | BA21: 52.32849 | BB21: 52.857279 | BC21: 52.341338 | BD21: 51.326419 | BE21: 51.463117 | BF21: 49.270546 | BG21: 50.337665 | BH21: 48.130368 | BI21: 45.269663 | BJ21: 44.780041 | BK21: 40.065753 | BL21: 41.920046 | BM21: 33.309589 | BN21: 47.014645 | BO21: 38.663934
B22: Cold Pig & Pig Equivalent
B23: MOG | C23: Mt | D23: 7740 | E23: 342 | F23: 556.07714 | G23: 342 | H23: 318.18764 | I23: 684 | J23: 874.26478 | K23: 720 | L23: 3128.8729 | M23: 1404 | N23: 4003.1377 | O23: 3600 | P23: 314.93231 | Q23: 5004 | R23: 4318.07 | S23: 342 | T23: 392.89329 | U23: 5346 | V23: 4710.9633 | W23: 342 | X23: 569 | Y23: 4284 | Z23: 1276.8256 | AA23: 5688 | AB23: 5279.9633 | AC23: 342 | AD23: 264.68337 | AE23: 6030 | AF23: 5544.6467 | AG23: 342 | AH23: 25.041 | AI23: 6372 | AJ23: 5569.6877 | AK23: 342 | AL23: 2134.9957 | AM23: 1026 | AN23: 2424.72 | AO23: 6714 | AP23: 7704.6834 | AQ23: 342 | AR23: 495.31098 | AS23: 7056 | AT23: 8199.9943 | AU23: 342 | AV23: 324.53136 | AW23: 7398 | AX23: 8524.5257 | AY23: 342 | AZ23: 4393.36 | BA23: 1026 | BB23: 5213.2023 | BC23: 2052 | BD23: 7637.9223 | BE23: 7740 | BF23: 12917.886 | BG23: 19561.1 | BH23: 7548.2756 | BI23: 9129.3344 | BJ23: 19735.515 | BK23: 22361.072 | BL23: 20755.018 | BM23: 58220.7 | BN23: 29957.856 | BO23: 134629.18
A24: 1000 | B24: UPIS | C24: Mt | D24: 0 | E24: 0 | F24: 78.505008 | G24: 0 | H24: 44.920608 | I24: 0 | J24: 123.42562 | K24: 0 | L24: 441.72324 | M24: 0 | N24: 565.14886 | O24: 0 | P24: 44.461032 | Q24: 0 | R24: 609.60989 | S24: 0 | T24: 55.467288 | U24: 0 | V24: 665.07718 | W24: 0 | X24: 80.319744 | Y24: 0 | Z24: 180.24806 | AA24: 0 | AB24: 745.39692 | AC24: 0 | AD24: 37.367064 | AE24: 0 | AF24: 782.76398 | AG24: 0 | AH24: 3.5352 | AI24: 0 | AJ24: 786.29918 | AK24: 0 | AL24: 301.41115 | AM24: 0 | AN24: 342.31342 | AO24: 0 | AP24: 1087.7103 | AQ24: 0 | AR24: 70 | AS24: 0 | AT24: 1157.7103 | AU24: 0 | AV24: 45.816192 | AW24: 0 | AX24: 1203.5265 | AY24: 0 | AZ24: 620.23906 | BA24: 0 | BB24: 736.05525 | BC24: 0 | BD24: 1078.3687 | BE24: 0 | BF24: 1823.7656 | BG24: 0 | BH24: 1026.6221 | BI24: 2541.6495 | BJ24: 0 | BK24: 2774.7649 | BL24: 392 | BM24: 3852.3 | BN24: 1419.0563 | BO24: 8272.9783
B25: Equiv. Pig Iron @ 65% of HM sent to Sand Pit | C25: Mt | D25: 1625 | E25: 0 | F25: 0 | G25: 0 | H25: 0 | I25: 0 | J25: 0 | K25: 0 | L25: 5978.4 | M25: 0 | N25: 5978.4 | O25: 1625 | P25: 0 | Q25: 1625 | R25: 5978.4 | S25: 0 | T25: 0 | U25: 1625 | V25: 5978.4 | W25: 0 | X25: 0 | Y25: 1625 | Z25: 0 | AA25: 1625 | AB25: 5978.4 | AC25: 0 | AD25: 0 | AE25: 1625 | AF25: 5978.4 | AG25: 0 | AH25: 1512.9 | AI25: 1625 | AJ25: 7491.3 | AK25: 0 | AL25: 2513.5 | AM25: 0 | AN25: 4026.4 | AO25: 1625 | AP25: 10004.8 | AQ25: 0 | AR25: 0 | AS25: 1625 | AT25: 10004.8 | AU25: 0 | AV25: 630 | AW25: 1625 | AX25: 10634.8 | AY25: 0 | AZ25: 480 | BA25: 0 | BB25: 1110 | BC25: 0 | BD25: 5136.4 | BE25: 1625 | BF25: 11114.8 | BG25: 2000 | BH25: 5022 | BI25: 4664.8 | BJ25: 14800 | BK25: 9214.4 | BL25: 0 | BM25: 0 | BN25: 0 | BO25: 26220.8
B26: TOTAL EQUIVALENT PIG IRON | C26: Mt | D26: 9365 | E26: 342 | F26: 634.58215 | G26: 342 | H26: 363.10825 | I26: 684 | J26: 997.6904 | K26: 720 | L26: 9548.9962 | M26: 1404 | N26: 10546.687 | O26: 5225 | P26: 359.39334 | Q26: 6629 | R26: 10906.08 | S26: 342 | T26: 448.36058 | U26: 6971 | V26: 11354.441 | W26: 342 | X26: 649.31974 | Y26: 5909 | Z26: 1457.0737 | AA26: 7313 | AB26: 12003.76 | AC26: 342 | AD26: 302.05043 | AE26: 7655 | AF26: 12305.811 | AG26: 342 | AH26: 1541.4762 | AI26: 7997 | AJ26: 13847.287 | AK26: 342 | AL26: 4949.9068 | AM26: 1026 | AN26: 6793.4334 | AO26: 8339 | AP26: 18797.194 | AQ26: 342 | AR26: 565.31098 | AS26: 8681 | AT26: 19362.505 | AU26: 342 | AV26: 1000.3476 | AW26: 9023 | AX26: 20362.852 | AY26: 342 | AZ26: 5493.599 | BA26: 1026 | BB26: 7059.2576 | BC26: 2052 | BD26: 13852.691 | BE26: 9365 | BF26: 25856.451 | BG26: 21561.1 | BH26: 13596.898 | BI26: 16335.784 | BJ26: 34535.515 | BK26: 34350.237 | BL26: 21147.018 | BM26: 62073 | BN26: 31376.912 | BO26: 169122.96
B27: Net PCI Production | C27: Mt | E27: 219 | F27: 0 | G27: 224.58 | H27: 64.519 | I27: 443.58 | J27: 64.519 | K27: 189.24 | L27: 1153.005 | M27: 632.82 | N27: 1217.524 | O27: 436.24 | P27: 1162.399 | Q27: 1069.06 | R27: 2379.923 | S27: 218.5 | T27: 1097.691 | U27: 1287.56 | V27: 3477.614 | W27: 212.42 | X27: 183 | Y27: 867.16 | Z27: 2443.09 | AA27: 1499.98 | AB27: 3660.614 | AC27: 226.1 | AD27: 0 | AE27: 1726.08 | AF27: 3660.614 | AG27: 220.02 | AH27: 1174.369 | AI27: 1946.1 | AJ27: 4834.983 | AK27: 226.1 | AL27: 1177.785 | AM27: 672.22 | AN27: 2352.154 | AO27: 2172.2 | AP27: 6012.768 | AQ27: 226.1 | AR27: 766.241 | AS27: 2398.3 | AT27: 6779.009 | AU27: 207.1 | AV27: 658.147 | AW27: 2605.4 | AX27: 7437.156 | AY27: 226.1 | AZ27: 554.33 | BA27: 659.3 | BB27: 1978.718 | BC27: 1331.52 | BD27: 4330.872 | BE27: 2831.5 | BF27: 7991.486 | BG27: 2377.872 | BH27: 6141.395 | BI27: 5885.734 | BJ27: 2398.56 | BK27: 13377.679 | BL27: 11568.99 | BM27: 41093.9 | BN27: 0 | BO27: 44255.19
B28: Net Granulated Slag Production | C28: Mt | D28: 987899.89 | E28: 89470.179 | F28: 81032.918 | G28: 92452.518 | H28: 71605.173 | I28: 181922.7 | J28: 152638.09 | K28: 55546.07 | L28: 55334.635 | M28: 237468.77 | N28: 207972.73 | O28: 27586.639 | P28: 84498.305 | Q28: 265055.41 | R28: 292471.03 | S28: 89470.179 | T28: 84615.104 | U28: 354525.58 | V28: 377086.13 | W28: 86487.84 | X28: 81116 | Y28: 203544.66 | Z28: 250229.41 | AA28: 441013.42 | AB28: 458202.13 | AC28: 93198.103 | AD28: 81673.877 | AE28: 534211.53 | AF28: 539876.01 | AG28: 90215.764 | AH28: 2328.2551 | AI28: 624427.29 | AJ28: 542204.27 | AK28: 93198.103 | AL28: 92452.296 | AM28: 276611.97 | AN28: 176454.43 | AO28: 717625.4 | AP28: 634656.56 | AQ28: 93198.103 | AR28: 94062.296 | AS28: 810823.5 | AT28: 728718.86 | AU28: 83878.293 | AV28: 80273.363 | AW28: 894701.79 | AX28: 808992.22 | AY28: 93198.103 | AZ28: 90266.534 | BA28: 270274.5 | BB28: 264602.19 | BC28: 546886.47 | BD28: 441056.62 | BE28: 987899.89 | BF28: 899258.76 | BG28: 1063047 | BH28: 1075244.6 | BI28: 1065593 | BJ28: 157305.12 | BK28: 920129.3 | BL28: 882599.97 | BM28: 776699 | BN28: 854658 | BO28: 809638.21
B29: Saleable Steel Production (Mill Wise)
B30: WR Mill | C30: Mt | D30: 500000 | E30: 43500 | F30: 36717.55 | G30: 45500 | H30: 38183.18 | I30: 89000 | J30: 74900.73 | K30: 30000 | L30: 38310.4 | M30: 119000 | N30: 113211.13 | O30: 25000 | P30: 42041.4 | Q30: 144000 | R30: 155252.53 | S30: 45500 | T30: 41559.65 | U30: 189500 | V30: 196812.18 | W30: 44000 | X30: 42947.5 | Y30: 114500 | Z30: 126548.55 | AA30: 233500 | AB30: 239759.68 | AC30: 45500 | AD30: 42384.76 | AE30: 279000 | AF30: 282144.44 | AG30: 44000 | AH30: 19981.35 | AI30: 323000 | AJ30: 302125.79 | AK30: 45500 | AL30: 39200.1 | AM30: 135000 | AN30: 101566.21 | AO30: 368500 | AP30: 341325.89 | AQ30: 45500 | AR30: 40296.85 | AS30: 414000 | AT30: 381622.74 | AU30: 40500 | AV30: 34335.35 | AW30: 454500 | AX30: 415958.09 | AY30: 45500 | AZ30: 43072.55 | BA30: 131500 | BB30: 117704.75 | BC30: 266500 | BD30: 219270.96 | BE30: 500000 | BF30: 459030.64 | BG30: 500000 | BH30: 478528.39 | BI30: 466114.65 | BJ30: 500000 | BK30: 465343.77 | BL30: 435965.96 | BM30: 356518.66 | BN30: 500000 | BO30: 412025.22
B31: Bar Mill | C31: Mt | D31: 870000 | E31: 77000 | F31: 69574.102 | G31: 80000 | H31: 65238.015 | I31: 157000 | J31: 134812.12 | K31: 48000 | L31: 49675.968 | M31: 205000 | N31: 184488.09 | O31: 37500 | P31: 70097.135 | Q31: 242500 | R31: 254585.22 | S31: 80000 | T31: 71164.143 | U31: 322500 | V31: 325749.36 | W31: 77500 | X31: 70484.61 | Y31: 195000 | Z31: 211745.89 | AA31: 400000 | AB31: 396233.97 | AC31: 80000 | AD31: 66747.8 | AE31: 480000 | AF31: 462981.77 | AG31: 77500 | AH31: 3169.72 | AI31: 557500 | AJ31: 466151.49 | AK31: 80000 | AL31: 70630.63 | AM31: 237500 | AN31: 140548.15 | AO31: 637500 | AP31: 536782.12 | AQ31: 80000 | AR31: 70085.115 | AS31: 717500 | AT31: 606867.24 | AU31: 72500 | AV31: 65990 | AW31: 790000 | AX31: 672857.24 | AY31: 80000 | AZ31: 78010.61 | BA31: 232500 | BB31: 214085.73 | BC31: 470000 | BD31: 354633.88 | BE31: 870000 | BF31: 750867.85 | BG31: 850000 | BH31: 795322.27 | BI31: 775906.63 | BJ31: 750000 | BK31: 649840.96 | BL31: 674875.14 | BM31: 440547.27 | BN31: 800000 | BO31: 632220.18
B32: US Mill | C32: Mt | D32: 560000 | E32: 46000 | F32: 47018.297 | G32: 47500 | H32: 44548.076 | I32: 93500 | J32: 91566.373 | K32: 35000 | L32: 27879.333 | M32: 128500 | N32: 119445.71 | O32: 12500 | P32: 44707.993 | Q32: 141000 | R32: 164153.7 | S32: 49000 | T32: 34390.132 | U32: 190000 | V32: 198543.83 | W32: 48000 | X32: 43670.795 | Y32: 109500 | Z32: 122768.92 | AA32: 238000 | AB32: 242214.63 | AC32: 54000 | AD32: 44900.301 | AE32: 292000 | AF32: 287114.93 | AG32: 52000 | AH32: 8584.984 | AI32: 344000 | AJ32: 295699.91 | AK32: 54000 | AL32: 40066.768 | AM32: 160000 | AN32: 93552.053 | AO32: 398000 | AP32: 335766.68 | AQ32: 54000 | AR32: 51039.179 | AS32: 452000 | AT32: 386805.86 | AU32: 48000 | AV32: 51009.48 | AW32: 500000 | AX32: 437815.34 | AY32: 60000 | AZ32: 62071.89 | BA32: 162000 | BB32: 164120.55 | BC32: 322000 | BD32: 257672.6 | BE32: 560000 | BF32: 499887.23 | BG32: 525000 | BH32: 459141.95 | BI32: 361987.56 | BJ32: 450000 | BK32: 213226.16 | BL32: 220000 | BM32: 88943.894 | BN32: 535000 | BO32: 171634.81
B33: Finished Steel | C33: Mt | D33: 1930000 | E33: 166500 | F33: 153309.95 | G33: 173000 | H33: 147969.27 | I33: 339500 | J33: 301279.22 | K33: 113000 | L33: 115865.7 | M33: 452500 | N33: 417144.92 | O33: 75000 | P33: 156846.53 | Q33: 527500 | R33: 573991.45 | S33: 174500 | T33: 147113.93 | U33: 702000 | V33: 721105.37 | W33: 169500 | X33: 157102.91 | Y33: 419000 | Z33: 461063.36 | AA33: 871500 | AB33: 878208.28 | AC33: 179500 | AD33: 154032.86 | AE33: 1051000 | AF33: 1032241.1 | AG33: 173500 | AH33: 31736.054 | AI33: 1224500 | AJ33: 1063977.2 | AK33: 179500 | AL33: 149897.5 | AM33: 532500 | AN33: 335666.41 | AO33: 1404000 | AP33: 1213874.7 | AQ33: 179500 | AR33: 161421.14 | AS33: 1583500 | AT33: 1375295.8 | AU33: 161000 | AV33: 151334.83 | AW33: 1744500 | AX33: 1526630.7 | AY33: 185500 | AZ33: 183155.05 | BA33: 526000 | BB33: 495911.02 | BC33: 1058500 | BD33: 831577.44 | BE33: 1930000 | BF33: 1709785.7 | BG33: 1875000 | BH33: 1732992.6 | BI33: 1604008.8 | BJ33: 1700000 | BK33: 1328410.9 | BL33: 1330841.1 | BM33: 886009.82 | BN33: 1835000 | BO33: 1215880.2
B34: 150x150 mm | C34: Mt | D34: 461999.71 | E34: 40719.754 | F34: 57019 | G34: 36952.46 | H34: 31956 | I34: 77672.214 | J34: 88975 | K34: 29529.067 | L34: 25895 | M34: 107201.28 | N34: 114870 | O34: 6183.2297 | P34: 58992 | Q34: 113384.51 | R34: 173862 | S34: 38452.612 | T34: 55648 | U34: 151837.12 | V34: 229510 | W34: 35980.786 | X34: 52843 | Y34: 80616.628 | Z34: 167483 | AA34: 187817.91 | AB34: 282353 | AC34: 47340.612 | AD34: 25418 | AE34: 235158.52 | AF34: 307771 | AG34: 45680.786 | AH34: 7935 | AI34: 280839.31 | AJ34: 315706 | AK34: 45710.062 | AL34: 64493 | AM34: 138731.46 | AN34: 97846 | AO34: 326549.37 | AP34: 380199 | AQ34: 47339.612 | AR34: 63074.18 | AS34: 373888.98 | AT34: 443273.18 | AU34: 42657.966 | AV34: 57481.27 | AW34: 416546.95 | AX34: 500754.45 | AY34: 45452.612 | AZ34: 57620 | BA34: 135450.19 | BB34: 178175.45 | BC34: 274181.65 | BD34: 276021.45 | BE34: 461999.56 | BF34: 558374.45 | BG34: 592000 | BH34: 574823.37 | BI34: 595119.91 | BJ34: 516406.77 | BK34: 627684.57 | BL34: 533055.82 | BM34: 608495.73 | BN34: 304999.74 | BO34: 629438.96
B35: 200x280 mm | C35: Mt | D35: 17999.828 | E35: 4999.7911 | F35: 4432 | G35: 0 | H35: 1377 | I35: 4999.7911 | J35: 5809 | K35: 0 | L35: 5866 | M35: 4999.7911 | N35: 11675 | O35: 0 | P35: 5431.48 | Q35: 4999.7911 | R35: 17106.48 | S35: 4999.5642 | T35: 8492 | U35: 9999.3553 | V35: 25598.48 | W35: 0 | X35: 6231 | Y35: 4999.5642 | Z35: 20154.48 | AA35: 9999.3553 | AB35: 31829.48 | AC35: 0.48160502 | AD35: 7379.5262 | AE35: 9999.8369 | AF35: 39209.006 | AG35: 4000.1297 | AH35: 637 | AI35: 13999.967 | AJ35: 39846.006 | AK35: 0 | AL35: 12910 | AM35: 4000.6113 | AN35: 20926.526 | AO35: 13999.967 | AP35: 52756.006 | AQ35: 0 | AR35: 10907.843 | AS35: 13999.967 | AT35: 63663.849 | AU35: 4000.0298 | AV35: 0 | AW35: 17999.996 | AX35: 63663.849 | AY35: 0 | AZ35: 0 | BA35: 4000.0298 | BB35: 10907.843 | BC35: 8000.6411 | BD35: 31834.369 | BE35: 17999.996 | BF35: 63663.849 | BG35: 57999.916 | BH35: 101828.14 | BI35: 116079.05 | BJ35: 153592.34 | BK35: 204330.35 | BL35: 371378.01 | BM35: 329378.8 | BN35: 267000 | BO35: 248401
B36: Saleable Semis | C36: Mt | D36: 479999.54 | E36: 45719.545 | F36: 61451 | G36: 36952.46 | H36: 33333 | I36: 82672.005 | J36: 94784 | K36: 29529.067 | L36: 31761 | M36: 112201.07 | N36: 126545 | O36: 6183.2297 | P36: 64423.48 | Q36: 118384.3 | R36: 190968.48 | S36: 43452.176 | T36: 64140 | U36: 161836.48 | V36: 255108.48 | W36: 35980.786 | X36: 59074 | Y36: 85616.192 | Z36: 187637.48 | AA36: 197817.26 | AB36: 314182.48 | AC36: 47341.094 | AD36: 32797.526 | AE36: 245158.36 | AF36: 346980.01 | AG36: 49680.916 | AH36: 8572 | AI36: 294839.27 | AJ36: 355552.01 | AK36: 45710.062 | AL36: 77403 | AM36: 142732.07 | AN36: 118772.53 | AO36: 340549.34 | AP36: 432955.01 | AQ36: 47339.612 | AR36: 73982.023 | AS36: 387888.95 | AT36: 506937.03 | AU36: 46657.996 | AV36: 57481.27 | AW36: 434546.94 | AX36: 564418.3 | AY36: 45452.612 | AZ36: 57620 | BA36: 139450.22 | BB36: 189083.29 | BC36: 282182.29 | BD36: 307855.82 | BE36: 479999.56 | BF36: 622038.3 | BG36: 649999.92 | BH36: 676651.51 | BI36: 711198.96 | BJ36: 669999.11 | BK36: 832014.92 | BL36: 904433.83 | BM36: 937874.53 | BN36: 571999.74 | BO36: 877839.96
B37: TOTAL SALEABLE STEEL | C37: Mt | D37: 2409999.5 | E37: 212219.54 | F37: 214760.95 | G37: 209952.46 | H37: 181302.27 | I37: 422172 | J37: 396063.22 | K37: 142529.07 | L37: 147626.7 | M37: 564701.07 | N37: 543689.92 | O37: 81183.23 | P37: 221270.01 | Q37: 645884.3 | R37: 764959.93 | S37: 217952.18 | T37: 211253.93 | U37: 863836.48 | V37: 976213.85 | W37: 205480.79 | X37: 216176.91 | Y37: 504616.19 | Z37: 648700.84 | AA37: 1069317.3 | AB37: 1192390.8 | AC37: 226841.09 | AD37: 186830.39 | AE37: 1296158.4 | AF37: 1379221.1 | AG37: 223180.92 | AH37: 40308.054 | AI37: 1519339.3 | AJ37: 1419529.2 | AK37: 225210.06 | AL37: 227300.5 | AM37: 675232.07 | AN37: 454438.94 | AO37: 1744549.3 | AP37: 1646829.7 | AQ37: 226839.61 | AR37: 235403.17 | AS37: 1971388.9 | AT37: 1882232.9 | AU37: 207658 | AV37: 208816.1 | AW37: 2179046.9 | AX37: 2091049 | AY37: 230952.61 | AZ37: 240775.05 | BA37: 665450.22 | BB37: 684994.32 | BC37: 1340682.3 | BD37: 1139433.3 | BE37: 2409999.6 | BF37: 2331824 | BG37: 2524999.9 | BH37: 2409644.1 | BI37: 2315207.8 | BJ37: 2369999.1 | BK37: 2160425.8 | BL37: 2235274.9 | BM37: 1823884.4 | BN37: 2406999.7 | BO37: 2093720.2
B38: SAL STEEL PRODN (CATEGORY WISE)
B39: Wire Rod Plain Coils | C39: Mt | D39: 500000 | E39: 43500 | F39: 36717.55 | G39: 45500 | H39: 38183.18 | I39: 89000 | J39: 74900.73 | K39: 30000 | L39: 38310.4 | M39: 119000 | N39: 113211.13 | O39: 25000 | P39: 42041.4 | Q39: 144000 | R39: 155252.53 | S39: 45500 | T39: 41559.65 | U39: 189500 | V39: 196812.18 | W39: 44000 | X39: 42947.5 | Y39: 114500 | Z39: 126548.55 | AA39: 233500 | AB39: 239759.68 | AC39: 45500 | AD39: 42384.76 | AE39: 279000 | AF39: 282144.44 | AG39: 44000 | AH39: 19981.35 | AI39: 323000 | AJ39: 302125.79 | AK39: 45500 | AL39: 39200.1 | AM39: 135000 | AN39: 101566.21 | AO39: 368500 | AP39: 341325.89 | AQ39: 45500 | AR39: 40296.85 | AS39: 414000 | AT39: 381622.74 | AU39: 40500 | AV39: 34335.35 | AW39: 454500 | AX39: 415958.09 | AY39: 45500 | AZ39: 43072.55 | BA39: 131500 | BB39: 117704.75 | BC39: 266500 | BD39: 219270.96 | BE39: 500000 | BF39: 459030.64 | BG39: 500000 | BH39: 471802.34 | BI39: 410762.6 | BJ39: 500000 | BK39: 456374.84 | BL39: 435965.96 | BM39: 333534.61 | BN39: 500000 | BO39: 270654.57
B40: TMT Coils | C40: Mt | F40: 0 | H40: 0 | J40: 0 | L40: 0 | N40: 0 | P40: 0 | R40: 0 | T40: 0 | V40: 0 | X40: 0 | Z40: 0 | AB40: 0 | AD40: 0 | AF40: 0 | AH40: 0 | AJ40: 0 | AL40: 0 | AN40: 0 | AP40: 0 | AR40: 0 | AT40: 0 | AV40: 0 | AX40: 0 | AZ40: 0 | BB40: 0 | BD40: 0 | BF40: 0 | BH40: 6726.05 | BI40: 55352.05 | BK40: 8968.93 | BM40: 22983.766 | BO40: 141370.65
B41: TMT Bars | C41: Mt | D41: 870000 | E41: 77000 | F41: 69574.102 | G41: 80000 | H41: 65238.015 | I41: 157000 | J41: 134812.12 | K41: 48000 | L41: 49675.968 | M41: 205000 | N41: 184488.09 | O41: 37500 | P41: 70097.135 | Q41: 242500 | R41: 254585.22 | S41: 80000 | T41: 71164.143 | U41: 322500 | V41: 325749.36 | W41: 77500 | X41: 70484.61 | Y41: 195000 | Z41: 211745.89 | AA41: 400000 | AB41: 396233.97 | AC41: 80000 | AD41: 66747.8 | AE41: 480000 | AF41: 462981.77 | AG41: 77500 | AH41: 3169.72 | AI41: 557500 | AJ41: 466151.49 | AK41: 80000 | AL41: 70630.63 | AM41: 237500 | AN41: 140548.15 | AO41: 637500 | AP41: 536782.12 | AQ41: 80000 | AR41: 70085.115 | AS41: 717500 | AT41: 606867.24 | AU41: 72500 | AV41: 65990 | AW41: 790000 | AX41: 672857.24 | AY41: 80000 | AZ41: 78010.61 | BA41: 232500 | BB41: 214085.73 | BC41: 470000 | BD41: 354633.88 | BE41: 870000 | BF41: 750867.85 | BG41: 850000 | BH41: 795322.27 | BI41: 775906.63 | BJ41: 750000 | BK41: 649840.96 | BL41: 674875.14 | BM41: 440547.14 | BN41: 800000 | BO41: 632220.18
B42: NPB | C42: Mt | D42: 560000 | E42: 46000 | F42: 34804.57 | G42: 47500 | H42: 37951.931 | I42: 93500 | J42: 72756.501 | K42: 35000 | L42: 16171.033 | M42: 128500 | N42: 88927.534 | O42: 12500 | P42: 33806.94 | Q42: 141000 | R42: 122734.47 | S42: 49000 | T42: 25023.575 | U42: 190000 | V42: 147758.05 | W42: 48000 | X42: 31597.72 | Y42: 109500 | Z42: 90428.235 | AA42: 238000 | AB42: 179355.77 | AC42: 54000 | AD42: 34793.765 | AE42: 292000 | AF42: 214149.53 | AG42: 52000 | AH42: 2029.933 | AI42: 344000 | AJ42: 216179.47 | AK42: 54000 | AL42: 29630.324 | AM42: 160000 | AN42: 66454.022 | AO42: 398000 | AP42: 245809.79 | AQ42: 54000 | AR42: 38310.493 | AS42: 452000 | AT42: 284120.28 | AU42: 48000 | AV42: 36772.828 | AW42: 500000 | AX42: 320893.11 | AY42: 60000 | AZ42: 48620.817 | BA42: 162000 | BB42: 123704.14 | BC42: 322000 | BD42: 190158.16 | BE42: 560000 | BF42: 369513.93 | BG42: 525000 | BH42: 322948.42 | BI42: 273627.65 | BJ42: 450000 | BK42: 168119.5 | BL42: 220000 | BM42: 78790 | BN42: 535000 | BO42: 171634.81
B43: WPB | C43: Mt | F43: 4894.263 | H43: 2942.204 | I43: 0 | J43: 7836.467 | L43: 4576.147 | N43: 12412.614 | P43: 4752.415 | Q43: 0 | R43: 17165.029 | T43: 0 | U43: 0 | V43: 17165.029 | X43: 1979.182 | Z43: 6731.597 | AB43: 19144.211 | AD43: 2513.328 | AE43: 0 | AF43: 21657.539 | AH43: 0 | AI43: 0 | AJ43: 21657.539 | AL43: 4923.02 | AN43: 7436.348 | AO43: 0 | AP43: 26580.559 | AR43: 5654.599 | AS43: 0 | AT43: 32235.158 | AV43: 7646.882 | AW43: 0 | AX43: 39882.04 | AZ43: 7746.718 | BB43: 21048.199 | BD43: 28484.547 | BE43: 0 | BF43: 47628.758 | BG43: 0 | BH43: 47288.061 | BI43: 21791.11
B44: Channels | C44: Mt | F44: 7319.464 | H44: 3653.941 | I44: 0 | J44: 10973.405 | L44: 7132.153 | N44: 18105.558 | P44: 6148.638 | Q44: 0 | R44: 24254.196 | T44: 9366.557 | U44: 0 | V44: 33620.753 | X44: 10093.893 | Z44: 25609.088 | AB44: 43714.646 | AD44: 6063.364 | AE44: 0 | AF44: 49778.01 | AH44: 6555.051 | AI44: 0 | AJ44: 56333.061 | AL44: 5513.424 | AN44: 18131.839 | AO44: 0 | AP44: 61846.485 | AR44: 7074.087 | AS44: 0 | AT44: 68920.572 | AV44: 6589.77 | AW44: 0 | AX44: 75510.342 | AZ44: 5704.355 | BB44: 19368.212 | BD44: 37500.051 | BE44: 0 | BF44: 81214.697 | BG44: 0 | BH44: 86018.164 | BI44: 62409.791 | BK44: 44187.11 | BM44: 4414.219
B45: Angles | C45: Mt | F45: 0 | H45: 0 | I45: 0 | J45: 0 | L45: 0 | N45: 0 | P45: 0 | Q45: 0 | R45: 0 | T45: 0 | U45: 0 | V45: 0 | X45: 0 | Z45: 0 | AB45: 0 | AD45: 1529.844 | AE45: 0 | AF45: 1529.844 | AH45: 0 | AI45: 0 | AJ45: 1529.844 | AL45: 0 | AN45: 1529.844 | AO45: 0 | AP45: 1529.844 | AR45: 0 | AS45: 0 | AT45: 1529.844 | AV45: 0 | AW45: 0 | AX45: 1529.844 | AZ45: 0 | BB45: 0 | BD45: 1529.844 | BE45: 0 | BF45: 1529.844 | BG45: 0 | BH45: 2887.321 | BI45: 4159.184 | BK45: 919.55454 | BM45: 5739.5256
B46: Semis | C46: Mt | D46: 479999.54 | E46: 45719.545 | F46: 61451 | G46: 36952.46 | H46: 33333 | I46: 82672.005 | J46: 94784 | K46: 29529.067 | L46: 31761 | M46: 112201.07 | N46: 126545 | O46: 6183.2297 | P46: 64423.48 | Q46: 118384.3 | R46: 190968.48 | S46: 43452.176 | T46: 64140 | U46: 161836.48 | V46: 255108.48 | W46: 35980.786 | X46: 59074 | Y46: 85616.192 | Z46: 187637.48 | AA46: 197817.26 | AB46: 314182.48 | AC46: 47341.094 | AD46: 32797.526 | AE46: 245158.36 | AF46: 346980.01 | AG46: 49680.916 | AH46: 8572 | AI46: 294839.27 | AJ46: 355552.01 | AK46: 45710.062 | AL46: 77403 | AM46: 142732.07 | AN46: 118772.53 | AO46: 340549.34 | AP46: 432955.01 | AQ46: 47339.612 | AR46: 73982.023 | AS46: 387888.95 | AT46: 506937.03 | AU46: 46657.996 | AV46: 57481.27 | AW46: 434546.94 | AX46: 564418.3 | AY46: 45452.612 | AZ46: 57620 | BA46: 139450.22 | BB46: 189083.29 | BC46: 282182.29 | BD46: 307855.82 | BE46: 479999.56 | BF46: 622038.3 | BG46: 649999.92 | BH46: 676651.51 | BI46: 711198.96 | BJ46: 669999.11 | BK46: 832014.92 | BL46: 904433.83 | BM46: 937874.53 | BN46: 571999.74 | BO46: 877839.96
B47: TOTAL SALEABLE STEEL | C47: Mt | D47: 2409999.5 | E47: 212219.54 | F47: 214760.95 | G47: 209952.46 | H47: 181302.27 | I47: 422172 | J47: 396063.22 | K47: 142529.07 | L47: 147626.7 | M47: 564701.07 | N47: 543689.92 | O47: 81183.23 | P47: 221270.01 | Q47: 645884.3 | R47: 764959.93 | S47: 217952.18 | T47: 211253.93 | U47: 863836.48 | V47: 976213.85 | W47: 205480.79 | X47: 216176.91 | Y47: 504616.19 | Z47: 648700.84 | AA47: 1069317.3 | AB47: 1192390.8 | AC47: 226841.09 | AD47: 186830.39 | AE47: 1296158.4 | AF47: 1379221.1 | AG47: 223180.92 | AH47: 40308.054 | AI47: 1519339.3 | AJ47: 1419529.2 | AK47: 225210.06 | AL47: 227300.5 | AM47: 675232.07 | AN47: 454438.94 | AO47: 1744549.3 | AP47: 1646829.7 | AQ47: 226839.61 | AR47: 235403.17 | AS47: 1971388.9 | AT47: 1882232.9 | AU47: 207658 | AV47: 208816.1 | AW47: 2179046.9 | AX47: 2091049 | AY47: 230952.61 | AZ47: 240775.05 | BA47: 665450.22 | BB47: 684994.32 | BC47: 1340682.3 | BD47: 1139433.3 | BE47: 2409999.6 | BF47: 2331824 | BG47: 2524999.9 | BH47: 2409644.1 | BI47: 2315208 | BJ47: 2369999.1 | BK47: 2160425.8 | BL47: 2235274.9 | BM47: 1823883.8 | BN47: 2406999.7 | BO47: 2093720.2
B48: COAL TAR | C48: Mt | D48: 46866.669 | E48: 3866.9886 | F48: 3589 | G48: 3995.8882 | H48: 3712.18 | I48: 7862.8768 | J48: 7301.18 | K48: 3811.2647 | L48: 3561.96 | M48: 11674.141 | N48: 10863.14 | O48: 3866.049 | P48: 3728.17 | Q48: 15540.19 | R48: 14591.31 | S48: 3996.382 | T48: 3668.08 | U48: 19536.573 | V48: 18259.39 | W48: 3867.4665 | X48: 3543.43 | Y48: 11729.898 | Z48: 10939.68 | AA48: 23404.039 | AB48: 21802.82 | AC48: 3996.382 | AD48: 3647.77 | AE48: 27400.421 | AF48: 25450.59 | AG48: 3867.4665 | AH48: 3383.76 | AI48: 31267.888 | AJ48: 28834.35 | AK48: 3996.382 | AL48: 3673.95 | AM48: 11860.231 | AN48: 10705.48 | AO48: 35264.27 | AP48: 32508.3 | AQ48: 3996.382 | AR48: 3683.34 | AS48: 39260.652 | AT48: 36191.64 | AU48: 3609.6354 | AV48: 3305.7 | AW48: 42870.287 | AX48: 39497.34 | AY48: 3996.382 | AZ48: 3667.4975 | BA48: 11602.399 | BB48: 10656.538 | BC48: 23462.63 | BD48: 21362.018 | BE48: 46866.669 | BF48: 43164.837 | BG48: 50890.946 | BH48: 44869.641 | BI48: 48878.17 | BJ48: 51086.383 | BK48: 49592.55 | BL48: 48584.311 | BM48: 46678.95 | BN48: 46118.873 | BO48: 49237.57
B49: AMMONIUM SULPHATE | C49: Mt | D49: 9348.2026 | E49: 877.4058 | F49: 433.9 | G49: 907.21338 | H49: 393.5 | I49: 1784.6192 | J49: 827.4 | K49: 486.11385 | L49: 299 | M49: 2270.733 | N49: 1126.4 | O49: 881.75916 | P49: 215.35 | Q49: 3152.4922 | R49: 1341.75 | S49: 902.03319 | T49: 487 | U49: 4054.5254 | V49: 1828.75 | W49: 872.4027 | X49: 369 | Y49: 2656.1951 | Z49: 1071.35 | AA49: 4926.9281 | AB49: 2197.75 | AC49: 902.03319 | AD49: 376 | AE49: 5828.9613 | AF49: 2573.75 | AG49: 0 | AH49: 317 | AI49: 5828.9613 | AJ49: 2890.75 | AK49: 902.03319 | AL49: 455 | AM49: 1804.0664 | AN49: 1148 | AO49: 6730.9945 | AP49: 3345.75 | AQ49: 902.03319 | AR49: 479 | AS49: 7633.0277 | AT49: 3824.75 | AU49: 813.14172 | AV49: 501 | AW49: 8446.1694 | AX49: 4325.75 | AY49: 902.03319 | AZ49: 572 | BA49: 2617.2081 | BB49: 1552 | BC49: 4421.2745 | BD49: 2700 | BE49: 9348.2026 | BF49: 4897.75 | BG49: 10780.781 | BH49: 6659.85 | BI49: 8145.2 | BJ49: 16578.809 | BK49: 8876.9 | BL49: 21728.852 | BM49: 10510.61 | BN49: 15654.415 | BO49: 12312.8
B51: Total casts | C51: No | D51: 16596.855 | E51: 1507.044 | F51: 1458 | G51: 1557.3585 | H51: 1298 | I51: 3064.4025 | J51: 2756 | K51: 932.07547 | L51: 948 | M51: 3996.478 | N51: 3704 | O51: 424.5283 | P51: 1544 | Q51: 4421.0063 | R51: 5248 | S51: 1507.044 | T51: 1519 | U51: 5928.0503 | V51: 6767 | W51: 1456.7295 | X51: 1510 | Y51: 3388.3019 | Z51: 4573 | AA51: 7384.7798 | AB51: 8277 | AC51: 1569.9371 | AD51: 1451 | AE51: 8954.717 | AF51: 9728 | AG51: 1519.6226 | AH51: 52 | AI51: 10474.34 | AJ51: 9780 | AK51: 1569.9371 | AL51: 1531 | AM51: 4659.4969 | AN51: 3034 | AO51: 12044.277 | AP51: 11311 | AQ51: 1569.9371 | AR51: 1599 | AS51: 13614.214 | AT51: 12910 | AU51: 1412.7044 | AV51: 1443 | AW51: 15026.918 | AX51: 14353 | AY51: 1569.9371 | AZ51: 1572 | BA51: 4552.5786 | BB51: 4614 | BC51: 9212.0755 | BD51: 7648 | BE51: 16596.855 | BF51: 15925 | BG51: 17467.17 | BH51: 16835 | BI51: 16116 | BJ51: 16344.715 | BK51: 14624 | BL51: 15300.817 | BM51: 12158 | BN51: 16891.892 | BO51: 14151
E53: 0 | F53: 0 | G53: 0 | H53: 0 | I53: 0 | J53: 0 | K53: 0 | L53: 0 | M53: 0 | N53: 0 | O53: 0 | P53: 0 | Q53: 0 | R53: 0 | S53: 0 | T53: 0 | U53: 0 | V53: 0 | W53: 0 | X53: 0 | Y53: 0 | Z53: 0 | AA53: 0 | AB53: 0 | AC53: 0 | AD53: 0 | AE53: 0 | AF53: 0 | AG53: 0 | AH53: 0 | AI53: 0 | AJ53: 0 | AK53: 0 | AL53: 0 | AM53: 0 | AN53: 0 | AO53: 0 | AP53: 0 | AQ53: 0 | AR53: 0 | AS53: 0 | AT53: 0 | AU53: 0 | AV53: 0 | AW53: 0 | AX53: 0 | AY53: 0 | AZ53: 0 | BA53: 0 | BB53: 0 | BC53: 0 | BD53: 0 | BE53: 0 | BF53: 0 | BG53: 0 | BH53: -0.01296 | BI53: -0.01296 | BJ53: 0 | BK53: -0.00039024325 | BL53: 0 | BM53: 0.55446018 | BN53: 0 | BO53: 0

Sheet Maj Despatch Summ
B1: MAJOR DESPATCH SUMMARY 2024-25 (As per Finance CENVAT report)
E2: 30 | F2: 30 | G2: 31 | H2: 31 | I2: 61 | J2: 61 | K2: 30 | L2: 30 | M2: 91 | N2: 91 | O2: 31 | P2: 31 | Q2: 122 | R2: 122 | S2: 31 | T2: 31 | U2: 153 | V2: 153 | W2: 30 | X2: 30 | Y2: 92 | Z2: 92 | AA2: 183 | AB2: 183 | AC2: 31 | AD2: 31 | AE2: 214 | AF2: 214 | AG2: 30 | AH2: 30 | AI2: 244 | AJ2: 244 | AK2: 31 | AL2: 31 | AM2: 92 | AN2: 92 | AO2: 275 | AP2: 275 | AQ2: 31 | AR2: 31 | AS2: 306 | AT2: 306 | AU2: 28 | AV2: 28 | AW2: 334 | AX2: 334 | AY2: 31 | AZ2: 31 | BA2: 90 | BB2: 90 | BC2: 182 | BD2: 182 | BE2: 365 | BF2: 365 | BM2: 365 | BN2: 365 | BO2: 366 | BP2: 366
B3: ITEM | C3: Unit | D3: 2024-25 ABP | E3: Apr'24 | G3: May'24 | I3: 2M | K3: Jun'24 | M3: QTR-1 | O3: Jul'24 | Q3: 4M | S3: Aug'24 | U3: 5M | W3: Sep'24 | Y3: QTR-2 | AA3: H1 | AC3: Oct'24 | AE3: 7M | AG3: Nov'24 | AI3: 8M | AK3: Dec'24 | AM3: QTR-3 | AO3: 9M | AQ3: Jan'25 | AS3: 10M | AU3: Feb'25 | AW3: 11M | AY3: Mar'25 | BA3: QTR-4 | BC3: H2 | BE3: 2024-25 | BG3: 2023-24 | BI3: 2022-23 | BK3: 2021-22 | BM3: 2020-21 | BO3: 2019-20
E4: ABP | F4: ACT | G4: ABP | H4: ACT | I4: ABP | J4: ACT | K4: ABP | L4: ACT | M4: ABP | N4: ACT | O4: ABP | P4: ACT | Q4: ABP | R4: ACT | S4: ABP | T4: ACT | U4: ABP | V4: ACT | W4: ABP | X4: ACT | Y4: ABP | Z4: ACT | AA4: ABP | AB4: ACT | AC4: ABP | AD4: ACT | AE4: ABP | AF4: ACT | AG4: ABP | AH4: ACT | AI4: ABP | AJ4: ACT | AK4: ABP | AL4: ACT | AM4: ABP | AN4: ACT | AO4: ABP | AP4: ACT | AQ4: ABP | AR4: ACT | AS4: ABP | AT4: ACT | AU4: ABP | AV4: ACT | AW4: ABP | AX4: ACT | AY4: ABP | AZ4: ACT | BA4: ABP | BB4: ACT | BC4: ABP | BD4: ACT | BE4: ABP | BF4: ACT | BG4: ABP | BH4: ACT | BI4: ABP | BJ4: ACT | BK4: ABP | BL4: ACT | BM4: ABP | BN4: ACT | BO4: ABP | BP4: ACT
B5: Saleable Steel (mill-wise)
B6: MKTG-Plant sales | C6: MT | D6: 21500 | E6: 2200 | F6: 3578.87 | G6: 2100 | H6: 8742.4 | I6: 4300 | J6: 12321.27 | K6: 100 | L6: 4335 | M6: 4400 | N6: 16656.27 | O6: 100 | P6: 2363.09 | Q6: 4500 | R6: 19019.36 | S6: 2100 | T6: 4615.5 | U6: 6600 | V6: 23634.86 | W6: 2200 | X6: 5085 | Y6: 4400 | Z6: 12063.59 | AA6: 8800 | AB6: 28719.86 | AC6: 2100 | AD6: 4044.21 | AE6: 10900 | AF6: 32764.07 | AG6: 2100 | AH6: 5778.35 | AI6: 13000 | AJ6: 38542.42 | AK6: 2100 | AL6: 3912 | AM6: 6300 | AN6: 13734.56 | AO6: 15100 | AP6: 42454.42 | AQ6: 2200 | AR6: 3486.44 | AS6: 17300 | AT6: 45940.86 | AU6: 2100 | AV6: 1080.89 | AW6: 19400 | AX6: 47021.75 | AY6: 2100 | AZ6: 6965.79 | BA6: 6400 | BB6: 11533.12 | BC6: 12700 | BD6: 25267.68 | BE6: 21500 | BF6: 53987.54 | BG6: 21500 | BH6: 30649.84 | BI6: 25500 | BJ6: 34807.22 | BK6: 16050 | BL6: 33201.15 | BM6: 0 | BN6: 35268.25 | BO6: 2000 | BP6: 28405.85
B7: IPT | C7: MT | D7: 0 | E7: 0 | F7: 0 | G7: 0 | H7: 322.72 | I7: 0 | J7: 322.72 | K7: 0 | L7: 0 | M7: 0 | N7: 322.72 | O7: 0 | P7: 0 | Q7: 0 | R7: 322.72 | S7: 0 | T7: 0 | U7: 0 | V7: 322.72 | W7: 0 | Y7: 0 | Z7: 0 | AA7: 0 | AB7: 322.72 | AC7: 0 | AD7: 0 | AE7: 0 | AF7: 322.72 | AG7: 0 | AH7: 0 | AI7: 0 | AJ7: 322.72 | AK7: 0 | AL7: 0 | AM7: 0 | AN7: 0 | AO7: 0 | AP7: 322.72 | AQ7: 0 | AR7: 0 | AS7: 0 | AT7: 322.72 | AU7: 0 | AV7: 0 | AW7: 0 | AX7: 322.72 | AY7: 0 | AZ7: 0 | BA7: 0 | BB7: 0 | BC7: 0 | BD7: 0 | BE7: 0 | BF7: 322.72 | BG7: 0 | BH7: 3076.2 | BI7: 123000 | BJ7: 42263.08 | BK7: 0 | BL7: 71707.42 | BM7: 10800 | BN7: 9758.51 | BO7: 24210 | BP7: 5928.095
B8: CMO-WR MILL | C8: MT | D8: 498500 | E8: 43300 | F8: 38606.76 | G8: 45400 | H8: 38320.77 | I8: 88700 | J8: 76927.53 | K8: 29900 | L8: 38679.25 | M8: 118600 | N8: 115606.78 | O8: 24900 | P8: 41309.15 | Q8: 143500 | R8: 156915.93 | S8: 45400 | T8: 40737.79 | U8: 188900 | V8: 197653.72 | W8: 43800 | X8: 42134.22 | Y8: 114100 | Z8: 124181.16 | AA8: 232700 | AB8: 239787.94 | AC8: 45400 | AD8: 37048.14 | AE8: 278100 | AF8: 276836.08 | AG8: 43900 | AH8: 30159.91 | AI8: 322000 | AJ8: 306995.99 | AK8: 45400 | AL8: 37390 | AM8: 134700 | AN8: 104598.05 | AO8: 367400 | AP8: 344385.99 | AQ8: 45300 | AR8: 37025.61 | AS8: 412700 | AT8: 381411.6 | AU8: 40400 | AV8: 32967.39 | AW8: 453100 | AX8: 414378.99 | AY8: 45400 | AZ8: 44837.42 | BA8: 131100 | BB8: 114830.42 | BC8: 265800 | BD8: 219428.47 | BE8: 498500 | BF8: 459216.41 | BG8: 498500 | BH8: 473494.21 | BI8: 498500 | BJ8: 453432.75 | BK8: 498500 | BL8: 467953.64 | BM8: 435166.29 | BN8: 351267.02 | BO8: 498000 | BP8: 399090.26
B9: CMO-BAR MILL | C9: MT | D9: 870000 | E9: 77000 | F9: 72159.95 | G9: 80000 | H9: 67613.13 | I9: 157000 | J9: 139773.08 | K9: 48000 | L9: 45346.21 | M9: 205000 | N9: 185119.29 | O9: 37500 | P9: 69331.99 | Q9: 242500 | R9: 254451.28 | S9: 80000 | T9: 73713.89 | U9: 322500 | V9: 328165.17 | W9: 77500 | X9: 66573.36 | Y9: 195000 | Z9: 209619.24 | AA9: 400000 | AB9: 394738.53 | AC9: 80000 | AD9: 64076.47 | AE9: 480000 | AF9: 458815 | AG9: 77500 | AH9: 10813.23 | AI9: 557500 | AJ9: 469628.23 | AK9: 80000 | AL9: 67253 | AM9: 237500 | AN9: 142142.7 | AO9: 637500 | AP9: 536881.23 | AQ9: 80000 | AR9: 70877.68 | AS9: 717500 | AT9: 607758.91 | AU9: 72500 | AV9: 58216.86 | AW9: 790000 | AX9: 665975.77 | AY9: 80000 | AZ9: 84208.42 | BA9: 232500 | BB9: 213302.96 | BC9: 470000 | BD9: 355445.66 | BE9: 870000 | BF9: 750184.19 | BG9: 850000 | BH9: 781402.45 | BI9: 780000 | BJ9: 768402.31 | BK9: 750000 | BL9: 648761.89 | BM9: 674874.74 | BN9: 436958.46 | BO9: 800000 | BP9: 612890.55
B10: CMO-US MILL | C10: MT | D10: 560000 | E10: 46000 | F10: 51397.78 | G10: 47500 | H10: 45578.34 | I10: 93500 | J10: 96976.12 | K10: 35000 | L10: 23860.35 | M10: 128500 | N10: 120836.47 | O10: 12500 | P10: 45789.59 | Q10: 141000 | R10: 166626.06 | S10: 49000 | T10: 38854.43 | U10: 190000 | V10: 205480.49 | W10: 48000 | X10: 43924.95 | Y10: 109500 | Z10: 128568.97 | AA10: 238000 | AB10: 249405.44 | AC10: 54000 | AD10: 43303.75 | AE10: 292000 | AF10: 292709.19 | AG10: 52000 | AH10: 15465.42 | AI10: 344000 | AJ10: 308174.61 | AK10: 54000 | AL10: 33463 | AM10: 160000 | AN10: 92232.17 | AO10: 398000 | AP10: 341637.61 | AQ10: 54000 | AR10: 44656.88 | AS10: 452000 | AT10: 386294.49 | AU10: 48000 | AV10: 47339.01 | AW10: 500000 | AX10: 433633.5 | AY10: 60000 | AZ10: 68418.51 | BA10: 162000 | BB10: 160414.4 | BC10: 322000 | BD10: 252646.57 | BE10: 560000 | BF10: 502052.01 | BG10: 525000 | BH10: 452802.59 | BI10: 470000 | BJ10: 357334.79 | BK10: 445000 | BL10: 214319.65 | BM10: 220000 | BN10: 100400.4 | BO10: 535000 | BP10: 167166.99
B11: CMO-SEMIS | C11: MT | D11: 459999.54 | E11: 43719.545 | F11: 65083.85 | G11: 34952.46 | H11: 37872.88 | I11: 78672.005 | J11: 102956.73 | K11: 29529.074 | L11: 22528.51 | M11: 108201.08 | N11: 125485.24 | O11: 6182.8629 | P11: 55129.39 | Q11: 114383.94 | R11: 180614.63 | S11: 41452.176 | T11: 58121.89 | U11: 155836.12 | V11: 238736.52 | W11: 33980.589 | X11: 53428.72 | Y11: 81615.629 | Z11: 166680 | AA11: 189816.71 | AB11: 292165.24 | AC11: 45341.094 | AD11: 31038.07 | AE11: 235157.8 | AF11: 323203.31 | AG11: 47680.916 | AH11: 11905.3 | AI11: 282838.72 | AJ11: 335108.61 | AK11: 43710.094 | AL11: 56100 | AM11: 136732.1 | AN11: 99043.37 | AO11: 326548.81 | AP11: 391208.61 | AQ11: 45340.094 | AR11: 82929.73 | AS11: 371888.9 | AT11: 474138.34 | AU11: 44657.996 | AV11: 49136.17 | AW11: 416546.9 | AX11: 523274.51 | AY11: 43452.64 | AZ11: 61705.96 | BA11: 133450.73 | BB11: 193771.86 | BC11: 270182.83 | BD11: 292815.23 | BE11: 459999.54 | BF11: 584980.47 | BG11: 630000.01 | BH11: 623466.17 | BI11: 513000.01 | BJ11: 641816.63 | BK11: 659950.15 | BL11: 742311.77 | BM11: 893633.78 | BN11: 944002.21 | BO11: 547789.74 | BP11: 836451
B12: TOTAL | C12: MT | D12: 2409999.5 | E12: 212219.54 | F12: 230827.21 | G12: 209952.46 | H12: 198450.24 | I12: 422172 | J12: 429277.45 | K12: 142529.07 | L12: 134749.32 | M12: 564701.08 | N12: 564026.77 | O12: 81182.863 | P12: 213923.21 | Q12: 645883.94 | R12: 777949.98 | S12: 217952.18 | T12: 216043.5 | U12: 863836.12 | V12: 993993.48 | W12: 205480.59 | X12: 211146.25 | Y12: 504615.63 | Z12: 641112.96 | AA12: 1069316.7 | AB12: 1205139.7 | AC12: 226841.09 | AD12: 179510.64 | AE12: 1296157.8 | AF12: 1384650.4 | AG12: 223180.92 | AH12: 74122.21 | AI12: 1519338.7 | AJ12: 1458772.6 | AK12: 225210.09 | AL12: 198118 | AM12: 675232.1 | AN12: 451750.85 | AO12: 1744548.8 | AP12: 1656890.6 | AQ12: 226840.09 | AR12: 238976.34 | AS12: 1971388.9 | AT12: 1895866.9 | AU12: 207658 | AV12: 188740.32 | AW12: 2179046.9 | AX12: 2084607.2 | AY12: 230952.64 | AZ12: 266136.1 | BA12: 665450.73 | BB12: 693852.76 | BC12: 1340682.8 | BD12: 1145603.6 | BE12: 2409999.5 | BF12: 2350743.3 | BG12: 2525000 | BH12: 2364891.5 | BI12: 2410000 | BJ12: 2298056.8 | BK12: 2369500.2 | BL12: 2178255.5 | BM12: 2234474.8 | BN12: 1877654.8 | BO12: 2406999.7 | BP12: 2049932.7
B13: Consideration in internal consumption | D13: Saleable production Plan: 2410000 (1500 T has been kept in plan for Internal consumption) | E13: Saleable production Plan: 201135 (200 T has been kept in plan for Internal consumption) | G13: Saleable production Plan: 201135 (200 T has been kept in plan for Internal consumption) | K13: Saleable production Plan: 201135 (200 T has been kept in plan for Internal consumption) | O13: Saleable production Plan: 201135 (200 T has been kept in plan for Internal consumption) | S13: Saleable production Plan: 201135 (200 T has been kept in plan for Internal consumption) | W13: Saleable production Plan: 201135 (200 T has been kept in plan for Internal consumption) | AC13: Saleable production Plan: 201135 (200 T has been kept in plan for Internal consumption) | AG13: Saleable production Plan: 201135 (200 T has been kept in plan for Internal consumption) | AK13: Saleable production Plan: 201135 (200 T has been kept in plan for Internal consumption) | AQ13: Saleable production Plan: 201135 (200 T has been kept in plan for Internal consumption) | AU13: Saleable production Plan: 201135 (200 T has been kept in plan for Internal consumption) | AY13: Saleable production Plan: 201135 (200 T has been kept in plan for Internal consumption)
B14: Saleable Steel (Sale type-wise)
B15: IPT | C15: MT | D15: 2409999.5 | E15: 212219.54 | F15: 0 | G15: 209952.46 | H15: 322.72 | I15: 422172 | J15: 322.72 | K15: 142529.07 | L15: 0 | M15: 564701.08 | N15: 322.72 | O15: 81182.863 | P15: 0 | Q15: 645883.94 | R15: 322.72 | S15: 217952.18 | T15: 0 | U15: 863836.12 | V15: 322.72 | W15: 205480.59 | X15: 0 | Y15: 504615.63 | Z15: 0 | AA15: 1069316.7 | AB15: 322.72 | AC15: 226841.09 | AD15: 0 | AE15: 1296157.8 | AF15: 322.72 | AG15: 223180.92 | AH15: 0 | AI15: 1519338.7 | AJ15: 322.72 | AK15: 225210.09 | AL15: 0 | AM15: 675232.1 | AN15: 0 | AO15: 1744548.8 | AP15: 322.72 | AQ15: 226840.09 | AR15: 0 | AS15: 1971388.9 | AT15: 322.72 | AU15: 207658 | AV15: 0 | AW15: 2179046.9 | AX15: 322.72 | AY15: 230952.64 | AZ15: 0 | BA15: 665450.73 | BB15: 0 | BC15: 1340682.8 | BD15: 0 | BE15: 2409999.5 | BF15: 322.72 | BG15: 2525000 | BH15: 3076.2 | BI15: 2410000 | BJ15: 42263.08 | BK15: 2369500.2 | BL15: 71707.42 | BM15: 2234474.8 | BN15: 9758.51 | BO15: 2406999.7 | BP15: 5928.249
B16: CMO DIR | C16: MT | F16: 163487.96 | H16: 137432.14 | J16: 300920.1 | L16: 93749.81 | N16: 394669.91 | P16: 132453.96 | R16: 527123.87 | T16: 130382.84 | V16: 657506.71 | X16: 153397.97 | Z16: 416234.77 | AB16: 810904.68 | AD16: 116531.94 | AF16: 927436.62 | AH16: 55204.14 | AJ16: 982640.76 | AL16: 139405.21 | AN16: 311141.29 | AP16: 1122046 | AR16: 171765.58 | AT16: 1293811.6 | AV16: 136540.59 | AX16: 1430352.1 | AZ16: 189752.74 | BB16: 498058.91 | BD16: 809200.2 | BF16: 1620104.9 | BH16: 1443296 | BJ16: 1325226.7 | BL16: 1097093.1 | BN16: 691326.52 | BP16: 569419.83
B17: CMO SYD | C17: MT | F17: 63760.38 | H17: 49193.61 | J17: 112953.99 | L17: 36624.69 | N17: 149578.68 | P17: 79067.16 | R17: 228645.84 | T17: 77925.77 | V17: 306571.61 | X17: 51623.67 | Z17: 208616.6 | AB17: 358195.28 | AD17: 56105 | AF17: 414300.28 | AH17: 12954.53 | AJ17: 427254.81 | AL17: 54572.32 | AN17: 123631.85 | AP17: 481827.13 | AR17: 60538.11 | AT17: 542365.24 | AV17: 51118.84 | AX17: 593484.08 | AZ17: 68622.95 | BB17: 180279.9 | BD17: 303911.75 | BF17: 662107.03 | BH17: 829404.4 | BJ17: 809005.31 | BL17: 567271.22 | BN17: 479205.15 | BP17: 909567
B18: MKTG DIR | C18: MT | F18: 3578.87 | H18: 8742.4 | J18: 12321.27 | L18: 4335 | N18: 16656.27 | P18: 2363.09 | R18: 19019.36 | T18: 4615.5 | V18: 23634.86 | X18: 5085 | Z18: 12063.59 | AB18: 28719.86 | AD18: 4044.21 | AF18: 32764.07 | AH18: 5778.35 | AJ18: 38542.42 | AL18: 3912 | AN18: 13734.56 | AP18: 42454.42 | AR18: 3486.44 | AT18: 45940.86 | AV18: 1080.89 | AX18: 47021.75 | AZ18: 6965.79 | BB18: 11533.12 | BD18: 25267.68 | BF18: 53987.54 | BH18: 30649.84 | BJ18: 34807.22 | BL18: 33201.15 | BN18: 35268.25 | BP18: 28405.85
B19: EXPORT | C19: MT | F19: 0 | H19: 2759.37 | J19: 2759.37 | L19: 39.82 | N19: 2799.19 | P19: 39 | R19: 2838.19 | T19: 3119.39 | V19: 5957.58 | X19: 1039.61 | Z19: 4198 | AB19: 6997.19 | AD19: 2829.49 | AF19: 9826.68 | AH19: 185.19 | AJ19: 10011.87 | AL19: 228.3 | AN19: 3242.98 | AP19: 10240.17 | AR19: 3186.21 | AT19: 13426.38 | AV19: 0 | AX19: 13426.38 | AZ19: 794.62 | BB19: 3980.83 | BD19: 7223.81 | BF19: 14221 | BH19: 58464.99 | BJ19: 86754.52 | BL19: 408982.58 | BN19: 662096.98 | BP19: 536611.98
B20: % DIRECT (IPT+CMO DIR+ EXPORT+ PLANT SALES) | C20: % | F20: 72.377442 | H20: 75.211111 | J20: 73.687416 | L20: 72.82013 | N20: 73.480216 | P20: 63.039466 | R20: 70.609185 | T20: 63.930519 | V20: 69.157583 | X20: 75.550752 | Z20: 67.460243 | AB20: 70.277697 | AD20: 68.745585 | AF20: 70.079069 | AH20: 82.522742 | AJ20: 70.711349 | AL20: 72.454552 | AN20: 72.632698 | AP20: 70.919788 | AR20: 74.667739 | AT20: 71.392221 | AV20: 72.915782 | AX20: 71.530165 | AZ20: 74.215091 | BB20: 74.017557 | BD20: 73.471459 | BF20: 71.834135 | BH20: 64.928437 | BJ20: 64.796113 | BL20: 70.665579 | BN20: 74.478558 | BP20: 55.62943
B21: Saleable Steel (Shipping Mode-wise)
B22: RAIL | C22: MT | D22: 2409999.5 | E22: 212219.54 | F22: 177654.4 | G22: 209952.46 | H22: 159975.22 | I22: 422172 | J22: 337629.62 | K22: 142529.07 | L22: 110092.96 | M22: 564701.08 | N22: 447722.58 | O22: 81182.863 | P22: 180420.56 | Q22: 645883.94 | R22: 628143.14 | S22: 217952.18 | T22: 173433.78 | U22: 863836.12 | V22: 801576.92 | W22: 205480.59 | X22: 170345.16 | Y22: 504615.63 | Z22: 524199.5 | AA22: 1069316.7 | AB22: 971922.08 | AC22: 226841.09 | AD22: 148158.06 | AE22: 1296157.8 | AF22: 1120080.1 | AG22: 223180.92 | AH22: 62803.84 | AI22: 1519338.7 | AJ22: 1182884 | AK22: 225210.09 | AL22: 157996.8 | AM22: 675232.1 | AN22: 368958.7 | AO22: 1744548.8 | AP22: 1340880.8 | AQ22: 226840.09 | AR22: 197810 | AS22: 1971388.9 | AT22: 1538690.8 | AU22: 207658 | AV22: 141082.9 | AW22: 2179046.9 | AX22: 1679773.7 | AY22: 230952.64 | AZ22: 218617.3 | BA22: 665450.73 | BB22: 557510.2 | BC22: 1340682.8 | BD22: 926468.9 | BE22: 2409999.5 | BF22: 1898391 | BG22: 2525000 | BH22: 1848504.3 | BI22: 2410000 | BJ22: 1959110.7 | BK22: 2369500.2 | BL22: 1882591.4 | BM22: 2234474.8 | BN22: 1557181.9 | BO22: 2406999.7 | BP22: 1655527.4
B23: ROAD | C23: MT | F23: 53172.81 | H23: 38475.02 | J23: 91647.83 | L23: 24656.36 | N23: 116304.19 | P23: 33502.65 | R23: 149806.84 | T23: 42609.72 | V23: 192416.56 | X23: 40801.09 | Z23: 116913.46 | AB23: 233217.65 | AD23: 31352.58 | AF23: 264570.23 | AH23: 11318.37 | AJ23: 275888.6 | AL23: 40121.52 | AN23: 82792.47 | AP23: 316010.12 | AR23: 41165.9 | AT23: 357176.02 | AV23: 47657.42 | AX23: 404833.44 | AZ23: 47518.8 | BB23: 136342.12 | BD23: 219134.59 | BF23: 452352.24 | BH23: 516386.89 | BJ23: 338946.25 | BL23: 295664.13 | BN23: 320472.9 | BP23: 394405.54
B24: TOTAL | C24: MT | F24: 230827.21 | H24: 198450.24 | J24: 429277.45 | L24: 134749.32 | N24: 564026.77 | P24: 213923.21 | R24: 777949.98 | T24: 216043.5 | V24: 993993.48 | X24: 211146.25 | Z24: 641112.96 | AB24: 1205139.7 | AD24: 179510.64 | AF24: 1384650.4 | AH24: 74122.21 | AJ24: 1458772.6 | AL24: 198118.32 | AN24: 451751.17 | AP24: 1656890.9 | AR24: 238975.9 | AT24: 1895866.8 | AV24: 188740.32 | AX24: 2084607.1 | AZ24: 266136.1 | BB24: 693852.32 | BD24: 1145603.5 | BF24: 2350743.2 | BH24: 2364891.2 | BJ24: 2298057 | BL24: 2178255.5 | BN24: 1877654.8 | BP24: 2049932.9
B25: ROAD CO-EFFICIENT (%) | C25: % | F25: 23.035763 | H25: 19.387742 | J25: 21.349323 | L25: 18.297948 | N25: 20.620332 | P25: 15.661064 | R25: 19.256616 | T25: 19.72275 | V25: 19.35793 | X25: 19.323616 | Z25: 18.236016 | AB25: 19.351918 | AD25: 17.465583 | AF25: 19.107367 | AH25: 15.269877 | AJ25: 18.912379 | AL25: 20.251292 | AN25: 18.327007 | AP25: 19.072476 | AR25: 17.225963 | AT25: 18.839721 | AV25: 25.250259 | AX25: 19.420131 | AZ25: 17.855075 | BB25: 19.65002 | BD25: 19.12831 | BF25: 19.242946 | BH25: 21.835546 | BJ25: 14.749254 | BL25: 13.573438 | BN25: 17.067721 | BP25: 19.239924
B26: Pig Iron | C26: MT | D26: 9365 | E26: 342 | F26: 298.84 | G26: 342 | H26: 0 | I26: 684 | J26: 298.84 | K26: 720 | L26: 598.73 | M26: 1404 | N26: 897.57 | O26: 5225 | P26: 2594.6 | Q26: 6629 | R26: 3492.17 | S26: 342 | T26: 499.34 | U26: 6971 | V26: 3991.51 | W26: 342 | X26: 0 | Y26: 5909 | Z26: 3093.94 | AA26: 7313 | AB26: 3991.51 | AC26: 342 | AD26: 748.03 | AE26: 7655 | AF26: 4739.54 | AG26: 342 | AH26: 298.97 | AI26: 7997 | AJ26: 5038.51 | AK26: 342 | AL26: 499.24 | AM26: 1026 | AN26: 1546.24 | AO26: 8339 | AP26: 5537.75 | AQ26: 342 | AR26: 1595.84 | AS26: 8681 | AT26: 7133.59 | AU26: 342 | AV26: 249.07 | AW26: 9023 | AX26: 7382.66 | AY26: 342 | AZ26: 1297.13 | BA26: 1026 | BB26: 3142.04 | BC26: 2052 | BD26: 4688.28 | BE26: 9365 | BF26: 8679.79 | BG26: 20742.204 | BH26: 7537.1 | BI26: 16929.735 | BJ26: 8801.74 | BK26: 19251.635 | BL26: 20488.86 | BM26: 20754.645 | BN26: 80002.18 | BO26: 29958.272 | BP26: 124050.8
B27: PCIS Plant Sales | C27: MT | D27: 0 | E27: 219 | F27: 259.35 | G27: 224.58 | H27: 150.17 | I27: 443.58 | J27: 409.52 | K27: 189.24 | L27: 167.22 | M27: 632.82 | N27: 576.74 | O27: 436.24 | P27: 1598.69 | Q27: 1069.06 | R27: 2175.43 | S27: 218.5 | T27: 1092.55 | U27: 1287.56 | V27: 3267.98 | W27: 212.42 | X27: 499.76 | Y27: 867.16 | Z27: 3191 | AA27: 1499.98 | AB27: 3767.74 | AC27: 226.1 | AD27: 0 | AE27: 1726.08 | AF27: 3767.74 | AG27: 220.02 | AH27: 198.57 | AI27: 1946.1 | AJ27: 3966.31 | AK27: 226.1 | AL27: 298.71 | AM27: 672.22 | AN27: 497.28 | AO27: 2172.2 | AP27: 4265.02 | AQ27: 226.1 | AR27: 499.09 | AS27: 2398.3 | AT27: 4764.11 | AU27: 207.1 | AV27: 0 | AW27: 2605.4 | AX27: 4764.11 | AY27: 226.1 | AZ27: 998.41 | BA27: 659.3 | BB27: 1497.5 | BC27: 1331.52 | BD27: 1994.78 | BE27: 2831.5 | BF27: 5762.52 | BG27: 2236.752 | BH27: 5991.84 | BI27: 2057.6 | BJ27: 5429.83 | BK27: 2163.56 | BL27: 17862.58 | BM27: 6973.7102 | BN27: 29483.78 | BO27: 8472.5251 | BP27: 59555.1
B28: Total Pig & Pig Equiv | C28: MT | D28: 9365 | E28: 561 | F28: 558.19 | G28: 566.58 | H28: 150.17 | I28: 1127.58 | J28: 708.36 | K28: 909.24 | L28: 765.95 | M28: 2036.82 | N28: 1474.31 | O28: 5661.24 | P28: 4193.29 | Q28: 7698.06 | R28: 5667.6 | S28: 560.5 | T28: 1591.89 | U28: 8258.56 | V28: 7259.49 | W28: 554.42 | X28: 499.76 | Y28: 6776.16 | Z28: 6284.94 | AA28: 8812.98 | AB28: 7759.25 | AC28: 568.1 | AD28: 748.03 | AE28: 9381.08 | AF28: 8507.28 | AG28: 562.02 | AH28: 497.54 | AI28: 9943.1 | AJ28: 9004.82 | AK28: 568.1 | AL28: 797.95 | AM28: 1698.22 | AN28: 2043.52 | AO28: 10511.2 | AP28: 9802.77 | AQ28: 568.1 | AR28: 2094.93 | AS28: 11079.3 | AT28: 11897.7 | AU28: 549.1 | AV28: 249.07 | AW28: 11628.4 | AX28: 12146.77 | AY28: 568.1 | AZ28: 2295.54 | BA28: 1685.3 | BB28: 4639.54 | BC28: 3383.52 | BD28: 6683.06 | BE28: 12196.5 | BF28: 14442.31 | BG28: 22978.956 | BH28: 13528.94 | BI28: 18987.335 | BJ28: 14231.57 | BK28: 21415.195 | BL28: 38351.44 | BM28: 27728.355 | BN28: 109485.96 | BO28: 38430.797 | BP28: 183605.9

Sheet Maj Techno Summ
A1: MAJOR TECHNO PARAMETERS 2024-2025
C2: 365 | D2: 30 | E2: 30 | F2: 31 | G2: 31 | H2: 61 | I2: 61 | J2: 30 | K2: 30 | L2: 91 | M2: 91 | N2: 31 | O2: 31 | P2: 122 | Q2: 122 | R2: 31 | S2: 31 | T2: 153 | U2: 153 | V2: 30 | W2: 30 | X2: 92 | Y2: 92 | Z2: 183 | AA2: 183 | AB2: 31 | AC2: 31 | AD2: 214 | AE2: 214 | AF2: 30 | AG2: 30 | AH2: 244 | AI2: 244 | AJ2: 31 | AK2: 31 | AL2: 92 | AM2: 92 | AN2: 275 | AO2: 275 | AP2: 31 | AQ2: 31 | AR2: 306 | AS2: 306 | AT2: 28 | AU2: 28 | AV2: 334 | AW2: 334 | AX2: 31 | AY2: 31 | AZ2: 90 | BA2: 90 | BB2: 182 | BC2: 182 | BD2: 365 | BE2: 365 | BL2: 365 | BM2: 365 | BN2: 366 | BO2: 366 | BP2: 365
A3: ITEM | B3: Unit | C3: 2024-25 Norm | D3: Apr'24 | F3: May'24 | H3: 2M | J3: Jun'24 | L3: QTR-1 | N3: Jul'24 | P3: 4M | R3: Aug'24 | T3: 5M | V3: Sep'24 | X3: QTR-2 | Z3: H1 | AB3: Oct'24 | AD3: 7M | AF3: Nov'24 | AH3: 8M | AJ3: Dec'24 | AL3: QTR-3 | AN3: 9 M | AP3: Jan'25 | AR3: 10M | AT3: Feb'25 | AV3: 11M | AX3: Mar'25 | AZ3: QTR-4 | BB3: H2 | BD3: 2024-25 | BF3: 2023-24 | BH3: 2022-23 | BJ3: 2021-22 | BL3: 2020-21 | BN3: 2019-20 | BP3: 2018-19
D4: ABP | E4: ACT | F4: ABP | G4: ACT | H4: ABP | I4: ACT | J4: ABP | K4: ACT | L4: ABP | M4: ACT | N4: ABP | O4: ACT | P4: ABP | Q4: ACT | R4: ABP | S4: ACT | T4: ABP | U4: ACT | V4: ABP | W4: ACT | X4: ABP | Y4: ACT | Z4: ABP | AA4: ACT | AB4: ABP | AC4: ACT | AD4: ABP | AE4: ACT | AF4: ABP | AG4: ACT | AH4: ABP | AI4: ACT | AJ4: ABP | AK4: ACT | AL4: ABP | AM4: ACT | AN4: ABP | AO4: ACT | AP4: ABP | AQ4: ACT | AR4: ABP | AS4: ACT | AT4: ABP | AU4: ACT | AV4: ABP | AW4: ACT | AX4: ABP | AY4: ACT | AZ4: ABP | BA4: ACT | BB4: ABP | BC4: ACT | BD4: ABP | BE4: ACT | BF4: ABP | BG4: ACT | BH4: ABP | BI4: ACT | BJ4: ABP | BK4: ACT | BL4: ABP | BM4: ACT | BN4: ABP | BO4: ACT | BP4: ACT
A5: B.F.Coke Yield | B5: % | C5: 70 | D5: 70 | E5: 70.02 | F5: 70 | G5: 70.02 | H5: 70 | I5: 70.02 | J5: 70 | K5: 70.01 | L5: 70 | M5: 70.01675 | N5: 70 | O5: 70.503373 | P5: 70 | Q5: 70.141085 | R5: 70 | S5: 70.5 | T5: 70 | U5: 70.214032 | V5: 70 | W5: 70.5 | X5: 70 | Y5: 70.501139 | Z5: 70 | AA5: 70.260896 | AB5: 70 | AC5: 70.453746 | AD5: 70 | AE5: 70.288712 | AF5: 70 | AG5: 70.49 | AH5: 70 | AI5: 70.312514 | AJ5: 70 | AK5: 70.01 | AL5: 70 | AM5: 70.313108 | AN5: 70 | AO5: 70.278182 | AP5: 70 | AQ5: 70.595 | AR5: 70 | AS5: 70.310473 | AT5: 70 | AU5: 70.5 | AV5: 70 | AW5: 70.326436 | AX5: 70 | AY5: 70.5 | AZ5: 70 | BA5: 70.532713 | BB5: 70 | BC5: 70.422664 | BD5: 70 | BE5: 70.341275 | BF5: 69.5 | BG5: 69.398029 | BH5: 69.5 | BI5: 69.459875 | BJ5: 70.500003 | BK5: 69.798394 | BL5: 70.999787 | BM5: 72.813877 | BN5: 66.5 | BO5: 67.48567 | BP5: 67.015011
A6: ICC in Coal Blend
A7: (COB#10) | B7: % | C7: 95 | D7: 95 | E7: 93.3 | F7: 95 | G7: 95 | H7: 95 | I7: 94.163689 | J7: 95 | K7: 94.999982 | L7: 95 | M7: 94.436875 | N7: 95 | O7: 95.000052 | P7: 95 | Q7: 94.579199 | R7: 95 | S7: 93.451695 | T7: 95 | U7: 94.348083 | V7: 95 | W7: 92.000071 | X7: 95 | Y7: 93.489976 | Z7: 95 | AA7: 93.959413 | AB7: 95 | AC7: 92.000348 | AD7: 95 | AE7: 93.676577 | AF7: 95 | AG7: 90.270086 | AH7: 95 | AI7: 93.273632 | AJ7: 95 | AK7: 91.999923 | AL7: 95 | AM7: 91.450919 | AN7: 95 | AO7: 93.130074 | AP7: 95 | AQ7: 91.999923 | AR7: 95 | AS7: 93.015598 | AT7: 95 | AU7: 90.285714 | AV7: 95 | AW7: 92.787463 | AX7: 95 | AY7: 89.032227 | AZ7: 95 | BA7: 90.444569 | BB7: 95 | BC7: 90.950596 | BD7: 95 | BE7: 92.468484 | BF7: 92 | BG7: 90.939873 | BH7: 92 | BI7: 89.651306 | BJ7: 95 | BK7: 93.865972 | BL7: 94.377235 | BM7: 95.478511 | BN7: 90 | BO7: 91.425995 | BP7: 91.808306
A8: (COB#11) | B8: % | C8: 100 | D8: 100 | E8: 97.166665 | F8: 100 | G8: 100 | H8: 100 | I8: 98.603087 | J8: 100 | K8: 100 | L8: 100 | M8: 99.057142 | N8: 100 | O8: 100 | P8: 100 | Q8: 99.298048 | R8: 100 | S8: 100 | T8: 100 | U8: 99.440715 | V8: 100 | W8: 97.799999 | X8: 100 | Y8: 99.28486 | Z8: 100 | AA8: 99.171912 | AB8: 100 | AC8: 96.999629 | AD8: 100 | AE8: 98.858749 | AF8: 100 | AG8: 95.266663 | AH8: 100 | AI8: 98.433936 | AJ8: 100 | AK8: 96.999996 | AL8: 100 | AM8: 96.450906 | AN8: 100 | AO8: 98.27118 | AP8: 100 | AQ8: 96.999996 | AR8: 100 | AS8: 98.141604 | AT8: 100 | AU8: 97.000003 | AV8: 100 | AW8: 98.045441 | AX8: 100 | AY8: 95.387093 | AZ8: 100 | BA8: 96.443687 | BB8: 100 | BC8: 96.447304 | BD8: 100 | BE8: 97.818139 | BF8: 94 | BG8: 93.889004 | BH8: 94 | BI8: 92.198587 | BJ8: 95 | BK8: 94.753433 | BL8: 94.836589 | BM8: 95.080613 | BN8: 90 | BO8: 96.370935 | BP8: 94.117213
A9: Overall ICC in Blend | B9: % | C9: 98.275343 | D9: 98.275343 | E9: 95.80456 | F9: 98.275343 | G9: 98.233722 | H9: 98.275343 | I9: 97.037004 | J9: 98.275343 | K9: 98.227714 | L9: 98.275343 | M9: 97.424716 | N9: 98.275343 | O9: 98.250206 | P9: 98.275343 | Q9: 97.634822 | R9: 98.275343 | S9: 97.675956 | T9: 98.275343 | U9: 97.643207 | V9: 98.275343 | W9: 95.736452 | X9: 98.275343 | Y9: 97.236172 | Z9: 98.275343 | AA9: 97.329674 | AB9: 98.275343 | AC9: 95.230804 | AD9: 98.275343 | AE9: 97.026939 | AF9: 98.275343 | AG9: 93.500197 | AH9: 98.275343 | AI9: 96.609824 | AJ9: 98.275343 | AK9: 95.241553 | AL9: 98.275343 | AM9: 94.685925 | AN9: 98.275343 | AO9: 96.454905 | AP9: 98.275343 | AQ9: 95.241553 | AR9: 98.275343 | AS9: 96.331499 | AT9: 98.275343 | AU9: 94.642312 | AV9: 98.275343 | AW9: 96.189607 | AX9: 98.275343 | AY9: 93.154562 | AZ9: 98.275343 | BA9: 94.335671 | BB9: 98.275343 | BC9: 94.51139 | BD9: 98.275343 | BE9: 95.930698 | BF9: 93.289716 | BG9: 92.83339 | BH9: 93.294359 | BI9: 91.262624 | BJ9: 95 | BK9: 94.439237 | BL9: 94.673168 | BM9: 94.71202 | BN9: 90 | BO9: 94.617133 | BP9: 93.297278
A10: BF Coke Rate | B10: Kg/ THM | C10: 360.04562 | D10: 357 | E10: 392.5025 | F10: 357 | G10: 395.17392 | H10: 357 | I10: 393.75733 | J10: 372 | K10: 407.7272 | L10: 360.50863 | M10: 397.5733 | N10: 392 | O10: 370.77684 | P10: 363.78622 | Q10: 389.80688 | R10: 365.4 | S10: 377.37067 | T10: 364.19348 | U10: 387.05271 | V10: 365.4 | W10: 380.23556 | X10: 369.00513 | Y10: 376.09629 | Z10: 364.43009 | AA10: 385.81518 | AB10: 362.4 | AC10: 380.55652 | AD10: 364.07592 | AE10: 385.02927 | AF10: 355.3 | AG10: 624.51898 | AH10: 362.808 | AI10: 386.26362 | AJ10: 355.3 | AK10: 366.34425 | AL10: 357.69218 | AM10: 377.28919 | AN10: 361.83294 | AO10: 383.50418 | AP10: 355.3 | AQ10: 348.01919 | AR10: 361.08202 | AS10: 379.11956 | AT10: 355.3 | AU10: 342.24192 | AV10: 360.53996 | AW10: 375.3732 | AX10: 355.3 | AY10: 339.29314 | AZ10: 355.3 | BA10: 343.20204 | BB10: 356.50995 | BC10: 356.72767 | BD10: 360.04562 | BE10: 371.74357 | BF10: 380.42 | BG10: 390.51224 | BH10: 389.92559 | BI10: 400.04041 | BJ10: 377.88521 | BK10: 396.71459 | BL10: 373.87865 | BM10: 423.66105 | BN10: 370.47898 | BO10: 381.58771 | BP10: 388.39311
A11: Nut Coke rate | B11: Kg/ THM | C11: 38.916226 | D11: 39 | E11: 47.860964 | F11: 39 | G11: 46.884775 | H11: 39 | I11: 47.402423 | J11: 39 | K11: 45.394613 | L11: 39 | M11: 46.853976 | N11: 36 | O11: 50.998254 | P11: 38.687764 | Q11: 48.055112 | R11: 39 | S11: 51.019755 | T11: 38.766562 | U11: 48.711672 | V11: 39 | W11: 47.771227 | X11: 38.593407 | Y11: 49.935351 | Z11: 38.812342 | AA11: 48.540951 | AB11: 39 | AC11: 39.767759 | AD11: 38.84508 | AE11: 47.229801 | AF11: 39 | AG11: 14.079452 | AH11: 38.867463 | AI11: 47.058941 | AJ11: 39 | AK11: 33.196782 | AL11: 39 | AM11: 35.988654 | AN11: 38.884675 | AO11: 45.138609 | AP11: 39 | AQ11: 30.413521 | AR11: 38.897931 | AS11: 43.319139 | AT11: 39 | AU11: 29.174869 | AV11: 38.9075 | AW11: 41.882234 | AX11: 39 | AY11: 28.136016 | AZ11: 39 | BA11: 29.240536 | BB11: 39 | BC11: 31.918159 | BD11: 38.916226 | BE11: 40.499376 | BF11: 32.204286 | BG11: 47.260949 | BH11: 30 | BI11: 36.610035 | BJ11: 23.751425 | BK11: 37.043769 | BL11: 34.857516 | BM11: 41.208946 | BN11: 25 | BO11: 44.993877 | BP11: 29.180384
A12: CDI rate | B12: Kg/ THM | C12: 140.90981 | D12: 136 | E12: 119.13023 | F12: 136 | G12: 114.32316 | H12: 136 | I12: 116.87223 | J12: 129 | K12: 118.97807 | L12: 134.36264 | M12: 117.44745 | N12: 112 | O12: 129.18393 | P12: 132.03516 | Q12: 120.84904 | R12: 136 | S12: 130.5057 | T12: 133.03575 | U12: 122.98764 | V12: 141 | W12: 122.30226 | X12: 134.87179 | Y12: 127.33972 | Z12: 134.59763 | AA12: 122.86322 | AB12: 146 | AC12: 126.07256 | AD12: 136.58688 | AE12: 123.34285 | AF12: 146 | AG12: 0 | AH12: 137.94687 | AI12: 122.70713 | AJ12: 146 | AK12: 138.96212 | AL12: 146 | AM12: 130.59501 | AN12: 138.99273 | AO12: 124.95895 | AP12: 146 | AQ12: 153.6184 | AR12: 139.79816 | AS12: 128.50018 | AT12: 146 | AU12: 156.32761 | AV12: 140.37958 | AW12: 131.32715 | AX12: 146 | AY12: 158.53603 | AZ12: 146 | BA12: 156.16199 | BB12: 146 | BC12: 146.01713 | BD12: 140.90981 | BE12: 134.06434 | BF12: 139.6475 | BG12: 125.94309 | BH12: 129.64578 | BI12: 122.58808 | BJ12: 133.64292 | BK12: 118.07599 | BL12: 128.57732 | BM12: 89.175353 | BN12: 139.85352 | BO12: 118.98027 | BP12: 123.03826
A13: Total Fuel | B13: Kg/ THM | C13: 539.87166 | D13: 532 | E13: 559.49369 | F13: 532 | G13: 556.38186 | H13: 532 | I13: 558.03198 | J13: 540 | K13: 572.09989 | L13: 533.87127 | M13: 561.87473 | N13: 540 | O13: 550.95902 | P13: 534.50914 | Q13: 558.71103 | R13: 540.4 | S13: 558.89613 | T13: 535.99579 | U13: 558.75202 | V13: 545.4 | W13: 550.30904 | X13: 542.47033 | Y13: 553.37135 | Z13: 537.84007 | AA13: 557.21935 | AB13: 547.4 | AC13: 546.39684 | AD13: 539.50789 | AE13: 555.60193 | AF13: 540.3 | AG13: 638.59844 | AH13: 539.62233 | AI13: 556.0297 | AJ13: 540.3 | AK13: 538.50316 | AL13: 542.69218 | AM13: 543.87286 | AN13: 539.71034 | AO13: 553.60174 | AP13: 540.3 | AQ13: 532.05111 | AR13: 539.77811 | AS13: 550.93888 | AT13: 540.3 | AU13: 527.7444 | AV13: 539.82704 | AW13: 548.58258 | AX13: 540.3 | AY13: 525.96518 | AZ13: 540.3 | BA13: 528.60456 | BB13: 541.50995 | BC13: 534.66296 | BD13: 539.87166 | BE13: 546.30729 | BF13: 552.27179 | BG13: 563.71628 | BH13: 549.57137 | BI13: 559.23852 | BJ13: 535.27955 | BK13: 551.83435 | BL13: 537.31348 | BM13: 554.04535 | BN13: 535.3325 | BO13: 545.56186 | BP13: 540.61176
A14: BF Productivity | B14: T/M³/Day | C14: 2.3140113 | D14: 2.3305723 | E14: 2.2165963 | F14: 2.3279827 | G14: 2.0052761 | H14: 2.3292555 | I14: 2.1120484 | J14: 2.2084216 | K14: 1.8780769 | L14: 2.2998216 | M14: 2.0425408 | N14: 2.1936 | O14: 2.3276758 | P14: 2.288289 | Q14: 2.1177276 | R14: 2.2528865 | S14: 2.3360393 | T14: 2.2792501 | U14: 2.1624836 | V14: 2.2528865 | W14: 2.3134741 | X14: 1.7131976 | Y14: 2.3256987 | Z14: 2.2740314 | AA14: 2.1884115 | AB14: 2.3467568 | AC14: 2.2356327 | AD14: 2.2863926 | AE14: 2.1953415 | AF14: 2.3499937 | AG14: 0.80694656 | AH14: 2.2953679 | AI14: 2.1760447 | AJ14: 2.3467568 | AK14: 2.3560234 | AL14: 2.3478115 | AM14: 2.2291989 | AN14: 2.3019143 | AO14: 2.1993189 | AP14: 2.3467568 | AQ14: 2.4887715 | AR14: 2.3069812 | AS14: 2.2313856 | AT14: 2.3467568 | AU14: 2.4820491 | AV14: 2.3106528 | AW14: 2.2545159 | AX14: 2.3467568 | AY14: 2.4580868 | AZ14: 2.3467568 | BA14: 2.4760163 | BB14: 2.3472901 | BC14: 2.3718147 | BD14: 2.3140113 | BE14: 2.2734567 | BF14: 2.2723639 | BG14: 2.1810142 | BH14: 2.2132463 | BI14: 2.0862545 | BJ14: 2.2066158 | BK14: 2.0192263 | BL14: 2.0565754 | BM14: 1.7450413 | BN14: 2.1585499 | BO14: 2.0057992 | BP14: 1.7419242
A15: Gross Coal to Hot Metal Ratio | B15: Kg/ THM | C15: 879.87856 | D15: 861.75448 | E15: 907.68211 | F15: 861.75448 | G15: 923.49485 | H15: 861.75043 | I15: 915.10977 | J15: 918.52304 | K15: 966.95283 | L15: 875.02915 | M15: 929.27106 | N15: 1076.904 | O15: 883.14642 | P15: 896.04003 | Q15: 915.90275 | R15: 876.78259 | S15: 908.5086 | T15: 891.18011 | U15: 914.26522 | V15: 882.41813 | W15: 913.73269 | X15: 906.29583 | Y15: 901.68529 | Z15: 889.45992 | AA15: 914.16854 | AB15: 882.68649 | AC15: 891.4153 | AD15: 888.27824 | AE15: 910.76808 | AF15: 869.98416 | AG15: 1821.6956 | AH15: 885.63515 | AI15: 915.46307 | AJ15: 869.98416 | AK15: 880.90898 | AL15: 874.25956 | AM15: 901.28448 | AN15: 883.60088 | AO15: 910.67627 | AP15: 869.98416 | AQ15: 839.50234 | AR15: 882.03574 | AS15: 901.88184 | AT15: 869.98416 | AU15: 833.03362 | AV15: 880.9059 | AW15: 894.88761 | AX15: 869.98416 | AY15: 821.74731 | AZ15: 869.9798 | BA15: 831.35602 | BB15: 872.14448 | BC15: 859.10332 | BD15: 879.87436 | BE15: 887.52975 | BF15: 900.75554 | BG15: 932.03785 | BH15: 910.43802 | BI15: 930.86111 | BJ15: 908.3767 | BK15: 935.21205 | BL15: 907.50854 | BM15: 991.44637 | BN15: 886.42712 | BO15: 931.68363 | BP15: 905.6097
A16: Hot Metal to Crude Steel | B16: Kg/ TCS | C16: 1060 | D16: 1060 | E16: 1065.6348 | F16: 1060 | G16: 1054.4582 | H16: 1060 | I16: 1060.3443 | J16: 1060 | K16: 1063.7514 | L16: 1060 | M16: 1061.2182 | N16: 1060 | O16: 1058.7752 | P16: 1060 | Q16: 1060.4991 | R16: 1060 | S16: 1052.5995 | T16: 1060 | U16: 1058.7203 | V16: 1060 | W16: 1057.3296 | X16: 1060 | Y16: 1056.2453 | Z16: 1060 | AA16: 1058.465 | AB16: 1060 | AC16: 1061.2178 | AD16: 1060 | AE16: 1058.8777 | AF16: 1060 | AG16: 1058.3743 | AH16: 1060 | AI16: 1058.875 | AJ16: 1060 | AK16: 1061.5577 | AL16: 1060 | AM16: 1061.341 | AN16: 1060 | AO16: 1059.2405 | AP16: 1060 | AQ16: 1062.3569 | AR16: 1060 | AS16: 1059.6296 | AT16: 1060 | AU16: 1061.4914 | AV16: 1060 | AW16: 1059.8188 | AX16: 1060 | AY16: 1057.0891 | AZ16: 1060 | BA16: 1060.2854 | BB16: 1060 | BC16: 1060.7023 | BD16: 1060 | BE16: 1059.546 | BF16: 1060 | BG16: 1066.0114 | BH16: 1062 | BI16: 1062.9741 | BJ16: 1064.9999 | BK16: 1062.0577 | BL16: 1077.0434 | BM16: 1071.1761 | BN16: 1065 | BO16: 1093.6626 | BP16: 1078.33
A17: Scrap consumption | B17: Kg/ TCS | C17: 40 | D17: 40 | E17: 31.706697 | F17: 40 | G17: 43.823729 | H17: 40 | I17: 37.442372 | J17: 40 | K17: 36.03881 | L17: 40 | M17: 37.082377 | N17: 40 | O17: 38.350113 | P17: 40 | Q17: 37.45555 | R17: 40 | S17: 44.128077 | T17: 40 | U17: 38.957985 | V17: 40 | W17: 36.786599 | X17: 40 | Y17: 39.749949 | Z17: 40 | AA17: 38.559266 | AB17: 40 | AC17: 34.008139 | AD17: 40 | AE17: 37.876913 | AF17: 40 | AG17: 41.109011 | AH17: 40 | AI17: 37.894131 | AJ17: 40 | AK17: 37.654621 | AL17: 40 | AM17: 35.971596 | AN17: 40 | AO17: 37.861502 | AP17: 40 | AQ17: 37.524386 | AR17: 40 | AS17: 37.819409 | AT17: 40 | AU17: 35.703807 | AV17: 40 | AW17: 37.604421 | AX17: 40 | AY17: 38.362239 | AZ17: 40 | BA17: 37.241241 | BB17: 40 | BC17: 36.739845 | BD17: 40 | BE17: 37.680158 | BF17: 40 | BG17: 34.431041 | BH17: 46 | BI17: 38.506405 | BJ17: 50 | BK17: 45.611233 | BL17: 40.465028 | BM17: 41.122433 | BN17: 50 | BO17: 25.532166 | BP17: 41.130412
A18: TMI | B18: Kg/ TCS | C18: 1100 | D18: 1100 | E18: 1097.3415 | F18: 1100 | G18: 1098.2819 | H18: 1100 | I18: 1097.7867 | J18: 1100 | K18: 1099.7902 | L18: 1100 | M18: 1098.3006 | N18: 1100 | O18: 1097.1253 | P18: 1100 | Q18: 1097.9546 | R18: 1100 | S18: 1096.7276 | T18: 1100 | U18: 1097.6783 | V18: 1100 | W18: 1094.1162 | X18: 1100 | Y18: 1095.9952 | Z18: 1100 | AA18: 1097.0242 | AB18: 1100 | AC18: 1095.2259 | AD18: 1100 | AE18: 1096.7546 | AF18: 1100 | AG18: 1099.4833 | AH18: 1100 | AI18: 1096.7691 | AJ18: 1100 | AK18: 1099.2123 | AL18: 1100 | AM18: 1097.3126 | AN18: 1100 | AO18: 1097.102 | AP18: 1100 | AQ18: 1099.8813 | AR18: 1100 | AS18: 1097.449 | AT18: 1100 | AU18: 1097.1952 | AV18: 1100 | AW18: 1097.4232 | AX18: 1100 | AY18: 1095.4514 | AZ18: 1100 | BA18: 1097.5267 | BB18: 1100 | BC18: 1097.4421 | BD18: 1100 | BE18: 1097.2261 | BF18: 1100 | BG18: 1100.4424 | BH18: 1108 | BI18: 1101.4805 | BJ18: 1114.9999 | BK18: 1107.6689 | BL18: 1117.5084 | BM18: 1112.2985 | BN18: 1115 | BO18: 1119.1948 | BP18: 1119.4604
A19: Ferro Alloys (FeMn+LCFeMn+SiMn+FeSi) | B19: Kg/ TCS | C19: 23 | D19: 23 | E19: 21.260454 | F19: 23 | G19: 20.358446 | H19: 23 | I19: 20.833483 | J19: 23 | K19: 17.594962 | L19: 23 | M19: 20.002846 | N19: 23 | O19: 19.659635 | P19: 23 | Q19: 19.901818 | R19: 23 | S19: 21.190669 | T19: 23 | U19: 20.192025 | V19: 23 | W19: 20.579529 | X19: 23 | Y19: 20.473064 | Z19: 23 | AA19: 20.26318 | AB19: 23 | AC19: 19.519398 | AD19: 23 | AE19: 20.151664 | AF19: 23 | AG19: 17.643352 | AH19: 23 | AI19: 20.138302 | AJ19: 23 | AK19: 21.325501 | AL19: 23 | AM19: 20.399868 | AN19: 23 | AO19: 20.300038 | AP19: 23 | AQ19: 20.886848 | AR19: 23 | AS19: 20.373308 | AT19: 23 | AU19: 20.63752 | AV19: 23 | AW19: 20.400157 | AX19: 23 | AY19: 20.430955 | AZ19: 23 | BA19: 20.653008 | BB19: 23 | BC19: 20.553041 | BD19: 23 | BE19: 20.403235 | BF19: 21.173677 | BG19: 22.701786 | BH19: 21 | BI19: 22.930617 | BJ19: 21.95779 | BK19: 20.936322 | BL19: 20.938578 | BM19: 20.212673 | BN19: 21 | BO19: 21.832464 | BP19: 23.120676
A20: Mill yield
A21: WR Mill | B21: % | C21: 96 | D21: 96 | E21: 95.880518 | F21: 96 | G21: 95.782523 | H21: 96 | I21: 95.830537 | J21: 96 | K21: 95.82832 | L21: 96 | M21: 95.829787 | N21: 96 | O21: 95.980374 | P21: 96 | Q21: 95.870518 | R21: 96 | S21: 95.889415 | T21: 96 | U21: 95.874508 | V21: 96 | W21: 96.019246 | X21: 96 | Y21: 95.963664 | Z21: 96 | AA21: 95.900402 | AB21: 96 | AC21: 95.917021 | AD21: 96 | AE21: 95.902898 | AF21: 96 | AG21: 95.589763 | AH21: 96 | AI21: 95.882126 | AJ21: 96 | AK21: 95.504191 | AL21: 96 | AM21: 95.69292 | AN21: 96 | AO21: 95.838569 | AP21: 96 | AQ21: 96.131408 | AR21: 96 | AS21: 95.869407 | AT21: 96 | AU21: 95.760199 | AV21: 96 | AW21: 95.860383 | AX21: 96 | AY21: 95.419404 | AZ21: 96 | BA21: 95.761639 | BB21: 96 | BC21: 95.729796 | BD21: 96 | BE21: 95.818831 | BF21: 96 | BG21: 95.881785 | BH21: 96 | BI21: 95.450038 | BJ21: 96 | BK21: 95.505336 | BL21: 96.222984 | BM21: 94.958654 | BN21: 96.5 | BO21: 96.195271 | BP21: 96.032659
A22: Bar Mill | B22: % | C22: 96.5 | D22: 96.5 | E22: 96.386344 | F22: 96.5 | G22: 96.377227 | H22: 96.5 | I22: 96.381932 | J22: 96.5 | K22: 96.36879 | L22: 96.5 | M22: 96.378393 | N22: 96.5 | O22: 96.278901 | P22: 96.5 | Q22: 96.350979 | R22: 96.5 | S22: 96.354196 | T22: 96.5 | U22: 96.351681 | V22: 96.5 | W22: 96.249592 | X22: 96.5 | Y22: 96.29443 | Z22: 96.5 | AA22: 96.333505 | AB22: 96.5 | AC22: 96.204059 | AD22: 96.5 | AE22: 96.314822 | AF22: 96.5 | AG22: 94.958487 | AH22: 96.5 | AI22: 96.305468 | AJ22: 96.5 | AK22: 96.296098 | AL22: 96.5 | AM22: 96.221812 | AN22: 96.5 | AO22: 96.304235 | AP22: 96.5 | AQ22: 96.148155 | AR22: 96.5 | AS22: 96.286184 | AT22: 96.5 | AU22: 96.184461 | AV22: 96.5 | AW22: 96.276198 | AX22: 96.5 | AY22: 96.379798 | AZ22: 96.5 | BA22: 96.243642 | BB22: 96.5 | BC22: 96.234989 | BD22: 96.5 | BE22: 96.286951 | BF22: 96.5 | BG22: 96.088708 | BH22: 96.5 | BI22: 95.450022 | BJ22: 96.499982 | BK22: 95.423966 | BL22: 96.209843 | BM22: 95.175924 | BN22: 96.5 | BO22: 96.065593 | BP22: 96.05494
A23: US Mill | B23: % | C23: 94.75 | D23: 94.75 | E23: 94.396456 | F23: 94.75 | G23: 94.472431 | H23: 94.75 | I23: 94.433403 | J23: 94.75 | K23: 94.056655 | L23: 94.75 | M23: 94.345198 | N23: 94.75 | O23: 93.978114 | P23: 94.75 | Q23: 94.244937 | R23: 94.75 | S23: 92.455322 | T23: 94.75 | U23: 93.930011 | V23: 94.75 | W23: 94.354897 | X23: 94.75 | Y23: 93.67897 | Z23: 94.75 | AA23: 94.006334 | AB23: 94.75 | AC23: 94.095026 | AD23: 94.75 | AE23: 94.020193 | AF23: 94.75 | AG23: 93.695979 | AH23: 94.75 | AI23: 94.010748 | AJ23: 94.75 | AK23: 91.062906 | AL23: 94.75 | AM23: 92.736312 | AN23: 94.75 | AO23: 93.648995 | AP23: 94.75 | AQ23: 93.529416 | AR23: 94.75 | AS23: 93.633199 | AT23: 94.75 | AU23: 94.085079 | AV23: 94.75 | AW23: 93.685624 | AX23: 94.75 | AY23: 94.093152 | AZ23: 94.75 | BA23: 93.914612 | BB23: 94.75 | BC23: 93.483365 | BD23: 94.75 | BE23: 93.736035 | BF23: 94.5 | BG23: 94.168642 | BH23: 94.5 | BI23: 93.371871 | BJ23: 95.700065 | BK23: 93.445481 | BL23: 95.699819 | BM23: 95.266762 | BN23: 95.7 | BO23: 95.476013 | BP23: 95.486333
A24: Sp Energy Consumption | B24: G.cal/TCS | C24: 5.950002 | D24: 5.8190698 | E24: 6.2156479 | F24: 5.8123281 | G24: 6.3285548 | H24: 5.8156436 | I24: 6.2723601 | J24: 6.2529957 | K24: 7.0163172 | L24: 5.9176447 | M24: 6.4699825 | N24: 7.7286662 | O24: 5.9975708 | P24: 6.0915485 | Q24: 6.3309225 | R24: 5.9155176 | S24: 5.9945722 | T24: 6.0467975 | U24: 6.2551875 | V24: 5.9554125 | W24: 5.9775121 | X24: 6.1598432 | Y24: 5.9899225 | Z24: 6.0287708 | AA24: 6.2078763 | AB24: 5.9185019 | AC24: 6.0970124 | AD24: 6.0094385 | AE24: 6.1913024 | AF24: 5.8679361 | AG24: 29.436172 | AH24: 5.9889093 | AI24: 6.3410739 | AJ24: 5.860739 | AK24: 5.9578574 | AL24: 5.8825485 | AM24: 6.4229771 | AN24: 5.9722026 | AO24: 6.2868672 | AP24: 5.8608476 | AQ24: 5.8560511 | AR24: 5.9593616 | AS24: 6.2300751 | AT24: 5.8591772 | AU24: 5.8885991 | AV24: 5.9499431 | AW24: 6.1941702 | AX24: 5.8704882 | AY24: 5.8758634 | AZ24: 5.8636538 | BA24: 5.873006 | BB24: 5.8732108 | BC24: 6.0909851 | BD24: 5.950002 | BE24: 6.1600133 | BF24: 5.9498029 | BG24: 6.1924446 | BH24: 5.9892031 | BI24: 6.2012038 | BJ24: 5.9854778 | BK24: 6.300637 | BL24: 6.1969869 | BM24: 6.4827566 | BN24: 5.95 | BO24: 6.1800191 | BP24: 6.3116941
A25: Sp Power Consumption | B25: KwH/TSS | C25: 498.86963 | D25: 485.07343 | E25: 474.83527 | F25: 507.78368 | G25: 565.47965 | H25: 496.3676 | I25: 516.32337 | J25: 593.17326 | K25: 591.60316 | L25: 520.81676 | M25: 536.99419 | N25: 853.7036 | O25: 472.54449 | P25: 563.2223 | Q25: 518.41033 | R25: 483.1292 | S25: 494.26516 | T25: 543.04701 | U25: 513.19767 | V25: 495.38777 | W25: 466.32576 | X25: 548.50849 | Y25: 477.545 | Z25: 533.90051 | AA25: 504.7149 | AB25: 473.75976 | AC25: 548.71956 | AD25: 523.38682 | AE25: 510.66495 | AF25: 466.25573 | AG25: 1065.6856 | AH25: 515.00246 | AI25: 526.53693 | AJ25: 477.18949 | AK25: 440.38863 | AL25: 472.42342 | AM25: 540.56277 | AN25: 510.12503 | AO25: 514.61576 | AP25: 473.76185 | AQ25: 429.41761 | AR25: 505.94401 | AS25: 503.98133 | AT25: 466.39505 | AU25: 447.46906 | AV25: 502.17743 | AW25: 498.34487 | AX25: 467.63958 | AY25: 432.53356 | AZ25: 469.33852 | BA25: 436.01158 | BB25: 470.89222 | BC25: 477.73863 | BD25: 498.86963 | BE25: 491.52958 | BF25: 491.86598 | BG25: 499.12041 | BH25: 499.14523 | BI25: 516.74946 | BJ25: 501.08848 | BK25: 528.34198 | BL25: 500.04339 | BM25: 579.80533 | BN25: 483.423 | BO25: 525.26173 | BP25: 552.03691
B26: KwH/TCS | C26: 483.40224 | D26: 455.56526 | E26: 463.60239 | F26: 456.55876 | G26: 518.43317 | H26: 456.07017 | I26: 489.55689 | J26: 605.46747 | K26: 615.50276 | L26: 490.91324 | M26: 521.8603 | N26: 1105.8745 | O26: 446.04086 | P26: 549.96505 | Q26: 499.54196 | R26: 465.99112 | S26: 451.24487 | T26: 528.61699 | U26: 488.66704 | V26: 466.04362 | W26: 436.22171 | X26: 546.18618 | Y26: 444.51204 | Z26: 516.2737 | AA26: 479.0368 | AB26: 456.53077 | AC26: 461.69014 | AD26: 505.79959 | AE26: 476.43601 | AF26: 456.68902 | AG26: 5465.2041 | AH26: 498.6746 | AI26: 503.01188 | AJ26: 456.53077 | AK26: 428.40644 | AL26: 456.58238 | AM26: 530.25646 | AN26: 493.18128 | AO26: 492.84816 | AP26: 456.53077 | AQ26: 411.09963 | AR26: 488.95488 | AS26: 482.64096 | AT26: 457.23431 | AU26: 419.70726 | AV26: 485.97278 | AW26: 476.24561 | AX26: 458.7979 | AY26: 430.04094 | AZ26: 457.53089 | BA26: 420.26723 | BB26: 457.05113 | BC26: 463.70311 | BD26: 483.40224 | BE26: 471.62787 | BF26: 475.02939 | BG26: 476.24946 | BH26: 482.32053 | BI26: 494.76974 | BJ26: 486.14726 | BK26: 514.38476 | BL26: 487.74658 | BM26: 580.20286 | BN26: 448.29125 | BO26: 538.52024 | BP26: 565.51994
A27: Sp Water Consumption | B27: M³/TCS | C27: 2.85 | D27: 2.85 | E27: 3.15 | F27: 2.85 | G27: 3.35 | H27: 2.85 | I27: 3.2446713 | J27: 2.85 | K27: 3.27 | L27: 2.85 | M27: 3.2511678 | N27: 2.85 | O27: 2.98 | P27: 2.85 | Q27: 3.1713463 | R27: 2.85 | S27: 2.93 | T27: 2.85 | U27: 3.117003 | V27: 2.85 | W27: 2.93 | X27: 2.85 | Y27: 2.9468158 | Z27: 2.85 | AA27: 3.0826648 | AB27: 2.85 | AC27: 2.99 | AD27: 2.85 | AE27: 3.0687715 | AF27: 2.85 | AG27: 3.19 | AH27: 2.85 | AI27: 3.0694173 | AJ27: 2.85 | AK27: 2.87 | AL27: 2.85 | AM27: 2.9327862 | AN27: 2.85 | AO27: 3.0422501 | AP27: 2.85 | AQ27: 2.87 | AR27: 2.85 | AS27: 3.0207428 | AT27: 2.85 | AU27: 2.86 | AV27: 2.85 | AW27: 3.004408 | AX27: 2.85 | AY27: 2.88 | AZ27: 2.85 | BA27: 2.8702899 | BB27: 2.85 | BC27: 2.8949703 | BD27: 2.85 | BE27: 2.9919746 | BF27: 2.85 | BG27: 3.0828892 | BH27: 3.3 | BI27: 3.0186532 | BJ27: 4.3 | BK27: 3.3197104 | BL27: 4.3 | BM27: 5.0407394 | BN27: 4.6 | BO27: 5.0056729 | BP27: 5.0192042
A28: Sp. CO2 emission | B28: T/TCS | C28: 2.32 | D28: 2.32 | E28: 2.45 | F28: 2.32 | G28: 2.39 | H28: 2.32 | I28: 2.4215986 | J28: 2.32 | K28: 2.591 | L28: 2.32 | M28: 2.4650478 | N28: 2.32 | O28: 2.36 | P28: 2.32 | Q28: 2.4341257 | R28: 2.32 | S28: 2.41 | T28: 2.32 | U28: 2.4286934 | V28: 2.32 | W28: 2.33 | X28: 2.32 | Y28: 2.3666511 | Z28: 2.32 | AA28: 2.4205709 | AB28: 2.32 | AC28: 2.36 | AD28: 2.32 | AE28: 2.4114895 | AF28: 2.32 | AH28: 2.32 | AI28: 2.45 | AJ28: 2.32 | AK28: 2.33 | AL28: 2.32 | AM28: 2.3045713 | AN28: 2.32 | AO28: 2.399652 | AP28: 2.32 | AQ28: 2.29 | AR28: 2.32 | AS28: 2.3759608 | AT28: 2.32 | AU28: 2.29 | AV28: 2.32 | AW28: 2.3672254 | AX28: 2.32 | AY28: 2.29 | AZ28: 2.32 | BA28: 2.29 | BB28: 2.32 | BC28: 2.2957544 | BD28: 2.32 | BE28: 2.3695074 | BF28: 2.375 | BG28: 2.4275692 | BH28: 2.35 | BI28: 2.4470555 | BJ28: 2.45 | BK28: 2.4734992 | BL28: 2.45 | BM28: 2.6211068 | BN28: 2.456658 | BO28: 2.4355942 | BP28: 2.609953
A29: Sp. PM emissions | B29: kg/TCS | C29: 0.5 | D29: 0.5 | E29: 0.54 | F29: 0.5 | G29: 0.57 | H29: 0.5 | I29: 0.55420069 | J29: 0.5 | K29: 0.58 | L29: 0.5 | M29: 0.56081787 | N29: 0.5 | O29: 0.52 | P29: 0.5 | Q29: 0.54880265 | R29: 0.5 | S29: 0.5 | T29: 0.5 | U29: 0.53781389 | V29: 0.5 | W29: 0.51 | X29: 0.5 | Y29: 0.51004297 | Z29: 0.5 | AA29: 0.53270659 | AB29: 0.5 | AC29: 0.5 | AD29: 0.5 | AE29: 0.52780287 | AF29: 0.5 | AH29: 0.5 | AI29: 0.54 | AJ29: 0.5 | AK29: 0.49 | AL29: 0.5 | AM29: 0.48641557 | AN29: 0.5 | AO29: 0.52318835 | AP29: 0.5 | AQ29: 0.46 | AR29: 0.5 | AS29: 0.51529859 | AT29: 0.5 | AU29: 0.44 | AV29: 0.5 | AW29: 0.50764672 | AX29: 0.5 | AY29: 0.49 | AZ29: 0.5 | BA29: 0.46399819 | BB29: 0.5 | BC29: 0.47285105 | BD29: 0.5 | BE29: 0.49588309 | BF29: 0.53 | BG29: 0.53450495 | BH29: 0.53 | BI29: 0.5280682 | BJ29: 0.55 | BK29: 0.53916083 | BL29: 0.55 | BM29: 0.62328215 | BN29: 0.551124 | BO29: 0.57147495 | BP29: 0.55061804
A30: Labour Productivity | B30: TCS/Man/Year | C30: 712.02135 | D30: 769.48165 | E30: 761.08746 | F30: 772.09241 | G30: 657.93142 | H30: 770.785 | I30: 708.55086 | J30: 480.12887 | K30: 511.97436 | L30: 675.31984 | M30: 643.66771 | N30: 221.11384 | O30: 780.59809 | P30: 560.72371 | Q30: 678.49399 | R30: 759.30661 | S30: 770.78122 | T30: 600.50395 | U30: 697.2069 | V30: 761.48024 | W30: 795.29293 | X30: 576.28232 | Y30: 782.08088 | Z30: 626.59207 | AA30: 713.30412 | AB30: 795.73412 | AC30: 739.55185 | AD30: 650.77455 | AE30: 717.10702 | AF30: 797.75563 | AG30: 30 * | AH30: 668.63469 | AI30: 632* | AJ30: 799.40216 | AK30: 783.42261 | AL30: 797.62644 | AM30: 523.0789 | AN30: 683.16207 | AO30: 649.49896 | AP30: 801.24889 | AQ30: 812.39513 | AR30: 694.94218 | AS30: 666.12009 | AT30: 800.86059 | AU30: 821.47127 | AV30: 703.76706 | AW30: 679.14173 | AX30: 804.50127 | AY30: 821.28851 | AZ30: 802.26722 | BA30: 818.29191 | BB30: 799.94404 | BC30: 668.98436 | BD30: 712.17383 | BE30: 691.16367 | BF30: 729.20664 | BG30: 695.16315 | BH30: 656.40621 | BI30: 639.11266 | BJ30: 615.77607 | BK30: 561.88094 | BL30: 549.90658 | BM30: 459.2495 | BN30: 562.64319 | BO30: 490.34382 | BP30: 421.02863
A31: Average Manpower (Works) | B31: Nos. | C31: 3503 | D31: 3577 | E31: 3524 | F31: 3565 | G31: 3544 | H31: 3571 | I31: 3534 | J31: 3552 | K31: 3540 | L31: 3564.6667 | M31: 3536 | N31: 3530 | O31: 3540 | P31: 3556 | Q31: 3537 | R31: 3508 | S31: 3540 | T31: 3546.4 | U31: 3537.6 | V31: 3494 | W31: 3543 | X31: 3519.3333 | Y31: 3541 | Z31: 3537.6667 | AA31: 3538.5 | AB31: 3487 | AC31: 3539 | AD31: 3530.4286 | AE31: 3538.5714 | AF31: 3479 | AG31: 3551 | AH31: 3524 | AI31: 3540.125 | AJ31: 3471 | AK31: 3568 | AL31: 3479 | AM31: 3552.6667 | AN31: 3518.1111 | AO31: 3543.2222 | AP31: 3463 | AQ31: 3570 | AR31: 3512.6 | AS31: 3545.9 | AT31: 3452 | AU31: 3545 | AV31: 3507.0909 | AW31: 3545.8182 | AX31: 3449 | AY31: 3531 | AZ31: 3454.6667 | BA31: 3548.6667 | BB31: 3466.8333 | BC31: 3550.6667 | BD31: 3502.25 | BE31: 3544.5833 | BF31: 3607.8333 | BG31: 3647.6667 | BH31: 3826.0833 | BI31: 3802.9167 | BJ31: 4009.5833 | BK31: 3995.5833 | BL31: 4196.5983 | BM31: 4090.3027 | BN31: 4470.8033 | BO31: 4421.3333 | BP31: 4614.4192
A32: Labor productivity calculation | B32: Crude Steel | C32: 2489528.3 | D32: 226056.6 | E32: 220127 | F32: 233603.77 | G32: 197854 | H32: 459660.38 | I32: 417981 | J32: 139811.32 | K32: 144189 | L32: 599471.7 | M32: 562170 | N32: 63679.245 | O32: 234513 | P32: 663150.94 | Q32: 796683 | R32: 226056.6 | S32: 231517 | T32: 889207.55 | U32: 1028200 | V32: 218509.43 | W32: 231269 | X32: 508245.28 | Y32: 697299 | Z32: 1107717 | AA32: 1259469 | AB32: 235490.57 | AC32: 222138 | AD32: 1343207.5 | AE32: 1481607 | AF32: 227943.4 | AG32: 7935 | AH32: 1571150.9 | AI32: 1489542 | AJ32: 235490.57 | AK32: 234930 | AL32: 698924.53 | AM32: 465003 | AN32: 1806641.5 | AO32: 1724472 | AP32: 235490.57 | AQ32: 246040 | AR32: 2042132.1 | AS32: 1970512 | AT32: 211905.66 | AU32: 222895 | AV32: 2254037.7 | AW32: 2193407 | AX32: 235490.57 | AY32: 243552 | AZ32: 682886.79 | BA32: 712487 | BB32: 1381811.3 | BC32: 1177490 | BD32: 2489528.3 | BE32: 2436959 | BF32: 2620075.5 | BG32: 2528925 | BH32: 2500000 | BI32: 2422324.3 | BJ32: 2573000.8 | BK32: 2322716
B33: Pig+Eq | C33: 9365 | D33: 342 | E33: 634.58215 | F33: 342 | G33: 363.10825 | H33: 684 | I33: 997.6904 | J33: 720 | K33: 9548.9962 | L33: 1404 | M33: 10546.687 | N33: 5225 | O33: 359.39334 | P33: 6629 | Q33: 10906.08 | R33: 342 | S33: 448.36058 | T33: 6971 | U33: 11354.441 | V33: 342 | W33: 649.31974 | X33: 5909 | Y33: 1457.0737 | Z33: 7313 | AA33: 12003.76 | AB33: 342 | AC33: 302.05043 | AD33: 7655 | AE33: 12305.811 | AF33: 342 | AG33: 1541.4762 | AH33: 7997 | AI33: 13847.287 | AJ33: 342 | AK33: 4949.9068 | AL33: 1026 | AM33: 6793.4334 | AN33: 8339 | AO33: 18797.194 | AP33: 342 | AQ33: 565.31098 | AR33: 8681 | AS33: 19362.505 | AT33: 342 | AU33: 1000.3476 | AV33: 9023 | AW33: 20362.852 | AX33: 342 | AY33: 5493.599 | AZ33: 1026 | BA33: 7059.2576 | BB33: 2052 | BC33: 13852.691 | BD33: 9365 | BE33: 25856.451 | BF33: 21561.1 | BG33: 13596.898 | BH33: 22929.735 | BI33: 16335.784 | BJ33: 34051.635 | BK33: 32547.079
B34: 50% of Pig Eq | C34: 4682.5 | D34: 171 | E34: 317.29107 | F34: 171 | G34: 181.55412 | H34: 342 | I34: 498.8452 | J34: 360 | K34: 4774.4981 | L34: 702 | M34: 5273.3433 | N34: 2612.5 | O34: 179.69667 | P34: 3314.5 | Q34: 5453.04 | R34: 171 | S34: 224.18029 | T34: 3485.5 | U34: 5677.2203 | V34: 171 | W34: 324.65987 | X34: 2954.5 | Y34: 728.53683 | Z34: 3656.5 | AA34: 6001.8801 | AB34: 171 | AC34: 151.02522 | AD34: 3827.5 | AE34: 6152.9053 | AF34: 171 | AG34: 770.7381 | AH34: 3998.5 | AI34: 6923.6434 | AJ34: 171 | AK34: 2474.9534 | AL34: 513 | AM34: 3396.7167 | AN34: 4169.5 | AO34: 9398.5968 | AP34: 171 | AQ34: 282.65549 | AR34: 4340.5 | AS34: 9681.2523 | AT34: 171 | AU34: 500.17378 | AV34: 4511.5 | AW34: 10181.426 | AX34: 171 | AY34: 2746.7995 | AZ34: 513 | BA34: 3529.6288 | BB34: 1026 | BC34: 6926.3455 | BD34: 4682.5 | BE34: 12928.226 | BF34: 10780.55 | BG34: 6798.4488 | BH34: 11464.868 | BI34: 8167.892 | BJ34: 17025.818 | BK34: 16273.54
B35: CS+50%Pig Eq | C35: 2494210.8 | D35: 226227.6 | E35: 220444.29 | F35: 233774.77 | G35: 198035.55 | H35: 460002.38 | I35: 418479.85 | J35: 140171.32 | K35: 148963.5 | L35: 600173.7 | M35: 567443.34 | N35: 66291.745 | O35: 234692.7 | P35: 666465.44 | Q35: 802136.04 | R35: 226227.6 | S35: 231741.18 | T35: 892693.05 | U35: 1033877.2 | V35: 218680.43 | W35: 231593.66 | X35: 511199.78 | Y35: 698027.54 | Z35: 1111373.5 | AA35: 1265470.9 | AB35: 235661.57 | AC35: 222289.03 | AD35: 1347035 | AE35: 1487759.9 | AF35: 228114.4 | AG35: 8705.7381 | AH35: 1575149.4 | AI35: 1496465.6 | AJ35: 235661.57 | AK35: 237404.95 | AL35: 699437.53 | AM35: 468399.72 | AN35: 1810811 | AO35: 1733870.6 | AP35: 235661.57 | AQ35: 246322.66 | AR35: 2046472.6 | AS35: 1980193.3 | AT35: 212076.66 | AU35: 223395.17 | AV35: 2258549.2 | AW35: 2203588.4 | AX35: 235661.57 | AY35: 246298.8 | AZ35: 683399.79 | BA35: 716016.63 | BB35: 1382837.3 | BC35: 1184416.3 | BD35: 2494210.8 | BE35: 2449887.2 | BF35: 2630856 | BG35: 2535723.4 | BH35: 2511464.9 | BI35: 2430492.2 | BJ35: 2590026.6 | BK35: 2338989.5
C36: 712.02135 | D36: 769.48165 | E36: 761.08746 | F36: 772.09241 | G36: 657.93142 | H36: 770.785 | I36: 708.55086 | J36: 480.12887 | K36: 511.97436 | L36: 675.31984 | M36: 643.66771 | N36: 221.11384 | O36: 780.59809 | P36: 560.72371 | Q36: 678.49399 | R36: 759.30661 | S36: 770.78122 | T36: 600.50395 | U36: 697.2069 | V36: 761.48024 | W36: 795.29293 | X36: 576.28232 | Y36: 782.08088 | Z36: 626.59207 | AA36: 713.30412 | AB36: 795.73412 | AC36: 739.55185 | AD36: 650.77455 | AE36: 717.10702 | AF36: 797.75563 | AG36: 29.828165 | AH36: 668.63469 | AI36: 632.34078 | AJ36: 799.40216 | AK36: 783.42261 | AL36: 797.62644 | AM36: 523.0789 | AN36: 683.16207 | AO36: 649.49896 | AP36: 801.24889 | AQ36: 812.39513 | AR36: 694.94218 | AS36: 666.12009 | AT36: 800.86059 | AU36: 821.47127 | AV36: 703.76706 | AW36: 679.14173 | AX36: 804.50127 | AY36: 821.28851 | AZ36: 802.26722 | BA36: 818.29191 | BB36: 799.94404 | BC36: 668.98436 | BD36: 712.17383 | BE36: 691.16367 | BF36: 729.20664 | BG36: 695.16315 | BH36: 656.40621 | BI36: 639.11266 | BJ36: 645.95904 | BK36: 585.39376
A38: Hot metal consumed in BOF | B38: MT | C38: 2638900 | D38: 239620 | E38: 234575 | F38: 247620 | G38: 208628.78 | H38: 487240 | I38: 443203.78 | J38: 148200 | K38: 153381.25 | L38: 635440 | M38: 596585.03 | N38: 67500 | O38: 248296.54 | P38: 702940 | Q38: 844881.57 | R38: 239620 | S38: 243694.68 | T38: 942560 | U38: 1088576.2 | V38: 231620 | W38: 244527.55 | X38: 538740 | Y38: 736518.77 | Z38: 1174180 | AA38: 1333103.8 | AB38: 249620 | AC38: 235736.8 | AD38: 1423800 | AE38: 1568840.6 | AF38: 241620 | AG38: 8398.2 | AH38: 1665420 | AI38: 1577238.8 | AJ38: 249620 | AK38: 249391.75 | AL38: 740860 | AM38: 493526.75 | AN38: 1915040 | AO38: 1826630.5 | AP38: 249620 | AQ38: 261382.3 | AR38: 2164660 | AS38: 2088012.8 | AT38: 224620 | AU38: 236601.12 | AV38: 2389280 | AW38: 2324614 | AX38: 249620 | AY38: 257456.17 | AZ38: 723860 | BA38: 755439.59 | BB38: 1464720 | BC38: 1248966.3 | BD38: 2638900 | BE38: 2582070.1 | BF38: 2777280 | BG38: 2695862.8 | BH38: 2655000 | BI38: 2574868 | BJ38: 2611100.5 | BK38: 2366123.2
A39: Total Scrap Charged | B39: MT | C39: 99581.132 | D39: 9042.2642 | E39: 6979.5 | F39: 9344.1509 | G39: 8670.7 | H39: 18386.415 | I39: 15650.2 | J39: 5592.4528 | K39: 5196.4 | L39: 23978.868 | M39: 20846.6 | N39: 2547.1698 | O39: 8993.6 | P39: 26526.038 | Q39: 29840.2 | R39: 9042.2642 | S39: 10216.4 | T39: 35568.302 | U39: 40056.6 | V39: 8740.3774 | W39: 8507.6 | X39: 20329.811 | Y39: 27717.6 | Z39: 44308.679 | AA39: 48564.2 | AB39: 9419.6226 | AC39: 7554.5 | AD39: 53728.302 | AE39: 56118.7 | AF39: 9117.7358 | AG39: 326.2 | AH39: 62846.038 | AI39: 56444.9 | AJ39: 9419.6226 | AK39: 8846.2 | AL39: 27956.981 | AM39: 16726.9 | AN39: 72265.66 | AO39: 65291.1 | AP39: 9419.6226 | AQ39: 9232.5 | AR39: 81685.283 | AS39: 74523.6 | AT39: 8476.2264 | AU39: 7958.2 | AV39: 90161.509 | AW39: 82481.8 | AX39: 9419.6226 | AY39: 9343.2 | AZ39: 27315.472 | BA39: 26533.9 | BB39: 55272.453 | BC39: 43260.8 | BD39: 99581.132 | BE39: 91825 | BF39: 104803.02 | BG39: 87073.52 | BH39: 121081.64 | BI39: 93275 | BJ39: 128650.04 | BK39: 101615.76
A40: Fe-Mn | B40: MT | C40: 4107.7217 | D40: 372.9934 | E40: 253 | F40: 385.44623 | G40: 224 | H40: 758.43962 | I40: 477 | J40: 230.68868 | K40: 92 | L40: 989.1283 | M40: 569 | N40: 105.07075 | O40: 248 | P40: 1094.1991 | Q40: 817 | R40: 372.9934 | S40: 276 | T40: 1467.1925 | U40: 1093 | V40: 360.54057 | W40: 314 | X40: 838.60472 | Y40: 838 | Z40: 1827.733 | AA40: 1407 | AB40: 388.55943 | AC40: 291 | AD40: 2216.2925 | AE40: 1698 | AF40: 376.1066 | AG40: 2 | AH40: 2592.3991 | AI40: 1700 | AJ40: 388.55943 | AK40: 421 | AL40: 1153.2255 | AM40: 714 | AN40: 2980.9585 | AO40: 2121 | AP40: 388.55943 | AQ40: 443 | AR40: 3369.5179 | AS40: 2564 | AT40: 349.64434 | AU40: 330 | AV40: 3719.1623 | AW40: 2894 | AX40: 388.55943 | AY40: 328 | AZ40: 1126.7632 | BA40: 1101 | BB40: 2279.9887 | BC40: 1815 | BD40: 4107.7217 | BE40: 3222 | BF40: 3385.0943 | BG40: 4727 | BH40: 4500 | BI40: 4569.84 | BJ40: 6693.3528 | BK40: 4136
A41: LCFeMn | B41: MT | C41: 2116.0991 | D41: 192.14811 | E41: 125 | F41: 198.56321 | G41: 98 | H41: 0 | I41: 223 | J41: 118.83962 | K41: 64 | L41: 0 | M41: 287 | N41: 54.127358 | O41: 205 | P41: 0 | Q41: 492 | R41: 192.14811 | S41: 120 | T41: 0 | U41: 612 | V41: 185.73302 | W41: 191 | X41: 432.00849 | Y41: 516 | Z41: 432.00849 | AA41: 803 | AB41: 200.16698 | AC41: 155 | AD41: 0 | AE41: 958 | AG41: 9 | AH41: 0 | AI41: 967 | AK41: 123 | AL41: 200.16698 | AM41: 287 | AN41: 0 | AO41: 1090 | AQ41: 116 | AR41: 0 | AS41: 1206 | AU41: 149 | AV41: 0 | AW41: 1355 | AY41: 78 | AZ41: 0 | BA41: 343 | BB41: 200.16698 | BC41: 630 | BD41: 0 | BE41: 1433 | BF41: 0 | BG41: 1668.305 | BH41: 0 | BI41: 1122.042 | BJ41: 0 | BK41: 968.34
A42: Total Fe-Mn | B42: MT | C42: 6223.8208 | D42: 565.14151 | E42: 378 | F42: 584.00943 | G42: 322 | H42: 758.43962 | I42: 700 | J42: 349.5283 | K42: 156 | L42: 989.1283 | M42: 856 | N42: 159.19811 | O42: 453 | P42: 1094.1991 | Q42: 1309 | R42: 565.14151 | S42: 396 | T42: 1467.1925 | U42: 1705 | V42: 546.27358 | W42: 505 | X42: 1270.6132 | Y42: 1354 | Z42: 2259.7415 | AA42: 2210 | AB42: 588.72642 | AC42: 446 | AD42: 2216.2925 | AE42: 2656 | AF42: 376.1066 | AG42: 11 | AH42: 2592.3991 | AI42: 2667 | AJ42: 388.55943 | AK42: 544 | AL42: 1353.3925 | AM42: 1001 | AN42: 2980.9585 | AO42: 3211 | AP42: 388.55943 | AQ42: 559 | AR42: 3369.5179 | AS42: 3770 | AT42: 349.64434 | AU42: 479 | AV42: 3719.1623 | AW42: 4249 | AX42: 388.55943 | AY42: 406 | AZ42: 1126.7632 | BA42: 1444 | BB42: 2480.1557 | BC42: 2445 | BD42: 4107.7217 | BE42: 4655 | BF42: 3385.0943 | BG42: 6395.305 | BH42: 4500 | BI42: 5691.882 | BJ42: 6693.3528 | BK42: 5104.34
A43: Si-Mn | B43: MT | C43: 45682.844 | D43: 4148.1387 | E43: 3841 | F43: 4286.6292 | G43: 3205 | H43: 8434.7679 | I43: 7046 | J43: 2565.5377 | K43: 2088 | L43: 11000.306 | M43: 9134 | N43: 1168.5142 | O43: 3644.44 | P43: 12168.82 | Q43: 12778.44 | R43: 4148.1387 | S43: 3948 | T43: 16316.958 | U43: 16726.44 | V43: 4009.6481 | W43: 3673 | X43: 9326.3009 | Y43: 11265.44 | Z43: 20326.607 | AA43: 20399.44 | AB43: 4321.2519 | AC43: 3276 | AD43: 24647.858 | AE43: 23675.44 | AF43: 4182.7613 | AG43: 110 | AH43: 28830.62 | AI43: 23785.44 | AJ43: 4321.2519 | AK43: 3928 | AL43: 12825.265 | AM43: 7314 | AN43: 33151.872 | AO43: 27713.44 | AP43: 4321.2519 | AQ43: 4040 | AR43: 37473.124 | AS43: 31753.44 | AT43: 3888.4689 | AU43: 3626 | AV43: 41361.592 | AW43: 35379.44 | AX43: 4321.2519 | AY43: 4060 | AZ43: 12530.973 | BA43: 11726 | BB43: 25356.238 | BC43: 19040 | BD43: 45682.844 | BE43: 39439.44 | BF43: 44076.08 | BG43: 45680 | BH43: 40000 | BI43: 44647.62 | BJ43: 42007.866 | BK43: 36347
A44: LP Si-Mn | B44: MT | E44: 0 | G44: 0 | I44: 0 | K44: 0 | M44: 0 | O44: 0 | Q44: 0 | S44: 0 | U44: 0 | W44: 0 | Y44: 0 | AA44: 0 | AC44: 0 | AE44: 0 | AG44: 0 | AI44: 0 | AK44: 0 | AM44: 0 | AO44: 0 | AQ44: 0 | AS44: 0 | AU44: 0 | AW44: 0 | AY44: 0 | BA44: 0 | BC44: 0 | BE44: 0 | BG44: 25.81
A45: Total Si-Mn | B45: MT | C45: 45682.844 | D45: 4148.1387 | E45: 3841 | F45: 4286.6292 | G45: 3205 | H45: 8434.7679 | I45: 7046 | J45: 2565.5377 | K45: 2088 | L45: 11000.306 | M45: 9134 | N45: 1168.5142 | O45: 3644.44 | P45: 12168.82 | Q45: 12778.44 | R45: 4148.1387 | S45: 3948 | T45: 16316.958 | U45: 16726.44 | V45: 4009.6481 | W45: 3673 | X45: 9326.3009 | Y45: 11265.44 | Z45: 20326.607 | AA45: 20399.44 | AB45: 4321.2519 | AC45: 3276 | AD45: 24647.858 | AE45: 23675.44 | AF45: 4182.7613 | AG45: 110 | AH45: 28830.62 | AI45: 23785.44 | AJ45: 4321.2519 | AK45: 3928 | AL45: 12825.265 | AM45: 7314 | AN45: 33151.872 | AO45: 27713.44 | AP45: 4321.2519 | AQ45: 4040 | AR45: 37473.124 | AS45: 31753.44 | AT45: 3888.4689 | AU45: 3626 | AV45: 41361.592 | AW45: 35379.44 | AX45: 4321.2519 | AY45: 4060 | AZ45: 12530.973 | BA45: 11726 | BB45: 25356.238 | BC45: 19040 | BD45: 45682.844 | BE45: 39439.44 | BF45: 44076.08 | BG45: 45705.81
A46: Fe-Si | B46: MT | C46: 5352.4858 | D46: 486.0217 | E46: 461 | F46: 502.24811 | G46: 501 | H46: 988.26981 | I46: 962 | J46: 300.59434 | K46: 293 | L46: 1288.8642 | M46: 1255 | N46: 136.91038 | O46: 513 | P46: 1425.7745 | Q46: 1768 | R46: 486.0217 | S46: 562 | T46: 1911.7962 | U46: 2330 | V46: 469.79528 | W46: 581.407 | X46: 1092.7274 | Y46: 1656.407 | Z46: 2381.5915 | AA46: 2911.407 | AB46: 506.30472 | AC46: 614 | AD46: 2887.8962 | AE46: 3525.407 | AF46: 490.0783 | AG46: 19 | AH46: 3377.9745 | AI46: 3544.407 | AJ46: 506.30472 | AK46: 538 | AL46: 1502.6877 | AM46: 1171 | AN46: 3884.2792 | AO46: 4082.407 | AP46: 506.30472 | AQ46: 540 | AR46: 4390.584 | AS46: 4622.407 | AT46: 455.59717 | AU46: 495 | AV46: 4846.1811 | AW46: 5117.407 | AX46: 506.30472 | AY46: 510 | AZ46: 1468.2066 | BA46: 1545 | BB46: 2970.8943 | BC46: 2716 | BD46: 5352.4858 | BE46: 5627.407 | BF46: 7386.6389 | BG46: 5310 | BH46: 8000 | BI46: 5205.89 | BJ46: 7796.1924 | BK46: 5192
A47: Ferro Alloys Break-up
A48: Fe-Mn | B48: Kg/TCS | C48: 1.65 | D48: 1.65 | E48: 1.1493365 | F48: 1.65 | G48: 1.1321479 | H48: 1.65 | I48: 1.1412002 | J48: 1.65 | K48: 0.63805145 | L48: 1.65 | M48: 1.0121493 | N48: 1.65 | O48: 1.0575107 | P48: 1.65 | Q48: 1.025502 | R48: 1.65 | S48: 1.1921371 | T48: 1.65 | U48: 1.0630228 | V48: 1.65 | W48: 1.3577263 | X48: 1.65 | Y48: 1.20178 | Z48: 1.65 | AA48: 1.1171375 | AB48: 1.65 | AC48: 1.3099965 | AD48: 1.65 | AE48: 1.1460529 | AF48: 1.65 | AG48: 0.25204789 | AH48: 1.65 | AI48: 1.1412904 | AJ48: 1.65 | AK48: 1.7920232 | AL48: 1.65 | AM48: 1.535474 | AN48: 1.65 | AO48: 1.2299417 | AP48: 1.65 | AQ48: 1.8005202 | AR48: 1.65 | AS48: 1.3011847 | AT48: 1.65 | AU48: 1.4805177 | AV48: 1.65 | AW48: 1.3194086 | AX48: 1.65 | AY48: 1.346735 | AZ48: 1.65 | BA48: 1.5452914 | BB48: 1.65 | BC48: 1.5414144 | BD48: 1.65 | BE48: 1.3221396 | BF48: 1.2919835 | BG48: 1.8691737 | BH48: 1.8 | BI48: 1.8865517 | BJ48: 2.60138 | BK48: 1.780674
A49: LCFeMn | B49: Kg/TCS | C49: 0.85 | D49: 0.85 | E49: 0.56785401 | F49: 0.85 | G49: 0.49531473 | H49: 0.85 | I49: 0.53351707 | J49: 0.85 | K49: 0.44386188 | L49: 0.85 | M49: 0.51052173 | N49: 0.85 | O49: 0.87415197 | P49: 0.85 | Q49: 0.61756056 | R49: 0.85 | S49: 0.51832047 | T49: 0.85 | U49: 0.59521494 | V49: 0.85 | W49: 0.82587809 | X49: 0.85 | Y49: 0.73999819 | Z49: 0.85 | AA49: 0.63757028 | AB49: 0.85 | AC49: 0.69776445 | AD49: 0.85 | AE49: 0.64659522 | AF49: 0.85 | AG49: 1.1342155 | AH49: 0.85 | AI49: 0.64919284 | AJ49: 0.85 | AK49: 0.52356021 | AL49: 0.85 | AM49: 0.61720032 | AN49: 0.85 | AO49: 0.63207753 | AP49: 0.85 | AQ49: 0.47146805 | AR49: 0.85 | AS49: 0.61202368 | AT49: 0.85 | AU49: 0.66847619 | AV49: 0.85 | AW49: 0.61776041 | AX49: 0.85 | AY49: 0.32026015 | AZ49: 0.85 | BA49: 0.48141229 | BB49: 0.85 | BC49: 0.53503639 | BD49: 0.85 | BE49: 0.58802795 | BF49: 0.24 | BG49: 0.65968939 | BH49: 0 | BI49: 0.46320883 | BJ49: 0 | BK49: 0.41689987
A50: Total Fe-Mn | B50: Kg/TCS | C50: 2.5 | D50: 2.5 | E50: 1.7171905 | F50: 2.5 | G50: 1.6274627 | H50: 2.5 | I50: 1.6747173 | J50: 2.5 | K50: 1.0819133 | L50: 2.5 | M50: 1.5226711 | N50: 2.5 | O50: 1.9316626 | P50: 2.5 | Q50: 1.6430625 | R50: 2.5 | S50: 1.7104575 | T50: 2.5 | U50: 1.6582377 | V50: 2.5 | W50: 2.1836044 | X50: 2.5 | Y50: 1.9417782 | Z50: 2.5 | AA50: 1.7547077 | AB50: 2.5 | AC50: 2.0077609 | AD50: 2.5 | AE50: 1.7926481 | AF50: 2.5 | AG50: 1.3862634 | AH50: 2.5 | AI50: 1.7904832 | AJ50: 2.5 | AK50: 2.3155834 | AL50: 2.5 | AM50: 2.1526743 | AN50: 2.5 | AO50: 1.8620192 | AP50: 2.5 | AQ50: 2.2719883 | AR50: 2.5 | AS50: 1.9132083 | AT50: 2.5 | AU50: 2.1489939 | AV50: 2.5 | AW50: 1.937169 | AX50: 2.5 | AY50: 1.6669951 | AZ50: 2.5 | BA50: 2.0267036 | BB50: 2.5 | BC50: 2.0764508 | BD50: 2.5 | BE50: 1.9101675 | BF50: 1.5319835 | BG50: 2.5288631 | BH50: 1.8 | BI50: 2.3497605 | BJ50: 2.60138 | BK50: 2.1975739
A51: Si-Mn | B51: Kg/TCS | C51: 18.35 | D51: 18.35 | E51: 17.449018 | F51: 18.35 | G51: 16.198813 | H51: 18.35 | I51: 16.857226 | J51: 18.35 | K51: 14.480994 | L51: 18.35 | M51: 16.247754 | N51: 18.35 | O51: 15.54046 | P51: 18.35 | Q51: 16.039554 | R51: 18.35 | S51: 17.052743 | T51: 18.35 | U51: 16.267691 | V51: 18.35 | W51: 15.881938 | X51: 18.35 | Y51: 16.155824 | Z51: 18.35 | AA51: 16.196858 | AB51: 18.35 | AC51: 14.747589 | AD51: 18.35 | AE51: 15.979568 | AF51: 18.35 | AG51: 13.862634 | AH51: 18.35 | AI51: 15.968291 | AJ51: 18.35 | AK51: 16.719874 | AL51: 18.35 | AM51: 15.728931 | AN51: 18.35 | AO51: 16.070681 | AP51: 18.35 | AQ51: 16.420094 | AR51: 18.35 | AS51: 16.114309 | AT51: 18.35 | AU51: 16.267749 | AV51: 18.35 | AW51: 16.129902 | AX51: 18.35 | AY51: 16.669951 | AZ51: 18.35 | BA51: 16.457844 | BB51: 18.35 | BC51: 16.169989 | BD51: 18.35 | BE51: 16.183875 | BF51: 16.822447 | BG51: 18.063011 | BH51: 16 | BI51: 18.431727 | BJ51: 16.32641 | BK51: 15.648491
A52: LP Si-Mn | B52: Kg/TCS | C52: 0 | D52: 0 | E52: 0 | F52: 0 | G52: 0 | I52: 0 | J52: 0 | K52: 0 | L52: 0 | M52: 0 | N52: 0 | O52: 0 | Q52: 0 | R52: 0 | S52: 0 | U52: 0 | V52: 0 | W52: 0 | X52: 0 | Y52: 0 | Z52: 0 | AA52: 0 | AB52: 0 | AC52: 0 | AE52: 0 | AF52: 0 | AG52: 0 | AH52: 0 | AI52: 0 | AJ52: 0 | AK52: 0 | AL52: 0 | AM52: 0 | AN52: 0 | AO52: 0 | AP52: 0 | AQ52: 0 | AR52: 0 | AS52: 0 | AT52: 0 | AU52: 0 | AV52: 0 | AW52: 0 | AX52: 0 | AY52: 0 | AZ52: 0 | BA52: 0 | BB52: 0 | BC52: 0 | BD52: 0 | BE52: 0 | BF52: 0 | BG52: 0.010205918
A53: Total Si-Mn | B53: Kg/TCS | C53: 18.35 | D53: 18.35 | E53: 17.449018 | F53: 18.35 | G53: 16.198813 | H53: 18.35 | I53: 16.857226 | J53: 18.35 | K53: 14.480994 | L53: 18.35 | M53: 16.247754 | N53: 18.35 | O53: 15.54046 | P53: 18.35 | Q53: 16.039554 | R53: 18.35 | S53: 17.052743 | T53: 18.35 | U53: 16.267691 | V53: 18.35 | W53: 15.881938 | X53: 18.35 | Y53: 16.155824 | Z53: 18.35 | AA53: 16.196858 | AB53: 18.35 | AC53: 14.747589 | AD53: 18.35 | AE53: 15.979568 | AF53: 18.35 | AG53: 13.862634 | AH53: 18.35 | AI53: 15.968291 | AJ53: 18.35 | AK53: 16.719874 | AL53: 18.35 | AM53: 15.728931 | AN53: 18.35 | AO53: 16.070681 | AP53: 18.35 | AQ53: 16.420094 | AR53: 18.35 | AS53: 16.114309 | AT53: 18.35 | AU53: 16.267749 | AV53: 18.35 | AW53: 16.129902 | AX53: 18.35 | AY53: 16.669951 | AZ53: 18.35 | BA53: 16.457844 | BB53: 18.35 | BC53: 16.169989 | BD53: 18.35 | BE53: 16.183875 | BF53: 16.822447 | BG53: 18.073217 | BH53: 16 | BI53: 18.431727 | BK53: 15.648491
A54: Fe-Si | B54: Kg/TCS | C54: 2.15 | D54: 2.15 | E54: 2.0942456 | F54: 2.15 | G54: 2.5321702 | H54: 2.15 | I54: 2.30154 | J54: 2.15 | K54: 2.0320551 | L54: 2.15 | M54: 2.2324208 | N54: 2.15 | O54: 2.187512 | P54: 2.15 | Q54: 2.2192014 | R54: 2.15 | S54: 2.4274675 | T54: 2.15 | U54: 2.2660961 | V54: 2.15 | W54: 2.5139859 | X54: 2.15 | Y54: 2.3754616 | Z54: 2.15 | AA54: 2.3116147 | AB54: 2.15 | AC54: 2.7640476 | AD54: 2.15 | AE54: 2.3794481 | AF54: 2.15 | AG54: 2.3944549 | AH54: 2.15 | AI54: 2.3795281 | AJ54: 2.15 | AK54: 2.2900438 | AL54: 2.15 | AM54: 2.5182633 | AN54: 2.15 | AO54: 2.3673374 | AP54: 2.15 | AQ54: 2.1947651 | AR54: 2.15 | AS54: 2.3457898 | AT54: 2.15 | AU54: 2.2207766 | AV54: 2.15 | AW54: 2.3330859 | AX54: 2.15 | AY54: 2.0940087 | AZ54: 2.15 | BA54: 2.1684606 | BB54: 2.15 | BC54: 2.3066013 | BD54: 2.15 | BE54: 2.3091923 | BF54: 2.8192466 | BG54: 2.0997064 | BH54: 3.2 | BI54: 2.1491301 | BJ54: 3.03 | BK54: 2.2353142
A57: *Blast Furnace was under capital repair in the month of Nov'24 wef 2nd Nov'24

Sheet Major techno all dept
C3: MAJOR TECHNO PARAMETERS 2024-25
C4: DEPARTMENTS | D4: ITEM | E4: Unit | F4: 2022-23 Actual | G4: ABP 2024-25 | H4: Apr'24 | J4: May'24 | L4: 2M | N4: Jun'24 | P4: QTR-1 | R4: Jul'24 | T4: 4M | V4: Aug'24 | X4: 5M | Z4: Sep'24 | AB4: QTR-2 | AD4: H1 | AF4: Oct'24 | AH4: 7M | AJ4: Nov'24 | AL4: 8M | AN4: Dec'24 | AP4: QTR-3 | AR4: 9M | AT4: Jan'25 | AV4: 10M | AX4: Feb'25 | AZ4: 11M | BB4: Mar'25 | BD4: QTR-4 | BF4: H2 | BH4: 2024-25
H5: ABP | I5: ACT | J5: ABP | K5: ACT | L5: ABP | M5: ACT | N5: ABP | O5: ACT | P5: ABP | Q5: ACT | R5: ABP | S5: ACT | T5: ABP | U5: ACT | V5: ABP | W5: ACT | X5: ABP | Y5: ACT | Z5: ABP | AA5: ACT | AB5: ABP | AC5: ACT | AD5: ABP | AE5: ACT | AF5: ABP | AG5: ACT | AH5: ABP | AI5: ACT | AJ5: ABP | AK5: ACT | AL5: ABP | AM5: ACT | AN5: ABP | AO5: ACT | AP5: ABP | AQ5: ACT | AR5: ABP | AS5: ACT | AT5: ABP | AU5: ACT | AV5: ABP | AW5: ACT | AX5: ABP | AY5: ACT | AZ5: ABP | BA5: ACT | BB5: ABP | BC5: ACT | BD5: ABP | BE5: ACT | BF5: ABP | BG5: ACT | BH5: ABP | BI5: ACT
C6: COKE OVENS | D6: B.F.Coke Yield | E6: % | F6: 69.459875 | G6: 70 | H6: 70 | I6: 70.02 | J6: 70 | K6: 70.02 | L6: 70 | M6: 70.02 | N6: 70 | O6: 70.01 | P6: 70 | Q6: 70.01675 | R6: 70 | S6: 70.503373 | T6: 70 | U6: 70.141085 | V6: 70 | W6: 70.5 | X6: 70 | Y6: 70.214032 | Z6: 70 | AA6: 70.5 | AB6: 70 | AC6: 70.501139 | AD6: 70 | AE6: 70.260896 | AF6: 70 | AG6: 70.453746 | AH6: 70 | AI6: 70.288712 | AJ6: 70 | AK6: 70.49 | AL6: 70 | AM6: 70.312514 | AN6: 70 | AO6: 70.01 | AP6: 70 | AQ6: 70.313108 | AR6: 70 | AS6: 70.278182 | AT6: 70 | AU6: 70.595 | AV6: 70 | AW6: 70.310473 | AX6: 70 | AY6: 70.5 | AZ6: 70 | BA6: 70.326436 | BB6: 70 | BC6: 70.5 | BD6: 70 | BE6: 70.532713 | BF6: 70 | BG6: 70.422664 | BH6: 70 | BI6: 70.341275
D7: ICC in Coal Blend
D8: (COB#10) | E8: % | F8: 89.651306 | G8: 95 | H8: 95 | I8: 93.3 | J8: 95 | K8: 95 | L8: 95 | M8: 94.163689 | N8: 95 | O8: 94.999982 | P8: 95 | Q8: 94.436875 | R8: 95 | S8: 95.000052 | T8: 95 | U8: 94.579199 | V8: 95 | W8: 93.451695 | X8: 95 | Y8: 94.348083 | Z8: 95 | AA8: 92.000071 | AB8: 95 | AC8: 93.489976 | AD8: 95 | AE8: 93.959413 | AF8: 95 | AG8: 92.000348 | AH8: 95 | AI8: 93.676577 | AJ8: 95 | AK8: 90.270086 | AL8: 95 | AM8: 93.273632 | AN8: 95 | AO8: 91.999923 | AP8: 95 | AQ8: 91.450919 | AR8: 95 | AS8: 93.130074 | AT8: 95 | AU8: 91.999923 | AV8: 95 | AW8: 93.015598 | AX8: 95 | AY8: 90.285714 | AZ8: 95 | BA8: 92.787463 | BB8: 95 | BC8: 89.032227 | BD8: 95 | BE8: 90.444569 | BF8: 95 | BG8: 90.950596 | BH8: 95 | BI8: 92.468484
D9: (COB#11) | E9: % | F9: 92.198587 | G9: 100 | H9: 100 | I9: 97.166665 | J9: 100 | K9: 100 | L9: 100 | M9: 98.603087 | N9: 100 | O9: 100 | P9: 100 | Q9: 99.057142 | R9: 100 | S9: 100 | T9: 100 | U9: 99.298048 | V9: 100 | W9: 100 | X9: 100 | Y9: 99.440715 | Z9: 100 | AA9: 97.799999 | AB9: 100 | AC9: 99.28486 | AD9: 100 | AE9: 99.171912 | AF9: 100 | AG9: 96.999629 | AH9: 100 | AI9: 98.858749 | AJ9: 100 | AK9: 95.266663 | AL9: 100 | AM9: 98.433936 | AN9: 100 | AO9: 96.999996 | AP9: 100 | AQ9: 96.450906 | AR9: 100 | AS9: 98.27118 | AT9: 100 | AU9: 96.999996 | AV9: 100 | AW9: 98.141604 | AX9: 100 | AY9: 97.000003 | AZ9: 100 | BA9: 98.045441 | BB9: 100 | BC9: 95.387093 | BD9: 100 | BE9: 96.443687 | BF9: 100 | BG9: 96.447304 | BH9: 100 | BI9: 97.818139
D10: Overall ICC in Blend | E10: % | F10: 91.262624 | G10: 98.275343 | H10: 98.275343 | I10: 95.80456 | J10: 98.275343 | K10: 98.233722 | L10: 98.275343 | M10: 97.037004 | N10: 98.275343 | O10: 98.227714 | P10: 98.275343 | Q10: 97.424716 | R10: 98.275343 | S10: 98.250206 | T10: 98.275343 | U10: 97.634822 | V10: 98.275343 | W10: 97.675956 | X10: 98.275343 | Y10: 97.643207 | Z10: 98.275343 | AA10: 95.736452 | AB10: 98.275343 | AC10: 97.236172 | AD10: 98.275343 | AE10: 97.329674 | AF10: 98.275343 | AG10: 95.230804 | AH10: 98.275343 | AI10: 97.026939 | AJ10: 98.275343 | AK10: 93.500197 | AL10: 98.275343 | AM10: 96.609824 | AN10: 98.275343 | AO10: 95.241553 | AP10: 98.275343 | AQ10: 94.685925 | AR10: 98.275343 | AS10: 96.454905 | AT10: 98.275343 | AU10: 95.241553 | AV10: 98.275343 | AW10: 96.331499 | AX10: 98.275343 | AY10: 94.642312 | AZ10: 98.275343 | BA10: 96.189607 | BB10: 98.275343 | BC10: 93.154562 | BD10: 98.275343 | BE10: 94.335671 | BF10: 98.275343 | BG10: 94.51139 | BH10: 98.275343 | BI10: 95.930698
D11: Soft Coal in Blend | E11: % | F11: 23.372863 | G11: 25.353632 | H11: 25.353632 | I11: 25.352267 | J11: 25.353632 | K11: 25.353257 | L11: 25.353632 | M11: 25.352769 | N11: 25.353632 | O11: 25.354448 | P11: 25.353632 | Q11: 25.353316 | R11: 25.353632 | S11: 25.916143 | T11: 25.353632 | U11: 25.496568 | V11: 25.353632 | W11: 26 | X11: 25.353632 | Y11: 25.599196 | Z11: 25.353632 | AA11: 25.355801 | AB11: 25.353632 | AC11: 25.761695 | AD11: 25.353632 | AE11: 25.559173 | AF11: 25.353632 | AG11: 25.353724 | AH11: 25.353632 | AI11: 25.52954 | AJ11: 25.353632 | AK11: 24.741917 | AL11: 25.353632 | AM11: 25.436386 | AN11: 25.353632 | AO11: 25.351664 | AP11: 25.353632 | AQ11: 25.159092 | AR11: 25.353632 | AS11: 25.426794 | AT11: 25.353632 | AU11: 22.433433 | AV11: 25.353632 | AW11: 25.122348 | AX11: 25.353632 | AY11: 21.847329 | AZ11: 25.353632 | BA11: 24.847246 | BB11: 25.353632 | BC11: 24.694018 | BD11: 25.350686 | BE11: 23.030989 | BF11: 25.350686 | BG11: 24.09864 | BH11: 25.353633 | BI11: 24.834175
D12: Average Coking Time | E12: Hrs | G12: 18.469687 | H12: 0 | I12: 0 | J12: 0 | K12: 0 | L12: 0 | M12: 0 | N12: 0 | O12: 0 | P12: 0 | Q12: 0 | R12: 0 | S12: 0 | T12: 0 | U12: 0 | V12: 0 | W12: 0 | X12: 0 | Y12: 0 | Z12: 0 | AA12: 0 | AB12: 0 | AC12: 0 | AD12: 0 | AE12: 0 | AF12: 0 | AG12: 0 | AH12: 0 | AI12: 0 | AJ12: 0 | AK12: 0 | AL12: 0 | AM12: 0 | AN12: 0 | AO12: 0 | AP12: 0 | AQ12: 0 | AR12: 0 | AS12: 0 | AT12: 0 | AU12: 0 | AV12: 0 | AW12: 0 | AX12: 0 | AY12: 0 | AZ12: 0 | BA12: 0 | BB12: 0 | BC12: 0 | BD12: 0 | BE12: 0 | BF12: 0 | BG12: 0 | BH12: 0 | BI12: 0
D14: COB#10
D15: Soft Coal in Blend | E15: % | F15: 23.078854 | G15: 26 | H15: 26 | I15: 26 | J15: 26 | K15: 26 | L15: 26 | M15: 26 | N15: 26 | O15: 25.999986 | P15: 26 | Q15: 25.999995 | R15: 26 | S15: 26.000042 | T15: 26 | U15: 26.000007 | V15: 26 | W15: 26.000007 | X15: 26 | Y15: 26.000007 | Z15: 26 | AA15: 26.000035 | AB15: 26 | AC15: 26.000028 | AD15: 26 | AE15: 26.000012 | AF15: 26 | AG15: 25.999305 | AH15: 26 | AI15: 25.99991 | AJ15: 26 | AK15: 24.269985 | AL15: 26 | AM15: 25.795282 | AN15: 26 | AO15: 25.999944 | AP15: 26 | AQ15: 25.450538 | AR15: 26 | AS15: 25.818349 | AT15: 26 | AU15: 21.032181 | AV15: 26 | AW15: 25.333546 | AX15: 26 | AY15: 22.357143 | AZ15: 26 | BA15: 25.08481 | BB15: 26 | BC15: 24.129024 | BD15: 26.014421 | BE15: 22.511239 | BF15: 26.014421 | BG15: 23.989218 | BH15: 26.014422 | BI15: 25.003623
D16: Average Coking Time | E16: Hrs | G16: 18.979186 | H16: 18.895706 | I16: 18.766667 | J16: 18.895706 | K16: 18.733333 | L16: 18.895706 | M16: 18.749732 | N16: 18.962274 | O16: 19.116667 | P16: 18.917599 | Q16: 18.869596 | R16: 19 | S16: 18.966667 | T16: 18.938266 | U16: 18.894127 | V16: 19 | W16: 18.883333 | X16: 18.950645 | Y16: 18.891942 | Z16: 19 | AA16: 18.883333 | AB16: 19 | AC16: 18.911333 | AD16: 18.958666 | AE16: 18.890532 | AF16: 19 | AG16: 18.933333 | AH16: 18.964609 | AI16: 18.896728 | AJ16: 19 | AK16: 19.666667 | AL16: 18.968932 | AM16: 18.98819 | AN16: 19 | AO16: 19 | AP16: 19 | AQ16: 19.189047 | AR16: 18.972414 | AS16: 18.989526 | AT16: 19 | AU16: 18.933333 | AV16: 18.975194 | AW16: 18.983815 | AX16: 19 | AY16: 19.033333 | AZ16: 18.977264 | BA16: 18.987966 | BB16: 19 | BC16: 18.966667 | BD16: 19 | BE16: 18.975867 | BF16: 19 | BG16: 19.083023 | BH16: 18.979186 | BI16: 18.986151
D17: M40 | E17: % | F17: 84.340172 | G17: 85.5-86 | H17: 85.5-86 | I17: 86.524944 | J17: 85.5-86 | K17: 86.642299 | L17: 85.5-86 | M17: 86.584566 | N17: 85.5-86 | O17: 86.746395 | P17: 85.5-86 | Q17: 86.637425 | R17: 85.5-86 | S17: 86.803258 | T17: 85.5-86 | U17: 86.679551 | V17: 85.5-86 | W17: 87.09 | X17: 85.5-86 | Y17: 86.762976 | Z17: 85.5-86 | AA17: 86.85 | AB17: 85.5-86 | AC17: 86.915279 | AD17: 85.5-86 | AE17: 86.77728 | AF17: 85.5-86 | AG17: 86.86 | AH17: 85.5-86 | AI17: 86.78929 | AJ17: 85.5-86 | AK17: 86.55 | AL17: 85.5-86 | AM17: 86.760795 | AN17: 85.5-86 | AO17: 86.5 | AP17: 85.5-86 | AQ17: 86.639035 | AR17: 85.5-86 | AS17: 86.731405 | AT17: 85.5-86 | AU17: 86.4 | AV17: 85.5-86 | AW17: 86.697588 | AX17: 85.5-86 | AY17: 86.45 | AZ17: 85.5-86 | BA17: 86.676783 | BB17: 85.5-86 | BC17: 86.43 | BD17: 85.5-86 | BE17: 86.425852 | BF17: 85.5-86 | BG17: 86.532856 | BH17: 85.5-86 | BI17: 86.655714
D18: M10 | E18: % | F18: 7.9983422 | G18: 7.5-7.6 | H18: 7.5-7.6 | I18: 7.5889888 | J18: 7.5-7.6 | K18: 7.4908046 | L18: 7.5-7.6 | M18: 7.5391061 | N18: 7.5-7.6 | O18: 7.4724419 | P18: 7.5-7.6 | Q18: 7.5173314 | R18: 7.5-7.6 | S18: 7.6134831 | T18: 7.5-7.6 | U18: 7.5417564 | V18: 7.5-7.6 | W18: 7.6 | X18: 7.5-7.6 | Y18: 7.5535946 | Z18: 7.5-7.6 | AA18: 7.73 | AB18: 7.5-7.6 | AC18: 7.6469823 | AD18: 7.5-7.6 | AE18: 7.5825898 | AF18: 7.5-7.6 | AG18: 7.73 | AH18: 7.5-7.6 | AI18: 7.6039919 | AJ18: 7.5-7.6 | AK18: 7.85 | AL18: 7.5-7.6 | AM18: 7.6332869 | AN18: 7.5-7.6 | AO18: 7.73 | AP18: 7.5-7.6 | AQ18: 7.7682092 | AR18: 7.5-7.6 | AS18: 7.644186 | AT18: 7.5-7.6 | AU18: 7.73 | AV18: 7.5-7.6 | AW18: 7.6529426 | AX18: 7.5-7.6 | AY18: 7.76 | AZ18: 7.5-7.6 | BA18: 7.6619387 | BB18: 7.5-7.6 | BC18: 7.81 | BD18: 7.5-7.6 | BE18: 7.7668788 | BF18: 7.5-7.6 | BG18: 7.7675466 | BH18: 7.5-7.6 | BI18: 7.674579
D19: CSR | E19: % | F19: 64.448248 | G19: 65.3-65.6 | H19: 65.3-65.6 | I19: 64.962 | J19: 65.3-65.6 | K19: 65.291818 | L19: 65.3-65.6 | M19: 65.129565 | N19: 65.3-65.6 | O19: 65.455455 | P19: 65.3-65.6 | Q19: 65.236011 | R19: 65.3-65.6 | S19: 65.26 | T19: 65.3-65.6 | U19: 65.242105 | V19: 65.3-65.6 | W19: 65.17 | X19: 65.3-65.6 | Y19: 65.227449 | Z19: 65.3-65.6 | AA19: 64.73 | AB19: 65.3-65.6 | AC19: 65.056558 | AD19: 65.3-65.6 | AE19: 65.145685 | AF19: 65.3-65.6 | AG19: 64.73 | AH19: 65.3-65.6 | AI19: 65.085333 | AJ19: 65.3-65.6 | AK19: 64.39 | AL19: 65.3-65.6 | AM19: 65.002532 | AN19: 65.3-65.6 | AO19: 64.7 | AP19: 65.3-65.6 | AQ19: 64.611552 | AR19: 65.3-65.6 | AS19: 64.968438 | AT19: 65.3-65.6 | AU19: 64.65 | AV19: 65.3-65.6 | AW19: 64.935944 | AX19: 65.3-65.6 | AY19: 65 | AZ19: 65.3-65.6 | BA19: 64.941327 | BB19: 65.3-65.6 | BC19: 64.98 | BD19: 65.3-65.6 | BE19: 64.872322 | BF19: 65.3-65.6 | BG19: 64.741433 | BH19: 65.3-65.6 | BI19: 64.944628
D20: CRI | E20: % | F20: 22.958248 | G20: 22.5-23 | H20: 22.5-23 | I20: 23.334 | J20: 22.5-23 | K20: 22.924545 | L20: 22.5-23 | M20: 23.125976 | N20: 22.5-23 | O20: 22.873636 | P20: 22.5-23 | Q20: 23.043554 | R20: 22.5-23 | S20: 23.161667 | T20: 22.5-23 | U20: 23.073557 | V20: 22.5-23 | W20: 23.13 | X20: 22.5-23 | Y20: 23.08503 | Z20: 22.5-23 | AA20: 23.56 | AB20: 22.5-23 | AC20: 23.281058 | AD20: 22.5-23 | AE20: 23.163099 | AF20: 22.5-23 | AG20: 23.4 | AH20: 22.5-23 | AI20: 23.197494 | AJ20: 22.5-23 | AK20: 23.59 | AL20: 22.5-23 | AM20: 23.244234 | AN20: 22.5-23 | AO20: 23.35 | AP20: 22.5-23 | AQ20: 23.443518 | AR20: 22.5-23 | AS20: 23.256153 | AT20: 22.5-23 | AU20: 23.62 | AV20: 22.5-23 | AW20: 23.293281 | AX20: 22.5-23 | AY20: 23.38 | AZ20: 22.5-23 | BA20: 23.300568 | BB20: 22.5-23 | BC20: 23.48 | BD20: 22.5-23 | BE20: 23.497288 | BF20: 22.5-23 | BG20: 23.470299 | BH20: 22.5-23 | BI20: 23.315886
D21: COB#11
D22: Soft Coal in Blend | E22: % | F22: 23.543644 | G22: 25 | H22: 25 | I22: 24.999998 | J22: 25 | K22: 25.000002 | L22: 25 | M22: 25 | N22: 25 | O22: 24.999995 | P22: 25 | Q22: 24.999998 | R22: 25 | S22: 25.870974 | T22: 25 | U22: 25.222537 | V22: 25 | W22: 25.999997 | X22: 25 | Y22: 25.380551 | Z22: 25 | AA22: 25 | AB22: 25 | AC22: 25.631358 | AD22: 25 | AE22: 25.318204 | AF22: 25 | AG22: 25.000238 | AH22: 25 | AI22: 25.272365 | AJ22: 25 | AK22: 25.000005 | AL22: 25 | AM22: 25.240155 | AN22: 25 | AO22: 25 | AP22: 25 | AQ22: 25.000083 | AR22: 25 | AS22: 25.212897 | AT22: 25 | AU22: 23.193551 | AV22: 25 | AW22: 25.007059 | AX22: 25 | AY22: 21.571429 | AZ22: 25 | BA22: 24.717658 | BB22: 25 | BC22: 25.000002 | BD22: 25 | BE22: 23.312565 | BF22: 25 | BG22: 24.15813 | BH22: 25 | BI22: 24.741799
D23: Average Coking Time | E23: Hrs | G23: 17.969256 | H23: 18 | I23: 17.55 | J23: 18 | K23: 17.666667 | L23: 18 | M23: 17.609273 | N23: 18.373724 | O23: 18 | P23: 18.122915 | Q23: 17.736909 | R23: 18.753086 | S23: 17.6 | T23: 18.280969 | U23: 17.70231 | V23: 17.818182 | W23: 17.616667 | X23: 18.188172 | Y23: 17.684974 | Z23: 17.818182 | AA23: 17.65 | AB23: 18.133204 | AC23: 17.621952 | AD23: 18.128043 | AE23: 17.679245 | AF23: 17.818182 | AG23: 17.75 | AH23: 18.08349 | AI23: 17.689487 | AJ23: 17.818182 | AK23: 18.533333 | AL23: 18.051082 | AM23: 17.789728 | AN23: 17.818182 | AO23: 17.716667 | AP23: 17.818182 | AQ23: 17.987483 | AR23: 18.02498 | AS23: 17.781463 | AT23: 17.818182 | AU23: 17.683333 | AV23: 18.004138 | AW23: 17.771489 | AX23: 17.818182 | AY23: 17.65 | AZ23: 17.988624 | BA23: 17.761305 | BB23: 17.818182 | BC23: 17.683333 | BD23: 17.818182 | BE23: 17.672986 | BF23: 17.818182 | BG23: 17.831069 | BH23: 17.974211 | BI23: 17.754663
D24: M40 | E24: % | F24: 88.59975 | G24: 89.8-90.2 | H24: 89.8-90.2 | I24: 89.947288 | J24: 89.8-90.2 | K24: 90.3055 | L24: 89.8-90.2 | M24: 90.128892 | N24: 89.8-90.2 | O24: 90.414923 | P24: 89.8-90.2 | Q24: 90.221855 | R24: 89.8-90.2 | S24: 90.199344 | T24: 89.8-90.2 | U24: 90.216074 | V24: 89.8-90.2 | W24: 90.37 | X24: 89.8-90.2 | Y24: 90.247486 | Z24: 89.8-90.2 | AA24: 89.73 | AB24: 89.8-90.2 | AC24: 90.104282 | AD24: 89.8-90.2 | AE24: 90.162392 | AF24: 89.8-90.2 | AG24: 89.73 | AH24: 89.8-90.2 | AI24: 90.099879 | AJ24: 89.8-90.2 | AK24: 89.42 | AL24: 89.8-90.2 | AM24: 90.019281 | AN24: 89.8-90.2 | AO24: 89.7 | AP24: 89.8-90.2 | AQ24: 89.621355 | AR24: 89.8-90.2 | AS24: 89.983184 | AT24: 89.8-90.2 | AU24: 89.69 | AV24: 89.8-90.2 | AW24: 89.953181 | AX24: 89.8-90.2 | AY24: 89.77 | AZ24: 89.8-90.2 | BA24: 89.937714 | BB24: 89.8-90.2 | BC24: 89.71 | BD24: 89.8-90.2 | BE24: 89.721743 | BF24: 89.8-90.2 | BG24: 89.671514 | BH24: 89.8-90.2 | BI24: 89.918201
D25: M10 | E25: % | F25: 5.9480711 | G25: 5.5-5.7 | H25: 5.5-5.7 | I25: 5.6581356 | J25: 5.5-5.7 | K25: 5.4698333 | L25: 5.5-5.7 | M25: 5.5626716 | N25: 5.5-5.7 | O25: 5.4764615 | P25: 5.5-5.7 | Q25: 5.5346524 | R25: 5.5-5.7 | S25: 5.5011475 | T25: 5.5-5.7 | U25: 5.5260475 | V25: 5.5-5.7 | W25: 5.43 | X25: 5.5-5.7 | Y25: 5.506447 | Z25: 5.5-5.7 | AA25: 5.7 | AB25: 5.5-5.7 | AC25: 5.5418136 | AD25: 5.5-5.7 | AE25: 5.5382742 | AF25: 5.5-5.7 | AG25: 5.72 | AH25: 5.5-5.7 | AI25: 5.5645472 | AJ25: 5.5-5.7 | AK25: 5.82 | AL25: 5.5-5.7 | AM25: 5.5948304 | AN25: 5.5-5.7 | AO25: 5.69 | AP25: 5.5-5.7 | AQ25: 5.741504 | AR25: 5.5-5.7 | AS25: 5.60559 | AT25: 5.5-5.7 | AU25: 5.65 | AV25: 5.5-5.7 | AW25: 5.6101347 | AX25: 5.5-5.7 | AY25: 5.6 | AZ25: 5.5-5.7 | BA25: 5.609279 | BB25: 5.5-5.7 | BC25: 5.64 | BD25: 5.5-5.7 | BE25: 5.6310228 | BF25: 5.5-5.7 | BG25: 5.6863016 | BH25: 5.5-5.7 | BI25: 5.6119115
D26: CSR | E26: % | F26: 66.654887 | G26: 67.5-68 | H26: 67.5-68 | I26: 67.798333 | J26: 67.5-68 | K26: 68.434167 | L26: 67.5-68 | M26: 68.120683 | N26: 67.5-68 | O26: 68.341 | P26: 67.5-68 | Q26: 68.192288 | R26: 67.5-68 | S26: 68.219091 | T26: 67.5-68 | U26: 68.199172 | V26: 67.5-68 | W26: 68.42 | X26: 67.5-68 | Y26: 68.244237 | Z26: 67.5-68 | AA26: 67.64 | AB26: 67.5-68 | AC26: 68.098546 | AD26: 67.5-68 | AE26: 68.144878 | AF26: 67.5-68 | AG26: 67.5 | AH26: 67.5-68 | AI26: 68.051645 | AJ26: 67.5-68 | AK26: 66.99 | AL26: 67.5-68 | AM26: 67.92579 | AN26: 67.5-68 | AO26: 67.74 | AP26: 67.5-68 | AQ26: 67.420025 | AR26: 67.5-68 | AS26: 67.904785 | AT26: 67.5-68 | AU26: 67.82 | AV26: 67.5-68 | AW26: 67.896108 | AX26: 67.5-68 | AY26: 67.97 | AZ26: 67.5-68 | BA26: 67.902347 | BB26: 67.5-68 | BC26: 67.73 | BD26: 67.5-68 | BE26: 67.835561 | BF26: 67.5-68 | BG26: 67.627649 | BH26: 67.5-68 | BI26: 67.887579
D27: CRI | E27: % | F27: 20.55944 | G27: 19.9-20.2 | H27: 19.9-20.2 | I27: 20.695833 | J27: 19.9-20.2 | K27: 20.496667 | L27: 19.9-20.2 | M27: 20.594861 | N27: 19.9-20.2 | O27: 20.453 | P27: 19.9-20.2 | Q27: 20.548755 | R27: 19.9-20.2 | S27: 20.570909 | T27: 19.9-20.2 | U27: 20.554445 | V27: 19.9-20.2 | W27: 20.53 | X27: 19.9-20.2 | Y27: 20.549456 | Z27: 19.9-20.2 | AA27: 21.17 | AB27: 19.9-20.2 | AC27: 20.751901 | AD27: 19.9-20.2 | AE27: 20.651496 | AF27: 19.9-20.2 | AG27: 21.54 | AH27: 19.9-20.2 | AI27: 20.779952 | AJ27: 19.9-20.2 | AK27: 21.62 | AL27: 19.9-20.2 | AM27: 20.879537 | AN27: 19.9-20.2 | AO27: 20.92 | AP27: 19.9-20.2 | AQ27: 21.353774 | AR27: 19.9-20.2 | AS27: 20.884112 | AT27: 19.9-20.2 | AU27: 20.71 | AV27: 19.9-20.2 | AW27: 20.866294 | AX27: 19.9-20.2 | AY27: 20.6 | AZ27: 19.9-20.2 | BA27: 20.843809 | BB27: 19.9-20.2 | BC27: 21.57 | BD27: 19.9-20.2 | BE27: 20.972322 | BF27: 19.9-20.2 | BG27: 21.16318 | BH27: 19.9-20.2 | BI27: 20.906037
C28: SINTER PLANT | D28: Sp. Productivity | E28: T/M²/Utlz Hr | F28: 1.330623 | G28: 1.3752523 | H28: 1.3957948 | I28: 1.3082051 | J28: 1.4041543 | K28: 1.2969298 | L28: 1.3957948 | M28: 1.3027042 | N28: 1.2868234 | O28: 1.2363344 | P28: 1.3679716 | Q28: 1.2841496 | R28: 1.1302954 | S28: 1.3504117 | T28: 1.329346 | U28: 1.3025971 | V28: 1.3797761 | W28: 1.341307 | X28: 1.3410192 | Y28: 1.3106424 | Z28: 1.3663036 | AA28: 1.3674157 | AB28: 1.3208733 | AC28: 1.3529339 | AD28: 1.3456433 | AE28: 1.3203115 | AF28: 1.4012354 | AG28: 1.3708526 | AH28: 1.3545924 | AI28: 1.3276919 | AJ28: 1.4040708 | AK28: 1.0403666 | AL28: 1.3612846 | AM28: 1.3241179 | AN28: 1.4012354 | AO28: 1.2510718 | AP28: 1.4021625 | AQ28: 1.2983544 | AR28: 1.3661664 | AS28: 1.3144112 | AT28: 1.4012354 | AU28: 1.3570211 | AV28: 1.369985 | AW28: 1.319149 | AX28: 1.3999166 | AY28: 1.3225856 | AZ28: 1.3726776 | BA28: 1.3194779 | BB28: 1.4012354 | BC28: 1.4164214 | BD28: 1.4008237 | BE28: 1.367109 | BF28: 1.4015004 | BG28: 1.3385074 | BH28: 1.3752523 | BI28: 1.3288458
D29: Iron Ore Fines | E29: Kg/T | F29: 783.62842 | G29: 779.40145 | H29: 779.40145 | I29: 778.31272 | J29: 779.40145 | K29: 779 | L29: 779.40145 | M29: 778.64654 | N29: 779.40145 | O29: 787.95491 | P29: 779.40145 | Q29: 781.15193 | R29: 779.40145 | S29: 786.95936 | T29: 779.40145 | U29: 782.82808 | V29: 779.40145 | W29: 785.89854 | X29: 779.40145 | Y29: 783.48116 | Z29: 779.40145 | AA29: 784.99947 | AB29: 779.40145 | AC29: 785.9727 | AD29: 779.40145 | AE29: 783.74897 | AF29: 779.40145 | AG29: 786.35241 | AH29: 779.40145 | AI29: 784.1415 | AJ29: 779.40145 | AK29: 786.00402 | AL29: 779.40145 | AM29: 784.15971 | AN29: 779.40145 | AO29: 785 | AP29: 779.40145 | AQ29: 785.69677 | AR29: 779.40145 | AS29: 784.26599 | AT29: 779.40145 | AU29: 787.86188 | AV29: 779.40145 | AW29: 784.6773 | AX29: 779.40145 | AY29: 789.55267 | AZ29: 779.40145 | BA29: 785.14494 | BB29: 779.40145 | BC29: 786.3714 | BD29: 779.40145 | BE29: 787.83332 | BF29: 779.40145 | BG29: 786.97119 | BH29: 779.40145 | BI29: 785.27127
D30: Limestone | E30: Kg/T | F30: 102.61678 | G30: 84.940005 | H30: 84.940005 | I30: 70.198181 | J30: 84.940005 | K30: 68.347687 | L30: 84.940005 | M30: 69.299378 | N30: 84.940005 | O30: 58.507231 | P30: 84.940005 | Q30: 66.394623 | R30: 84.940005 | S30: 62.758089 | T30: 84.940005 | U30: 65.345041 | V30: 84.940005 | W30: 61.137674 | X30: 84.940005 | Y30: 64.450147 | Z30: 84.940005 | AA30: 63.351214 | AB30: 84.940005 | AC30: 62.425366 | AD30: 84.940005 | AE30: 64.256309 | AF30: 84.940005 | AG30: 68.047536 | AH30: 84.940005 | AI30: 64.827932 | AJ30: 84.940005 | AK30: 72.274348 | AL30: 84.940005 | AM30: 64.900707 | AN30: 84.940005 | AO30: 82.969215 | AP30: 84.940005 | AQ30: 75.293727 | AR30: 84.940005 | AS30: 67.186042 | AT30: 84.940005 | AU30: 78.20176 | AV30: 84.940005 | AW30: 68.44605 | AX30: 84.940005 | AY30: 56.706735 | AZ30: 84.940005 | BA30: 67.320022 | BB30: 84.940005 | BC30: 69.886835 | BD30: 84.940005 | BE30: 68.599685 | BF30: 84.940005 | BG30: 71.300841 | BH30: 84.940005 | BI30: 67.584408
D31: Dolomite | E31: Kg/T | F31: 101.93133 | G31: 89.796142 | H31: 89.796142 | I31: 104.23441 | J31: 89.796142 | K31: 92.248208 | L31: 89.796142 | M31: 98.412598 | N31: 89.796142 | O31: 97.949275 | P31: 89.796142 | Q31: 98.287893 | R31: 89.796142 | S31: 93.088875 | T31: 89.796142 | U31: 96.787344 | V31: 89.796142 | W31: 96.311136 | X31: 89.796142 | Y31: 96.686056 | Z31: 89.796142 | AA31: 95.962227 | AB31: 89.796142 | AC31: 95.077478 | AD31: 89.796142 | AE31: 96.558382 | AF31: 89.796142 | AG31: 101.97475 | AH31: 89.796142 | AI31: 97.375036 | AJ31: 89.796142 | AK31: 98.947023 | AL31: 89.796142 | AM31: 97.390399 | AN31: 89.796142 | AO31: 101.49777 | AP31: 89.796142 | AQ31: 101.65009 | AR31: 89.796142 | AS31: 97.909906 | AT31: 89.796142 | AU31: 99.591063 | AV31: 89.796142 | AW31: 98.102202 | AX31: 89.796142 | AY31: 94.04407 | AZ31: 89.796142 | BA31: 97.712948 | BB31: 89.796142 | BC31: 98.392761 | BD31: 89.796142 | BE31: 97.459459 | BF31: 89.796142 | BG31: 99.150447 | BH31: 89.796142 | BI31: 97.78297
D32: Coke Breeze | E32: Kg/T | F32: 74.095728 | G32: 67.816371 | H32: 67.816371 | I32: 77.325109 | J32: 67.816371 | K32: 69.085787 | L32: 67.816371 | M32: 73.323192 | N32: 67.816371 | O32: 63.209288 | P32: 67.816371 | Q32: 70.600988 | R32: 67.816371 | S32: 68.111329 | T32: 67.816371 | U32: 69.882419 | V32: 67.816371 | W32: 69.441764 | X32: 67.816371 | Y32: 69.788693 | Z32: 67.816371 | AA32: 63.405205 | AB32: 67.816371 | AC32: 67.003079 | AD32: 67.816371 | AE32: 68.662727 | AF32: 67.816371 | AG32: 62.573587 | AH32: 67.816371 | AI32: 67.744636 | AJ32: 67.816371 | AK32: 73.913222 | AL32: 67.816371 | AM32: 67.804923 | AN32: 67.816371 | AO32: 63.699517 | AP32: 67.816371 | AQ32: 63.474807 | AR32: 67.816371 | AS32: 67.285664 | AT32: 67.816371 | AU32: 65.042654 | AV32: 67.816371 | AW32: 67.029102 | AX32: 67.816371 | AY32: 65.787053 | AZ32: 67.816371 | BA32: 66.909966 | BB32: 67.816371 | BC32: 62.794498 | BD32: 67.816371 | BE32: 64.448206 | BF32: 67.816371 | BG32: 64.055424 | BH32: 67.816371 | BI32: 66.486066
D33: Mill Scale | E33: Kg/T | F33: 6.4308813 | G33: 7.3 | H33: 7.3 | I33: 6.0915323 | J33: 7.3 | K33: 3.7 | L33: 7.3 | M33: 4.9299423 | N33: 7.3 | O33: 11.55187 | P33: 7.3 | Q33: 6.7122643 | R33: 7.3 | S33: 12.558742 | T33: 7.3 | U33: 8.3996837 | V33: 7.3 | W33: 9.7365796 | X33: 7.3 | Y33: 8.6840372 | Z33: 7.3 | AA33: 8.6062841 | AB33: 7.3 | AC33: 10.346922 | AD33: 7.3 | AE33: 8.6703225 | AF33: 7.3 | AG33: 7.26552 | AH33: 7.3 | AI33: 8.4585132 | AJ33: 7.3 | AK33: 6.3096653 | AL33: 7.3 | AM33: 8.4375121 | AN33: 7.3 | AO33: 4.7538191 | AP33: 7.3 | AQ33: 6.0379407 | AR33: 7.3 | AS33: 7.9715926 | AT33: 7.3 | AU33: 0.35748138 | AV33: 7.3 | AW33: 7.1006692 | AX33: 7.3 | AY33: 0.014598583 | AZ33: 7.3 | BA33: 6.4209772 | BB33: 7.3 | BC33: 0 | BD33: 7.3 | BE33: 0.12212853 | BF33: 7.3 | BG33: 2.5092562 | BH33: 7.3 | BI33: 5.7596062
D34: SMS Scale | E34: Kg/T | G34: 0 | H34: 0 | I34: 1.7467153 | J34: 0 | K34: 1.9076588 | L34: 0 | M34: 1.8248871 | N34: 0 | O34: 1.9943468 | P34: 0 | Q34: 1.870498 | R34: 0 | S34: 2.2135546 | T34: 0 | U34: 1.9695115 | V34: 0 | W34: 1.6716908 | X34: 0 | Y34: 1.906166 | Z34: 0 | AA34: 0.92055925 | AB34: 0 | AC34: 1.6139995 | AD34: 0 | AE34: 1.7323174 | AF34: 0 | AG34: 3.7252888 | AH34: 0 | AI34: 2.032808 | AJ34: 0 | AK34: 1.10624 | AL34: 0 | AM34: 2.0237525 | AN34: 0 | AO34: 3.9214168 | AP34: 0 | AQ34: 3.7345098 | AR34: 0 | AS34: 2.2637721 | AT34: 0 | AU34: 5.0941097 | AV34: 0 | AW34: 2.5875141 | AX34: 0 | AY34: 0 | AZ34: 0 | BA34: 2.3393212 | BB34: 0 | BC34: 0 | BD34: 0 | BE34: 1.6768158 | BF34: 0 | BG34: 2.5071292 | BH34: 0 | BI34: 2.0983673
D35: BOF Slag | E35: Kg/T | F35: 12.079401 | G35: 21.85867 | H35: 21.85867 | I35: 0 | J35: 21.85867 | K35: 0 | L35: 21.85867 | M35: 0 | N35: 21.85867 | O35: 0 | P35: 21.85867 | Q35: 0 | R35: 21.85867 | S35: 0 | T35: 21.85867 | U35: 0 | V35: 21.85867 | W35: 0 | X35: 21.85867 | Y35: 0 | Z35: 21.85867 | AA35: 2.3324434 | AB35: 21.85867 | AC35: 0.76368872 | AD35: 21.85867 | AE35: 0.41141349 | AF35: 21.85867 | AG35: 0.42643694 | AH35: 21.85867 | AI35: 0.41367865 | AJ35: 21.85867 | AK35: 0 | AL35: 21.85867 | AM35: 0.40963569 | AN35: 21.85867 | AO35: 1.2969989 | AP35: 21.85867 | AQ35: 0.8275484 | AR35: 21.85867 | AS35: 0.52187083 | AT35: 21.85867 | AU35: 3.9918754 | AV35: 21.85867 | AW35: 0.91877969 | AX35: 21.85867 | AY35: 2.6832195 | AZ35: 21.85867 | BA35: 1.0880238 | BB35: 21.85867 | BC35: 0 | BD35: 21.85867 | BE35: 2.1332378 | BF35: 21.85867 | BG35: 1.6063706 | BH35: 21.85867 | BI35: 0.97595557
D36: Sp. Power | E36: KwH/T | F36: 32.711238 | G36: 30.83 | H36: 30.83 | I36: 32.52964 | J36: 30.83 | K36: 32.013037 | L36: 30.83 | M36: 32.278721 | N36: 30.83 | O36: 35.092411 | P36: 30.83 | Q36: 33.036038 | R36: 30.83 | S36: 31.521145 | T36: 30.83 | U36: 32.598807 | V36: 30.83 | W36: 31.723717 | X36: 30.83 | Y36: 32.412678 | Z36: 30.83 | AA36: 30.737967 | AB36: 30.83 | AC36: 31.330589 | AD36: 30.83 | AE36: 32.117281 | AF36: 30.83 | AG36: 30.930429 | AH36: 30.83 | AI36: 31.938333 | AJ36: 30.83 | AK36: 64.478633 | AL36: 30.83 | AM36: 32.256356 | AN36: 30.83 | AO36: 31.6994 | AP36: 30.83 | AQ36: 32.375837 | AR36: 30.83 | AS36: 32.185911 | AT36: 30.83 | AU36: 30.616357 | AV36: 30.83 | AW36: 32.006381 | AX36: 30.83 | AY36: 30.784061 | AZ36: 30.83 | BA36: 31.889137 | BB36: 30.83 | BC36: 29.247476 | BD36: 30.83 | BE36: 30.167218 | BF36: 30.83 | BG36: 31.058432 | BH36: 30.83 | BI36: 31.617041
C37: BLAST FURNACE | D37: BF Coke Rate | E37: Kg/ THM | F37: 400.04041 | G37: 360.04562 | H37: 357 | I37: 392.5025 | J37: 357 | K37: 395.17392 | L37: 357 | M37: 393.75733 | N37: 372 | O37: 407.7272 | P37: 360.50863 | Q37: 397.5733 | R37: 392 | S37: 370.77684 | T37: 363.78622 | U37: 389.80688 | V37: 365.4 | W37: 377.37067 | X37: 364.19348 | Y37: 387.05271 | Z37: 365.4 | AA37: 380.23556 | AB37: 369.00513 | AC37: 376.09629 | AD37: 364.43009 | AE37: 385.81518 | AF37: 362.4 | AG37: 380.55652 | AH37: 364.07592 | AI37: 385.02927 | AJ37: 355.3 | AK37: 624.51898 | AL37: 362.808 | AM37: 386.26362 | AN37: 355.3 | AO37: 366.34425 | AP37: 357.69218 | AQ37: 377.28919 | AR37: 361.83294 | AS37: 383.50418 | AT37: 355.3 | AU37: 348.01919 | AV37: 361.08202 | AW37: 379.11956 | AX37: 355.3 | AY37: 342.24192 | AZ37: 360.53996 | BA37: 375.3732 | BB37: 355.3 | BC37: 339.29314 | BD37: 355.3 | BE37: 343.20204 | BF37: 356.50995 | BG37: 356.72767 | BH37: 360.04562 | BI37: 371.74357
D38: Nut Coke rate | E38: Kg/ THM | F38: 36.610035 | G38: 38.916226 | H38: 39 | I38: 47.860964 | J38: 39 | K38: 46.884775 | L38: 39 | M38: 47.402423 | N38: 39 | O38: 45.394613 | P38: 39 | Q38: 46.853976 | R38: 36 | S38: 50.998254 | T38: 38.687764 | U38: 48.055112 | V38: 39 | W38: 51.019755 | X38: 38.766562 | Y38: 48.711672 | Z38: 39 | AA38: 47.771227 | AB38: 38.593407 | AC38: 49.935351 | AD38: 38.812342 | AE38: 48.540951 | AF38: 39 | AG38: 39.767759 | AH38: 38.84508 | AI38: 47.229801 | AJ38: 39 | AK38: 14.079452 | AL38: 38.867463 | AM38: 47.058941 | AN38: 39 | AO38: 33.196782 | AP38: 39 | AQ38: 35.988654 | AR38: 38.884675 | AS38: 45.138609 | AT38: 39 | AU38: 30.413521 | AV38: 38.897931 | AW38: 43.319139 | AX38: 39 | AY38: 29.174869 | AZ38: 38.9075 | BA38: 41.882234 | BB38: 39 | BC38: 28.136016 | BD38: 39 | BE38: 29.240536 | BF38: 39 | BG38: 31.918159 | BH38: 38.916226 | BI38: 40.499376
D39: CDI rate | E39: Kg/ THM | F39: 122.58808 | G39: 140.90981 | H39: 136 | I39: 119.13023 | J39: 136 | K39: 114.32316 | L39: 136 | M39: 116.87223 | N39: 129 | O39: 118.97807 | P39: 134.36264 | Q39: 117.44745 | R39: 112 | S39: 129.18393 | T39: 132.03516 | U39: 120.84904 | V39: 136 | W39: 130.5057 | X39: 133.03575 | Y39: 122.98764 | Z39: 141 | AA39: 122.30226 | AB39: 134.87179 | AC39: 127.33972 | AD39: 134.59763 | AE39: 122.86322 | AF39: 146 | AG39: 126.07256 | AH39: 136.58688 | AI39: 123.34285 | AJ39: 146 | AK39: 0 | AL39: 137.94687 | AM39: 122.70713 | AN39: 146 | AO39: 138.96212 | AP39: 146 | AQ39: 130.59501 | AR39: 138.99273 | AS39: 124.95895 | AT39: 146 | AU39: 153.6184 | AV39: 139.79816 | AW39: 128.50018 | AX39: 146 | AY39: 156.32761 | AZ39: 140.37958 | BA39: 131.32715 | BB39: 146 | BC39: 158.53603 | BD39: 146 | BE39: 156.16199 | BF39: 146 | BG39: 146.01713 | BH39: 140.90981 | BI39: 134.06434
D40: Total Fuel | E40: Kg/ THM | F40: 559.23852 | G40: 539.87166 | H40: 532 | I40: 559.49369 | J40: 532 | K40: 556.38186 | L40: 532 | M40: 558.03198 | N40: 540 | O40: 572.09989 | P40: 533.87127 | Q40: 561.87473 | R40: 540 | S40: 550.95902 | T40: 534.50914 | U40: 558.71103 | V40: 540.4 | W40: 558.89613 | X40: 535.99579 | Y40: 558.75202 | Z40: 545.4 | AA40: 550.30904 | AB40: 542.47033 | AC40: 553.37135 | AD40: 537.84007 | AE40: 557.21935 | AF40: 547.4 | AG40: 546.39684 | AH40: 539.50789 | AI40: 555.60193 | AJ40: 540.3 | AK40: 638.59844 | AL40: 539.62233 | AM40: 556.0297 | AN40: 540.3 | AO40: 538.50316 | AP40: 542.69218 | AQ40: 543.87286 | AR40: 539.71034 | AS40: 553.60174 | AT40: 540.3 | AU40: 532.05111 | AV40: 539.77811 | AW40: 550.93888 | AX40: 540.3 | AY40: 527.7444 | AZ40: 539.82704 | BA40: 548.58258 | BB40: 540.3 | BC40: 525.96518 | BD40: 540.3 | BE40: 528.60456 | BF40: 541.50995 | BG40: 534.66296 | BH40: 539.87166 | BI40: 546.30729
D41: BF Productivity | E41: T/M³/Day | F41: 2.0862545 | G41: 2.3140113 | H41: 2.3305723 | I41: 2.2165963 | J41: 2.3279827 | K41: 2.0052761 | L41: 2.3292555 | M41: 2.1120484 | N41: 2.2084216 | O41: 1.8780769 | P41: 2.2998216 | Q41: 2.0425408 | R41: 2.1936 | S41: 2.3276758 | T41: 2.288289 | U41: 2.1177276 | V41: 2.2528865 | W41: 2.3360393 | X41: 2.2792501 | Y41: 2.1624836 | Z41: 2.2528865 | AA41: 2.3134741 | AB41: 1.7131976 | AC41: 2.3256987 | AD41: 2.2740314 | AE41: 2.1884115 | AF41: 2.3467568 | AG41: 2.2356327 | AH41: 2.2863926 | AI41: 2.1953415 | AJ41: 2.3499937 | AK41: 0.80694656 | AL41: 2.2953679 | AM41: 2.1760447 | AN41: 2.3467568 | AO41: 2.3560234 | AP41: 2.3478115 | AQ41: 2.2291989 | AR41: 2.3019143 | AS41: 2.1993189 | AT41: 2.3467568 | AU41: 2.4887715 | AV41: 2.3069812 | AW41: 2.2313856 | AX41: 2.3467568 | AY41: 2.4820491 | AZ41: 2.3106528 | BA41: 2.2545159 | BB41: 2.3467568 | BC41: 2.4580868 | BD41: 2.3467568 | BE41: 2.4760163 | BF41: 2.3472901 | BG41: 2.3718147 | BH41: 2.3140113 | BI41: 2.2734567
D42: Sinter in Burden | E42: % | G42: 78 | H42: 78 | I42: 75.783752 | J42: 78 | K42: 79.67372 | L42: 78 | M42: 77.592017 | N42: 78 | O42: 81.082147 | P42: 78 | Q42: 78.522436 | R42: 78 | S42: 76.953707 | T42: 78 | U42: 78.065415 | V42: 78 | W42: 74.861377 | X42: 78 | Y42: 77.359659 | Z42: 78 | AA42: 72.663235 | AB42: 78 | AC42: 74.845528 | AD42: 78 | AE42: 76.509468 | AF42: 78 | AG42: 75.45646 | AH42: 78 | AI42: 76.352117 | AJ42: 78 | AK42: 65.313173 | AL42: 78 | AM42: 76.300081 | AN42: 78 | AO42: 68.301122 | AP42: 78 | AQ42: 71.61962 | AR42: 78 | AS42: 75.179001 | AT42: 78 | AU42: 67.761756 | AV42: 78 | AW42: 74.261521 | AX42: 78 | AY42: 69.7135 | AZ42: 78 | BA42: 73.797979 | BB42: 78 | BC42: 71.926188 | BD42: 78 | BE42: 69.824228 | BF42: 78 | BG42: 70.534182 | BH42: 78 | BI42: 73.605873
D43: Pellet in burden | E43: % | G43: 15 | H43: 15 | I43: 12.883608 | J43: 15 | K43: 1.7407885 | L43: 15 | M43: 7.7038297 | N43: 15 | O43: 6.7183214 | P43: 15 | Q43: 7.4411071 | R43: 15 | S43: 13.65561 | T43: 15 | U43: 9.2515916 | V43: 15 | W43: 14.38873 | X43: 15 | Y43: 10.383153 | Z43: 15 | AA43: 14.085178 | AB43: 15 | AC43: 14.039227 | AD43: 15 | AE43: 11.053329 | AF43: 15 | AG43: 14.345528 | AH43: 15 | AI43: 11.545281 | AJ43: 15 | AK43: 30.952461 | AL43: 15 | AM43: 11.636764 | AN43: 15 | AO43: 19.898646 | AP43: 15 | AQ43: 17.453346 | AR43: 15 | AS43: 12.794693 | AT43: 15 | AU43: 16.716074 | AV43: 15 | AW43: 13.27975 | AX43: 15 | AY43: 13.446591 | AZ43: 15 | BA43: 13.296755 | BB43: 15 | BC43: 8.5266574 | BD43: 15 | BE43: 12.837228 | BF43: 15 | BG43: 14.662584 | BH43: 15 | BI43: 12.807189
D44: Prepared Burden | E44: % | G44: 93 | H44: 93 | I44: 88.66736 | J44: 93 | K44: 81.414508 | L44: 93 | M44: 85.295847 | N44: 93 | O44: 87.800468 | P44: 93 | Q44: 85.963543 | R44: 93 | S44: 90.609317 | T44: 93 | U44: 87.317007 | V44: 93 | W44: 89.250107 | X44: 93 | Y44: 87.742812 | Z44: 93 | AA44: 86.748414 | AB44: 93 | AC44: 88.884755 | AD44: 93 | AE44: 87.562796 | AF44: 93 | AG44: 89.801989 | AH44: 93 | AI44: 87.897399 | AJ44: 93 | AK44: 96.265634 | AL44: 93 | AM44: 87.936845 | AN44: 93 | AO44: 88.199769 | AP44: 93 | AQ44: 89.072966 | AR44: 93 | AS44: 87.973695 | AT44: 93 | AU44: 84.47783 | AV44: 93 | AW44: 87.541272 | AX44: 93 | AY44: 83.160091 | AZ44: 93 | BA44: 87.094734 | BB44: 93 | BC44: 80.452845 | BD44: 93 | BE44: 82.661455 | BF44: 93 | BG44: 85.196766 | BH44: 93 | BI44: 86.413062
D45: Hot Blast Temp | E45: ⁰C | F45: 1139.2637 | G45: 1170 | H45: 1170 | I45: 1153.7333 | J45: 1170 | K45: 1160.9548 | L45: 1170 | M45: 1157.4033 | N45: 1170 | O45: 1134.6538 | P45: 1170 | Q45: 1149.9035 | R45: 1170 | S45: 1171.9745 | T45: 1170 | U45: 1155.5117 | V45: 1170 | W45: 1161 | X45: 1170 | Y45: 1156.6237 | Z45: 1170 | AA45: 1162.436 | AB45: 1170 | AC45: 1165.1662 | AD45: 1170 | AE45: 1157.5765 | AF45: 1170 | AG45: 1146.5461 | AH45: 1170 | AI45: 1155.9787 | AJ45: 1170 | AK45: 1008.6667 | AL45: 1170 | AM45: 1137.8665 | AN45: 1170 | AO45: 1168.2703 | AP45: 1170 | AQ45: 1108.9055 | AR45: 1170 | AS45: 1141.2939 | AT45: 1170 | AU45: 1180.3109 | AV45: 1170 | AW45: 1145.2466 | AX45: 1170 | AY45: 1171.6967 | AZ45: 1170 | BA45: 1147.464 | BB45: 1170 | BC45: 1179.4646 | BD45: 1170 | BE45: 1177.3394 | BF45: 1170 | BG45: 1142.7465 | BH45: 1170 | BI45: 1150.1818
D46: Sinter | E46: Kg/THM | G46: 1311.5705 | H46: 1311.5705 | I46: 1259.2435 | J46: 1311.5705 | K46: 1298.2188 | L46: 1311.5705 | M46: 1277.5512 | N46: 1311.5705 | O46: 1291.2277 | P46: 1311.5705 | Q46: 1281.287 | R46: 1311.5705 | S46: 1264.8722 | T46: 1311.5705 | U46: 1276.5295 | V46: 1311.5705 | W46: 1215.6825 | X46: 1311.5705 | Y46: 1263.0541 | Z46: 1311.5705 | AA46: 1182.3633 | AB46: 1311.5705 | AC46: 1221.2278 | AD46: 1311.5705 | AE46: 1248.4061 | AF46: 1311.5705 | AG46: 1231.0322 | AH46: 1311.5705 | AI46: 1245.8096 | AJ46: 1311.5705 | AK46: 974.23149 | AL46: 1311.5705 | AM46: 1244.4099 | AN46: 1311.5705 | AO46: 1129.1266 | AP46: 1311.5705 | AQ46: 1174.7435 | AR46: 1311.5705 | AS46: 1228.4396 | AT46: 1311.5705 | AU46: 1108.6 | AV46: 1311.5705 | AW46: 1213.6319 | AX46: 1311.5705 | AY46: 1143.4579 | AZ46: 1311.5705 | BA46: 1206.503 | BB46: 1311.5705 | BC46: 1202.3849 | BD46: 1311.5705 | BE46: 1151.8459 | BF46: 1311.5705 | BG46: 1160.9315 | BH46: 1311.5705 | BI46: 1206.0887
D47: Pellet | E47: Kg/THM | G47: 252.2251 | H47: 252.2251 | I47: 214.07755 | J47: 252.2251 | K47: 28.36474 | L47: 252.2251 | M47: 126.84342 | N47: 252.2251 | O47: 106.98882 | P47: 252.2251 | Q47: 121.42 | R47: 252.2251 | S47: 224.45444 | T47: 252.2251 | U47: 151.28248 | V47: 252.2251 | W47: 233.66025 | X47: 252.2251 | Y47: 169.52613 | Z47: 252.2251 | AA47: 229.19153 | AB47: 252.2251 | AC47: 229.07307 | AD47: 252.2251 | AE47: 180.35733 | AF47: 252.2251 | AG47: 234.03971 | AH47: 252.2251 | AI47: 188.38014 | AJ47: 252.2251 | AK47: 461.69648 | AL47: 252.2251 | AM47: 189.78884 | AN47: 252.2251 | AO47: 328.9564 | AP47: 252.2251 | AQ47: 286.27915 | AR47: 252.2251 | AS47: 209.0678 | AT47: 252.2251 | AU47: 273.47931 | AV47: 252.2251 | AW47: 217.02665 | AX47: 252.2251 | AY47: 220.55429 | AZ47: 252.2251 | BA47: 217.38502 | BB47: 252.2251 | BC47: 142.53951 | BD47: 252.2251 | BE47: 211.76758 | BF47: 252.2251 | BG47: 241.33344 | BH47: 252.2251 | BI47: 209.85562
D48: Iron Ore Lump | E48: Kg/THM | G48: 117.70505 | H48: 117.70505 | I48: 188.30624 | J48: 117.70505 | K48: 302.83554 | L48: 117.70505 | M48: 242.10363 | N48: 117.70505 | O48: 194.27673 | P48: 117.70505 | Q48: 229.03938 | R48: 117.70505 | S48: 154.35271 | T48: 117.70505 | U48: 207.39293 | V48: 117.70505 | W48: 174.56876 | X48: 117.70505 | Y48: 200.12358 | Z48: 117.70505 | AA48: 215.62747 | AB48: 117.70505 | AC48: 181.36349 | AD48: 117.70505 | AE48: 202.93804 | AF48: 117.70505 | AG48: 166.37516 | AH48: 117.70505 | AI48: 197.47373 | AJ48: 117.70505 | AK48: 55.702953 | AL48: 117.70505 | AM48: 196.74303 | AN48: 117.70505 | AO48: 195.07667 | AP48: 117.70505 | AQ48: 179.23108 | AR48: 117.70505 | AS48: 196.51219 | AT48: 117.70505 | AU48: 253.94674 | AV48: 117.70505 | AW48: 203.60895 | AX48: 117.70505 | AY48: 276.21232 | AZ48: 117.70505 | BA48: 210.98467 | BB48: 117.70505 | BC48: 326.76837 | BD48: 117.70505 | BE48: 286.02294 | BF48: 117.70505 | BG48: 243.64841 | BH48: 117.70505 | BI48: 222.63241
D49: Burden | E49: Kg/THM | G49: 1681.5007 | H49: 1681.5007 | I49: 1661.6273 | J49: 1681.5007 | K49: 1629.4191 | L49: 1681.5007 | M49: 1646.4982 | N49: 1681.5007 | O49: 1592.4933 | P49: 1681.5007 | Q49: 1631.7464 | R49: 1681.5007 | S49: 1643.6793 | T49: 1681.5007 | U49: 1635.2049 | V49: 1681.5007 | W49: 1623.9115 | X49: 1681.5007 | Y49: 1632.7039 | Z49: 1681.5007 | AA49: 1627.1823 | AB49: 1681.5007 | AC49: 1631.6644 | AD49: 1681.5007 | AE49: 1631.7015 | AF49: 1681.5007 | AG49: 1631.4471 | AH49: 1681.5007 | AI49: 1631.6635 | AJ49: 1681.5007 | AK49: 1491.6309 | AL49: 1681.5007 | AM49: 1630.9418 | AN49: 1681.5007 | AO49: 1653.1597 | AP49: 1681.5007 | AQ49: 1640.2537 | AR49: 1681.5007 | AS49: 1634.0196 | AT49: 1681.5007 | AU49: 1636.026 | AV49: 1681.5007 | AW49: 1634.2675 | AX49: 1681.5007 | AY49: 1640.2245 | AZ49: 1681.5007 | BA49: 1634.8727 | BB49: 1681.5007 | BC49: 1671.6928 | BD49: 1681.5007 | BE49: 1649.6364 | BF49: 1681.5007 | BG49: 1645.9134 | BH49: 1681.5007 | BI49: 1638.5768
D50: Avg Si | E50: % | F50: 0.72420555 | G50: 0.57103774 | H50: 0.55 | I50: 0.70427994 | J50: 0.55 | K50: 0.6728903 | L50: 0.55 | M50: 0.68953541 | N50: 0.8 | O50: 0.82446182 | P50: 0.60847724 | Q50: 0.72639149 | R50: 0.8 | S50: 0.56939299 | T50: 0.62841069 | U50: 0.6808886 | V50: 0.55 | W50: 0.6815576 | X50: 0.6086225 | Y50: 0.68103676 | Z50: 0.55 | AA50: 0.57478962 | AB50: 0.58388278 | AC50: 0.60831841 | AD50: 0.59712595 | AE50: 0.66174947 | AF50: 0.55 | AG50: 0.69457018 | AH50: 0.5889044 | AI50: 0.66665451 | AJ50: 0.55 | AK50: 1.1329131 | AL50: 0.58328358 | AM50: 0.66905764 | AN50: 0.55 | AO50: 0.71038423 | AP50: 0.55 | AQ50: 0.70983288 | AR50: 0.57896104 | AS50: 0.67478264 | AT50: 0.55 | AU50: 0.61304458 | AV50: 0.57563218 | AW50: 0.66715413 | AX50: 0.55 | AY50: 0.65020291 | AZ50: 0.57322917 | BA50: 0.66543207 | BB50: 0.55 | BC50: 0.62914753 | BD50: 0.55 | BE50: 0.63023062 | BF50: 0.55 | BG50: 0.66181645 | BH50: 0.57103774 | BI50: 0.66178187
D51: Avg S | E51: % | F51: 0.038244802 | G51: 0.05 | H51: 0.05 | I51: 0.043837478 | J51: 0.05 | K51: 0.042424641 | L51: 0.05 | M51: 0.043173832 | N51: 0.05 | O51: 0.039794953 | P51: 0.05 | Q51: 0.042250868 | R51: 0.05 | S51: 0.040190247 | T51: 0.05 | U51: 0.041653638 | V51: 0.05 | W51: 0.039597716 | X51: 0.05 | Y51: 0.041198327 | Z51: 0.05 | AA51: 0.040452516 | AB51: 0.05 | AC51: 0.040081033 | AD51: 0.05 | AE51: 0.041062938 | AF51: 0.05 | AG51: 0.039479461 | AH51: 0.05 | AI51: 0.040826288 | AJ51: 0.05 | AK51: 0.061084638 | AL51: 0.05 | AM51: 0.040930701 | AN51: 0.05 | AO51: 0.04255282 | AP51: 0.05 | AQ51: 0.041404111 | AR51: 0.05 | AS51: 0.041155414 | AT51: 0.05 | AU51: 0.039421993 | AV51: 0.05 | AW51: 0.040941228 | AX51: 0.05 | AY51: 0.040352792 | AZ51: 0.05 | BA51: 0.040881449 | BB51: 0.05 | BC51: 0.038488351 | BD51: 0.05 | BE51: 0.039391572 | BF51: 0.05 | BG51: 0.040190139 | BH51: 0.05 | BI51: 0.040640706
D52: Slag Rate | E52: Kg/THM | F52: 413.76313 | G52: 380 | H52: 380 | I52: 425.42494 | J52: 380 | K52: 422.86102 | L52: 380 | M52: 424.2206 | N52: 380 | O52: 431.8169 | P52: 380 | Q52: 426.29558 | R52: 380 | S52: 391.22823 | T52: 380 | U52: 416.13201 | V52: 380 | W52: 394.64164 | X52: 380 | Y52: 411.37268 | Z52: 380 | AA52: 374.19126 | AB52: 380 | AC52: 386.70922 | AD52: 380 | AE52: 404.62305 | AF52: 380 | AG52: 375.79212 | AH52: 380 | AI52: 400.31428 | AJ52: 380 | AK52: 425.17589 | AL52: 380 | AM52: 400.44242 | AN52: 380 | AO52: 389.56683 | AP52: 380 | AQ52: 383.64108 | AR52: 380 | AS52: 398.93582 | AT52: 380 | AU52: 405.53336 | AV52: 380 | AW52: 399.75103 | AX52: 380 | AY52: 363.15162 | AZ52: 380 | BA52: 396.03292 | BB52: 380 | BC52: 388.34272 | BD52: 380 | BE52: 386.33683 | BF52: 380 | BG52: 385.26717 | BH52: 380 | BI52: 395.25929
D53: Gross Coal to Hot Metal Ratio | E53: Kg/ THM | F53: 930.86111 | G53: 879.87856 | H53: 861.75448 | I53: 907.68211 | J53: 861.75448 | K53: 923.49485 | L53: 861.75043 | M53: 915.10977 | N53: 918.52304 | O53: 966.95283 | P53: 875.02915 | Q53: 929.27106 | R53: 1076.904 | S53: 883.14642 | T53: 896.04003 | U53: 915.90275 | V53: 876.78259 | W53: 908.5086 | X53: 891.18011 | Y53: 914.26522 | Z53: 882.41813 | AA53: 913.73269 | AB53: 906.29583 | AC53: 901.68529 | AD53: 889.45992 | AE53: 914.16854 | AF53: 882.68649 | AG53: 891.4153 | AH53: 888.27824 | AI53: 910.76808 | AJ53: 869.98416 | AK53: 1821.6956 | AL53: 885.63515 | AM53: 915.46307 | AN53: 869.98416 | AO53: 880.90898 | AP53: 874.25956 | AQ53: 901.28448 | AR53: 883.60088 | AS53: 910.67627 | AT53: 869.98416 | AU53: 839.50234 | AV53: 882.03574 | AW53: 901.88184 | AX53: 869.98416 | AY53: 833.03362 | AZ53: 880.9059 | BA53: 894.88761 | BB53: 869.98416 | BC53: 821.74731 | BD53: 869.9798 | BE53: 831.35602 | BF53: 872.14448 | BG53: 859.10332 | BH53: 879.87436 | BI53: 887.52975
C54: SMS | D54: Hot Metal to Crude Steel | E54: Kg/ TCS | F54: 1062.9741 | G54: 1060 | H54: 1060 | I54: 1065.6348 | J54: 1060 | K54: 1054.4582 | L54: 1060 | M54: 1060.3443 | N54: 1060 | O54: 1063.7514 | P54: 1060 | Q54: 1061.2182 | R54: 1060 | S54: 1058.7752 | T54: 1060 | U54: 1060.4991 | V54: 1060 | W54: 1052.5995 | X54: 1060 | Y54: 1058.7203 | Z54: 1060 | AA54: 1057.3296 | AB54: 1060 | AC54: 1056.2453 | AD54: 1060 | AE54: 1058.465 | AF54: 1060 | AG54: 1061.2178 | AH54: 1060 | AI54: 1058.8777 | AJ54: 1060 | AK54: 1058.3743 | AL54: 1060 | AM54: 1058.875 | AN54: 1060 | AO54: 1061.5577 | AP54: 1060 | AQ54: 1061.341 | AR54: 1060 | AS54: 1059.2405 | AT54: 1060 | AU54: 1062.3569 | AV54: 1060 | AW54: 1059.6296 | AX54: 1060 | AY54: 1061.4914 | AZ54: 1060 | BA54: 1059.8188 | BB54: 1060 | BC54: 1057.0891 | BD54: 1060 | BE54: 1060.2854 | BF54: 1060 | BG54: 1060.7023 | BH54: 1060 | BI54: 1059.546
D55: Scrap consumption at SMS | E55: Kg/ TCS | F55: 38.506405 | G55: 40 | H55: 40 | I55: 31.706697 | J55: 40 | K55: 43.823729 | L55: 40 | M55: 37.442372 | N55: 40 | O55: 36.03881 | P55: 40 | Q55: 37.082377 | R55: 40 | S55: 38.350113 | T55: 40 | U55: 37.45555 | V55: 40 | W55: 44.128077 | X55: 40 | Y55: 38.957985 | Z55: 40 | AA55: 36.786599 | AB55: 40 | AC55: 39.749949 | AD55: 40 | AE55: 38.559266 | AF55: 40 | AG55: 34.008139 | AH55: 40 | AI55: 37.876913 | AJ55: 40 | AK55: 41.109011 | AL55: 40 | AM55: 37.894131 | AN55: 40 | AO55: 37.654621 | AP55: 40 | AQ55: 35.971596 | AR55: 40 | AS55: 37.861502 | AT55: 40 | AU55: 37.524386 | AV55: 40 | AW55: 37.819409 | AX55: 40 | AY55: 35.703807 | AZ55: 40 | BA55: 37.604421 | BB55: 40 | BC55: 38.362239 | BD55: 40 | BE55: 37.241241 | BF55: 40 | BG55: 36.739845 | BH55: 40 | BI55: 37.680158
D56: TMI | E56: Kg/ TCS | F56: 1101.4805 | G56: 1100 | H56: 1100 | I56: 1097.3415 | J56: 1100 | K56: 1098.2819 | L56: 1100 | M56: 1097.7867 | N56: 1100 | O56: 1099.7902 | P56: 1100 | Q56: 1098.3006 | R56: 1100 | S56: 1097.1253 | T56: 1100 | U56: 1097.9546 | V56: 1100 | W56: 1096.7276 | X56: 1100 | Y56: 1097.6783 | Z56: 1100 | AA56: 1094.1162 | AB56: 1100 | AC56: 1095.9952 | AD56: 1100 | AE56: 1097.0242 | AF56: 1100 | AG56: 1095.2259 | AH56: 1100 | AI56: 1096.7546 | AJ56: 1100 | AK56: 1099.4833 | AL56: 1100 | AM56: 1096.7691 | AN56: 1100 | AO56: 1099.2123 | AP56: 1100 | AQ56: 1097.3126 | AR56: 1100 | AS56: 1097.102 | AT56: 1100 | AU56: 1099.8813 | AV56: 1100 | AW56: 1097.449 | AX56: 1100 | AY56: 1097.1952 | AZ56: 1100 | BA56: 1097.4232 | BB56: 1100 | BC56: 1095.4514 | BD56: 1100 | BE56: 1097.5267 | BF56: 1100 | BG56: 1097.4421 | BH56: 1100 | BI56: 1097.2261
D57: Ferro Alloys (FeMn+LCFeMn+SiMn+FeSi) | E57: Kg/ TCS | F57: 22.930617 | G57: 23 | H57: 23 | I57: 21.260454 | J57: 23 | K57: 20.358446 | L57: 23 | M57: 20.833483 | N57: 23 | O57: 17.594962 | P57: 23 | Q57: 20.002846 | R57: 23 | S57: 19.659635 | T57: 23 | U57: 19.901818 | V57: 23 | W57: 21.190669 | X57: 23 | Y57: 20.192025 | Z57: 23 | AA57: 20.579529 | AB57: 23 | AC57: 20.473064 | AD57: 23 | AE57: 20.26318 | AF57: 23 | AG57: 19.519398 | AH57: 23 | AI57: 20.151664 | AJ57: 23 | AK57: 17.643352 | AL57: 23 | AM57: 20.138302 | AN57: 23 | AO57: 21.325501 | AP57: 23 | AQ57: 20.399868 | AR57: 23 | AS57: 20.300038 | AT57: 23 | AU57: 20.886848 | AV57: 23 | AW57: 20.373308 | AX57: 23 | AY57: 20.63752 | AZ57: 23 | BA57: 20.400157 | BB57: 23 | BC57: 20.430955 | BD57: 23 | BE57: 20.653008 | BF57: 23 | BG57: 20.553041 | BH57: 23 | BI57: 20.403235
D58: Cast Weight | E58: T/ Cast | F58: 150.30562 | G58: 150 | H58: 150 | I58: 150.97874 | J58: 150 | K58: 152.42978 | L58: 150 | M58: 151.66214 | N58: 150 | O58: 152.09806 | P58: 150 | Q58: 151.77371 | R58: 150 | S58: 151.88683 | T58: 150 | U58: 151.80699 | V58: 150 | W58: 152.41399 | X58: 150 | Y58: 151.94325 | Z58: 150 | AA58: 153.15815 | AB58: 150 | AC58: 152.48172 | AD58: 150 | AE58: 152.16488 | AF58: 150 | AG58: 153.09301 | AH58: 150 | AI58: 152.30332 | AJ58: 150 | AK58: 152.59615 | AL58: 150 | AM58: 152.30488 | AN58: 150 | AO58: 153.44855 | AP58: 150 | AQ58: 153.26391 | AR58: 150 | AS58: 152.45968 | AT58: 150 | AU58: 153.87124 | AV58: 150 | AW58: 152.63451 | AX58: 150 | AY58: 154.46695 | AZ58: 150 | BA58: 152.81874 | BB58: 150 | BC58: 154.93111 | BD58: 150 | BE58: 154.41864 | BF58: 150 | BG58: 153.96055 | BH58: 150 | BI58: 153.02726
D59: Specific Refractory Consumption | E59: Kg/ TCS | F59: 10.871441 | G59: 9.5 | H59: 9.5 | I59: 7.6 | J59: 9.5 | K59: 9.01 | L59: 9.5 | M59: 8.2674326 | N59: 9.5 | O59: 9.72 | P59: 9.5 | Q59: 8.6399965 | R59: 9.5 | S59: 8.83 | T59: 9.5 | U59: 8.6959262 | V59: 9.5 | W59: 7.94 | X59: 9.5 | Y59: 8.5257164 | Z59: 9.5 | AA59: 6.72 | AB59: 9.5 | AC59: 7.8346914 | AD59: 9.5 | AE59: 8.1941431 | AF59: 9.5 | AG59: 7.04 | AH59: 9.5 | AI59: 8.0211019 | AJ59: 9.5 | AK59: 5.23 | AL59: 9.5 | AM59: 8.0062334 | AN59: 9.5 | AO59: 7.54 | AP59: 9.5 | AQ59: 7.2617247 | AR59: 9.5 | AS59: 7.942717 | AT59: 9.5 | AU59: 6.3 | AV59: 9.5 | AW59: 7.7376058 | AX59: 9.5 | AY59: 6.2 | AZ59: 9.5 | BA59: 7.5813536 | BB59: 9.5 | BC59: 6.03 | BD59: 9.5 | BE59: 6.1764208 | BF59: 9.5 | BG59: 6.6050186 | BH59: 9.5 | BI59: 7.4263098
D60: Specific Electrode Consumption | E60: Kg/ TCS | F60: 0.35658561 | G60: 0.32 | H60: 0.32 | I60: 0.31538612 | J60: 0.32 | K60: 0.35055647 | L60: 0.32 | M60: 0.33203423 | N60: 0.32 | O60: 0.33741131 | P60: 0.32 | Q60: 0.33341338 | R60: 0.32 | S60: 0.31955585 | T60: 0.32 | U60: 0.32933425 | V60: 0.32 | W60: 0.30459102 | X60: 0.32 | Y60: 0.32376289 | Z60: 0.32 | AA60: 0.33362448 | AB60: 0.32 | AC60: 0.31925329 | AD60: 0.32 | AE60: 0.32557371 | AF60: 0.32 | AG60: 0.35362702 | AH60: 0.32 | AI60: 0.32977976 | AJ60: 0.32 | AK60: 0.31505986 | AL60: 0.32 | AM60: 0.32970134 | AN60: 0.32 | AO60: 0.31999319 | AP60: 0.32 | AQ60: 0.33597633 | AR60: 0.32 | AS60: 0.32837877 | AT60: 0.32 | AU60: 0.33417331 | AV60: 0.32 | AW60: 0.32910228 | AX60: 0.32 | AY60: 0.32437695 | AZ60: 0.32 | BA60: 0.32862209 | BB60: 0.32 | BC60: 0.30043276 | BD60: 0.32 | BE60: 0.31957495 | BF60: 0.32 | BG60: 0.32605203 | BH60: 0.32 | BI60: 0.32580482
D61: Calcined Lime | E61: Kg/ TCS | F61: 64.983071 | G61: 70 | H61: 70 | I61: 69.609498 | J61: 70 | K61: 67.169223 | L61: 69.999966 | M61: 68.454379 | N61: 70 | O61: 69.817204 | P61: 69.999974 | Q61: 68.803925 | R61: 70 | S61: 63.354837 | T61: 69.999976 | U61: 67.19992 | V61: 70 | W61: 68.229548 | X61: 69.999983 | Y61: 67.431758 | Z61: 70 | AA61: 65.92434 | AB61: 70.000001 | AC61: 65.825547 | AD61: 69.999986 | AE61: 67.15496 | AF61: 70 | AG61: 68.143405 | AH61: 69.999989 | AI61: 67.303158 | AJ61: 70 | AK61: 79.727662 | AL61: 69.99999 | AM61: 67.369345 | AN61: 70 | AO61: 66.182441 | AP61: 70 | AQ61: 67.350361 | AR61: 69.999992 | AS61: 67.20765 | AT61: 70 | AU61: 66.009705 | AV61: 69.999993 | AW61: 67.058073 | AX61: 70 | AY61: 67.556905 | AZ61: 69.999993 | BA61: 67.108765 | BB61: 70 | BC61: 66.364784 | BD61: 70 | BE61: 66.615111 | BF61: 70 | BG61: 66.905469 | BH61: 69.999994 | BI61: 67.034411
D62: Calcined Dolo | E62: Kg/ TCS | F62: 18.939405 | G62: 20 | H62: 20 | I62: 23.851095 | J62: 20 | K62: 22.697207 | L62: 19.99999 | M62: 23.304895 | N62: 20 | O62: 24.35812 | P62: 19.999992 | Q62: 23.575033 | R62: 20 | S62: 26.616831 | T62: 19.999993 | U62: 24.470423 | V62: 20 | W62: 24.824111 | X62: 19.999995 | Y62: 24.550062 | Z62: 20 | AA62: 22.398611 | AB62: 20 | AC62: 24.622582 | AD62: 19.999996 | AE62: 24.155004 | AF62: 20 | AG62: 22.757929 | AH62: 19.999997 | AI62: 23.94554 | AJ62: 20 | AK62: 22.432262 | AL62: 19.999997 | AM62: 23.937478 | AN62: 20 | AO62: 17.177477 | AP62: 20 | AQ62: 19.933003 | AR62: 19.999998 | AS62: 23.016544 | AT62: 20 | AU62: 24.512629 | AV62: 19.999998 | AW62: 23.203346 | AX62: 20 | AY62: 25.294253 | AZ62: 19.999998 | BA62: 23.415826 | BB62: 20 | BC62: 26.637605 | BD62: 20 | BE62: 25.48354 | BF62: 20 | BG62: 23.291578 | BH62: 19.999998 | BI62: 23.737813
C63: MILLS | D63: WR Mill
D64: Yield | E64: % | F64: 95.450038 | G64: 96 | H64: 96 | I64: 95.880518 | J64: 96 | K64: 95.782523 | L64: 96 | M64: 95.830537 | N64: 96 | O64: 95.82832 | P64: 96 | Q64: 95.829787 | R64: 96 | S64: 95.980374 | T64: 96 | U64: 95.870518 | V64: 96 | W64: 95.889415 | X64: 96 | Y64: 95.874508 | Z64: 96 | AA64: 96.019246 | AB64: 96 | AC64: 95.963664 | AD64: 96 | AE64: 95.900402 | AF64: 96 | AG64: 95.917021 | AH64: 96 | AI64: 95.902898 | AJ64: 96 | AK64: 95.589763 | AL64: 96 | AM64: 95.882126 | AN64: 96 | AO64: 95.504191 | AP64: 96 | AQ64: 95.69292 | AR64: 96 | AS64: 95.838569 | AT64: 96 | AU64: 96.131408 | AV64: 96 | AW64: 95.869407 | AX64: 96 | AY64: 95.760199 | AZ64: 96 | BA64: 95.860383 | BB64: 96 | BC64: 95.419404 | BD64: 96 | BE64: 95.761639 | BF64: 96 | BG64: 95.729796 | BH64: 96 | BI64: 95.818831
D65: Utilization | E65: % | F65: 83.928535 | G65: 85.833333 | H65: 85.833333 | I65: 87.433769 | J65: 85.833333 | K65: 89.607108 | L65: 85.833333 | M65: 88.531441 | N65: 85.833333 | O65: 85.877091 | P65: 85.833333 | Q65: 87.655887 | R65: 85.833333 | S65: 86.060639 | T65: 85.833333 | U65: 87.24945 | V65: 85.833333 | W65: 91.13665 | X65: 85.833333 | Y65: 88.068414 | Z65: 85.833333 | AA65: 89.736373 | AB65: 85.833333 | AC65: 89.008381 | AD65: 85.833333 | AE65: 88.344512 | AF65: 85.833333 | AG65: 88.890958 | AH65: 85.833333 | AI65: 88.425265 | AJ65: 85.833333 | AK65: 82.317263 | AL65: 85.833333 | AM65: 87.994723 | AN65: 85.833333 | AO65: 83.777627 | AP65: 85.833333 | AQ65: 85.527326 | AR65: 85.833333 | AS65: 87.493962 | AT65: 85.833333 | AU65: 88.013518 | AV65: 85.833333 | AW65: 87.548069 | AX65: 85.833333 | AY65: 89.435326 | AZ65: 85.833333 | BA65: 87.713049 | BB65: 85.833333 | BC65: 87.499671 | BD65: 85.833333 | BE65: 88.271185 | BF65: 85.833333 | BG65: 86.991999 | BH65: 85.833333 | BI65: 87.693622
D66: Rolling Rate on yield Wt | E66: T/Utlzn Hr | F66: 75.551243 | G66: 79.319754 | H66: 79.088033 | I66: 71.393253 | J66: 79.737829 | K66: 70.990047 | L66: 79.418903 | M66: 71.187134 | N66: 76.647931 | O66: 76.259837 | P66: 78.701622 | Q66: 72.826441 | R66: 75.849515 | S66: 80.56995 | T66: 78.191177 | U66: 74.77245 | V66: 79.737829 | W66: 71.790724 | X66: 78.557038 | Y66: 74.122367 | Z66: 79.997091 | AA66: 80.023912 | AB66: 78.952449 | AC66: 77.287064 | AD66: 78.824419 | AE66: 75.114643 | AF66: 79.737829 | AG66: 76.106108 | AH66: 78.971949 | AI66: 75.261932 | AJ66: 79.997091 | AK66: 75.501039 | AL66: 79.110049 | AM66: 75.277699 | AN66: 79.737829 | AO66: 76.133946 | AP66: 79.822144 | AQ66: 75.997014 | AR66: 79.187028 | AS66: 75.375056 | AT66: 79.737829 | AU66: 76.098798 | AV66: 79.24719 | AW66: 75.450827 | AX66: 79.595928 | AY66: 69.371351 | AZ66: 79.278142 | BA66: 74.908937 | BB66: 79.737829 | BC66: 77.629179 | BD66: 79.694072 | BE66: 74.528124 | BF66: 79.758898 | BG66: 75.20139 | BH66: 79.319754 | BI66: 75.156055
D67: Bar Mill
D68: Yield | E68: % | F68: 95.450022 | G68: 96.5 | H68: 96.5 | I68: 96.386344 | J68: 96.5 | K68: 96.377227 | L68: 96.5 | M68: 96.381932 | N68: 96.5 | O68: 96.36879 | P68: 96.5 | Q68: 96.378393 | R68: 96.5 | S68: 96.278901 | T68: 96.5 | U68: 96.350979 | V68: 96.5 | W68: 96.354196 | X68: 96.5 | Y68: 96.351681 | Z68: 96.5 | AA68: 96.249592 | AB68: 96.5 | AC68: 96.29443 | AD68: 96.5 | AE68: 96.333505 | AF68: 96.5 | AG68: 96.204059 | AH68: 96.5 | AI68: 96.314822 | AJ68: 96.5 | AK68: 94.958487 | AL68: 96.5 | AM68: 96.305468 | AN68: 96.5 | AO68: 96.296098 | AP68: 96.5 | AQ68: 96.221812 | AR68: 96.5 | AS68: 96.304235 | AT68: 96.5 | AU68: 96.148155 | AV68: 96.5 | AW68: 96.286184 | AX68: 96.5 | AY68: 96.184461 | AZ68: 96.5 | BA68: 96.276198 | BB68: 96.5 | BC68: 96.379798 | BD68: 96.5 | BE68: 96.243642 | BF68: 96.5 | BG68: 96.234989 | BH68: 96.5 | BI68: 96.286951
D69: Utilization | E69: % | F69: 80.103401 | G69: 83.333333 | H69: 83.333333 | I69: 84.439269 | J69: 83.333333 | K69: 78.991149 | L69: 83.333333 | M69: 81.74075 | N69: 83.333333 | O69: 83.857179 | P69: 83.333333 | Q69: 82.309661 | R69: 83.333333 | S69: 87.487472 | T69: 83.333333 | U69: 83.697227 | V69: 83.333333 | W69: 89.146649 | X69: 83.333333 | Y69: 84.843208 | Z69: 83.333333 | AA69: 88.383798 | AB69: 83.333333 | AC69: 88.337539 | AD69: 83.333333 | AE69: 85.459399 | AF69: 83.333333 | AG69: 79.715141 | AH69: 83.333333 | AI69: 84.569946 | AJ69: 83.333333 | AK69: 72.067715 | AL69: 83.333333 | AM69: 84.450242 | AN69: 83.333333 | AO69: 87.548184 | AP69: 83.333333 | AQ69: 83.265566 | AR69: 83.333333 | AS69: 84.859406 | AT69: 83.333333 | AU69: 87.271777 | AV69: 83.333333 | AW69: 85.133595 | AX69: 83.333333 | AY69: 84.796459 | AZ69: 83.333333 | BA69: 85.101474 | BB69: 83.333333 | BC69: 87.801023 | BD69: 83.333333 | BE69: 86.68468 | BF69: 83.333333 | BG69: 85.255002 | BH69: 83.333333 | BI69: 85.362564
D70: Rolling Rate on yield Wt | E70: T/Utlzn Hr | F70: 129.3573 | G70: 136.79245 | H70: 137.5 | I70: 129.35596 | J70: 137.93103 | K70: 132.11425 | L70: 137.7193 | M70: 130.67621 | N70: 141.17647 | O70: 127.67437 | P70: 138.51351 | Q70: 129.85413 | R70: 110.29412 | S70: 126.79614 | T70: 133.24176 | U70: 128.99753 | V70: 137.93103 | W70: 127.1318 | X70: 134.375 | Y70: 128.58527 | Z70: 138.39286 | AA70: 126.75568 | AB70: 131.75676 | AC70: 126.89526 | AD70: 135.13514 | AE70: 128.25596 | AF70: 137.93103 | AG70: 126.42427 | AH70: 135.59322 | AI70: 127.98862 | AJ70: 138.39286 | AK70: 106.36644 | AL70: 135.97561 | AM70: 127.81195 | AN70: 137.93103 | AO70: 122.7576 | AP70: 138.0814 | AQ70: 124.03496 | AR70: 136.21795 | AS70: 127.12324 | AT70: 137.93103 | AU70: 125.85619 | AV70: 136.40684 | AW70: 126.97561 | AX70: 139.42308 | AY70: 131.63337 | AZ70: 136.6782 | BA70: 127.41779 | BB70: 137.93103 | BC70: 133.72865 | BD70: 138.39286 | BE70: 130.41814 | BF70: 138.23529 | BG70: 127.81134 | BH70: 136.79245 | BI70: 128.04559
D71: US Mill
D72: Yield | E72: % | F72: 93.371871 | G72: 94.75 | H72: 94.75 | I72: 94.396456 | J72: 94.75 | K72: 94.472431 | L72: 94.75 | M72: 94.433403 | N72: 94.75 | O72: 94.056655 | P72: 94.75 | Q72: 94.345198 | R72: 94.75 | S72: 93.978114 | T72: 94.75 | U72: 94.244937 | V72: 94.75 | W72: 92.455322 | X72: 94.75 | Y72: 93.930011 | Z72: 94.75 | AA72: 94.354897 | AB72: 94.75 | AC72: 93.67897 | AD72: 94.75 | AE72: 94.006334 | AF72: 94.75 | AG72: 94.095026 | AH72: 94.75 | AI72: 94.020193 | AJ72: 94.75 | AK72: 93.695979 | AL72: 94.75 | AM72: 94.010748 | AN72: 94.75 | AO72: 91.062906 | AP72: 94.75 | AQ72: 92.736312 | AR72: 94.75 | AS72: 93.648995 | AT72: 94.75 | AU72: 93.529416 | AV72: 94.75 | AW72: 93.633199 | AX72: 94.75 | AY72: 94.085079 | AZ72: 94.75 | BA72: 93.685624 | BB72: 94.75 | BC72: 94.093152 | BD72: 94.75 | BE72: 93.914612 | BF72: 94.75 | BG72: 93.483365 | BH72: 94.75 | BI72: 93.736035
D73: Utilization | E73: % | F73: 68.17524 | G73: 81.25 | H73: 81.25 | I73: 85.642877 | J73: 81.25 | K73: 84.565056 | L73: 81.25 | M73: 85.122424 | N73: 81.25 | O73: 78.017586 | P73: 81.25 | Q73: 83.244414 | R73: 81.25 | S73: 85.815912 | T73: 81.25 | U73: 83.930439 | V73: 81.25 | W73: 73.77073 | X73: 81.25 | Y73: 81.794268 | Z73: 81.25 | AA73: 89.265455 | AB73: 81.25 | AC73: 82.952949 | AD73: 81.25 | AE73: 83.092398 | AF73: 81.25 | AG73: 80.337965 | AH73: 81.25 | AI73: 82.670791 | AJ73: 81.25 | AK73: 87.625595 | AL73: 81.25 | AM73: 82.86354 | AN73: 81.25 | AO73: 74.710918 | AP73: 81.25 | AQ73: 78.829173 | AR73: 81.25 | AS73: 81.881285 | AT73: 81.25 | AU73: 82.111785 | AV73: 81.25 | AW73: 81.909104 | AX73: 81.25 | AY73: 88.17552 | AZ73: 81.25 | BA73: 82.495987 | BB73: 81.25 | BC73: 84.861464 | BD73: 81.25 | BE73: 84.892353 | BF73: 81.25 | BG73: 82.336905 | BH73: 81.25 | BI73: 82.726034
D74: Rolling Rate on yield Wt | E74: T/Utlzn Hr | F74: 72.378211 | G74: 93.849506 | H74: 87.369421 | I74: 91.475286 | J74: 86.996337 | K74: 93.999809 | L74: 87.179487 | M74: 92.686333 | N74: 74.786325 | O74: 85.694671 | P74: 83.414476 | Q74: 90.954278 | R74: 80.128205 | S74: 90.762293 | T74: 83.11229 | U74: 90.90191 | V74: 89.74359 | W74: 81.380711 | X74: 84.726867 | Y74: 89.096368 | Z74: 91.168091 | AA74: 85.39181 | AB74: 89.133089 | AC74: 86.058008 | AD74: 85.951607 | AE74: 88.404876 | AF74: 98.901099 | AG74: 93.78653 | AH74: 88.084465 | AI74: 89.205373 | AJ74: 98.765432 | AK74: 62.172485 | AL74: 89.548354 | AM74: 88.09332 | AN74: 98.901099 | AO74: 96.643461 | AP74: 98.856966 | AQ74: 90.702483 | AR74: 90.712251 | AS74: 89.033259 | AT74: 98.901099 | AU74: 98.325598 | AV74: 91.618526 | AW74: 90.15753 | AX74: 98.461538 | AY74: 106.8821 | AZ74: 92.233905 | BA74: 91.831712 | BB74: 109.89011 | BC74: 117.48623 | BD74: 102.5641 | BE74: 107.64356 | BF74: 100.68793 | BG74: 100.80759 | BH74: 93.849506 | BI74: 94.391068
C75: ENERGY & POWER | D75: Sp Energy Consumpt | E75: G.cal/TCS | F75: 6.2012038 | G75: 5.950002 | H75: 5.8190698 | I75: 6.2156479 | J75: 5.8123281 | K75: 6.3285548 | L75: 5.8156436 | M75: 6.2723601 | N75: 6.2529957 | O75: 7.0163172 | P75: 5.9176447 | Q75: 6.4699825 | R75: 7.7286662 | S75: 5.9975708 | T75: 6.0915485 | U75: 6.3309225 | V75: 5.9155176 | W75: 5.9945722 | X75: 6.0467975 | Y75: 6.2551875 | Z75: 5.9554125 | AA75: 5.9775121 | AB75: 6.1598432 | AC75: 5.9899225 | AD75: 6.0287708 | AE75: 6.2078763 | AF75: 5.9185019 | AG75: 6.0970124 | AH75: 6.0094385 | AI75: 6.1913024 | AJ75: 5.8679361 | AK75: 29.436172 | AL75: 5.9889093 | AM75: 6.3410739 | AN75: 5.860739 | AO75: 5.9578574 | AP75: 5.8825485 | AQ75: 6.4229771 | AR75: 5.9722026 | AS75: 6.2868672 | AT75: 5.8608476 | AU75: 5.8560511 | AV75: 5.9593616 | AW75: 6.2300751 | AX75: 5.8591772 | AY75: 5.8885991 | AZ75: 5.9499431 | BA75: 6.1941702 | BB75: 5.8704882 | BC75: 5.8758634 | BD75: 5.8636538 | BE75: 5.873006 | BF75: 5.8732108 | BG75: 6.0909851 | BH75: 5.950002 | BI75: 6.1600133
D76: Sp Power Consumption | E76: KwH/TSS | F76: 516.74946 | G76: 498.86963 | H76: 485.07343 | I76: 474.83527 | J76: 507.78368 | K76: 565.47965 | L76: 496.3676 | M76: 516.32337 | N76: 593.17326 | O76: 591.60316 | P76: 520.81676 | Q76: 536.99419 | R76: 853.7036 | S76: 472.54449 | T76: 563.2223 | U76: 518.41033 | V76: 483.1292 | W76: 494.26516 | X76: 543.04701 | Y76: 513.19767 | Z76: 495.38777 | AA76: 466.32576 | AB76: 548.50849 | AC76: 477.545 | AD76: 533.90051 | AE76: 504.7149 | AF76: 473.75976 | AG76: 548.71956 | AH76: 523.38682 | AI76: 510.66495 | AJ76: 466.25573 | AK76: 1065.6856 | AL76: 515.00246 | AM76: 526.53693 | AN76: 477.18949 | AO76: 440.38863 | AP76: 472.42342 | AQ76: 540.56277 | AR76: 510.12503 | AS76: 514.61576 | AT76: 473.76185 | AU76: 429.41761 | AV76: 505.94401 | AW76: 503.98133 | AX76: 466.39505 | AY76: 447.46906 | AZ76: 502.17743 | BA76: 498.34487 | BB76: 467.63958 | BC76: 432.53356 | BD76: 469.33852 | BE76: 436.01158 | BF76: 470.89222 | BG76: 477.73863 | BH76: 498.86963 | BI76: 491.52958
C77: ENVIRONMENT | D77: Sp Water Consumption | E77: M³/TCS | F77: 3.0186532 | G77: 2.85 | H77: 2.85 | I77: 3.15 | J77: 2.85 | K77: 3.35 | L77: 2.85 | M77: 3.2446713 | N77: 2.85 | O77: 3.27 | P77: 2.85 | Q77: 3.2511678 | R77: 2.85 | S77: 2.98 | T77: 2.85 | U77: 3.1713463 | V77: 2.85 | W77: 2.93 | X77: 2.85 | Y77: 3.117003 | Z77: 2.85 | AA77: 2.93 | AB77: 2.85 | AC77: 2.9468158 | AD77: 2.85 | AE77: 3.0826648 | AF77: 2.85 | AG77: 2.99 | AH77: 2.85 | AI77: 3.0687715 | AJ77: 2.85 | AK77: 3.19 | AL77: 2.85 | AM77: 3.0694173 | AN77: 2.85 | AO77: 2.87 | AP77: 2.85 | AQ77: 2.9327862 | AR77: 2.85 | AS77: 3.0422501 | AT77: 2.85 | AU77: 2.87 | AV77: 2.85 | AW77: 3.0207428 | AX77: 2.85 | AY77: 2.86 | AZ77: 2.85 | BA77: 3.004408 | BB77: 2.85 | BC77: 2.88 | BD77: 2.85 | BE77: 2.8702899 | BF77: 2.85 | BG77: 2.8949703 | BH77: 2.85 | BI77: 2.9919746
D78: Sp. CO2 emission | E78: T/TCS | F78: 2.4470555 | G78: 2.32 | H78: 2.32 | I78: 2.45 | J78: 2.32 | K78: 2.39 | L78: 2.32 | M78: 2.4215986 | N78: 2.32 | O78: 2.591 | P78: 2.32 | Q78: 2.4650478 | R78: 2.32 | S78: 2.36 | T78: 2.32 | U78: 2.4341257 | V78: 2.32 | W78: 2.41 | X78: 2.32 | Y78: 2.4286934 | Z78: 2.32 | AA78: 2.33 | AB78: 2.32 | AC78: 2.3666511 | AD78: 2.32 | AE78: 2.4205709 | AF78: 2.32 | AG78: 2.36 | AH78: 2.32 | AI78: 2.4114895 | AJ78: 2.32 | AK78: 0 | AL78: 2.32 | AM78: 2.45 | AN78: 2.32 | AO78: 2.33 | AP78: 2.32 | AQ78: 2.3045713 | AR78: 2.32 | AS78: 2.399652 | AT78: 2.32 | AU78: 2.29 | AV78: 2.32 | AW78: 2.3759608 | AX78: 2.32 | AY78: 2.29 | AZ78: 2.32 | BA78: 2.3672254 | BB78: 2.32 | BC78: 2.29 | BD78: 2.32 | BE78: 2.29 | BF78: 2.32 | BG78: 2.2957544 | BH78: 2.32 | BI78: 2.3695074
D79: Sp. PM emissions | E79: kg/TCS | F79: 0.5280682 | G79: 0.5 | H79: 0.5 | I79: 0.54 | J79: 0.5 | K79: 0.57 | L79: 0.5 | M79: 0.55420069 | N79: 0.5 | O79: 0.58 | P79: 0.5 | Q79: 0.56081787 | R79: 0.5 | S79: 0.52 | T79: 0.5 | U79: 0.54880265 | V79: 0.5 | W79: 0.5 | X79: 0.5 | Y79: 0.53781389 | Z79: 0.5 | AA79: 0.51 | AB79: 0.5 | AC79: 0.51004297 | AD79: 0.5 | AE79: 0.53270659 | AF79: 0.5 | AG79: 0.5 | AH79: 0.5 | AI79: 0.52780287 | AJ79: 0.5 | AK79: 0 | AL79: 0.5 | AM79: 0.54 | AN79: 0.5 | AO79: 0.49 | AP79: 0.5 | AQ79: 0.48641557 | AR79: 0.5 | AS79: 0.52318835 | AT79: 0.5 | AU79: 0.46 | AV79: 0.5 | AW79: 0.51529859 | AX79: 0.5 | AY79: 0.44 | AZ79: 0.5 | BA79: 0.50764672 | BB79: 0.5 | BC79: 0.49 | BD79: 0.5 | BE79: 0.46399819 | BF79: 0.5 | BG79: 0.47285105 | BH79: 0.5 | BI79: 0.49588309
C80: LABOR PRODUCTIVITY | D80: Labour Productivity | E80: TCS/Man/Year | F80: 639.11266 | G80: 712.02135 | H80: 769.48165 | I80: 761.08746 | J80: 772.09241 | K80: 657.93142 | L80: 770.785 | M80: 708.55086 | N80: 480.12887 | O80: 511.97436 | P80: 675.31984 | Q80: 643.66771 | R80: 221.11384 | S80: 780.59809 | T80: 560.72371 | U80: 678.49399 | V80: 759.30661 | W80: 770.78122 | X80: 600.50395 | Y80: 697.2069 | Z80: 761.48024 | AA80: 795.29293 | AB80: 576.28232 | AC80: 782.08088 | AD80: 626.59207 | AE80: 713.30412 | AF80: 795.73412 | AG80: 739.55185 | AH80: 650.77455 | AI80: 717.10702 | AJ80: 797.75563 | AK80: 30 * | AL80: 668.63469 | AM80: 632* | AN80: 799.40216 | AO80: 783.42261 | AP80: 797.62644 | AQ80: 523.0789 | AR80: 683.16207 | AS80: 649.49896 | AT80: 801.24889 | AU80: 812.39513 | AV80: 694.94218 | AW80: 666.12009 | AX80: 800.86059 | AY80: 821.47127 | AZ80: 703.76706 | BA80: 679.14173 | BB80: 804.50127 | BC80: 821.28851 | BD80: 802.26722 | BE80: 818.29191 | BF80: 799.94404 | BG80: 668.98436 | BH80: 712.17383 | BI80: 691.16367

Sheet Direct sales IPT details
B2: DIRECT SALES/INTERNAL CONSUMPTION/IPT DETAILS
B3: ITEM | C3: Unit | D3: Apr'24 | F3: May'24 | H3: 2M | J3: Jun'24 | L3: QTR-1 | N3: Jul'24 | P3: 4M | R3: Aug'24 | T3: 5M | V3: Sep'24 | X3: QTR-2 | Z3: H1 | AB3: Oct'24 | AD3: 7M | AF3: Nov'24 | AH3: 8M | AJ3: Dec'24 | AL3: QTR-3 | AN3: 9M | AP3: Jan'25 | AR3: 10M | AT3: Feb'25 | AV3: 11M | AX3: Mar'25 | AZ3: QTR-4 | BB3: H2 | BD3: 2024-25
D4: ABP | E4: ACT | F4: ABP | G4: ACT | H4: ABP | I4: ACT | J4: ABP | K4: ACT | L4: ABP | M4: ACT | N4: ABP | O4: ACT | P4: ABP | Q4: ACT | R4: ABP | S4: ACT | T4: ABP | U4: ACT | V4: ABP | W4: ACT | X4: ABP | Y4: ACT | Z4: ABP | AA4: ACT | AB4: ABP | AC4: ACT | AD4: ABP | AE4: ACT | AF4: ABP | AG4: ACT | AH4: ABP | AI4: ACT | AJ4: ABP | AK4: ACT | AL4: ABP | AM4: ACT | AN4: ABP | AO4: ACT | AP4: ABP | AQ4: ACT | AR4: ABP | AS4: ACT | AT4: ABP | AU4: ACT | AV4: ABP | AW4: ACT | AX4: ABP | AY4: ACT | AZ4: ABP | BA4: ACT | BB4: ABP | BC4: ACT | BD4: ABP | BE4: ACT
B5: Assorted Semis | E5: 3578.87 | G5: 8742.4 | I5: 12321.27 | K5: 4335 | M5: 16656.27 | O5: 2363.09 | Q5: 19019.36 | S5: 4615.5 | U5: 23634.86 | W5: 5084.52 | Y5: 12063.11 | AA5: 28719.38 | AC5: 4044.21 | AE5: 32763.59 | AG5: 5778.35 | AI5: 38541.94 | AK5: 3912.49 | AM5: 13735.05 | AO5: 42454.43 | AQ5: 3486.44 | AS5: 45940.87 | AU5: 1080.44 | AW5: 47021.31 | AY5: 6965.79 | BA5: 11532.67 | BC5: 25267.72 | BE5: 53987.1
B6: ASSORTED BILLET (CCP)150*150 | C6: MT | E6: 3578.87 | F6: 0 | G6: 7520.1 | I6: 11098.97 | J6: 0 | K6: 2866.62 | M6: 13965.59 | N6: 0 | O6: 2363.09 | Q6: 16328.68 | R6: 0 | S6: 3766.74 | U6: 20095.42 | V6: 0 | W6: 4291.22 | Y6: 10421.05 | AA6: 24386.64 | AB6: 0 | AC6: 3411.65 | AE6: 27798.29 | AF6: 0 | AG6: 5141.47 | AI6: 32939.76 | AJ6: 0 | AK6: 3545.03 | AM6: 12098.15 | AO6: 36484.79 | AP6: 0 | AQ6: 3486.44 | AS6: 39971.23 | AT6: 0 | AU6: 1080.44 | AW6: 41051.67 | AX6: 0 | AY6: 6449.17 | BA6: 11016.05 | BC6: 23114.2 | BE6: 47500.84
B7: Plant Sales (Other Parties) | C7: MT | E7: 158.35 | G7: 1436.16 | I7: 1594.51 | K7: 0 | M7: 1594.51 | O7: 299.77 | Q7: 1894.28 | S7: 0 | U7: 1894.28 | W7: 0 | Y7: 299.77 | AA7: 1894.28 | AC7: 651.15 | AE7: 2545.43 | AG7: 710.81 | AI7: 3256.24 | AK7: 40.57 | AM7: 1402.53 | AO7: 3296.81 | AS7: 3296.81 | AU7: 1080.44 | AW7: 4377.25 | AY7: 5154.93 | BA7: 6235.37 | BC7: 7637.9 | BE7: 9532.18
B8: Plant Sales (IPT) -Rail | C8: MT | E8: 3420.52 | F8: 0 | G8: 6083.94 | I8: 9504.46 | J8: 0 | K8: 2866.62 | M8: 12371.08 | N8: 0 | O8: 2063.32 | Q8: 14434.4 | R8: 0 | S8: 3766.74 | U8: 18201.14 | V8: 0 | W8: 4291.22 | Y8: 10121.28 | AA8: 22492.36 | AB8: 0 | AC8: 2760.5 | AE8: 25252.86 | AF8: 0 | AG8: 4430.66 | AI8: 29683.52 | AJ8: 0 | AK8: 3504.46 | AM8: 10695.62 | AO8: 33187.98 | AP8: 0 | AQ8: 3486.44 | AS8: 36674.42 | AT8: 0 | AU8: 0 | AW8: 36674.42 | AX8: 0 | AY8: 1294.24 | BA8: 4780.68 | BC8: 15476.3 | BE8: 37968.66
B9: Bokaro | C9: MT | E9: 2147.8 | G9: 4842.68 | I9: 6990.48 | K9: 1651.5 | M9: 8641.98 | O9: 2063.32 | Q9: 10705.3 | S9: 2278.38 | U9: 12983.68 | W9: 2804.22 | Y9: 7145.92 | AA9: 15787.9 | AC9: 1273.2 | AE9: 17061.1 | AG9: 1411.16 | AI9: 18472.26 | AK9: 2020.64 | AM9: 4705 | AO9: 20492.9 | AQ9: 1990.42 | AS9: 22483.32 | AW9: 22483.32 | BA9: 1990.42 | BC9: 6695.42 | BE9: 22483.32
B10: ASP | C10: MT | E10: 1272.72 | G10: 1241.26 | I10: 2513.98 | K10: 1215.12 | M10: 3729.1 | Q10: 3729.1 | S10: 1488.36 | U10: 5217.46 | W10: 1487 | Y10: 2975.36 | AA10: 6704.46 | AC10: 1487.3 | AE10: 8191.76 | AG10: 3019.5 | AI10: 11211.26 | AK10: 1483.82 | AM10: 5990.62 | AO10: 12695.08 | AQ10: 1496.02 | AS10: 14191.1 | AW10: 14191.1 | AY10: 1294.24 | BA10: 2790.26 | BC10: 8780.88 | BE10: 15485.34
B12: ASSORTED CC BLOOM 200*280- Road | I12: 0 | M12: 0 | Q12: 0 | U12: 0 | Y12: 0 | AA12: 0 | AE12: 0 | AI12: 0 | AM12: 0 | AO12: 0 | AS12: 0 | AW12: 0 | AY12: 516.62 | BA12: 516.62 | BC12: 516.62 | BE12: 516.62
B14: ASSORTED CC BEAM BLANK | C14: MT | E14: 0 | F14: 0 | G14: 1222.3 | I14: 1222.3 | K14: 1468.38 | M14: 2690.68 | O14: 0 | Q14: 2690.68 | S14: 848.76 | U14: 3539.44 | W14: 793.3 | Y14: 1642.06 | AA14: 4332.74 | AC14: 632.56 | AE14: 4965.3 | AG14: 636.88 | AI14: 5602.18 | AK14: 367.46 | AM14: 1636.9 | AO14: 5969.64 | AQ14: 0 | AS14: 5969.64 | AU14: 0 | AW14: 5969.64 | AY14: 0 | BA14: 0 | BC14: 1636.9 | BE14: 5969.64
B15: Plant Sales (Other Parties)- Road | C15: MT | F15: 0 | I15: 0 | J15: 0 | M15: 0 | N15: 0 | Q15: 0 | R15: 0 | U15: 0 | V15: 0 | Y15: 0 | AA15: 0 | AE15: 0 | AI15: 0 | AJ15: 0 | AM15: 0 | AO15: 0 | AS15: 0 | AW15: 0 | BA15: 0 | BC15: 0 | BE15: 0
B16: Plant Sales (IPT) -Rail | C16: MT | E16: 0 | F16: 0 | G16: 1222.3 | H16: 0 | I16: 1222.3 | J16: 0 | K16: 1468.38 | L16: 0 | M16: 2690.68 | N16: 0 | O16: 0 | P16: 0 | Q16: 2690.68 | R16: 0 | S16: 848.76 | T16: 0 | U16: 3539.44 | V16: 0 | W16: 793.3 | X16: 0 | Y16: 1642.06 | Z16: 0 | AA16: 4332.74 | AB16: 0 | AC16: 632.56 | AD16: 0 | AE16: 4965.3 | AF16: 0 | AG16: 636.88 | AH16: 0 | AI16: 5602.18 | AJ16: 0 | AK16: 367.46 | AL16: 0 | AM16: 1636.9 | AN16: 0 | AO16: 5969.64 | AP16: 0 | AQ16: 0 | AR16: 0 | AS16: 5969.64 | AT16: 0 | AU16: 0 | AV16: 0 | AW16: 5969.64 | AX16: 0 | AY16: 0 | AZ16: 0 | BA16: 0 | BB16: 0 | BC16: 1636.9 | BD16: 0 | BE16: 5969.64
B17: ASP | C17: MT | I17: 0 | M17: 0 | Q17: 0 | U17: 0 | Y17: 0 | AA17: 0 | AE17: 0 | AI17: 0 | AM17: 0 | AO17: 0 | AS17: 0 | AW17: 0 | BA17: 0 | BC17: 0 | BE17: 0
B18: Bokaro | C18: MT | G18: 1222.3 | I18: 1222.3 | K18: 1468.38 | M18: 2690.68 | Q18: 2690.68 | S18: 848.76 | U18: 3539.44 | W18: 793.3 | Y18: 1642.06 | AA18: 4332.74 | AC18: 632.56 | AE18: 4965.3 | AG18: 636.88 | AI18: 5602.18 | AK18: 367.46 | AM18: 1636.9 | AO18: 5969.64 | AS18: 5969.64 | AW18: 5969.64 | BA18: 0 | BC18: 1636.9 | BE18: 5969.64
B19: REJECTED WIRE ROD COIL SCRAP- Road | C19: MT | I19: 0 | M19: 0 | Q19: 0 | U19: 0 | Y19: 0 | AA19: 0 | AE19: 0 | AI19: 0 | AM19: 0 | AO19: 0 | AS19: 0 | AW19: 0 | BA19: 0 | BC19: 0 | BE19: 0
M20: 0
B21: ISP DIRECT SALES (Except assorted semis)
B22: BY ROAD | AE22: 0
B23: BY PRODUCT | C23: MT | E23: 4073.92 | G23: 4232.67 | I23: 8306.59 | K23: 3557 | M23: 11863.59 | O23: 3617.16 | Q23: 15480.75 | S23: 3009.8 | U23: 18490.55 | W23: 3072.89 | Y23: 9699.85 | AA23: 21563.44 | AC23: 3713.79 | AE23: 25277.23 | AG23: 3826.97 | AI23: 29104.2 | AK23: 3981.27 | AM23: 11522.03 | AO23: 33085.47 | AQ23: 3120.15 | AS23: 36205.62 | AU23: 4844.83 | AW23: 41050.45 | AY23: 4199.58 | BA23: 12164.56 | BC23: 23686.59 | BE23: 45250.03
B24: AMMONIUM SULPHATE | C24: MT | E24: 457.04 | G24: 458.01 | I24: 915.05 | K24: 356.9 | M24: 1271.95 | O24: 297.34 | Q24: 1569.29 | S24: 416.53 | U24: 1985.82 | W24: 198.21 | Y24: 912.08 | AA24: 2184.03 | AC24: 238.4 | AE24: 2422.43 | AG24: 496.85 | AI24: 2919.28 | AK24: 436.56 | AM24: 1171.81 | AO24: 3355.84 | AQ24: 455.26 | AS24: 3811.1 | AU24: 614.73 | AW24: 4425.83 | AY24: 455.19 | BA24: 1525.18 | BC24: 2696.99 | BE24: 4881.02
B25: BENZENE | C25: MT | I25: 0 | M25: 0 | Q25: 0 | U25: 0 | Y25: 0 | AA25: 0 | AE25: 0 | AI25: 0 | AM25: 0 | AO25: 0 | AS25: 0 | AW25: 0 | BA25: 0 | BC25: 0 | BE25: 0
B26: BENZOL | C26: MT | I26: 0 | M26: 0 | Q26: 0 | U26: 0 | Y26: 0 | AA26: 0 | AE26: 0 | AI26: 0 | AM26: 0 | AO26: 0 | AS26: 0 | AW26: 0 | BA26: 0 | BC26: 0 | BE26: 0
B27: CRUDE BENZOL | C27: MT | I27: 0 | M27: 0 | Q27: 0 | U27: 0 | Y27: 0 | AA27: 0 | AE27: 0 | AM27: 0 | AS27: 0 | AW27: 0 | BA27: 0 | BC27: 0 | BE27: 0
B28: CRUDE COAL TAR | C28: MT | E28: 3616.88 | G28: 3759.68 | I28: 7376.56 | K28: 3200.1 | M28: 10576.66 | O28: 3319.82 | Q28: 13896.48 | S28: 2593.27 | U28: 16489.75 | W28: 2874.68 | Y28: 8787.77 | AA28: 19364.43 | AC28: 3460.9 | AE28: 22825.33 | AG28: 3330.12 | AI28: 26155.45 | AK28: 3544.71 | AM28: 10335.73 | AO28: 29700.16 | AQ28: 2649.93 | AS28: 32350.09 | AU28: 4230.1 | AW28: 36580.19 | AY28: 3744.39 | BA28: 10624.42 | BC28: 20960.15 | BE28: 40324.58
B29: LIGHT SOLVENT NAPHTHA | C29: MT | I29: 0 | M29: 0 | Q29: 0 | U29: 0 | Y29: 0 | AA29: 0 | AE29: 0 | AI29: 0 | AM29: 0 | AO29: 0 | AS29: 0 | AW29: 0 | BA29: 0 | BC29: 0 | BE29: 0
B30: TOLUENE | C30: MT | I30: 0 | M30: 0 | Q30: 0 | U30: 0 | Y30: 0 | AA30: 0 | AE30: 0 | AI30: 0 | AM30: 0 | AO30: 0 | AS30: 0 | AW30: 0 | BA30: 0 | BC30: 0 | BE30: 0
B31: STILL BOTTOM OIL | C31: MT | I31: 0 | M31: 0 | Q31: 0 | U31: 0 | Y31: 0 | AA31: 0 | AE31: 0 | AI31: 0 | AM31: 0 | AO31: 0 | AS31: 0 | AW31: 0 | BA31: 0 | BC31: 0 | BE31: 0
B32: WHIZZED NAPHTHALENE | C32: MT | G32: 14.98 | I32: 14.98 | M32: 14.98 | Q32: 14.98 | U32: 14.98 | Y32: 0 | AA32: 14.98 | AC32: 14.49 | AE32: 29.47 | AI32: 29.47 | AM32: 14.49 | AO32: 29.47 | AQ32: 14.96 | AS32: 44.43 | AW32: 44.43 | BA32: 14.96 | BC32: 29.45 | BE32: 44.43
B33: COKE DUST FINES | C33: MT | I33: 0 | M33: 0 | Q33: 0 | U33: 0 | Y33: 0 | AA33: 0 | AE33: 0 | AI33: 0 | AM33: 0 | AO33: 0 | AS33: 0 | AW33: 0 | BA33: 0 | BC33: 0 | BE33: 0
B34: IDLE ASSET | E34: 93.87 | G34: 104.5 | I34: 198.37 | K34: 23.8 | M34: 222.17 | O34: 173.31 | Q34: 395.48 | S34: 0 | U34: 395.48 | W34: 0 | Y34: 173.31 | AA34: 395.48 | AC34: 0 | AE34: 395.48 | AG34: 0 | AI34: 395.48 | AK34: 0 | AM34: 0 | AO34: 395.48 | AQ34: 0 | AS34: 395.48 | AU34: 63.75 | AW34: 459.23 | AY34: 30.16 | BA34: 93.91 | BC34: 93.91 | BE34: 489.39
B35: DISMANTLED CAST IRON SCRAP | C35: MT | I35: 0 | M35: 0 | O35: 173.31 | Q35: 173.31 | U35: 173.31 | Y35: 173.31 | AA35: 173.31 | AE35: 173.31 | AI35: 173.31 | AM35: 0 | AO35: 173.31 | AS35: 173.31 | AW35: 173.31 | BA35: 0 | BC35: 0 | BE35: 173.31
B36: DISMANTLED MILD STEEL SCRAP | C36: MT | E36: 84.21 | G36: 96.54 | I36: 180.75 | K36: 18.91 | M36: 199.66 | Q36: 199.66 | U36: 199.66 | Y36: 0 | AA36: 199.66 | AE36: 199.66 | AI36: 199.66 | AM36: 0 | AO36: 199.66 | AS36: 199.66 | AW36: 199.66 | BA36: 0 | BC36: 0 | BE36: 199.66
B37: DISMANTLED ALUMINIUM CABLE | C37: MT | I37: 0 | M37: 0 | Q37: 0 | U37: 0 | Y37: 0 | AA37: 0 | AE37: 0 | AI37: 0 | AM37: 0 | AO37: 0 | AS37: 0 | AW37: 0 | BA37: 0 | BC37: 0 | BE37: 0
B38: DISMANTLED FIREBRICKS | C38: MT | I38: 0 | M38: 0 | Q38: 0 | U38: 0 | Y38: 0 | AA38: 0 | AE38: 0 | AI38: 0 | AM38: 0 | AO38: 0 | AS38: 0 | AW38: 0 | BA38: 0 | BC38: 0 | BE38: 0
B39: FIELD MACHINERY EQUIPMENT SCRAP | C39: MT | I39: 0 | M39: 0 | Q39: 0 | U39: 0 | Y39: 0 | AA39: 0 | AE39: 0 | AI39: 0 | AM39: 0 | AO39: 0 | AS39: 0 | AU39: 63.75 | AW39: 63.75 | AY39: 30.16 | BA39: 93.91 | BC39: 93.91 | BE39: 93.91
B40: DISMANTLED REFRACTORY SCRAP | C40: MT | I40: 0 | M40: 0 | Q40: 0 | U40: 0 | Y40: 0 | AA40: 0 | AE40: 0 | AI40: 0 | AM40: 0 | AO40: 0 | AS40: 0 | AW40: 0 | BA40: 0 | BC40: 0 | BE40: 0
B41: DISMANTLED RUSTED MILD STEEL SHEETS | C41: MT | E41: 9.66 | G41: 7.96 | I41: 17.62 | K41: 4.89 | M41: 22.51 | Q41: 22.51 | U41: 22.51 | Y41: 0 | AA41: 22.51 | AE41: 22.51 | AI41: 22.51 | AM41: 0 | AO41: 22.51 | AS41: 22.51 | AW41: 22.51 | BA41: 0 | BC41: 0 | BE41: 22.51
B42: DISPOSABLE MOTOR,ELE. BKR & PANELS SCRAP | C42: MT | I42: 0 | M42: 0 | Q42: 0 | U42: 0 | Y42: 0 | AA42: 0 | AE42: 0 | AI42: 0 | AM42: 0 | AO42: 0 | AS42: 0 | AW42: 0 | BA42: 0 | BC42: 0 | BE42: 0
B43: DISMANTLED RUBBER SCRAP | C43: MT | I43: 0 | M43: 0 | Q43: 0 | U43: 0 | Y43: 0 | AA43: 0 | AE43: 0 | AI43: 0 | AM43: 0 | AO43: 0 | AS43: 0 | AW43: 0 | BA43: 0 | BC43: 0 | BE43: 0
B44: FIELD MACHINERY EQUIPMENT SCRAP | C44: MT | I44: 0 | M44: 0 | Q44: 0 | U44: 0 | Y44: 0 | AA44: 0 | AM44: 0 | AS44: 0 | AW44: 0 | BA44: 0 | BC44: 0 | BE44: 0
B45: DISMANTLED CR-MO-V BASED ALLOY SCRAP | C45: MT | I45: 0 | M45: 0 | Q45: 0 | U45: 0 | Y45: 0 | AA45: 0 | AE45: 0 | AI45: 0 | AM45: 0 | AO45: 0 | AS45: 0 | AW45: 0 | BA45: 0 | BC45: 0 | BE45: 0
B46: DISMANTLED STAINLESS STEEL SCRAP | C46: MT | I46: 0 | M46: 0 | Q46: 0 | U46: 0 | Y46: 0 | AA46: 0 | AE46: 0 | AI46: 0 | AM46: 0 | AO46: 0 | AS46: 0 | AW46: 0 | BA46: 0 | BC46: 0 | BE46: 0
B47: DISMANTLED COPPER SCRAP | C47: MT | I47: 0 | M47: 0 | Q47: 0 | U47: 0 | Y47: 0 | AA47: 0 | AE47: 0 | AI47: 0 | AM47: 0 | AO47: 0 | AS47: 0 | AW47: 0 | BA47: 0 | BC47: 0 | BE47: 0
B48: IRON SCRAP | E48: 358.44 | G48: 616.32 | I48: 974.76 | K48: 167.22 | M48: 1141.98 | O48: 2152.42 | Q48: 3294.4 | S48: 4035.86 | U48: 7330.26 | W48: 595.91 | Y48: 6784.19 | AA48: 7926.17 | AC48: 1002.83 | AE48: 8929 | AG48: 198.57 | AI48: 9127.57 | AK48: 1114.75 | AM48: 2316.15 | AO48: 10242.32 | AQ48: 1017.51 | AS48: 11259.83 | AU48: 664.93 | AW48: 11924.76 | AY48: 998.41 | BA48: 2680.85 | BC48: 4997 | BE48: 12923.17
B49: CAST HOUSE DEBRIS | C49: MT | E49: 20.74 | G49: 466.15 | I49: 486.89 | M49: 486.89 | O49: 553.73 | Q49: 1040.62 | S49: 2943.31 | U49: 3983.93 | Y49: 3497.04 | AA49: 3983.93 | AC49: 998.58 | AE49: 4982.51 | AI49: 4982.51 | AK49: 816.04 | AM49: 1814.62 | AO49: 5798.55 | AQ49: 518.42 | AS49: 6316.97 | AU49: 664.93 | AW49: 6981.9 | BA49: 1183.35 | BC49: 2997.97 | BE49: 6981.9
B50: CAST IRON SCRAP | C50: MT | I50: 0 | M50: 0 | Q50: 0 | U50: 0 | Y50: 0 | AA50: 0 | AE50: 0 | AI50: 0 | AM50: 0 | AO50: 0 | AS50: 0 | AW50: 0 | BA50: 0 | BC50: 0 | BE50: 0
B51: IRON BASED SCRAPED ROLLS | C51: MT | E51: 78.35 | I51: 78.35 | M51: 78.35 | Q51: 78.35 | U51: 78.35 | W51: 96.15 | Y51: 96.15 | AA51: 174.5 | AC51: 4.25 | AE51: 178.75 | AI51: 178.75 | AM51: 4.25 | AO51: 178.75 | AS51: 178.75 | AW51: 178.75 | BA51: 0 | BC51: 4.25 | BE51: 178.75
B52: PROCESSED CI SCRAP | C52: MT | E52: 259.35 | G52: 150.17 | I52: 409.52 | K52: 167.22 | M52: 576.74 | O52: 1598.69 | Q52: 2175.43 | S52: 1092.55 | U52: 3267.98 | W52: 499.76 | Y52: 3191 | AA52: 3767.74 | AE52: 3767.74 | AG52: 198.57 | AI52: 3966.31 | AK52: 298.71 | AM52: 497.28 | AO52: 4265.02 | AQ52: 499.09 | AS52: 4764.11 | AW52: 4764.11 | AY52: 998.41 | BA52: 1497.5 | BC52: 1994.78 | BE52: 5762.52
B53: REFRACTORY | E53: 25.23 | G53: 24.76 | I53: 49.99 | K53: 61.46 | M53: 111.45 | O53: 113.46 | Q53: 224.91 | S53: 49.95 | U53: 274.86 | W53: 40.02 | Y53: 203.43 | AA53: 314.88 | AC53: 62.35 | AE53: 377.23 | AG53: 22.6 | AI53: 399.83 | AK53: 24.97 | AM53: 109.92 | AO53: 424.8 | AQ53: 49.92 | AS53: 474.72 | AU53: 76.09 | AW53: 550.81 | AY53: 48.89 | BA53: 174.9 | BC53: 284.82 | BE53: 599.7
B54: USED & REJECTED REFRACTORY SCRAPS | C54: MT | E54: 25.23 | G54: 24.76 | I54: 49.99 | M54: 49.99 | O54: 25 | Q54: 74.99 | S54: 24.99 | U54: 99.98 | Y54: 49.99 | AA54: 99.98 | AC54: 24.99 | AE54: 124.97 | AI54: 124.97 | AM54: 24.99 | AO54: 124.97 | AQ54: 24.95 | AS54: 149.92 | AW54: 149.92 | AY54: 24.98 | BA54: 49.93 | BC54: 74.92 | BE54: 174.9
B55: USED & REJ REF BK BATS-TORPEDO (W/L) | C55: MT | I55: 0 | K55: 24.88 | M55: 24.88 | Q55: 24.88 | U55: 24.88 | Y55: 0 | AA55: 24.88 | AE55: 24.88 | AI55: 24.88 | AK55: 24.97 | AM55: 24.97 | AO55: 49.85 | AS55: 49.85 | AW55: 49.85 | BA55: 0 | BC55: 24.97 | BE55: 49.85
B56: USED & REJ REF BK BATS-LDCP | C56: MT | I56: 0 | M56: 0 | Q56: 0 | U56: 0 | Y56: 0 | AA56: 0 | AE56: 0 | AI56: 0 | AM56: 0 | AO56: 0 | AQ56: 24.97 | AS56: 24.97 | AW56: 24.97 | BA56: 24.97 | BC56: 24.97 | BE56: 24.97
B57: OLD, USED & REJECTED REFRACTORY BRICKS | C57: MT | I57: 0 | K57: 36.58 | M57: 36.58 | O57: 88.46 | Q57: 125.04 | S57: 24.96 | U57: 150 | W57: 40.02 | Y57: 153.44 | AA57: 190.02 | AC57: 37.36 | AE57: 227.38 | AG57: 22.6 | AI57: 249.98 | AM57: 59.96 | AO57: 249.98 | AS57: 249.98 | AU57: 76.09 | AW57: 326.07 | AY57: 23.91 | BA57: 100 | BC57: 159.96 | BE57: 349.98
B58: STEEL SCRAP | E58: 35.86 | F58: 0 | G58: 80.57 | H58: 0 | I58: 116.43 | K58: 0 | M58: 116.43 | O58: 88.05 | Q58: 204.48 | S58: 0 | U58: 204.48 | W58: 0 | Y58: 88.05 | AA58: 204.48 | AC58: 0 | AE58: 204.48 | AG58: 0 | AI58: 204.48 | AK58: 0 | AM58: 0 | AO58: 204.48 | AQ58: 0 | AS58: 204.48 | AU58: 0 | AW58: 204.48 | AY58: 0 | BA58: 0 | BC58: 0 | BE58: 204.48
B59: USED & REJECTED MILD STEEL SCRAP | C59: MT | I59: 0 | M59: 0 | Q59: 0 | U59: 0 | Y59: 0 | AA59: 0 | AE59: 0 | AI59: 0 | AM59: 0 | AO59: 0 | AS59: 0 | AW59: 0 | BA59: 0 | BC59: 0 | BE59: 0
B60: STEEL BASED SCRAPED ROLLS | C60: MT | E60: 35.86 | G60: 80.57 | I60: 116.43 | M60: 116.43 | O60: 88.05 | Q60: 204.48 | U60: 204.48 | Y60: 88.05 | AA60: 204.48 | AE60: 204.48 | AI60: 204.48 | AM60: 0 | AO60: 204.48 | AS60: 204.48 | AW60: 204.48 | BA60: 0 | BC60: 0 | BE60: 204.48
B61: STEEL SCRAP BALED | C61: MT | I61: 0 | M61: 0 | Q61: 0 | U61: 0 | Y61: 0 | AA61: 0 | AE61: 0 | AI61: 0 | AM61: 0 | AO61: 0 | AS61: 0 | AW61: 0 | BA61: 0 | BC61: 0 | BE61: 0
B62: OLD ,U/ R STEEL MAINTENANCE SCRAP | C62: MT | I62: 0 | M62: 0 | Q62: 0 | U62: 0 | Y62: 0 | AA62: 0 | AE62: 0 | AI62: 0 | AM62: 0 | AO62: 0 | AS62: 0 | AW62: 0 | BA62: 0 | BC62: 0 | BE62: 0
B63: WRM COILS (REBAR/WR) TRIMMED END SCRAP | C63: MT | I63: 0 | M63: 0 | Q63: 0 | U63: 0 | Y63: 0 | AA63: 0 | AE63: 0 | AI63: 0 | AM63: 0 | AO63: 0 | AS63: 0 | AW63: 0 | BA63: 0 | BC63: 0 | BE63: 0
B64: END CUT PIECES & ARISINGS OF WRM & BM | C64: MT | I64: 0 | M64: 0 | Q64: 0 | U64: 0 | Y64: 0 | AA64: 0 | AE64: 0 | AI64: 0 | AM64: 0 | AO64: 0 | AS64: 0 | AW64: 0 | BA64: 0 | BC64: 0 | BE64: 0
B65: Others | E65: 1592.36 | G65: 5445.62 | I65: 7037.98 | K65: 9350.66 | M65: 16388.64 | O65: 12383.79 | Q65: 28772.43 | S65: 6940.93 | U65: 35713.36 | W65: 11508.41 | Y65: 30833.13 | AA65: 47221.77 | AC65: 4534.22 | AE65: 51755.99 | AG65: 8049.23 | AI65: 59805.22 | AK65: 3799.66 | AM65: 16383.11 | AO65: 63604.88 | AQ65: 5872.43 | AS65: 69477.31 | AU65: 5624.84 | AW65: 75102.15 | AY65: 8506.61 | BA65: 20003.88 | BC65: 36386.99 | BE65: 83608.76
B66: LIQUID ARGON | C66: MT | E66: 550.17 | G66: 500.52 | I66: 1050.69 | K66: 589.31 | M66: 1640 | O66: 523.21 | Q66: 2163.21 | S66: 424.99 | U66: 2588.2 | W66: 228.8 | Y66: 1177 | AA66: 2817 | AC66: 539.12 | AE66: 3356.12 | AG66: 287.66 | AI66: 3643.78 | AK66: 580.71 | AM66: 1407.49 | AO66: 4224.49 | AQ66: 406.42 | AS66: 4630.91 | AU66: 382.41 | AW66: 5013.32 | AY66: 744.94 | BA66: 1533.77 | BC66: 2941.26 | BE66: 5758.26
B67: SCRAP AL ARMOURED/UNARMOURED(DIFF SIZES) | C67: MT | I67: 0 | M67: 0 | Q67: 0 | U67: 0 | Y67: 0 | AA67: 0 | AE67: 0 | AI67: 0 | AM67: 0 | AO67: 0 | AS67: 0 | AW67: 0 | AY67: 1.77 | BA67: 1.77 | BC67: 1.77 | BE67: 1.77
B68: USED & REJECTED EMPTY OIL DRUMS | C68: MT | E68: 200 | I68: 200 | M68: 200 | O68: 420 | Q68: 620 | U68: 620 | Y68: 420 | AA68: 620 | AE68: 620 | AG68: 165 | AI68: 785 | AK68: 535 | AM68: 700 | AO68: 1320 | AQ68: 320 | AS68: 1640 | AW68: 1640 | AY68: 500 | BA68: 820 | BC68: 1520 | BE68: 2140
B69: SPENT REFRACTORY FINES | C69: MT | E69: 138.28 | G69: 146.59 | I69: 284.87 | M69: 284.87 | O69: 99.98 | Q69: 384.85 | S69: 84.81 | U69: 469.66 | W69: 15.15 | Y69: 199.94 | AA69: 484.81 | AC69: 62.54 | AE69: 547.35 | AG69: 37.43 | AI69: 584.78 | AK69: 29.78 | AM69: 129.75 | AO69: 614.56 | AQ69: 70.19 | AS69: 684.75 | AW69: 684.75 | AY69: 81.99 | BA69: 152.18 | BC69: 281.93 | BE69: 766.74
B70: INDUSTRIAL SAFETY SHOE | C70: MT | S70: 94 | U70: 94 | Y70: 94 | AA70: 94 | AE70: 94 | AG70: 18 | AI70: 112 | AM70: 18 | AO70: 112 | AS70: 112 | AU70: 24 | AW70: 136 | BA70: 24 | BC70: 42 | BE70: 136
B71: REFLECTIVE FLUORESCENT JACKET, ORANGE | C71: MT | S71: 211 | U71: 211 | Y71: 211 | AA71: 211 | AC71: 3 | AE71: 214 | AG71: 27 | AI71: 241 | AM71: 30 | AO71: 241 | AS71: 241 | AW71: 241 | BA71: 0 | BC71: 30 | BE71: 241
B72: SCRAP FILTER | C72: MT | S72: 558 | U72: 558 | Y72: 558 | AA72: 558 | AE72: 558 | AI72: 558 | AM72: 0 | AO72: 558 | AS72: 558 | AW72: 558 | BA72: 0 | BC72: 0 | BE72: 558
B73: CONCORD HELMET WITH RATCHET-BLUE | C73: MT | I73: 0 | M73: 0 | Q73: 0 | U73: 0 | Y73: 0 | AA73: 0 | AE73: 0 | AI73: 0 | AM73: 0 | AO73: 0 | AQ73: 796 | AS73: 796 | AU73: 259 | AW73: 1055 | BA73: 1055 | BC73: 1055 | BE73: 1055
B74: TARPOLINE COVER FOR RAILWAY WAGONS | C74: MT | I74: 0 | M74: 0 | Q74: 0 | U74: 0 | Y74: 0 | AA74: 0 | AE74: 0 | AI74: 0 | AM74: 0 | AO74: 0 | AQ74: 12.37 | AS74: 12.37 | AU74: 7.54 | AW74: 19.91 | AY74: 27.84 | BA74: 47.75 | BC74: 47.75 | BE74: 47.75
B75: BRASS SCRAP | C75: MT | G75: 7.83 | I75: 7.83 | M75: 7.83 | Q75: 7.83 | U75: 7.83 | Y75: 0 | AA75: 7.83 | AE75: 7.83 | AI75: 7.83 | AM75: 0 | AO75: 7.83 | AS75: 7.83 | AW75: 7.83 | BA75: 0 | BC75: 0 | BE75: 7.83
B76: BF ETP SLUDGE | C76: MT | E76: 488.28 | G76: 486.03 | I76: 974.31 | K76: 1975.52 | M76: 2949.83 | O76: 499.11 | Q76: 3448.94 | S76: 1497.94 | U76: 4946.88 | W76: 1350.48 | Y76: 3347.53 | AA76: 6297.36 | AC76: 146.71 | AE76: 6444.07 | AI76: 6444.07 | AK76: 467.96 | AM76: 614.67 | AO76: 6912.03 | AQ76: 529.83 | AS76: 7441.86 | AU76: 999.38 | AW76: 8441.24 | AY76: 1999.58 | BA76: 3528.79 | BC76: 4143.46 | BE76: 10440.82
B77: BOF GCP SLUDGE | C77: MT | E77: 39.92 | G77: 3948.77 | I77: 3988.69 | K77: 6679.66 | M77: 10668.35 | O77: 9326.49 | Q77: 19994.84 | U77: 19994.84 | W77: 7873.7 | Y77: 17200.19 | AA77: 27868.54 | AC77: 2125.13 | AE77: 29993.67 | AG77: 4123.4 | AI77: 34117.07 | AK77: 319.88 | AM77: 6568.41 | AO77: 34436.95 | AQ77: 555.46 | AS77: 34992.41 | AU77: 3331.72 | AW77: 38324.13 | AY77: 2160.37 | BA77: 6047.55 | BC77: 12615.96 | BE77: 40484.5
B78: LEG PROTECTION ITEMS | C78: MT | I78: 0 | M78: 0 | Q78: 0 | U78: 0 | Y78: 0 | AA78: 0 | AE78: 0 | AI78: 0 | AM78: 0 | AO78: 0 | AQ78: 51 | AS78: 51 | AW78: 51 | AY78: 21 | BA78: 72 | BC78: 72 | BE78: 72
B79: OLD, USED REJECTED OIL FILLED IN DRUMS | C79: MT | G79: 53 | I79: 53 | M79: 53 | O79: 70 | Q79: 123 | U79: 123 | W79: 152 | Y79: 222 | AA79: 275 | AE79: 275 | AI79: 275 | AM79: 0 | AO79: 275 | AS79: 275 | AW79: 275 | BA79: 0 | BC79: 0 | BE79: 275
B80: USED & REJECTED EMPTY PVC DRUMS | C80: MT | I80: 0 | M80: 0 | Q80: 0 | U80: 0 | Y80: 0 | AA80: 0 | AE80: 0 | AI80: 0 | AK80: 395 | AM80: 395 | AO80: 395 | AQ80: 520 | AS80: 915 | AW80: 915 | AY80: 136 | BA80: 656 | BC80: 1051 | BE80: 1051
B81: USED & REJECTED EMPTY GREASE DRUMS | C81: MT | E81: 120 | I81: 120 | M81: 120 | Q81: 120 | U81: 120 | Y81: 0 | AA81: 120 | AE81: 120 | AI81: 120 | AK81: 200 | AM81: 200 | AO81: 320 | AS81: 320 | AW81: 320 | BA81: 0 | BC81: 200 | BE81: 320
B82: OLD/USED & REJECTED TYRES OF MV/EQUIP. | C82: MT | I82: 0 | M82: 0 | O82: 130 | Q82: 130 | U82: 130 | Y82: 130 | AA82: 130 | AE82: 130 | AI82: 130 | AM82: 0 | AO82: 130 | AQ82: 120 | AS82: 250 | AW82: 250 | BA82: 120 | BC82: 120 | BE82: 250
B83: E-WASTE ELECTRIC./ELECTRONIC SCRAP ITEMS | C83: MT | I83: 0 | M83: 0 | Q83: 0 | U83: 0 | Y83: 0 | AA83: 0 | AE83: 0 | AG83: 1 | AI83: 1 | AM83: 1 | AO83: 1 | AS83: 1 | AU83: 1 | AW83: 2 | AY83: 1 | BA83: 2 | BC83: 3 | BE83: 3
B84: USED & REJECTED BATTERIES | C84: MT | G84: 71 | I84: 71 | M84: 71 | Q84: 71 | U84: 71 | Y84: 0 | AA84: 71 | AE84: 71 | AG84: 427 | AI84: 498 | AK84: 178 | AM84: 605 | AO84: 676 | AQ84: 185 | AS84: 861 | AW84: 861 | BA84: 185 | BC84: 790 | BE84: 861
B85: FLASH-MIXER DROSS | C85: MT | I85: 0 | M85: 0 | O85: 1129.71 | Q85: 1129.71 | S85: 3869.02 | U85: 4998.73 | W85: 1632.27 | Y85: 6631 | AA85: 6631 | AC85: 1364.84 | AE85: 7995.84 | AG85: 2002.66 | AI85: 9998.5 | AM85: 3367.5 | AO85: 9998.5 | AQ85: 1339.24 | AS85: 11337.74 | AW85: 11337.74 | AY85: 1869.27 | BA85: 3208.51 | BC85: 6576.01 | BE85: 13207.01
B86: REFLECTIVE FLUORESCENT JACKET, ORANGE,XL/M | C86: MT | I86: 0 | M86: 0 | Q86: 0 | U86: 0 | W86: 26 | Y86: 26 | AA86: 26 | AE86: 26 | AI86: 26 | AK86: 78 | AM86: 78 | AO86: 104 | AS86: 104 | AW86: 104 | BA86: 0 | BC86: 78 | BE86: 104
B87: REJECTED/BROKEN GRAPHITE ELECTRODES | C87: MT | I87: 0 | M87: 0 | Q87: 0 | U87: 0 | Y87: 0 | AA87: 0 | AE87: 0 | AG87: 6.73 | AI87: 6.73 | AM87: 6.73 | AO87: 6.73 | AS87: 6.73 | AW87: 6.73 | BA87: 0 | BC87: 6.73 | BE87: 6.73
B88: OLD, USED & REJECTED TRACTION BATTERY | C88: MT | I88: 0 | M88: 0 | Q88: 0 | U88: 0 | Y88: 0 | AA88: 0 | AE88: 0 | AI88: 0 | AK88: 160 | AM88: 160 | AO88: 160 | AS88: 160 | AW88: 160 | BA88: 0 | BC88: 160 | BE88: 160
B89: USED & REJECTED RAILS | C89: MT | I89: 0 | M89: 0 | Q89: 0 | U89: 0 | Y89: 0 | AA89: 0 | AE89: 0 | AG89: 59.66 | AI89: 59.66 | AM89: 59.66 | AO89: 59.66 | AS89: 59.66 | AW89: 59.66 | BA89: 0 | BC89: 59.66 | BE89: 59.66
B90: USED & REJECTED WOODEN PALLETS/ SLEEPER | C90: MT | E90: 12.09 | G90: 7.09 | I90: 19.18 | K90: 9.91 | M90: 29.09 | Q90: 29.09 | S90: 29.39 | U90: 58.48 | Y90: 29.39 | AA90: 58.48 | AC90: 9.82 | AE90: 68.3 | AG90: 19.89 | AI90: 88.19 | AM90: 29.71 | AO90: 88.19 | AS90: 88.19 | AW90: 88.19 | BA90: 0 | BC90: 29.71 | BE90: 88.19
B91: USED & REJECTED SLEEPER | C91: MT | E91: 16.53 | G91: 33.15 | I91: 49.68 | M91: 49.68 | Q91: 49.68 | U91: 49.68 | W91: 28.8 | Y91: 28.8 | AA91: 78.48 | AC91: 13.88 | AE91: 92.36 | AG91: 6.1 | AI91: 98.46 | AM91: 19.98 | AO91: 98.46 | AS91: 98.46 | AW91: 98.46 | BA91: 0 | BC91: 19.98 | BE91: 98.46
B92: USED & REJECTED CONVEYOR BELT (NYLON) | C92: MT | E92: 10.28 | G92: 26.9 | I92: 37.18 | K92: 81.11 | M92: 118.29 | O92: 16.29 | Q92: 134.58 | S92: 41.78 | U92: 176.36 | W92: 29.8 | Y92: 87.87 | AA92: 206.16 | AC92: 74.52 | AE92: 280.68 | AI92: 280.68 | AK92: 6.9 | AM92: 81.42 | AO92: 287.58 | AS92: 287.58 | AW92: 287.58 | AY92: 21.93 | BA92: 21.93 | BC92: 103.35 | BE92: 309.51
B93: SLAG REDUCER & CONDITIONER BRIQUETTES | C93: MT | AC93: 96.7 | AE93: 96.7 | AG93: 210.92 | AI93: 307.62 | AM93: 307.62 | AO93: 307.62 | AS93: 307.62 | AW93: 307.62 | BA93: 0 | BC93: 307.62 | BE93: 307.62
