Workbook
Name _1: #REF!
Name _1: #REF!
Name _1: #REF!
Name _1: #REF!
Name _1: #REF!
Name _1: #REF!
Name _1: #REF!
Name _1: #REF!
Name _2: #REF!
Name _2: #REF!
Name _2: #REF!
Name _2: #REF!
Name _2: #REF!
Name _2: #REF!
Name _2: #REF!
Name _2: #REF!
Name _3: #REF!
Name _3: #REF!
Name _3: #REF!
Name _3: #REF!
Name _3: #REF!
Name _3: #REF!
Name _3: #REF!
Name _4: #REF!
Name _4: #REF!
Name a: #REF!
Name a: #REF!
Name a: #REF!
Name a: #REF!
Name a: #REF!
Name AA: #REF!
Name AA: #REF!
Name AA: #REF!
Name AB: #REF!
Name AB: #REF!
Name AB: #REF!
Name AC: #REF!
Name AC: #REF!
Name AD: #REF!
Name AD: #REF!
Name AE: #REF!
Name AE: #REF!
Name AF: #REF!
Name AF: #REF!
Name AG: #REF!
Name AG: #REF!
Name AH: #REF!
Name AH: #REF!
Name AI: #REF!
Name AI: #REF!
Name AK: #REF!
Name AK: #REF!
Name AL: #REF!
Name AL: #REF!
Name AM: #REF!
Name AM: #REF!
Name AN: #REF!
Name AN: #REF!
Name AS: #REF!
Name AS: #REF!

Sheet Maj Production Summ
B1: MAJOR PRODUCTION SUMMARY | D1: 347 | E1: 29 | F1: =30-'B-FCE'!F3 -> 29.5 | G1: 25 | H1: =27-'B-FCE'!H3 -> 26.791667 | I1: =E1+G1 -> 54 | J1: =F1+H1 -> 56.291667 | K1: 27 | L1: =26-'B-FCE'!L3 -> 24.708333 | M1: =+E1+G1+K1 -> 81 | N1: =+F1+H1+L1 -> 81 | O1: 30 | P1: =31-'B-FCE'!P3 -> 30.5 | Q1: =+M1+O1 -> 111 | R1: =+N1+P1 -> 111.5 | S1: 30 | T1: =31-'B-FCE'!T3 -> 31 | U1: =+Q1+S1 -> 141 | V1: =+R1+T1 -> 142.5 | W1: 29 | X1: =30-'B-FCE'!X3 -> 28.458333 | Y1: =+O1+S1+W1 -> 89 | Z1: =+P1+T1+X1 -> 89.958333 | AA1: =+U1+W1 -> 170 | AB1: =+V1+X1 -> 170.95833 | AC1: 30 | AD1: =31-'B-FCE'!AD3 -> 30.5 | AE1: =AA1+AC1 -> 200 | AF1: =AB1+AD1 -> 201.45833 | AG1: 29 | AH1: =30-'B-FCE'!AH3 -> 29 | AI1: =AE1+AG1 -> 229 | AJ1: =AF1+AH1 -> 230.45833 | AK1: 30 | AL1: =31-'B-FCE'!AL3 -> 30.541667 | AM1: =+AC1+AG1+AK1 -> 89 | AN1: =+AD1+AH1+AL1 -> 90.041667 | AO1: =AI1+AK1 -> 259 | AP1: =AJ1+AL1 -> 261 | AQ1: 30 | AR1: =30-'B-FCE'!AR3 -> 30 | AS1: =AO1+AQ1 -> 289 | AT1: =AP1+AR1 -> 291 | AU1: 28 | AV1: =29-'B-FCE'!AV3 -> 29 | AW1: =AS1+AU1 -> 317 | AX1: =AT1+AV1 -> 320 | AY1: 30 | AZ1: =31-'B-FCE'!AZ3 -> 29.779167 | BA1: =+AQ1+AU1+AY1 -> 88 | BB1: =+AR1+AV1+AZ1 -> 88.779167 | BC1: =+AM1+BA1 -> 177 | BD1: =+AN1+BB1 -> 178.82083 | BE1: =AW1+AY1 -> 347 | BF1: =AX1+AZ1 -> 349.77917
D2: 366 | E2: 30 | F2: 30 | G2: 31 | H2: 31 | I2: =+E2+G2 -> 61 | J2: =+F2+H2 -> 61 | K2: 30 | L2: 30 | M2: =+I2+K2 -> 91 | N2: =+J2+L2 -> 91 | O2: 31 | P2: 31 | Q2: =+M2+O2 -> 122 | R2: =+N2+P2 -> 122 | S2: 31 | T2: 31 | U2: =+Q2+S2 -> 153 | V2: =+R2+T2 -> 153 | W2: 30 | X2: 30 | Y2: =+O2+S2+W2 -> 92 | Z2: =+P2+T2+X2 -> 92 | AA2: =+U2+W2 -> 183 | AB2: =+V2+X2 -> 183 | AC2: 31 | AD2: 31 | AE2: =AA2+AC2 -> 214 | AF2: =AB2+AD2 -> 214 | AG2: 30 | AH2: 30 | AI2: =AE2+AG2 -> 244 | AJ2: =AF2+AH2 -> 244 | AK2: 31 | AL2: 31 | AM2: =+AC2+AG2+AK2 -> 92 | AN2: =+AD2+AH2+AL2 -> 92 | AO2: =AI2+AK2 -> 275 | AP2: =AJ2+AL2 -> 275 | AQ2: 31 | AR2: 31 | AS2: =AO2+AQ2 -> 306 | AT2: =AP2+AR2 -> 306 | AU2: 29 | AV2: 29 | AW2: =AS2+AU2 -> 335 | AX2: =AT2+AV2 -> 335 | AY2: 31 | AZ2: 31 | BA2: =+AQ2+AU2+AY2 -> 91 | BB2: =+AR2+AV2+AZ2 -> 91 | BC2: =+AM2+BA2 -> 183 | BD2: =+AN2+BB2 -> 183 | BE2: =AW2+AY2 -> 366 | BF2: =AX2+AZ2 -> 366 | BK2: 365 | BL2: 365 | BM2: 366 | BN2: 366
B3: ITEM | C3: Unit | D3: 2023-24 ABP | E3: Apr'23 | G3: May'23 | I3: 2M | K3: Jun'23 | M3: QTR-1 | O3: Jul'23 | Q3: 4M | S3: Aug'23 | U3: 5M | W3: Sep'23 | Y3: QTR 2 | AA3: H1 | AC3: Oct'23 | AE3: 7M | AG3: Nov'23 | AI3: 8M | AK3: Dec'23 | AM3: QTR 3 | AO3: 9M | AQ3: Jan'24 | AS3: 10M | AU3: Feb'24 | AW3: 11M | AY3: Mar'24 | BA3: QTR 4 | BC3: H2 | BE3: 2023-24 | BG3: 2022-23 | BI3: 2021-22 | BK3: 2020-21 | BM3: 2019-20
E4: ABP | F4: ACT | G4: ABP | H4: ACT | I4: ABP | J4: ACT | K4: ABP | L4: ACT | M4: ABP | N4: ACT | O4: ABP | P4: ACT | Q4: ABP | R4: ACT | S4: ABP | T4: ACT | U4: ABP | V4: ACT | W4: ABP | X4: ACT | Y4: ABP | Z4: ACT | AA4: ABP | AB4: ACT | AC4: ABP | AD4: ACT | AE4: ABP | AF4: ACT | AG4: ABP | AH4: ACT | AI4: ABP | AJ4: ACT | AK4: ABP | AL4: ACT | AM4: ABP | AN4: ACT | AO4: ABP | AP4: ACT | AQ4: ABP | AR4: ACT | AS4: ABP | AT4: ACT | AU4: ABP | AV4: ACT | AW4: ABP | AX4: ACT | AY4: ABP | AZ4: ACT | BA4: ABP | BB4: ACT | BC4: ABP | BD4: ACT | BE4: ABP | BF4: ACT | BG4: ABP | BH4: ACT | BI4: ABP | BJ4: ACT | BK4: ABP | BL4: ACT | BM4: ABP | BN4: ACT
B5: COKE OVENS PUSHING
B6: (COB#10) | C6: Nos/ day | D6: 99 | E6: 99 | F6: =+F9/F2 -> 99.133333 | G6: 99 | H6: =+H9/H2 -> 99.096774 | I6: =+((E6*$E$2)+(G6*$G$2))/$I$2 -> 99 | J6: =+((F6*$F$2)+(H6*$H$2))/$J$2 -> 99.114754 | K6: 99 | L6: =+L9/L2 -> 99.133333 | M6: =+((E6*$E$2)+(G6*$G$2)+(K6*$K$2))/$M$2 -> 99 | N6: =+((F6*$F$2)+(H6*$H$2)+(L6*$L$2))/$N$2 -> 99.120879 | O6: 99 | P6: =+P9/P2 -> 99.064516 | Q6: =+((M6*M$2)+(O6*O$2))/Q$2 -> 99 | R6: =+((N6*N$2)+(P6*P$2))/R$2 -> 99.106557 | S6: 99 | T6: =+T9/T2 -> 99.451613 | U6: =+((Q6*Q$2)+(S6*S$2))/U$2 -> 99 | V6: =+((R6*R$2)+(T6*T$2))/V$2 -> 99.176471 | W6: 99 | X6: =X9/X2 -> 99.1 | Y6: =+((O$6*O$1)+(S$6*S$1)+(W$6*W$1))/Y$1 -> 99 | Z6: =+((P$6*P$1)+(T$6*T$1)+(X$6*X$1))/Z$1 -> 99.209137 | AA6: =+((M6*M$2)+(Y6*Y$2))/AA$2 -> 99 | AB6: =+((N6*N$2)+(Z6*Z$2))/AB$2 -> 99.165249 | AC6: 99 | AD6: =+AD9/AD2 -> 97.677419 | AE6: =+((AA6*$AA$2)+(AC6*$AC$2))/$AE$2 -> 99 | AF6: =+((AB6*$AB$2)+(AD6*$AD$2))/$AF$2 -> 98.949722 | AG6: 99 | AH6: =+AH9/AH2 -> 99 | AI6: =+((AE6*$AE$2)+(AG6*$AG$2))/$AI$2 -> 99 | AJ6: =+((AF6*$AF$2)+(AH6*$AH$2))/$AJ$2 -> 98.955904 | AK6: 99 | AL6: =AL9/AL2 -> 99 | AM6: =+((AC$6*AC$1)+(AG$6*AG$1)+(AK$6*AK$1))/AM$1 -> 99 | AN6: =+((AD$6*AD$1)+(AH$6*AH$1)+(AL$6*AL$1))/AN$1 -> 98.552 | AO6: =+((AK6*$AK$2)+(AI6*$AI$2))/$AO$2 -> 99 | AP6: =+((AL6*$AL$2)+(AJ6*$AJ$2))/$AP$2 -> 98.960875 | AQ6: 99 | AR6: =+AR9/AR2 -> 99 | AS6: =+((AO6*$AO$2)+(AQ6*$AQ$2))/$AS$2 -> 99 | AT6: =+((AP6*$AP$2)+(AR6*$AR$2))/$AT$2 -> 98.964838 | AU6: 99 | AV6: =+AV9/AV2 -> 99 | AW6: =+((AS6*$AS$2)+(AU6*$AU$2))/$AW$2 -> 99 | AX6: =+((AT6*$AT$2)+(AV6*$AV$2))/$AX$2 -> 98.967882 | AY6: 99 | AZ6: =+AZ9/AZ2 -> 99.064516 | BA6: =+((AQ$6*AQ$1)+(AU$6*AU$1)+(AY$6*AY$1))/BA$1 -> 99 | BB6: =+((AR$6*AR$1)+(AV$6*AV$1)+(AZ$6*AZ$1))/BB$1 -> 99.021641 | BC6: =+((AM6*AM$2)+(BA6*BA$2))/BC$2 -> 99 | BD6: =+((AN6*AN$2)+(BB6*BB$2))/BD$2 -> 98.785537 | BE6: =+((AW6*$AW$2)+(AY6*$AY$2))/$BE$2 -> 99 | BF6: =+((AZ6*$AZ$2)+(AX6*$AX$2))/$BF$2 -> 98.976067 | BG6: 99 | BH6: 98.783562 | BI6: 99 | BJ6: 97.824658 | BK6: 95.547945 | BL6: 95.342466 | BM6: 97 | BN6: 97.10959
B7: (COB#11) | C7: Nos/ day | D7: 98 | E7: 98.333333 | F7: =+F10/F2 -> 97.8 | G7: 98.333333 | H7: =+H10/H2 -> 91.741935 | I7: =+((E7*$E$2)+(G7*$G$2))/$I$2 -> 98.333333 | J7: =+((F7*$F$2)+(H7*$H$2))/$J$2 -> 94.721311 | K7: 98.333333 | L7: =+L10/L2 -> 93.766667 | M7: =+((E7*$E$2)+(G7*$G$2)+(K7*$K$2))/$M$2 -> 98.333333 | N7: =+((F7*$F$2)+(H7*$H$2)+(L7*$L$2))/$N$2 -> 94.406593 | O7: 98.333333 | P7: =+P10/P2 -> 95.645161 | Q7: =+((M7*M$2)+(O7*O$2))/Q$2 -> 98.333333 | R7: =+((N7*N$2)+(P7*P$2))/R$2 -> 94.721311 | S7: 96.333333 | T7: =+T10/T2 -> 95.16129 | U7: =+((Q7*Q$2)+(S7*S$2))/U$2 -> 97.928105 | V7: =+((R7*R$2)+(T7*T$2))/V$2 -> 94.810458 | W7: 96.333333 | X7: =X10/X2 -> 96.033333 | Y7: =+((O$7*O$1)+(S$7*S$1)+(W$7*W$1))/Y$1 -> 97.007491 | Z7: =+((P$7*P$1)+(T$7*T$1)+(X$7*X$1))/Z$1 -> 95.601216 | AA7: =+((M7*M$2)+(Y7*Y$2))/AA$2 -> 97.666789 | AB7: =+((N7*N$2)+(Z7*Z$2))/AB$2 -> 95.007169 | AC7: 98.333333 | AD7: =+AD10/AD2 -> 97.806452 | AE7: =+((AA7*$AA$2)+(AC7*$AC$2))/$AE$2 -> 97.763345 | AF7: =+((AB7*$AB$2)+(AD7*$AD$2))/$AF$2 -> 95.412672 | AG7: 98.333333 | AH7: =+AH10/AH2 -> 97.333333 | AI7: =+((AE7*$AE$2)+(AG7*$AG$2))/$AI$2 -> 97.833425 | AJ7: =+((AF7*$AF$2)+(AH7*$AH$2))/$AJ$2 -> 95.648819 | AK7: 98.333333 | AL7: =AL10/AL2 -> 98.83871 | AM7: =+((AC$7*AC$1)+(AG$7*AG$1)+(AK$7*AK$1))/AM$1 -> 98.333333 | AN7: =+((AD$7*AD$1)+(AH$7*AH$1)+(AL$7*AL$1))/AN$1 -> 98.00421 | AO7: =+((AK7*$AK$2)+(AI7*$AI$2))/$AO$2 -> 97.889779 | AP7: =+((AL7*$AL$2)+(AJ7*$AJ$2))/$AP$2 -> 96.008407 | AQ7: 98.333333 | AR7: =+AR10/AR2 -> 98.612903 | AS7: =+((AO7*$AO$2)+(AQ7*$AQ$2))/$AS$2 -> 97.934714 | AT7: =+((AP7*$AP$2)+(AR7*$AR$2))/$AT$2 -> 96.272261 | AU7: 98.333333 | AV7: =+AV10/AV2 -> 98.758621 | AW7: =+((AS7*$AS$2)+(AU7*$AU$2))/$AW$2 -> 97.969221 | AX7: =+((AT7*$AT$2)+(AV7*$AV$2))/$AX$2 -> 96.487498 | AY7: 98.333333 | AZ7: =+AZ10/AZ2 -> 98.645161 | BA7: =+((AQ$7*AQ$1)+(AU$7*AU$1)+(AY$7*AY$1))/BA$1 -> 98.333333 | BB7: =+((AR$7*AR$1)+(AV$7*AV$1)+(AZ$7*AZ$1))/BB$1 -> 98.671323 | BC7: =+((AM7*AM$2)+(BA7*BA$2))/BC$2 -> 98.333333 | BD7: =+((AN7*AN$2)+(BB7*BB$2))/BD$2 -> 98.335943 | BE7: =+((AW7*$AW$2)+(AY7*$AY$2))/$BE$2 -> 98.000061 | BF7: =+((AZ7*$AZ$2)+(AX7*$AX$2))/$BF$2 -> 96.670251 | BG7: 99 | BH7: 92.210959 | BI7: 99 | BJ7: 96.816438 | BK7: 94.2 | BL7: 90.778082 | BM7: 97 | BN7: 95.710246
B8: Overall Equiv. Ovens Pushed/ Day | C8: Nos/ day | D8: =+D6+(D7*(31.55/17.2)) -> 278.76163 | E8: =+E6+(E7*(31.55/17.2)) -> 279.37306 | F8: =+F6+(F7*(31.55/17.2)) -> 278.5281 | G8: =+G6+(G7*(31.55/17.2)) -> 279.37306 | H8: =+H6+(H7*(31.55/17.2)) -> 267.37922 | I8: =+I6+(I7*(31.55/17.2)) -> 279.37306 | J8: =+J6+(J7*(31.55/17.2)) -> 272.86228 | K8: =+K6+(K7*(31.55/17.2)) -> 279.37306 | ... X8: =+X6+(X7*(31.55/17.2)) -> 275.25417 | Y8: =Y6+(Y7*31.55/17.2) -> 276.94107 | Z8: =Z6+(Z7*31.55/17.2) -> 274.57067 | AA8: =AA6+(AA7*31.55/17.2) -> 278.15042 | AB8: =AB6+(AB7*31.55/17.2) -> 273.43712 | AC8: =+AC6+(AC7*(31.55/17.2)) -> 279.37306 | AD8: =+AD6+(AD7*(31.55/17.2)) -> 277.08402 | AE8: =+AE6+(AE7*(31.55/17.2)) -> 278.32753 | AF8: =+AF6+(AF7*(31.55/17.2)) -> 273.96541 | AG8: =+AG6+(AG7*(31.55/17.2)) -> 279.37306 | AH8: =+AH6+(AH7*(31.55/17.2)) -> 277.53876 | AI8: =+AI6+(AI7*(31.55/17.2)) -> 278.45608 | AJ8: =+AJ6+(AJ7*(31.55/17.2)) -> 274.40476 | ... AL8: =+AL6+(AL7*(31.55/17.2)) -> 280.30008 | AM8: =AM6+(AM7*31.55/17.2) -> 279.37306 | AN8: =AN6+(AN7*31.55/17.2) -> 278.32135 | AO8: =+AO6+(AO7*(31.55/17.2)) -> 278.55945 | AP8: =+AP6+(AP7*(31.55/17.2)) -> 275.06932 | AQ8: =+AQ6+(AQ7*(31.55/17.2)) -> 279.37306 | AR8: =+AR6+(AR7*(31.55/17.2)) -> 279.88588 | AS8: =+AS6+(AS7*(31.55/17.2)) -> 278.64187 | AT8: =+AT6+(AT7*(31.55/17.2)) -> 275.55727 | AU8: =+AU6+(AU7*(31.55/17.2)) -> 279.37306 | AV8: =+AV6+(AV7*(31.55/17.2)) -> 280.15317 | ... AZ8: =+AZ6+(AZ7*(31.55/17.2)) -> 280.00956 | BA8: =BA6+(BA7*31.55/17.2) -> 279.37306 | BB8: =BB6+(BB7*31.55/17.2) -> 280.01468 | BC8: =BC6+(BC7*31.55/17.2) -> 279.37306 | BD8: =BD6+(BD7*31.55/17.2) -> 279.16339 | BE8: =+BE6+(BE7*(31.55/17.2)) -> 278.76174 | BF8: =+BF6+(BF7*(31.55/17.2)) -> 276.29853 | BG8: 280.59593 | BH8: 267.92634 | BI8: 280.59593 | BJ8: 275.41528 | BK8: 268.33922 | BL8: 261.85691 | BM8: 274.92733 | BN8: 272.67112
B9: (COB#10) | C9: Nos | D9: =+D6*D2 -> 36234 | E9: =+E6*E2 -> 2970 | F9: 2974 | G9: =+G6*G2 -> 3069 | H9: 3072 | I9: =+I6*I2 -> 6039 | J9: =+F9+H9 -> 6046 | K9: =+K6*K2 -> 2970 | L9: 2974 | M9: =+E9+G9+K9 -> 9009 | N9: =+F9+H9+L9 -> 9020 | O9: =+O6*O2 -> 3069 | P9: 3071 | Q9: =+M9+O9 -> 12078 | R9: =+N9+P9 -> 12091 | S9: =+S6*S2 -> 3069 | T9: 3083 | U9: =+Q9+S9 -> 15147 | V9: =+R9+T9 -> 15174 | W9: =+W6*W2 -> 2970 | X9: 2973 | Y9: =+O9+S9+W9 -> 9108 | Z9: =+P9+T9+X9 -> 9127 | AA9: =M9+Y9 -> 18117 | AB9: =+N9+Z9 -> 18147 | AC9: =+AC6*AC2 -> 3069 | AD9: 3028 | AE9: =+AE6*AE2 -> 21186 | AF9: =+AB9+AD9 -> 21175 | AG9: =+AG6*AG2 -> 2970 | AH9: 2970 | AI9: =+AI6*AI2 -> 24156 | AJ9: =+AF9+AH9 -> 24145 | AK9: =+AK6*AK2 -> 3069 | AL9: 3069 | AM9: =+AC9+AG9+AK9 -> 9108 | AN9: =+AD9+AH9+AL9 -> 9067 | AO9: =AI9+AK9 -> 27225 | AP9: =AJ9+AL9 -> 27214 | AQ9: =+AQ6*AQ2 -> 3069 | AR9: 3069 | AS9: =+AS6*AS2 -> 30294 | AT9: =+AP9+AR9 -> 30283 | AU9: =+AU6*AU2 -> 2871 | AV9: 2871 | AW9: =+AW6*AW2 -> 33165 | AX9: =+AT9+AV9 -> 33154 | AY9: =+AY6*AY2 -> 3069 | AZ9: 3071 | BA9: =+AQ9+AU9+AY9 -> 9009 | BB9: =+AR9+AV9+AZ9 -> 9011 | BC9: =AM9+BA9 -> 18117 | BD9: =AN9+BB9 -> 18078 | BE9: =AW9+AY9 -> 36234 | BF9: =AX9+AZ9 -> 36225 | BG9: 36135 | BH9: 36056 | BI9: 36135 | BJ9: 35706 | BK9: 34875 | BL9: 34800 | BM9: 35502 | BN9: 35543
B10: (COB#11) | C10: Nos | D10: =+D7*D2 -> 35868 | E10: =+E7*E2 -> 2950 | F10: 2934 | G10: =+G7*G2 -> 3048.3333 | H10: 2844 | I10: =+I7*I2 -> 5998.3333 | J10: =+F10+H10 -> 5778 | K10: =+K7*K2 -> 2950 | L10: 2813 | M10: =+E10+G10+K10 -> 8948.3333 | N10: =+F10+H10+L10 -> 8591 | O10: =+O7*O2 -> 3048.3333 | P10: 2965 | Q10: =+M10+O10 -> 11996.667 | R10: =+N10+P10 -> 11556 | S10: =+S7*S2 -> 2986.3333 | T10: 2950 | U10: =+Q10+S10 -> 14983 | V10: =+R10+T10 -> 14506 | W10: =+W7*W2 -> 2890 | X10: 2881 | Y10: =+O10+S10+W10 -> 8924.6667 | Z10: =+P10+T10+X10 -> 8796 | AA10: =+M10+Y10 -> 17873 | AB10: =+N10+Z10 -> 17387 | AC10: =+AC7*AC2 -> 3048.3333 | AD10: 3032 | AE10: =+AE7*AE2 -> 20921.356 | AF10: =+AB10+AD10 -> 20419 | AG10: =+AG7*AG2 -> 2950 | AH10: 2920 | AI10: =+AI7*AI2 -> 23871.356 | AJ10: =+AF10+AH10 -> 23339 | AK10: =+AK7*AK2 -> 3048.3333 | AL10: 3064 | AM10: =+AC10+AG10+AK10 -> 9046.6667 | AN10: =+AD10+AH10+AL10 -> 9016 | AO10: =AI10+AK10 -> 26919.689 | AP10: =AJ10+AL10 -> 26403 | AQ10: =+AQ7*AQ2 -> 3048.3333 | AR10: 3057 | AS10: =+AS7*AS2 -> 29968.022 | AT10: =+AP10+AR10 -> 29460 | AU10: =+AU7*AU2 -> 2851.6667 | AV10: 2864 | AW10: =+AW7*AW2 -> 32819.689 | AX10: =+AT10+AV10 -> 32324 | AY10: =+AY7*AY2 -> 3048.3333 | AZ10: 3058 | BA10: =+AQ10+AU10+AY10 -> 8948.3333 | BB10: =+AR10+AV10+AZ10 -> 8979 | BC10: =AM10+BA10 -> 17995 | BD10: =AN10+BB10 -> 17995 | BE10: =AW10+AY10 -> 35868.022 | BF10: =AX10+AZ10 -> 35382 | BG10: 36135 | BH10: 33657 | BI10: 36135 | BJ10: 35338 | BK10: 34383 | BL10: 33134 | BM10: 35502 | BN10: 35030
B11: Overall Equiv. Ovens Pushed | C11: Nos | D11: =+D9+(D10*(31.55/17.2)) -> 102026.76 | E11: =+E9+(E10*(31.55/17.2)) -> 8381.1919 | F11: =+F9+(F10*(31.55/17.2)) -> 8355.843 | G11: =+G9+(G10*(31.55/17.2)) -> 8660.5649 | H11: =+H9+(H10*(31.55/17.2)) -> 8288.7558 | I11: =+I9+(I10*(31.55/17.2)) -> 17041.757 | J11: =+J9+(J10*(31.55/17.2)) -> 16644.599 | K11: =+K9+(K10*(31.55/17.2)) -> 8381.1919 | ... X11: =+X9+(X10*(31.55/17.2)) -> 8257.625 | Y11: =Y9+(Y10*31.55/17.2) -> 25478.537 | Z11: =Z9+(Z10*31.55/17.2) -> 25261.523 | AA11: =AA9+(AA10*31.55/17.2) -> 50901.485 | AB11: =AB9+(AB10*31.55/17.2) -> 50040.015 | AC11: =+AC9+(AC10*(31.55/17.2)) -> 8660.5649 | AD11: =+AD9+(AD10*(31.55/17.2)) -> 8589.6047 | AE11: =+AE9+(AE10*(31.55/17.2)) -> 59562.092 | AF11: =+AF9+(AF10*(31.55/17.2)) -> 58629.619 | AG11: =+AG9+(AG10*(31.55/17.2)) -> 8381.1919 | AH11: =+AH9+(AH10*(31.55/17.2)) -> 8326.1628 | AI11: =+AI9+(AI10*(31.55/17.2)) -> 67943.283 | AJ11: =+AJ9+(AJ10*(31.55/17.2)) -> 66955.782 | ... AL11: =+AL9+(AL10*(31.55/17.2)) -> 8689.3023 | AM11: =AM9+(AM10*31.55/17.2) -> 25702.322 | AN11: =AN9+(AN10*31.55/17.2) -> 25605.07 | AO11: =+AO9+(AO10*(31.55/17.2)) -> 76603.848 | AP11: =+AP9+(AP10*(31.55/17.2)) -> 75645.084 | AQ11: =+AQ9+(AQ10*(31.55/17.2)) -> 8660.5649 | AR11: =+AR9+(AR10*(31.55/17.2)) -> 8676.4622 | AS11: =+AS9+(AS10*(31.55/17.2)) -> 85264.413 | AT11: =+AT9+(AT10*(31.55/17.2)) -> 84321.547 | AU11: =+AU9+(AU10*(31.55/17.2)) -> 8101.8188 | AV11: =+AV9+(AV10*(31.55/17.2)) -> 8124.4419 | ... AZ11: =+AZ9+(AZ10*(31.55/17.2)) -> 8680.2965 | BA11: =BA9+(BA10*31.55/17.2) -> 25422.949 | BB11: =BB9+(BB10*31.55/17.2) -> 25481.201 | BC11: =BC9+(BC10*31.55/17.2) -> 51125.27 | BD11: =BD9+(BD10*31.55/17.2) -> 51086.27 | BE11: =+BE9+(BE10*(31.55/17.2)) -> 102026.8 | BF11: =+BF9+(BF10*(31.55/17.2)) -> 101126.28 | BG11: 102417.51 | BH11: 97793.113 | BI11: 102417.51 | BJ11: 100526.58 | BK11: 97943.817 | BL11: 95577.773 | BM11: 100623.4 | BN11: 99798.61
B12: BF COKE
B13: COB#10 | C13: Mt | D13: =+D9*0.695*17.2 -> 433141.24 | E13: =+E9*0.695*17.2 -> 35503.38 | F13: ='COKE OVENS'!F17 -> 35508.019 | G13: =+G9*0.695*17.2 -> 36686.826 | H13: ='COKE OVENS'!H17 -> 36403.897 | I13: =+E13+G13 -> 72190.206 | J13: =+F13+H13 -> 71911.915 | K13: =+K9*0.695*17.2 -> 35503.38 | L13: ='COKE OVENS'!L17 -> 35495.568 | M13: =+E13+G13+K13 -> 107693.59 | N13: =+F13+H13+L13 -> 107407.48 | O13: =+O9*0.695*17.2 -> 36686.826 | P13: ='COKE OVENS'!P17 -> 36666.024 | Q13: =+M13+O13 -> 144380.41 | R13: =+N13+P13 -> 144073.51 | S13: =+S9*0.695*17.2 -> 36686.826 | T13: ='COKE OVENS'!T17 -> 36801.599 | U13: =+Q13+S13 -> 181067.24 | V13: =+R13+T13 -> 180875.11 | W13: =+W9*0.695*17.2 -> 35503.38 | X13: ='COKE OVENS'!X17 -> 35479.971 | Y13: =+O13+S13+W13 -> 108877.03 | Z13: =+P13+T13+X13 -> 108947.59 | AA13: =+M13+Y13 -> 216570.62 | AB13: =+N13+Z13 -> 216355.08 | AC13: =+AC9*0.695*17.2 -> 36686.826 | AD13: ='COKE OVENS'!AD17 -> 36145.99 | AE13: =+AA13+AC13 -> 253257.44 | AF13: =+AB13+AD13 -> 252501.07 | AG13: =+AG9*0.695*17.2 -> 35503.38 | AH13: ='COKE OVENS'!AH17 -> 35697.791 | AI13: =+AE13+AG13 -> 288760.82 | AJ13: =+AF13+AH13 -> 288198.86 | AK13: =+AK9*0.695*17.2 -> 36686.826 | AL13: ='COKE OVENS'!AL17 -> 36631.214 | AM13: =+AC13+AG13+AK13 -> 108877.03 | AN13: =+AD13+AH13+AL13 -> 108475 | AO13: =AI13+AK13 -> 325447.65 | AP13: =AJ13+AL13 -> 324830.07 | AQ13: =+AQ9*0.695*17.2 -> 36686.826 | AR13: ='COKE OVENS'!AR17 -> 36627.85 | AS13: =+AO13+AQ13 -> 362134.48 | AT13: =+AP13+AR13 -> 361457.92 | AU13: =+AU9*0.695*17.2 -> 34319.934 | AV13: ='COKE OVENS'!AV17 -> 34268.545 | AW13: =+AS13+AU13 -> 396454.41 | AX13: =+AT13+AV13 -> 395726.47 | AY13: =+AY9*0.695*17.2 -> 36686.826 | AZ13: ='COKE OVENS'!AZ17 -> 36656.379 | BA13: =+AQ13+AU13+AY13 -> 107693.59 | BB13: =+AR13+AV13+AZ13 -> 107552.77 | BC13: =AM13+BA13 -> 216570.62 | BD13: =AN13+BB13 -> 216027.77 | BE13: =AW13+AY13 -> 433141.24 | BF13: =AX13+AZ13 -> 432382.85 | BG13: 431957.79 | BH13: 430769.03 | BI13: 438172.79 | BJ13: 428806 | BK13: 425506 | BL13: 430922.2 | BM13: 406071.88 | BN13: 412610.14
B14: COB#11 | C14: Mt | D14: =+D10*0.695*31.55 -> 786486.6 | E14: =+E10*31.55*0.695 -> 64685.387 | F14: ='COKE OVENS'!F18 -> 64256.416 | G14: =+G10*31.55*0.695 -> 66841.567 | H14: ='COKE OVENS'!H18 -> 61819.739 | I14: =+E14+G14 -> 131526.95 | J14: =+F14+H14 -> 126076.16 | K14: =+K10*31.55*0.695 -> 64685.387 | L14: ='COKE OVENS'!L18 -> 61584.84 | M14: =+E14+G14+K14 -> 196212.34 | N14: =+F14+H14+L14 -> 187661 | O14: =+O10*31.55*0.695 -> 66841.567 | P14: ='COKE OVENS'!P18 -> 64935.116 | Q14: =+M14+O14 -> 263053.91 | R14: =+N14+P14 -> 252596.11 | S14: =+S10*31.55*0.695 -> 65482.078 | T14: ='COKE OVENS'!T18 -> 64593.095 | U14: =+Q14+S14 -> 328535.99 | V14: =+R14+T14 -> 317189.21 | W14: =+W10*31.55*0.695 -> 63369.752 | X14: ='COKE OVENS'!X18 -> 63067.05 | Y14: =+O14+S14+W14 -> 195693.4 | Z14: =+P14+T14+X14 -> 192595.26 | AA14: =+M14+Y14 -> 391905.74 | AB14: =+N14+Z14 -> 380256.26 | AC14: =+AC10*31.55*0.695 -> 66841.567 | AD14: ='COKE OVENS'!AD18 -> 66390.26 | AE14: =+AA14+AC14 -> 458747.31 | AF14: =+AB14+AD14 -> 446646.52 | AG14: =+AG10*31.55*0.695 -> 64685.387 | AH14: ='COKE OVENS'!AH18 -> 64378.175 | AI14: =+AE14+AG14 -> 523432.69 | AJ14: =+AF14+AH14 -> 511024.69 | AK14: =+AK10*31.55*0.695 -> 66841.567 | AL14: ='COKE OVENS'!AL18 -> 67083.252 | AM14: =+AC14+AG14+AK14 -> 198368.52 | AN14: =+AD14+AH14+AL14 -> 197851.69 | AO14: =AI14+AK14 -> 590274.26 | AP14: =AJ14+AL14 -> 578107.94 | AQ14: =+AQ10*31.55*0.695 -> 66841.567 | AR14: ='COKE OVENS'!AR18 -> 66923.846 | AS14: =+AO14+AQ14 -> 657115.83 | AT14: =+AP14+AR14 -> 645031.79 | AU14: =+AU10*31.55*0.695 -> 62529.208 | AV14: ='COKE OVENS'!AV18 -> 62705.61 | AW14: =+AS14+AU14 -> 719645.04 | AX14: =+AT14+AV14 -> 707737.4 | AY14: =+AY10*31.55*0.695 -> 66841.567 | AZ14: ='COKE OVENS'!AZ18 -> 66954.249 | BA14: =+AQ14+AU14+AY14 -> 196212.34 | BB14: =+AR14+AV14+AZ14 -> 196583.71 | BC14: =AM14+BA14 -> 394580.86 | BD14: =AN14+BB14 -> 394435.39 | BE14: =AW14+AY14 -> 786486.6 | BF14: =AX14+AZ14 -> 774691.65 | BG14: 792341.18 | BH14: 737579.38 | BI14: 803741.8 | BJ14: 778192 | BK14: 770203 | BL14: 752591.4 | BM14: 744858.59 | BN14: 745859.84
B15: Total BF COKE | C15: Mt | D15: =SUM(D13:D14) -> 1219627.8 | E15: =SUM(E13:E14) -> 100188.77 | F15: =SUM(F13:F14) -> 99764.435 | G15: =SUM(G13:G14) -> 103528.39 | H15: =SUM(H13:H14) -> 98223.636 | I15: =SUM(I13:I14) -> 203717.16 | J15: =SUM(J13:J14) -> 197988.07 | K15: =SUM(K13:K14) -> 100188.77 | ... BF15: =SUM(BF13:BF14) -> 1207074.5 | BG15: 1224299 | BH15: 1168348.4 | BI15: 1241914.6 | BJ15: 1206998 | BK15: 1195709 | BL15: 1183513.6 | BM15: 1150930.5 | BN15: 1158470
B16: SINTER | C16: Mt | D16: =4499.99991230893*1000 -> 4499999.9 | E16: =377.584105466039*1000 -> 377584.11 | F16: 384170 | G16: =306.849799901736*1000 -> 306849.8 | H16: 311568 | I16: =+E16+G16 -> 684433.91 | J16: =+F16+H16 -> 695738 | K16: =312.959344062177*1000 -> 312959.34 | L16: 329870 | M16: =+E16+G16+K16 -> 997393.25 | N16: =+F16+H16+L16 -> 1025608 | O16: =386.18051358637*1000 -> 386180.51 | P16: 386985 | Q16: =+M16+O16 -> 1383573.8 | R16: =+N16+P16 -> 1412593 | S16: 386180.51 | T16: 373273 | U16: =+Q16+S16 -> 1769754.3 | V16: =+R16+T16 -> 1785866 | W16: 375455.56 | X16: 373826 | Y16: =+O16+S16+W16 -> 1147816.6 | Z16: =+P16+T16+X16 -> 1134084 | AA16: =+M16+Y16 -> 2145209.8 | AB16: =+N16+Z16 -> 2159692 | AC16: =392.905465867142*1000 -> 392905.47 | AD16: 395455 | AE16: =+AA16+AC16 -> 2538115.3 | AF16: =+AB16+AD16 -> 2555147 | AG16: =384.648377546259*1000 -> 384648.38 | AH16: 372411 | AI16: =+AE16+AG16 -> 2922763.7 | AJ16: =+AF16+AH16 -> 2927558 | AK16: =398.437601907252*1000 -> 398437.6 | AL16: 378682 | AM16: =+AC16+AG16+AK16 -> 1175991.4 | AN16: =+AD16+AH16+AL16 -> 1146548 | AO16: =AI16+AK16 -> 3321201.3 | AP16: =AJ16+AL16 -> 3306240 | AQ16: 402437.6 | AR16: 359440 | AS16: =+AO16+AQ16 -> 3723638.9 | AT16: =+AP16+AR16 -> 3665680 | AU16: 372391.29 | AV16: 372508 | AW16: =+AS16+AU16 -> 4096030.2 | AX16: =+AT16+AV16 -> 4038188 | AY16: 403969.74 | AZ16: 360257 | BA16: =+AQ16+AU16+AY16 -> 1178798.6 | BB16: =+AR16+AV16+AZ16 -> 1092205 | BC16: =AM16+BA16 -> 2354790.1 | BD16: =AN16+BB16 -> 2238753 | BE16: =AW16+AY16 -> 4499999.9 | BF16: =AX16+AZ16 -> 4398445 | BG16: 4270000.1 | BH16: 4395665 | BI16: 4183927.8 | BJ16: 4277831 | BK16: 3665891.3 | BL16: 3629577 | BM16: 3903932.5 | BN16: 3709525
B17: HOT METAL | C17: Mt | D17: =2800*1000 -> 2800000 | E17: =236*1000 -> 236000 | F17: 231705 | G17: 197000 | H17: 186324.9 | I17: =+E17+G17 -> 433000 | J17: =+F17+H17 -> 418029.9 | K17: 201000 | L17: 213361 | M17: =+E17+G17+K17 -> 634000 | N17: =+F17+H17+L17 -> 631390.9 | O17: 239000 | P17: 245255 | Q17: =+M17+O17 -> 873000 | R17: =+N17+P17 -> 876645.9 | S17: 239000 | T17: 240285 | U17: =+Q17+S17 -> 1112000 | V17: =+R17+T17 -> 1116930.9 | W17: 232000 | X17: 229120 | Y17: =+O17+S17+W17 -> 710000 | Z17: =+P17+T17+X17 -> 714660 | AA17: =+M17+Y17 -> 1344000 | AB17: =+N17+Z17 -> 1346050.9 | AC17: =246*1000 -> 246000 | AD17: 243314 | AE17: =+AA17+AC17 -> 1590000 | AF17: =+AB17+AD17 -> 1589364.9 | AG17: 238000 | AH17: 206094 | AI17: =+AE17+AG17 -> 1828000 | AJ17: =+AF17+AH17 -> 1795458.9 | AK17: 247000 | AL17: 228212.7 | AM17: =+AC17+AG17+AK17 -> 731000 | AN17: =+AD17+AH17+AL17 -> 677620.7 | AO17: =AI17+AK17 -> 2075000 | AP17: =AJ17+AL17 -> 2023671.6 | AQ17: 247000 | AR17: 232525.2 | AS17: =+AO17+AQ17 -> 2322000 | AT17: =+AP17+AR17 -> 2256196.8 | AU17: 230000 | AV17: 230199.2 | AW17: =+AS17+AU17 -> 2552000 | AX17: =+AT17+AV17 -> 2486396 | AY17: 248000 | AZ17: 234872.1 | BA17: =+AQ17+AU17+AY17 -> 725000 | BB17: =+AR17+AV17+AZ17 -> 697596.5 | BC17: =AM17+BA17 -> 1456000 | BD17: =AN17+BB17 -> 1375217.2 | BE17: =AW17+AY17 -> 2800000 | BF17: =AX17+AZ17 -> 2721268.1 | BG17: 2680000 | BH17: 2592119.6 | BI17: 2650001 | BJ17: 2406785.7 | BK17: 2496672.2 | BL17: 2092798 | BM17: 2700000 | BN17: 2505193
B18: CRUDE STEEL | C18: Mt | D18: =2620.07547169811*1000 -> 2620075.5 | E18: =221.509433962264*1000 -> 221509.43 | F18: 215539 | G18: =184.716981132075*1000 -> 184716.98 | H18: 175895 | I18: =+E18+G18 -> 406226.42 | J18: =+F18+H18 -> 391434 | K18: =180.641509433962*1000 -> 180641.51 | L18: 187063 | M18: =+E18+G18+K18 -> 586867.92 | N18: =+F18+H18+L18 -> 578497 | O18: =224.339622641509*1000 -> 224339.62 | P18: 230148 | Q18: =+M18+O18 -> 811207.55 | R18: =+N18+P18 -> 808645 | S18: 224339.62 | T18: 224642 | U18: =+Q18+S18 -> 1035547.2 | V18: =+R18+T18 -> 1033287 | W18: 217735.85 | X18: 210766 | Y18: =+O18+S18+W18 -> 666415.09 | Z18: =+P18+T18+X18 -> 665556 | AA18: =+M18+Y18 -> 1253283 | AB18: =+N18+Z18 -> 1244053 | AC18: =230.943396226415*1000 -> 230943.4 | AD18: 223439 | AE18: =+AA18+AC18 -> 1484226.4 | AF18: =+AB18+AD18 -> 1467492 | AG18: =223.396226415094*1000 -> 223396.23 | AH18: 192334 | AI18: =+AE18+AG18 -> 1707622.6 | AJ18: =+AF18+AH18 -> 1659826 | AK18: =231.88679245283*1000 -> 231886.79 | AL18: 217585 | AM18: =+AC18+AG18+AK18 -> 686226.42 | AN18: =+AD18+AH18+AL18 -> 633358 | AO18: =AI18+AK18 -> 1939509.4 | AP18: =AJ18+AL18 -> 1877411 | AQ18: 231886.79 | AR18: 217679 | AS18: =+AO18+AQ18 -> 2171396.2 | AT18: =+AP18+AR18 -> 2095090 | AU18: 215849.06 | AV18: 214408 | AW18: =+AS18+AU18 -> 2387245.3 | AX18: =+AT18+AV18 -> 2309498 | AY18: =232.830188679245*1000 -> 232830.19 | AZ18: 219427 | BA18: =+AQ18+AU18+AY18 -> 680566.04 | BB18: =+AR18+AV18+AZ18 -> 651514 | BC18: =AM18+BA18 -> 1366792.5 | BD18: =AN18+BB18 -> 1284872 | BE18: =AW18+AY18 -> 2620075.5 | BF18: =AX18+AZ18 -> 2528925 | BG18: 2500000 | BH18: 2422324.3 | BI18: 2451737.7 | BJ18: 2227867 | BK18: 2297163.5 | BL18: 1847433 | BM18: 2500000 | BN18: 2083412
B19: Avg Heats Cast per Day | C19: Nos. / day | D19: =D49/D1 -> 50.337665 | E19: =+E49/E1 -> 50.921709 | F19: =+F49/F1 -> 48.881356 | G19: =+G49/G1 -> 49.257862 | H19: =+H49/H1 -> 43.670295 | I19: =+I49/I1 -> 50.151409 | J19: =+J49/J1 -> 46.401184 | K19: =+K49/K1 -> 44.602842 | L19: =+L49/L1 -> 50.671164 | ... BF19: =+BF49/BF1 -> 48.130368 | BG19: 46.816479 | BH19: 45.269663 | BI19: 44.780041 | BJ19: 40.065753 | BK19: 41.920046 | BL19: 33.309589 | BM19: 47.014645 | BN19: 38.663934
B20: Cold Pig & Pig Equivalent
B21: MOG | C21: Mt | D21: 19561 | E21: 1160.8961 | F21: 302.9961 | G21: =1.16089613034623*1000 -> 1160.8961 | H21: 888.9555 | I21: =+E21+G21 -> 2321.7923 | J21: =+F21+H21 -> 1191.9516 | K21: =6.79124236252546*1000 -> 6791.2424 | L21: 5386.3191 | M21: =+E21+G21+K21 -> 9113.0346 | N21: =+F21+H21+L21 -> 6578.2707 | O21: =1.16089613034623*1000 -> 1160.8961 | P21: 151.0807 | Q21: =+M21+O21 -> 10273.931 | R21: =+N21+P21 -> 6729.3514 | S21: 1160.8961 | T21: 0 | U21: =+Q21+S21 -> 11434.827 | V21: =+R21+T21 -> 6729.3514 | W21: 1160.8961 | X21: 0 | Y21: =+O21+S21+W21 -> 3482.6884 | Z21: =+P21+T21+X21 -> 151.0807 | AA21: =+M21+Y21 -> 12595.723 | AB21: =+N21+Z21 -> 6729.3514 | AC21: 1160.8961 | AD21: 0 | AE21: =+AA21+AC21 -> 13756.619 | AF21: =+AB21+AD21 -> 6729.3514 | AG21: 1160.8961 | AH21: 397.3172 | AI21: =+AE21+AG21 -> 14917.515 | AJ21: =+AF21+AH21 -> 7126.6686 | AK21: =1.16089613034623*1000 -> 1160.8961 | AL21: 145.2378 | AM21: =+AC21+AG21+AK21 -> 3482.6884 | AN21: =+AD21+AH21+AL21 -> 542.555 | AO21: =AI21+AK21 -> 16078.411 | AP21: =AJ21+AL21 -> 7271.9064 | AQ21: 1160.8961 | AR21: 0 | AS21: =+AO21+AQ21 -> 17239.308 | AT21: =+AP21+AR21 -> 7271.9064 | AU21: 1160.8961 | AV21: 0 | AW21: =+AS21+AU21 -> 18400.204 | AX21: =+AT21+AV21 -> 7271.9064 | AY21: =1.16089613034623*1000 -> 1160.8961 | AZ21: 276.36917 | BA21: =+AQ21+AU21+AY21 -> 3482.6884 | BB21: =+AR21+AV21+AZ21 -> 276.36917 | BC21: =AM21+BA21 -> 6965.3768 | BD21: =AN21+BB21 -> 818.92417 | BE21: =AW21+AY21 -> 19561.1 | BF21: =AX21+AZ21 -> 7548.2756 | BG21: 16929.735 | BH21: 9129.3344 | BI21: 19735.515 | BJ21: 22361.072 | BK21: 20755.018 | BL21: 58220.7 | BM21: 29957.856 | BN21: 134629.18
A22: 1000 | B22: UPIS | C22: Mt | D22: 0 | E22: 0 | F22: 42.77592 | G22: 0 | H22: 125.4996 | I22: =+E22+G22 -> 0 | J22: =+F22+H22 -> 168.27552 | K22: 0 | L22: 760.42152 | M22: =+E22+G22+K22 -> 0 | N22: =+F22+H22+L22 -> 928.69704 | O22: 0 | P22: 21.32904 | Q22: =+M22+O22 -> 0 | R22: =+N22+P22 -> 950.02608 | S22: 0 | T22: 0 | U22: =+Q22+S22 -> 0 | V22: =+R22+T22 -> 950.02608 | W22: 0 | X22: 0 | Y22: =+O22+S22+W22 -> 0 | Z22: =+P22+T22+X22 -> 21.32904 | AA22: =+M22+Y22 -> 0 | AB22: =+N22+Z22 -> 950.02608 | AC22: 0 | AD22: 0 | AE22: =+AA22+AC22 -> 0 | AF22: =+AB22+AD22 -> 950.02608 | AG22: 0 | AH22: 56.09184 | AI22: =+AE22+AG22 -> 0 | AJ22: =+AF22+AH22 -> 1006.1179 | AK22: 0 | AL22: 20.50416 | AM22: =+AC22+AG22+AK22 -> 0 | AN22: =+AD22+AH22+AL22 -> 76.596 | AO22: =AI22+AK22 -> 0 | AP22: =AJ22+AL22 -> 1026.6221 | AQ22: 0 | AR22: 0 | AS22: =+AO22+AQ22 -> 0 | AT22: =+AP22+AR22 -> 1026.6221 | AU22: 0 | AV22: 0 | AW22: =+AS22+AU22 -> 0 | AX22: =+AT22+AV22 -> 1026.6221 | AY22: 0 | AZ22: 0 | BA22: =+AQ22+AU22+AY22 -> 0 | BB22: =+AR22+AV22+AZ22 -> 0 | BC22: =AM22+BA22 -> 0 | BD22: =AN22+BB22 -> 76.596 | BE22: =AW22+AY22 -> 0 | BF22: =AX22+AZ22 -> 1026.6221 | BG22: 0 | BH22: 2541.6495 | BI22: 0 | BJ22: 2774.7649 | BK22: 392 | BL22: 3852.3 | BM22: 1419.0563 | BN22: 8272.9783
B23: (Equiv. Pig Iron @ 80% of HM sent to Sand Pit. (Ref to Fax Msg from ED (O), vide SAIL/OPRNS/ PPMS/33 dt. 05.02.15) | C23: Mt | D23: 2000 | E23: 0 | F23: 0 | G23: 0 | H23: 0 | I23: =+E23+G23 -> 0 | J23: =+F23+H23 -> 0 | K23: 2000 | L23: 5022 | M23: =+E23+G23+K23 -> 2000 | N23: =+F23+H23+L23 -> 5022 | O23: 0 | P23: 0 | Q23: =+M23+O23 -> 2000 | R23: =+N23+P23 -> 5022 | S23: 0 | T23: 0 | U23: =+Q23+S23 -> 2000 | V23: =+R23+T23 -> 5022 | W23: 0 | X23: 0 | Y23: =+O23+S23+W23 -> 0 | Z23: =+P23+T23+X23 -> 0 | AA23: =+M23+Y23 -> 2000 | AB23: =+N23+Z23 -> 5022 | AC23: 0 | AD23: 0 | AE23: =+AA23+AC23 -> 2000 | AF23: =+AB23+AD23 -> 5022 | AG23: 0 | AH23: 0 | AI23: =+AE23+AG23 -> 2000 | AJ23: =+AF23+AH23 -> 5022 | AK23: 0 | AL23: 0 | AM23: =+AC23+AG23+AK23 -> 0 | AN23: =+AD23+AH23+AL23 -> 0 | AO23: =AI23+AK23 -> 2000 | AP23: =AJ23+AL23 -> 5022 | AQ23: 0 | AR23: 0 | AS23: =+AO23+AQ23 -> 2000 | AT23: =+AP23+AR23 -> 5022 | AU23: 0 | AV23: 0 | AW23: =+AS23+AU23 -> 2000 | AX23: =+AT23+AV23 -> 5022 | AY23: 0 | AZ23: 0 | BA23: =+AQ23+AU23+AY23 -> 0 | BB23: =+AR23+AV23+AZ23 -> 0 | BC23: =AM23+BA23 -> 0 | BD23: =AN23+BB23 -> 0 | BE23: =AW23+AY23 -> 2000 | BF23: =AX23+AZ23 -> 5022 | BG23: 6000 | BH23: 4664.8 | BI23: 14800 | BJ23: 9214.4 | BK23: 0 | BL23: 0 | BM23: 0 | BN23: 26220.8
B24: TOTAL EQUIVALENT PIG IRON | C24: Mt | D24: =SUM(D21:D23) -> 21561 | E24: =SUM(E21:E23) -> 1160.8961 | F24: =SUM(F21:F23) -> 345.77202 | G24: =SUM(G21:G23) -> 1160.8961 | H24: =SUM(H21:H23) -> 1014.4551 | I24: =SUM(I21:I23) -> 2321.7923 | J24: =SUM(J21:J23) -> 1360.2271 | K24: =SUM(K21:K23) -> 8791.2424 | ... BF24: =SUM(BF21:BF23) -> 13596.898 | BG24: 22929.735 | BH24: 16335.784 | BI24: 34535.515 | BJ24: 34350.237 | BK24: 21147.018 | BL24: 62073 | BM24: 31376.912 | BN24: 169122.96
B25: Net PCI Production | C25: Mt | D25: 2377.872 | E25: 141.12 | F25: 226.856 | G25: 141.12 | H25: 721 | I25: =+E25+G25 -> 282.24 | J25: =+F25+H25 -> 947.856 | K25: 825.552 | L25: 1000 | M25: =+E25+G25+K25 -> 1107.792 | N25: =+F25+H25+L25 -> 1947.856 | O25: 141.12 | P25: 1119.16 | Q25: =+M25+O25 -> 1248.912 | R25: =+N25+P25 -> 3067.016 | S25: 141.12 | T25: 1304.1 | U25: =+Q25+S25 -> 1390.032 | V25: =+R25+T25 -> 4371.116 | W25: 141.12 | X25: 670.208 | Y25: =+O25+S25+W25 -> 423.36 | Z25: =+P25+T25+X25 -> 3093.468 | AA25: =+M25+Y25 -> 1531.152 | AB25: =+N25+Z25 -> 5041.324 | AC25: 141.12 | AD25: 763.147 | AE25: =+AA25+AC25 -> 1672.272 | AF25: =+AB25+AD25 -> 5804.471 | AG25: 141.12 | AH25: 0 | AI25: =+AE25+AG25 -> 1813.392 | AJ25: =+AF25+AH25 -> 5804.471 | AK25: 141.12 | AL25: 0 | AM25: =+AC25+AG25+AK25 -> 423.36 | AN25: =+AD25+AH25+AL25 -> 763.147 | AO25: =AI25+AK25 -> 1954.512 | AP25: =AJ25+AL25 -> 5804.471 | AQ25: 141.12 | AR25: 110.775 | AS25: =+AO25+AQ25 -> 2095.632 | AT25: =+AP25+AR25 -> 5915.246 | AU25: 141.12 | AV25: 0 | AW25: =+AS25+AU25 -> 2236.752 | AX25: =+AT25+AV25 -> 5915.246 | AY25: 141.12 | AZ25: 226.149 | BA25: =+AQ25+AU25+AY25 -> 423.36 | BB25: =+AR25+AV25+AZ25 -> 336.924 | BC25: =AM25+BA25 -> 846.72 | BD25: =AN25+BB25 -> 1100.071 | BE25: =AW25+AY25 -> 2377.872 | BF25: =AX25+AZ25 -> 6141.395 | BG25: 2057.6 | BH25: 5885.734 | BI25: 2398.56 | BJ25: 13377.679 | BK25: 11568.99 | BL25: 41093.9 | BM25: 0 | BN25: 44255.19
B26: Net Granulated Slag Production | C26: Mt | D26: 1063047 | E26: 89599.675 | F26: 104981.63 | G26: 74792.949 | H26: 89191.765 | I26: =+E26+G26 -> 164392.62 | J26: =+F26+H26 -> 194173.39 | K26: 76311.588 | L26: 82961.954 | M26: =+E26+G26+K26 -> 240704.21 | N26: =+F26+H26+L26 -> 277135.35 | O26: 90738.654 | P26: 104404.72 | Q26: =+M26+O26 -> 331442.87 | R26: =+N26+P26 -> 381540.07 | S26: 90738.654 | T26: 120487.19 | U26: =+Q26+S26 -> 422181.52 | V26: =+R26+T26 -> 502027.26 | W26: 88081.037 | X26: 99564.148 | Y26: =+O26+S26+W26 -> 269558.35 | Z26: =+P26+T26+X26 -> 324456.06 | AA26: =+M26+Y26 -> 510262.56 | AB26: =+N26+Z26 -> 601591.41 | AC26: 93396.272 | AD26: 103143.64 | AE26: =+AA26+AC26 -> 603658.83 | AF26: =+AB26+AD26 -> 704735.05 | AG26: 90358.995 | AH26: 82013.501 | AI26: =+AE26+AG26 -> 694017.83 | AJ26: =+AF26+AH26 -> 786748.55 | AK26: 93775.932 | AL26: 71167.549 | AM26: =+AC26+AG26+AK26 -> 277531.2 | AN26: =+AD26+AH26+AL26 -> 256324.69 | AO26: =AI26+AK26 -> 787793.76 | AP26: =AJ26+AL26 -> 857916.1 | AQ26: 93775.932 | AR26: 58850.349 | AS26: =+AO26+AQ26 -> 881569.69 | AT26: =+AP26+AR26 -> 916766.45 | AU26: 87321.718 | AV26: 76969.95 | AW26: =+AS26+AU26 -> 968891.41 | AX26: =+AT26+AV26 -> 993736.4 | AY26: 94155.591 | AZ26: 81508.241 | BA26: =+AQ26+AU26+AY26 -> 275253.24 | BB26: =+AR26+AV26+AZ26 -> 217328.54 | BC26: =AM26+BA26 -> 552784.44 | BD26: =AN26+BB26 -> 473653.23 | BE26: =AW26+AY26 -> 1063047 | BF26: =AX26+AZ26 -> 1075244.6 | BG26: 887402.68 | BH26: 1065593 | BI26: 157305.12 | BJ26: 920129.3 | BK26: 882599.97 | BL26: 776699 | BM26: 854658 | BN26: 809638.21
B27: Saleable Steel Production (Mill Wise)
B28: WR Mill | C28: Mt | D28: 500000 | E28: =42.5*1000 -> 42500 | F28: =+WRM!F125 -> 38790.1 | G28: =36.5*1000 -> 36500 | H28: =+WRM!H125 -> 31436.75 | I28: =+E28+G28 -> 79000 | J28: =+F28+H28 -> 70226.85 | K28: 34000 | L28: =+WRM!L125 -> 32975.4 | M28: =+E28+G28+K28 -> 113000 | N28: =+F28+H28+L28 -> 103202.25 | O28: =43.5*1000 -> 43500 | P28: =+WRM!P125 -> 41411.41 | Q28: =+M28+O28 -> 156500 | R28: =+N28+P28 -> 144613.66 | S28: 43500 | T28: =+WRM!T125 -> 46120.9 | U28: =+Q28+S28 -> 200000 | V28: =+R28+T28 -> 190734.56 | W28: 42500 | X28: 44910.375 | Y28: =+O28+S28+W28 -> 129500 | Z28: =+P28+T28+X28 -> 132442.69 | AA28: =+M28+Y28 -> 242500 | AB28: =+N28+Z28 -> 235644.94 | AC28: =43.5*1000 -> 43500 | AD28: 42767.05 | AE28: =+AA28+AC28 -> 286000 | AF28: =+AB28+AD28 -> 278411.99 | AG28: =42.5*1000 -> 42500 | AH28: 40266.1 | AI28: =+AE28+AG28 -> 328500 | AJ28: =+AF28+AH28 -> 318678.09 | AK28: =43.5*1000 -> 43500 | AL28: 41541.2 | AM28: =+AC28+AG28+AK28 -> 129500 | AN28: =+AD28+AH28+AL28 -> 124574.35 | AO28: =AI28+AK28 -> 372000 | AP28: =AJ28+AL28 -> 360219.29 | AQ28: 43500 | AR28: 43760.85 | AS28: =+AO28+AQ28 -> 415500 | AT28: =+AP28+AR28 -> 403980.14 | AU28: 41000 | AV28: 36414.15 | AW28: =+AS28+AU28 -> 456500 | AX28: =+AT28+AV28 -> 440394.29 | AY28: 43500 | AZ28: 38134.1 | BA28: =+AQ28+AU28+AY28 -> 128000 | BB28: =+AR28+AV28+AZ28 -> 118309.1 | BC28: =AM28+BA28 -> 257500 | BD28: =AN28+BB28 -> 242883.45 | BE28: =AW28+AY28 -> 500000 | BF28: =AX28+AZ28 -> 478528.39 | BG28: 500000 | BH28: 466114.65 | BI28: 500000 | BJ28: 465343.77 | BK28: 435965.96 | BL28: 356518.66 | BM28: 500000 | BN28: 412025.22
B29: Bar Mill | C29: Mt | D29: 850000 | E29: =72.5*1000 -> 72500 | F29: =+BM!F52 -> 70044.755 | G29: =62.5*1000 -> 62500 | H29: =+BM!H52 -> 56061.496 | I29: =+E29+G29 -> 135000 | J29: =+F29+H29 -> 126106.25 | K29: 47000 | L29: =+BM!L52 -> 54192.347 | M29: =+E29+G29+K29 -> 182000 | N29: =+F29+H29+L29 -> 180298.6 | O29: =75*1000 -> 75000 | P29: =+BM!P52 -> 73996.973 | Q29: =+M29+O29 -> 257000 | R29: =+N29+P29 -> 254295.57 | S29: 75000 | T29: =+BM!T52 -> 81550.701 | U29: =+Q29+S29 -> 332000 | V29: =+R29+T29 -> 335846.27 | W29: 73000 | X29: 66170.788 | Y29: =+O29+S29+W29 -> 223000 | Z29: =+P29+T29+X29 -> 221718.46 | AA29: =+M29+Y29 -> 405000 | AB29: =+N29+Z29 -> 402017.06 | AC29: =75.5*1000 -> 75500 | AD29: 61010.23 | AE29: =+AA29+AC29 -> 480500 | AF29: =+AB29+AD29 -> 463027.29 | AG29: 73000 | AH29: 59054.402 | AI29: =+AE29+AG29 -> 553500 | AJ29: =+AF29+AH29 -> 522081.69 | AK29: =75.5*1000 -> 75500 | AL29: 67544.47 | AM29: =+AC29+AG29+AK29 -> 224000 | AN29: =+AD29+AH29+AL29 -> 187609.1 | AO29: =AI29+AK29 -> 629000 | AP29: =AJ29+AL29 -> 589626.16 | AQ29: 75500 | AR29: 70905.326 | AS29: =+AO29+AQ29 -> 704500 | AT29: =+AP29+AR29 -> 660531.49 | AU29: 70000 | AV29: 65231.44 | AW29: =+AS29+AU29 -> 774500 | AX29: =+AT29+AV29 -> 725762.93 | AY29: 75500 | AZ29: 69559.345 | BA29: =+AQ29+AU29+AY29 -> 221000 | BB29: =+AR29+AV29+AZ29 -> 205696.11 | BC29: =AM29+BA29 -> 445000 | BD29: =AN29+BB29 -> 393305.21 | BE29: =AW29+AY29 -> 850000 | BF29: =AX29+AZ29 -> 795322.27 | BG29: 780000 | BH29: 775906.63 | BI29: 750000 | BJ29: 649840.96 | BK29: 674875.14 | BL29: 440547.27 | BM29: 800000 | BN29: 632220.18
B30: US Mill | C30: Mt | D30: 525000 | E30: =44.5*1000 -> 44500 | F30: =+USM!G73 -> 34411.017 | G30: =37.5*1000 -> 37500 | H30: =+USM!I73 -> 29035.71 | I30: =+E30+G30 -> 82000 | J30: =+F30+H30 -> 63446.727 | K30: 36000 | L30: =+USM!M73 -> 29014.605 | M30: =+E30+G30+K30 -> 118000 | N30: =+F30+H30+L30 -> 92461.332 | O30: =46*1000 -> 46000 | P30: =+USM!Q73 -> 33200.704 | Q30: =+M30+O30 -> 164000 | R30: =+N30+P30 -> 125662.04 | S30: 46000 | T30: =+USM!U73 -> 44285.714 | U30: =+Q30+S30 -> 210000 | V30: =+R30+T30 -> 169947.75 | W30: 44500 | X30: 37549.827 | Y30: =+O30+S30+W30 -> 136500 | Z30: =+P30+T30+X30 -> 115036.24 | AA30: =+M30+Y30 -> 254500 | AB30: =+N30+Z30 -> 207497.58 | AC30: =46*1000 -> 46000 | AD30: 38658.05 | AE30: =+AA30+AC30 -> 300500 | AF30: =+AB30+AD30 -> 246155.63 | AG30: =44.5*1000 -> 44500 | AH30: 41612.207 | AI30: =+AE30+AG30 -> 345000 | AJ30: =+AF30+AH30 -> 287767.83 | AK30: 46000 | AL30: 41025.187 | AM30: =+AC30+AG30+AK30 -> 136500 | AN30: =+AD30+AH30+AL30 -> 121295.44 | AO30: =AI30+AK30 -> 391000 | AP30: =AJ30+AL30 -> 328793.02 | AQ30: 46000 | AR30: 41204.778 | AS30: =+AO30+AQ30 -> 437000 | AT30: =+AP30+AR30 -> 369997.8 | AU30: 42000 | AV30: 42591.4 | AW30: =+AS30+AU30 -> 479000 | AX30: =+AT30+AV30 -> 412589.2 | AY30: =46*1000 -> 46000 | AZ30: 46552.753 | BA30: =+AQ30+AU30+AY30 -> 134000 | BB30: =+AR30+AV30+AZ30 -> 130348.93 | BC30: =AM30+BA30 -> 270500 | BD30: =AN30+BB30 -> 251644.38 | BE30: =AW30+AY30 -> 525000 | BF30: =AX30+AZ30 -> 459141.95 | BG30: 470000 | BH30: 361987.56 | BI30: 450000 | BJ30: 213226.16 | BK30: 220000 | BL30: 88943.894 | BM30: 535000 | BN30: 171634.81
B31: Finished Steel | C31: Mt | D31: =SUM(D28:D30) -> 1875000 | E31: =SUM(E28:E30) -> 159500 | F31: =SUM(F28:F30) -> 143245.87 | G31: =SUM(G28:G30) -> 136500 | H31: =SUM(H28:H30) -> 116533.96 | I31: =SUM(I28:I30) -> 296000 | J31: =SUM(J28:J30) -> 259779.83 | K31: =SUM(K28:K30) -> 117000 | ... BF31: =SUM(BF28:BF30) -> 1732992.6 | BG31: 1750000 | BH31: 1604008.8 | BI31: 1700000 | BJ31: 1328410.9 | BK31: 1330841.1 | BL31: 886009.82 | BM31: =SUM(BM28:BM30) -> 1835000 | BN31: =SUM(BN28:BN30) -> 1215880.2
B32: 150x150 mm | C32: Mt | D32: =592.000000270625*1000 -> 592000 | E32: =49.9999999999102*1000 -> 50000 | F32: 49376 | G32: =38.0000000004283*1000 -> 38000 | H32: 41843 | I32: =+E32+G32 -> 88000 | J32: =+F32+H32 -> 91219 | K32: =53.9999999998981*1000 -> 54000 | L32: =46513+23.4 -> 46536.4 | M32: =+E32+G32+K32 -> 142000 | N32: =+F32+H32+L32 -> 137755.4 | O32: =49.000000270114*1000 -> 49000 | P32: 54670 | Q32: =+M32+O32 -> 191000 | R32: =+N32+P32 -> 192425.4 | S32: 49000 | T32: 43042 | U32: =+Q32+S32 -> 240000 | V32: =+R32+T32 -> 235467.4 | W32: 46000 | X32: 48357 | Y32: =+O32+S32+W32 -> 144000 | Z32: =+P32+T32+X32 -> 146069 | AA32: =+M32+Y32 -> 286000 | AB32: =+N32+Z32 -> 283824.4 | AC32: =52.0000000000881*1000 -> 52000 | AD32: =54787.2-16.23+94 -> 54864.97 | AE32: =+AA32+AC32 -> 338000 | AF32: =+AB32+AD32 -> 338689.37 | AG32: =49.9999999998843*1000 -> 50000 | AH32: =43278+118-43 -> 43353 | AI32: =+AE32+AG32 -> 388000 | AJ32: =+AF32+AH32 -> 382042.37 | AK32: =52.0000000000881*1000 -> 52000 | AL32: 47527 | AM32: =+AC32+AG32+AK32 -> 154000 | AN32: =+AD32+AH32+AL32 -> 145744.97 | AO32: =AI32+AK32 -> 440000 | AP32: =AJ32+AL32 -> 429569.37 | AQ32: 52000 | AR32: 41110 | AS32: =+AO32+AQ32 -> 492000 | AT32: =+AP32+AR32 -> 470679.37 | AU32: 48000 | AV32: 54846 | AW32: =+AS32+AU32 -> 540000 | AX32: =+AT32+AV32 -> 525525.37 | AY32: =52.0000000000881*1000 -> 52000 | AZ32: 49298 | BA32: =+AQ32+AU32+AY32 -> 152000 | BB32: =+AR32+AV32+AZ32 -> 145254 | BC32: =AM32+BA32 -> 306000 | BD32: =AN32+BB32 -> 290998.97 | BE32: =AW32+AY32 -> 592000 | BF32: =AX32+AZ32 -> 574823.37 | BG32: 544999.51 | BH32: 595119.91 | BI32: 516406.77 | BJ32: 627684.57 | BK32: 533055.82 | BL32: 608495.73 | BM32: 304999.74 | BN32: 629438.96
B33: 200x280 mm | C33: Mt | D33: =57.9999161425576*1000 -> 57999.916 | E33: =4.00048687231707*1000 -> 4000.4869 | F33: 13419.07 | G33: =3.50044144953577*1000 -> 3500.4414 | H33: 4696 | I33: =+E33+G33 -> 7500.9283 | J33: =+F33+H33 -> 18115.07 | K33: =2.50027133872416*1000 -> 2500.2713 | L33: 16270.81 | M33: =+E33+G33+K33 -> 10001.2 | N33: =+F33+H33+L33 -> 34385.88 | O33: =3.00037396426075*1000 -> 3000.374 | P33: 12217 | Q33: =+M33+O33 -> 13001.574 | R33: =+N33+P33 -> 46602.88 | S33: 3000.374 | T33: 1476.4208 | U33: =+Q33+S33 -> 16001.948 | V33: =+R33+T33 -> 48079.301 | W33: 3999.902 | X33: 9032.5434 | Y33: =+O33+S33+W33 -> 10000.65 | Z33: =+P33+T33+X33 -> 22725.964 | AA33: =+M33+Y33 -> 20001.85 | AB33: =+N33+Z33 -> 57111.844 | AC33: =5.49914754916641*1000 -> 5499.1475 | AD33: 12963.3 | AE33: =+AA33+AC33 -> 25500.997 | AF33: =+AB33+AD33 -> 70075.144 | AG33: =5.50027932514725*1000 -> 5500.2793 | AH33: 691 | AI33: =+AE33+AG33 -> 31001.276 | AJ33: =+AF33+AH33 -> 70766.144 | AK33: =6.4995437755815*1000 -> 6499.5438 | AL33: 9126 | AM33: =+AC33+AG33+AK33 -> 17498.971 | AN33: =+AD33+AH33+AL33 -> 22780.3 | AO33: =AI33+AK33 -> 37500.82 | AP33: =AJ33+AL33 -> 79892.144 | AQ33: 6499.5438 | AR33: 12121 | AS33: =+AO33+AQ33 -> 44000.364 | AT33: =+AP33+AR33 -> 92013.144 | AU33: 6999.6122 | AV33: 6079 | AW33: =+AS33+AU33 -> 50999.976 | AX33: =+AT33+AV33 -> 98092.144 | AY33: =6.99994000199659*1000 -> 6999.94 | AZ33: 3736 | BA33: =+AQ33+AU33+AY33 -> 20499.096 | BB33: =+AR33+AV33+AZ33 -> 21936 | BC33: =AM33+BA33 -> 37998.067 | BD33: =AN33+BB33 -> 44716.3 | BE33: =AW33+AY33 -> 57999.916 | BF33: =AX33+AZ33 -> 101828.14 | BG33: 115000.5 | BH33: 116079.05 | BI33: 153592.34 | BJ33: 204330.35 | BK33: 371378.01 | BL33: 329378.8 | BM33: 267000 | BN33: 248401
B34: Saleable Semis | C34: Mt | D34: =SUM(D32:D33) -> 649999.92 | E34: =SUM(E32:E33) -> 54000.487 | F34: =SUM(F32:F33) -> 62795.07 | G34: =SUM(G32:G33) -> 41500.441 | H34: =SUM(H32:H33) -> 46539 | I34: =SUM(I32:I33) -> 95500.928 | J34: =SUM(J32:J33) -> 109334.07 | K34: =SUM(K32:K33) -> 56500.271 | ... BF34: =SUM(BF32:BF33) -> 676651.51 | BG34: 660000.01 | BH34: 711198.96 | BI34: 669999.11 | BJ34: 832014.92 | BK34: 904433.83 | BL34: 937874.53 | BM34: =SUM(BM32:BM33) -> 571999.74 | BN34: =SUM(BN32:BN33) -> 877839.96
B35: TOTAL SALEABLE STEEL | C35: Mt | D35: =+D31+D34 -> 2524999.9 | E35: =+E31+E34 -> 213500.49 | F35: =+F31+F34 -> 206040.94 | G35: =+G31+G34 -> 178000.44 | H35: =+H31+H34 -> 163072.96 | I35: =+I31+I34 -> 391500.93 | J35: =+J31+J34 -> 369113.9 | K35: =+K31+K34 -> 173500.27 | ... BF35: =+BF31+BF34 -> 2409644.1 | BG35: 2410000 | BH35: 2315207.8 | BI35: 2369999.1 | BJ35: 2160425.8 | BK35: 2235274.9 | BL35: 1823884.4 | BM35: =+BM31+BM34 -> 2406999.7 | BN35: =+BN31+BN34 -> 2093720.2
B36: SAL STEEL PRODN (CATEGORY WISE)
B37: Wire Rod Plain Coils | C37: Mt | D37: =+D28 -> 500000 | E37: =+E28 -> 42500 | F37: =+WRM!F165 -> 38790.1 | G37: =+G28 -> 36500 | H37: =+WRM!H165 -> 24710.7 | I37: =+E37+G37 -> 79000 | J37: =+F37+H37 -> 63500.8 | K37: =+K28 -> 34000 | L37: =+WRM!L165 -> 32975.4 | M37: =+E37+G37+K37 -> 113000 | N37: =+F37+H37+L37 -> 96476.2 | O37: =+O28 -> 43500 | P37: =+WRM!P165 -> 41411.41 | Q37: =+M37+O37 -> 156500 | R37: =+N37+P37 -> 137887.61 | S37: =+S28 -> 43500 | T37: =+WRM!T165 -> 46120.9 | U37: =+Q37+S37 -> 200000 | V37: =+R37+T37 -> 184008.51 | W37: =+W28 -> 42500 | X37: =+WRM!X165 -> 44910.375 | Y37: =+O37+S37+W37 -> 129500 | Z37: =+P37+T37+X37 -> 132442.69 | AA37: =+M37+Y37 -> 242500 | AB37: =+N37+Z37 -> 228918.89 | AC37: =+AC28 -> 43500 | AD37: =+WRM!AD165 -> 42767.05 | AE37: =+AA37+AC37 -> 286000 | AF37: =+AB37+AD37 -> 271685.94 | AG37: =+AG28 -> 42500 | AH37: =+WRM!AH165 -> 40266.1 | AI37: =+AE37+AG37 -> 328500 | AJ37: =+AF37+AH37 -> 311952.04 | AK37: =+AK28 -> 43500 | AL37: 41541.2 | AM37: =+AC37+AG37+AK37 -> 129500 | AN37: =+AD37+AH37+AL37 -> 124574.35 | AO37: =AI37+AK37 -> 372000 | AP37: =AJ37+AL37 -> 353493.24 | AQ37: =+AQ28 -> 43500 | AR37: 43760.85 | AS37: =+AO37+AQ37 -> 415500 | AT37: =+AP37+AR37 -> 397254.09 | AU37: =+AU28 -> 41000 | AV37: 36414.15 | AW37: =+AS37+AU37 -> 456500 | AX37: =+AT37+AV37 -> 433668.24 | AY37: =+AY28 -> 43500 | AZ37: 38134.1 | BA37: =+AQ37+AU37+AY37 -> 128000 | BB37: =+AR37+AV37+AZ37 -> 118309.1 | BC37: =AM37+BA37 -> 257500 | BD37: =AN37+BB37 -> 242883.45 | BE37: =AW37+AY37 -> 500000 | BF37: =AX37+AZ37 -> 471802.34 | BG37: 500000 | BH37: 410762.6 | BI37: =+BI28 -> 500000 | BJ37: 456374.84 | BK37: =+BK28 -> 435965.96 | BL37: 333534.61 | BM37: 500000 | BN37: 270654.57
B38: TMT Coils | C38: Mt | F38: =+WRM!F166 -> 0 | H38: =+WRM!H166 -> 6726.05 | J38: =+F38+H38 -> 6726.05 | L38: =+WRM!L166 -> 0 | N38: =+F38+H38+L38 -> 6726.05 | P38: =+WRM!P166 -> 0 | R38: =+N38+P38 -> 6726.05 | T38: =+WRM!T166 -> 0 | V38: =+R38+T38 -> 6726.05 | X38: =+WRM!X166 -> 0 | Z38: =+P38+T38+X38 -> 0 | AB38: =+N38+Z38 -> 6726.05 | AD38: =+WRM!AD166 -> 0 | AF38: =+AB38+AD38 -> 6726.05 | AH38: =+WRM!AH166 -> 0 | AJ38: =+AF38+AH38 -> 6726.05 | AL38: 0 | AN38: =+AD38+AH38+AL38 -> 0 | AP38: =AJ38+AL38 -> 6726.05 | AR38: 0 | AT38: =+AP38+AR38 -> 6726.05 | AV38: 0 | AX38: =+AT38+AV38 -> 6726.05 | AZ38: 0 | BB38: =+AR38+AV38+AZ38 -> 0 | BD38: =AN38+BB38 -> 0 | BF38: =AX38+AZ38 -> 6726.05 | BH38: 55352.05 | BJ38: 8968.93 | BL38: 22983.766 | BN38: 141370.65
B39: TMT Bars | C39: Mt | D39: =+D29 -> 850000 | E39: =+E29 -> 72500 | F39: =+F29 -> 70044.755 | G39: =+G29 -> 62500 | H39: =+H29 -> 56061.496 | I39: =+E39+G39 -> 135000 | J39: =+F39+H39 -> 126106.25 | K39: =+K29 -> 47000 | L39: =+L29 -> 54192.347 | M39: =+E39+G39+K39 -> 182000 | N39: =+F39+H39+L39 -> 180298.6 | O39: =+O29 -> 75000 | P39: =+P29 -> 73996.973 | Q39: =+M39+O39 -> 257000 | R39: =+N39+P39 -> 254295.57 | S39: =+S29 -> 75000 | T39: =+T29 -> 81550.701 | U39: =+Q39+S39 -> 332000 | V39: =+R39+T39 -> 335846.27 | W39: =+W29 -> 73000 | X39: =+X29 -> 66170.788 | Y39: =+O39+S39+W39 -> 223000 | Z39: =+P39+T39+X39 -> 221718.46 | AA39: =+M39+Y39 -> 405000 | AB39: =+N39+Z39 -> 402017.06 | AC39: =+AC29 -> 75500 | AD39: =+AD29 -> 61010.23 | AE39: =+AA39+AC39 -> 480500 | AF39: =+AB39+AD39 -> 463027.29 | AG39: =+AG29 -> 73000 | AH39: 59054.402 | AI39: =+AE39+AG39 -> 553500 | AJ39: =+AF39+AH39 -> 522081.69 | AK39: =+AK29 -> 75500 | AL39: =+AL29 -> 67544.47 | AM39: =+AC39+AG39+AK39 -> 224000 | AN39: =+AD39+AH39+AL39 -> 187609.1 | AO39: =AI39+AK39 -> 629000 | AP39: =AJ39+AL39 -> 589626.16 | AQ39: =+AQ29 -> 75500 | AR39: 70905.326 | AS39: =+AO39+AQ39 -> 704500 | AT39: =+AP39+AR39 -> 660531.49 | AU39: =+AU29 -> 70000 | AV39: 65231.44 | AW39: =+AS39+AU39 -> 774500 | AX39: =+AT39+AV39 -> 725762.93 | AY39: =+AY29 -> 75500 | AZ39: 69559.345 | BA39: =+AQ39+AU39+AY39 -> 221000 | BB39: =+AR39+AV39+AZ39 -> 205696.11 | BC39: =AM39+BA39 -> 445000 | BD39: =AN39+BB39 -> 393305.21 | BE39: =AW39+AY39 -> 850000 | BF39: =AX39+AZ39 -> 795322.27 | BG39: 780000 | BH39: 775906.63 | BI39: 750000 | BJ39: 649840.96 | BK39: =+BK29 -> 674875.14 | BL39: 440547.14 | BM39: 800000 | BN39: 632220.18
B40: NPB | C40: Mt | D40: =+D30 -> 525000 | E40: =+E30 -> 44500 | F40: 26875 | G40: =+G30 -> 37500 | H40: 14939.49 | I40: =+G40+E40 -> 82000 | J40: =+F40+H40 -> 41814.49 | K40: =+K30 -> 36000 | L40: 21806.96 | M40: =+K40+G40+E40 -> 118000 | N40: =+F40+H40+L40 -> 63621.45 | O40: =+O30 -> 46000 | P40: 21694.56 | Q40: =+M40+O40 -> 164000 | R40: =+N40+P40 -> 85316.01 | S40: =+S30 -> 46000 | T40: 33615.366 | U40: =+Q40+S40 -> 210000 | V40: =+R40+T40 -> 118931.38 | W40: =+W30 -> 44500 | X40: 26746.403 | Y40: =+W40+S40+O40 -> 136500 | Z40: =+P40+T40+X40 -> 82056.329 | AA40: =+M40+Y40 -> 254500 | AB40: =+N40+Z40 -> 145677.78 | AC40: =+AC30 -> 46000 | AD40: 26323.05 | AE40: =+AC40+AA40 -> 300500 | AF40: =+AB40+AD40 -> 172000.83 | AG40: =+AG30 -> 44500 | AH40: 33154.34 | AI40: =+AG40+AE40 -> 345000 | AJ40: =+AF40+AH40 -> 205155.17 | AK40: =+AK30 -> 46000 | AL40: 27743.84 | AM40: =+AK40+AG40+AC40 -> 136500 | AN40: =+AD40+AH40+AL40 -> 87221.23 | AO40: =AI40+AK40 -> 391000 | AP40: =AJ40+AL40 -> 232899.01 | AQ40: =+AQ30 -> 46000 | AR40: 28609.52 | AS40: =+AQ40+AO40 -> 437000 | AT40: =+AP40+AR40 -> 261508.53 | AU40: =+AU30 -> 42000 | AV40: 28117.57 | AW40: =+AU40+AS40 -> 479000 | AX40: =+AT40+AV40 -> 289626.1 | AY40: =+AY30 -> 46000 | AZ40: 33322.32 | BA40: =+AY40+AU40+AQ40 -> 134000 | BB40: =+AR40+AV40+AZ40 -> 90049.41 | BC40: =AM40+BA40 -> 270500 | BD40: =AN40+BB40 -> 177270.64 | BE40: =AW40+AY40 -> 525000 | BF40: =AX40+AZ40 -> 322948.42 | BG40: 470000 | BH40: 273627.65 | BI40: =+BI30 -> 450000 | BJ40: 168120 | BK40: =+BK30 -> 220000 | BL40: 78790 | BM40: 535000 | BN40: =+BN30 -> 171634.81
B41: WPB | C41: Mt | F41: 0 | H41: 7320.1 | I41: =+E41+G41 -> 0 | J41: =+F41+H41 -> 7320.1 | L41: 4683.4 | N41: =+F41+H41+L41 -> 12003.5 | P41: 4813.682 | Q41: =+M41+O41 -> 0 | R41: =+N41+P41 -> 16817.182 | T41: 2816.585 | U41: =+Q41+S41 -> 0 | V41: =+R41+T41 -> 19633.767 | X41: 0 | Z41: =+P41+T41+X41 -> 7630.267 | AB41: =+N41+Z41 -> 19633.767 | AD41: 5096.24 | AE41: =+AA41+AC41 -> 0 | AF41: =+AB41+AD41 -> 24730.007 | AH41: 2965.5 | AI41: =+AE41+AG41 -> 0 | AJ41: =+AF41+AH41 -> 27695.507 | AL41: 2483.064 | AN41: =+AD41+AH41+AL41 -> 10544.804 | AO41: =+AK41+AM41 -> 0 | AP41: =AJ41+AL41 -> 30178.571 | AR41: 3466.67 | AS41: =+AO41+AQ41 -> 0 | AT41: =+AP41+AR41 -> 33645.241 | AV41: 7074.06 | AW41: =+AS41+AU41 -> 0 | AX41: =+AT41+AV41 -> 40719.301 | AZ41: 6568.76 | BB41: =+AR41+AV41+AZ41 -> 17109.49 | BD41: =AN41+BB41 -> 27654.294 | BE41: =+AY41+BA41 -> 0 | BF41: =AX41+AZ41 -> 47288.061 | BH41: 21791.11
B42: Channels | C42: Mt | F42: 6325.42 | H42: 6776.13 | I42: =+E42+G42 -> 0 | J42: =+F42+H42 -> 13101.55 | L42: 2524.241 | N42: =+F42+H42+L42 -> 15625.791 | P42: 6692.46 | Q42: =+M42+O42 -> 0 | R42: =+N42+P42 -> 22318.251 | T42: 7853.763 | U42: =+Q42+S42 -> 0 | V42: =+R42+T42 -> 30172.014 | X42: 10500.078 | Z42: =+P42+T42+X42 -> 25046.301 | AB42: =+N42+Z42 -> 40672.092 | AD42: 6104.51 | AE42: =+AA42+AC42 -> 0 | AF42: =+AB42+AD42 -> 46776.602 | AH42: 5492.372 | AI42: =+AE42+AG42 -> 0 | AJ42: =+AF42+AH42 -> 52268.974 | AL42: 10559.16 | AN42: =+AD42+AH42+AL42 -> 22156.042 | AO42: =+AK42+AM42 -> 0 | AP42: =AJ42+AL42 -> 62828.134 | AR42: 9128.59 | AS42: =+AO42+AQ42 -> 0 | AT42: =+AP42+AR42 -> 71956.724 | AV42: 7399.77 | AW42: =+AS42+AU42 -> 0 | AX42: =+AT42+AV42 -> 79356.494 | AZ42: 6661.67 | BB42: =+AR42+AV42+AZ42 -> 23190.03 | BD42: =AN42+BB42 -> 45346.072 | BE42: =+AY42+BA42 -> 0 | BF42: =AX42+AZ42 -> 86018.164 | BH42: 62409.791 | BJ42: 44187.11 | BL42: 4414.219
B43: Angles | C43: Mt | F43: 1210.601 | H43: 0 | I43: =+E43+G43 -> 0 | J43: =+F43+H43 -> 1210.601 | L43: 0 | N43: =+F43+H43+L43 -> 1210.601 | P43: 0 | Q43: =+M43+O43 -> 0 | R43: =+N43+P43 -> 1210.601 | T43: 0 | U43: =+Q43+S43 -> 0 | V43: =+R43+T43 -> 1210.601 | X43: 303.346 | Z43: =+P43+T43+X43 -> 303.346 | AB43: =+N43+Z43 -> 1513.947 | AD43: 1134.248 | AE43: =+AA43+AC43 -> 0 | AF43: =+AB43+AD43 -> 2648.195 | AH43: 0 | AI43: =+AE43+AG43 -> 0 | AJ43: =+AF43+AH43 -> 2648.195 | AL43: 239.126 | AN43: =+AD43+AH43+AL43 -> 1373.374 | AO43: =+AK43+AM43 -> 0 | AP43: =AJ43+AL43 -> 2887.321 | AR43: 0 | AS43: =+AO43+AQ43 -> 0 | AT43: =+AP43+AR43 -> 2887.321 | AV43: 0 | AW43: =+AS43+AU43 -> 0 | AX43: =+AT43+AV43 -> 2887.321 | AZ43: 0 | BB43: =+AR43+AV43+AZ43 -> 0 | BD43: =AN43+BB43 -> 1373.374 | BE43: =+AY43+BA43 -> 0 | BF43: =AX43+AZ43 -> 2887.321 | BH43: 4159.184 | BJ43: 920.38655 | BL43: 5739.5256
B44: Semis | C44: Mt | D44: =+D34 -> 649999.92 | E44: =+E34 -> 54000.487 | F44: =+F34 -> 62795.07 | G44: =+G34 -> 41500.441 | H44: =+H34 -> 46539 | I44: =+I34 -> 95500.928 | J44: =+J34 -> 109334.07 | K44: =+K34 -> 56500.271 | L44: =+L34 -> 62807.21 | M44: =+E44+G44+K44 -> 152001.2 | N44: =+F44+H44+L44 -> 172141.28 | O44: =+O34 -> 52000.374 | P44: =+P34 -> 66887 | Q44: =+Q34 -> 204001.57 | R44: =+R34 -> 239028.28 | S44: =+S34 -> 52000.374 | T44: =+T34 -> 44518.421 | U44: =+U34 -> 256001.95 | V44: =+V34 -> 283546.7 | ... AA44: =+AA34 -> 306001.85 | AB44: =+N44+Z44 -> 340936.24 | AC44: =+AC34 -> 57499.148 | AD44: =+AD34 -> 67828.27 | AE44: =+AE34 -> 363501 | AF44: =+AF34 -> 408764.51 | AG44: =+AG34 -> 55500.279 | AH44: =+AH34 -> 44044 | AI44: =+AI34 -> 419001.28 | AJ44: =+AJ34 -> 452808.51 | ... AN44: =+AN34 -> 168525.27 | AO44: =AI44+AK44 -> 477500.82 | AP44: =AJ44+AL44 -> 509461.51 | AQ44: =+AQ34 -> 58499.544 | AR44: =+AR34 -> 53231 | AS44: =+AS34 -> 536000.36 | AT44: =+AT34 -> 562692.51 | AU44: =+AU34 -> 54999.612 | AV44: =+AV34 -> 60925 | AW44: =+AW34 -> 590999.98 | AX44: =+AX34 -> 623617.51 | ... BC44: =+BC34 -> 343998.07 | BD44: =AN44+BB44 -> 335715.27 | BE44: =AW44+AY44 -> 649999.92 | BF44: =AX44+AZ44 -> 676651.51 | BG44: 660000.01 | BH44: 711198.96 | BI44: 669999.11 | BJ44: 832014.92 | BK44: =+BK34 -> 904433.83 | BL44: 937874.53 | BM44: 571999.74 | BN44: =+BN34 -> 877839.96
B45: TOTAL SALEABLE STEEL | C45: Mt | D45: =SUM(D37:D44) -> 2524999.9 | E45: =SUM(E37:E44) -> 213500.49 | F45: =SUM(F37:F44) -> 206040.95 | G45: =SUM(G37:G44) -> 178000.44 | H45: =SUM(H37:H44) -> 163072.97 | I45: =SUM(I37:I44) -> 391500.93 | J45: =SUM(J37:J44) -> 369113.91 | K45: =SUM(K37:K44) -> 173500.27 | ... BF45: =SUM(BF37:BF44) -> 2409644.1 | BG45: 2410000 | BH45: 2315208 | BI45: =SUM(BI37:BI44) -> 2369999.1 | BJ45: =SUM(BJ37:BJ44) -> 2160427.2 | BK45: =SUM(BK37:BK44) -> 2235274.9 | BL45: =SUM(BL37:BL44) -> 1823883.8 | BM45: =SUM(BM37:BM44) -> 2406999.7 | BN45: =SUM(BN37:BN44) -> 2093720.2
B46: COAL TAR | C46: Mt | D46: 50890.946 | E46: 4180.5385 | F46: 3925.65 | G46: 4319.8898 | H46: 3857.82 | I46: =+E46+G46 -> 8500.4283 | J46: =+F46+H46 -> 7783.47 | K46: 4180.5385 | L46: 3773.6565 | M46: =+E46+G46+K46 -> 12680.967 | N46: =+F46+H46+L46 -> 11557.126 | O46: 4319.8898 | P46: 3992.9 | Q46: =+M46+O46 -> 17000.857 | R46: =+N46+P46 -> 15550.026 | S46: 4263.1629 | T46: 3862 | U46: =+Q46+S46 -> 21264.019 | V46: =+R46+T46 -> 19412.026 | W46: 4125.6415 | X46: 3615.15 | Y46: =+O46+S46+W46 -> 12708.694 | Z46: =+P46+T46+X46 -> 11470.05 | AA46: =+M46+Y46 -> 25389.661 | AB46: =+N46+Z46 -> 23027.176 | AC46: 4319.8898 | AD46: 3687.19 | AE46: =+AA46+AC46 -> 29709.551 | AF46: =+AB46+AD46 -> 26714.366 | AG46: 4180.5385 | AH46: 3565.5 | AI46: =+AE46+AG46 -> 33890.089 | AJ46: =+AF46+AH46 -> 30279.866 | AK46: 4319.8898 | AL46: 3721.1 | AM46: =+AC46+AG46+AK46 -> 12820.318 | AN46: =+AD46+AH46+AL46 -> 10973.79 | AO46: =AI46+AK46 -> 38209.979 | AP46: =AJ46+AL46 -> 34000.966 | AQ46: 4319.8898 | AR46: 3674.175 | AS46: =+AO46+AQ46 -> 42529.869 | AT46: =+AP46+AR46 -> 37675.141 | AU46: 4041.1872 | AV46: 3478.3 | AW46: =+AS46+AU46 -> 46571.056 | AX46: =+AT46+AV46 -> 41153.442 | AY46: 4319.8898 | AZ46: 3716.2 | BA46: =+AQ46+AU46+AY46 -> 12680.967 | BB46: =+AR46+AV46+AZ46 -> 10868.675 | BC46: =AM46+BA46 -> 25501.285 | BD46: =AN46+BB46 -> 21842.465 | BE46: =AW46+AY46 -> 50890.946 | BF46: =AX46+AZ46 -> 44869.641 | BG46: 51086.019 | BH46: 48878.17 | BI46: 51086.383 | BJ46: 49592.55 | BK46: 48584.311 | BL46: 46678.95 | BM46: 46118.873 | BN46: 49237.57
B47: AMMONIUM SULPHATE | C47: Mt | D47: 10780.781 | E47: 884.7165 | F47: 830 | G47: 914.77465 | H47: 678 | I47: =+E47+G47 -> 1799.4912 | J47: =+F47+H47 -> 1508 | K47: 884.7165 | L47: 611 | M47: =+E47+G47+K47 -> 2684.2077 | N47: =+F47+H47+L47 -> 2119 | O47: 914.77465 | P47: 717 | Q47: =+M47+O47 -> 3598.9823 | R47: =+N47+P47 -> 2836 | S47: 906.55903 | T47: 710 | U47: =+Q47+S47 -> 4505.5413 | V47: =+R47+T47 -> 3546 | W47: 876.7659 | X47: 661 | Y47: =+O47+S47+W47 -> 2698.0996 | Z47: =+P47+T47+X47 -> 2088 | AA47: =+M47+Y47 -> 5382.3072 | AB47: =+N47+Z47 -> 4207 | AC47: 914.77465 | AD47: 528 | AE47: =+AA47+AC47 -> 6297.0819 | AF47: =+AB47+AD47 -> 4735 | AG47: 884.7165 | AH47: 529 | AI47: =+AE47+AG47 -> 7181.7984 | AJ47: =+AF47+AH47 -> 5264 | AK47: 914.77465 | AL47: 345 | AM47: =+AC47+AG47+AK47 -> 2714.2658 | AN47: =+AD47+AH47+AL47 -> 1402 | AO47: =AI47+AK47 -> 8096.573 | AP47: =AJ47+AL47 -> 5609 | AQ47: 914.77465 | AR47: 172.35 | AS47: =+AO47+AQ47 -> 9011.3477 | AT47: =+AP47+AR47 -> 5781.35 | AU47: 854.65835 | AV47: 433 | AW47: =+AS47+AU47 -> 9866.006 | AX47: =+AT47+AV47 -> 6214.35 | AY47: 914.77465 | AZ47: 445.5 | BA47: =+AQ47+AU47+AY47 -> 2684.2077 | BB47: =+AR47+AV47+AZ47 -> 1050.85 | BC47: =AM47+BA47 -> 5398.4735 | BD47: =AN47+BB47 -> 2452.85 | BE47: =AW47+AY47 -> 10780.781 | BF47: =AX47+AZ47 -> 6659.85 | BG47: 9611.7069 | BH47: 8145.2 | BI47: 16578.809 | BJ47: 8876.9 | BK47: 21728.852 | BL47: 10510.61 | BM47: 15654.415 | BN47: 12312.8
B49: Total casts | C49: No | D49: 17467.17 | E49: 1476.7296 | F49: 1442 | G49: 1231.4465 | H49: 1170 | I49: =+E49+G49 -> 2708.1761 | J49: =+F49+H49 -> 2612 | K49: 1204.2767 | L49: 1252 | M49: =+E49+G49+K49 -> 3912.4528 | N49: =+F49+H49+L49 -> 3864 | O49: 1495.5975 | P49: 1537 | Q49: =+M49+O49 -> 5408.0503 | R49: =+N49+P49 -> 5401 | S49: 1495.5975 | T49: 1493 | U49: =+Q49+S49 -> 6903.6478 | V49: =+R49+T49 -> 6894 | W49: 1451.5723 | X49: 1400 | Y49: =+O49+S49+W49 -> 4442.7673 | Z49: =+P49+T49+X49 -> 4430 | AA49: =+M49+Y49 -> 8355.2201 | AB49: =+N49+Z49 -> 8294 | AC49: 1539.6226 | AD49: 1490 | AE49: =+AA49+AC49 -> 9894.8428 | AF49: =+AB49+AD49 -> 9784 | AG49: 1489.3082 | AH49: 1265 | AI49: =+AE49+AG49 -> 11384.151 | AJ49: =+AF49+AH49 -> 11049 | AK49: 1545.9119 | AL49: 1439 | AM49: =+AC49+AG49+AK49 -> 4574.8428 | AN49: =+AD49+AH49+AL49 -> 4194 | AO49: =AI49+AK49 -> 12930.063 | AP49: =AJ49+AL49 -> 12488 | AQ49: 1545.9119 | AR49: 1452 | AS49: =+AO49+AQ49 -> 14475.975 | AT49: =+AP49+AR49 -> 13940 | AU49: 1438.9937 | AV49: 1429 | AW49: =+AS49+AU49 -> 15914.969 | AX49: =+AT49+AV49 -> 15369 | AY49: 1552.2013 | AZ49: 1466 | BA49: =+AQ49+AU49+AY49 -> 4537.1069 | BB49: =+AR49+AV49+AZ49 -> 4347 | BC49: =AM49+BA49 -> 9111.9497 | BD49: =AN49+BB49 -> 8541 | BE49: =AW49+AY49 -> 17467.17 | BF49: =AX49+AZ49 -> 16835 | BG49: 16666.667 | BH49: 16116 | BI49: 16344.715 | BJ49: 14624 | BK49: 15300.817 | BL49: 12158 | BM49: 16891.892 | BN49: 14151
F51: =+F35-F45 -> -0.004 | G51: =+G35-G45 -> 0 | H51: =+H35-H45 -> -0.01 | I51: =+I35-I45 -> 0 | J51: =+J35-J45 -> -0.014 | K51: =+K35-K45 -> 0 | L51: =+L35-L45 -> 0.004 | M51: =+M35-M45 -> 0 | ... BF51: =+BF35-BF45 -> -0.01296 | BI51: =+BI35-BI45 -> 0 | BJ51: =+BJ35-BJ45 -> -1.3323902 | BK51: =+BK35-BK45 -> 0 | BL51: =+BL35-BL45 -> 0.55446018 | BM51: =+BM35-BM45 -> 0 | BN51: =+BN35-BN45 -> 0

Sheet Maj Despatch Summ
B1: MAJOR DESPATCH SUMMARY 2023-24 (As per Finance CENVAT report)
E2: 30 | F2: 30 | G2: 31 | H2: 31 | I2: =+G2+E2 -> 61 | J2: =+H2+F2 -> 61 | K2: 30 | L2: 30 | M2: =+E2+G2+K2 -> 91 | N2: =+F2+H2+L2 -> 91 | O2: 31 | P2: 31 | Q2: =+M2+O2 -> 122 | R2: =+N2+P2 -> 122 | S2: 31 | T2: 31 | U2: =+Q2+S2 -> 153 | V2: =+R2+T2 -> 153 | W2: 30 | X2: 30 | Y2: =+O2+S2+W2 -> 92 | Z2: =+P2+T2+X2 -> 92 | AA2: =+M2+Y2 -> 183 | AB2: =+N2+Z2 -> 183 | AC2: 31 | AD2: 31 | AE2: =AA2+AC2 -> 214 | AF2: =AB2+AD2 -> 214 | AG2: 30 | AH2: 30 | AI2: =AE2+AG2 -> 244 | AJ2: =AF2+AH2 -> 244 | AK2: 31 | AL2: 31 | AM2: =+AC2+AG2+AK2 -> 92 | AN2: =+AD2+AH2+AL2 -> 92 | AO2: =AI2+AK2 -> 275 | AP2: =AJ2+AL2 -> 275 | AQ2: 31 | AR2: 31 | AS2: =AO2+AQ2 -> 306 | AT2: =AP2+AR2 -> 306 | AU2: 29 | AV2: 29 | AW2: =AS2+AU2 -> 335 | AX2: =AT2+AV2 -> 335 | AY2: 31 | AZ2: 31 | BA2: =+AQ2+AU2+AY2 -> 91 | BB2: =+AR2+AV2+AZ2 -> 91 | BC2: =AM2+BA2 -> 183 | BD2: =AN2+BB2 -> 183 | BE2: =AW2+AY2 -> 366 | BF2: =AX2+AZ2 -> 366 | BK2: 365 | BL2: 365 | BM2: 366 | BN2: 366
B3: ITEM | C3: Unit | D3: 2023-24 ABP | E3: Apr'23 | G3: May'23 | I3: 2M | K3: Jun'23 | M3: QTR-1 | O3: Jul'23 | Q3: 4M | S3: Aug'23 | U3: 5M | W3: Sep'23 | Y3: QTR-2 | AA3: H1 | AC3: Oct'23 | AE3: 7M | AG3: Nov'23 | AI3: 8M | AK3: Dec'23 | AM3: QTR-3 | AO3: 9M | AQ3: Jan'24 | AS3: 10M | AU3: Feb'24 | AW3: 11M | AY3: Mar'24 | BA3: QTR-4 | BC3: H2 | BE3: 2023-24 | BG3: 2022-23 | BI3: 2021-22 | BK3: 2020-21 | BM3: 2019-20
E4: ABP | F4: ACT | G4: ABP | H4: ACT | I4: ABP | J4: ACT | K4: ABP | L4: ACT | M4: ABP | N4: ACT | O4: ABP | P4: ACT | Q4: ABP | R4: ACT | S4: ABP | T4: ACT | U4: ABP | V4: ACT | W4: ABP | X4: ACT | Y4: ABP | Z4: ACT | AA4: ABP | AB4: ACT | AC4: ABP | AD4: ACT | AE4: ABP | AF4: ACT | AG4: ABP | AH4: ACT | AI4: ABP | AJ4: ACT | AK4: ABP | AL4: ACT | AM4: ABP | AN4: ACT | AO4: ABP | AP4: ACT | AQ4: ABP | AR4: ACT | AS4: ABP | AT4: ACT | AU4: ABP | AV4: ACT | AW4: ABP | AX4: ACT | AY4: ABP | AZ4: ACT | BA4: ABP | BB4: ACT | BC4: ABP | BD4: ACT | BE4: ABP | BF4: ACT | BG4: ABP | BH4: ACT | BI4: ABP | BJ4: ACT | BK4: ABP | BL4: ACT | BM4: ABP | BN4: ACT
B5: Saleable Steel (mill-wise)
B6: MKTG-Plant sales | C6: MT | D6: =20000+1500 -> 21500 | E6: =1500+200 -> 1700 | F6: 1921.85 | G6: =1500+100 -> 1600 | H6: 4260.13 | I6: =+E6+G6 -> 3300 | J6: =+F6+H6 -> 6181.98 | K6: 2100 | L6: 1412.02 | M6: =+E6+G6+K6 -> 5400 | N6: =+F6+H6+L6 -> 7594 | O6: 2100 | P6: 1785.37 | Q6: =+M6+O6 -> 7500 | R6: =+N6+P6 -> 9379.37 | S6: 1600 | T6: 1518.53 | U6: =+Q6+S6 -> 9100 | V6: =+R6+T6 -> 10897.9 | W6: 1700 | X6: 2496.45 | Y6: =+O6+S6+W6 -> 5400 | Z6: =+P6+T6+X6 -> 5800.35 | AA6: =+M6+Y6 -> 10800 | AB6: =+N6+Z6 -> 13394.35 | AC6: 1600 | AD6: 2994.67 | AE6: =+AA6+AC6 -> 12400 | AF6: =+AB6+AD6 -> 16389.02 | AG6: 1600 | AH6: 2457.06 | AI6: =+AE6+AG6 -> 14000 | AJ6: =+AF6+AH6 -> 18846.08 | AK6: 1600 | AL6: 1302.1 | AM6: =+AC6+AG6+AK6 -> 4800 | AN6: =+AD6+AH6+AL6 -> 6753.83 | AO6: =AI6+AK6 -> 15600 | AP6: =AJ6+AL6 -> 20148.18 | AQ6: 2200 | AR6: 2913.06 | AS6: =+AO6+AQ6 -> 17800 | AT6: =+AP6+AR6 -> 23061.24 | AU6: 1600 | AV6: 2516.6 | AW6: =+AS6+AU6 -> 19400 | AX6: =+AT6+AV6 -> 25577.84 | AY6: 2100 | AZ6: 5072 | BA6: =+AQ6+AU6+AY6 -> 5900 | BB6: =+AR6+AV6+AZ6 -> 10501.66 | BC6: =AM6+BA6 -> 10700 | BD6: =AN6+BB6 -> 17255.49 | BE6: =+AW6+AY6 -> 21500 | BF6: =+AX6+AZ6 -> 30649.84 | BG6: 25500 | BH6: 34807.22 | BI6: 16050 | BJ6: 33201.15 | BK6: 0 | BL6: 35268.25 | BM6: 2000 | BN6: 28405.85
B7: IPT | C7: MT | D7: 0 | E7: 0 | F7: 0 | G7: 0 | H7: 103 | I7: =+E7+G7 -> 0 | J7: =+F7+H7 -> 103 | K7: 0 | L7: 0 | M7: =+E7+G7+K7 -> 0 | N7: =+F7+H7+L7 -> 103 | O7: 0 | P7: 2735.94 | Q7: =+M7+O7 -> 0 | R7: =+N7+P7 -> 2838.94 | S7: 0 | T7: 237.26 | U7: =+Q7+S7 -> 0 | V7: =+R7+T7 -> 3076.2 | W7: 0 | X7: 0 | Y7: =+O7+S7+W7 -> 0 | Z7: =+P7+T7+X7 -> 2973.2 | AA7: =+M7+Y7 -> 0 | AB7: =+N7+Z7 -> 3076.2 | AC7: 0 | AD7: 0 | AE7: =+AA7+AC7 -> 0 | AF7: =+AB7+AD7 -> 3076.2 | AG7: 0 | AH7: 0 | AI7: =+AE7+AG7 -> 0 | AJ7: =+AF7+AH7 -> 3076.2 | AK7: 0 | AL7: 0 | AM7: =+AC7+AG7+AK7 -> 0 | AN7: =+AD7+AH7+AL7 -> 0 | AO7: =AI7+AK7 -> 0 | AP7: =AJ7+AL7 -> 3076.2 | AQ7: 0 | AR7: 0 | AS7: =+AO7+AQ7 -> 0 | AT7: =+AP7+AR7 -> 3076.2 | AU7: 0 | AV7: 0 | AW7: =+AS7+AU7 -> 0 | AX7: =+AT7+AV7 -> 3076.2 | AY7: 0 | AZ7: 0 | BA7: =+AQ7+AU7+AY7 -> 0 | BB7: =+AR7+AV7+AZ7 -> 0 | BC7: =AM7+BA7 -> 0 | BD7: =AN7+BB7 -> 0 | BE7: =+AW7+AY7 -> 0 | BF7: =+AX7+AZ7 -> 3076.2 | BG7: 123000 | BH7: 42263.08 | BI7: 0 | BJ7: 71707.42 | BK7: 10800 | BL7: 9758.51 | BM7: 24210 | BN7: 5928.095
B8: CMO-WR MILL | C8: MT | D8: 498500 | E8: 42300 | F8: 36663.08 | G8: 36400 | H8: 32908.66 | I8: =+E8+G8 -> 78700 | J8: =+F8+H8 -> 69571.74 | K8: 33900 | L8: 32223.46 | M8: =+E8+G8+K8 -> 112600 | N8: =+F8+H8+L8 -> 101795.2 | O8: 43400 | P8: 41040.98 | Q8: =+M8+O8 -> 156000 | R8: =+N8+P8 -> 142836.18 | S8: 43400 | T8: 48167.69 | U8: =+Q8+S8 -> 199400 | V8: =+R8+T8 -> 191003.87 | W8: 42300 | X8: 43039.34 | Y8: =+O8+S8+W8 -> 129100 | Z8: =+P8+T8+X8 -> 132248.01 | AA8: =+M8+Y8 -> 241700 | AB8: =+N8+Z8 -> 234043.21 | AC8: 43400 | AD8: 41924.59 | AE8: =+AA8+AC8 -> 285100 | AF8: =+AB8+AD8 -> 275967.8 | AG8: 42400 | AH8: 38006.17 | AI8: =+AE8+AG8 -> 327500 | AJ8: =+AF8+AH8 -> 313973.97 | AK8: 43400 | AL8: 39686.53 | AM8: =+AC8+AG8+AK8 -> 129200 | AN8: =+AD8+AH8+AL8 -> 119617.29 | AO8: =AI8+AK8 -> 370900 | AP8: =AJ8+AL8 -> 353660.5 | AQ8: 43300 | AR8: 43617.43 | AS8: =+AO8+AQ8 -> 414200 | AT8: =+AP8+AR8 -> 397277.93 | AU8: 40900 | AV8: 35011.66 | AW8: =+AS8+AU8 -> 455100 | AX8: =+AT8+AV8 -> 432289.59 | AY8: 43400 | AZ8: 41204.62 | BA8: =+AQ8+AU8+AY8 -> 127600 | BB8: =+AR8+AV8+AZ8 -> 119833.71 | BC8: =AM8+BA8 -> 256800 | BD8: =AN8+BB8 -> 239451 | BE8: =+AW8+AY8 -> 498500 | BF8: =+AX8+AZ8 -> 473494.21 | BG8: 498500 | BH8: 453432.75 | BI8: 498500 | BJ8: 467953.64 | BK8: 435166.29 | BL8: 351267.02 | BM8: 498000 | BN8: 399090.26
B9: CMO-BAR MILL | C9: MT | D9: 850000 | E9: 72500 | F9: 67261.57 | G9: 62500 | H9: 58474.66 | I9: =+E9+G9 -> 135000 | J9: =+F9+H9 -> 125736.23 | K9: 47000 | L9: 43079.61 | M9: =+E9+G9+K9 -> 182000 | N9: =+F9+H9+L9 -> 168815.84 | O9: 75000 | P9: 76651.34 | Q9: =+M9+O9 -> 257000 | R9: =+N9+P9 -> 245467.18 | S9: 75000 | T9: 86324.79 | U9: =+Q9+S9 -> 332000 | V9: =+R9+T9 -> 331791.97 | W9: 73000 | X9: 63071.09 | Y9: =+O9+S9+W9 -> 223000 | Z9: =+P9+T9+X9 -> 226047.22 | AA9: =+M9+Y9 -> 405000 | AB9: =+N9+Z9 -> 394863.06 | AC9: 75500 | AD9: 60175.53 | AE9: =+AA9+AC9 -> 480500 | AF9: =+AB9+AD9 -> 455038.59 | AG9: 73000 | AH9: 58175.82 | AI9: =+AE9+AG9 -> 553500 | AJ9: =+AF9+AH9 -> 513214.41 | AK9: 75500 | AL9: 69407.98 | AM9: =+AC9+AG9+AK9 -> 224000 | AN9: =+AD9+AH9+AL9 -> 187759.33 | AO9: =AI9+AK9 -> 629000 | AP9: =AJ9+AL9 -> 582622.39 | AQ9: 75500 | AR9: 65803.18 | AS9: =+AO9+AQ9 -> 704500 | AT9: =+AP9+AR9 -> 648425.57 | AU9: 70000 | AV9: 64969.65 | AW9: =+AS9+AU9 -> 774500 | AX9: =+AT9+AV9 -> 713395.22 | AY9: 75500 | AZ9: 68007.23 | BA9: =+AQ9+AU9+AY9 -> 221000 | BB9: =+AR9+AV9+AZ9 -> 198780.06 | BC9: =AM9+BA9 -> 445000 | BD9: =AN9+BB9 -> 386539.39 | BE9: =+AW9+AY9 -> 850000 | BF9: =+AX9+AZ9 -> 781402.45 | BG9: 780000 | BH9: 768402.31 | BI9: 750000 | BJ9: 648761.89 | BK9: 674874.74 | BL9: 436958.46 | BM9: 800000 | BN9: 612890.55
B10: CMO-US MILL | C10: MT | D10: 525000 | E10: 44500 | F10: 37547.6 | G10: 37500 | H10: 29799.49 | I10: =+E10+G10 -> 82000 | J10: =+F10+H10 -> 67347.09 | K10: 36000 | L10: 23668.07 | M10: =+E10+G10+K10 -> 118000 | N10: =+F10+H10+L10 -> 91015.16 | O10: 46000 | P10: 38466.17 | Q10: =+M10+O10 -> 164000 | R10: =+N10+P10 -> 129481.33 | S10: 46000 | T10: 44584.21 | U10: =+Q10+S10 -> 210000 | V10: =+R10+T10 -> 174065.54 | W10: 44500 | X10: 33234.17 | Y10: =+O10+S10+W10 -> 136500 | Z10: =+P10+T10+X10 -> 116284.55 | AA10: =+M10+Y10 -> 254500 | AB10: =+N10+Z10 -> 207299.71 | AC10: 46000 | AD10: 40148.93 | AE10: =+AA10+AC10 -> 300500 | AF10: =+AB10+AD10 -> 247448.64 | AG10: 44500 | AH10: 39586.21 | AI10: =+AE10+AG10 -> 345000 | AJ10: =+AF10+AH10 -> 287034.85 | AK10: 46000 | AL10: 40554.65 | AM10: =+AC10+AG10+AK10 -> 136500 | AN10: =+AD10+AH10+AL10 -> 120289.79 | AO10: =AI10+AK10 -> 391000 | AP10: =AJ10+AL10 -> 327589.5 | AQ10: 46000 | AR10: 40291.74 | AS10: =+AO10+AQ10 -> 437000 | AT10: =+AP10+AR10 -> 367881.24 | AU10: 42000 | AV10: 38561.13 | AW10: =+AS10+AU10 -> 479000 | AX10: =+AT10+AV10 -> 406442.37 | AY10: 46000 | AZ10: 46360.22 | BA10: =+AQ10+AU10+AY10 -> 134000 | BB10: =+AR10+AV10+AZ10 -> 125213.09 | BC10: =AM10+BA10 -> 270500 | BD10: =AN10+BB10 -> 245502.88 | BE10: =+AW10+AY10 -> 525000 | BF10: =+AX10+AZ10 -> 452802.59 | BG10: 470000 | BH10: 357334.79 | BI10: 445000 | BJ10: 214319.65 | BK10: 220000 | BL10: 100400.4 | BM10: 535000 | BN10: 167166.99
B11: CMO-SEMIS | C11: MT | D11: 629999.92 | E11: 52500.487 | F11: 53555.83 | G11: 40000.441 | H11: 44868.35 | I11: =+E11+G11 -> 92500.928 | J11: =+F11+H11 -> 98424.18 | K11: 54500.271 | L11: 46793.86 | M11: =+E11+G11+K11 -> 147001.2 | N11: =+F11+H11+L11 -> 145218.04 | O11: 50000.374 | P11: 63562.36 | Q11: =+M11+O11 -> 197001.57 | R11: =+N11+P11 -> 208780.4 | S11: 50500.374 | T11: 55744.74 | U11: =+Q11+S11 -> 247501.95 | V11: =+R11+T11 -> 264525.14 | W11: 48500 | X11: 55406.37 | Y11: =+O11+S11+W11 -> 149000.75 | Z11: =+P11+T11+X11 -> 174713.47 | AA11: =+M11+Y11 -> 296001.95 | AB11: =+N11+Z11 -> 319931.51 | AC11: 55999.148 | AD11: 59697.33 | AE11: =+AA11+AC11 -> 352001.1 | AF11: =+AB11+AD11 -> 379628.84 | AG11: 54000.279 | AH11: 44349.57 | AI11: =+AE11+AG11 -> 406001.37 | AJ11: =+AF11+AH11 -> 423978.41 | AK11: 56999.544 | AL11: 54537.14 | AM11: =+AC11+AG11+AK11 -> 166998.97 | AN11: =+AD11+AH11+AL11 -> 158584.04 | AO11: =AI11+AK11 -> 463000.92 | AP11: =AJ11+AL11 -> 478515.55 | AQ11: 56499.544 | AR11: 44164.2 | AS11: =+AO11+AQ11 -> 519500.46 | AT11: =+AP11+AR11 -> 522679.75 | AU11: 53499.612 | AV11: 46507.46 | AW11: =+AS11+AU11 -> 573000.07 | AX11: =+AT11+AV11 -> 569187.21 | AY11: 56999.94 | AZ11: 54278.96 | BA11: =+AQ11+AU11+AY11 -> 166999.1 | BB11: =+AR11+AV11+AZ11 -> 144950.62 | BC11: =AM11+BA11 -> 333998.07 | BD11: =AN11+BB11 -> 303534.66 | BE11: =+AW11+AY11 -> 630000.01 | BF11: =+AX11+AZ11 -> 623466.17 | BG11: 513000.01 | BH11: 641816.63 | BI11: 659950.15 | BJ11: 742311.77 | BK11: 893633.78 | BL11: 944002.21 | BM11: 547789.74 | BN11: 836451
B12: TOTAL | C12: MT | D12: =SUM(D6:D11) -> 2524999.9 | E12: =SUM(E6:E11) -> 213500.49 | F12: =SUM(F6:F11) -> 196949.93 | G12: =SUM(G6:G11) -> 178000.44 | H12: =SUM(H6:H11) -> 170414.29 | I12: =SUM(I6:I11) -> 391500.93 | J12: =SUM(J6:J11) -> 367364.22 | K12: =SUM(K6:K11) -> 173500.27 | ... BF12: =SUM(BF6:BF11) -> 2364891.5 | BG12: 2410000 | BH12: 2298056.8 | BI12: 2369500.2 | BJ12: 2178255.5 | BK12: 2234474.8 | BL12: 1877654.8 | BM12: 2406999.7 | BN12: 2049932.7
B13: Consideration in internal consumption | D13: Saleable production Plan: 2410000 (1500 T has been kept in plan for Internal consumption) | E13: Saleable production Plan: 201135 (200 T has been kept in plan for Internal consumption) | G13: Saleable production Plan: 201135 (200 T has been kept in plan for Internal consumption) | K13: Saleable production Plan: 201135 (200 T has been kept in plan for Internal consumption) | O13: Saleable production Plan: 201135 (200 T has been kept in plan for Internal consumption) | AC13: Saleable production Plan: 201135 (200 T has been kept in plan for Internal consumption) | AG13: Saleable production Plan: 201135 (200 T has been kept in plan for Internal consumption) | AQ13: Saleable production Plan: 201135 (200 T has been kept in plan for Internal consumption) | AU13: Saleable production Plan: 201135 (200 T has been kept in plan for Internal consumption) | AY13: Saleable production Plan: 201135 (200 T has been kept in plan for Internal consumption)
B14: Saleable Steel (Sale type-wise)
B15: IPT | C15: MT | D15: =+D12 -> 2524999.9 | E15: =+E12 -> 213500.49 | F15: =+F7 -> 0 | G15: =+G12 -> 178000.44 | H15: =+H7 -> 103 | I15: =+E15+G15 -> 391500.93 | J15: =+F15+H15 -> 103 | K15: =+K12 -> 173500.27 | L15: =+L7 -> 0 | M15: =+E15+G15+K15 -> 565001.2 | N15: =+F15+H15+L15 -> 103 | O15: =+O12 -> 216500.37 | P15: =+P7 -> 2735.94 | Q15: =+M15+O15 -> 781501.57 | R15: =+N15+P15 -> 2838.94 | S15: =+S12 -> 216500.37 | T15: =+T7 -> 237.26 | U15: =+Q15+S15 -> 998001.95 | V15: =+R15+T15 -> 3076.2 | W15: =+W12 -> 210000 | X15: 0 | Y15: =+O15+S15+W15 -> 643000.75 | Z15: =+P15+T15+X15 -> 2973.2 | AA15: =+M15+Y15 -> 1208001.9 | AB15: =+N15+Z15 -> 3076.2 | AC15: =+AC12 -> 222499.15 | AD15: =+AD7 -> 0 | AE15: =+AA15+AC15 -> 1430501.1 | AF15: =+AB15+AD15 -> 3076.2 | AG15: =+AG12 -> 215500.28 | AH15: =+AH7 -> 0 | AI15: =+AE15+AG15 -> 1646001.4 | AJ15: =+AF15+AH15 -> 3076.2 | AK15: =+AK12 -> 223499.54 | AL15: 0 | AM15: =+AC15+AG15+AK15 -> 661498.97 | AN15: =+AD15+AH15+AL15 -> 0 | AO15: =AI15+AK15 -> 1869500.9 | AP15: =AJ15+AL15 -> 3076.2 | AQ15: =+AQ12 -> 223499.54 | AR15: =+AR7 -> 0 | AS15: =+AO15+AQ15 -> 2093000.5 | AT15: =+AP15+AR15 -> 3076.2 | AU15: =+AU12 -> 207999.61 | AV15: =+AV7 -> 0 | AW15: =+AS15+AU15 -> 2301000.1 | AX15: =+AT15+AV15 -> 3076.2 | AY15: =+AY12 -> 223999.94 | AZ15: =+AZ7 -> 0 | BA15: =+AQ15+AU15+AY15 -> 655499.1 | BB15: =+AR15+AV15+AZ15 -> 0 | BC15: =+AM15+BA15 -> 1316998.1 | BD15: =AN15+BB15 -> 0 | BE15: =+AW15+AY15 -> 2525000 | BF15: =+AX15+AZ15 -> 3076.2 | BG15: 2410000 | BH15: 42263.08 | BI15: 2369500.2 | BJ15: 71707.42 | BK15: 2234474.8 | BL15: 9758.51 | BM15: =+BM12 -> 2406999.7 | BN15: 5928.249
B16: CMO DIR | C16: MT | F16: 104891.27 | H16: 87682.64 | J16: =+F16+H16 -> 192573.91 | L16: 99454.32 | N16: =+F16+H16+L16 -> 292028.23 | P16: 113441.65 | R16: =+N16+P16 -> 405469.88 | T16: 176869.32 | V16: =+R16+T16 -> 582339.2 | X16: 154305.76 | Z16: =+P16+T16+X16 -> 444616.73 | AB16: =+N16+Z16 -> 736644.96 | AD16: 123656.59 | AF16: =+AB16+AD16 -> 860301.55 | AH16: 86468.88 | AJ16: =+AF16+AH16 -> 946770.43 | AL16: 111571.93 | AN16: =+AD16+AH16+AL16 -> 321697.4 | AP16: =AJ16+AL16 -> 1058342.4 | AR16: 119773.9 | AT16: =+AP16+AR16 -> 1178116.3 | AV16: 111589.56 | AX16: =+AT16+AV16 -> 1289705.8 | AZ16: 153590.21 | BB16: =+AR16+AV16+AZ16 -> 384953.67 | BD16: =AN16+BB16 -> 706651.07 | BF16: =+AX16+AZ16 -> 1443296 | BH16: 1325226.7 | BJ16: 1097093.1 | BL16: 691326.52 | BN16: 569419.83
B17: CMO SYD | C17: MT | F17: 84895.57 | H17: 70112.74 | J17: =+F17+H17 -> 155008.31 | L17: 40887.3 | N17: =+F17+H17+L17 -> 195895.61 | P17: 97492.3 | R17: =+N17+P17 -> 293387.91 | T17: 57871.63 | V17: =+R17+T17 -> 351259.54 | X17: 33474.99 | Z17: =+P17+T17+X17 -> 188838.92 | AB17: =+N17+Z17 -> 384734.53 | AD17: 69838.6 | AF17: =+AB17+AD17 -> 454573.13 | AH17: 89546.19 | AJ17: =+AF17+AH17 -> 544119.32 | AL17: 89920.91 | AN17: =+AD17+AH17+AL17 -> 249305.7 | AP17: =AJ17+AL17 -> 634040.23 | AR17: 74069.33 | AT17: =+AP17+AR17 -> 708109.56 | AV17: 70681.4 | AX17: =+AT17+AV17 -> 778790.96 | AZ17: 50613.44 | BB17: =+AR17+AV17+AZ17 -> 195364.17 | BD17: =AN17+BB17 -> 444669.87 | BF17: =+AX17+AZ17 -> 829404.4 | BH17: 809005.31 | BJ17: 567271.22 | BL17: 479205.15 | BN17: 909567
B18: MKTG DIR (DEF) | C18: MT | F18: =+F6 -> 1921.85 | H18: =+H6 -> 4260.13 | J18: =+F18+H18 -> 6181.98 | L18: =+L6 -> 1412.02 | N18: =+F18+H18+L18 -> 7594 | P18: =+P6 -> 1785.37 | R18: =+N18+P18 -> 9379.37 | T18: =+T6 -> 1518.53 | V18: =+R18+T18 -> 10897.9 | X18: =+X6 -> 2496.45 | Z18: =+P18+T18+X18 -> 5800.35 | AB18: =+N18+Z18 -> 13394.35 | AD18: =+AD6 -> 2994.67 | AF18: =+AB18+AD18 -> 16389.02 | AH18: =+AH6 -> 2457.06 | AJ18: =+AF18+AH18 -> 18846.08 | AL18: 1302.1 | AN18: =+AD18+AH18+AL18 -> 6753.83 | AP18: =AJ18+AL18 -> 20148.18 | AR18: =+AR6 -> 2913.06 | AT18: =+AP18+AR18 -> 23061.24 | AV18: =+AV6 -> 2516.6 | AX18: =+AT18+AV18 -> 25577.84 | AZ18: =+AZ6 -> 5072 | BB18: =+AR18+AV18+AZ18 -> 10501.66 | BD18: =AN18+BB18 -> 17255.49 | BF18: =+AX18+AZ18 -> 30649.84 | BH18: 34807.22 | BJ18: 33201.15 | BL18: 35268.25 | BN18: 28405.85
B19: EXPORT | C19: MT | F19: 5241.24 | H19: 8255.78 | J19: =+F19+H19 -> 13497.02 | L19: 5423.38 | N19: =+F19+H19+L19 -> 18920.4 | P19: 8786.9 | R19: =+N19+P19 -> 27707.3 | T19: 80.48 | V19: =+R19+T19 -> 27787.78 | X19: 6970.22 | Z19: =+P19+T19+X19 -> 15837.6 | AB19: =+N19+Z19 -> 34758 | AD19: 8451.19 | AF19: =+AB19+AD19 -> 43209.19 | AH19: 4102.7 | AJ19: =+AF19+AH19 -> 47311.89 | AL19: 2693.46 | AN19: =+AD19+AH19+AL19 -> 15247.35 | AP19: =AJ19+AL19 -> 50005.35 | AR19: 33.32 | AT19: =+AP19+AR19 -> 50038.67 | AV19: 2778.94 | AX19: =+AT19+AV19 -> 52817.61 | AZ19: 5647.38 | BB19: =+AR19+AV19+AZ19 -> 8459.64 | BD19: =AN19+BB19 -> 23706.99 | BF19: =+AX19+AZ19 -> 58464.99 | BH19: 86754.52 | BJ19: 408982.58 | BL19: 662096.98 | BN19: 536611.98
B20: % DIRECT (IPT+CMO DIR+ EXPORT+ PLANT SALES) | C20: % | F20: =+((F16+F18+F15+F19)/F12)*100 -> 56.894846 | H20: =+((H16+H18+H15+H19)/H12)*100 -> 58.857476 | J20: =+((+J15+J16+J18+J19)/J12)*100 -> 57.805278 | L20: =+((L16+L18+L15+L19)/L12)*100 -> 72.218965 | N20: =+((+N15+N16+N18+N19)/N12)*100 -> 61.928103 | P20: =+((P16+P18+P15+P19)/P12)*100 -> 56.523653 | R20: =+((R16+R18+R15+R19)/R12)*100 -> 60.287696 | T20: =+((T16+T18+T15+T19)/T12)*100 -> 75.537953 | V20: =+((V16+V18+V15+V19)/V12)*100 -> 63.986701 | X20: =+((X16+X18+X15+X19)/X12)*100 -> 83.028934 | Z20: =+((Z16+Z18+Z15+Z19)/Z12)*100 -> 71.303989 | AB20: =+((AB16+AB18+AB15+AB19)/AB12)*100 -> 67.189844 | AD20: =+((AD16+AD18+AD15+AD19)/AD12)*100 -> 65.922591 | AF20: =+((+AF15+AF16+AF18+AF19)/AF12)*100 -> 67.001312 | AH20: =+((AH16+AH18+AH15+AH19)/AH12)*100 -> 50.953705 | AJ20: =+((+AJ15+AJ16+AJ18+AJ19)/AJ12)*100 -> 65.123327 | AL20: =+((AL16+AL18+AL15+AL19)/AL12)*100 -> 56.240396 | AN20: =+((AN16+AN18+AN15+AN19)/AN12)*100 -> 57.95887 | AP20: =+((+AP15+AP16+AP18+AP19)/AP12)*100 -> 64.089499 | AR20: =+((AR16+AR18+AR15+AR19)/AR12)*100 -> 62.361158 | AT20: =+((+AT15+AT16+AT18+AT19)/AT12)*100 -> 63.916181 | AV20: =+((AV16+AV18+AV15+AV19)/AV12)*100 -> 62.316618 | AX20: =+((+AX15+AX16+AX18+AX19)/AX12)*100 -> 63.776633 | AZ20: =+((AZ16+AZ18+AZ15+AZ19)/AZ12)*100 -> 76.450434 | BB20: =+((BB16+BB18+BB15+BB19)/BB12)*100 -> 67.400138 | BD20: =+((BD16+BD18+BD15+BD19)/BD12)*100 -> 62.704348 | BF20: =+((+BF15+BF16+BF18+BF19)/BF12)*100 -> 64.928437 | BH20: 64.796113 | BJ20: 70.665579 | BL20: =+((BL16+BL18+BL15+BL19)/BL12)*100 -> 74.478558 | BN20: =+((BN16+BN18+BN15+BN19)/BN12)*100 -> 55.62943
B21: Saleable Steel (Shipping Mode-wise)
B22: RAIL | C22: MT | D22: =+D12 -> 2524999.9 | E22: =+E12 -> 213500.49 | F22: 159666.08 | G22: =+G12 -> 178000.44 | H22: 141426.82 | I22: =+I12 -> 391500.93 | J22: =+F22+H22 -> 301092.9 | K22: =+K12 -> 173500.27 | L22: 112183.96 | M22: =+M12 -> 565001.2 | N22: =+F22+H22+L22 -> 413276.86 | O22: =+O12 -> 216500.37 | P22: 172985.62 | Q22: =+Q12 -> 781501.57 | R22: =+N22+P22 -> 586262.48 | S22: =+S12 -> 216500.37 | T22: 178397.7 | U22: =+U12 -> 998001.95 | V22: =+R22+T22 -> 764660.18 | W22: =+W12 -> 210000 | X22: 154561.7 | Y22: =+Y12 -> 643000.75 | Z22: =+P22+T22+X22 -> 505945.02 | AA22: =+AA12 -> 1208001.9 | AB22: =+N22+Z22 -> 919221.88 | AC22: =+AC12 -> 222499.15 | AD22: 164873.26 | AE22: =+AE12 -> 1430501.1 | AF22: =+AB22+AD22 -> 1084095.1 | AG22: =+AG12 -> 215500.28 | AH22: 154044.05 | AI22: =+AI12 -> 1646001.4 | AJ22: =+AF22+AH22 -> 1238139.2 | AK22: =+AK12 -> 223499.54 | AL22: 166233.32 | AM22: =+AM12 -> 661498.97 | AN22: =+AD22+AH22+AL22 -> 485150.63 | AO22: =AI22+AK22 -> 1869500.9 | AP22: =AJ22+AL22 -> 1404372.5 | AQ22: =+AQ12 -> 223499.54 | AR22: 151596.9 | AS22: =+AS12 -> 2093000.5 | AT22: =+AP22+AR22 -> 1555969.4 | AU22: =+AU12 -> 207999.61 | AV22: 133782.46 | AW22: =+AW12 -> 2301000.1 | AX22: =+AT22+AV22 -> 1689751.9 | AY22: =+AY12 -> 223999.94 | AZ22: 158752.4 | BA22: =+BA12 -> 655499.1 | BB22: =+AR22+AV22+AZ22 -> 444131.76 | BC22: =+BC12 -> 1316998.1 | BD22: =AN22+BB22 -> 929282.39 | BE22: =+BE12 -> 2525000 | BF22: =+AX22+AZ22 -> 1848504.3 | BG22: 2410000 | BH22: 1959110.7 | BI22: 2369500.2 | BJ22: 1882591.4 | BK22: 2234474.8 | BL22: 1557181.9 | BM22: =+BM12 -> 2406999.7 | BN22: 1655527.4
B23: ROAD | C23: MT | F23: 37283.85 | H23: 28987.47 | J23: =+F23+H23 -> 66271.32 | L23: 34993.06 | N23: =+F23+H23+L23 -> 101264.38 | P23: 51256.54 | R23: =+N23+P23 -> 152520.92 | T23: 58179.52 | V23: =+R23+T23 -> 210700.44 | X23: 42685.72 | Z23: =+P23+T23+X23 -> 152121.78 | AB23: =+N23+Z23 -> 253386.16 | AD23: 40067.79 | AF23: =+AB23+AD23 -> 293453.95 | AH23: 28530.78 | AJ23: =+AF23+AH23 -> 321984.73 | AL23: 39255.08 | AN23: =+AD23+AH23+AL23 -> 107853.65 | AP23: =AJ23+AL23 -> 361239.81 | AR23: 45192.71 | AT23: =+AP23+AR23 -> 406432.52 | AV23: 53784.04 | AX23: =+AT23+AV23 -> 460216.56 | AZ23: 56170.33 | BB23: =+AR23+AV23+AZ23 -> 155147.08 | BD23: =AN23+BB23 -> 263000.73 | BF23: =+AX23+AZ23 -> 516386.89 | BH23: 338946.25 | BJ23: 295664.13 | BL23: 320472.9 | BN23: 394405.54
B24: TOTAL | C24: MT | F24: =SUM(F22:F23) -> 196949.93 | H24: =SUM(H22:H23) -> 170414.29 | J24: =SUM(J22:J23) -> 367364.22 | L24: =SUM(L22:L23) -> 147177.02 | N24: =SUM(N22:N23) -> 514541.24 | P24: =SUM(P22:P23) -> 224242.16 | R24: =SUM(R22:R23) -> 738783.4 | T24: =SUM(T22:T23) -> 236577.22 | V24: =SUM(V22:V23) -> 975360.62 | X24: =SUM(X22:X23) -> 197247.42 | Z24: =SUM(Z22:Z23) -> 658066.8 | AB24: =SUM(AB22:AB23) -> 1172608 | AD24: =SUM(AD22:AD23) -> 204941.05 | AF24: =SUM(AF22:AF23) -> 1377549.1 | AH24: =SUM(AH22:AH23) -> 182574.83 | AJ24: =SUM(AJ22:AJ23) -> 1560123.9 | AL24: =SUM(AL22:AL23) -> 205488.4 | AN24: =SUM(AN22:AN23) -> 593004.28 | AP24: =SUM(AP22:AP23) -> 1765612.3 | AR24: =SUM(AR22:AR23) -> 196789.61 | AT24: =SUM(AT22:AT23) -> 1962401.9 | AV24: =SUM(AV22:AV23) -> 187566.5 | AX24: =SUM(AX22:AX23) -> 2149968.4 | AZ24: =SUM(AZ22:AZ23) -> 214922.73 | BB24: =SUM(BB22:BB23) -> 599278.84 | BD24: =SUM(BD22:BD23) -> 1192283.1 | BF24: =SUM(BF22:BF23) -> 2364891.2 | BH24: 2298057 | BJ24: =SUM(BJ22:BJ23) -> 2178255.5 | BL24: 1877654.8 | BN24: =SUM(BN22:BN23) -> 2049932.9
B25: ROAD CO-EFFICIENT (%) | C25: % | F25: =+F23/F24*100 -> 18.930624 | H25: =+H23/H24*100 -> 17.01 | J25: =+J23/J24*100 -> 18.039677 | L25: =+L23/L24*100 -> 23.776171 | N25: =+N23/N24*100 -> 19.680518 | P25: =+P23/P24*100 -> 22.857673 | R25: =+R23/R24*100 -> 20.644876 | T25: =+T23/T24*100 -> 24.59219 | V25: =+V23/V24*100 -> 21.602312 | X25: =+X23/X24*100 -> 21.640699 | Z25: =+Z23/Z24*100 -> 23.116465 | AB25: =+AB23/AB24*100 -> 21.608769 | AD25: =+AD23/AD24*100 -> 19.550885 | AF25: =+AF23/AF24*100 -> 21.302613 | AH25: =+AH23/AH24*100 -> 15.626897 | AJ25: =+AJ23/AJ24*100 -> 20.638407 | AL25: =+AL23/AL24*100 -> 19.103307 | AN25: =+AN23/AN24*100 -> 18.187668 | AP25: =+AP23/AP24*100 -> 20.459747 | AR25: =+AR23/AR24*100 -> 22.964988 | AT25: =+AT23/AT24*100 -> 20.710972 | AV25: =+AV23/AV24*100 -> 28.674651 | AX25: =+AX23/AX24*100 -> 21.405736 | AZ25: =+AZ23/AZ24*100 -> 26.135128 | BB25: =+BB23/BB24*100 -> 25.888963 | BD25: =+BD23/BD24*100 -> 22.05858 | BF25: =+BF23/BF24*100 -> 21.835546 | BH25: 14.749254 | BJ25: 13.573438 | BL25: =+BL23/BL24*100 -> 17.067721 | BN25: =+BN23/BN24*100 -> 19.239924
B26: Pig Iron | C26: MT | D26: 21561.1 | E26: =+'Maj Production Summ'!E24 -> 1160.8961 | F26: 549.29 | G26: =+'Maj Production Summ'!G24 -> 1160.8961 | H26: 599.23 | I26: =+E26+G26 -> 2321.7923 | J26: =+F26+H26 -> 1148.52 | K26: =+'Maj Production Summ'!K24 -> 8791.2424 | L26: 778.25 | M26: =+E26+G26+K26 -> 11113.035 | N26: =+F26+H26+L26 -> 1926.77 | O26: =+'Maj Production Summ'!O24 -> 1160.8961 | P26: 4016.72 | Q26: =+M26+O26 -> 12273.931 | R26: =+N26+P26 -> 5943.49 | S26: =+'Maj Production Summ'!S24 -> 1160.8961 | T26: 272.59 | U26: =+Q26+S26 -> 13434.827 | V26: =+R26+T26 -> 6216.08 | W26: =+'Maj Production Summ'!W24 -> 1160.8961 | X26: 226.36 | Y26: =+O26+S26+W26 -> 3482.6884 | Z26: =+P26+T26+X26 -> 4515.67 | AA26: =+M26+Y26 -> 14595.723 | AB26: =+N26+Z26 -> 6442.44 | AC26: =+'Maj Production Summ'!AC24 -> 1160.8961 | AD26: 199.6 | AE26: =+AA26+AC26 -> 15756.619 | AF26: =+AB26+AD26 -> 6642.04 | AG26: =+'Maj Production Summ'!AG24 -> 1160.8961 | AH26: 199.59 | AI26: =+AE26+AG26 -> 16917.515 | AJ26: =+AF26+AH26 -> 6841.63 | AK26: =+'Maj Production Summ'!AK24 -> 1160.8961 | AL26: 198.96 | AM26: =+AC26+AG26+AK26 -> 3482.6884 | AN26: =+AD26+AH26+AL26 -> 598.15 | AO26: =AI26+AK26 -> 18078.411 | AP26: =AJ26+AL26 -> 7040.59 | AQ26: =+'Maj Production Summ'!AQ24 -> 1160.8961 | AR26: 198.86 | AS26: =+AO26+AQ26 -> 19239.308 | AT26: =+AP26+AR26 -> 7239.45 | AU26: =+'Maj Production Summ'!AU24 -> 1160.8961 | AV26: 199.92 | AW26: =+AS26+AU26 -> 20400.204 | AX26: =+AT26+AV26 -> 7439.37 | AY26: =+'Maj Production Summ'!AY24 -> 1160.8961 | AZ26: 97.73 | BA26: =+AQ26+AU26+AY26 -> 3482.6884 | BB26: =+AR26+AV26+AZ26 -> 496.51 | BC26: =AM26+BA26 -> 6965.3768 | BD26: =AN26+BB26 -> 1094.66 | BE26: =+AW26+AY26 -> 21561.1 | BF26: =+AX26+AZ26 -> 7537.1 | BG26: 16929.735 | BH26: 8801.74 | BI26: 19251.635 | BJ26: 20488.86 | BK26: 20754.645 | BL26: 80002.18 | BM26: 29958.272 | BN26: 124050.8
B27: PCIS Plant Sales | C27: MT | D27: =+'Maj Production Summ'!D25 -> 2377.872 | E27: =+'Maj Production Summ'!E25 -> 141.12 | F27: 483.58 | G27: =+'Maj Production Summ'!G25 -> 141.12 | H27: 652.81 | I27: =+E27+G27 -> 282.24 | J27: =+F27+H27 -> 1136.39 | K27: =+'Maj Production Summ'!K25 -> 825.552 | L27: 922.14 | M27: =+E27+G27+K27 -> 1107.792 | N27: =+F27+H27+L27 -> 2058.53 | O27: =+'Maj Production Summ'!O25 -> 141.12 | P27: 935.92 | Q27: =+M27+O27 -> 1248.912 | R27: =+N27+P27 -> 2994.45 | S27: =+'Maj Production Summ'!S25 -> 141.12 | T27: 1061.57 | U27: =+Q27+S27 -> 1390.032 | V27: =+R27+T27 -> 4056.02 | W27: =+'Maj Production Summ'!W25 -> 141.12 | X27: 800.25 | Y27: =+O27+S27+W27 -> 423.36 | Z27: =+P27+T27+X27 -> 2797.74 | AA27: =+M27+Y27 -> 1531.152 | AB27: =+N27+Z27 -> 4856.27 | AC27: =+'Maj Production Summ'!AC25 -> 141.12 | AD27: 698.44 | AE27: =+AA27+AC27 -> 1672.272 | AF27: =+AB27+AD27 -> 5554.71 | AG27: =+'Maj Production Summ'!AG25 -> 141.12 | AH27: 0 | AI27: =+AE27+AG27 -> 1813.392 | AJ27: =+AF27+AH27 -> 5554.71 | AK27: =+'Maj Production Summ'!AK25 -> 141.12 | AL27: 0 | AM27: =+AC27+AG27+AK27 -> 423.36 | AN27: =+AD27+AH27+AL27 -> 698.44 | AO27: =AI27+AK27 -> 1954.512 | AP27: =AJ27+AL27 -> 5554.71 | AQ27: =+'Maj Production Summ'!AQ25 -> 141.12 | AR27: 197.33 | AS27: =+AO27+AQ27 -> 2095.632 | AT27: =+AP27+AR27 -> 5752.04 | AU27: =+'Maj Production Summ'!AU25 -> 141.12 | AV27: 0 | AW27: =+AS27+AU27 -> 2236.752 | AX27: =+AT27+AV27 -> 5752.04 | AY27: =+'Maj Production Summ'!AY25 -> 141.12 | AZ27: 239.8 | BA27: =+AQ27+AU27+AY27 -> 423.36 | BB27: =+AR27+AV27+AZ27 -> 437.13 | BC27: =AM27+BA27 -> 846.72 | BD27: =AN27+BB27 -> 1135.57 | BE27: =+AW27+AY27 -> 2377.872 | BF27: =+AX27+AZ27 -> 5991.84 | BG27: 2057.6 | BH27: 5429.83 | BI27: 2163.56 | BJ27: 17862.58 | BK27: 6973.7102 | BL27: 29483.78 | BM27: 8472.5251 | BN27: 59555.1
B28: Total Pig & Pig Equiv | C28: MT | D28: =SUM(D26:D27) -> 23938.972 | E28: =SUM(E26:E27) -> 1302.0161 | F28: =SUM(F26:F27) -> 1032.87 | G28: =SUM(G26:G27) -> 1302.0161 | H28: =SUM(H26:H27) -> 1252.04 | I28: =SUM(I26:I27) -> 2604.0323 | J28: =SUM(J26:J27) -> 2284.91 | K28: =SUM(K26:K27) -> 9616.7944 | ... AO28: =SUM(AO26:AO27) -> 20032.923 | AP28: =AJ28+AL28 -> 12595.3 | AQ28: =SUM(AQ26:AQ27) -> 1302.0161 | AR28: =SUM(AR26:AR27) -> 396.19 | AS28: =SUM(AS26:AS27) -> 21334.94 | AT28: =SUM(AT26:AT27) -> 12991.49 | AU28: =SUM(AU26:AU27) -> 1302.0161 | AV28: =SUM(AV26:AV27) -> 199.92 | AW28: =SUM(AW26:AW27) -> 22636.956 | AX28: =SUM(AX26:AX27) -> 13191.41 | ... BB28: =SUM(BB26:BB27) -> 933.64 | BC28: =AM28+BA28 -> 7812.0968 | BD28: =AN28+BB28 -> 2230.23 | BE28: =SUM(BE26:BE27) -> 23938.972 | BF28: =SUM(BF26:BF27) -> 13528.94 | BG28: 18987.335 | BH28: 14231.57 | BI28: 21415.195 | BJ28: 38351.44 | BK28: 27728.355 | BL28: 109485.96 | BM28: =SUM(BM26:BM27) -> 38430.797 | BN28: =SUM(BN26:BN27) -> 183605.9
I30: =I12-I24 -> 391500.93 | J30: =J12-J24 -> 0 | Q30: =Q12-Q24 -> 781501.57 | R30: =R12-R24 -> 0 | U30: =U12-U24 -> 998001.95 | V30: =V12-V24 -> 0 | AI30: =AI12-AI24 -> 1646001.4 | AJ30: =AJ12-AJ24 -> 0 | AS30: =AS12-AS24 -> 2093000.5 | AT30: =AT12-AT24 -> 0

Sheet Maj Techno Summ
B1: MAJOR TECHNO PARAMETERS 2023-24
E2: 30 | F2: 30 | G2: 31 | H2: 31 | I2: =+E2+G2 -> 61 | J2: =+F2+H2 -> 61 | K2: 30 | L2: 30 | M2: =+I2+K2 -> 91 | N2: =+J2+L2 -> 91 | O2: 31 | P2: 31 | Q2: =+M2+O2 -> 122 | R2: =+N2+P2 -> 122 | S2: 31 | T2: 31 | U2: =+Q2+S2 -> 153 | V2: =+R2+T2 -> 153 | W2: 30 | X2: 30 | Y2: =+O2+S2+W2 -> 92 | Z2: =+P2+T2+X2 -> 92 | AA2: =+U2+W2 -> 183 | AB2: =+V2+X2 -> 183 | AC2: 31 | AD2: 31 | AE2: =+AA2+AC2 -> 214 | AF2: =+AB2+AD2 -> 214 | AG2: 30 | AH2: 30 | AI2: =+AE2+AG2 -> 244 | AJ2: =+AF2+AH2 -> 244 | AK2: 31 | AL2: 31 | AM2: =+AC2+AG2+AK2 -> 92 | AN2: =+AD2+AH2+AL2 -> 92 | AO2: =+AI2+AK2 -> 275 | AP2: =+AJ2+AL2 -> 275 | AQ2: 31 | AR2: 31 | AS2: =+AO2+AQ2 -> 306 | AT2: =+AP2+AR2 -> 306 | AU2: 29 | AV2: 29 | AW2: =+AS2+AU2 -> 335 | AX2: =+AT2+AV2 -> 335 | AY2: 31 | AZ2: 31 | BA2: =+AQ2+AU2+AY2 -> 91 | BB2: =+AR2+AV2+AZ2 -> 91 | BC2: =+AM2+BA2 -> 183 | BD2: =+AN2+BB2 -> 183 | BE2: =+AW2+AY2 -> 366 | BF2: =+AX2+AZ2 -> 366 | BK2: 365 | BL2: 365 | BM2: 366 | BN2: 366 | BO2: 365
B3: ITEM | C3: Unit | D3: 2023-24 Norm | E3: Apr'23 | G3: May'23 | I3: 2M | K3: Jun'23 | M3: QTR-1 | O3: Jul'23 | Q3: 4M | S3: Aug'23 | U3: 5M | W3: Sep'23 | Y3: QTR-2 | AA3: H1 | AC3: Oct'23 | AE3: 7M | AG3: Nov'23 | AI3: 8M | AK3: Dec'23 | AM3: QTR-3 | AO3: 9 M | AQ3: Jan'24 | AS3: 10M | AU3: Feb'24 | AW3: 11M | AY3: Mar'24 | BA3: QTR-4 | BC3: H2 | BE3: 2023-24 | BG3: 2022-23 | BI3: 2021-22 | BK3: 2020-21 | BM3: 2019-20 | BO3: 2018-19
E4: ABP | F4: ACT | G4: ABP | H4: ACT | I4: ABP | J4: ACT | K4: ABP | L4: ACT | M4: ABP | N4: ACT | O4: ABP | P4: ACT | Q4: ABP | R4: ACT | S4: ABP | T4: ACT | U4: ABP | V4: ACT | W4: ABP | X4: ACT | Y4: ABP | Z4: ACT | AA4: ABP | AB4: ACT | AC4: ABP | AD4: ACT | AE4: ABP | AF4: ACT | AG4: ABP | AH4: ACT | AI4: ABP | AJ4: ACT | AK4: ABP | AL4: ACT | AM4: ABP | AN4: ACT | AO4: ABP | AP4: ACT | AQ4: ABP | AR4: ACT | AS4: ABP | AT4: ACT | AU4: ABP | AV4: ACT | AW4: ABP | AX4: ACT | AY4: ABP | AZ4: ACT | BA4: ABP | BB4: ACT | BC4: ABP | BD4: ACT | BE4: ABP | BF4: ACT | BG4: ABP | BH4: ACT | BI4: ABP | BJ4: ACT | BK4: ABP | BL4: ACT | BM4: ABP | BN4: ACT | BO4: ACT
B5: B.F.Coke Yield | C5: % | D5: 69.5 | E5: =+$D$5 -> 69.5 | F5: =('Maj Production Summ'!F14*100)/('Maj Production Summ'!F10*31.55) -> 69.415591 | G5: =+$D$5 -> 69.5 | H5: =('Maj Production Summ'!H14*100)/('Maj Production Summ'!H10*31.55) -> 68.896667 | I5: =+$D$5 -> 69.5 | J5: =('Maj Production Summ'!J14*100)/('Maj Production Summ'!J10*31.55) -> 69.160171 | K5: =+$D$5 -> 69.5 | L5: =('Maj Production Summ'!L14*100)/('Maj Production Summ'!L10*31.55) -> 69.391251 | M5: =+$D$5 -> 69.5 | N5: =('Maj Production Summ'!N14*100)/('Maj Production Summ'!N10*31.55) -> 69.235835 | O5: =+$D$5 -> 69.5 | P5: =('Maj Production Summ'!P14*100)/('Maj Production Summ'!P10*31.55) -> 69.415356 | Q5: =+$D$5 -> 69.5 | R5: =('Maj Production Summ'!R14*100)/('Maj Production Summ'!R10*31.55) -> 69.281896 | S5: =+$D$5 -> 69.5 | T5: =('Maj Production Summ'!T14*100)/('Maj Production Summ'!T10*31.55) -> 69.400838 | U5: =+$D$5 -> 69.5 | V5: =('Maj Production Summ'!V14*100)/('Maj Production Summ'!V10*31.55) -> 69.306085 | W5: =+$D$5 -> 69.5 | X5: =('Maj Production Summ'!X14*100)/('Maj Production Summ'!X10*31.55) -> 69.38409 | Y5: =+$D$5 -> 69.5 | Z5: =('Maj Production Summ'!Z14*100)/('Maj Production Summ'!Z10*31.55) -> 69.400247 | AA5: =+$D$5 -> 69.5 | AB5: =('Maj Production Summ'!AB14*100)/('Maj Production Summ'!AB10*31.55) -> 69.31901 | AC5: =+$D$5 -> 69.5 | AD5: =('Maj Production Summ'!AD14*100)/('Maj Production Summ'!AD10*31.55) -> 69.402611 | AE5: =+$D$5 -> 69.5 | AF5: =('Maj Production Summ'!AF14*100)/('Maj Production Summ'!AF10*31.55) -> 69.331424 | AG5: =+$D$5 -> 69.5 | AH5: =('Maj Production Summ'!AH14*100)/('Maj Production Summ'!AH10*31.55) -> 69.880571 | AI5: =+$D$5 -> 69.5 | AJ5: =('Maj Production Summ'!AJ14*100)/('Maj Production Summ'!AJ10*31.55) -> 69.400129 | AK5: =+$D$5 -> 69.5 | AL5: =('Maj Production Summ'!AL14*100)/('Maj Production Summ'!AL10*31.55) -> 69.394649 | AM5: =+$D$5 -> 69.5 | AN5: =('Maj Production Summ'!AN14*100)/('Maj Production Summ'!AN10*31.55) -> 69.554702 | AO5: =+$D$5 -> 69.5 | AP5: =('Maj Production Summ'!AP14*100)/('Maj Production Summ'!AP10*31.55) -> 69.399493 | AQ5: =+$D$5 -> 69.5 | AR5: =('Maj Production Summ'!AR14*100)/('Maj Production Summ'!AR10*31.55) -> 69.388275 | AS5: =+$D$5 -> 69.5 | AT5: =('Maj Production Summ'!AT14*100)/('Maj Production Summ'!AT10*31.55) -> 69.398329 | AU5: =+$D$5 -> 69.5 | AV5: =('Maj Production Summ'!AV14*100)/('Maj Production Summ'!AV10*31.55) -> 69.395933 | AW5: =+$D$5 -> 69.5 | AX5: =('Maj Production Summ'!AX14*100)/('Maj Production Summ'!AX10*31.55) -> 69.398117 | AY5: =+$D$5 -> 69.5 | AZ5: =('Maj Production Summ'!AZ14*100)/('Maj Production Summ'!AZ10*31.55) -> 69.397096 | BA5: =+$D$5 -> 69.5 | BB5: =('Maj Production Summ'!BB14*100)/('Maj Production Summ'!BB10*31.55) -> 69.393722 | BC5: =+$D$5 -> 69.5 | BD5: =('Maj Production Summ'!BD14*100)/('Maj Production Summ'!BD10*31.55) -> 69.474377 | BE5: =+$D$5 -> 69.5 | BF5: =('Maj Production Summ'!BF14*100)/('Maj Production Summ'!BF10*31.55) -> 69.398029 | BG5: 69.5 | BH5: 69.459875 | BI5: 70.500003 | BJ5: 69.798394 | BK5: 70.999787 | BL5: 72.813877 | BM5: 66.5 | BN5: 67.48567 | BO5: 67.015011
B6: ICC in Coal Blend
B7: (COB#10) | C7: % | D7: 92 | E7: =+$D$7 -> 92 | F7: ='COKE OVENS'!F142 -> 90.000179 | G7: =+$D$7 -> 92 | H7: ='COKE OVENS'!H142 -> 90.000693 | I7: =+$D$7 -> 92 | J7: ='COKE OVENS'!J142 -> 90.00044 | K7: =+$D$7 -> 92 | L7: ='COKE OVENS'!L142 -> 90 | M7: =+$D$7 -> 92 | N7: ='COKE OVENS'!N142 -> 90.000295 | O7: =+$D$7 -> 92 | P7: ='COKE OVENS'!P142 -> 89.991702 | Q7: =+$D$7 -> 92 | R7: ='COKE OVENS'!R142 -> 89.998087 | S7: =+$D$7 -> 92 | T7: ='COKE OVENS'!T142 -> 89.806452 | U7: =+$D$7 -> 92 | V7: ='COKE OVENS'!V142 -> 89.958052 | W7: =+$D$7 -> 92 | X7: ='COKE OVENS'!X142 -> 90.000071 | Y7: =+$D$7 -> 92 | Z7: ='COKE OVENS'!Z142 -> 89.931386 | AA7: =+$D$7 -> 92 | AB7: ='COKE OVENS'!AB142 -> 89.965097 | AC7: =+$D$7 -> 92 | AD7: ='COKE OVENS'!AD142 -> 90 | AE7: =+$D$7 -> 92 | AF7: ='COKE OVENS'!AF142 -> 89.970189 | AG7: =+$D$7 -> 92 | AH7: ='COKE OVENS'!AH142 -> 91.2 | AI7: =+$D$7 -> 92 | AJ7: ='COKE OVENS'!AJ142 -> 90.121011 | AK7: =+$D$7 -> 92 | AL7: ='COKE OVENS'!AL142 -> 90 | AM7: =+$D$7 -> 92 | AN7: ='COKE OVENS'!AN142 -> 90.391382 | AO7: =+$D$7 -> 92 | AP7: ='COKE OVENS'!AP142 -> 90.107527 | AQ7: =+$D$7 -> 92 | AR7: ='COKE OVENS'!AR142 -> 90.645161 | AS7: =+$D$7 -> 92 | AT7: ='COKE OVENS'!AT142 -> 90.161428 | AU7: =+$D$7 -> 92 | AV7: ='COKE OVENS'!AV142 -> 95 | AW7: =+$D$7 -> 92 | AX7: ='COKE OVENS'!AX142 -> 90.576315 | AY7: =+$D$7 -> 92 | AZ7: ='COKE OVENS'!AZ142 -> 94.90369 | BA7: =+$D$7 -> 92 | BB7: ='COKE OVENS'!BB142 -> 93.483991 | BC7: =+$D$7 -> 92 | BD7: ='COKE OVENS'!BD142 -> 91.921423 | BE7: =+$D$7 -> 92 | BF7: ='COKE OVENS'!BF142 -> 90.939873 | BG7: 92 | BH7: 89.651306 | BI7: 95 | BJ7: 93.865972 | BK7: 94.377235 | BL7: 95.478511 | BM7: 90 | BN7: 91.425995 | BO7: 91.808306
B8: (COB#11) | C8: % | D8: 94 | E8: =+$D$8 -> 94 | F8: ='COKE OVENS'!F167 -> 91.999843 | G8: =+$D$8 -> 94 | H8: ='COKE OVENS'!H167 -> 92.000162 | I8: =+$D$8 -> 94 | J8: ='COKE OVENS'!J167 -> 92 | K8: =+$D$8 -> 94 | L8: ='COKE OVENS'!L167 -> 91.33333 | M8: =+$D$8 -> 94 | N8: ='COKE OVENS'!N167 -> 91.781708 | O8: =+$D$8 -> 94 | P8: ='COKE OVENS'!P167 -> 92 | Q8: =+$D$8 -> 94 | R8: ='COKE OVENS'!R167 -> 91.838112 | S8: =+$D$8 -> 94 | T8: ='COKE OVENS'!T167 -> 92 | U8: =+$D$8 -> 94 | V8: ='COKE OVENS'!V167 -> 91.871857 | W8: =+$D$8 -> 94 | X8: ='COKE OVENS'!X167 -> 92 | Y8: =+$D$8 -> 94 | Z8: ='COKE OVENS'!Z167 -> 92 | AA8: =+$D$8 -> 94 | AB8: ='COKE OVENS'!AB167 -> 91.89353 | AC8: =+$D$8 -> 94 | AD8: ='COKE OVENS'!AD167 -> 91.56 | AE8: =+$D$8 -> 94 | AF8: ='COKE OVENS'!AF167 -> 91.843133 | AG8: =+$D$8 -> 94 | AH8: ='COKE OVENS'!AH167 -> 93.199999 | AI8: =+$D$8 -> 94 | AJ8: ='COKE OVENS'!AJ167 -> 92.012124 | AK8: =+$D$8 -> 94 | AL8: ='COKE OVENS'!AL167 -> 95 | AM8: =+$D$8 -> 94 | AN8: ='COKE OVENS'!AN167 -> 93.240813 | AO8: =+$D$8 -> 94 | AP8: ='COKE OVENS'!AP167 -> 92.35417 | AQ8: =+$D$8 -> 94 | AR8: ='COKE OVENS'!AR167 -> 95.65 | AS8: =+$D$8 -> 94 | AT8: ='COKE OVENS'!AT167 -> 92.69202 | AU8: =+$D$8 -> 94 | AV8: ='COKE OVENS'!AV167 -> 100 | AW8: =+$D$8 -> 94 | AX8: ='COKE OVENS'!AX167 -> 93.332363 | AY8: =+$D$8 -> 94 | AZ8: ='COKE OVENS'!AZ167 -> 99.838713 | BA8: =+$D$8 -> 94 | BB8: ='COKE OVENS'!BB167 -> 98.464073 | BC8: =+$D$8 -> 94 | BD8: ='COKE OVENS'!BD167 -> 95.82767 | BE8: =+$D$8 -> 94 | BF8: ='COKE OVENS'!BF167 -> 93.889004 | BG8: 94 | BH8: 92.198587 | BI8: 95 | BJ8: 94.753433 | BK8: 94.836589 | BL8: 95.080613 | BM8: 90 | BN8: 96.370935 | BO8: 94.117213
B9: Overall ICC in Blend | C9: % | D9: 93.289716 | E9: =+$D$9 -> 93.289716 | F9: ='COKE OVENS'!F207 -> 91.290585 | G9: =+$D$9 -> 93.289716 | H9: ='COKE OVENS'!H207 -> 91.261608 | I9: =+$D$9 -> 93.289716 | J9: ='COKE OVENS'!J207 -> 91.276155 | K9: =+$D$9 -> 93.289716 | L9: ='COKE OVENS'!L207 -> 90.847481 | M9: =+$D$9 -> 93.289716 | N9: ='COKE OVENS'!N207 -> 91.135438 | O9: =+$D$9 -> 93.289716 | P9: ='COKE OVENS'!P207 -> 91.274767 | Q9: =+$D$9 -> 93.289716 | R9: ='COKE OVENS'!R207 -> 91.171369 | S9: =+$D$9 -> 93.289716 | T9: ='COKE OVENS'!T207 -> 91.203726 | U9: =+$D$9 -> 93.289716 | V9: ='COKE OVENS'!V207 -> 91.178119 | W9: =+$D$9 -> 93.289716 | X9: ='COKE OVENS'!X207 -> 91.279824 | Y9: =+$D$9 -> 93.289716 | Z9: ='COKE OVENS'!Z207 -> 91.252355 | AA9: =+$D$9 -> 93.289716 | AB9: ='COKE OVENS'!AB207 -> 91.195267 | AC9: =+$D$9 -> 93.289716 | AD9: ='COKE OVENS'!AD207 -> 91.009965 | AE9: =+$D$9 -> 93.289716 | AF9: ='COKE OVENS'!AF207 -> 91.167618 | AG9: =+$D$9 -> 93.289716 | AH9: ='COKE OVENS'!AH207 -> 92.486753 | AI9: =+$D$9 -> 93.289716 | AJ9: ='COKE OVENS'!AJ207 -> 91.331004 | AK9: =+$D$9 -> 93.289716 | AL9: ='COKE OVENS'!AL207 -> 93.234091 | AM9: =+$D$9 -> 93.289716 | AN9: ='COKE OVENS'!AN207 -> 92.23185 | AO9: =+$D$9 -> 93.289716 | AP9: ='COKE OVENS'!AP207 -> 91.546778 | AQ9: =+$D$9 -> 93.289716 | AR9: ='COKE OVENS'!AR207 -> 93.879766 | AS9: =+$D$9 -> 93.289716 | AT9: ='COKE OVENS'!AT207 -> 91.784043 | AU9: =+$D$9 -> 93.289716 | AV9: ='COKE OVENS'!AV207 -> 98.233176 | AW9: =+$D$9 -> 93.289716 | AX9: ='COKE OVENS'!AX207 -> 92.344795 | AY9: =+$D$9 -> 93.289716 | AZ9: ='COKE OVENS'!AZ207 -> 98.092816 | BA9: =+$D$9 -> 93.289716 | BB9: ='COKE OVENS'!BB207 -> 96.703012 | BC9: =+$D$9 -> 93.289716 | BD9: ='COKE OVENS'!BD207 -> 94.445409 | BE9: =+$D$9 -> 93.289716 | BF9: ='COKE OVENS'!BF207 -> 92.83339 | BG9: 93.294359 | BH9: 91.262624 | BI9: 95 | BJ9: 94.439237 | BK9: 94.673168 | BL9: 94.71202 | BM9: 90 | BN9: 94.617133 | BO9: 93.297278
B10: BF Coke Rate | C10: Kg/ THM | D10: 380.42 | E10: 380 | F10: =+('B-FCE'!F22/'Maj Production Summ'!F$17)*1000 -> 394.49 | G10: 382 | H10: =+('B-FCE'!H22/'Maj Production Summ'!H$17)*1000 -> 404.39415 | I10: =+('B-FCE'!I22/'Maj Production Summ'!I$17)*1000 -> 380.90993 | J10: =+('B-FCE'!J22/'Maj Production Summ'!J$17)*1000 -> 398.90449 | K10: 400 | L10: =+('B-FCE'!L22/'Maj Production Summ'!L$17)*1000 -> 415.90322 | M10: =+('B-FCE'!M22/'Maj Production Summ'!M$17)*1000 -> 386.96215 | N10: =+('B-FCE'!N22/'Maj Production Summ'!N$17)*1000 -> 404.64874 | O10: 387 | P10: =+('B-FCE'!P22/'Maj Production Summ'!P$17)*1000 -> 388.83616 | Q10: =+('B-FCE'!Q22/'Maj Production Summ'!Q$17)*1000 -> 386.97251 | R10: =+('B-FCE'!R22/'Maj Production Summ'!R$17)*1000 -> 400.22493 | S10: 387 | T10: =+('B-FCE'!T22/'Maj Production Summ'!T$17)*1000 -> 399.04897 | U10: =+('B-FCE'!U22/'Maj Production Summ'!U$17)*1000 -> 386.97842 | V10: =+('B-FCE'!V22/'Maj Production Summ'!V$17)*1000 -> 399.97195 | W10: 383 | X10: =+('B-FCE'!X22/'Maj Production Summ'!X$17)*1000 -> 385.23413 | Y10: =+('B-FCE'!Y22/'Maj Production Summ'!Y$17)*1000 -> 385.69296 | Z10: =+('B-FCE'!Z22/'Maj Production Summ'!Z$17)*1000 -> 391.11513 | AA10: =+('B-FCE'!AA22/'Maj Production Summ'!AA$17)*1000 -> 386.29167 | AB10: =+('B-FCE'!AB22/'Maj Production Summ'!AB$17)*1000 -> 397.46333 | AC10: 375 | AD10: =+('B-FCE'!AD22/'Maj Production Summ'!AD$17)*1000 -> 384.15685 | AE10: =+('B-FCE'!AE22/'Maj Production Summ'!AE$17)*1000 -> 384.54465 | AF10: =+('B-FCE'!AF22/'Maj Production Summ'!AF$17)*1000 -> 395.42625 | AG10: 375 | AH10: =+('B-FCE'!AH22/'Maj Production Summ'!AH$17)*1000 -> 410.63356 | AI10: =+('B-FCE'!AI22/'Maj Production Summ'!AI$17)*1000 -> 383.30197 | AJ10: =+('B-FCE'!AJ22/'Maj Production Summ'!AJ$17)*1000 -> 397.17184 | AK10: 375 | AL10: =+('B-FCE'!AL22/'Maj Production Summ'!AL$17)*1000 -> 390.56688 | AM10: =+('B-FCE'!AM22/'Maj Production Summ'!AM$17)*1000 -> 375 | AN10: =+('B-FCE'!AN22/'Maj Production Summ'!AN$17)*1000 -> 394.36837 | AO10: =+('B-FCE'!AO22/'Maj Production Summ'!AO$17)*1000 -> 382.31373 | AP10: =+('B-FCE'!AP22/'Maj Production Summ'!AP$17)*1000 -> 396.42699 | AQ10: 375 | AR10: =+('B-FCE'!AR22/'Maj Production Summ'!AR$17)*1000 -> 372.42693 | AS10: =+('B-FCE'!AS22/'Maj Production Summ'!AS$17)*1000 -> 381.53575 | AT10: =+('B-FCE'!AT22/'Maj Production Summ'!AT$17)*1000 -> 393.95353 | AU10: 375 | AV10: =+('B-FCE'!AV22/'Maj Production Summ'!AV$17)*1000 -> 371.85846 | AW10: =+('B-FCE'!AW22/'Maj Production Summ'!AW$17)*1000 -> 380.94671 | AX10: =+('B-FCE'!AX22/'Maj Production Summ'!AX$17)*1000 -> 391.90789 | AY10: 375 | AZ10: =+('B-FCE'!AZ22/'Maj Production Summ'!AZ$17)*1000 -> 375.73762 | BA10: =+('B-FCE'!BA22/'Maj Production Summ'!BA$17)*1000 -> 375 | BB10: =+('B-FCE'!BB22/'Maj Production Summ'!BB$17)*1000 -> 373.35401 | BC10: =+('B-FCE'!BC22/'Maj Production Summ'!BC$17)*1000 -> 375 | BD10: =+('B-FCE'!BD22/'Maj Production Summ'!BD$17)*1000 -> 383.70857 | BE10: =+('B-FCE'!BE22/'Maj Production Summ'!BE$17)*1000 -> 380.42 | BF10: =+('B-FCE'!BF22/'Maj Production Summ'!BF$17)*1000 -> 390.51224 | BG10: 389.92559 | BH10: 400.04041 | BI10: 377.88521 | BJ10: 396.71459 | BK10: 373.87865 | BL10: 423.66105 | BM10: 370.47898 | BN10: 381.58771 | BO10: 388.39311
B11: Nut Coke rate | C11: Kg/ THM | D11: 32.204286 | E11: 30 | F11: =+('B-FCE'!F23/'Maj Production Summ'!F$17)*1000 -> 37.49 | G11: 33 | H11: =+('B-FCE'!H23/'Maj Production Summ'!H$17)*1000 -> 40.719195 | I11: =+('B-FCE'!I23/'Maj Production Summ'!I$17)*1000 -> 31.364896 | J11: =+('B-FCE'!J23/'Maj Production Summ'!J$17)*1000 -> 38.929322 | K11: 40 | L11: =+('B-FCE'!L23/'Maj Production Summ'!L$17)*1000 -> 42.650208 | M11: =+('B-FCE'!M23/'Maj Production Summ'!M$17)*1000 -> 34.102524 | N11: =+('B-FCE'!N23/'Maj Production Summ'!N$17)*1000 -> 40.186692 | O11: 40 | P11: =+('B-FCE'!P23/'Maj Production Summ'!P$17)*1000 -> 48.366092 | Q11: =+('B-FCE'!Q23/'Maj Production Summ'!Q$17)*1000 -> 35.717068 | R11: =+('B-FCE'!R23/'Maj Production Summ'!R$17)*1000 -> 42.475003 | S11: 33 | T11: =+('B-FCE'!T23/'Maj Production Summ'!T$17)*1000 -> 51.63736 | U11: =+('B-FCE'!U23/'Maj Production Summ'!U$17)*1000 -> 35.133094 | V11: =+('B-FCE'!V23/'Maj Production Summ'!V$17)*1000 -> 44.446098 | W11: 32 | X11: =+('B-FCE'!X23/'Maj Production Summ'!X$17)*1000 -> 50.589062 | Y11: =+('B-FCE'!Y23/'Maj Production Summ'!Y$17)*1000 -> 35.029577 | Z11: =+('B-FCE'!Z23/'Maj Production Summ'!Z$17)*1000 -> 50.178651 | AA11: =+('B-FCE'!AA23/'Maj Production Summ'!AA$17)*1000 -> 34.592262 | AB11: =+('B-FCE'!AB23/'Maj Production Summ'!AB$17)*1000 -> 45.491732 | AC11: 30 | AD11: =+('B-FCE'!AD23/'Maj Production Summ'!AD$17)*1000 -> 49.194103 | AE11: =+('B-FCE'!AE23/'Maj Production Summ'!AE$17)*1000 -> 33.881761 | AF11: =+('B-FCE'!AF23/'Maj Production Summ'!AF$17)*1000 -> 46.058523 | AG11: 30 | AH11: =+('B-FCE'!AH23/'Maj Production Summ'!AH$17)*1000 -> 50.76057 | AI11: =+('B-FCE'!AI23/'Maj Production Summ'!AI$17)*1000 -> 33.376368 | AJ11: =+('B-FCE'!AJ23/'Maj Production Summ'!AJ$17)*1000 -> 46.598254 | AK11: 30 | AL11: =+('B-FCE'!AL23/'Maj Production Summ'!AL$17)*1000 -> 51.847824 | AM11: =+('B-FCE'!AM23/'Maj Production Summ'!AM$17)*1000 -> 30 | AN11: =+('B-FCE'!AN23/'Maj Production Summ'!AN$17)*1000 -> 50.564268 | AO11: =+('B-FCE'!AO23/'Maj Production Summ'!AO$17)*1000 -> 32.974458 | AP11: =+('B-FCE'!AP23/'Maj Production Summ'!AP$17)*1000 -> 47.190256 | AQ11: 30 | AR11: =+('B-FCE'!AR23/'Maj Production Summ'!AR$17)*1000 -> 53.092168 | AS11: =+('B-FCE'!AS23/'Maj Production Summ'!AS$17)*1000 -> 32.658053 | AT11: =+('B-FCE'!AT23/'Maj Production Summ'!AT$17)*1000 -> 47.798511 | AU11: 30 | AV11: =+('B-FCE'!AV23/'Maj Production Summ'!AV$17)*1000 -> 44.050117 | AW11: =+('B-FCE'!AW23/'Maj Production Summ'!AW$17)*1000 -> 32.418495 | AX11: =+('B-FCE'!AX23/'Maj Production Summ'!AX$17)*1000 -> 47.451472 | AY11: 30 | AZ11: =+('B-FCE'!AZ23/'Maj Production Summ'!AZ$17)*1000 -> 45.244039 | BA11: =+('B-FCE'!BA23/'Maj Production Summ'!BA$17)*1000 -> 30 | BB11: =+('B-FCE'!BB23/'Maj Production Summ'!BB$17)*1000 -> 47.466022 | BC11: =+('B-FCE'!BC23/'Maj Production Summ'!BC$17)*1000 -> 30 | BD11: =+('B-FCE'!BD23/'Maj Production Summ'!BD$17)*1000 -> 48.992644 | BE11: =+('B-FCE'!BE23/'Maj Production Summ'!BE$17)*1000 -> 32.204286 | BF11: =+('B-FCE'!BF23/'Maj Production Summ'!BF$17)*1000 -> 47.260949 | BG11: 30 | BH11: 36.610035 | BI11: 23.751425 | BJ11: 37.043769 | BK11: 34.857516 | BL11: 41.208946 | BM11: 25 | BN11: 44.993877 | BO11: 29.180384
B12: CDI rate | C12: Kg/ THM | D12: 139.6475 | E12: 140 | F12: =+('B-FCE'!F24/'Maj Production Summ'!F$17)*1000 -> 129.13437 | G12: 135 | H12: =+('B-FCE'!H24/'Maj Production Summ'!H$17)*1000 -> 124.4423 | I12: =+('B-FCE'!I24/'Maj Production Summ'!I$17)*1000 -> 137.72517 | J12: =+('B-FCE'!J24/'Maj Production Summ'!J$17)*1000 -> 127.04302 | K12: 125 | L12: =+('B-FCE'!L24/'Maj Production Summ'!L$17)*1000 -> 111.23054 | M12: =+('B-FCE'!M24/'Maj Production Summ'!M$17)*1000 -> 133.69085 | N12: =+('B-FCE'!N24/'Maj Production Summ'!N$17)*1000 -> 121.69963 | O12: 132 | P12: =+('B-FCE'!P24/'Maj Production Summ'!P$17)*1000 -> 126.53246 | Q12: =+('B-FCE'!Q24/'Maj Production Summ'!Q$17)*1000 -> 133.22795 | R12: =+('B-FCE'!R24/'Maj Production Summ'!R$17)*1000 -> 123.05169 | S12: 135 | T12: =+('B-FCE'!T24/'Maj Production Summ'!T$17)*1000 -> 122.95135 | U12: =+('B-FCE'!U24/'Maj Production Summ'!U$17)*1000 -> 133.60881 | V12: =+('B-FCE'!V24/'Maj Production Summ'!V$17)*1000 -> 123.0301 | W12: 135 | X12: =+('B-FCE'!X24/'Maj Production Summ'!X$17)*1000 -> 133.70807 | Y12: =+('B-FCE'!Y24/'Maj Production Summ'!Y$17)*1000 -> 133.99014 | Z12: =+('B-FCE'!Z24/'Maj Production Summ'!Z$17)*1000 -> 127.62891 | AA12: =+('B-FCE'!AA24/'Maj Production Summ'!AA$17)*1000 -> 133.84896 | AB12: =+('B-FCE'!AB24/'Maj Production Summ'!AB$17)*1000 -> 124.84767 | AC12: 145 | AD12: =+('B-FCE'!AD24/'Maj Production Summ'!AD$17)*1000 -> 132.87581 | AE12: =+('B-FCE'!AE24/'Maj Production Summ'!AE$17)*1000 -> 135.57421 | AF12: =+('B-FCE'!AF24/'Maj Production Summ'!AF$17)*1000 -> 126.07669 | AG12: 145 | AH12: =+('B-FCE'!AH24/'Maj Production Summ'!AH$17)*1000 -> 112.08721 | AI12: =+('B-FCE'!AI24/'Maj Production Summ'!AI$17)*1000 -> 136.80142 | AJ12: =+('B-FCE'!AJ24/'Maj Production Summ'!AJ$17)*1000 -> 124.47089 | AK12: 145 | AL12: =+('B-FCE'!AL24/'Maj Production Summ'!AL$17)*1000 -> 120.35507 | AM12: =+('B-FCE'!AM24/'Maj Production Summ'!AM$17)*1000 -> 145 | AN12: =+('B-FCE'!AN24/'Maj Production Summ'!AN$17)*1000 -> 122.33629 | AO12: =+('B-FCE'!AO24/'Maj Production Summ'!AO$17)*1000 -> 137.77735 | AP12: =+('B-FCE'!AP24/'Maj Production Summ'!AP$17)*1000 -> 124.00674 | AQ12: 145 | AR12: =+('B-FCE'!AR24/'Maj Production Summ'!AR$17)*1000 -> 132.05398 | AS12: =+('B-FCE'!AS24/'Maj Production Summ'!AS$17)*1000 -> 138.54565 | AT12: =+('B-FCE'!AT24/'Maj Production Summ'!AT$17)*1000 -> 124.83609 | AU12: 145 | AV12: =+('B-FCE'!AV24/'Maj Production Summ'!AV$17)*1000 -> 134.28032 | AW12: =+('B-FCE'!AW24/'Maj Production Summ'!AW$17)*1000 -> 139.12735 | AX12: =+('B-FCE'!AX24/'Maj Production Summ'!AX$17)*1000 -> 125.71047 | AY12: 145 | AZ12: =+('B-FCE'!AZ24/'Maj Production Summ'!AZ$17)*1000 -> 128.40565 | BA12: =+('B-FCE'!BA24/'Maj Production Summ'!BA$17)*1000 -> 145 | BB12: =+('B-FCE'!BB24/'Maj Production Summ'!BB$17)*1000 -> 131.5603 | BC12: =+('B-FCE'!BC24/'Maj Production Summ'!BC$17)*1000 -> 145 | BD12: =+('B-FCE'!BD24/'Maj Production Summ'!BD$17)*1000 -> 127.01529 | BE12: =+('B-FCE'!BE24/'Maj Production Summ'!BE$17)*1000 -> 139.6475 | BF12: =+('B-FCE'!BF24/'Maj Production Summ'!BF$17)*1000 -> 125.94309 | BG12: 129.64578 | BH12: 122.58808 | BI12: 133.64292 | BJ12: 118.07599 | BK12: 128.57732 | BL12: 89.175353 | BM12: 139.85352 | BN12: 118.98027 | BO12: 123.03826
B13: Total Fuel | C13: Kg/ THM | D13: =SUM(D10:D12) -> 552.27179 | E13: =SUM(E10:E12) -> 550 | F13: =SUM(F10:F12) -> 561.11437 | G13: =SUM(G10:G12) -> 550 | H13: =SUM(H10:H12) -> 569.55565 | I13: =SUM(I10:I12) -> 550 | J13: =SUM(J10:J12) -> 564.87683 | K13: =SUM(K10:K12) -> 565 | ... BF13: =SUM(BF10:BF12) -> 563.71628 | BG13: 549.57137 | BH13: 559.23852 | BI13: 535.27955 | BJ13: 551.83435 | BK13: 537.31348 | BL13: 554.04535 | BM13: 535.3325 | BN13: 545.56186 | BO13: 540.61176
B14: BF PRODUCTIVITY | C14: T/M³/Day | D14: 2.2723639 | E14: 2.2917294 | F14: 2.2197239 | G14: 2.2190932 | H14: 2.0635913 | I14: =+('Maj Production Summ'!I17/3551)/('B-FCE'!E49+'B-FCE'!G49) -> 2.2581015 | J14: =+('Maj Production Summ'!J17/3551)/('B-FCE'!F49+'B-FCE'!H49) -> 2.147309 | K14: 2.0964361 | L14: 2.0914204 | M14: =+('Maj Production Summ'!M17/3551)/('B-FCE'!E49+'B-FCE'!G49+'B-FCE'!K49) -> 2.204213 | N14: =+('Maj Production Summ'!N17/3551)/('B-FCE'!F49+'B-FCE'!H49+'B-FCE'!L49) -> 2.1280918 | O14: 2.2434995 | P14: 2.2642163 | Q14: =+('Maj Production Summ'!Q17/3551)/('B-FCE'!M49+'B-FCE'!O49) -> 2.214831 | R14: =+('Maj Production Summ'!R17/3551)/('B-FCE'!N49+'B-FCE'!P49) -> 2.1644975 | S14: 2.2434995 | T14: 2.1828018 | U14: =+('Maj Production Summ'!U17/3551)/('B-FCE'!Q49+'B-FCE'!S49) -> 2.2209307 | V14: =+('Maj Production Summ'!V17/3551)/('B-FCE'!R49+'B-FCE'!T49) -> 2.1684093 | W14: 2.2528865 | X14: 2.2661621 | Y14: =+('Maj Production Summ'!Y17/3551)/('B-FCE'!P49+'B-FCE'!T49+'B-FCE'!X49) -> 2.2221966 | Z14: =+('Maj Production Summ'!Z17/3551)/('B-FCE'!P49+'B-FCE'!T49+'B-FCE'!X49) -> 2.2367817 | AA14: =+('Maj Production Summ'!AA17/3551)/('B-FCE'!M49+'B-FCE'!Y49) -> 2.226382 | AB14: =+('Maj Production Summ'!AB17/3551)/('B-FCE'!N49+'B-FCE'!Z49) -> 2.1844485 | AC14: 2.3092087 | AD14: 2.2465526 | AE14: =+('Maj Production Summ'!AE17/3551)/('B-FCE'!AA49+'B-FCE'!AC49) -> 2.238806 | AF14: =+('Maj Production Summ'!AF17/3551)/('B-FCE'!AB49+'B-FCE'!AD49) -> 2.1937324 | AG14: 2.3111508 | AH14: 2.0003626 | AI14: =+('Maj Production Summ'!AI17/3551)/('B-FCE'!AE49+'B-FCE'!AG49) -> 2.2479675 | AJ14: =+('Maj Production Summ'!AJ17/3551)/('B-FCE'!AF49+'B-FCE'!AH49) -> 2.1696577 | AK14: 2.3185957 | AL14: 2.131 | AM14: =+('Maj Production Summ'!AM17/3551)/('B-FCE'!AC49+'B-FCE'!AG49+'B-FCE'!AK49) -> 2.3130057 | AN14: =+('Maj Production Summ'!AN17/3551)/('B-FCE'!AD49+'B-FCE'!AH49+'B-FCE'!AL49) -> 2.1280343 | AO14: =+('Maj Production Summ'!AO17/3551)/('B-FCE'!AK49+'B-FCE'!AI49) -> 2.2561484 | AP14: =+('Maj Production Summ'!AP17/3551)/('B-FCE'!AL49+'B-FCE'!AJ49) -> 2.1652282 | AQ14: 2.3185957 | AR14: 2.228 | AS14: =+('Maj Production Summ'!AS17/3551)/('B-FCE'!AO49+'B-FCE'!AQ49) -> 2.2626308 | AT14: =+('Maj Production Summ'!AT17/3551)/('B-FCE'!AP49+'B-FCE'!AR49) -> 2.1715335 | AU14: 2.3132317 | AV14: 2.2353995 | AW14: =+('Maj Production Summ'!AW17/3551)/('B-FCE'!AS49+'B-FCE'!AU49) -> 2.2671003 | AX14: =+('Maj Production Summ'!AX17/3551)/('B-FCE'!AT49+'B-FCE'!AV49) -> 2.1772928 | AY14: 2.3279827 | AZ14: 2.2212041 | BA14: =+('Maj Production Summ'!BA17/3551)/('B-FCE'!AQ49+'B-FCE'!AU49+'B-FCE'!AY49) -> 2.3200891 | BB14: =+('Maj Production Summ'!BB17/3551)/('B-FCE'!AR49+'B-FCE'!AV49+'B-FCE'!AZ49) -> 2.2281386 | BC14: =+('Maj Production Summ'!BC17/3551)/('B-FCE'!AM49+'B-FCE'!BA49) -> 2.3165274 | BD14: =+('Maj Production Summ'!BD17/3551)/('B-FCE'!AN49+'B-FCE'!BB49) -> 2.1776631 | BE14: =+('Maj Production Summ'!BE17/3551)/('B-FCE'!AW49+'B-FCE'!AY49) -> 2.2723639 | BF14: =+('Maj Production Summ'!BF17/3551)/('B-FCE'!AX49+'B-FCE'!AZ49) -> 2.1810142 | BG14: 2.2132463 | BH14: 2.0862545 | BI14: 2.2066158 | BJ14: 2.0192263 | BK14: 2.0565754 | BL14: 1.7450413 | BM14: 2.1585499 | BN14: 2.0057992 | BO14: 1.7419242
B15: Gross Coal to Hot Metal Ratio | C15: Kg/ THM | D15: 900.75554 | E15: 893.55022 | F15: =+'Coal to Hot Metal'!F20 -> 925.1827 | G15: 905.15064 | H15: =+'Coal to Hot Metal'!H20 -> 937.47513 | I15: =+'Coal to Hot Metal'!I20 -> 898.82801 | J15: =+'Coal to Hot Metal'!J20 -> 930.88043 | K15: 962.86201 | L15: =+'Coal to Hot Metal'!L20 -> 954.82611 | M15: =+'Coal to Hot Metal'!M20 -> 919.12901 | N15: =+'Coal to Hot Metal'!N20 -> 939.04003 | O15: 915.2098 | P15: =+'Coal to Hot Metal'!P20 -> 910.83232 | Q15: =+((M15*'Maj Production Summ'!M$17)+('Maj Production Summ'!O$17*O15))/('Maj Production Summ'!Q$17) -> 918.05605 | R15: =+'Coal to Hot Metal'!R20 -> 931.14038 | S15: 905.96326 | T15: =+'Coal to Hot Metal'!T20 -> 944.91307 | U15: =+((Q15*'Maj Production Summ'!Q$17)+('Maj Production Summ'!S$17*S15))/('Maj Production Summ'!U$17) -> 915.45697 | V15: =+'Coal to Hot Metal'!V20 -> 934.02494 | W15: 896.96967 | X15: =+'Coal to Hot Metal'!X20 -> 929.11391 | Y15: =+'Coal to Hot Metal'!Y20 -> 906.13708 | Z15: =+'Coal to Hot Metal'!Z20 -> 928.27267 | AA15: =+((M15*'Maj Production Summ'!M$17)+('Maj Production Summ'!Y$17*Y15))/('Maj Production Summ'!AA$17) -> 912.26571 | AB15: =+'Coal to Hot Metal'!AB20 -> 933.20939 | AC15: 890.13076 | AD15: =+'Coal to Hot Metal'!AD20 -> 937.6445 | AE15: =+((AA15*'Maj Production Summ'!AA$17)+('Maj Production Summ'!AC$17*AC15))/('Maj Production Summ'!AE$17) -> 908.84106 | AF15: =+'Coal to Hot Metal'!AF20 -> 933.87597 | AG15: 890.13076 | AH15: =+'Coal to Hot Metal'!AH20 -> 997.38835 | AI15: =+((AE15*'Maj Production Summ'!AE$17)+('Maj Production Summ'!AG$17*AG15))/('Maj Production Summ'!AI$17) -> 906.40504 | AJ15: =+'Coal to Hot Metal'!AJ20 -> 941.15458 | AK15: 890.13076 | AL15: =+'Coal to Hot Metal'!AL20 -> 934.24824 | AM15: =+'Coal to Hot Metal'!AM20 -> 890.13076 | AN15: =+'Coal to Hot Metal'!AN20 -> 954.63214 | AO15: =+'Coal to Hot Metal'!AO20 -> 904.46781 | AP15: =+'Coal to Hot Metal'!AP20 -> 940.3759 | AQ15: 890.13076 | AR15: =+'Coal to Hot Metal'!AR20 -> 925.34688 | AS15: =+((AO15*'Maj Production Summ'!AO$17)+('Maj Production Summ'!AQ$17*AQ15))/('Maj Production Summ'!AS$17) -> 902.94272 | AT15: =+'Coal to Hot Metal'!AT20 -> 938.81777 | AU15: 890.13076 | AV15: =+'Coal to Hot Metal'!AV20 -> 904.46032 | AW15: =+((AS15*'Maj Production Summ'!AS$17)+('Maj Production Summ'!AU$17*AU15))/('Maj Production Summ'!AW$17) -> 901.78804 | AX15: =+'Coal to Hot Metal'!AX20 -> 935.63748 | AY15: 890.13076 | AZ15: =+'Coal to Hot Metal'!AZ20 -> 894.04149 | BA15: =+'Coal to Hot Metal'!BA20 -> 890.13076 | BB15: =+'Coal to Hot Metal'!BB20 -> 907.90589 | BC15: =+'Coal to Hot Metal'!BC20 -> 890.13076 | BD15: =+'Coal to Hot Metal'!BD20 -> 930.90931 | BE15: =+'Coal to Hot Metal'!BE20 -> 900.75554 | BF15: =+'Coal to Hot Metal'!BF20 -> 932.03785 | BG15: 910.43802 | BH15: 930.86111 | BI15: 908.3767 | BJ15: 935.21205 | BK15: 907.50854 | BL15: 991.44637 | BM15: 886.42712 | BN15: 931.68363 | BO15: 905.6097
B16: Hot Metal to Crude Steel | C16: Kg/ TCS | D16: 1060 | E16: =+$D$16 -> 1060 | F16: =+(F38/'Maj Production Summ'!F18)*1000 -> 1071.4673 | G16: =+$D$16 -> 1060 | H16: =+(H38/'Maj Production Summ'!H18)*1000 -> 1063.2423 | I16: =+$D$16 -> 1060 | J16: =+(J38/'Maj Production Summ'!J18)*1000 -> 1067.7713 | K16: =+$D$16 -> 1060 | L16: =+(L38/'Maj Production Summ'!L18)*1000 -> 1068.4689 | M16: =+$D$16 -> 1060 | N16: =+(N38/'Maj Production Summ'!N18)*1000 -> 1067.9969 | O16: =+$D$16 -> 1060 | P16: =+(P38/'Maj Production Summ'!P18)*1000 -> 1061.4144 | Q16: =+$D$16 -> 1060 | R16: =+(R38/'Maj Production Summ'!R18)*1000 -> 1066.1235 | S16: =+$D$16 -> 1060 | T16: =+(T38/'Maj Production Summ'!T18)*1000 -> 1063.9466 | U16: =+$D$16 -> 1060 | V16: =+(V38/'Maj Production Summ'!V18)*1000 -> 1065.6502 | W16: =$D$16 -> 1060 | X16: =+(X38/'Maj Production Summ'!X18)*1000 -> 1078.7197 | Y16: =+$D$16 -> 1060 | Z16: =+(Z38/'Maj Production Summ'!Z18)*1000 -> 1067.7493 | AA16: =+$D$16 -> 1060 | AB16: =+(AB38/'Maj Production Summ'!AB18)*1000 -> 1067.8644 | AC16: =$D$16 -> 1060 | AD16: =+(AD38/'Maj Production Summ'!AD18)*1000 -> 1086.2346 | AE16: =+$D$16 -> 1060 | AF16: =+(AF38/'Maj Production Summ'!AF18)*1000 -> 1070.6615 | AG16: =$D$16 -> 1060 | AH16: =+(AH38/'Maj Production Summ'!AH18)*1000 -> 1062.7649 | AI16: =+$D$16 -> 1060 | AJ16: =+(AJ38/'Maj Production Summ'!AJ18)*1000 -> 1069.7464 | AK16: =$D$16 -> 1060 | AL16: =+(AL38/'Maj Production Summ'!AL18)*1000 -> 1045.1989 | AM16: =+$D$16 -> 1060 | AN16: =+(AN38/'Maj Production Summ'!AN18)*1000 -> 1065.01 | AO16: =+$D$16 -> 1060 | AP16: =+(AP38/'Maj Production Summ'!AP18)*1000 -> 1066.9015 | AQ16: =$D$16 -> 1060 | AR16: =+(AR38/'Maj Production Summ'!AR18)*1000 -> 1059.626 | AS16: =+$D$16 -> 1060 | AT16: =+(AT38/'Maj Production Summ'!AT18)*1000 -> 1066.1455 | AU16: =$D$16 -> 1060 | AV16: =+(AV38/'Maj Production Summ'!AV18)*1000 -> 1066.2531 | AW16: =+$D$16 -> 1060 | AX16: =+(AX38/'Maj Production Summ'!AX18)*1000 -> 1066.1555 | AY16: =$D$16 -> 1060 | AZ16: =+(AZ38/'Maj Production Summ'!AZ18)*1000 -> 1064.4942 | BA16: =+$D$16 -> 1060 | BB16: =+(BB38/'Maj Production Summ'!BB18)*1000 -> 1063.4465 | BC16: =+$D$16 -> 1060 | BD16: =+(BD38/'Maj Production Summ'!BD18)*1000 -> 1064.2172 | BE16: =+$D$16 -> 1060 | BF16: =+(BF38/'Maj Production Summ'!BF18)*1000 -> 1066.0114 | BG16: 1062 | BH16: 1062.9741 | BI16: 1064.9999 | BJ16: 1062.0577 | BK16: 1077.0434 | BL16: 1071.1761 | BM16: 1065 | BN16: 1093.6626 | BO16: 1078.33
B17: Scrap consumption at SMS | C17: Kg/ TCS | D17: 40 | E17: =+$D$17 -> 40 | F17: =+(F39/'Maj Production Summ'!F18)*1000 -> 31.793782 | G17: =+$D$17 -> 40 | H17: =+(H39/'Maj Production Summ'!H18)*1000 -> 42.997243 | I17: =+$D$17 -> 40 | J17: =+(J39/'Maj Production Summ'!J18)*1000 -> 36.828175 | K17: =+$D$17 -> 40 | L17: =+(L39/'Maj Production Summ'!L18)*1000 -> 36.034919 | M17: =+$D$17 -> 40 | N17: =+(N39/'Maj Production Summ'!N18)*1000 -> 36.571668 | O17: =+$D$17 -> 40 | P17: =+(P39/'Maj Production Summ'!P18)*1000 -> 38.166745 | Q17: =+$D$17 -> 40 | R17: =+(R39/'Maj Production Summ'!R18)*1000 -> 37.025642 | S17: =+$D$17 -> 40 | T17: =+(T39/'Maj Production Summ'!T18)*1000 -> 34.125408 | U17: =+$D$17 -> 40 | V17: =+(V39/'Maj Production Summ'!V18)*1000 -> 36.395116 | W17: =$D$17 -> 40 | X17: =+(X39/'Maj Production Summ'!X18)*1000 -> 22.128095 | Y17: =+$D$17 -> 40 | Z17: =+(Z39/'Maj Production Summ'!Z18)*1000 -> 31.723627 | AA17: =+$D$17 -> 40 | AB17: =+(AB39/'Maj Production Summ'!AB18)*1000 -> 33.978014 | AC17: =$D$17 -> 40 | AD17: =+(AD39/'Maj Production Summ'!AD18)*1000 -> 14.188033 | AE17: =+$D$17 -> 40 | AF17: =+(AF39/'Maj Production Summ'!AF18)*1000 -> 30.964809 | AG17: =$D$17 -> 40 | AH17: =+(AH39/'Maj Production Summ'!AH18)*1000 -> 32.065625 | AI17: =+$D$17 -> 40 | AJ17: =+(AJ39/'Maj Production Summ'!AJ18)*1000 -> 31.092368 | AK17: =$D$17 -> 40 | AL17: =+(AL39/'Maj Production Summ'!AL18)*1000 -> 54.232185 | AM17: =+$D$17 -> 40 | AN17: =+(AN39/'Maj Production Summ'!AN18)*1000 -> 33.373826 | AO17: =+$D$17 -> 40 | AP17: =+(AP39/'Maj Production Summ'!AP18)*1000 -> 33.774187 | AQ17: =$D$17 -> 40 | AR17: =+(AR39/'Maj Production Summ'!AR18)*1000 -> 40.27807 | AS17: =+$D$17 -> 40 | AT17: =+(AT39/'Maj Production Summ'!AT18)*1000 -> 34.449938 | AU17: =$D$17 -> 40 | AV17: =+(AV39/'Maj Production Summ'!AV18)*1000 -> 33.453509 | AW17: =+$D$17 -> 40 | AX17: =+(AX39/'Maj Production Summ'!AX18)*1000 -> 34.357432 | AY17: =$D$17 -> 40 | AZ17: =+(AZ39/'Maj Production Summ'!AZ18)*1000 -> 35.205786 | BA17: =+(BA39/'Maj Production Summ'!BA18)*1000 -> 40 | BB17: =+(BB39/'Maj Production Summ'!BB18)*1000 -> 36.32384 | BC17: =+(BC39/'Maj Production Summ'!BC18)*1000 -> 40 | BD17: =+(BD39/'Maj Production Summ'!BD18)*1000 -> 34.869676 | BE17: =+(BE39/'Maj Production Summ'!BE18)*1000 -> 40 | BF17: =+(BF39/'Maj Production Summ'!BF18)*1000 -> 34.431041 | BG17: 46 | BH17: 38.506405 | BI17: 50 | BJ17: 45.611233 | BK17: 40.465028 | BL17: 41.122433 | BM17: 50 | BN17: 25.532166 | BO17: 41.130412
B18: TMI | C18: Kg/ TCS | D18: =SUM(D16:D17) -> 1100 | E18: =+$D$18 -> 1100 | F18: =SUM(F16:F17) -> 1103.2611 | G18: =+$D$18 -> 1100 | H18: =SUM(H16:H17) -> 1106.2395 | I18: =+$D$18 -> 1100 | J18: =SUM(J16:J17) -> 1104.5995 | K18: =+$D$18 -> 1100 | L18: =SUM(L16:L17) -> 1104.5038 | M18: =+$D$18 -> 1100 | N18: =SUM(N16:N17) -> 1104.5686 | O18: =+$D$18 -> 1100 | P18: =SUM(P16:P17) -> 1099.5811 | Q18: =+$D$18 -> 1100 | R18: =SUM(R16:R17) -> 1103.1491 | S18: =+$D$18 -> 1100 | T18: =SUM(T16:T17) -> 1098.072 | U18: =+$D$18 -> 1100 | V18: =SUM(V16:V17) -> 1102.0453 | W18: =+$D$18 -> 1100 | X18: =SUM(X16:X17) -> 1100.8478 | Y18: =+$D$18 -> 1100 | Z18: =SUM(Z16:Z17) -> 1099.4729 | AA18: =+$D$18 -> 1100 | AB18: =SUM(AB16:AB17) -> 1101.8424 | AC18: =+$D$18 -> 1100 | AD18: =SUM(AD16:AD17) -> 1100.4227 | AE18: =+$D$18 -> 1100 | AF18: =SUM(AF16:AF17) -> 1101.6263 | AG18: =+$D$18 -> 1100 | AH18: =SUM(AH16:AH17) -> 1094.8305 | AI18: =+$D$18 -> 1100 | AJ18: =SUM(AJ16:AJ17) -> 1100.8388 | AK18: =+$D$18 -> 1100 | AL18: =SUM(AL16:AL17) -> 1099.4311 | AM18: =+$D$18 -> 1100 | AN18: =SUM(AN16:AN17) -> 1098.3838 | AO18: =+$D$18 -> 1100 | AP18: =SUM(AP16:AP17) -> 1100.6756 | AQ18: =+$D$18 -> 1100 | AR18: =SUM(AR16:AR17) -> 1099.9041 | AS18: =+$D$18 -> 1100 | AT18: =SUM(AT16:AT17) -> 1100.5955 | AU18: =+$D$18 -> 1100 | AV18: =SUM(AV16:AV17) -> 1099.7066 | AW18: =+$D$18 -> 1100 | AX18: =SUM(AX16:AX17) -> 1100.513 | AY18: =+$D$18 -> 1100 | AZ18: =SUM(AZ16:AZ17) -> 1099.7 | BA18: =+$D$18 -> 1100 | BB18: =SUM(BB16:BB17) -> 1099.7704 | BC18: =+$D$18 -> 1100 | BD18: =SUM(BD16:BD17) -> 1099.0869 | BE18: =+$D$18 -> 1100 | BF18: =SUM(BF16:BF17) -> 1100.4424 | BG18: 1108 | BH18: 1101.4805 | BI18: 1114.9999 | BJ18: 1107.6689 | BK18: 1117.5084 | BL18: 1112.2985 | BM18: 1115 | BN18: 1119.1948 | BO18: 1119.4604
B19: Ferro Alloys (inc LCFeMn) | C19: Kg/ TCS | D19: =+D50+D51+D54 -> 21.173677 | E19: =+$D$19 -> 21.173677 | F19: =F50+F53+F54 -> 24.26939 | G19: =+$D$19 -> 21.173677 | H19: =H50+H53+H54 -> 23.571449 | I19: =+$D$19 -> 21.173677 | J19: =J50+J53+J54 -> 23.955763 | K19: =+$D$19 -> 21.173677 | L19: =L50+L53+L54 -> 22.901375 | M19: =+$D$19 -> 21.173677 | N19: =N50+N53+N54 -> 23.614816 | O19: =+$D$19 -> 21.173677 | P19: =+P50+P53+P54 -> 22.624572 | Q19: =+$D$19 -> 21.173677 | R19: =R50+R53+R54 -> 23.332983 | S19: =+$D$19 -> 21.173677 | T19: =+T50+T53+T54 -> 23.204552 | U19: =+$D$19 -> 21.173677 | V19: =V50+V53+V54 -> 23.305061 | W19: =+$D$19 -> 21.173677 | X19: =X50+X51+X54 -> 22.921154 | Y19: =+$D$19 -> 21.173677 | Z19: =Z50+Z53+Z54 -> 22.914251 | AA19: =+$D$19 -> 21.173677 | AB19: =AB50+AB53+AB54 -> 23.24002 | AC19: =+$D$19 -> 21.173677 | AD19: =AD50+AD53+AD54 -> 23.482919 | AE19: =+$D$19 -> 21.173677 | AF19: =AF50+AF53+AF54 -> 23.277004 | AG19: =+$D$19 -> 21.173677 | AH19: =AH50+AH53+AH54 -> 23.745152 | AI19: =+$D$19 -> 21.173677 | AJ19: =AJ50+AJ53+AJ54 -> 23.331251 | AK19: =+$D$19 -> 21.173677 | AL19: =AL50+AL53+AL54 -> 22.64862 | AM19: =+$D$19 -> 21.173677 | AN19: =AN50+AN53+AN54 -> 23.275936 | AO19: =+$D$19 -> 21.173677 | AP19: =AP50+AP53+AP54 -> 23.252137 | AQ19: =+$D$19 -> 21.173677 | AR19: =AR50+AR53+AR54 -> 21.097667 | AS19: =+$D$19 -> 21.173677 | AT19: =AT50+AT53+AT54 -> 23.028288 | AU19: =+$D$19 -> 21.173677 | AV19: =AV50+AV53+AV54 -> 21.056952 | AW19: =+$D$19 -> 21.173677 | AX19: =AX50+AX53+AX54 -> 22.845274 | AY19: =+$D$19 -> 21.173677 | AZ19: =AZ50+AZ53+AZ54 -> 21.191558 | BA19: =+$D$19 -> 21.173677 | BB19: =BB50+BB53+BB54 -> 21.11589 | BC19: =+$D$19 -> 21.173677 | BD19: =BD50+BD53+BD54 -> 22.180651 | BE19: =+$D$19 -> 21.173677 | BF19: =BF50+BF53+BF54 -> 22.701786 | BG19: 21 | BH19: 22.930617 | BI19: 21.95779 | BJ19: 20.936322 | BK19: 20.938578 | BL19: 20.212673 | BM19: 21 | BN19: 21.832464 | BO19: 23.120676
B20: Mill yield
B21: WR Mill | C21: % | D21: 96 | E21: =+$D$21 -> 96 | F21: =+WRM!F127 -> 95.511559 | G21: =+$D$21 -> 96 | H21: =+WRM!H127 -> 95.428893 | I21: =+$D$21 -> 96 | J21: =+WRM!J127 -> 95.474536 | K21: =+$D$21 -> 96 | L21: =+WRM!L127 -> 95.378901 | M21: =+$D$21 -> 96 | N21: =+WRM!N127 -> 95.443958 | O21: =+$D$21 -> 96 | P21: =+WRM!P127 -> 96.122203 | Q21: =+$D$21 -> 96 | R21: =+WRM!R127 -> 95.6372 | S21: =+$D$21 -> 96 | T21: =+WRM!T127 -> 95.912175 | U21: =+$D$21 -> 96 | V21: =+WRM!V127 -> 95.703546 | W21: =+$D$21 -> 96 | X21: =+WRM!X127 -> 96.332563 | Y21: =+$D$21 -> 96 | Z21: =+WRM!Z127 -> 96.12008 | AA21: =+$D$21 -> 96 | AB21: =+WRM!AB127 -> 95.822793 | AC21: =+$D$21 -> 96 | AD21: =+WRM!AD127 -> 95.789459 | AE21: =+$D$21 -> 96 | AF21: =+WRM!AF127 -> 95.817671 | AG21: =+$D$21 -> 96 | AH21: =+WRM!AH127 -> 96.219045 | AI21: =+$D$21 -> 96 | AJ21: =+WRM!AJ127 -> 95.868201 | AK21: =+$D$21 -> 96 | AL21: =+WRM!AL127 -> 96.179584 | AM21: =+$D$21 -> 96 | AN21: =+WRM!AN127 -> 96.05801 | AO21: =+$D$21 -> 96 | AP21: =+WRM!AP127 -> 95.904007 | AQ21: =+$D$21 -> 96 | AR21: =+WRM!AR127 -> 96.114071 | AS21: =+$D$21 -> 96 | AT21: =+WRM!AT127 -> 95.926718 | AU21: =+$D$21 -> 96 | AV21: =+WRM!AV127 -> 95.658422 | AW21: =+$D$21 -> 96 | AX21: =+WRM!AX127 -> 95.904477 | AY21: =+$D$21 -> 96 | AZ21: =+WRM!AZ127 -> 95.620503 | BA21: =+$D$21 -> 96 | BB21: =+WRM!BB127 -> 95.814187 | BC21: =+$D$21 -> 96 | BD21: =+WRM!BD127 -> 95.939089 | BE21: =+$D$21 -> 96 | BF21: =+WRM!BF127 -> 95.881785 | BG21: 96 | BH21: 95.450038 | BI21: 96 | BJ21: 95.505336 | BK21: 96.222984 | BL21: 94.958654 | BM21: 96.5 | BN21: 96.195271 | BO21: 96.032659
B22: Bar Mill | C22: % | D22: 96.5 | E22: =+$D$22 -> 96.5 | F22: =+BM!F54 -> 95.688197 | G22: =+$D$22 -> 96.5 | H22: =+BM!H54 -> 95.843256 | I22: =+$D$22 -> 96.5 | J22: =+BM!J54 -> 95.757067 | K22: =+$D$22 -> 96.5 | L22: =+BM!L54 -> 95.747583 | M22: =+$D$22 -> 96.5 | N22: =+BM!N54 -> 95.754217 | O22: =+$D$22 -> 96.5 | P22: =+BM!P54 -> 95.984318 | Q22: =+$D$22 -> 96.5 | R22: =+BM!R54 -> 95.821059 | S22: =+$D$22 -> 96.5 | T22: =+BM!T54 -> 96.282521 | U22: =+$D$22 -> 96.5 | V22: =+BM!V54 -> 95.932705 | W22: =+$D$22 -> 96.5 | X22: =+BM!X54 -> 96.220523 | Y22: =+$D$22 -> 96.5 | Z22: =+BM!Z54 -> 96.164319 | AA22: =+$D$22 -> 96.5 | AB22: =+BM!AB54 -> 95.97996 | AC22: =+$D$22 -> 96.5 | AD22: =+BM!AD54 -> 96.155345 | AE22: =+$D$22 -> 96.5 | AF22: =+BM!AF54 -> 96.003033 | AG22: =+$D$22 -> 96.5 | AH22: =+BM!AH54 -> 95.971529 | AI22: =+$D$22 -> 96.5 | AJ22: =+BM!AJ54 -> 95.999469 | AK22: =+$D$22 -> 96.5 | AL22: =+BM!AL54 -> 96.151151 | AM22: =+$D$22 -> 96.5 | AN22: =+BM!AN54 -> 96.095901 | AO22: =+$D$22 -> 96.5 | AP22: =+BM!AP54 -> 96.01682 | AQ22: =+$D$22 -> 96.5 | AR22: =+BM!AR54 -> 96.359159 | AS22: =+$D$22 -> 96.5 | AT22: =+BM!AT54 -> 96.053452 | AU22: =+$D$22 -> 96.5 | AV22: =+BM!AV54 -> 96.19913 | AW22: =+$D$22 -> 96.5 | AX22: =+BM!AX54 -> 96.066528 | AY22: =+$D$22 -> 96.5 | AZ22: =+BM!AZ54 -> 96.320742 | BA22: =+$D$22 -> 96.5 | BB22: =+BM!BB54 -> 96.295371 | BC22: =+$D$22 -> 96.5 | BD22: =+BM!BD54 -> 96.200119 | BE22: =+$D$22 -> 96.5 | BF22: =+BM!BF54 -> 96.088708 | BG22: 96.5 | BH22: 95.450022 | BI22: 96.499982 | BJ22: 95.423966 | BK22: 96.209843 | BL22: 95.175924 | BM22: 96.5 | BN22: 96.065593 | BO22: 96.05494
B23: US Mill | C23: % | D23: 94.5 | E23: =+$D$23 -> 94.5 | F23: =+USM!G75 -> 93.240057 | G23: =+$D$23 -> 94.5 | H23: =+USM!I75 -> 93.172235 | I23: =+$D$23 -> 94.5 | J23: =+USM!K75 -> 86.30769 | K23: =+$D$23 -> 94.5 | L23: =+USM!M75 -> 93.333162 | M23: =+$D$23 -> 94.5 | N23: =+USM!O75 -> 93.247931 | O23: =+$D$23 -> 94.5 | P23: =+USM!Q75 -> 93.234016 | Q23: =+$D$23 -> 94.5 | R23: =+USM!S75 -> 86.312579 | S23: =+$D$23 -> 94.5 | T23: =+USM!U75 -> 93.989717 | U23: =+$D$23 -> 94.5 | V23: =+USM!W75 -> 88.301364 | W23: =+$D$23 -> 94.5 | X23: =+USM!Y75 -> 94.274437 | Y23: =+$D$23 -> 94.5 | Z23: =+USM!AA75 -> 93.862675 | AA23: =+$D$23 -> 94.5 | AB23: =+USM!AC75 -> 93.587746 | AC23: =+$D$23 -> 94.5 | AD23: =+USM!AE75 -> 94.011323 | AE23: =+$D$23 -> 94.5 | AF23: =+USM!AG75 -> 93.654014 | AG23: =+$D$23 -> 94.5 | AH23: =+USM!AI75 -> 94.749412 | AI23: =+$D$23 -> 94.5 | AJ23: =+USM!AK75 -> 93.810844 | AK23: =+$D$23 -> 94.5 | AL23: =+USM!AM75 -> 95.116565 | AM23: =+$D$23 -> 94.5 | AN23: =+USM!AO75 -> 94.636166 | AO23: =+$D$23 -> 94.5 | AP23: =+USM!AQ75 -> 93.971804 | AQ23: =+$D$23 -> 94.5 | AR23: =+USM!AS75 -> 95.222924 | AS23: =+$D$23 -> 94.5 | AT23: =+USM!AU75 -> 94.109506 | AU23: =+$D$23 -> 94.5 | AV23: =+USM!AW75 -> 94.477483 | AW23: =+$D$23 -> 94.5 | AX23: =+USM!AY75 -> 94.147359 | AY23: =+$D$23 -> 94.5 | AZ23: =+USM!BA75 -> 94.357689 | BA23: =+$D$23 -> 94.5 | BB23: =+USM!BC75 -> 94.66883 | BC23: =+$D$23 -> 94.5 | BD23: =+USM!BE75 -> 94.653083 | BE23: =+$D$23 -> 94.5 | BF23: =+USM!BG75 -> 94.168642 | BG23: 94.5 | BH23: 93.371871 | BI23: 95.700065 | BJ23: 93.445481 | BK23: 95.699819 | BL23: 95.266762 | BM23: 95.7 | BN23: 95.476013 | BO23: 95.486333
B24: Sp Energy Consumpt | C24: G.cal/TCS | D24: 5.9501062 | E24: =+EMD!D123 -> 5.9143822 | F24: =+EMD!E123 -> 6.0968116 | G24: =+EMD!F123 -> 6.1808715 | H24: =+EMD!G123 -> 6.3183196 | I24: =+EMD!H123 -> 6.0355587 | J24: =+EMD!I123 -> 6.1978563 | K24: =+EMD!J123 -> 6.0720788 | L24: =+EMD!K123 -> 6.3149178 | ... BF24: =+EMD!BE123 -> 6.1924446 | BG24: 5.9892031 | BH24: 6.2012038 | BI24: 5.9854778 | BJ24: 6.300637 | BK24: 6.1969869 | BL24: 6.4827566 | BM24: 5.95 | BN24: 6.1800191 | BO24: 6.3116941
B25: Sp Power Consumption | C25: KwH/TSS | D25: 491.86961 | E25: 483.19686 | F25: =+'POWER DISTRIBUTION'!J18/('Maj Production Summ'!F35+0.25*'Maj Production Summ'!F24) -> 489.61448 | G25: 555.34525 | H25: =+'POWER DISTRIBUTION'!L18/('Maj Production Summ'!H35+0.25*'Maj Production Summ'!H24) -> 565.21868 | I25: =+'POWER DISTRIBUTION'!M18/('Maj Production Summ'!I35+0.25*'Maj Production Summ'!I24) -> 516.00481 | J25: =+'POWER DISTRIBUTION'!N18/('Maj Production Summ'!J35+0.25*'Maj Production Summ'!J24) -> 523.03725 | K25: 535.82414 | L25: =+'POWER DISTRIBUTION'!P18/('Maj Production Summ'!L35+0.25*'Maj Production Summ'!L24) -> 507.59125 | M25: =+'POWER DISTRIBUTION'!Q18/('Maj Production Summ'!M35+0.25*'Maj Production Summ'!M24) -> 522.13785 | N25: =+'POWER DISTRIBUTION'!R18/('Maj Production Summ'!N35+0.25*'Maj Production Summ'!N24) -> 517.9436 | O25: 488.4818 | P25: =+'POWER DISTRIBUTION'!T18/('Maj Production Summ'!P35+0.25*'Maj Production Summ'!P24) -> 486.99952 | Q25: =+'POWER DISTRIBUTION'!U18/('Maj Production Summ'!Q35+0.25*'Maj Production Summ'!Q24) -> 512.83809 | R25: =+'POWER DISTRIBUTION'!V18/('Maj Production Summ'!R35+0.25*'Maj Production Summ'!R24) -> 509.24527 | S25: 488.01481 | T25: =+'POWER DISTRIBUTION'!X18/('Maj Production Summ'!T35+0.25*'Maj Production Summ'!T24) -> 489.83593 | U25: =+'POWER DISTRIBUTION'!Y18/('Maj Production Summ'!U35+0.25*'Maj Production Summ'!U24) -> 507.46395 | V25: =+'POWER DISTRIBUTION'!Z18/('Maj Production Summ'!V35+0.25*'Maj Production Summ'!V24) -> 504.97205 | W25: 488.05176 | X25: =+'POWER DISTRIBUTION'!AB18/('Maj Production Summ'!X35+0.25*'Maj Production Summ'!X24) -> 485.68393 | Y25: =+'POWER DISTRIBUTION'!AC18/('Maj Production Summ'!Y35+0.25*'Maj Production Summ'!Y24) -> 488.18411 | Z25: =+'POWER DISTRIBUTION'!AD18/('Maj Production Summ'!Z35+0.25*'Maj Production Summ'!Z24) -> 487.53707 | AA25: =+'POWER DISTRIBUTION'!AE18/('Maj Production Summ'!AA35+0.25*'Maj Production Summ'!AA24) -> 504.09483 | AB25: =+'POWER DISTRIBUTION'!AF18/('Maj Production Summ'!AB35+0.25*'Maj Production Summ'!AB24) -> 501.63071 | AC25: 480.77609 | AD25: =+'POWER DISTRIBUTION'!AH18/('Maj Production Summ'!AD35+0.25*'Maj Production Summ'!AD24) -> 494.44383 | AE25: =+'POWER DISTRIBUTION'!AI18/('Maj Production Summ'!AE35+0.25*'Maj Production Summ'!AE24) -> 500.47309 | AF25: =+'POWER DISTRIBUTION'!AJ18/('Maj Production Summ'!AF35+0.25*'Maj Production Summ'!AF24) -> 500.55097 | AG25: 481.19179 | AH25: =+'POWER DISTRIBUTION'!AL18/('Maj Production Summ'!AH35+0.25*'Maj Production Summ'!AH24) -> 530.33804 | AI25: =+'POWER DISTRIBUTION'!AM18/('Maj Production Summ'!AI35+0.25*'Maj Production Summ'!AI24) -> 497.9518 | AJ25: =+'POWER DISTRIBUTION'!AN18/('Maj Production Summ'!AJ35+0.25*'Maj Production Summ'!AJ24) -> 504.03021 | AK25: 479.98442 | AL25: =+'POWER DISTRIBUTION'!AP18/('Maj Production Summ'!AL35+0.25*'Maj Production Summ'!AL24) -> 499.38184 | AM25: =+'POWER DISTRIBUTION'!AQ18/('Maj Production Summ'!AM35+0.25*'Maj Production Summ'!AM24) -> 480.64404 | AN25: =+'POWER DISTRIBUTION'!AR18/('Maj Production Summ'!AN35+0.25*'Maj Production Summ'!AN24) -> 507.17281 | AO25: =+'POWER DISTRIBUTION'!AS18/('Maj Production Summ'!AO35+0.25*'Maj Production Summ'!AO24) -> 495.80619 | AP25: =+'POWER DISTRIBUTION'!AT18/('Maj Production Summ'!AP35+0.25*'Maj Production Summ'!AP24) -> 503.4936 | AQ25: 480.51811 | AR25: =+'POWER DISTRIBUTION'!AV18/('Maj Production Summ'!AR35+0.25*'Maj Production Summ'!AR24) -> 494.11669 | AS25: =+'POWER DISTRIBUTION'!AW18/('Maj Production Summ'!AS35+0.25*'Maj Production Summ'!AS24) -> 494.17529 | AT25: =+'POWER DISTRIBUTION'!AX18/('Maj Production Summ'!AT35+0.25*'Maj Production Summ'!AT24) -> 502.51349 | AU25: 481.09641 | AV25: =+'POWER DISTRIBUTION'!AZ18/('Maj Production Summ'!AV35+0.25*'Maj Production Summ'!AV24) -> 471.21666 | AW25: =+'POWER DISTRIBUTION'!BA18/('Maj Production Summ'!AW35+0.25*'Maj Production Summ'!AW24) -> 492.99399 | AX25: =+'POWER DISTRIBUTION'!BB18/('Maj Production Summ'!AX35+0.25*'Maj Production Summ'!AX24) -> 499.60243 | AY25: =+'POWER DISTRIBUTION'!BC18/('Maj Production Summ'!AY35+0.25*'Maj Production Summ'!AY24) -> 480.26805 | AZ25: =+'POWER DISTRIBUTION'!BD18/('Maj Production Summ'!AZ35+0.25*'Maj Production Summ'!AZ24) -> 493.99288 | BA25: =+'POWER DISTRIBUTION'!BE18/('Maj Production Summ'!BA35+0.25*'Maj Production Summ'!BA24) -> 480.61617 | BB25: =+'POWER DISTRIBUTION'!BF18/('Maj Production Summ'!BB35+0.25*'Maj Production Summ'!BB24) -> 486.51729 | BC25: =+'POWER DISTRIBUTION'!BG18/('Maj Production Summ'!BC35+0.25*'Maj Production Summ'!BC24) -> 480.63017 | ... BF25: =+'POWER DISTRIBUTION'!BJ18/('Maj Production Summ'!BF35+0.25*'Maj Production Summ'!BF24) -> 499.12041 | BG25: 499.14523 | BH25: 516.74946 | BI25: 501.08848 | BJ25: 528.34198 | BK25: 500.04339 | BL25: 579.80533 | BM25: 483.423 | BN25: 525.26173 | BO25: 552.03691
C26: KwH/TCS | D26: 475.03289 | E26: 466.35937 | F26: =+'POWER DISTRIBUTION'!J18/'Maj Production Summ'!F18 -> 468.23522 | G26: 536.02476 | H26: =+'POWER DISTRIBUTION'!L18/'Maj Production Summ'!H18 -> 524.83145 | I26: =+'POWER DISTRIBUTION'!M18/'Maj Production Summ'!I18 -> 498.03722 | J26: =+'POWER DISTRIBUTION'!N18/'Maj Production Summ'!J18 -> 493.66733 | K26: 521.1608 | L26: =+'POWER DISTRIBUTION'!P18/'Maj Production Summ'!L18 -> 493.26069 | M26: =+'POWER DISTRIBUTION'!Q18/'Maj Production Summ'!M18 -> 505.1548 | N26: =+'POWER DISTRIBUTION'!R18/'Maj Production Summ'!N18 -> 493.53584 | O26: 472.0444 | P26: =+'POWER DISTRIBUTION'!T18/'Maj Production Summ'!P18 -> 456.08687 | Q26: =+'POWER DISTRIBUTION'!U18/'Maj Production Summ'!Q18 -> 495.99811 | R26: =+'POWER DISTRIBUTION'!V18/'Maj Production Summ'!R18 -> 482.87751 | S26: 471.59312 | T26: =+'POWER DISTRIBUTION'!X18/'Maj Production Summ'!T18 -> 472.02925 | U26: =+'POWER DISTRIBUTION'!Y18/'Maj Production Summ'!U18 -> 490.71104 | V26: =+'POWER DISTRIBUTION'!Z18/'Maj Production Summ'!V18 -> 480.51904 | W26: 471.36227 | X26: =+'POWER DISTRIBUTION'!AB18/'Maj Production Summ'!X18 -> 474.74859 | Y26: =+'POWER DISTRIBUTION'!AC18/'Maj Production Summ'!Y18 -> 471.66961 | Z26: =+'POWER DISTRIBUTION'!AD18/'Maj Production Summ'!Z18 -> 467.37756 | AA26: =+'POWER DISTRIBUTION'!AE18/'Maj Production Summ'!AA18 -> 487.34954 | AB26: =+'POWER DISTRIBUTION'!AF18/'Maj Production Summ'!AB18 -> 479.54142 | AC26: 463.80111 | AD26: =+'POWER DISTRIBUTION'!AH18/'Maj Production Summ'!AD18 -> 465.28824 | AE26: =+'POWER DISTRIBUTION'!AI18/'Maj Production Summ'!AE18 -> 483.68544 | AF26: =+'POWER DISTRIBUTION'!AJ18/'Maj Production Summ'!AF18 -> 477.37124 | AG26: 464.80919 | AH26: =+'POWER DISTRIBUTION'!AL18/'Maj Production Summ'!AH18 -> 510.36374 | AI26: =+'POWER DISTRIBUTION'!AM18/'Maj Production Summ'!AI18 -> 481.21599 | AJ26: =+'POWER DISTRIBUTION'!AN18/'Maj Production Summ'!AJ18 -> 481.19428 | AK26: 463.22432 | AL26: =+'POWER DISTRIBUTION'!AP18/'Maj Production Summ'!AL18 -> 474.64121 | AM26: =+'POWER DISTRIBUTION'!AQ18/'Maj Production Summ'!AM18 -> 463.93438 | AN26: =+'POWER DISTRIBUTION'!AR18/'Maj Production Summ'!AN18 -> 482.18961 | AO26: =+'POWER DISTRIBUTION'!AS18/'Maj Production Summ'!AO18 -> 479.06491 | AP26: =+'POWER DISTRIBUTION'!AT18/'Maj Production Summ'!AP18 -> 480.43481 | AQ26: 463.73937 | AR26: =+'POWER DISTRIBUTION'!AV18/'Maj Production Summ'!AR18 -> 474.64737 | AS26: =+'POWER DISTRIBUTION'!AW18/'Maj Production Summ'!AS18 -> 477.42828 | AT26: =+'POWER DISTRIBUTION'!AX18/'Maj Production Summ'!AT18 -> 479.83349 | AU26: 464.248 | AV26: =+'POWER DISTRIBUTION'!AZ18/'Maj Production Summ'!AV18 -> 450.89618 | AW26: =+'POWER DISTRIBUTION'!BA18/'Maj Production Summ'!AW18 -> 476.23655 | AX26: =+'POWER DISTRIBUTION'!BB18/'Maj Production Summ'!AX18 -> 477.14703 | AY26: =+'POWER DISTRIBUTION'!BC18/'Maj Production Summ'!AY18 -> 462.6522 | AZ26: =+'POWER DISTRIBUTION'!BD18/'Maj Production Summ'!AZ18 -> 466.8025 | BA26: =+'POWER DISTRIBUTION'!BE18/'Maj Production Summ'!BA18 -> 463.52875 | BB26: =+'POWER DISTRIBUTION'!BF18/'Maj Production Summ'!BB18 -> 464.18893 | BC26: =+'POWER DISTRIBUTION'!BG18/'Maj Production Summ'!BC18 -> 463.7324 | ... BF26: =+'POWER DISTRIBUTION'!BJ18/'Maj Production Summ'!BF18 -> 476.24946 | BG26: 482.32053 | BH26: 494.76974 | BI26: 486.14726 | BJ26: 514.38476 | BK26: 487.74658 | BL26: 580.20286 | BM26: 448.29125 | BN26: 538.52024 | BO26: 565.51994
B27: Sp Water Consumption | C27: M³/TCS | D27: 2.85 | E27: =+$D$27 -> 2.85 | F27: 2.95 | G27: =+$D$27 -> 2.85 | H27: 3.15 | I27: =+$D$27 -> 2.85 | J27: =+((F27*F32)+(H27*H32))/J32 -> 3.0398721 | K27: =+$D$27 -> 2.85 | L27: 3.07 | M27: =+$D$27 -> 2.85 | N27: =+((F32*F27)+(H32*H27)+(L32*L27))/N32 -> 3.0496143 | O27: =+$D$27 -> 2.85 | P27: 3.02 | Q27: =+$D$27 -> 2.85 | R27: =+(((N27*N32)+(P27*P32))/R32) -> 3.0411858 | S27: =+$D$27 -> 2.85 | T27: 3.04 | U27: =+$D$27 -> 2.85 | V27: =+(((R27*R32)+(T27*T32))/V32) -> 3.040928 | W27: =+$D$27 -> 2.85 | X27: 3.1 | Y27: =+$D$27 -> 2.85 | Z27: =+((P32*P27)+(T32*T27)+(X32*X27))/Z32 -> 3.0520846 | AA27: =+$D$27 -> 2.85 | AB27: =+((N27*N32)+(Z27*Z32))/AB32 -> 3.0509359 | AC27: =+$D$27 -> 2.85 | AD27: 3.08 | AE27: =+$D$27 -> 2.85 | AF27: =+(((AB27*AB32)+(AD27*AD32))/AF32) -> 3.0553612 | AG27: =+$D$27 -> 2.85 | AH27: 3.26 | AI27: =+$D$27 -> 2.85 | AJ27: =+(((AF27*AF32)+(AH27*AH32))/AJ32) -> 3.0790739 | AK27: =+$D$27 -> 2.85 | AL27: 3.09 | AM27: =+$D$27 -> 2.85 | AN27: =+((AD32*AD27)+(AH32*AH27)+(AL32*AL27))/AN32 -> 3.1380966 | AO27: =+$D$27 -> 2.85 | AP27: =+(((AL27*AL32)+(AJ27*AJ32))/AP32) -> 3.0803402 | AQ27: =+$D$27 -> 2.85 | AR27: 3.06 | AS27: =+$D$27 -> 2.85 | AT27: =+(((AP27*AP32)+(AR27*AR32))/AT32) -> 3.0782269 | AU27: =+$D$27 -> 2.85 | AV27: 3.07 | AW27: =+$D$27 -> 2.85 | AX27: =+(((AT27*AT32)+(AV27*AV32))/AX32) -> 3.0774631 | AY27: =+$D$27 -> 2.85 | AZ27: 3.14 | BA27: =+$D$27 -> 2.85 | BB27: =+((AR27*AR32)+(AV27*AV32)+(AZ27*AZ32))/BB32 -> 3.0902346 | BC27: =+$D$27 -> 2.85 | BD27: =+((AN27*AN32)+(BB27*BB32))/BD32 -> 3.1138274 | BE27: =+$D$27 -> 2.85 | BF27: =+((AX27*AX32)+(AZ27*AZ32))/BF32 -> 3.0828892 | BG27: 3.3 | BH27: 3.0186532 | BI27: 4.3 | BJ27: 3.3197104 | BK27: 4.3 | BL27: 5.0407394 | BM27: 4.6 | BN27: 5.0056729 | BO27: 5.0192042
B28: Sp. CO2 emission | C28: T/TCS | D28: 2.375 | E28: =+$D$28 -> 2.375 | F28: 2.4119365 | G28: =+$D$28 -> 2.375 | H28: 2.4220974 | I28: =+$D$28 -> 2.375 | J28: =+((F28*F32)+(H28*H32))/J32 -> 2.4165024 | K28: =+$D$28 -> 2.375 | L28: 2.4593055 | M28: =+$D$28 -> 2.375 | N28: =+((F32*F28)+(H32*H28)+(L32*L28))/N32 -> 2.4303432 | O28: =+$D$28 -> 2.375 | P28: 2.3670535 | Q28: =+$D$28 -> 2.375 | R28: =+((N28*N32)+(P28*P32))/R32 -> 2.4123304 | S28: =+$D$28 -> 2.375 | T28: 2.4238159 | U28: =+$D$28 -> 2.375 | V28: =+((R28*R32)+(T28*T32))/V32 -> 2.4148274 | W28: =+$D$28 -> 2.375 | X28: 2.4517134 | Y28: =+$D$28 -> 2.375 | Z28: =+((P32*P28)+(T32*T28)+(X32*X28))/Z32 -> 2.413022 | AA28: =+$D$28 -> 2.375 | AB28: =+((N28*N32)+(Z28*Z32))/AB32 -> 2.4210766 | AC28: =+$D$28 -> 2.375 | AD28: 2.4494084 | AE28: =+$D$28 -> 2.375 | AF28: =+((AB28*AB32)+(AD28*AD32))/AF32 -> 2.4253903 | AG28: =+$D$28 -> 2.375 | AH28: 2.5126795 | AI28: =+$D$28 -> 2.375 | AJ28: =+((AF28*AF32)+(AH28*AH32))/AJ32 -> 2.4355051 | AK28: =+$D$28 -> 2.375 | AL28: 2.4288938 | AM28: =+$D$28 -> 2.375 | AN28: =+((AD32*AD28)+(AH32*AH28)+(AL32*AL28))/AN32 -> 2.4615745 | AO28: =+$D$28 -> 2.375 | AP28: =+((AL28*AL32)+(AJ28*AJ32))/AP32 -> 2.4347388 | AQ28: =+$D$28 -> 2.375 | AR28: 2.4203245 | AS28: =+$D$28 -> 2.375 | AT28: =+((AP28*AP32)+(AR28*AR32))/AT32 -> 2.4332412 | AU28: =+$D$28 -> 2.375 | AV28: 2.4305684 | AW28: =+$D$28 -> 2.375 | AX28: =+((AT28*AT32)+(AV28*AV32))/AX32 -> 2.4329931 | AY28: =+$D$28 -> 2.375 | AZ28: 2.3704819 | BA28: =+$D$28 -> 2.375 | BB28: =+((AR28*AR32)+(AV28*AV32)+(AZ28*AZ32))/BB32 -> 2.4069089 | BC28: =+$D$28 -> 2.375 | BD28: =+((AN28*AN32)+(BB28*BB32))/BD32 -> 2.4338555 | BE28: =+$D$28 -> 2.375 | BF28: =+((AX28*AX32)+(AZ28*AZ32))/BF32 -> 2.4275692 | BG28: 2.35 | BH28: 2.4470555 | BI28: 2.45 | BJ28: 2.4734992 | BK28: 2.45 | BL28: 2.6211068 | BM28: 2.456658 | BN28: 2.4355942 | BO28: 2.609953
B29: Sp. PM emissions | C29: kg/TCS | D29: 0.53 | E29: =+$D$29 -> 0.53 | F29: 0.54 | G29: =+$D$29 -> 0.53 | H29: 0.61 | I29: =+$D$29 -> 0.53 | J29: =+((F29*F32)+(H29*H32))/J32 -> 0.57145524 | K29: =+$D$29 -> 0.53 | L29: 0.56 | M29: =+$D$29 -> 0.53 | N29: =+((F32*F29)+(H32*H29)+(L32*L29))/N32 -> 0.56775107 | O29: =+$D$29 -> 0.53 | P29: 0.53 | Q29: =+$D$29 -> 0.53 | R29: =+((N29*N32)+(P29*P32))/R32 -> 0.55700676 | S29: =+$D$29 -> 0.53 | T29: 0.52 | U29: =+$D$29 -> 0.53 | V29: =+((R29*R32)+(T29*T32))/V32 -> 0.5489613 | W29: =+$D$29 -> 0.53 | X29: 0.51 | Y29: =+$D$29 -> 0.53 | Z29: =+((P32*P29)+(T32*T29)+(X32*X29))/Z32 -> 0.52029122 | AA29: =+$D$29 -> 0.53 | AB29: =+((N29*N32)+(Z29*Z32))/AB32 -> 0.54236052 | AC29: =+$D$29 -> 0.53 | AD29: 0.49 | AE29: =+$D$29 -> 0.53 | AF29: =+((AB29*AB32)+(AD29*AD32))/AF32 -> 0.53438815 | AG29: =+$D$29 -> 0.53 | AH29: 0.59 | AI29: =+$D$29 -> 0.53 | AJ29: =+((AF29*AF32)+(AH29*AH32))/AJ32 -> 0.54083223 | AK29: =+$D$29 -> 0.53 | AL29: 0.55 | AM29: =+$D$29 -> 0.53 | AN29: =+((AD32*AD29)+(AH32*AH29)+(AL32*AL29))/AN32 -> 0.54097986 | AO29: =+$D$29 -> 0.53 | AP29: =+((AL29*AL32)+(AJ29*AJ32))/AP32 -> 0.54189474 | AQ29: =+$D$29 -> 0.53 | AR29: 0.54 | AS29: =+$D$29 -> 0.53 | AT29: =+((AP29*AP32)+(AR29*AR32))/AT32 -> 0.54169788 | AU29: =+$D$29 -> 0.53 | AV29: 0.52 | AW29: =+$D$29 -> 0.53 | AX29: =+((AT29*AT32)+(AV29*AV32))/AX32 -> 0.5396835 | AY29: =+$D$29 -> 0.53 | AZ29: 0.48 | BA29: =+$D$29 -> 0.53 | BB29: =+((AR29*AR32)+(AV29*AV32)+(AZ29*AZ32))/BB32 -> 0.51321043 | BC29: =+$D$29 -> 0.53 | BD29: =+((AN29*AN32)+(BB29*BB32))/BD32 -> 0.52689894 | BE29: =+$D$29 -> 0.53 | BF29: =+((AX29*AX32)+(AZ29*AZ32))/BF32 -> 0.53450495 | BG29: 0.53 | BH29: 0.5280682 | BI29: 0.55 | BJ29: 0.53916083 | BK29: 0.55 | BL29: 0.62328215 | BM29: 0.551124 | BN29: 0.57147495 | BO29: 0.55061804
B30: Labour Productivity | C30: TCS/Man/Year | D30: 729.20664 | E30: =+E36 -> 733.68442 | F30: =+F36 -> 706.87215 | G30: =+G36 -> 593.83961 | H30: =+H36 -> 561.06799 | I30: =+I36 -> 662.68778 | J30: =+J36 -> 632.86743 | K30: =+K36 -> 614.6074 | L30: =+L36 -> 632.82119 | ... BF30: =+BF36 -> 695.16315 | BG30: 656.40621 | BH30: 639.11266 | BI30: 615.77607 | BJ30: 561.88094 | BK30: 549.90658 | BL30: 459.2495 | BM30: 562.64319 | BN30: 490.34382 | BO30: 421.02863
B31: Average Manpower (Works) | C31: Nos. | D31: 3607.8333 | E31: 3693 | F31: 3723 | G31: 3684 | H31: 3712 | I31: =+AVERAGE(E31,G31) -> 3688.5 | J31: =+AVERAGE(F31,H31) -> 3717.5 | K31: 3673 | L31: 3714 | M31: =+AVERAGE(E31,G31,K31) -> 3683.3333 | N31: =+AVERAGE(F31,H31,L31) -> 3716.3333 | O31: 3648 | P31: 3686 | Q31: =+AVERAGE(E31,G31,K31,O31) -> 3674.5 | R31: =+AVERAGE(F31,H31,L31,P31) -> 3708.75 | S31: 3629 | T31: 3663 | U31: =+AVERAGE(E31,G31,K31,O31,S31) -> 3665.4 | V31: =+AVERAGE(F31,H31,L31,P31,T31) -> 3699.6 | W31: 3617 | X31: 3645 | Y31: =+AVERAGE(Q31,S31,W31) -> 3640.1667 | Z31: =+AVERAGE(P31,T31,X31) -> 3664.6667 | AA31: =+AVERAGE(E31,G31,K31,O31,S31,W31) -> 3657.3333 | AB31: =+AVERAGE(X31,P31,L31,H31,T31,F31) -> 3690.5 | AC31: 3601 | AD31: 3640 | AE31: =+AVERAGE(E31,G31,K31,O31,S31,W31,AC31) -> 3649.2857 | AF31: =+AVERAGE(F31,H31,L31,P31,T31,X31,AD31) -> 3683.2857 | AG31: 3590 | AH31: 3603 | AI31: =+AVERAGE(E31,G31,K31,O31,S31,W31,AC31,AG31) -> 3641.875 | AJ31: =+AVERAGE(F31,H31,L31,P31,T31,X31,AD31,AH31) -> 3673.25 | AK31: 3563 | AL31: 3603 | AM31: =+AVERAGE(AC31,AG31,AK31) -> 3584.6667 | AN31: =+AVERAGE(AD31,AH31,AL31) -> 3615.3333 | AO31: =+AVERAGE(E31,G31,K31,O31,S31,W31,AC31,AG31,AK31) -> 3633.1111 | AP31: =+AVERAGE(F31,H31,L31,P31,T31,X31,AD31,AH31,AL31) -> 3665.4444 | AQ31: 3542 | AR31: 3501 | AS31: =+AVERAGE(E31,G31,K31,O31,S31,W31,AC31,AG31,AK31,AQ31) -> 3624 | AT31: =+AVERAGE(F31,H31,L31,P31,T31,X31,AD31,AH31,AL31,AR31) -> 3649 | AU31: 3530 | AV31: 3643 | AW31: =+AVERAGE(E31,G31,K31,O31,S31,W31,AC31,AG31,AK31,AQ31,AU31) -> 3615.4545 | AX31: =+AVERAGE(F31,H31,L31,P31,T31,X31,AD31,AH31,AL31,AR31,AV31) -> 3648.4545 | AY31: 3524 | AZ31: 3639 | BA31: =+AVERAGE(AQ31,AU31,AY31) -> 3532 | BB31: =+AVERAGE(AR31,AV31,AZ31) -> 3594.3333 | BC31: =+AVERAGE(AC31,AG31,AK31,AQ31,AU31,AY31) -> 3558.3333 | BD31: =+AVERAGE(AD31,AH31,AL31,AR31,AV31,AZ31) -> 3604.8333 | BE31: =+AVERAGE(E31,G31,K31,O31,S31,W31,AC31,AG31,AK31,AQ31,AU31,AY31) -> 3607.8333 | BF31: =+AVERAGE(F31,H31,L31,P31,T31,X31,AD31,AH31,AL31,AR31,AV31,AZ31) -> 3647.6667 | BG31: 3826.0833 | BH31: 3802.9167 | BI31: 4009.5833 | BJ31: 3995.5833 | BK31: 4196.5983 | BL31: 4090.3027 | BM31: 4470.8033 | BN31: 4421.3333 | BO31: 4614.4192
B32: Labor productivity calculation | C32: Crude Steel | E32: ='Maj Production Summ'!E18 -> 221509.43 | F32: ='Maj Production Summ'!F18 -> 215539 | G32: ='Maj Production Summ'!G18 -> 184716.98 | H32: ='Maj Production Summ'!H18 -> 175895 | I32: =+E32+G32 -> 406226.42 | J32: =+F32+H32 -> 391434 | K32: ='Maj Production Summ'!K18 -> 180641.51 | L32: ='Maj Production Summ'!L18 -> 187063 | M32: =+E32+G32+K32 -> 586867.92 | N32: =+F32+H32+L32 -> 578497 | O32: ='Maj Production Summ'!O18 -> 224339.62 | P32: ='Maj Production Summ'!P18 -> 230148 | Q32: =+M32+O32 -> 811207.55 | R32: =+N32+P32 -> 808645 | S32: ='Maj Production Summ'!S18 -> 224339.62 | T32: ='Maj Production Summ'!T18 -> 224642 | U32: =+Q32+S32 -> 1035547.2 | V32: =+R32+T32 -> 1033287 | W32: ='Maj Production Summ'!W18 -> 217735.85 | X32: ='Maj Production Summ'!X18 -> 210766 | Y32: =+O32+S32+W32 -> 666415.09 | Z32: =+P32+T32+X32 -> 665556 | AA32: =+M32+Y32 -> 1253283 | AB32: =+N32+Z32 -> 1244053 | AC32: ='Maj Production Summ'!AC18 -> 230943.4 | AD32: ='Maj Production Summ'!AD18 -> 223439 | AE32: =+AA32+AC32 -> 1484226.4 | AF32: =+AB32+AD32 -> 1467492 | AG32: ='Maj Production Summ'!AG18 -> 223396.23 | AH32: ='Maj Production Summ'!AH18 -> 192334 | AI32: =+AE32+AG32 -> 1707622.6 | AJ32: =+AF32+AH32 -> 1659826 | AK32: ='Maj Production Summ'!AK18 -> 231886.79 | AL32: ='Maj Production Summ'!AL18 -> 217585 | AM32: =+AC32+AG32+AK32 -> 686226.42 | AN32: =+AD32+AH32+AL32 -> 633358 | AO32: =AI32+AK32 -> 1939509.4 | AP32: =AJ32+AL32 -> 1877411 | AQ32: ='Maj Production Summ'!AQ18 -> 231886.79 | AR32: ='Maj Production Summ'!AR18 -> 217679 | AS32: =+AO32+AQ32 -> 2171396.2 | AT32: =+AP32+AR32 -> 2095090 | AU32: ='Maj Production Summ'!AU18 -> 215849.06 | AV32: ='Maj Production Summ'!AV18 -> 214408 | AW32: =+AS32+AU32 -> 2387245.3 | AX32: =+AT32+AV32 -> 2309498 | AY32: ='Maj Production Summ'!AY18 -> 232830.19 | AZ32: ='Maj Production Summ'!AZ18 -> 219427 | BA32: =+AQ32+AU32+AY32 -> 680566.04 | BB32: =+AR32+AV32+AZ32 -> 651514 | BC32: =+AM32+BA32 -> 1366792.5 | BD32: =+AN32+BB32 -> 1284872 | BE32: =+AW32+AY32 -> 2620075.5 | BF32: =+AX32+AZ32 -> 2528925 | BG32: 2500000 | BH32: 2422324.3 | BI32: 2573000.8 | BJ32: 2322716
C33: Pig+Eq | E33: ='Maj Production Summ'!E24 -> 1160.8961 | F33: ='Maj Production Summ'!F24 -> 345.77202 | G33: ='Maj Production Summ'!G24 -> 1160.8961 | H33: ='Maj Production Summ'!H24 -> 1014.4551 | I33: =+E33+G33 -> 2321.7923 | J33: =+F33+H33 -> 1360.2271 | K33: ='Maj Production Summ'!K24 -> 8791.2424 | L33: ='Maj Production Summ'!L24 -> 11168.741 | M33: =+E33+G33+K33 -> 11113.035 | N33: =+F33+H33+L33 -> 12528.968 | O33: ='Maj Production Summ'!O24 -> 1160.8961 | P33: ='Maj Production Summ'!P24 -> 172.40974 | Q33: =+M33+O33 -> 12273.931 | R33: =+N33+P33 -> 12701.377 | S33: ='Maj Production Summ'!S24 -> 1160.8961 | T33: ='Maj Production Summ'!T24 -> 0 | U33: =+Q33+S33 -> 13434.827 | V33: =+R33+T33 -> 12701.377 | W33: ='Maj Production Summ'!W24 -> 1160.8961 | X33: ='Maj Production Summ'!X24 -> 0 | Y33: =+O33+S33+W33 -> 3482.6884 | Z33: =+P33+T33+X33 -> 172.40974 | AA33: =+M33+Y33 -> 14595.723 | AB33: =+N33+Z33 -> 12701.377 | AC33: ='Maj Production Summ'!AC24 -> 1160.8961 | AD33: ='Maj Production Summ'!AD24 -> 0 | AE33: =+AA33+AC33 -> 15756.619 | AF33: =+AB33+AD33 -> 12701.377 | AG33: ='Maj Production Summ'!AG24 -> 1160.8961 | AH33: ='Maj Production Summ'!AH24 -> 453.40904 | AI33: =+AE33+AG33 -> 16917.515 | AJ33: =+AF33+AH33 -> 13154.787 | AK33: ='Maj Production Summ'!AK24 -> 1160.8961 | AL33: ='Maj Production Summ'!AL24 -> 165.74196 | AM33: =+AC33+AG33+AK33 -> 3482.6884 | AN33: =+AD33+AH33+AL33 -> 619.151 | AO33: =AI33+AK33 -> 18078.411 | AP33: =AJ33+AL33 -> 13320.528 | AQ33: ='Maj Production Summ'!AQ24 -> 1160.8961 | AR33: ='Maj Production Summ'!AR24 -> 0 | AS33: =+AO33+AQ33 -> 19239.308 | AT33: =+AP33+AR33 -> 13320.528 | AU33: ='Maj Production Summ'!AU24 -> 1160.8961 | AV33: ='Maj Production Summ'!AV24 -> 0 | AW33: =+AS33+AU33 -> 20400.204 | AX33: =+AT33+AV33 -> 13320.528 | AY33: ='Maj Production Summ'!AY24 -> 1160.8961 | AZ33: ='Maj Production Summ'!AZ24 -> 276.36917 | BA33: =+AQ33+AU33+AY33 -> 3482.6884 | BB33: =+AR33+AV33+AZ33 -> 276.36917 | BC33: =+AM33+BA33 -> 6965.3768 | BD33: =+AN33+BB33 -> 895.52017 | BE33: =+AW33+AY33 -> 21561.1 | BF33: =+AX33+AZ33 -> 13596.898 | BG33: 22929.735 | BH33: 16335.784 | BI33: 34051.635 | BJ33: 32547.079
C34: 50% of Pig Eq | E34: =+E33/2 -> 580.44807 | F34: =+F33/2 -> 172.88601 | G34: =+G33/2 -> 580.44807 | H34: =+H33/2 -> 507.22755 | I34: =+E34+G34 -> 1160.8961 | J34: =+F34+H34 -> 680.11356 | K34: =+K33/2 -> 4395.6212 | L34: =+L33/2 -> 5584.3703 | M34: =+E34+G34+K34 -> 5556.5173 | N34: =+F34+H34+L34 -> 6264.4839 | O34: =+O33/2 -> 580.44807 | P34: =+P33/2 -> 86.20487 | Q34: =+M34+O34 -> 6136.9654 | R34: =+N34+P34 -> 6350.6887 | S34: =+S33/2 -> 580.44807 | T34: =+T33/2 -> 0 | U34: =+Q34+S34 -> 6717.4134 | V34: =+R34+T34 -> 6350.6887 | W34: =+W33/2 -> 580.44807 | X34: =+X33/2 -> 0 | Y34: =+O34+S34+W34 -> 1741.3442 | Z34: =+P34+T34+X34 -> 86.20487 | AA34: =+M34+Y34 -> 7297.8615 | AB34: =+N34+Z34 -> 6350.6887 | AC34: =+AC33/2 -> 580.44807 | AD34: =+AD33/2 -> 0 | AE34: =+AA34+AC34 -> 7878.3096 | AF34: =+AB34+AD34 -> 6350.6887 | AG34: =+AG33/2 -> 580.44807 | AH34: =+AH33/2 -> 226.70452 | AI34: =+AE34+AG34 -> 8458.7576 | AJ34: =+AF34+AH34 -> 6577.3933 | AK34: =+AK33/2 -> 580.44807 | AL34: =+AL33/2 -> 82.87098 | AM34: =+AC34+AG34+AK34 -> 1741.3442 | AN34: =+AD34+AH34+AL34 -> 309.5755 | AO34: =AI34+AK34 -> 9039.2057 | AP34: =AJ34+AL34 -> 6660.2642 | AQ34: =+AQ33/2 -> 580.44807 | AR34: =+AR33/2 -> 0 | AS34: =+AO34+AQ34 -> 9619.6538 | AT34: =+AP34+AR34 -> 6660.2642 | AU34: =+AU33/2 -> 580.44807 | AV34: =+AV33/2 -> 0 | AW34: =+AS34+AU34 -> 10200.102 | AX34: =+AT34+AV34 -> 6660.2642 | AY34: =+AY33/2 -> 580.44807 | AZ34: =+AZ33/2 -> 138.18458 | BA34: =+AQ34+AU34+AY34 -> 1741.3442 | BB34: =+AR34+AV34+AZ34 -> 138.18458 | BC34: =+AM34+BA34 -> 3482.6884 | BD34: =+AN34+BB34 -> 447.76008 | BE34: =+AW34+AY34 -> 10780.55 | BF34: =+AX34+AZ34 -> 6798.4488 | BG34: 11464.868 | BH34: 8167.892 | BI34: 17025.818 | BJ34: 16273.54
C35: CS+50%Pig Eq | E35: =+E32+E34 -> 222089.88 | F35: =+F32+F34 -> 215711.89 | G35: =+G32+G34 -> 185297.43 | H35: =+H32+H34 -> 176402.23 | I35: =+E35+G35 -> 407387.31 | J35: =+F35+H35 -> 392114.11 | K35: =+K32+K34 -> 185037.13 | L35: =+L32+L34 -> 192647.37 | M35: =+E35+G35+K35 -> 592424.44 | N35: =+F35+H35+L35 -> 584761.48 | O35: =+O32+O34 -> 224920.07 | P35: =+P32+P34 -> 230234.2 | Q35: =+M35+O35 -> 817344.51 | R35: =+N35+P35 -> 814995.69 | S35: =+S32+S34 -> 224920.07 | T35: =+T32+T34 -> 224642 | U35: =+Q35+S35 -> 1042264.6 | V35: =+R35+T35 -> 1039637.7 | W35: =+W32+W34 -> 218316.3 | X35: =+X32+X34 -> 210766 | Y35: =+O35+S35+W35 -> 668156.44 | Z35: =+P35+T35+X35 -> 665642.2 | AA35: =+M35+Y35 -> 1260580.9 | AB35: =+N35+Z35 -> 1250403.7 | AC35: =+AC32+AC34 -> 231523.84 | AD35: =+AD32+AD34 -> 223439 | AE35: =+AA35+AC35 -> 1492104.7 | AF35: =+AB35+AD35 -> 1473842.7 | AG35: =+AG32+AG34 -> 223976.67 | AH35: =+AH32+AH34 -> 192560.7 | AI35: =+AE35+AG35 -> 1716081.4 | AJ35: =+AF35+AH35 -> 1666403.4 | AK35: =+AK32+AK34 -> 232467.24 | AL35: =+AL32+AL34 -> 217667.87 | AM35: =+AC35+AG35+AK35 -> 687967.76 | AN35: =+AD35+AH35+AL35 -> 633667.58 | AO35: =AI35+AK35 -> 1948548.6 | AP35: =AJ35+AL35 -> 1884071.3 | AQ35: =+AQ32+AQ34 -> 232467.24 | AR35: =+AR32+AR34 -> 217679 | AS35: =+AO35+AQ35 -> 2181015.9 | AT35: =+AP35+AR35 -> 2101750.3 | AU35: =+AU32+AU34 -> 216429.5 | AV35: =+AV32+AV34 -> 214408 | AW35: =+AS35+AU35 -> 2397445.4 | AX35: =+AT35+AV35 -> 2316158.3 | AY35: =+AY32+AY34 -> 233410.64 | AZ35: =+AZ32+AZ34 -> 219565.18 | BA35: =+AQ35+AU35+AY35 -> 682307.38 | BB35: =+AR35+AV35+AZ35 -> 651652.18 | BC35: =+AM35+BA35 -> 1370275.1 | BD35: =+AN35+BB35 -> 1285319.8 | BE35: =+AW35+AY35 -> 2630856 | BF35: =+AX35+AZ35 -> 2535723.4 | BG35: 2511464.9 | BH35: 2430492.2 | BI35: 2590026.6 | BJ35: 2338989.5
E36: =+E35/(E31/366*E2) -> 733.68442 | F36: =+F35/(F31/366*F2) -> 706.87215 | G36: =+G35/(G31/366*G2) -> 593.83961 | H36: =+H35/(H31/366*H2) -> 561.06799 | I36: =+I35/(I31/366*I2) -> 662.68778 | J36: =+J35/(J31/366*J2) -> 632.86743 | K36: =+K35/(K31/366*K2) -> 614.6074 | L36: =+L35/(L31/366*L2) -> 632.82119 | ... BF36: =+BF35/(BF31/366*BF2) -> 695.16315 | BG36: 656.40621 | BH36: 639.11266 | BI36: 645.95904 | BJ36: 585.39376
B38: Hot metal consumed in BOF | C38: MT | E38: =+(E16*E32)/1000 -> 234800 | F38: =+SMS!F15 -> 230943 | G38: =+(G16*G32)/1000 -> 195800 | H38: =+SMS!H15 -> 187019 | I38: =+(I16*I32)/1000 -> 430600 | J38: =+SMS!J15 -> 417962 | K38: =+(K16*K32)/1000 -> 191480 | L38: =+SMS!L15 -> 199871 | M38: =+(M16*M32)/1000 -> 622080 | N38: =+SMS!N15 -> 617833 | O38: =+(O16*O32)/1000 -> 237800 | P38: =+SMS!P15 -> 244282.4 | Q38: =+(Q16*Q32)/1000 -> 859880 | R38: =+SMS!R15 -> 862115.4 | S38: =+(S16*S32)/1000 -> 237800 | T38: =+SMS!T15 -> 239007.1 | U38: =+(U16*U32)/1000 -> 1097680 | V38: =+SMS!V15 -> 1101122.5 | W38: =+(W16*W32)/1000 -> 230800 | X38: =+SMS!X15 -> 227357.44 | Y38: =+O38+S38+W38 -> 706400 | Z38: =+P38+T38+X38 -> 710646.94 | AA38: =+M38+Y38 -> 1328480 | AB38: =+N38+Z38 -> 1328479.9 | AC38: =+(AC16*AC32)/1000 -> 244800 | AD38: =+SMS!AD15 -> 242707.18 | AE38: =+(AE16*AE32)/1000 -> 1573280 | AF38: =+SMS!AF15 -> 1571187.1 | AG38: =+(AG16*AG32)/1000 -> 236800 | AH38: =+SMS!AH15 -> 204405.82 | AI38: =+(AI16*AI32)/1000 -> 1810080 | AJ38: =+SMS!AJ15 -> 1775592.9 | AK38: =+(AK16*AK32)/1000 -> 245800 | AL38: =+SMS!AL15 -> 227419.6 | AM38: =+AC38+AG38+AK38 -> 727400 | AN38: =+AD38+AH38+AL38 -> 674532.6 | AO38: =+(AO16*AO32)/1000 -> 2055880 | AP38: =+SMS!AP15 -> 2003012.5 | AQ38: =+(AQ16*AQ32)/1000 -> 245800 | AR38: =+SMS!AR15 -> 230658.33 | AS38: =+(AS16*AS32)/1000 -> 2301680 | AT38: =+SMS!AT15 -> 2233670.9 | AU38: =+(AU16*AU32)/1000 -> 228800 | AV38: =+SMS!AV15 -> 228613.19 | AW38: =+(AW16*AW32)/1000 -> 2530480 | AX38: =+SMS!AX15 -> 2462284.1 | AY38: =+(AY16*AY32)/1000 -> 246800 | AZ38: =+SMS!AZ15 -> 233578.77 | BA38: =+AQ38+AU38+AY38 -> 721400 | BB38: =+AR38+AV38+AZ38 -> 692850.29 | BC38: =+AM38+BA38 -> 1448800 | BD38: =+AN38+BB38 -> 1367382.9 | BE38: =+AW38+AY38 -> 2777280 | BF38: =+AX38+AZ38 -> 2695862.8 | BG38: 2655000 | BH38: 2574868 | BI38: 2611100.5 | BJ38: 2366123.2
B39: Total Scrap Charged | C39: MT | E39: =+(E17*E32)/1000 -> 8860.3774 | F39: =+SMS!F19 -> 6852.8 | G39: =+(G17*G32)/1000 -> 7388.6792 | H39: =+SMS!H19 -> 7563 | I39: =+(I17*I32)/1000 -> 16249.057 | J39: =+SMS!J19 -> 14415.8 | K39: =+(K17*K32)/1000 -> 7225.6604 | L39: =+SMS!L19 -> 6740.8 | M39: =+(M17*M32)/1000 -> 23474.717 | N39: =+SMS!N19 -> 21156.6 | O39: =+(O17*O32)/1000 -> 8973.5849 | P39: =+SMS!P19 -> 8784 | Q39: =+(Q17*Q32)/1000 -> 32448.302 | R39: =+SMS!R19 -> 29940.6 | S39: =+(S17*S32)/1000 -> 8973.5849 | T39: =+SMS!T19 -> 7666 | U39: =+(U17*U32)/1000 -> 41421.887 | V39: =+SMS!V19 -> 37606.6 | W39: =+(W17*W32)/1000 -> 8709.434 | X39: =+SMS!X19 -> 4663.85 | Y39: =+O39+S39+W39 -> 26656.604 | Z39: =+P39+T39+X39 -> 21113.85 | AA39: =+M39+Y39 -> 50131.321 | AB39: =+N39+Z39 -> 42270.45 | AC39: =+(AC17*AC32)/1000 -> 9237.7358 | AD39: =+SMS!AD19 -> 3170.16 | AE39: =+(AE17*AE32)/1000 -> 59369.057 | AF39: =+SMS!AF19 -> 45440.61 | AG39: =+(AG17*AG32)/1000 -> 8935.8491 | AH39: =+SMS!AH19 -> 6167.31 | AI39: =+(AI17*AI32)/1000 -> 68304.906 | AJ39: =+SMS!AJ19 -> 51607.92 | AK39: =+(AK17*AK32)/1000 -> 9275.4717 | AL39: =+SMS!AL19 -> 11800.11 | AM39: =+AC39+AG39+AK39 -> 27449.057 | AN39: =+AD39+AH39+AL39 -> 21137.58 | AO39: =+(AO17*AO32)/1000 -> 77580.377 | AP39: =+SMS!AP19 -> 63408.03 | AQ39: =+(AQ17*AQ32)/1000 -> 9275.4717 | AR39: =+SMS!AR19 -> 8767.69 | AS39: =+(AS17*AS32)/1000 -> 86855.849 | AT39: =+SMS!AT19 -> 72175.72 | AU39: =+(AU17*AU32)/1000 -> 8633.9623 | AV39: =+SMS!AV19 -> 7172.7 | AW39: =+(AW17*AW32)/1000 -> 95489.811 | AX39: =+SMS!AX19 -> 79348.42 | AY39: =+(AY17*AY32)/1000 -> 9313.2075 | AZ39: =+SMS!AZ19 -> 7725.1 | BA39: =+AQ39+AU39+AY39 -> 27222.642 | BB39: =+AR39+AV39+AZ39 -> 23665.49 | BC39: =+AM39+BA39 -> 54671.698 | BD39: =+AN39+BB39 -> 44803.07 | BE39: =+AW39+AY39 -> 104803.02 | BF39: =+AX39+AZ39 -> 87073.52 | BG39: 121081.64 | BH39: 93275 | BI39: 128650.04 | BJ39: 101615.76
B40: Fe-Mn | C40: MT | E40: =+(E48*'Maj Production Summ'!E$18)/1000 -> 286.18653 | F40: =+SMS!F55 -> 361 | G40: =+(G48*'Maj Production Summ'!G$18)/1000 -> 238.65129 | H40: =+SMS!H55 -> 259 | I40: =+(I48*'Maj Production Summ'!I$18)/1000 -> 524.83782 | J40: =+SMS!J55 -> 620 | K40: =+(K48*'Maj Production Summ'!K$18)/1000 -> 233.38585 | L40: =+SMS!L55 -> 313 | M40: =+(M48*'Maj Production Summ'!M$18)/1000 -> 758.22367 | N40: =+SMS!N55 -> 933 | O40: =+(O48*'Maj Production Summ'!O$18)/1000 -> 289.84309 | P40: =+SMS!P55 -> 465 | Q40: =+(Q48*'Maj Production Summ'!Q$18)/1000 -> 1048.0668 | R40: =+SMS!R55 -> 1398 | S40: =+(S48*'Maj Production Summ'!S$18)/1000 -> 289.84309 | T40: =+SMS!T55 -> 488 | U40: =+(U48*'Maj Production Summ'!U$18)/1000 -> 1337.9098 | V40: =+SMS!V55 -> 1886 | W40: =+(W48*'Maj Production Summ'!W$18)/1000 -> 281.31112 | X40: =+SMS!X55 -> 460 | Y40: =+O40+S40+W40 -> 860.9973 | Z40: =+P40+T40+X40 -> 1413 | AA40: =+M40+Y40 -> 1619.221 | AB40: =+N40+Z40 -> 2346 | AC40: =+(AC48*'Maj Production Summ'!AC$18)/1000 -> 298.37506 | AD40: =+SMS!AD55 -> 438 | AE40: =+(AE48*'Maj Production Summ'!AE$18)/1000 -> 1917.596 | AF40: =+SMS!AF55 -> 2784 | AG40: =+(AG48*'Maj Production Summ'!AG$18)/1000 -> 288.62424 | AH40: =+SMS!AH55 -> 383 | AI40: =+(AI48*'Maj Production Summ'!AI$18)/1000 -> 2206.2203 | AJ40: =+SMS!AJ55 -> 3167 | AK40: =+(AK48*'Maj Production Summ'!AK$18)/1000 -> 299.59391 | AL40: =+SMS!AL55 -> 468 | AM40: =+AC40+AG40+AK40 -> 886.5932 | AN40: =+AD40+AH40+AL40 -> 1289 | AO40: =+(AO48*'Maj Production Summ'!AO$18)/1000 -> 2505.8142 | AP40: =+SMS!AP55 -> 3635 | AQ40: =+(AQ48*'Maj Production Summ'!AQ$18)/1000 -> 299.59391 | AR40: =+SMS!AR55 -> 509 | AS40: =+(AS48*'Maj Production Summ'!AS$18)/1000 -> 2805.4081 | AT40: =+SMS!AT55 -> 4144 | AU40: =+(AU48*'Maj Production Summ'!AU$18)/1000 -> 278.87342 | AV40: =+SMS!AV55 -> 351 | AW40: =+(AW48*'Maj Production Summ'!AW$18)/1000 -> 3084.2815 | AX40: =+SMS!AX55 -> 4495 | AY40: =+(AY48*'Maj Production Summ'!AY$18)/1000 -> 300.81276 | AZ40: =+SMS!AZ55 -> 232 | BA40: =+AQ40+AU40+AY40 -> 879.28009 | BB40: =+AR40+AV40+AZ40 -> 1092 | BC40: =+AM40+BA40 -> 1765.8733 | BD40: =+AN40+BB40 -> 2381 | BE40: =+AW40+AY40 -> 3385.0943 | BF40: =+AX40+AZ40 -> 4727 | BG40: 4500 | BH40: 4569.84 | BI40: 6693.3528 | BJ40: 4136
B41: LCFeMn | C41: MT | E41: 0 | F41: =+SMS!F56 -> 172 | G41: 0 | H41: =+SMS!H56 -> 132.1 | I41: 0 | J41: =+SMS!J56 -> 304.1 | K41: 0 | L41: =+SMS!L56 -> 115 | M41: 0 | N41: =+SMS!N56 -> 419.1 | O41: 0 | P41: =+SMS!P56 -> 53 | Q41: 0 | R41: =+SMS!R56 -> 472.1 | S41: 0 | T41: =+SMS!T56 -> 161.907 | U41: 0 | V41: =+SMS!V56 -> 634.007 | W41: 0 | X41: =+SMS!X56 -> 138 | Y41: =+O41+S41+W41 -> 0 | Z41: =+P41+T41+X41 -> 352.907 | AA41: =+M41+Y41 -> 0 | AB41: =+N41+Z41 -> 772.007 | AD41: =+SMS!AD56 -> 141 | AE41: 0 | AF41: =+SMS!AF56 -> 913.007 | AH41: =+SMS!AH56 -> 180 | AI41: 0 | AJ41: =+SMS!AJ56 -> 1093.007 | AL41: =+SMS!AL56 -> 154 | AM41: =+AC41+AG41+AK41 -> 0 | AN41: =+AD41+AH41+AL41 -> 475 | AO41: 0 | AP41: =+SMS!AP56 -> 1247.007 | AR41: =+SMS!AR56 -> 147.519 | AS41: 0 | AT41: =+SMS!AT56 -> 1394.526 | AV41: =+SMS!AV56 -> 149.779 | AW41: 0 | AX41: =+SMS!AX56 -> 1544.305 | AZ41: =+SMS!AZ56 -> 124 | BA41: =+AQ41+AU41+AY41 -> 0 | BB41: =+AR41+AV41+AZ41 -> 421.298 | BC41: =+AM41+BA41 -> 0 | BD41: =+AN41+BB41 -> 896.298 | BE41: =+AW41+AY41 -> 0 | BF41: =+AX41+AZ41 -> 1668.305 | BG41: 0 | BH41: 1122.042 | BI41: 0 | BJ41: 968.34
B42: Total Fe-Mn | C42: MT | E42: =SUM(E40:E41) -> 286.18653 | F42: =SUM(F40:F41) -> 533 | G42: =SUM(G40:G41) -> 238.65129 | H42: =SUM(H40:H41) -> 391.1 | I42: =SUM(I40:I41) -> 524.83782 | J42: =SUM(J40:J41) -> 924.1 | K42: =SUM(K40:K41) -> 233.38585 | L42: =SUM(L40:L41) -> 428 | ... BF42: =SUM(BF40:BF41) -> 6395.305 | BG42: 4500 | BH42: 5691.882 | BI42: 6693.3528 | BJ42: 5104.34
B43: Si-Mn | C43: MT | E43: =+(E51*'Maj Production Summ'!E$18)/1000 -> 3726.3307 | F43: =+SMS!F58 -> 4210 | G43: =+(G51*'Maj Production Summ'!G$18)/1000 -> 3107.3916 | H43: =+SMS!H58 -> 3389 | I43: =+(I51*'Maj Production Summ'!I$18)/1000 -> 6833.7223 | J43: =+SMS!J58 -> 7599 | K43: =+(K51*'Maj Production Summ'!K$18)/1000 -> 3038.8322 | L43: =+SMS!L58 -> 3467 | M43: =+(M51*'Maj Production Summ'!M$18)/1000 -> 9872.5544 | N43: =+SMS!N58 -> 11066 | O43: =+(O51*'Maj Production Summ'!O$18)/1000 -> 3773.9414 | P43: =+SMS!P58 -> 4239 | Q43: =+(Q51*'Maj Production Summ'!Q$18)/1000 -> 13646.496 | R43: =+SMS!R58 -> 15305 | S43: =+(S51*'Maj Production Summ'!S$18)/1000 -> 3773.9414 | T43: =+SMS!T58 -> 4070 | U43: =+(U51*'Maj Production Summ'!U$18)/1000 -> 17420.437 | V43: =+SMS!V58 -> 19375 | W43: =+(W51*'Maj Production Summ'!W$18)/1000 -> 3662.8497 | X43: =+SMS!X58 -> 3797 | Y43: =+O43+S43+W43 -> 11210.732 | Z43: =+P43+T43+X43 -> 12106 | AA43: =+M43+Y43 -> 21083.287 | AB43: =+N43+Z43 -> 23172 | AC43: =+(AC51*'Maj Production Summ'!AC$18)/1000 -> 3885.033 | AD43: =+SMS!AD58 -> 4187 | AE43: =+(AE51*'Maj Production Summ'!AE$18)/1000 -> 24968.32 | AF43: =+SMS!AF58 -> 27359 | AG43: =+(AG51*'Maj Production Summ'!AG$18)/1000 -> 3758.0711 | AH43: =+SMS!AH58 -> 3639 | AI43: =+(AI51*'Maj Production Summ'!AI$18)/1000 -> 28726.391 | AJ43: =+SMS!AJ58 -> 30998 | AK43: =+(AK51*'Maj Production Summ'!AK$18)/1000 -> 3900.9032 | AL43: =+SMS!AL58 -> 3809 | AM43: =+AC43+AG43+AK43 -> 11544.007 | AN43: =+AD43+AH43+AL43 -> 11635 | AO43: =+(AO51*'Maj Production Summ'!AO$18)/1000 -> 32627.294 | AP43: =+SMS!AP58 -> 34807 | AQ43: =+(AQ51*'Maj Production Summ'!AQ$18)/1000 -> 3900.9032 | AR43: =+SMS!AR58 -> 3467 | AS43: =+(AS51*'Maj Production Summ'!AS$18)/1000 -> 36528.197 | AT43: =+SMS!AT58 -> 38274 | AU43: =+(AU51*'Maj Production Summ'!AU$18)/1000 -> 3631.1093 | AV43: =+SMS!AV58 -> 3544 | AW43: =+(AW51*'Maj Production Summ'!AW$18)/1000 -> 40159.307 | AX43: =+SMS!AX58 -> 41818 | AY43: =+(AY51*'Maj Production Summ'!AY$18)/1000 -> 3916.7735 | AZ43: =+SMS!AZ58 -> 3862 | BA43: =+AQ43+AU43+AY43 -> 11448.786 | BB43: =+AR43+AV43+AZ43 -> 10873 | BC43: =+AM43+BA43 -> 22992.793 | BD43: =+AN43+BB43 -> 22508 | BE43: =+AW43+AY43 -> 44076.08 | BF43: =+AX43+AZ43 -> 45680 | BG43: 40000 | BH43: 44647.62 | BI43: 42007.866 | BJ43: 36347
B44: LP Si-Mn | C44: MT | F44: =+SMS!F59 -> 0 | H44: =+SMS!H59 -> 0 | J44: =+SMS!J59 -> 0 | L44: =+SMS!L59 -> 0 | N44: =+SMS!N59 -> 0 | P44: =+SMS!P59 -> 0 | R44: =+SMS!R59 -> 0 | T44: =+SMS!T59 -> 25.81 | V44: =+SMS!V59 -> 25.81 | X44: =+SMS!X59 -> 0 | Z44: =P44+T44+X44 -> 25.81 | AB44: =+N44+Z44 -> 25.81 | AD44: =+SMS!AD59 -> 0 | AF44: =+SMS!AF59 -> 25.81 | AH44: =+SMS!AH59 -> 0 | AJ44: =+SMS!AJ59 -> 25.81 | AL44: =+SMS!AL59 -> 0 | AN44: =AD44+AH44+AL44 -> 0 | AP44: =+SMS!AP59 -> 25.81 | AR44: =+SMS!AR59 -> 0 | AT44: =+SMS!AT59 -> 25.81 | AV44: =+SMS!AV59 -> 0 | AX44: =+SMS!AX59 -> 25.81 | AZ44: =+SMS!AZ59 -> 0 | BB44: =+SMS!BB59 -> 0 | BD44: =+SMS!BD59 -> 0 | BF44: =+SMS!BF59 -> 25.81
B45: Total Si-Mn | C45: MT | E45: =SUM(E43:E44) -> 3726.3307 | F45: =SUM(F43:F44) -> 4210 | G45: =SUM(G43:G44) -> 3107.3916 | H45: =SUM(H43:H44) -> 3389 | I45: =SUM(I43:I44) -> 6833.7223 | J45: =SUM(J43:J44) -> 7599 | K45: =SUM(K43:K44) -> 3038.8322 | L45: =SUM(L43:L44) -> 3467 | ... BF45: =SUM(BF43:BF44) -> 45705.81
B46: Fe-Si | C46: MT | E46: =+(E54*'Maj Production Summ'!E$18)/1000 -> 624.48972 | F46: =+SMS!F61 -> 488 | G46: =+(G54*'Maj Production Summ'!G$18)/1000 -> 520.76272 | H46: =+SMS!H61 -> 366 | I46: =+(I54*'Maj Production Summ'!I$18)/1000 -> 1145.2524 | J46: =+SMS!J61 -> 854 | K46: =+(K54*'Maj Production Summ'!K$18)/1000 -> 509.27296 | L46: =+SMS!L61 -> 389 | M46: =+(M54*'Maj Production Summ'!M$18)/1000 -> 1654.5254 | N46: =+SMS!N61 -> 1243 | O46: =+(O54*'Maj Production Summ'!O$18)/1000 -> 632.46872 | P46: =+SMS!P61 -> 450 | Q46: =+(Q54*'Maj Production Summ'!Q$18)/1000 -> 2286.9941 | R46: =+SMS!R61 -> 1693 | S46: =+(S54*'Maj Production Summ'!S$18)/1000 -> 632.46872 | T46: =+SMS!T61 -> 467 | U46: =+(U54*'Maj Production Summ'!U$18)/1000 -> 2919.4629 | V46: =+SMS!V61 -> 2160 | W46: =+(W54*'Maj Production Summ'!W$18)/1000 -> 613.85106 | X46: =+SMS!X61 -> 436 | Y46: =+O46+S46+W46 -> 1878.7885 | Z46: =+P46+T46+X46 -> 1353 | AA46: =+M46+Y46 -> 3533.3139 | AB46: =+N46+Z46 -> 2596 | AC46: =+(AC54*'Maj Production Summ'!AC$18)/1000 -> 651.08639 | AD46: =+SMS!AD61 -> 481 | AE46: =+(AE54*'Maj Production Summ'!AE$18)/1000 -> 4184.4003 | AF46: =+SMS!AF61 -> 3077 | AG46: =+(AG54*'Maj Production Summ'!AG$18)/1000 -> 629.80905 | AH46: =+SMS!AH61 -> 365 | AI46: =+(AI54*'Maj Production Summ'!AI$18)/1000 -> 4814.2094 | AJ46: =+SMS!AJ61 -> 3442 | AK46: =+(AK54*'Maj Production Summ'!AK$18)/1000 -> 653.74605 | AL46: =+SMS!AL61 -> 497 | AM46: =+AC46+AG46+AK46 -> 1934.6415 | AN46: =+AD46+AH46+AL46 -> 1343 | AO46: =+(AO54*'Maj Production Summ'!AO$18)/1000 -> 5467.9554 | AP46: =+SMS!AP61 -> 3939 | AQ46: =+(AQ54*'Maj Production Summ'!AQ$18)/1000 -> 653.74605 | AR46: =+SMS!AR61 -> 469 | AS46: =+(AS54*'Maj Production Summ'!AS$18)/1000 -> 6121.7015 | AT46: =+SMS!AT61 -> 4408 | AU46: =+(AU54*'Maj Production Summ'!AU$18)/1000 -> 608.53172 | AV46: =+SMS!AV61 -> 470 | AW46: =+(AW54*'Maj Production Summ'!AW$18)/1000 -> 6730.2332 | AX46: =+SMS!AX61 -> 4878 | AY46: =+(AY54*'Maj Production Summ'!AY$18)/1000 -> 656.40572 | AZ46: =+SMS!AZ61 -> 432 | BA46: =+AQ46+AU46+AY46 -> 1918.6835 | BB46: =+AR46+AV46+AZ46 -> 1371 | BC46: =+AM46+BA46 -> 3853.325 | BD46: =+AN46+BB46 -> 2714 | BE46: =+AW46+AY46 -> 7386.6389 | BF46: =+AX46+AZ46 -> 5310 | BG46: 8000 | BH46: 5205.89 | BI46: 7796.1924 | BJ46: 5192
B47: Ferro Alloys Break-up
B48: Fe-Mn | C48: Kg/TCS | D48: 1.2919835 | E48: =+$D$48 -> 1.2919835 | F48: =+(F40/'Maj Production Summ'!F$18)*1000 -> 1.6748709 | G48: =+$D$48 -> 1.2919835 | H48: =+(H40/'Maj Production Summ'!H$18)*1000 -> 1.4724694 | I48: =+$D$48 -> 1.2919835 | J48: =+(J40/'Maj Production Summ'!J$18)*1000 -> 1.5839196 | K48: =+$D$48 -> 1.2919835 | L48: =+(L40/'Maj Production Summ'!L$18)*1000 -> 1.6732331 | M48: =+$D$48 -> 1.2919835 | N48: =+(N40/'Maj Production Summ'!N$18)*1000 -> 1.6128001 | O48: =+$D$48 -> 1.2919835 | P48: =+(P40/'Maj Production Summ'!P$18)*1000 -> 2.020439 | Q48: =+$D$48 -> 1.2919835 | R48: =+(R40/'Maj Production Summ'!R$18)*1000 -> 1.728818 | S48: =+$D$48 -> 1.2919835 | T48: =+(T40/'Maj Production Summ'!T$18)*1000 -> 2.1723453 | U48: =+$D$48 -> 1.2919835 | V48: =+(V40/'Maj Production Summ'!V$18)*1000 -> 1.8252431 | W48: =+$D$48 -> 1.2919835 | X48: =+(X40/'Maj Production Summ'!X$18)*1000 -> 2.1825152 | Y48: =+$D$48 -> 1.2919835 | Z48: =+(Z40/'Maj Production Summ'!Z$18)*1000 -> 2.123037 | AA48: =+$D$48 -> 1.2919835 | AB48: =+(AB40/'Maj Production Summ'!AB$18)*1000 -> 1.8857717 | AC48: =+$D$48 -> 1.2919835 | AD48: =+(AD40/'Maj Production Summ'!AD$18)*1000 -> 1.9602666 | AE48: =+$D$48 -> 1.2919835 | AF48: =+(AF40/'Maj Production Summ'!AF$18)*1000 -> 1.8971143 | AG48: =+$D$48 -> 1.2919835 | AH48: =+(AH40/'Maj Production Summ'!AH$18)*1000 -> 1.9913276 | AI48: =+$D$48 -> 1.2919835 | AJ48: =+(AJ40/'Maj Production Summ'!AJ$18)*1000 -> 1.9080313 | AK48: =+$D$48 -> 1.2919835 | AL48: =+(AL40/'Maj Production Summ'!AL$18)*1000 -> 2.1508836 | AM48: =+$D$48 -> 1.2919835 | AN48: =+(AN40/'Maj Production Summ'!AN$18)*1000 -> 2.0351839 | AO48: =+$D$48 -> 1.2919835 | AP48: =+(AP40/'Maj Production Summ'!AP$18)*1000 -> 1.936177 | AQ48: =+$D$48 -> 1.2919835 | AR48: =+(AR40/'Maj Production Summ'!AR$18)*1000 -> 2.3383055 | AS48: =+$D$48 -> 1.2919835 | AT48: =+(AT40/'Maj Production Summ'!AT$18)*1000 -> 1.977958 | AU48: =+$D$48 -> 1.2919835 | AV48: =+(AV40/'Maj Production Summ'!AV$18)*1000 -> 1.6370658 | AW48: =+$D$48 -> 1.2919835 | AX48: =+(AX40/'Maj Production Summ'!AX$18)*1000 -> 1.9463104 | AY48: =+$D$48 -> 1.2919835 | AZ48: =+(AZ40/'Maj Production Summ'!AZ$18)*1000 -> 1.0572992 | BA48: =+$D$48 -> 1.2919835 | BB48: =+(BB40/'Maj Production Summ'!BB$18)*1000 -> 1.676096 | BC48: =+$D$48 -> 1.2919835 | BD48: =+(BD40/'Maj Production Summ'!BD$18)*1000 -> 1.8531029 | BE48: =+$D$48 -> 1.2919835 | BF48: =+(BF40/'Maj Production Summ'!BF$18)*1000 -> 1.8691737 | BG48: 1.8 | BH48: 1.8865517 | BI48: 2.60138 | BJ48: 1.780674
B49: LCFeMn | C49: Kg/TCS | D49: 0.24 | E49: =+$D$49 -> 0.24 | F49: =+(F41/'Maj Production Summ'!F$18)*1000 -> 0.79799943 | G49: =+$D$49 -> 0.24 | H49: =+(H41/'Maj Production Summ'!H$18)*1000 -> 0.75101623 | I49: =+$D$49 -> 0.24 | J49: =+(J41/'Maj Production Summ'!J$18)*1000 -> 0.77688704 | K49: =+$D$49 -> 0.24 | L49: =+(L41/'Maj Production Summ'!L$18)*1000 -> 0.61476615 | M49: =+$D$49 -> 0.24 | N49: =+(N41/'Maj Production Summ'!N$18)*1000 -> 0.72446357 | O49: =+$D$49 -> 0.24 | P49: =+(P41/'Maj Production Summ'!P$18)*1000 -> 0.2302866 | Q49: =+$D$49 -> 0.24 | R49: =+(R41/'Maj Production Summ'!R$18)*1000 -> 0.58381614 | S49: =+$D$49 -> 0.24 | T49: =+(T41/'Maj Production Summ'!T$18)*1000 -> 0.72073343 | U49: =+$D$49 -> 0.24 | V49: =+(V41/'Maj Production Summ'!V$18)*1000 -> 0.61358267 | W49: =+$D$49 -> 0.24 | X49: =+(X41/'Maj Production Summ'!X$18)*1000 -> 0.65475456 | Y49: =+$D$49 -> 0.24 | Z49: =+(Z41/'Maj Production Summ'!Z$18)*1000 -> 0.53024389 | AA49: =+$D$49 -> 0.24 | AB49: =+(AB41/'Maj Production Summ'!AB$18)*1000 -> 0.62055797 | AC49: =+$D$49 -> 0.24 | AD49: =+(AD41/'Maj Production Summ'!AD$18)*1000 -> 0.63104471 | AE49: =+$D$49 -> 0.24 | AF49: =+(AF41/'Maj Production Summ'!AF$18)*1000 -> 0.62215467 | AG49: =+$D$49 -> 0.24 | AH49: =+(AH41/'Maj Production Summ'!AH$18)*1000 -> 0.93587197 | AI49: =+$D$49 -> 0.24 | AJ49: =+(AJ41/'Maj Production Summ'!AJ$18)*1000 -> 0.65850698 | AK49: =+$D$49 -> 0.24 | AL49: =+(AL41/'Maj Production Summ'!AL$18)*1000 -> 0.70776938 | AM49: =+$D$49 -> 0.24 | AN49: =+(AN41/'Maj Production Summ'!AN$18)*1000 -> 0.74997079 | AO49: =+$D$49 -> 0.24 | AP49: =+(AP41/'Maj Production Summ'!AP$18)*1000 -> 0.66421631 | AQ49: =+$D$49 -> 0.24 | AR49: =+(AR41/'Maj Production Summ'!AR$18)*1000 -> 0.67769054 | AS49: =+$D$49 -> 0.24 | AT49: =+(AT41/'Maj Production Summ'!AT$18)*1000 -> 0.66561627 | AU49: =+$D$49 -> 0.24 | AV49: =+(AV41/'Maj Production Summ'!AV$18)*1000 -> 0.69857002 | AW49: =+$D$49 -> 0.24 | AX49: =+(AX41/'Maj Production Summ'!AX$18)*1000 -> 0.66867562 | AY49: =+$D$49 -> 0.24 | AZ49: =+(AZ41/'Maj Production Summ'!AZ$18)*1000 -> 0.56510821 | BA49: =+$D$49 -> 0.24 | BB49: =+(BB41/'Maj Production Summ'!BB$18)*1000 -> 0.64664458 | BC49: =+$D$49 -> 0.24 | BD49: =+(BD41/'Maj Production Summ'!BD$18)*1000 -> 0.69757766 | BE49: =+$D$49 -> 0.24 | BF49: =+(BF41/'Maj Production Summ'!BF$18)*1000 -> 0.65968939 | BG49: 0 | BH49: 0.46320883 | BI49: 0 | BJ49: 0.41689987
B50: Total Fe-Mn | C50: Kg/TCS | D50: =SUM(D48:D49) -> 1.5319835 | E50: =SUM(E48:E49) -> 1.5319835 | F50: =SUM(F48:F49) -> 2.4728703 | G50: =SUM(G48:G49) -> 1.5319835 | H50: =SUM(H48:H49) -> 2.2234856 | I50: =SUM(I48:I49) -> 1.5319835 | J50: =SUM(J48:J49) -> 2.3608067 | K50: =SUM(K48:K49) -> 1.5319835 | ... BF50: =SUM(BF48:BF49) -> 2.5288631 | BG50: 1.8 | BH50: 2.3497605 | BI50: 2.60138 | BJ50: 2.1975739
B51: Si-Mn | C51: Kg/TCS | D51: 16.822447 | E51: =+$D$51 -> 16.822447 | F51: =+(F43/'Maj Production Summ'!F$18)*1000 -> 19.532428 | G51: =+$D$51 -> 16.822447 | H51: =+(H43/'Maj Production Summ'!H$18)*1000 -> 19.267176 | I51: =+$D$51 -> 16.822447 | J51: =+(J43/'Maj Production Summ'!J$18)*1000 -> 19.413234 | K51: =+$D$51 -> 16.822447 | L51: =+(L43/'Maj Production Summ'!L$18)*1000 -> 18.533863 | M51: =+$D$51 -> 16.822447 | N51: =+(N43/'Maj Production Summ'!N$18)*1000 -> 19.128881 | O51: =+$D$51 -> 16.822447 | P51: =+(P43/'Maj Production Summ'!P$18)*1000 -> 18.418583 | Q51: =+$D$51 -> 16.822447 | R51: =+(R43/'Maj Production Summ'!R$18)*1000 -> 18.926723 | S51: =+$D$51 -> 16.822447 | T51: =+(T43/'Maj Production Summ'!T$18)*1000 -> 18.117716 | U51: =+$D$51 -> 16.822447 | V51: =+(V43/'Maj Production Summ'!V$18)*1000 -> 18.750841 | W51: =+$D$51 -> 16.822447 | X51: =+(X43/'Maj Production Summ'!X$18)*1000 -> 18.01524 | Y51: =+$D$51 -> 16.822447 | Z51: =+(Z43/'Maj Production Summ'!Z$18)*1000 -> 18.189303 | AA51: =+$D$51 -> 16.822447 | AB51: =+(AB43/'Maj Production Summ'!AB$18)*1000 -> 18.626216 | AC51: =+$D$51 -> 16.822447 | AD51: =+(AD43/'Maj Production Summ'!AD$18)*1000 -> 18.738895 | AE51: =+$D$51 -> 16.822447 | AF51: =+(AF43/'Maj Production Summ'!AF$18)*1000 -> 18.643373 | AG51: =+$D$51 -> 16.822447 | AH51: =+(AH43/'Maj Production Summ'!AH$18)*1000 -> 18.920212 | AI51: =+$D$51 -> 16.822447 | AJ51: =+(AJ43/'Maj Production Summ'!AJ$18)*1000 -> 18.675452 | AK51: =+$D$51 -> 16.822447 | AL51: =+(AL43/'Maj Production Summ'!AL$18)*1000 -> 17.505802 | AM51: =+$D$51 -> 16.822447 | AN51: =+(AN43/'Maj Production Summ'!AN$18)*1000 -> 18.370337 | AO51: =+$D$51 -> 16.822447 | AP51: =+(AP43/'Maj Production Summ'!AP$18)*1000 -> 18.539894 | AQ51: =+$D$51 -> 16.822447 | AR51: =+(AR43/'Maj Production Summ'!AR$18)*1000 -> 15.927122 | AS51: =+$D$51 -> 16.822447 | AT51: =+(AT43/'Maj Production Summ'!AT$18)*1000 -> 18.268428 | AU51: =+$D$51 -> 16.822447 | AV51: =+(AV43/'Maj Production Summ'!AV$18)*1000 -> 16.529234 | AW51: =+$D$51 -> 16.822447 | AX51: =+(AX43/'Maj Production Summ'!AX$18)*1000 -> 18.106965 | AY51: =+$D$51 -> 16.822447 | AZ51: =+(AZ43/'Maj Production Summ'!AZ$18)*1000 -> 17.600386 | BA51: =+$D$51 -> 16.822447 | BB51: =+(BB43/'Maj Production Summ'!BB$18)*1000 -> 16.68882 | BC51: =+$D$51 -> 16.822447 | BD51: =+(BD43/'Maj Production Summ'!BD$18)*1000 -> 17.517698 | BE51: =+$D$51 -> 16.822447 | BF51: =+(BF43/'Maj Production Summ'!BF$18)*1000 -> 18.063011 | BG51: 16 | BH51: 18.431727 | BI51: 16.32641 | BJ51: 15.648491
B52: LP Si-Mn | C52: Kg/TCS | D52: 0 | E52: =D52 -> 0 | F52: =+(F44/'Maj Production Summ'!F$18)*1000 -> 0 | G52: =D52 -> 0 | H52: =+(H44/'Maj Production Summ'!H$18)*1000 -> 0 | J52: =+(J44/'Maj Production Summ'!J$18)*1000 -> 0 | K52: =D52 -> 0 | L52: =+(L44/'Maj Production Summ'!L$18)*1000 -> 0 | M52: =D52 -> 0 | N52: =+(N44/'Maj Production Summ'!N$18)*1000 -> 0 | O52: =D52 -> 0 | P52: =+(P44/'Maj Production Summ'!P$18)*1000 -> 0 | R52: =+(R44/'Maj Production Summ'!R$18)*1000 -> 0 | S52: =D52 -> 0 | T52: =+(T44/'Maj Production Summ'!T$18)*1000 -> 0.11489392 | V52: =+(V44/'Maj Production Summ'!V$18)*1000 -> 0.024978539 | W52: =D52 -> 0 | X52: =+(X44/'Maj Production Summ'!X$18)*1000 -> 0 | Y52: =D52 -> 0 | Z52: =+(Z44/'Maj Production Summ'!Z$18)*1000 -> 0.038779607 | AA52: =D52 -> 0 | AB52: =+(AB44/'Maj Production Summ'!AB$18)*1000 -> 0.020746705 | AC52: =D52 -> 0 | AD52: =+(AD44/'Maj Production Summ'!AD$18)*1000 -> 0 | AF52: =+(AF44/'Maj Production Summ'!AF$18)*1000 -> 0.01758783 | AG52: =D52 -> 0 | AH52: =+(AH44/'Maj Production Summ'!AH$18)*1000 -> 0 | AI52: =D52 -> 0 | AJ52: =+(AJ44/'Maj Production Summ'!AJ$18)*1000 -> 0.015549823 | AK52: 0 | AL52: =+(AL44/'Maj Production Summ'!AL$18)*1000 -> 0 | AM52: 0 | AN52: =+(AN44/'Maj Production Summ'!AN$18)*1000 -> 0 | AO52: =D52 -> 0 | AP52: =+(AP44/'Maj Production Summ'!AP$18)*1000 -> 0.013747656 | AQ52: =D52 -> 0 | AR52: =+(AR44/'Maj Production Summ'!AR$18)*1000 -> 0 | AS52: =D52 -> 0 | AT52: =+(AT44/'Maj Production Summ'!AT$18)*1000 -> 0.01231928 | AU52: =H52 -> 0 | AV52: =+(AV44/'Maj Production Summ'!AV$18)*1000 -> 0 | AW52: =H52 -> 0 | AX52: =+(AX44/'Maj Production Summ'!AX$18)*1000 -> 0.011175589 | AY52: =L52 -> 0 | AZ52: =+(AZ44/'Maj Production Summ'!AZ$18)*1000 -> 0 | BA52: =L52 -> 0 | BB52: =+(BB44/'Maj Production Summ'!BB$18)*1000 -> 0 | BC52: =N52 -> 0 | BD52: =+(BD44/'Maj Production Summ'!BD$18)*1000 -> 0 | BE52: =P52 -> 0 | BF52: =+(BF44/'Maj Production Summ'!BF$18)*1000 -> 0.010205918
B53: Total Si-Mn | C53: Kg/TCS | D53: =SUM(D51:D52) -> 16.822447 | E53: =+$D$51 -> 16.822447 | F53: =SUM(F51:F52) -> 19.532428 | G53: =+$D$51 -> 16.822447 | H53: =SUM(H51:H52) -> 19.267176 | I53: =+$D$51 -> 16.822447 | J53: =SUM(J51:J52) -> 19.413234 | K53: =+$D$51 -> 16.822447 | L53: =SUM(L51:L52) -> 18.533863 | M53: =+$D$51 -> 16.822447 | N53: =SUM(N51:N52) -> 19.128881 | O53: =+$D$51 -> 16.822447 | P53: =SUM(P51:P52) -> 18.418583 | Q53: =+$D$51 -> 16.822447 | R53: =SUM(R51:R52) -> 18.926723 | S53: =+$D$51 -> 16.822447 | T53: =SUM(T51:T52) -> 18.23261 | U53: =+$D$51 -> 16.822447 | V53: =SUM(V51:V52) -> 18.775819 | W53: =+$D$51 -> 16.822447 | X53: =SUM(X51:X52) -> 18.01524 | Y53: =SUM(Y51:Y52) -> 16.822447 | Z53: =SUM(Z51:Z52) -> 18.228083 | AA53: =SUM(AA51:AA52) -> 16.822447 | AB53: =SUM(AB51:AB52) -> 18.646963 | AC53: =+$D$51 -> 16.822447 | AD53: =SUM(AD51:AD52) -> 18.738895 | AE53: =+$D$51 -> 16.822447 | AF53: =SUM(AF51:AF52) -> 18.66096 | AG53: =+$D$51 -> 16.822447 | AH53: =SUM(AH51:AH52) -> 18.920212 | AI53: =+$D$51 -> 16.822447 | AJ53: =SUM(AJ51:AJ52) -> 18.691001 | AK53: =+$D$51 -> 16.822447 | AL53: =SUM(AL51:AL52) -> 17.505802 | AM53: =SUM(AM51:AM52) -> 16.822447 | AN53: =SUM(AN51:AN52) -> 18.370337 | AO53: =+$D$51 -> 16.822447 | AP53: =SUM(AP51:AP52) -> 18.553641 | AQ53: =+$D$51 -> 16.822447 | AR53: =SUM(AR51:AR52) -> 15.927122 | AS53: =+$D$51 -> 16.822447 | AT53: =SUM(AT51:AT52) -> 18.280747 | AU53: =+$D$51 -> 16.822447 | AV53: =SUM(AV51:AV52) -> 16.529234 | AW53: =+$D$51 -> 16.822447 | AX53: =SUM(AX51:AX52) -> 18.118141 | AY53: =+$D$51 -> 16.822447 | AZ53: =SUM(AZ51:AZ52) -> 17.600386 | BA53: =+$D$51 -> 16.822447 | BB53: =SUM(BB51:BB52) -> 16.68882 | BC53: =+$D$51 -> 16.822447 | BD53: =SUM(BD51:BD52) -> 17.517698 | BE53: =+$D$51 -> 16.822447 | BF53: =SUM(BF51:BF52) -> 18.073217 | BG53: =SUM(BG51:BG52) -> 16 | BH53: =SUM(BH51:BH52) -> 18.431727 | BJ53: =SUM(BJ51:BJ52) -> 15.648491
B54: Fe-Si | C54: Kg/TCS | D54: 2.8192466 | E54: =+$D$54 -> 2.8192466 | F54: =+(F46/'Maj Production Summ'!F$18)*1000 -> 2.2640914 | G54: =+$D$54 -> 2.8192466 | H54: =+(H46/'Maj Production Summ'!H$18)*1000 -> 2.0807868 | I54: =+$D$54 -> 2.8192466 | J54: =+(J46/'Maj Production Summ'!J$18)*1000 -> 2.1817216 | K54: =+$D$54 -> 2.8192466 | L54: =+(L46/'Maj Production Summ'!L$18)*1000 -> 2.0795133 | M54: =+$D$54 -> 2.8192466 | N54: =+(N46/'Maj Production Summ'!N$18)*1000 -> 2.1486715 | O54: =+$D$54 -> 2.8192466 | P54: =+(P46/'Maj Production Summ'!P$18)*1000 -> 1.9552636 | Q54: =+$D$54 -> 2.8192466 | R54: =+(R46/'Maj Production Summ'!R$18)*1000 -> 2.0936258 | S54: =+$D$54 -> 2.8192466 | T54: =+(T46/'Maj Production Summ'!T$18)*1000 -> 2.0788633 | U54: =+$D$54 -> 2.8192466 | V54: =+(V46/'Maj Production Summ'!V$18)*1000 -> 2.0904163 | W54: =+$D$54 -> 2.8192466 | X54: =+(X46/'Maj Production Summ'!X$18)*1000 -> 2.0686448 | Y54: =+$D$54 -> 2.8192466 | Z54: =+(Z46/'Maj Production Summ'!Z$18)*1000 -> 2.0328868 | AA54: =+$D$54 -> 2.8192466 | AB54: =+(AB46/'Maj Production Summ'!AB$18)*1000 -> 2.0867278 | AC54: =+$D$54 -> 2.8192466 | AD54: =+(AD46/'Maj Production Summ'!AD$18)*1000 -> 2.1527128 | AE54: =+$D$54 -> 2.8192466 | AF54: =+(AF46/'Maj Production Summ'!AF$18)*1000 -> 2.0967746 | AG54: =+$D$54 -> 2.8192466 | AH54: =+(AH46/'Maj Production Summ'!AH$18)*1000 -> 1.8977404 | AI54: =+$D$54 -> 2.8192466 | AJ54: =+(AJ46/'Maj Production Summ'!AJ$18)*1000 -> 2.0737113 | AK54: =+$D$54 -> 2.8192466 | AL54: =+(AL46/'Maj Production Summ'!AL$18)*1000 -> 2.2841648 | AM54: =+$D$54 -> 2.8192466 | AN54: =+(AN46/'Maj Production Summ'!AN$18)*1000 -> 2.1204437 | AO54: =+$D$54 -> 2.8192466 | AP54: =+(AP46/'Maj Production Summ'!AP$18)*1000 -> 2.0981021 | AQ54: =+$D$54 -> 2.8192466 | AR54: =+(AR46/'Maj Production Summ'!AR$18)*1000 -> 2.1545487 | AS54: =+$D$54 -> 2.8192466 | AT54: =+(AT46/'Maj Production Summ'!AT$18)*1000 -> 2.1039669 | AU54: =+$D$54 -> 2.8192466 | AV54: =+(AV46/'Maj Production Summ'!AV$18)*1000 -> 2.1920824 | AW54: =+$D$54 -> 2.8192466 | AX54: =+(AX46/'Maj Production Summ'!AX$18)*1000 -> 2.1121473 | AY54: =+$D$54 -> 2.8192466 | AZ54: =+(AZ46/'Maj Production Summ'!AZ$18)*1000 -> 1.9687641 | BA54: =+$D$54 -> 2.8192466 | BB54: =+(BB46/'Maj Production Summ'!BB$18)*1000 -> 2.1043293 | BC54: =+$D$54 -> 2.8192466 | BD54: =+(BD46/'Maj Production Summ'!BD$18)*1000 -> 2.1122727 | BE54: =+$D$54 -> 2.8192466 | BF54: =+(BF46/'Maj Production Summ'!BF$18)*1000 -> 2.0997064 | BG54: 3.2 | BH54: 2.1491301 | BI54: 3.03 | BJ54: 2.2353142
L63: =92*17.2 -> 1582.4
L64: =95*31.55 -> 2997.25
L65: =L63+L64 -> 4579.65
L66: =L65/(17.2+31.55) -> 93.941538

Sheet Major techno all dept
C3: MAJOR TECHNO PARAMETERS 2023-24
C4: DEPARTMENTS | D4: ITEM | E4: Unit | F4: 2022-23 Actual | G4: ABP 2023-24 | H4: Apr'23 | J4: May'23 | L4: 2M | N4: Jun'23 | P4: QTR-1 | R4: Jul'23 | T4: 4M | V4: Aug'23 | X4: 5M | Z4: Sep'23 | AB4: QTR-2 | AD4: H1 | AF4: Oct'23 | AH4: 7M | AJ4: Nov'23 | AL4: 8M | AN4: Dec'23 | AP4: QTR-3 | AR4: 9M | AT4: Jan'24 | AV4: 10M | AX4: Feb'24 | AZ4: 11M | BB4: Mar'24 | BD4: QTR-4 | BF4: H2 | BH4: 2023-24
H5: ABP | I5: ACT | J5: ABP | K5: ACT | L5: ABP | M5: ACT | N5: ABP | O5: ACT | P5: ABP | Q5: ACT | R5: ABP | S5: ACT | T5: ABP | U5: ACT | V5: ABP | W5: ACT | X5: ABP | Y5: ACT | Z5: ABP | AA5: ACT | AB5: ABP | AC5: ACT | AD5: ABP | AE5: ACT | AF5: ABP | AG5: ACT | AH5: ABP | AI5: ACT | AJ5: ABP | AK5: ACT | AL5: ABP | AM5: ACT | AN5: ABP | AO5: ACT | AP5: ABP | AQ5: ACT | AR5: ABP | AS5: ACT | AT5: ABP | AU5: ACT | AV5: ABP | AW5: ACT | AX5: ABP | AY5: ACT | AZ5: ABP | BA5: ACT | BB5: ABP | BC5: ACT | BD5: ABP | BE5: ACT | BF5: ABP | BG5: ACT | BH5: ABP | BI5: ACT
C6: COKE OVENS | D6: B.F.Coke Yield | E6: % | F6: 69.459875 | G6: 69.5 | H6: =+'Maj Techno Summ'!E5 -> 69.5 | I6: =+'Maj Techno Summ'!F5 -> 69.415591 | J6: =+'Maj Techno Summ'!G5 -> 69.5 | K6: =+'Maj Techno Summ'!H5 -> 68.896667 | L6: =+'Maj Techno Summ'!I5 -> 69.5 | M6: =+'Maj Techno Summ'!J5 -> 69.160171 | N6: =+'Maj Techno Summ'!K5 -> 69.5 | O6: =+'Maj Techno Summ'!L5 -> 69.391251 | ... BI6: =+'Maj Techno Summ'!BF5 -> 69.398029
D7: ICC in Coal Blend
D8: (COB#10) | E8: % | F8: 89.651306 | G8: 92 | H8: =+'Maj Techno Summ'!E7 -> 92 | I8: =+'Maj Techno Summ'!F7 -> 90.000179 | J8: =+'Maj Techno Summ'!G7 -> 92 | K8: =+'Maj Techno Summ'!H7 -> 90.000693 | L8: =+'Maj Techno Summ'!I7 -> 92 | M8: =+'Maj Techno Summ'!J7 -> 90.00044 | N8: =+'Maj Techno Summ'!K7 -> 92 | O8: =+'Maj Techno Summ'!L7 -> 90 | ... BI8: =+'Maj Techno Summ'!BF7 -> 90.939873
D9: (COB#11) | E9: % | F9: 92.198587 | G9: 94 | H9: =+'Maj Techno Summ'!E8 -> 94 | I9: =+'Maj Techno Summ'!F8 -> 91.999843 | J9: =+'Maj Techno Summ'!G8 -> 94 | K9: =+'Maj Techno Summ'!H8 -> 92.000162 | L9: =+'Maj Techno Summ'!I8 -> 94 | M9: =+'Maj Techno Summ'!J8 -> 92 | N9: =+'Maj Techno Summ'!K8 -> 94 | O9: =+'Maj Techno Summ'!L8 -> 91.33333 | ... BI9: =+'Maj Techno Summ'!BF8 -> 93.889004
D10: Overall ICC in Blend | E10: % | F10: 91.262624 | G10: 93.294359 | H10: =+'Maj Techno Summ'!E9 -> 93.289716 | I10: =+'Maj Techno Summ'!F9 -> 91.290585 | J10: =+'Maj Techno Summ'!G9 -> 93.289716 | K10: =+'Maj Techno Summ'!H9 -> 91.261608 | L10: =+'Maj Techno Summ'!I9 -> 93.289716 | M10: =+'Maj Techno Summ'!J9 -> 91.276155 | N10: =+'Maj Techno Summ'!K9 -> 93.289716 | O10: =+'Maj Techno Summ'!L9 -> 90.847481 | ... BI10: =+'Maj Techno Summ'!BF9 -> 92.83339
D11: Soft Coal in Blend | E11: % | F11: 23.372863 | G11: =+'COKE OVENS'!D206 -> 26.664201 | H11: =+$G$11 -> 26.664201 | I11: =+'COKE OVENS'!F206 -> 20.741718 | J11: =+$G$11 -> 26.664201 | K11: =+'COKE OVENS'!H206 -> 21.381335 | L11: =+$G$11 -> 26.664201 | M11: =+'COKE OVENS'!J206 -> 21.060225 | N11: =+$G$11 -> 26.664201 | O11: =+'COKE OVENS'!L206 -> 21.322913 | P11: =+$G$11 -> 26.664201 | Q11: =+'COKE OVENS'!N206 -> 21.146455 | R11: =+$G$11 -> 26.664201 | S11: =+'COKE OVENS'!P206 -> 18.576452 | T11: =+$G$11 -> 26.664201 | U11: =+'COKE OVENS'!R206 -> 20.483688 | V11: =+$G$11 -> 26.664201 | W11: =+'COKE OVENS'!T206 -> 18.534962 | X11: =+$G$11 -> 26.664201 | Y11: =+'COKE OVENS'!V206 -> 20.077153 | Z11: =+$G$11 -> 26.664201 | AA11: =+'COKE OVENS'!X206 -> 19.830314 | AB11: =+$G$11 -> 26.664201 | AC11: =+'COKE OVENS'!Z206 -> 18.975518 | AD11: =+$G$11 -> 26.664201 | AE11: =+'COKE OVENS'!AB206 -> 20.035534 | AF11: =+$G$11 -> 26.664201 | AG11: =+'COKE OVENS'!AD206 -> 22.370766 | AH11: =+$G$11 -> 26.664201 | AI11: =+'COKE OVENS'!AF206 -> 20.383982 | AJ11: =+$G$11 -> 26.664201 | AK11: =+'COKE OVENS'!AH206 -> 27.54546 | AL11: =+$G$11 -> 26.664201 | AM11: =+'COKE OVENS'!AJ206 -> 21.270991 | AN11: =+$G$11 -> 26.664201 | AO11: =+'COKE OVENS'!AL206 -> 27.33 | AP11: =+$G$11 -> 26.664201 | AQ11: =+'COKE OVENS'!AN206 -> 25.704665 | AR11: =+$G$11 -> 26.664201 | AS11: =+'COKE OVENS'!AP206 -> 21.95797 | AT11: =+$G$11 -> 26.664201 | AU11: =+'COKE OVENS'!AR206 -> 26.379404 | AV11: =+$G$11 -> 26.664201 | AW11: =+'COKE OVENS'!AT206 -> 22.40763 | AX11: =+$G$11 -> 26.664201 | AY11: =+'COKE OVENS'!AV206 -> 25.353363 | AZ11: =+$G$11 -> 26.664201 | BA11: =+'COKE OVENS'!AX206 -> 22.663762 | BB11: =+$G$11 -> 26.664201 | BC11: =+'COKE OVENS'!AZ206 -> 25.353827 | BD11: =+'COKE OVENS'!BA206 -> 26.664977 | BE11: =+'COKE OVENS'!BB206 -> 25.702891 | BF11: =+'COKE OVENS'!BC206 -> 26.664976 | BG11: =+'COKE OVENS'!BD206 -> 25.703787 | BH11: =+'COKE OVENS'!BE206 -> 26.664201 | BI11: =+'COKE OVENS'!BF206 -> 22.892423
D12: Average Coking Time | E12: Hrs | G12: 18.395939 | H12: =+'COKE OVENS'!E58 -> 18.364865 | I12: =+'COKE OVENS'!F58 -> 18.63 | J12: =+'COKE OVENS'!G58 -> 18.364865 | K12: =+'COKE OVENS'!H58 -> 19.25 | L12: =+'COKE OVENS'!I58 -> 18.364865 | M12: =+'COKE OVENS'!J58 -> 18.945025 | N12: =+'COKE OVENS'!K58 -> 18.364865 | O12: =+'COKE OVENS'!L58 -> 19.35 | ... BI12: =+'COKE OVENS'!BF58 -> 18.597582
D14: COB#10
D15: Soft Coal in Blend | E15: % | F15: 23.078854 | G15: 26 | H15: =+$G$15 -> 26 | I15: =+'COKE OVENS'!F141 -> 19.999642 | J15: =+$G$15 -> 26 | K15: =+'COKE OVENS'!H141 -> 21.096374 | L15: =+$G$15 -> 26 | M15: =+'COKE OVENS'!J141 -> 20.5569 | N15: =+$G$15 -> 26 | O15: =+'COKE OVENS'!L141 -> 20.2 | P15: =+$G$15 -> 26 | Q15: =+'COKE OVENS'!N141 -> 20.439226 | R15: =+$G$15 -> 26 | S15: =+'COKE OVENS'!P141 -> 15.969487 | T15: =+$G$15 -> 26 | U15: =+'COKE OVENS'!R141 -> 19.290479 | V15: =+$G$15 -> 26 | W15: =+'COKE OVENS'!T141 -> 16.806452 | X15: =+$G$15 -> 26 | Y15: =+'COKE OVENS'!V141 -> 18.771533 | Z15: =+$G$15 -> 26 | AA15: =+'COKE OVENS'!X141 -> 19.599861 | AB15: =+$G$15 -> 26 | AC15: =+'COKE OVENS'!Z141 -> 17.446184 | AD15: =+$G$15 -> 26 | AE15: =+'COKE OVENS'!AB141 -> 18.910427 | AF15: =+$G$15 -> 26 | AG15: =+'COKE OVENS'!AD141 -> 20.903226 | AH15: =+$G$15 -> 26 | AI15: =+'COKE OVENS'!AF141 -> 19.201114 | AJ15: =+$G$15 -> 26 | AK15: =+'COKE OVENS'!AH141 -> 27.266667 | AL15: =+$G$15 -> 26 | AM15: =+'COKE OVENS'!AJ141 -> 20.190265 | AN15: =+$G$15 -> 26 | AO15: =+'COKE OVENS'!AL141 -> 27.33 | AP15: =+$G$15 -> 26 | AQ15: =+'COKE OVENS'!AN141 -> 25.12196 | AR15: =+$G$15 -> 26 | AS15: =+'COKE OVENS'!AP141 -> 20.985824 | AT15: =+$G$15 -> 26 | AU15: =+'COKE OVENS'!AR141 -> 25.903226 | AV15: =+$G$15 -> 26 | AW15: =+'COKE OVENS'!AT141 -> 21.478822 | AX15: =+$G$15 -> 26 | AY15: =+'COKE OVENS'!AV141 -> 26 | AZ15: =+$G$15 -> 26 | BA15: =+'COKE OVENS'!AX141 -> 21.866494 | BB15: =+$G$15 -> 26 | BC15: =+'COKE OVENS'!AZ141 -> 26.000138 | BD15: =+'COKE OVENS'!BA141 -> 26.022507 | BE15: =+'COKE OVENS'!BB141 -> 25.967087 | BF15: =+'COKE OVENS'!BC141 -> 26.022507 | BG15: =+'COKE OVENS'!BD141 -> 25.540079 | BH15: =+'COKE OVENS'!BE141 -> 26.022504 | BI15: =+'COKE OVENS'!BF141 -> 22.213775
D16: Average Coking Time | E16: Hrs | G16: 18.787879 | H16: =+'COKE OVENS'!E56 -> 18.787879 | I16: =+'COKE OVENS'!F56 -> 18.83 | J16: =+'COKE OVENS'!G56 -> 18.787879 | K16: =+'COKE OVENS'!H56 -> 18.783 | L16: =+'COKE OVENS'!I56 -> 18.787879 | M16: =+'COKE OVENS'!J56 -> 18.806119 | N16: =+'COKE OVENS'!K56 -> 18.787879 | O16: =+'COKE OVENS'!L56 -> 18.8 | ... BI16: =+'COKE OVENS'!BF56 -> 18.817733
D17: M40 | E17: % | F17: 84.340172 | G17: 84 | H17: 84 | I17: =+'COKE OVENS'!F151 -> 84.88 | J17: =+'COKE OVENS'!G151 -> 84 | K17: =+'COKE OVENS'!H151 -> 84.900235 | L17: =+'COKE OVENS'!I151 -> 84 | M17: =+'COKE OVENS'!J151 -> 84.890244 | N17: =+'COKE OVENS'!K151 -> 84 | O17: =+'COKE OVENS'!L151 -> 84.840227 | P17: =+'COKE OVENS'!M151 -> 84 | ... BI17: =+'COKE OVENS'!BF151 -> 85.083955
D18: M10 | E18: % | F18: 7.9983422 | G18: 8 | H18: 8 | I18: =+'COKE OVENS'!F152 -> 7.8 | J18: =+'COKE OVENS'!G152 -> 8 | K18: =+'COKE OVENS'!H152 -> 7.8034118 | L18: =+'COKE OVENS'!I152 -> 8 | M18: =+'COKE OVENS'!J152 -> 7.8017271 | N18: =+'COKE OVENS'!K152 -> 8 | O18: =+'COKE OVENS'!L152 -> 7.8992045 | P18: =+'COKE OVENS'!M152 -> 8 | ... BI18: =+'COKE OVENS'!BF152 -> 7.8141195
D19: CSR | E19: % | F19: 64.448248 | G19: 63.5 | H19: 63.5 | I19: =+'COKE OVENS'!F153 -> 65.18 | J19: =+'COKE OVENS'!G153 -> 63.5 | K19: =+'COKE OVENS'!H153 -> 65.206154 | L19: =+'COKE OVENS'!I153 -> 63.5 | M19: =+'COKE OVENS'!J153 -> 65.19324 | N19: =+'COKE OVENS'!K153 -> 63.5 | O19: =+'COKE OVENS'!L153 -> 64.903571 | P19: =+'COKE OVENS'!M153 -> 63.5 | ... BI19: =+'COKE OVENS'!BF153 -> 65.168348
D20: CRI | E20: % | F20: 22.958248 | G20: 23 | H20: 23 | I20: =+'COKE OVENS'!F154 -> 22.86 | J20: =+'COKE OVENS'!G154 -> 23 | K20: =+'COKE OVENS'!H154 -> 22.902308 | L20: =+'COKE OVENS'!I154 -> 23 | M20: =+'COKE OVENS'!J154 -> 22.881417 | N20: =+'COKE OVENS'!K154 -> 23 | O20: =+'COKE OVENS'!L154 -> 23.267857 | P20: =+'COKE OVENS'!M154 -> 23 | ... BI20: =+'COKE OVENS'!BF154 -> 23.064174
D21: COB#11
D22: Soft Coal in Blend | E22: % | F22: 23.543644 | G22: 27 | H22: =+$G$22 -> 27 | I22: =+'COKE OVENS'!F166 -> 21.149593 | J22: =+$G$22 -> 27 | K22: =+'COKE OVENS'!H166 -> 21.548244 | L22: =+$G$22 -> 27 | M22: =+'COKE OVENS'!J166 -> 21.345813 | N22: =+$G$22 -> 27 | O22: =+'COKE OVENS'!L166 -> 21.966663 | P22: =+$G$22 -> 27 | Q22: =+'COKE OVENS'!N166 -> 21.549102 | R22: =+$G$22 -> 27 | S22: =+'COKE OVENS'!P166 -> 20.05 | T22: =+$G$15 -> 26 | U22: =+'COKE OVENS'!R166 -> 21.161755 | V22: =+$G$22 -> 27 | W22: =+'COKE OVENS'!T166 -> 19.52 | X22: =+$G$15 -> 26 | Y22: =+'COKE OVENS'!V166 -> 20.819536 | Z22: =+$G$22 -> 27 | AA22: =+'COKE OVENS'!X166 -> 19.96 | AB22: =+$G$22 -> 27 | AC22: =+'COKE OVENS'!Z166 -> 19.841094 | AD22: =+$G$22 -> 27 | AE22: =+'COKE OVENS'!AB166 -> 20.674162 | AF22: =+$G$22 -> 27 | AG22: =+'COKE OVENS'!AD166 -> 23.17 | AH22: =+$G$22 -> 27 | AI22: =+'COKE OVENS'!AF166 -> 21.051283 | AJ22: =+$G$22 -> 27 | AK22: =+'COKE OVENS'!AH166 -> 27.699994 | AL22: =+$G$22 -> 27 | AM22: =+'COKE OVENS'!AJ166 -> 21.879346 | AN22: =+$G$22 -> 27 | AO22: =+'COKE OVENS'!AL166 -> 27.33 | AP22: =+$G$22 -> 27 | AQ22: =+'COKE OVENS'!AN166 -> 26.024109 | AR22: =+$G$22 -> 27 | AS22: =+'COKE OVENS'!AP166 -> 22.503325 | AT22: =+$G$22 -> 27 | AU22: =+'COKE OVENS'!AR166 -> 26.640006 | AV22: =+$G$22 -> 27 | AW22: =+'COKE OVENS'!AT166 -> 22.927369 | AX22: =+$G$22 -> 27 | AY22: =+'COKE OVENS'!AV166 -> 24.999997 | AZ22: =+$G$22 -> 27 | BA22: =+'COKE OVENS'!AX166 -> 23.108978 | BB22: =+$G$22 -> 27 | BC22: =+'COKE OVENS'!AZ166 -> 25.000002 | BD22: =+'COKE OVENS'!BA166 -> 27.017528 | BE22: =+'COKE OVENS'!BB166 -> 25.558355 | BF22: =+'COKE OVENS'!BC166 -> 27.017527 | BG22: =+'COKE OVENS'!BD166 -> 25.793441 | BH22: =+'COKE OVENS'!BE166 -> 27.017526 | BI22: =+'COKE OVENS'!BF166 -> 23.270762
D23: Average Coking Time | E23: Hrs | G23: 18 | H23: =+'COKE OVENS'!E57 -> 17.938983 | I23: =+'COKE OVENS'!F57 -> 17.78 | J23: =+'COKE OVENS'!G57 -> 17.938983 | K23: =+'COKE OVENS'!H57 -> 19.07 | L23: =+'COKE OVENS'!I57 -> 17.938983 | M23: =+'COKE OVENS'!J57 -> 18.435455 | N23: =+'COKE OVENS'!K57 -> 17.938983 | O23: =+'COKE OVENS'!L57 -> 18.9 | ... BI23: =+'COKE OVENS'!BF57 -> 18.020524
D24: M40 | E24: % | F24: 88.59975 | G24: 87 | H24: 87 | I24: =+'COKE OVENS'!F176 -> 89.61 | J24: =+'COKE OVENS'!G176 -> 87 | K24: =+'COKE OVENS'!H176 -> 89.547246 | L24: =+'COKE OVENS'!I176 -> 87 | M24: =+'COKE OVENS'!J176 -> 89.57923 | N24: =+'COKE OVENS'!K176 -> 87 | O24: =+'COKE OVENS'!L176 -> 89.087619 | P24: =+'COKE OVENS'!M176 -> 87 | ... BI24: =+'COKE OVENS'!BF176 -> 89.451319
D25: M10 | E25: % | F25: 5.9480711 | G25: 6.4 | H25: 6.4 | I25: =+'COKE OVENS'!F177 -> 5.65 | J25: =+'COKE OVENS'!G177 -> 6.4 | K25: =+'COKE OVENS'!H177 -> 5.6581159 | L25: =+'COKE OVENS'!I177 -> 6.4 | M25: =+'COKE OVENS'!J177 -> 5.6539795 | N25: =+'COKE OVENS'!K177 -> 6.4 | O25: =+'COKE OVENS'!L177 -> 5.798254 | P25: =+'COKE OVENS'!M177 -> 6.4 | ... BI25: =+'COKE OVENS'!BF177 -> 5.7564367
D26: CSR | E26: % | F26: 66.654887 | G26: 66 | H26: 66 | I26: =+'COKE OVENS'!F178 -> 67.21 | J26: =+'COKE OVENS'!G178 -> 66 | K26: =+'COKE OVENS'!H178 -> 67.205714 | L26: =+'COKE OVENS'!I178 -> 66 | M26: =+'COKE OVENS'!J178 -> 67.207899 | N26: =+'COKE OVENS'!K178 -> 66 | O26: =+'COKE OVENS'!L178 -> 67.036154 | P26: =+'COKE OVENS'!M178 -> 66 | ... BI26: =+'COKE OVENS'!BF178 -> 67.300073
D27: CRI | E27: % | F27: 20.55944 | G27: 20.083333 | H27: 20 | I27: =+'COKE OVENS'!F179 -> 19.98 | J27: =+'COKE OVENS'!G179 -> 20 | K27: =+'COKE OVENS'!H179 -> 19.965 | L27: =+'COKE OVENS'!I179 -> 20 | M27: =+'COKE OVENS'!J179 -> 19.972645 | N27: =+'COKE OVENS'!K179 -> 20 | O27: =+'COKE OVENS'!L179 -> 20.391538 | P27: =+'COKE OVENS'!M179 -> 20 | ... BI27: =+'COKE OVENS'!BF179 -> 20.38682
C28: SINTER PLANT | D28: Sp. Productivity | E28: T/M²/Utlz Hr | F28: 1.330623 | G28: 1.360668 | H28: 1.3568075 | I28: =+SINTER!F75 -> 1.4015348 | J28: =+SINTER!G75 -> 1.2922386 | K28: =+SINTER!H75 -> 1.4077481 | L28: =+SINTER!I75 -> 1.327079 | M28: =+SINTER!J75 -> 1.4043105 | N28: =+SINTER!K75 -> 1.3179677 | O28: =+SINTER!L75 -> 1.3852801 | P28: =+SINTER!M75 -> 1.3242066 | ... BI28: =+SINTER!BF75 -> 1.3796182
D29: Iron Ore Fines | E29: Kg/T | F29: 783.62842 | G29: 781.57203 | H29: 781.57203 | I29: =+SINTER!F81 -> 778.13208 | J29: =+SINTER!G81 -> 781.57203 | K29: =+SINTER!H81 -> 771.76732 | L29: =+SINTER!I81 -> 781.57203 | M29: =+SINTER!J81 -> 775.28179 | N29: =+SINTER!K81 -> 781.57203 | O29: =+SINTER!L81 -> 781.63519 | P29: =+SINTER!M81 -> 781.57203 | ... BI29: =+SINTER!BF81 -> 782.4729
D30: Limestone | E30: Kg/T | F30: 102.61678 | G30: 97 | H30: 97 | I30: =+SINTER!F82 -> 102.47026 | J30: =+SINTER!G82 -> 97 | K30: =+SINTER!H82 -> 102.26339 | L30: =+SINTER!I82 -> 97 | M30: =+SINTER!J82 -> 102.37762 | N30: =+SINTER!K82 -> 97 | O30: =+SINTER!L82 -> 62.821718 | P30: =+SINTER!M82 -> 97 | ... BI30: =+SINTER!BF82 -> 83.686621
D31: Dolomite | E31: Kg/T | F31: 101.93133 | G31: 89.57152 | H31: 89.57152 | I31: =+SINTER!F83 -> 84.186688 | J31: =+SINTER!G83 -> 89.57152 | K31: =+SINTER!H83 -> 87.18161 | L31: =+SINTER!I83 -> 89.57152 | M31: =+SINTER!J83 -> 85.527885 | N31: =+SINTER!K83 -> 89.57152 | O31: =+SINTER!L83 -> 112.83233 | P31: =+SINTER!M83 -> 89.57152 | ... BI31: =+SINTER!BF83 -> 94.573878
D32: Coke Breeze | E32: Kg/T | F32: 74.095728 | G32: 75 | H32: 75 | I32: =+SINTER!F93 -> 75.979384 | J32: =+SINTER!G93 -> 75 | K32: =+SINTER!H93 -> 76.914189 | L32: =+SINTER!I93 -> 75 | M32: =+SINTER!J93 -> 76.398012 | N32: =+SINTER!K93 -> 75 | O32: =+SINTER!L93 -> 65.798648 | P32: =+SINTER!M93 -> 75 | ... BI32: =+SINTER!BF93 -> 73.49029
D33: Mill Scale | E33: Kg/T | F33: 6.4308813 | G33: =+SINTER!D87 -> 6 | H33: =+SINTER!E87 -> 6 | I33: =+SINTER!F87 -> 7.6010003 | J33: =+SINTER!G87 -> 6 | K33: =+SINTER!H87 -> 6.742531 | L33: =+SINTER!I87 -> 6 | M33: =+SINTER!J87 -> 7.2165573 | N33: =+SINTER!K87 -> 6 | ... BI33: =+SINTER!BF87 -> 8.4134223
D34: SMS Scale | E34: Kg/T | G34: 0 | H34: =+SINTER!E88 -> 0 | I34: =+SINTER!F88 -> 3.4107407 | J34: =+SINTER!G88 -> 0 | K34: =+SINTER!H88 -> 1.7980083 | L34: =+SINTER!I88 -> 6 | M34: =+SINTER!J88 -> 2.6885208 | N34: =+SINTER!K88 -> 0 | O34: =+SINTER!L88 -> 6.3045794 | ... BI34: =+SINTER!BF88 -> 2.4695674
D35: BOF Slag | E35: Kg/T | F35: 12.079401 | G35: =+SINTER!D89 -> 29.655436 | H35: =+SINTER!E89 -> 29.655436 | I35: =+SINTER!F89 -> 22.024104 | J35: =+SINTER!G89 -> 29.655436 | K35: =+SINTER!H89 -> 22.974118 | L35: =+SINTER!I89 -> 29.655436 | M35: =+SINTER!J89 -> 22.449543 | N35: =+SINTER!K89 -> 29.655436 | ... BI35: =+SINTER!BF89 -> 10.157453
D36: Sp. Power | E36: KwH/T | F36: 32.711238 | G36: 29.858528 | H36: 29.858528 | I36: =+SINTER!F77 -> 32.501679 | J36: =+SINTER!G77 -> 29.858528 | K36: =+SINTER!H77 -> 33.025182 | L36: =+SINTER!I77 -> 29.858528 | M36: =+SINTER!J77 -> 32.736116 | N36: =+SINTER!K77 -> 29.858528 | O36: =+SINTER!L77 -> 32.464031 | P36: =+SINTER!M77 -> 29.858528 | ... BI36: =+SINTER!BF77 -> 31.618306
C37: BLAST FURNACE | D37: BF Coke Rate | E37: Kg/ THM | F37: 400.04041 | G37: 380.42 | H37: 380 | I37: =+'Maj Techno Summ'!F10 -> 394.49 | J37: =+'Maj Techno Summ'!G10 -> 382 | K37: =+'Maj Techno Summ'!H10 -> 404.39415 | L37: =+'Maj Techno Summ'!I10 -> 380.90993 | M37: =+'Maj Techno Summ'!J10 -> 398.90449 | N37: =+'Maj Techno Summ'!K10 -> 400 | O37: =+'Maj Techno Summ'!L10 -> 415.90322 | P37: =+'Maj Techno Summ'!M10 -> 386.96215 | ... BI37: =+'Maj Techno Summ'!BF10 -> 390.51224
D38: Nut Coke rate | E38: Kg/ THM | F38: 36.610035 | G38: 32.204286 | H38: 30 | I38: =+'Maj Techno Summ'!F11 -> 37.49 | J38: =+'Maj Techno Summ'!G11 -> 33 | K38: =+'Maj Techno Summ'!H11 -> 40.719195 | L38: =+'Maj Techno Summ'!I11 -> 31.364896 | M38: =+'Maj Techno Summ'!J11 -> 38.929322 | N38: =+'Maj Techno Summ'!K11 -> 40 | O38: =+'Maj Techno Summ'!L11 -> 42.650208 | P38: =+'Maj Techno Summ'!M11 -> 34.102524 | ... BI38: =+'Maj Techno Summ'!BF11 -> 47.260949
D39: CDI rate | E39: Kg/ THM | F39: 122.58808 | G39: 139.6475 | H39: 140 | I39: =+'Maj Techno Summ'!F12 -> 129.13437 | J39: =+'Maj Techno Summ'!G12 -> 135 | K39: =+'Maj Techno Summ'!H12 -> 124.4423 | L39: =+'Maj Techno Summ'!I12 -> 137.72517 | M39: =+'Maj Techno Summ'!J12 -> 127.04302 | N39: =+'Maj Techno Summ'!K12 -> 125 | O39: =+'Maj Techno Summ'!L12 -> 111.23054 | P39: =+'Maj Techno Summ'!M12 -> 133.69085 | ... BI39: =+'Maj Techno Summ'!BF12 -> 125.94309
D40: Total Fuel | E40: Kg/ THM | F40: 559.23852 | G40: 552.27179 | H40: 550 | I40: =+'Maj Techno Summ'!F13 -> 561.11437 | J40: =+'Maj Techno Summ'!G13 -> 550 | K40: =+'Maj Techno Summ'!H13 -> 569.55565 | L40: =+'Maj Techno Summ'!I13 -> 550 | M40: =+'Maj Techno Summ'!J13 -> 564.87683 | N40: =+'Maj Techno Summ'!K13 -> 565 | O40: =+'Maj Techno Summ'!L13 -> 569.78397 | P40: =+'Maj Techno Summ'!M13 -> 554.75552 | ... BI40: =+'Maj Techno Summ'!BF13 -> 563.71628
D41: BF PRODUCTIVITY | E41: T/M³/Day | F41: 2.0862545 | G41: 2.2723639 | H41: =+'Maj Techno Summ'!E14 -> 2.2917294 | I41: =+'Maj Techno Summ'!F14 -> 2.2197239 | J41: =+'Maj Techno Summ'!G14 -> 2.2190932 | K41: =+'Maj Techno Summ'!H14 -> 2.0635913 | L41: =+'Maj Techno Summ'!I14 -> 2.2581015 | M41: =+'Maj Techno Summ'!J14 -> 2.147309 | N41: =+'Maj Techno Summ'!K14 -> 2.0964361 | O41: =+'Maj Techno Summ'!L14 -> 2.0914204 | ... BI41: =+'Maj Techno Summ'!BF14 -> 2.1810142
D42: Hot Blast Temp | E42: ⁰C | F42: 1139.2637 | G42: 1150 | H42: =+'B-FCE'!E75 -> 1150 | I42: =+'B-FCE'!F75 -> 1144.7037 | J42: =+'B-FCE'!G75 -> 1150 | K42: =+'B-FCE'!H75 -> 1125.6648 | L42: =+'B-FCE'!I75 -> 1150 | M42: =+'B-FCE'!J75 -> 1135.0282 | N42: =+'B-FCE'!K75 -> 1150 | O42: =+'B-FCE'!L75 -> 1140.1154 | ... BI42: =+'B-FCE'!BF75 -> 1154.6169
D43: Avg Si | E43: % | F43: 0.72420555 | G43: =+'B-FCE'!D77 -> 0.8 | H43: =+'B-FCE'!E77 -> 0.8 | I43: =+'B-FCE'!F77 -> 0.62562624 | J43: =+'B-FCE'!G77 -> 0.8 | K43: =+'B-FCE'!H77 -> 0.68950088 | L43: =+'B-FCE'!I77 -> <0.8 | M43: =+'B-FCE'!J77 -> 0.65409653 | N43: =+'B-FCE'!K77 -> 0.8 | ... BI43: =+'B-FCE'!BF77 -> 0.70146862
D44: Avg S | E44: % | F44: 0.038244802 | G44: =+'B-FCE'!D78 -> 0.05 | H44: =+'B-FCE'!E78 -> 0.05 | I44: =+'B-FCE'!F78 -> 0.035435895 | J44: =+'B-FCE'!G78 -> 0.05 | K44: =+'B-FCE'!H78 -> 0.036956734 | L44: =+'B-FCE'!I78 -> <0.05 | M44: =+'B-FCE'!J78 -> 0.036113766 | N44: =+'B-FCE'!K78 -> 0.05 | ... BI44: =+'B-FCE'!BF78 -> 0.040082007
D45: Slag Rate | E45: Kg/THM | F45: 413.76313 | G45: 387 | H45: =+'B-FCE'!E76 -> 387 | I45: =+'B-FCE'!F76 -> 455.89766 | J45: =+'B-FCE'!G76 -> 387 | K45: =+'B-FCE'!H76 -> 487.61155 | L45: =+'B-FCE'!I76 -> 387 | M45: =+'B-FCE'!J76 -> 470.03322 | N45: =+'B-FCE'!K76 -> 387 | O45: =+'B-FCE'!L76 -> 400.09125 | ... BI45: =+'B-FCE'!BF76 -> 447.89213
