Workbook
Name _1: #REF!
Name _1: #REF!
Name _1: #REF!
Name _1: #REF!
Name _1: #REF!
Name _1: #REF!
Name _1: #REF!
Name _1: #REF!
Name _2: #REF!
Name _2: #REF!
Name _2: #REF!
Name _2: #REF!
Name _2: #REF!
Name _2: #REF!
Name _2: #REF!
Name _2: #REF!
Name _3: #REF!
Name _3: #REF!
Name _3: #REF!
Name _3: #REF!
Name _3: #REF!
Name _3: #REF!
Name _3: #REF!
Name _4: #REF!
Name _4: #REF!
Name a: #REF!
Name a: #REF!
Name a: #REF!
Name a: #REF!
Name AA: #REF!
Name AA: #REF!
Name AA: #REF!
Name AB: #REF!
Name AB: #REF!
Name AB: #REF!
Name AC: #REF!
Name AC: #REF!
Name AD: #REF!
Name AD: #REF!
Name AE: #REF!
Name AE: #REF!
Name AF: #REF!
Name AF: #REF!
Name AG: #REF!
Name AG: #REF!
Name AH: #REF!
Name AH: #REF!
Name AI: #REF!
Name AI: #REF!
Name AK: #REF!
Name AK: #REF!
Name AL: #REF!
Name AL: #REF!
Name AM: #REF!
Name AM: #REF!
Name AN: #REF!
Name AN: #REF!
Name AS: #REF!
Name AS: #REF!
Name CL: #REF!

Sheet Maj Production Summ
B1: MAJOR PRODUCTION SUMMARY | D1: 340 | E1: 26 | F1: =F2-'B-FCE'!F3 -> 29.538194 | G1: 30 | H1: =H2-'B-FCE'!H3 -> 29.791667 | I1: =E1+G1 -> 56 | J1: =F1+H1 -> 59.329861 | K1: 29 | L1: =L2-'B-FCE'!L3 -> 29.61125 | M1: =+E1+G1+K1 -> 85 | N1: =+F1+H1+L1 -> 88.941111 | O1: 30 | P1: =P2-'B-FCE'!P3 -> 31 | Q1: =+M1+O1 -> 115 | R1: =+N1+P1 -> 119.94111 | S1: 30 | T1: =T2-'B-FCE'!T3 -> 30.024306 | U1: =+Q1+S1 -> 145 | V1: =+R1+T1 -> 149.96542 | W1: 17.016867 | X1: =X2-'B-FCE'!X3 -> 29.67375 | Y1: =+O1+S1+W1 -> 77.016867 | Z1: =+P1+T1+X1 -> 90.698056 | AA1: =+U1+W1 -> 162.01687 | AB1: =+V1+X1 -> 179.63917 | AC1: 30 | AD1: =AD2-'B-FCE'!AD3-2 -> 24.930556 | AE1: =AA1+AC1 -> 192.01687 | AF1: =AB1+AD1 -> 204.56972 | AG1: 29 | AH1: =AH2-'B-FCE'!AH3 -> 29.1075 | AI1: =AE1+AG1 -> 221.01687 | AJ1: =AF1+AH1 -> 233.67722 | AK1: 30 | AL1: =31-'B-FCE'!AL3 -> 30.697917 | AM1: =+AC1+AG1+AK1 -> 89 | AN1: =+AD1+AH1+AL1 -> 84.735972 | AO1: =AI1+AK1 -> 251.01687 | AP1: =AJ1+AL1 -> 264.37514 | AQ1: 30 | AR1: =31-'B-FCE'!AR3 -> 30.413194 | AS1: =AO1+AQ1 -> 281.01687 | AT1: =AP1+AR1 -> 294.78833 | AU1: 27 | AV1: =28-'B-FCE'!AV3 -> 27.57625 | AW1: =AS1+AU1 -> 308.01687 | AX1: =AT1+AV1 -> 322.36458 | AY1: 30 | AZ1: =31-'B-FCE'!AZ3 -> 29.972222 | BA1: =+AQ1+AU1+AY1 -> 87 | BB1: =+AR1+AV1+AZ1 -> 87.961667 | BC1: =+AM1+BA1 -> 176 | BD1: =+AN1+BB1 -> 172.69764 | BE1: =AW1+AY1 -> 338.01687 | BF1: =AX1+AZ1 -> 352.33681
A2: 1000 | D2: 365 | E2: 30 | F2: 30 | G2: 31 | H2: 31 | I2: =+E2+G2 -> 61 | J2: =+F2+H2 -> 61 | K2: 30 | L2: 30 | M2: =+I2+K2 -> 91 | N2: =+J2+L2 -> 91 | O2: 31 | P2: 31 | Q2: =+M2+O2 -> 122 | R2: =+N2+P2 -> 122 | S2: 31 | T2: 31 | U2: =+Q2+S2 -> 153 | V2: =+R2+T2 -> 153 | W2: 30 | X2: 30 | Y2: =+O2+S2+W2 -> 92 | Z2: =+P2+T2+X2 -> 92 | AA2: =+U2+W2 -> 183 | AB2: =+V2+X2 -> 183 | AC2: 31 | AD2: 31 | AE2: =AA2+AC2 -> 214 | AF2: =AB2+AD2 -> 214 | AG2: 30 | AH2: 30 | AI2: =AE2+AG2 -> 244 | AJ2: =AF2+AH2 -> 244 | AK2: 31 | AL2: 31 | AM2: =+AC2+AG2+AK2 -> 92 | AN2: =+AD2+AH2+AL2 -> 92 | AO2: =AI2+AK2 -> 275 | AP2: =AJ2+AL2 -> 275 | AQ2: 31 | AR2: 31 | AS2: =AO2+AQ2 -> 306 | AT2: =AP2+AR2 -> 306 | AU2: 28 | AV2: 28 | AW2: =AS2+AU2 -> 334 | AX2: =AT2+AV2 -> 334 | AY2: 31 | AZ2: 31 | BA2: =+AQ2+AU2+AY2 -> 90 | BB2: =+AR2+AV2+AZ2 -> 90 | BC2: =+AM2+BA2 -> 182 | BD2: =+AN2+BB2 -> 182 | BE2: =AW2+AY2 -> 365 | BF2: =AX2+AZ2 -> 365 | BN2: 365 | BO2: 365 | BP2: 366 | BQ2: 366
A3: 1000 | B3: ITEM | C3: Unit | D3: 2026-27 ABP | E3: Apr'26 | G3: May'25 | I3: 2M | K3: Jun'25 | M3: QTR-1 | O3: Jul'25 | Q3: 4M | S3: Aug'25 | U3: 5M | W3: Sep'25 | Y3: QTR 2 | AA3: H1 | AC3: Oct'25 | AE3: 7M | AG3: Nov'25 | AI3: 8M | AK3: Dec'25 | AM3: QTR 3 | AO3: 9M | AQ3: Jan'26 | AS3: 10M | AU3: Feb'26 | AW3: 11M | AY3: Mar'26 | BA3: QTR 4 | BC3: H2 | BE3: 2025-26 | BG3: 2024-25 | BI3: 2023-24 | BK3: 2022-23 | BL3: 2021-22 | BN3: 2020-21 | BP3: 2019-20
E4: ABP | F4: ACT | G4: ABP | H4: ACT | I4: ABP | J4: ACT | K4: ABP | L4: ACT | M4: ABP | N4: ACT | O4: ABP | P4: ACT | Q4: ABP | R4: ACT | S4: ABP | T4: ACT | U4: ABP | V4: ACT | W4: ABP | X4: ACT | Y4: ABP | Z4: ACT | AA4: ABP | AB4: ACT | AC4: ABP | AD4: ACT | AE4: ABP | AF4: ACT | AG4: ABP | AH4: ACT | AI4: ABP | AJ4: ACT | AK4: ABP | AL4: ACT | AM4: ABP | AN4: ACT | AO4: ABP | AP4: ACT | AQ4: ABP | AR4: ACT | AS4: ABP | AT4: ACT | AU4: ABP | AV4: ACT | AW4: ABP | AX4: ACT | AY4: ABP | AZ4: ACT | BA4: ABP | BB4: ACT | BC4: ABP | BD4: ACT | BE4: ABP | BF4: ACT | BG4: ABP | BH4: ACT | BI4: ABP | BJ4: ACT | BK4: ACT | BL4: ABP | BM4: ACT | BN4: ABP | BO4: ACT | BP4: ABP | BQ4: ACT
B5: COKE OVENS PUSHING
B6: (COB#10) | C6: Nos/ day | D6: 96.509589 | E6: 98 | F6: =+F9/F2 -> 98 | G6: 98 | H6: =+H9/H2 -> 97.612903 | I6: =+((E6*$E$2)+(G6*$G$2))/$I$2 -> 98 | J6: =+((F6*$F$2)+(H6*$H$2))/$J$2 -> 97.803279 | K6: 94 | L6: =+L9/L2 -> 96.066667 | M6: =+((E6*$E$2)+(G6*$G$2)+(K6*$K$2))/$M$2 -> 96.681319 | N6: =+((F6*$F$2)+(H6*$H$2)+(L6*$L$2))/$N$2 -> 97.230769 | O6: 94 | P6: =+P9/P2 -> 95.419355 | Q6: =+((M6*M$2)+(O6*O$2))/Q$2 -> 96 | R6: =+((N6*N$2)+(P6*P$2))/R$2 -> 96.770492 | S6: 94 | T6: =+T9/T2 -> 98 | U6: =+((Q6*Q$2)+(S6*S$2))/U$2 -> 95.594771 | V6: =+((R6*R$2)+(T6*T$2))/V$2 -> 97.019608 | W6: 92.1 | X6: =+X9/X2 -> 98 | Y6: =+((O$6*O$2)+(S$6*S$2)+(W$6*W$2))/Y$2 -> 93.380435 | Z6: =+((P$6*P$2)+(T$6*T$2)+(X$6*X$2))/Z$2 -> 97.130435 | AA6: =+((M6*M$2)+(Y6*Y$2))/AA$2 -> 95.021858 | AB6: =+((N6*N$2)+(Z6*Z$2))/AB$2 -> 97.180328 | AC6: 94 | AD6: =+AD9/AD2 -> 96.548387 | AE6: =+((AA6*$AA$2)+(AC6*$AC$2))/$AE$2 -> 94.873832 | AF6: =+((AB6*$AB$2)+(AD6*$AD$2))/$AF$2 -> 97.088785 | AG6: 94 | AH6: =+AH9/AH2 -> 94.233333 | AI6: =+((AE6*$AE$2)+(AG6*$AG$2))/$AI$2 -> 94.766393 | AJ6: =+((AF6*$AF$2)+(AH6*$AH$2))/$AJ$2 -> 96.737705 | AK6: 94 | AL6: =+AL9/AL2 -> 94.096774 | AM6: =+((AC$6*AC$2)+(AG$6*AG$2)+(AK$6*AK$2))/AM$2 -> 94 | AN6: =+((AD$6*AD$2)+(AH$6*AH$2)+(AL$6*AL$2))/AN$2 -> 94.967391 | AO6: =+((AK6*$AK$2)+(AI6*$AI$2))/$AO$2 -> 94.68 | AP6: =+((AL6*$AL$2)+(AJ6*$AJ$2))/$AP$2 -> 96.44 | AQ6: 94 | AR6: =+AR9/AR2 -> 94.83871 | AS6: =+((AO6*$AO$2)+(AQ6*$AQ$2))/$AS$2 -> 94.611111 | AT6: =+((AP6*$AP$2)+(AR6*$AR$2))/$AT$2 -> 96.277778 | AU6: 94 | AV6: =+AV9/AV2 -> 94.428571 | AW6: =+((AS6*$AS$2)+(AU6*$AU$2))/$AW$2 -> 94.55988 | AX6: =+((AT6*$AT$2)+(AV6*$AV$2))/$AX$2 -> 96.122754 | AY6: 94 | AZ6: =+AZ9/AZ2 -> 98 | BA6: =+((AQ$6*AQ$2)+(AU$6*AU$2)+(AY$6*AY$2))/BA$2 -> 94 | BB6: =+((AR$6*AR$2)+(AV$6*AV$2)+(AZ$6*AZ$2))/BB$2 -> 95.8 | BC6: =+((AM6*AM$2)+(BA6*BA$2))/BC$2 -> 94 | BD6: =+((AN6*AN$2)+(BB6*BB$2))/BD$2 -> 95.379121 | BE6: =+((AW6*$AW$2)+(AY6*$AY$2))/$BE$2 -> 94.512329 | BF6: =+((AZ6*$AZ$2)+(AX6*$AX$2))/$BF$2 -> 96.282192 | BG6: 96.420548 | BH6: 97.709589 | BI6: 99 | BJ6: 98.976067 | BK6: 98.783562 | BL6: 99 | BM6: 97.824658 | BN6: 95.547945 | BO6: 95.342466 | BP6: 97 | BQ6: 97.10959
B7: (COB#11) | C7: Nos/ day | D7: 97.717616 | E7: 96.6 | F7: =+F10/F2 -> 98.433333 | G7: 98 | H7: =+H10/H2 -> 97.483871 | I7: =+((E7*$E$2)+(G7*$G$2))/$I$2 -> 97.311475 | J7: =+((F7*$F$2)+(H7*$H$2))/$J$2 -> 97.95082 | K7: 98 | L7: =+L10/L2 -> 98.466667 | M7: =+((E7*$E$2)+(G7*$G$2)+(K7*$K$2))/$M$2 -> 97.538462 | N7: =+((F7*$F$2)+(H7*$H$2)+(L7*$L$2))/$N$2 -> 98.120879 | O7: 98 | P7: =+P10/P2 -> 99 | Q7: =+((M7*M$2)+(O7*O$2))/Q$2 -> 97.655738 | R7: =+((N7*N$2)+(P7*P$2))/R$2 -> 98.344262 | S7: 98 | T7: =+T10/T2 -> 98.516129 | U7: =+((Q7*Q$2)+(S7*S$2))/U$2 -> 97.72549 | V7: =+((R7*R$2)+(T7*T$2))/V$2 -> 98.379085 | W7: 93.5 | X7: =+X10/X2 -> 98.766667 | Y7: =((O7*O2)+(S7*S2)+(W7*W2))/Y2 -> 96.532609 | Z7: =+((P$7*P$2)+(T$7*T$2)+(X$7*X$2))/Z$2 -> 98.76087 | AA7: =+((M7*M$2)+(Y7*Y$2))/AA$2 -> 97.032787 | AB7: =+((N7*N$2)+(Z7*Z$2))/AB$2 -> 98.442623 | AC7: 98 | AD7: =+AD10/AD2 -> 97.193548 | AE7: =+((AA7*$AA$2)+(AC7*$AC$2))/$AE$2 -> 97.172897 | AF7: =+((AB7*$AB$2)+(AD7*$AD$2))/$AF$2 -> 98.261682 | AG7: 98 | AH7: =+AH10/AH2 -> 98.666667 | AI7: =+((AE7*$AE$2)+(AG7*$AG$2))/$AI$2 -> 97.27459 | AJ7: =+((AF7*$AF$2)+(AH7*$AH$2))/$AJ$2 -> 98.311475 | AK7: 98 | AL7: =+AL10/AL2 -> 98.741935 | AM7: =+((AC$7*AC$2)+(AG$7*AG$2)+(AK$7*AK$2))/AM$2 -> 98 | AN7: =+((AD$7*AD$2)+(AH$7*AH$2)+(AL$7*AL$2))/AN$2 -> 98.195652 | AO7: =+((AK7*$AK$2)+(AI7*$AI$2))/$AO$2 -> 97.356364 | AP7: =+((AL7*$AL$2)+(AJ7*$AJ$2))/$AP$2 -> 98.36 | AQ7: 98 | AR7: =+AR10/AR2 -> 97.870968 | AS7: =+((AO7*$AO$2)+(AQ7*$AQ$2))/$AS$2 -> 97.421569 | AT7: =+((AP7*$AP$2)+(AR7*$AR$2))/$AT$2 -> 98.310458 | AU7: 98 | AV7: =+AV10/AV2 -> 98.035714 | AW7: =+((AS7*$AS$2)+(AU7*$AU$2))/$AW$2 -> 97.47006 | AX7: =+((AT7*$AT$2)+(AV7*$AV$2))/$AX$2 -> 98.287425 | AY7: 98 | AZ7: =+AZ10/AZ2 -> 98.677419 | BA7: =+((AQ$7*AQ$2)+(AU$7*AU$2)+(AY$7*AY$2))/BA$2 -> 98 | BB7: =+((AR$7*AR$2)+(AV$7*AV$2)+(AZ$7*AZ$2))/BB$2 -> 98.2 | BC7: =+((AM7*AM$2)+(BA7*BA$2))/BC$2 -> 98 | BD7: =+((AN7*AN$2)+(BB7*BB$2))/BD$2 -> 98.197802 | BE7: =+((AW7*$AW$2)+(AY7*$AY$2))/$BE$2 -> 97.515068 | BF7: =+((AZ7*$AZ$2)+(AX7*$AX$2))/$BF$2 -> 98.320548 | BG7: 98.167671 | BH7: 97.991781 | BI7: 98.000061 | BJ7: 96.670251 | BK7: 92.210959 | BL7: 99 | BM7: 96.816438 | BN7: 94.2 | BO7: 90.778082 | BP7: 97 | BQ7: 95.710246
B8: Overall Equiv. Ovens Pushed/ Day | C8: Nos/ day | D8: =+D6+(D7*(31.55/17.2)) -> 275.75324 | E8: =+E6+(E7*(31.55/17.2)) -> 275.1936 | F8: =+F6+(F7*(31.55/17.2)) -> 278.55649 | G8: =+G6+(G7*(31.55/17.2)) -> 277.76163 | H8: =+H6+(H7*(31.55/17.2)) -> 276.42779 | I8: =+I6+(I7*(31.55/17.2)) -> 276.49867 | J8: =+J6+(J7*(31.55/17.2)) -> 277.4747 | K8: =+K6+(K7*(31.55/17.2)) -> 273.76163 | ... X8: =+X6+(X7*(31.55/17.2)) -> 279.16793 | Y8: =Y6+(Y7*31.55/17.2) -> 270.45042 | Z8: =Z6+(Z7*31.55/17.2) -> 278.28773 | AA8: =AA6+(AA7*31.55/17.2) -> 273.00932 | AB8: =AB6+(AB7*31.55/17.2) -> 277.75386 | AC8: =+AC6+(AC7*(31.55/17.2)) -> 273.76163 | AD8: =+AD6+(AD7*(31.55/17.2)) -> 274.83074 | AE8: =+AE6+(AE7*(31.55/17.2)) -> 273.1183 | AF8: =+AF6+(AF7*(31.55/17.2)) -> 277.33042 | AG8: =+AG6+(AG7*(31.55/17.2)) -> 273.76163 | AH8: =+AH6+(AH7*(31.55/17.2)) -> 275.21783 | AI8: =+AI6+(AI7*(31.55/17.2)) -> 273.1974 | AJ8: =+AJ6+(AJ7*(31.55/17.2)) -> 277.07067 | ... AL8: =+AL6+(AL7*(31.55/17.2)) -> 275.21934 | AM8: =AM6+(AM7*31.55/17.2) -> 273.76163 | AN8: =AN6+(AN7*31.55/17.2) -> 275.0879 | AO8: =+AO6+(AO7*(31.55/17.2)) -> 273.261 | AP8: =+AP6+(AP7*(31.55/17.2)) -> 276.86198 | AQ8: =+AQ6+(AQ7*(31.55/17.2)) -> 273.76163 | AR8: =+AR6+(AR7*(31.55/17.2)) -> 274.36365 | AS8: =+AS6+(AS7*(31.55/17.2)) -> 273.31172 | AT8: =+AT6+(AT7*(31.55/17.2)) -> 276.60888 | AU8: =+AU6+(AU7*(31.55/17.2)) -> 273.76163 | AV8: =+AV6+(AV7*(31.55/17.2)) -> 274.25571 | ... AZ8: =+AZ6+(AZ7*(31.55/17.2)) -> 279.00422 | BA8: =BA6+(BA7*31.55/17.2) -> 273.76163 | BB8: =BB6+(BB7*31.55/17.2) -> 275.92849 | BC8: =BC6+(BC7*31.55/17.2) -> 273.76163 | BD8: =BD6+(BD7*31.55/17.2) -> 275.50358 | BE8: =+BE6+(BE7*(31.55/17.2)) -> 273.38445 | BF8: =+BF6+(BF7*(31.55/17.2)) -> 276.6318 | BG8: 276.48974 | BH8: 277.45614 | BI8: 278.76174 | BJ8: 276.29853 | BK8: 267.92634 | BL8: 280.59593 | BM8: 275.41528 | BN8: 268.33922 | BO8: 261.85691 | BP8: 274.92733 | BQ8: 272.67112
B9: (COB#10) | C9: Nos | D9: =+D6*D2 -> 35226 | E9: =+E6*E2 -> 2940 | F9: 2940 | G9: =+G6*G2 -> 3038 | H9: 3026 | I9: =+I6*I2 -> 5978 | J9: =+F9+H9 -> 5966 | K9: =+K6*K2 -> 2820 | L9: 2882 | M9: =+E9+G9+K9 -> 8798 | N9: =+F9+H9+L9 -> 8848 | O9: =+O6*O2 -> 2914 | P9: 2958 | Q9: =+M9+O9 -> 11712 | R9: =+N9+P9 -> 11806 | S9: =+S6*S2 -> 2914 | T9: 3038 | U9: =+Q9+S9 -> 14626 | V9: =+R9+T9 -> 14844 | W9: =+W6*W2 -> 2763 | X9: 2940 | Y9: =+O9+S9+W9 -> 8591 | Z9: =+P9+T9+X9 -> 8936 | AA9: =M9+Y9 -> 17389 | AB9: =+N9+Z9 -> 17784 | AC9: =+AC6*AC2 -> 2914 | AD9: 2993 | AE9: =+AE6*AE2 -> 20303 | AF9: =+AB9+AD9 -> 20777 | AG9: =+AG6*AG2 -> 2820 | AH9: 2827 | AI9: =+AI6*AI2 -> 23123 | AJ9: =+AF9+AH9 -> 23604 | AK9: =+AK6*AK2 -> 2914 | AL9: 2917 | AM9: =+AC9+AG9+AK9 -> 8648 | AN9: =+AD9+AH9+AL9 -> 8737 | AO9: =AI9+AK9 -> 26037 | AP9: =AJ9+AL9 -> 26521 | AQ9: =+AQ6*AQ2 -> 2914 | AR9: 2940 | AS9: =+AS6*AS2 -> 28951 | AT9: =+AP9+AR9 -> 29461 | AU9: =+AU6*AU2 -> 2632 | AV9: 2644 | AW9: =+AW6*AW2 -> 31583 | AX9: =+AT9+AV9 -> 32105 | AY9: =+AY6*AY2 -> 2914 | AZ9: 3038 | BA9: =+AQ9+AU9+AY9 -> 8460 | BB9: =+AR9+AV9+AZ9 -> 8622 | BC9: =AM9+BA9 -> 17108 | BD9: =AN9+BB9 -> 17359 | BE9: =AW9+AY9 -> 34497 | BF9: =AX9+AZ9 -> 35143 | BG9: 35193.5 | BH9: 35664 | BI9: 36234 | BJ9: 36225 | BK9: 36056 | BL9: 36135 | BM9: 35706 | BN9: 34875 | BO9: 34800 | BP9: 35502 | BQ9: 35543
B10: (COB#11) | C10: Nos | D10: =+D7*D2 -> 35666.93 | E10: =+E7*E2 -> 2898 | F10: 2953 | G10: =+G7*G2 -> 3038 | H10: 3022 | I10: =+I7*I2 -> 5936 | J10: =+F10+H10 -> 5975 | K10: =+K7*K2 -> 2940 | L10: 2954 | M10: =+E10+G10+K10 -> 8876 | N10: =+F10+H10+L10 -> 8929 | O10: =+O7*O2 -> 3038 | P10: 3069 | Q10: =+M10+O10 -> 11914 | R10: =+N10+P10 -> 11998 | S10: =+S7*S2 -> 3038 | T10: 3054 | U10: =+Q10+S10 -> 14952 | V10: =+R10+T10 -> 15052 | W10: =+W7*W2 -> 2805 | X10: 2963 | Y10: =+O10+S10+W10 -> 8881 | Z10: =+P10+T10+X10 -> 9086 | AA10: =+M10+Y10 -> 17757 | AB10: =+N10+Z10 -> 18015 | AC10: =+AC7*AC2 -> 3038 | AD10: 3013 | AE10: =+AE7*AE2 -> 20795 | AF10: =+AB10+AD10 -> 21028 | AG10: =+AG7*AG2 -> 2940 | AH10: 2960 | AI10: =+AI7*AI2 -> 23735 | AJ10: =+AF10+AH10 -> 23988 | AK10: =+AK7*AK2 -> 3038 | AL10: 3061 | AM10: =+AC10+AG10+AK10 -> 9016 | AN10: =+AD10+AH10+AL10 -> 9034 | AO10: =AI10+AK10 -> 26773 | AP10: =AJ10+AL10 -> 27049 | AQ10: =+AQ7*AQ2 -> 3038 | AR10: 3034 | AS10: =+AS7*AS2 -> 29811 | AT10: =+AP10+AR10 -> 30083 | AU10: =+AU7*AU2 -> 2744 | AV10: 2745 | AW10: =+AW7*AW2 -> 32555 | AX10: =+AT10+AV10 -> 32828 | AY10: =+AY7*AY2 -> 3038 | AZ10: 3059 | BA10: =+AQ10+AU10+AY10 -> 8820 | BB10: =+AR10+AV10+AZ10 -> 8838 | BC10: =AM10+BA10 -> 17836 | BD10: =AN10+BB10 -> 17872 | BE10: =AW10+AY10 -> 35593 | BF10: =AX10+AZ10 -> 35887 | BG10: 35831.2 | BH10: 35767 | BI10: 35868.022 | BJ10: 35382 | BK10: 33657 | BL10: 36135 | BM10: 35338 | BN10: 34383 | BO10: 33134 | BP10: 35502 | BQ10: 35030
B11: Overall Equiv. Ovens Pushed | C11: Nos | D11: =+D9+(D10*(31.55/17.2)) -> 100649.93 | E11: =+E9+(E10*(31.55/17.2)) -> 8255.8081 | F11: =+F9+(F10*(31.55/17.2)) -> 8356.6948 | G11: =+G9+(G10*(31.55/17.2)) -> 8610.6105 | H11: =+H9+(H10*(31.55/17.2)) -> 8569.2616 | I11: =+I9+(I10*(31.55/17.2)) -> 16866.419 | J11: =+J9+(J10*(31.55/17.2)) -> 16925.956 | K11: =+K9+(K10*(31.55/17.2)) -> 8212.8488 | ... X11: =+X9+(X10*(31.55/17.2)) -> 8375.0378 | Y11: =Y9+(Y10*31.55/17.2) -> 24881.439 | Z11: =Z9+(Z10*31.55/17.2) -> 25602.471 | AA11: =AA9+(AA10*31.55/17.2) -> 49960.706 | AB11: =AB9+(AB10*31.55/17.2) -> 50828.956 | AC11: =+AC9+(AC10*(31.55/17.2)) -> 8486.6105 | AD11: =+AD9+(AD10*(31.55/17.2)) -> 8519.7529 | AE11: =+AE9+(AE10*(31.55/17.2)) -> 58447.317 | AF11: =+AF9+(AF10*(31.55/17.2)) -> 59348.709 | AG11: =+AG9+(AG10*(31.55/17.2)) -> 8212.8488 | AH11: =+AH9+(AH10*(31.55/17.2)) -> 8256.5349 | AI11: =+AI9+(AI10*(31.55/17.2)) -> 66660.166 | AJ11: =+AJ9+(AJ10*(31.55/17.2)) -> 67605.244 | ... AL11: =+AL9+(AL10*(31.55/17.2)) -> 8531.7994 | AM11: =AM9+(AM10*31.55/17.2) -> 25186.07 | AN11: =AN9+(AN10*31.55/17.2) -> 25308.087 | AO11: =+AO9+(AO10*(31.55/17.2)) -> 75146.776 | AP11: =+AP9+(AP10*(31.55/17.2)) -> 76137.044 | AQ11: =+AQ9+(AQ10*(31.55/17.2)) -> 8486.6105 | AR11: =+AR9+(AR10*(31.55/17.2)) -> 8505.2733 | AS11: =+AS9+(AS10*(31.55/17.2)) -> 83633.387 | AT11: =+AT9+(AT10*(31.55/17.2)) -> 84642.317 | AU11: =+AU9+(AU10*(31.55/17.2)) -> 7665.3256 | AV11: =+AV9+(AV10*(31.55/17.2)) -> 7679.1599 | ... AZ11: =+AZ9+(AZ10*(31.55/17.2)) -> 8649.1308 | BA11: =BA9+(BA10*31.55/17.2) -> 24638.547 | BB11: =BB9+(BB10*31.55/17.2) -> 24833.564 | BC11: =BC9+(BC10*31.55/17.2) -> 49824.616 | BD11: =BD9+(BD10*31.55/17.2) -> 50141.651 | BE11: =+BE9+(BE10*(31.55/17.2)) -> 99785.323 | BF11: =+BF9+(BF10*(31.55/17.2)) -> 100970.61 | BG11: 100918.75 | BH11: 101271.49 | BI11: 102026.8 | BJ11: 101126.28 | BK11: 97793.113 | BL11: 102417.51 | BM11: 100526.58 | BN11: 97943.817 | BO11: 95577.773 | BP11: 100623.4 | BQ11: 99798.61
B12: BF COKE
B13: COB#10 | C13: Mt | D13: =+D9*0.7*17.2 -> 424121.04 | E13: =+E9*0.7*17.2 -> 35397.6 | F13: ='COKE OVENS'!F21 -> 35144.76 | G13: =+G9*0.7*17.2 -> 36577.52 | H13: ='COKE OVENS'!H21 -> 36433.04 | I13: =+E13+G13 -> 71975.12 | J13: =+F13+H13 -> 71577.8 | K13: =+K9*0.7*17.2 -> 33952.8 | L13: ='COKE OVENS'!L21 -> 34699.28 | M13: =+E13+G13+K13 -> 105927.92 | N13: =+F13+H13+L13 -> 106277.08 | O13: =+O9*0.7*17.2 -> 35084.56 | P13: ='COKE OVENS'!P21 -> 35614.32 | Q13: =+M13+O13 -> 141012.48 | R13: =+N13+P13 -> 141891.4 | S13: =+S9*0.7*17.2 -> 35084.56 | T13: ='COKE OVENS'!T21 -> 36577.52 | U13: =+Q13+S13 -> 176097.04 | V13: =+R13+T13 -> 178468.92 | W13: =+W9*0.7*17.2 -> 33266.52 | X13: ='COKE OVENS'!X21 -> 35397.6 | Y13: =+O13+S13+W13 -> 103435.64 | Z13: =+P13+T13+X13 -> 107589.44 | AA13: =+M13+Y13 -> 209363.56 | AB13: =+N13+Z13 -> 213866.52 | AC13: =+AC9*0.7*17.2 -> 35084.56 | AD13: ='COKE OVENS'!AD21 -> 35881.281 | AE13: =+AA13+AC13 -> 244448.12 | AF13: =+AB13+AD13 -> 249747.8 | AG13: =+AG9*0.7*17.2 -> 33952.8 | AH13: ='COKE OVENS'!AH21 -> 33793.958 | AI13: =+AE13+AG13 -> 278400.92 | AJ13: =+AF13+AH13 -> 283541.76 | AK13: =+AK9*0.7*17.2 -> 35084.56 | AL13: ='COKE OVENS'!AL21 -> 34869.818 | AM13: =+AC13+AG13+AK13 -> 104121.92 | AN13: =+AD13+AH13+AL13 -> 104545.06 | AO13: =AI13+AK13 -> 313485.48 | AP13: =AJ13+AL13 -> 318411.58 | AQ13: =+AQ9*0.7*17.2 -> 35084.56 | AR13: ='COKE OVENS'!AR21 -> 35144.76 | AS13: =+AO13+AQ13 -> 348570.04 | AT13: =+AP13+AR13 -> 353556.34 | AU13: =+AU9*0.7*17.2 -> 31689.28 | AV13: ='COKE OVENS'!AV21 -> 31606.376 | AW13: =+AS13+AU13 -> 380259.32 | AX13: =+AT13+AV13 -> 385162.71 | AY13: =+AY9*0.7*17.2 -> 35084.56 | AZ13: ='COKE OVENS'!AZ21 -> 36316.252 | BA13: =+AQ13+AU13+AY13 -> 101858.4 | BB13: =+AR13+AV13+AZ13 -> 103067.39 | BC13: =AM13+BA13 -> 205980.32 | BD13: =AN13+BB13 -> 207612.45 | BE13: =AW13+AY13 -> 415343.88 | BF13: =AX13+AZ13 -> 421478.97 | BG13: 423729.74 | BH13: 431508.84 | BI13: 433141.24 | BJ13: 432382.85 | BK13: 430769.03 | BL13: 438172.79 | BM13: 428806 | BN13: 425506 | BO13: 430922.2 | BP13: 406071.88 | BQ13: 412610.14
B14: COB#11 | C14: Mt | D14: =+D10*0.7*31.55 -> 787704.15 | E14: =+E10*31.55*0.7 -> 64002.33 | F14: ='COKE OVENS'!F22 -> 64751.169 | G14: =+G10*31.55*0.7 -> 67094.23 | H14: ='COKE OVENS'!H22 -> 66740.87 | I14: =+E14+G14 -> 131096.56 | J14: =+F14+H14 -> 131492.04 | K14: =+K10*31.55*0.7 -> 64929.9 | L14: ='COKE OVENS'!L22 -> 65239.09 | M14: =+E14+G14+K14 -> 196026.46 | N14: =+F14+H14+L14 -> 196731.13 | O14: =+O10*31.55*0.7 -> 67094.23 | P14: ='COKE OVENS'!P22 -> 67778.865 | Q14: =+M14+O14 -> 263120.69 | R14: =+N14+P14 -> 264509.99 | S14: =+S10*31.55*0.7 -> 67094.23 | T14: ='COKE OVENS'!T22 -> 67447.59 | U14: =+Q14+S14 -> 330214.92 | V14: =+R14+T14 -> 331957.58 | W14: =+W10*31.55*0.7 -> 61948.425 | X14: ='COKE OVENS'!X22 -> 64963.855 | Y14: =+O14+S14+W14 -> 196136.88 | Z14: =+P14+T14+X14 -> 200190.31 | AA14: =+M14+Y14 -> 392163.34 | AB14: =+N14+Z14 -> 396921.44 | AC14: =+AC10*31.55*0.7 -> 67094.23 | AD14: ='COKE OVENS'!AD22 -> 66256.925 | AE14: =+AA14+AC14 -> 459257.57 | AF14: =+AB14+AD14 -> 463178.36 | AG14: =+AG10*31.55*0.7 -> 64929.9 | AH14: ='COKE OVENS'!AH22 -> 64904.66 | AI14: =+AE14+AG14 -> 524187.47 | AJ14: =+AF14+AH14 -> 528083.02 | AK14: =+AK10*31.55*0.7 -> 67094.23 | AL14: ='COKE OVENS'!AL22 -> 67119.312 | AM14: =+AC14+AG14+AK14 -> 199118.36 | AN14: =+AD14+AH14+AL14 -> 198280.9 | AO14: =AI14+AK14 -> 591281.7 | AP14: =AJ14+AL14 -> 595202.34 | AQ14: =+AQ10*31.55*0.7 -> 67094.23 | AR14: ='COKE OVENS'!AR22 -> 66527.276 | AS14: =+AO14+AQ14 -> 658375.93 | AT14: =+AP14+AR14 -> 661729.61 | AU14: =+AU10*31.55*0.7 -> 60601.24 | AV14: ='COKE OVENS'!AV22 -> 60190.301 | AW14: =+AS14+AU14 -> 718977.17 | AX14: =+AT14+AV14 -> 721919.91 | AY14: =+AY10*31.55*0.7 -> 67094.23 | AZ14: ='COKE OVENS'!AZ22 -> 67075.458 | BA14: =+AQ14+AU14+AY14 -> 194789.7 | BB14: =+AR14+AV14+AZ14 -> 193793.04 | BC14: =AM14+BA14 -> 393908.06 | BD14: =AN14+BB14 -> 392073.93 | BE14: =AW14+AY14 -> 786071.4 | BF14: =AX14+AZ14 -> 788995.37 | BG14: 791332.05 | BH14: 793765.31 | BI14: 786486.6 | BJ14: 774691.65 | BK14: 737579.38 | BL14: 803741.8 | BM14: 778192 | BN14: 770203 | BO14: 752591.4 | BP14: 744858.59 | BQ14: 745859.84
B15: Total BF COKE | C15: Mt | D15: =SUM(D13:D14) -> 1211825.2 | E15: =SUM(E13:E14) -> 99399.93 | F15: =SUM(F13:F14) -> 99895.929 | G15: =SUM(G13:G14) -> 103671.75 | H15: =SUM(H13:H14) -> 103173.91 | I15: =SUM(I13:I14) -> 203071.68 | J15: =SUM(J13:J14) -> 203069.84 | K15: =SUM(K13:K14) -> 98882.7 | ... BF15: =SUM(BF13:BF14) -> 1210474.3 | BG15: 1215061.8 | BH15: 1225274.2 | BI15: 1219627.8 | BJ15: 1207074.5 | BK15: 1168348.4 | BL15: 1241914.6 | BM15: 1206998 | BN15: 1195709 | BO15: 1183513.6 | BP15: 1150930.5 | BQ15: 1158470
B16: SINTER | C16: Mt | D16: 4206886.4 | E16: 291677.45 | F16: 353508 | G16: =383.372118766*1000 -> 383372.12 | H16: 355306 | I16: =+E16+G16 -> 675049.57 | J16: =+F16+H16 -> 708814 | K16: =372.191438188584*1000 -> 372191.44 | L16: 376274 | M16: =+E16+G16+K16 -> 1047241 | N16: =+F16+H16+L16 -> 1085088 | O16: =376.384193405115*1000 -> 376384.19 | P16: 397960 | Q16: =+M16+O16 -> 1423625.2 | R16: =+N16+P16 -> 1483048 | S16: =376.384193405115*1000 -> 376384.19 | T16: 383179 | U16: =+Q16+S16 -> 1800009.4 | V16: =+R16+T16 -> 1866227 | W16: =207.661910104769*1000 -> 207661.91 | X16: 374784 | Y16: =+O16+S16+W16 -> 960430.3 | Z16: =+P16+T16+X16 -> 1155923 | AA16: =+M16+Y16 -> 2007671.3 | AB16: =+N16+Z16 -> 2241011 | AC16: =383.372118766*1000 -> 383372.12 | AD16: 301448 | AE16: =+AA16+AC16 -> 2391043.4 | AF16: =+AB16+AD16 -> 2542459 | AG16: =376.191438188584*1000 -> 376191.44 | AH16: 366206 | AI16: =+AE16+AG16 -> 2767234.9 | AJ16: =+AF16+AH16 -> 2908665 | AK16: =387.372118766*1000 -> 387372.12 | AL16: 360713 | AM16: =+AC16+AG16+AK16 -> 1146935.7 | AN16: =+AD16+AH16+AL16 -> 1028367 | AO16: =AI16+AK16 -> 3154607 | AP16: =AJ16+AL16 -> 3269378 | AQ16: 388962.46 | AR16: 366580 | AS16: =+AO16+AQ16 -> 3543569.4 | AT16: =+AP16+AR16 -> 3635958 | AU16: 349830.08 | AV16: 314846 | AW16: =+AS16+AU16 -> 3893399.5 | AX16: =+AT16+AV16 -> 3950804 | AY16: 388962.46 | AZ16: 379828 | BA16: =+AQ16+AU16+AY16 -> 1127755 | BB16: =+AR16+AV16+AZ16 -> 1061254 | BC16: =AM16+BA16 -> 2274690.7 | BD16: =AN16+BB16 -> 2089621 | BE16: =AW16+AY16 -> 4282362 | BF16: =AX16+AZ16 -> 4330632 | BG16: 4387544.5 | BH16: 3980714 | BI16: 4499999.9 | BJ16: 4398445 | BK16: 4395665 | BL16: 4183927.8 | BM16: 4277831 | BN16: 3665891.3 | BO16: 3629577 | BP16: 3903932.5 | BQ16: 3709525
B17: HOT METAL | C17: Mt | D17: 3000000 | E17: 208000 | F17: 237076.8 | G17: 260000 | H17: 255730.9 | I17: =+E17+G17 -> 468000 | J17: =+F17+H17 -> 492807.7 | K17: =252*1000 -> 252000 | L17: 261489.9 | M17: =+E17+G17+K17 -> 720000 | N17: =+F17+H17+L17 -> 754297.6 | O17: 255000 | P17: 268142.3 | Q17: =+M17+O17 -> 975000 | R17: =+N17+P17 -> 1022439.9 | S17: 255000 | T17: 253263.6 | U17: =+Q17+S17 -> 1230000 | V17: =+R17+T17 -> 1275703.5 | W17: 140000 | X17: 243297.4 | Y17: =+O17+S17+W17 -> 650000 | Z17: =+P17+T17+X17 -> 764703.3 | AA17: =+M17+Y17 -> 1370000 | AB17: =+N17+Z17 -> 1519000.9 | AC17: 260000 | AD17: 202962.1 | AE17: =+AA17+AC17 -> 1630000 | AF17: =+AB17+AD17 -> 1721963 | AG17: 252000 | AH17: 244148.2 | AI17: =+AE17+AG17 -> 1882000 | AJ17: =+AF17+AH17 -> 1966111.2 | AK17: 260000 | AL17: 251561 | AM17: =+AC17+AG17+AK17 -> 772000 | AN17: =+AD17+AH17+AL17 -> 698671.3 | AO17: =AI17+AK17 -> 2142000 | AP17: =AJ17+AL17 -> 2217672.2 | AQ17: 264000 | AR17: 244851.4 | AS17: =+AO17+AQ17 -> 2406000 | AT17: =+AP17+AR17 -> 2462523.6 | AU17: 236000 | AV17: 196575.3 | AW17: =+AS17+AU17 -> 2642000 | AX17: =+AT17+AV17 -> 2659098.9 | AY17: 264000 | AZ17: 251871.7 | BA17: =+AQ17+AU17+AY17 -> 764000 | BB17: =+AR17+AV17+AZ17 -> 693298.4 | BC17: =AM17+BA17 -> 1536000 | BD17: =AN17+BB17 -> 1391969.7 | BE17: =AW17+AY17 -> 2906000 | BF17: =AX17+AZ17 -> 2910970.6 | BG17: 2650000 | BH17: 2622585.7 | BI17: 2800000 | BJ17: 2721268.1 | BK17: 2592119.6 | BL17: 2650001 | BM17: 2406785.7 | BN17: 2496672.2 | BO17: 2092798 | BP17: 2700000 | BQ17: 2505193
B18: CRUDE STEEL | C18: Mt | D18: 2817514.1 | E18: 193691.15 | F18: 223226 | G18: =244.66477809254*1000 -> 244664.78 | H18: 236638 | I18: =+E18+G18 -> 438355.93 | J18: =+F18+H18 -> 459864 | K18: =237.110481586402*1000 -> 237110.48 | L18: 243453 | M18: =+E18+G18+K18 -> 675466.41 | N18: =+F18+H18+L18 -> 703317 | O18: =239.943342776204*1000 -> 239943.34 | P18: 253662 | Q18: =+M18+O18 -> 915409.75 | R18: =+N18+P18 -> 956979 | S18: =239.943342776204*1000 -> 239943.34 | T18: 237622 | U18: =+Q18+S18 -> 1155353.1 | V18: =+R18+T18 -> 1194601 | W18: =125.920679886686*1000 -> 125920.68 | X18: 226847 | Y18: =+O18+S18+W18 -> 605807.37 | Z18: =+P18+T18+X18 -> 718131 | AA18: =+M18+Y18 -> 1281273.8 | AB18: =+N18+Z18 -> 1421448 | AC18: =244.66477809254*1000 -> 244664.78 | AD18: 179201 | AE18: =+AA18+AC18 -> 1525938.6 | AF18: =+AB18+AD18 -> 1600649 | AG18: =237.110481586402*1000 -> 237110.48 | AH18: 229502 | AI18: =+AE18+AG18 -> 1763049 | AJ18: =+AF18+AH18 -> 1830151 | AK18: =244.66477809254*1000 -> 244664.78 | AL18: 234365 | AM18: =+AC18+AG18+AK18 -> 726440.04 | AN18: =+AD18+AH18+AL18 -> 643068 | AO18: =AI18+AK18 -> 2007713.8 | AP18: =AJ18+AL18 -> 2064516 | AQ18: 248441.93 | AR18: 228047 | AS18: =+AO18+AQ18 -> 2256155.7 | AT18: =+AP18+AR18 -> 2292563 | AU18: 222001.89 | AV18: 185016 | AW18: =+AS18+AU18 -> 2478157.6 | AX18: =+AT18+AV18 -> 2477579 | AY18: 248441.93 | AZ18: 241240 | BA18: =+AQ18+AU18+AY18 -> 718885.74 | BB18: =+AR18+AV18+AZ18 -> 654303 | BC18: =AM18+BA18 -> 1445325.8 | BD18: =AN18+BB18 -> 1297371 | BE18: =AW18+AY18 -> 2726599.6 | BF18: =AX18+AZ18 -> 2718819 | BG18: 2489528.3 | BH18: 2436959 | BI18: 2620075.5 | BJ18: 2528925 | BK18: 2422324.3 | BL18: 2451737.7 | BM18: 2227867 | BN18: 2297163.5 | BO18: 1847433 | BP18: 2500000 | BQ18: 2083412
B19: Caster #(1+2 ) | C19: Mt | D19: 1920416.1 | E19: =SMS!E29 -> 134587.97 | F19: =SMS!F37 -> 166745.17 | G19: =SMS!G29 -> 176063.19 | H19: =SMS!H37 -> 175199.54 | I19: =+E19+G19 -> 310651.17 | J19: =SMS!J37 -> 341944.71 | K19: =SMS!K29 -> 171147.42 | L19: =SMS!L37 -> 182735 | M19: =+E19+G19+K19 -> 481798.59 | N19: =+F19+H19+L19 -> 524679.71 | O19: =SMS!O29 -> 171341.76 | P19: =SMS!P37 -> 189077 | Q19: =+M19+O19 -> 653140.35 | R19: =+N19+P19 -> 713756.71 | S19: =SMS!S29 -> 171341.76 | T19: =SMS!T37 -> 179543 | U19: =+Q19+S19 -> 824482.11 | V19: =+R19+T19 -> 893299.71 | W19: =SMS!W29 -> 90564.479 | X19: =SMS!X37 -> 172339.6 | Y19: =+O19+S19+W19 -> 433248 | Z19: =+P19+T19+X19 -> 540959.6 | AA19: =+M19+Y19 -> 915046.59 | AB19: =+N19+Z19 -> 1065639.3 | AC19: =SMS!AC29 -> 173952.38 | AD19: =SMS!AD37 -> 135241 | AE19: =+AA19+AC19 -> 1088999 | AF19: =+AB19+AD19 -> 1200880.3 | AG19: =SMS!AG29 -> 168508.9 | AH19: =SMS!AH37 -> 178010.44 | AI19: =SMS!AI29 -> 1257507.9 | AJ19: =SMS!AJ37 -> 1378890.8 | AK19: =SMS!AK29 -> 173424.67 | AL19: =SMS!AL37 -> 168781 | AM19: =SMS!AM29 -> 515885.95 | AN19: =SMS!AN37 -> 482032.44 | AO19: =SMS!AO29 -> 1430932.5 | AP19: =SMS!AP37 -> 1547671.8 | AQ19: =SMS!AQ29 -> 176674.12 | AR19: =SMS!AR37 -> 164934.28 | AS19: =+AO19+AQ19 -> 1607606.7 | AT19: =+AP19+AR19 -> 1712606 | AU19: =SMS!AU29 -> 157621.94 | AV19: =SMS!AV37 -> 135607.79 | AW19: =+AS19+AU19 -> 1765228.6 | AX19: =+AT19+AV19 -> 1848213.8 | AY19: =SMS!AY29 -> 176146.41 | AZ19: =SMS!AZ37 -> 176644.91 | BA19: =+AQ19+AU19+AY19 -> 510442.47 | BB19: =+AR19+AV19+AZ19 -> 477186.98 | BC19: =AM19+BA19 -> 1026328.4 | BD19: =AN19+BB19 -> 959219.42 | BE19: =AW19+AY19 -> 1941375 | BF19: =AX19+AZ19 -> 2024858.7 | BG19: 1880445.4 | BH19: 1818588.7 | BJ19: 1922629.6 | BK19: 1903696 | BM19: 1777963.7
B20: Caster #3 | C20: Mt | D20: 897098.03 | E20: =SMS!E38 -> 59103.176 | F20: =SMS!F46 -> 56481.07 | G20: =SMS!G38 -> 68601.583 | H20: =SMS!H46 -> 61438.56 | I20: =+E20+G20 -> 127704.76 | J20: =SMS!J46 -> 117919.63 | K20: =SMS!K38 -> 65963.061 | L20: =SMS!L46 -> 60718.3 | M20: =+E20+G20+K20 -> 193667.82 | N20: =+F20+H20+L20 -> 178637.93 | O20: =SMS!O38 -> 68601.583 | P20: =SMS!P46 -> 64584.79 | Q20: =+M20+O20 -> 262269.4 | R20: =+N20+P20 -> 243222.72 | S20: =SMS!S38 -> 68601.583 | T20: =SMS!T46 -> 58078.79 | U20: =+Q20+S20 -> 330870.99 | V20: =+R20+T20 -> 301301.51 | W20: =SMS!W38 -> 35356.201 | X20: =SMS!X46 -> 54507 | Y20: =+O20+S20+W20 -> 172559.37 | Z20: =+P20+T20+X20 -> 177170.58 | AA20: =+M20+Y20 -> 366227.19 | AB20: =+N20+Z20 -> 355808.51 | AC20: =SMS!AC38 -> 70712.4 | AD20: =SMS!AD46 -> 43960.31 | AE20: =+AA20+AC20 -> 436939.59 | AF20: =+AB20+AD20 -> 399768.82 | AG20: =SMS!AG38 -> 68601.583 | AH20: =SMS!AH46 -> 51491.21 | AI20: =SMS!AI38 -> 505541.17 | AJ20: =SMS!AJ46 -> 451260.03 | AK20: =SMS!AK38 -> 71240.106 | AL20: =SMS!AL46 -> 65584.38 | AM20: =SMS!AM38 -> 210554.09 | AN20: =SMS!AN46 -> 161035.9 | AO20: =SMS!AO38 -> 576781.27 | AP20: =SMS!AP46 -> 516844.41 | AQ20: =SMS!AQ38 -> 71767.81 | AR20: =SMS!AR46 -> 63113.1 | AS20: =+AO20+AQ20 -> 648549.09 | AT20: =+AP20+AR20 -> 579957.51 | AU20: =SMS!AU38 -> 64379.947 | AV20: =SMS!AV46 -> 49408.38 | AW20: =+AS20+AU20 -> 712929.03 | AX20: =+AT20+AV20 -> 629365.89 | AY20: =SMS!AY38 -> 72295.515 | AZ20: =SMS!AZ46 -> 64595.04 | BA20: =+AQ20+AU20+AY20 -> 208443.27 | BB20: =+AR20+AV20+AZ20 -> 177116.52 | BC20: =AM20+BA20 -> 418997.36 | BD20: =AN20+BB20 -> 338152.42 | BE20: =AW20+AY20 -> 785224.55 | BF20: =AX20+AZ20 -> 693960.93 | BG20: 609083.07 | BH20: 618370.32 | BJ20: 606294.79 | BK20: 518629.33 | BM20: 449903.88
B21: Avg Heats Cast per Day | C21: Nos. / day | D21: =D53/D1 -> 53.120553 | E21: =+E53/E1 -> 47.754228 | F21: =+F53/F1 -> 48.005642 | G21: =+G53/G1 -> 54.369951 | H21: =+H53/H1 -> 50.886713 | I21: =+I53/I1 -> 51.298365 | J21: =+J53/J1 -> 49.452332 | K21: =+K53/K1 -> 54.508157 | L21: =+L53/L1 -> 52.547596 | ... BF21: =+BF53/BF1 -> 49.217112 | BG21: 51.463117 | BH21: 49.270546 | BI21: 50.337665 | BJ21: 48.130368 | BK21: 45.269663 | BL21: 44.780041 | BM21: 40.065753 | BN21: 41.920046 | BO21: 33.309589 | BP21: 47.014645 | BQ21: 38.663934
B22: Cold Pig & Pig Equivalent
B23: MOG | C23: Mt | D23: 3420 | E23: 1620 | F23: 246.31997 | G23: 810 | H23: 2383.6528 | I23: =+E23+G23 -> 2430 | J23: =+F23+H23 -> 2629.9728 | K23: =0.81*1000 -> 810 | L23: 902.97846 | M23: =+E23+G23+K23 -> 3240 | N23: =+F23+H23+L23 -> 3532.9512 | O23: 810 | P23: 0 | Q23: =+M23+O23 -> 4050 | R23: =+N23+P23 -> 3532.9512 | S23: =0.81*1000 -> 810 | T23: 144.06922 | U23: =+Q23+S23 -> 4860 | V23: =+R23+T23 -> 3677.0204 | W23: =5360-1625 -> 3735 | X23: 256.58678 | Y23: =+O23+S23+W23 -> 5355 | Z23: =+P23+T23+X23 -> 400.656 | AA23: =+M23+Y23 -> 8595 | AB23: =+N23+Z23 -> 3933.6072 | AC23: 810 | AD23: 3014.2686 | AE23: =+AA23+AC23 -> 9405 | AF23: =+AB23+AD23 -> 6947.8759 | AG23: 810 | AH23: 135.13793 | AI23: =+AE23+AG23 -> 10215 | AJ23: =+AF23+AH23 -> 7083.0138 | AK23: 810 | AL23: 35.72516 | AM23: =+AC23+AG23+AK23 -> 2430 | AN23: =+AD23+AH23+AL23 -> 3185.1317 | AO23: =AI23+AK23 -> 11025 | AP23: =AJ23+AL23 -> 7118.7389 | AQ23: 810 | AR23: 662.91874 | AS23: =+AO23+AQ23 -> 11835 | AT23: =+AP23+AR23 -> 7781.6577 | AU23: 810 | AV23: 0 | AW23: =+AS23+AU23 -> 12645 | AX23: =+AT23+AV23 -> 7781.6577 | AY23: 810 | AZ23: 80.29814 | BA23: =+AQ23+AU23+AY23 -> 2430 | BB23: =+AR23+AV23+AZ23 -> 743.21688 | BC23: =AM23+BA23 -> 4860 | BD23: =AN23+BB23 -> 3928.3486 | BE23: =AW23+AY23 -> 13455 | BF23: =AX23+AZ23 -> 7861.9558 | BG23: 7740 | BH23: 12917.886 | BI23: 19561.1 | BJ23: 7548.2756 | BK23: 9129.3344 | BL23: 19735.515 | BM23: 22361.072 | BN23: 20755.018 | BO23: 58220.7 | BP23: 29957.856 | BQ23: 134629.18
B24: UPIS | C24: Mt | D24: 0 | E24: 0 | F24: 34.774584 | G24: 0 | H24: 336.51569 | I24: =+E24+G24 -> 0 | J24: =+F24+H24 -> 371.29027 | K24: 0 | L24: 127.47931 | M24: =+E24+G24+K24 -> 0 | N24: =+F24+H24+L24 -> 498.76958 | O24: 0 | P24: 0 | Q24: =+M24+O24 -> 0 | R24: =+N24+P24 -> 498.76958 | S24: 0 | T24: 20.339184 | U24: =+Q24+S24 -> 0 | V24: =+R24+T24 -> 519.10877 | W24: 0 | X24: 36.224016 | Y24: =+O24+S24+W24 -> 0 | Z24: =+P24+T24+X24 -> 56.5632 | AA24: =+M24+Y24 -> 0 | AB24: =+N24+Z24 -> 555.33278 | AC24: 0 | AD24: 426 | AE24: =+AA24+AC24 -> 0 | AF24: =+AB24+AD24 -> 981.33278 | AG24: 0 | AH24: 19.078296 | AI24: =+AE24+AG24 -> 0 | AJ24: =+AF24+AH24 -> 1000.4111 | AK24: 0 | AL24: 5 | AM24: =+AC24+AG24+AK24 -> 0 | AN24: =+AD24+AH24+AL24 -> 450.0783 | AO24: =AI24+AK24 -> 0 | AP24: =AJ24+AL24 -> 1005.4111 | AQ24: 0 | AR24: 93.588528 | AS24: =+AO24+AQ24 -> 0 | AT24: =+AP24+AR24 -> 1098.9996 | AU24: 0 | AV24: 0 | AW24: =+AS24+AU24 -> 0 | AX24: =+AT24+AV24 -> 1098.9996 | AY24: 0 | AZ24: 11.336208 | BA24: =+AQ24+AU24+AY24 -> 0 | BB24: =+AR24+AV24+AZ24 -> 104.92474 | BC24: =AM24+BA24 -> 0 | BD24: =AN24+BB24 -> 555.00303 | BE24: =AW24+AY24 -> 0 | BF24: =AX24+AZ24 -> 1110.3358 | BG24: 0 | BH24: 1823.7656 | BI24: 0 | BJ24: 1026.6221 | BK24: 2541.6495 | BL24: 0 | BM24: 2774.7649 | BN24: 392 | BO24: 3852.3 | BP24: 1419.0563 | BQ24: 8272.9783
B25: Equiv. Pig Iron @ 65% of HM sent to Sand Pit | C25: Mt | D25: 2600 | E25: 325 | F25: 190 | G25: 0 | H25: 230 | I25: =+E25+G25 -> 325 | J25: =+F25+H25 -> 420 | K25: 0 | L25: 0 | M25: =+E25+G25+K25 -> 325 | N25: =+F25+H25+L25 -> 420 | O25: 0 | P25: 0 | Q25: =+M25+O25 -> 325 | R25: =+N25+P25 -> 420 | S25: 0 | T25: 0 | U25: =+Q25+S25 -> 325 | V25: =+R25+T25 -> 420 | W25: =2500*0.65 -> 1625 | X25: 0 | Y25: =+O25+S25+W25 -> 1625 | Z25: =+P25+T25+X25 -> 0 | AA25: =+M25+Y25 -> 1950 | AB25: =+N25+Z25 -> 420 | AC25: 0 | AD25: 5603 | AE25: =+AA25+AC25 -> 1950 | AF25: =+AB25+AD25 -> 6023 | AG25: 0 | AH25: 0 | AI25: =+AE25+AG25 -> 1950 | AJ25: =+AF25+AH25 -> 6023 | AK25: 0 | AL25: 0 | AM25: =+AC25+AG25+AK25 -> 0 | AN25: =+AD25+AH25+AL25 -> 5603 | AO25: =AI25+AK25 -> 1950 | AP25: =AJ25+AL25 -> 6023 | AQ25: 0 | AR25: 800.6 | AS25: =+AO25+AQ25 -> 1950 | AT25: =+AP25+AR25 -> 6823.6 | AU25: 0 | AV25: 920 | AW25: =+AS25+AU25 -> 1950 | AX25: =+AT25+AV25 -> 7743.6 | AY25: 0 | AZ25: 310 | BA25: =+AQ25+AU25+AY25 -> 0 | BB25: =+AR25+AV25+AZ25 -> 2030.6 | BC25: =AM25+BA25 -> 0 | BD25: =AN25+BB25 -> 7633.6 | BE25: =AW25+AY25 -> 1950 | BF25: =AX25+AZ25 -> 8053.6 | BG25: 1625 | BH25: 11114.8 | BI25: 2000 | BJ25: 5022 | BK25: 4664.8 | BL25: 14800 | BM25: 9214.4 | BN25: 0 | BO25: 0 | BP25: 0 | BQ25: 26220.8
B26: TOTAL EQUIVALENT PIG IRON | C26: Mt | D26: =SUM(D23:D25) -> 6020 | E26: =SUM(E23:E25) -> 1945 | F26: =SUM(F23:F25) -> 471.09455 | G26: =SUM(G23:G25) -> 810 | H26: =SUM(H23:H25) -> 2950.1685 | I26: =SUM(I23:I25) -> 2755 | J26: =SUM(J23:J25) -> 3421.263 | K26: =SUM(K23:K25) -> 810 | ... BF26: =SUM(BF23:BF25) -> 17025.892 | BG26: 9365 | BH26: 25856.451 | BI26: 21561.1 | BJ26: 13596.898 | BK26: 16335.784 | BL26: 34535.515 | BM26: 34350.237 | BN26: 21147.018 | BO26: 62073 | BP26: 31376.912 | BQ26: 169122.96
B27: Net PCI Production | C27: Mt | D27: 5103 | E27: 644.512 | F27: 160.65 | G27: 279.98 | H27: 603.862 | I27: =+E27+G27 -> 924.492 | J27: =+F27+H27 -> 764.512 | K27: 273.996 | L27: 0 | M27: =+E27+G27+K27 -> 1198.488 | N27: =+F27+H27+L27 -> 764.512 | O27: 276.24 | P27: 0 | Q27: =+M27+O27 -> 1474.728 | R27: =+N27+P27 -> 764.512 | S27: 276.24 | T27: 0 | U27: =+Q27+S27 -> 1750.968 | V27: =+R27+T27 -> 764.512 | W27: 498.97 | X27: 0 | Y27: =+O27+S27+W27 -> 1051.45 | Z27: =+P27+T27+X27 -> 0 | AA27: =+M27+Y27 -> 2249.938 | AB27: =+N27+Z27 -> 764.512 | AC27: 279.98 | AD27: 549.087 | AE27: =+AA27+AC27 -> 2529.918 | AF27: =+AB27+AD27 -> 1313.599 | AG27: 273.996 | AH27: 833.469 | AI27: =+AE27+AG27 -> 2803.914 | AJ27: =+AF27+AH27 -> 2147.068 | AK27: 279.98 | AL27: 1510.747 | AM27: =+AC27+AG27+AK27 -> 833.956 | AN27: =+AD27+AH27+AL27 -> 2893.303 | AO27: =AI27+AK27 -> 3083.894 | AP27: =AJ27+AL27 -> 3657.815 | AQ27: 282.972 | AR27: 1549.45 | AS27: =+AO27+AQ27 -> 3366.866 | AT27: =+AP27+AR27 -> 5207.265 | AU27: 262.028 | AV27: 755.405 | AW27: =+AS27+AU27 -> 3628.894 | AX27: =+AT27+AV27 -> 5962.67 | AY27: 282.972 | AZ27: 209.86 | BA27: =+AQ27+AU27+AY27 -> 827.972 | BB27: =+AR27+AV27+AZ27 -> 2514.715 | BC27: =AM27+BA27 -> 1661.928 | BD27: =AN27+BB27 -> 5408.018 | BE27: =AW27+AY27 -> 3911.866 | BF27: =AX27+AZ27 -> 6172.53 | BG27: 2831.5 | BH27: 7991.486 | BI27: 2377.872 | BJ27: 6141.395 | BK27: 5885.734 | BL27: 2398.56 | BM27: 13377.679 | BN27: 11568.99 | BO27: 41093.9 | BP27: 0 | BQ27: 44255.19
B28: Net Granulated Slag Production | C28: Mt | D28: 1049580 | E28: 72770.88 | F28: 73016.796 | G28: 95295.2 | H28: 75418.546 | I28: =+E28+G28 -> 168066.08 | J28: =+F28+H28 -> 148435.34 | K28: 92363.04 | L28: 72846.055 | M28: =+E28+G28+K28 -> 260429.12 | N28: =+F28+H28+L28 -> 221281.4 | O28: 93462.6 | P28: 75682.97 | Q28: =+M28+O28 -> 353891.72 | R28: =+N28+P28 -> 296964.37 | S28: 93462.6 | T28: 80832.023 | U28: =+Q28+S28 -> 447354.32 | V28: =+R28+T28 -> 377796.39 | W28: 51312.8 | X28: 79584.049 | Y28: =+O28+S28+W28 -> 238238 | Z28: =+P28+T28+X28 -> 236099.04 | AA28: =+M28+Y28 -> 498667.12 | AB28: =+N28+Z28 -> 457380.44 | AC28: 95295.2 | AD28: 63840.922 | AE28: =+AA28+AC28 -> 593962.32 | AF28: =+AB28+AD28 -> 521221.36 | AG28: 92363.04 | AH28: 88321.763 | AI28: =+AE28+AG28 -> 686325.36 | AJ28: =+AF28+AH28 -> 609543.13 | AK28: 95295.2 | AL28: 84104.855 | AM28: =+AC28+AG28+AK28 -> 282953.44 | AN28: =+AD28+AH28+AL28 -> 236267.54 | AO28: =AI28+AK28 -> 781620.56 | AP28: =AJ28+AL28 -> 693647.98 | AQ28: 96761.28 | AR28: 81040.671 | AS28: =+AO28+AQ28 -> 878381.84 | AT28: =+AP28+AR28 -> 774688.65 | AU28: 86498.72 | AV28: 67236.848 | AW28: =+AS28+AU28 -> 964880.56 | AX28: =+AT28+AV28 -> 841925.5 | AY28: 96761.28 | AZ28: 71373.052 | BA28: =+AQ28+AU28+AY28 -> 280021.28 | BB28: =+AR28+AV28+AZ28 -> 219650.57 | BC28: =AM28+BA28 -> 562974.72 | BD28: =AN28+BB28 -> 455918.11 | BE28: =AW28+AY28 -> 1061641.8 | BF28: =AX28+AZ28 -> 913298.55 | BG28: 987899.89 | BH28: 899258.76 | BI28: 1063047 | BJ28: 1075244.6 | BK28: 1065593 | BL28: 157305.12 | BM28: 920129.3 | BN28: 882599.97 | BO28: 776699 | BP28: 854658 | BQ28: 809638.21
B29: Saleable Steel Production (Mill Wise)
B30: WR Mill | C30: Mt | D30: 520000 | E30: 36500 | F30: =+WRM!F159 -> 41533 | G30: 44000 | H30: =+WRM!H159 -> 39351.8 | I30: =+E30+G30 -> 80500 | J30: =+F30+H30 -> 80884.8 | K30: 42500 | L30: =+WRM!L159 -> 38291.35 | M30: =+E30+G30+K30 -> 123000 | N30: =+F30+H30+L30 -> 119176.15 | O30: 44000 | P30: =+WRM!P159 -> 47063.9 | Q30: =+M30+O30 -> 167000 | R30: =+N30+P30 -> 166240.05 | S30: 44000 | T30: =+WRM!T159 -> 38718.35 | U30: =+Q30+S30 -> 211000 | V30: =+R30+T30 -> 204958.4 | W30: 25000 | X30: =+WRM!X159 -> 41006.15 | Y30: =+O30+S30+W30 -> 113000 | Z30: =+P30+T30+X30 -> 126788.4 | AA30: =+M30+Y30 -> 236000 | AB30: =+N30+Z30 -> 245964.55 | AC30: 42500 | AD30: =+WRM!AD159 -> 30034.55 | AE30: =+AA30+AC30 -> 278500 | AF30: =+AB30+AD30 -> 275999.1 | AG30: 42500 | AH30: =+WRM!AH159 -> 34614.25 | AI30: =+AE30+AG30 -> 321000 | AJ30: =+AF30+AH30 -> 310613.35 | AK30: 44000 | AL30: =+WRM!AL159 -> 44007.35 | AM30: =+AC30+AG30+AK30 -> 129000 | AN30: =+AD30+AH30+AL30 -> 108656.15 | AO30: =AI30+AK30 -> 365000 | AP30: =AJ30+AL30 -> 354620.7 | AQ30: 44500 | AR30: =+WRM!AR159 -> 44589.55 | AS30: =+AO30+AQ30 -> 409500 | AT30: =+AP30+AR30 -> 399210.25 | AU30: 40000 | AV30: =+WRM!AV159 -> 37420.7 | AW30: =+AS30+AU30 -> 449500 | AX30: =+AT30+AV30 -> 436630.95 | AY30: 44500 | AZ30: =+WRM!AZ159 -> 46692.85 | BA30: =+AQ30+AU30+AY30 -> 129000 | BB30: =+AR30+AV30+AZ30 -> 128703.1 | BC30: =AM30+BA30 -> 258000 | BD30: =AN30+BB30 -> 237359.25 | BE30: =AW30+AY30 -> 494000 | BF30: =AX30+AZ30 -> 483323.8 | BG30: 500000 | BH30: 459030.64 | BI30: 500000 | BJ30: 478528.39 | BK30: 466114.65 | BL30: 500000 | BM30: 465343.77 | BN30: 435965.96 | BO30: 356518.66 | BP30: 500000 | BQ30: 412025.22
B31: Bar Mill | C31: Mt | D31: 990000 | E31: 68500 | F31: =+BM!F56 -> 74661.04 | G31: 79000 | H31: =+BM!H56 -> 76175.635 | I31: =+E31+G31 -> 147500 | J31: =+F31+H31 -> 150836.68 | K31: 76000 | L31: =+BM!L56 -> 73644.015 | M31: =+E31+G31+K31 -> 223500 | N31: =+F31+H31+L31 -> 224480.69 | O31: 79000 | P31: =+BM!P56 -> 88056.49 | Q31: =+M31+O31 -> 302500 | R31: =+N31+P31 -> 312537.18 | S31: 79000 | T31: =+BM!T56 -> 75853.695 | U31: =+Q31+S31 -> 381500 | V31: =+R31+T31 -> 388390.88 | W31: =47.5*1000 -> 47500 | X31: =+BM!X56 -> 76319.035 | Y31: =+O31+S31+W31 -> 205500 | Z31: =+P31+T31+X31 -> 240229.22 | AA31: =+M31+Y31 -> 429000 | AB31: =+N31+Z31 -> 464709.91 | AC31: 78000 | AD31: =+BM!AD56 -> 50950.275 | AE31: =+AA31+AC31 -> 507000 | AF31: =+AB31+AD31 -> 515660.19 | AG31: 76000 | AH31: =+BM!AH56 -> 69720.765 | AI31: =+AE31+AG31 -> 583000 | AJ31: =+AF31+AH31 -> 585380.95 | AK31: 79000 | AL31: =+BM!AL56 -> 81616.765 | AM31: =+AC31+AG31+AK31 -> 233000 | AN31: =+AD31+AH31+AL31 -> 202287.81 | AO31: =AI31+AK31 -> 662000 | AP31: =AJ31+AL31 -> 666997.72 | AQ31: 79000 | AR31: =+BM!AR56 -> 85804.6 | AS31: =+AO31+AQ31 -> 741000 | AT31: =+AP31+AR31 -> 752802.32 | AU31: 71500 | AV31: =+BM!AV56 -> 74058.32 | AW31: =+AS31+AU31 -> 812500 | AX31: =+AT31+AV31 -> 826860.64 | AY31: 80000 | AZ31: =+BM!AZ56 -> 81200 | BA31: =+AQ31+AU31+AY31 -> 230500 | BB31: =+AR31+AV31+AZ31 -> 241062.92 | BC31: =AM31+BA31 -> 463500 | BD31: =AN31+BB31 -> 443350.73 | BE31: =AW31+AY31 -> 892500 | BF31: =AX31+AZ31 -> 908060.64 | BG31: 870000 | BH31: 750867.85 | BI31: 850000 | BJ31: 795322.27 | BK31: 775906.63 | BL31: 750000 | BM31: 649840.96 | BN31: 674875.14 | BO31: 440547.27 | BP31: 800000 | BQ31: 632220.18
B32: US Mill | C32: Mt | D32: 850000 | E32: 56000 | F32: =+USM!G122 -> 52516.132 | G32: 65000 | H32: =+USM!I122 -> 57219.144 | I32: =+E32+G32 -> 121000 | J32: =+F32+H32 -> 109735.28 | K32: 62500 | L32: =+USM!M122 -> 58674.633 | M32: =+E32+G32+K32 -> 183500 | N32: =+F32+H32+L32 -> 168409.91 | O32: 65000 | P32: =+USM!Q122 -> 57327.387 | Q32: =+M32+O32 -> 248500 | R32: =+N32+P32 -> 225737.3 | S32: 65000 | T32: =+USM!U122 -> 44406.293 | U32: =+Q32+S32 -> 313500 | V32: =+R32+T32 -> 270143.59 | W32: 33500 | X32: =+USM!Y122 -> 49996.716 | Y32: =+O32+S32+W32 -> 163500 | Z32: =+P32+T32+X32 -> 151730.4 | AA32: =+M32+Y32 -> 347000 | AB32: =+N32+Z32 -> 320140.3 | AC32: 67000 | AD32: =+USM!AE122 -> 29659.897 | AE32: =+AA32+AC32 -> 414000 | AF32: =+AB32+AD32 -> 349800.2 | AG32: 65000 | AH32: =+USM!AI122 -> 49060.044 | AI32: =+AE32+AG32 -> 479000 | AJ32: =+AF32+AH32 -> 398860.25 | AK32: =67.5*1000 -> 67500 | AL32: =+USM!AM122 -> 52987.18 | AM32: =+AC32+AG32+AK32 -> 199500 | AN32: =+AD32+AH32+AL32 -> 131707.12 | AO32: =AI32+AK32 -> 546500 | AP32: =AJ32+AL32 -> 451847.43 | AQ32: 68000 | AR32: =+USM!AS122 -> 56169.978 | AS32: =+AO32+AQ32 -> 614500 | AT32: =+AP32+AR32 -> 508017.4 | AU32: 61000 | AV32: =+USM!AW122 -> 54279.398 | AW32: =+AS32+AU32 -> 675500 | AX32: =+AT32+AV32 -> 562296.8 | AY32: 68500 | AZ32: =+USM!BA122 -> 63120.146 | BA32: =+AQ32+AU32+AY32 -> 197500 | BB32: =+AR32+AV32+AZ32 -> 173569.52 | BC32: =AM32+BA32 -> 397000 | BD32: =AN32+BB32 -> 305276.64 | BE32: =AW32+AY32 -> 744000 | BF32: =AX32+AZ32 -> 625416.95 | BG32: 560000 | BH32: 499887.23 | BI32: 525000 | BJ32: 459141.95 | BK32: 361987.56 | BL32: 450000 | BM32: 213226.16 | BN32: 220000 | BO32: 88943.894 | BP32: 535000 | BQ32: 171634.81
B33: Finished Steel | C33: Mt | D33: =SUM(D30:D32) -> 2360000 | E33: =SUM(E30:E32) -> 161000 | F33: =SUM(F30:F32) -> 168710.17 | G33: =SUM(G30:G32) -> 188000 | H33: =SUM(H30:H32) -> 172746.58 | I33: =SUM(I30:I32) -> 349000 | J33: =SUM(J30:J32) -> 341456.75 | K33: =SUM(K30:K32) -> 181000 | ... BF33: =SUM(BF30:BF32) -> 2016801.4 | BG33: 1930000 | BH33: 1709785.7 | BI33: 1875000 | BJ33: 1732992.6 | BK33: 1604008.8 | BL33: 1700000 | BM33: 1328410.9 | BN33: 1330841.1 | BO33: 886009.82 | BP33: =SUM(BP30:BP32) -> 1835000 | BQ33: =SUM(BQ30:BQ32) -> 1215880.2
B34: 150x150 mm | C34: Mt | D34: 349999.99 | E34: 20999.684 | F34: =38395.02-12 -> 38383.02 | G34: 48499.577 | H34: 52556 | I34: =+E34+G34 -> 69499.26 | J34: =+F34+H34 -> 90939.02 | K34: =48.0001108831152*1000 -> 48000.111 | L34: 56218 | M34: =+E34+G34+K34 -> 117499.37 | N34: =+F34+H34+L34 -> 147157.02 | O34: =43.5001413553209*1000 -> 43500.141 | P34: 50303 | Q34: =+M34+O34 -> 160999.51 | R34: =+N34+P34 -> 197460.02 | S34: =43.5001413553209*1000 -> 43500.141 | T34: 51235.42 | U34: =+Q34+S34 -> 204499.65 | V34: =+R34+T34 -> 248695.44 | W34: =15.3000147648532*1000 -> 15300.015 | X34: 54076 | Y34: =+O34+S34+W34 -> 102300.3 | Z34: =+P34+T34+X34 -> 155614.42 | AA34: =+M34+Y34 -> 219799.67 | AB34: =+N34+Z34 -> 302771.44 | AC34: =48.9995281597563*1000 -> 48999.528 | AD34: 54595 | AE34: =+AA34+AC34 -> 268799.2 | AF34: =+AB34+AD34 -> 357366.44 | AG34: =45.4995884556746*1000 -> 45499.588 | AH34: 61080 | AI34: =+AE34+AG34 -> 314298.79 | AJ34: =+AF34+AH34 -> 418446.44 | AK34: =46.0000542442164*1000 -> 46000.054 | AL34: 52347.66 | AM34: =+AC34+AG34+AK34 -> 140499.17 | AN34: =+AD34+AH34+AL34 -> 168022.66 | AO34: =AI34+AK34 -> 360298.84 | AP34: =AJ34+AL34 -> 470794.1 | AQ34: 48499.665 | AR34: 30958 | AS34: =+AO34+AQ34 -> 408798.5 | AT34: =+AP34+AR34 -> 501752.1 | AU34: 41500.01 | AV34: 16550 | AW34: =+AS34+AU34 -> 450298.51 | AX34: =+AT34+AV34 -> 518302.1 | AY34: 46999.691 | AZ34: =38139.639-111 -> 38028.639 | BA34: =+AQ34+AU34+AY34 -> 136999.37 | BB34: =+AR34+AV34+AZ34 -> 85536.639 | BC34: =AM34+BA34 -> 277498.54 | BD34: =AN34+BB34 -> 253559.3 | BE34: =AW34+AY34 -> 497298.21 | BF34: =AX34+AZ34 -> 556330.74 | BG34: 461999.56 | BH34: 558374.45 | BI34: 592000 | BJ34: 574823.37 | BK34: 595119.91 | BL34: 516406.77 | BM34: 627684.57 | BN34: 533055.82 | BO34: 608495.73 | BP34: 304999.74 | BQ34: 629438.96
B35: 200x280 mm | C35: Mt | D35: 0.40803377 | E35: 0.27340158 | F35: 1625.08 | G35: 0 | H35: 3000 | I35: =+E35+G35 -> 0.27340158 | J35: =+F35+H35 -> 4625.08 | K35: 0 | L35: 1066 | M35: =+E35+G35+K35 -> 0.27340158 | N35: =+F35+H35+L35 -> 5691.08 | O35: 0 | P35: 463 | Q35: =+M35+O35 -> 0.27340158 | R35: =+N35+P35 -> 6154.08 | S35: 0 | T35: 8811.77 | U35: =+Q35+S35 -> 0.27340158 | V35: =+R35+T35 -> 14965.85 | W35: 0 | X35: 1414 | Y35: =+O35+S35+W35 -> 0 | Z35: =+P35+T35+X35 -> 10688.77 | AA35: =+M35+Y35 -> 0.27340158 | AB35: =+N35+Z35 -> 16379.85 | AC35: 0 | AD35: =11175+37 -> 11212 | AE35: =+AA35+AC35 -> 0.27340158 | AF35: =+AB35+AD35 -> 27591.85 | AG35: 0 | AH35: 0 | AI35: =+AE35+AG35 -> 0.27340158 | AJ35: =+AF35+AH35 -> 27591.85 | AK35: 0 | AL35: 703.34 | AM35: =+AC35+AG35+AK35 -> 0 | AN35: =+AD35+AH35+AL35 -> 11915.34 | AO35: =AI35+AK35 -> 0.27340158 | AP35: =AJ35+AL35 -> 28295.19 | AQ35: 0 | AR35: 7040 | AS35: =+AO35+AQ35 -> 0.27340158 | AT35: =+AP35+AR35 -> 35335.19 | AU35: 0 | AV35: 1892 | AW35: =+AS35+AU35 -> 0.27340158 | AX35: =+AT35+AV35 -> 37227.19 | AY35: 0 | AZ35: =4180.26+111 -> 4291.26 | BA35: =+AQ35+AU35+AY35 -> 0 | BB35: =+AR35+AV35+AZ35 -> 13223.26 | BC35: =AM35+BA35 -> 0 | BD35: =AN35+BB35 -> 25138.6 | BE35: =AW35+AY35 -> 0.27340158 | BF35: =AX35+AZ35 -> 41518.45 | BG35: 17999.996 | BH35: 63663.849 | BI35: 57999.916 | BJ35: 101828.14 | BK35: 116079.05 | BL35: 153592.34 | BM35: 204330.35 | BN35: 371378.01 | BO35: 329378.8 | BP35: 267000 | BQ35: 248401
B36: Saleable Semis | C36: Mt | D36: =SUM(D34:D35) -> 350000.4 | E36: =SUM(E34:E35) -> 20999.957 | F36: =SUM(F34:F35) -> 40008.1 | G36: =SUM(G34:G35) -> 48499.577 | H36: =SUM(H34:H35) -> 55556 | I36: =SUM(I34:I35) -> 69499.534 | J36: =SUM(J34:J35) -> 95564.1 | K36: =SUM(K34:K35) -> 48000.111 | ... BF36: =SUM(BF34:BF35) -> 597849.19 | BG36: 479999.56 | BH36: 622038.3 | BI36: 649999.92 | BJ36: 676651.51 | BK36: 711198.96 | BL36: 669999.11 | BM36: 832014.92 | BN36: 904433.83 | BO36: 937874.53 | BP36: =SUM(BP34:BP35) -> 571999.74 | BQ36: =SUM(BQ34:BQ35) -> 877839.96
B37: TOTAL SALEABLE STEEL | C37: Mt | D37: =+D33+D36 -> 2710000.4 | E37: =+E33+E36 -> 181999.96 | F37: =+F33+F36 -> 208718.27 | G37: =+G33+G36 -> 236499.58 | H37: =+H33+H36 -> 228302.58 | I37: =+I33+I36 -> 418499.53 | J37: =+J33+J36 -> 437020.85 | K37: =+K33+K36 -> 229000.11 | ... BF37: =+BF33+BF36 -> 2614650.6 | BG37: 2409999.6 | BH37: 2331824 | BI37: 2524999.9 | BJ37: 2409644.1 | BK37: 2315207.8 | BL37: 2369999.1 | BM37: 2160425.8 | BN37: 2235274.9 | BO37: 1823884.4 | BP37: =+BP33+BP36 -> 2406999.7 | BQ37: =+BQ33+BQ36 -> 2093720.2
B38: SAL STEEL PRODN (CATEGORY WISE)
B39: Wire Rod Plain Coils | C39: Mt | D39: =+D30 -> 520000 | E39: =+E30 -> 36500 | F39: =+WRM!F199 -> 41533 | G39: =+G30 -> 44000 | H39: =+WRM!H199 -> 39351.8 | I39: =+E39+G39 -> 80500 | J39: =+F39+H39 -> 80884.8 | K39: =+K30 -> 42500 | L39: =+WRM!L199 -> 28929.6 | M39: =+E39+G39+K39 -> 123000 | N39: =+F39+H39+L39 -> 109814.4 | O39: =+O30 -> 44000 | P39: =+WRM!P199 -> 35815.55 | Q39: =+M39+O39 -> 167000 | R39: =+N39+P39 -> 145629.95 | S39: =+S30 -> 44000 | T39: =+WRM!T199 -> 38718.35 | U39: =+Q39+S39 -> 211000 | V39: =+R39+T39 -> 184348.3 | W39: =+W30 -> 25000 | X39: =+WRM!X199 -> 41006.15 | Y39: =+O39+S39+W39 -> 113000 | Z39: =+P39+T39+X39 -> 115540.05 | AA39: =+M39+Y39 -> 236000 | AB39: =+N39+Z39 -> 225354.45 | AC39: =+AC30 -> 42500 | AD39: =+WRM!AD199 -> 30034.55 | AE39: =+AA39+AC39 -> 278500 | AF39: =+AB39+AD39 -> 255389 | AG39: =+AG30 -> 42500 | AH39: =+WRM!AH199 -> 34614.25 | AI39: =+AE39+AG39 -> 321000 | AJ39: =+AF39+AH39 -> 290003.25 | AK39: =+AK30 -> 44000 | AL39: =+WRM!AL199 -> 44007.35 | AM39: =+AC39+AG39+AK39 -> 129000 | AN39: =+AD39+AH39+AL39 -> 108656.15 | AO39: =AI39+AK39 -> 365000 | AP39: =AJ39+AL39 -> 334010.6 | AQ39: =+AQ30 -> 44500 | AR39: =+WRM!AR199 -> 44589.55 | AS39: =+AO39+AQ39 -> 409500 | AT39: =+AP39+AR39 -> 378600.15 | AU39: =+AU30 -> 40000 | AV39: =+WRM!AV199 -> 37420.7 | AW39: =+AS39+AU39 -> 449500 | AX39: =+AT39+AV39 -> 416020.85 | AY39: =+AY30 -> 44500 | AZ39: =+WRM!AZ199 -> 46692.85 | BA39: =+AQ39+AU39+AY39 -> 129000 | BB39: =+AR39+AV39+AZ39 -> 128703.1 | BC39: =AM39+BA39 -> 258000 | BD39: =AN39+BB39 -> 237359.25 | BE39: =AW39+AY39 -> 494000 | BF39: =AX39+AZ39 -> 462713.7 | BG39: 500000 | BH39: 459030.64 | BI39: 500000 | BJ39: 471802.34 | BK39: 410762.6 | BL39: =+BL30 -> 500000 | BM39: 456374.84 | BN39: =+BN30 -> 435965.96 | BO39: 333534.61 | BP39: 500000 | BQ39: 270654.57
B40: TMT Coils | C40: Mt | F40: =+WRM!F200 -> 0 | H40: =+WRM!H200 -> 0 | J40: =+F40+H40 -> 0 | L40: =+WRM!L200 -> 9361.75 | N40: =+F40+H40+L40 -> 9361.75 | P40: =+WRM!P200 -> 11248.35 | R40: =+N40+P40 -> 20610.1 | T40: =+WRM!T200 -> 0 | V40: =+R40+T40 -> 20610.1 | X40: =+WRM!X200 -> 0 | Z40: =+P40+T40+X40 -> 11248.35 | AB40: =+N40+Z40 -> 20610.1 | AD40: =+WRM!AD200 -> 0 | AF40: =+AB40+AD40 -> 20610.1 | AH40: =+WRM!AH200 -> 0 | AJ40: =+AF40+AH40 -> 20610.1 | AL40: =+WRM!AL200 -> 0 | AN40: =+AD40+AH40+AL40 -> 0 | AP40: =AJ40+AL40 -> 20610.1 | AR40: =+WRM!AR200 -> 0 | AT40: =+AP40+AR40 -> 20610.1 | AV40: =+WRM!AV200 -> 0 | AX40: =+AT40+AV40 -> 20610.1 | AZ40: =+WRM!AZ200 -> 0 | BA40: =+AQ40+AU40+AY40 -> 0 | BB40: =+AR40+AV40+AZ40 -> 0 | BC40: =AM40+BA40 -> 0 | BD40: =AN40+BB40 -> 0 | BF40: =AX40+AZ40 -> 20610.1 | BH40: 0 | BJ40: 6726.05 | BK40: 55352.05 | BM40: 8968.93 | BO40: 22983.766 | BQ40: 141370.65
B41: TMT Bars | C41: Mt | D41: =+D31 -> 990000 | E41: =+E31 -> 68500 | F41: =+F31 -> 74661.04 | G41: =+G31 -> 79000 | H41: =+H31 -> 76175.635 | I41: =+E41+G41 -> 147500 | J41: =+F41+H41 -> 150836.68 | K41: =+K31 -> 76000 | L41: =+L31 -> 73644.015 | M41: =+E41+G41+K41 -> 223500 | N41: =+F41+H41+L41 -> 224480.69 | O41: =+O31 -> 79000 | P41: =+P31 -> 88056.49 | Q41: =+M41+O41 -> 302500 | R41: =+N41+P41 -> 312537.18 | S41: =+S31 -> 79000 | T41: =+T31 -> 75853.695 | U41: =+Q41+S41 -> 381500 | V41: =+R41+T41 -> 388390.88 | W41: =+W31 -> 47500 | X41: =+X31 -> 76319.035 | Y41: =+O41+S41+W41 -> 205500 | Z41: =+P41+T41+X41 -> 240229.22 | AA41: =+M41+Y41 -> 429000 | AB41: =+N41+Z41 -> 464709.91 | AC41: =+AC31 -> 78000 | AD41: =+AD31 -> 50950.275 | AE41: =+AA41+AC41 -> 507000 | AF41: =+AB41+AD41 -> 515660.19 | AG41: =+AG31 -> 76000 | AH41: =+AH31 -> 69720.765 | AI41: =+AE41+AG41 -> 583000 | AJ41: =+AF41+AH41 -> 585380.95 | AK41: =+AK31 -> 79000 | AL41: =+AL31 -> 81616.765 | AM41: =+AC41+AG41+AK41 -> 233000 | AN41: =+AD41+AH41+AL41 -> 202287.81 | AO41: =AI41+AK41 -> 662000 | AP41: =AJ41+AL41 -> 666997.72 | AQ41: =+AQ31 -> 79000 | AR41: =+AR31 -> 85804.6 | AS41: =+AO41+AQ41 -> 741000 | AT41: =+AP41+AR41 -> 752802.32 | AU41: =+AU31 -> 71500 | AV41: =+AV31 -> 74058.32 | AW41: =+AS41+AU41 -> 812500 | AX41: =+AT41+AV41 -> 826860.64 | AY41: =+AY31 -> 80000 | AZ41: =+AZ31 -> 81200 | BA41: =+AQ41+AU41+AY41 -> 230500 | BB41: =+AR41+AV41+AZ41 -> 241062.92 | BC41: =AM41+BA41 -> 463500 | BD41: =AN41+BB41 -> 443350.73 | BE41: =AW41+AY41 -> 892500 | BF41: =AX41+AZ41 -> 908060.64 | BG41: 870000 | BH41: 750867.85 | BI41: 850000 | BJ41: 795322.27 | BK41: 775906.63 | BL41: 750000 | BM41: 649840.96 | BN41: =+BN31 -> 674875.14 | BO41: 440547.14 | BP41: 800000 | BQ41: 632220.18
B42: NPB | C42: Mt | D42: =+D32 -> 850000 | E42: =+E32 -> 56000 | F42: =+USM!G171 -> 35833.333 | G42: =+G32 -> 65000 | H42: =+USM!I171 -> 44993.634 | I42: =+G42+E42 -> 121000 | J42: =+F42+H42 -> 80826.967 | K42: =+K32 -> 62500 | L42: =+USM!M171 -> 41676.831 | M42: =+K42+G42+E42 -> 183500 | N42: =+F42+H42+L42 -> 122503.8 | O42: =+O32 -> 65000 | P42: =+USM!Q171 -> 39505.728 | Q42: =+M42+O42 -> 248500 | R42: =+N42+P42 -> 162009.53 | S42: =+S32 -> 65000 | T42: =+USM!U171 -> 30061.678 | U42: =+Q42+S42 -> 313500 | V42: =+R42+T42 -> 192071.2 | W42: =+W32 -> 33500 | X42: =+USM!Y171 -> 32261.594 | Y42: =+W42+S42+O42 -> 163500 | Z42: =+P42+T42+X42 -> 101829 | AA42: =+M42+Y42 -> 347000 | AB42: =+N42+Z42 -> 224332.8 | AC42: =+AC32 -> 67000 | AD42: =+USM!AE171 -> 26347.059 | AE42: =+AC42+AA42 -> 414000 | AF42: =+AB42+AD42 -> 250679.86 | AG42: =+AG32 -> 65000 | AH42: =+USM!AI171 -> 33174.987 | AI42: =+AG42+AE42 -> 479000 | AJ42: =+AF42+AH42 -> 283854.84 | AK42: =+AK32 -> 67500 | AL42: =+USM!AM171 -> 34992.378 | AM42: =+AK42+AG42+AC42 -> 199500 | AN42: =+AD42+AH42+AL42 -> 94514.424 | AO42: =AI42+AK42 -> 546500 | AP42: =AJ42+AL42 -> 318847.22 | AQ42: =+AQ32 -> 68000 | AR42: =+USM!AS171 -> 35829.667 | AS42: =+AQ42+AO42 -> 614500 | AT42: =+AP42+AR42 -> 354676.89 | AU42: =+AU32 -> 61000 | AV42: =+USM!AW171 -> 43359.471 | AW42: =+AU42+AS42 -> 675500 | AX42: =+AT42+AV42 -> 398036.36 | AY42: =+AY32 -> 68500 | AZ42: =+USM!BA171 -> 50048.393 | BA42: =+AQ42+AU42+AY42 -> 197500 | BB42: =+AR42+AV42+AZ42 -> 129237.53 | BC42: =AM42+BA42 -> 397000 | BD42: =AN42+BB42 -> 223751.95 | BE42: =AW42+AY42 -> 744000 | BF42: =AX42+AZ42 -> 448084.75 | BG42: 560000 | BH42: 369513.93 | BI42: 525000 | BJ42: 322948.42 | BK42: 273627.65 | BL42: =+BL32 -> 450000 | BM42: 168119.5 | BN42: =+BN32 -> 220000 | BO42: 78790 | BP42: 535000 | BQ42: =+BQ32 -> 171634.81
B43: WPB | C43: Mt | F43: =+USM!G172 -> 8136.526 | H43: =+USM!I172 -> 5159.029 | I43: =+E43+G43 -> 0 | J43: =+F43+H43 -> 13295.555 | L43: =+USM!M172 -> 5963.765 | N43: =+F43+H43+L43 -> 19259.32 | P43: =+USM!Q172 -> 6848.383 | Q43: =+M43+O43 -> 0 | R43: =+N43+P43 -> 26107.703 | T43: =+USM!U172 -> 1438.253 | U43: =+Q43+S43 -> 0 | V43: =+R43+T43 -> 27545.956 | X43: =+USM!Y172 -> 5720.883 | Z43: =+P43+T43+X43 -> 14007.519 | AB43: =+N43+Z43 -> 33266.839 | AD43: =+USM!AE172 -> 0 | AE43: =+AA43+AC43 -> 0 | AF43: =+AB43+AD43 -> 33266.839 | AH43: =+USM!AI172 -> 6170.536 | AI43: =+AE43+AG43 -> 0 | AJ43: =+AF43+AH43 -> 39437.375 | AL43: =+USM!AM172 -> 4072.823 | AN43: =+AD43+AH43+AL43 -> 10243.359 | AO43: =+AK43+AM43 -> 0 | AP43: =AJ43+AL43 -> 43510.198 | AR43: =+USM!AS172 -> 5596.393 | AS43: =+AO43+AQ43 -> 0 | AT43: =+AP43+AR43 -> 49106.591 | AV43: =+USM!AW172 -> 3073.86 | AW43: =+AS43+AU43 -> 0 | AX43: =+AT43+AV43 -> 52180.451 | AZ43: =+USM!BA172 -> 4775.869 | BA43: =+AQ43+AU43+AY43 -> 0 | BB43: =+AR43+AV43+AZ43 -> 13446.122 | BC43: =AM43+BA43 -> 0 | BD43: =AN43+BB43 -> 23689.481 | BE43: =+AY43+BA43 -> 0 | BF43: =AX43+AZ43 -> 56956.32 | BG43: 0 | BH43: 47628.758 | BI43: 0 | BJ43: 47288.061 | BK43: 21791.11
B44: Channels | C44: Mt | F44: =+USM!G173 -> 3735.17 | H44: =+USM!I173 -> 7066.481 | I44: =+E44+G44 -> 0 | J44: =+F44+H44 -> 10801.651 | L44: =+USM!M173 -> 6391.514 | N44: =+F44+H44+L44 -> 17193.165 | P44: =+USM!Q173 -> 8126.569 | Q44: =+M44+O44 -> 0 | R44: =+N44+P44 -> 25319.734 | T44: =+USM!U173 -> 9825.494 | U44: =+Q44+S44 -> 0 | V44: =+R44+T44 -> 35145.228 | X44: =+USM!Y173 -> 9271.39 | Z44: =+P44+T44+X44 -> 27223.453 | AB44: =+N44+Z44 -> 44416.618 | AD44: =+USM!AE173 -> 2320.602 | AE44: =+AA44+AC44 -> 0 | AF44: =+AB44+AD44 -> 46737.22 | AH44: =+USM!AI173 -> 6989.325 | AI44: =+AE44+AG44 -> 0 | AJ44: =+AF44+AH44 -> 53726.545 | AL44: =+USM!AM173 -> 10163.959 | AN44: =+AD44+AH44+AL44 -> 19473.886 | AO44: =+AK44+AM44 -> 0 | AP44: =AJ44+AL44 -> 63890.504 | AR44: =+USM!AS173 -> 7822.952 | AS44: =+AO44+AQ44 -> 0 | AT44: =+AP44+AR44 -> 71713.456 | AV44: =+USM!AW173 -> 7846.067 | AW44: =+AS44+AU44 -> 0 | AX44: =+AT44+AV44 -> 79559.523 | AZ44: =+USM!BA173 -> 4314.13 | BA44: =+AQ44+AU44+AY44 -> 0 | BB44: =+AR44+AV44+AZ44 -> 19983.149 | BC44: =AM44+BA44 -> 0 | BD44: =AN44+BB44 -> 39457.035 | BE44: =+AY44+BA44 -> 0 | BF44: =AX44+AZ44 -> 83873.653 | BG44: 0 | BH44: 81214.697 | BI44: 0 | BJ44: 86018.164 | BK44: 62409.791 | BM44: 44187.11 | BO44: 4414.219
B45: Angles | C45: Mt | F45: =+USM!G174 -> 2238.924 | H45: =+USM!I174 -> 0 | I45: =+E45+G45 -> 0 | J45: =+F45+H45 -> 2238.924 | L45: =+USM!M174 -> 1992.848 | N45: =+F45+H45+L45 -> 4231.772 | P45: =+USM!Q174 -> 0 | Q45: =+M45+O45 -> 0 | R45: =+N45+P45 -> 4231.772 | T45: =+USM!U174 -> 468.21 | U45: =+Q45+S45 -> 0 | V45: =+R45+T45 -> 4699.982 | X45: =+USM!Y174 -> 0 | Z45: =+P45+T45+X45 -> 468.21 | AB45: =+N45+Z45 -> 4699.982 | AD45: =+USM!AE174 -> 0 | AE45: =+AA45+AC45 -> 0 | AF45: =+AB45+AD45 -> 4699.982 | AH45: =+USM!AI174 -> 0 | AI45: =+AE45+AG45 -> 0 | AJ45: =+AF45+AH45 -> 4699.982 | AL45: =+USM!AM174 -> 0 | AN45: =+AD45+AH45+AL45 -> 0 | AO45: =+AK45+AM45 -> 0 | AP45: =AJ45+AL45 -> 4699.982 | AR45: =+USM!AS174 -> 0 | AS45: =+AO45+AQ45 -> 0 | AT45: =+AP45+AR45 -> 4699.982 | AV45: =+USM!AW174 -> 0 | AW45: =+AS45+AU45 -> 0 | AX45: =+AT45+AV45 -> 4699.982 | AZ45: =+USM!BA174 -> 0 | BA45: =+AQ45+AU45+AY45 -> 0 | BB45: =+AR45+AV45+AZ45 -> 0 | BC45: =AM45+BA45 -> 0 | BD45: =AN45+BB45 -> 0 | BE45: =+AY45+BA45 -> 0 | BF45: =AX45+AZ45 -> 4699.982 | BG45: 0 | BH45: 1529.844 | BI45: 0 | BJ45: 2887.321 | BK45: 4159.184 | BM45: 919.55454 | BO45: 5739.5256
B46: Beam | F46: =+USM!G175 -> 1617.461 | H46: 0 | L46: =+USM!M175 -> 0 | N46: =+F46+H46+L46 -> 1617.461 | P46: =+USM!Q175 -> 15.713 | R46: =+N46+P46 -> 1633.174 | T46: =+USM!U175 -> 0 | V46: =+R46+T46 -> 1633.174 | X46: =+USM!Y175 -> 1199.047 | Z46: =+P46+T46+X46 -> 1214.76 | AB46: =+N46+Z46 -> 2832.221 | AD46: =+USM!AE175 -> 992.236 | AF46: =+AB46+AD46 -> 3824.457 | AH46: =+USM!AI175 -> 1383.221 | AJ46: =+AF46+AH46 -> 5207.678 | AL46: =+USM!AM175 -> 3758.02 | AN46: =+AD46+AH46+AL46 -> 6133.477 | AP46: =AJ46+AL46 -> 8965.698 | AR46: =+USM!AS175 -> 2622.34 | AT46: =+AP46+AR46 -> 11588.038 | AV46: =+USM!AW175 -> 0 | AX46: =+AT46+AV46 -> 11588.038 | AZ46: =+USM!BA175 -> 1750.001 | BA46: =+AQ46+AU46+AY46 -> 0 | BB46: =+AR46+AV46+AZ46 -> 4372.341 | BC46: =AM46+BA46 -> 0 | BD46: =AN46+BB46 -> 10505.818 | BE46: =AW46+AY46 -> 0 | BF46: =AX46+AZ46 -> 13338.039
B47: Column | F47: =+USM!G176 -> 954.718 | H47: =+USM!I176 -> 0 | J47: =+USM!K176 -> 954.718 | L47: =+USM!M176 -> 2649.675 | N47: =+USM!O176 -> 3604.393 | P47: =+USM!Q176 -> 2830.994 | R47: =+N47+P47 -> 6435.387 | T47: =+USM!U176 -> 2612.658 | V47: =+R47+T47 -> 9048.045 | X47: =+USM!Y176 -> 1543.802 | Z47: =+P47+T47+X47 -> 6987.454 | AB47: =+N47+Z47 -> 10591.847 | AD47: =+USM!AE176 -> 0 | AF47: =+AB47+AD47 -> 10591.847 | AH47: =+USM!AI176 -> 1341.975 | AJ47: =+AF47+AH47 -> 11933.822 | AL47: =+USM!AM176 -> 0 | AN47: =+AD47+AH47+AL47 -> 1341.975 | AP47: =AJ47+AL47 -> 11933.822 | AR47: =+USM!AS176 -> 4298.626 | AT47: =+AP47+AR47 -> 16232.448 | AV47: =+USM!AW176 -> 0 | AX47: =+AT47+AV47 -> 16232.448 | AZ47: =+USM!BA176 -> 2231.753 | BA47: =+AQ47+AU47+AY47 -> 0 | BB47: =+AR47+AV47+AZ47 -> 6530.379 | BC47: =AM47+BA47 -> 0 | BD47: =AN47+BB47 -> 7872.354 | BE47: =AW47+AY47 -> 0 | BF47: =AX47+AZ47 -> 18464.201
B48: Semis | C48: Mt | D48: =+D36 -> 350000.4 | E48: =+E36 -> 20999.957 | F48: =+F36 -> 40008.1 | G48: =+G36 -> 48499.577 | H48: =+H36 -> 55556 | I48: =+I36 -> 69499.534 | J48: =+J36 -> 95564.1 | K48: =+K36 -> 48000.111 | L48: =+L36 -> 57284 | M48: =+E48+G48+K48 -> 117499.64 | N48: =+F48+H48+L48 -> 152848.1 | O48: =+O36 -> 43500.141 | P48: =+P36 -> 50766 | Q48: =+Q36 -> 160999.79 | R48: =+R36 -> 203614.1 | S48: =+S36 -> 43500.141 | T48: =+T36 -> 60047.19 | U48: =+U36 -> 204499.93 | V48: =+V36 -> 263661.29 | ... AA48: =+AA36 -> 219799.94 | AB48: =+N48+Z48 -> 319151.29 | AC48: =+AC36 -> 48999.528 | AD48: =+AD36 -> 65807 | AE48: =+AE36 -> 268799.47 | AF48: =+AF36 -> 384958.29 | AG48: =+AG36 -> 45499.588 | AH48: =+AH36 -> 61080 | AI48: =+AI36 -> 314299.06 | AJ48: =+AJ36 -> 446038.29 | ... AN48: =+AN36 -> 179938 | AO48: =AI48+AK48 -> 360299.11 | AP48: =AJ48+AL48 -> 499089.29 | AQ48: =+AQ36 -> 48499.665 | AR48: =+AR36 -> 37998 | AS48: =+AS36 -> 408798.78 | AT48: =+AT36 -> 537087.29 | AU48: =+AU36 -> 41500.01 | AV48: =+AV36 -> 18442 | AW48: =+AW36 -> 450298.79 | AX48: =+AX36 -> 555529.29 | ... AZ48: =+AZ36 -> 42319.899 | BA48: =+AQ48+AU48+AY48 -> 136999.37 | BB48: =+AR48+AV48+AZ48 -> 98759.899 | BC48: =AM48+BA48 -> 277498.54 | BD48: =AN48+BB48 -> 278697.9 | BE48: =AW48+AY48 -> 497298.48 | BF48: =AX48+AZ48 -> 597849.19 | BG48: 479999.56 | BH48: 622038.3 | BI48: 649999.92 | BJ48: 676651.51 | BK48: 711198.96 | BL48: 669999.11 | BM48: 832014.92 | BN48: =+BN36 -> 904433.83 | BO48: 937874.53 | BP48: 571999.74 | BQ48: =+BQ36 -> 877839.96
B49: TOTAL SALEABLE STEEL | C49: Mt | D49: =SUM(D39:D48) -> 2710000.4 | E49: =SUM(E39:E48) -> 181999.96 | F49: =SUM(F39:F48) -> 208718.27 | G49: =SUM(G39:G48) -> 236499.58 | H49: =SUM(H39:H48) -> 228302.58 | I49: =SUM(I39:I48) -> 418499.53 | J49: =SUM(J39:J48) -> 435403.39 | K49: =SUM(K39:K48) -> 229000.11 | ... BF49: =SUM(BF39:BF48) -> 2614650.6 | BG49: 2409999.6 | BH49: 2331824 | BI49: 2524999.9 | BJ49: 2409644.1 | BK49: 2315208 | BL49: =SUM(BL39:BL48) -> 2369999.1 | BM49: =SUM(BM39:BM48) -> 2160425.8 | BN49: =SUM(BN39:BN48) -> 2235274.9 | BO49: =SUM(BO39:BO48) -> 1823883.8 | BP49: =SUM(BP39:BP48) -> 2406999.7 | BQ49: =SUM(BQ39:BQ48) -> 2093720.2
B50: COAL TAR | C50: Mt | D50: 42110.938 | E50: 3555.1789 | F50: 3446.42 | G50: 3702.5625 | H50: 3578.13 | I50: =+E50+G50 -> 7257.7414 | J50: =+F50+H50 -> 7024.55 | K50: 3531.525 | L50: 3463.07 | M50: =+E50+G50+K50 -> 10789.266 | N50: =+F50+H50+L50 -> 10487.62 | O50: 3649.2425 | P50: 3586.12 | Q50: =+M50+O50 -> 14438.509 | R50: =+N50+P50 -> 14073.74 | S50: 3649.2425 | T50: 3608.69 | U50: =+Q50+S50 -> 18087.751 | V50: =+R50+T50 -> 17682.43 | W50: 3400.5337 | X50: 3497.87 | Y50: =+O50+S50+W50 -> 10699.019 | Z50: =+P50+T50+X50 -> 10692.68 | AA50: =+M50+Y50 -> 21488.285 | AB50: =+N50+Z50 -> 21180.3 | AC50: 3649.2425 | AD50: 3405.82 | AE50: =+AA50+AC50 -> 25137.528 | AF50: =+AB50+AD50 -> 24586.12 | AG50: 3531.525 | AH50: 3215 | AI50: =+AE50+AG50 -> 28669.053 | AJ50: =+AF50+AH50 -> 27801.12 | AK50: 3649.2425 | AL50: 3251.75 | AM50: =+AC50+AG50+AK50 -> 10830.01 | AN50: =+AD50+AH50+AL50 -> 9872.57 | AO50: =AI50+AK50 -> 32318.295 | AP50: =AJ50+AL50 -> 31052.87 | AQ50: 3649.2425 | AR50: 3434.68 | AS50: =+AO50+AQ50 -> 35967.538 | AT50: =+AP50+AR50 -> 34487.55 | AU50: 3296.09 | AV50: 3170.67 | AW50: =+AS50+AU50 -> 39263.628 | AX50: =+AT50+AV50 -> 37658.22 | AY50: 3649.2425 | AZ50: 3562.08 | BA50: =+AQ50+AU50+AY50 -> 10594.575 | BB50: =+AR50+AV50+AZ50 -> 10167.43 | BC50: =AM50+BA50 -> 21424.585 | BD50: =AN50+BB50 -> 20040 | BE50: =AW50+AY50 -> 42912.87 | BF50: =AX50+AZ50 -> 41220.3 | BG50: 46866.669 | BH50: 43164.837 | BI50: 50890.946 | BJ50: 44869.641 | BK50: 48878.17 | BL50: 51086.383 | BM50: 49592.55 | BN50: 48584.311 | BO50: 46678.95 | BP50: 46118.873 | BQ50: 49237.57
B51: AMMONIUM SULPHATE | C51: Mt | D51: 10785.097 | E51: 917.00899 | F51: 553 | G51: 865.41742 | H51: 488.5 | I51: =+E51+G51 -> 1782.4264 | J51: =+F51+H51 -> 1041.5 | K51: 816.31144 | L51: 494.65 | M51: =+E51+G51+K51 -> 2598.7379 | N51: =+F51+H51+L51 -> 1536.15 | O51: 845.46542 | P51: 717.5 | Q51: =+M51+O51 -> 3444.2033 | R51: =+N51+P51 -> 2253.65 | S51: 845.46542 | T51: 586.55 | U51: =+Q51+S51 -> 4289.6687 | V51: =+R51+T51 -> 2840.2 | W51: 790.46478 | X51: 519.6 | Y51: =+O51+S51+W51 -> 2481.3956 | Z51: =+P51+T51+X51 -> 1823.65 | AA51: =+M51+Y51 -> 5080.1335 | AB51: =+N51+Z51 -> 3359.8 | AC51: 376.59342 | AD51: 502.5 | AE51: =+AA51+AC51 -> 5456.7269 | AF51: =+AB51+AD51 -> 3862.3 | AG51: 452.704 | AH51: 384 | AI51: =+AE51+AG51 -> 5909.4309 | AJ51: =+AF51+AH51 -> 4246.3 | AK51: 845.46542 | AL51: 573.8 | AM51: =+AC51+AG51+AK51 -> 1674.7628 | AN51: =+AD51+AH51+AL51 -> 1460.3 | AO51: =AI51+AK51 -> 6754.8963 | AP51: =AJ51+AL51 -> 4820.1 | AQ51: 845.46542 | AR51: 682.35 | AS51: =+AO51+AQ51 -> 7600.3617 | AT51: =+AP51+AR51 -> 5502.45 | AU51: 758.00348 | AV51: 478.4 | AW51: =+AS51+AU51 -> 8358.3652 | AX51: =+AT51+AV51 -> 5980.85 | AY51: 845.46542 | AZ51: 412.2 | BA51: =+AQ51+AU51+AY51 -> 2448.9343 | BB51: =+AR51+AV51+AZ51 -> 1572.95 | BC51: =AM51+BA51 -> 4123.6972 | BD51: =AN51+BB51 -> 3033.25 | BE51: =AW51+AY51 -> 9203.8306 | BF51: =AX51+AZ51 -> 6393.05 | BG51: 9348.2026 | BH51: 4897.75 | BI51: 8145.2 | BJ51: 16578.809 | BK51: 8876.9 | BL51: 21728.852 | BM51: 10510.61 | BN51: 15654.415 | BO51: 12312.8
B53: Total casts | C53: No | D53: 18060.988 | E53: 1241.6099 | F53: 1418 | G53: 1631.0985 | H53: 1516 | I53: =+E53+G53 -> 2872.7084 | J53: =+F53+H53 -> 2934 | K53: 1580.7365 | L53: 1556 | M53: =+E53+G53+K53 -> 4453.445 | N53: =+F53+H53+L53 -> 4490 | O53: 1599.6223 | P53: 1610 | Q53: =+M53+O53 -> 6053.0673 | R53: =+N53+P53 -> 6100 | S53: 1599.6223 | T53: 1515 | U53: =+Q53+S53 -> 7652.6896 | V53: =+R53+T53 -> 7615 | W53: 839.4712 | X53: 1448 | Y53: =+O53+S53+W53 -> 4038.7158 | Z53: =+P53+T53+X53 -> 4573 | AA53: =+M53+Y53 -> 8492.1608 | AB53: =+N53+Z53 -> 9063 | AC53: 1631.0985 | AD53: 1145 | AE53: =+AA53+AC53 -> 10123.259 | AF53: =+AB53+AD53 -> 10208 | AG53: 1580.7365 | AH53: 1457 | AI53: =+AE53+AG53 -> 11703.996 | AJ53: =+AF53+AH53 -> 11665 | AK53: 1631.0985 | AL53: 1504 | AM53: =+AC53+AG53+AK53 -> 4842.9336 | AN53: =+AD53+AH53+AL53 -> 4106 | AO53: =AI53+AK53 -> 13335.094 | AP53: =AJ53+AL53 -> 13169 | AQ53: 1656.2795 | AR53: 1461 | AS53: =+AO53+AQ53 -> 14991.374 | AT53: =+AP53+AR53 -> 14630 | AU53: 1480.0126 | AV53: 1185 | AW53: =+AS53+AU53 -> 16471.386 | AX53: =+AT53+AV53 -> 15815 | AY53: 1656.2795 | AZ53: 1526 | BA53: =+AQ53+AU53+AY53 -> 4792.5716 | BB53: =+AR53+AV53+AZ53 -> 4172 | BC53: =AM53+BA53 -> 9635.5052 | BD53: =AN53+BB53 -> 8278 | BE53: =AW53+AY53 -> 18127.666 | BF53: =AX53+AZ53 -> 17341 | BG53: 16596.855 | BH53: 15925 | BI53: 16116 | BJ53: 16344.715 | BK53: 14624 | BL53: 15300.817 | BM53: 12158 | BN53: 16891.892 | BO53: 14151
E55: =+E37-E49 -> 0 | F55: =+F37-F49 -> 0 | G55: =+G37-G49 -> 0 | H55: =+H37-H49 -> 0 | I55: =+I37-I49 -> 0 | J55: =+J37-J49 -> 1617.461 | K55: =+K37-K49 -> 0 | L55: =+L37-L49 -> 0 | ... BF55: =+BF37-BF49 -> 0 | BG55: 0 | BH55: 0 | BI55: -0.01296 | BJ55: =+BL37-BL49 -> 0 | BK55: =+BM37-BM49 -> -0.00039024325 | BL55: =+BN37-BN49 -> 0 | BM55: =+BO37-BO49 -> 0.55446018 | BN55: =+BP37-BP49 -> 0 | BO55: =+BQ37-BQ49 -> 0
H60: 230

Sheet Maj Despatch Summ
B1: MAJOR DESPATCH SUMMARY 2025-26 (As per Finance CENVAT report)
E2: 30 | F2: 30 | G2: 31 | H2: 31 | I2: =+G2+E2 -> 61 | J2: =+H2+F2 -> 61 | K2: 30 | L2: 30 | M2: =+E2+G2+K2 -> 91 | N2: =+F2+H2+L2 -> 91 | O2: 31 | P2: 31 | Q2: =+M2+O2 -> 122 | R2: =+N2+P2 -> 122 | S2: 31 | T2: 31 | U2: =+Q2+S2 -> 153 | V2: =+R2+T2 -> 153 | W2: 30 | X2: 30 | Y2: =+O2+S2+W2 -> 92 | Z2: =+P2+T2+X2 -> 92 | AA2: =+M2+Y2 -> 183 | AB2: =+N2+Z2 -> 183 | AC2: 31 | AD2: 31 | AE2: =AA2+AC2 -> 214 | AF2: =AB2+AD2 -> 214 | AG2: 30 | AH2: 30 | AI2: =AE2+AG2 -> 244 | AJ2: =AF2+AH2 -> 244 | AK2: 31 | AL2: 31 | AM2: =+AC2+AG2+AK2 -> 92 | AN2: =+AD2+AH2+AL2 -> 92 | AO2: =AI2+AK2 -> 275 | AP2: =AJ2+AL2 -> 275 | AQ2: 31 | AR2: 31 | AS2: =AO2+AQ2 -> 306 | AT2: =AP2+AR2 -> 306 | AU2: 28 | AV2: 28 | AW2: =AS2+AU2 -> 334 | AX2: =AT2+AV2 -> 334 | AY2: 31 | AZ2: 31 | BA2: =+AQ2+AU2+AY2 -> 90 | BB2: =+AR2+AV2+AZ2 -> 90 | BC2: =AM2+BA2 -> 182 | BD2: =AN2+BB2 -> 182 | BE2: =AW2+AY2 -> 365 | BF2: =AX2+AZ2 -> 365 | BO2: 365 | BP2: 365 | BQ2: 366 | BR2: 366
B3: ITEM | C3: Unit | D3: 2026-27 ABP | E3: Apr'26 | G3: May'25 | I3: 2M | K3: Jun'25 | M3: QTR-1 | O3: Jul'25 | Q3: 4M | S3: Aug'25 | U3: 5M | W3: Sep'25 | Y3: QTR-2 | AA3: H1 | AC3: Oct'25 | AE3: 7M | AG3: Nov'25 | AI3: 8M | AK3: Dec'25 | AM3: QTR-3 | AO3: 9M | AQ3: Jan'26 | AS3: 10M | AU3: Feb'26 | AW3: 11M | AY3: Mar'26 | BA3: QTR-4 | BC3: H2 | BE3: 2025-26 | BG3: 2024-25 | BI3: 2023-24 | BK3: 2022-23 | BM3: 2021-22 | BO3: 2020-21 | BQ3: 2019-20
E4: ABP | F4: ACT | G4: ABP | H4: ACT | I4: ABP | J4: ACT | K4: ABP | L4: ACT | M4: ABP | N4: ACT | O4: ABP | P4: ACT | Q4: ABP | R4: ACT | S4: ABP | T4: ACT | U4: ABP | V4: ACT | W4: ABP | X4: ACT | Y4: ABP | Z4: ACT | AA4: ABP | AB4: ACT | AC4: ABP | AD4: ACT | AE4: ABP | AF4: ACT | AG4: ABP | AH4: ACT | AI4: ABP | AJ4: ACT | AK4: ABP | AL4: ACT | AM4: ABP | AN4: ACT | AO4: ABP | AP4: ACT | AQ4: ABP | AR4: ACT | AS4: ABP | AT4: ACT | AU4: ABP | AV4: ACT | AW4: ABP | AX4: ACT | AY4: ABP | AZ4: ACT | BA4: ABP | BB4: ACT | BC4: ABP | BD4: ACT | BE4: ABP | BF4: ACT | BG4: ABP | BH4: ACT | BI4: ABP | BJ4: ACT | BK4: ABP | BL4: ACT | BM4: ABP | BN4: ACT | BO4: ABP | BP4: ACT | BQ4: ABP | BR4: ACT
B5: Saleable Steel (mill-wise)
B6: MKTG-Plant sales | C6: MT | D6: 16000 | E6: 83 | F6: 5965.35 | G6: 2083.3333 | H6: 2704.95 | I6: =+E6+G6 -> 2166.3333 | J6: =+F6+H6 -> 8670.3 | K6: 2083.3333 | L6: 6803.81 | M6: =+E6+G6+K6 -> 4249.6667 | N6: =+F6+H6+L6 -> 15474.11 | O6: 2083.3333 | P6: 3865.36 | Q6: =+M6+O6 -> 6333 | R6: =+N6+P6 -> 19339.47 | S6: 2083.3333 | T6: 6257.93 | U6: =+Q6+S6 -> 8416.3333 | V6: =+R6+T6 -> 25597.4 | W6: 2083 | X6: 5182.59 | Y6: =+O6+S6+W6 -> 6249.6667 | Z6: =+P6+T6+X6 -> 15305.88 | AA6: =+M6+Y6 -> 10499.333 | AB6: =+N6+Z6 -> 30779.99 | AC6: =83.3333333333333+2000 -> 2083.3333 | AD6: 5221.92 | AE6: =+AA6+AC6 -> 12582.667 | AF6: =+AB6+AD6 -> 36001.91 | AG6: 2083.3333 | AH6: 0 | AI6: =+AE6+AG6 -> 14666 | AJ6: =+AF6+AH6 -> 36001.91 | AK6: 2083.3333 | AL6: 2960.73 | AM6: =+AC6+AG6+AK6 -> 6250 | AN6: =+AD6+AH6+AL6 -> 8182.65 | AO6: =AI6+AK6 -> 16749.333 | AP6: =AJ6+AL6 -> 38962.64 | AQ6: 2083.3333 | AR6: 6204.61 | AS6: =+AO6+AQ6 -> 18832.667 | AT6: =+AP6+AR6 -> 45167.25 | AU6: 2083.3333 | AV6: 3912.15 | AW6: =+AS6+AU6 -> 20916 | AX6: =+AT6+AV6 -> 49079.4 | AY6: 2083.3333 | AZ6: 3740.4 | BA6: =+AQ6+AU6+AY6 -> 6250 | BB6: =+AR6+AV6+AZ6 -> 13857.16 | BC6: =AM6+BA6 -> 12500 | BD6: =AN6+BB6 -> 22039.81 | BE6: =+AW6+AY6 -> 22999.333 | BF6: =+AX6+AZ6 -> 52819.8 | BG6: 21500 | BH6: 53987.54 | BI6: 21500 | BJ6: 30649.84 | BK6: 25500 | BL6: 34807.22 | BM6: 16050 | BN6: 33201.15 | BO6: 0 | BP6: 35268.25 | BQ6: 2000 | BR6: 28405.85
B7: IPT | C7: MT | D7: 0 | E7: 0 | F7: 0 | G7: 0 | H7: 0 | I7: =+E7+G7 -> 0 | J7: =+F7+H7 -> 0 | K7: 0 | L7: 0 | M7: =+E7+G7+K7 -> 0 | N7: =+F7+H7+L7 -> 0 | O7: 0 | P7: 64.1 | Q7: =+M7+O7 -> 0 | R7: =+N7+P7 -> 64.1 | S7: 0 | T7: 1485.16 | U7: =+Q7+S7 -> 0 | V7: =+R7+T7 -> 1549.26 | W7: 0 | X7: 694 | Y7: =+O7+S7+W7 -> 0 | Z7: =+P7+T7+X7 -> 2243.26 | AA7: =+M7+Y7 -> 0 | AB7: =+N7+Z7 -> 2243.26 | AC7: 0 | AD7: 747.82 | AE7: =+AA7+AC7 -> 0 | AF7: =+AB7+AD7 -> 2991.08 | AG7: 0 | AH7: 0 | AI7: =+AE7+AG7 -> 0 | AJ7: =+AF7+AH7 -> 2991.08 | AK7: 0 | AL7: 244.1 | AM7: =+AC7+AG7+AK7 -> 0 | AN7: =+AD7+AH7+AL7 -> 991.92 | AO7: =AI7+AK7 -> 0 | AP7: =AJ7+AL7 -> 3235.18 | AQ7: 0 | AR7: 0 | AS7: =+AO7+AQ7 -> 0 | AT7: =+AP7+AR7 -> 3235.18 | AU7: 0 | AV7: 2333.64 | AW7: =+AS7+AU7 -> 0 | AX7: =+AT7+AV7 -> 5568.82 | AY7: 0 | AZ7: 2066.9 | BA7: =+AQ7+AU7+AY7 -> 0 | BB7: =+AR7+AV7+AZ7 -> 4400.54 | BC7: =AM7+BA7 -> 0 | BD7: =AN7+BB7 -> 5392.46 | BE7: =+AW7+AY7 -> 0 | BF7: =+AX7+AZ7 -> 7635.72 | BG7: 0 | BH7: 322.72 | BI7: 0 | BJ7: 3076.2 | BK7: 123000 | BL7: 42263.08 | BM7: 0 | BN7: 71707.42 | BO7: 10800 | BP7: 9758.51 | BQ7: 24210 | BR7: 5928.095
B8: CMO-WR MILL | C8: MT | D8: 519000 | E8: 36417 | F8: 41076.23 | G8: 43916.667 | H8: 39367.02 | I8: =+E8+G8 -> 80333.667 | J8: =+F8+H8 -> 80443.25 | K8: 42416.667 | L8: 37508.06 | M8: =+E8+G8+K8 -> 122750.33 | N8: =+F8+H8+L8 -> 117951.31 | O8: 43916.667 | P8: 44133.19 | Q8: =+M8+O8 -> 166667 | R8: =+N8+P8 -> 162084.5 | S8: 43916.667 | T8: 40726.54 | U8: =+Q8+S8 -> 210583.67 | V8: =+R8+T8 -> 202811.04 | W8: 24916.667 | X8: 36332.97 | Y8: =+O8+S8+W8 -> 112750 | Z8: =+P8+T8+X8 -> 121192.7 | AA8: =+M8+Y8 -> 235500.33 | AB8: =+N8+Z8 -> 239144.01 | AC8: 42416.667 | AD8: 31032.3 | AE8: =+AA8+AC8 -> 277917 | AF8: =+AB8+AD8 -> 270176.31 | AG8: 42416.667 | AH8: 38334.736 | AI8: =+AE8+AG8 -> 320333.67 | AJ8: =+AF8+AH8 -> 308511.05 | AK8: 43916.667 | AL8: 41187.81 | AM8: =+AC8+AG8+AK8 -> 128750 | AN8: =+AD8+AH8+AL8 -> 110554.85 | AO8: =AI8+AK8 -> 364250.33 | AP8: =AJ8+AL8 -> 349698.86 | AQ8: 44416.667 | AR8: 39752.561 | AS8: =+AO8+AQ8 -> 408667 | AT8: =+AP8+AR8 -> 389451.42 | AU8: 39916.667 | AV8: 41871.84 | AW8: =+AS8+AU8 -> 448583.67 | AX8: =+AT8+AV8 -> 431323.26 | AY8: 44416.667 | AZ8: 48073.32 | BA8: =+AQ8+AU8+AY8 -> 128750 | BB8: =+AR8+AV8+AZ8 -> 129697.72 | BC8: =AM8+BA8 -> 257500 | BD8: =AN8+BB8 -> 240252.57 | BE8: =+AW8+AY8 -> 493000.33 | BF8: =+AX8+AZ8 -> 479396.58 | BG8: 498500 | BH8: 459216.41 | BI8: 498500 | BJ8: 473494.21 | BK8: 498500 | BL8: 453432.75 | BM8: 498500 | BN8: 467953.64 | BO8: 435166.29 | BP8: 351267.02 | BQ8: 498000 | BR8: 399090.26
B9: CMO-BAR MILL | C9: MT | D9: 990000 | E9: 68500 | F9: 78698.73 | G9: 79000 | H9: 67347.9 | I9: =+E9+G9 -> 147500 | J9: =+F9+H9 -> 146046.63 | K9: 76000 | L9: 73175.63 | M9: =+E9+G9+K9 -> 223500 | N9: =+F9+H9+L9 -> 219222.26 | O9: 79000 | P9: 84102.5 | Q9: =+M9+O9 -> 302500 | R9: =+N9+P9 -> 303324.76 | S9: 79000 | T9: 86905.93 | U9: =+Q9+S9 -> 381500 | V9: =+R9+T9 -> 390230.69 | W9: 47500 | X9: 68689.99 | Y9: =+O9+S9+W9 -> 205500 | Z9: =+P9+T9+X9 -> 239698.42 | AA9: =+M9+Y9 -> 429000 | AB9: =+N9+Z9 -> 458920.68 | AC9: 78000 | AD9: 52260.41 | AE9: =+AA9+AC9 -> 507000 | AF9: =+AB9+AD9 -> 511181.09 | AG9: 76000 | AH9: 70091.169 | AI9: =+AE9+AG9 -> 583000 | AJ9: =+AF9+AH9 -> 581272.26 | AK9: 79000 | AL9: 83237.28 | AM9: =+AC9+AG9+AK9 -> 233000 | AN9: =+AD9+AH9+AL9 -> 205588.86 | AO9: =AI9+AK9 -> 662000 | AP9: =AJ9+AL9 -> 664509.54 | AQ9: 79000 | AR9: 79536.07 | AS9: =+AO9+AQ9 -> 741000 | AT9: =+AP9+AR9 -> 744045.61 | AU9: 71500 | AV9: 77559.29 | AW9: =+AS9+AU9 -> 812500 | AX9: =+AT9+AV9 -> 821604.9 | AY9: 80000 | AZ9: 81642.31 | BA9: =+AQ9+AU9+AY9 -> 230500 | BB9: =+AR9+AV9+AZ9 -> 238737.67 | BC9: =AM9+BA9 -> 463500 | BD9: =AN9+BB9 -> 444326.53 | BE9: =+AW9+AY9 -> 892500 | BF9: =+AX9+AZ9 -> 903247.21 | BG9: 870000 | BH9: 750184.19 | BI9: 850000 | BJ9: 781402.45 | BK9: 780000 | BL9: 768402.31 | BM9: 750000 | BN9: 648761.89 | BO9: 674874.74 | BP9: 436958.46 | BQ9: 800000 | BR9: 612890.55
B10: CMO-US MILL | C10: MT | D10: 850000 | E10: 56000 | F10: 50540.923 | G10: 65000 | H10: 57716 | I10: =+E10+G10 -> 121000 | J10: =+F10+H10 -> 108256.92 | K10: 62500 | L10: 56720.68 | M10: =+E10+G10+K10 -> 183500 | N10: =+F10+H10+L10 -> 164977.6 | O10: 65000 | P10: 57264.83 | Q10: =+M10+O10 -> 248500 | R10: =+N10+P10 -> 222242.43 | S10: 65000 | T10: 47224.14 | U10: =+Q10+S10 -> 313500 | V10: =+R10+T10 -> 269466.57 | W10: 33500 | X10: 45948.12 | Y10: =+O10+S10+W10 -> 163500 | Z10: =+P10+T10+X10 -> 150437.09 | AA10: =+M10+Y10 -> 347000 | AB10: =+N10+Z10 -> 315414.69 | AC10: 67000 | AD10: 30215.88 | AE10: =+AA10+AC10 -> 414000 | AF10: =+AB10+AD10 -> 345630.57 | AG10: 65000 | AH10: 49444.75 | AI10: =+AE10+AG10 -> 479000 | AJ10: =+AF10+AH10 -> 395075.32 | AK10: 67500 | AL10: 51538.881 | AM10: =+AC10+AG10+AK10 -> 199500 | AN10: =+AD10+AH10+AL10 -> 131199.51 | AO10: =AI10+AK10 -> 546500 | AP10: =AJ10+AL10 -> 446614.2 | AQ10: 68000 | AR10: 55396.94 | AS10: =+AO10+AQ10 -> 614500 | AT10: =+AP10+AR10 -> 502011.14 | AU10: 61000 | AV10: 53071.49 | AW10: =+AS10+AU10 -> 675500 | AX10: =+AT10+AV10 -> 555082.63 | AY10: 68500 | AZ10: 58800.212 | BA10: =+AQ10+AU10+AY10 -> 197500 | BB10: =+AR10+AV10+AZ10 -> 167268.64 | BC10: =AM10+BA10 -> 397000 | BD10: =AN10+BB10 -> 298468.15 | BE10: =+AW10+AY10 -> 744000 | BF10: =+AX10+AZ10 -> 613882.85 | BG10: 560000 | BH10: 502052.01 | BI10: 525000 | BJ10: 452802.59 | BK10: 470000 | BL10: 357334.79 | BM10: 445000 | BN10: 214319.65 | BO10: 220000 | BP10: 100400.4 | BQ10: 535000 | BR10: 167166.99
B11: CMO-SEMIS | C11: MT | D11: 334999.99 | E11: 20999.684 | F11: 26141.36 | G11: 46499.577 | H11: 50330.16 | I11: =+E11+G11 -> 67499.26 | J11: =+F11+H11 -> 76471.52 | K11: 46000.111 | L11: 44296.21 | M11: =+E11+G11+K11 -> 113499.37 | N11: =+F11+H11+L11 -> 120767.73 | O11: 41500.141 | P11: 54193.85 | Q11: =+M11+O11 -> 154999.51 | R11: =+N11+P11 -> 174961.58 | S11: 41500.141 | T11: 63719.03 | U11: =+Q11+S11 -> 196499.65 | V11: =+R11+T11 -> 238680.61 | W11: 13300.015 | X11: 50417.94 | Y11: =+O11+S11+W11 -> 96300.297 | Z11: =+P11+T11+X11 -> 168330.82 | AA11: =+M11+Y11 -> 209799.67 | AB11: =+N11+Z11 -> 289098.55 | AC11: 46999.528 | AD11: 54079.36 | AE11: =+AA11+AC11 -> 256799.2 | AF11: =+AB11+AD11 -> 343177.91 | AG11: 43499.588 | AH11: 63043.03 | AI11: =+AE11+AG11 -> 300298.79 | AJ11: =+AF11+AH11 -> 406220.94 | AK11: 44000.054 | AL11: 51546.68 | AM11: =+AC11+AG11+AK11 -> 134499.17 | AN11: =+AD11+AH11+AL11 -> 168669.07 | AO11: =AI11+AK11 -> 344298.84 | AP11: =AJ11+AL11 -> 457767.62 | AQ11: 46499.665 | AR11: 35800.43 | AS11: =+AO11+AQ11 -> 390798.5 | AT11: =+AP11+AR11 -> 493568.05 | AU11: 39500.01 | AV11: 12710.87 | AW11: =+AS11+AU11 -> 430298.51 | AX11: =+AT11+AV11 -> 506278.92 | AY11: 45000 | AZ11: 37056.46 | BA11: =+AQ11+AU11+AY11 -> 130999.68 | BB11: =+AR11+AV11+AZ11 -> 85567.76 | BC11: =AM11+BA11 -> 265498.85 | BD11: =AN11+BB11 -> 254236.83 | BE11: =+AW11+AY11 -> 475298.51 | BF11: =+AX11+AZ11 -> 543335.38 | BG11: 459999.54 | BH11: 584980.47 | BI11: 630000.01 | BJ11: 623466.17 | BK11: 513000.01 | BL11: 641816.63 | BM11: 659950.15 | BN11: 742311.77 | BO11: 893633.78 | BP11: 944002.21 | BQ11: 547789.74 | BR11: 836451
B12: TOTAL | C12: MT | D12: =SUM(D6:D11) -> 2710000 | E12: =SUM(E6:E11) -> 181999.68 | F12: =SUM(F6:F11) -> 202422.59 | G12: =SUM(G6:G11) -> 236499.58 | H12: =SUM(H6:H11) -> 217466.03 | I12: =SUM(I6:I11) -> 418499.26 | J12: =SUM(J6:J11) -> 419888.62 | K12: =SUM(K6:K11) -> 229000.11 | ... BF12: =SUM(BF6:BF11) -> 2600317.5 | BG12: 2409999.5 | BH12: 2350743.3 | BI12: 2525000 | BJ12: 2364891.5 | BK12: 2410000 | BL12: 2298056.8 | BM12: 2369500.2 | BN12: 2178255.5 | BO12: 2234474.8 | BP12: 1877654.8 | BQ12: 2406999.7 | BR12: 2049932.7
B13: Consideration in internal consumption | D13: Saleable production Plan: 2410000 (1500 T has been kept in plan for Internal consumption) | E13: Saleable production Plan: 201135 (200 T has been kept in plan for Internal consumption) | G13: Saleable production Plan: 201135 (200 T has been kept in plan for Internal consumption) | K13: Saleable production Plan: 201135 (200 T has been kept in plan for Internal consumption) | O13: Saleable production Plan: 201135 (200 T has been kept in plan for Internal consumption) | S13: Saleable production Plan: 201135 (200 T has been kept in plan for Internal consumption) | W13: Saleable production Plan: 201135 (200 T has been kept in plan for Internal consumption) | AC13: Saleable production Plan: 201135 (200 T has been kept in plan for Internal consumption) | AG13: Saleable production Plan: 201135 (200 T has been kept in plan for Internal consumption) | AK13: Saleable production Plan: 201135 (200 T has been kept in plan for Internal consumption) | AQ13: Saleable production Plan: 201135 (200 T has been kept in plan for Internal consumption) | AU13: Saleable production Plan: 201135 (200 T has been kept in plan for Internal consumption) | AY13: Saleable production Plan: 201135 (200 T has been kept in plan for Internal consumption)
B14: Saleable Steel (Sale type-wise)
B15: IPT | C15: MT | D15: =+D12 -> 2710000 | E15: =+E12 -> 181999.68 | F15: =+F7 -> 0 | G15: =+G12 -> 236499.58 | H15: =+H7 -> 0 | I15: =+E15+G15 -> 418499.26 | J15: =+F15+H15 -> 0 | K15: =+K12 -> 229000.11 | L15: =+L7 -> 0 | M15: =+E15+G15+K15 -> 647499.37 | N15: =+F15+H15+L15 -> 0 | O15: =+O12 -> 231500.14 | P15: =+P7 -> 64.1 | Q15: =+M15+O15 -> 878999.51 | R15: =+N15+P15 -> 64.1 | S15: =+S12 -> 231500.14 | T15: =+T7 -> 1485.16 | U15: =+Q15+S15 -> 1110499.7 | V15: =+R15+T15 -> 1549.26 | W15: =+W12 -> 121299.68 | X15: =+X7 -> 694 | Y15: =+O15+S15+W15 -> 584299.96 | Z15: =+P15+T15+X15 -> 2243.26 | AA15: =+M15+Y15 -> 1231799.3 | AB15: =+N15+Z15 -> 2243.26 | AC15: =+AC12 -> 236499.53 | AD15: =+AD7 -> 747.82 | AE15: =+AA15+AC15 -> 1468298.9 | AF15: =+AB15+AD15 -> 2991.08 | AG15: =+AG12 -> 228999.59 | AH15: =+AH7 -> 0 | AI15: =+AE15+AG15 -> 1697298.5 | AJ15: =+AF15+AH15 -> 2991.08 | AK15: =+AK12 -> 236500.05 | AL15: =+AL7 -> 244.1 | AM15: =+AC15+AG15+AK15 -> 701999.17 | AN15: =+AD15+AH15+AL15 -> 991.92 | AO15: =AI15+AK15 -> 1933798.5 | AP15: =AJ15+AL15 -> 3235.18 | AQ15: =+AQ12 -> 239999.66 | AR15: =+AR7 -> 0 | AS15: =+AO15+AQ15 -> 2173798.2 | AT15: =+AP15+AR15 -> 3235.18 | AU15: =+AU12 -> 214000.01 | AV15: =+AV7 -> 2333.64 | AW15: =+AS15+AU15 -> 2387798.2 | AX15: =+AT15+AV15 -> 5568.82 | AY15: =+AY12 -> 240000 | AZ15: =+AZ7 -> 2066.9 | BA15: =+AQ15+AU15+AY15 -> 693999.68 | BB15: =+AR15+AV15+AZ15 -> 4400.54 | BC15: =+AM15+BA15 -> 1395998.8 | BD15: =AN15+BB15 -> 5392.46 | BE15: =+AW15+AY15 -> 2627798.2 | BF15: =+AX15+AZ15 -> 7635.72 | BG15: 2409999.5 | BH15: 322.72 | BI15: 2525000 | BJ15: 3076.2 | BK15: 2410000 | BL15: 42263.08 | BM15: 2369500.2 | BN15: 71707.42 | BO15: 2234474.8 | BP15: 9758.51 | BQ15: =+BQ12 -> 2406999.7 | BR15: 5928.249
B16: CMO DIR | C16: MT | F16: 118626.72 | H16: 138747.01 | J16: =+F16+H16 -> 257373.73 | L16: 120386.74 | N16: =+F16+H16+L16 -> 377760.47 | P16: 136780.81 | R16: =+N16+P16 -> 514541.28 | T16: 149407.49 | V16: =+R16+T16 -> 663948.77 | X16: 118171.66 | Z16: =+P16+T16+X16 -> 404359.96 | AB16: =+N16+Z16 -> 782120.43 | AD16: 102074.34 | AF16: =+AB16+AD16 -> 884194.77 | AH16: 144101.09 | AJ16: =+AF16+AH16 -> 1028295.9 | AL16: 155324.23 | AN16: =+AD16+AH16+AL16 -> 401499.66 | AP16: =AJ16+AL16 -> 1183620.1 | AR16: 154023.1 | AT16: =+AP16+AR16 -> 1337643.2 | AV16: 143472.91 | AX16: =+AT16+AV16 -> 1481116.1 | AZ16: 163014.04 | BB16: =+AR16+AV16+AZ16 -> 460510.05 | BD16: =AN16+BB16 -> 862009.71 | BF16: =+AX16+AZ16 -> 1644130.1 | BH16: 1620104.9 | BJ16: 1443296 | BL16: 1325226.7 | BN16: 1097093.1 | BP16: 691326.52 | BR16: 569419.83
B17: CMO SYD | C17: MT | F17: 74831.493 | H17: 73085.04 | J17: =+F17+H17 -> 147916.53 | L17: 91277.94 | N17: =+F17+H17+L17 -> 239194.47 | P17: 102874.62 | R17: =+N17+P17 -> 342069.09 | T17: 89009.36 | V17: =+R17+T17 -> 431078.45 | X17: 83127.57 | Z17: =+P17+T17+X17 -> 275011.55 | AB17: =+N17+Z17 -> 514206.02 | AD17: 62676.91 | AF17: =+AB17+AD17 -> 576882.93 | AH17: 73868.745 | AJ17: =+AF17+AH17 -> 650751.68 | AL17: 69474.281 | AN17: =+AD17+AH17+AL17 -> 206019.94 | AP17: =AJ17+AL17 -> 720225.96 | AR17: 53620.361 | AT17: =+AP17+AR17 -> 773846.32 | AV17: 41740.58 | AX17: =+AT17+AV17 -> 815586.9 | AZ17: 59773.862 | BB17: =+AR17+AV17+AZ17 -> 155134.8 | BD17: =AN17+BB17 -> 361154.74 | BF17: =+AX17+AZ17 -> 875360.76 | BH17: 662107.03 | BJ17: 829404.4 | BL17: 809005.31 | BN17: 567271.22 | BP17: 479205.15 | BR17: 909567
B18: MKTG DIR | C18: MT | F18: =+F6 -> 5965.35 | H18: =+H6 -> 2704.95 | J18: =+F18+H18 -> 8670.3 | L18: =+L6 -> 6803.81 | N18: =+F18+H18+L18 -> 15474.11 | P18: =+P6 -> 3865.36 | R18: =+N18+P18 -> 19339.47 | T18: =+T6 -> 6257.93 | V18: =+R18+T18 -> 25597.4 | X18: =+X6 -> 5182.59 | Z18: =+P18+T18+X18 -> 15305.88 | AB18: =+N18+Z18 -> 30779.99 | AD18: =+AD6 -> 5221.92 | AF18: =+AB18+AD18 -> 36001.91 | AH18: =+AH6 -> 0 | AJ18: =+AF18+AH18 -> 36001.91 | AL18: =+AL6 -> 2960.73 | AN18: =+AD18+AH18+AL18 -> 8182.65 | AP18: =AJ18+AL18 -> 38962.64 | AR18: =+AR6 -> 6204.61 | AT18: =+AP18+AR18 -> 45167.25 | AV18: =+AV6 -> 3912.15 | AX18: =+AT18+AV18 -> 49079.4 | AZ18: =+AZ6 -> 3740.4 | BB18: =+AR18+AV18+AZ18 -> 13857.16 | BD18: =AN18+BB18 -> 22039.81 | BF18: =+AX18+AZ18 -> 52819.8 | BH18: 53987.54 | BJ18: 30649.84 | BL18: 34807.22 | BN18: 33201.15 | BP18: 35268.25 | BR18: 28405.85
B19: EXPORT | C19: MT | F19: 2999.03 | H19: 2929.03 | J19: =+F19+H19 -> 5928.06 | L19: 35.9 | N19: =+F19+H19+L19 -> 5963.96 | P19: 38.94 | R19: =+N19+P19 -> 6002.9 | T19: 158.79 | V19: =+R19+T19 -> 6161.69 | X19: 89.79 | Z19: =+P19+T19+X19 -> 287.52 | AB19: =+N19+Z19 -> 6251.48 | AD19: 2836.7 | AF19: =+AB19+AD19 -> 9088.18 | AH19: 2943.85 | AJ19: =+AF19+AH19 -> 12032.03 | AL19: 2712.14 | AN19: =+AD19+AH19+AL19 -> 8492.69 | AP19: =AJ19+AL19 -> 14744.17 | AR19: 2842.54 | AT19: =+AP19+AR19 -> 17586.71 | AV19: 0 | AX19: =+AT19+AV19 -> 17586.71 | AZ19: 2784.4 | BB19: =+AR19+AV19+AZ19 -> 5626.94 | BD19: =AN19+BB19 -> 14119.63 | BF19: =+AX19+AZ19 -> 20371.11 | BH19: 14221 | BJ19: 58464.99 | BL19: 86754.52 | BN19: 408982.58 | BP19: 662096.98 | BR19: 536611.98
B20: % DIRECT (IPT+CMO DIR+ EXPORT+ PLANT SALES) | C20: % | F20: =+((F16+F18+F15+F19)/F12)*100 -> 63.032045 | H20: =+((H16+H18+H15+H19)/H12)*100 -> 66.392434 | J20: =+((+J15+J16+J18+J19)/J12)*100 -> 64.772436 | L20: =+((L16+L18+L15+L19)/L12)*100 -> 58.226038 | N20: =+((+N15+N16+N18+N19)/N12)*100 -> 62.531784 | P20: =+((P16+P18+P15+P19)/P12)*100 -> 57.77317 | R20: =+((+R15+R16+R18+R19)/R12)*100 -> 61.217397 | T20: =+((T16+T18+T15+T19)/T12)*100 -> 63.864153 | V20: =+((+V15+V16+V18+V19)/V12)*100 -> 61.795191 | X20: =+((X16+X18+X15+X19)/X12)*100 -> 59.893216 | Z20: =+((Z16+Z18+Z15+Z19)/Z12)*100 -> 60.555317 | AB20: =+((AB16+AB18+AB15+AB19)/AB12)*100 -> 61.500032 | AD20: =+((AD16+AD18+AD15+AD19)/AD12)*100 -> 63.886988 | AF20: =+((+AF15+AF16+AF18+AF19)/AF12)*100 -> 61.774539 | AH20: =+((AH16+AH18+AH15+AH19)/AH12)*100 -> 66.562169 | AJ20: =+((+AJ15+AJ16+AJ18+AJ19)/AJ12)*100 -> 62.385874 | AL20: =+((AL16+AL18+AL15+AL19)/AL12)*100 -> 69.887465 | AN20: =+((AN16+AN18+AN15+AN19)/AN12)*100 -> 67.046662 | AP20: =+((+AP15+AP16+AP18+AP19)/AP12)*100 -> 63.268546 | AR20: =+((AR16+AR18+AR15+AR19)/AR12)*100 -> 75.254876 | AT20: =+((+AT15+AT16+AT18+AT19)/AT12)*100 -> 64.461359 | AV20: =+((AV16+AV18+AV15+AV19)/AV12)*100 -> 78.198717 | AX20: =+((+AX15+AX16+AX18+AX19)/AX12)*100 -> 65.571622 | AZ20: =+((AZ16+AZ18+AZ15+AZ19)/AZ12)*100 -> 74.166322 | BB20: =+((BB16+BB18+BB15+BB19)/BB12)*100 -> 75.742354 | BD20: =+((BD16+BD18+BD15+BD19)/BD12)*100 -> 71.443815 | BF20: =+((+BF15+BF16+BF18+BF19)/BF12)*100 -> 66.33639 | BH20: 71.834135 | BJ20: 64.928437 | BL20: 64.796113 | BN20: 70.665579 | BP20: =+((BP16+BP18+BP15+BP19)/BP12)*100 -> 74.478558 | BR20: =+((BR16+BR18+BR15+BR19)/BR12)*100 -> 55.62943
B21: Saleable Steel (Shipping Mode-wise)
B22: RAIL | C22: MT | D22: =+D12 -> 2710000 | E22: =+E12 -> 181999.68 | F22: 164894.72 | G22: =+G12 -> 236499.58 | H22: 175451.52 | I22: =+I12 -> 418499.26 | J22: =+F22+H22 -> 340346.24 | K22: =+K12 -> 229000.11 | L22: 185082.04 | M22: =+M12 -> 647499.37 | N22: =+F22+H22+L22 -> 525428.28 | O22: =+O12 -> 231500.14 | P22: 192470.12 | Q22: =+Q12 -> 878999.51 | R22: =+N22+P22 -> 717898.4 | S22: =+S12 -> 231500.14 | T22: 199128.92 | U22: =+U12 -> 1110499.7 | V22: =+R22+T22 -> 917027.32 | W22: =+W12 -> 121299.68 | X22: 164143.06 | Y22: =+Y12 -> 584299.96 | Z22: =+P22+T22+X22 -> 555742.1 | AA22: =+AA12 -> 1231799.3 | AB22: =+N22+Z22 -> 1081170.4 | AC22: =+AC12 -> 236499.53 | AD22: 145794.66 | AE22: =+AE12 -> 1468298.9 | AF22: =+AB22+AD22 -> 1226965 | AG22: =+AG12 -> 228999.59 | AH22: 168162.39 | AI22: =+AI12 -> 1697298.5 | AJ22: =+AF22+AH22 -> 1395127.4 | AK22: =+AK12 -> 236500.05 | AL22: 173711.4 | AM22: =+AM12 -> 701999.17 | AN22: =+AD22+AH22+AL22 -> 487668.45 | AO22: =AI22+AK22 -> 1933798.5 | AP22: =AJ22+AL22 -> 1568838.8 | AQ22: =+AQ12 -> 239999.66 | AR22: 175869.74 | AS22: =+AS12 -> 2173798.2 | AT22: =+AP22+AR22 -> 1744708.6 | AU22: =+AU12 -> 214000.01 | AV22: 153661.52 | AW22: =+AW12 -> 2387798.2 | AX22: =+AT22+AV22 -> 1898370.1 | AY22: =+AY12 -> 240000 | AZ22: 193134.93 | BA22: =+BA12 -> 693999.68 | BB22: =+AR22+AV22+AZ22 -> 522666.19 | BC22: =+BC12 -> 1395998.8 | BD22: =AN22+BB22 -> 1010334.6 | BE22: =+BE12 -> 2627798.2 | BF22: =+AX22+AZ22 -> 2091505 | BG22: 2409999.5 | BH22: 1898391 | BI22: 2525000 | BJ22: 1848504.3 | BK22: 2410000 | BL22: 1959110.7 | BM22: 2369500.2 | BN22: 1882591.4 | BO22: 2234474.8 | BP22: 1557181.9 | BQ22: =+BQ12 -> 2406999.7 | BR22: 1655527.4
B23: ROAD | C23: MT | F23: 37527.87 | H23: 42014.51 | J23: =+F23+H23 -> 79542.38 | L23: 33422.35 | N23: =+F23+H23+L23 -> 112964.73 | P23: 51153.71 | R23: =+N23+P23 -> 164118.44 | T23: 47189.73 | V23: =+R23+T23 -> 211308.17 | X23: 43122.55 | Z23: =+P23+T23+X23 -> 141465.99 | AB23: =+N23+Z23 -> 254430.72 | AD23: 27763.03 | AF23: =+AB23+AD23 -> 282193.75 | AH23: 52751.3 | AJ23: =+AF23+AH23 -> 334945.05 | AL23: 57004.08 | AN23: =+AD23+AH23+AL23 -> 137518.41 | AP23: =AJ23+AL23 -> 391949.13 | AR23: 40820.87 | AT23: =+AP23+AR23 -> 432770 | AV23: 37797.76 | AX23: =+AT23+AV23 -> 470567.76 | AZ23: 38244.77 | BB23: =+AR23+AV23+AZ23 -> 116863.4 | BD23: =AN23+BB23 -> 254381.81 | BF23: =+AX23+AZ23 -> 508812.53 | BH23: 452352.24 | BJ23: 516386.89 | BL23: 338946.25 | BN23: 295664.13 | BP23: 320472.9 | BR23: 394405.54
B24: TOTAL | C24: MT | F24: =SUM(F22:F23) -> 202422.59 | H24: =SUM(H22:H23) -> 217466.03 | J24: =SUM(J22:J23) -> 419888.62 | L24: =SUM(L22:L23) -> 218504.39 | N24: =SUM(N22:N23) -> 638393.01 | P24: =SUM(P22:P23) -> 243623.83 | R24: =SUM(R22:R23) -> 882016.84 | T24: =SUM(T22:T23) -> 246318.65 | V24: =SUM(V22:V23) -> 1128335.5 | X24: =SUM(X22:X23) -> 207265.61 | Z24: =SUM(Z22:Z23) -> 697208.09 | AB24: =SUM(AB22:AB23) -> 1335601.1 | AD24: =SUM(AD22:AD23) -> 173557.69 | AF24: =SUM(AF22:AF23) -> 1509158.8 | AH24: =SUM(AH22:AH23) -> 220913.69 | AJ24: =SUM(AJ22:AJ23) -> 1730072.5 | AL24: =SUM(AL22:AL23) -> 230715.48 | AN24: =SUM(AN22:AN23) -> 625186.86 | AP24: =SUM(AP22:AP23) -> 1960788 | AR24: =SUM(AR22:AR23) -> 216690.61 | AT24: =SUM(AT22:AT23) -> 2177478.6 | AV24: =SUM(AV22:AV23) -> 191459.28 | AX24: =SUM(AX22:AX23) -> 2368937.9 | AZ24: =SUM(AZ22:AZ23) -> 231379.7 | BB24: =SUM(BB22:BB23) -> 639529.59 | BD24: =SUM(BD22:BD23) -> 1264716.4 | BF24: =SUM(BF22:BF23) -> 2600317.6 | BH24: 2350743.2 | BJ24: 2364891.2 | BL24: 2298057 | BN24: =SUM(BN22:BN23) -> 2178255.5 | BP24: 1877654.8 | BR24: =SUM(BR22:BR23) -> 2049932.9
B25: ROAD CO-EFFICIENT (%) | C25: % | F25: =+F23/F24*100 -> 18.539368 | H25: =+H23/H24*100 -> 19.320034 | J25: =+J23/J24*100 -> 18.943685 | L25: =+L23/L24*100 -> 15.295963 | N25: =+N23/N24*100 -> 17.69517 | P25: =+P23/P24*100 -> 20.997006 | R25: =+R23/R24*100 -> 18.607178 | T25: =+T23/T24*100 -> 19.158001 | V25: =+V23/V24*100 -> 18.727424 | X25: =+X23/X24*100 -> 20.805453 | Z25: =+Z23/Z24*100 -> 20.290354 | AB25: =+AB23/AB24*100 -> 19.049903 | AD25: =+AD23/AD24*100 -> 15.996427 | AF25: =+AF23/AF24*100 -> 18.698745 | AH25: =+AH23/AH24*100 -> 23.878693 | AJ25: =+AJ23/AJ24*100 -> 19.360174 | AL25: =+AL23/AL24*100 -> 24.707523 | AN25: =+AN23/AN24*100 -> 21.996369 | AP25: =+AP23/AP24*100 -> 19.989368 | AR25: =+AR23/AR24*100 -> 18.83832 | AT25: =+AT23/AT24*100 -> 19.874822 | AV25: =+AV23/AV24*100 -> 19.741932 | AX25: =+AX23/AX24*100 -> 19.864082 | AZ25: =+AZ23/AZ24*100 -> 16.529008 | BB25: =+BB23/BB24*100 -> 18.273337 | BD25: =+BD23/BD24*100 -> 20.113743 | BF25: =+BF23/BF24*100 -> 19.567323 | BH25: 19.242946 | BJ25: 21.835546 | BL25: 14.749254 | BN25: 13.573438 | BP25: =+BP23/BP24*100 -> 17.067721 | BR25: =+BR23/BR24*100 -> 19.239924
B26: Pig Iron | C26: MT | E26: =+'Maj Production Summ'!E26 -> 1945 | F26: ='Direct sales IPT details'!E97 -> 296.7 | G26: =+'Maj Production Summ'!G26 -> 810 | H26: 2497.59 | I26: =+E26+G26 -> 2755 | J26: =+F26+H26 -> 2794.29 | K26: =+'Maj Production Summ'!K26 -> 810 | L26: 996.79 | M26: =+E26+G26+K26 -> 3565 | N26: =+F26+H26+L26 -> 3791.08 | O26: =+'Maj Production Summ'!O26 -> 810 | P26: 900.29 | Q26: =+M26+O26 -> 4375 | R26: =+N26+P26 -> 4691.37 | S26: =+'Maj Production Summ'!S26 -> 810 | T26: 98.82 | U26: =+Q26+S26 -> 5185 | V26: =+R26+T26 -> 4790.19 | W26: =+'Maj Production Summ'!W26 -> 5360 | X26: 199.97 | Y26: =+O26+S26+W26 -> 6980 | Z26: =+P26+T26+X26 -> 1199.08 | AA26: =+M26+Y26 -> 10545 | AB26: =+N26+Z26 -> 4990.16 | AC26: =+'Maj Production Summ'!AC26 -> 810 | AD26: 696.92 | AE26: =+AA26+AC26 -> 11355 | AF26: =+AB26+AD26 -> 5687.08 | AG26: =+'Maj Production Summ'!AG26 -> 810 | AH26: 1596.1 | AI26: =+AE26+AG26 -> 12165 | AJ26: =+AF26+AH26 -> 7283.18 | AK26: =+'Maj Production Summ'!AK26 -> 810 | AL26: 298.72 | AM26: =+AC26+AG26+AK26 -> 2430 | AN26: =+AD26+AH26+AL26 -> 2591.74 | AO26: =AI26+AK26 -> 12975 | AP26: =AJ26+AL26 -> 7581.9 | AQ26: =+'Maj Production Summ'!AQ26 -> 810 | AR26: 99.25 | AS26: =+AO26+AQ26 -> 13785 | AT26: =+AP26+AR26 -> 7681.15 | AU26: =+'Maj Production Summ'!AU26 -> 810 | AV26: 647.95 | AW26: =+AS26+AU26 -> 14595 | AX26: =+AT26+AV26 -> 8329.1 | AY26: =+'Maj Production Summ'!AY26 -> 810 | AZ26: 99.5 | BA26: =+AQ26+AU26+AY26 -> 2430 | BB26: =+AR26+AV26+AZ26 -> 846.7 | BC26: =AM26+BA26 -> 4860 | BD26: =AN26+BB26 -> 3438.44 | BE26: =+AW26+AY26 -> 15405 | BF26: =+AX26+AZ26 -> 8428.6 | BG26: 9365 | BH26: 8679.79 | BI26: 20742.204 | BJ26: 7537.1 | BK26: 16929.735 | BL26: 8801.74 | BM26: 19251.635 | BN26: 20488.86 | BO26: 20754.645 | BP26: 80002.18 | BQ26: 29958.272 | BR26: 124050.8
B27: PCIS Plant Sales | C27: MT | D27: =+'Maj Production Summ'!D27 -> 5103 | E27: =+'Maj Production Summ'!E27 -> 644.512 | F27: ='Direct sales IPT details'!E45 -> 499.25 | G27: =+'Maj Production Summ'!G27 -> 279.98 | H27: 0 | I27: =+E27+G27 -> 924.492 | J27: =+F27+H27 -> 499.25 | K27: =+'Maj Production Summ'!K27 -> 273.996 | L27: 0 | M27: =+E27+G27+K27 -> 1198.488 | N27: =+F27+H27+L27 -> 499.25 | O27: =+'Maj Production Summ'!O27 -> 276.24 | P27: 996.4 | Q27: =+M27+O27 -> 1474.728 | R27: =+N27+P27 -> 1495.65 | S27: =+'Maj Production Summ'!S27 -> 276.24 | T27: 496.32 | U27: =+Q27+S27 -> 1750.968 | V27: =+R27+T27 -> 1991.97 | W27: =+'Maj Production Summ'!W27 -> 498.97 | X27: 335.17 | Y27: =+O27+S27+W27 -> 1051.45 | Z27: =+P27+T27+X27 -> 1827.89 | AA27: =+M27+Y27 -> 2249.938 | AB27: =+N27+Z27 -> 2327.14 | AC27: =+'Maj Production Summ'!AC27 -> 279.98 | AD27: 162.11 | AE27: =+AA27+AC27 -> 2529.918 | AF27: =+AB27+AD27 -> 2489.25 | AG27: =+'Maj Production Summ'!AG27 -> 273.996 | AH27: 498.65 | AI27: =+AE27+AG27 -> 2803.914 | AJ27: =+AF27+AH27 -> 2987.9 | AK27: =+'Maj Production Summ'!AK27 -> 279.98 | AL27: 1493.55 | AM27: =+AC27+AG27+AK27 -> 833.956 | AN27: =+AD27+AH27+AL27 -> 2154.31 | AO27: =AI27+AK27 -> 3083.894 | AP27: =AJ27+AL27 -> 4481.45 | AQ27: =+'Maj Production Summ'!AQ27 -> 282.972 | AR27: 1497.07 | AS27: =+AO27+AQ27 -> 3366.866 | AT27: =+AP27+AR27 -> 5978.52 | AU27: =+'Maj Production Summ'!AU27 -> 262.028 | AV27: 499.07 | AW27: =+AS27+AU27 -> 3628.894 | AX27: =+AT27+AV27 -> 6477.59 | AY27: =+'Maj Production Summ'!AY27 -> 282.972 | AZ27: 499.56 | BA27: =+AQ27+AU27+AY27 -> 827.972 | BB27: =+AR27+AV27+AZ27 -> 2495.7 | BC27: =AM27+BA27 -> 1661.928 | BD27: =AN27+BB27 -> 4650.01 | BE27: =+AW27+AY27 -> 3911.866 | BF27: =+AX27+AZ27 -> 6977.15 | BG27: 2831.5 | BH27: 5762.52 | BI27: 2236.752 | BJ27: 5991.84 | BK27: 2057.6 | BL27: 5429.83 | BM27: 2163.56 | BN27: 17862.58 | BO27: 6973.7102 | BP27: 29483.78 | BQ27: 8472.5251 | BR27: 59555.1
B28: Total Pig & Pig Equiv | C28: MT | D28: =SUM(D26:D27) -> 5103 | E28: =SUM(E26:E27) -> 2589.512 | F28: =SUM(F26:F27) -> 795.95 | G28: =SUM(G26:G27) -> 1089.98 | H28: =SUM(H26:H27) -> 2497.59 | I28: =SUM(I26:I27) -> 3679.492 | J28: =SUM(J26:J27) -> 3293.54 | K28: =SUM(K26:K27) -> 1083.996 | ... AO28: =SUM(AO26:AO27) -> 16058.894 | AP28: =AJ28+AL28 -> 12063.35 | AQ28: =SUM(AQ26:AQ27) -> 1092.972 | AR28: =SUM(AR26:AR27) -> 1596.32 | AS28: =SUM(AS26:AS27) -> 17151.866 | AT28: =SUM(AT26:AT27) -> 13659.67 | AU28: =SUM(AU26:AU27) -> 1072.028 | AV28: =SUM(AV26:AV27) -> 1147.02 | AW28: =SUM(AW26:AW27) -> 18223.894 | AX28: =SUM(AX26:AX27) -> 14806.69 | ... BB28: =SUM(BB26:BB27) -> 3342.4 | BC28: =AM28+BA28 -> 6521.928 | BD28: =AN28+BB28 -> 8088.45 | BE28: =SUM(BE26:BE27) -> 19316.866 | BF28: =SUM(BF26:BF27) -> 15405.75 | BG28: 12196.5 | BH28: 14442.31 | BI28: 22978.956 | BJ28: 13528.94 | BK28: 18987.335 | BL28: 14231.57 | BM28: 21415.195 | BN28: 38351.44 | BO28: 27728.355 | BP28: 109485.96 | BQ28: =SUM(BQ26:BQ27) -> 38430.797 | BR28: =SUM(BR26:BR27) -> 183605.9

Sheet Maj Techno Summ
B1: MAJOR TECHNO PARAMETERS 2025-2026
D2: 365 | E2: 30 | F2: 30 | G2: 31 | H2: 31 | I2: =+E2+G2 -> 61 | J2: =+F2+H2 -> 61 | K2: 30 | L2: 30 | M2: =+I2+K2 -> 91 | N2: =+J2+L2 -> 91 | O2: 31 | P2: 31 | Q2: =+M2+O2 -> 122 | R2: =+N2+P2 -> 122 | S2: 31 | T2: 31 | U2: =+Q2+S2 -> 153 | V2: =+R2+T2 -> 153 | W2: 30 | X2: 30 | Y2: =+O2+S2+W2 -> 92 | Z2: =+P2+T2+X2 -> 92 | AA2: =+U2+W2 -> 183 | AB2: =+V2+X2 -> 183 | AC2: 31 | AD2: 31 | AE2: =+AA2+AC2 -> 214 | AF2: =+AB2+AD2 -> 214 | AG2: 30 | AH2: 30 | AI2: =+AE2+AG2 -> 244 | AJ2: =+AF2+AH2 -> 244 | AK2: 31 | AL2: 31 | AM2: =+AC2+AG2+AK2 -> 92 | AN2: =+AD2+AH2+AL2 -> 92 | AO2: =+AI2+AK2 -> 275 | AP2: =+AJ2+AL2 -> 275 | AQ2: 31 | AR2: 31 | AS2: =+AO2+AQ2 -> 306 | AT2: =+AP2+AR2 -> 306 | AU2: 28 | AV2: 28 | AW2: =+AS2+AU2 -> 334 | AX2: =+AT2+AV2 -> 334 | AY2: 31 | AZ2: 31 | BA2: =+AQ2+AU2+AY2 -> 90 | BB2: =+AR2+AV2+AZ2 -> 90 | BC2: =+AM2+BA2 -> 182 | BD2: =+AN2+BB2 -> 182 | BE2: =+AW2+AY2 -> 365 | BF2: =+AX2+AZ2 -> 365 | BO2: 365 | BP2: 365 | BQ2: 366 | BR2: 366 | BS2: 365
B3: ITEM | C3: Unit | D3: 2026-27 Norm | E3: Apr'26 | G3: May'25 | I3: 2M | K3: Jun'25 | M3: QTR-1 | O3: Jul'25 | Q3: 4M | S3: Aug'25 | U3: 5M | W3: Sep'25 | Y3: QTR-2 | AA3: H1 | AC3: Oct'25 | AE3: 7M | AG3: Nov'25 | AI3: 8M | AK3: Dec'25 | AM3: QTR-3 | AO3: 9 M | AQ3: Jan'26 | AS3: 10M | AU3: Feb'26 | AW3: 11M | AY3: Mar'26 | BA3: QTR-4 | BC3: H2 | BE3: 2025-26 | BG3: 2024-25 | BI3: 2023-24 | BK3: 2022-23 | BM3: 2021-22 | BO3: 2020-21 | BQ3: 2019-20 | BS3: 2018-19
E4: ABP | F4: ACT | G4: ABP | H4: ACT | I4: ABP | J4: ACT | K4: ABP | L4: ACT | M4: ABP | N4: ACT | O4: ABP | P4: ACT | Q4: ABP | R4: ACT | S4: ABP | T4: ACT | U4: ABP | V4: ACT | W4: ABP | X4: ACT | Y4: ABP | Z4: ACT | AA4: ABP | AB4: ACT | AC4: ABP | AD4: ACT | AE4: ABP | AF4: ACT | AG4: ABP | AH4: ACT | AI4: ABP | AJ4: ACT | AK4: ABP | AL4: ACT | AM4: ABP | AN4: ACT | AO4: ABP | AP4: ACT | AQ4: ABP | AR4: ACT | AS4: ABP | AT4: ACT | AU4: ABP | AV4: ACT | AW4: ABP | AX4: ACT | AY4: ABP | AZ4: ACT | BA4: ABP | BB4: ACT | BC4: ABP | BD4: ACT | BE4: ABP | BF4: ACT | BG4: ABP | BH4: ACT | BI4: ABP | BJ4: ACT | BK4: ABP | BL4: ACT | BM4: ABP | BN4: ACT | BO4: ABP | BP4: ACT | BQ4: ABP | BR4: ACT | BS4: ACT
B5: B.F.Coke Yield | C5: % | D5: 69.5 | E5: =+$D$5 -> 69.5 | F5: =('Maj Production Summ'!F14*100)/('Maj Production Summ'!F10*31.55) -> 69.5 | G5: =+$D$5 -> 69.5 | H5: =('Maj Production Summ'!H14*100)/('Maj Production Summ'!H10*31.55) -> 70 | I5: =+$D$5 -> 69.5 | J5: =('Maj Production Summ'!J14*100)/('Maj Production Summ'!J10*31.55) -> 69.752887 | K5: =+$D$5 -> 69.5 | L5: =('Maj Production Summ'!L14*100)/('Maj Production Summ'!L10*31.55) -> 70 | M5: =+$D$5 -> 69.5 | N5: =('Maj Production Summ'!N14*100)/('Maj Production Summ'!N10*31.55) -> 69.83464 | O5: =+$D$5 -> 69.5 | P5: =('Maj Production Summ'!P14*100)/('Maj Production Summ'!P10*31.55) -> 70 | Q5: =+$D$5 -> 69.5 | R5: =('Maj Production Summ'!R14*100)/('Maj Production Summ'!R10*31.55) -> 69.876938 | S5: =+$D$5 -> 69.5 | T5: =('Maj Production Summ'!T14*100)/('Maj Production Summ'!T10*31.55) -> 70 | U5: =+$D$5 -> 69.5 | V5: =('Maj Production Summ'!V14*100)/('Maj Production Summ'!V10*31.55) -> 69.901907 | W5: =+$D$5 -> 69.5 | X5: =('Maj Production Summ'!X14*100)/('Maj Production Summ'!X10*31.55) -> 69.492954 | Y5: =+$D$5 -> 69.5 | Z5: =('Maj Production Summ'!Z14*100)/('Maj Production Summ'!Z10*31.55) -> 69.834649 | AA5: =+$D$5 -> 69.5 | AB5: =('Maj Production Summ'!AB14*100)/('Maj Production Summ'!AB10*31.55) -> 69.834645 | AC5: =+$D$5 -> 69.5 | AD5: =('Maj Production Summ'!AD14*100)/('Maj Production Summ'!AD10*31.55) -> 69.7 | AE5: =+$D$5 -> 69.5 | AF5: =('Maj Production Summ'!AF14*100)/('Maj Production Summ'!AF10*31.55) -> 69.815352 | AG5: =+$D$5 -> 69.5 | AH5: =('Maj Production Summ'!AH14*100)/('Maj Production Summ'!AH10*31.55) -> 69.5 | AI5: =+$D$5 -> 69.5 | AJ5: =('Maj Production Summ'!AJ14*100)/('Maj Production Summ'!AJ10*31.55) -> 69.776439 | AK5: =+$D$5 -> 69.5 | AL5: =('Maj Production Summ'!AL14*100)/('Maj Production Summ'!AL10*31.55) -> 69.5 | AM5: =+$D$5 -> 69.5 | AN5: =('Maj Production Summ'!AN14*100)/('Maj Production Summ'!AN10*31.55) -> 69.566704 | AO5: =+$D$5 -> 69.5 | AP5: =('Maj Production Summ'!AP14*100)/('Maj Production Summ'!AP10*31.55) -> 69.745156 | AQ5: =+$D$5 -> 69.5 | AR5: =('Maj Production Summ'!AR14*100)/('Maj Production Summ'!AR10*31.55) -> 69.5 | AS5: =+$D$5 -> 69.5 | AT5: =('Maj Production Summ'!AT14*100)/('Maj Production Summ'!AT10*31.55) -> 69.720431 | AU5: =+$D$5 -> 69.5 | AV5: =('Maj Production Summ'!AV14*100)/('Maj Production Summ'!AV10*31.55) -> 69.5 | AW5: =+$D$5 -> 69.5 | AX5: =('Maj Production Summ'!AX14*100)/('Maj Production Summ'!AX10*31.55) -> 69.701999 | AY5: =+$D$5 -> 69.5 | AZ5: =('Maj Production Summ'!AZ14*100)/('Maj Production Summ'!AZ10*31.55) -> 69.5 | BA5: =+$D$5 -> 69.5 | BB5: =('Maj Production Summ'!BB14*100)/('Maj Production Summ'!BB10*31.55) -> 69.5 | BC5: =+$D$5 -> 69.5 | BD5: =('Maj Production Summ'!BD14*100)/('Maj Production Summ'!BD10*31.55) -> 69.533718 | BE5: =+$D$5 -> 69.5 | BF5: =('Maj Production Summ'!BF14*100)/('Maj Production Summ'!BF10*31.55) -> 69.684781 | BG5: 70 | BH5: 70.341275 | BI5: 69.5 | BJ5: 69.398029 | BK5: 69.5 | BL5: 69.459875 | BM5: 70.500003 | BN5: 69.798394 | BO5: 70.999787 | BP5: 72.813877 | BQ5: 66.5 | BR5: 67.48567 | BS5: 67.015011
B6: ICC in Coal Blend
B7: (COB#10) | C7: % | D7: 89 | E7: =+$D$7 -> 89 | F7: ='COKE OVENS'!F145 -> 89 | G7: =+$D$7 -> 89 | H7: ='COKE OVENS'!H145 -> #REF! | I7: =+$D$7 -> 89 | J7: ='COKE OVENS'!J145 -> #REF! | K7: =+$D$7 -> 89 | L7: ='COKE OVENS'!L145 -> #REF! | M7: =+$D$7 -> 89 | N7: ='COKE OVENS'!N145 -> #REF! | O7: =+$D$7 -> 89 | P7: ='COKE OVENS'!P145 -> #REF! | Q7: =+$D$7 -> 89 | R7: ='COKE OVENS'!R145 -> #REF! | S7: =+$D$7 -> 89 | T7: ='COKE OVENS'!T145 -> #REF! | U7: =+$D$7 -> 89 | V7: ='COKE OVENS'!V145 -> #REF! | W7: =+$D$7 -> 89 | X7: ='COKE OVENS'!X145 -> #REF! | Y7: =+$D$7 -> 89 | Z7: ='COKE OVENS'!Z145 -> #REF! | AA7: =+$D$7 -> 89 | AB7: ='COKE OVENS'!AB145 -> #REF! | AC7: =+$D$7 -> 89 | AD7: ='COKE OVENS'!AD145 -> #REF! | AE7: =+$D$7 -> 89 | AF7: ='COKE OVENS'!AF145 -> #REF! | AG7: =+$D$7 -> 89 | AH7: ='COKE OVENS'!AH145 -> #REF! | AI7: =+$D$7 -> 89 | AJ7: ='COKE OVENS'!AJ145 -> #REF! | AK7: =+$D$7 -> 89 | AL7: ='COKE OVENS'!AL145 -> #REF! | AM7: =+$D$7 -> 89 | AN7: ='COKE OVENS'!AN145 -> #REF! | AO7: =+$D$7 -> 89 | AP7: ='COKE OVENS'!AP145 -> #REF! | AQ7: =+$D$7 -> 89 | AR7: ='COKE OVENS'!AR145 -> #REF! | AS7: =+$D$7 -> 89 | AT7: ='COKE OVENS'!AT145 -> #REF! | AU7: =+$D$7 -> 89 | AV7: ='COKE OVENS'!AV145 -> #REF! | AW7: =+$D$7 -> 89 | AX7: ='COKE OVENS'!AX145 -> #REF! | AY7: =+$D$7 -> 89 | AZ7: ='COKE OVENS'!AZ145 -> #REF! | BA7: =+$D$7 -> 89 | BB7: ='COKE OVENS'!BB145 -> #REF! | BC7: =+$D$7 -> 89 | BD7: ='COKE OVENS'!BD145 -> #REF! | BE7: =+$D$7 -> 89 | BF7: ='COKE OVENS'!BF145 -> #REF! | BG7: 95 | BH7: 92.468484 | BI7: 92 | BJ7: 90.939873 | BK7: 92 | BL7: 89.651306 | BM7: 95 | BN7: 93.865972 | BO7: 94.377235 | BP7: 94.02333 | BQ7: 90 | BR7: 91.425995 | BS7: 91.808306
B8: (COB#11) | C8: % | D8: 95 | E8: =+$D$8 -> 95 | F8: ='COKE OVENS'!F170 -> 95 | G8: =+$D$8 -> 95 | H8: ='COKE OVENS'!H170 -> 94.999998 | I8: =+$D$8 -> 95 | J8: ='COKE OVENS'!J170 -> 94.999999 | K8: =+$D$8 -> 95 | L8: ='COKE OVENS'!L170 -> 95 | M8: =+$D$8 -> 95 | N8: ='COKE OVENS'!N170 -> 94.999999 | O8: =+$D$8 -> 95 | P8: ='COKE OVENS'!P170 -> 95.000001 | Q8: =+$D$8 -> 95 | R8: ='COKE OVENS'!R170 -> 95 | S8: =+$D$8 -> 95 | T8: ='COKE OVENS'!T170 -> 95 | U8: =+$D$8 -> 95 | V8: ='COKE OVENS'!V170 -> 95 | W8: =+$D$8 -> 95 | X8: ='COKE OVENS'!X170 -> 95 | Y8: =+$D$8 -> 95 | Z8: ='COKE OVENS'!Z170 -> 95 | AA8: =+$D$8 -> 95 | AB8: ='COKE OVENS'!AB170 -> 95 | AC8: =+$D$8 -> 95 | AD8: ='COKE OVENS'!AD170 -> 95 | AE8: =+$D$8 -> 95 | AF8: ='COKE OVENS'!AF170 -> 95 | AG8: =+$D$8 -> 95 | AH8: ='COKE OVENS'!AH170 -> 95 | AI8: =+$D$8 -> 95 | AJ8: ='COKE OVENS'!AJ170 -> 95 | AK8: =+$D$8 -> 95 | AL8: ='COKE OVENS'!AL170 -> 95 | AM8: =+$D$8 -> 95 | AN8: ='COKE OVENS'!AN170 -> 95 | AO8: =+$D$8 -> 95 | AP8: ='COKE OVENS'!AP170 -> 95 | AQ8: =+$D$8 -> 95 | AR8: ='COKE OVENS'!AR170 -> 95 | AS8: =+$D$8 -> 95 | AT8: ='COKE OVENS'!AT170 -> 95 | AU8: =+$D$8 -> 95 | AV8: ='COKE OVENS'!AV170 -> 95 | AW8: =+$D$8 -> 95 | AX8: ='COKE OVENS'!AX170 -> 95 | AY8: =+$D$8 -> 95 | AZ8: ='COKE OVENS'!AZ170 -> 95 | BA8: =+$D$8 -> 95 | BB8: ='COKE OVENS'!BB170 -> 95 | BC8: =+$D$8 -> 95 | BD8: ='COKE OVENS'!BD170 -> 95 | BE8: =+$D$8 -> 95 | BF8: ='COKE OVENS'!BF170 -> 95 | BG8: 100 | BH8: 97.818139 | BI8: 94 | BJ8: 93.889004 | BK8: 94 | BL8: 92.198587 | BM8: 95 | BN8: 94.753433 | BO8: 94.836589 | BP8: 95.080613 | BQ8: 90 | BR8: 96.370935 | BS8: 94.117213
B9: Overall ICC in Blend | C9: % | D9: 92.972626 | E9: =+$D$9 -> 92.972626 | F9: ='COKE OVENS'!F212 -> 92.889184 | G9: =+$D$9 -> 92.972626 | H9: ='COKE OVENS'!H212 -> 93.667282 | I9: =+$D$9 -> 92.972626 | J9: ='COKE OVENS'!J212 -> 92.876873 | K9: =+$D$9 -> 92.972626 | L9: ='COKE OVENS'!L212 -> 93.437619 | M9: =+$D$9 -> 92.972626 | N9: ='COKE OVENS'!N212 -> 93.068722 | O9: =+$D$9 -> 92.972626 | P9: ='COKE OVENS'!P212 -> 93.966668 | Q9: =+$D$9 -> 92.972626 | R9: ='COKE OVENS'!R212 -> 93.303468 | S9: =+$D$9 -> 92.972626 | T9: ='COKE OVENS'!T212 -> 93.241945 | U9: =+$D$9 -> 92.972626 | V9: ='COKE OVENS'!V212 -> 93.290656 | W9: =+$D$9 -> 92.972626 | X9: ='COKE OVENS'!X212 -> 93.24483 | Y9: =+$D$9 -> 92.972626 | Z9: ='COKE OVENS'!Z212 -> 93.485973 | AA9: =+$D$9 -> 92.972626 | AB9: ='COKE OVENS'!AB212 -> 93.282959 | AC9: =+$D$9 -> 92.972626 | AD9: ='COKE OVENS'!AD212 -> 93.243541 | AE9: =+$D$9 -> 92.972626 | AF9: ='COKE OVENS'!AF212 -> 93.277207 | AG9: =+$D$9 -> 92.972626 | AH9: ='COKE OVENS'!AH212 -> 93.288077 | AI9: =+$D$9 -> 92.972626 | AJ9: ='COKE OVENS'!AJ212 -> 93.278554 | AK9: =+$D$9 -> 92.972626 | AL9: ='COKE OVENS'!AL212 -> 92.364182 | AM9: =+$D$9 -> 92.972626 | AN9: ='COKE OVENS'!AN212 -> 92.961622 | AO9: =+$D$9 -> 92.972626 | AP9: ='COKE OVENS'!AP212 -> 93.174774 | AQ9: =+$D$9 -> 92.972626 | AR9: ='COKE OVENS'!AR212 -> 92.234745 | AS9: =+$D$9 -> 92.972626 | AT9: ='COKE OVENS'!AT212 -> 93.079226 | AU9: =+$D$9 -> 92.972626 | AV9: ='COKE OVENS'!AV212 -> 93.244082 | AW9: =+$D$9 -> 92.972626 | AX9: ='COKE OVENS'!AX212 -> 93.093083 | AY9: =+$D$9 -> 92.972626 | AZ9: ='COKE OVENS'!AZ212 -> 93.243821 | BA9: =+$D$9 -> 92.972626 | BB9: ='COKE OVENS'!BB212 -> 92.898302 | BC9: =+$D$9 -> 92.972626 | BD9: ='COKE OVENS'!BD212 -> 92.930262 | BE9: =+$D$9 -> 92.972626 | BF9: ='COKE OVENS'!BF212 -> 93.10612 | BG9: 98.275343 | BH9: 95.930698 | BI9: 93.289716 | BJ9: 92.83339 | BK9: 93.294359 | BL9: 91.262624 | BM9: 95 | BN9: 94.439237 | BO9: 94.673168 | BP9: 94.71202 | BQ9: 90 | BR9: 94.617133 | BS9: 93.297278
B10: BF Coke Rate | C10: Kg/ THM | D10: 348.374 | E10: 375 | F10: =+('B-FCE'!F23/'Maj Production Summ'!F$17)*1000 -> 383.57168 | G10: 356 | H10: =+('B-FCE'!H23/'Maj Production Summ'!H$17)*1000 -> 345.97012 | I10: =+('B-FCE'!I23/'Maj Production Summ'!I$17)*1000 -> 364.44444 | J10: =+('B-FCE'!J23/'Maj Production Summ'!J$17)*1000 -> 364.05924 | K10: 356 | L10: =+('B-FCE'!L23/'Maj Production Summ'!L$17)*1000 -> 348.40699 | M10: =+('B-FCE'!M23/'Maj Production Summ'!M$17)*1000 -> 361.48889 | N10: =+('B-FCE'!N23/'Maj Production Summ'!N$17)*1000 -> 358.63313 | O10: 356 | P10: =+('B-FCE'!P23/'Maj Production Summ'!P$17)*1000 -> 362.56962 | Q10: =+('B-FCE'!Q23/'Maj Production Summ'!Q$17)*1000 -> 360.05333 | R10: =+('B-FCE'!R23/'Maj Production Summ'!R$17)*1000 -> 359.6655 | S10: 356 | T10: =+('B-FCE'!T23/'Maj Production Summ'!T$17)*1000 -> 365.93798 | U10: =+('B-FCE'!U23/'Maj Production Summ'!U$17)*1000 -> 359.21301 | V10: =+('B-FCE'!V23/'Maj Production Summ'!V$17)*1000 -> 360.91077 | W10: 383 | X10: =+('B-FCE'!X23/'Maj Production Summ'!X$17)*1000 -> 390.38903 | Y10: =+('B-FCE'!Y23/'Maj Production Summ'!Y$17)*1000 -> 361.81538 | Z10: =+('B-FCE'!Z23/'Maj Production Summ'!Z$17)*1000 -> 372.5362 | AA10: =+('B-FCE'!AA23/'Maj Production Summ'!AA$17)*1000 -> 361.6438 | AB10: =+('B-FCE'!AB23/'Maj Production Summ'!AB$17)*1000 -> 365.63228 | AC10: 354 | AD10: =+('B-FCE'!AD23/'Maj Production Summ'!AD$17)*1000 -> 407.03377 | AE10: =+('B-FCE'!AE23/'Maj Production Summ'!AE$17)*1000 -> 360.42454 | AF10: =+('B-FCE'!AF23/'Maj Production Summ'!AF$17)*1000 -> 370.51214 | AG10: 354 | AH10: =+('B-FCE'!AH23/'Maj Production Summ'!AH$17)*1000 -> 366.29801 | AI10: =+('B-FCE'!AI23/'Maj Production Summ'!AI$17)*1000 -> 359.56429 | AJ10: =+('B-FCE'!AJ23/'Maj Production Summ'!AJ$17)*1000 -> 369.98884 | AK10: 354 | AL10: =+('B-FCE'!AL23/'Maj Production Summ'!AL$17)*1000 -> 379.38955 | AM10: =+('B-FCE'!AM23/'Maj Production Summ'!AM$17)*1000 -> 354 | AN10: =+('B-FCE'!AN23/'Maj Production Summ'!AN$17)*1000 -> 382.84533 | AO10: =+('B-FCE'!AO23/'Maj Production Summ'!AO$17)*1000 -> 358.88889 | AP10: =+('B-FCE'!AP23/'Maj Production Summ'!AP$17)*1000 -> 371.0552 | AQ10: 354 | AR10: =+('B-FCE'!AR23/'Maj Production Summ'!AR$17)*1000 -> 385.39817 | AS10: =+('B-FCE'!AS23/'Maj Production Summ'!AS$17)*1000 -> 358.35245 | AT10: =+('B-FCE'!AT23/'Maj Production Summ'!AT$17)*1000 -> 372.48134 | AU10: 354 | AV10: =+('B-FCE'!AV23/'Maj Production Summ'!AV$17)*1000 -> 429.82864 | AW10: =+('B-FCE'!AW23/'Maj Production Summ'!AW$17)*1000 -> 357.96366 | AX10: =+('B-FCE'!AX23/'Maj Production Summ'!AX$17)*1000 -> 376.72077 | AY10: 354 | AZ10: =+('B-FCE'!AZ23/'Maj Production Summ'!AZ$17)*1000 -> 367.13629 | BA10: =+('B-FCE'!BA23/'Maj Production Summ'!BA$17)*1000 -> 354 | BB10: =+('B-FCE'!BB23/'Maj Production Summ'!BB$17)*1000 -> 391.36138 | BC10: =+('B-FCE'!BC23/'Maj Production Summ'!BC$17)*1000 -> 354 | BD10: =+('B-FCE'!BD23/'Maj Production Summ'!BD$17)*1000 -> 387.08692 | BE10: =+('B-FCE'!BE23/'Maj Production Summ'!BE$17)*1000 -> 357.60358 | BF10: =+('B-FCE'!BF23/'Maj Production Summ'!BF$17)*1000 -> 375.89147 | BG10: 360.04562 | BH10: 371.74357 | BI10: 380.42 | BJ10: 390.51224 | BK10: 389.92559 | BL10: 400.04041 | BM10: 377.88521 | BN10: 396.71459 | BO10: 373.87865 | BP10: 423.66105 | BQ10: 370.47898 | BR10: 381.58771 | BS10: 388.39311
B11: Nut Coke rate | C11: Kg/ THM | D11: 27.055333 | E11: 26 | F11: =+('B-FCE'!F24/'Maj Production Summ'!F$17)*1000 -> 31.725019 | G11: 29 | H11: =+('B-FCE'!H24/'Maj Production Summ'!H$17)*1000 -> 29.246391 | I11: =+('B-FCE'!I24/'Maj Production Summ'!I$17)*1000 -> 27.666667 | J11: =+('B-FCE'!J24/'Maj Production Summ'!J$17)*1000 -> 30.438794 | K11: 29 | L11: =+('B-FCE'!L24/'Maj Production Summ'!L$17)*1000 -> 31.876011 | M11: =+('B-FCE'!M24/'Maj Production Summ'!M$17)*1000 -> 28.133333 | N11: =+('B-FCE'!N24/'Maj Production Summ'!N$17)*1000 -> 30.937029 | O11: 29 | P11: =+('B-FCE'!P24/'Maj Production Summ'!P$17)*1000 -> 40.769373 | Q11: =+('B-FCE'!Q24/'Maj Production Summ'!Q$17)*1000 -> 28.36 | R11: =+('B-FCE'!R24/'Maj Production Summ'!R$17)*1000 -> 33.515633 | S11: 29 | T11: =+('B-FCE'!T24/'Maj Production Summ'!T$17)*1000 -> 37.253344 | U11: =+('B-FCE'!U24/'Maj Production Summ'!U$17)*1000 -> 28.492683 | V11: =+('B-FCE'!V24/'Maj Production Summ'!V$17)*1000 -> 34.257675 | W11: 28 | X11: =+('B-FCE'!X24/'Maj Production Summ'!X$17)*1000 -> 36.73382 | Y11: =+('B-FCE'!Y24/'Maj Production Summ'!Y$17)*1000 -> 28.784615 | Z11: =+('B-FCE'!Z24/'Maj Production Summ'!Z$17)*1000 -> 38.320944 | AA11: =+('B-FCE'!AA24/'Maj Production Summ'!AA$17)*1000 -> 28.442336 | AB11: =+('B-FCE'!AB24/'Maj Production Summ'!AB$17)*1000 -> 34.654278 | AC11: 29 | AD11: =+('B-FCE'!AD24/'Maj Production Summ'!AD$17)*1000 -> 30.284128 | AE11: =+('B-FCE'!AE24/'Maj Production Summ'!AE$17)*1000 -> 28.531288 | AF11: =+('B-FCE'!AF24/'Maj Production Summ'!AF$17)*1000 -> 34.139183 | AG11: 29 | AH11: =+('B-FCE'!AH24/'Maj Production Summ'!AH$17)*1000 -> 37.743469 | AI11: =+('B-FCE'!AI24/'Maj Production Summ'!AI$17)*1000 -> 28.594049 | AJ11: =+('B-FCE'!AJ24/'Maj Production Summ'!AJ$17)*1000 -> 34.586757 | AK11: 29 | AL11: =+('B-FCE'!AL24/'Maj Production Summ'!AL$17)*1000 -> 35.629725 | AM11: =+('B-FCE'!AM24/'Maj Production Summ'!AM$17)*1000 -> 29 | AN11: =+('B-FCE'!AN24/'Maj Production Summ'!AN$17)*1000 -> 34.815484 | AO11: =+('B-FCE'!AO24/'Maj Production Summ'!AO$17)*1000 -> 28.643324 | AP11: =+('B-FCE'!AP24/'Maj Production Summ'!AP$17)*1000 -> 34.705065 | AQ11: 29 | AR11: =+('B-FCE'!AR24/'Maj Production Summ'!AR$17)*1000 -> 31.827294 | AS11: =+('B-FCE'!AS24/'Maj Production Summ'!AS$17)*1000 -> 28.682461 | AT11: =+('B-FCE'!AT24/'Maj Production Summ'!AT$17)*1000 -> 34.418925 | AU11: 29 | AV11: =+('B-FCE'!AV24/'Maj Production Summ'!AV$17)*1000 -> 29.819622 | AW11: =+('B-FCE'!AW24/'Maj Production Summ'!AW$17)*1000 -> 28.710825 | AX11: =+('B-FCE'!AX24/'Maj Production Summ'!AX$17)*1000 -> 34.07892 | AY11: 29 | AZ11: =+('B-FCE'!AZ24/'Maj Production Summ'!AZ$17)*1000 -> 32.889139 | BA11: =+('B-FCE'!BA24/'Maj Production Summ'!BA$17)*1000 -> 29 | BB11: =+('B-FCE'!BB24/'Maj Production Summ'!BB$17)*1000 -> 31.643809 | BC11: =+('B-FCE'!BC24/'Maj Production Summ'!BC$17)*1000 -> 29 | BD11: =+('B-FCE'!BD24/'Maj Production Summ'!BD$17)*1000 -> 33.235768 | BE11: =+('B-FCE'!BE24/'Maj Production Summ'!BE$17)*1000 -> 28.737096 | BF11: =+('B-FCE'!BF24/'Maj Production Summ'!BF$17)*1000 -> 33.975974 | BG11: 38.916226 | BH11: 40.499376 | BI11: 32.204286 | BJ11: 47.260949 | BK11: 30 | BL11: 36.610035 | BM11: 23.751425 | BN11: 37.043769 | BO11: 34.857516 | BP11: 41.208946 | BQ11: 25 | BR11: 44.993877 | BS11: 29.180384
B12: CDI rate | C12: Kg/ THM | D12: 149.57067 | E12: 124 | F12: =+('B-FCE'!F25/'Maj Production Summ'!F$17)*1000 -> 125.12614 | G12: 150 | H12: =+('B-FCE'!H25/'Maj Production Summ'!H$17)*1000 -> 155.93209 | I12: =+('B-FCE'!I25/'Maj Production Summ'!I$17)*1000 -> 138.44444 | J12: =+('B-FCE'!J25/'Maj Production Summ'!J$17)*1000 -> 141.11216 | K12: 150 | L12: =+('B-FCE'!L25/'Maj Production Summ'!L$17)*1000 -> 155.24561 | M12: =+('B-FCE'!M25/'Maj Production Summ'!M$17)*1000 -> 142.48889 | N12: =+('B-FCE'!N25/'Maj Production Summ'!N$17)*1000 -> 146.01176 | O12: 150 | P12: =+('B-FCE'!P25/'Maj Production Summ'!P$17)*1000 -> 142.77674 | Q12: =+('B-FCE'!Q25/'Maj Production Summ'!Q$17)*1000 -> 144.45333 | R12: =+('B-FCE'!R25/'Maj Production Summ'!R$17)*1000 -> 145.16335 | S12: 150 | T12: =+('B-FCE'!T25/'Maj Production Summ'!T$17)*1000 -> 141.84997 | U12: =+('B-FCE'!U25/'Maj Production Summ'!U$17)*1000 -> 145.60325 | V12: =+('B-FCE'!V25/'Maj Production Summ'!V$17)*1000 -> 144.50555 | W12: 121 | X12: =+('B-FCE'!X25/'Maj Production Summ'!X$17)*1000 -> 128.55199 | Y12: =+('B-FCE'!Y25/'Maj Production Summ'!Y$17)*1000 -> 143.75385 | Z12: =+('B-FCE'!Z25/'Maj Production Summ'!Z$17)*1000 -> 137.94406 | AA12: =+('B-FCE'!AA25/'Maj Production Summ'!AA$17)*1000 -> 143.08905 | AB12: =+('B-FCE'!AB25/'Maj Production Summ'!AB$17)*1000 -> 141.95028 | AC12: 152 | AD12: =+('B-FCE'!AD25/'Maj Production Summ'!AD$17)*1000 -> 125.46642 | AE12: =+('B-FCE'!AE25/'Maj Production Summ'!AE$17)*1000 -> 144.51043 | AF12: =+('B-FCE'!AF25/'Maj Production Summ'!AF$17)*1000 -> 140.00738 | AG12: 152 | AH12: =+('B-FCE'!AH25/'Maj Production Summ'!AH$17)*1000 -> 136.65061 | AI12: =+('B-FCE'!AI25/'Maj Production Summ'!AI$17)*1000 -> 145.51328 | AJ12: =+('B-FCE'!AJ25/'Maj Production Summ'!AJ$17)*1000 -> 139.59054 | AK12: 152 | AL12: =+('B-FCE'!AL25/'Maj Production Summ'!AL$17)*1000 -> 130.86443 | AM12: =+('B-FCE'!AM25/'Maj Production Summ'!AM$17)*1000 -> 152 | AN12: =+('B-FCE'!AN25/'Maj Production Summ'!AN$17)*1000 -> 131.31828 | AO12: =+('B-FCE'!AO25/'Maj Production Summ'!AO$17)*1000 -> 146.30065 | AP12: =+('B-FCE'!AP25/'Maj Production Summ'!AP$17)*1000 -> 138.6007 | AQ12: 152 | AR12: =+('B-FCE'!AR25/'Maj Production Summ'!AR$17)*1000 -> 129.82366 | AS12: =+('B-FCE'!AS25/'Maj Production Summ'!AS$17)*1000 -> 146.92602 | AT12: =+('B-FCE'!AT25/'Maj Production Summ'!AT$17)*1000 -> 137.72799 | AU12: 152 | AV12: =+('B-FCE'!AV25/'Maj Production Summ'!AV$17)*1000 -> 89.192169 | AW12: =+('B-FCE'!AW25/'Maj Production Summ'!AW$17)*1000 -> 147.37926 | AX12: =+('B-FCE'!AX25/'Maj Production Summ'!AX$17)*1000 -> 134.13995 | AY12: 152 | AZ12: =+('B-FCE'!AZ25/'Maj Production Summ'!AZ$17)*1000 -> 135.42125 | BA12: =+('B-FCE'!BA25/'Maj Production Summ'!BA$17)*1000 -> 152 | BB12: =+('B-FCE'!BB25/'Maj Production Summ'!BB$17)*1000 -> 120.33673 | BC12: =+('B-FCE'!BC25/'Maj Production Summ'!BC$17)*1000 -> 152 | BD12: =+('B-FCE'!BD25/'Maj Production Summ'!BD$17)*1000 -> 125.8487 | BE12: =+('B-FCE'!BE25/'Maj Production Summ'!BE$17)*1000 -> 147.79904 | BF12: =+('B-FCE'!BF25/'Maj Production Summ'!BF$17)*1000 -> 134.25082 | BG12: 140.90981 | BH12: 134.06434 | BI12: 139.6475 | BJ12: 125.94309 | BK12: 129.64578 | BL12: 122.58808 | BM12: 133.64292 | BN12: 118.07599 | BO12: 128.57732 | BP12: 89.175353 | BQ12: 139.85352 | BR12: 118.98027 | BS12: 123.03826
B13: Total Fuel | C13: Kg/ THM | D13: =SUM(D10:D12) -> 525 | E13: =SUM(E10:E12) -> 525 | F13: =SUM(F10:F12) -> 540.42285 | G13: =SUM(G10:G12) -> 535 | H13: =SUM(H10:H12) -> 531.14861 | I13: =SUM(I10:I12) -> 530.55556 | J13: =SUM(J10:J12) -> 535.6102 | K13: =SUM(K10:K12) -> 535 | ... BF13: =SUM(BF10:BF12) -> 544.11826 | BG13: 539.87166 | BH13: 546.30729 | BI13: 552.27179 | BJ13: 563.71628 | BK13: 549.57137 | BL13: 559.23852 | BM13: 535.27955 | BN13: 551.83435 | BO13: 537.31348 | BP13: 554.04535 | BQ13: 535.3325 | BR13: 545.56186 | BS13: 540.61176
B14: BF Productivity | C14: T/M³/Day | D14: 2.4702703 | E14: 2.2528865 | F14: 2.2602394 | G14: 2.4406271 | H14: 2.41734 | I14: =+('Maj Production Summ'!I17/3551)/('B-FCE'!E50+'B-FCE'!G50) -> 2.3534618 | J14: =+('Maj Production Summ'!J17/3551)/('B-FCE'!F50+'B-FCE'!H50) -> 2.3391198 | K14: 2.4471009 | L14: 2.4868497 | M14: =+('Maj Production Summ'!M17/3551)/('B-FCE'!E50+'B-FCE'!G50+'B-FCE'!K50) -> 2.3854092 | N14: =+('Maj Production Summ'!N17/3551)/('B-FCE'!F50+'B-FCE'!H50+'B-FCE'!L50) -> 2.3883034 | O14: 2.3936919 | P14: 2.4358636 | Q14: =+('Maj Production Summ'!Q17/3551)/('B-FCE'!M50+'B-FCE'!O50) -> 2.3875699 | R14: =+('Maj Production Summ'!R17/3551)/('B-FCE'!N50+'B-FCE'!P50) -> 2.4005958 | S14: 2.3936919 | T14: 2.3754677 | U14: =+('Maj Production Summ'!U17/3551)/('B-FCE'!Q50+'B-FCE'!S50) -> 2.3888366 | V14: =+('Maj Production Summ'!V17/3551)/('B-FCE'!R50+'B-FCE'!T50) -> 2.395565 | W14: 2.3168491 | X14: 2.3089599 | Y14: =+('Maj Production Summ'!Y17/3551)/('B-FCE'!P50+'B-FCE'!T50+'B-FCE'!X50) -> 2.0182054 | Z14: =+('Maj Production Summ'!Z17/3551)/('B-FCE'!P50+'B-FCE'!T50+'B-FCE'!X50) -> 2.3743513 | AA14: =+('Maj Production Summ'!AA17/3551)/('B-FCE'!M50+'B-FCE'!Y50) -> 2.3812756 | AB14: =+('Maj Production Summ'!AB17/3551)/('B-FCE'!N50+'B-FCE'!Z50) -> 2.3812592 | AC14: 2.4406271 | AD14: 2.1223596 | AE14: =+('Maj Production Summ'!AE17/3551)/('B-FCE'!AA50+'B-FCE'!AC50) -> 2.3905485 | AF14: =+('Maj Production Summ'!AF17/3551)/('B-FCE'!AB50+'B-FCE'!AD50) -> 2.3475063 | AG14: 2.4471009 | AH14: 2.3620869 | AI14: =+('Maj Production Summ'!AI17/3551)/('B-FCE'!AE50+'B-FCE'!AG50) -> 2.3979688 | AJ14: =+('Maj Production Summ'!AJ17/3551)/('B-FCE'!AF50+'B-FCE'!AH50) -> 2.3493071 | AK14: 2.4406271 | AL14: 2.3077233 | AM14: =+('Maj Production Summ'!AM17/3551)/('B-FCE'!AC50+'B-FCE'!AG50+'B-FCE'!AK50) -> 2.4427365 | AN14: =+('Maj Production Summ'!AN17/3551)/('B-FCE'!AD50+'B-FCE'!AH50+'B-FCE'!AL50) -> 2.2684138 | AO14: =+('Maj Production Summ'!AO17/3551)/('B-FCE'!AK50+'B-FCE'!AI50) -> 2.4030671 | AP14: =+('Maj Production Summ'!AP17/3551)/('B-FCE'!AL50+'B-FCE'!AJ50) -> 2.3445149 | AQ14: 2.4781752 | AR14: 2.2672002 | AS14: =+('Maj Production Summ'!AS17/3551)/('B-FCE'!AO50+'B-FCE'!AQ50) -> 2.4110852 | AT14: =+('Maj Production Summ'!AT17/3551)/('B-FCE'!AP50+'B-FCE'!AR50) -> 2.3365921 | AU14: 2.4614871 | AV14: 2.0074322 | AW14: =+('Maj Production Summ'!AW17/3551)/('B-FCE'!AS50+'B-FCE'!AU50) -> 2.4155033 | AX14: =+('Maj Production Summ'!AX17/3551)/('B-FCE'!AT50+'B-FCE'!AV50) -> 2.308608 | AY14: 2.4781752 | AZ14: 2.3665177 | BA14: =+('Maj Production Summ'!BA17/3551)/('B-FCE'!AQ50+'B-FCE'!AU50+'B-FCE'!AY50) -> 2.4729961 | BB14: =+('Maj Production Summ'!BB17/3551)/('B-FCE'!AR50+'B-FCE'!AV50+'B-FCE'!AZ50) -> 2.2196034 | BC14: =+('Maj Production Summ'!BC17/3551)/('B-FCE'!AM50+'B-FCE'!BA50) -> 2.4576944 | BD14: =+('Maj Production Summ'!BD17/3551)/('B-FCE'!AN50+'B-FCE'!BB50) -> 2.2438374 | BE14: =+('Maj Production Summ'!BE17/3551)/('B-FCE'!AW50+'B-FCE'!AY50) -> 2.4210656 | BF14: =+('Maj Production Summ'!BF17/3551)/('B-FCE'!AX50+'B-FCE'!AZ50) -> 2.3135064 | BG14: 2.3140113 | BH14: 2.2734567 | BI14: 2.2723639 | BJ14: 2.1810142 | BK14: 2.2132463 | BL14: 2.0862545 | BM14: 2.2066158 | BN14: 2.0192263 | BO14: 2.0565754 | BP14: 1.7450413 | BQ14: 2.1585499 | BR14: 2.0057992 | BS14: 1.7419242
B15: Gross Coal to Hot Metal Ratio | C15: Kg/ THM | D15: 859.24202 | E15: 871.2139 | F15: =+'Coal to Hot Metal'!F20 -> 881.94094 | G15: 866.91252 | H15: =+'Coal to Hot Metal'!H20 -> #REF! | I15: =+'Coal to Hot Metal'!I20 -> 871.48255 | J15: =+'Coal to Hot Metal'!J20 -> #REF! | K15: 866.91252 | L15: =+'Coal to Hot Metal'!L20 -> #REF! | M15: =+'Coal to Hot Metal'!M20 -> 871.55702 | N15: =+'Coal to Hot Metal'!N20 -> #REF! | O15: 866.91252 | P15: =+'Coal to Hot Metal'!P20 -> #REF! | Q15: =+((M15*'Maj Production Summ'!M$17)+('Maj Production Summ'!O$17*O15))/('Maj Production Summ'!Q$17) -> 870.34231 | R15: =+'Coal to Hot Metal'!R20 -> #REF! | S15: 866.91252 | T15: =+'Coal to Hot Metal'!T20 -> #REF! | U15: =+((Q15*'Maj Production Summ'!Q$17)+('Maj Production Summ'!S$17*S15))/('Maj Production Summ'!U$17) -> 869.63125 | V15: =+'Coal to Hot Metal'!V20 -> #REF! | W15: 973.86832 | X15: =+'Coal to Hot Metal'!X20 -> #REF! | Y15: =+'Coal to Hot Metal'!Y20 -> 894.94289 | Z15: =+'Coal to Hot Metal'!Z20 -> #REF! | AA15: =+((M15*'Maj Production Summ'!M$17)+('Maj Production Summ'!Y$17*Y15))/('Maj Production Summ'!AA$17) -> 882.65251 | AB15: =+'Coal to Hot Metal'!AB20 -> #REF! | AC15: 865.57463 | AD15: =+'Coal to Hot Metal'!AD20 -> #REF! | AE15: =+((AA15*'Maj Production Summ'!AA$17)+('Maj Production Summ'!AC$17*AC15))/('Maj Production Summ'!AE$17) -> 879.92843 | AF15: =+'Coal to Hot Metal'!AF20 -> #REF! | AG15: 865.57463 | AH15: =+'Coal to Hot Metal'!AH20 -> #REF! | AI15: =+((AE15*'Maj Production Summ'!AE$17)+('Maj Production Summ'!AG$17*AG15))/('Maj Production Summ'!AI$17) -> 878.00646 | AJ15: =+'Coal to Hot Metal'!AJ20 -> #REF! | AK15: 865.57463 | AL15: =+'Coal to Hot Metal'!AL20 -> #REF! | AM15: =+'Coal to Hot Metal'!AM20 -> 870.3318 | AN15: =+'Coal to Hot Metal'!AN20 -> #REF! | AO15: =+'Coal to Hot Metal'!AO20 -> 878.21199 | AP15: =+'Coal to Hot Metal'!AP20 -> #REF! | AQ15: 865.57463 | AR15: =+'Coal to Hot Metal'!AR20 -> #REF! | AS15: =+((AO15*'Maj Production Summ'!AO$17)+('Maj Production Summ'!AQ$17*AQ15))/('Maj Production Summ'!AS$17) -> 876.82535 | AT15: =+'Coal to Hot Metal'!AT20 -> #REF! | AU15: 865.57463 | AV15: =+'Coal to Hot Metal'!AV20 -> #REF! | AW15: =+((AS15*'Maj Production Summ'!AS$17)+('Maj Production Summ'!AU$17*AU15))/('Maj Production Summ'!AW$17) -> 875.82036 | AX15: =+'Coal to Hot Metal'!AX20 -> #REF! | AY15: 865.57463 | AZ15: =+'Coal to Hot Metal'!AZ20 -> #REF! | BA15: =+'Coal to Hot Metal'!BA20 -> 870.3318 | BB15: =+'Coal to Hot Metal'!BB20 -> #REF! | BC15: =+'Coal to Hot Metal'!BC20 -> 870.3318 | BD15: =+'Coal to Hot Metal'!BD20 -> #REF! | BE15: =+'Coal to Hot Metal'!BE20 -> 876.14025 | BF15: =+'Coal to Hot Metal'!BF20 -> #REF! | BG15: 879.87436 | BH15: 887.52975 | BI15: 900.75554 | BJ15: 932.03785 | BK15: 910.43802 | BL15: 930.86111 | BM15: 908.3767 | BN15: 935.21205 | BO15: 907.50854 | BP15: 991.44637 | BQ15: 886.42712 | BR15: 931.68363 | BS15: 905.6097
B16: Hot Metal to Crude Steel | C16: Kg/ TCS | D16: 1062 | E16: =+$D$16 -> 1062 | F16: =+(F56/'Maj Production Summ'!F18)*1000 -> 1055.9173 | G16: =+$D$16 -> 1062 | H16: =+(H56/'Maj Production Summ'!H18)*1000 -> 1067.8205 | I16: =+$D$16 -> 1062 | J16: =+(J56/'Maj Production Summ'!J18)*1000 -> 1062.0425 | K16: =+$D$16 -> 1062 | L16: =+(L56/'Maj Production Summ'!L18)*1000 -> 1061.9197 | M16: =+$D$16 -> 1062 | N16: =+(N56/'Maj Production Summ'!N18)*1000 -> 1062 | O16: =+$D$16 -> 1062 | P16: =+(P56/'Maj Production Summ'!P18)*1000 -> 1051.7069 | Q16: =+$D$16 -> 1062 | R16: =+(R56/'Maj Production Summ'!R18)*1000 -> 1059.2716 | S16: =+$D$16 -> 1062 | T16: =+(T56/'Maj Production Summ'!T18)*1000 -> 1060.1658 | U16: =+$D$16 -> 1062 | V16: =+(V56/'Maj Production Summ'!V18)*1000 -> 1059.4495 | W16: =+$D$16 -> 1062 | X16: =+(X56/'Maj Production Summ'!X18)*1000 -> 1063.8153 | Y16: =+$D$16 -> 1062 | Z16: =+(Z56/'Maj Production Summ'!Z18)*1000 -> 1058.3307 | AA16: =+$D$16 -> 1062 | AB16: =+(AB56/'Maj Production Summ'!AB18)*1000 -> 1060.1462 | AC16: =+$D$16 -> 1062 | AD16: =+(AD56/'Maj Production Summ'!AD18)*1000 -> 1064.5745 | AE16: =+$D$16 -> 1062 | AF16: =+(AF56/'Maj Production Summ'!AF18)*1000 -> 1060.642 | AG16: =+$D$16 -> 1062 | AH16: =+(AH56/'Maj Production Summ'!AH18)*1000 -> 1059.8754 | AI16: =+$D$16 -> 1062 | AJ16: =+(AJ56/'Maj Production Summ'!AJ18)*1000 -> 1060.5459 | AK16: =+$D$16 -> 1062 | AL16: =+(AL56/'Maj Production Summ'!AL18)*1000 -> 1068.1895 | AM16: =+$D$16 -> 1062 | AN16: =+(AN56/'Maj Production Summ'!AN18)*1000 -> 1064.215 | AO16: =+$D$16 -> 1062 | AP16: =+(AP56/'Maj Production Summ'!AP18)*1000 -> 1061.4136 | AQ16: =+$D$16 -> 1062 | AR16: =+(AR56/'Maj Production Summ'!AR18)*1000 -> 1062.1673 | AS16: =+$D$16 -> 1062 | AT16: =+(AT56/'Maj Production Summ'!AT18)*1000 -> 1061.4886 | AU16: =+$D$16 -> 1062 | AV16: =+(AV56/'Maj Production Summ'!AV18)*1000 -> 1052.2391 | AW16: =+$D$16 -> 1062 | AX16: =+(AX56/'Maj Production Summ'!AX18)*1000 -> 1060.7978 | AY16: =+$D$16 -> 1062 | AZ16: =+(AZ56/'Maj Production Summ'!AZ18)*1000 -> 1038.4428 | BA16: =+$D$16 -> 1062 | BB16: =+(BB56/'Maj Production Summ'!BB18)*1000 -> 1050.6128 | BC16: =+$D$16 -> 1062 | BD16: =+(BD56/'Maj Production Summ'!BD18)*1000 -> 1057.355 | BE16: =+$D$16 -> 1062 | BF16: =+(BF56/'Maj Production Summ'!BF18)*1000 -> 1058.8143 | BG16: 1060 | BH16: 1059.546 | BI16: 1060 | BJ16: 1066.0114 | BK16: 1062 | BL16: 1062.9741 | BM16: 1064.9999 | BN16: 1062.0577 | BO16: 1077.0434 | BP16: 1071.1761 | BQ16: 1065 | BR16: 1093.6626 | BS16: 1078.33
B17: Scrap consumption | C17: Kg/ TCS | D17: 34 | E17: =+$D$17 -> 34 | F17: =+(F57/'Maj Production Summ'!F18)*1000 -> 40.079113 | G17: =+$D$17 -> 34 | H17: =+(H57/'Maj Production Summ'!H18)*1000 -> 28.189893 | I17: =+$D$17 -> 34 | J17: =+(J57/'Maj Production Summ'!J18)*1000 -> 33.961128 | K17: =+$D$17 -> 34 | L17: =+(L57/'Maj Production Summ'!L18)*1000 -> 34.520832 | M17: =+$D$17 -> 34 | N17: =+(N57/'Maj Production Summ'!N18)*1000 -> 34.154869 | O17: =+$D$17 -> 34 | P17: =+(P57/'Maj Production Summ'!P18)*1000 -> 44.526181 | Q17: =+$D$17 -> 34 | R17: =+(R57/'Maj Production Summ'!R18)*1000 -> 36.903945 | S17: =+$D$17 -> 34 | T17: =+(T57/'Maj Production Summ'!T18)*1000 -> 36.183939 | U17: =+$D$17 -> 34 | V17: =+(V57/'Maj Production Summ'!V18)*1000 -> 36.760726 | W17: =+$D$17 -> 34 | X17: =+(X57/'Maj Production Summ'!X18)*1000 -> 34.040565 | Y17: =+$D$17 -> 34 | Z17: =+(Z57/'Maj Production Summ'!Z18)*1000 -> 38.453569 | AA17: =+$D$17 -> 34 | AB17: =+(AB57/'Maj Production Summ'!AB18)*1000 -> 36.326619 | AC17: =+$D$17 -> 34 | AD17: =+(AD57/'Maj Production Summ'!AD18)*1000 -> 30.862551 | AE17: =+$D$17 -> 34 | AF17: =+(AF57/'Maj Production Summ'!AF18)*1000 -> 35.714888 | AG17: =+$D$17 -> 34 | AH17: =+(AH57/'Maj Production Summ'!AH18)*1000 -> 36.486828 | AI17: =+$D$17 -> 34 | AJ17: =+(AJ57/'Maj Production Summ'!AJ18)*1000 -> 35.81169 | AK17: =+$D$17 -> 34 | AL17: =+(AL57/'Maj Production Summ'!AL18)*1000 -> 27.934205 | AM17: =+$D$17 -> 34 | AN17: =+(AN57/'Maj Production Summ'!AN18)*1000 -> 31.802547 | AO17: =+$D$17 -> 34 | AP17: =+(AP57/'Maj Production Summ'!AP18)*1000 -> 34.917433 | AQ17: =+$D$17 -> 34 | AR17: =+(AR57/'Maj Production Summ'!AR18)*1000 -> 33.233062 | AS17: =+$D$17 -> 34 | AT17: =+(AT57/'Maj Production Summ'!AT18)*1000 -> 34.749885 | AU17: =+$D$17 -> 34 | AV17: =+(AV57/'Maj Production Summ'!AV18)*1000 -> 43.482726 | AW17: =+$D$17 -> 34 | AX17: =+(AX57/'Maj Production Summ'!AX18)*1000 -> 35.402019 | AY17: =+$D$17 -> 34 | AZ17: =+(AZ57/'Maj Production Summ'!AZ18)*1000 -> 54.990466 | BA17: =+(BA57/'Maj Production Summ'!BA18)*1000 -> 34 | BB17: =+(BB57/'Maj Production Summ'!BB18)*1000 -> 44.153244 | BC17: =+(BC57/'Maj Production Summ'!BC18)*1000 -> 34 | BD17: =+(BD57/'Maj Production Summ'!BD18)*1000 -> 38.031373 | BE17: =+(BE57/'Maj Production Summ'!BE18)*1000 -> 34 | BF17: =+(BF57/'Maj Production Summ'!BF18)*1000 -> 37.140096 | BG17: 40 | BH17: 37.680158 | BI17: 40 | BJ17: 34.431041 | BK17: 46 | BL17: 38.506405 | BM17: 50 | BN17: 45.611233 | BO17: 40.465028 | BP17: 41.122433 | BQ17: 50 | BR17: 25.532166 | BS17: 41.130412
B18: TMI | C18: Kg/ TCS | D18: =SUM(D16:D17) -> 1096 | E18: =+$D$18 -> 1096 | F18: =SUM(F16:F17) -> 1095.9964 | G18: =+$D$18 -> 1096 | H18: =SUM(H16:H17) -> 1096.0104 | I18: =+$D$18 -> 1096 | J18: =SUM(J16:J17) -> 1096.0036 | K18: =+$D$18 -> 1096 | L18: =SUM(L16:L17) -> 1096.4405 | M18: =+$D$18 -> 1096 | N18: =SUM(N16:N17) -> 1096.1548 | O18: =+$D$18 -> 1096 | P18: =SUM(P16:P17) -> 1096.2331 | Q18: =+$D$18 -> 1096 | R18: =SUM(R16:R17) -> 1096.1756 | S18: =+$D$18 -> 1096 | T18: =SUM(T16:T17) -> 1096.3497 | U18: =+$D$18 -> 1096 | V18: =SUM(V16:V17) -> 1096.2102 | W18: =+$D$18 -> 1096 | X18: =SUM(X16:X17) -> 1097.8558 | Y18: =+$D$18 -> 1096 | Z18: =SUM(Z16:Z17) -> 1096.7843 | AA18: =+$D$18 -> 1096 | AB18: =SUM(AB16:AB17) -> 1096.4728 | AC18: =+$D$18 -> 1096 | AD18: =SUM(AD16:AD17) -> 1095.4371 | AE18: =+$D$18 -> 1096 | AF18: =SUM(AF16:AF17) -> 1096.3569 | AG18: =+$D$18 -> 1096 | AH18: =SUM(AH16:AH17) -> 1096.3623 | AI18: =+$D$18 -> 1096 | AJ18: =SUM(AJ16:AJ17) -> 1096.3576 | AK18: =+$D$18 -> 1096 | AL18: =SUM(AL16:AL17) -> 1096.1237 | AM18: =+$D$18 -> 1096 | AN18: =SUM(AN16:AN17) -> 1096.0175 | AO18: =+$D$18 -> 1096 | AP18: =SUM(AP16:AP17) -> 1096.331 | AQ18: =+$D$18 -> 1096 | AR18: =SUM(AR16:AR17) -> 1095.4004 | AS18: =+$D$18 -> 1096 | AT18: =SUM(AT16:AT17) -> 1096.2384 | AU18: =+$D$18 -> 1096 | AV18: =SUM(AV16:AV17) -> 1095.7219 | AW18: =+$D$18 -> 1096 | AX18: =SUM(AX16:AX17) -> 1096.1999 | AY18: =+$D$18 -> 1096 | AZ18: =SUM(AZ16:AZ17) -> 1093.4333 | BA18: =+$D$18 -> 1096 | BB18: =SUM(BB16:BB17) -> 1094.766 | BC18: =+$D$18 -> 1096 | BD18: =SUM(BD16:BD17) -> 1095.3863 | BE18: =+$D$18 -> 1096 | BF18: =SUM(BF16:BF17) -> 1095.9544 | BG18: 1100 | BH18: 1097.2261 | BI18: 1100 | BJ18: 1100.4424 | BK18: 1108 | BL18: 1101.4805 | BM18: 1114.9999 | BN18: 1107.6689 | BO18: 1117.5084 | BP18: 1112.2985 | BQ18: 1115 | BR18: 1119.1948 | BS18: 1119.4604
B19: Ferro Alloys (FeMn+LCFeMn+SiMn+FeSi) | C19: Kg/ TCS | D19: =+D68+D69+D72 -> 18.044118 | E19: =+$D$19 -> 18.044118 | F19: =F68+F71+F72 -> 17.484522 | G19: =+$D$19 -> 18.044118 | H19: =H68+H71+H72 -> 19.422071 | I19: =+$D$19 -> 18.044118 | J19: =J68+J71+J72 -> 18.481551 | K19: =+$D$19 -> 18.044118 | L19: =L68+L71+L72 -> 19.733624 | M19: =+$D$19 -> 18.044118 | N19: =N68+N71+N72 -> 18.914956 | O19: =+$D$19 -> 18.044118 | P19: =P68+P71+P72 -> 20.120846 | Q19: =+$D$19 -> 18.044118 | R19: =R68+R71+R72 -> 19.234596 | S19: =+$D$19 -> 18.044118 | T19: =T68+T71+T72 -> 19.080809 | U19: =+$D$19 -> 18.044118 | V19: =V68+V71+V72 -> 19.204005 | W19: =+$D$19 -> 18.044118 | X19: =X68+X71+X72 -> 17.254405 | Y19: =+$D$19 -> 18.044118 | Z19: =Z68+Z71+Z72 -> 18.871242 | AA19: =+$D$19 -> 18.044118 | AB19: =AB68+AB71+AB72 -> 18.892871 | AC19: =+$D$19 -> 18.044118 | AD19: =AD68+AD71+AD72 -> 17.868204 | AE19: =+$D$19 -> 18.044118 | AF19: =AF68+AF71+AF72 -> 18.778154 | AG19: =+$D$19 -> 18.044118 | AH19: =AH68+AH71+AH72 -> 16.204652 | AI19: =+$D$19 -> 18.044118 | AJ19: =AJ68+AJ71+AJ72 -> 18.455436 | AK19: =+$D$19 -> 18.044118 | AL19: =AL68+AL71+AL72 -> 17.496341 | AM19: =+$D$19 -> 18.044118 | AN19: =AN68+AN71+AN72 -> 17.138981 | AO19: =+$D$19 -> 18.044118 | AP19: =AP68+AP71+AP72 -> 18.346559 | AQ19: =+$D$19 -> 18.044118 | AR19: =AR68+AR71+AR72 -> 17.201717 | AS19: =+$D$19 -> 18.044118 | AT19: =AT68+AT71+AT72 -> 18.232678 | AU19: =+$D$19 -> 18.044118 | AV19: =AV68+AV71+AV72 -> 16.786191 | AW19: =+$D$19 -> 18.044118 | AX19: =AX68+AX71+AX72 -> 18.12466 | AY19: =+$D$19 -> 18.044118 | AZ19: =AZ68+AZ71+AZ72 -> 17.903333 | BA19: =+$D$19 -> 18.044118 | BB19: =BB68+BB71+BB72 -> 17.342904 | BC19: =+$D$19 -> 18.044118 | BD19: =BD68+BD71+BD72 -> 17.241825 | BE19: =+$D$19 -> 18.044118 | BF19: =BF68+BF71+BF72 -> 18.105022 | BG19: 23 | BH19: 20.403235 | BI19: 21.173677 | BJ19: 22.701786 | BK19: 21 | BL19: 22.930617 | BM19: 21.95779 | BN19: 20.936322 | BO19: 20.938578 | BP19: 20.212673 | BQ19: 21 | BR19: 21.832464 | BS19: 23.120676
B20: Mill yield
B21: WR Mill | C21: % | D21: 96 | E21: =+$D$21 -> 96 | F21: =+WRM!F161 -> 95.64166 | G21: =+$D$21 -> 96 | H21: =+WRM!H161 -> 95.612744 | I21: =+$D$21 -> 96 | J21: =+WRM!J161 -> 95.62759 | K21: =+$D$21 -> 96 | L21: =+WRM!L161 -> 95.257541 | M21: =+$D$21 -> 96 | N21: =+WRM!N161 -> 95.50838 | O21: =+$D$21 -> 96 | P21: =+WRM!P161 -> 95.750554 | Q21: =+$D$21 -> 96 | R21: =+WRM!R161 -> 95.576817 | S21: =+$D$21 -> 96 | T21: =+WRM!T161 -> 95.876083 | U21: =+$D$21 -> 96 | V21: =+WRM!V161 -> 95.633207 | W21: =+$D$21 -> 96 | X21: =+WRM!X161 -> 95.610321 | Y21: =+$D$21 -> 96 | Z21: =+WRM!Z161 -> 95.743417 | AA21: =+$D$21 -> 96 | AB21: =+WRM!AB161 -> 95.629391 | AC21: =+$D$21 -> 96 | AD21: =+WRM!AD161 -> 95.95434 | AE21: =+$D$21 -> 96 | AF21: =+WRM!AF161 -> 95.664646 | AG21: =+$D$21 -> 96 | AH21: =+WRM!AH161 -> 95.766381 | AI21: =+$D$21 -> 96 | AJ21: =+WRM!AJ161 -> 95.675972 | AK21: =+$D$21 -> 96 | AL21: =+WRM!AL161 -> 95.336202 | AM21: =+$D$21 -> 96 | AN21: =+WRM!AN161 -> 95.643378 | AO21: =+$D$21 -> 96 | AP21: =+WRM!AP161 -> 95.633676 | AQ21: =+$D$21 -> 96 | AR21: =+WRM!AR161 -> 95.804245 | AS21: =+$D$21 -> 96 | AT21: =+WRM!AT161 -> 95.652698 | AU21: =+$D$21 -> 96 | AV21: =+WRM!AV161 -> 95.614821 | AW21: =+$D$21 -> 96 | AX21: =+WRM!AX161 -> 95.64945 | AY21: =+$D$21 -> 96 | AZ21: =+WRM!AZ161 -> 95.474823 | BA21: =+$D$21 -> 96 | BB21: =+WRM!BB161 -> 95.629455 | BC21: =+$D$21 -> 96 | BD21: =+WRM!BD161 -> 95.635828 | BE21: =+$D$21 -> 96 | BF21: =+WRM!BF161 -> 95.632552 | BG21: 96 | BH21: 95.818831 | BI21: 96 | BJ21: 95.881785 | BK21: 96 | BL21: 95.450038 | BM21: 96 | BN21: 95.505336 | BO21: 96.222984 | BP21: 94.958654 | BQ21: 96.5 | BR21: 96.195271 | BS21: 96.032659
B22: Bar Mill | C22: % | D22: 96.5 | E22: =+$D$22 -> 96.5 | F22: =+BM!F58 -> 95.918611 | G22: =+$D$22 -> 96.5 | H22: =+BM!H58 -> 96.517504 | I22: =+$D$22 -> 96.5 | J22: =+BM!J58 -> 96.220132 | K22: =+$D$22 -> 96.5 | L22: =+BM!L58 -> 96.41942 | M22: =+$D$22 -> 96.5 | N22: =+BM!N58 -> 96.28542 | O22: =+$D$22 -> 96.5 | P22: =+BM!P58 -> 96.454668 | Q22: =+$D$22 -> 96.5 | R22: =+BM!R58 -> 96.333045 | S22: =+$D$22 -> 96.5 | T22: =+BM!T58 -> 96.32902 | U22: =+$D$22 -> 96.5 | V22: =+BM!V58 -> 96.332259 | W22: =+$D$22 -> 96.5 | X22: =+BM!X58 -> 96.394637 | Y22: =+$D$22 -> 96.5 | Z22: =+BM!Z58 -> 96.395895 | AA22: =+$D$22 -> 96.5 | AB22: =+BM!AB58 -> 96.342498 | AC22: =+$D$22 -> 96.5 | AD22: =+BM!AD58 -> 96.409969 | AE22: =+$D$22 -> 96.5 | AF22: =+BM!AF58 -> 96.34916 | AG22: =+$D$22 -> 96.5 | AH22: =+BM!AH58 -> 96.083718 | AI22: =+$D$22 -> 96.5 | AJ22: =+BM!AJ58 -> 96.317468 | AK22: =+$D$22 -> 96.5 | AL22: =+BM!AL58 -> 95.865818 | AM22: =+$D$22 -> 96.5 | AN22: =+BM!AN58 -> 96.077498 | AO22: =+$D$22 -> 96.5 | AP22: =+BM!AP58 -> 96.261974 | AQ22: =+$D$22 -> 96.5 | AR22: =+BM!AR58 -> 95.990775 | AS22: =+$D$22 -> 96.5 | AT22: =+BM!AT58 -> 96.230985 | AU22: =+$D$22 -> 96.5 | AV22: =+BM!AV58 -> 95.960644 | AW22: =+$D$22 -> 96.5 | AX22: =+BM!AX58 -> 96.20671 | AY22: =+$D$22 -> 96.5 | AZ22: =+BM!AZ58 -> 93.352458 | BA22: =+$D$22 -> 96.5 | BB22: =+BM!BB58 -> 95.076496 | BC22: =+$D$22 -> 96.5 | BD22: =+BM!BD58 -> 95.530624 | BE22: =+$D$22 -> 96.5 | BF22: =+BM!BF58 -> 95.944392 | BG22: 96.5 | BH22: 96.286951 | BI22: 96.5 | BJ22: 96.088708 | BK22: 96.5 | BL22: 95.450022 | BM22: 96.499982 | BN22: 95.423966 | BO22: 96.209843 | BP22: 95.175924 | BQ22: 96.5 | BR22: 96.065593 | BS22: 96.05494
B23: US Mill | C23: % | D23: 94.75 | E23: =+$D$23 -> 94.75 | F23: =+USM!G124 -> 93.964286 | G23: =+$D$23 -> 94.75 | H23: =+USM!I124 -> 93.848373 | I23: =+$D$23 -> 94.75 | J23: =+USM!K124 -> 90.323329 | K23: =+$D$23 -> 94.75 | L23: =+USM!M124 -> 94.300658 | M23: =+$D$23 -> 94.75 | N23: =+USM!O124 -> 93.020053 | O23: =+$D$23 -> 94.75 | P23: =+USM!Q124 -> 94.039737 | Q23: =+$D$23 -> 94.75 | R23: =+USM!S124 -> 92.754828 | S23: =+$D$23 -> 94.75 | T23: =+USM!U124 -> 93.446166 | U23: =+$D$23 -> 94.75 | V23: =+USM!W124 -> 92.869075 | W23: =+$D$23 -> 94.75 | X23: =+USM!Y124 -> 93.97245 | Y23: =+$D$23 -> 94.75 | Z23: =+USM!AA124 -> 93.84314 | AA23: =+$D$23 -> 94.75 | AB23: =+USM!AC124 -> 93.410589 | AC23: =+$D$23 -> 94.75 | AD23: =+USM!AE124 -> 93.165856 | AE23: =+$D$23 -> 94.75 | AF23: =+USM!AG124 -> 93.389678 | AG23: =+$D$23 -> 94.75 | AH23: =+USM!AI124 -> 93.342594 | AI23: =+$D$23 -> 94.75 | AJ23: =+USM!AK124 -> 93.383858 | AK23: =+$D$23 -> 94.75 | AL23: =+USM!AM124 -> 93.351849 | AM23: =+$D$23 -> 94.75 | AN23: =+USM!AO124 -> 93.306455 | AO23: =+$D$23 -> 94.75 | AP23: =+USM!AQ124 -> 93.380088 | AQ23: =+$D$23 -> 94.75 | AR23: =+USM!AS124 -> 93.241261 | AS23: =+$D$23 -> 94.75 | AT23: =+USM!AU124 -> 93.364662 | AU23: =+$D$23 -> 94.75 | AV23: =+USM!AW124 -> 94.339918 | AW23: =+$D$23 -> 94.75 | AX23: =+USM!AY124 -> 93.45823 | AY23: =+$D$23 -> 94.75 | AZ23: =+USM!BA124 -> 94.146465 | BA23: =+$D$23 -> 94.75 | BB23: =+USM!BC124 -> 93.911642 | BC23: =+$D$23 -> 94.75 | BD23: =+USM!BE124 -> 93.649583 | BE23: =+$D$23 -> 94.75 | BF23: =+USM!BG124 -> 93.527435 | BG23: 94.75 | BH23: 93.736035 | BI23: 94.5 | BJ23: 94.168642 | BK23: 94.5 | BL23: 93.371871 | BM23: 95.700065 | BN23: 93.445481 | BO23: 95.699819 | BP23: 95.266762 | BQ23: 95.7 | BR23: 95.476013 | BS23: 95.486333
B24: Sp Energy Consumption | C24: G.cal/TCS | D24: 5.886278 | E24: 6.0987917 | F24: =EMD!E128 -> 6.1129634 | G24: 5.8950819 | H24: =EMD!G128 -> 5.9791618 | I24: =EMD!H128 -> 5.9260303 | J24: =EMD!I128 -> 6.0300559 | K24: 5.8881875 | L24: =EMD!K128 -> 5.9510025 | M24: =EMD!L128 -> 5.9135486 | N24: =EMD!M128 -> 6.0018291 | O24: 5.9044904 | P24: =EMD!O128 -> 5.923191 | Q24: =+EMD!P128 -> 5.9112818 | R24: =+EMD!Q128 -> 5.9807715 | S24: 5.9110636 | T24: =EMD!S128 -> 6.0281542 | U24: =+EMD!T128 -> 5.9112381 | V24: =+EMD!U128 -> 5.9902738 | W24: 6.4404862 | X24: =EMD!W128 -> 6.2161034 | Y24: =+EMD!X128 -> 6.0185038 | Z24: =+EMD!Y128 -> 6.0504489 | AA24: =+EMD!Z128 -> 5.9615466 | AB24: =+EMD!AA128 -> 6.0267097 | AC24: 5.897773 | AD24: =EMD!AC128 -> 6.5564134 | AE24: =+EMD!AD128 -> 5.9515643 | AF24: =+EMD!AE128 -> 6.0869784 | AG24: 5.9674105 | AH24: =EMD!AG128 -> 6.0353483 | AI24: =+EMD!AH128 -> 5.9533717 | AJ24: =+EMD!AI128 -> 6.0801532 | AK24: 5.961908 | AL24: =EMD!AK128 -> 6.1355366 | AM24: =+EMD!AL128 -> 5.9413396 | AN24: =+EMD!AM128 -> 6.2170648 | AO24: =+EMD!AN128 -> 5.954412 | AP24: =+EMD!AO128 -> 6.0864404 | AQ24: 5.95667 | AR24: 6.1463269 | AS24: =+EMD!AR128 -> 5.9546606 | AT24: =+EMD!AS128 -> 6.0923974 | AU24: 5.9639133 | AV24: 6.1805508 | AW24: =+EMD!AV128 -> 5.9554895 | AX24: =+EMD!AW128 -> 6.0928466 | AY24: 5.8906678 | AZ24: 5.9116956 | BA24: =+EMD!AZ128 -> 5.9360969 | BB24: =+EMD!BA128 -> 6.0462703 | BC24: =+EMD!BB128 -> 5.938732 | BD24: =+EMD!BC128 -> 6.130928 | BE24: =+EMD!BD128 -> 5.9495831 | BF24: =+EMD!BE128 -> 6.0767731 | BG24: 5.950002 | BH24: 6.1600133 | BI24: 5.9498029 | BJ24: 6.1924446 | BK24: 5.9892031 | BL24: 6.2012038 | BM24: 5.9854778 | BN24: 6.300637 | BO24: 6.1969869 | BP24: 6.4827566 | BQ24: 5.95 | BR24: 6.1800191 | BS24: 6.3116941
B25: Sp Power Consumption | C25: KwH/TSS | D25: 458.20337 | E25: 494.08443 | F25: =+'POWER DISTRIBUTION'!J17/('Maj Production Summ'!F37+0.25*'Maj Production Summ'!F26) -> 492.30286 | G25: 461.80049 | H25: =+'POWER DISTRIBUTION'!L17/('Maj Production Summ'!H37+0.25*'Maj Production Summ'!H26) -> 454.11623 | I25: =+'POWER DISTRIBUTION'!M17/('Maj Production Summ'!I37+0.25*'Maj Production Summ'!I26) -> 475.85473 | J25: =+'POWER DISTRIBUTION'!N17/('Maj Production Summ'!J37+0.25*'Maj Production Summ'!J26) -> 472.32855 | K25: 461.3094 | L25: =+'POWER DISTRIBUTION'!P17/('Maj Production Summ'!L37+0.25*'Maj Production Summ'!L26) -> 452.70789 | M25: =+'POWER DISTRIBUTION'!Q17/('Maj Production Summ'!M37+0.25*'Maj Production Summ'!M26) -> 470.71304 | N25: =+'POWER DISTRIBUTION'!R17/('Maj Production Summ'!N37+0.25*'Maj Production Summ'!N26) -> 465.60738 | O25: 467.74394 | P25: =+'POWER DISTRIBUTION'!T17/('Maj Production Summ'!P37+0.25*'Maj Production Summ'!P26) -> 442.75385 | Q25: =+'POWER DISTRIBUTION'!U17/('Maj Production Summ'!Q37+0.25*'Maj Production Summ'!Q26) -> 469.93136 | R25: =+'POWER DISTRIBUTION'!V17/('Maj Production Summ'!R37+0.25*'Maj Production Summ'!R26) -> 459.49427 | S25: 467.74394 | T25: =+'POWER DISTRIBUTION'!X17/('Maj Production Summ'!T37+0.25*'Maj Production Summ'!T26) -> 478.6447 | U25: =+'POWER DISTRIBUTION'!Y17/('Maj Production Summ'!U37+0.25*'Maj Production Summ'!U26) -> 469.4755 | V25: =+'POWER DISTRIBUTION'!Z17/('Maj Production Summ'!V37+0.25*'Maj Production Summ'!V26) -> 463.21242 | W25: 583.45256 | X25: =+'POWER DISTRIBUTION'!AB17/('Maj Production Summ'!X37+0.25*'Maj Production Summ'!X26) -> 460.52955 | Y25: =+'POWER DISTRIBUTION'!AC17/('Maj Production Summ'!Y37+0.25*'Maj Production Summ'!Y26) -> 491.95795 | Z25: =+'POWER DISTRIBUTION'!AD17/('Maj Production Summ'!Z37+0.25*'Maj Production Summ'!Z26) -> 460.01162 | AA25: =+'POWER DISTRIBUTION'!AE17/('Maj Production Summ'!AA37+0.25*'Maj Production Summ'!AA26) -> 480.79901 | AB25: =+'POWER DISTRIBUTION'!AF17/('Maj Production Summ'!AB37+0.25*'Maj Production Summ'!AB26) -> 462.76987 | AC25: 460.88039 | AD25: =+'POWER DISTRIBUTION'!AH17/('Maj Production Summ'!AD37+0.25*'Maj Production Summ'!AD26) -> 521.9908 | AE25: =+'POWER DISTRIBUTION'!AI17/('Maj Production Summ'!AE37+0.25*'Maj Production Summ'!AE26) -> 477.59416 | AF25: =+'POWER DISTRIBUTION'!AJ17/('Maj Production Summ'!AF37+0.25*'Maj Production Summ'!AF26) -> 469.68763 | AG25: 462.80371 | AH25: =+'POWER DISTRIBUTION'!AL17/('Maj Production Summ'!AH37+0.25*'Maj Production Summ'!AH26) -> 473.49811 | AI25: =+'POWER DISTRIBUTION'!AM17/('Maj Production Summ'!AI37+0.25*'Maj Production Summ'!AI26) -> 475.60044 | AJ25: =+'POWER DISTRIBUTION'!AN17/('Maj Production Summ'!AJ37+0.25*'Maj Production Summ'!AJ26) -> 470.15621 | AK25: 463.03105 | AL25: =+'POWER DISTRIBUTION'!AP17/('Maj Production Summ'!AL37+0.25*'Maj Production Summ'!AL26) -> 443.87204 | AM25: =+'POWER DISTRIBUTION'!AQ17/('Maj Production Summ'!AM37+0.25*'Maj Production Summ'!AM26) -> 462.23235 | AN25: =+'POWER DISTRIBUTION'!AR17/('Maj Production Summ'!AN37+0.25*'Maj Production Summ'!AN26) -> 476.38291 | AO25: =+'POWER DISTRIBUTION'!AS17/('Maj Production Summ'!AO37+0.25*'Maj Production Summ'!AO26) -> 474.06449 | AP25: =+'POWER DISTRIBUTION'!AT17/('Maj Production Summ'!AP37+0.25*'Maj Production Summ'!AP26) -> 467.07472 | AQ25: 459.24603 | AR25: =+'POWER DISTRIBUTION'!AV17/('Maj Production Summ'!AR37+0.25*'Maj Production Summ'!AR26) -> 461.48647 | AS25: =+'POWER DISTRIBUTION'!AW17/('Maj Production Summ'!AS37+0.25*'Maj Production Summ'!AS26) -> 472.42966 | AT25: =+'POWER DISTRIBUTION'!AX17/('Maj Production Summ'!AT37+0.25*'Maj Production Summ'!AT26) -> 466.50358 | AU25: 463.10735 | AV25: =+'POWER DISTRIBUTION'!AZ17/('Maj Production Summ'!AV37+0.25*'Maj Production Summ'!AV26) -> 502.65661 | AW25: =+'POWER DISTRIBUTION'!BA17/('Maj Production Summ'!AW37+0.25*'Maj Production Summ'!AW26) -> 471.59466 | AX25: =+'POWER DISTRIBUTION'!BB17/('Maj Production Summ'!AX37+0.25*'Maj Production Summ'!AX26) -> 469.29872 | AY25: 459.76937 | AZ25: =+'POWER DISTRIBUTION'!BD17/('Maj Production Summ'!AZ37+0.25*'Maj Production Summ'!AZ26) -> 450.62512 | BA25: =+'POWER DISTRIBUTION'!BE17/('Maj Production Summ'!BA37+0.25*'Maj Production Summ'!BA26) -> 460.61776 | BB25: =+'POWER DISTRIBUTION'!BF17/('Maj Production Summ'!BB37+0.25*'Maj Production Summ'!BB26) -> 469.3544 | BC25: =+'POWER DISTRIBUTION'!BG17/('Maj Production Summ'!BC37+0.25*'Maj Production Summ'!BC26) -> 461.42968 | BD25: =+'POWER DISTRIBUTION'!BH17/('Maj Production Summ'!BD37+0.25*'Maj Production Summ'!BD26) -> 472.81899 | BE25: =+'POWER DISTRIBUTION'!BI17/('Maj Production Summ'!BE37+0.25*'Maj Production Summ'!BE26) -> 470.51531 | BF25: =+'POWER DISTRIBUTION'!BJ17/('Maj Production Summ'!BF37+0.25*'Maj Production Summ'!BF26) -> 467.63427 | BG25: 498.86963 | BH25: 491.52958 | BI25: 491.86598 | BJ25: 499.12041 | BK25: 499.14523 | BL25: 516.74946 | BM25: 501.08848 | BN25: 528.34198 | BO25: 500.04339 | BP25: 579.80533 | BQ25: 483.423 | BR25: 525.26173 | BS25: 552.03691
C26: KwH/TCS | D26: 440.96351 | E26: 465.50188 | F26: =+'POWER DISTRIBUTION'!J17/'Maj Production Summ'!F18 -> 460.56724 | G26: 446.77103 | H26: =+'POWER DISTRIBUTION'!L17/'Maj Production Summ'!H18 -> 439.53564 | I26: =+'POWER DISTRIBUTION'!M17/'Maj Production Summ'!I18 -> 455.04741 | J26: =+'POWER DISTRIBUTION'!N17/'Maj Production Summ'!J18 -> 449.74474 | K26: 445.92427 | L26: =+'POWER DISTRIBUTION'!P17/'Maj Production Summ'!L18 -> 424.25451 | M26: =+'POWER DISTRIBUTION'!Q17/'Maj Production Summ'!M18 -> 451.8449 | N26: =+'POWER DISTRIBUTION'!R17/'Maj Production Summ'!N18 -> 440.92131 | O26: 451.67958 | P26: =+'POWER DISTRIBUTION'!T17/'Maj Production Summ'!P18 -> 424.51702 | Q26: =+'POWER DISTRIBUTION'!U17/'Maj Production Summ'!Q18 -> 451.80156 | R26: =+'POWER DISTRIBUTION'!V17/'Maj Production Summ'!R18 -> 436.5731 | S26: 451.67958 | T26: =+'POWER DISTRIBUTION'!X17/'Maj Production Summ'!T18 -> 441.26841 | U26: =+'POWER DISTRIBUTION'!Y17/'Maj Production Summ'!U18 -> 451.77623 | V26: =+'POWER DISTRIBUTION'!Z17/'Maj Production Summ'!V18 -> 437.50706 | W26: 568.25163 | X26: =+'POWER DISTRIBUTION'!AB17/'Maj Production Summ'!X18 -> 452.48637 | Y26: =+'POWER DISTRIBUTION'!AC17/'Maj Production Summ'!Y18 -> 475.90977 | Z26: =+'POWER DISTRIBUTION'!AD17/'Maj Production Summ'!Z18 -> 438.89498 | AA26: =+'POWER DISTRIBUTION'!AE17/'Maj Production Summ'!AA18 -> 463.22317 | AB26: =+'POWER DISTRIBUTION'!AF17/'Maj Production Summ'!AB18 -> 439.89759 | AC26: 445.88079 | AD26: =+'POWER DISTRIBUTION'!AH17/'Maj Production Summ'!AD18 -> 520.56797 | AE26: =+'POWER DISTRIBUTION'!AI17/'Maj Production Summ'!AE18 -> 460.44254 | AF26: =+'POWER DISTRIBUTION'!AJ17/'Maj Production Summ'!AF18 -> 448.92906 | AG26: 447.36773 | AH26: =+'POWER DISTRIBUTION'!AL17/'Maj Production Summ'!AH18 -> 442.57475 | AI26: =+'POWER DISTRIBUTION'!AM17/'Maj Production Summ'!AI18 -> 458.68412 | AJ26: =+'POWER DISTRIBUTION'!AN17/'Maj Production Summ'!AJ18 -> 448.13222 | AK26: 447.96245 | AL26: =+'POWER DISTRIBUTION'!AP17/'Maj Production Summ'!AL18 -> 438.77258 | AM26: =+'POWER DISTRIBUTION'!AQ17/'Maj Production Summ'!AM18 -> 447.06723 | AN26: =+'POWER DISTRIBUTION'!AR17/'Maj Production Summ'!AN18 -> 462.92309 | AO26: =+'POWER DISTRIBUTION'!AS17/'Maj Production Summ'!AO18 -> 457.37755 | AP26: =+'POWER DISTRIBUTION'!AT17/'Maj Production Summ'!AP18 -> 447.06971 | AQ26: 444.0148 | AR26: =+'POWER DISTRIBUTION'!AV17/'Maj Production Summ'!AR18 -> 455.22208 | AS26: =+'POWER DISTRIBUTION'!AW17/'Maj Production Summ'!AS18 -> 455.90608 | AT26: =+'POWER DISTRIBUTION'!AX17/'Maj Production Summ'!AT18 -> 447.88065 | AU26: 446.83745 | AV26: =+'POWER DISTRIBUTION'!AZ17/'Maj Production Summ'!AV18 -> 501.06568 | AW26: =+'POWER DISTRIBUTION'!BA17/'Maj Production Summ'!AW18 -> 455.09368 | AX26: =+'POWER DISTRIBUTION'!BB17/'Maj Production Summ'!AX18 -> 451.8523 | AY26: 444.52083 | AZ26: =+'POWER DISTRIBUTION'!BD17/'Maj Production Summ'!AZ18 -> 436.04258 | BA26: =+'POWER DISTRIBUTION'!BE17/'Maj Production Summ'!BA18 -> 445.06135 | BB26: =+'POWER DISTRIBUTION'!BF17/'Maj Production Summ'!BB18 -> 461.11375 | BC26: =+'POWER DISTRIBUTION'!BG17/'Maj Production Summ'!BC18 -> 446.06953 | BD26: =+'POWER DISTRIBUTION'!BH17/'Maj Production Summ'!BD18 -> 462.01058 | BE26: =+'POWER DISTRIBUTION'!BI17/'Maj Production Summ'!BE18 -> 454.13031 | BF26: =+'POWER DISTRIBUTION'!BJ17/'Maj Production Summ'!BF18 -> 450.44951 | BG26: 483.40224 | BH26: 471.62787 | BI26: 475.02939 | BJ26: 476.24946 | BK26: 482.32053 | BL26: 494.76974 | BM26: 486.14726 | BN26: 514.38476 | BO26: 487.74658 | BP26: 580.20286 | BQ26: 448.29125 | BR26: 538.52024 | BS26: 565.51994
B27: Sp Water Consumption | C27: M³/TCS | D27: 2.8 | E27: =+$D$27 -> 2.8 | F27: 2.82 | G27: =+$D$27 -> 2.8 | H27: 2.97 | I27: =+$D$27 -> 2.8 | J27: =+((F27*F33)+(H27*H33))/J33 -> 2.8971874 | K27: =+$D$27 -> 2.8 | L27: 2.96 | M27: =+$D$27 -> 2.8 | N27: =+((F33*F27)+(H33*H27)+(L33*L27))/N33 -> 2.91893 | O27: =+$D$27 -> 2.8 | P27: 2.9 | Q27: =+$D$27 -> 2.8 | R27: =+(((N27*N33)+(P27*P33))/R33) -> 2.9139123 | S27: =+$D$27 -> 2.8 | T27: 2.9 | U27: =+$D$27 -> 2.8 | V27: =+(((R27*R33)+(T27*T33))/V33) -> 2.9111449 | W27: =+$D$27 -> 2.8 | X27: 2.905 | Y27: =+$D$27 -> 2.8 | Z27: =+((P33*P27)+(T33*T27)+(X33*X27))/Z33 -> 2.9015794 | AA27: =+$D$27 -> 2.8 | AB27: =+((N27*N33)+(Z27*Z33))/AB33 -> 2.9101643 | AC27: =+$D$27 -> 2.8 | AD27: 2.94 | AE27: =+$D$27 -> 2.8 | AF27: =+(((AB27*AB33)+(AD27*AD33))/AF33) -> 2.9135045 | AG27: =+$D$27 -> 2.8 | AH27: 2.86 | AI27: =+$D$27 -> 2.8 | AJ27: =+(((AF27*AF33)+(AH27*AH33))/AJ33) -> 2.906795 | AK27: =+$D$27 -> 2.8 | AL27: 2.87 | AM27: =+$D$27 -> 2.8 | AN27: =+((AD33*AD27)+(AH33*AH27)+(AL33*AL27))/AN33 -> 2.8859377 | AO27: =+$D$27 -> 2.8 | AP27: =+(((AL27*AL33)+(AJ27*AJ33))/AP33) -> 2.902618 | AQ27: 2.85 | AR27: 2.88 | AS27: =+$D$27 -> 2.8 | AT27: =+(((AP27*AP33)+(AR27*AR33))/AT33) -> 2.9003682 | AU27: 2.85 | AV27: 2.86 | AW27: =+$D$27 -> 2.8 | AX27: =+(((AT27*AT33)+(AV27*AV33))/AX33) -> 2.8973536 | AY27: 2.85 | AZ27: 2.87 | BA27: =+$D$27 -> 2.8 | BB27: =+((AR27*AR33)+(AV27*AV33)+(AZ27*AZ33))/BB33 -> 2.8706577 | BC27: =+$D$27 -> 2.8 | BD27: =+((AN27*AN33)+(BB27*BB33))/BD33 -> 2.8782315 | BE27: =+$D$27 -> 2.8 | BF27: =+((AX27*AX33)+(AZ27*AZ33))/BF33 -> 2.8949266 | BG27: 2.85 | BH27: 2.9919746 | BI27: 2.85 | BJ27: 3.0828892 | BK27: 3.3 | BL27: 3.0186532 | BM27: 4.3 | BN27: 3.3197104 | BO27: 4.3 | BP27: 5.0407394 | BQ27: 4.6 | BR27: 5.0056729 | BS27: 5.0192042
B28: Sp. CO2 emission | C28: T/TCS | D28: 2.51 | E28: =+$D$28 -> 2.51 | F28: 2.68 | G28: =+$D$28 -> 2.51 | H28: 2.32 | I28: =+$D$28 -> 2.51 | J28: =+((F28*F33)+(H28*H33))/J33 -> 2.4947503 | K28: =+$D$28 -> 2.51 | L28: 2.34 | M28: =+$D$28 -> 2.51 | N28: =+((F33*F28)+(H33*H28)+(L33*L28))/N33 -> 2.4411835 | O28: =+$D$28 -> 2.51 | P28: 2.35 | Q28: =+$D$28 -> 2.51 | R28: =+((N28*N33)+(P28*P33))/R33 -> 2.4170139 | S28: =+$D$28 -> 2.51 | T28: 2.4 | U28: =+$D$28 -> 2.51 | V28: =+((R28*R33)+(T28*T33))/V33 -> 2.4136296 | W28: =+$D$28 -> 2.51 | X28: 2.45 | Y28: =+$D$28 -> 2.51 | Z28: =+((P33*P28)+(T33*T28)+(X33*X28))/Z33 -> 2.398133 | AA28: =+$D$28 -> 2.51 | AB28: =+((N28*N33)+(Z28*Z33))/AB33+0.01 -> 2.4294339 | AC28: =+$D$28 -> 2.51 | AD28: 2.78 | AE28: =+$D$28 -> 2.51 | AF28: =+((AB28*AB33)+(AD28*AD33))/AF33 -> 2.4686816 | AG28: =+$D$28 -> 2.51 | AH28: 2.41 | AI28: =+$D$28 -> 2.51 | AJ28: =+(((AF28*AF33)+(AH28*AH33))/AJ33)-0.01 -> 2.4513229 | AK28: =+$D$28 -> 2.51 | AL28: 2.4 | AM28: =+$D$28 -> 2.51 | AN28: =+((AD33*AD28)+(AH33*AH28)+(AL33*AL28))/AN33 -> 2.5094618 | AO28: =+$D$28 -> 2.51 | AP28: =+((AL28*AL33)+(AJ28*AJ33))/AP33 -> 2.4454967 | AQ28: =+$D$28 -> 2.51 | AR28: 2.4 | AS28: =+$D$28 -> 2.51 | AT28: =+((AP28*AP33)+(AR28*AR33))/AT33 -> 2.440971 | AU28: =+$D$28 -> 2.51 | AV28: 2.48 | AW28: =+$D$28 -> 2.51 | AX28: =+((AT28*AT33)+(AV28*AV33))/AX33 -> 2.4438856 | AY28: =+$D$28 -> 2.51 | AZ28: 2.37 | BA28: =+$D$28 -> 2.51 | BB28: =+((AR28*AR33)+(AV28*AV33)+(AZ28*AZ33))/BB33 -> 2.4115605 | BC28: =+$D$28 -> 2.51 | BD28: =+((AN28*AN33)+(BB28*BB33))/BD33 -> 2.4600873 | BE28: =+$D$28 -> 2.51 | BF28: =+((AX28*AX33)+(AZ28*AZ33))/BF33 -> 2.4373297 | BG28: 2.32 | BH28: 2.3695074 | BI28: 2.375 | BJ28: 2.4275692 | BK28: 2.35 | BL28: 2.4470555 | BM28: 2.45 | BN28: 2.4734992 | BO28: 2.45 | BP28: 2.6211068 | BQ28: 2.456658 | BR28: 2.4355942 | BS28: 2.609953
B29: Sp. PM emissions | C29: kg/TCS | D29: 0.5 | E29: =+$D$29 -> 0.5 | F29: 0.52 | G29: =+$D$29 -> 0.5 | H29: 0.492 | I29: =+$D$29 -> 0.5 | J29: =+((F29*F33)+(H29*H33))/J33 -> 0.50559169 | K29: =+$D$29 -> 0.5 | L29: 0.5 | M29: =+$D$29 -> 0.5 | N29: =+((F33*F29)+(H33*H29)+(L33*L29))/N33 -> 0.50365613 | O29: =+$D$29 -> 0.5 | P29: 0.5 | Q29: =+$D$29 -> 0.5 | R29: =+((N29*N33)+(P29*P33))/R33 -> 0.50268701 | S29: =+$D$29 -> 0.5 | T29: 0.5 | U29: =+$D$29 -> 0.5 | V29: =+((R29*R33)+(T29*T33))/V33 -> 0.50215253 | W29: =+$D$29 -> 0.5 | X29: 0.5 | Y29: =+$D$29 -> 0.5 | Z29: =+((P33*P29)+(T33*T29)+(X33*X29))/Z33 -> 0.5 | AA29: =+$D$29 -> 0.5 | AB29: =+((N29*N33)+(Z29*Z33))/AB33 -> 0.50180901 | AC29: =+$D$29 -> 0.5 | AD29: 0.5 | AE29: =+$D$29 -> 0.5 | AF29: =+((AB29*AB33)+(AD29*AD33))/AF33 -> 0.50160648 | AG29: =+$D$29 -> 0.5 | AH29: 0.46 | AI29: =+$D$29 -> 0.5 | AJ29: =+((AF29*AF33)+(AH29*AH33))/AJ33 -> 0.49638901 | AK29: =+$D$29 -> 0.5 | AL29: 0.49 | AM29: =+$D$29 -> 0.5 | AN29: =+((AD33*AD29)+(AH33*AH29)+(AL33*AL29))/AN33 -> 0.48208008 | AO29: =+$D$29 -> 0.5 | AP29: =+((AL29*AL33)+(AJ29*AJ33))/AP33 -> 0.49566372 | AQ29: =+$D$29 -> 0.5 | AR29: 0.5 | AS29: =+$D$29 -> 0.5 | AT29: =+((AP29*AP33)+(AR29*AR33))/AT33 -> 0.49609506 | AU29: =+$D$29 -> 0.5 | AV29: 0.52 | AW29: =+$D$29 -> 0.5 | AX29: =+((AT29*AT33)+(AV29*AV33))/AX33 -> 0.49788019 | AY29: =+$D$29 -> 0.5 | AZ29: 0.5 | BA29: =+$D$29 -> 0.5 | BB29: =+((AR29*AR33)+(AV29*AV33)+(AZ29*AZ33))/BB33 -> 0.50565536 | BC29: =+$D$29 -> 0.5 | BD29: =+((AN29*AN33)+(BB29*BB33))/BD33 -> 0.4939698 | BE29: =+$D$29 -> 0.5 | BF29: =+((AX29*AX33)+(AZ29*AZ33))/BF33 -> 0.49806828 | BG29: 0.5 | BH29: 0.49588309 | BI29: 0.53 | BJ29: 0.53450495 | BK29: 0.53 | BL29: 0.5280682 | BM29: 0.55 | BN29: 0.53916083 | BO29: 0.55 | BP29: 0.62328215 | BQ29: 0.551124 | BR29: 0.57147495 | BS29: 0.55061804
B30: Labour Productivity (Pre-existing) | C30: TCS/Man/Year | D30: 832.79094 | E30: =+E38 -> 694.95532 | F30: =+F38 -> 802.23728 | G30: =+G38 -> 814.88252 | H30: =+H38 -> 799.42673 | I30: =+I38 -> 757.28646 | J30: =+J38 -> 801.00957 | K30: =+K38 -> 817.70563 | L30: =+L38 -> 850.75383 | ... BF30: =+BF38 -> 792.13824 | BG30: 712.17383 | BH30: 691.16367 | BI30: 729.20664 | BJ30: 695.16315 | BK30: 656.40621 | BL30: 639.11266 | BM30: 615.77607 | BN30: 561.88094 | BO30: 549.90658 | BP30: 459.2495 | BQ30: 562.64319 | BR30: 490.34382 | BS30: 421.02863
B31: Labour Productivity (MoU) | C31: TCS/Man/Year | D31: =D43 -> 308.34707 | E31: =E43 -> 258.6936 | F31: =F43 -> 296.57273 | AD31: =+AD43 -> 210.92734 | AH31: =+AH43 -> 268.17839 | AL31: =+AL43 -> 268.16346 | AR31: =+AR43 -> 274.37361 | AV31: =+AV43 -> 256.65063 | AZ31: =+AZ43 -> 308.14853
B33: Labor productivity calculation (Pre existing) | C33: Crude Steel | D33: ='Maj Production Summ'!D18 -> 2817514.1 | E33: ='Maj Production Summ'!E18 -> 193691.15 | F33: ='Maj Production Summ'!F18 -> 223226 | G33: ='Maj Production Summ'!G18 -> 244664.78 | H33: ='Maj Production Summ'!H18 -> 236638 | I33: =+E33+G33 -> 438355.93 | J33: =+F33+H33 -> 459864 | K33: ='Maj Production Summ'!K18 -> 237110.48 | L33: ='Maj Production Summ'!L18 -> 243453 | M33: =+E33+G33+K33 -> 675466.41 | N33: =+F33+H33+L33 -> 703317 | O33: ='Maj Production Summ'!O18 -> 239943.34 | P33: ='Maj Production Summ'!P18 -> 253662 | Q33: =+M33+O33 -> 915409.75 | R33: =+N33+P33 -> 956979 | S33: ='Maj Production Summ'!S18 -> 239943.34 | T33: ='Maj Production Summ'!T18 -> 237622 | U33: =+Q33+S33 -> 1155353.1 | V33: =+R33+T33 -> 1194601 | W33: ='Maj Production Summ'!W18 -> 125920.68 | X33: ='Maj Production Summ'!X18 -> 226847 | Y33: =+O33+S33+W33 -> 605807.37 | Z33: =+P33+T33+X33 -> 718131 | AA33: =+M33+Y33 -> 1281273.8 | AB33: =+N33+Z33 -> 1421448 | AC33: ='Maj Production Summ'!AC18 -> 244664.78 | AD33: ='Maj Production Summ'!AD18 -> 179201 | AE33: =+AA33+AC33 -> 1525938.6 | AF33: =+AB33+AD33 -> 1600649 | AG33: ='Maj Production Summ'!AG18 -> 237110.48 | AH33: ='Maj Production Summ'!AH18 -> 229502 | AI33: =+AE33+AG33 -> 1763049 | AJ33: =+AF33+AH33 -> 1830151 | AK33: ='Maj Production Summ'!AK18 -> 244664.78 | AL33: ='Maj Production Summ'!AL18 -> 234365 | AM33: =+AC33+AG33+AK33 -> 726440.04 | AN33: =+AD33+AH33+AL33 -> 643068 | AO33: =AI33+AK33 -> 2007713.8 | AP33: =AJ33+AL33 -> 2064516 | AQ33: ='Maj Production Summ'!AQ18 -> 248441.93 | AR33: ='Maj Production Summ'!AR18 -> 228047 | AS33: =+AO33+AQ33 -> 2256155.7 | AT33: =+AP33+AR33 -> 2292563 | AU33: ='Maj Production Summ'!AU18 -> 222001.89 | AV33: ='Maj Production Summ'!AV18 -> 185016 | AW33: =+AS33+AU33 -> 2478157.6 | AX33: =+AT33+AV33 -> 2477579 | AY33: ='Maj Production Summ'!AY18 -> 248441.93 | AZ33: ='Maj Production Summ'!AZ18 -> 241240 | BA33: =+AQ33+AU33+AY33 -> 718885.74 | BB33: =+AR33+AV33+AZ33 -> 654303 | BC33: =+AM33+BA33 -> 1445325.8 | BD33: =+AN33+BB33 -> 1297371 | BE33: =+AW33+AY33 -> 2726599.6 | BF33: =+AX33+AZ33 -> 2718819 | BG33: 2489528.3 | BH33: 2436959 | BI33: 2620075.5 | BJ33: 2528925 | BK33: 2500000 | BL33: 2422324.3 | BM33: 2573000.8 | BN33: 2322716
C34: Pig+Eq | D34: ='Maj Production Summ'!D26 -> 6020 | E34: ='Maj Production Summ'!E26 -> 1945 | F34: ='Maj Production Summ'!F26 -> 471.09455 | G34: ='Maj Production Summ'!G26 -> 810 | H34: ='Maj Production Summ'!H26 -> 2950.1685 | I34: =+E34+G34 -> 2755 | J34: =+F34+H34 -> 3421.263 | K34: ='Maj Production Summ'!K26 -> 810 | L34: ='Maj Production Summ'!L26 -> 1030.4578 | M34: =+E34+G34+K34 -> 3565 | N34: =+F34+H34+L34 -> 4451.7208 | O34: ='Maj Production Summ'!O26 -> 810 | P34: ='Maj Production Summ'!P26 -> 0 | Q34: =+M34+O34 -> 4375 | R34: =+N34+P34 -> 4451.7208 | S34: ='Maj Production Summ'!S26 -> 810 | T34: ='Maj Production Summ'!T26 -> 164.4084 | U34: =+Q34+S34 -> 5185 | V34: =+R34+T34 -> 4616.1292 | W34: ='Maj Production Summ'!W26 -> 5360 | X34: ='Maj Production Summ'!X26 -> 292.8108 | Y34: =+O34+S34+W34 -> 6980 | Z34: =+P34+T34+X34 -> 457.2192 | AA34: =+M34+Y34 -> 10545 | AB34: =+N34+Z34 -> 4908.94 | AC34: ='Maj Production Summ'!AC26 -> 810 | AD34: ='Maj Production Summ'!AD26 -> 9043.2686 | AE34: =+AA34+AC34 -> 11355 | AF34: =+AB34+AD34 -> 13952.209 | AG34: ='Maj Production Summ'!AG26 -> 810 | AH34: ='Maj Production Summ'!AH26 -> 154.21623 | AI34: =+AE34+AG34 -> 12165 | AJ34: =+AF34+AH34 -> 14106.425 | AK34: ='Maj Production Summ'!AK26 -> 810 | AL34: ='Maj Production Summ'!AL26 -> 40.72516 | AM34: =+AC34+AG34+AK34 -> 2430 | AN34: =+AD34+AH34+AL34 -> 9238.21 | AO34: =AI34+AK34 -> 12975 | AP34: =AJ34+AL34 -> 14147.15 | AQ34: ='Maj Production Summ'!AQ26 -> 810 | AR34: ='Maj Production Summ'!AR26 -> 1557.1073 | AS34: =+AO34+AQ34 -> 13785 | AT34: =+AP34+AR34 -> 15704.257 | AU34: ='Maj Production Summ'!AU26 -> 810 | AV34: ='Maj Production Summ'!AV26 -> 920 | AW34: =+AS34+AU34 -> 14595 | AX34: =+AT34+AV34 -> 16624.257 | AY34: ='Maj Production Summ'!AY26 -> 810 | AZ34: ='Maj Production Summ'!AZ26 -> 401.63435 | BA34: =+AQ34+AU34+AY34 -> 2430 | BB34: =+AR34+AV34+AZ34 -> 2878.7416 | BC34: =+AM34+BA34 -> 4860 | BD34: =+AN34+BB34 -> 12116.952 | BE34: =+AW34+AY34 -> 15405 | BF34: =+AX34+AZ34 -> 17025.892 | BG34: 9365 | BH34: 25856.451 | BI34: 21561.1 | BJ34: 13596.898 | BK34: 22929.735 | BL34: 16335.784 | BM34: 34051.635 | BN34: 32547.079
C35: 50% of Pig Eq | D35: =+D34/2 -> 3010 | E35: =+E34/2 -> 972.5 | F35: =+F34/2 -> 235.54728 | G35: =+G34/2 -> 405 | H35: =+H34/2 -> 1475.0842 | I35: =+E35+G35 -> 1377.5 | J35: =+F35+H35 -> 1710.6315 | K35: =+K34/2 -> 405 | L35: =+L34/2 -> 515.22889 | M35: =+E35+G35+K35 -> 1782.5 | N35: =+F35+H35+L35 -> 2225.8604 | O35: =+O34/2 -> 405 | P35: =+P34/2 -> 0 | Q35: =+M35+O35 -> 2187.5 | R35: =+N35+P35 -> 2225.8604 | S35: =+S34/2 -> 405 | T35: =+T34/2 -> 82.204202 | U35: =+Q35+S35 -> 2592.5 | V35: =+R35+T35 -> 2308.0646 | W35: =+W34/2 -> 2680 | X35: =+X34/2 -> 146.4054 | Y35: =+O35+S35+W35 -> 3490 | Z35: =+P35+T35+X35 -> 228.6096 | AA35: =+M35+Y35 -> 5272.5 | AB35: =+N35+Z35 -> 2454.47 | AC35: =+AC34/2 -> 405 | AD35: =+AD34/2 -> 4521.6343 | AE35: =+AA35+AC35 -> 5677.5 | AF35: =+AB35+AD35 -> 6976.1043 | AG35: =+AG34/2 -> 405 | AH35: =+AH34/2 -> 77.108113 | AI35: =+AE35+AG35 -> 6082.5 | AJ35: =+AF35+AH35 -> 7053.2124 | AK35: =+AK34/2 -> 405 | AL35: =+AL34/2 -> 20.36258 | AM35: =+AC35+AG35+AK35 -> 1215 | AN35: =+AD35+AH35+AL35 -> 4619.105 | AO35: =AI35+AK35 -> 6487.5 | AP35: =AJ35+AL35 -> 7073.575 | AQ35: =+AQ34/2 -> 405 | AR35: =+AR34/2 -> 778.55363 | AS35: =+AO35+AQ35 -> 6892.5 | AT35: =+AP35+AR35 -> 7852.1286 | AU35: =+AU34/2 -> 405 | AV35: =+AV34/2 -> 460 | AW35: =+AS35+AU35 -> 7297.5 | AX35: =+AT35+AV35 -> 8312.1286 | AY35: =+AY34/2 -> 405 | AZ35: =+AZ34/2 -> 200.81717 | BA35: =+AQ35+AU35+AY35 -> 1215 | BB35: =+AR35+AV35+AZ35 -> 1439.3708 | BC35: =+AM35+BA35 -> 2430 | BD35: =+AN35+BB35 -> 6058.4758 | BE35: =+AW35+AY35 -> 7702.5 | BF35: =+AX35+AZ35 -> 8512.9458 | BG35: 4682.5 | BH35: 12928.226 | BI35: 10780.55 | BJ35: 6798.4488 | BK35: 11464.868 | BL35: 8167.892 | BM35: 17025.818 | BN35: 16273.54
C36: CS+50%Pig Eq | D36: =+D33+D35 -> 2820524.1 | E36: =+E33+E35 -> 194663.65 | F36: =+F33+F35 -> 223461.55 | G36: =+G33+G35 -> 245069.78 | H36: =+H33+H35 -> 238113.08 | I36: =+E36+G36 -> 439733.43 | J36: =+F36+H36 -> 461574.63 | K36: =+K33+K35 -> 237515.48 | L36: =+L33+L35 -> 243968.23 | M36: =+E36+G36+K36 -> 677248.91 | N36: =+F36+H36+L36 -> 705542.86 | O36: =+O33+O35 -> 240348.34 | P36: =+P33+P35 -> 253662 | Q36: =+M36+O36 -> 917597.25 | R36: =+N36+P36 -> 959204.86 | S36: =+S33+S35 -> 240348.34 | T36: =+T33+T35 -> 237704.2 | U36: =+Q36+S36 -> 1157945.6 | V36: =+R36+T36 -> 1196909.1 | W36: =+W33+W35 -> 128600.68 | X36: =+X33+X35 -> 226993.41 | Y36: =+O36+S36+W36 -> 609297.37 | Z36: =+P36+T36+X36 -> 718359.61 | AA36: =+M36+Y36 -> 1286546.3 | AB36: =+N36+Z36 -> 1423902.5 | AC36: =+AC33+AC35 -> 245069.78 | AD36: =+AD33+AD35 -> 183722.63 | AE36: =+AA36+AC36 -> 1531616.1 | AF36: =+AB36+AD36 -> 1607625.1 | AG36: =+AG33+AG35 -> 237515.48 | AH36: =+AH33+AH35 -> 229579.11 | AI36: =+AE36+AG36 -> 1769131.5 | AJ36: =+AF36+AH36 -> 1837204.2 | AK36: =+AK33+AK35 -> 245069.78 | AL36: =+AL33+AL35 -> 234385.36 | AM36: =+AC36+AG36+AK36 -> 727655.04 | AN36: =+AD36+AH36+AL36 -> 647687.11 | AO36: =AI36+AK36 -> 2014201.3 | AP36: =AJ36+AL36 -> 2071589.6 | AQ36: =+AQ33+AQ35 -> 248846.93 | AR36: =+AR33+AR35 -> 228825.55 | AS36: =+AO36+AQ36 -> 2263048.2 | AT36: =+AP36+AR36 -> 2300415.1 | AU36: =+AU33+AU35 -> 222406.89 | AV36: =+AV33+AV35 -> 185476 | AW36: =+AS36+AU36 -> 2485455.1 | AX36: =+AT36+AV36 -> 2485891.1 | AY36: =+AY33+AY35 -> 248846.93 | AZ36: =+AZ33+AZ35 -> 241440.82 | BA36: =+AQ36+AU36+AY36 -> 720100.74 | BB36: =+AR36+AV36+AZ36 -> 655742.37 | BC36: =+AM36+BA36 -> 1447755.8 | BD36: =+AN36+BB36 -> 1303429.5 | BE36: =+AW36+AY36 -> 2734302.1 | BF36: =+AX36+AZ36 -> 2727331.9 | BG36: 2494210.8 | BH36: 2449887.2 | BI36: 2630856 | BJ36: 2535723.4 | BK36: 2511464.9 | BL36: 2430492.2 | BM36: 2590026.6 | BN36: 2338989.5
C37: Average Manpower (Works) | D37: 3387 | E37: 3408 | F37: 3389 | G37: 3541 | H37: 3507 | I37: =+AVERAGE(E37,G37) -> 3474.5 | J37: =+AVERAGE(F37,H37) -> 3448 | K37: 3534 | L37: 3489 | M37: =+AVERAGE(E37,G37,K37) -> 3494.3333 | N37: =+AVERAGE(F37,H37,L37) -> 3461.6667 | O37: 3527 | P37: 3478 | Q37: =+AVERAGE(E37,G37,K37,O37) -> 3502.5 | R37: =+AVERAGE(F37,H37,L37,P37) -> 3465.75 | S37: 3524 | T37: 3465 | U37: =+AVERAGE(E37,G37,K37,O37,S37) -> 3506.8 | V37: =+AVERAGE(F37,H37,L37,P37,T37) -> 3465.6 | W37: 3517 | X37: 3450 | Y37: =+AVERAGE(Q37,S37,W37) -> 3514.5 | Z37: =+AVERAGE(P37,T37,X37) -> 3464.3333 | AA37: =+AVERAGE(E37,G37,K37,O37,S37,W37) -> 3508.5 | AB37: =+AVERAGE(X37,P37,L37,H37,T37,F37) -> 3463 | AC37: 3512 | AD37: 3449 | AE37: =+AVERAGE(E37,G37,K37,O37,S37,W37,AC37) -> 3509 | AF37: =+AVERAGE(F37,H37,L37,P37,T37,X37,AD37) -> 3461 | AG37: 3502 | AH37: 3439 | AI37: =AVERAGE(E37,G37,K37,O37,S37,W37,AC37,AG37) -> 3508.125 | AJ37: =AVERAGE(AH37,AD37,X37,T37,L37,P37,H37,F37) -> 3458.25 | AK37: 3500 | AL37: 3428 | AM37: =+AVERAGE(AC37,AG37,AK37) -> 3504.6667 | AN37: =+AVERAGE(AD37,AH37,AL37) -> 3438.6667 | AO37: =+AVERAGE(E37,G37,K37,O37,S37,W37,AC37,AG37,AK37) -> 3507.2222 | AP37: =+AVERAGE(F37,H37,L37,P37,T37,X37,AD37,AH37,AL37) -> 3454.8889 | AQ37: 3493 | AR37: 3412 | AS37: =+AVERAGE(E37,G37,K37,O37,S37,W37,AC37,AG37,AK37,AQ37) -> 3505.8 | AT37: =+AVERAGE(F37,H37,L37,P37,T37,X37,AD37,AH37,AL37,AR37) -> 3450.6 | AU37: 3491 | AV37: 3415 | AW37: =+AVERAGE(E37,G37,K37,O37,S37,W37,AC37,AG37,AK37,AQ37,AU37) -> 3504.4545 | AX37: =+AVERAGE(F37,H37,L37,P37,T37,X37,AD37,AH37,AL37,AR37,AV37) -> 3447.3636 | AY37: 3489 | AZ37: 3395 | BA37: =+AVERAGE(AQ37,AU37,AY37) -> 3491 | BB37: =+AVERAGE(AR37,AV37,AZ37) -> 3407.3333 | BC37: =+AVERAGE(AC37,AG37,AK37,AQ37,AU37,AY37) -> 3497.8333 | BD37: =+AVERAGE(AD37,AH37,AL37,AR37,AV37,AZ37) -> 3423 | BE37: =+AVERAGE(E37,G37,K37,O37,S37,W37,AC37,AG37,AK37,AQ37,AU37,AY37) -> 3503.1667 | BF37: =+AVERAGE(F37,H37,L37,P37,T37,X37,AD37,AH37,AL37,AR37,AV37,AZ37) -> 3443 | BG37: 3502.25 | BH37: 3544.5833 | BI37: 3607.8333 | BJ37: 3647.6667 | BK37: 3826.0833 | BL37: 3802.9167
C38: LP | D38: =+D36/(D37/365*D2) -> 832.74996 | E38: =+E36/(E37/365*E2) -> 694.95532 | F38: =+F36/(F37/365*F2) -> 802.23728 | G38: =+G36/(G37/365*G2) -> 814.88252 | H38: =+H36/(H37/365*H2) -> 799.42673 | I38: =+I36/(I37/365*I2) -> 757.28646 | J38: =+J36/(J37/365*J2) -> 801.00957 | K38: =+K36/(K37/365*K2) -> 817.70563 | ... BF38: =+BF36/(BF37/365*BF2) -> 792.13824 | BG38: 712.17383 | BH38: 691.16367 | BI38: 729.20664 | BJ38: 695.16315 | BK38: 656.40621 | BL38: 639.11266 | BM38: 645.95904 | BN38: 585.39376
B40: Labor productivity calculation (MoU) | C40: Crude Steel | D40: =+D33 -> 2817514.1 | E40: =+E33 -> 193691.15 | F40: =+F33 -> 223226 | H40: =+H33 -> 236638 | J40: =+J33 -> 459864 | L40: =+L33 -> 243453 | N40: =+N33 -> 703317 | P40: =+P33 -> 253662 | R40: =+R33 -> 956979 | T40: =+T33 -> 237622 | V40: =+V33 -> 1194601 | X40: =+X33 -> 226847 | Z40: =+Z33 -> 718131 | AB40: =+AB33 -> 1421448 | AD40: =+AD33 -> 179201 | AF40: =+AF33 -> 1600649 | AH40: =+AH33 -> 229502 | AJ40: =+AJ33 -> 1830151 | AL40: =+AL33 -> 234365 | AN40: =+AN33 -> 643068 | AR40: =+AR33 -> 228047 | AV40: =+AV33 -> 185016 | AZ40: =+AZ33 -> 241240 | BB40: =+BB33 -> 654303 | BD40: =+BD33 -> 1297371
C41: Pig+Eq | D41: =+D34 -> 6020 | E41: =+E34 -> 1945 | F41: =+F34 -> 471.09455 | H41: =+H34 -> 2950.1685 | J41: =+J34 -> 3421.263 | L41: =+L34 -> 1030.4578 | N41: =+N34 -> 4451.7208 | P41: =+P34 -> 0 | R41: =+R34 -> 4451.7208 | T41: =+T34 -> 164.4084 | V41: =+V34 -> 4616.1292 | X41: =+X34 -> 292.8108 | Z41: =+Z34 -> 457.2192 | AB41: =+AB34 -> 4908.94 | AD41: =+AD34 -> 9043.2686 | AF41: =+AF34 -> 13952.209 | AH41: =+AH34 -> 154.21623 | AJ41: =+AJ34 -> 14106.425 | AL41: =+AL34 -> 40.72516 | AN41: =+AN34 -> 9238.21 | AR41: =+AR34 -> 1557.1073 | AV41: =+AV34 -> 920 | AZ41: =+AZ34 -> 401.63435 | BB41: =+BB34 -> 2878.7416 | BD41: =+BD34 -> 12116.952
C42: Average MP = all regular employees + Contract workers deployed in the Works & NW areas of the Plant except workforce deployed in Projects. | D42: 9157 | E42: 9201 | F42: 9177 | AD42: 10508 | AH42: 10419 | AL42: 10292 | AN42: =+AVERAGE(AD42,AH42,AL42) -> 10406.333 | AR42: 9853 | AV42: 9444 | AZ42: 9233 | BB42: =+AVERAGE(AR42,AV42,AZ42) -> 9510 | BD42: =+AVERAGE(AN42,BB42) -> 9958.1667
C43: LP | D43: =(D40+D41)/(D42/$D$2*D2) -> 308.34707 | E43: =(E40+E41)/(E42/$D$2*E2) -> 258.6936 | F43: =(F40+F41)/(F42/$D$2*F2) -> 296.57273 | AD43: =+(AD41+AD40)/(AD42/365*AD2) -> 210.92734 | AH43: =+(AH41+AH40)/(AH42/365*AH2) -> 268.17839 | AL43: =+(AL41+AL40)/(AL42/365*AL2) -> 268.16346 | AN43: =+(AN41+AN40)/(AN42/365*AN2) -> 248.69028 | AR43: =+(AR41+AR40)/(AR42/365*AR2) -> 274.37361 | AV43: =+(AV41+AV40)/(AV42/365*AV2) -> 256.65063 | AZ43: =+(AZ41+AZ40)/(AZ42/365*AZ2) -> 308.14853 | BB43: =+(BB41+BB40)/(BB42/365*BB2) -> 280.25626 | BD43: =+(BD41+BD40)/(BD42/365*BD2) -> 263.72032
B56: Hot metal consumed in BOF | C56: MT | D56: =+(D16*D33)/1000 -> 2992200 | E56: =+(E16*E33)/1000 -> 205700 | F56: =+SMS!F15 -> 235708.2 | G56: =+(G16*G33)/1000 -> 259833.99 | H56: =+SMS!H15 -> 252686.9 | I56: =+(I16*I33)/1000 -> 465533.99 | J56: =+SMS!J15 -> 488395.1 | K56: =+(K16*K33)/1000 -> 251811.33 | L56: =+SMS!L15 -> 258527.52 | M56: =+(M16*M33)/1000 -> 717345.33 | N56: =+SMS!N15 -> 746922.62 | O56: =+(O16*O33)/1000 -> 254819.83 | P56: =+SMS!P15 -> 266778.08 | Q56: =+(Q16*Q33)/1000 -> 972165.16 | R56: =+SMS!R15 -> 1013700.7 | S56: =+(S16*S33)/1000 -> 254819.83 | T56: =+SMS!T15 -> 251918.72 | U56: =+(U16*U33)/1000 -> 1226985 | V56: =+SMS!V15 -> 1265619.4 | W56: =+(W16*W33)/1000 -> 133727.76 | X56: =+SMS!X15 -> 241323.3 | Y56: =+O56+S56+W56 -> 643367.42 | Z56: =+P56+T56+X56 -> 760020.09 | AA56: =+M56+Y56 -> 1360712.7 | AB56: =+N56+Z56 -> 1506942.7 | AC56: =+(AC16*AC33)/1000 -> 259833.99 | AD56: =+SMS!AD15 -> 190772.82 | AE56: =+(AE16*AE33)/1000 -> 1620546.7 | AF56: =+SMS!AF15 -> 1697715.5 | AG56: =+(AG16*AG33)/1000 -> 251811.33 | AH56: =+SMS!AH15 -> 243243.53 | AI56: =+(AI16*AI33)/1000 -> 1872358.1 | AJ56: =+SMS!AJ15 -> 1940959.1 | AK56: =+(AK16*AK33)/1000 -> 259833.99 | AL56: =+SMS!AL15 -> 250346.24 | AM56: =+AC56+AG56+AK56 -> 771479.32 | AN56: =+AD56+AH56+AL56 -> 684362.59 | AO56: =+(AO16*AO33)/1000 -> 2132192.1 | AP56: =+SMS!AP15 -> 2191305.3 | AQ56: =+(AQ16*AQ33)/1000 -> 263845.33 | AR56: =+SMS!AR15 -> 242224.07 | AS56: =+(AS16*AS33)/1000 -> 2396037.4 | AT56: =+SMS!AT15 -> 2433529.4 | AU56: =+(AU16*AU33)/1000 -> 235766.01 | AV56: =+SMS!AV15 -> 194681.08 | AW56: =+(AW16*AW33)/1000 -> 2631803.4 | AX56: =+SMS!AX15 -> 2628210.5 | AY56: =+(AY16*AY33)/1000 -> 263845.33 | AZ56: =+SMS!AZ15 -> 250513.95 | BA56: =+AQ56+AU56+AY56 -> 763456.66 | BB56: =+AR56+AV56+AZ56 -> 687419.09 | BC56: =+AM56+BA56 -> 1534936 | BD56: =+AN56+BB56 -> 1371781.7 | BE56: =+AW56+AY56 -> 2895648.7 | BF56: =+AX56+AZ56 -> 2878724.4 | BG56: 2638900 | BH56: 2582070.1 | BI56: 2777280 | BJ56: 2695862.8 | BK56: 2655000 | BL56: 2574868 | BM56: 2611100.5 | BN56: 2366123.2
B57: Total Scrap Charged | C57: MT | D57: =+(D17*D33)/1000 -> 95795.48 | E57: =+(E17*E33)/1000 -> 6585.4991 | F57: =+SMS!F19 -> 8946.7 | G57: =+(G17*G33)/1000 -> 8318.6025 | H57: =+SMS!H19 -> 6670.8 | I57: =+(I17*I33)/1000 -> 14904.102 | J57: =+SMS!J19 -> 15617.5 | K57: =+(K17*K33)/1000 -> 8061.7564 | L57: =+SMS!L19 -> 8404.2 | M57: =+(M17*M33)/1000 -> 22965.858 | N57: =+SMS!N19 -> 24021.7 | O57: =+(O17*O33)/1000 -> 8158.0737 | P57: =+SMS!P19 -> 11294.6 | Q57: =+(Q17*Q33)/1000 -> 31123.932 | R57: =+SMS!R19 -> 35316.3 | S57: =+(S17*S33)/1000 -> 8158.0737 | T57: =+SMS!T19 -> 8598.1 | U57: =+(U17*U33)/1000 -> 39282.005 | V57: =+SMS!V19 -> 43914.4 | W57: =+(W17*W33)/1000 -> 4281.3031 | X57: =+SMS!X19 -> 7722 | Y57: =+O57+S57+W57 -> 20597.45 | Z57: =+P57+T57+X57 -> 27614.7 | AA57: =+M57+Y57 -> 43563.308 | AB57: =+N57+Z57 -> 51636.4 | AC57: =+(AC17*AC33)/1000 -> 8318.6025 | AD57: =+SMS!AD19 -> 5530.6 | AE57: =+(AE17*AE33)/1000 -> 51881.911 | AF57: =+SMS!AF19 -> 57167 | AG57: =+(AG17*AG33)/1000 -> 8061.7564 | AH57: =+SMS!AH19 -> 8373.8 | AI57: =+(AI17*AI33)/1000 -> 59943.667 | AJ57: =+SMS!AJ19 -> 65540.8 | AK57: =+(AK17*AK33)/1000 -> 8318.6025 | AL57: =+SMS!AL19 -> 6546.8 | AM57: =+AC57+AG57+AK57 -> 24698.961 | AN57: =+AD57+AH57+AL57 -> 20451.2 | AO57: =+(AO17*AO33)/1000 -> 68262.27 | AP57: =+SMS!AP19 -> 72087.6 | AQ57: =+(AQ17*AQ33)/1000 -> 8447.0255 | AR57: =+SMS!AR19 -> 7578.7 | AS57: =+(AS17*AS33)/1000 -> 76709.295 | AT57: =+SMS!AT19 -> 79666.3 | AU57: =+(AU17*AU33)/1000 -> 7548.0642 | AV57: =+SMS!AV19 -> 8045 | AW57: =+(AW17*AW33)/1000 -> 84257.359 | AX57: =+SMS!AX19 -> 87711.3 | AY57: =+(AY17*AY33)/1000 -> 8447.0255 | AZ57: =+SMS!AZ19 -> 13265.9 | BA57: =+AQ57+AU57+AY57 -> 24442.115 | BB57: =+AR57+AV57+AZ57 -> 28889.6 | BC57: =+AM57+BA57 -> 49141.076 | BD57: =+AN57+BB57 -> 49340.8 | BE57: =+AW57+AY57 -> 92704.385 | BF57: =+AX57+AZ57 -> 100977.2 | BG57: 99581.132 | BH57: 91825 | BI57: 104803.02 | BJ57: 87073.52 | BK57: 121081.64 | BL57: 93275 | BM57: 128650.04 | BN57: 101615.76
B58: Fe-Mn | C58: MT | D58: =+(D66*'Maj Production Summ'!D$18)/1000 -> 3512.0014 | E58: =+(E66*'Maj Production Summ'!E$18)/1000 -> 241.43396 | F58: =+SMS!F55 -> 409 | G58: =+(G66*'Maj Production Summ'!G$18)/1000 -> 304.97204 | H58: =+SMS!H55 -> 297 | I58: =+(I66*'Maj Production Summ'!I$18)/1000 -> 546.406 | J58: =+SMS!J55 -> 706 | K58: =+(K66*'Maj Production Summ'!K$18)/1000 -> 295.55569 | L58: =+SMS!L55 -> 405 | M58: =+(M66*'Maj Production Summ'!M$18)/1000 -> 841.96169 | N58: =+SMS!N55 -> 1111 | O58: =+(O66*'Maj Production Summ'!O$18)/1000 -> 299.08683 | P58: =+SMS!P55 -> 383 | Q58: =+(Q66*'Maj Production Summ'!Q$18)/1000 -> 1141.0485 | R58: =+SMS!R55 -> 1494 | S58: =+(S66*'Maj Production Summ'!S$18)/1000 -> 299.08683 | T58: =+SMS!T55 -> 300 | U58: =+(U66*'Maj Production Summ'!U$18)/1000 -> 1440.1353 | V58: =+SMS!V55 -> 1794 | W58: =+(W66*'Maj Production Summ'!W$18)/1000 -> 156.95879 | X58: =+SMS!X55 -> 293 | Y58: =+O58+S58+W58 -> 755.13244 | Z58: =+P58+T58+X58 -> 976 | AA58: =+M58+Y58 -> 1597.0941 | AB58: =+N58+Z58 -> 2087 | AC58: =+(AC66*'Maj Production Summ'!AC$18)/1000 -> 304.97204 | AD58: =+SMS!AD55 -> 251 | AE58: =+(AE66*'Maj Production Summ'!AE$18)/1000 -> 1902.0662 | AF58: =+SMS!AF55 -> 2338 | AG58: =+(AG66*'Maj Production Summ'!AG$18)/1000 -> 295.55569 | AH58: =+SMS!AH55 -> 290 | AI58: =+(AI66*'Maj Production Summ'!AI$18)/1000 -> 2197.6219 | AJ58: =+SMS!AJ55 -> 2628 | AK58: =+(AK66*'Maj Production Summ'!AK$18)/1000 -> 304.97204 | AL58: =+SMS!AL55 -> 401.53 | AM58: =+AC58+AG58+AK58 -> 905.49978 | AN58: =+AD58+AH58+AL58 -> 942.53 | AO58: =+(AO66*'Maj Production Summ'!AO$18)/1000 -> 2502.5939 | AP58: =+SMS!AP55 -> 3029.53 | AQ58: =+(AQ66*'Maj Production Summ'!AQ$18)/1000 -> 309.68022 | AR58: =+SMS!AR55 -> 267.8 | AS58: =+(AS66*'Maj Production Summ'!AS$18)/1000 -> 2812.2741 | AT58: =+SMS!AT55 -> 3297.33 | AU58: =+(AU66*'Maj Production Summ'!AU$18)/1000 -> 276.72299 | AV58: =+SMS!AV55 -> 135 | AW58: =+(AW66*'Maj Production Summ'!AW$18)/1000 -> 3088.9971 | AX58: =+SMS!AX55 -> 3432.33 | AY58: =+(AY66*'Maj Production Summ'!AY$18)/1000 -> 309.68022 | AZ58: =+SMS!AZ55 -> 421 | BA58: =+AQ58+AU58+AY58 -> 896.08343 | BB58: =+AR58+AV58+AZ58 -> 823.8 | BC58: =+AM58+BA58 -> 1801.5832 | BD58: =+AN58+BB58 -> 1766.33 | BE58: =+AW58+AY58 -> 3398.6773 | BF58: =+AX58+AZ58 -> 3853.33 | BG58: 4107.7217 | BH58: 3222 | BI58: 3385.0943 | BJ58: 4727 | BK58: 4500 | BL58: 4569.84 | BM58: 6693.3528 | BN58: 4136
B59: LCFeMn | C59: MT | D59: =+(D67*'Maj Production Summ'!D$18)/1000 -> 2201.7356 | E59: =+(E67*'Maj Production Summ'!E$18)/1000 -> 151.35921 | F59: =+SMS!F56 -> 140 | G59: =+(G67*'Maj Production Summ'!G$18)/1000 -> 191.19235 | H59: =+SMS!H56 -> 178 | I59: 0 | J59: =+SMS!J56 -> 318 | K59: =+(K67*'Maj Production Summ'!K$18)/1000 -> 185.28908 | L59: =+SMS!L56 -> 105 | M59: 0 | N59: =+SMS!N56 -> 423 | O59: =+(O67*'Maj Production Summ'!O$18)/1000 -> 187.50281 | P59: =+SMS!P56 -> 137 | Q59: 0 | R59: =+SMS!R56 -> 560 | S59: =+(S67*'Maj Production Summ'!S$18)/1000 -> 187.50281 | T59: =+SMS!T56 -> 131 | U59: 0 | V59: =+SMS!V56 -> 691 | W59: =+(W67*'Maj Production Summ'!W$18)/1000 -> 98.400233 | X59: =+SMS!X56 -> 129 | Y59: =+O59+S59+W59 -> 473.40584 | Z59: =+P59+T59+X59 -> 397 | AA59: =+M59+Y59 -> 473.40584 | AB59: =+N59+Z59 -> 820 | AC59: =+(AC67*'Maj Production Summ'!AC$18)/1000 -> 191.19235 | AD59: =+SMS!AD56 -> 94 | AE59: 0 | AF59: =+SMS!AF56 -> 914 | AG59: =+(AG67*'Maj Production Summ'!AG$18)/1000 -> 185.28908 | AH59: =+SMS!AH56 -> 112 | AI59: 0 | AJ59: =+SMS!AJ56 -> 1026 | AK59: =+(AK67*'Maj Production Summ'!AK$18)/1000 -> 191.19235 | AL59: =+SMS!AL56 -> 70 | AM59: =+AC59+AG59+AK59 -> 567.67378 | AN59: =+AD59+AH59+AL59 -> 276 | AO59: 0 | AP59: =+SMS!AP56 -> 1096 | AQ59: =+(AQ67*'Maj Production Summ'!AQ$18)/1000 -> 194.14399 | AR59: =+SMS!AR56 -> 88 | AS59: 0 | AT59: =+SMS!AT56 -> 1184 | AU59: =+(AU67*'Maj Production Summ'!AU$18)/1000 -> 173.48253 | AV59: =+SMS!AV56 -> 143.714 | AW59: 0 | AX59: =+SMS!AX56 -> 1327.714 | AY59: =+(AY67*'Maj Production Summ'!AY$18)/1000 -> 194.14399 | AZ59: =+SMS!AZ56 -> 122 | BA59: =+AQ59+AU59+AY59 -> 561.77051 | BB59: =+AR59+AV59+AZ59 -> 353.714 | BC59: =+AM59+BA59 -> 1129.4443 | BD59: =+AN59+BB59 -> 629.714 | BE59: =+AW59+AY59 -> 194.14399 | BF59: =+AX59+AZ59 -> 1449.714 | BG59: 0 | BH59: 1433 | BI59: 0 | BJ59: 1668.305 | BK59: 0 | BL59: 1122.042 | BM59: 0 | BN59: 968.34
B60: Total Fe-Mn | C60: MT | D60: =SUM(D58:D59) -> 5713.737 | E60: =SUM(E58:E59) -> 392.79316 | F60: =SUM(F58:F59) -> 549 | G60: =SUM(G58:G59) -> 496.1644 | H60: =SUM(H58:H59) -> 475 | I60: =SUM(I58:I59) -> 546.406 | J60: =SUM(J58:J59) -> 1024 | K60: =SUM(K58:K59) -> 480.84477 | ... BF60: =SUM(BF58:BF59) -> 5303.044 | BG60: 4107.7217 | BH60: 4655 | BI60: 3385.0943 | BJ60: 6395.305 | BK60: 4500 | BL60: 5691.882 | BM60: 6693.3528 | BN60: 5104.34
B61: Si-Mn | C61: MT | D61: =+(D69*'Maj Production Summ'!D$18)/1000 -> 39108.929 | E61: =+(E69*'Maj Production Summ'!E$18)/1000 -> 2688.5592 | F61: =+SMS!F58 -> 2872 | G61: =+(G69*'Maj Production Summ'!G$18)/1000 -> 3396.1063 | H61: =+SMS!H58 -> 3570 | I61: =+(I69*'Maj Production Summ'!I$18)/1000 -> 6084.6655 | J61: =+SMS!J58 -> 6442 | K61: =+(K69*'Maj Production Summ'!K$18)/1000 -> 3291.2478 | L61: =+SMS!L58 -> 3768 | M61: =+(M69*'Maj Production Summ'!M$18)/1000 -> 9375.9132 | N61: =+SMS!N58 -> 10210 | O61: =+(O69*'Maj Production Summ'!O$18)/1000 -> 3330.5697 | P61: =+SMS!P58 -> 4098 | Q61: =+(Q69*'Maj Production Summ'!Q$18)/1000 -> 12706.483 | R61: =+SMS!R58 -> 14308 | S61: =+(S69*'Maj Production Summ'!S$18)/1000 -> 3330.5697 | T61: =+SMS!T58 -> 3587.02 | U61: =+(U69*'Maj Production Summ'!U$18)/1000 -> 16037.053 | V61: =+SMS!V58 -> 17895.02 | W61: =+(W69*'Maj Production Summ'!W$18)/1000 -> 1747.861 | X61: =+SMS!X58 -> 3011.11 | Y61: =+O61+S61+W61 -> 8409.0004 | Z61: =+P61+T61+X61 -> 10696.13 | AA61: =+M61+Y61 -> 17784.914 | AB61: =+N61+Z61 -> 20906.13 | AC61: =+(AC69*'Maj Production Summ'!AC$18)/1000 -> 3396.1063 | AD61: =+SMS!AD58 -> 2470 | AE61: =+(AE69*'Maj Production Summ'!AE$18)/1000 -> 21181.02 | AF61: =+SMS!AF58 -> 23376.13 | AG61: =+(AG69*'Maj Production Summ'!AG$18)/1000 -> 3291.2478 | AH61: =+SMS!AH58 -> 2814 | AI61: =+(AI69*'Maj Production Summ'!AI$18)/1000 -> 24472.268 | AJ61: =+SMS!AJ58 -> 26190.13 | AK61: =+(AK69*'Maj Production Summ'!AK$18)/1000 -> 3396.1063 | AL61: =+SMS!AL58 -> 3092 | AM61: =+AC61+AG61+AK61 -> 10083.46 | AN61: =+AD61+AH61+AL61 -> 8376 | AO61: =+(AO69*'Maj Production Summ'!AO$18)/1000 -> 27868.374 | AP61: =+SMS!AP58 -> 29282.13 | AQ61: =+(AQ69*'Maj Production Summ'!AQ$18)/1000 -> 3448.5356 | AR61: =+SMS!AR58 -> 3008 | AS61: =+(AS69*'Maj Production Summ'!AS$18)/1000 -> 31316.91 | AT61: =+SMS!AT58 -> 32290.13 | AU61: =+(AU69*'Maj Production Summ'!AU$18)/1000 -> 3081.5307 | AV61: =+SMS!AV58 -> 2409 | AW61: =+(AW69*'Maj Production Summ'!AW$18)/1000 -> 34398.44 | AX61: =+SMS!AX58 -> 34699.13 | AY61: =+(AY69*'Maj Production Summ'!AY$18)/1000 -> 3448.5356 | AZ61: =+SMS!AZ58 -> 3289 | BA61: =+AQ61+AU61+AY61 -> 9978.6018 | BB61: =+AR61+AV61+AZ61 -> 8706 | BC61: =+AM61+BA61 -> 20062.062 | BD61: =+AN61+BB61 -> 17082 | BE61: =+AW61+AY61 -> 37846.976 | BF61: =+AX61+AZ61 -> 37988.13 | BG61: 45682.844 | BH61: 39439.44 | BI61: 44076.08 | BJ61: 45680 | BK61: 40000 | BL61: 44647.62 | BM61: 42007.866 | BN61: 36347
B62: LP Si-Mn | C62: MT | F62: =+SMS!F59 -> 0 | H62: =+SMS!H59 -> 0 | J62: =+SMS!J59 -> 0 | L62: =+SMS!L59 -> 0 | N62: =+SMS!N59 -> 0 | P62: =+SMS!P59 -> 0 | R62: =+SMS!R59 -> 0 | T62: =+SMS!T59 -> 0 | V62: =+SMS!V59 -> 0 | X62: =+SMS!X59 -> 0 | Z62: =P62+T62+X62 -> 0 | AB62: =+N62+Z62 -> 0 | AD62: =+SMS!AD59 -> 0 | AF62: =+SMS!AF59 -> 0 | AH62: =+SMS!AH59 -> 0 | AJ62: =+SMS!AJ59 -> 0 | AL62: =+SMS!AL59 -> 0 | AN62: =AD62+AH62+AL62 -> 0 | AP62: =+SMS!AP59 -> 0 | AR62: =+SMS!AR59 -> 0 | AT62: =+SMS!AT59 -> 0 | AV62: =+SMS!AV59 -> 0 | AX62: =+SMS!AX59 -> 0 | AZ62: =+SMS!AZ59 -> 0 | BB62: =+SMS!BB59 -> 0 | BD62: =+SMS!BD59 -> 0 | BF62: =+SMS!BF59 -> 0 | BH62: 0 | BJ62: 25.81
B63: Total Si-Mn | C63: MT | D63: =SUM(D61:D62) -> 39108.929 | E63: =SUM(E61:E62) -> 2688.5592 | F63: =SUM(F61:F62) -> 2872 | G63: =SUM(G61:G62) -> 3396.1063 | H63: =SUM(H61:H62) -> 3570 | I63: =SUM(I61:I62) -> 6084.6655 | J63: =SUM(J61:J62) -> 6442 | K63: =SUM(K61:K62) -> 3291.2478 | ... BF63: =SUM(BF61:BF62) -> 37988.13 | BG63: 45682.844 | BH63: 39439.44 | BI63: 44076.08 | BJ63: 45705.81
B64: Fe-Si | C64: MT | D64: =+(D72*'Maj Production Summ'!D$18)/1000 -> 6016.8906 | E64: =+(E72*'Maj Production Summ'!E$18)/1000 -> 413.63358 | F64: =+SMS!F61 -> 482 | G64: =+(G72*'Maj Production Summ'!G$18)/1000 -> 522.48938 | H64: =+SMS!H61 -> 551 | I64: =+(I72*'Maj Production Summ'!I$18)/1000 -> 936.12296 | J64: =+SMS!J61 -> 1033 | K64: =+(K72*'Maj Production Summ'!K$18)/1000 -> 506.35694 | L64: =+SMS!L61 -> 526.21 | M64: =+(M72*'Maj Production Summ'!M$18)/1000 -> 1442.4799 | N64: =+SMS!N61 -> 1559.21 | O64: =+(O72*'Maj Production Summ'!O$18)/1000 -> 512.40661 | P64: =+SMS!P61 -> 485.894 | Q64: =+(Q72*'Maj Production Summ'!Q$18)/1000 -> 1954.8865 | R64: =+SMS!R61 -> 2045.104 | S64: =+(S72*'Maj Production Summ'!S$18)/1000 -> 512.40661 | T64: =+SMS!T61 -> 516 | U64: =+(U72*'Maj Production Summ'!U$18)/1000 -> 2467.2931 | V64: =+SMS!V61 -> 2561.104 | W64: =+(W72*'Maj Production Summ'!W$18)/1000 -> 268.9076 | X64: =+SMS!X61 -> 481 | Y64: =+O64+S64+W64 -> 1293.7208 | Z64: =+P64+T64+X64 -> 1482.894 | AA64: =+M64+Y64 -> 2736.2007 | AB64: =+N64+Z64 -> 3042.104 | AC64: =+(AC72*'Maj Production Summ'!AC$18)/1000 -> 522.48938 | AD64: =+SMS!AD61 -> 387 | AE64: =+(AE72*'Maj Production Summ'!AE$18)/1000 -> 3258.6901 | AF64: =+SMS!AF61 -> 3429.104 | AG64: =+(AG72*'Maj Production Summ'!AG$18)/1000 -> 506.35694 | AH64: =+SMS!AH61 -> 503 | AI64: =+(AI72*'Maj Production Summ'!AI$18)/1000 -> 3765.047 | AJ64: =+SMS!AJ61 -> 3932.104 | AK64: =+(AK72*'Maj Production Summ'!AK$18)/1000 -> 522.48938 | AL64: =+SMS!AL61 -> 537 | AM64: =+AC64+AG64+AK64 -> 1551.3357 | AN64: =+AD64+AH64+AL64 -> 1427 | AO64: =+(AO72*'Maj Production Summ'!AO$18)/1000 -> 4287.5364 | AP64: =+SMS!AP61 -> 4469.104 | AQ64: =+(AQ72*'Maj Production Summ'!AQ$18)/1000 -> 530.5556 | AR64: =+SMS!AR61 -> 559 | AS64: =+(AS72*'Maj Production Summ'!AS$18)/1000 -> 4818.092 | AT64: =+SMS!AT61 -> 5028.104 | AU64: =+(AU72*'Maj Production Summ'!AU$18)/1000 -> 474.09206 | AV64: =+SMS!AV61 -> 418 | AW64: =+(AW72*'Maj Production Summ'!AW$18)/1000 -> 5292.1841 | AX64: =+SMS!AX61 -> 5446.104 | AY64: =+(AY72*'Maj Production Summ'!AY$18)/1000 -> 530.5556 | AZ64: =+SMS!AZ61 -> 487 | BA64: =+AQ64+AU64+AY64 -> 1535.2033 | BB64: =+AR64+AV64+AZ64 -> 1464 | BC64: =+AM64+BA64 -> 3086.539 | BD64: =+AN64+BB64 -> 2891 | BE64: =+AW64+AY64 -> 5822.7397 | BF64: =+AX64+AZ64 -> 5933.104 | BG64: 5352.4858 | BH64: 5627.407 | BI64: 7386.6389 | BJ64: 5310 | BK64: 8000 | BL64: 5205.89 | BM64: 7796.1924 | BN64: 5192
B65: Ferro Alloys Break-up
B66: Fe-Mn | C66: Kg/TCS | D66: 1.2464894 | E66: =+$D$66 -> 1.2464894 | F66: =+(F58/'Maj Production Summ'!F$18)*1000 -> 1.8322238 | G66: =+$D$66 -> 1.2464894 | H66: =+(H58/'Maj Production Summ'!H$18)*1000 -> 1.2550816 | I66: =+$D$66 -> 1.2464894 | J66: =+(J58/'Maj Production Summ'!J$18)*1000 -> 1.5352365 | K66: =+$D$66 -> 1.2464894 | L66: =+(L58/'Maj Production Summ'!L$18)*1000 -> 1.6635655 | M66: =+$D$66 -> 1.2464894 | N66: =+(N58/'Maj Production Summ'!N$18)*1000 -> 1.5796575 | O66: =+$D$66 -> 1.2464894 | P66: =+(P58/'Maj Production Summ'!P$18)*1000 -> 1.5098832 | Q66: =+$D$66 -> 1.2464894 | R66: =+(R58/'Maj Production Summ'!R$18)*1000 -> 1.5611628 | S66: =+$D$66 -> 1.2464894 | T66: =+(T58/'Maj Production Summ'!T$18)*1000 -> 1.2625094 | U66: =+$D$66 -> 1.2464894 | V66: =+(V58/'Maj Production Summ'!V$18)*1000 -> 1.5017567 | W66: =+$D$66 -> 1.2464894 | X66: =+(X58/'Maj Production Summ'!X$18)*1000 -> 1.2916195 | Y66: =+$D$66 -> 1.2464894 | Z66: =+(Z58/'Maj Production Summ'!Z$18)*1000 -> 1.3590835 | AA66: =+$D$66 -> 1.2464894 | AB66: =+(AB58/'Maj Production Summ'!AB$18)*1000 -> 1.4682211 | AC66: =+$D$66 -> 1.2464894 | AD66: =+(AD58/'Maj Production Summ'!AD$18)*1000 -> 1.4006618 | AE66: =+$D$66 -> 1.2464894 | AF66: =+(AF58/'Maj Production Summ'!AF$18)*1000 -> 1.4606575 | AG66: =+$D$66 -> 1.2464894 | AH66: =+(AH58/'Maj Production Summ'!AH$18)*1000 -> 1.2636055 | AI66: =+$D$66 -> 1.2464894 | AJ66: =+(AJ58/'Maj Production Summ'!AJ$18)*1000 -> 1.4359471 | AK66: =+$D$66 -> 1.2464894 | AL66: =+(AL58/'Maj Production Summ'!AL$18)*1000 -> 1.7132678 | AM66: =+$D$66 -> 1.2464894 | AN66: =+(AN58/'Maj Production Summ'!AN$18)*1000 -> 1.465677 | AO66: =+$D$66 -> 1.2464894 | AP66: =+(AP58/'Maj Production Summ'!AP$18)*1000 -> 1.4674287 | AQ66: =+$D$66 -> 1.2464894 | AR66: =+(AR58/'Maj Production Summ'!AR$18)*1000 -> 1.1743193 | AS66: =+$D$66 -> 1.2464894 | AT66: =+(AT58/'Maj Production Summ'!AT$18)*1000 -> 1.4382724 | AU66: =+$D$66 -> 1.2464894 | AV66: =+(AV58/'Maj Production Summ'!AV$18)*1000 -> 0.72966662 | AW66: =+$D$66 -> 1.2464894 | AX66: =+(AX58/'Maj Production Summ'!AX$18)*1000 -> 1.3853564 | AY66: =+$D$66 -> 1.2464894 | AZ66: =+(AZ58/'Maj Production Summ'!AZ$18)*1000 -> 1.7451501 | BA66: =+$D$66 -> 1.2464894 | BB66: =+(BB58/'Maj Production Summ'!BB$18)*1000 -> 1.2590497 | BC66: =+$D$66 -> 1.2464894 | BD66: =+(BD58/'Maj Production Summ'!BD$18)*1000 -> 1.3614687 | BE66: =+$D$66 -> 1.2464894 | BF66: =+(BF58/'Maj Production Summ'!BF$18)*1000 -> 1.4172808 | BG66: 1.65 | BH66: 1.3221396 | BI66: 1.2919835 | BJ66: 1.8691737 | BK66: 1.8 | BL66: 1.8865517 | BM66: 2.60138 | BN66: 1.780674
B67: LCFeMn | C67: Kg/TCS | D67: 0.78144617 | E67: =+$D$67 -> 0.78144617 | F67: =+(F59/'Maj Production Summ'!F$18)*1000 -> 0.62716709 | G67: =+$D$67 -> 0.78144617 | H67: =+(H59/'Maj Production Summ'!H$18)*1000 -> 0.75220379 | I67: =+$D$67 -> 0.78144617 | J67: =+(J59/'Maj Production Summ'!J$18)*1000 -> 0.69150879 | K67: =+$D$67 -> 0.78144617 | L67: =+(L59/'Maj Production Summ'!L$18)*1000 -> 0.43129475 | M67: =+$D$67 -> 0.78144617 | N67: =+(N59/'Maj Production Summ'!N$18)*1000 -> 0.60143577 | O67: =+$D$67 -> 0.78144617 | P67: =+(P59/'Maj Production Summ'!P$18)*1000 -> 0.54008878 | Q67: =+$D$67 -> 0.78144617 | R67: =+(R59/'Maj Production Summ'!R$18)*1000 -> 0.58517481 | S67: =+$D$67 -> 0.78144617 | T67: =+(T59/'Maj Production Summ'!T$18)*1000 -> 0.55129576 | U67: =+$D$67 -> 0.78144617 | V67: =+(V59/'Maj Production Summ'!V$18)*1000 -> 0.57843581 | W67: =+$D$67 -> 0.78144617 | X67: =+(X59/'Maj Production Summ'!X$18)*1000 -> 0.56866522 | Y67: =+$D$67 -> 0.78144617 | Z67: =+(Z59/'Maj Production Summ'!Z$18)*1000 -> 0.55282393 | AA67: =+$D$67 -> 0.78144617 | AB67: =+(AB59/'Maj Production Summ'!AB$18)*1000 -> 0.57687654 | AC67: =+$D$67 -> 0.78144617 | AD67: =+(AD59/'Maj Production Summ'!AD$18)*1000 -> 0.52455064 | AE67: =+$D$67 -> 0.78144617 | AF67: =+(AF59/'Maj Production Summ'!AF$18)*1000 -> 0.57101838 | AG67: =+$D$67 -> 0.78144617 | AH67: =+(AH59/'Maj Production Summ'!AH$18)*1000 -> 0.48801318 | AI67: =+$D$67 -> 0.78144617 | AJ67: =+(AJ59/'Maj Production Summ'!AJ$18)*1000 -> 0.56060948 | AK67: =+$D$67 -> 0.78144617 | AL67: =+(AL59/'Maj Production Summ'!AL$18)*1000 -> 0.29867941 | AM67: =+$D$67 -> 0.78144617 | AN67: =+(AN59/'Maj Production Summ'!AN$18)*1000 -> 0.42919256 | AO67: =+$D$67 -> 0.78144617 | AP67: =+(AP59/'Maj Production Summ'!AP$18)*1000 -> 0.53087503 | AQ67: =+$D$67 -> 0.78144617 | AR67: =+(AR59/'Maj Production Summ'!AR$18)*1000 -> 0.38588537 | AS67: =+$D$67 -> 0.78144617 | AT67: =+(AT59/'Maj Production Summ'!AT$18)*1000 -> 0.51645255 | AU67: =+$D$67 -> 0.78144617 | AV67: =+(AV59/'Maj Production Summ'!AV$18)*1000 -> 0.77676525 | AW67: =+$D$67 -> 0.78144617 | AX67: =+(AX59/'Maj Production Summ'!AX$18)*1000 -> 0.53589169 | AY67: =+$D$67 -> 0.78144617 | AZ67: =+(AZ59/'Maj Production Summ'!AZ$18)*1000 -> 0.50572044 | BA67: =+$D$67 -> 0.78144617 | BB67: =+(BB59/'Maj Production Summ'!BB$18)*1000 -> 0.54059663 | BC67: =+$D$67 -> 0.78144617 | BD67: =+(BD59/'Maj Production Summ'!BD$18)*1000 -> 0.48537697 | BE67: =+$D$67 -> 0.78144617 | BF67: =+(BF59/'Maj Production Summ'!BF$18)*1000 -> 0.53321461 | BG67: 0.85 | BH67: 0.58802795 | BI67: 0.24 | BJ67: 0.65968939 | BK67: 0 | BL67: 0.46320883 | BM67: 0 | BN67: 0.41689987
B68: Total Fe-Mn | C68: Kg/TCS | D68: =SUM(D66:D67) -> 2.0279355 | E68: =SUM(E66:E67) -> 2.0279355 | F68: =SUM(F66:F67) -> 2.4593909 | G68: =SUM(G66:G67) -> 2.0279355 | H68: =SUM(H66:H67) -> 2.0072854 | I68: =SUM(I66:I67) -> 2.0279355 | J68: =SUM(J66:J67) -> 2.2267453 | K68: =SUM(K66:K67) -> 2.0279355 | ... BF68: =SUM(BF66:BF67) -> 1.9504954 | BG68: 2.5 | BH68: 1.9101675 | BI68: 1.5319835 | BJ68: 2.5288631 | BK68: 1.8 | BL68: 2.3497605 | BM68: 2.60138 | BN68: 2.1975739
B69: Si-Mn | C69: Kg/TCS | D69: 13.880651 | E69: =+$D$69 -> 13.880651 | F69: =+(F61/'Maj Production Summ'!F$18)*1000 -> 12.865885 | G69: =+$D$69 -> 13.880651 | H69: =+(H61/'Maj Production Summ'!H$18)*1000 -> 15.086334 | I69: =+$D$69 -> 13.880651 | J69: =+(J61/'Maj Production Summ'!J$18)*1000 -> 14.008489 | K69: =+$D$69 -> 13.880651 | L69: =+(L61/'Maj Production Summ'!L$18)*1000 -> 15.47732 | M69: =+$D$69 -> 13.880651 | N69: =+(N61/'Maj Production Summ'!N$18)*1000 -> 14.516925 | O69: =+$D$69 -> 13.880651 | P69: =+(P61/'Maj Production Summ'!P$18)*1000 -> 16.155356 | Q69: =+$D$69 -> 13.880651 | R69: =+(R61/'Maj Production Summ'!R$18)*1000 -> 14.951216 | S69: =+$D$69 -> 13.880651 | T69: =+(T61/'Maj Production Summ'!T$18)*1000 -> 15.095488 | U69: =+$D$69 -> 13.880651 | V69: =+(V61/'Maj Production Summ'!V$18)*1000 -> 14.979914 | W69: =+$D$69 -> 13.880651 | X69: =+(X61/'Maj Production Summ'!X$18)*1000 -> 13.273748 | Y69: =+$D$69 -> 13.880651 | Z69: =+(Z61/'Maj Production Summ'!Z$18)*1000 -> 14.894399 | AA69: =+$D$69 -> 13.880651 | AB69: =+(AB61/'Maj Production Summ'!AB$18)*1000 -> 14.707629 | AC69: =+$D$69 -> 13.880651 | AD69: =+(AD61/'Maj Production Summ'!AD$18)*1000 -> 13.783405 | AE69: =+$D$69 -> 13.880651 | AF69: =+(AF61/'Maj Production Summ'!AF$18)*1000 -> 14.604157 | AG69: =+$D$69 -> 13.880651 | AH69: =+(AH61/'Maj Production Summ'!AH$18)*1000 -> 12.261331 | AI69: =+$D$69 -> 13.880651 | AJ69: =+(AJ61/'Maj Production Summ'!AJ$18)*1000 -> 14.310366 | AK69: =+$D$69 -> 13.880651 | AL69: =+(AL61/'Maj Production Summ'!AL$18)*1000 -> 13.193096 | AM69: =+$D$69 -> 13.880651 | AN69: =+(AN61/'Maj Production Summ'!AN$18)*1000 -> 13.025061 | AO69: =+$D$69 -> 13.880651 | AP69: =+(AP61/'Maj Production Summ'!AP$18)*1000 -> 14.183533 | AQ69: =+$D$69 -> 13.880651 | AR69: =+(AR61/'Maj Production Summ'!AR$18)*1000 -> 13.190263 | AS69: =+$D$69 -> 13.880651 | AT69: =+(AT61/'Maj Production Summ'!AT$18)*1000 -> 14.08473 | AU69: =+$D$69 -> 13.880651 | AV69: =+(AV61/'Maj Production Summ'!AV$18)*1000 -> 13.020496 | AW69: =+$D$69 -> 13.880651 | AX69: =+(AX61/'Maj Production Summ'!AX$18)*1000 -> 14.005257 | AY69: =+$D$69 -> 13.880651 | AZ69: =+(AZ61/'Maj Production Summ'!AZ$18)*1000 -> 13.633726 | BA69: =+$D$69 -> 13.880651 | BB69: =+(BB61/'Maj Production Summ'!BB$18)*1000 -> 13.305762 | BC69: =+$D$69 -> 13.880651 | BD69: =+(BD61/'Maj Production Summ'!BD$18)*1000 -> 13.166627 | BE69: =+$D$69 -> 13.880651 | BF69: =+(BF61/'Maj Production Summ'!BF$18)*1000 -> 13.972291 | BG69: 18.35 | BH69: 16.183875 | BI69: 16.822447 | BJ69: 18.063011 | BK69: 16 | BL69: 18.431727 | BM69: 16.32641 | BN69: 15.648491
B70: LP Si-Mn | C70: Kg/TCS | D70: 0 | E70: =D70 -> 0 | F70: =+(F62/'Maj Production Summ'!F$18)*1000 -> 0 | G70: =F70 -> 0 | H70: =+(H62/'Maj Production Summ'!H$18)*1000 -> 0 | J70: =+(J62/'Maj Production Summ'!J$18)*1000 -> 0 | K70: =J70 -> 0 | L70: =+(L62/'Maj Production Summ'!L$18)*1000 -> 0 | M70: =D70 -> 0 | N70: =+(N62/'Maj Production Summ'!N$18)*1000 -> 0 | O70: =N70 -> 0 | P70: =+(P62/'Maj Production Summ'!P$18)*1000 -> 0 | R70: =+(R62/'Maj Production Summ'!R$18)*1000 -> 0 | S70: =R70 -> 0 | T70: =+(T62/'Maj Production Summ'!T$18)*1000 -> 0 | V70: =+(V62/'Maj Production Summ'!V$18)*1000 -> 0 | W70: =V70 -> 0 | X70: =+(X62/'Maj Production Summ'!X$18)*1000 -> 0 | Y70: =D70 -> 0 | Z70: =+(Z62/'Maj Production Summ'!Z$18)*1000 -> 0 | AA70: =D70 -> 0 | AB70: =+(AB62/'Maj Production Summ'!AB$18)*1000 -> 0 | AC70: =AB70 -> 0 | AD70: =+(AD62/'Maj Production Summ'!AD$18)*1000 -> 0 | AF70: =+(AF62/'Maj Production Summ'!AF$18)*1000 -> 0 | AG70: =AF70 -> 0 | AH70: =+(AH62/'Maj Production Summ'!AH$18)*1000 -> 0 | AJ70: =+(AJ62/'Maj Production Summ'!AJ$18)*1000 -> 0 | AK70: =AJ70 -> 0 | AL70: =+(AL62/'Maj Production Summ'!AL$18)*1000 -> 0 | AM70: 0 | AN70: =+(AN62/'Maj Production Summ'!AN$18)*1000 -> 0 | AO70: =D70 -> 0 | AP70: =+(AP62/'Maj Production Summ'!AP$18)*1000 -> 0 | AQ70: =AP70 -> 0 | AR70: =+(AR62/'Maj Production Summ'!AR$18)*1000 -> 0 | AS70: =D70 -> 0 | AT70: =+(AT62/'Maj Production Summ'!AT$18)*1000 -> 0 | AU70: =AT70 -> 0 | AV70: =+(AV62/'Maj Production Summ'!AV$18)*1000 -> 0 | AW70: =H70 -> 0 | AX70: =+(AX62/'Maj Production Summ'!AX$18)*1000 -> 0 | AY70: =AX70 -> 0 | AZ70: =+(AZ62/'Maj Production Summ'!AZ$18)*1000 -> 0 | BA70: =L70 -> 0 | BB70: =+(BB62/'Maj Production Summ'!BB$18)*1000 -> 0 | BC70: =N70 -> 0 | BD70: =+(BD62/'Maj Production Summ'!BD$18)*1000 -> 0 | BE70: =P70 -> 0 | BF70: =+(BF62/'Maj Production Summ'!BF$18)*1000 -> 0 | BG70: 0 | BH70: 0 | BI70: 0 | BJ70: 0.010205918
B71: Total Si-Mn | C71: Kg/TCS | D71: =SUM(D69:D70) -> 13.880651 | E71: =+$D$69 -> 13.880651 | F71: =SUM(F69:F70) -> 12.865885 | G71: =+$D$69 -> 13.880651 | H71: =SUM(H69:H70) -> 15.086334 | I71: =+$D$69 -> 13.880651 | J71: =SUM(J69:J70) -> 14.008489 | K71: =+$D$69 -> 13.880651 | L71: =SUM(L69:L70) -> 15.47732 | M71: =+$D$69 -> 13.880651 | N71: =SUM(N69:N70) -> 14.516925 | O71: =+$D$69 -> 13.880651 | P71: =SUM(P69:P70) -> 16.155356 | Q71: =+$D$69 -> 13.880651 | R71: =SUM(R69:R70) -> 14.951216 | S71: =+$D$69 -> 13.880651 | T71: =SUM(T69:T70) -> 15.095488 | U71: =+$D$69 -> 13.880651 | V71: =SUM(V69:V70) -> 14.979914 | W71: =+$D$69 -> 13.880651 | X71: =SUM(X69:X70) -> 13.273748 | Y71: =SUM(Y69:Y70) -> 13.880651 | Z71: =SUM(Z69:Z70) -> 14.894399 | AA71: =SUM(AA69:AA70) -> 13.880651 | AB71: =SUM(AB69:AB70) -> 14.707629 | AC71: =+$D$69 -> 13.880651 | AD71: =SUM(AD69:AD70) -> 13.783405 | AE71: =+$D$69 -> 13.880651 | AF71: =SUM(AF69:AF70) -> 14.604157 | AG71: =+$D$69 -> 13.880651 | AH71: =SUM(AH69:AH70) -> 12.261331 | AI71: =+$D$69 -> 13.880651 | AJ71: =SUM(AJ69:AJ70) -> 14.310366 | AK71: =+$D$69 -> 13.880651 | AL71: =SUM(AL69:AL70) -> 13.193096 | AM71: =SUM(AM69:AM70) -> 13.880651 | AN71: =SUM(AN69:AN70) -> 13.025061 | AO71: =+$D$69 -> 13.880651 | AP71: =SUM(AP69:AP70) -> 14.183533 | AQ71: =+$D$69 -> 13.880651 | AR71: =SUM(AR69:AR70) -> 13.190263 | AS71: =+$D$69 -> 13.880651 | AT71: =SUM(AT69:AT70) -> 14.08473 | AU71: =+$D$69 -> 13.880651 | AV71: =SUM(AV69:AV70) -> 13.020496 | AW71: =+$D$69 -> 13.880651 | AX71: =SUM(AX69:AX70) -> 14.005257 | AY71: =+$D$69 -> 13.880651 | AZ71: =SUM(AZ69:AZ70) -> 13.633726 | BA71: =+$D$69 -> 13.880651 | BB71: =SUM(BB69:BB70) -> 13.305762 | BC71: =+$D$69 -> 13.880651 | BD71: =SUM(BD69:BD70) -> 13.166627 | BE71: =+$D$69 -> 13.880651 | BF71: =SUM(BF69:BF70) -> 13.972291 | BG71: 18.35 | BH71: 16.183875 | BI71: 16.822447 | BJ71: 18.073217 | BK71: =SUM(BK69:BK70) -> 16 | BL71: =SUM(BL69:BL70) -> 18.431727 | BN71: =SUM(BN69:BN70) -> 15.648491
B72: Fe-Si | C72: Kg/TCS | D72: 2.1355317 | E72: =+$D$72 -> 2.1355317 | F72: =+(F64/'Maj Production Summ'!F$18)*1000 -> 2.1592467 | G72: =+$D$72 -> 2.1355317 | H72: =+(H64/'Maj Production Summ'!H$18)*1000 -> 2.3284511 | I72: =+$D$72 -> 2.1355317 | J72: =+(J64/'Maj Production Summ'!J$18)*1000 -> 2.2463163 | K72: =+$D$72 -> 2.1355317 | L72: =+(L64/'Maj Production Summ'!L$18)*1000 -> 2.1614439 | M72: =+$D$72 -> 2.1355317 | N72: =+(N64/'Maj Production Summ'!N$18)*1000 -> 2.2169377 | O72: =+$D$72 -> 2.1355317 | P72: =+(P64/'Maj Production Summ'!P$18)*1000 -> 1.9155175 | Q72: =+$D$72 -> 2.1355317 | R72: =+(R64/'Maj Production Summ'!R$18)*1000 -> 2.1370417 | S72: =+$D$72 -> 2.1355317 | T72: =+(T64/'Maj Production Summ'!T$18)*1000 -> 2.1715161 | U72: =+$D$72 -> 2.1355317 | V72: =+(V64/'Maj Production Summ'!V$18)*1000 -> 2.1438991 | W72: =+$D$72 -> 2.1355317 | X72: =+(X64/'Maj Production Summ'!X$18)*1000 -> 2.1203719 | Y72: =+$D$72 -> 2.1355317 | Z72: =+(Z64/'Maj Production Summ'!Z$18)*1000 -> 2.0649352 | AA72: =+$D$72 -> 2.1355317 | AB72: =+(AB64/'Maj Production Summ'!AB$18)*1000 -> 2.1401444 | AC72: =+$D$72 -> 2.1355317 | AD72: =+(AD64/'Maj Production Summ'!AD$18)*1000 -> 2.1595862 | AE72: =+$D$72 -> 2.1355317 | AF72: =+(AF64/'Maj Production Summ'!AF$18)*1000 -> 2.142321 | AG72: =+$D$72 -> 2.1355317 | AH72: =+(AH64/'Maj Production Summ'!AH$18)*1000 -> 2.191702 | AI72: =+$D$72 -> 2.1355317 | AJ72: =+(AJ64/'Maj Production Summ'!AJ$18)*1000 -> 2.1485134 | AK72: =+$D$72 -> 2.1355317 | AL72: =+(AL64/'Maj Production Summ'!AL$18)*1000 -> 2.2912978 | AM72: =+$D$72 -> 2.1355317 | AN72: =+(AN64/'Maj Production Summ'!AN$18)*1000 -> 2.2190499 | AO72: =+$D$72 -> 2.1355317 | AP72: =+(AP64/'Maj Production Summ'!AP$18)*1000 -> 2.1647224 | AQ72: =+$D$72 -> 2.1355317 | AR72: =+(AR64/'Maj Production Summ'!AR$18)*1000 -> 2.4512491 | AS72: =+$D$72 -> 2.1355317 | AT72: =+(AT64/'Maj Production Summ'!AT$18)*1000 -> 2.1932239 | AU72: =+$D$72 -> 2.1355317 | AV72: =+(AV64/'Maj Production Summ'!AV$18)*1000 -> 2.2592641 | AW72: =+$D$72 -> 2.1355317 | AX72: =+(AX64/'Maj Production Summ'!AX$18)*1000 -> 2.1981555 | AY72: =+$D$72 -> 2.1355317 | AZ72: =+(AZ64/'Maj Production Summ'!AZ$18)*1000 -> 2.0187365 | BA72: =+$D$72 -> 2.1355317 | BB72: =+(BB64/'Maj Production Summ'!BB$18)*1000 -> 2.2374955 | BC72: =+$D$72 -> 2.1355317 | BD72: =+(BD64/'Maj Production Summ'!BD$18)*1000 -> 2.2283526 | BE72: =+$D$72 -> 2.1355317 | BF72: =+(BF64/'Maj Production Summ'!BF$18)*1000 -> 2.1822357 | BG72: 2.15 | BH72: 2.3091923 | BI72: 2.8192466 | BJ72: 2.0997064 | BK72: 3.2 | BL72: 2.1491301 | BM72: 3.03 | BN72: 2.2353142

Sheet Major techno all dept
C3: MAJOR TECHNO PARAMETERS 2026-27
C4: DEPARTMENTS | D4: ITEM | E4: Unit | F4: 2022-23 Actual | G4: ABP 2026-27 | H4: Apr'26 | J4: May'25 | L4: 2M | N4: Jun'25 | P4: QTR-1 | R4: Jul'25 | T4: 4M | V4: Aug'25 | X4: 5M | Z4: Sep'25 | AB4: QTR-2 | AD4: H1 | AF4: Oct'25 | AH4: 7M | AJ4: Nov'25 | AL4: 8M | AN4: Dec'25 | AP4: QTR-3 | AR4: 9M | AT4: Jan'26 | AV4: 10M | AX4: Feb'26 | AZ4: 11M | BB4: Mar'26 | BD4: QTR-4 | BF4: H2 | BH4: 2025-26
H5: ABP | I5: ACT | J5: ABP | K5: ACT | L5: ABP | M5: ACT | N5: ABP | O5: ACT | P5: ABP | Q5: ACT | R5: ABP | S5: ACT | T5: ABP | U5: ACT | V5: ABP | W5: ACT | X5: ABP | Y5: ACT | Z5: ABP | AA5: ACT | AB5: ABP | AC5: ACT | AD5: ABP | AE5: ACT | AF5: ABP | AG5: ACT | AH5: ABP | AI5: ACT | AJ5: ABP | AK5: ACT | AL5: ABP | AM5: ACT | AN5: ABP | AO5: ACT | AP5: ABP | AQ5: ACT | AR5: ABP | AS5: ACT | AT5: ABP | AU5: ACT | AV5: ABP | AW5: ACT | AX5: ABP | AY5: ACT | AZ5: ABP | BA5: ACT | BB5: ABP | BC5: ACT | BD5: ABP | BE5: ACT | BF5: ABP | BG5: ACT | BH5: ABP | BI5: ACT
C6: COKE OVENS | D6: B.F.Coke Yield | E6: % | F6: 69.459875 | G6: 69.5 | H6: =+'Maj Techno Summ'!E5 -> 69.5 | I6: =+'Maj Techno Summ'!F5 -> 69.5 | J6: =+'Maj Techno Summ'!G5 -> 69.5 | K6: =+'Maj Techno Summ'!H5 -> 70 | L6: =+'Maj Techno Summ'!I5 -> 69.5 | M6: =+'Maj Techno Summ'!J5 -> 69.752887 | N6: =+'Maj Techno Summ'!K5 -> 69.5 | O6: =+'Maj Techno Summ'!L5 -> 70 | ... BI6: =+'Maj Techno Summ'!BF5 -> 69.684781
D7: ICC in Coal Blend
D8: (COB#10) | E8: % | F8: 89.651306 | G8: 89 | H8: =+'Maj Techno Summ'!E7 -> 89 | I8: =+'Maj Techno Summ'!F7 -> 89 | J8: =+'Maj Techno Summ'!G7 -> 89 | K8: =+'Maj Techno Summ'!H7 -> #REF! | L8: =+'Maj Techno Summ'!I7 -> 89 | M8: =+'Maj Techno Summ'!J7 -> #REF! | N8: =+'Maj Techno Summ'!K7 -> 89 | O8: =+'Maj Techno Summ'!L7 -> #REF! | ... BI8: =+'Maj Techno Summ'!BF7 -> #REF!
D9: (COB#11) | E9: % | F9: 92.198587 | G9: 95 | H9: =+'Maj Techno Summ'!E8 -> 95 | I9: =+'Maj Techno Summ'!F8 -> 95 | J9: =+'Maj Techno Summ'!G8 -> 95 | K9: =+'Maj Techno Summ'!H8 -> 94.999998 | L9: =+'Maj Techno Summ'!I8 -> 95 | M9: =+'Maj Techno Summ'!J8 -> 94.999999 | N9: =+'Maj Techno Summ'!K8 -> 95 | O9: =+'Maj Techno Summ'!L8 -> 95 | ... BI9: =+'Maj Techno Summ'!BF8 -> 95
D10: Overall ICC in Blend | E10: % | F10: 91.262624 | G10: 93 | H10: =+'Maj Techno Summ'!E9 -> 92.972626 | I10: =+'Maj Techno Summ'!F9 -> 92.889184 | J10: =+'Maj Techno Summ'!G9 -> 92.972626 | K10: =+'Maj Techno Summ'!H9 -> 93.667282 | L10: =+'Maj Techno Summ'!I9 -> 92.972626 | M10: =+'Maj Techno Summ'!J9 -> 92.876873 | N10: =+'Maj Techno Summ'!K9 -> 92.972626 | O10: =+'Maj Techno Summ'!L9 -> 93.437619 | ... BI10: =+'Maj Techno Summ'!BF9 -> 93.10612
